Workbook

Sheet detalle y gastos
B2: CANCIANI, Carolina | C2: MP 1148
B3: Tel. 11 5320-2676
B4: consorciosrc13@gmail.com
A7: EDIFICIO ROSALES 624 | B7: LIQUIDACIÓN EXPENSAS NOVIEMBRE 2025 | C7: Vto. 15/12
A10: Teléfonos útiles
A11: EDESUR 0800-333-3787
A12: AySA 0800-321-2482
A13: Metrogas 0800-333-6427
A15: GASTOS ORDINARIOS
A16: ABONOS y SERVICIOS
A18: Seguro de consorcio obligatorio - federacion patronal - poliza nro. 2027630 | C18: 76654
A19: AYSA | C19: 316973.44
A20: Ascensores Lema | C20: 80000
A21: TSG MES 10 | C21: 15748 | F21: Subidos en 0CT 2025
A22: RC Adm Cons CANCIANI, Carolina | B22: Honorarios administracion | C22: 83400
C23: =SUM(C17:C22) -> 572775.44
A24: LIMPIEZA / MANTENIMIENTO / GASTOS GENERALES
A25: Sueldo personal de limpieza y maestranza | C25: =349151.87+ (349151.87*10%) -> 384067.06
A26: Seguro de vida Sra encargada | C26: 5684
A27: Fumigacion | C27: 55000
A28: PREVISION ORDINARIA
C29: =SUM(C24:C28) -> 444751.06
A30: TOTAL GASTOS ORDINARIOS (A) | C30: =+C29+C23 -> 1017526.5
A32: GASTOS EXTRAORDINARIOS
A33: Sr. Leonardo Balcazza - Mano de obra y materiales - Arreglo medianera | C33: 610000
A34: Cuota 1 revaluo ARBA | C34: 1034026.5
A37: PREVISION EXTRAORDINARIA | C37: 0
A39: TOTAL GASTOS EXTRAORDINARIOS (B) | C39: =+C33+C34+C35+C38 -> 1644026.5
A41: TOTAL GENERAL DE GASTOS (A) + (B) | C41: =+C39+C30 -> 2661553
A43: ATENCIÓN: Al momento de abonar en efectivo las expensas (dado que no se dispone de cuenta bancaria), deberán cancelar el monto total correspondiente, que incluye tanto las expensas como el consumo de Edesur de cada unidad funcional. Les recordamos que el pago debe realizarse con dinero justo.
A48: CAJA ANTERIOR | C48: 1081522.7
A49: EGRESOS DEL MES DE NOVIEMBRE | C49: =-(C41-C28) -> -2661553
A50: INGRESOS CORRESPONDIENTES AL PAGO DE EXPENSAS | C50: ='prorrateo '!F31 -> 2610074.2
A51: PUNITORIOS MAL COBRADOS | C51: 0
A52: CUOTA PLAN DE PAGOS (4/6) | C52: 107386.2
A53: Saldo al cierre $ (pesos) | C53: =SUM(C48:C52) -> 1137430.1
A57: CAJA EXTRAORDINARIA
A58: Egreso extraordinario | C58: =-C39 -> -1644026.5
A61: TOTAL | C61: =SUM(C57:C60) -> -1644026.5
A62: CAJA NO REAL, YA QUE DE ESTE FONDO SE PAGA EDESUR DE LAS UNIDADES

Sheet prorrateo 
A1: Expensas ordinarias: | B1: =N1 -> 1017526.5 | D1: 1667839.1 | E1: Gastos extraordinarios: | I1: ARBA: | L1: 1000000 | N1: 1017526.5
A2: Propietarios | B2: Inquilinos | C2: UNIDAD FUNCIONAL | D2: % | E2: SALDO ANTERIOR | F2: SALDO ABONADO | G2: SALDO | H2: PUNITORIOS 4% | I2: ORDINARIAS | J2: EDESUR | K2: EXTRAORD. | L2: ARBA | M2: A PAGAR | O2: SIN EDESUR
A3: Ferrea Nestor | B3: Gabriel | C3: 1ro. "A" | D3: 5.11 | E3: 105505.58 | F3: =E3 -> 105505.58 | G3: =E3-F3 -> 0 | H3: =IF(G3>0,G3*4%,0) -> 0 | I3: =B$1*D3/100 -> 51995.604 | J3: =Edesur!N10 -> 31008.737 | K3: =G$1*D3/100 -> 0 | L3: =L$1*D3/100 -> 51100 | M3: =I3+G3+L3+K3+H3+J3 -> 134104.34 | O3: =M3-J3 -> 103095.6
A4: Gnecchi Nicolas | B4: Brian | C4: 1ro. "B" | D4: 5.09 | E4: 104519.01 | F4: =E4 -> 104519.01 | G4: =E4-F4 -> 0 | H4: =IF(G4>0,G4*4%,0) -> 0 | I4: =B$1*D4/100 -> 51792.099 | J4: =Edesur!N11 -> 27414.77 | K4: =G$1*D4/100 -> 0 | L4: =L$1*D4/100 -> 50900 | M4: =I4+G4+L4+K4+H4+J4 -> 130106.87 | O4: =M4-J4 -> 102692.1
A5: Triñanes Gaston | C5: 2do. "A" | D5: 5.04 | E5: 407656.01 | F5: =497170.55-64957-F23 -> 377751.01 | G5: =E5-F5 -> 29904.995 | H5: =IF(G5>0,G5*4%,0) -> 1196.1998 | I5: =B$1*D5/100 -> 51283.335 | J5: =Edesur!N12 -> 27942.199 | K5: =G$1*D5/100 -> 0 | L5: =L$1*D5/100 -> 50400 | M5: =I5+G5+L5+K5+H5+J5 -> 160726.73 | O5: =M5-J5 -> 132784.53
A6: Nuñez Eva | C6: 2do. "B" | D6: 5.21 | E6: 107734.42 | G6: =E6-F6 -> 107734.42 | H6: =IF(G6>0,G6*4%,0) -> 4309.3767 | I6: =B$1*D6/100 -> 53013.13 | J6: =Edesur!N13 -> 25698.764 | K6: =G$1*D6/100 -> 0 | L6: =L$1*D6/100 -> 52100 | M6: =I6+G6+L6+K6+H6+J6 -> 242855.69 | O6: =M6-J6 -> 217156.93
A7: Triñanes Gaston | B7: Leandro | C7: 3ro. "A" | D7: 5.11 | E7: 105666.58 | F7: =E7 -> 105666.58 | G7: =E7-F7 -> 0 | H7: =IF(G7>0,G7*4%,0) -> 0 | I7: =B$1*D7/100 -> 51995.604 | J7: =Edesur!N14 -> 27391.373 | K7: =G$1*D7/100 -> 0 | L7: =L$1*D7/100 -> 51100 | M7: =I7+G7+L7+K7+H7+J7 -> 130486.98 | O7: =M7-J7 -> 103095.6
A8: Grecco Pedro | C8: 3ro. "B" | D8: 5.09 | E8: 105253.01 | F8: =E8 -> 105253.01 | G8: =E8-F8 -> 0 | H8: =IF(G8>0,G8*4%,0) -> 0 | I8: =B$1*D8/100 -> 51792.099 | J8: =Edesur!N15 -> 25501.515 | K8: =G$1*D8/100 -> 0 | L8: =L$1*D8/100 -> 50900 | M8: =I8+G8+L8+K8+H8+J8 -> 128193.61 | O8: =M8-J8 -> 102692.1
A9: Mteljan Barbara | C9: 4to. "A" | D9: 5.11 | E9: 105666.58 | F9: =E9 -> 105666.58 | G9: =E9-F9 -> 0 | H9: =IF(G9>0,G9*4%,0) -> 0 | I9: =B$1*D9/100 -> 51995.604 | J9: =Edesur!N16 -> 26537.911 | K9: =G$1*D9/100 -> 0 | L9: =L$1*D9/100 -> 51100 | M9: =I9+G9+L9+K9+H9+J9 -> 129633.51 | O9: =M9-J9 -> 103095.6
A10: Carnevalli | B10: Christian / Vanina | C10: 4to. "B" | D10: 5.09 | E10: 105253.01 | F10: =E10 -> 105253.01 | G10: =E10-F10 -> 0 | I10: =B$1*D10/100 -> 51792.099 | J10: =Edesur!N17 -> 20193.171 | K10: =G$1*D10/100 -> 0 | L10: =L$1*D10/100 -> 50900 | M10: =I10+G10+L10+K10+H10+J10 -> 122885.27 | O10: =M10-J10 -> 102692.1
A11: Leonor | C11: 5to. "A" | D11: 5.04 | E11: 104219.09 | F11: =E11 -> 104219.09 | G11: =E11-F11 -> 0 | H11: =IF(G11>0,G11*4%,0) -> 0 | I11: =B$1*D11/100 -> 51283.335 | J11: =Edesur!N18 -> 25635.038 | K11: =G$1*D11/100 -> 0 | L11: =L$1*D11/100 -> 50400 | M11: =I11+G11+L11+K11+H11+J11 -> 127318.37 | O11: =M11-J11 -> 101683.34
A12: Strangio Federico | C12: 5to. "B" | D12: 5.21 | E12: 107734.42 | F12: =E12 -> 107734.42 | G12: =E12-F12 -> 0 | H12: =IF(G12>0,G12*4%,0) -> 0 | I12: =B$1*D12/100 -> 53013.13 | J12: =Edesur!N19 -> 39279.121 | K12: =G$1*D12/100 -> 0 | L12: =L$1*D12/100 -> 52100 | M12: =I12+G12+L12+K12+H12+J12 -> 144392.25 | O12: =M12-J12 -> 105113.13
A13: Senderowicz Rosalia | B13: Alejo | C13: 6to. "A" | D13: 5.11 | E13: 105666.58 | F13: =E13 -> 105666.58 | G13: =E13-F13 -> 0 | H13: =IF(G13>0,G13*4%,0) -> 0 | I13: =B$1*D13/100 -> 51995.604 | J13: =Edesur!N20 -> 71949.576 | K13: =G$1*D13/100 -> 0 | L13: =L$1*D13/100 -> 51100 | M13: =I13+G13+L13+K13+H13+J13 -> 175045.18 | O13: =M13-J13 -> 103095.6
A14: Senderowicz Rosalia | B14: Anabella | C14: 6to. "B" | D14: 5.09 | E14: 371509.96 | F14: =580000-F25-84879 -> 416293.74 | G14: =E14-F14 -> -44783.784 | H14: =IF(G14>0,G14*4%,0) -> 0 | I14: =B$1*D14/100 -> 51792.099 | J14: =Edesur!N21 -> 26064.237 | K14: =G$1*D14/100 -> 0 | L14: =L$1*D14/100 -> 50900 | M14: =I14+G14+L14+K14+H14+J14 -> 83972.552 | O14: =M14-J14 -> 57908.314
A15: Alonso Graciela | B15: Facundo | C15: 7mo. "A" | D15: 5.04 | E15: 104219.09 | F15: =104219-F29+22333.1-0.35 -> 104219.09 | G15: =E15-F15 -> 0.0044524 | H15: =IF(G15>0,G15*4%,0) -> 0.000178096 | I15: =B$1*D15/100 -> 51283.335 | J15: =Edesur!N22 -> 22952.73 | K15: =G$1*D15/100 -> 0 | L15: =L$1*D15/100 -> 50400 | M15: =I15+G15+L15+K15+H15+J15 -> 124636.07 | O15: =M15-J15 -> 101683.34
A16: Perez Rodriguez | B16: Mariel | C16: 7mo. "B" | D16: 5.21 | E16: 107734.42 | F16: =E16 -> 107734.42 | G16: =E16-F16 -> 0 | H16: =IF(G16>0,G16*4%,0) -> 0 | I16: =B$1*D16/100 -> 53013.13 | J16: =Edesur!N23 -> 28971.93 | K16: =G$1*D16/100 -> 0 | L16: =L$1*D16/100 -> 52100 | M16: =I16+G16+L16+K16+H16+J16 -> 134085.06 | O16: =M16-J16 -> 105113.13
A17: Mourelos Pablo | C17: 8vo. "A" | D17: 5.04 | E17: 104219.09 | F17: =E17 -> 104219.09 | G17: =E17-F17 -> 0 | H17: =IF(G17>0,G17*4%,0) -> 0 | I17: =B$1*D17/100 -> 51283.335 | J17: =Edesur!N24 -> 20176.635 | K17: =G$1*D17/100 -> 0 | L17: =L$1*D17/100 -> 50400 | M17: =I17+G17+L17+K17+H17+J17 -> 121859.97 | O17: =M17-J17 -> 101683.34
A18: Calabria Carlos/Giarrizzo Silvia | C18: 8vo. "B" | D18: 5.21 | E18: 107734.42 | F18: =E18 -> 107734.42 | G18: =E18-F18 -> 0 | H18: =IF(G18>0,G18*4%,0) -> 0 | I18: =B$1*D18/100 -> 53013.13 | J18: =Edesur!N25 -> 25848.823 | K18: =G$1*D18/100 -> 0 | L18: =L$1*D18/100 -> 52100 | M18: =I18+G18+L18+K18+H18+J18 -> 130961.95 | O18: =M18-J18 -> 105113.13
A19: Ariel | C19: 9no. "A" | D19: 7.4 | E19: 153020.1 | F19: =E19 -> 153020.1 | G19: =E19-F19 -> 0 | H19: =IF(G19>0,G19*4%,0) -> 0 | I19: =B$1*D19/100 -> 75296.961 | J19: =Edesur!N26 -> 41293.909 | K19: =G$1*D19/100 -> 0 | L19: =L$1*D19/100 -> 74000 | M19: =I19+G19+L19+K19+H19+J19 -> 190590.87 | O19: =M19-J19 -> 149296.96
B20: Christian / Vanina | C20: COCHERA 1 | D20: 1.08 | E20: 22332.663 | F20: =E20 -> 22332.663 | G20: =E20-F20 -> 0 | I20: =B$1*D20/100 -> 10989.286 | J20: =Edesur!N27 -> 3801.0371 | K20: =G$1*D20/100 -> 0 | L20: =L$1*D20/100 -> 10800 | M20: =I20+G20+L20+K20+H20+J20 -> 25590.323 | O20: =M20-J20 -> 21789.286
B21: Mariel | C21: COCHERA 2 | D21: 1.08 | E21: 22332.663 | F21: =E21 -> 22332.663 | G21: =E21-F21 -> 0 | H21: =IF(G21>0,G21*4%,0) -> 0 | I21: =B$1*D21/100 -> 10989.286 | J21: =Edesur!N28 -> 3801.0371 | K21: =G$1*D21/100 -> 0 | L21: =L$1*D21/100 -> 10800 | M21: =I21+G21+L21+K21+H21+J21 -> 25590.323 | O21: =M21-J21 -> 21789.286
C22: COCHERA 3 | D22: 1.08 | E22: 262598.52 | F22: 0 | G22: =E22-F22 -> 262598.52 | H22: =IF(G22>0,G22*4%,0) -> 10503.941 | I22: =B$1*D22/100 -> 10989.286 | J22: =Edesur!N29 -> 3801.0371 | K22: =G$1*D22/100 -> 0 | L22: =L$1*D22/100 -> 10800 | M22: =I22+G22+L22+K22+H22+J22 -> 298692.78 | O22: =M22-J22 -> 294891.74
A23: Triñanes Gaston | C23: COCHERA 4 | D23: 1.08 | E23: 54462.539 | F23: =E23 -> 54462.539 | G23: =E23-F23 -> 0 | H23: =IF(G23>0,G23*4%,0) -> 0 | I23: =B$1*D23/100 -> 10989.286 | J23: =Edesur!N30 -> 3801.0371 | K23: =G$1*D23/100 -> 0 | L23: =L$1*D23/100 -> 10800 | M23: =I23+G23+L23+K23+H23+J23 -> 25590.323 | O23: =M23-J23 -> 21789.286
A24: Senderowicz Rosalia | B24: Alejo | C24: COCHERA 5 | D24: 1.08 | E24: 22332.663 | F24: =E24 -> 22332.663 | G24: =E24-F24 -> 0 | H24: =IF(G24>0,G24*4%,0) -> 0 | I24: =B$1*D24/100 -> 10989.286 | J24: =Edesur!N31 -> 3801.0371 | K24: =G$1*D24/100 -> 0 | L24: =L$1*D24/100 -> 10800 | M24: =I24+G24+L24+K24+H24+J24 -> 25590.323 | O24: =M24-J24 -> 21789.286
A25: Senderowicz Rosalia | B25: Anabella | C25: COCHERA 6 | D25: 1.08 | E25: 78827.255 | F25: =E25 -> 78827.255 | G25: =E25-F25 -> 0 | H25: =IF(G25>0,G25*4%,0) -> 0 | I25: =B$1*D25/100 -> 10989.286 | J25: =Edesur!N32 -> 3801.0371 | K25: =G$1*D25/100 -> 0 | L25: =L$1*D25/100 -> 10800 | M25: =I25+G25+L25+K25+H25+J25 -> 25590.323 | O25: =M25-J25 -> 21789.286
A26: Ariel | C26: COCHERA 7 | D26: 1.08 | E26: 22332.663 | F26: =E26 -> 22332.663 | G26: =E26-F26 -> 0 | H26: =IF(G26>0,G26*4%,0) -> 0 | I26: =B$1*D26/100 -> 10989.286 | J26: =Edesur!N33 -> 3801.0371 | K26: =G$1*D26/100 -> 0 | L26: =L$1*D26/100 -> 10800 | M26: =I26+G26+L26+K26+H26+J26 -> 25590.323 | O26: =M26-J26 -> 21789.286
A27: Ariel | C27: COCHERA 8 | D27: 1.08 | E27: 22332.663 | F27: =E27 -> 22332.663 | G27: =E27-F27 -> 0 | H27: =IF(G27>0,G27*4%,0) -> 0 | I27: =B$1*D27/100 -> 10989.286 | J27: =Edesur!N34 -> 3801.0371 | K27: =G$1*D27/100 -> 0 | L27: =L$1*D27/100 -> 10800 | M27: =I27+G27+L27+K27+H27+J27 -> 25590.323 | O27: =M27-J27 -> 21789.286 | P27: =F27+F26+F19 -> 197685.42
B28: =B7 -> Leandro | C28: COCHERA 9 | D28: 1.08 | E28: 22332.663 | F28: =E28 -> 22332.663 | G28: =E28-F28 -> 0 | H28: =IF(G28>0,G28*4%,0) -> 0 | I28: =B$1*D28/100 -> 10989.286 | J28: =Edesur!N35 -> 3801.0371 | K28: =G$1*D28/100 -> 0 | L28: =L$1*D28/100 -> 10800 | M28: =I28+G28+L28+K28+H28+J28 -> 25590.323 | O28: =M28-J28 -> 21789.286
A29: Alonso Graciela | B29: Facundo | C29: COCHERA 10 | D29: 1.08 | E29: 22332.663 | F29: =E29 -> 22332.663 | G29: =E29-F29 -> 0 | H29: =IF(G29>0,G29*4%,0) -> 0 | I29: =B$1*D29/100 -> 10989.286 | J29: =Edesur!N36 -> 3801.0371 | K29: =G$1*D29/100 -> 0 | L29: =L$1*D29/100 -> 10800 | M29: =I29+G29+L29+K29+H29+J29 -> 25590.323 | O29: =M29-J29 -> 21789.286
C31: TOTAL EXPENSAS | D31: =SUM(D3:D30) -> 100 | F31: =SUM(F3:F30) -> 2610074.2 | I31: =SUM(I3:I30) -> 1017526.5 | K31: =SUM(K3:K30) -> 0 | M31: =SUM(M3:M29) -> 2940861
A33: LAS LINEAS GRISES CORRESPONDEN A PLANES DE PAGO VIGENTES - RESTA ABONAR 6 CUOTAS DE $107.386,20 + LAS EXPENSAS AL DIA - PARTE DE LA DEUDA CANCELA EDESUR Y EXPENSAS CON TASA DE INTERES MENSUAL

Sheet Edesur
A1: EDESUR
C6: ='detalle y gastos'!C7 -> Vto. 15/12
B7: EDESUR | C7: 551870.81 | F7: Se abona hasta el | J7: ='detalle y gastos'!C7 -> Vto. 15/12
B8: EDESUR | K8: =C8-J38 -> -199922.93 | L8: =C7-J38 -> 351947.88
A9: U.F. | B9: U.F. | C9: PISO - DEPTO | D9: PROPIETARIOS | E9: % | F9: CONSUMO ANT. | G9: CONSUMO ACTUAL | H9: KWH | I9: INTERES POR MORA 7% | J9: EDESUR | K9: PARTES COMUNES | L9: PARTES COMUNES | M9: KWH | N9: EDESUR FINAL
A10: 1 | B10: 1 | C10: 1ro. "A" | D10: Ferrea Nestor | E10: 5.11 | F10: 4302.83 | G10: 4441.7 | H10: =G10-F10 -> 138.87 | I10: =H10*7% -> 9.7209 | J10: =M10*93.787 -> 13024.201 | K10: =K8*E10% -> -10216.062 | L10: =L$8*E10/S$12 -> 17984.536 | M10: =G10-F10 -> 138.87 | N10: =J10+L10 -> 31008.737 | O10: =N10+'prorrateo '!M3 -> 165113.08
A11: 2 | B11: 2 | C11: 1ro. "B" | D11: Gnecchi Nicolas | E11: 5.09 | F11: 4106.5 | G11: 4207.8 | H11: =G11-F11 -> 101.3 | I11: =H11*7% -> 7.091 | J11: =M11*93.787 -> 9500.6231 | K11: =K8*E11% -> -10176.077 | L11: =L$8*E11/S$12 -> 17914.147 | M11: =G11-F11 -> 101.3 | N11: =J11+L11 -> 27414.77 | O11: =N11+'prorrateo '!M4 -> 157521.64
A12: 3 | B12: 3 | C12: 2do. "A" | D12: Triñanes Gaston | E12: 5.04 | F12: 1558.7 | G12: 1667.5 | H12: =G12-F12 -> 108.8 | I12: =H12*7% -> 7.616 | J12: =M12*93.787 -> 10204.026 | K12: =K8*E12% -> -10076.116 | L12: =L$8*E12/S$12 -> 17738.173 | M12: =G12-F12 -> 108.8 | N12: =J12+L12 -> 27942.199 | O12: =N12+'prorrateo '!M5 -> 188668.93 | S12: 100
A13: 4 | B13: 4 Y 5 | C13: 2do. "B" | D13: Nuñez Eva | E13: 5.21 | F13: 1204.6 | G13: 1283.1 | H13: =G13-F13 -> 78.5 | I13: =H13*7% -> 5.495 | J13: =M13*93.787 -> 7362.2795 | K13: =K8*E13% -> -10415.985 | L13: =L$8*E13/S$12 -> 18336.484 | M13: =G13-F13 -> 78.5 | N13: =J13+L13 -> 25698.764 | O13: =N13+'prorrateo '!M6 -> 268554.45
A14: 6 | B14: 6 | C14: 3ro. "A" | D14: Triñanes Gaston | E14: 5.11 | F14: 1814 | G14: 1914.3 | H14: =G14-F14 -> 100.3 | I14: =H14*7% -> 7.021 | J14: =M14*93.787 -> 9406.8361 | K14: =K8*E14% -> -10216.062 | L14: =L$8*E14/S$12 -> 17984.536 | M14: =G14-F14 -> 100.3 | N14: =J14+L14 -> 27391.373 | O14: =N14+'prorrateo '!M7 -> 157878.35
A15: 7 | B15: 7 | C15: 3ro. "B" | D15: Grecco Pedro | E15: 5.09 | F15: 3018 | G15: 3098.9 | H15: =G15-F15 -> 80.9 | I15: =H15*7% -> 5.663 | J15: =M15*93.787 -> 7587.3683 | K15: =K8*E15% -> -10176.077 | L15: =L$8*E15/S$12 -> 17914.147 | M15: =G15-F15 -> 80.9 | N15: =J15+L15 -> 25501.515 | O15: =N15+'prorrateo '!M8 -> 153695.13
A16: 8 | B16: 8 | C16: 4to. "A" | D16: Mteljan Barbara | E16: 5.11 | F16: 2516.4 | G16: 2607.6 | H16: =G16-F16 -> 91.2 | I16: =H16*7% -> 6.384 | J16: =M16*93.787 -> 8553.3744 | K16: =K8*E16% -> -10216.062 | L16: =L$8*E16/S$12 -> 17984.536 | M16: =G16-F16 -> 91.2 | N16: =J16+L16 -> 26537.911 | O16: =N16+'prorrateo '!M9 -> 156171.43
A17: 9 | B17: 9 | C17: 4to. "B" | D17: Carnevalli | E17: 5.09 | F17: 3375.8 | G17: 3400.1 | H17: =G17-F17 -> 24.3 | I17: =H17*7% -> 1.701 | J17: =M17*93.787 -> 2279.0241 | K17: =K8*E17% -> -10176.077 | L17: =L$8*E17/S$12 -> 17914.147 | M17: =G17-F17 -> 24.3 | N17: =J17+L17 -> 20193.171 | O17: =N17+'prorrateo '!M10 -> 143078.44
A18: 10 | B18: 10 | C18: 5to. "A" | D18: Leonor | E18: 5.04 | F18: 2270.5 | G18: 2354.7 | H18: =G18-F18 -> 84.2 | I18: =H18*7% -> 5.894 | J18: =M18*93.787 -> 7896.8654 | K18: =K8*E18% -> -10076.116 | L18: =L$8*E18/S$12 -> 17738.173 | M18: =G18-F18 -> 84.2 | N18: =J18+L18 -> 25635.038 | O18: =N18+'prorrateo '!M11 -> 152953.41
A19: 11 | B19: 11 | C19: 5to. "B" | D19: Strangio Federico | E19: 5.21 | F19: 4351.6 | G19: 4574.9 | H19: =G19-F19 -> 223.3 | I19: =H19*7% -> 15.631 | J19: =M19*93.787 -> 20942.637 | K19: =K8*E19% -> -10415.985 | L19: =L$8*E19/S$12 -> 18336.484 | M19: =G19-F19 -> 223.3 | N19: =J19+L19 -> 39279.121 | O19: =N19+'prorrateo '!M12 -> 183671.37
A20: 12 | B20: 12 | C20: 6to. "A" | D20: Senderowicz Rosalia | E20: 5.11 | F20: 5489.3 | G20: 6064.7 | H20: =G20-F20 -> 575.4 | I20: =H20*7% -> 40.278 | J20: =M20*93.787 -> 53965.04 | K20: =K8*E20% -> -10216.062 | L20: =L$8*E20/S$12 -> 17984.536 | M20: =G20-F20 -> 575.4 | N20: =J20+L20 -> 71949.576 | O20: =N20+'prorrateo '!M13 -> 246994.76
A21: 13 | B21: 13 | C21: 6to. "B" | D21: Senderowicz Rosalia | E21: 5.09 | F21: 4112.1 | G21: 4199 | H21: =G21-F21 -> 86.9 | I21: =H21*7% -> 6.083 | J21: =M21*93.787 -> 8150.0903 | K21: =K8*E21% -> -10176.077 | L21: =L$8*E21/S$12 -> 17914.147 | M21: =G21-F21 -> 86.9 | N21: =J21+L21 -> 26064.237 | O21: =N21+'prorrateo '!M14 -> 110036.79
A22: 14 | B22: 14 | C22: 7mo. "A" | D22: Alonso Graciela | E22: 5.04 | F22: 2441.5 | G22: 2497.1 | H22: =G22-F22 -> 55.6 | I22: =H22*7% -> 3.892 | J22: =M22*93.787 -> 5214.5572 | K22: =K8*E22% -> -10076.116 | L22: =L$8*E22/S$12 -> 17738.173 | M22: =G22-F22 -> 55.6 | N22: =J22+L22 -> 22952.73 | O22: =N22+'prorrateo '!M15 -> 147588.8
A23: 15 | B23: 15 | C23: 7mo. "B" | D23: Perez Rodriguez | E23: 5.21 | F23: 4886.6 | G23: 5000 | H23: =G23-F23 -> 113.4 | I23: =H23*7% -> 7.938 | J23: =M23*93.787 -> 10635.446 | K23: =K8*E23% -> -10415.985 | L23: =L$8*E23/S$12 -> 18336.484 | M23: =G23-F23 -> 113.4 | N23: =J23+L23 -> 28971.93 | O23: =N23+'prorrateo '!M16 -> 163056.99
A24: 16 | B24: 16 | C24: 8vo. "A" | D24: Mourelos Pablo | E24: 5.04 | F24: 1776.7 | G24: 1802.7 | H24: =G24-F24 -> 26 | I24: =H24*7% -> 1.82 | J24: =M24*93.787 -> 2438.462 | K24: =K8*E24% -> -10076.116 | L24: =L$8*E24/S$12 -> 17738.173 | M24: =G24-F24 -> 26 | N24: =J24+L24 -> 20176.635 | O24: =N24+'prorrateo '!M17 -> 142036.61
A25: 17 | B25: 17 | C25: 8vo. "B" | D25: Calabria Carlos/Giarrizzo Silvia | E25: 5.21 | F25: 1869.3 | G25: 1949.4 | H25: =G25-F25 -> 80.1 | I25: =H25*7% -> 5.607 | J25: =M25*93.787 -> 7512.3387 | K25: =K8*E25% -> -10415.985 | L25: =L$8*E25/S$12 -> 18336.484 | M25: =G25-F25 -> 80.1 | N25: =J25+L25 -> 25848.823 | O25: =N25+'prorrateo '!M18 -> 156810.78
A26: 18 | B26: 18 | C26: 9no. "A" | D26: Ariel | E26: 7.4 | F26: 8914.5 | G26: 9077.1 | H26: =G26-F26 -> 162.6 | I26: =H26*7% -> 11.382 | J26: =M26*93.787 -> 15249.766 | K26: =K8*E26% -> -14794.297 | L26: =L$8*E26/S$12 -> 26044.143 | M26: =G26-F26 -> 162.6 | N26: =J26+L26 -> 41293.909 | O26: =N26+'prorrateo '!M19 -> 231884.78
A27: 19 | B27: 19 | C27: COCHERA 1 | E27: 1.08 | H27: =G27-F27 -> 0 | I27: =H27*7% -> 0 | L27: =L$8*E27/S$12 -> 3801.0371 | M27: 0 | N27: =J27+L27 -> 3801.0371 | O27: =N27+'prorrateo '!M20 -> 29391.36
A28: 20 | C28: COCHERA 2 | E28: 1.08 | H28: 0 | I28: =H28*7% -> 0 | L28: =L$8*E28/S$12 -> 3801.0371 | M28: 0 | N28: =J28+L28 -> 3801.0371 | O28: =N28+'prorrateo '!M21 -> 29391.36
C29: COCHERA 3 | E29: 1.08 | L29: =L$8*E29/S$12 -> 3801.0371 | M29: 0 | N29: =J29+L29 -> 3801.0371 | O29: =N29+'prorrateo '!M22 -> 302493.82
C30: COCHERA 4 | E30: 1.08 | L30: =L$8*E30/S$12 -> 3801.0371 | M30: 0 | N30: =J30+L30 -> 3801.0371 | O30: =N30+'prorrateo '!M23 -> 29391.36
C31: COCHERA 5 | D31: Senderowicz Rosalia | E31: 1.08 | L31: =L$8*E31/S$12 -> 3801.0371 | M31: 0 | N31: =J31+L31 -> 3801.0371 | O31: =N31+'prorrateo '!M24 -> 29391.36
C32: COCHERA 6 | D32: Senderowicz Rosalia | E32: 1.08 | L32: =L$8*E32/S$12 -> 3801.0371 | M32: 0 | N32: =J32+L32 -> 3801.0371 | O32: =N32+'prorrateo '!M25 -> 29391.36
C33: COCHERA 7 | D33: Ariel | E33: 1.08 | L33: =L$8*E33/S$12 -> 3801.0371 | M33: 0 | N33: =J33+L33 -> 3801.0371 | O33: =N33+'prorrateo '!M26 -> 29391.36
C34: COCHERA 8 | D34: Ariel | E34: 1.08 | L34: =L$8*E34/S$12 -> 3801.0371 | M34: 0 | N34: =J34+L34 -> 3801.0371 | O34: =N34+'prorrateo '!M27 -> 29391.36
A35: 21 | C35: COCHERA 9 | E35: 1.08 | H35: 0 | I35: =H35*7% -> 0 | L35: =L$8*E35/S$12 -> 3801.0371 | M35: 0 | N35: =J35+L35 -> 3801.0371 | O35: =N35+'prorrateo '!M28 -> 29391.36
A36: 22 | C36: COCHERA 10 | D36: Alonso Graciela | E36: 1.08 | H36: 0 | I36: =H36*7% -> 0 | L36: =L$8*E36/S$12 -> 3801.0371 | M36: 0 | N36: =J36+L36 -> 3801.0371 | O36: =N36+'prorrateo '!M29 -> 29391.36
A37: 23 | H37: 0 | I37: =H37*7% -> 0 | L37: 0 | M37: 0 | N37: =J37+L37 -> 0
A38: 24 | J38: =SUM(J10:J37) -> 199922.93 | L38: =SUM(L10:L37) -> 351947.88 | N38: =SUM(N10:N37) -> 551870.81
E39: =SUM(E10:E38) -> 100 | I39: =SUM(I10:I38) -> 149.2169 | L39: =L38+J38 -> 551870.81
A40: NOTA:
