Workbook

Sheet detalle y gastos
B2: CANCIANI, Carolina | C2: MP 1148
B3: Tel. 11 5320-2676
B4: consorciosrc13@gmail.com
A7: EDIFICIO ROSALES 624 | B7: LIQUIDACIÓN EXPENSAS FEBRERO 2025 | C7: Vto. 13/03
A10: Teléfonos útiles
A11: EDESUR 0800-333-3787
A12: AySA 0800-321-2482
A13: Metrogas 0800-333-6427
A15: GASTOS ORDINARIOS
A16: ABONOS y SERVICIOS
A18: Seguro de consorcio obligatorio - federacion patronal - poliza nro. 2027630 | C18: 76654
A19: AYSA | C19: 358727.59
A20: Ascensores Lema | C20: 85000
A21: Ascensores Lema - Puesta en marcha de ascensor - Trabajos realizados con mecanismos de puerta en 2do piso | C21: 130000
A22: ARBA - Cuota 3 del plan | C22: 1034026.5
A23: RC Adm Cons CANCIANI, Carolina | B23: Honorarios administracion | C23: 89200 | F23: Subidos en EN3R0
C24: =SUM(C17:C23) -> 1773608.1
A25: LIMPIEZA / MANTENIMIENTO / GASTOS GENERALES
A26: Sueldo personal de limpieza y maestranza | C26: =349151.87+ (349151.87*10%) -> 384067.06
A27: Seguro de vida Sra encargada | C27: 7458
A28: Articulos de limpieza | C28: 84450
A29: Fumigacion | C29: No llego factura
A30: PREVISION ORDINARIA
C31: =SUM(C25:C30) -> 475975.06
A32: TOTAL GASTOS ORDINARIOS (A) | C32: =+C31+C24 -> 2249583.1
A34: GASTOS EXTRAORDINARIOS
A39: PREVISION EXTRAORDINARIA - ARBA | C39: 500000
A41: TOTAL GASTOS EXTRAORDINARIOS (B) | C41: =+C35+C36+C37+C40 -> 0
A43: TOTAL GENERAL DE GASTOS (A) + (B) | C43: =+C41+C32 -> 2249583.1
A46: CAJA ANTERIOR | C46: -141024.51
A47: EGRESOS DEL MES DE FEBRERO | C47: =-(C43-C30) -> -2249583.1
A48: INGRESOS CORRESPONDIENTES AL PAGO DE EXPENSAS | C48: ='prorrateo '!F31 -> 4309983.1
A49: EDESUR | C49: -987480.77
A50: ULTIMA CUOTA PLAN DE PAGOS 4B | C50: 107386
A51: PUNITORIOS MAL COBRADOS | C51: 0
A52: Saldo al cierre $ (pesos) | C52: =SUM(C46:C51) -> 1039280.7
A56: CAJA EXTRAORDINARIA
A57: Egreso extraordinario | C57: =-C41 -> 0
A60: TOTAL | C60: =SUM(C56:C59) -> 0
A61: ATENCIÓN: Al momento de abonar en efectivo las expensas (dado que no se dispone de cuenta bancaria), deberán cancelar el monto total correspondiente, que incluye tanto las expensas como el consumo de Edesur de cada unidad funcional. Les recordamos que el pago debe realizarse con dinero justo.

Sheet prorrateo 
A1: Expensas ordinarias: | B1: =N1 -> 2249583.1 | D1: 1667839.1 | E1: Gastos extraordinarios: | G1: 0 | I1: ARBA: | L1: 500000 | N1: 2249583.1
A2: Propietarios | B2: Inquilinos | C2: UNIDAD FUNCIONAL | D2: % | E2: SALDO ANTERIOR | F2: SALDO ABONADO | G2: SALDO | H2: PUNITORIOS 4% | I2: ORDINARIAS | J2: EDESUR | K2: EXTRAORD. | L2: ARBA | M2: A PAGAR | O2: SIN EDESUR
A3: Ferrea Nestor | B3: Gabriel | C3: 1ro. "A" | D3: 5.11 | E3: 245146.06 | F3: =E3 -> 245146.06 | G3: =E3-F3 -> 0 | H3: =IF(G3>0,G3*4%,0) -> 0 | I3: =B$1*D3/100 -> 114953.7 | J3: =Edesur!N10 -> 56073.66 | K3: =G$1*D3/100 -> 0 | L3: =L$1*D3/100 -> 25550 | M3: =I3+G3+L3+K3+H3+J3 -> 196577.36 | O3: =M3-J3 -> 140503.7
A4: Gnecchi Nicolas | C4: 1ro. "B" | D4: 5.09 | E4: 237726.74 | F4: 110474 | G4: =E4-F4 -> 127252.74 | H4: =IF(G4>0,G4*4%,0) -> 5090.1095 | I4: =B$1*D4/100 -> 114503.78 | J4: =Edesur!N11 -> 32949.206 | K4: =G$1*D4/100 -> 0 | L4: =L$1*D4/100 -> 25450 | M4: =I4+G4+L4+K4+H4+J4 -> 305245.84 | O4: =M4-J4 -> 272296.63
A5: Triñanes Gaston | C5: 2do. "A" | D5: 5.04 | E5: 254798.72 | F5: =301940.37-F23 -> 254798.72 | G5: =E5-F5 -> -0.00053379126 | H5: =IF(G5>0,G5*4%,0) -> 0 | I5: =B$1*D5/100 -> 113378.99 | J5: =Edesur!N12 -> 65764.449 | K5: =G$1*D5/100 -> 0 | L5: =L$1*D5/100 -> 25200 | M5: =I5+G5+L5+K5+H5+J5 -> 204343.44 | O5: =M5-J5 -> 138578.99
A6: Nuñez Eva | C6: 2do. "B" | D6: 5.21 | E6: 390207.99 | F6: =E6 -> 390207.99 | G6: =E6-F6 -> 0 | H6: =IF(G6>0,G6*4%,0) -> 0 | I6: =B$1*D6/100 -> 117203.28 | J6: =Edesur!N13 -> 44952.18 | K6: =G$1*D6/100 -> 0 | L6: =L$1*D6/100 -> 26050 | M6: =I6+G6+L6+K6+H6+J6 -> 188205.46 | O6: =M6-J6 -> 143253.28
A7: Triñanes Gaston | B7: Leandro | C7: 3ro. "A" | D7: 5.11 | E7: 244958.49 | F7: =199250.14+92850-F28 -> 244958.49 | G7: =E7-F7 -> -0.00264251 | H7: =IF(G7>0,G7*4%,0) -> 0 | I7: =B$1*D7/100 -> 114953.7 | J7: =Edesur!N14 -> 58709.075 | K7: =G$1*D7/100 -> 0 | L7: =L$1*D7/100 -> 25550 | M7: =I7+G7+L7+K7+H7+J7 -> 199212.77 | O7: =M7-J7 -> 140503.7
A8: Grecco Pedro | C8: 3ro. "B" | D8: 5.09 | E8: 244451.27 | F8: =E8 -> 244451.27 | G8: =E8-F8 -> 0 | H8: =IF(G8>0,G8*4%,0) -> 0 | I8: =B$1*D8/100 -> 114503.78 | J8: =Edesur!N15 -> 62295.158 | K8: =G$1*D8/100 -> 0 | L8: =L$1*D8/100 -> 25450 | M8: =I8+G8+L8+K8+H8+J8 -> 202248.94 | O8: =M8-J8 -> 139953.78
A9: Mteljan Barbara | C9: 4to. "A" | D9: 5.11 | E9: 231697.01 | F9: =E9 -> 231697.01 | G9: =E9-F9 -> 0 | H9: =IF(G9>0,G9*4%,0) -> 0 | I9: =B$1*D9/100 -> 114953.7 | J9: =Edesur!N16 -> 45513.244 | K9: =G$1*D9/100 -> 0 | L9: =L$1*D9/100 -> 25550 | M9: =I9+G9+L9+K9+H9+J9 -> 186016.94 | O9: =M9-J9 -> 140503.7
A10: Carnevalli Christian | C10: 4to. "B" | D10: 5.09 | E10: 224924.81 | F10: =379452.66-107386-F22 -> 224925.01 | G10: =E10-F10 -> -0.19616077 | I10: =B$1*D10/100 -> 114503.78 | J10: =Edesur!N17 -> 36438.083 | K10: =G$1*D10/100 -> 0 | L10: =L$1*D10/100 -> 25450 | M10: =I10+G10+L10+K10+H10+J10 -> 176391.67 | O10: =M10-J10 -> 139953.59
A11: Leonor | C11: 5to. "A" | D11: 5.04 | E11: 379810.44 | F11: =E11 -> 379810.44 | G11: =E11-F11 -> 0 | H11: =IF(G11>0,G11*4%,0) -> 0 | I11: =B$1*D11/100 -> 113378.99 | J11: =Edesur!N18 -> 43527.551 | K11: =G$1*D11/100 -> 0 | L11: =L$1*D11/100 -> 25200 | M11: =I11+G11+L11+K11+H11+J11 -> 182106.54 | O11: =M11-J11 -> 138578.99
A12: Strangio Federico | C12: 5to. "B" | D12: 5.21 | E12: 253412.57 | F12: =E12 -> 253412.57 | G12: =E12-F12 -> 0 | H12: =IF(G12>0,G12*4%,0) -> 0 | I12: =B$1*D12/100 -> 117203.28 | J12: =Edesur!N19 -> 68736.563 | K12: =G$1*D12/100 -> 0 | L12: =L$1*D12/100 -> 26050 | M12: =I12+G12+L12+K12+H12+J12 -> 211989.84 | O12: =M12-J12 -> 143253.28
A13: Senderowicz Rosalia | B13: Alejo | C13: 6to. "A" | D13: 5.11 | E13: 253624.4 | F13: =300766.05-F24 -> 253624.4 | G13: =E13-F13 -> 0.00435749 | H13: =IF(G13>0,G13*4%,0) -> 0.0001742996 | I13: =B$1*D13/100 -> 114953.7 | J13: =Edesur!N20 -> 64608.277 | K13: =G$1*D13/100 -> 0 | L13: =L$1*D13/100 -> 25550 | M13: =I13+G13+L13+K13+H13+J13 -> 205111.98 | O13: =M13-J13 -> 140503.7
A14: Senderowicz Rosalia | B14: Anabella | C14: 6to. "B" | D14: 5.09 | E14: 228413.77 | F14: =275555.42-F25 -> 228413.77 | G14: =E14-F14 -> 0.0017421029 | H14: =IF(G14>0,G14*4%,0) -> 6.9684115e-05 | I14: =B$1*D14/100 -> 114503.78 | J14: =Edesur!N21 -> 40799.178 | K14: =G$1*D14/100 -> 0 | L14: =L$1*D14/100 -> 25450 | M14: =I14+G14+L14+K14+H14+J14 -> 180752.96 | O14: =M14-J14 -> 139953.78
A15: Alonso Graciela | B15: Facundo | C15: 7mo. "A" | D15: 5.04 | E15: 229298.05 | G15: =E15-F15 -> 229298.05 | H15: =IF(G15>0,G15*4%,0) -> 9171.9219 | I15: =B$1*D15/100 -> 113378.99 | J15: =Edesur!N22 -> 64882.851 | K15: =G$1*D15/100 -> 0 | L15: =L$1*D15/100 -> 25200 | M15: =I15+G15+L15+K15+H15+J15 -> 441931.81 | O15: =M15-J15 -> 377048.96
A16: Perez Rodriguez | B16: Mariel | C16: 7mo. "B" | D16: 5.21 | E16: 257482.92 | F16: =304624.57-F21 -> 257482.92 | G16: =E16-F16 -> 0.00198459 | H16: =IF(G16>0,G16*4%,0) -> 7.93836e-05 | I16: =B$1*D16/100 -> 117203.28 | J16: =Edesur!N23 -> 57585.289 | K16: =G$1*D16/100 -> 0 | L16: =L$1*D16/100 -> 26050 | M16: =I16+G16+L16+K16+H16+J16 -> 200838.57 | O16: =M16-J16 -> 143253.28
A17: Mourelos Pablo | C17: 8vo. "A" | D17: 5.04 | E17: 97801.26 | G17: =E17-F17 -> 97801.26 | H17: =IF(G17>0,G17*4%,0) -> 3912.0504 | I17: =B$1*D17/100 -> 113378.99 | J17: =Edesur!N24 -> 35780.745 | K17: =G$1*D17/100 -> 0 | L17: =L$1*D17/100 -> 25200 | M17: =I17+G17+L17+K17+H17+J17 -> 276073.05 | O17: =M17-J17 -> 240292.3
A18: Calabria Carlos/Giarrizzo Silvia | C18: 8vo. "B" | D18: 5.21 | E18: 239269.49 | F18: =E18 -> 239269.49 | G18: =E18-F18 -> 0 | H18: =IF(G18>0,G18*4%,0) -> 0 | I18: =B$1*D18/100 -> 117203.28 | J18: =Edesur!N25 -> 48459.813 | K18: =G$1*D18/100 -> 0 | L18: =L$1*D18/100 -> 26050 | M18: =I18+G18+L18+K18+H18+J18 -> 191713.1 | O18: =M18-J18 -> 143253.28
A19: Ariel | C19: 9no. "A" | D19: 7.4 | E19: 374177.79 | F19: =E19 -> 374177.79 | G19: =E19-F19 -> 0 | H19: =IF(G19>0,G19*4%,0) -> 0 | I19: =B$1*D19/100 -> 166469.15 | J19: =Edesur!N26 -> 91349.268 | K19: =G$1*D19/100 -> 0 | L19: =L$1*D19/100 -> 37000 | M19: =I19+G19+L19+K19+H19+J19 -> 294818.42 | O19: =M19-J19 -> 203469.15
A20: Espacio Edesur | C20: COCHERA 1 | D20: 1.08 | E20: 399381.2 | F20: 0 | G20: =E20-F20 -> 399381.2 | I20: =B$1*D20/100 -> 24295.498 | J20: =Edesur!N27 -> 6905.618 | K20: =G$1*D20/100 -> 0 | L20: =L$1*D20/100 -> 5400 | M20: =I20+G20+L20+K20+H20+J20 -> 435982.32 | O20: =M20-J20 -> 429076.7
B21: Mariel | C21: COCHERA 2 | D21: 1.08 | E21: 47141.651 | F21: =E21 -> 47141.651 | G21: =E21-F21 -> 0 | H21: =IF(G21>0,G21*4%,0) -> 0 | I21: =B$1*D21/100 -> 24295.498 | J21: =Edesur!N28 -> 6905.618 | K21: =G$1*D21/100 -> 0 | L21: =L$1*D21/100 -> 5400 | M21: =I21+G21+L21+K21+H21+J21 -> 36601.116 | O21: =M21-J21 -> 29695.498
A22: Carnevalli Christian | C22: COCHERA 3 | D22: 1.08 | E22: 47141.651 | F22: 47141.651 | G22: =E22-F22 -> 0 | H22: =IF(G22>0,G22*4%,0) -> 0 | I22: =B$1*D22/100 -> 24295.498 | J22: =Edesur!N29 -> 6905.618 | K22: =G$1*D22/100 -> 0 | L22: =L$1*D22/100 -> 5400 | M22: =I22+G22+L22+K22+H22+J22 -> 36601.116 | O22: =M22-J22 -> 29695.498
A23: Triñanes Gaston | C23: COCHERA 4 | D23: 1.08 | E23: 47141.651 | F23: =E23 -> 47141.651 | G23: =E23-F23 -> 0 | H23: =IF(G23>0,G23*4%,0) -> 0 | I23: =B$1*D23/100 -> 24295.498 | J23: =Edesur!N30 -> 6905.618 | K23: =G$1*D23/100 -> 0 | L23: =L$1*D23/100 -> 5400 | M23: =I23+G23+L23+K23+H23+J23 -> 36601.116 | O23: =M23-J23 -> 29695.498
A24: Senderowicz Rosalia | B24: Alejo | C24: COCHERA 5 | D24: 1.08 | E24: 47141.651 | F24: =E24 -> 47141.651 | G24: =E24-F24 -> 0 | H24: =IF(G24>0,G24*4%,0) -> 0 | I24: =B$1*D24/100 -> 24295.498 | J24: =Edesur!N31 -> 6905.618 | K24: =G$1*D24/100 -> 0 | L24: =L$1*D24/100 -> 5400 | M24: =I24+G24+L24+K24+H24+J24 -> 36601.116 | O24: =M24-J24 -> 29695.498
A25: Senderowicz Rosalia | B25: Anabella | C25: COCHERA 6 | D25: 1.08 | E25: 47141.651 | F25: =E25 -> 47141.651 | G25: =E25-F25 -> 0 | H25: =IF(G25>0,G25*4%,0) -> 0 | I25: =B$1*D25/100 -> 24295.498 | J25: =Edesur!N32 -> 6905.618 | K25: =G$1*D25/100 -> 0 | L25: =L$1*D25/100 -> 5400 | M25: =I25+G25+L25+K25+H25+J25 -> 36601.116 | O25: =M25-J25 -> 29695.498
A26: Ariel | C26: COCHERA 7 | D26: 1.08 | E26: 47141.651 | F26: =E26 -> 47141.651 | G26: =E26-F26 -> 0 | H26: =IF(G26>0,G26*4%,0) -> 0 | I26: =B$1*D26/100 -> 24295.498 | J26: =Edesur!N33 -> 6905.618 | K26: =G$1*D26/100 -> 0 | L26: =L$1*D26/100 -> 5400 | M26: =I26+G26+L26+K26+H26+J26 -> 36601.116 | O26: =M26-J26 -> 29695.498
A27: Ariel | C27: COCHERA 8 | D27: 1.08 | E27: 47141.651 | F27: =E27 -> 47141.651 | G27: =E27-F27 -> 0 | H27: =IF(G27>0,G27*4%,0) -> 0 | I27: =B$1*D27/100 -> 24295.498 | J27: =Edesur!N34 -> 6905.618 | K27: =G$1*D27/100 -> 0 | L27: =L$1*D27/100 -> 5400 | M27: =I27+G27+L27+K27+H27+J27 -> 36601.116 | O27: =M27-J27 -> 29695.498 | P27: =F27+F26+F19 -> 468461.1
B28: =B7 -> Leandro | C28: COCHERA 9 | D28: 1.08 | E28: 47141.651 | F28: =E28 -> 47141.651 | G28: =E28-F28 -> 0 | H28: =IF(G28>0,G28*4%,0) -> 0 | I28: =B$1*D28/100 -> 24295.498 | J28: =Edesur!N35 -> 6905.618 | K28: =G$1*D28/100 -> 0 | L28: =L$1*D28/100 -> 5400 | M28: =I28+G28+L28+K28+H28+J28 -> 36601.116 | O28: =M28-J28 -> 29695.498
A29: Alonso Graciela | B29: Facundo | C29: COCHERA 10 | D29: 1.08 | E29: 47141.651 | G29: =E29-F29 -> 47141.651 | H29: =IF(G29>0,G29*4%,0) -> 1885.666 | I29: =B$1*D29/100 -> 24295.498 | J29: =Edesur!N36 -> 6905.618 | K29: =G$1*D29/100 -> 0 | L29: =L$1*D29/100 -> 5400 | M29: =I29+G29+L29+K29+H29+J29 -> 85628.433 | O29: =M29-J29 -> 78722.815
C31: TOTAL EXPENSAS | D31: =SUM(D3:D30) -> 100 | F31: =SUM(F3:F30) -> 4309983.1 | I31: =SUM(I3:I30) -> 2249583.1 | K31: =SUM(K3:K30) -> 0 | M31: =SUM(M3:M29) -> 4657998.4

Sheet Edesur
A1: EDESUR
C6: ='detalle y gastos'!C7 -> Vto. 13/03
B7: EDESUR | C7: =-'detalle y gastos'!C49 -> 987480.77
B8: EDESUR | K8: =C8-J38 -> -348071.69 | L8: =C7-J38 -> 639409.08
A9: U.F. | B9: U.F. | C9: PISO - DEPTO | D9: PROPIETARIOS | E9: % | F9: CONSUMO ANT. | G9: CONSUMO ACTUAL | H9: KWH | I9: INTERES POR MORA 7% | J9: EDESUR | K9: PARTES COMUNES | L9: PARTES COMUNES | M9: KWH | N9: EDESUR FINAL
A10: 1 | B10: 1 | C10: 1ro. "A" | D10: Ferrea Nestor | E10: 5.11 | F10: 4893.5 | G10: 5143 | H10: =G10-F10 -> 249.5 | I10: =H10*7% -> 17.465 | J10: =M10*93.787 -> 23399.857 | K10: =K8*E10% -> -17786.464 | L10: =L$8*E10/S$12 -> 32673.804 | M10: =G10-F10 -> 249.5 | N10: =J10+L10 -> 56073.66 | O10: =N10+'prorrateo '!M3 -> 252651.02
A11: 2 | B11: 2 | C11: 1ro. "B" | D11: Gnecchi Nicolas | E11: 5.09 | F11: 4543.8 | G11: 4548.1 | H11: =G11-F11 -> 4.3 | I11: =H11*7% -> 0.301 | J11: =M11*93.787 -> 403.2841 | K11: =K8*E11% -> -17716.849 | L11: =L$8*E11/S$12 -> 32545.922 | M11: =G11-F11 -> 4.3 | N11: =J11+L11 -> 32949.206 | O11: =N11+'prorrateo '!M4 -> 338195.04
A12: 3 | B12: 3 | C12: 2do. "A" | D12: Triñanes Gaston | E12: 5.04 | F12: 2352.9 | G12: 2710.5 | H12: =G12-F12 -> 357.6 | I12: =H12*7% -> 25.032 | J12: =M12*93.787 -> 33538.231 | K12: =K8*E12% -> -17542.813 | L12: =L$8*E12/S$12 -> 32226.217 | M12: =G12-F12 -> 357.6 | N12: =J12+L12 -> 65764.449 | O12: =N12+'prorrateo '!M5 -> 270107.89 | S12: 100
A13: 4 | B13: 4 Y 5 | C13: 2do. "B" | D13: Nuñez Eva | E13: 5.21 | F13: 1511.5 | G13: 1635.6 | H13: =G13-F13 -> 124.1 | I13: =H13*7% -> 8.687 | J13: =M13*93.787 -> 11638.967 | K13: =K8*E13% -> -18134.535 | L13: =L$8*E13/S$12 -> 33313.213 | M13: =G13-F13 -> 124.1 | N13: =J13+L13 -> 44952.18 | O13: =N13+'prorrateo '!M6 -> 233157.64
A14: 6 | B14: 6 | C14: 3ro. "A" | D14: Triñanes Gaston | E14: 5.11 | F14: 2363.6 | G14: 2641.2 | H14: =G14-F14 -> 277.6 | I14: =H14*7% -> 19.432 | J14: =M14*93.787 -> 26035.271 | K14: =K8*E14% -> -17786.464 | L14: =L$8*E14/S$12 -> 32673.804 | M14: =G14-F14 -> 277.6 | N14: =J14+L14 -> 58709.075 | O14: =N14+'prorrateo '!M7 -> 257921.85
A15: 7 | B15: 7 | C15: 3ro. "B" | D15: Grecco Pedro | E15: 5.09 | F15: 3564.3 | G15: 3881.5 | H15: =G15-F15 -> 317.2 | I15: =H15*7% -> 22.204 | J15: =M15*93.787 -> 29749.236 | K15: =K8*E15% -> -17716.849 | L15: =L$8*E15/S$12 -> 32545.922 | M15: =G15-F15 -> 317.2 | N15: =J15+L15 -> 62295.158 | O15: =N15+'prorrateo '!M8 -> 264544.1
A16: 8 | B16: 8 | C16: 4to. "A" | D16: Mteljan Barbara | E16: 5.11 | F16: 2836.7 | G16: 2973.6 | H16: =G16-F16 -> 136.9 | I16: =H16*7% -> 9.583 | J16: =M16*93.787 -> 12839.44 | K16: =K8*E16% -> -17786.464 | L16: =L$8*E16/S$12 -> 32673.804 | M16: =G16-F16 -> 136.9 | N16: =J16+L16 -> 45513.244 | O16: =N16+'prorrateo '!M9 -> 231530.19
A17: 9 | B17: 9 | C17: 4to. "B" | D17: Carnevalli | E17: 5.09 | F17: 3459.5 | G17: 3501 | H17: =G17-F17 -> 41.5 | I17: =H17*7% -> 2.905 | J17: =M17*93.787 -> 3892.1605 | K17: =K8*E17% -> -17716.849 | L17: =L$8*E17/S$12 -> 32545.922 | M17: =G17-F17 -> 41.5 | N17: =J17+L17 -> 36438.083 | O17: =N17+'prorrateo '!M10 -> 212829.75
A18: 10 | B18: 10 | C18: 5to. "A" | D18: Leonor | E18: 5.04 | F18: 2601.9 | G18: 2722.4 | H18: =G18-F18 -> 120.5 | I18: =H18*7% -> 8.435 | J18: =M18*93.787 -> 11301.334 | K18: =K8*E18% -> -17542.813 | L18: =L$8*E18/S$12 -> 32226.217 | M18: =G18-F18 -> 120.5 | N18: =J18+L18 -> 43527.551 | O18: =N18+'prorrateo '!M11 -> 225634.09
A19: 11 | B19: 11 | C19: 5to. "B" | D19: Strangio Federico | E19: 5.21 | F19: 5191 | G19: 5568.7 | H19: =G19-F19 -> 377.7 | I19: =H19*7% -> 26.439 | J19: =M19*93.787 -> 35423.35 | K19: =K8*E19% -> -18134.535 | L19: =L$8*E19/S$12 -> 33313.213 | M19: =G19-F19 -> 377.7 | N19: =J19+L19 -> 68736.563 | O19: =N19+'prorrateo '!M12 -> 280726.41
A20: 12 | B20: 12 | C20: 6to. "A" | D20: Senderowicz Rosalia | E20: 5.11 | F20: 6705 | G20: 7045.5 | H20: =G20-F20 -> 340.5 | I20: =H20*7% -> 23.835 | J20: =M20*93.787 -> 31934.474 | K20: =K8*E20% -> -17786.464 | L20: =L$8*E20/S$12 -> 32673.804 | M20: =G20-F20 -> 340.5 | N20: =J20+L20 -> 64608.277 | O20: =N20+'prorrateo '!M13 -> 269720.26
A21: 13 | B21: 13 | C21: 6to. "B" | D21: Senderowicz Rosalia | E21: 5.09 | F21: 4338.3 | G21: 4426.3 | H21: =G21-F21 -> 88 | I21: =H21*7% -> 6.16 | J21: =M21*93.787 -> 8253.256 | K21: =K8*E21% -> -17716.849 | L21: =L$8*E21/S$12 -> 32545.922 | M21: =G21-F21 -> 88 | N21: =J21+L21 -> 40799.178 | O21: =N21+'prorrateo '!M14 -> 221552.14
A22: 14 | B22: 14 | C22: 7mo. "A" | D22: Alonso Graciela | E22: 5.04 | F22: 2797.6 | G22: 3145.8 | H22: =G22-F22 -> 348.2 | I22: =H22*7% -> 24.374 | J22: =M22*93.787 -> 32656.633 | K22: =K8*E22% -> -17542.813 | L22: =L$8*E22/S$12 -> 32226.217 | M22: =G22-F22 -> 348.2 | N22: =J22+L22 -> 64882.851 | O22: =N22+'prorrateo '!M15 -> 506814.66
A23: 15 | B23: 15 | C23: 7mo. "B" | D23: Perez Rodriguez | E23: 5.21 | F23: 5576.5 | G23: 5835.3 | H23: =G23-F23 -> 258.8 | I23: =H23*7% -> 18.116 | J23: =M23*93.787 -> 24272.076 | K23: =K8*E23% -> -18134.535 | L23: =L$8*E23/S$12 -> 33313.213 | M23: =G23-F23 -> 258.8 | N23: =J23+L23 -> 57585.289 | O23: =N23+'prorrateo '!M16 -> 258423.86
A24: 16 | B24: 16 | C24: 8vo. "A" | D24: Mourelos Pablo | E24: 5.04 | F24: 1982.9 | G24: 2020.8 | H24: =G24-F24 -> 37.9 | I24: =H24*7% -> 2.653 | J24: =M24*93.787 -> 3554.5273 | K24: =K8*E24% -> -17542.813 | L24: =L$8*E24/S$12 -> 32226.217 | M24: =G24-F24 -> 37.9 | N24: =J24+L24 -> 35780.745 | O24: =N24+'prorrateo '!M17 -> 311853.79
A25: 17 | B25: 17 | C25: 8vo. "B" | D25: Calabria Carlos/Giarrizzo Silvia | E25: 5.21 | F25: 2155.8 | G25: 2317.3 | H25: =G25-F25 -> 161.5 | I25: =H25*7% -> 11.305 | J25: =M25*93.787 -> 15146.601 | K25: =K8*E25% -> -18134.535 | L25: =L$8*E25/S$12 -> 33313.213 | M25: =G25-F25 -> 161.5 | N25: =J25+L25 -> 48459.813 | O25: =N25+'prorrateo '!M18 -> 240172.91
A26: 18 | B26: 18 | C26: 9no. "A" | D26: Ariel | E26: 7.4 | F26: 9974.5 | G26: 10444 | H26: =G26-F26 -> 469.5 | I26: =H26*7% -> 32.865 | J26: =M26*93.787 -> 44032.997 | K26: =K8*E26% -> -25757.305 | L26: =L$8*E26/S$12 -> 47316.272 | M26: =G26-F26 -> 469.5 | N26: =J26+L26 -> 91349.268 | O26: =N26+'prorrateo '!M19 -> 386167.69
A27: 19 | B27: 19 | C27: COCHERA 1 | E27: 1.08 | H27: =G27-F27 -> 0 | I27: =H27*7% -> 0 | L27: =L$8*E27/S$12 -> 6905.618 | M27: 0 | N27: =J27+L27 -> 6905.618 | O27: =N27+'prorrateo '!M20 -> 442887.94
A28: 20 | C28: COCHERA 2 | E28: 1.08 | H28: 0 | I28: =H28*7% -> 0 | L28: =L$8*E28/S$12 -> 6905.618 | M28: 0 | N28: =J28+L28 -> 6905.618 | O28: =N28+'prorrateo '!M21 -> 43506.734
C29: COCHERA 3 | E29: 1.08 | L29: =L$8*E29/S$12 -> 6905.618 | M29: 0 | N29: =J29+L29 -> 6905.618 | O29: =N29+'prorrateo '!M22 -> 43506.734
C30: COCHERA 4 | E30: 1.08 | L30: =L$8*E30/S$12 -> 6905.618 | M30: 0 | N30: =J30+L30 -> 6905.618 | O30: =N30+'prorrateo '!M23 -> 43506.734
C31: COCHERA 5 | D31: Senderowicz Rosalia | E31: 1.08 | L31: =L$8*E31/S$12 -> 6905.618 | M31: 0 | N31: =J31+L31 -> 6905.618 | O31: =N31+'prorrateo '!M24 -> 43506.734
C32: COCHERA 6 | D32: Senderowicz Rosalia | E32: 1.08 | L32: =L$8*E32/S$12 -> 6905.618 | M32: 0 | N32: =J32+L32 -> 6905.618 | O32: =N32+'prorrateo '!M25 -> 43506.734
C33: COCHERA 7 | D33: Ariel | E33: 1.08 | L33: =L$8*E33/S$12 -> 6905.618 | M33: 0 | N33: =J33+L33 -> 6905.618 | O33: =N33+'prorrateo '!M26 -> 43506.734
C34: COCHERA 8 | D34: Ariel | E34: 1.08 | L34: =L$8*E34/S$12 -> 6905.618 | M34: 0 | N34: =J34+L34 -> 6905.618 | O34: =N34+'prorrateo '!M27 -> 43506.734
A35: 21 | C35: COCHERA 9 | E35: 1.08 | H35: 0 | I35: =H35*7% -> 0 | L35: =L$8*E35/S$12 -> 6905.618 | M35: 0 | N35: =J35+L35 -> 6905.618 | O35: =N35+'prorrateo '!M28 -> 43506.734
A36: 22 | C36: COCHERA 10 | D36: Alonso Graciela | E36: 1.08 | H36: 0 | I36: =H36*7% -> 0 | L36: =L$8*E36/S$12 -> 6905.618 | M36: 0 | N36: =J36+L36 -> 6905.618 | O36: =N36+'prorrateo '!M29 -> 92534.051
A37: 23 | H37: 0 | I37: =H37*7% -> 0 | L37: 0 | M37: 0 | N37: =J37+L37 -> 0
A38: 24 | J38: =SUM(J10:J37) -> 348071.69 | L38: =SUM(L10:L37) -> 639409.08 | N38: =SUM(N10:N37) -> 987480.77
E39: =SUM(E10:E38) -> 100 | I39: =SUM(I10:I38) -> 259.791 | L39: =L38+J38 -> 987480.77
A40: NOTA:
