Workbook

Sheet RESUMEN
C1: MAIL: elmiradorconsorcios@gmail.com
C2: CUIT ADMINISTRACION: 27231256879
C3: CBU: 0720039720000002171436 | E3: TELEFONO: 11 5320-2676
C4: ADMINISTRADORA: CAROLINA CANCIANI MP:1148
C5: PERÍODO: DICIEMBRE | E5: HORARIOS DE ATENCION: LUNES A VIERNES - 10 A 16HS - EMERGENCIAS 24HS
C6: LIQUIDACION DE EXPENSAS
A14: Importante para dueños o inquilinos de departamentos o coheras: Queremos recordarles una cuestión importante respecto a los pagos de expensas que ayuda a evitar errores en la imputación de los mismos. El sistema que utilizamos asigna centavos únicos a cada Unidad Funcional (UF), lo cual nos permite identificar automáticamente a qué unidad corresponde cada transferencia. Es decir, cada UF tiene un número específico de centavos que actúa como "identificador". Por ejemplo, si tu UF es la 45, el importe a abonar debería terminar en $...,45. Si tenés más de una unidad (por ejemplo, un departamento y una cochera), cada una tiene su propio código de centavos. En esos casos, te pedimos por favor que realices una transferencia por cada UF, respetando el importe con sus centavos correspondientes. Sabemos que a veces por comodidad se suele enviar todo junto en una sola transferencia, pero esto puede generar confusión o errores en la imputación automática. Realizar los pagos por separado nos permite asegurar que cada importe se asigne correctamente. Agradecemos muchísimo la colaboración para seguir manteniendo todo ordenado. Saludos cordiales.
A20: VTO 15/01
A24: GASTOS ORDINARIOS UNIDADES FUNCIONALES: | E24: UF 93,20% | F24: LOCAL 1 (1,08%) | G24: LOCAL 2 (1,28%) | H24: LOCAL 3 (1,21%) | I24: LOCAL 4 (1,49%) | J24: LOCAL 5 (1,74%)
A25: Sueldo encargada Sonia Arzamendia Galeano
A26: Haberes | D26: 1042462
A27: Plus pileta | D27: 36382.7
A28: Plus retiro de basura | D28: =1584.8*80 -> 126784
A29: Plus cochera | D29: 21627.4
A30: Adicional Viaticos | D30: 60810.3
A31: Adicional remuneracion | D31: 50000
A32: SUBTOTAL | D32: =SUM(D26:D31) -> 1338066.4
A33: Sueldo encargada Miriam
A34: Haberes | D34: 521231
A35: Horas extras | D35: 100235
A36: Plus pileta | D36: =D27 -> 36382.7
A37: Plus retiro de basura | D37: =D28 -> 126784
A38: Plus cochera | D38: =D29 -> 21627.4
A39: Adicional Viaticos | D39: =D30 -> 60810.3
A40: Adicional remuneracion | D40: 50000
A41: SUBTOTAL | D41: =SUM(D34:D40) -> 917070.4
A42: TOTAL SUELDO | D42: =D32+D41 -> 2255136.8 | E42: =D42*93.2% -> 2101787.5 | F42: =$D42*1.08% -> 24355.477 | G42: =$D42*1.28% -> 28865.751 | H42: =$D42*1.21% -> 27287.155 | I42: =$D42*1.49% -> 33601.538 | J42: =D42*1.74% -> 39239.38 | K42: =E42+J42+F42+G42+H42+I42 -> 2255136.8 | L42: =K42-600000 -> 1655136.8
A43: SAC | D43: 0 | E43: =D43*91.91% -> 0 | J43: =D43*8.09% -> 0
D44: 0 | E44: =D44*91.91% -> 0 | J44: =D44*8.09% -> 0
A47: TOTAL | D47: =SUM(D43:D45) -> 0 | E47: =SUM(E43:E45) -> 0 | J47: =SUM(J43:J45) -> 0 | K47: =E47+J47 -> 0 | L47: =IF(D47=K47, "", "Error")
A48: COMBUSTIBLE PARA GRUPO ELECTROGENO | E48: =D48*91.91% -> 0 | J48: =D48*8.09% -> 0
E49: =D49 -> 0
E50: =D50 -> 0
E51: =D51*91.91% -> 0 | J51: =D51*8.09% -> 0
A52: TOTAL SAC | D52: =SUM(D44:D51) -> 0 | E52: =SUM(E44:E51) -> 0 | K52: =E52+J52+F52+G52+H52+I52 -> 0 | L52: =IF(D52=K52, "", "Error")
A53: IMPUESTOS
A54: ARBA - Impuesto inmobiliario partida 025024270-0 | C54: Cuota adicional | D54: 278973.9
A55: ARBA - Impuesto inmobiliario partida 025024270-0 | C55: Cuota 5 | D55: 14032.9
A56: TSG - Partida 197229000 | B56: Mes de DICIEMBRE | D56: 763852
A57: TSG - Partida 197229000 | B57: Mes de DICIEMBRE | D57: 763852
A58: TOTAL IMPUESTOS | D58: =SUM(D54:D57) -> 1820710.8 | E58: =D58*93.2% -> 1696902.5 | F58: =$D58*1.08% -> 19663.677 | G58: =$D58*1.28% -> 23305.098 | H58: =$D58*1.21% -> 22030.601 | I58: =$D58*1.49% -> 27128.591 | J58: =D58*1.74% -> 31680.368 | K58: =E58+J58+F58+G58+H58+I58 -> 1820710.8 | L58: =IF(D58=K58, "", "Error")
A59: APORTES Y CONTRIBUCIONES
A60: Monotributo Sra. Sonia | C60: PMC 20/11 | D60: 56231.41
A61: Monotributo Sra. Miriam | C61: PMC 27/11 | D61: 64940.71
A62: TOTAL APORTES Y CONTRIBUCIONES | D62: =SUM(D59:D61) -> 121172.12 | E62: =D62*93.2% -> 112932.42 | F62: =$D62*1.08% -> 1308.6589 | G62: =$D62*1.28% -> 1551.0031 | H62: =$D62*1.21% -> 1466.1827 | I62: =$D62*1.49% -> 1805.4646 | J62: =D62*1.74% -> 2108.3949 | K62: =E62+J62+F62+G62+H62+I62 -> 121172.12 | L62: =IF(D62=K62, "", "Error")
A63: SEGUROS
A64: Federacion patronal - Poliza integral para consorcios nro. 2152393 | D64: 160913 | E64: =D64*93.2% -> 149970.92 | F64: =$D64*1.08% -> 1737.8604 | G64: =$D64*1.28% -> 2059.6864 | H64: =$D64*1.21% -> 1947.0473 | I64: =$D64*1.49% -> 2397.6037 | J64: =D64*1.74% -> 2799.8862 | K64: =SUM(E64:J64) -> 160913
A65: Federacion patronal - Poliza accidentes personales Sra. Sonia - nro. 9559834 | D65: 7907 | E65: =D65*93.2% -> 7369.324 | F65: =$D65*1.08% -> 85.3956 | G65: =$D65*1.28% -> 101.2096 | H65: =$D65*1.21% -> 95.6747 | I65: =$D65*1.49% -> 117.8143 | J65: =D65*1.74% -> 137.5818 | K65: =SUM(E65:J65) -> 7907
A66: Federacion patronal - Poliza accidentes personales Sra. Miriam - nro. 9559886 | D66: 7907 | E66: =D66*93.2% -> 7369.324 | F66: =$D66*1.08% -> 85.3956 | G66: =$D66*1.28% -> 101.2096 | H66: =$D66*1.21% -> 95.6747 | I66: =$D66*1.49% -> 117.8143 | J66: =D66*1.74% -> 137.5818 | K66: =SUM(E66:J66) -> 7907
A67: TOTAL Aportes y Contribuciones - Sindicato | D67: =SUM(D64:D66) -> 176727 | E67: =SUM(E64:E66) -> 164709.56 | F67: =SUM(F64:F66) -> 1908.6516 | G67: =SUM(G64:G66) -> 2262.1056 | H67: =SUM(H64:H66) -> 2138.3967 | I67: =SUM(I64:I66) -> 2633.2323 | J67: =SUM(J64:J66) -> 3075.0498 | K67: =E67+J67+F67+G67+H67+I67 -> 176727 | L67: =IF(D67=K67, "", "Error")
A68: ABONOS Y SERVICIOS
A69: Aysa - Cuenta 249011 | C69: Transf 15/12 | D69: 834391.68 | E69: =D69*93.2% -> 777653.05 | F69: =$D69*1.08% -> 9011.4301 | G69: =$D69*1.28% -> 10680.214 | H69: =$D69*1.21% -> 10096.139 | I69: =$D69*1.49% -> 12432.436 | J69: =D69*1.74% -> 14518.415 | K69: =D69 -> 834391.68 | L69: =SUM(E69:J69) -> 834391.68
A70: Edesur - Cliente 01291636 | C70: Transf 15/12 | D70: 2334594.1 | E70: =D70*93.2% -> 2175841.7 | F70: =$D70*1.08% -> 25213.616 | G70: =$D70*1.28% -> 29882.805 | H70: =$D70*1.21% -> 28248.589 | I70: =$D70*1.49% -> 34785.452 | J70: =D70*1.74% -> 40621.938 | K70: =D70 -> 2334594.1 | L70: =E70+J70+I70+H70+G70+F70 -> 2334594.1
A71: Telecentro - Zona coworking - Cliente 7725479 | C71: Transf 25/11 | D71: 118908 | E71: =D71 -> 118908 | K71: =D71 -> 118908 | L71: =E71+J71+I71+H71+G71+F71 -> 118908 | M71: =L71-D71 -> 0 | N71: =K71-D71 -> 0
A72: ADS - Abono de mantenimiento ascensores DICIEMBRE del 2025 | C72: Transf 05/12 | D72: 352314.06 | E72: =D72 -> 352314.06 | K72: =D72 -> 352314.06 | L72: =E72+J72+I72+H72+G72+F72 -> 352314.06
A73: ADS - Abono de mantenimiento ascensores NOVIEMBRE del 2025 | C73: Transf 05/12 | D73: 309917.37
A74: Victor Martinez - Abono mantenimiento control de accesos | D74: 0 | E74: =D74 -> 0 | K74: =D74 -> 0 | L74: =E74+J74+I74+H74+G74+F74 -> 0 | M74: =L74-D74 -> 0 | N74: =K74-D74 -> 0
A75: Metrogas - Cliente nro. 40000496339 | D75: 1008555.2 | E75: =D75*93.2% -> 939973.41 | F75: =$D75*1.08% -> 10892.396 | G75: =$D75*1.28% -> 12909.506 | H75: =$D75*1.21% -> 12203.517 | I75: =$D75*1.49% -> 15027.472 | J75: =D75*1.74% -> 17548.86 | K75: =D75 -> 1008555.2 | L75: =E75+J75+I75+H75+G75+F75 -> 1008555.2 | M75: =L75-D75 -> 0 | N75: =K75-D75 -> 0
A76: Metrogas - Cliente nro. 40000497007 | D76: 10221.41 | E76: =D76*93.2% -> 9526.3541 | F76: =$D76*1.08% -> 110.39123 | G76: =$D76*1.28% -> 130.83405 | H76: =$D76*1.21% -> 123.67906 | I76: =$D76*1.49% -> 152.29901 | J76: =D76*1.74% -> 177.85253 | K76: =D76 -> 10221.41 | L76: =E76+J76+I76+H76+G76+F76 -> 10221.41 | M76: =L76-D76 -> 0 | N76: =K76-D76 -> 0
A77: Loschi Mantenimiento grupo electrogeno - Abono bimestral | C77: Transf 26/11 | D77: 100000 | E77: =D77*93.2% -> 93200 | F77: =$D77*1.08% -> 1080 | G77: =$D77*1.28% -> 1280 | H77: =$D77*1.21% -> 1210 | I77: =$D77*1.49% -> 1490 | J77: =D77*1.74% -> 1740 | K77: =D77 -> 100000 | L77: =E77+J77+I77+H77+G77+F77 -> 100000 | M77: =L77-D77 -> 0 | N77: =K77-D77 -> 0
A78: Loschi Reparacion de burro de arranque, rele y luces testigo | C78: Transf 09/12 | D78: 460000 | E78: =D79 -> 25000 | K78: =D78 -> 460000 | N78: =K78-D78 -> 0
A79: Servisur - Programacion de reloj filtrado pileta | C79: Transf 25/11 | D79: 25000 | K79: =D79 -> 25000 | L79: =E78+J79+I79+H79+G79+F79 -> 25000
A80: Servisur - Restablecimiento de emergencia generador por salto de termica | C80: Transf 11/11 | D80: 60000 | E80: =D80 -> 60000 | K80: =D80 -> 60000 | L80: =E80+J80+I80+H80+G80+F80 -> 60000 | N80: =K80-D80 -> 0
A81: Uniforme de trabajo Megasec | C81: Transf 23/12 | D81: 337100 | E81: =D81 -> 337100 | K81: =D81 -> 337100 | L81: =E81+J81+I81+H81+G81+F81 -> 337100 | M81: =L81-D81 -> 0 | N81: =K81-D81 -> 0
A82: Distribuidora Barbiero - Tubo led, plafones y demas articulos | C82: Transf 04/12 | D82: 123908 | E82: =D82 -> 123908 | K82: =D82 -> 123908 | M82: =IF(K82=L82, "", "Error") -> Error | N82: =K82-D82 -> 0
A83: TOTAL ABONOS Y SERVICIOS | D83: =SUM(D69:D82) -> 6074909.8 | E83: =SUM(E69:E82) -> 5013424.6 | F83: =SUM(F69:F82) -> 46307.834 | G83: =SUM(G69:G82) -> 54883.358 | H83: =SUM(H69:H82) -> 51881.925 | I83: =SUM(I69:I82) -> 63887.659 | J83: =SUM(J69:J82) -> 74607.065 | K83: =E83+J83+F83+G83+H83+I83 -> 5304992.4 | L83: =IF(D83=K83, "", "Error") -> Error | M83: =D83-K83 -> 769917.37
A86: GASTOS VARIOS
A87: Articulos de limpieza - Mes de DICIEMBRE | C87: Transf 19/12 | D87: 474000 | E87: =D87*93.2% -> 441768 | F87: =$D87*1.08% -> 5119.2 | G87: =$D87*1.28% -> 6067.2 | H87: =$D87*1.21% -> 5735.4 | I87: =$D87*1.49% -> 7062.6 | J87: =D87*1.74% -> 8247.6
A88: Articulos de limpieza - Mes de DICIEMBRE | C88: Transf 19/12 | D88: 512900 | E88: =D88 -> 512900
A89: Julio Doartero - Colocacion sifon en pileta | C89: Transf 18/12 | D89: 45000 | E89: =D89 -> 45000
A90: Julio Doartero - Destapacion bacha de cocina | C90: Transf 15/12 | D90: 85000 | E90: =D90 -> 85000
A91: Julio Doartero - Cambio de automaticos | C91: Transf 15/12 | D91: 135000 | E91: =D91 -> 135000
A92: Desobstruccion de columna lavadero en el 3C | C92: Transf 18/12 | D92: 24100 | E92: =D92 -> 24100
A93: Repaso en sector de trabajo (Desobstruccion 3C) | C93: Transf 18/12 | D93: 24100 | E93: =D93 -> 24100
A94: Servisur - Colocacion de 7 tubos 18w en sector cocheras - Regulacion de 31 sensores de movimineto en cocheras y pallieres | C94: Transf 04/12 | D94: 322000 | E94: =D94 -> 322000
A95: TOTAL GASTOS VARIOS | D95: =SUM(D87:D94) -> 1622100 | E95: =SUM(E87:E94) -> 1589868 | F95: =SUM(F87:F94) -> 5119.2 | G95: =SUM(G87:G94) -> 6067.2 | H95: =SUM(H87:H94) -> 5735.4 | I95: =SUM(I87:I94) -> 7062.6 | J95: =SUM(J87:J94) -> 8247.6 | K95: =E95+J95+F95+G95+H95+I95 -> 1622100 | L95: =IF(D95=K95, "", "Error")
A98: GASTOS DE ADMINISTRACION
A99: RC Adm Cons. CANCIANI, Carolina | B99: MP:1148 | D99: 753700 | E99: =D99*93.2% -> 702448.4 | F99: =$D99*1.08% -> 8139.96 | G99: =$D99*1.28% -> 9647.36 | H99: =$D99*1.21% -> 9119.77 | I99: =$D99*1.49% -> 11230.13 | J99: =D99*1.74% -> 13114.38 | L99: 0CTtubr3
A102: TOTAL GASTOS DE ADMINISTRACION | D102: =SUM(D99:D101) -> 753700 | E102: =SUM(E99:E101) -> 702448.4 | F102: =SUM(F99:F101) -> 8139.96 | G102: =SUM(G99:G101) -> 9647.36 | H102: =SUM(H99:H101) -> 9119.77 | I102: =SUM(I99:I101) -> 11230.13 | J102: =SUM(J99:J101) -> 13114.38 | K102: =E102+J102+F102+G102+H102+I102 -> 753700 | L102: =IF(D102=K102, "", "Error")
A103: Gastos bancarios | D103: 119739.39 | E103: =D103*93.2% -> 111597.11 | F103: =$D103*1.08% -> 1293.1854 | G103: =$D103*1.28% -> 1532.6642 | H103: =$D103*1.21% -> 1448.8466 | I103: =$D103*1.49% -> 1784.1169 | J103: =D103*1.74% -> 2083.4654
A104: Mantenimiento de cuenta | E104: =D104*93.2% -> 0 | F104: =$D104*1.08% -> 0 | G104: =$D104*1.28% -> 0 | H104: =$D104*1.21% -> 0 | I104: =$D104*1.49% -> 0 | J104: =D104*1.74% -> 0
A105: TOTAL GASTOS BANCARIOS | D105: =SUM(D103:D104) -> 119739.39 | E105: =SUM(E103:E104) -> 111597.11 | F105: =SUM(F103:F104) -> 1293.1854 | G105: =SUM(G103:G104) -> 1532.6642 | H105: =SUM(H103:H104) -> 1448.8466 | I105: =SUM(I103:I104) -> 1784.1169 | J105: =SUM(J103:J104) -> 2083.4654 | K105: =E105+J105+F105+G105+H105+I105 -> 119739.39 | L105: =IF(D105=K105, "", "Error")
A107: FONDO DE GASTOS ORDINARIOS - PARA EDESUR | D107: =12500000-10547732.29-60000*2+2000000 -> 3832267.7 | E107: =D107*93.2% -> 3571673.5 | F107: =$D107*1.08% -> 41388.491 | G107: =$D107*1.28% -> 49053.027 | H107: =$D107*1.21% -> 46370.439 | I107: =$D107*1.49% -> 57100.789 | J107: =D107*1.74% -> 66681.458 | K107: =E107+J107+F107+G107+H107+I107 -> 3832267.7 | L107: =IF(D107=K107, "", "Error")
A109: TOTAL ORDINARIOS | D109: =SUM(D107+D58+D52+D105+D102+D95+D83+D67+D47+D42+D62) -> 16776464 | E109: =SUM(E107+E58+E52+E105+E102+E95+E83+E67+E47+E42+E62) -> 15065344 | F109: =SUM(F107+F58+F52+F105+F102+F95+F83+F67+F47+F42+F62) -> 149485.13 | G109: =SUM(G107+G58+G52+G105+G102+G95+G83+G67+G47+G42+G62) -> 177167.57 | H109: =SUM(H107+H58+H52+H105+H102+H95+H83+H67+H47+H42+H62) -> 167478.72 | I109: =SUM(I107+I58+I52+I105+I102+I95+I83+I67+I47+I42+I62) -> 206234.12 | J109: =SUM(J107+J58+J52+J105+J102+J95+J83+J67+J47+J42+J62) -> 240837.16 | K109: =E109+J109+F109+G109+H109+I109 -> 16006546 | L109: =IF(D109=K109, "", "Error") -> Error | M109: =D109-K109 -> 769917.37
A111: Gastos particulares
A112: Copia de llaves | B112: 3B | C112: 24000
A113: Copia de llaves | B113: 13D | C113: 12000
A122: TOTAL | C122: =SUM(C112:C121) -> 36000
A125: GASTOS EXTRAORDINARIOS | E125: UF | F125: LOCAL 1 (1,08%) | G125: LOCAL 2 (1,28%) | H125: LOCAL 3 (1,21%) | I125: LOCAL 4 (1,49%) | J125: LOCAL 5 (1,74%)
E126: =D126 -> 0
A128: TOTAL | D128: =SUM(D126:D127) -> 0 | E128: =SUM(E126:E127) -> 0 | J128: =SUM(J126:J127) -> 0 | L128: =E128+J128 -> 0 | M128: =IF(D128=L128, "", "Error")
A131: GASTOS ORDINARIOS + PREVISION : | B131: =D109 -> 16776464
A132: GASTOS ORDINARIOS SIN PREVISION: | B132: =D109-D107 -> 12944196 | D132: Se recuerda a todos los propietarios que, en caso de producirse la venta o transferencia de una unidad funcional, es obligatorio informar a la Administración los datos de los nuevos titulares. Dicha notificación resulta indispensable para actualizar los registros del consorcio, emitir correctamente las expensas y garantizar que toda comunicación formal llegue a quienes correspondan. La información a presentar deberá incluir al menos: * Nombre y apellido de los nuevos propietarios. * Domicilio de contacto (en caso de ser distinto de la unidad funcional). * Correo electrónico y/o teléfono de contacto. * Copia de la escritura, acta notarial o documentación que acredite la transferencia. Hasta tanto no se reciba la notificación formal, toda comunicación y responsabilidad respecto de la unidad seguirá dirigida al propietario anterior.
A134: CAJA EFECTIVO $ (pesos)
A135: Saldo anterior | B135: -979600.31
A136: Ingresos | B136: =PRORRATEO!H133 -> 10274652
A137: Egresos Ordinarios | B137: =-B132 -> -12944196
A138: Egresos Extraordinarios | B138: =-D128 -> 0
A139: Dinero sin identificar | B139: =B148 -> 0
A140: Dinero ingreso SUM | B140: =-B153 -> 0
...

Sheet PRORRATEO
F1: Banco Santander Rio. | K1: SE GASTO: | L1: =RESUMEN!D109-RESUMEN!D107 -> 12944196
F2: CBU: 0720039720000002171436 | K2: SE PRORRATEA EN LAS UF: | M2: 14500000
A3: =RESUMEN!C5 -> PERÍODO: DICIEMBRE | F3: CTA CTE $ 0039 - 21714/3 FIDEICOMISO 25 DE MAYO 837 LAN 30716676737
C5: IMPORTANTE: Las personas marcadas en color naranja abonaron de forma incorrecta mediante Mercado Pago. A partir de ahora (incluso desde hace meses), ya se encuentra habilitada la cuenta bancaria correspondiente, por lo que todos los pagos deben realizarse exclusivamente a través de dicha cuenta. Los datos de la misma se encuentran justo arriba de este aviso. Quienes abonen por Mercado Pago corren el riesgo de que su pago no sea imputado correctamente.
P8: =L1-K133 -> -1368465.8
C9: IMPORTANTE: Quienes estan en violeta NO ha respetado los centavos al abonar. Para la proxima oportunidad, solicitamos que los respeten.
A11: Piso | B11: Dpto. | C11: UF | D11: Propietario | E11: Inquilinos | F11: (%) | G11: Saldo | H11: Ingreso | I11: SALDO | J11: Expensas extraor. | K11: Expensas ord | L11: SUM/ GASTOS PART | M11: TOTAL A ABONAR HASTA | N11: TOTAL A ABONAR 2DO VTO - DESDE EL
M13: =RESUMEN!A20 -> VTO 15/01 | N13: =RESUMEN!A20 -> VTO 15/01
A14: conf sup | C14: LOC 1 | D14: Fernandez, Cristian | E14: Gladys ojeda Britez - Exequiel alexis giuliani | F14: 0.0108 | G14: 124701 | H14: 124701 | I14: =G14-H14 -> 0 | J14: 0 | K14: 131452.15 | L14: 0 | M14: =K14+J14+I14+L14 -> 131452.15 | N14: =M14*6% + M14 -> 139339.28 | Q14: para copias y pegar las expensas ord del local
C15: LOC 2 | D15: Sr propietario | F15: 0.013 | G15: 147794 | H15: =G15+RESUMEN!D55 -> 161826.9 | I15: =G15-H15 -> -14032.9 | J15: 0 | K15: 155795.14 | L15: 0 | M15: =K15+J15+I15+L15 -> 141762.24 | N15: =M15*6% + M15 -> 150267.98
A16: conf sup | C16: LOC 3 | D16: Schiaffino, Edgardo Angel | F16: 0.0121 | G16: 139712 | H16: =G16 -> 139712 | I16: =G16-H16 -> 0 | J16: 0 | K16: 147275.1 | L16: 0 | M16: =K16+J16+I16+L16 -> 147275.1 | N16: =M16*6% + M16 -> 156111.6 | Q16: LOCAL 1 | R16: =RESUMEN!F109 -> 149485.13
A17: conf sup | C17: LOC 4 | D17: Cordero, Leandro Emanuel - Orona, Victoria | F17: 0.0149 | G17: 172042 | I17: =G17-H17 -> 172042 | J17: 0 | K17: 181355.28 | L17: 0 | M17: =K17+J17+I17+L17 -> 353397.28 | N17: =M17*6% + M17 -> 374601.12 | Q17: LOCAL 2 | R17: =RESUMEN!G109 -> 177167.57
A18: conf sup | C18: LOC 5 | D18: Orsi, Jose Luis - Fernandez, Cristian Gabriel | F18: 0.0174 | G18: 200908 | H18: =G18 -> 200908 | I18: =G18-H18 -> 0 | J18: 0 | K18: 211784.02 | L18: 0 | M18: =K18+J18+I18+L18 -> 211784.02 | N18: =M18*6% + M18 -> 224491.06 | Q18: LOCAL 3 | R18: =RESUMEN!H109 -> 167478.72
A19: 3 amb | C19: 2ºA | D19: Franco, Lucas Fabián | F19: 0.0188 | G19: 225600.01 | H19: =G19 -> 225600.01 | I19: =G19-H19 -> 0 | J19: =M$8*F19 -> 0 | K19: =M$2*F19 -> 272600 | L19: 0 | M19: =ROUND((K19+J19+I19+L19),0) + O19 -> 272600.01 | N19: =ROUND((M19*6% + M19 ),0) + O19 -> 288956.01 | O19: 0.01 | Q19: LOCAL 4 | R19: =RESUMEN!I109 -> 206234.12
A20: 1 amb | C20: 2ºB | D20: Martinez, Diego | F20: 0.0084 | G20: 100800.02 | H20: =G20 -> 100800.02 | I20: =G20-H20 -> 0 | J20: =M$8*F20 -> 0 | K20: =M$2*F20 -> 121800 | L20: 0 | M20: =ROUND((K20+J20+I20+L20),0) + O20 -> 121800.02 | N20: =ROUND((M20*6% + M20 ),0) + O20 -> 129108.02 | O20: =O19+0.01 -> 0.02 | Q20: LOCAL 5 | R20: =RESUMEN!J109 -> 240837.16
A21: 3 amb | C21: 2ºC | D21: Rodriguez, Carlos Alberto Miguel | F21: 0.0201 | G21: 227101.03 | H21: =G21 -> 227101.03 | I21: =G21-H21 -> 0 | J21: =M$8*F21 -> 0 | K21: =M$2*F21 -> 291450 | L21: 0 | M21: =ROUND((K21+J21+I21+L21),0) + O21 -> 291450.03 | N21: =ROUND((M21*6% + M21 ),0) + O21 -> 308937.03 | O21: =O20+0.01 -> 0.03
A22: 2 amb | C22: 2ºD | D22: Ferraro, José | E22: Matias Cuevas | F22: 0.0094 | G22: 277972.04 | H22: 112800 | I22: =G22-H22 -> 165172.04 | J22: =M$8*F22 -> 0 | K22: =M$2*F22 -> 136300 | L22: 0 | M22: =ROUND((K22+J22+I22+L22),0) + O22 -> 301472.04 | N22: =ROUND((M22*6% + M22 ),0) + O22 -> 319560.04 | O22: =O21+0.01 -> 0.04 | P22: Matias alejandro ezequiel
A23: 2 amb | C23: 2ºE | D23: Dieci, Matias Orlando | E23: Julieta Damiano/Damiani | F23: 0.0087 | G23: 191400.05 | H23: =104400.05 -> 104400.05 | I23: =G23-H23 -> 87000 | J23: =M$8*F23 -> 0 | K23: =M$2*F23 -> 126150 | L23: 0 | M23: =ROUND((K23+J23+I23+L23),0) + O23 -> 213150.05 | N23: =ROUND((M23*6% + M23 ),0) + O23 -> 225939.05 | O23: =O22+0.01 -> 0.05
A24: 2 amb | C24: 2ºF | D24: Ferraro, Jose | E24: Carolina Massa | F24: 0.0095 | G24: 114000.06 | H24: =G24 -> 114000.06 | I24: =G24-H24 -> 0 | J24: =M$8*F24 -> 0 | K24: =M$2*F24 -> 137750 | L24: 0 | M24: =ROUND((K24+J24+I24+L24),0) + O24 -> 137750.06 | N24: =ROUND((M24*6% + M24 ),0) + O24 -> 146015.06 | O24: =O23+0.01 -> 0.06
A25: 3 amb | C25: 3ºA | D25: Ferraro, Jose | E25: Walter Gabriel Ledesma | F25: 0.0165 | G25: 325977.07 | H25: 198000 | I25: =G25-H25 -> 127977.07 | J25: =M$8*F25 -> 0 | K25: =M$2*F25 -> 239250 | L25: 0 | M25: =ROUND((K25+J25+I25+L25),0) + O25 -> 367227.07 | N25: =ROUND((M25*6% + M25 ),0) + O25 -> 389261.07 | O25: =O24+0.01 -> 0.07
A26: 1 amb | C26: 3ºB | D26: Balduzzi, Stella Maris | F26: 0.0073 | G26: 87600.08 | H26: =G26 -> 87600.08 | I26: =G26-H26 -> 0 | J26: =M$8*F26 -> 0 | K26: =M$2*F26 -> 105850 | L26: =24000+20000 -> 44000 | M26: =ROUND((K26+J26+I26+L26),0) + O26 -> 149850.08 | N26: =ROUND((M26*6% + M26 ),0) + O26 -> 158841.08 | O26: =O25+0.01 -> 0.08
A27: 3 amb | C27: 3ºC | D27: Ferraro, Jose | F27: 0.0178 | G27: 728372.09 | I27: =G27-H27 -> 728372.09 | J27: =M$8*F27 -> 0 | K27: =M$2*F27 -> 258100 | L27: 0 | M27: =ROUND((K27+J27+I27+L27),0) + O27 -> 986472.09 | N27: =ROUND((M27*6% + M27 ),0) + O27 -> 1045660.1 | O27: =O26+0.01 -> 0.09
A28: 2 amb | C28: 3ºD | D28: Heredia, Christian | F28: 0.0094 | G28: 112800.1 | I28: =G28-H28 -> 112800.1 | J28: =M$8*F28 -> 0 | K28: =M$2*F28 -> 136300 | L28: 0 | M28: =ROUND((K28+J28+I28+L28),0) + O28 -> 249100.1 | N28: =ROUND((M28*6% + M28 ),0) + O28 -> 264046.1 | O28: =O27+0.01 -> 0.1
A29: 2 amb | C29: 3ºE | D29: Dallorso, Maria Ines - Dallorso, Ana Paula | F29: 0.0087 | G29: 99744.11 | H29: =G29 -> 99744.11 | I29: =G29-H29 -> 0 | J29: =M$8*F29 -> 0 | K29: =M$2*F29 -> 126150 | L29: 0 | M29: =ROUND((K29+J29+I29+L29),0) + O29 -> 126150.11 | N29: =ROUND((M29*6% + M29 ),0) + O29 -> 133719.11 | O29: =O28+0.01 -> 0.11
A30: 2 amb | C30: 3ºF | D30: Ayala, Roberto Adrian | F30: 0.0095 | G30: 380000.12 | I30: =G30-H30 -> 380000.12 | J30: =M$8*F30 -> 0 | K30: =M$2*F30 -> 137750 | L30: 0 | M30: =ROUND((K30+J30+I30+L30),0) + O30 -> 517750.12 | N30: =ROUND((M30*6% + M30 ),0) + O30 -> 548815.12 | O30: =O29+0.01 -> 0.12
A31: 3 amb | C31: 4ºA | D31: Barral, Carlos Daniel | F31: 0.0164 | G31: 196800.13 | H31: =G31 -> 196800.13 | I31: =G31-H31 -> 0 | J31: =M$8*F31 -> 0 | K31: =M$2*F31 -> 237800 | L31: 0 | M31: =ROUND((K31+J31+I31+L31),0) + O31 -> 237800.13 | N31: =ROUND((M31*6% + M31 ),0) + O31 -> 252068.13 | O31: =O30+0.01 -> 0.13
A32: 1 amb | C32: 4ºB | D32: Sr. Propietario | E32: Liria | F32: 0.0072 | G32: 86400.14 | H32: =G32 -> 86400.14 | I32: =G32-H32 -> 0 | J32: =M$8*F32 -> 0 | K32: =M$2*F32 -> 104400 | L32: 0 | M32: =ROUND((K32+J32+I32+L32),0) + O32 -> 104400.14 | N32: =ROUND((M32*6% + M32 ),0) + O32 -> 110664.14 | O32: =O31+0.01 -> 0.14
A33: 3 amb | C33: 4ºC | D33: Osipowicz, Ariel Marcelo | F33: 0.0173 | G33: 207600.15 | H33: =G33 -> 207600.15 | I33: =G33-H33 -> 0 | J33: =M$8*F33 -> 0 | K33: =M$2*F33 -> 250850 | L33: 0 | M33: =ROUND((K33+J33+I33+L33),0) + O33 -> 250850.15 | N33: =ROUND((M33*6% + M33 ),0) + O33 -> 265901.15 | O33: =O32+0.01 -> 0.15
A34: 2 amb | C34: 4ºD | D34: Ruiz, Juana Del Valle | F34: 0.0094 | G34: 124800.16 | H34: 132288.16 | I34: =G34-H34 -> -7488 | J34: =M$8*F34 -> 0 | K34: =M$2*F34 -> 136300 | L34: 0 | M34: =ROUND((K34+J34+I34+L34),0) + O34 -> 128812.16 | N34: =ROUND((M34*6% + M34 ),0) + O34 -> 136541.16 | O34: =O33+0.01 -> 0.16
A35: 2 amb | C35: 4ºE | D35: Ayala, Roberto Adrian | E35: Iara | F35: 0.0087 | G35: 121800.17 | H35: 113100.17 | I35: =G35-H35 -> 8700 | J35: =M$8*F35 -> 0 | K35: =M$2*F35 -> 126150 | L35: 0 | M35: =ROUND((K35+J35+I35+L35),0) + O35 -> 134850.17 | N35: =ROUND((M35*6% + M35 ),0) + O35 -> 142941.17 | O35: =O34+0.01 -> 0.17
A36: 2 amb | C36: 4ºF | D36: Ayala, Roberto Adrian | F36: 0.0095 | G36: 209000.18 | I36: =G36-H36 -> 209000.18 | J36: =M$8*F36 -> 0 | K36: =M$2*F36 -> 137750 | L36: 0 | M36: =ROUND((K36+J36+I36+L36),0) + O36 -> 346750.18 | N36: =ROUND((M36*6% + M36 ),0) + O36 -> 367555.18 | O36: =O35+0.01 -> 0.18
A37: 3 amb | C37: 5ºA | D37: Chehab, Gabriel Adrian | E37: Santiago Rodriguez | F37: 0.0164 | G37: 233800.19 | H37: =G37 -> 233800.19 | I37: =G37-H37 -> 0 | J37: =M$8*F37 -> 0 | K37: =M$2*F37 -> 237800 | L37: 20000 | M37: =ROUND((K37+J37+I37+L37),0) + O37 -> 257800.19 | N37: =ROUND((M37*6% + M37 ),0) + O37 -> 273268.19 | O37: =O36+0.01 -> 0.19
A38: 1 amb | C38: 5ºB | D38: Mesa, Mariano | F38: 0.0072 | G38: 86400.2 | H38: =G38 -> 86400.2 | I38: =G38-H38 -> 0 | J38: =M$8*F38 -> 0 | K38: =M$2*F38 -> 104400 | L38: 0 | M38: =ROUND((K38+J38+I38+L38),0) + O38 -> 104400.2 | N38: =ROUND((M38*6% + M38 ),0) + O38 -> 110664.2 | O38: =O37+0.01 -> 0.2
A39: 3 amb | C39: 5ºC | D39: Di Mito, Vicente Argentino - Serantes, Mabel | F39: 0.0173 | G39: 207600.21 | H39: =G39 -> 207600.21 | I39: =G39-H39 -> 0 | J39: =M$8*F39 -> 0 | K39: =M$2*F39 -> 250850 | L39: 0 | M39: =ROUND((K39+J39+I39+L39),0) + O39 -> 250850.21 | N39: =ROUND((M39*6% + M39 ),0) + O39 -> 265901.21 | O39: =O38+0.01 -> 0.21
A40: 2 amb | C40: 5ºD | D40: Ayala, Agustin | F40: 0.0094 | G40: 206800.22 | I40: =G40-H40 -> 206800.22 | J40: =M$8*F40 -> 0 | K40: =M$2*F40 -> 136300 | L40: 0 | M40: =ROUND((K40+J40+I40+L40),0) + O40 -> 343100.22 | N40: =ROUND((M40*6% + M40 ),0) + O40 -> 363686.22 | O40: =O39+0.01 -> 0.22
A41: 2 amb | C41: 5ºE | D41: Ayala, Roberto Adrian | F41: 0.0087 | G41: 104400.23 | H41: =G41 -> 104400.23 | I41: =G41-H41 -> 0 | J41: =M$8*F41 -> 0 | K41: =M$2*F41 -> 126150 | L41: 0 | M41: =ROUND((K41+J41+I41+L41),0) + O41 -> 126150.23 | N41: =ROUND((M41*6% + M41 ),0) + O41 -> 133719.23 | O41: =O40+0.01 -> 0.23 | P41: COCHERA 31
A42: 2 amb | C42: 5ºF | D42: Ayala, Agustin | F42: 0.0095 | G42: 209000.24 | I42: =G42-H42 -> 209000.24 | J42: =M$8*F42 -> 0 | K42: =M$2*F42 -> 137750 | L42: 0 | M42: =ROUND((K42+J42+I42+L42),0) + O42 -> 346750.24 | N42: =ROUND((M42*6% + M42 ),0) + O42 -> 367555.24 | O42: =O41+0.01 -> 0.24
A43: 3 amb | C43: 6ºA | D43: Morandi, Victoria Ayelen | Calvo, Luciano Ezequiel | F43: 0.0164 | G43: 196800.25 | H43: =G43 -> 196800.25 | I43: =G43-H43 -> 0 | J43: =M$8*F43 -> 0 | K43: =M$2*F43 -> 237800 | L43: 0 | M43: =ROUND((K43+J43+I43+L43),0) + O43 -> 237800.25 | N43: =ROUND((M43*6% + M43 ),0) + O43 -> 252068.25 | O43: =O42+0.01 -> 0.25
A44: 1 amb | C44: 6ºB | D44: Grizak Ruben | E44: Christian | F44: 0.0072 | G44: 86400.26 | H44: =G44 -> 86400.26 | I44: =G44-H44 -> 0 | J44: =M$8*F44 -> 0 | K44: =M$2*F44 -> 104400 | L44: 0 | M44: =ROUND((K44+J44+I44+L44),0) + O44 -> 104400.26 | N44: =ROUND((M44*6% + M44 ),0) + O44 -> 110664.26 | O44: =O43+0.01 -> 0.26
A45: 3 amb | C45: 6ºC | D45: Nuñez Leonel - Corrieri Giuliana | F45: 0.0173 | G45: 207600.27 | H45: =G45 -> 207600.27 | I45: =G45-H45 -> 0 | J45: =M$8*F45 -> 0 | K45: =M$2*F45 -> 250850 | L45: 0 | M45: =ROUND((K45+J45+I45+L45),0) + O45 -> 250850.27 | N45: =ROUND((M45*6% + M45 ),0) + O45 -> 265901.27 | O45: =O44+0.01 -> 0.27 | P45: COCHERA 33 | Q45: COCHERA 33
A46: 2 amb | C46: 6ºD | D46: Sr propietario | F46: 0.0094 | G46: 112800.28 | H46: =G46 -> 112800.28 | I46: =G46-H46 -> 0 | J46: =M$8*F46 -> 0 | K46: =M$2*F46 -> 136300 | L46: 0 | M46: =ROUND((K46+J46+I46+L46),0) + O46 -> 136300.28 | N46: =ROUND((M46*6% + M46 ),0) + O46 -> 144478.28 | O46: =O45+0.01 -> 0.28 | Q46: mariano hecimovic
A47: 2 amb | C47: 6ºE | D47: Dieci, Matias Orlando | E47: Gaston Smith | F47: 0.0087 | G47: 104400.29 | I47: =G47-H47 -> 104400.29 | J47: =M$8*F47 -> 0 | K47: =M$2*F47 -> 126150 | L47: 0 | M47: =ROUND((K47+J47+I47+L47),0) + O47 -> 230550.29 | N47: =ROUND((M47*6% + M47 ),0) + O47 -> 244383.29 | O47: =O46+0.01 -> 0.29
A48: 2 amb | C48: 6ºF | D48: Mazzia Alexia | F48: 0.0095 | G48: 114000.3 | H48: =G48 -> 114000.3 | I48: =G48-H48 -> 0 | J48: =M$8*F48 -> 0 | K48: =M$2*F48 -> 137750 | L48: 0 | M48: =ROUND((K48+J48+I48+L48),0) + O48 -> 137750.3 | N48: =ROUND((M48*6% + M48 ),0) + O48 -> 146015.3 | O48: =O47+0.01 -> 0.3
A49: 3 amb | C49: 7ºA | D49: Campelo, Mariano | F49: 0.0164 | G49: 196800.31 | H49: =G49 -> 196800.31 | I49: =G49-H49 -> 0 | J49: =M$8*F49 -> 0 | K49: =M$2*F49 -> 237800 | L49: 0 | M49: =ROUND((K49+J49+I49+L49),0) + O49 -> 237800.31 | N49: =ROUND((M49*6% + M49 ),0) + O49 -> 252068.31 | O49: =O48+0.01 -> 0.31
A50: 1 amb | C50: 7ºB | D50: Paes, Yazmin Luciana | F50: 0.0072 | G50: 86400.32 | I50: =G50-H50 -> 86400.32 | J50: =M$8*F50 -> 0 | K50: =M$2*F50 -> 104400 | L50: 20000 | M50: =ROUND((K50+J50+I50+L50),0) + O50 -> 210800.32 | N50: =ROUND((M50*6% + M50 ),0) + O50 -> 223448.32 | O50: =O49+0.01 -> 0.32
A51: 3 amb | C51: 7ºC | D51: Gonzalez Fedullo, Roxana y Valeria | F51: 0.0173 | G51: 207600.33 | H51: =G51 -> 207600.33 | I51: =G51-H51 -> 0 | J51: =M$8*F51 -> 0 | K51: =M$2*F51 -> 250850 | L51: 0 | M51: =ROUND((K51+J51+I51+L51),0) + O51 -> 250850.33 | N51: =ROUND((M51*6% + M51 ),0) + O51 -> 265901.33 | O51: =O50+0.01 -> 0.33
A52: 2 amb | C52: 7ºD | D52: Solleiro, Carolina Mabel | F52: 0.0094 | G52: 124800.34 | H52: =G52 -> 124800.34 | I52: =G52-H52 -> 0 | J52: =M$8*F52 -> 0 | K52: =M$2*F52 -> 136300 | L52: 20000 | M52: =ROUND((K52+J52+I52+L52),0) + O52 -> 156300.34 | N52: =ROUND((M52*6% + M52 ),0) + O52 -> 165678.34 | O52: =O51+0.01 -> 0.34 | P52: Walter Javier Dimiziunas
A53: 2 amb | C53: 7ºE | D53: Leyes, Javier | F53: 0.0087 | G53: 113100.35 | H53: =G53 -> 113100.35 | I53: =G53-H53 -> 0 | J53: =M$8*F53 -> 0 | K53: =M$2*F53 -> 126150 | L53: 0 | M53: =ROUND((K53+J53+I53+L53),0) + O53 -> 126150.35 | N53: =ROUND((M53*6% + M53 ),0) + O53 -> 133719.35 | O53: =O52+0.01 -> 0.35
A54: 2 amb | C54: 7ºF | D54: Puente, Matias | F54: 0.0095 | G54: 150000.36 | I54: =G54-H54 -> 150000.36 | J54: =M$8*F54 -> 0 | K54: =M$2*F54 -> 137750 | L54: 0 | M54: =ROUND((K54+J54+I54+L54),0) + O54 -> 287750.36 | N54: =ROUND((M54*6% + M54 ),0) + O54 -> 305015.36 | O54: =O53+0.01 -> 0.36
A55: 3 amb | C55: 8ºA | D55: Campelo, Mariano | F55: 0.0164 | G55: 196800.37 | H55: =G55 -> 196800.37 | I55: =G55-H55 -> 0 | J55: =M$8*F55 -> 0 | K55: =M$2*F55 -> 237800 | L55: 0 | M55: =ROUND((K55+J55+I55+L55),0) + O55 -> 237800.37 | N55: =ROUND((M55*6% + M55 ),0) + O55 -> 252068.37 | O55: =O54+0.01 -> 0.37
A56: 1 amb | C56: 8ºB | D56: Morvillo, Mariana Yanil | E56: Aylen | F56: 0.0072 | G56: 86400.38 | H56: =G56 -> 86400.38 | I56: =G56-H56 -> 0 | J56: =M$8*F56 -> 0 | K56: =M$2*F56 -> 104400 | L56: 0 | M56: =ROUND((K56+J56+I56+L56),0) + O56 -> 104400.38 | N56: =ROUND((M56*6% + M56 ),0) + O56 -> 110664.38 | O56: =O55+0.01 -> 0.38
A57: 3 amb | C57: 8ºC | D57: Frontale, Federico Carlos | Celentano, Alejandra Verónica | F57: 0.0173 | G57: 207600.39 | H57: =G57 -> 207600.39 | I57: =G57-H57 -> 0 | J57: =M$8*F57 -> 0 | K57: =M$2*F57 -> 250850 | L57: 0 | M57: =ROUND((K57+J57+I57+L57),0) + O57 -> 250850.39 | N57: =ROUND((M57*6% + M57 ),0) + O57 -> 265901.39 | O57: =O56+0.01 -> 0.39
A58: 2 amb | C58: 8ºD | D58: Argul, Sergio Walter - Taboada, María Paz | F58: 0.0094 | G58: 112800.4 | H58: =G58 -> 112800.4 | I58: =G58-H58 -> 0 | J58: =M$8*F58 -> 0 | K58: =M$2*F58 -> 136300 | L58: 0 | M58: =ROUND((K58+J58+I58+L58),0) + O58 -> 136300.4 | N58: =ROUND((M58*6% + M58 ),0) + O58 -> 144478.4 | O58: =O57+0.01 -> 0.4
A59: 2 amb | C59: 8ºE | D59: Sr propietario | F59: 0.0087 | G59: 104400.41 | H59: =G59 -> 104400.41 | I59: =G59-H59 -> 0 | J59: =M$8*F59 -> 0 | K59: =M$2*F59 -> 126150 | L59: 0 | M59: =ROUND((K59+J59+I59+L59),0) + O59 -> 126150.41 | N59: =ROUND((M59*6% + M59 ),0) + O59 -> 133719.41 | O59: =O58+0.01 -> 0.41 | Q59: el de sergio
A60: 2 amb | C60: 8ºF | D60: Arias, Mariana Laura | F60: 0.0095 | G60: 114000.42 | H60: =G60 -> 114000.42 | I60: =G60-H60 -> 0 | J60: =M$8*F60 -> 0 | K60: =M$2*F60 -> 137750 | L60: 20000 | M60: =ROUND((K60+J60+I60+L60),0) + O60 -> 157750.42 | N60: =ROUND((M60*6% + M60 ),0) + O60 -> 167215.42 | O60: =O59+0.01 -> 0.42 | P60: alonso sabrina eugenia
A61: 3 amb | C61: 9ºA | D61: Fanjul, Alejandro Rubén Marcelo | F61: 0.0164 | G61: 196800.43 | H61: =G61 -> 196800.43 | I61: =G61-H61 -> 0 | J61: =M$8*F61 -> 0 | K61: =M$2*F61 -> 237800 | L61: 0 | M61: =ROUND((K61+J61+I61+L61),0) + O61 -> 237800.43 | N61: =ROUND((M61*6% + M61 ),0) + O61 -> 252068.43 | O61: =O60+0.01 -> 0.43
A62: 1 amb | C62: 9ºB | D62: Fanjul, Alejandro Rubén Marcelo | F62: 0.0072 | G62: 86400.44 | H62: =G62 -> 86400.44 | I62: =G62-H62 -> 0 | J62: =M$8*F62 -> 0 | K62: =M$2*F62 -> 104400 | L62: 0 | M62: =ROUND((K62+J62+I62+L62),0) + O62 -> 104400.44 | N62: =ROUND((M62*6% + M62 ),0) + O62 -> 110664.44 | O62: =O61+0.01 -> 0.44
A63: 3 amb | C63: 9ºC | D63: Franchino, Mauro | F63: 0.0173 | G63: 243600.45 | H63: =G63 -> 243600.45 | I63: =G63-H63 -> 0 | J63: =M$8*F63 -> 0 | K63: =M$2*F63 -> 250850 | L63: 0 | M63: =ROUND((K63+J63+I63+L63),0) + O63 -> 250850.45 | N63: =ROUND((M63*6% + M63 ),0) + O63 -> 265901.45 | O63: =O62+0.01 -> 0.45
A64: 2 amb | C64: 9ºD | D64: Cerra, Antonio Osvaldo | E64: Adrian | F64: 0.0094 | G64: 112800.46 | H64: =G64 -> 112800.46 | I64: =G64-H64 -> 0 | J64: =M$8*F64 -> 0 | K64: =M$2*F64 -> 136300 | L64: 0 | M64: =ROUND((K64+J64+I64+L64),0) + O64 -> 136300.46 | N64: =ROUND((M64*6% + M64 ),0) + O64 -> 144478.46 | O64: =O63+0.01 -> 0.46
A65: 2 amb | C65: 9ºE | D65: Dieci, Matias Orlando | F65: 0.0087 | G65: 22200.47 | H65: =G65 -> 22200.47 | I65: =G65-H65 -> 0 | J65: =M$8*F65 -> 0 | K65: =M$2*F65 -> 126150 | L65: 0 | M65: =ROUND((K65+J65+I65+L65),0) + O65 -> 126150.47 | N65: =ROUND((M65*6% + M65 ),0) + O65 -> 133719.47 | O65: =O64+0.01 -> 0.47
A66: 2 amb | C66: 9ºF | D66: Rosales, Rubén Darío | F66: 0.0095 | G66: 114000.48 | H66: =95000.48 -> 95000.48 | I66: =G66-H66 -> 19000 | J66: =M$8*F66 -> 0 | K66: =M$2*F66 -> 137750 | L66: 0 | M66: =ROUND((K66+J66+I66+L66),0) + O66 -> 156750.48 | N66: =ROUND((M66*6% + M66 ),0) + O66 -> 166156.48 | O66: =O65+0.01 -> 0.48
A67: 3 amb | C67: 10ºA | D67: Puisys Guillermo Antonio | F67: 0.0164 | G67: 196800.49 | H67: =G67 -> 196800.49 | I67: =G67-H67 -> 0 | J67: =M$8*F67 -> 0 | K67: =M$2*F67 -> 237800 | L67: 0 | M67: =ROUND((K67+J67+I67+L67),0) + O67 -> 237800.49 | N67: =ROUND((M67*6% + M67 ),0) + O67 -> 252069.49 | O67: =O66+0.01 -> 0.49
A68: 1 amb | C68: 10ºB | D68: Lange, Gustavo Daniel | F68: 0.0072 | G68: 339431.5 | I68: =G68-H68 -> 339431.5 | J68: =M$8*F68 -> 0 | K68: =M$2*F68 -> 104400 | L68: 0 | M68: =ROUND((K68+J68+I68+L68),0) + O68 -> 443832.5 | N68: =ROUND((M68*6% + M68 ),0) + O68 -> 470462.5 | O68: =O67+0.01 -> 0.5
A69: 3 amb | C69: 10ºC | D69: Espósito, Franco Ezequiel | F69: 0.0173 | G69: 207600.51 | I69: =G69-H69 -> 207600.51 | J69: =M$8*F69 -> 0 | K69: =M$2*F69 -> 250850 | L69: 0 | M69: =ROUND((K69+J69+I69+L69),0) + O69 -> 458451.51 | N69: =ROUND((M69*6% + M69 ),0) + O69 -> 485959.51 | O69: =O68+0.01 -> 0.51
A70: 2 amb | C70: 10ºD | D70: Lobato, Lorena - Vega, Maximiliano | F70: 0.0094 | G70: 112046.52 | I70: =G70-H70 -> 112046.52 | J70: =M$8*F70 -> 0 | K70: =M$2*F70 -> 136300 | L70: 0 | M70: =ROUND((K70+J70+I70+L70),0) + O70 -> 248347.52 | N70: =ROUND((M70*6% + M70 ),0) + O70 -> 263248.52 | O70: =O69+0.01 -> 0.52
A71: 2 amb | C71: 10ºE | D71: Sr propietario | F71: 0.0087 | G71: 104400.53 | H71: =G71 -> 104400.53 | I71: =G71-H71 -> 0 | J71: =M$8*F71 -> 0 | K71: =M$2*F71 -> 126150 | L71: 0 | M71: =ROUND((K71+J71+I71+L71),0) + O71 -> 126150.53 | N71: =ROUND((M71*6% + M71 ),0) + O71 -> 133720.53 | O71: =O70+0.01 -> 0.53 | Q71: mariano hecimovic
A72: 2 amb | C72: 10ºF | D72: Ramos, Sergio Eugenio | F72: 0.0095 | G72: 120841.54 | H72: =G72 -> 120841.54 | I72: =G72-H72 -> 0 | J72: =M$8*F72 -> 0 | K72: =M$2*F72 -> 137750 | L72: 0 | M72: =ROUND((K72+J72+I72+L72),0) + O72 -> 137750.54 | N72: =ROUND((M72*6% + M72 ),0) + O72 -> 146016.54 | O72: =O71+0.01 -> 0.54
A73: 4 amb | C73: 11ºA/B | D73: Mosquera, Julio Rodolfo | Cuzzolino, Daniela Carol | F73: 0.0235 | G73: 517001.55 | H73: =258500.55+235000.55+23500 -> 517001.1 | I73: =G73-H73 -> 0.45 | J73: =M$8*F73 -> 0 | K73: =M$2*F73 -> 340750 | L73: 0 | M73: =ROUND((K73+J73+I73+L73),0) + O73 -> 340750.55 | N73: =ROUND((M73*6% + M73 ),0) + O73 -> 361196.55 | O73: =O72+0.01 -> 0.55 | P73: LEER LA ANOTACIOn
A74: 3 amb | C74: 11ºC | D74: Silvestre Villarruel Eduardo | F74: 0.0173 | G74: 207600.56 | H74: =G74 -> 207600.56 | I74: =G74-H74 -> 0 | J74: =M$8*F74 -> 0 | K74: =M$2*F74 -> 250850 | L74: 0 | M74: =ROUND((K74+J74+I74+L74),0) + O74 -> 250850.56 | N74: =ROUND((M74*6% + M74 ),0) + O74 -> 265902.56 | O74: =O73+0.01 -> 0.56
A75: 2 amb | C75: 11ºD | D75: Sr. Propietario | F75: 0.0094 | G75: 112800.57 | H75: =G75 -> 112800.57 | I75: =G75-H75 -> 0 | J75: =M$8*F75 -> 0 | K75: =M$2*F75 -> 136300 | L75: 0 | M75: =ROUND((K75+J75+I75+L75),0) + O75 -> 136300.57 | N75: =ROUND((M75*6% + M75 ),0) + O75 -> 144479.57 | O75: =O74+0.01 -> 0.57
A76: 2 amb | C76: 11ºE | D76: Argúl, Adrián Norberto | E76: Lara | F76: 0.0087 | G76: 116400.58 | I76: =G76-H76 -> 116400.58 | J76: =M$8*F76 -> 0 | K76: =M$2*F76 -> 126150 | L76: 0 | M76: =ROUND((K76+J76+I76+L76),0) + O76 -> 242551.58 | N76: =ROUND((M76*6% + M76 ),0) + O76 -> 257105.58 | O76: =O75+0.01 -> 0.58
A77: 2 amb | C77: 11ºF | D77: Lobato, Lorena - Vega, Maximiliano | F77: 0.0095 | G77: 115124.59 | H77: =G77 -> 115124.59 | I77: =G77-H77 -> 0 | J77: =M$8*F77 -> 0 | K77: =M$2*F77 -> 137750 | L77: 0 | M77: =ROUND((K77+J77+I77+L77),0) + O77 -> 137750.59 | N77: =ROUND((M77*6% + M77 ),0) + O77 -> 146016.59 | O77: =O76+0.01 -> 0.59
A78: 4 amb | C78: 12ºA/B | D78: Luciano, Carmen Veronica - Rey, Javier Pablo | F78: 0.0235 | G78: 276480.6 | H78: =G78 -> 276480.6 | I78: =G78-H78 -> 0 | J78: =M$8*F78 -> 0 | K78: =M$2*F78 -> 340750 | L78: 0 | M78: =ROUND((K78+J78+I78+L78),0) + O78 -> 340750.6 | N78: =ROUND((M78*6% + M78 ),0) + O78 -> 361196.6 | O78: =O77+0.01 -> 0.6
A79: 3 amb | C79: 12ºC | D79: Hernandez, Marisa Beatriz - Hernandez, Adrian Jose | F79: 0.0173 | G79: 207600.61 | H79: =G79 -> 207600.61 | I79: =G79-H79 -> 0 | J79: =M$8*F79 -> 0 | K79: =M$2*F79 -> 250850 | L79: 0 | M79: =ROUND((K79+J79+I79+L79),0) + O79 -> 250850.61 | N79: =ROUND((M79*6% + M79 ),0) + O79 -> 265902.61 | O79: =O78+0.01 -> 0.61
A80: 2 amb | C80: 12ºD | D80: Morini, Micaela | F80: 0.0094 | G80: 247001.62 | H80: 122201.62 | I80: =G80-H80 -> 124800 | J80: =M$8*F80 -> 0 | K80: =M$2*F80 -> 136300 | L80: 0 | M80: =ROUND((K80+J80+I80+L80),0) + O80 -> 261100.62 | N80: =ROUND((M80*6% + M80 ),0) + O80 -> 276767.62 | O80: =O79+0.01 -> 0.62
A81: 2 amb | C81: 12ºE | D81: Armerding, Jorge | E81: Agustina | F81: 0.0087 | G81: 104400.63 | H81: =G81 -> 104400.63 | I81: =G81-H81 -> 0 | J81: =M$8*F81 -> 0 | K81: =M$2*F81 -> 126150 | L81: 0 | M81: =ROUND((K81+J81+I81+L81),0) + O81 -> 126150.63 | N81: =ROUND((M81*6% + M81 ),0) + O81 -> 133720.63 | O81: =O80+0.01 -> 0.63
A82: 2 amb | C82: 12ºF | D82: Bilyj, Josefa Catalina | F82: 0.0095 | G82: 114000.64 | H82: =G82 -> 114000.64 | I82: =G82-H82 -> 0 | J82: =M$8*F82 -> 0 | K82: =M$2*F82 -> 137750 | L82: 0 | M82: =ROUND((K82+J82+I82+L82),0) + O82 -> 137750.64 | N82: =ROUND((M82*6% + M82 ),0) + O82 -> 146016.64 | O82: =O81+0.01 -> 0.64 | P82: Laura Quintas Perez
A83: 4 amb | C83: 13ºA/B | D83: Gazzaneo, Francisco | F83: 0.0235 | G83: 282000.65 | H83: =G83 -> 282000.65 | I83: =G83-H83 -> 0 | J83: =M$8*F83 -> 0 | K83: =M$2*F83 -> 340750 | L83: 0 | M83: =ROUND((K83+J83+I83+L83),0) + O83 -> 340750.65 | N83: =ROUND((M83*6% + M83 ),0) + O83 -> 361196.65 | O83: =O82+0.01 -> 0.65
A84: 3 amb | C84: 13ºC | D84: Argentino, Javier Leonardo | F84: 0.0173 | G84: 207600.66 | H84: =G84 -> 207600.66 | I84: =G84-H84 -> 0 | J84: =M$8*F84 -> 0 | K84: =M$2*F84 -> 250850 | L84: 0 | M84: =ROUND((K84+J84+I84+L84),0) + O84 -> 250850.66 | N84: =ROUND((M84*6% + M84 ),0) + O84 -> 265902.66 | O84: =O83+0.01 -> 0.66
A85: 2 amb | C85: 13ºD | D85: Scardigno, Gabriela Susana - Ripoll, Luis Alberto | F85: 0.0094 | G85: 112800.67 | H85: =G85 -> 112800.67 | I85: =G85-H85 -> 0 | J85: =M$8*F85 -> 0 | K85: =M$2*F85 -> 136300 | L85: 12000 | M85: =ROUND((K85+J85+I85+L85),0) + O85 -> 148300.67 | N85: =ROUND((M85*6% + M85 ),0) + O85 -> 157199.67 | O85: =O84+0.01 -> 0.67
A86: 2 amb | C86: 13ºE | D86: Quiñones, Carlos Eduardo | F86: 0.0087 | G86: 104400.68 | H86: =G86 -> 104400.68 | I86: =G86-H86 -> 0 | J86: =M$8*F86 -> 0 | K86: =M$2*F86 -> 126150 | L86: 0 | M86: =ROUND((K86+J86+I86+L86),0) + O86 -> 126150.68 | N86: =ROUND((M86*6% + M86 ),0) + O86 -> 133720.68 | O86: =O85+0.01 -> 0.68
A87: 2 amb | C87: 13ºF | D87: Mosquera, José Elias | F87: 0.0095 | G87: 114000.69 | H87: =G87 -> 114000.69 | I87: =G87-H87 -> 0 | J87: =M$8*F87 -> 0 | K87: =M$2*F87 -> 137750 | L87: 0 | M87: =ROUND((K87+J87+I87+L87),0) + O87 -> 137750.69 | N87: =ROUND((M87*6% + M87 ),0) + O87 -> 146016.69 | O87: =O86+0.01 -> 0.69
C88: COCH 1 | D88: Osipowicz, Ariel Marcelo | F88: 0.0023 | G88: 27600.7 | H88: =G88 -> 27600.7 | I88: =G88-H88 -> 0 | J88: =M$8*F88 -> 0 | K88: =M$2*F88 -> 33350 | L88: 0 | M88: =ROUND((K88+J88+I88+L88),0) + O88 -> 33350.7 | N88: =ROUND((M88*6% + M88 ),0) + O88 -> 35352.7 | O88: =O87+0.01 -> 0.7
C89: COCH 2 | D89: Sr propietario | F89: 0.0023 | G89: 27600.71 | H89: =G89 -> 27600.71 | I89: =G89-H89 -> 0 | J89: =M$8*F89 -> 0 | K89: =M$2*F89 -> 33350 | L89: 0 | M89: =ROUND((K89+J89+I89+L89),0) + O89 -> 33350.71 | N89: =ROUND((M89*6% + M89 ),0) + O89 -> 35352.71 | O89: =O88+0.01 -> 0.71
C90: COCH 3 | D90: Paes, Yazmin Luciana | F90: 0.0023 | G90: 27600.72 | H90: =G90 -> 27600.72 | I90: =G90-H90 -> 0 | J90: =M$8*F90 -> 0 | K90: =M$2*F90 -> 33350 | L90: 0 | M90: =ROUND((K90+J90+I90+L90),0) + O90 -> 33350.72 | N90: =ROUND((M90*6% + M90 ),0) + O90 -> 35352.72 | O90: =O89+0.01 -> 0.72
C91: COCH 4 | D91: Puisys Guillermo Antonio | F91: 0.0023 | G91: 27600.73 | H91: =G91 -> 27600.73 | I91: =G91-H91 -> 0 | J91: =M$8*F91 -> 0 | K91: =M$2*F91 -> 33350 | L91: 0 | M91: =ROUND((K91+J91+I91+L91),0) + O91 -> 33350.73 | N91: =ROUND((M91*6% + M91 ),0) + O91 -> 35352.73 | O91: =O90+0.01 -> 0.73
C92: COCH 5 | D92: Arias, Mariana Laura | F92: 0.0023 | G92: 27600.74 | H92: =G92 -> 27600.74 | I92: =G92-H92 -> 0 | J92: =M$8*F92 -> 0 | K92: =M$2*F92 -> 33350 | L92: 0 | M92: =ROUND((K92+J92+I92+L92),0) + O92 -> 33350.74 | N92: =ROUND((M92*6% + M92 ),0) + O92 -> 35352.74 | O92: =O91+0.01 -> 0.74 | P92: alonso sabrina eugenia
C93: COCH 6 | D93: Dimito, Vicente Argentino - Cerantes , Mabel | F93: 0.0023 | G93: 27600.75 | H93: =G93 -> 27600.75 | I93: =G93-H93 -> 0 | J93: =M$8*F93 -> 0 | K93: =M$2*F93 -> 33350 | L93: 0 | M93: =ROUND((K93+J93+I93+L93),0) + O93 -> 33350.75 | N93: =ROUND((M93*6% + M93 ),0) + O93 -> 35352.75 | O93: =O92+0.01 -> 0.75
C94: COCH 7 | D94: Campelo, Mariano | F94: 0.0023 | G94: 27600.76 | H94: =G94 -> 27600.76 | I94: =G94-H94 -> 0 | J94: =M$8*F94 -> 0 | K94: =M$2*F94 -> 33350 | L94: 0 | M94: =ROUND((K94+J94+I94+L94),0) + O94 -> 33350.76 | N94: =ROUND((M94*6% + M94 ),0) + O94 -> 35352.76 | O94: =O93+0.01 -> 0.76
C95: COCH 8 | D95: Campelo, Mariano | F95: 0.0023 | G95: 27600.77 | H95: =G95 -> 27600.77 | I95: =G95-H95 -> 0 | J95: =M$8*F95 -> 0 | K95: =M$2*F95 -> 33350 | L95: 0 | M95: =ROUND((K95+J95+I95+L95),0) + O95 -> 33350.77 | N95: =ROUND((M95*6% + M95 ),0) + O95 -> 35352.77 | O95: =O94+0.01 -> 0.77
C96: COCH 9 | D96: Gazzaneo, Francisco | F96: 0.0023 | G96: 26219.78 | H96: =G96 -> 26219.78 | I96: =G96-H96 -> 0 | J96: =M$8*F96 -> 0 | K96: =M$2*F96 -> 33350 | L96: 0 | M96: =ROUND((K96+J96+I96+L96),0) + O96 -> 33350.78 | N96: =ROUND((M96*6% + M96 ),0) + O96 -> 35352.78 | O96: =O95+0.01 -> 0.78
C97: COCH 10 | D97: Cerra, Antonio Osvaldo | F97: 0.0023 | G97: 108432.79 | I97: =G97-H97 -> 108432.79 | J97: =M$8*F97 -> 0 | K97: =M$2*F97 -> 33350 | L97: 0 | M97: =ROUND((K97+J97+I97+L97),0) + O97 -> 141783.79 | N97: =ROUND((M97*6% + M97 ),0) + O97 -> 150291.79 | O97: =O96+0.01 -> 0.79
C98: COCH 11 | D98: Osipowicz, Ariel Marcelo | F98: 0.0023 | G98: 27600.8 | H98: =G98 -> 27600.8 | I98: =G98-H98 -> 0 | J98: =M$8*F98 -> 0 | K98: =M$2*F98 -> 33350 | L98: 0 | M98: =ROUND((K98+J98+I98+L98),0) + O98 -> 33350.8 | N98: =ROUND((M98*6% + M98 ),0) + O98 -> 35352.8 | O98: =O97+0.01 -> 0.8
C99: COCH 12 | D99: Dieci, Matias Orlando | F99: 0.0023 | G99: 27600.81 | I99: =G99-H99 -> 27600.81 | J99: =M$8*F99 -> 0 | K99: =M$2*F99 -> 33350 | L99: 0 | M99: =ROUND((K99+J99+I99+L99),0) + O99 -> 60951.81 | N99: =ROUND((M99*6% + M99 ),0) + O99 -> 64609.81 | O99: =O98+0.01 -> 0.81
C100: COCH 13 | D100: Scardigno, Gabriela Susana - Ripoli, Luis Alberto | F100: 0.0023 | G100: 27600.82 | H100: =G100 -> 27600.82 | I100: =G100-H100 -> 0 | J100: =M$8*F100 -> 0 | K100: =M$2*F100 -> 33350 | L100: 0 | M100: =ROUND((K100+J100+I100+L100),0) + O100 -> 33350.82 | N100: =ROUND((M100*6% + M100 ),0) + O100 -> 35352.82 | O100: =O99+0.01 -> 0.82
C101: COCH 14 | D101: Fontale Federico Carlos - Celentano Alejandra Veronica | F101: 0.0023 | G101: 27600.83 | H101: =G101 -> 27600.83 | I101: =G101-H101 -> 0 | J101: =M$8*F101 -> 0 | K101: =M$2*F101 -> 33350 | L101: 0 | M101: =ROUND((K101+J101+I101+L101),0) + O101 -> 33350.83 | N101: =ROUND((M101*6% + M101 ),0) + O101 -> 35352.83 | O101: =O100+0.01 -> 0.83
C102: COCH 15 | D102: Hernandez, Marisa Beatriz - Hernandez, Adrian Jose | F102: 0.0023 | G102: 27600.84 | H102: =G102 -> 27600.84 | I102: =G102-H102 -> 0 | J102: =M$8*F102 -> 0 | K102: =M$2*F102 -> 33350 | L102: 0 | M102: =ROUND((K102+J102+I102+L102),0) + O102 -> 33350.84 | N102: =ROUND((M102*6% + M102 ),0) + O102 -> 35352.84 | O102: =O101+0.01 -> 0.84
C103: COCH 16 | D103: Mesa, Mariano | F103: 0.0023 | G103: 27600.85 | H103: =G103 -> 27600.85 | I103: =G103-H103 -> 0 | J103: =M$8*F103 -> 0 | K103: =M$2*F103 -> 33350 | L103: 0 | M103: =ROUND((K103+J103+I103+L103),0) + O103 -> 33350.85 | N103: =ROUND((M103*6% + M103 ),0) + O103 -> 35352.85 | O103: =O102+0.01 -> 0.85
C104: COCH 17 | D104: Espósito, Franco Ezequiel | F104: 0.0023 | G104: 27600.86 | I104: =G104-H104 -> 27600.86 | J104: =M$8*F104 -> 0 | K104: =M$2*F104 -> 33350 | L104: 0 | M104: =ROUND((K104+J104+I104+L104),0) + O104 -> 60951.86 | N104: =ROUND((M104*6% + M104 ),0) + O104 -> 64609.86 | O104: =O103+0.01 -> 0.86
C105: COCH 18 | D105: Sr propietario | F105: 0.0023 | G105: 27600.87 | H105: =G105 -> 27600.87 | I105: =G105-H105 -> 0 | J105: =M$8*F105 -> 0 | K105: =M$2*F105 -> 33350 | L105: 0 | M105: =ROUND((K105+J105+I105+L105),0) + O105 -> 33350.87 | N105: =ROUND((M105*6% + M105 ),0) + O105 -> 35352.87 | O105: =O104+0.01 -> 0.87
...

Sheet ANOTACIONES
B4: Jose ferraro pago con un monton de depositos el 10/12
B6: El comprobante de $ 90.000.- corresponde a setiembre cochera 37 y 38 $. 20.700 cada una
B7: Octubre cochera 29 $ 25.626 y cochera 34 $ 20.700 y el comprobante de $ 71.500 es de la cochera 30 saldo al 30/11
B8: El pago de $166.000, es del Dto 2 D
B9: El pago de $103.000. Es del Dto 3A
B10: Y el pago de $ 730.000 es del Dto 3C
B13: Julieta damiano en septiembre pago $87,000 a la cuenta de carolina en MP - debe estar sin deuda ya que es un pago que se nos traspapelo. Hablamos con rocio soria x mail quien es la dueña del dpto

Sheet SUELDOS
C3: =RESUMEN!C5 -> PERÍODO: DICIEMBRE | F3: =[1]RESUMEN!A22 -> Sueldo encargada Sonia Arzamendia Galeano
C5: =RESUMEN!A26 -> Haberes | G5: =RESUMEN!D26 -> 1042462 | H5: Firma
C6: =RESUMEN!A27 -> Plus pileta | G6: =RESUMEN!D27 -> 36382.7 | H6: __________________________________
C7: =RESUMEN!A28 -> Plus retiro de basura | G7: =RESUMEN!D28 -> 126784
C8: =RESUMEN!A29 -> Plus cochera | G8: =RESUMEN!D29 -> 21627.4
C9: =RESUMEN!A30 -> Adicional Viaticos | G9: =RESUMEN!D30 -> 60810.3 | H9: Aclaracion
C10: =RESUMEN!A31 -> Adicional remuneracion | G10: =RESUMEN!D31 -> 50000 | H10: __________________________________
C12: TOTAL | G12: =SUM(G5:G11) -> 1338066.4
C16: =C3 -> PERÍODO: DICIEMBRE | F16: =[1]RESUMEN!A30 -> Sueldo encargada Miriam
H18: Firma
C19: =RESUMEN!A34 -> Haberes | G19: =RESUMEN!D34 -> 521231 | H19: __________________________________
C20: =RESUMEN!A35 -> Horas extras | G20: =RESUMEN!D35 -> 100235
C21: =RESUMEN!A36 -> Plus pileta | G21: =RESUMEN!D36 -> 36382.7
C22: =RESUMEN!A37 -> Plus retiro de basura | G22: =RESUMEN!D37 -> 126784 | H22: Aclaracion
C23: =RESUMEN!A38 -> Plus cochera | G23: =RESUMEN!D38 -> 21627.4 | H23: __________________________________
C24: =RESUMEN!A39 -> Adicional Viaticos | G24: =RESUMEN!D39 -> 60810.3
C25: =RESUMEN!A40 -> Adicional remuneracion | G25: =RESUMEN!D40 -> 50000
C26: TOTAL | G26: =SUM(G18:G25) -> 917070.4

Sheet Hoja1
C4: AYALA
C5: 52141.08 | D5: 3B
C6: 67140.1 | D6: 3D
C7: 52121.11 | D7: 3E
C8: 67885.12 | D8: 3F
C9: 67140.16 | D9: 4D
C10: 62141.17 | D10: 4E
C11: 67855.18 | D11: 4F
C12: 62141.23 | D12: 5E
C13: 67855.24 | D13: 5F
C14: =SUM(C5:C13) -> 566420.39
