Workbook

Sheet RESUMEN
B1: MAIL: consorciovergara1670@gmail.com
B2: CUIT ADMINISTRACION: 27231256879
B3: CBU: 2990024602400258030006 | D3: TELEFONO: 11 5320-2676
A4: LIQUIDACION DE EXPENSAS | B4: ALIAS: VERGARA.1670
A5: CUIT DEL EDIFICIO: 30-71802922-4 | B5: PERÍODO: JUNIO - ADMINISTRADORA: CAROLINA CANCIANI MP:1148
A6: CONSORCIO DE PROPIETARIOS DEL EDIFICIO CALLE VERGARA 1670 | D6: HORARIOS DE ATENCION: LUNES A VIERNES
B8: VTO 14/07
A13: ESTIMADOS PROPIETARIOS E INQUILINOS: POR FAVOR LOS QUE ABONAN EN PRIMER VENCIMIENTO ABONEN EL MONTO DE PRIMER VENCIMIENTO, ASI AGILIZAN LA LIQUIDACION, LES PEDIMOS ENCARECIDAMENTE QUE RESPETEN LOS CENTAVOS CORRESPONDIENTES A LA UNIDAD FUNCIONAL. ES DE CARÁCTER OBLIGATORIO INFORMAR VIA MAIL LAS EXPENSAS.
A20: GASTOS ORDINARIOS UNIDADES FUNCIONALES:
A21: HABERES ENCARGADOS
A22: Remunerativos encargado Gonzalo Guenaga | D22: 598522.2
A23: Deducciones | D23: -139605.89
A24: Redondeo | D24: 0.69
A25: Neto | D25: =SUM(D22:D24) -> 458917
A26: TOTAL SUELDO | E26: =D25 -> 458917
A27: HONORARIOS
A28: Marcela De Biase- Sra. Contadora - Mes de JUNIO | D28: 35000 | E28: Transf 11/06
A29: Honorarios administracion - Mes de MAYO - Se debe JUNIO | D29: 470000 | E29: Transf 12/05
A30: TOTAL | E30: =SUM(D28:D29) -> 505000
A31: SEGUROS
A32: Seguro integral consorcio. Póliza 2161474 | D32: 70868
A33: Seguro de accidentes personales | D33: 719.9
A34: TOTAL IMPUESTO | E34: =SUM(D32:D33) -> 71587.9
A35: APORTES Y CONTRIBUCIONES
A36: ARCA | D36: 371183.27 | E36: PMC 06/05
A37: Sindicatos mes de JUNIO | B37: Fatheryh | D37: 26576.33 | E37: Debito 12/05
A38: =A37 -> Sindicatos mes de JUNIO | B38: Suther | D38: 50388.03 | E38: =E37 -> Debito 12/05
A39: =A38 -> Sindicatos mes de JUNIO | B39: Seracarh | D39: 2952.93 | E39: =E37 -> Debito 12/05
A40: TOTAL Aportes y Contribuciones - Sindicato | E40: =SUM(D36:D39) -> 451100.56
A41: ABONOS Y SERVICIOS
A42: AYSA - Nro de cliente. 318350 | D42: 84629.46
A43: Servicio de mantenimiento de ascensores | D43: 50000 | E43: Transf 19/05
A44: Cablevision - servicio | D44: 81423.93 | E44: Debito 07/05
A45: TOTAL ABONOS Y SERVICIOS | E45: =SUM(D42:D44) -> 216053.39
A46: GASTOS GENERALES / MANTENIMIENTO
A47: Matafuegos Firex compra de matafuego x5 kg | D47: 84500 | E47: Tranfs 16/05
A48: Recarga 14 matafuegos x5kg | D48: 262099.86 | E48: Tranfs 16/05
A49: Calderista - Visita tecnica - Bernardo Curcio | D49: 36300 | E49: Transf 27/05
A50: Electricista - Busqueda de fuga de corriente salto de disyuntor | D50: 25000 | E50: Transf 307/05
A51: Doartero Julio - Mano de obra y materiales reparacion de entrada de agua | D51: 165000 | E51: Tranfs 13/05
A52: Zaffalon Veronica -instalacion bomba de napa nueva | D52: 110000 | E52: Transf 12/06
A53: Zaffalon Veronica - Compra de bomba pozo napa nieva vazzer | D53: 135000 | E53: Tranfs 13/05
A54: Zaffalon Veronica - Vaciemiento de cochera inundada | D54: 385000 | E54: Tranfs 13/05
A55: Zaffalon Veronica - Compra de bomba de achique zona rampa de cochera | D55: 135000 | E55: Transf 27/05
A56: Servisur - busqueda de fuga de corriente por salto de disyuntor | D56: 25000 | E56: Tranfs 29/05
A57: Espindola Christian - Tuerca accionadora e instalacion rampa | D57: 110000 | E57: Transf 12/06
A58: Articulos de limpieza | D58: 51150 | E58: Transf 26/05
A59: TOTAL | E59: =SUM(D47:D58) -> 1524049.9
A60: GASTOS BANCARIOS
A61: Gastos banacarios | D61: =23840.19+13389.86+12056.54+26998.34+23983.39+19115.39 -> 119383.71
A62: Mantenimiento de cuenta | D62: 49082
A63: TOTAL | E63: =SUM(D61:D62) -> 168465.71
A65: PREVISION ORDINARIA
A67: TOTAL ORDINARIOS | E67: =(SUM(E26:E65)) -> 3395174.4
A70: GASTOS EXTRAORDINARIOS:
A71: Metrogas Plan de pagos cuota 6 | D71: 304993.06 | E71: Transf 06/05
E73: =SUM(D71:D72) -> 304993.06
A76: PREVISION EXTRAORDINARIA
A78: TOTAL EXTRAORDINARIOS | E78: =E73+E76 -> 304993.06
A80: GASTOS ORDINARIOS + PREVISION : | B80: =E67 -> 3395174.4
A81: GASTOS ORDINARIOS SIN PREVISION: | B81: =E67-E65 -> 3395174.4
A82: GASTOS EXTRAORDINARIOS SIN PREVISION: | B82: =E78-E76 -> 304993.06
A83: GASTOS EXTRAORDINARIOS CON PREVISION: | B83: =E78 -> 304993.06
A85: RESUMEN
A86: Saldo anterior | B86: 491399.42
A87: Ingreso | B87: =PRORRATEO!H92 -> 6723784.4
A88: Deposito sin identificar | B88: =B104 -> 0
A89: Transferencia ya identificada mes anterior Santiago Tarragosa | B89: =-28214*2 -> -56428
A90: Transferencia ya identificada mes anterior | B90: -89980.82
A91: Punitorios mal cobrados | B91: -2699
A92: Egresos Ordinarios | B92: =-B81 -> -3395174.4
A93: Edesur - cliente nro. 01469567 | B93: =-PRORRATEO!F1 -> -1241030.2
A94: Metrogas - Cliente nro. 30015090344 | B94: =-PRORRATEO!F2 -> -561462.8
A95: Egresos Extraordinarios | B95: =-(B82) -> -304993.06
A96: TOTAL | B96: =SUM(B86:B95) -> 1563415.6
A99: DEPOSITOS NO IDENTIFICADOS
C101: 11948.17
C103: 61209
A104: TOTAL | B104: =SUM(B101:B103) -> 0

Sheet PRORRATEO
E1: EDESUR: | F1: 1241030.2 | K1: Gastos Ordinarios: | M1: =P1 -> 3600000 | P1: 3600000
E2: METROGAS: | F2: 561462.8 | H2: Extras: | I2: 1200000 | K2: Plan de pago metrogas: | M2: 304993.06
A3: Dpto. | C3: UF | D3: Propietario | E3: Inquilinos | F3: (%) | G3: Saldo Ord | H3: Ingreso | I3: Deuda o Saldo a favor | J3: Interes 3% | K3: =K2 -> Plan de pago metrogas: | L3: Expensas ord. | M3: EDESUR | N3: METROGAS | O3: Expensas extraord | P3: Total 1er Vto | Q3: Total 2do Vto
P4: =RESUMEN!B8 -> VTO 14/07
B5: 1°A | C5: 33 | D5: Alejandro Raul Cuezzo | F5: 0.0202 | G5: 154290.33 | H5: =158919.33 -> 158919.33 | I5: =G5-H5 -> -4629 | J5: =IF(I5>0,I5*3%,0) -> 0 | K5: =M$2*F5 -> 6160.8598 | L5: =M$1*F5 -> 72720 | M5: =F$1*F5 -> 25068.809 | N5: =F$2*F5 -> 11341.549 | O5: =I$2*F5 -> 24240 | P5: =ROUND(SUM(I5:O5),0) + R5 -> 134902.33 | Q5: =ROUND(P5*3%,0) + P5 -> 138949.33 | R5: =ROUND(0.001+C5/100,2) -> 0.33
B6: 1°B | C6: 34 | D6: Daniel Julian Guzzo | F6: 0.0139 | G6: 106170.34 | H6: =G6 -> 106170.34 | I6: =G6-H6 -> 0 | J6: =IF(I6>0,I6*3%,0) -> 0 | K6: =M$2*F6 -> 4239.4035 | L6: =M$1*F6 -> 50040 | M6: =F$1*F6 -> 17250.319 | N6: =F$2*F6 -> 7804.3329 | O6: =I$2*F6 -> 16680 | P6: =ROUND(SUM(I6:O6),0) + R6 -> 96014.34 | Q6: =ROUND(P6*3%,0) + P6 -> 98894.34 | R6: =ROUND(0.001+C6/100,2) -> 0.34
A7: 1 | B7: 1°C | C7: 35 | D7: Pablo Plebs | F7: 0.0142 | G7: 203142.35 | H7: 108461 | I7: =G7-H7 -> 94681.35 | J7: =IF(I7>0,I7*3%,0) -> 2840.4405 | K7: =M$2*F7 -> 4330.9015 | L7: =M$1*F7 -> 51120 | M7: =F$1*F7 -> 17622.628 | N7: =F$2*F7 -> 7972.7718 | O7: =I$2*F7 -> 17040 | P7: =ROUND(SUM(I7:O7),0) + R7 -> 195608.35 | Q7: =ROUND(P7*3%,0) + P7 -> 201476.35 | R7: =ROUND(0.001+C7/100,2) -> 0.35
A8: 2 | B8: 1°D | C8: 36 | D8: Adrian Alejandro Pozo | F8: 0.0202 | G8: 150347.36 | I8: =G8-H8 -> 150347.36 | J8: =IF(I8>0,I8*3%,0) -> 4510.4208 | K8: =M$2*F8 -> 6160.8598 | L8: =M$1*F8 -> 72720 | M8: =F$1*F8 -> 25068.809 | N8: =F$2*F8 -> 11341.549 | O8: =I$2*F8 -> 24240 | P8: =ROUND(SUM(I8:O8),0) + R8 -> 294389.36 | Q8: =ROUND(P8*3%,0) + P8 -> 303221.36 | R8: =ROUND(0.001+C8/100,2) -> 0.36
A9: 3 | B9: 2°A | C9: 37 | D9: Guillen Maria / Alejandro DI LEO | E9: Claudia / Laura Avido | F9: 0.0202 | G9: 93012.37 | H9: =20200+5300+72812.37-H63 -> 96784.16 | I9: =G9-H9 -> -3771.79 | J9: =IF(I9>0,I9*3%,0) -> 0 | K9: =M$2*F9 -> 6160.8598 | L9: =M$1*F9 -> 72720 | M9: =F$1*F9 -> 25068.809 | N9: =F$2*F9 -> 11341.549 | O9: =I$2*F9 -> 24240 | P9: =ROUND(SUM(I9:O9),0) + R9 -> 135759.37 | Q9: =ROUND(P9*3%,0) + P9 -> 139832.37 | R9: =ROUND(0.001+C9/100,2) -> 0.37
A10: 4 | B10: 2°B | C10: 38 | D10: Jose Luis Gurtubay | E10: Santiago Flores | F10: 0.0139 | G10: 106170.38 | H10: =106170.54 -> 106170.54 | I10: =G10-H10 -> -0.16 | J10: =IF(I10>0,I10*3%,0) -> 0 | K10: =M$2*F10 -> 4239.4035 | L10: =M$1*F10 -> 50040 | M10: =F$1*F10 -> 17250.319 | N10: =F$2*F10 -> 7804.3329 | O10: =I$2*F10 -> 16680 | P10: =ROUND(SUM(I10:O10),0) + R10 -> 96014.38 | Q10: =ROUND(P10*3%,0) + P10 -> 98894.38 | R10: =ROUND(0.001+C10/100,2) -> 0.38
A11: 5 | B11: 2°C | C11: 39 | D11: Magali Carrivale | F11: 0.0139 | G11: 106170.39 | H11: =95038.42 -> 95038.42 | I11: =G11-H11 -> 11131.97 | J11: =IF(I11>0,I11*3%,0) -> 333.9591 | K11: =M$2*F11 -> 4239.4035 | L11: =M$1*F11 -> 50040 | M11: =F$1*F11 -> 17250.319 | N11: =F$2*F11 -> 7804.3329 | O11: =I$2*F11 -> 16680 | P11: =ROUND(SUM(I11:O11),0) + R11 -> 107480.39 | Q11: =ROUND(P11*3%,0) + P11 -> 110704.39 | R11: =ROUND(0.001+C11/100,2) -> 0.39
A12: 6 | B12: 2°D | C12: 40 | D12: Juan Carlos Alonso | F12: 0.0202 | G12: 149338.4 | H12: =31194+164320.44-H78 -> 155032.4 | I12: =G12-H12 -> -5694 | J12: =IF(I12>0,I12*3%,0) -> 0 | K12: =M$2*F12 -> 6160.8598 | L12: =M$1*F12 -> 72720 | M12: =F$1*F12 -> 25068.809 | N12: =F$2*F12 -> 11341.549 | O12: =I$2*F12 -> 24240 | P12: =ROUND(SUM(I12:O12),0) + R12 -> 133837.4 | Q12: =ROUND(P12*3%,0) + P12 -> 137852.4 | R12: =ROUND(0.001+C12/100,2) -> 0.4
A13: 7 | B13: 3°A | C13: 41 | D13: Lucas Oscar Ramil | E13: Camila Benitez Nahiara | F13: 0.0202 | G13: 154290.41 | H13: =134090 -> 134090 | I13: =G13-H13 -> 20200.41 | J13: =IF(I13>0,I13*3%,0) -> 606.0123 | K13: =M$2*F13 -> 6160.8598 | L13: =M$1*F13 -> 72720 | M13: =F$1*F13 -> 25068.809 | N13: =F$2*F13 -> 11341.549 | O13: =I$2*F13 -> 24240 | P13: =ROUND(SUM(I13:O13),0) + R13 -> 160338.41 | Q13: =ROUND(P13*3%,0) + P13 -> 165148.41 | R13: =ROUND(0.001+C13/100,2) -> 0.41
A14: 8 | B14: 3°B | C14: 42 | D14: Raul Boffi | E14: Gian y Micaela Parra | F14: 0.0139 | G14: 106170.42 | H14: =G14 -> 106170.42 | I14: =G14-H14 -> 0 | J14: =IF(I14>0,I14*3%,0) -> 0 | K14: =M$2*F14 -> 4239.4035 | L14: =M$1*F14 -> 50040 | M14: =F$1*F14 -> 17250.319 | N14: =F$2*F14 -> 7804.3329 | O14: =I$2*F14 -> 16680 | P14: =ROUND(SUM(I14:O14),0) + R14 -> 96014.42 | Q14: =ROUND(P14*3%,0) + P14 -> 98894.42 | R14: =ROUND(0.001+C14/100,2) -> 0.42
A15: 1 | B15: 3°C | C15: 43 | D15: Raul Boffi | E15: Lujan / Natalia Capece | F15: 0.0139 | G15: 198850.43 | H15: =G15 -> 198850.43 | I15: =G15-H15 -> 0 | J15: =IF(I15>0,I15*3%,0) -> 0 | K15: =M$2*F15 -> 4239.4035 | L15: =M$1*F15 -> 50040 | M15: =F$1*F15 -> 17250.319 | N15: =F$2*F15 -> 7804.3329 | O15: =I$2*F15 -> 16680 | P15: =ROUND(SUM(I15:O15),0) + R15 -> 96014.43 | Q15: =ROUND(P15*3%,0) + P15 -> 98894.43 | R15: =ROUND(0.001+C15/100,2) -> 0.43
A16: 1 | B16: 3°D | C16: 44 | D16: Roxana Elena Maya | E16: Daniela Bernabe | F16: 0.0202 | G16: 149367.44 | H16: =153848.44 -> 153848.44 | I16: =G16-H16 -> -4481 | J16: =IF(I16>0,I16*3%,0) -> 0 | K16: =M$2*F16 -> 6160.8598 | L16: =M$1*F16 -> 72720 | M16: =F$1*F16 -> 25068.809 | N16: =F$2*F16 -> 11341.549 | O16: =I$2*F16 -> 24240 | P16: =ROUND(SUM(I16:O16),0) + R16 -> 135050.44 | Q16: =ROUND(P16*3%,0) + P16 -> 139102.44 | R16: =ROUND(0.001+C16/100,2) -> 0.44
A17: 2 | B17: 4°A | C17: 45 | D17: Raul Boffi | E17: Paula Murado | F17: 0.0202 | G17: 154290.45 | H17: =134090.45+20200 -> 154290.45 | I17: =G17-H17 -> 0 | J17: =IF(I17>0,I17*3%,0) -> 0 | K17: =M$2*F17 -> 6160.8598 | L17: =M$1*F17 -> 72720 | M17: =F$1*F17 -> 25068.809 | N17: =F$2*F17 -> 11341.549 | O17: =I$2*F17 -> 24240 | P17: =ROUND(SUM(I17:O17),0) + R17 -> 139531.45 | Q17: =ROUND(P17*3%,0) + P17 -> 143717.45 | R17: =ROUND(0.001+C17/100,2) -> 0.45
A18: 2 | B18: 4°B | C18: 46 | D18: Raul Boffi | E18: Maria Florencia Boffi | F18: 0.0139 | G18: 106170.46 | H18: =92270.46+13900+3185 -> 109355.46 | I18: =G18-H18 -> -3185 | J18: =IF(I18>0,I18*3%,0) -> 0 | K18: =M$2*F18 -> 4239.4035 | L18: =M$1*F18 -> 50040 | M18: =F$1*F18 -> 17250.319 | N18: =F$2*F18 -> 7804.3329 | O18: =I$2*F18 -> 16680 | P18: =ROUND(SUM(I18:O18),0) + R18 -> 92829.46 | Q18: =ROUND(P18*3%,0) + P18 -> 95614.46 | R18: =ROUND(0.001+C18/100,2) -> 0.46
A19: 3 | B19: 4°C | C19: 47 | D19: Raul Boffi | E19: Norberto omar picin | F19: 0.0139 | G19: 67614.47 | H19: 27614.47 | I19: =G19-H19 -> 40000 | J19: =IF(I19>0,I19*3%,0) -> 1200 | K19: =M$2*F19 -> 4239.4035 | L19: =M$1*F19 -> 50040 | M19: =F$1*F19 -> 17250.319 | N19: =F$2*F19 -> 7804.3329 | O19: =I$2*F19 -> 16680 | P19: =ROUND(SUM(I19:O19),0) + R19 -> 137214.47 | Q19: =ROUND(P19*3%,0) + P19 -> 141330.47 | R19: =ROUND(0.001+C19/100,2) -> 0.47 | S19: TODO LO QUE HABIA DEPOSITADO NORBERTO OMAR PICIN SE LO HABIAMOS PUESTO A EZEQUIEL GARRO ERRONEAMENTE, HAY QUE CORREGIR ESO)
A20: 3 | B20: 4°D | C20: 48 | D20: Hernán Gastón Padilla | E20: Armando Ezequiel Garro | F20: 0.0202 | G20: 154290.48 | H20: =194772.48-H89 -> 154290.33 | I20: =G20-H20 -> 0.15 | J20: =IF(I20>0,I20*3%,0) -> 0.0045 | K20: =M$2*F20 -> 6160.8598 | L20: =M$1*F20 -> 72720 | M20: =F$1*F20 -> 25068.809 | N20: =F$2*F20 -> 11341.549 | O20: =I$2*F20 -> 24240 | P20: =ROUND(SUM(I20:O20),0) + R20 -> 139531.48 | Q20: =ROUND(P20*3%,0) + P20 -> 143717.48 | R20: =ROUND(0.001+C20/100,2) -> 0.48 | S20: 40000+9980+20000+20000+48097+20000+20000+ TODO ESTO ES DE PICIN
A21: 4 | B21: 5°A | C21: 49 | D21: Raul Boffi | E21: Barbara Fucito | F21: 0.0202 | G21: 154290.49 | H21: =G21 -> 154290.49 | I21: =G21-H21 -> 0 | J21: =IF(I21>0,I21*3%,0) -> 0 | K21: =M$2*F21 -> 6160.8598 | L21: =M$1*F21 -> 72720 | M21: =F$1*F21 -> 25068.809 | N21: =F$2*F21 -> 11341.549 | O21: =I$2*F21 -> 24240 | P21: =ROUND(SUM(I21:O21),0) + R21 -> 139531.49 | Q21: =ROUND(P21*3%,0) + P21 -> 143717.49 | R21: =ROUND(0.001+C21/100,2) -> 0.49
A22: 4 | B22: 5°B | C22: 50 | D22: Raul Boffi | F22: 0.0139 | G22: 341684.5 | I22: =G22-H22 -> 341684.5 | J22: =IF(I22>0,I22*3%,0) -> 10250.535 | K22: =M$2*F22 -> 4239.4035 | L22: =M$1*F22 -> 50040 | M22: =F$1*F22 -> 17250.319 | N22: =F$2*F22 -> 7804.3329 | O22: =I$2*F22 -> 16680 | P22: =ROUND(SUM(I22:O22),0) + R22 -> 447949.5 | Q22: =ROUND(P22*3%,0) + P22 -> 461387.5 | R22: =ROUND(0.001+C22/100,2) -> 0.5
A23: 5 | B23: 5°C | C23: 51 | D23: Raul Boffi | E23: Brenda Carrasco | F23: 0.0139 | G23: 172203.51 | I23: =G23-H23 -> 172203.51 | J23: =IF(I23>0,I23*3%,0) -> 5166.1053 | K23: =M$2*F23 -> 4239.4035 | L23: =M$1*F23 -> 50040 | M23: =F$1*F23 -> 17250.319 | N23: =F$2*F23 -> 7804.3329 | O23: =I$2*F23 -> 16680 | P23: =ROUND(SUM(I23:O23),0) + R23 -> 273384.51 | Q23: =ROUND(P23*3%,0) + P23 -> 281586.51 | R23: =ROUND(0.001+C23/100,2) -> 0.51
A24: 5 | B24: 5°D | C24: 52 | D24: Fernando Andres Canepa | E24: Matias / Carla Esteves | F24: 0.0202 | G24: 154290.52 | H24: =20200+150290.52+40482.12-G86 -> 170490.52 | I24: =G24-H24 -> -16200 | J24: =IF(I24>0,I24*3%,0) -> 0 | K24: =M$2*F24 -> 6160.8598 | L24: =M$1*F24 -> 72720 | M24: =F$1*F24 -> 25068.809 | N24: =F$2*F24 -> 11341.549 | O24: =I$2*F24 -> 24240 | P24: =ROUND(SUM(I24:O24),0) + R24 -> 123331.52 | Q24: =ROUND(P24*3%,0) + P24 -> 127031.52 | R24: =ROUND(0.001+C24/100,2) -> 0.52
A25: 6 | B25: 6°A | C25: 53 | D25: Andres Gabriel Devouassoux | F25: 0.0202 | G25: 120367.53 | H25: 123198.53 | I25: =G25-H25 -> -2831 | J25: =IF(I25>0,I25*3%,0) -> 0 | K25: =M$2*F25 -> 6160.8598 | L25: =M$1*F25 -> 72720 | M25: =F$1*F25 -> 25068.809 | N25: =F$2*F25 -> 11341.549 | O25: =I$2*F25 -> 24240 | P25: =ROUND(SUM(I25:O25),0) + R25 -> 136700.53 | Q25: =ROUND(P25*3%,0) + P25 -> 140801.53 | R25: =ROUND(0.001+C25/100,2) -> 0.53
A26: 6 | B26: 6°B | C26: 54 | D26: Raul Boffi | E26: Nicolas Iudice | F26: 0.0139 | G26: 106170.54 | H26: =G26 -> 106170.54 | I26: =G26-H26 -> 0 | J26: =IF(I26>0,I26*3%,0) -> 0 | K26: =M$2*F26 -> 4239.4035 | L26: =M$1*F26 -> 50040 | M26: =F$1*F26 -> 17250.319 | N26: =F$2*F26 -> 7804.3329 | O26: =I$2*F26 -> 16680 | P26: =ROUND(SUM(I26:O26),0) + R26 -> 96014.54 | Q26: =ROUND(P26*3%,0) + P26 -> 98894.54 | R26: =ROUND(0.001+C26/100,2) -> 0.54
A27: 7 | B27: 6°C | C27: 55 | D27: Barbara Eugenia GARCIA FONTENLA | E27: Diego Coronel / Mirta Beatriz Castañeda | F27: 0.0139 | G27: 106171.55 | H27: =95039.55 -> 95039.55 | I27: =G27-H27 -> 11132 | J27: =IF(I27>0,I27*3%,0) -> 333.96 | K27: =M$2*F27 -> 4239.4035 | L27: =M$1*F27 -> 50040 | M27: =F$1*F27 -> 17250.319 | N27: =F$2*F27 -> 7804.3329 | O27: =I$2*F27 -> 16680 | P27: =ROUND(SUM(I27:O27),0) + R27 -> 107480.55 | Q27: =ROUND(P27*3%,0) + P27 -> 110704.55 | R27: =ROUND(0.001+C27/100,2) -> 0.55
A28: 7 | B28: 6°D | C28: 56 | D28: Javier Alejandro Panaccio | E28: Javier Enrique Zambrano | F28: 0.0202 | G28: 237024.56 | H28: =20200.56+200.56+220309-H65 -> 239181.89 | I28: =G28-H28 -> -2157.33 | J28: =IF(I28>0,I28*3%,0) -> 0 | K28: =M$2*F28 -> 6160.8598 | L28: =M$1*F28 -> 72720 | M28: =F$1*F28 -> 25068.809 | N28: =F$2*F28 -> 11341.549 | O28: =I$2*F28 -> 24240 | P28: =ROUND(SUM(I28:O28),0) + R28 -> 137374.56 | Q28: =ROUND(P28*3%,0) + P28 -> 141495.56 | R28: =ROUND(0.001+C28/100,2) -> 0.56
A29: 8 | B29: 7°A | C29: 57 | D29: Mirta Isabel Asturino | F29: 0.0202 | G29: 154290.57 | H29: =G29 -> 154290.57 | I29: =G29-H29 -> 0 | J29: =IF(I29>0,I29*3%,0) -> 0 | K29: =M$2*F29 -> 6160.8598 | L29: =M$1*F29 -> 72720 | M29: =F$1*F29 -> 25068.809 | N29: =F$2*F29 -> 11341.549 | O29: =I$2*F29 -> 24240 | P29: =ROUND(SUM(I29:O29),0) + R29 -> 139531.57 | Q29: =ROUND(P29*3%,0) + P29 -> 143717.57 | R29: =ROUND(0.001+C29/100,2) -> 0.57
A30: 8 | B30: 7°B | C30: 58 | D30: Jorge Antonio Mendiola | E30: Carlos Mehinger Lisa | F30: 0.0139 | G30: 106170.58 | H30: =13900.58+92270.58 -> 106171.16 | I30: =G30-H30 -> -0.58 | J30: =IF(I30>0,I30*3%,0) -> 0 | K30: =M$2*F30 -> 4239.4035 | L30: =M$1*F30 -> 50040 | M30: =F$1*F30 -> 17250.319 | N30: =F$2*F30 -> 7804.3329 | O30: =I$2*F30 -> 16680 | P30: =ROUND(SUM(I30:O30),0) + R30 -> 96013.58 | Q30: =ROUND(P30*3%,0) + P30 -> 98893.58 | R30: =ROUND(0.001+C30/100,2) -> 0.58
A31: 9 | B31: 7°C | C31: 59 | D31: Nelson Ariel FRAGA | F31: 0.0139 | G31: 205309.59 | H31: =205309.59 -> 205309.59 | I31: =G31-H31 -> 0 | J31: =IF(I31>0,I31*3%,0) -> 0 | K31: =M$2*F31 -> 4239.4035 | L31: =M$1*F31 -> 50040 | M31: =F$1*F31 -> 17250.319 | N31: =F$2*F31 -> 7804.3329 | O31: =I$2*F31 -> 16680 | P31: =ROUND(SUM(I31:O31),0) + R31 -> 96014.59 | Q31: =ROUND(P31*3%,0) + P31 -> 98894.59 | R31: =ROUND(0.001+C31/100,2) -> 0.59
A32: 9 | B32: 7°D | C32: 60 | D32: Domingo Alifraco | E32: Micaela Contreras | F32: 0.0202 | G32: 154878.6 | H32: 154879 | I32: =G32-H32 -> -0.4 | J32: =IF(I32>0,I32*3%,0) -> 0 | K32: =M$2*F32 -> 6160.8598 | L32: =M$1*F32 -> 72720 | M32: =F$1*F32 -> 25068.809 | N32: =F$2*F32 -> 11341.549 | O32: =I$2*F32 -> 24240 | P32: =ROUND(SUM(I32:O32),0) + R32 -> 139531.6 | Q32: =ROUND(P32*3%,0) + P32 -> 143717.6 | R32: =ROUND(0.001+C32/100,2) -> 0.6
A33: 10 | B33: 8°A | C33: 61 | D33: Juan Pablo Charpin | F33: 0.0202 | G33: 154290.61 | H33: =169272.74-H87 -> 128790.61 | I33: =G33-H33 -> 25500 | J33: =IF(I33>0,I33*3%,0) -> 765 | K33: =M$2*F33 -> 6160.8598 | L33: =M$1*F33 -> 72720 | M33: =F$1*F33 -> 25068.809 | N33: =F$2*F33 -> 11341.549 | O33: =I$2*F33 -> 24240 | P33: =ROUND(SUM(I33:O33),0) + R33 -> 165796.61 | Q33: =ROUND(P33*3%,0) + P33 -> 170770.61 | R33: =ROUND(0.001+C33/100,2) -> 0.61
A34: 10 | B34: 8°B | C34: 62 | D34: Adriana Del Bagno | E34: Fanta / Alejandro Gabriel Lopez | F34: 0.0139 | G34: 106170.62 | H34: =109365.52 -> 109365.52 | I34: =G34-H34 -> -3194.9 | J34: =IF(I34>0,I34*3%,0) -> 0 | K34: =M$2*F34 -> 4239.4035 | L34: =M$1*F34 -> 50040 | M34: =F$1*F34 -> 17250.319 | N34: =F$2*F34 -> 7804.3329 | O34: =I$2*F34 -> 16680 | P34: =ROUND(SUM(I34:O34),0) + R34 -> 92819.62 | Q34: =ROUND(P34*3%,0) + P34 -> 95604.62 | R34: =ROUND(0.001+C34/100,2) -> 0.62
A35: 11 | B35: 8°C | C35: 63 | D35: Claudio Moroni | E35: Macarena Barraza | F35: 0.0139 | G35: 106170.63 | H35: =G35 -> 106170.63 | I35: =G35-H35 -> 0 | J35: =IF(I35>0,I35*3%,0) -> 0 | K35: =M$2*F35 -> 4239.4035 | L35: =M$1*F35 -> 50040 | M35: =F$1*F35 -> 17250.319 | N35: =F$2*F35 -> 7804.3329 | O35: =I$2*F35 -> 16680 | P35: =ROUND(SUM(I35:O35),0) + R35 -> 96014.63 | Q35: =ROUND(P35*3%,0) + P35 -> 98894.63 | R35: =ROUND(0.001+C35/100,2) -> 0.63
A36: 11 | B36: 8°D | C36: 64 | D36: Karina Edith Mastandrea | E36: Ayelen Agustina | F36: 0.0202 | G36: 88536.64 | H36: =150000 -> 150000 | I36: =G36-H36 -> -61463.36 | J36: =IF(I36>0,I36*3%,0) -> 0 | K36: =M$2*F36 -> 6160.8598 | L36: =M$1*F36 -> 72720 | M36: =F$1*F36 -> 25068.809 | N36: =F$2*F36 -> 11341.549 | O36: =I$2*F36 -> 24240 | P36: =ROUND(SUM(I36:O36),0) + R36 -> 78068.64 | Q36: =ROUND(P36*3%,0) + P36 -> 80410.64 | R36: =ROUND(0.001+C36/100,2) -> 0.64
A37: 12 | B37: 9°A | C37: 65 | D37: Fernando Fernandez | E37: Olivera Rodrigo | F37: 0.0202 | G37: 150368.65 | H37: =G37 -> 150368.65 | I37: =G37-H37 -> 0 | J37: =IF(I37>0,I37*3%,0) -> 0 | K37: =M$2*F37 -> 6160.8598 | L37: =M$1*F37 -> 72720 | M37: =F$1*F37 -> 25068.809 | N37: =F$2*F37 -> 11341.549 | O37: =I$2*F37 -> 24240 | P37: =ROUND(SUM(I37:O37),0) + R37 -> 139531.65 | Q37: =ROUND(P37*3%,0) + P37 -> 143717.65 | R37: =ROUND(0.001+C37/100,2) -> 0.65
A38: 12 | B38: 9°B | C38: 66 | D38: Gonzalo Cadiz | E38: Micaela Dib | F38: 0.0139 | G38: 198850.66 | I38: =G38-H38 -> 198850.66 | J38: =IF(I38>0,I38*3%,0) -> 5965.5198 | K38: =M$2*F38 -> 4239.4035 | L38: =M$1*F38 -> 50040 | M38: =F$1*F38 -> 17250.319 | N38: =F$2*F38 -> 7804.3329 | O38: =I$2*F38 -> 16680 | P38: =ROUND(SUM(I38:O38),0) + R38 -> 300830.66 | Q38: =ROUND(P38*3%,0) + P38 -> 309855.66 | R38: =ROUND(0.001+C38/100,2) -> 0.66
A39: 1 | B39: 9°C | C39: 67 | D39: Hernan Miñambres | E39: Laura Quintana | F39: 0.0139 | G39: 188028.67 | H39: =168651.67 -> 168651.67 | I39: =G39-H39 -> 19377 | J39: =IF(I39>0,I39*3%,0) -> 581.31 | K39: =M$2*F39 -> 4239.4035 | L39: =M$1*F39 -> 50040 | M39: =F$1*F39 -> 17250.319 | N39: =F$2*F39 -> 7804.3329 | O39: =I$2*F39 -> 16680 | P39: =ROUND(SUM(I39:O39),0) + R39 -> 115972.67 | Q39: =ROUND(P39*3%,0) + P39 -> 119451.67 | R39: =ROUND(0.001+C39/100,2) -> 0.67
A40: 1 | B40: 9°D | C40: 68 | D40: Matías Ezequiel Tobío | E40: =D76 -> Jesica Romina Tobio | F40: 0.0202 | G40: 149124.68 | H40: =198008.7-H76 -> 149124.68 | I40: =G40-H40 -> 0 | J40: =IF(I40>0,I40*3%,0) -> 0 | K40: =M$2*F40 -> 6160.8598 | L40: =M$1*F40 -> 72720 | M40: =F$1*F40 -> 25068.809 | N40: =F$2*F40 -> 11341.549 | O40: =I$2*F40 -> 24240 | P40: =ROUND(SUM(I40:O40),0) + R40 -> 139531.68 | Q40: =ROUND(P40*3%,0) + P40 -> 143717.68 | R40: =ROUND(0.001+C40/100,2) -> 0.68
A41: 1 | B41: 10°A | C41: 69 | D41: Ariel Marcelo FERNANDEZ | E41: Sol Gatti Maria | F41: 0.0202 | G41: 147443.69 | H41: 147500 | I41: =G41-H41 -> -56.31 | J41: =IF(I41>0,I41*3%,0) -> 0 | K41: =M$2*F41 -> 6160.8598 | L41: =M$1*F41 -> 72720 | M41: =F$1*F41 -> 25068.809 | N41: =F$2*F41 -> 11341.549 | O41: =I$2*F41 -> 24240 | P41: =ROUND(SUM(I41:O41),0) + R41 -> 139475.69 | Q41: =ROUND(P41*3%,0) + P41 -> 143659.69 | R41: =ROUND(0.001+C41/100,2) -> 0.69
A42: 2 | B42: 10°B | C42: 70 | D42: Jose Luis Gurtubay | E42: Antonela escobar | F42: 0.0139 | G42: 106170.7 | H42: =33100 -> 33100 | I42: =G42-H42 -> 73070.7 | J42: =IF(I42>0,I42*3%,0) -> 2192.121 | K42: =M$2*F42 -> 4239.4035 | L42: =M$1*F42 -> 50040 | M42: =F$1*F42 -> 17250.319 | N42: =F$2*F42 -> 7804.3329 | O42: =I$2*F42 -> 16680 | P42: =ROUND(SUM(I42:O42),0) + R42 -> 171277.7 | Q42: =ROUND(P42*3%,0) + P42 -> 176415.7 | R42: =ROUND(0.001+C42/100,2) -> 0.7
A43: 2 | B43: 10°C | C43: 71 | D43: Antonio Carlos Caputo | E43: Benitez Gabriela | F43: 0.0139 | G43: 106170.71 | I43: =G43-H43 -> 106170.71 | J43: =IF(I43>0,I43*3%,0) -> 3185.1213 | K43: =M$2*F43 -> 4239.4035 | L43: =M$1*F43 -> 50040 | M43: =F$1*F43 -> 17250.319 | N43: =F$2*F43 -> 7804.3329 | O43: =I$2*F43 -> 16680 | P43: =ROUND(SUM(I43:O43),0) + R43 -> 205370.71 | Q43: =ROUND(P43*3%,0) + P43 -> 211531.71 | R43: =ROUND(0.001+C43/100,2) -> 0.71
A44: 2 | B44: 10°D | C44: 72 | D44: Antonio Carlos Caputo | E44: Luz Maria Alberio | F44: 0.0202 | G44: 149338.72 | I44: =G44-H44 -> 149338.72 | J44: =IF(I44>0,I44*3%,0) -> 4480.1616 | K44: =M$2*F44 -> 6160.8598 | L44: =M$1*F44 -> 72720 | M44: =F$1*F44 -> 25068.809 | N44: =F$2*F44 -> 11341.549 | O44: =I$2*F44 -> 24240 | P44: =ROUND(SUM(I44:O44),0) + R44 -> 293350.72 | Q44: =ROUND(P44*3%,0) + P44 -> 302151.72 | R44: =ROUND(0.001+C44/100,2) -> 0.72
A45: 3 | B45: 11°A | C45: 73 | D45: Manuel Salvador FERNANDEZ | E45: Nadia Santillan Soledad | F45: 0.0202 | G45: 154290.73 | I45: =G45-H45 -> 154290.73 | J45: =IF(I45>0,I45*3%,0) -> 4628.7219 | K45: =M$2*F45 -> 6160.8598 | L45: =M$1*F45 -> 72720 | M45: =F$1*F45 -> 25068.809 | N45: =F$2*F45 -> 11341.549 | O45: =I$2*F45 -> 24240 | P45: =ROUND(SUM(I45:O45),0) + R45 -> 298451.73 | Q45: =ROUND(P45*3%,0) + P45 -> 307405.73 | R45: =ROUND(0.001+C45/100,2) -> 0.73
A46: 3 | B46: 11°B | C46: 74 | D46: Jorge Antonio VILLONE | E46: Micaela Acevedo | F46: 0.0139 | G46: 106170.74 | H46: =G46 -> 106170.74 | I46: =G46-H46 -> 0 | J46: =IF(I46>0,I46*3%,0) -> 0 | K46: =M$2*F46 -> 4239.4035 | L46: =M$1*F46 -> 50040 | M46: =F$1*F46 -> 17250.319 | N46: =F$2*F46 -> 7804.3329 | O46: =I$2*F46 -> 16680 | P46: =ROUND(SUM(I46:O46),0) + R46 -> 96014.74 | Q46: =ROUND(P46*3%,0) + P46 -> 98894.74 | R46: =ROUND(0.001+C46/100,2) -> 0.74
A47: 3 | B47: 11°C | C47: 75 | D47: Daniela Noemi Araujo | E47: Araceli Lohaysa | F47: 0.0139 | G47: 189024.75 | H47: =168077 -> 168077 | I47: =G47-H47 -> 20947.75 | J47: =IF(I47>0,I47*3%,0) -> 628.4325 | K47: =M$2*F47 -> 4239.4035 | L47: =M$1*F47 -> 50040 | M47: =F$1*F47 -> 17250.319 | N47: =F$2*F47 -> 7804.3329 | O47: =I$2*F47 -> 16680 | P47: =ROUND(SUM(I47:O47),0) + R47 -> 117590.75 | Q47: =ROUND(P47*3%,0) + P47 -> 121118.75 | R47: =ROUND(0.001+C47/100,2) -> 0.75
A48: 4 | B48: 11°D | C48: 76 | D48: Gabriela Santiso/Claudio Touzon | E48: Ignacio Touzon | F48: 0.0202 | G48: 154290.76 | H48: =G48 -> 154290.76 | I48: =G48-H48 -> 0 | J48: =IF(I48>0,I48*3%,0) -> 0 | K48: =M$2*F48 -> 6160.8598 | L48: =M$1*F48 -> 72720 | M48: =F$1*F48 -> 25068.809 | N48: =F$2*F48 -> 11341.549 | O48: =I$2*F48 -> 24240 | P48: =ROUND(SUM(I48:O48),0) + R48 -> 139531.76 | Q48: =ROUND(P48*3%,0) + P48 -> 143717.76 | R48: =ROUND(0.001+C48/100,2) -> 0.76
A49: 4 | B49: 12°A | C49: 77 | D49: Antonio Carlos Caputo | E49: Ezequiel /Maria Delfina Saavedra | F49: 0.0202 | G49: 335646.77 | H49: =G49 -> 335646.77 | I49: =G49-H49 -> 0 | J49: =IF(I49>0,I49*3%,0) -> 0 | K49: =M$2*F49 -> 6160.8598 | L49: =M$1*F49 -> 72720 | M49: =F$1*F49 -> 25068.809 | N49: =F$2*F49 -> 11341.549 | O49: =I$2*F49 -> 24240 | P49: =ROUND(SUM(I49:O49),0) + R49 -> 139531.77 | Q49: =ROUND(P49*3%,0) + P49 -> 143717.77 | R49: =ROUND(0.001+C49/100,2) -> 0.77
A50: 4 | B50: 12°B | C50: 78 | D50: Antonio Carlos Caputo | E50: Mayne Romero | F50: 0.0139 | G50: 203571.78 | I50: =G50-H50 -> 203571.78 | J50: =IF(I50>0,I50*3%,0) -> 6107.1534 | K50: =M$2*F50 -> 4239.4035 | L50: =M$1*F50 -> 50040 | M50: =F$1*F50 -> 17250.319 | N50: =F$2*F50 -> 7804.3329 | O50: =I$2*F50 -> 16680 | P50: =ROUND(SUM(I50:O50),0) + R50 -> 305693.78 | Q50: =ROUND(P50*3%,0) + P50 -> 314864.78 | R50: =ROUND(0.001+C50/100,2) -> 0.78
A51: 5 | B51: 12°C | C51: 79 | D51: Pedro Eugenio Negri | F51: 0.0139 | G51: 106170.79 | H51: =G51 -> 106170.79 | I51: =G51-H51 -> 0 | J51: =IF(I51>0,I51*3%,0) -> 0 | K51: =M$2*F51 -> 4239.4035 | L51: =M$1*F51 -> 50040 | M51: =F$1*F51 -> 17250.319 | N51: =F$2*F51 -> 7804.3329 | O51: =I$2*F51 -> 16680 | P51: =ROUND(SUM(I51:O51),0) + R51 -> 96014.79 | Q51: =ROUND(P51*3%,0) + P51 -> 98894.79 | R51: =ROUND(0.001+C51/100,2) -> 0.79
A52: 5 | B52: 12°D | C52: 80 | D52: Luis Alberto Guarch | E52: Biyik / Jefferson barreto | F52: 0.0202 | G52: 146851.8 | H52: =151257.8 -> 151257.8 | I52: =G52-H52 -> -4406 | J52: =IF(I52>0,I52*3%,0) -> 0 | K52: =M$2*F52 -> 6160.8598 | L52: =M$1*F52 -> 72720 | M52: =F$1*F52 -> 25068.809 | N52: =F$2*F52 -> 11341.549 | O52: =I$2*F52 -> 24240 | P52: =ROUND(SUM(I52:O52),0) + R52 -> 135125.8 | Q52: =ROUND(P52*3%,0) + P52 -> 139179.8 | R52: =ROUND(0.001+C52/100,2) -> 0.8
A53: 5 | B53: 13°A | C53: 81 | D53: Soraya Mariel Varela | E53: Rosa Garnica | F53: 0.0202 | G53: 282685.81 | H53: =124377.81+157553.81 -> 281931.62 | I53: =G53-H53 -> 754.19 | J53: =IF(I53>0,I53*3%,0) -> 22.6257 | K53: =M$2*F53 -> 6160.8598 | L53: =M$1*F53 -> 72720 | M53: =F$1*F53 -> 25068.809 | N53: =F$2*F53 -> 11341.549 | O53: =I$2*F53 -> 24240 | P53: =ROUND(SUM(I53:O53),0) + R53 -> 140308.81 | Q53: =ROUND(P53*3%,0) + P53 -> 144517.81 | R53: =ROUND(0.001+C53/100,2) -> 0.81
A54: 6 | B54: 13°B | C54: 82 | D54: Camila Finocchiaro | F54: 0.0139 | G54: 198850.82 | H54: =106170.82+89980.82+2699 -> 198850.64 | I54: =G54-H54 -> 0.18 | J54: =IF(I54>0,I54*3%,0) -> 0.0054 | K54: =M$2*F54 -> 4239.4035 | L54: =M$1*F54 -> 50040 | M54: =F$1*F54 -> 17250.319 | N54: =F$2*F54 -> 7804.3329 | O54: =I$2*F54 -> 16680 | P54: =ROUND(SUM(I54:O54),0) + R54 -> 96014.82 | Q54: =ROUND(P54*3%,0) + P54 -> 98894.82 | R54: =ROUND(0.001+C54/100,2) -> 0.82
A55: 6 | B55: 13°C | C55: 83 | D55: Maria Gabriela Diaz | E55: Clobas Ezequiel / Lencina mariana mabel | F55: 0.0139 | G55: 106170.83 | I55: =G55-H55 -> 106170.83 | J55: =IF(I55>0,I55*3%,0) -> 3185.1249 | K55: =M$2*F55 -> 4239.4035 | L55: =M$1*F55 -> 50040 | M55: =F$1*F55 -> 17250.319 | N55: =F$2*F55 -> 7804.3329 | O55: =I$2*F55 -> 16680 | P55: =ROUND(SUM(I55:O55),0) + R55 -> 205370.83 | Q55: =ROUND(P55*3%,0) + P55 -> 211531.83 | R55: =ROUND(0.001+C55/100,2) -> 0.83
A56: 6 | B56: 13°D | C56: 84 | D56: Fabiana Besteiro | F56: 0.0202 | G56: 154290.84 | H56: =134090.84 -> 134090.84 | I56: =G56-H56 -> 20200 | J56: =IF(I56>0,I56*3%,0) -> 606 | K56: =M$2*F56 -> 6160.8598 | L56: =M$1*F56 -> 72720 | M56: =F$1*F56 -> 25068.809 | N56: =F$2*F56 -> 11341.549 | O56: =I$2*F56 -> 24240 | P56: =ROUND(SUM(I56:O56),0) + R56 -> 160337.84 | Q56: =ROUND(P56*3%,0) + P56 -> 165147.84 | R56: =ROUND(0.001+C56/100,2) -> 0.84
A57: 7 | G57: 0 | L57: =M$1*F57 -> 0 | O57: =I$2*F57 -> 0 | P57: =ROUND(SUM(I57:O57),0) + R57 -> 0 | R57: =ROUND(0.001+C57/100,2) -> 0
A58: 7 | G58: 0 | L58: =M$1*F58 -> 0 | O58: =I$2*F58 -> 0 | P58: =ROUND(SUM(I58:O58),0) + R58 -> 0 | R58: =ROUND(0.001+C58/100,2) -> 0
A59: 7 | B59: P.B.1 | C59: 17 | D59: Antonio Carlos Caputo | E59: Barbara Bañon / Delia Martinez | F59: 0.0032 | G59: 24442.17 | H59: =23247.47-H72+2723 -> 24442.17 | I59: =G59-H59 -> 0 | J59: =IF(I59>0,I59*3%,0) -> 0 | K59: =M$2*F59 -> 975.97779 | L59: =M$1*F59 -> 11520 | M59: =F$1*F59 -> 3971.2965 | N59: =F$2*F59 -> 1796.681 | O59: =I$2*F59 -> 3840 | P59: =ROUND(SUM(I59:O59),0) + R59 -> 22104.17 | Q59: =ROUND(P59*3%,0) + P59 -> 22767.17 | R59: =ROUND(0.001+C59/100,2) -> 0.17
A60: 8 | B60: P.B.2 | C60: 18 | D60: Osvaldo Ricardo Colombo | F60: 0.0033 | G60: 142877.18 | I60: =G60-H60 -> 142877.18 | J60: =IF(I60>0,I60*3%,0) -> 4286.3154 | K60: =M$2*F60 -> 1006.4771 | L60: =M$1*F60 -> 11880 | M60: =F$1*F60 -> 4095.3995 | N60: =F$2*F60 -> 1852.8272 | O60: =I$2*F60 -> 3960 | P60: =ROUND(SUM(I60:O60),0) + R60 -> 169958.18 | Q60: =ROUND(P60*3%,0) + P60 -> 175057.18 | R60: =ROUND(0.001+C60/100,2) -> 0.18
A61: 8 | B61: P.B.3 | C61: 19 | D61: Fernando Saavedra | F61: 0.0004 | G61: 935.19 | I61: =G61-H61 -> 935.19 | J61: =IF(I61>0,I61*3%,0) -> 28.0557 | K61: =M$2*F61 -> 121.99722 | L61: =M$1*F61 -> 1440 | M61: =F$1*F61 -> 496.41206 | N61: =F$2*F61 -> 224.58512 | O61: =I$2*F61 -> 480 | P61: =ROUND(SUM(I61:O61),0) + R61 -> 3726.19 | Q61: =ROUND(P61*3%,0) + P61 -> 3838.19 | R61: =ROUND(0.001+C61/100,2) -> 0.19
A62: 8 | B62: P.B.4 | C62: 20 | D62: Fernando Saavedra | F62: 0.0002 | G62: 1528.2 | I62: =G62-H62 -> 1528.2 | J62: =IF(I62>0,I62*3%,0) -> 45.846 | K62: =M$2*F62 -> 60.998612 | L62: =M$1*F62 -> 720 | M62: =F$1*F62 -> 248.20603 | N62: =F$2*F62 -> 112.29256 | O62: =I$2*F62 -> 240 | P62: =ROUND(SUM(I62:O62),0) + R62 -> 2956.2 | Q62: =ROUND(P62*3%,0) + P62 -> 3045.2 | R62: =ROUND(0.001+C62/100,2) -> 0.2
A63: 9 | B63: P.B.5 | C63: 21 | D63: Ayelen Bárbara Kisch | E63: Claudia / Laura Avido | F63: 0.0002 | G63: 1528.21 | H63: =G63 -> 1528.21 | I63: =G63-H63 -> 0 | J63: =IF(I63>0,I63*3%,0) -> 0 | K63: =M$2*F63 -> 60.998612 | L63: =M$1*F63 -> 720 | M63: =F$1*F63 -> 248.20603 | N63: =F$2*F63 -> 112.29256 | O63: =I$2*F63 -> 240 | P63: =ROUND(SUM(I63:O63),0) + R63 -> 1381.21 | Q63: =ROUND(P63*3%,0) + P63 -> 1422.21 | R63: =ROUND(0.001+C63/100,2) -> 0.21
A64: 9 | B64: P.B.6 | C64: 22 | D64: Adrian Alejandro Pozo | F64: 0.0002 | G64: 1528.22 | I64: =G64-H64 -> 1528.22 | J64: =IF(I64>0,I64*3%,0) -> 45.8466 | K64: =M$2*F64 -> 60.998612 | L64: =M$1*F64 -> 720 | M64: =F$1*F64 -> 248.20603 | N64: =F$2*F64 -> 112.29256 | O64: =I$2*F64 -> 240 | P64: =ROUND(SUM(I64:O64),0) + R64 -> 2956.22 | Q64: =ROUND(P64*3%,0) + P64 -> 3045.22 | R64: =ROUND(0.001+C64/100,2) -> 0.22
A65: 9 | B65: P.B.7 | C65: 23 | D65: Javier Alejandro Panaccio | E65: Javier Enrique Zambrano | F65: 0.0002 | G65: 1528.23 | H65: =G65 -> 1528.23 | I65: =G65-H65 -> 0 | J65: =IF(I65>0,I65*3%,0) -> 0 | K65: =M$2*F65 -> 60.998612 | L65: =M$1*F65 -> 720 | M65: =F$1*F65 -> 248.20603 | N65: =F$2*F65 -> 112.29256 | O65: =I$2*F65 -> 240 | P65: =ROUND(SUM(I65:O65),0) + R65 -> 1381.23 | Q65: =ROUND(P65*3%,0) + P65 -> 1422.23 | R65: =ROUND(0.001+C65/100,2) -> 0.23
A66: 10 | B66: P.B.8 | C66: 24 | D66: Pedro Eugenio Negri | F66: 0.0002 | G66: 1528.24 | H66: =G66 -> 1528.24 | I66: =G66-H66 -> 0 | J66: =IF(I66>0,I66*3%,0) -> 0 | K66: =M$2*F66 -> 60.998612 | L66: =M$1*F66 -> 720 | M66: =F$1*F66 -> 248.20603 | N66: =F$2*F66 -> 112.29256 | O66: =I$2*F66 -> 240 | P66: =ROUND(SUM(I66:O66),0) + R66 -> 1381.24 | Q66: =ROUND(P66*3%,0) + P66 -> 1422.24 | R66: =ROUND(0.001+C66/100,2) -> 0.24
A67: 10 | B67: P.B.9 | C67: 25 | D67: Laura Natalia Carrillo | E67: Emiliano Calderon Alberto | F67: 0.0002 | G67: 1528.25 | H67: 1328.25 | I67: =G67-H67 -> 200 | J67: =IF(I67>0,I67*3%,0) -> 6 | K67: =M$2*F67 -> 60.998612 | L67: =M$1*F67 -> 720 | M67: =F$1*F67 -> 248.20603 | N67: =F$2*F67 -> 112.29256 | O67: =I$2*F67 -> 240 | P67: =ROUND(SUM(I67:O67),0) + R67 -> 1587.25 | Q67: =ROUND(P67*3%,0) + P67 -> 1635.25 | R67: =ROUND(0.001+C67/100,2) -> 0.25
A68: 10 | B68: P.B.10 | C68: 26 | D68: Jorge Antonio Mendiola | F68: 0.0002 | G68: 1489.26 | H68: 1289.26 | I68: =G68-H68 -> 200 | J68: =IF(I68>0,I68*3%,0) -> 6 | K68: =M$2*F68 -> 60.998612 | L68: =M$1*F68 -> 720 | M68: =F$1*F68 -> 248.20603 | N68: =F$2*F68 -> 112.29256 | O68: =I$2*F68 -> 240 | P68: =ROUND(SUM(I68:O68),0) + R68 -> 1587.26 | Q68: =ROUND(P68*3%,0) + P68 -> 1635.26 | R68: =ROUND(0.001+C68/100,2) -> 0.26
A69: 11 | B69: P.B.11 | C69: 27 | D69: García | F69: 0.0002 | G69: 10064.27 | I69: =G69-H69 -> 10064.27 | J69: =IF(I69>0,I69*3%,0) -> 301.9281 | K69: =M$2*F69 -> 60.998612 | L69: =M$1*F69 -> 720 | M69: =F$1*F69 -> 248.20603 | N69: =F$2*F69 -> 112.29256 | O69: =I$2*F69 -> 240 | P69: =ROUND(SUM(I69:O69),0) + R69 -> 11748.27 | Q69: =ROUND(P69*3%,0) + P69 -> 12100.27 | R69: =ROUND(0.001+C69/100,2) -> 0.27
A70: 11 | B70: P.B.12 | C70: 28 | D70: García | F70: 0.0002 | G70: 10064.28 | I70: =G70-H70 -> 10064.28 | J70: =IF(I70>0,I70*3%,0) -> 301.9284 | K70: =M$2*F70 -> 60.998612 | L70: =M$1*F70 -> 720 | M70: =F$1*F70 -> 248.20603 | N70: =F$2*F70 -> 112.29256 | O70: =I$2*F70 -> 240 | P70: =ROUND(SUM(I70:O70),0) + R70 -> 11748.28 | Q70: =ROUND(P70*3%,0) + P70 -> 12100.28 | R70: =ROUND(0.001+C70/100,2) -> 0.28
A71: 11 | B71: P.B.13 | C71: 29 | D71: Raul Boffi | E71: Dario Javier Flecha | F71: 0.0002 | G71: 2862.29 | H71: 2945.29 | I71: =G71-H71 -> -83 | J71: =IF(I71>0,I71*3%,0) -> 0 | K71: =M$2*F71 -> 60.998612 | L71: =M$1*F71 -> 720 | M71: =F$1*F71 -> 248.20603 | N71: =F$2*F71 -> 112.29256 | O71: =I$2*F71 -> 240 | P71: =ROUND(SUM(I71:O71),0) + R71 -> 1298.29 | Q71: =ROUND(P71*3%,0) + P71 -> 1337.29 | R71: =ROUND(0.001+C71/100,2) -> 0.29
B72: P.B.14 | C72: 30 | D72: Raul Boffi | E72: Barbara Bañon / Delia Martinez | F72: 0.0002 | G72: 1528.3 | H72: =G72 -> 1528.3 | I72: =G72-H72 -> 0 | J72: =IF(I72>0,I72*3%,0) -> 0 | K72: =M$2*F72 -> 60.998612 | L72: =M$1*F72 -> 720 | M72: =F$1*F72 -> 248.20603 | N72: =F$2*F72 -> 112.29256 | O72: =I$2*F72 -> 240 | P72: =ROUND(SUM(I72:O72),0) + R72 -> 1381.3 | Q72: =ROUND(P72*3%,0) + P72 -> 1422.3 | R72: =ROUND(0.001+C72/100,2) -> 0.3
B73: P.B.15 | C73: 31 | D73: Raul Boffi | F73: 0.0002 | G73: 3991.31 | I73: =G73-H73 -> 3991.31 | J73: =IF(I73>0,I73*3%,0) -> 119.7393 | K73: =M$2*F73 -> 60.998612 | L73: =M$1*F73 -> 720 | M73: =F$1*F73 -> 248.20603 | N73: =F$2*F73 -> 112.29256 | O73: =I$2*F73 -> 240 | P73: =ROUND(SUM(I73:O73),0) + R73 -> 5493.31 | Q73: =ROUND(P73*3%,0) + P73 -> 5658.31 | R73: =ROUND(0.001+C73/100,2) -> 0.31
B74: GALPON | C74: 32 | D74: Club Atlético Banfield | F74: 0.0158 | G74: 2242283.3 | I74: =G74-H74 -> 2242283.3 | J74: =IF(I74>0,I74*3%,0) -> 67268.5 | K74: =M$2*F74 -> 4818.8903 | L74: =M$1*F74 -> 56880 | M74: =F$1*F74 -> 19608.277 | N74: =F$2*F74 -> 8871.1122 | O74: =I$2*F74 -> 18960 | P74: =ROUND(SUM(I74:O74),0) + R74 -> 2418690.3 | Q74: =ROUND(P74*3%,0) + P74 -> 2491251.3 | R74: =ROUND(0.001+C74/100,2) -> 0.32
B75: S.S.16 | C75: 1 | D75: Antonio Carlos Caputo | F75: 0.0061 | G75: 233073.01 | I75: =G75-H75 -> 233073.01 | J75: =IF(I75>0,I75*3%,0) -> 6992.1903 | K75: =M$2*F75 -> 1860.4577 | L75: =M$1*F75 -> 21960 | M75: =F$1*F75 -> 7570.284 | N75: =F$2*F75 -> 3424.9231 | O75: =I$2*F75 -> 7320 | P75: =ROUND(SUM(I75:O75),0) + R75 -> 282201.01 | Q75: =ROUND(P75*3%,0) + P75 -> 290667.01 | R75: =ROUND(0.001+C75/100,2) -> 0.01
B76: S.S.17 | C76: 2 | D76: Jesica Romina Tobio | F76: 0.0064 | G76: 48884.02 | H76: =G76 -> 48884.02 | I76: =G76-H76 -> 0 | J76: =IF(I76>0,I76*3%,0) -> 0 | K76: =M$2*F76 -> 1951.9556 | L76: =M$1*F76 -> 23040 | M76: =F$1*F76 -> 7942.593 | N76: =F$2*F76 -> 3593.3619 | O76: =I$2*F76 -> 7680 | P76: =ROUND(SUM(I76:O76),0) + R76 -> 44208.02 | Q76: =ROUND(P76*3%,0) + P76 -> 45534.02 | R76: =ROUND(0.001+C76/100,2) -> 0.02
B77: S.S.18 | C77: 3 | D77: Diaz Laura Natalia | F77: 0.0057 | G77: 42430.03 | H77: =G77 -> 42430.03 | I77: =G77-H77 -> 0 | J77: =IF(I77>0,I77*3%,0) -> 0 | K77: =M$2*F77 -> 1738.4604 | L77: =M$1*F77 -> 20520 | M77: =F$1*F77 -> 7073.8719 | N77: =F$2*F77 -> 3200.338 | O77: =I$2*F77 -> 6840 | P77: =ROUND(SUM(I77:O77),0) + R77 -> 39373.03 | Q77: =ROUND(P77*3%,0) + P77 -> 40554.03 | R77: =ROUND(0.001+C77/100,2) -> 0.03
B78: S.S.19 | C78: 4 | D78: Juan Carlos Alonso | F78: 0.0053 | G78: 40482.04 | H78: =G78 -> 40482.04 | I78: =G78-H78 -> 0 | J78: =IF(I78>0,I78*3%,0) -> 0 | K78: =M$2*F78 -> 1616.4632 | L78: =M$1*F78 -> 19080 | M78: =F$1*F78 -> 6577.4598 | N78: =F$2*F78 -> 2975.7528 | O78: =I$2*F78 -> 6360 | P78: =ROUND(SUM(I78:O78),0) + R78 -> 36610.04 | Q78: =ROUND(P78*3%,0) + P78 -> 37708.04 | R78: =ROUND(0.001+C78/100,2) -> 0.04
B79: S.S.20 | C79: 5 | D79: Jose Luis Gurtubay | E79: Santiago Flores | F79: 0.0053 | G79: 40482.05 | I79: =G79-H79 -> 40482.05 | J79: =IF(I79>0,I79*3%,0) -> 1214.4615 | K79: =M$2*F79 -> 1616.4632 | L79: =M$1*F79 -> 19080 | M79: =F$1*F79 -> 6577.4598 | N79: =F$2*F79 -> 2975.7528 | O79: =I$2*F79 -> 6360 | P79: =ROUND(SUM(I79:O79),0) + R79 -> 78306.05 | Q79: =ROUND(P79*3%,0) + P79 -> 80655.05 | R79: =ROUND(0.001+C79/100,2) -> 0.05
B80: S.S.21 | C80: 6 | D80: Alejandro DI LEO - | E80: Claudia / Laura Avido | F80: 0.0053 | G80: 105752.06 | H80: =100452.06 -> 100452.06 | I80: =G80-H80 -> 5300 | J80: =IF(I80>0,I80*3%,0) -> 159 | K80: =M$2*F80 -> 1616.4632 | L80: =M$1*F80 -> 19080 | M80: =F$1*F80 -> 6577.4598 | N80: =F$2*F80 -> 2975.7528 | O80: =I$2*F80 -> 6360 | P80: =ROUND(SUM(I80:O80),0) + R80 -> 42069.06 | Q80: =ROUND(P80*3%,0) + P80 -> 43331.06 | R80: =ROUND(0.001+C80/100,2) -> 0.06 | S80: HABIA PAGADO LOS 5300, SU DEUDA DEBE ESTAR EN 0
A81: 12 | B81: S.S.22 | C81: 7 | D81: Karina Edith Mastandrea | E81: Ayelen Agustina | F81: 0.0053 | G81: 105752.07 | I81: =G81-H81 -> 105752.07 | J81: =IF(I81>0,I81*3%,0) -> 3172.5621 | K81: =M$2*F81 -> 1616.4632 | L81: =M$1*F81 -> 19080 | M81: =F$1*F81 -> 6577.4598 | N81: =F$2*F81 -> 2975.7528 | O81: =I$2*F81 -> 6360 | P81: =ROUND(SUM(I81:O81),0) + R81 -> 145534.07 | Q81: =ROUND(P81*3%,0) + P81 -> 149900.07 | R81: =ROUND(0.001+C81/100,2) -> 0.07
A82: 12 | B82: S.S.23 | C82: 8 | D82: Antonio Carlos Caputo | F82: 0.0053 | G82: 105752.08 | I82: =G82-H82 -> 105752.08 | J82: =IF(I82>0,I82*3%,0) -> 3172.5624 | K82: =M$2*F82 -> 1616.4632 | L82: =M$1*F82 -> 19080 | M82: =F$1*F82 -> 6577.4598 | N82: =F$2*F82 -> 2975.7528 | O82: =I$2*F82 -> 6360 | P82: =ROUND(SUM(I82:O82),0) + R82 -> 145534.08 | Q82: =ROUND(P82*3%,0) + P82 -> 149900.08 | R82: =ROUND(0.001+C82/100,2) -> 0.08
A83: 12 | B83: S.S.24 | C83: 9 | D83: Antonio Carlos Caputo | E83: =E44 -> Luz Maria Alberio | F83: 0.0053 | G83: 40482.09 | I83: =G83-H83 -> 40482.09 | J83: =IF(I83>0,I83*3%,0) -> 1214.4627 | K83: =M$2*F83 -> 1616.4632 | L83: =M$1*F83 -> 19080 | M83: =F$1*F83 -> 6577.4598 | N83: =F$2*F83 -> 2975.7528 | O83: =I$2*F83 -> 6360 | P83: =ROUND(SUM(I83:O83),0) + R83 -> 78306.09 | Q83: =ROUND(P83*3%,0) + P83 -> 80655.09 | R83: =ROUND(0.001+C83/100,2) -> 0.09
B84: S.S.25 | C84: 10 | D84: Antonio Carlos Caputo | F84: 0.0053 | G84: 199247.1 | I84: =G84-H84 -> 199247.1 | J84: =IF(I84>0,I84*3%,0) -> 5977.413 | K84: =M$2*F84 -> 1616.4632 | L84: =M$1*F84 -> 19080 | M84: =F$1*F84 -> 6577.4598 | N84: =F$2*F84 -> 2975.7528 | O84: =I$2*F84 -> 6360 | P84: =ROUND(SUM(I84:O84),0) + R84 -> 241834.1 | Q84: =ROUND(P84*3%,0) + P84 -> 249089.1 | R84: =ROUND(0.001+C84/100,2) -> 0.1
B85: S.S.26 | C85: 11 | D85: Antonio Carlos Caputo | E85: Santiago Tarragosa | F85: 0.0053 | G85: 158529.11 | H85: =28214*2+35181 -> 91609 | I85: =G85-H85 -> 66920.11 | J85: =IF(I85>0,I85*3%,0) -> 2007.6033 | K85: =M$2*F85 -> 1616.4632 | L85: =M$1*F85 -> 19080 | M85: =F$1*F85 -> 6577.4598 | N85: =F$2*F85 -> 2975.7528 | O85: =I$2*F85 -> 6360 | P85: =ROUND(SUM(I85:O85),0) + R85 -> 105537.11 | Q85: =ROUND(P85*3%,0) + P85 -> 108703.11 | R85: =ROUND(0.001+C85/100,2) -> 0.11
B86: S.S.27 | C86: 12 | D86: Fernando Andres Canepa | E86: Matias / Carla Esteves | F86: 0.0053 | G86: 40482.12 | H86: =G86 -> 40482.12 | I86: =G86-H86 -> 0 | J86: =IF(I86>0,I86*3%,0) -> 0 | K86: =M$2*F86 -> 1616.4632 | L86: =M$1*F86 -> 19080 | M86: =F$1*F86 -> 6577.4598 | N86: =F$2*F86 -> 2975.7528 | O86: =I$2*F86 -> 6360 | P86: =ROUND(SUM(I86:O86),0) + R86 -> 36610.12 | Q86: =ROUND(P86*3%,0) + P86 -> 37708.12 | R86: =ROUND(0.001+C86/100,2) -> 0.12
B87: S.S.28 | C87: 13 | D87: Juan Pablo Charpin | F87: 0.0053 | G87: 40482.13 | H87: =G87 -> 40482.13 | I87: =G87-H87 -> 0 | J87: =IF(I87>0,I87*3%,0) -> 0 | K87: =M$2*F87 -> 1616.4632 | L87: =M$1*F87 -> 19080 | M87: =F$1*F87 -> 6577.4598 | N87: =F$2*F87 -> 2975.7528 | O87: =I$2*F87 -> 6360 | P87: =ROUND(SUM(I87:O87),0) + R87 -> 36610.13 | Q87: =ROUND(P87*3%,0) + P87 -> 37708.13 | R87: =ROUND(0.001+C87/100,2) -> 0.13
B88: S.S.29 | C88: 14 | D88: Javier Alejandro Panaccio | E88: Malbares Gaston Emiliano | F88: 0.0053 | G88: 37978.14 | I88: =G88-H88 -> 37978.14 | J88: =IF(I88>0,I88*3%,0) -> 1139.3442 | K88: =M$2*F88 -> 1616.4632 | L88: =M$1*F88 -> 19080 | M88: =F$1*F88 -> 6577.4598 | N88: =F$2*F88 -> 2975.7528 | O88: =I$2*F88 -> 6360 | P88: =ROUND(SUM(I88:O88),0) + R88 -> 75727.14 | Q88: =ROUND(P88*3%,0) + P88 -> 77999.14 | R88: =ROUND(0.001+C88/100,2) -> 0.14
B89: S.S.30 | C89: 15 | D89: Hernán Gastón Padilla | E89: =E20 -> Armando Ezequiel Garro | F89: 0.0053 | G89: 40482.15 | H89: =G89 -> 40482.15 | I89: =G89-H89 -> 0 | J89: =IF(I89>0,I89*3%,0) -> 0 | K89: =M$2*F89 -> 1616.4632 | L89: =M$1*F89 -> 19080 | M89: =F$1*F89 -> 6577.4598 | N89: =F$2*F89 -> 2975.7528 | O89: =I$2*F89 -> 6360 | P89: =ROUND(SUM(I89:O89),0) + R89 -> 36610.15 | Q89: =ROUND(P89*3%,0) + P89 -> 37708.15 | R89: =ROUND(0.001+C89/100,2) -> 0.15
B90: S.S.31 | C90: 16 | D90: Domingo Alifraco | E90: Micaela Contreras | F90: 0.0062 | G90: 88696.16 | H90: =G90 -> 88696.16 | I90: =G90-H90 -> 0 | J90: =IF(I90>0,I90*3%,0) -> 0 | K90: =M$2*F90 -> 1890.957 | L90: =M$1*F90 -> 22320 | M90: =F$1*F90 -> 7694.387 | N90: =F$2*F90 -> 3481.0694 | O90: =I$2*F90 -> 7440 | P90: =ROUND(SUM(I90:O90),0) + R90 -> 42826.16 | Q90: =ROUND(P90*3%,0) + P90 -> 44111.16 | R90: =ROUND(0.001+C90/100,2) -> 0.16
F92: =SUM(F5:F91) -> 1 | G92: =SUM(G5:G91) -> 11779914 | H92: =SUM(H5:H91) -> 6723784.4 | I92: =SUM(I5:I91) -> 5056129.3 | J92: =SUM(J5:J91) -> 155048.49 | K92: =SUM(K5:K91) -> 304993.06 | L92: =SUM(L5:L91) -> 3600000 | M92: =SUM(M5:M90) -> 1241030.2 | N92: =SUM(N5:N90) -> 561462.8 | O92: =SUM(O5:O90) -> 1200000 | P92: =SUM(P5:P91) -> 12118693 | Q92: =SUM(Q5:Q91) -> 12482247
D95: =RESUMEN!A13 -> ESTIMADOS PROPIETARIOS E INQUILINOS: POR FAVOR LOS QUE ABONAN EN PRIMER VENCIMIENTO ABONEN EL MONTO DE PRIMER VENCIMIENTO, ASI AGILIZAN LA LIQUIDACION, LES PEDIMOS ENCARECIDAMENTE QUE RESPETEN LOS CENTAVOS CORRESPONDIENTES A LA UNIDAD FUNCIONAL. ES DE CARÁCTER OBLIGATORIO INFORMAR VIA MAIL LAS EXPENSAS.

Sheet anotaciones 
D4: LA COCHERA S.S31 DE MICAELA CONTRERAS ESTABA ABONADA EL MES PASADO CON UN MONTO DE 91,358 , SIN EMBARGO ESE MONTO LO PUSIMOS EN LA UF 60 COMO DINERO A FAVOR, CORREGIR ESO
D8: AGUSTINA AYELEN MARTINEZ PAGA EK 8D Y LA COCHERA S.S 22, DESDE SIEMPRE LE PONEMOS PAGO EL 8D PERO COMO NO SABIAMOS QUE TAMBIEN PAGA LA COCHERA S.S 22 LA COCHERA LE QUEDABA IMPAGA, RASTREAR LOS PAGOS Y RESTAR LO NECESARIO
D12: QUE QUEDE SIN DEUDA
D15: PABLO PLEBS TIENE UNA TRANSFERENCIA DE $91.922,35 EN ABRIL QUE NO SE LA IMPUTAMOS NUNCA (NI COMO TRANSF NO IDENTIDICADA) POR ENDE NO DEBE TENER DEUDA ALGUNA - ES MAS, SEGÚN ROMI EL PAGO (ESTE MES, EN JUNIO) 119 MIL Y PICO, POR ENDE LE DEBE QUEDAR DINERO A FAVOR
D18: hay que agregar a luzalberio@gmail.com a la cadena, es nueva inquilina del 10D
D21: el mes pasado quedo debiendo 5,300$ cuando es incorrecto, debe quedar sin deuda (si es que este mes abono)
