Workbook

Sheet Gastos
D3: Cel. | E3: 1153202676 - Horarios de atencion: Lunes a Viernes de 10hs a 16hs
D4: e-mail: | E4: consorciobelgrano1328@gmail.com
D5: Administradora: CAROLINA CANCIANI
D6: CUIT Administradora: | E6: 27231256879 | G6: MP 1148
D7: Doctor Melo 2958 - Lanus Oeste - Piso 8 - con cita previa
A8: LIQUIDACION DE EXPENSAS | C8: PERIODO: MAYO | G8: 1ER VTO: 16/06
A9: CONSORCIO: ADMINISTRACION DE CONSORCIOS RC
A12: 1- SUELDO ENCARGADA
A13: SUELDO - REMUNERACIONES SUJETAS A RETENCION | H13: 494448
A14: REDONDEO | H14: 0.88
A15: DEDUCCIONES | H15: -122375.88
A16: TOTAL | H16: =SUM(H13:H15) -> 372073
A17: BONOS Y AJUSTES
A18: Gratificacion anual | H18: 0
A19: Deducciones | H19: 0
A20: Ajuste MAYO 2023 | H20: 0
A21: Deducciones | H21: 0
A22: Ajuste MAYO 2023 | H22: 0
A23: Deducciones | H23: 0
A24: TOTAL | H24: =SUM(H18:H23) -> 0
A25: SAC MAYO
A28: TOTAL SAC | H28: =SUM(H26:H27) -> 0
A29: 2-CARGAS SOCIALES
A30: SUTHER | B30: NO SE DEBITA | H30: 17301.4
A31: FATHERY | B31: NO SE DEBITA | H31: 49790.91
A32: SERACARH | B32: NO SE DEBITA | H32: 1922.38
A33: SUTHER | H33: 56139.12
A34: FATHERY | H34: 2472.24
A35: SERACARH | H35: 22250.16
A36: SEGURO SRA EVA | B36: FEDERACION PATRONAL - ACCIDENTE DE RIESGOS PERSONALES | H36: 5712
A37: ARCA | H37: 245128.34
A38: TOTAL | H38: =SUM(H30:H37) -> 400716.55
A39: 3- SERVICIOS
A40: AYSA - NRO. DE CUENTA 297930 - Vto. 1/04 | H40: 382405.71
A41: AYSA - NRO. DE CUENTA 297930 - Vto. 28/04 | H41: 381241.28
A42: CABLEVISION - NRO DE REFERENCIA 0477093152678 | H42: 19443.71
A43: EDESUR - CLIENTE NRO 01408557 | H43: 529266.62
A44: TOTAL | H44: =SUM(H40:H43) -> 1312357.3
A45: 4- MANTENIMIENTO DE PARTES COMUNES
A46: LEMA MANTENIMIENTO DE ASCENSORES | D46: MES DE MAYO | H46: 72800
A47: LEMA ASCENSORES - TRABAJOS REALIZACOS EN LOS CASCOS GUIADORES EN EL UNICO ASCENSOR DE LA PARTE SUPERIOR DE LA CABINA | H47: 160000
A48: REPARACION PERDIDA DE BAÑERA PISO 10B - MANO DE OBRA Y MATERIALES | H48: 360000
A49: FUMIGACION - SERVICIO | H49: 55000
A50: LAURA | H50: 20000
A51: ESTER | H51: 54999.05
A52: DARIO ARREGLA PUERTAS DE GAS | H52: 65000
A53: JPL ARTICULOS DE LIMPIEZA | H53: 106700
A54: ELECTRICIDAD LOMAS - ABONO GRUPO MAYO | H54: 60000
A55: SALVATIERRA - REPASO D ECOLUMNA DE BAÑO EN UF 10 | H55: 27300
A56: SALVATIERRA - DESOBSTRUCCION DE COLUMNA EN COCINA 3A | H56: 18500
A57: TOTAL | H57: =SUM(H46:H56) -> 1000299.1
A58: 5 - GASTO DE ADMINISTRACION
A59: ADMINISTRACION HONORARIOS | H59: 55995
A60: GUSTAVO PADRON - SR CONTADOR - TRAMITES INSCRIPCION CONSORCIO ARCA | H60: 100000
A61: GUSTAVO PADRON - SR CONTADOR | H61: 28000
A62: TOTAL | H62: =SUM(H59:H61) -> 183995
A63: 6- GASTOS BANCARIOS
A64: GASTOS BANCARIOS | H64: 32718.38
A66: TOTAL | H66: =SUM(H64:H65) -> 32718.38
A67: 7- SEGUROS OBLIGATORIOS
A68: MERCANTIL ANDINA - POLIZA DE SEGURO - NRO. 174612 | H68: 59038.23
A70: TOTAL | H70: =SUM(H68:H69) -> 59038.23
A72: GASTOS EXTRAORDINARIOS
H75: 0
H76: 0
H77: 0
A78: TOTAL | H78: =SUM(H73:H77) -> 0
A80: TOTAL GASTOS EXTRAORDINARIOS: | H80: =H78 -> 0
A81: FONDO DE GASTOS ORDINARIOS
A82: FONDO DE GASTOS EXTRAORDINARIOS
A83: TOTAL GASTOS ORDINARIOS | H83: =H70+H66+H62+H57+H44+H24+H16+H28+H38 -> 3361197.5
A84: GASTOS ORDINARIOS + FONDO DE RESERVA (GASTOS A PRORRATEAR) | H84: =H83+H81 -> 3361197.5
A85: GASTOS EXTRAORDINARIOS + FONDO DE RESERVA EXT (A PRORRATEAR COMO EXTRAORD) | H85: =H80+H82 -> 0
A86: TOTAL EGRESOS DE GAST ORD Y EXT | H86: =H83+H80 -> 3361197.5
A87: TOTAL GASTOS EXTRAORDINARIOS (B): | H87: 0
A92: ESTADO FINANCIERO
A93: Saldo anterior | H93: 900085.1
A94: Ingreso por pago de Expensas | H94: =Planilla!G44 -> 1613089.5
A97: Ingreso correspondiente a la caja SUM | H97: =-H103 -> 0
A98: Egresos por gastos mes ordinarios | H98: =-H83 -> -3361197.5
A100: Saldo al cierre | H100: =SUM(H93:H99) -> -848022.91
A101: CAJA SUM | CC101: CAJA DOLARES | CK101: CAJA DOLARES | CS101: CAJA DOLARES | DA101: CAJA DOLARES | DI101: CAJA DOLARES | DQ101: CAJA DOLARES | DY101: CAJA DOLARES | EG101: CAJA DOLARES | EO101: CAJA DOLARES | EW101: CAJA DOLARES | FE101: CAJA DOLARES | FM101: CAJA DOLARES | FU101: CAJA DOLARES | GC101: CAJA DOLARES | GK101: CAJA DOLARES | GS101: CAJA DOLARES | HA101: CAJA DOLARES | HI101: CAJA DOLARES | HQ101: CAJA DOLARES | HY101: CAJA DOLARES | IG101: CAJA DOLARES | IO101: CAJA DOLARES | IW101: CAJA DOLARES | JE101: CAJA DOLARES | JM101: CAJA DOLARES | JU101: CAJA DOLARES | KC101: CAJA DOLARES | KK101: CAJA DOLARES | KS101: CAJA DOLARES | LA101: CAJA DOLARES | LI101: CAJA DOLARES | LQ101: CAJA DOLARES | LY101: CAJA DOLARES | MG101: CAJA DOLARES | MO101: CAJA DOLARES | MW101: CAJA DOLARES | NE101: CAJA DOLARES | NM101: CAJA DOLARES | NU101: CAJA DOLARES | OC101: CAJA DOLARES | OK101: CAJA DOLARES | OS101: CAJA DOLARES | PA101: CAJA DOLARES | PI101: CAJA DOLARES | PQ101: CAJA DOLARES | PY101: CAJA DOLARES | QG101: CAJA DOLARES | QO101: CAJA DOLARES | QW101: CAJA DOLARES | RE101: CAJA DOLARES | RM101: CAJA DOLARES | RU101: CAJA DOLARES | SC101: CAJA DOLARES | SK101: CAJA DOLARES | SS101: CAJA DOLARES | TA101: CAJA DOLARES | TI101: CAJA DOLARES | TQ101: CAJA DOLARES | TY101: CAJA DOLARES | UG101: CAJA DOLARES | UO101: CAJA DOLARES | UW101: CAJA DOLARES | VE101: CAJA DOLARES | VM101: CAJA DOLARES | VU101: CAJA DOLARES | WC101: CAJA DOLARES | WK101: CAJA DOLARES | WS101: CAJA DOLARES | XA101: CAJA DOLARES | XI101: CAJA DOLARES | XQ101: CAJA DOLARES | XY101: CAJA DOLARES | YG101: CAJA DOLARES | YO101: CAJA DOLARES | YW101: CAJA DOLARES | ZE101: CAJA DOLARES | ZM101: CAJA DOLARES | ZU101: CAJA DOLARES | AAC101: CAJA DOLARES | AAK101: CAJA DOLARES | AAS101: CAJA DOLARES | ABA101: CAJA DOLARES | ABI101: CAJA DOLARES | ABQ101: CAJA DOLARES | ABY101: CAJA DOLARES | ACG101: CAJA DOLARES | ACO101: CAJA DOLARES | ACW101: CAJA DOLARES | ADE101: CAJA DOLARES | ADM101: CAJA DOLARES | ADU101: CAJA DOLARES | AEC101: CAJA DOLARES | AEK101: CAJA DOLARES | AES101: CAJA DOLARES | AFA101: CAJA DOLARES | AFI101: CAJA DOLARES | AFQ101: CAJA DOLARES | AFY101: CAJA DOLARES | AGG101: CAJA DOLARES | AGO101: CAJA DOLARES | AGW101: CAJA DOLARES | AHE101: CAJA DOLARES | AHM101: CAJA DOLARES | AHU101: CAJA DOLARES | AIC101: CAJA DOLARES | AIK101: CAJA DOLARES | AIS101: CAJA DOLARES | AJA101: CAJA DOLARES | AJI101: CAJA DOLARES | AJQ101: CAJA DOLARES | AJY101: CAJA DOLARES | AKG101: CAJA DOLARES | AKO101: CAJA DOLARES | AKW101: CAJA DOLARES | ALE101: CAJA DOLARES | ALM101: CAJA DOLARES | ALU101: CAJA DOLARES | AMC101: CAJA DOLARES | AMK101: CAJA DOLARES | AMS101: CAJA DOLARES | ANA101: CAJA DOLARES | ANI101: CAJA DOLARES | ANQ101: CAJA DOLARES | ANY101: CAJA DOLARES | AOG101: CAJA DOLARES | AOO101: CAJA DOLARES | AOW101: CAJA DOLARES | APE101: CAJA DOLARES | APM101: CAJA DOLARES | APU101: CAJA DOLARES | AQC101: CAJA DOLARES | AQK101: CAJA DOLARES | AQS101: CAJA DOLARES | ARA101: CAJA DOLARES | ARI101: CAJA DOLARES | ARQ101: CAJA DOLARES | ARY101: CAJA DOLARES | ASG101: CAJA DOLARES | ASO101: CAJA DOLARES | ASW101: CAJA DOLARES | ATE101: CAJA DOLARES | ATM101: CAJA DOLARES | ATU101: CAJA DOLARES | AUC101: CAJA DOLARES | AUK101: CAJA DOLARES | AUS101: CAJA DOLARES | AVA101: CAJA DOLARES | AVI101: CAJA DOLARES | AVQ101: CAJA DOLARES | AVY101: CAJA DOLARES | AWG101: CAJA DOLARES | AWO101: CAJA DOLARES | AWW101: CAJA DOLARES | AXE101: CAJA DOLARES | AXM101: CAJA DOLARES | AXU101: CAJA DOLARES | AYC101: CAJA DOLARES | AYK101: CAJA DOLARES | AYS101: CAJA DOLARES | AZA101: CAJA DOLARES | AZI101: CAJA DOLARES | AZQ101: CAJA DOLARES | AZY101: CAJA DOLARES | BAG101: CAJA DOLARES | BAO101: CAJA DOLARES | BAW101: CAJA DOLARES | BBE101: CAJA DOLARES | BBM101: CAJA DOLARES | BBU101: CAJA DOLARES | BCC101: CAJA DOLARES | BCK101: CAJA DOLARES | BCS101: CAJA DOLARES | BDA101: CAJA DOLARES | BDI101: CAJA DOLARES | BDQ101: CAJA DOLARES | BDY101: CAJA DOLARES | BEG101: CAJA DOLARES | BEO101: CAJA DOLARES | BEW101: CAJA DOLARES | BFE101: CAJA DOLARES | BFM101: CAJA DOLARES | BFU101: CAJA DOLARES | BGC101: CAJA DOLARES | BGK101: CAJA DOLARES | BGS101: CAJA DOLARES | BHA101: CAJA DOLARES | BHI101: CAJA DOLARES | BHQ101: CAJA DOLARES | BHY101: CAJA DOLARES | BIG101: CAJA DOLARES | BIO101: CAJA DOLARES | BIW101: CAJA DOLARES | BJE101: CAJA DOLARES | BJM101: CAJA DOLARES | BJU101: CAJA DOLARES | BKC101: CAJA DOLARES | BKK101: CAJA DOLARES | BKS101: CAJA DOLARES | BLA101: CAJA DOLARES | BLI101: CAJA DOLARES | BLQ101: CAJA DOLARES | BLY101: CAJA DOLARES | BMG101: CAJA DOLARES | BMO101: CAJA DOLARES | BMW101: CAJA DOLARES | BNE101: CAJA DOLARES | BNM101: CAJA DOLARES | BNU101: CAJA DOLARES | BOC101: CAJA DOLARES | BOK101: CAJA DOLARES | BOS101: CAJA DOLARES | BPA101: CAJA DOLARES | BPI101: CAJA DOLARES | BPQ101: CAJA DOLARES | BPY101: CAJA DOLARES | BQG101: CAJA DOLARES | BQO101: CAJA DOLARES | BQW101: CAJA DOLARES | BRE101: CAJA DOLARES | BRM101: CAJA DOLARES | BRU101: CAJA DOLARES | BSC101: CAJA DOLARES | BSK101: CAJA DOLARES | BSS101: CAJA DOLARES | BTA101: CAJA DOLARES | BTI101: CAJA DOLARES | BTQ101: CAJA DOLARES | BTY101: CAJA DOLARES | BUG101: CAJA DOLARES | BUO101: CAJA DOLARES | BUW101: CAJA DOLARES | BVE101: CAJA DOLARES | BVM101: CAJA DOLARES | BVU101: CAJA DOLARES | BWC101: CAJA DOLARES | BWK101: CAJA DOLARES | BWS101: CAJA DOLARES | BXA101: CAJA DOLARES | BXI101: CAJA DOLARES | BXQ101: CAJA DOLARES | BXY101: CAJA DOLARES | BYG101: CAJA DOLARES | BYO101: CAJA DOLARES | BYW101: CAJA DOLARES | BZE101: CAJA DOLARES | BZM101: CAJA DOLARES | BZU101: CAJA DOLARES | CAC101: CAJA DOLARES | CAK101: CAJA DOLARES | CAS101: CAJA DOLARES | CBA101: CAJA DOLARES | CBI101: CAJA DOLARES | CBQ101: CAJA DOLARES | CBY101: CAJA DOLARES | CCG101: CAJA DOLARES | CCO101: CAJA DOLARES | CCW101: CAJA DOLARES | CDE101: CAJA DOLARES | CDM101: CAJA DOLARES | CDU101: CAJA DOLARES | CEC101: CAJA DOLARES | CEK101: CAJA DOLARES | CES101: CAJA DOLARES | CFA101: CAJA DOLARES | CFI101: CAJA DOLARES | CFQ101: CAJA DOLARES | CFY101: CAJA DOLARES | CGG101: CAJA DOLARES | CGO101: CAJA DOLARES | CGW101: CAJA DOLARES | CHE101: CAJA DOLARES | CHM101: CAJA DOLARES | CHU101: CAJA DOLARES | CIC101: CAJA DOLARES | CIK101: CAJA DOLARES | CIS101: CAJA DOLARES | CJA101: CAJA DOLARES | CJI101: CAJA DOLARES | CJQ101: CAJA DOLARES | CJY101: CAJA DOLARES | CKG101: CAJA DOLARES | CKO101: CAJA DOLARES | CKW101: CAJA DOLARES | CLE101: CAJA DOLARES | CLM101: CAJA DOLARES | CLU101: CAJA DOLARES | CMC101: CAJA DOLARES | CMK101: CAJA DOLARES | CMS101: CAJA DOLARES | CNA101: CAJA DOLARES | CNI101: CAJA DOLARES | CNQ101: CAJA DOLARES | CNY101: CAJA DOLARES | COG101: CAJA DOLARES | COO101: CAJA DOLARES | COW101: CAJA DOLARES | CPE101: CAJA DOLARES | CPM101: CAJA DOLARES | CPU101: CAJA DOLARES | CQC101: CAJA DOLARES | CQK101: CAJA DOLARES | CQS101: CAJA DOLARES | CRA101: CAJA DOLARES | CRI101: CAJA DOLARES | CRQ101: CAJA DOLARES | CRY101: CAJA DOLARES | CSG101: CAJA DOLARES | CSO101: CAJA DOLARES | CSW101: CAJA DOLARES | CTE101: CAJA DOLARES | CTM101: CAJA DOLARES | CTU101: CAJA DOLARES | CUC101: CAJA DOLARES | CUK101: CAJA DOLARES | CUS101: CAJA DOLARES | CVA101: CAJA DOLARES | CVI101: CAJA DOLARES | CVQ101: CAJA DOLARES | CVY101: CAJA DOLARES | CWG101: CAJA DOLARES | CWO101: CAJA DOLARES | CWW101: CAJA DOLARES | CXE101: CAJA DOLARES | CXM101: CAJA DOLARES | CXU101: CAJA DOLARES | CYC101: CAJA DOLARES | CYK101: CAJA DOLARES | CYS101: CAJA DOLARES | CZA101: CAJA DOLARES | CZI101: CAJA DOLARES | CZQ101: CAJA DOLARES | CZY101: CAJA DOLARES | DAG101: CAJA DOLARES | DAO101: CAJA DOLARES | DAW101: CAJA DOLARES | DBE101: CAJA DOLARES | DBM101: CAJA DOLARES | DBU101: CAJA DOLARES | DCC101: CAJA DOLARES | DCK101: CAJA DOLARES | DCS101: CAJA DOLARES | DDA101: CAJA DOLARES | DDI101: CAJA DOLARES | DDQ101: CAJA DOLARES | DDY101: CAJA DOLARES | DEG101: CAJA DOLARES | DEO101: CAJA DOLARES | DEW101: CAJA DOLARES | DFE101: CAJA DOLARES | DFM101: CAJA DOLARES | DFU101: CAJA DOLARES | DGC101: CAJA DOLARES | DGK101: CAJA DOLARES | DGS101: CAJA DOLARES | DHA101: CAJA DOLARES | DHI101: CAJA DOLARES | DHQ101: CAJA DOLARES | DHY101: CAJA DOLARES | DIG101: CAJA DOLARES | DIO101: CAJA DOLARES | DIW101: CAJA DOLARES | DJE101: CAJA DOLARES | DJM101: CAJA DOLARES | DJU101: CAJA DOLARES | DKC101: CAJA DOLARES | DKK101: CAJA DOLARES | DKS101: CAJA DOLARES | DLA101: CAJA DOLARES | DLI101: CAJA DOLARES | DLQ101: CAJA DOLARES | DLY101: CAJA DOLARES | DMG101: CAJA DOLARES | DMO101: CAJA DOLARES | DMW101: CAJA DOLARES | DNE101: CAJA DOLARES | DNM101: CAJA DOLARES | DNU101: CAJA DOLARES | DOC101: CAJA DOLARES | DOK101: CAJA DOLARES | DOS101: CAJA DOLARES | DPA101: CAJA DOLARES | DPI101: CAJA DOLARES | DPQ101: CAJA DOLARES | DPY101: CAJA DOLARES | DQG101: CAJA DOLARES | DQO101: CAJA DOLARES | DQW101: CAJA DOLARES | DRE101: CAJA DOLARES | DRM101: CAJA DOLARES | DRU101: CAJA DOLARES | DSC101: CAJA DOLARES | DSK101: CAJA DOLARES | DSS101: CAJA DOLARES | DTA101: CAJA DOLARES | DTI101: CAJA DOLARES | DTQ101: CAJA DOLARES | DTY101: CAJA DOLARES | DUG101: CAJA DOLARES | DUO101: CAJA DOLARES | DUW101: CAJA DOLARES | DVE101: CAJA DOLARES | DVM101: CAJA DOLARES | DVU101: CAJA DOLARES | DWC101: CAJA DOLARES | DWK101: CAJA DOLARES | DWS101: CAJA DOLARES | DXA101: CAJA DOLARES | DXI101: CAJA DOLARES | DXQ101: CAJA DOLARES | DXY101: CAJA DOLARES | DYG101: CAJA DOLARES | DYO101: CAJA DOLARES | DYW101: CAJA DOLARES | DZE101: CAJA DOLARES | DZM101: CAJA DOLARES | DZU101: CAJA DOLARES | EAC101: CAJA DOLARES | EAK101: CAJA DOLARES | EAS101: CAJA DOLARES | EBA101: CAJA DOLARES | EBI101: CAJA DOLARES | EBQ101: CAJA DOLARES | EBY101: CAJA DOLARES | ECG101: CAJA DOLARES | ECO101: CAJA DOLARES | ECW101: CAJA DOLARES | EDE101: CAJA DOLARES | EDM101: CAJA DOLARES | EDU101: CAJA DOLARES | EEC101: CAJA DOLARES | EEK101: CAJA DOLARES | EES101: CAJA DOLARES | EFA101: CAJA DOLARES | EFI101: CAJA DOLARES | EFQ101: CAJA DOLARES | EFY101: CAJA DOLARES | EGG101: CAJA DOLARES | EGO101: CAJA DOLARES | EGW101: CAJA DOLARES | EHE101: CAJA DOLARES | EHM101: CAJA DOLARES | EHU101: CAJA DOLARES | EIC101: CAJA DOLARES | EIK101: CAJA DOLARES | EIS101: CAJA DOLARES | EJA101: CAJA DOLARES | EJI101: CAJA DOLARES | EJQ101: CAJA DOLARES | EJY101: CAJA DOLARES | EKG101: CAJA DOLARES | EKO101: CAJA DOLARES | EKW101: CAJA DOLARES | ELE101: CAJA DOLARES | ELM101: CAJA DOLARES | ELU101: CAJA DOLARES | EMC101: CAJA DOLARES | EMK101: CAJA DOLARES | EMS101: CAJA DOLARES | ENA101: CAJA DOLARES | ENI101: CAJA DOLARES | ENQ101: CAJA DOLARES | ENY101: CAJA DOLARES | EOG101: CAJA DOLARES | EOO101: CAJA DOLARES | EOW101: CAJA DOLARES | EPE101: CAJA DOLARES | EPM101: CAJA DOLARES | EPU101: CAJA DOLARES | EQC101: CAJA DOLARES | EQK101: CAJA DOLARES | EQS101: CAJA DOLARES | ERA101: CAJA DOLARES | ERI101: CAJA DOLARES | ERQ101: CAJA DOLARES | ERY101: CAJA DOLARES | ESG101: CAJA DOLARES | ESO101: CAJA DOLARES | ESW101: CAJA DOLARES | ETE101: CAJA DOLARES | ETM101: CAJA DOLARES | ETU101: CAJA DOLARES | EUC101: CAJA DOLARES | EUK101: CAJA DOLARES | EUS101: CAJA DOLARES | EVA101: CAJA DOLARES | EVI101: CAJA DOLARES | EVQ101: CAJA DOLARES | EVY101: CAJA DOLARES | EWG101: CAJA DOLARES | EWO101: CAJA DOLARES | EWW101: CAJA DOLARES | EXE101: CAJA DOLARES | EXM101: CAJA DOLARES | EXU101: CAJA DOLARES | EYC101: CAJA DOLARES | EYK101: CAJA DOLARES | EYS101: CAJA DOLARES | EZA101: CAJA DOLARES | EZI101: CAJA DOLARES | EZQ101: CAJA DOLARES | EZY101: CAJA DOLARES | FAG101: CAJA DOLARES | FAO101: CAJA DOLARES | FAW101: CAJA DOLARES | FBE101: CAJA DOLARES | FBM101: CAJA DOLARES | FBU101: CAJA DOLARES | FCC101: CAJA DOLARES | FCK101: CAJA DOLARES | FCS101: CAJA DOLARES | FDA101: CAJA DOLARES | FDI101: CAJA DOLARES | FDQ101: CAJA DOLARES | FDY101: CAJA DOLARES | FEG101: CAJA DOLARES | FEO101: CAJA DOLARES | FEW101: CAJA DOLARES | FFE101: CAJA DOLARES | FFM101: CAJA DOLARES | FFU101: CAJA DOLARES | FGC101: CAJA DOLARES | FGK101: CAJA DOLARES | FGS101: CAJA DOLARES | FHA101: CAJA DOLARES | FHI101: CAJA DOLARES | FHQ101: CAJA DOLARES | FHY101: CAJA DOLARES | FIG101: CAJA DOLARES | FIO101: CAJA DOLARES | FIW101: CAJA DOLARES | FJE101: CAJA DOLARES | FJM101: CAJA DOLARES | FJU101: CAJA DOLARES | FKC101: CAJA DOLARES | FKK101: CAJA DOLARES | FKS101: CAJA DOLARES | FLA101: CAJA DOLARES | FLI101: CAJA DOLARES | FLQ101: CAJA DOLARES | FLY101: CAJA DOLARES | FMG101: CAJA DOLARES | FMO101: CAJA DOLARES | FMW101: CAJA DOLARES | FNE101: CAJA DOLARES | FNM101: CAJA DOLARES | FNU101: CAJA DOLARES | FOC101: CAJA DOLARES | FOK101: CAJA DOLARES | FOS101: CAJA DOLARES | FPA101: CAJA DOLARES | FPI101: CAJA DOLARES | FPQ101: CAJA DOLARES | FPY101: CAJA DOLARES | FQG101: CAJA DOLARES | FQO101: CAJA DOLARES | FQW101: CAJA DOLARES | FRE101: CAJA DOLARES | FRM101: CAJA DOLARES | FRU101: CAJA DOLARES | FSC101: CAJA DOLARES | FSK101: CAJA DOLARES | FSS101: CAJA DOLARES | FTA101: CAJA DOLARES | FTI101: CAJA DOLARES | FTQ101: CAJA DOLARES | FTY101: CAJA DOLARES | FUG101: CAJA DOLARES | FUO101: CAJA DOLARES | FUW101: CAJA DOLARES | FVE101: CAJA DOLARES | FVM101: CAJA DOLARES | FVU101: CAJA DOLARES | FWC101: CAJA DOLARES | FWK101: CAJA DOLARES | FWS101: CAJA DOLARES | FXA101: CAJA DOLARES | FXI101: CAJA DOLARES | FXQ101: CAJA DOLARES | FXY101: CAJA DOLARES | FYG101: CAJA DOLARES | FYO101: CAJA DOLARES | FYW101: CAJA DOLARES | FZE101: CAJA DOLARES | FZM101: CAJA DOLARES | FZU101: CAJA DOLARES | GAC101: CAJA DOLARES | GAK101: CAJA DOLARES | GAS101: CAJA DOLARES | GBA101: CAJA DOLARES | GBI101: CAJA DOLARES | GBQ101: CAJA DOLARES | GBY101: CAJA DOLARES | GCG101: CAJA DOLARES | GCO101: CAJA DOLARES | GCW101: CAJA DOLARES | GDE101: CAJA DOLARES | GDM101: CAJA DOLARES | GDU101: CAJA DOLARES | GEC101: CAJA DOLARES | GEK101: CAJA DOLARES | GES101: CAJA DOLARES | GFA101: CAJA DOLARES | GFI101: CAJA DOLARES | GFQ101: CAJA DOLARES | GFY101: CAJA DOLARES | GGG101: CAJA DOLARES | GGO101: CAJA DOLARES | GGW101: CAJA DOLARES | GHE101: CAJA DOLARES | GHM101: CAJA DOLARES | GHU101: CAJA DOLARES | GIC101: CAJA DOLARES | GIK101: CAJA DOLARES | GIS101: CAJA DOLARES | GJA101: CAJA DOLARES | GJI101: CAJA DOLARES | GJQ101: CAJA DOLARES | GJY101: CAJA DOLARES | GKG101: CAJA DOLARES | GKO101: CAJA DOLARES | GKW101: CAJA DOLARES | GLE101: CAJA DOLARES | GLM101: CAJA DOLARES | GLU101: CAJA DOLARES | GMC101: CAJA DOLARES | GMK101: CAJA DOLARES | GMS101: CAJA DOLARES | GNA101: CAJA DOLARES | GNI101: CAJA DOLARES | GNQ101: CAJA DOLARES | GNY101: CAJA DOLARES | GOG101: CAJA DOLARES | GOO101: CAJA DOLARES | GOW101: CAJA DOLARES | GPE101: CAJA DOLARES | GPM101: CAJA DOLARES | GPU101: CAJA DOLARES | GQC101: CAJA DOLARES | GQK101: CAJA DOLARES | GQS101: CAJA DOLARES | GRA101: CAJA DOLARES | GRI101: CAJA DOLARES | GRQ101: CAJA DOLARES | GRY101: CAJA DOLARES | GSG101: CAJA DOLARES | GSO101: CAJA DOLARES | GSW101: CAJA DOLARES | GTE101: CAJA DOLARES | GTM101: CAJA DOLARES | GTU101: CAJA DOLARES | GUC101: CAJA DOLARES | GUK101: CAJA DOLARES | GUS101: CAJA DOLARES | GVA101: CAJA DOLARES | GVI101: CAJA DOLARES | GVQ101: CAJA DOLARES | GVY101: CAJA DOLARES | GWG101: CAJA DOLARES | GWO101: CAJA DOLARES | GWW101: CAJA DOLARES | GXE101: CAJA DOLARES | GXM101: CAJA DOLARES | GXU101: CAJA DOLARES | GYC101: CAJA DOLARES | GYK101: CAJA DOLARES | GYS101: CAJA DOLARES | GZA101: CAJA DOLARES | GZI101: CAJA DOLARES | GZQ101: CAJA DOLARES | GZY101: CAJA DOLARES | HAG101: CAJA DOLARES | HAO101: CAJA DOLARES | HAW101: CAJA DOLARES | HBE101: CAJA DOLARES | HBM101: CAJA DOLARES | HBU101: CAJA DOLARES | HCC101: CAJA DOLARES | HCK101: CAJA DOLARES | HCS101: CAJA DOLARES | HDA101: CAJA DOLARES | HDI101: CAJA DOLARES | HDQ101: CAJA DOLARES | HDY101: CAJA DOLARES | HEG101: CAJA DOLARES | HEO101: CAJA DOLARES | HEW101: CAJA DOLARES | HFE101: CAJA DOLARES | HFM101: CAJA DOLARES | HFU101: CAJA DOLARES | HGC101: CAJA DOLARES | HGK101: CAJA DOLARES | HGS101: CAJA DOLARES | HHA101: CAJA DOLARES | HHI101: CAJA DOLARES | HHQ101: CAJA DOLARES | HHY101: CAJA DOLARES | HIG101: CAJA DOLARES | HIO101: CAJA DOLARES | HIW101: CAJA DOLARES | HJE101: CAJA DOLARES | HJM101: CAJA DOLARES | HJU101: CAJA DOLARES | HKC101: CAJA DOLARES | HKK101: CAJA DOLARES | HKS101: CAJA DOLARES | HLA101: CAJA DOLARES | HLI101: CAJA DOLARES | HLQ101: CAJA DOLARES | HLY101: CAJA DOLARES | HMG101: CAJA DOLARES | HMO101: CAJA DOLARES | HMW101: CAJA DOLARES | HNE101: CAJA DOLARES | HNM101: CAJA DOLARES | HNU101: CAJA DOLARES | HOC101: CAJA DOLARES | HOK101: CAJA DOLARES | HOS101: CAJA DOLARES | HPA101: CAJA DOLARES | HPI101: CAJA DOLARES | HPQ101: CAJA DOLARES | HPY101: CAJA DOLARES | HQG101: CAJA DOLARES | HQO101: CAJA DOLARES | HQW101: CAJA DOLARES | HRE101: CAJA DOLARES | HRM101: CAJA DOLARES | HRU101: CAJA DOLARES | HSC101: CAJA DOLARES | HSK101: CAJA DOLARES | HSS101: CAJA DOLARES | HTA101: CAJA DOLARES | HTI101: CAJA DOLARES | HTQ101: CAJA DOLARES | HTY101: CAJA DOLARES | HUG101: CAJA DOLARES | HUO101: CAJA DOLARES | HUW101: CAJA DOLARES | HVE101: CAJA DOLARES | HVM101: CAJA DOLARES | HVU101: CAJA DOLARES | HWC101: CAJA DOLARES | HWK101: CAJA DOLARES | HWS101: CAJA DOLARES | HXA101: CAJA DOLARES | HXI101: CAJA DOLARES | HXQ101: CAJA DOLARES | HXY101: CAJA DOLARES | HYG101: CAJA DOLARES | HYO101: CAJA DOLARES | HYW101: CAJA DOLARES | HZE101: CAJA DOLARES | HZM101: CAJA DOLARES | HZU101: CAJA DOLARES | IAC101: CAJA DOLARES | IAK101: CAJA DOLARES | IAS101: CAJA DOLARES | IBA101: CAJA DOLARES | IBI101: CAJA DOLARES | IBQ101: CAJA DOLARES | IBY101: CAJA DOLARES | ICG101: CAJA DOLARES | ICO101: CAJA DOLARES | ICW101: CAJA DOLARES | IDE101: CAJA DOLARES | IDM101: CAJA DOLARES | IDU101: CAJA DOLARES | IEC101: CAJA DOLARES | IEK101: CAJA DOLARES | IES101: CAJA DOLARES | IFA101: CAJA DOLARES | IFI101: CAJA DOLARES | IFQ101: CAJA DOLARES | IFY101: CAJA DOLARES | IGG101: CAJA DOLARES | IGO101: CAJA DOLARES | IGW101: CAJA DOLARES | IHE101: CAJA DOLARES | IHM101: CAJA DOLARES | IHU101: CAJA DOLARES | IIC101: CAJA DOLARES | IIK101: CAJA DOLARES | IIS101: CAJA DOLARES | IJA101: CAJA DOLARES | IJI101: CAJA DOLARES | IJQ101: CAJA DOLARES | IJY101: CAJA DOLARES | IKG101: CAJA DOLARES | IKO101: CAJA DOLARES | IKW101: CAJA DOLARES | ILE101: CAJA DOLARES | ILM101: CAJA DOLARES | ILU101: CAJA DOLARES | IMC101: CAJA DOLARES | IMK101: CAJA DOLARES | IMS101: CAJA DOLARES | INA101: CAJA DOLARES | INI101: CAJA DOLARES | INQ101: CAJA DOLARES | INY101: CAJA DOLARES | IOG101: CAJA DOLARES | IOO101: CAJA DOLARES | IOW101: CAJA DOLARES | IPE101: CAJA DOLARES | IPM101: CAJA DOLARES | IPU101: CAJA DOLARES | IQC101: CAJA DOLARES | IQK101: CAJA DOLARES | IQS101: CAJA DOLARES | IRA101: CAJA DOLARES | IRI101: CAJA DOLARES | IRQ101: CAJA DOLARES | IRY101: CAJA DOLARES | ISG101: CAJA DOLARES | ISO101: CAJA DOLARES | ISW101: CAJA DOLARES | ITE101: CAJA DOLARES | ITM101: CAJA DOLARES | ITU101: CAJA DOLARES | IUC101: CAJA DOLARES | IUK101: CAJA DOLARES | IUS101: CAJA DOLARES | IVA101: CAJA DOLARES | IVI101: CAJA DOLARES | IVQ101: CAJA DOLARES | IVY101: CAJA DOLARES | IWG101: CAJA DOLARES | IWO101: CAJA DOLARES | IWW101: CAJA DOLARES | IXE101: CAJA DOLARES | IXM101: CAJA DOLARES | IXU101: CAJA DOLARES | IYC101: CAJA DOLARES | IYK101: CAJA DOLARES | IYS101: CAJA DOLARES | IZA101: CAJA DOLARES | IZI101: CAJA DOLARES | IZQ101: CAJA DOLARES | IZY101: CAJA DOLARES | JAG101: CAJA DOLARES | JAO101: CAJA DOLARES | JAW101: CAJA DOLARES | JBE101: CAJA DOLARES | JBM101: CAJA DOLARES | JBU101: CAJA DOLARES | JCC101: CAJA DOLARES | JCK101: CAJA DOLARES | JCS101: CAJA DOLARES | JDA101: CAJA DOLARES | JDI101: CAJA DOLARES | JDQ101: CAJA DOLARES | JDY101: CAJA DOLARES | JEG101: CAJA DOLARES | JEO101: CAJA DOLARES | JEW101: CAJA DOLARES | JFE101: CAJA DOLARES | JFM101: CAJA DOLARES | JFU101: CAJA DOLARES | JGC101: CAJA DOLARES | JGK101: CAJA DOLARES | JGS101: CAJA DOLARES | JHA101: CAJA DOLARES | JHI101: CAJA DOLARES | JHQ101: CAJA DOLARES | JHY101: CAJA DOLARES | JIG101: CAJA DOLARES | JIO101: CAJA DOLARES | JIW101: CAJA DOLARES | JJE101: CAJA DOLARES | JJM101: CAJA DOLARES | JJU101: CAJA DOLARES | JKC101: CAJA DOLARES | JKK101: CAJA DOLARES | JKS101: CAJA DOLARES | JLA101: CAJA DOLARES | JLI101: CAJA DOLARES | JLQ101: CAJA DOLARES | JLY101: CAJA DOLARES | JMG101: CAJA DOLARES | JMO101: CAJA DOLARES | JMW101: CAJA DOLARES | JNE101: CAJA DOLARES | JNM101: CAJA DOLARES | JNU101: CAJA DOLARES | JOC101: CAJA DOLARES | JOK101: CAJA DOLARES | JOS101: CAJA DOLARES | JPA101: CAJA DOLARES | JPI101: CAJA DOLARES | JPQ101: CAJA DOLARES | JPY101: CAJA DOLARES | JQG101: CAJA DOLARES | JQO101: CAJA DOLARES | JQW101: CAJA DOLARES | JRE101: CAJA DOLARES | JRM101: CAJA DOLARES | JRU101: CAJA DOLARES | JSC101: CAJA DOLARES | JSK101: CAJA DOLARES | JSS101: CAJA DOLARES | JTA101: CAJA DOLARES | JTI101: CAJA DOLARES | JTQ101: CAJA DOLARES | JTY101: CAJA DOLARES | JUG101: CAJA DOLARES | JUO101: CAJA DOLARES | JUW101: CAJA DOLARES | JVE101: CAJA DOLARES | JVM101: CAJA DOLARES | JVU101: CAJA DOLARES | JWC101: CAJA DOLARES | JWK101: CAJA DOLARES | JWS101: CAJA DOLARES | JXA101: CAJA DOLARES | JXI101: CAJA DOLARES | JXQ101: CAJA DOLARES | JXY101: CAJA DOLARES | JYG101: CAJA DOLARES | JYO101: CAJA DOLARES | JYW101: CAJA DOLARES | JZE101: CAJA DOLARES | JZM101: CAJA DOLARES | JZU101: CAJA DOLARES | KAC101: CAJA DOLARES | KAK101: CAJA DOLARES | KAS101: CAJA DOLARES | KBA101: CAJA DOLARES | KBI101: CAJA DOLARES | KBQ101: CAJA DOLARES | KBY101: CAJA DOLARES | KCG101: CAJA DOLARES | KCO101: CAJA DOLARES | KCW101: CAJA DOLARES | KDE101: CAJA DOLARES | KDM101: CAJA DOLARES | KDU101: CAJA DOLARES | KEC101: CAJA DOLARES | KEK101: CAJA DOLARES | KES101: CAJA DOLARES | KFA101: CAJA DOLARES | KFI101: CAJA DOLARES | KFQ101: CAJA DOLARES | KFY101: CAJA DOLARES | KGG101: CAJA DOLARES | KGO101: CAJA DOLARES | KGW101: CAJA DOLARES | KHE101: CAJA DOLARES | KHM101: CAJA DOLARES | KHU101: CAJA DOLARES | KIC101: CAJA DOLARES | KIK101: CAJA DOLARES | KIS101: CAJA DOLARES | KJA101: CAJA DOLARES | KJI101: CAJA DOLARES | KJQ101: CAJA DOLARES | KJY101: CAJA DOLARES | KKG101: CAJA DOLARES | KKO101: CAJA DOLARES | KKW101: CAJA DOLARES | KLE101: CAJA DOLARES | KLM101: CAJA DOLARES | KLU101: CAJA DOLARES | KMC101: CAJA DOLARES | KMK101: CAJA DOLARES | KMS101: CAJA DOLARES | KNA101: CAJA DOLARES | KNI101: CAJA DOLARES | KNQ101: CAJA DOLARES | KNY101: CAJA DOLARES | KOG101: CAJA DOLARES | KOO101: CAJA DOLARES | KOW101: CAJA DOLARES | KPE101: CAJA DOLARES | KPM101: CAJA DOLARES | KPU101: CAJA DOLARES | KQC101: CAJA DOLARES | KQK101: CAJA DOLARES | KQS101: CAJA DOLARES | KRA101: CAJA DOLARES | KRI101: CAJA DOLARES | KRQ101: CAJA DOLARES | KRY101: CAJA DOLARES | KSG101: CAJA DOLARES | KSO101: CAJA DOLARES | KSW101: CAJA DOLARES | KTE101: CAJA DOLARES | KTM101: CAJA DOLARES | KTU101: CAJA DOLARES | KUC101: CAJA DOLARES | KUK101: CAJA DOLARES | KUS101: CAJA DOLARES | KVA101: CAJA DOLARES | KVI101: CAJA DOLARES | KVQ101: CAJA DOLARES | KVY101: CAJA DOLARES | KWG101: CAJA DOLARES | KWO101: CAJA DOLARES | KWW101: CAJA DOLARES | KXE101: CAJA DOLARES | KXM101: CAJA DOLARES | KXU101: CAJA DOLARES | KYC101: CAJA DOLARES | KYK101: CAJA DOLARES | KYS101: CAJA DOLARES | KZA101: CAJA DOLARES | KZI101: CAJA DOLARES | KZQ101: CAJA DOLARES | KZY101: CAJA DOLARES | LAG101: CAJA DOLARES | LAO101: CAJA DOLARES | LAW101: CAJA DOLARES | LBE101: CAJA DOLARES | LBM101: CAJA DOLARES | LBU101: CAJA DOLARES | LCC101: CAJA DOLARES | LCK101: CAJA DOLARES | LCS101: CAJA DOLARES | LDA101: CAJA DOLARES | LDI101: CAJA DOLARES | LDQ101: CAJA DOLARES | LDY101: CAJA DOLARES | LEG101: CAJA DOLARES | LEO101: CAJA DOLARES | LEW101: CAJA DOLARES | LFE101: CAJA DOLARES | LFM101: CAJA DOLARES | LFU101: CAJA DOLARES | LGC101: CAJA DOLARES | LGK101: CAJA DOLARES | LGS101: CAJA DOLARES | LHA101: CAJA DOLARES | LHI101: CAJA DOLARES | LHQ101: CAJA DOLARES | LHY101: CAJA DOLARES | LIG101: CAJA DOLARES | LIO101: CAJA DOLARES | LIW101: CAJA DOLARES | LJE101: CAJA DOLARES | LJM101: CAJA DOLARES | LJU101: CAJA DOLARES | LKC101: CAJA DOLARES | LKK101: CAJA DOLARES | LKS101: CAJA DOLARES | LLA101: CAJA DOLARES | LLI101: CAJA DOLARES | LLQ101: CAJA DOLARES | LLY101: CAJA DOLARES | LMG101: CAJA DOLARES | LMO101: CAJA DOLARES | LMW101: CAJA DOLARES | LNE101: CAJA DOLARES | LNM101: CAJA DOLARES | LNU101: CAJA DOLARES | LOC101: CAJA DOLARES | LOK101: CAJA DOLARES | LOS101: CAJA DOLARES | LPA101: CAJA DOLARES | LPI101: CAJA DOLARES | LPQ101: CAJA DOLARES | LPY101: CAJA DOLARES | LQG101: CAJA DOLARES | LQO101: CAJA DOLARES | LQW101: CAJA DOLARES | LRE101: CAJA DOLARES | LRM101: CAJA DOLARES | LRU101: CAJA DOLARES | LSC101: CAJA DOLARES | LSK101: CAJA DOLARES | LSS101: CAJA DOLARES | LTA101: CAJA DOLARES | LTI101: CAJA DOLARES | LTQ101: CAJA DOLARES | LTY101: CAJA DOLARES | LUG101: CAJA DOLARES | LUO101: CAJA DOLARES | LUW101: CAJA DOLARES | LVE101: CAJA DOLARES | LVM101: CAJA DOLARES | LVU101: CAJA DOLARES | LWC101: CAJA DOLARES | LWK101: CAJA DOLARES | LWS101: CAJA DOLARES | LXA101: CAJA DOLARES | LXI101: CAJA DOLARES | LXQ101: CAJA DOLARES | LXY101: CAJA DOLARES | LYG101: CAJA DOLARES | LYO101: CAJA DOLARES | LYW101: CAJA DOLARES | LZE101: CAJA DOLARES | LZM101: CAJA DOLARES | LZU101: CAJA DOLARES | MAC101: CAJA DOLARES | MAK101: CAJA DOLARES | MAS101: CAJA DOLARES | MBA101: CAJA DOLARES | MBI101: CAJA DOLARES | MBQ101: CAJA DOLARES | MBY101: CAJA DOLARES | MCG101: CAJA DOLARES | MCO101: CAJA DOLARES | MCW101: CAJA DOLARES | MDE101: CAJA DOLARES | MDM101: CAJA DOLARES | MDU101: CAJA DOLARES | MEC101: CAJA DOLARES | MEK101: CAJA DOLARES | MES101: CAJA DOLARES | MFA101: CAJA DOLARES | MFI101: CAJA DOLARES | MFQ101: CAJA DOLARES | MFY101: CAJA DOLARES | MGG101: CAJA DOLARES | MGO101: CAJA DOLARES | MGW101: CAJA DOLARES | MHE101: CAJA DOLARES | MHM101: CAJA DOLARES | MHU101: CAJA DOLARES | MIC101: CAJA DOLARES | MIK101: CAJA DOLARES | MIS101: CAJA DOLARES | MJA101: CAJA DOLARES | MJI101: CAJA DOLARES | MJQ101: CAJA DOLARES | MJY101: CAJA DOLARES | MKG101: CAJA DOLARES | MKO101: CAJA DOLARES | MKW101: CAJA DOLARES | MLE101: CAJA DOLARES | MLM101: CAJA DOLARES | MLU101: CAJA DOLARES | MMC101: CAJA DOLARES | MMK101: CAJA DOLARES | MMS101: CAJA DOLARES | MNA101: CAJA DOLARES | MNI101: CAJA DOLARES | MNQ101: CAJA DOLARES | MNY101: CAJA DOLARES | MOG101: CAJA DOLARES | MOO101: CAJA DOLARES | MOW101: CAJA DOLARES | MPE101: CAJA DOLARES | MPM101: CAJA DOLARES | MPU101: CAJA DOLARES | MQC101: CAJA DOLARES | MQK101: CAJA DOLARES | MQS101: CAJA DOLARES | MRA101: CAJA DOLARES | MRI101: CAJA DOLARES | MRQ101: CAJA DOLARES | MRY101: CAJA DOLARES | MSG101: CAJA DOLARES | MSO101: CAJA DOLARES | MSW101: CAJA DOLARES | MTE101: CAJA DOLARES | MTM101: CAJA DOLARES | MTU101: CAJA DOLARES | MUC101: CAJA DOLARES | MUK101: CAJA DOLARES | MUS101: CAJA DOLARES | MVA101: CAJA DOLARES | MVI101: CAJA DOLARES | MVQ101: CAJA DOLARES | MVY101: CAJA DOLARES | MWG101: CAJA DOLARES | MWO101: CAJA DOLARES | MWW101: CAJA DOLARES | MXE101: CAJA DOLARES | MXM101: CAJA DOLARES | MXU101: CAJA DOLARES | MYC101: CAJA DOLARES | MYK101: CAJA DOLARES | MYS101: CAJA DOLARES | MZA101: CAJA DOLARES | MZI101: CAJA DOLARES | MZQ101: CAJA DOLARES | MZY101: CAJA DOLARES | NAG101: CAJA DOLARES | NAO101: CAJA DOLARES | NAW101: CAJA DOLARES | NBE101: CAJA DOLARES | NBM101: CAJA DOLARES | NBU101: CAJA DOLARES | NCC101: CAJA DOLARES | NCK101: CAJA DOLARES | NCS101: CAJA DOLARES | NDA101: CAJA DOLARES | NDI101: CAJA DOLARES | NDQ101: CAJA DOLARES | NDY101: CAJA DOLARES | NEG101: CAJA DOLARES | NEO101: CAJA DOLARES | NEW101: CAJA DOLARES | NFE101: CAJA DOLARES | NFM101: CAJA DOLARES | NFU101: CAJA DOLARES | NGC101: CAJA DOLARES | NGK101: CAJA DOLARES | NGS101: CAJA DOLARES | NHA101: CAJA DOLARES | NHI101: CAJA DOLARES | NHQ101: CAJA DOLARES | NHY101: CAJA DOLARES | NIG101: CAJA DOLARES | NIO101: CAJA DOLARES | NIW101: CAJA DOLARES | NJE101: CAJA DOLARES | NJM101: CAJA DOLARES | NJU101: CAJA DOLARES | NKC101: CAJA DOLARES | NKK101: CAJA DOLARES | NKS101: CAJA DOLARES | NLA101: CAJA DOLARES | NLI101: CAJA DOLARES | NLQ101: CAJA DOLARES | NLY101: CAJA DOLARES | NMG101: CAJA DOLARES | NMO101: CAJA DOLARES | NMW101: CAJA DOLARES | NNE101: CAJA DOLARES | NNM101: CAJA DOLARES | NNU101: CAJA DOLARES | NOC101: CAJA DOLARES | NOK101: CAJA DOLARES | NOS101: CAJA DOLARES | NPA101: CAJA DOLARES | NPI101: CAJA DOLARES | NPQ101: CAJA DOLARES | NPY101: CAJA DOLARES | NQG101: CAJA DOLARES | NQO101: CAJA DOLARES | NQW101: CAJA DOLARES | NRE101: CAJA DOLARES | NRM101: CAJA DOLARES | NRU101: CAJA DOLARES | NSC101: CAJA DOLARES | NSK101: CAJA DOLARES | NSS101: CAJA DOLARES | NTA101: CAJA DOLARES | NTI101: CAJA DOLARES | NTQ101: CAJA DOLARES | NTY101: CAJA DOLARES | NUG101: CAJA DOLARES | NUO101: CAJA DOLARES | NUW101: CAJA DOLARES | NVE101: CAJA DOLARES | NVM101: CAJA DOLARES | NVU101: CAJA DOLARES | NWC101: CAJA DOLARES | NWK101: CAJA DOLARES | NWS101: CAJA DOLARES | NXA101: CAJA DOLARES | NXI101: CAJA DOLARES | NXQ101: CAJA DOLARES | NXY101: CAJA DOLARES | NYG101: CAJA DOLARES | NYO101: CAJA DOLARES | NYW101: CAJA DOLARES | NZE101: CAJA DOLARES | NZM101: CAJA DOLARES | NZU101: CAJA DOLARES | OAC101: CAJA DOLARES | OAK101: CAJA DOLARES | OAS101: CAJA DOLARES | OBA101: CAJA DOLARES | OBI101: CAJA DOLARES | OBQ101: CAJA DOLARES | OBY101: CAJA DOLARES | OCG101: CAJA DOLARES | OCO101: CAJA DOLARES | OCW101: CAJA DOLARES | ODE101: CAJA DOLARES | ODM101: CAJA DOLARES | ODU101: CAJA DOLARES | OEC101: CAJA DOLARES | OEK101: CAJA DOLARES | OES101: CAJA DOLARES | OFA101: CAJA DOLARES | OFI101: CAJA DOLARES | OFQ101: CAJA DOLARES | OFY101: CAJA DOLARES | OGG101: CAJA DOLARES | OGO101: CAJA DOLARES | OGW101: CAJA DOLARES | OHE101: CAJA DOLARES | OHM101: CAJA DOLARES | OHU101: CAJA DOLARES | OIC101: CAJA DOLARES | OIK101: CAJA DOLARES | OIS101: CAJA DOLARES | OJA101: CAJA DOLARES | OJI101: CAJA DOLARES | OJQ101: CAJA DOLARES | OJY101: CAJA DOLARES | OKG101: CAJA DOLARES | OKO101: CAJA DOLARES | OKW101: CAJA DOLARES | OLE101: CAJA DOLARES | OLM101: CAJA DOLARES | OLU101: CAJA DOLARES | OMC101: CAJA DOLARES | OMK101: CAJA DOLARES | OMS101: CAJA DOLARES | ONA101: CAJA DOLARES | ONI101: CAJA DOLARES | ONQ101: CAJA DOLARES | ONY101: CAJA DOLARES | OOG101: CAJA DOLARES | OOO101: CAJA DOLARES | OOW101: CAJA DOLARES | OPE101: CAJA DOLARES | OPM101: CAJA DOLARES | OPU101: CAJA DOLARES | OQC101: CAJA DOLARES | OQK101: CAJA DOLARES | OQS101: CAJA DOLARES | ORA101: CAJA DOLARES | ORI101: CAJA DOLARES | ORQ101: CAJA DOLARES | ORY101: CAJA DOLARES | OSG101: CAJA DOLARES | OSO101: CAJA DOLARES | OSW101: CAJA DOLARES | OTE101: CAJA DOLARES | OTM101: CAJA DOLARES | OTU101: CAJA DOLARES | OUC101: CAJA DOLARES | OUK101: CAJA DOLARES | OUS101: CAJA DOLARES | OVA101: CAJA DOLARES | OVI101: CAJA DOLARES | OVQ101: CAJA DOLARES | OVY101: CAJA DOLARES | OWG101: CAJA DOLARES | OWO101: CAJA DOLARES | OWW101: CAJA DOLARES | OXE101: CAJA DOLARES | OXM101: CAJA DOLARES | OXU101: CAJA DOLARES | OYC101: CAJA DOLARES | OYK101: CAJA DOLARES | OYS101: CAJA DOLARES | OZA101: CAJA DOLARES | OZI101: CAJA DOLARES | OZQ101: CAJA DOLARES | OZY101: CAJA DOLARES | PAG101: CAJA DOLARES | PAO101: CAJA DOLARES | PAW101: CAJA DOLARES | PBE101: CAJA DOLARES | PBM101: CAJA DOLARES | PBU101: CAJA DOLARES | PCC101: CAJA DOLARES | PCK101: CAJA DOLARES | PCS101: CAJA DOLARES | PDA101: CAJA DOLARES | PDI101: CAJA DOLARES | PDQ101: CAJA DOLARES | PDY101: CAJA DOLARES | PEG101: CAJA DOLARES | PEO101: CAJA DOLARES | PEW101: CAJA DOLARES | PFE101: CAJA DOLARES | PFM101: CAJA DOLARES | PFU101: CAJA DOLARES | PGC101: CAJA DOLARES | PGK101: CAJA DOLARES | PGS101: CAJA DOLARES | PHA101: CAJA DOLARES | PHI101: CAJA DOLARES | PHQ101: CAJA DOLARES | PHY101: CAJA DOLARES | PIG101: CAJA DOLARES | PIO101: CAJA DOLARES | PIW101: CAJA DOLARES | PJE101: CAJA DOLARES | PJM101: CAJA DOLARES | PJU101: CAJA DOLARES | PKC101: CAJA DOLARES | PKK101: CAJA DOLARES | PKS101: CAJA DOLARES | PLA101: CAJA DOLARES | PLI101: CAJA DOLARES | PLQ101: CAJA DOLARES | PLY101: CAJA DOLARES | PMG101: CAJA DOLARES | PMO101: CAJA DOLARES | PMW101: CAJA DOLARES | PNE101: CAJA DOLARES | PNM101: CAJA DOLARES | PNU101: CAJA DOLARES | POC101: CAJA DOLARES | POK101: CAJA DOLARES | POS101: CAJA DOLARES | PPA101: CAJA DOLARES | PPI101: CAJA DOLARES | PPQ101: CAJA DOLARES | PPY101: CAJA DOLARES | PQG101: CAJA DOLARES | PQO101: CAJA DOLARES | PQW101: CAJA DOLARES | PRE101: CAJA DOLARES | PRM101: CAJA DOLARES | PRU101: CAJA DOLARES | PSC101: CAJA DOLARES | PSK101: CAJA DOLARES | PSS101: CAJA DOLARES | PTA101: CAJA DOLARES | PTI101: CAJA DOLARES | PTQ101: CAJA DOLARES | PTY101: CAJA DOLARES | PUG101: CAJA DOLARES | PUO101: CAJA DOLARES | PUW101: CAJA DOLARES | PVE101: CAJA DOLARES | PVM101: CAJA DOLARES | PVU101: CAJA DOLARES | PWC101: CAJA DOLARES | PWK101: CAJA DOLARES | PWS101: CAJA DOLARES | PXA101: CAJA DOLARES | PXI101: CAJA DOLARES | PXQ101: CAJA DOLARES | PXY101: CAJA DOLARES | PYG101: CAJA DOLARES | PYO101: CAJA DOLARES | PYW101: CAJA DOLARES | PZE101: CAJA DOLARES | PZM101: CAJA DOLARES | PZU101: CAJA DOLARES | QAC101: CAJA DOLARES | QAK101: CAJA DOLARES | QAS101: CAJA DOLARES | QBA101: CAJA DOLARES | QBI101: CAJA DOLARES | QBQ101: CAJA DOLARES | QBY101: CAJA DOLARES | QCG101: CAJA DOLARES | QCO101: CAJA DOLARES | QCW101: CAJA DOLARES | QDE101: CAJA DOLARES | QDM101: CAJA DOLARES | QDU101: CAJA DOLARES | QEC101: CAJA DOLARES | QEK101: CAJA DOLARES | QES101: CAJA DOLARES | QFA101: CAJA DOLARES | QFI101: CAJA DOLARES | QFQ101: CAJA DOLARES | QFY101: CAJA DOLARES | QGG101: CAJA DOLARES | QGO101: CAJA DOLARES | QGW101: CAJA DOLARES | QHE101: CAJA DOLARES | QHM101: CAJA DOLARES | QHU101: CAJA DOLARES | QIC101: CAJA DOLARES | QIK101: CAJA DOLARES | QIS101: CAJA DOLARES | QJA101: CAJA DOLARES | QJI101: CAJA DOLARES | QJQ101: CAJA DOLARES | QJY101: CAJA DOLARES | QKG101: CAJA DOLARES | QKO101: CAJA DOLARES | QKW101: CAJA DOLARES | QLE101: CAJA DOLARES | QLM101: CAJA DOLARES | QLU101: CAJA DOLARES | QMC101: CAJA DOLARES | QMK101: CAJA DOLARES | QMS101: CAJA DOLARES | QNA101: CAJA DOLARES | QNI101: CAJA DOLARES | QNQ101: CAJA DOLARES | QNY101: CAJA DOLARES | QOG101: CAJA DOLARES | QOO101: CAJA DOLARES | QOW101: CAJA DOLARES | QPE101: CAJA DOLARES | QPM101: CAJA DOLARES | QPU101: CAJA DOLARES | QQC101: CAJA DOLARES | QQK101: CAJA DOLARES | QQS101: CAJA DOLARES | QRA101: CAJA DOLARES | QRI101: CAJA DOLARES | QRQ101: CAJA DOLARES | QRY101: CAJA DOLARES | QSG101: CAJA DOLARES | QSO101: CAJA DOLARES | QSW101: CAJA DOLARES | QTE101: CAJA DOLARES | QTM101: CAJA DOLARES | QTU101: CAJA DOLARES | QUC101: CAJA DOLARES | QUK101: CAJA DOLARES | QUS101: CAJA DOLARES | QVA101: CAJA DOLARES | QVI101: CAJA DOLARES | QVQ101: CAJA DOLARES | QVY101: CAJA DOLARES | QWG101: CAJA DOLARES | QWO101: CAJA DOLARES | QWW101: CAJA DOLARES | QXE101: CAJA DOLARES | QXM101: CAJA DOLARES | QXU101: CAJA DOLARES | QYC101: CAJA DOLARES | QYK101: CAJA DOLARES | QYS101: CAJA DOLARES | QZA101: CAJA DOLARES | QZI101: CAJA DOLARES | QZQ101: CAJA DOLARES | QZY101: CAJA DOLARES | RAG101: CAJA DOLARES | RAO101: CAJA DOLARES | RAW101: CAJA DOLARES | RBE101: CAJA DOLARES | RBM101: CAJA DOLARES | RBU101: CAJA DOLARES | RCC101: CAJA DOLARES | RCK101: CAJA DOLARES | RCS101: CAJA DOLARES | RDA101: CAJA DOLARES | RDI101: CAJA DOLARES | RDQ101: CAJA DOLARES | RDY101: CAJA DOLARES | REG101: CAJA DOLARES | REO101: CAJA DOLARES | REW101: CAJA DOLARES | RFE101: CAJA DOLARES | RFM101: CAJA DOLARES | RFU101: CAJA DOLARES | RGC101: CAJA DOLARES | RGK101: CAJA DOLARES | RGS101: CAJA DOLARES | RHA101: CAJA DOLARES | RHI101: CAJA DOLARES | RHQ101: CAJA DOLARES | RHY101: CAJA DOLARES | RIG101: CAJA DOLARES | RIO101: CAJA DOLARES | RIW101: CAJA DOLARES | RJE101: CAJA DOLARES | RJM101: CAJA DOLARES | RJU101: CAJA DOLARES | RKC101: CAJA DOLARES | RKK101: CAJA DOLARES | RKS101: CAJA DOLARES | RLA101: CAJA DOLARES | RLI101: CAJA DOLARES | RLQ101: CAJA DOLARES | RLY101: CAJA DOLARES | RMG101: CAJA DOLARES | RMO101: CAJA DOLARES | RMW101: CAJA DOLARES | RNE101: CAJA DOLARES | RNM101: CAJA DOLARES | RNU101: CAJA DOLARES | ROC101: CAJA DOLARES | ROK101: CAJA DOLARES | ROS101: CAJA DOLARES | RPA101: CAJA DOLARES | RPI101: CAJA DOLARES | RPQ101: CAJA DOLARES | RPY101: CAJA DOLARES | RQG101: CAJA DOLARES | RQO101: CAJA DOLARES | RQW101: CAJA DOLARES | RRE101: CAJA DOLARES | RRM101: CAJA DOLARES | RRU101: CAJA DOLARES | RSC101: CAJA DOLARES | RSK101: CAJA DOLARES | RSS101: CAJA DOLARES | RTA101: CAJA DOLARES | RTI101: CAJA DOLARES | RTQ101: CAJA DOLARES | RTY101: CAJA DOLARES | RUG101: CAJA DOLARES | RUO101: CAJA DOLARES | RUW101: CAJA DOLARES | RVE101: CAJA DOLARES | RVM101: CAJA DOLARES | RVU101: CAJA DOLARES | RWC101: CAJA DOLARES | RWK101: CAJA DOLARES | RWS101: CAJA DOLARES | RXA101: CAJA DOLARES | RXI101: CAJA DOLARES | RXQ101: CAJA DOLARES | RXY101: CAJA DOLARES | RYG101: CAJA DOLARES | RYO101: CAJA DOLARES | RYW101: CAJA DOLARES | RZE101: CAJA DOLARES | RZM101: CAJA DOLARES | RZU101: CAJA DOLARES | SAC101: CAJA DOLARES | SAK101: CAJA DOLARES | SAS101: CAJA DOLARES | SBA101: CAJA DOLARES | SBI101: CAJA DOLARES | SBQ101: CAJA DOLARES | SBY101: CAJA DOLARES | SCG101: CAJA DOLARES | SCO101: CAJA DOLARES | SCW101: CAJA DOLARES | SDE101: CAJA DOLARES | SDM101: CAJA DOLARES | SDU101: CAJA DOLARES | SEC101: CAJA DOLARES | SEK101: CAJA DOLARES | SES101: CAJA DOLARES | SFA101: CAJA DOLARES | SFI101: CAJA DOLARES | SFQ101: CAJA DOLARES | SFY101: CAJA DOLARES | SGG101: CAJA DOLARES | SGO101: CAJA DOLARES | SGW101: CAJA DOLARES | SHE101: CAJA DOLARES | SHM101: CAJA DOLARES | SHU101: CAJA DOLARES | SIC101: CAJA DOLARES | SIK101: CAJA DOLARES | SIS101: CAJA DOLARES | SJA101: CAJA DOLARES | SJI101: CAJA DOLARES | SJQ101: CAJA DOLARES | SJY101: CAJA DOLARES | SKG101: CAJA DOLARES | SKO101: CAJA DOLARES | SKW101: CAJA DOLARES | SLE101: CAJA DOLARES | SLM101: CAJA DOLARES | SLU101: CAJA DOLARES | SMC101: CAJA DOLARES | SMK101: CAJA DOLARES | SMS101: CAJA DOLARES | SNA101: CAJA DOLARES | SNI101: CAJA DOLARES | SNQ101: CAJA DOLARES | SNY101: CAJA DOLARES | SOG101: CAJA DOLARES | SOO101: CAJA DOLARES | SOW101: CAJA DOLARES | SPE101: CAJA DOLARES | SPM101: CAJA DOLARES | SPU101: CAJA DOLARES | SQC101: CAJA DOLARES | SQK101: CAJA DOLARES | SQS101: CAJA DOLARES | SRA101: CAJA DOLARES | SRI101: CAJA DOLARES | SRQ101: CAJA DOLARES | SRY101: CAJA DOLARES | SSG101: CAJA DOLARES | SSO101: CAJA DOLARES | SSW101: CAJA DOLARES | STE101: CAJA DOLARES | STM101: CAJA DOLARES | STU101: CAJA DOLARES | SUC101: CAJA DOLARES | SUK101: CAJA DOLARES | SUS101: CAJA DOLARES | SVA101: CAJA DOLARES | SVI101: CAJA DOLARES | SVQ101: CAJA DOLARES | SVY101: CAJA DOLARES | SWG101: CAJA DOLARES | SWO101: CAJA DOLARES | SWW101: CAJA DOLARES | SXE101: CAJA DOLARES | SXM101: CAJA DOLARES | SXU101: CAJA DOLARES | SYC101: CAJA DOLARES | SYK101: CAJA DOLARES | SYS101: CAJA DOLARES | SZA101: CAJA DOLARES | SZI101: CAJA DOLARES | SZQ101: CAJA DOLARES | SZY101: CAJA DOLARES | TAG101: CAJA DOLARES | TAO101: CAJA DOLARES | TAW101: CAJA DOLARES | TBE101: CAJA DOLARES | TBM101: CAJA DOLARES | TBU101: CAJA DOLARES | TCC101: CAJA DOLARES | TCK101: CAJA DOLARES | TCS101: CAJA DOLARES | TDA101: CAJA DOLARES | TDI101: CAJA DOLARES | TDQ101: CAJA DOLARES | TDY101: CAJA DOLARES | TEG101: CAJA DOLARES | TEO101: CAJA DOLARES | TEW101: CAJA DOLARES | TFE101: CAJA DOLARES | TFM101: CAJA DOLARES | TFU101: CAJA DOLARES | TGC101: CAJA DOLARES | TGK101: CAJA DOLARES | TGS101: CAJA DOLARES | THA101: CAJA DOLARES | THI101: CAJA DOLARES | THQ101: CAJA DOLARES | THY101: CAJA DOLARES | TIG101: CAJA DOLARES | TIO101: CAJA DOLARES | TIW101: CAJA DOLARES | TJE101: CAJA DOLARES | TJM101: CAJA DOLARES | TJU101: CAJA DOLARES | TKC101: CAJA DOLARES | TKK101: CAJA DOLARES | TKS101: CAJA DOLARES | TLA101: CAJA DOLARES | TLI101: CAJA DOLARES | TLQ101: CAJA DOLARES | TLY101: CAJA DOLARES | TMG101: CAJA DOLARES | TMO101: CAJA DOLARES | TMW101: CAJA DOLARES | TNE101: CAJA DOLARES | TNM101: CAJA DOLARES | TNU101: CAJA DOLARES | TOC101: CAJA DOLARES | TOK101: CAJA DOLARES | TOS101: CAJA DOLARES | TPA101: CAJA DOLARES | TPI101: CAJA DOLARES | TPQ101: CAJA DOLARES | TPY101: CAJA DOLARES | TQG101: CAJA DOLARES | TQO101: CAJA DOLARES | TQW101: CAJA DOLARES | TRE101: CAJA DOLARES | TRM101: CAJA DOLARES | TRU101: CAJA DOLARES | TSC101: CAJA DOLARES | TSK101: CAJA DOLARES | TSS101: CAJA DOLARES | TTA101: CAJA DOLARES | TTI101: CAJA DOLARES | TTQ101: CAJA DOLARES | TTY101: CAJA DOLARES | TUG101: CAJA DOLARES | TUO101: CAJA DOLARES | TUW101: CAJA DOLARES | TVE101: CAJA DOLARES | TVM101: CAJA DOLARES | TVU101: CAJA DOLARES | TWC101: CAJA DOLARES | TWK101: CAJA DOLARES | TWS101: CAJA DOLARES | TXA101: CAJA DOLARES | TXI101: CAJA DOLARES | TXQ101: CAJA DOLARES | TXY101: CAJA DOLARES | TYG101: CAJA DOLARES | TYO101: CAJA DOLARES | TYW101: CAJA DOLARES | TZE101: CAJA DOLARES | TZM101: CAJA DOLARES | TZU101: CAJA DOLARES | UAC101: CAJA DOLARES | UAK101: CAJA DOLARES | UAS101: CAJA DOLARES | UBA101: CAJA DOLARES | UBI101: CAJA DOLARES | UBQ101: CAJA DOLARES | UBY101: CAJA DOLARES | UCG101: CAJA DOLARES | UCO101: CAJA DOLARES | UCW101: CAJA DOLARES | UDE101: CAJA DOLARES | UDM101: CAJA DOLARES | UDU101: CAJA DOLARES | UEC101: CAJA DOLARES | UEK101: CAJA DOLARES | UES101: CAJA DOLARES | UFA101: CAJA DOLARES | UFI101: CAJA DOLARES | UFQ101: CAJA DOLARES | UFY101: CAJA DOLARES | UGG101: CAJA DOLARES | UGO101: CAJA DOLARES | UGW101: CAJA DOLARES | UHE101: CAJA DOLARES | UHM101: CAJA DOLARES | UHU101: CAJA DOLARES | UIC101: CAJA DOLARES | UIK101: CAJA DOLARES | UIS101: CAJA DOLARES | UJA101: CAJA DOLARES | UJI101: CAJA DOLARES | UJQ101: CAJA DOLARES | UJY101: CAJA DOLARES | UKG101: CAJA DOLARES | UKO101: CAJA DOLARES | UKW101: CAJA DOLARES | ULE101: CAJA DOLARES | ULM101: CAJA DOLARES | ULU101: CAJA DOLARES | UMC101: CAJA DOLARES | UMK101: CAJA DOLARES | UMS101: CAJA DOLARES | UNA101: CAJA DOLARES | UNI101: CAJA DOLARES | UNQ101: CAJA DOLARES | UNY101: CAJA DOLARES | UOG101: CAJA DOLARES | UOO101: CAJA DOLARES | UOW101: CAJA DOLARES | UPE101: CAJA DOLARES | UPM101: CAJA DOLARES | UPU101: CAJA DOLARES | UQC101: CAJA DOLARES | UQK101: CAJA DOLARES | UQS101: CAJA DOLARES | URA101: CAJA DOLARES | URI101: CAJA DOLARES | URQ101: CAJA DOLARES | URY101: CAJA DOLARES | USG101: CAJA DOLARES | USO101: CAJA DOLARES | USW101: CAJA DOLARES | UTE101: CAJA DOLARES | UTM101: CAJA DOLARES | UTU101: CAJA DOLARES | UUC101: CAJA DOLARES | UUK101: CAJA DOLARES | UUS101: CAJA DOLARES | UVA101: CAJA DOLARES | UVI101: CAJA DOLARES | UVQ101: CAJA DOLARES | UVY101: CAJA DOLARES | UWG101: CAJA DOLARES | UWO101: CAJA DOLARES | UWW101: CAJA DOLARES | UXE101: CAJA DOLARES | UXM101: CAJA DOLARES | UXU101: CAJA DOLARES | UYC101: CAJA DOLARES | UYK101: CAJA DOLARES | UYS101: CAJA DOLARES | UZA101: CAJA DOLARES | UZI101: CAJA DOLARES | UZQ101: CAJA DOLARES | UZY101: CAJA DOLARES | VAG101: CAJA DOLARES | VAO101: CAJA DOLARES | VAW101: CAJA DOLARES | VBE101: CAJA DOLARES | VBM101: CAJA DOLARES | VBU101: CAJA DOLARES | VCC101: CAJA DOLARES | VCK101: CAJA DOLARES | VCS101: CAJA DOLARES | VDA101: CAJA DOLARES | VDI101: CAJA DOLARES | VDQ101: CAJA DOLARES | VDY101: CAJA DOLARES | VEG101: CAJA DOLARES | VEO101: CAJA DOLARES | VEW101: CAJA DOLARES | VFE101: CAJA DOLARES | VFM101: CAJA DOLARES | VFU101: CAJA DOLARES | VGC101: CAJA DOLARES | VGK101: CAJA DOLARES | VGS101: CAJA DOLARES | VHA101: CAJA DOLARES | VHI101: CAJA DOLARES | VHQ101: CAJA DOLARES | VHY101: CAJA DOLARES | VIG101: CAJA DOLARES | VIO101: CAJA DOLARES | VIW101: CAJA DOLARES | VJE101: CAJA DOLARES | VJM101: CAJA DOLARES | VJU101: CAJA DOLARES | VKC101: CAJA DOLARES | VKK101: CAJA DOLARES | VKS101: CAJA DOLARES | VLA101: CAJA DOLARES | VLI101: CAJA DOLARES | VLQ101: CAJA DOLARES | VLY101: CAJA DOLARES | VMG101: CAJA DOLARES | VMO101: CAJA DOLARES | VMW101: CAJA DOLARES | VNE101: CAJA DOLARES | VNM101: CAJA DOLARES | VNU101: CAJA DOLARES | VOC101: CAJA DOLARES | VOK101: CAJA DOLARES | VOS101: CAJA DOLARES | VPA101: CAJA DOLARES | VPI101: CAJA DOLARES | VPQ101: CAJA DOLARES | VPY101: CAJA DOLARES | VQG101: CAJA DOLARES | VQO101: CAJA DOLARES | VQW101: CAJA DOLARES | VRE101: CAJA DOLARES | VRM101: CAJA DOLARES | VRU101: CAJA DOLARES | VSC101: CAJA DOLARES | VSK101: CAJA DOLARES | VSS101: CAJA DOLARES | VTA101: CAJA DOLARES | VTI101: CAJA DOLARES | VTQ101: CAJA DOLARES | VTY101: CAJA DOLARES | VUG101: CAJA DOLARES | VUO101: CAJA DOLARES | VUW101: CAJA DOLARES | VVE101: CAJA DOLARES | VVM101: CAJA DOLARES | VVU101: CAJA DOLARES | VWC101: CAJA DOLARES | VWK101: CAJA DOLARES | VWS101: CAJA DOLARES | VXA101: CAJA DOLARES | VXI101: CAJA DOLARES | VXQ101: CAJA DOLARES | VXY101: CAJA DOLARES | VYG101: CAJA DOLARES | VYO101: CAJA DOLARES | VYW101: CAJA DOLARES | VZE101: CAJA DOLARES | VZM101: CAJA DOLARES | VZU101: CAJA DOLARES | WAC101: CAJA DOLARES | WAK101: CAJA DOLARES | WAS101: CAJA DOLARES | WBA101: CAJA DOLARES | WBI101: CAJA DOLARES | WBQ101: CAJA DOLARES | WBY101: CAJA DOLARES | WCG101: CAJA DOLARES | WCO101: CAJA DOLARES | WCW101: CAJA DOLARES | WDE101: CAJA DOLARES | WDM101: CAJA DOLARES | WDU101: CAJA DOLARES | WEC101: CAJA DOLARES | WEK101: CAJA DOLARES | WES101: CAJA DOLARES | WFA101: CAJA DOLARES | WFI101: CAJA DOLARES | WFQ101: CAJA DOLARES | WFY101: CAJA DOLARES | WGG101: CAJA DOLARES | WGO101: CAJA DOLARES | WGW101: CAJA DOLARES | WHE101: CAJA DOLARES | WHM101: CAJA DOLARES | WHU101: CAJA DOLARES | WIC101: CAJA DOLARES | WIK101: CAJA DOLARES | WIS101: CAJA DOLARES | WJA101: CAJA DOLARES | WJI101: CAJA DOLARES | WJQ101: CAJA DOLARES | WJY101: CAJA DOLARES | WKG101: CAJA DOLARES | WKO101: CAJA DOLARES | WKW101: CAJA DOLARES | WLE101: CAJA DOLARES | WLM101: CAJA DOLARES | WLU101: CAJA DOLARES | WMC101: CAJA DOLARES | WMK101: CAJA DOLARES | WMS101: CAJA DOLARES | WNA101: CAJA DOLARES | WNI101: CAJA DOLARES | WNQ101: CAJA DOLARES | WNY101: CAJA DOLARES | WOG101: CAJA DOLARES | WOO101: CAJA DOLARES | WOW101: CAJA DOLARES | WPE101: CAJA DOLARES | WPM101: CAJA DOLARES | WPU101: CAJA DOLARES | WQC101: CAJA DOLARES | WQK101: CAJA DOLARES | WQS101: CAJA DOLARES | WRA101: CAJA DOLARES | WRI101: CAJA DOLARES | WRQ101: CAJA DOLARES | WRY101: CAJA DOLARES | WSG101: CAJA DOLARES | WSO101: CAJA DOLARES | WSW101: CAJA DOLARES | WTE101: CAJA DOLARES | WTM101: CAJA DOLARES | WTU101: CAJA DOLARES | WUC101: CAJA DOLARES | WUK101: CAJA DOLARES | WUS101: CAJA DOLARES | WVA101: CAJA DOLARES | WVI101: CAJA DOLARES | WVQ101: CAJA DOLARES | WVY101: CAJA DOLARES | WWG101: CAJA DOLARES | WWO101: CAJA DOLARES | WWW101: CAJA DOLARES | WXE101: CAJA DOLARES | WXM101: CAJA DOLARES | WXU101: CAJA DOLARES | WYC101: CAJA DOLARES | WYK101: CAJA DOLARES | WYS101: CAJA DOLARES | WZA101: CAJA DOLARES | WZI101: CAJA DOLARES | WZQ101: CAJA DOLARES | WZY101: CAJA DOLARES | XAG101: CAJA DOLARES | XAO101: CAJA DOLARES | XAW101: CAJA DOLARES | XBE101: CAJA DOLARES | XBM101: CAJA DOLARES | XBU101: CAJA DOLARES | XCC101: CAJA DOLARES | XCK101: CAJA DOLARES | XCS101: CAJA DOLARES | XDA101: CAJA DOLARES | XDI101: CAJA DOLARES | XDQ101: CAJA DOLARES | XDY101: CAJA DOLARES | XEG101: CAJA DOLARES | XEO101: CAJA DOLARES | XEW101: CAJA DOLARES
A102: Saldo anterior | H102: 84000 | CC102: Saldo anterior | CJ102: 0 | CK102: Saldo anterior | CR102: 0 | CS102: Saldo anterior | CZ102: 0 | DA102: Saldo anterior | DH102: 0 | DI102: Saldo anterior | DP102: 0 | DQ102: Saldo anterior | DX102: 0 | DY102: Saldo anterior | EF102: 0 | EG102: Saldo anterior | EN102: 0 | EO102: Saldo anterior | EV102: 0 | EW102: Saldo anterior | FD102: 0 | FE102: Saldo anterior | FL102: 0 | FM102: Saldo anterior | FT102: 0 | FU102: Saldo anterior | GB102: 0 | GC102: Saldo anterior | GJ102: 0 | GK102: Saldo anterior | GR102: 0 | GS102: Saldo anterior | GZ102: 0 | HA102: Saldo anterior | HH102: 0 | HI102: Saldo anterior | HP102: 0 | HQ102: Saldo anterior | HX102: 0 | HY102: Saldo anterior | IF102: 0 | IG102: Saldo anterior | IN102: 0 | IO102: Saldo anterior | IV102: 0 | IW102: Saldo anterior | JD102: 0 | JE102: Saldo anterior | JL102: 0 | JM102: Saldo anterior | JT102: 0 | JU102: Saldo anterior | KB102: 0 | KC102: Saldo anterior | KJ102: 0 | KK102: Saldo anterior | KR102: 0 | KS102: Saldo anterior | KZ102: 0 | LA102: Saldo anterior | LH102: 0 | LI102: Saldo anterior | LP102: 0 | LQ102: Saldo anterior | LX102: 0 | LY102: Saldo anterior | MF102: 0 | MG102: Saldo anterior | MN102: 0 | MO102: Saldo anterior | MV102: 0 | MW102: Saldo anterior | ND102: 0 | NE102: Saldo anterior | NL102: 0 | NM102: Saldo anterior | NT102: 0 | NU102: Saldo anterior | OB102: 0 | OC102: Saldo anterior | OJ102: 0 | OK102: Saldo anterior | OR102: 0 | OS102: Saldo anterior | OZ102: 0 | PA102: Saldo anterior | PH102: 0 | PI102: Saldo anterior | PP102: 0 | PQ102: Saldo anterior | PX102: 0 | PY102: Saldo anterior | QF102: 0 | QG102: Saldo anterior | QN102: 0 | QO102: Saldo anterior | QV102: 0 | QW102: Saldo anterior | RD102: 0 | RE102: Saldo anterior | RL102: 0 | RM102: Saldo anterior | RT102: 0 | RU102: Saldo anterior | SB102: 0 | SC102: Saldo anterior | SJ102: 0 | SK102: Saldo anterior | SR102: 0 | SS102: Saldo anterior | SZ102: 0 | TA102: Saldo anterior | TH102: 0 | TI102: Saldo anterior | TP102: 0 | TQ102: Saldo anterior | TX102: 0 | TY102: Saldo anterior | UF102: 0 | UG102: Saldo anterior | UN102: 0 | UO102: Saldo anterior | UV102: 0 | UW102: Saldo anterior | VD102: 0 | VE102: Saldo anterior | VL102: 0 | VM102: Saldo anterior | VT102: 0 | VU102: Saldo anterior | WB102: 0 | WC102: Saldo anterior | WJ102: 0 | WK102: Saldo anterior | WR102: 0 | WS102: Saldo anterior | WZ102: 0 | XA102: Saldo anterior | XH102: 0 | XI102: Saldo anterior | XP102: 0 | XQ102: Saldo anterior | XX102: 0 | XY102: Saldo anterior | YF102: 0 | YG102: Saldo anterior | YN102: 0 | YO102: Saldo anterior | YV102: 0 | YW102: Saldo anterior | ZD102: 0 | ZE102: Saldo anterior | ZL102: 0 | ZM102: Saldo anterior | ZT102: 0 | ZU102: Saldo anterior | AAB102: 0 | AAC102: Saldo anterior | AAJ102: 0 | AAK102: Saldo anterior | AAR102: 0 | AAS102: Saldo anterior | AAZ102: 0 | ABA102: Saldo anterior | ABH102: 0 | ABI102: Saldo anterior | ABP102: 0 | ABQ102: Saldo anterior | ABX102: 0 | ABY102: Saldo anterior | ACF102: 0 | ACG102: Saldo anterior | ACN102: 0 | ACO102: Saldo anterior | ACV102: 0 | ACW102: Saldo anterior | ADD102: 0 | ADE102: Saldo anterior | ADL102: 0 | ADM102: Saldo anterior | ADT102: 0 | ADU102: Saldo anterior | AEB102: 0 | AEC102: Saldo anterior | AEJ102: 0 | AEK102: Saldo anterior | AER102: 0 | AES102: Saldo anterior | AEZ102: 0 | AFA102: Saldo anterior | AFH102: 0 | AFI102: Saldo anterior | AFP102: 0 | AFQ102: Saldo anterior | AFX102: 0 | AFY102: Saldo anterior | AGF102: 0 | AGG102: Saldo anterior | AGN102: 0 | AGO102: Saldo anterior | AGV102: 0 | AGW102: Saldo anterior | AHD102: 0 | AHE102: Saldo anterior | AHL102: 0 | AHM102: Saldo anterior | AHT102: 0 | AHU102: Saldo anterior | AIB102: 0 | AIC102: Saldo anterior | AIJ102: 0 | AIK102: Saldo anterior | AIR102: 0 | AIS102: Saldo anterior | AIZ102: 0 | AJA102: Saldo anterior | AJH102: 0 | AJI102: Saldo anterior | AJP102: 0 | AJQ102: Saldo anterior | AJX102: 0 | AJY102: Saldo anterior | AKF102: 0 | AKG102: Saldo anterior | AKN102: 0 | AKO102: Saldo anterior | AKV102: 0 | AKW102: Saldo anterior | ALD102: 0 | ALE102: Saldo anterior | ALL102: 0 | ALM102: Saldo anterior | ALT102: 0 | ALU102: Saldo anterior | AMB102: 0 | AMC102: Saldo anterior | AMJ102: 0 | AMK102: Saldo anterior | AMR102: 0 | AMS102: Saldo anterior | AMZ102: 0 | ANA102: Saldo anterior | ANH102: 0 | ANI102: Saldo anterior | ANP102: 0 | ANQ102: Saldo anterior | ANX102: 0 | ANY102: Saldo anterior | AOF102: 0 | AOG102: Saldo anterior | AON102: 0 | AOO102: Saldo anterior | AOV102: 0 | AOW102: Saldo anterior | APD102: 0 | APE102: Saldo anterior | APL102: 0 | APM102: Saldo anterior | APT102: 0 | APU102: Saldo anterior | AQB102: 0 | AQC102: Saldo anterior | AQJ102: 0 | AQK102: Saldo anterior | AQR102: 0 | AQS102: Saldo anterior | AQZ102: 0 | ARA102: Saldo anterior | ARH102: 0 | ARI102: Saldo anterior | ARP102: 0 | ARQ102: Saldo anterior | ARX102: 0 | ARY102: Saldo anterior | ASF102: 0 | ASG102: Saldo anterior | ASN102: 0 | ASO102: Saldo anterior | ASV102: 0 | ASW102: Saldo anterior | ATD102: 0 | ATE102: Saldo anterior | ATL102: 0 | ATM102: Saldo anterior | ATT102: 0 | ATU102: Saldo anterior | AUB102: 0 | AUC102: Saldo anterior | AUJ102: 0 | AUK102: Saldo anterior | AUR102: 0 | AUS102: Saldo anterior | AUZ102: 0 | AVA102: Saldo anterior | AVH102: 0 | AVI102: Saldo anterior | AVP102: 0 | AVQ102: Saldo anterior | AVX102: 0 | AVY102: Saldo anterior | AWF102: 0 | AWG102: Saldo anterior | AWN102: 0 | AWO102: Saldo anterior | AWV102: 0 | AWW102: Saldo anterior | AXD102: 0 | AXE102: Saldo anterior | AXL102: 0 | AXM102: Saldo anterior | AXT102: 0 | AXU102: Saldo anterior | AYB102: 0 | AYC102: Saldo anterior | AYJ102: 0 | AYK102: Saldo anterior | AYR102: 0 | AYS102: Saldo anterior | AYZ102: 0 | AZA102: Saldo anterior | AZH102: 0 | AZI102: Saldo anterior | AZP102: 0 | AZQ102: Saldo anterior | AZX102: 0 | AZY102: Saldo anterior | BAF102: 0 | BAG102: Saldo anterior | BAN102: 0 | BAO102: Saldo anterior | BAV102: 0 | BAW102: Saldo anterior | BBD102: 0 | BBE102: Saldo anterior | BBL102: 0 | BBM102: Saldo anterior | BBT102: 0 | BBU102: Saldo anterior | BCB102: 0 | BCC102: Saldo anterior | BCJ102: 0 | BCK102: Saldo anterior | BCR102: 0 | BCS102: Saldo anterior | BCZ102: 0 | BDA102: Saldo anterior | BDH102: 0 | BDI102: Saldo anterior | BDP102: 0 | BDQ102: Saldo anterior | BDX102: 0 | BDY102: Saldo anterior | BEF102: 0 | BEG102: Saldo anterior | BEN102: 0 | BEO102: Saldo anterior | BEV102: 0 | BEW102: Saldo anterior | BFD102: 0 | BFE102: Saldo anterior | BFL102: 0 | BFM102: Saldo anterior | BFT102: 0 | BFU102: Saldo anterior | BGB102: 0 | BGC102: Saldo anterior | BGJ102: 0 | BGK102: Saldo anterior | BGR102: 0 | BGS102: Saldo anterior | BGZ102: 0 | BHA102: Saldo anterior | BHH102: 0 | BHI102: Saldo anterior | BHP102: 0 | BHQ102: Saldo anterior | BHX102: 0 | BHY102: Saldo anterior | BIF102: 0 | BIG102: Saldo anterior | BIN102: 0 | BIO102: Saldo anterior | BIV102: 0 | BIW102: Saldo anterior | BJD102: 0 | BJE102: Saldo anterior | BJL102: 0 | BJM102: Saldo anterior | BJT102: 0 | BJU102: Saldo anterior | BKB102: 0 | BKC102: Saldo anterior | BKJ102: 0 | BKK102: Saldo anterior | BKR102: 0 | BKS102: Saldo anterior | BKZ102: 0 | BLA102: Saldo anterior | BLH102: 0 | BLI102: Saldo anterior | BLP102: 0 | BLQ102: Saldo anterior | BLX102: 0 | BLY102: Saldo anterior | BMF102: 0 | BMG102: Saldo anterior | BMN102: 0 | BMO102: Saldo anterior | BMV102: 0 | BMW102: Saldo anterior | BND102: 0 | BNE102: Saldo anterior | BNL102: 0 | BNM102: Saldo anterior | BNT102: 0 | BNU102: Saldo anterior | BOB102: 0 | BOC102: Saldo anterior | BOJ102: 0 | BOK102: Saldo anterior | BOR102: 0 | BOS102: Saldo anterior | BOZ102: 0 | BPA102: Saldo anterior | BPH102: 0 | BPI102: Saldo anterior | BPP102: 0 | BPQ102: Saldo anterior | BPX102: 0 | BPY102: Saldo anterior | BQF102: 0 | BQG102: Saldo anterior | BQN102: 0 | BQO102: Saldo anterior | BQV102: 0 | BQW102: Saldo anterior | BRD102: 0 | BRE102: Saldo anterior | BRL102: 0 | BRM102: Saldo anterior | BRT102: 0 | BRU102: Saldo anterior | BSB102: 0 | BSC102: Saldo anterior | BSJ102: 0 | BSK102: Saldo anterior | BSR102: 0 | BSS102: Saldo anterior | BSZ102: 0 | BTA102: Saldo anterior | BTH102: 0 | BTI102: Saldo anterior | BTP102: 0 | BTQ102: Saldo anterior | BTX102: 0 | BTY102: Saldo anterior | BUF102: 0 | BUG102: Saldo anterior | BUN102: 0 | BUO102: Saldo anterior | BUV102: 0 | BUW102: Saldo anterior | BVD102: 0 | BVE102: Saldo anterior | BVL102: 0 | BVM102: Saldo anterior | BVT102: 0 | BVU102: Saldo anterior | BWB102: 0 | BWC102: Saldo anterior | BWJ102: 0 | BWK102: Saldo anterior | BWR102: 0 | BWS102: Saldo anterior | BWZ102: 0 | BXA102: Saldo anterior | BXH102: 0 | BXI102: Saldo anterior | BXP102: 0 | BXQ102: Saldo anterior | BXX102: 0 | BXY102: Saldo anterior | BYF102: 0 | BYG102: Saldo anterior | BYN102: 0 | BYO102: Saldo anterior | BYV102: 0 | BYW102: Saldo anterior | BZD102: 0 | BZE102: Saldo anterior | BZL102: 0 | BZM102: Saldo anterior | BZT102: 0 | BZU102: Saldo anterior | CAB102: 0 | CAC102: Saldo anterior | CAJ102: 0 | CAK102: Saldo anterior | CAR102: 0 | CAS102: Saldo anterior | CAZ102: 0 | CBA102: Saldo anterior | CBH102: 0 | CBI102: Saldo anterior | CBP102: 0 | CBQ102: Saldo anterior | CBX102: 0 | CBY102: Saldo anterior | CCF102: 0 | CCG102: Saldo anterior | CCN102: 0 | CCO102: Saldo anterior | CCV102: 0 | CCW102: Saldo anterior | CDD102: 0 | CDE102: Saldo anterior | CDL102: 0 | CDM102: Saldo anterior | CDT102: 0 | CDU102: Saldo anterior | CEB102: 0 | CEC102: Saldo anterior | CEJ102: 0 | CEK102: Saldo anterior | CER102: 0 | CES102: Saldo anterior | CEZ102: 0 | CFA102: Saldo anterior | CFH102: 0 | CFI102: Saldo anterior | CFP102: 0 | CFQ102: Saldo anterior | CFX102: 0 | CFY102: Saldo anterior | CGF102: 0 | CGG102: Saldo anterior | CGN102: 0 | CGO102: Saldo anterior | CGV102: 0 | CGW102: Saldo anterior | CHD102: 0 | CHE102: Saldo anterior | CHL102: 0 | CHM102: Saldo anterior | CHT102: 0 | CHU102: Saldo anterior | CIB102: 0 | CIC102: Saldo anterior | CIJ102: 0 | CIK102: Saldo anterior | CIR102: 0 | CIS102: Saldo anterior | CIZ102: 0 | CJA102: Saldo anterior | CJH102: 0 | CJI102: Saldo anterior | CJP102: 0 | CJQ102: Saldo anterior | CJX102: 0 | CJY102: Saldo anterior | CKF102: 0 | CKG102: Saldo anterior | CKN102: 0 | CKO102: Saldo anterior | CKV102: 0 | CKW102: Saldo anterior | CLD102: 0 | CLE102: Saldo anterior | CLL102: 0 | CLM102: Saldo anterior | CLT102: 0 | CLU102: Saldo anterior | CMB102: 0 | CMC102: Saldo anterior | CMJ102: 0 | CMK102: Saldo anterior | CMR102: 0 | CMS102: Saldo anterior | CMZ102: 0 | CNA102: Saldo anterior | CNH102: 0 | CNI102: Saldo anterior | CNP102: 0 | CNQ102: Saldo anterior | CNX102: 0 | CNY102: Saldo anterior | COF102: 0 | COG102: Saldo anterior | CON102: 0 | COO102: Saldo anterior | COV102: 0 | COW102: Saldo anterior | CPD102: 0 | CPE102: Saldo anterior | CPL102: 0 | CPM102: Saldo anterior | CPT102: 0 | CPU102: Saldo anterior | CQB102: 0 | CQC102: Saldo anterior | CQJ102: 0 | CQK102: Saldo anterior | CQR102: 0 | CQS102: Saldo anterior | CQZ102: 0 | CRA102: Saldo anterior | CRH102: 0 | CRI102: Saldo anterior | CRP102: 0 | CRQ102: Saldo anterior | CRX102: 0 | CRY102: Saldo anterior | CSF102: 0 | CSG102: Saldo anterior | CSN102: 0 | CSO102: Saldo anterior | CSV102: 0 | CSW102: Saldo anterior | CTD102: 0 | CTE102: Saldo anterior | CTL102: 0 | CTM102: Saldo anterior | CTT102: 0 | CTU102: Saldo anterior | CUB102: 0 | CUC102: Saldo anterior | CUJ102: 0 | CUK102: Saldo anterior | CUR102: 0 | CUS102: Saldo anterior | CUZ102: 0 | CVA102: Saldo anterior | CVH102: 0 | CVI102: Saldo anterior | CVP102: 0 | CVQ102: Saldo anterior | CVX102: 0 | CVY102: Saldo anterior | CWF102: 0 | CWG102: Saldo anterior | CWN102: 0 | CWO102: Saldo anterior | CWV102: 0 | CWW102: Saldo anterior | CXD102: 0 | CXE102: Saldo anterior | CXL102: 0 | CXM102: Saldo anterior | CXT102: 0 | CXU102: Saldo anterior | CYB102: 0 | CYC102: Saldo anterior | CYJ102: 0 | CYK102: Saldo anterior | CYR102: 0 | CYS102: Saldo anterior | CYZ102: 0 | CZA102: Saldo anterior | CZH102: 0 | CZI102: Saldo anterior | CZP102: 0 | CZQ102: Saldo anterior | CZX102: 0 | CZY102: Saldo anterior | DAF102: 0 | DAG102: Saldo anterior | DAN102: 0 | DAO102: Saldo anterior | DAV102: 0 | DAW102: Saldo anterior | DBD102: 0 | DBE102: Saldo anterior | DBL102: 0 | DBM102: Saldo anterior | DBT102: 0 | DBU102: Saldo anterior | DCB102: 0 | DCC102: Saldo anterior | DCJ102: 0 | DCK102: Saldo anterior | DCR102: 0 | DCS102: Saldo anterior | DCZ102: 0 | DDA102: Saldo anterior | DDH102: 0 | DDI102: Saldo anterior | DDP102: 0 | DDQ102: Saldo anterior | DDX102: 0 | DDY102: Saldo anterior | DEF102: 0 | DEG102: Saldo anterior | DEN102: 0 | DEO102: Saldo anterior | DEV102: 0 | DEW102: Saldo anterior | DFD102: 0 | DFE102: Saldo anterior | DFL102: 0 | DFM102: Saldo anterior | DFT102: 0 | DFU102: Saldo anterior | DGB102: 0 | DGC102: Saldo anterior | DGJ102: 0 | DGK102: Saldo anterior | DGR102: 0 | DGS102: Saldo anterior | DGZ102: 0 | DHA102: Saldo anterior | DHH102: 0 | DHI102: Saldo anterior | DHP102: 0 | DHQ102: Saldo anterior | DHX102: 0 | DHY102: Saldo anterior | DIF102: 0 | DIG102: Saldo anterior | DIN102: 0 | DIO102: Saldo anterior | DIV102: 0 | DIW102: Saldo anterior | DJD102: 0 | DJE102: Saldo anterior | DJL102: 0 | DJM102: Saldo anterior | DJT102: 0 | DJU102: Saldo anterior | DKB102: 0 | DKC102: Saldo anterior | DKJ102: 0 | DKK102: Saldo anterior | DKR102: 0 | DKS102: Saldo anterior | DKZ102: 0 | DLA102: Saldo anterior | DLH102: 0 | DLI102: Saldo anterior | DLP102: 0 | DLQ102: Saldo anterior | DLX102: 0 | DLY102: Saldo anterior | DMF102: 0 | DMG102: Saldo anterior | DMN102: 0 | DMO102: Saldo anterior | DMV102: 0 | DMW102: Saldo anterior | DND102: 0 | DNE102: Saldo anterior | DNL102: 0 | DNM102: Saldo anterior | DNT102: 0 | DNU102: Saldo anterior | DOB102: 0 | DOC102: Saldo anterior | DOJ102: 0 | DOK102: Saldo anterior | DOR102: 0 | DOS102: Saldo anterior | DOZ102: 0 | DPA102: Saldo anterior | DPH102: 0 | DPI102: Saldo anterior | DPP102: 0 | DPQ102: Saldo anterior | DPX102: 0 | DPY102: Saldo anterior | DQF102: 0 | DQG102: Saldo anterior | DQN102: 0 | DQO102: Saldo anterior | DQV102: 0 | DQW102: Saldo anterior | DRD102: 0 | DRE102: Saldo anterior | DRL102: 0 | DRM102: Saldo anterior | DRT102: 0 | DRU102: Saldo anterior | DSB102: 0 | DSC102: Saldo anterior | DSJ102: 0 | DSK102: Saldo anterior | DSR102: 0 | DSS102: Saldo anterior | DSZ102: 0 | DTA102: Saldo anterior | DTH102: 0 | DTI102: Saldo anterior | DTP102: 0 | DTQ102: Saldo anterior | DTX102: 0 | DTY102: Saldo anterior | DUF102: 0 | DUG102: Saldo anterior | DUN102: 0 | DUO102: Saldo anterior | DUV102: 0 | DUW102: Saldo anterior | DVD102: 0 | DVE102: Saldo anterior | DVL102: 0 | DVM102: Saldo anterior | DVT102: 0 | DVU102: Saldo anterior | DWB102: 0 | DWC102: Saldo anterior | DWJ102: 0 | DWK102: Saldo anterior | DWR102: 0 | DWS102: Saldo anterior | DWZ102: 0 | DXA102: Saldo anterior | DXH102: 0 | DXI102: Saldo anterior | DXP102: 0 | DXQ102: Saldo anterior | DXX102: 0 | DXY102: Saldo anterior | DYF102: 0 | DYG102: Saldo anterior | DYN102: 0 | DYO102: Saldo anterior | DYV102: 0 | DYW102: Saldo anterior | DZD102: 0 | DZE102: Saldo anterior | DZL102: 0 | DZM102: Saldo anterior | DZT102: 0 | DZU102: Saldo anterior | EAB102: 0 | EAC102: Saldo anterior | EAJ102: 0 | EAK102: Saldo anterior | EAR102: 0 | EAS102: Saldo anterior | EAZ102: 0 | EBA102: Saldo anterior | EBH102: 0 | EBI102: Saldo anterior | EBP102: 0 | EBQ102: Saldo anterior | EBX102: 0 | EBY102: Saldo anterior | ECF102: 0 | ECG102: Saldo anterior | ECN102: 0 | ECO102: Saldo anterior | ECV102: 0 | ECW102: Saldo anterior | EDD102: 0 | EDE102: Saldo anterior | EDL102: 0 | EDM102: Saldo anterior | EDT102: 0 | EDU102: Saldo anterior | EEB102: 0 | EEC102: Saldo anterior | EEJ102: 0 | EEK102: Saldo anterior | EER102: 0 | EES102: Saldo anterior | EEZ102: 0 | EFA102: Saldo anterior | EFH102: 0 | EFI102: Saldo anterior | EFP102: 0 | EFQ102: Saldo anterior | EFX102: 0 | EFY102: Saldo anterior | EGF102: 0 | EGG102: Saldo anterior | EGN102: 0 | EGO102: Saldo anterior | EGV102: 0 | EGW102: Saldo anterior | EHD102: 0 | EHE102: Saldo anterior | EHL102: 0 | EHM102: Saldo anterior | EHT102: 0 | EHU102: Saldo anterior | EIB102: 0 | EIC102: Saldo anterior | EIJ102: 0 | EIK102: Saldo anterior | EIR102: 0 | EIS102: Saldo anterior | EIZ102: 0 | EJA102: Saldo anterior | EJH102: 0 | EJI102: Saldo anterior | EJP102: 0 | EJQ102: Saldo anterior | EJX102: 0 | EJY102: Saldo anterior | EKF102: 0 | EKG102: Saldo anterior | EKN102: 0 | EKO102: Saldo anterior | EKV102: 0 | EKW102: Saldo anterior | ELD102: 0 | ELE102: Saldo anterior | ELL102: 0 | ELM102: Saldo anterior | ELT102: 0 | ELU102: Saldo anterior | EMB102: 0 | EMC102: Saldo anterior | EMJ102: 0 | EMK102: Saldo anterior | EMR102: 0 | EMS102: Saldo anterior | EMZ102: 0 | ENA102: Saldo anterior | ENH102: 0 | ENI102: Saldo anterior | ENP102: 0 | ENQ102: Saldo anterior | ENX102: 0 | ENY102: Saldo anterior | EOF102: 0 | EOG102: Saldo anterior | EON102: 0 | EOO102: Saldo anterior | EOV102: 0 | EOW102: Saldo anterior | EPD102: 0 | EPE102: Saldo anterior | EPL102: 0 | EPM102: Saldo anterior | EPT102: 0 | EPU102: Saldo anterior | EQB102: 0 | EQC102: Saldo anterior | EQJ102: 0 | EQK102: Saldo anterior | EQR102: 0 | EQS102: Saldo anterior | EQZ102: 0 | ERA102: Saldo anterior | ERH102: 0 | ERI102: Saldo anterior | ERP102: 0 | ERQ102: Saldo anterior | ERX102: 0 | ERY102: Saldo anterior | ESF102: 0 | ESG102: Saldo anterior | ESN102: 0 | ESO102: Saldo anterior | ESV102: 0 | ESW102: Saldo anterior | ETD102: 0 | ETE102: Saldo anterior | ETL102: 0 | ETM102: Saldo anterior | ETT102: 0 | ETU102: Saldo anterior | EUB102: 0 | EUC102: Saldo anterior | EUJ102: 0 | EUK102: Saldo anterior | EUR102: 0 | EUS102: Saldo anterior | EUZ102: 0 | EVA102: Saldo anterior | EVH102: 0 | EVI102: Saldo anterior | EVP102: 0 | EVQ102: Saldo anterior | EVX102: 0 | EVY102: Saldo anterior | EWF102: 0 | EWG102: Saldo anterior | EWN102: 0 | EWO102: Saldo anterior | EWV102: 0 | EWW102: Saldo anterior | EXD102: 0 | EXE102: Saldo anterior | EXL102: 0 | EXM102: Saldo anterior | EXT102: 0 | EXU102: Saldo anterior | EYB102: 0 | EYC102: Saldo anterior | EYJ102: 0 | EYK102: Saldo anterior | EYR102: 0 | EYS102: Saldo anterior | EYZ102: 0 | EZA102: Saldo anterior | EZH102: 0 | EZI102: Saldo anterior | EZP102: 0 | EZQ102: Saldo anterior | EZX102: 0 | EZY102: Saldo anterior | FAF102: 0 | FAG102: Saldo anterior | FAN102: 0 | FAO102: Saldo anterior | FAV102: 0 | FAW102: Saldo anterior | FBD102: 0 | FBE102: Saldo anterior | FBL102: 0 | FBM102: Saldo anterior | FBT102: 0 | FBU102: Saldo anterior | FCB102: 0 | FCC102: Saldo anterior | FCJ102: 0 | FCK102: Saldo anterior | FCR102: 0 | FCS102: Saldo anterior | FCZ102: 0 | FDA102: Saldo anterior | FDH102: 0 | FDI102: Saldo anterior | FDP102: 0 | FDQ102: Saldo anterior | FDX102: 0 | FDY102: Saldo anterior | FEF102: 0 | FEG102: Saldo anterior | FEN102: 0 | FEO102: Saldo anterior | FEV102: 0 | FEW102: Saldo anterior | FFD102: 0 | FFE102: Saldo anterior | FFL102: 0 | FFM102: Saldo anterior | FFT102: 0 | FFU102: Saldo anterior | FGB102: 0 | FGC102: Saldo anterior | FGJ102: 0 | FGK102: Saldo anterior | FGR102: 0 | FGS102: Saldo anterior | FGZ102: 0 | FHA102: Saldo anterior | FHH102: 0 | FHI102: Saldo anterior | FHP102: 0 | FHQ102: Saldo anterior | FHX102: 0 | FHY102: Saldo anterior | FIF102: 0 | FIG102: Saldo anterior | FIN102: 0 | FIO102: Saldo anterior | FIV102: 0 | FIW102: Saldo anterior | FJD102: 0 | FJE102: Saldo anterior | FJL102: 0 | FJM102: Saldo anterior | FJT102: 0 | FJU102: Saldo anterior | FKB102: 0 | FKC102: Saldo anterior | FKJ102: 0 | FKK102: Saldo anterior | FKR102: 0 | FKS102: Saldo anterior | FKZ102: 0 | FLA102: Saldo anterior | FLH102: 0 | FLI102: Saldo anterior | FLP102: 0 | FLQ102: Saldo anterior | FLX102: 0 | FLY102: Saldo anterior | FMF102: 0 | FMG102: Saldo anterior | FMN102: 0 | FMO102: Saldo anterior | FMV102: 0 | FMW102: Saldo anterior | FND102: 0 | FNE102: Saldo anterior | FNL102: 0 | FNM102: Saldo anterior | FNT102: 0 | FNU102: Saldo anterior | FOB102: 0 | FOC102: Saldo anterior | FOJ102: 0 | FOK102: Saldo anterior | FOR102: 0 | FOS102: Saldo anterior | FOZ102: 0 | FPA102: Saldo anterior | FPH102: 0 | FPI102: Saldo anterior | FPP102: 0 | FPQ102: Saldo anterior | FPX102: 0 | FPY102: Saldo anterior | FQF102: 0 | FQG102: Saldo anterior | FQN102: 0 | FQO102: Saldo anterior | FQV102: 0 | FQW102: Saldo anterior | FRD102: 0 | FRE102: Saldo anterior | FRL102: 0 | FRM102: Saldo anterior | FRT102: 0 | FRU102: Saldo anterior | FSB102: 0 | FSC102: Saldo anterior | FSJ102: 0 | FSK102: Saldo anterior | FSR102: 0 | FSS102: Saldo anterior | FSZ102: 0 | FTA102: Saldo anterior | FTH102: 0 | FTI102: Saldo anterior | FTP102: 0 | FTQ102: Saldo anterior | FTX102: 0 | FTY102: Saldo anterior | FUF102: 0 | FUG102: Saldo anterior | FUN102: 0 | FUO102: Saldo anterior | FUV102: 0 | FUW102: Saldo anterior | FVD102: 0 | FVE102: Saldo anterior | FVL102: 0 | FVM102: Saldo anterior | FVT102: 0 | FVU102: Saldo anterior | FWB102: 0 | FWC102: Saldo anterior | FWJ102: 0 | FWK102: Saldo anterior | FWR102: 0 | FWS102: Saldo anterior | FWZ102: 0 | FXA102: Saldo anterior | FXH102: 0 | FXI102: Saldo anterior | FXP102: 0 | FXQ102: Saldo anterior | FXX102: 0 | FXY102: Saldo anterior | FYF102: 0 | FYG102: Saldo anterior | FYN102: 0 | FYO102: Saldo anterior | FYV102: 0 | FYW102: Saldo anterior | FZD102: 0 | FZE102: Saldo anterior | FZL102: 0 | FZM102: Saldo anterior | FZT102: 0 | FZU102: Saldo anterior | GAB102: 0 | GAC102: Saldo anterior | GAJ102: 0 | GAK102: Saldo anterior | GAR102: 0 | GAS102: Saldo anterior | GAZ102: 0 | GBA102: Saldo anterior | GBH102: 0 | GBI102: Saldo anterior | GBP102: 0 | GBQ102: Saldo anterior | GBX102: 0 | GBY102: Saldo anterior | GCF102: 0 | GCG102: Saldo anterior | GCN102: 0 | GCO102: Saldo anterior | GCV102: 0 | GCW102: Saldo anterior | GDD102: 0 | GDE102: Saldo anterior | GDL102: 0 | GDM102: Saldo anterior | GDT102: 0 | GDU102: Saldo anterior | GEB102: 0 | GEC102: Saldo anterior | GEJ102: 0 | GEK102: Saldo anterior | GER102: 0 | GES102: Saldo anterior | GEZ102: 0 | GFA102: Saldo anterior | GFH102: 0 | GFI102: Saldo anterior | GFP102: 0 | GFQ102: Saldo anterior | GFX102: 0 | GFY102: Saldo anterior | GGF102: 0 | GGG102: Saldo anterior | GGN102: 0 | GGO102: Saldo anterior | GGV102: 0 | GGW102: Saldo anterior | GHD102: 0 | GHE102: Saldo anterior | GHL102: 0 | GHM102: Saldo anterior | GHT102: 0 | GHU102: Saldo anterior | GIB102: 0 | GIC102: Saldo anterior | GIJ102: 0 | GIK102: Saldo anterior | GIR102: 0 | GIS102: Saldo anterior | GIZ102: 0 | GJA102: Saldo anterior | GJH102: 0 | GJI102: Saldo anterior | GJP102: 0 | GJQ102: Saldo anterior | GJX102: 0 | GJY102: Saldo anterior | GKF102: 0 | GKG102: Saldo anterior | GKN102: 0 | GKO102: Saldo anterior | GKV102: 0 | GKW102: Saldo anterior | GLD102: 0 | GLE102: Saldo anterior | GLL102: 0 | GLM102: Saldo anterior | GLT102: 0 | GLU102: Saldo anterior | GMB102: 0 | GMC102: Saldo anterior | GMJ102: 0 | GMK102: Saldo anterior | GMR102: 0 | GMS102: Saldo anterior | GMZ102: 0 | GNA102: Saldo anterior | GNH102: 0 | GNI102: Saldo anterior | GNP102: 0 | GNQ102: Saldo anterior | GNX102: 0 | GNY102: Saldo anterior | GOF102: 0 | GOG102: Saldo anterior | GON102: 0 | GOO102: Saldo anterior | GOV102: 0 | GOW102: Saldo anterior | GPD102: 0 | GPE102: Saldo anterior | GPL102: 0 | GPM102: Saldo anterior | GPT102: 0 | GPU102: Saldo anterior | GQB102: 0 | GQC102: Saldo anterior | GQJ102: 0 | GQK102: Saldo anterior | GQR102: 0 | GQS102: Saldo anterior | GQZ102: 0 | GRA102: Saldo anterior | GRH102: 0 | GRI102: Saldo anterior | GRP102: 0 | GRQ102: Saldo anterior | GRX102: 0 | GRY102: Saldo anterior | GSF102: 0 | GSG102: Saldo anterior | GSN102: 0 | GSO102: Saldo anterior | GSV102: 0 | GSW102: Saldo anterior | GTD102: 0 | GTE102: Saldo anterior | GTL102: 0 | GTM102: Saldo anterior | GTT102: 0 | GTU102: Saldo anterior | GUB102: 0 | GUC102: Saldo anterior | GUJ102: 0 | GUK102: Saldo anterior | GUR102: 0 | GUS102: Saldo anterior | GUZ102: 0 | GVA102: Saldo anterior | GVH102: 0 | GVI102: Saldo anterior | GVP102: 0 | GVQ102: Saldo anterior | GVX102: 0 | GVY102: Saldo anterior | GWF102: 0 | GWG102: Saldo anterior | GWN102: 0 | GWO102: Saldo anterior | GWV102: 0 | GWW102: Saldo anterior | GXD102: 0 | GXE102: Saldo anterior | GXL102: 0 | GXM102: Saldo anterior | GXT102: 0 | GXU102: Saldo anterior | GYB102: 0 | GYC102: Saldo anterior | GYJ102: 0 | GYK102: Saldo anterior | GYR102: 0 | GYS102: Saldo anterior | GYZ102: 0 | GZA102: Saldo anterior | GZH102: 0 | GZI102: Saldo anterior | GZP102: 0 | GZQ102: Saldo anterior | GZX102: 0 | GZY102: Saldo anterior | HAF102: 0 | HAG102: Saldo anterior | HAN102: 0 | HAO102: Saldo anterior | HAV102: 0 | HAW102: Saldo anterior | HBD102: 0 | HBE102: Saldo anterior | HBL102: 0 | HBM102: Saldo anterior | HBT102: 0 | HBU102: Saldo anterior | HCB102: 0 | HCC102: Saldo anterior | HCJ102: 0 | HCK102: Saldo anterior | HCR102: 0 | HCS102: Saldo anterior | HCZ102: 0 | HDA102: Saldo anterior | HDH102: 0 | HDI102: Saldo anterior | HDP102: 0 | HDQ102: Saldo anterior | HDX102: 0 | HDY102: Saldo anterior | HEF102: 0 | HEG102: Saldo anterior | HEN102: 0 | HEO102: Saldo anterior | HEV102: 0 | HEW102: Saldo anterior | HFD102: 0 | HFE102: Saldo anterior | HFL102: 0 | HFM102: Saldo anterior | HFT102: 0 | HFU102: Saldo anterior | HGB102: 0 | HGC102: Saldo anterior | HGJ102: 0 | HGK102: Saldo anterior | HGR102: 0 | HGS102: Saldo anterior | HGZ102: 0 | HHA102: Saldo anterior | HHH102: 0 | HHI102: Saldo anterior | HHP102: 0 | HHQ102: Saldo anterior | HHX102: 0 | HHY102: Saldo anterior | HIF102: 0 | HIG102: Saldo anterior | HIN102: 0 | HIO102: Saldo anterior | HIV102: 0 | HIW102: Saldo anterior | HJD102: 0 | HJE102: Saldo anterior | HJL102: 0 | HJM102: Saldo anterior | HJT102: 0 | HJU102: Saldo anterior | HKB102: 0 | HKC102: Saldo anterior | HKJ102: 0 | HKK102: Saldo anterior | HKR102: 0 | HKS102: Saldo anterior | HKZ102: 0 | HLA102: Saldo anterior | HLH102: 0 | HLI102: Saldo anterior | HLP102: 0 | HLQ102: Saldo anterior | HLX102: 0 | HLY102: Saldo anterior | HMF102: 0 | HMG102: Saldo anterior | HMN102: 0 | HMO102: Saldo anterior | HMV102: 0 | HMW102: Saldo anterior | HND102: 0 | HNE102: Saldo anterior | HNL102: 0 | HNM102: Saldo anterior | HNT102: 0 | HNU102: Saldo anterior | HOB102: 0 | HOC102: Saldo anterior | HOJ102: 0 | HOK102: Saldo anterior | HOR102: 0 | HOS102: Saldo anterior | HOZ102: 0 | HPA102: Saldo anterior | HPH102: 0 | HPI102: Saldo anterior | HPP102: 0 | HPQ102: Saldo anterior | HPX102: 0 | HPY102: Saldo anterior | HQF102: 0 | HQG102: Saldo anterior | HQN102: 0 | HQO102: Saldo anterior | HQV102: 0 | HQW102: Saldo anterior | HRD102: 0 | HRE102: Saldo anterior | HRL102: 0 | HRM102: Saldo anterior | HRT102: 0 | HRU102: Saldo anterior | HSB102: 0 | HSC102: Saldo anterior | HSJ102: 0 | HSK102: Saldo anterior | HSR102: 0 | HSS102: Saldo anterior | HSZ102: 0 | HTA102: Saldo anterior | HTH102: 0 | HTI102: Saldo anterior | HTP102: 0 | HTQ102: Saldo anterior | HTX102: 0 | HTY102: Saldo anterior | HUF102: 0 | HUG102: Saldo anterior | HUN102: 0 | HUO102: Saldo anterior | HUV102: 0 | HUW102: Saldo anterior | HVD102: 0 | HVE102: Saldo anterior | HVL102: 0 | HVM102: Saldo anterior | HVT102: 0 | HVU102: Saldo anterior | HWB102: 0 | HWC102: Saldo anterior | HWJ102: 0 | HWK102: Saldo anterior | HWR102: 0 | HWS102: Saldo anterior | HWZ102: 0 | HXA102: Saldo anterior | HXH102: 0 | HXI102: Saldo anterior | HXP102: 0 | HXQ102: Saldo anterior | HXX102: 0 | HXY102: Saldo anterior | HYF102: 0 | HYG102: Saldo anterior | HYN102: 0 | HYO102: Saldo anterior | HYV102: 0 | HYW102: Saldo anterior | HZD102: 0 | HZE102: Saldo anterior | HZL102: 0 | HZM102: Saldo anterior | HZT102: 0 | HZU102: Saldo anterior | IAB102: 0 | IAC102: Saldo anterior | IAJ102: 0 | IAK102: Saldo anterior | IAR102: 0 | IAS102: Saldo anterior | IAZ102: 0 | IBA102: Saldo anterior | IBH102: 0 | IBI102: Saldo anterior | IBP102: 0 | IBQ102: Saldo anterior | IBX102: 0 | IBY102: Saldo anterior | ICF102: 0 | ICG102: Saldo anterior | ICN102: 0 | ICO102: Saldo anterior | ICV102: 0 | ICW102: Saldo anterior | IDD102: 0 | IDE102: Saldo anterior | IDL102: 0 | IDM102: Saldo anterior | IDT102: 0 | IDU102: Saldo anterior | IEB102: 0 | IEC102: Saldo anterior | IEJ102: 0 | IEK102: Saldo anterior | IER102: 0 | IES102: Saldo anterior | IEZ102: 0 | IFA102: Saldo anterior | IFH102: 0 | IFI102: Saldo anterior | IFP102: 0 | IFQ102: Saldo anterior | IFX102: 0 | IFY102: Saldo anterior | IGF102: 0 | IGG102: Saldo anterior | IGN102: 0 | IGO102: Saldo anterior | IGV102: 0 | IGW102: Saldo anterior | IHD102: 0 | IHE102: Saldo anterior | IHL102: 0 | IHM102: Saldo anterior | IHT102: 0 | IHU102: Saldo anterior | IIB102: 0 | IIC102: Saldo anterior | IIJ102: 0 | IIK102: Saldo anterior | IIR102: 0 | IIS102: Saldo anterior | IIZ102: 0 | IJA102: Saldo anterior | IJH102: 0 | IJI102: Saldo anterior | IJP102: 0 | IJQ102: Saldo anterior | IJX102: 0 | IJY102: Saldo anterior | IKF102: 0 | IKG102: Saldo anterior | IKN102: 0 | IKO102: Saldo anterior | IKV102: 0 | IKW102: Saldo anterior | ILD102: 0 | ILE102: Saldo anterior | ILL102: 0 | ILM102: Saldo anterior | ILT102: 0 | ILU102: Saldo anterior | IMB102: 0 | IMC102: Saldo anterior | IMJ102: 0 | IMK102: Saldo anterior | IMR102: 0 | IMS102: Saldo anterior | IMZ102: 0 | INA102: Saldo anterior | INH102: 0 | INI102: Saldo anterior | INP102: 0 | INQ102: Saldo anterior | INX102: 0 | INY102: Saldo anterior | IOF102: 0 | IOG102: Saldo anterior | ION102: 0 | IOO102: Saldo anterior | IOV102: 0 | IOW102: Saldo anterior | IPD102: 0 | IPE102: Saldo anterior | IPL102: 0 | IPM102: Saldo anterior | IPT102: 0 | IPU102: Saldo anterior | IQB102: 0 | IQC102: Saldo anterior | IQJ102: 0 | IQK102: Saldo anterior | IQR102: 0 | IQS102: Saldo anterior | IQZ102: 0 | IRA102: Saldo anterior | IRH102: 0 | IRI102: Saldo anterior | IRP102: 0 | IRQ102: Saldo anterior | IRX102: 0 | IRY102: Saldo anterior | ISF102: 0 | ISG102: Saldo anterior | ISN102: 0 | ISO102: Saldo anterior | ISV102: 0 | ISW102: Saldo anterior | ITD102: 0 | ITE102: Saldo anterior | ITL102: 0 | ITM102: Saldo anterior | ITT102: 0 | ITU102: Saldo anterior | IUB102: 0 | IUC102: Saldo anterior | IUJ102: 0 | IUK102: Saldo anterior | IUR102: 0 | IUS102: Saldo anterior | IUZ102: 0 | IVA102: Saldo anterior | IVH102: 0 | IVI102: Saldo anterior | IVP102: 0 | IVQ102: Saldo anterior | IVX102: 0 | IVY102: Saldo anterior | IWF102: 0 | IWG102: Saldo anterior | IWN102: 0 | IWO102: Saldo anterior | IWV102: 0 | IWW102: Saldo anterior | IXD102: 0 | IXE102: Saldo anterior | IXL102: 0 | IXM102: Saldo anterior | IXT102: 0 | IXU102: Saldo anterior | IYB102: 0 | IYC102: Saldo anterior | IYJ102: 0 | IYK102: Saldo anterior | IYR102: 0 | IYS102: Saldo anterior | IYZ102: 0 | IZA102: Saldo anterior | IZH102: 0 | IZI102: Saldo anterior | IZP102: 0 | IZQ102: Saldo anterior | IZX102: 0 | IZY102: Saldo anterior | JAF102: 0 | JAG102: Saldo anterior | JAN102: 0 | JAO102: Saldo anterior | JAV102: 0 | JAW102: Saldo anterior | JBD102: 0 | JBE102: Saldo anterior | JBL102: 0 | JBM102: Saldo anterior | JBT102: 0 | JBU102: Saldo anterior | JCB102: 0 | JCC102: Saldo anterior | JCJ102: 0 | JCK102: Saldo anterior | JCR102: 0 | JCS102: Saldo anterior | JCZ102: 0 | JDA102: Saldo anterior | JDH102: 0 | JDI102: Saldo anterior | JDP102: 0 | JDQ102: Saldo anterior | JDX102: 0 | JDY102: Saldo anterior | JEF102: 0 | JEG102: Saldo anterior | JEN102: 0 | JEO102: Saldo anterior | JEV102: 0 | JEW102: Saldo anterior | JFD102: 0 | JFE102: Saldo anterior | JFL102: 0 | JFM102: Saldo anterior | JFT102: 0 | JFU102: Saldo anterior | JGB102: 0 | JGC102: Saldo anterior | JGJ102: 0 | JGK102: Saldo anterior | JGR102: 0 | JGS102: Saldo anterior | JGZ102: 0 | JHA102: Saldo anterior | JHH102: 0 | JHI102: Saldo anterior | JHP102: 0 | JHQ102: Saldo anterior | JHX102: 0 | JHY102: Saldo anterior | JIF102: 0 | JIG102: Saldo anterior | JIN102: 0 | JIO102: Saldo anterior | JIV102: 0 | JIW102: Saldo anterior | JJD102: 0 | JJE102: Saldo anterior | JJL102: 0 | JJM102: Saldo anterior | JJT102: 0 | JJU102: Saldo anterior | JKB102: 0 | JKC102: Saldo anterior | JKJ102: 0 | JKK102: Saldo anterior | JKR102: 0 | JKS102: Saldo anterior | JKZ102: 0 | JLA102: Saldo anterior | JLH102: 0 | JLI102: Saldo anterior | JLP102: 0 | JLQ102: Saldo anterior | JLX102: 0 | JLY102: Saldo anterior | JMF102: 0 | JMG102: Saldo anterior | JMN102: 0 | JMO102: Saldo anterior | JMV102: 0 | JMW102: Saldo anterior | JND102: 0 | JNE102: Saldo anterior | JNL102: 0 | JNM102: Saldo anterior | JNT102: 0 | JNU102: Saldo anterior | JOB102: 0 | JOC102: Saldo anterior | JOJ102: 0 | JOK102: Saldo anterior | JOR102: 0 | JOS102: Saldo anterior | JOZ102: 0 | JPA102: Saldo anterior | JPH102: 0 | JPI102: Saldo anterior | JPP102: 0 | JPQ102: Saldo anterior | JPX102: 0 | JPY102: Saldo anterior | JQF102: 0 | JQG102: Saldo anterior | JQN102: 0 | JQO102: Saldo anterior | JQV102: 0 | JQW102: Saldo anterior | JRD102: 0 | JRE102: Saldo anterior | JRL102: 0 | JRM102: Saldo anterior | JRT102: 0 | JRU102: Saldo anterior | JSB102: 0 | JSC102: Saldo anterior | JSJ102: 0 | JSK102: Saldo anterior | JSR102: 0 | JSS102: Saldo anterior | JSZ102: 0 | JTA102: Saldo anterior | JTH102: 0 | JTI102: Saldo anterior | JTP102: 0 | JTQ102: Saldo anterior | JTX102: 0 | JTY102: Saldo anterior | JUF102: 0 | JUG102: Saldo anterior | JUN102: 0 | JUO102: Saldo anterior | JUV102: 0 | JUW102: Saldo anterior | JVD102: 0 | JVE102: Saldo anterior | JVL102: 0 | JVM102: Saldo anterior | JVT102: 0 | JVU102: Saldo anterior | JWB102: 0 | JWC102: Saldo anterior | JWJ102: 0 | JWK102: Saldo anterior | JWR102: 0 | JWS102: Saldo anterior | JWZ102: 0 | JXA102: Saldo anterior | JXH102: 0 | JXI102: Saldo anterior | JXP102: 0 | JXQ102: Saldo anterior | JXX102: 0 | JXY102: Saldo anterior | JYF102: 0 | JYG102: Saldo anterior | JYN102: 0 | JYO102: Saldo anterior | JYV102: 0 | JYW102: Saldo anterior | JZD102: 0 | JZE102: Saldo anterior | JZL102: 0 | JZM102: Saldo anterior | JZT102: 0 | JZU102: Saldo anterior | KAB102: 0 | KAC102: Saldo anterior | KAJ102: 0 | KAK102: Saldo anterior | KAR102: 0 | KAS102: Saldo anterior | KAZ102: 0 | KBA102: Saldo anterior | KBH102: 0 | KBI102: Saldo anterior | KBP102: 0 | KBQ102: Saldo anterior | KBX102: 0 | KBY102: Saldo anterior | KCF102: 0 | KCG102: Saldo anterior | KCN102: 0 | KCO102: Saldo anterior | KCV102: 0 | KCW102: Saldo anterior | KDD102: 0 | KDE102: Saldo anterior | KDL102: 0 | KDM102: Saldo anterior | KDT102: 0 | KDU102: Saldo anterior | KEB102: 0 | KEC102: Saldo anterior | KEJ102: 0 | KEK102: Saldo anterior | KER102: 0 | KES102: Saldo anterior | KEZ102: 0 | KFA102: Saldo anterior | KFH102: 0 | KFI102: Saldo anterior | KFP102: 0 | KFQ102: Saldo anterior | KFX102: 0 | KFY102: Saldo anterior | KGF102: 0 | KGG102: Saldo anterior | KGN102: 0 | KGO102: Saldo anterior | KGV102: 0 | KGW102: Saldo anterior | KHD102: 0 | KHE102: Saldo anterior | KHL102: 0 | KHM102: Saldo anterior | KHT102: 0 | KHU102: Saldo anterior | KIB102: 0 | KIC102: Saldo anterior | KIJ102: 0 | KIK102: Saldo anterior | KIR102: 0 | KIS102: Saldo anterior | KIZ102: 0 | KJA102: Saldo anterior | KJH102: 0 | KJI102: Saldo anterior | KJP102: 0 | KJQ102: Saldo anterior | KJX102: 0 | KJY102: Saldo anterior | KKF102: 0 | KKG102: Saldo anterior | KKN102: 0 | KKO102: Saldo anterior | KKV102: 0 | KKW102: Saldo anterior | KLD102: 0 | KLE102: Saldo anterior | KLL102: 0 | KLM102: Saldo anterior | KLT102: 0 | KLU102: Saldo anterior | KMB102: 0 | KMC102: Saldo anterior | KMJ102: 0 | KMK102: Saldo anterior | KMR102: 0 | KMS102: Saldo anterior | KMZ102: 0 | KNA102: Saldo anterior | KNH102: 0 | KNI102: Saldo anterior | KNP102: 0 | KNQ102: Saldo anterior | KNX102: 0 | KNY102: Saldo anterior | KOF102: 0 | KOG102: Saldo anterior | KON102: 0 | KOO102: Saldo anterior | KOV102: 0 | KOW102: Saldo anterior | KPD102: 0 | KPE102: Saldo anterior | KPL102: 0 | KPM102: Saldo anterior | KPT102: 0 | KPU102: Saldo anterior | KQB102: 0 | KQC102: Saldo anterior | KQJ102: 0 | KQK102: Saldo anterior | KQR102: 0 | KQS102: Saldo anterior | KQZ102: 0 | KRA102: Saldo anterior | KRH102: 0 | KRI102: Saldo anterior | KRP102: 0 | KRQ102: Saldo anterior | KRX102: 0 | KRY102: Saldo anterior | KSF102: 0 | KSG102: Saldo anterior | KSN102: 0 | KSO102: Saldo anterior | KSV102: 0 | KSW102: Saldo anterior | KTD102: 0 | KTE102: Saldo anterior | KTL102: 0 | KTM102: Saldo anterior | KTT102: 0 | KTU102: Saldo anterior | KUB102: 0 | KUC102: Saldo anterior | KUJ102: 0 | KUK102: Saldo anterior | KUR102: 0 | KUS102: Saldo anterior | KUZ102: 0 | KVA102: Saldo anterior | KVH102: 0 | KVI102: Saldo anterior | KVP102: 0 | KVQ102: Saldo anterior | KVX102: 0 | KVY102: Saldo anterior | KWF102: 0 | KWG102: Saldo anterior | KWN102: 0 | KWO102: Saldo anterior | KWV102: 0 | KWW102: Saldo anterior | KXD102: 0 | KXE102: Saldo anterior | KXL102: 0 | KXM102: Saldo anterior | KXT102: 0 | KXU102: Saldo anterior | KYB102: 0 | KYC102: Saldo anterior | KYJ102: 0 | KYK102: Saldo anterior | KYR102: 0 | KYS102: Saldo anterior | KYZ102: 0 | KZA102: Saldo anterior | KZH102: 0 | KZI102: Saldo anterior | KZP102: 0 | KZQ102: Saldo anterior | KZX102: 0 | KZY102: Saldo anterior | LAF102: 0 | LAG102: Saldo anterior | LAN102: 0 | LAO102: Saldo anterior | LAV102: 0 | LAW102: Saldo anterior | LBD102: 0 | LBE102: Saldo anterior | LBL102: 0 | LBM102: Saldo anterior | LBT102: 0 | LBU102: Saldo anterior | LCB102: 0 | LCC102: Saldo anterior | LCJ102: 0 | LCK102: Saldo anterior | LCR102: 0 | LCS102: Saldo anterior | LCZ102: 0 | LDA102: Saldo anterior | LDH102: 0 | LDI102: Saldo anterior | LDP102: 0 | LDQ102: Saldo anterior | LDX102: 0 | LDY102: Saldo anterior | LEF102: 0 | LEG102: Saldo anterior | LEN102: 0 | LEO102: Saldo anterior | LEV102: 0 | LEW102: Saldo anterior | LFD102: 0 | LFE102: Saldo anterior | LFL102: 0 | LFM102: Saldo anterior | LFT102: 0 | LFU102: Saldo anterior | LGB102: 0 | LGC102: Saldo anterior | LGJ102: 0 | LGK102: Saldo anterior | LGR102: 0 | LGS102: Saldo anterior | LGZ102: 0 | LHA102: Saldo anterior | LHH102: 0 | LHI102: Saldo anterior | LHP102: 0 | LHQ102: Saldo anterior | LHX102: 0 | LHY102: Saldo anterior | LIF102: 0 | LIG102: Saldo anterior | LIN102: 0 | LIO102: Saldo anterior | LIV102: 0 | LIW102: Saldo anterior | LJD102: 0 | LJE102: Saldo anterior | LJL102: 0 | LJM102: Saldo anterior | LJT102: 0 | LJU102: Saldo anterior | LKB102: 0 | LKC102: Saldo anterior | LKJ102: 0 | LKK102: Saldo anterior | LKR102: 0 | LKS102: Saldo anterior | LKZ102: 0 | LLA102: Saldo anterior | LLH102: 0 | LLI102: Saldo anterior | LLP102: 0 | LLQ102: Saldo anterior | LLX102: 0 | LLY102: Saldo anterior | LMF102: 0 | LMG102: Saldo anterior | LMN102: 0 | LMO102: Saldo anterior | LMV102: 0 | LMW102: Saldo anterior | LND102: 0 | LNE102: Saldo anterior | LNL102: 0 | LNM102: Saldo anterior | LNT102: 0 | LNU102: Saldo anterior | LOB102: 0 | LOC102: Saldo anterior | LOJ102: 0 | LOK102: Saldo anterior | LOR102: 0 | LOS102: Saldo anterior | LOZ102: 0 | LPA102: Saldo anterior | LPH102: 0 | LPI102: Saldo anterior | LPP102: 0 | LPQ102: Saldo anterior | LPX102: 0 | LPY102: Saldo anterior | LQF102: 0 | LQG102: Saldo anterior | LQN102: 0 | LQO102: Saldo anterior | LQV102: 0 | LQW102: Saldo anterior | LRD102: 0 | LRE102: Saldo anterior | LRL102: 0 | LRM102: Saldo anterior | LRT102: 0 | LRU102: Saldo anterior | LSB102: 0 | LSC102: Saldo anterior | LSJ102: 0 | LSK102: Saldo anterior | LSR102: 0 | LSS102: Saldo anterior | LSZ102: 0 | LTA102: Saldo anterior | LTH102: 0 | LTI102: Saldo anterior | LTP102: 0 | LTQ102: Saldo anterior | LTX102: 0 | LTY102: Saldo anterior | LUF102: 0 | LUG102: Saldo anterior | LUN102: 0 | LUO102: Saldo anterior | LUV102: 0 | LUW102: Saldo anterior | LVD102: 0 | LVE102: Saldo anterior | LVL102: 0 | LVM102: Saldo anterior | LVT102: 0 | LVU102: Saldo anterior | LWB102: 0 | LWC102: Saldo anterior | LWJ102: 0 | LWK102: Saldo anterior | LWR102: 0 | LWS102: Saldo anterior | LWZ102: 0 | LXA102: Saldo anterior | LXH102: 0 | LXI102: Saldo anterior | LXP102: 0 | LXQ102: Saldo anterior | LXX102: 0 | LXY102: Saldo anterior | LYF102: 0 | LYG102: Saldo anterior | LYN102: 0 | LYO102: Saldo anterior | LYV102: 0 | LYW102: Saldo anterior | LZD102: 0 | LZE102: Saldo anterior | LZL102: 0 | LZM102: Saldo anterior | LZT102: 0 | LZU102: Saldo anterior | MAB102: 0 | MAC102: Saldo anterior | MAJ102: 0 | MAK102: Saldo anterior | MAR102: 0 | MAS102: Saldo anterior | MAZ102: 0 | MBA102: Saldo anterior | MBH102: 0 | MBI102: Saldo anterior | MBP102: 0 | MBQ102: Saldo anterior | MBX102: 0 | MBY102: Saldo anterior | MCF102: 0 | MCG102: Saldo anterior | MCN102: 0 | MCO102: Saldo anterior | MCV102: 0 | MCW102: Saldo anterior | MDD102: 0 | MDE102: Saldo anterior | MDL102: 0 | MDM102: Saldo anterior | MDT102: 0 | MDU102: Saldo anterior | MEB102: 0 | MEC102: Saldo anterior | MEJ102: 0 | MEK102: Saldo anterior | MER102: 0 | MES102: Saldo anterior | MEZ102: 0 | MFA102: Saldo anterior | MFH102: 0 | MFI102: Saldo anterior | MFP102: 0 | MFQ102: Saldo anterior | MFX102: 0 | MFY102: Saldo anterior | MGF102: 0 | MGG102: Saldo anterior | MGN102: 0 | MGO102: Saldo anterior | MGV102: 0 | MGW102: Saldo anterior | MHD102: 0 | MHE102: Saldo anterior | MHL102: 0 | MHM102: Saldo anterior | MHT102: 0 | MHU102: Saldo anterior | MIB102: 0 | MIC102: Saldo anterior | MIJ102: 0 | MIK102: Saldo anterior | MIR102: 0 | MIS102: Saldo anterior | MIZ102: 0 | MJA102: Saldo anterior | MJH102: 0 | MJI102: Saldo anterior | MJP102: 0 | MJQ102: Saldo anterior | MJX102: 0 | MJY102: Saldo anterior | MKF102: 0 | MKG102: Saldo anterior | MKN102: 0 | MKO102: Saldo anterior | MKV102: 0 | MKW102: Saldo anterior | MLD102: 0 | MLE102: Saldo anterior | MLL102: 0 | MLM102: Saldo anterior | MLT102: 0 | MLU102: Saldo anterior | MMB102: 0 | MMC102: Saldo anterior | MMJ102: 0 | MMK102: Saldo anterior | MMR102: 0 | MMS102: Saldo anterior | MMZ102: 0 | MNA102: Saldo anterior | MNH102: 0 | MNI102: Saldo anterior | MNP102: 0 | MNQ102: Saldo anterior | MNX102: 0 | MNY102: Saldo anterior | MOF102: 0 | MOG102: Saldo anterior | MON102: 0 | MOO102: Saldo anterior | MOV102: 0 | MOW102: Saldo anterior | MPD102: 0 | MPE102: Saldo anterior | MPL102: 0 | MPM102: Saldo anterior | MPT102: 0 | MPU102: Saldo anterior | MQB102: 0 | MQC102: Saldo anterior | MQJ102: 0 | MQK102: Saldo anterior | MQR102: 0 | MQS102: Saldo anterior | MQZ102: 0 | MRA102: Saldo anterior | MRH102: 0 | MRI102: Saldo anterior | MRP102: 0 | MRQ102: Saldo anterior | MRX102: 0 | MRY102: Saldo anterior | MSF102: 0 | MSG102: Saldo anterior | MSN102: 0 | MSO102: Saldo anterior | MSV102: 0 | MSW102: Saldo anterior | MTD102: 0 | MTE102: Saldo anterior | MTL102: 0 | MTM102: Saldo anterior | MTT102: 0 | MTU102: Saldo anterior | MUB102: 0 | MUC102: Saldo anterior | MUJ102: 0 | MUK102: Saldo anterior | MUR102: 0 | MUS102: Saldo anterior | MUZ102: 0 | MVA102: Saldo anterior | MVH102: 0 | MVI102: Saldo anterior | MVP102: 0 | MVQ102: Saldo anterior | MVX102: 0 | MVY102: Saldo anterior | MWF102: 0 | MWG102: Saldo anterior | MWN102: 0 | MWO102: Saldo anterior | MWV102: 0 | MWW102: Saldo anterior | MXD102: 0 | MXE102: Saldo anterior | MXL102: 0 | MXM102: Saldo anterior | MXT102: 0 | MXU102: Saldo anterior | MYB102: 0 | MYC102: Saldo anterior | MYJ102: 0 | MYK102: Saldo anterior | MYR102: 0 | MYS102: Saldo anterior | MYZ102: 0 | MZA102: Saldo anterior | MZH102: 0 | MZI102: Saldo anterior | MZP102: 0 | MZQ102: Saldo anterior | MZX102: 0 | MZY102: Saldo anterior | NAF102: 0 | NAG102: Saldo anterior | NAN102: 0 | NAO102: Saldo anterior | NAV102: 0 | NAW102: Saldo anterior | NBD102: 0 | NBE102: Saldo anterior | NBL102: 0 | NBM102: Saldo anterior | NBT102: 0 | NBU102: Saldo anterior | NCB102: 0 | NCC102: Saldo anterior | NCJ102: 0 | NCK102: Saldo anterior | NCR102: 0 | NCS102: Saldo anterior | NCZ102: 0 | NDA102: Saldo anterior | NDH102: 0 | NDI102: Saldo anterior | NDP102: 0 | NDQ102: Saldo anterior | NDX102: 0 | NDY102: Saldo anterior | NEF102: 0 | NEG102: Saldo anterior | NEN102: 0 | NEO102: Saldo anterior | NEV102: 0 | NEW102: Saldo anterior | NFD102: 0 | NFE102: Saldo anterior | NFL102: 0 | NFM102: Saldo anterior | NFT102: 0 | NFU102: Saldo anterior | NGB102: 0 | NGC102: Saldo anterior | NGJ102: 0 | NGK102: Saldo anterior | NGR102: 0 | NGS102: Saldo anterior | NGZ102: 0 | NHA102: Saldo anterior | NHH102: 0 | NHI102: Saldo anterior | NHP102: 0 | NHQ102: Saldo anterior | NHX102: 0 | NHY102: Saldo anterior | NIF102: 0 | NIG102: Saldo anterior | NIN102: 0 | NIO102: Saldo anterior | NIV102: 0 | NIW102: Saldo anterior | NJD102: 0 | NJE102: Saldo anterior | NJL102: 0 | NJM102: Saldo anterior | NJT102: 0 | NJU102: Saldo anterior | NKB102: 0 | NKC102: Saldo anterior | NKJ102: 0 | NKK102: Saldo anterior | NKR102: 0 | NKS102: Saldo anterior | NKZ102: 0 | NLA102: Saldo anterior | NLH102: 0 | NLI102: Saldo anterior | NLP102: 0 | NLQ102: Saldo anterior | NLX102: 0 | NLY102: Saldo anterior | NMF102: 0 | NMG102: Saldo anterior | NMN102: 0 | NMO102: Saldo anterior | NMV102: 0 | NMW102: Saldo anterior | NND102: 0 | NNE102: Saldo anterior | NNL102: 0 | NNM102: Saldo anterior | NNT102: 0 | NNU102: Saldo anterior | NOB102: 0 | NOC102: Saldo anterior | NOJ102: 0 | NOK102: Saldo anterior | NOR102: 0 | NOS102: Saldo anterior | NOZ102: 0 | NPA102: Saldo anterior | NPH102: 0 | NPI102: Saldo anterior | NPP102: 0 | NPQ102: Saldo anterior | NPX102: 0 | NPY102: Saldo anterior | NQF102: 0 | NQG102: Saldo anterior | NQN102: 0 | NQO102: Saldo anterior | NQV102: 0 | NQW102: Saldo anterior | NRD102: 0 | NRE102: Saldo anterior | NRL102: 0 | NRM102: Saldo anterior | NRT102: 0 | NRU102: Saldo anterior | NSB102: 0 | NSC102: Saldo anterior | NSJ102: 0 | NSK102: Saldo anterior | NSR102: 0 | NSS102: Saldo anterior | NSZ102: 0 | NTA102: Saldo anterior | NTH102: 0 | NTI102: Saldo anterior | NTP102: 0 | NTQ102: Saldo anterior | NTX102: 0 | NTY102: Saldo anterior | NUF102: 0 | NUG102: Saldo anterior | NUN102: 0 | NUO102: Saldo anterior | NUV102: 0 | NUW102: Saldo anterior | NVD102: 0 | NVE102: Saldo anterior | NVL102: 0 | NVM102: Saldo anterior | NVT102: 0 | NVU102: Saldo anterior | NWB102: 0 | NWC102: Saldo anterior | NWJ102: 0 | NWK102: Saldo anterior | NWR102: 0 | NWS102: Saldo anterior | NWZ102: 0 | NXA102: Saldo anterior | NXH102: 0 | NXI102: Saldo anterior | NXP102: 0 | NXQ102: Saldo anterior | NXX102: 0 | NXY102: Saldo anterior | NYF102: 0 | NYG102: Saldo anterior | NYN102: 0 | NYO102: Saldo anterior | NYV102: 0 | NYW102: Saldo anterior | NZD102: 0 | NZE102: Saldo anterior | NZL102: 0 | NZM102: Saldo anterior | NZT102: 0 | NZU102: Saldo anterior | OAB102: 0 | OAC102: Saldo anterior | OAJ102: 0 | OAK102: Saldo anterior | OAR102: 0 | OAS102: Saldo anterior | OAZ102: 0 | OBA102: Saldo anterior | OBH102: 0 | OBI102: Saldo anterior | OBP102: 0 | OBQ102: Saldo anterior | OBX102: 0 | OBY102: Saldo anterior | OCF102: 0 | OCG102: Saldo anterior | OCN102: 0 | OCO102: Saldo anterior | OCV102: 0 | OCW102: Saldo anterior | ODD102: 0 | ODE102: Saldo anterior | ODL102: 0 | ODM102: Saldo anterior | ODT102: 0 | ODU102: Saldo anterior | OEB102: 0 | OEC102: Saldo anterior | OEJ102: 0 | OEK102: Saldo anterior | OER102: 0 | OES102: Saldo anterior | OEZ102: 0 | OFA102: Saldo anterior | OFH102: 0 | OFI102: Saldo anterior | OFP102: 0 | OFQ102: Saldo anterior | OFX102: 0 | OFY102: Saldo anterior | OGF102: 0 | OGG102: Saldo anterior | OGN102: 0 | OGO102: Saldo anterior | OGV102: 0 | OGW102: Saldo anterior | OHD102: 0 | OHE102: Saldo anterior | OHL102: 0 | OHM102: Saldo anterior | OHT102: 0 | OHU102: Saldo anterior | OIB102: 0 | OIC102: Saldo anterior | OIJ102: 0 | OIK102: Saldo anterior | OIR102: 0 | OIS102: Saldo anterior | OIZ102: 0 | OJA102: Saldo anterior | OJH102: 0 | OJI102: Saldo anterior | OJP102: 0 | OJQ102: Saldo anterior | OJX102: 0 | OJY102: Saldo anterior | OKF102: 0 | OKG102: Saldo anterior | OKN102: 0 | OKO102: Saldo anterior | OKV102: 0 | OKW102: Saldo anterior | OLD102: 0 | OLE102: Saldo anterior | OLL102: 0 | OLM102: Saldo anterior | OLT102: 0 | OLU102: Saldo anterior | OMB102: 0 | OMC102: Saldo anterior | OMJ102: 0 | OMK102: Saldo anterior | OMR102: 0 | OMS102: Saldo anterior | OMZ102: 0 | ONA102: Saldo anterior | ONH102: 0 | ONI102: Saldo anterior | ONP102: 0 | ONQ102: Saldo anterior | ONX102: 0 | ONY102: Saldo anterior | OOF102: 0 | OOG102: Saldo anterior | OON102: 0 | OOO102: Saldo anterior | OOV102: 0 | OOW102: Saldo anterior | OPD102: 0 | OPE102: Saldo anterior | OPL102: 0 | OPM102: Saldo anterior | OPT102: 0 | OPU102: Saldo anterior | OQB102: 0 | OQC102: Saldo anterior | OQJ102: 0 | OQK102: Saldo anterior | OQR102: 0 | OQS102: Saldo anterior | OQZ102: 0 | ORA102: Saldo anterior | ORH102: 0 | ORI102: Saldo anterior | ORP102: 0 | ORQ102: Saldo anterior | ORX102: 0 | ORY102: Saldo anterior | OSF102: 0 | OSG102: Saldo anterior | OSN102: 0 | OSO102: Saldo anterior | OSV102: 0 | OSW102: Saldo anterior | OTD102: 0 | OTE102: Saldo anterior | OTL102: 0 | OTM102: Saldo anterior | OTT102: 0 | OTU102: Saldo anterior | OUB102: 0 | OUC102: Saldo anterior | OUJ102: 0 | OUK102: Saldo anterior | OUR102: 0 | OUS102: Saldo anterior | OUZ102: 0 | OVA102: Saldo anterior | OVH102: 0 | OVI102: Saldo anterior | OVP102: 0 | OVQ102: Saldo anterior | OVX102: 0 | OVY102: Saldo anterior | OWF102: 0 | OWG102: Saldo anterior | OWN102: 0 | OWO102: Saldo anterior | OWV102: 0 | OWW102: Saldo anterior | OXD102: 0 | OXE102: Saldo anterior | OXL102: 0 | OXM102: Saldo anterior | OXT102: 0 | OXU102: Saldo anterior | OYB102: 0 | OYC102: Saldo anterior | OYJ102: 0 | OYK102: Saldo anterior | OYR102: 0 | OYS102: Saldo anterior | OYZ102: 0 | OZA102: Saldo anterior | OZH102: 0 | OZI102: Saldo anterior | OZP102: 0 | OZQ102: Saldo anterior | OZX102: 0 | OZY102: Saldo anterior | PAF102: 0 | PAG102: Saldo anterior | PAN102: 0 | PAO102: Saldo anterior | PAV102: 0 | PAW102: Saldo anterior | PBD102: 0 | PBE102: Saldo anterior | PBL102: 0 | PBM102: Saldo anterior | PBT102: 0 | PBU102: Saldo anterior | PCB102: 0 | PCC102: Saldo anterior | PCJ102: 0 | PCK102: Saldo anterior | PCR102: 0 | PCS102: Saldo anterior | PCZ102: 0 | PDA102: Saldo anterior | PDH102: 0 | PDI102: Saldo anterior | PDP102: 0 | PDQ102: Saldo anterior | PDX102: 0 | PDY102: Saldo anterior | PEF102: 0 | PEG102: Saldo anterior | PEN102: 0 | PEO102: Saldo anterior | PEV102: 0 | PEW102: Saldo anterior | PFD102: 0 | PFE102: Saldo anterior | PFL102: 0 | PFM102: Saldo anterior | PFT102: 0 | PFU102: Saldo anterior | PGB102: 0 | PGC102: Saldo anterior | PGJ102: 0 | PGK102: Saldo anterior | PGR102: 0 | PGS102: Saldo anterior | PGZ102: 0 | PHA102: Saldo anterior | PHH102: 0 | PHI102: Saldo anterior | PHP102: 0 | PHQ102: Saldo anterior | PHX102: 0 | PHY102: Saldo anterior | PIF102: 0 | PIG102: Saldo anterior | PIN102: 0 | PIO102: Saldo anterior | PIV102: 0 | PIW102: Saldo anterior | PJD102: 0 | PJE102: Saldo anterior | PJL102: 0 | PJM102: Saldo anterior | PJT102: 0 | PJU102: Saldo anterior | PKB102: 0 | PKC102: Saldo anterior | PKJ102: 0 | PKK102: Saldo anterior | PKR102: 0 | PKS102: Saldo anterior | PKZ102: 0 | PLA102: Saldo anterior | PLH102: 0 | PLI102: Saldo anterior | PLP102: 0 | PLQ102: Saldo anterior | PLX102: 0 | PLY102: Saldo anterior | PMF102: 0 | PMG102: Saldo anterior | PMN102: 0 | PMO102: Saldo anterior | PMV102: 0 | PMW102: Saldo anterior | PND102: 0 | PNE102: Saldo anterior | PNL102: 0 | PNM102: Saldo anterior | PNT102: 0 | PNU102: Saldo anterior | POB102: 0 | POC102: Saldo anterior | POJ102: 0 | POK102: Saldo anterior | POR102: 0 | POS102: Saldo anterior | POZ102: 0 | PPA102: Saldo anterior | PPH102: 0 | PPI102: Saldo anterior | PPP102: 0 | PPQ102: Saldo anterior | PPX102: 0 | PPY102: Saldo anterior | PQF102: 0 | PQG102: Saldo anterior | PQN102: 0 | PQO102: Saldo anterior | PQV102: 0 | PQW102: Saldo anterior | PRD102: 0 | PRE102: Saldo anterior | PRL102: 0 | PRM102: Saldo anterior | PRT102: 0 | PRU102: Saldo anterior | PSB102: 0 | PSC102: Saldo anterior | PSJ102: 0 | PSK102: Saldo anterior | PSR102: 0 | PSS102: Saldo anterior | PSZ102: 0 | PTA102: Saldo anterior | PTH102: 0 | PTI102: Saldo anterior | PTP102: 0 | PTQ102: Saldo anterior | PTX102: 0 | PTY102: Saldo anterior | PUF102: 0 | PUG102: Saldo anterior | PUN102: 0 | PUO102: Saldo anterior | PUV102: 0 | PUW102: Saldo anterior | PVD102: 0 | PVE102: Saldo anterior | PVL102: 0 | PVM102: Saldo anterior | PVT102: 0 | PVU102: Saldo anterior | PWB102: 0 | PWC102: Saldo anterior | PWJ102: 0 | PWK102: Saldo anterior | PWR102: 0 | PWS102: Saldo anterior | PWZ102: 0 | PXA102: Saldo anterior | PXH102: 0 | PXI102: Saldo anterior | PXP102: 0 | PXQ102: Saldo anterior | PXX102: 0 | PXY102: Saldo anterior | PYF102: 0 | PYG102: Saldo anterior | PYN102: 0 | PYO102: Saldo anterior | PYV102: 0 | PYW102: Saldo anterior | PZD102: 0 | PZE102: Saldo anterior | PZL102: 0 | PZM102: Saldo anterior | PZT102: 0 | PZU102: Saldo anterior | QAB102: 0 | QAC102: Saldo anterior | QAJ102: 0 | QAK102: Saldo anterior | QAR102: 0 | QAS102: Saldo anterior | QAZ102: 0 | QBA102: Saldo anterior | QBH102: 0 | QBI102: Saldo anterior | QBP102: 0 | QBQ102: Saldo anterior | QBX102: 0 | QBY102: Saldo anterior | QCF102: 0 | QCG102: Saldo anterior | QCN102: 0 | QCO102: Saldo anterior | QCV102: 0 | QCW102: Saldo anterior | QDD102: 0 | QDE102: Saldo anterior | QDL102: 0 | QDM102: Saldo anterior | QDT102: 0 | QDU102: Saldo anterior | QEB102: 0 | QEC102: Saldo anterior | QEJ102: 0 | QEK102: Saldo anterior | QER102: 0 | QES102: Saldo anterior | QEZ102: 0 | QFA102: Saldo anterior | QFH102: 0 | QFI102: Saldo anterior | QFP102: 0 | QFQ102: Saldo anterior | QFX102: 0 | QFY102: Saldo anterior | QGF102: 0 | QGG102: Saldo anterior | QGN102: 0 | QGO102: Saldo anterior | QGV102: 0 | QGW102: Saldo anterior | QHD102: 0 | QHE102: Saldo anterior | QHL102: 0 | QHM102: Saldo anterior | QHT102: 0 | QHU102: Saldo anterior | QIB102: 0 | QIC102: Saldo anterior | QIJ102: 0 | QIK102: Saldo anterior | QIR102: 0 | QIS102: Saldo anterior | QIZ102: 0 | QJA102: Saldo anterior | QJH102: 0 | QJI102: Saldo anterior | QJP102: 0 | QJQ102: Saldo anterior | QJX102: 0 | QJY102: Saldo anterior | QKF102: 0 | QKG102: Saldo anterior | QKN102: 0 | QKO102: Saldo anterior | QKV102: 0 | QKW102: Saldo anterior | QLD102: 0 | QLE102: Saldo anterior | QLL102: 0 | QLM102: Saldo anterior | QLT102: 0 | QLU102: Saldo anterior | QMB102: 0 | QMC102: Saldo anterior | QMJ102: 0 | QMK102: Saldo anterior | QMR102: 0 | QMS102: Saldo anterior | QMZ102: 0 | QNA102: Saldo anterior | QNH102: 0 | QNI102: Saldo anterior | QNP102: 0 | QNQ102: Saldo anterior | QNX102: 0 | QNY102: Saldo anterior | QOF102: 0 | QOG102: Saldo anterior | QON102: 0 | QOO102: Saldo anterior | QOV102: 0 | QOW102: Saldo anterior | QPD102: 0 | QPE102: Saldo anterior | QPL102: 0 | QPM102: Saldo anterior | QPT102: 0 | QPU102: Saldo anterior | QQB102: 0 | QQC102: Saldo anterior | QQJ102: 0 | QQK102: Saldo anterior | QQR102: 0 | QQS102: Saldo anterior | QQZ102: 0 | QRA102: Saldo anterior | QRH102: 0 | QRI102: Saldo anterior | QRP102: 0 | QRQ102: Saldo anterior | QRX102: 0 | QRY102: Saldo anterior | QSF102: 0 | QSG102: Saldo anterior | QSN102: 0 | QSO102: Saldo anterior | QSV102: 0 | QSW102: Saldo anterior | QTD102: 0 | QTE102: Saldo anterior | QTL102: 0 | QTM102: Saldo anterior | QTT102: 0 | QTU102: Saldo anterior | QUB102: 0 | QUC102: Saldo anterior | QUJ102: 0 | QUK102: Saldo anterior | QUR102: 0 | QUS102: Saldo anterior | QUZ102: 0 | QVA102: Saldo anterior | QVH102: 0 | QVI102: Saldo anterior | QVP102: 0 | QVQ102: Saldo anterior | QVX102: 0 | QVY102: Saldo anterior | QWF102: 0 | QWG102: Saldo anterior | QWN102: 0 | QWO102: Saldo anterior | QWV102: 0 | QWW102: Saldo anterior | QXD102: 0 | QXE102: Saldo anterior | QXL102: 0 | QXM102: Saldo anterior | QXT102: 0 | QXU102: Saldo anterior | QYB102: 0 | QYC102: Saldo anterior | QYJ102: 0 | QYK102: Saldo anterior | QYR102: 0 | QYS102: Saldo anterior | QYZ102: 0 | QZA102: Saldo anterior | QZH102: 0 | QZI102: Saldo anterior | QZP102: 0 | QZQ102: Saldo anterior | QZX102: 0 | QZY102: Saldo anterior | RAF102: 0 | RAG102: Saldo anterior | RAN102: 0 | RAO102: Saldo anterior | RAV102: 0 | RAW102: Saldo anterior | RBD102: 0 | RBE102: Saldo anterior | RBL102: 0 | RBM102: Saldo anterior | RBT102: 0 | RBU102: Saldo anterior | RCB102: 0 | RCC102: Saldo anterior | RCJ102: 0 | RCK102: Saldo anterior | RCR102: 0 | RCS102: Saldo anterior | RCZ102: 0 | RDA102: Saldo anterior | RDH102: 0 | RDI102: Saldo anterior | RDP102: 0 | RDQ102: Saldo anterior | RDX102: 0 | RDY102: Saldo anterior | REF102: 0 | REG102: Saldo anterior | REN102: 0 | REO102: Saldo anterior | REV102: 0 | REW102: Saldo anterior | RFD102: 0 | RFE102: Saldo anterior | RFL102: 0 | RFM102: Saldo anterior | RFT102: 0 | RFU102: Saldo anterior | RGB102: 0 | RGC102: Saldo anterior | RGJ102: 0 | RGK102: Saldo anterior | RGR102: 0 | RGS102: Saldo anterior | RGZ102: 0 | RHA102: Saldo anterior | RHH102: 0 | RHI102: Saldo anterior | RHP102: 0 | RHQ102: Saldo anterior | RHX102: 0 | RHY102: Saldo anterior | RIF102: 0 | RIG102: Saldo anterior | RIN102: 0 | RIO102: Saldo anterior | RIV102: 0 | RIW102: Saldo anterior | RJD102: 0 | RJE102: Saldo anterior | RJL102: 0 | RJM102: Saldo anterior | RJT102: 0 | RJU102: Saldo anterior | RKB102: 0 | RKC102: Saldo anterior | RKJ102: 0 | RKK102: Saldo anterior | RKR102: 0 | RKS102: Saldo anterior | RKZ102: 0 | RLA102: Saldo anterior | RLH102: 0 | RLI102: Saldo anterior | RLP102: 0 | RLQ102: Saldo anterior | RLX102: 0 | RLY102: Saldo anterior | RMF102: 0 | RMG102: Saldo anterior | RMN102: 0 | RMO102: Saldo anterior | RMV102: 0 | RMW102: Saldo anterior | RND102: 0 | RNE102: Saldo anterior | RNL102: 0 | RNM102: Saldo anterior | RNT102: 0 | RNU102: Saldo anterior | ROB102: 0 | ROC102: Saldo anterior | ROJ102: 0 | ROK102: Saldo anterior | ROR102: 0 | ROS102: Saldo anterior | ROZ102: 0 | RPA102: Saldo anterior | RPH102: 0 | RPI102: Saldo anterior | RPP102: 0 | RPQ102: Saldo anterior | RPX102: 0 | RPY102: Saldo anterior | RQF102: 0 | RQG102: Saldo anterior | RQN102: 0 | RQO102: Saldo anterior | RQV102: 0 | RQW102: Saldo anterior | RRD102: 0 | RRE102: Saldo anterior | RRL102: 0 | RRM102: Saldo anterior | RRT102: 0 | RRU102: Saldo anterior | RSB102: 0 | RSC102: Saldo anterior | RSJ102: 0 | RSK102: Saldo anterior | RSR102: 0 | RSS102: Saldo anterior | RSZ102: 0 | RTA102: Saldo anterior | RTH102: 0 | RTI102: Saldo anterior | RTP102: 0 | RTQ102: Saldo anterior | RTX102: 0 | RTY102: Saldo anterior | RUF102: 0 | RUG102: Saldo anterior | RUN102: 0 | RUO102: Saldo anterior | RUV102: 0 | RUW102: Saldo anterior | RVD102: 0 | RVE102: Saldo anterior | RVL102: 0 | RVM102: Saldo anterior | RVT102: 0 | RVU102: Saldo anterior | RWB102: 0 | RWC102: Saldo anterior | RWJ102: 0 | RWK102: Saldo anterior | RWR102: 0 | RWS102: Saldo anterior | RWZ102: 0 | RXA102: Saldo anterior | RXH102: 0 | RXI102: Saldo anterior | RXP102: 0 | RXQ102: Saldo anterior | RXX102: 0 | RXY102: Saldo anterior | RYF102: 0 | RYG102: Saldo anterior | RYN102: 0 | RYO102: Saldo anterior | RYV102: 0 | RYW102: Saldo anterior | RZD102: 0 | RZE102: Saldo anterior | RZL102: 0 | RZM102: Saldo anterior | RZT102: 0 | RZU102: Saldo anterior | SAB102: 0 | SAC102: Saldo anterior | SAJ102: 0 | SAK102: Saldo anterior | SAR102: 0 | SAS102: Saldo anterior | SAZ102: 0 | SBA102: Saldo anterior | SBH102: 0 | SBI102: Saldo anterior | SBP102: 0 | SBQ102: Saldo anterior | SBX102: 0 | SBY102: Saldo anterior | SCF102: 0 | SCG102: Saldo anterior | SCN102: 0 | SCO102: Saldo anterior | SCV102: 0 | SCW102: Saldo anterior | SDD102: 0 | SDE102: Saldo anterior | SDL102: 0 | SDM102: Saldo anterior | SDT102: 0 | SDU102: Saldo anterior | SEB102: 0 | SEC102: Saldo anterior | SEJ102: 0 | SEK102: Saldo anterior | SER102: 0 | SES102: Saldo anterior | SEZ102: 0 | SFA102: Saldo anterior | SFH102: 0 | SFI102: Saldo anterior | SFP102: 0 | SFQ102: Saldo anterior | SFX102: 0 | SFY102: Saldo anterior | SGF102: 0 | SGG102: Saldo anterior | SGN102: 0 | SGO102: Saldo anterior | SGV102: 0 | SGW102: Saldo anterior | SHD102: 0 | SHE102: Saldo anterior | SHL102: 0 | SHM102: Saldo anterior | SHT102: 0 | SHU102: Saldo anterior | SIB102: 0 | SIC102: Saldo anterior | SIJ102: 0 | SIK102: Saldo anterior | SIR102: 0 | SIS102: Saldo anterior | SIZ102: 0 | SJA102: Saldo anterior | SJH102: 0 | SJI102: Saldo anterior | SJP102: 0 | SJQ102: Saldo anterior | SJX102: 0 | SJY102: Saldo anterior | SKF102: 0 | SKG102: Saldo anterior | SKN102: 0 | SKO102: Saldo anterior | SKV102: 0 | SKW102: Saldo anterior | SLD102: 0 | SLE102: Saldo anterior | SLL102: 0 | SLM102: Saldo anterior | SLT102: 0 | SLU102: Saldo anterior | SMB102: 0 | SMC102: Saldo anterior | SMJ102: 0 | SMK102: Saldo anterior | SMR102: 0 | SMS102: Saldo anterior | SMZ102: 0 | SNA102: Saldo anterior | SNH102: 0 | SNI102: Saldo anterior | SNP102: 0 | SNQ102: Saldo anterior | SNX102: 0 | SNY102: Saldo anterior | SOF102: 0 | SOG102: Saldo anterior | SON102: 0 | SOO102: Saldo anterior | SOV102: 0 | SOW102: Saldo anterior | SPD102: 0 | SPE102: Saldo anterior | SPL102: 0 | SPM102: Saldo anterior | SPT102: 0 | SPU102: Saldo anterior | SQB102: 0 | SQC102: Saldo anterior | SQJ102: 0 | SQK102: Saldo anterior | SQR102: 0 | SQS102: Saldo anterior | SQZ102: 0 | SRA102: Saldo anterior | SRH102: 0 | SRI102: Saldo anterior | SRP102: 0 | SRQ102: Saldo anterior | SRX102: 0 | SRY102: Saldo anterior | SSF102: 0 | SSG102: Saldo anterior | SSN102: 0 | SSO102: Saldo anterior | SSV102: 0 | SSW102: Saldo anterior | STD102: 0 | STE102: Saldo anterior | STL102: 0 | STM102: Saldo anterior | STT102: 0 | STU102: Saldo anterior | SUB102: 0 | SUC102: Saldo anterior | SUJ102: 0 | SUK102: Saldo anterior | SUR102: 0 | SUS102: Saldo anterior | SUZ102: 0 | SVA102: Saldo anterior | SVH102: 0 | SVI102: Saldo anterior | SVP102: 0 | SVQ102: Saldo anterior | SVX102: 0 | SVY102: Saldo anterior | SWF102: 0 | SWG102: Saldo anterior | SWN102: 0 | SWO102: Saldo anterior | SWV102: 0 | SWW102: Saldo anterior | SXD102: 0 | SXE102: Saldo anterior | SXL102: 0 | SXM102: Saldo anterior | SXT102: 0 | SXU102: Saldo anterior | SYB102: 0 | SYC102: Saldo anterior | SYJ102: 0 | SYK102: Saldo anterior | SYR102: 0 | SYS102: Saldo anterior | SYZ102: 0 | SZA102: Saldo anterior | SZH102: 0 | SZI102: Saldo anterior | SZP102: 0 | SZQ102: Saldo anterior | SZX102: 0 | SZY102: Saldo anterior | TAF102: 0 | TAG102: Saldo anterior | TAN102: 0 | TAO102: Saldo anterior | TAV102: 0 | TAW102: Saldo anterior | TBD102: 0 | TBE102: Saldo anterior | TBL102: 0 | TBM102: Saldo anterior | TBT102: 0 | TBU102: Saldo anterior | TCB102: 0 | TCC102: Saldo anterior | TCJ102: 0 | TCK102: Saldo anterior | TCR102: 0 | TCS102: Saldo anterior | TCZ102: 0 | TDA102: Saldo anterior | TDH102: 0 | TDI102: Saldo anterior | TDP102: 0 | TDQ102: Saldo anterior | TDX102: 0 | TDY102: Saldo anterior | TEF102: 0 | TEG102: Saldo anterior | TEN102: 0 | TEO102: Saldo anterior | TEV102: 0 | TEW102: Saldo anterior | TFD102: 0 | TFE102: Saldo anterior | TFL102: 0 | TFM102: Saldo anterior | TFT102: 0 | TFU102: Saldo anterior | TGB102: 0 | TGC102: Saldo anterior | TGJ102: 0 | TGK102: Saldo anterior | TGR102: 0 | TGS102: Saldo anterior | TGZ102: 0 | THA102: Saldo anterior | THH102: 0 | THI102: Saldo anterior | THP102: 0 | THQ102: Saldo anterior | THX102: 0 | THY102: Saldo anterior | TIF102: 0 | TIG102: Saldo anterior | TIN102: 0 | TIO102: Saldo anterior | TIV102: 0 | TIW102: Saldo anterior | TJD102: 0 | TJE102: Saldo anterior | TJL102: 0 | TJM102: Saldo anterior | TJT102: 0 | TJU102: Saldo anterior | TKB102: 0 | TKC102: Saldo anterior | TKJ102: 0 | TKK102: Saldo anterior | TKR102: 0 | TKS102: Saldo anterior | TKZ102: 0 | TLA102: Saldo anterior | TLH102: 0 | TLI102: Saldo anterior | TLP102: 0 | TLQ102: Saldo anterior | TLX102: 0 | TLY102: Saldo anterior | TMF102: 0 | TMG102: Saldo anterior | TMN102: 0 | TMO102: Saldo anterior | TMV102: 0 | TMW102: Saldo anterior | TND102: 0 | TNE102: Saldo anterior | TNL102: 0 | TNM102: Saldo anterior | TNT102: 0 | TNU102: Saldo anterior | TOB102: 0 | TOC102: Saldo anterior | TOJ102: 0 | TOK102: Saldo anterior | TOR102: 0 | TOS102: Saldo anterior | TOZ102: 0 | TPA102: Saldo anterior | TPH102: 0 | TPI102: Saldo anterior | TPP102: 0 | TPQ102: Saldo anterior | TPX102: 0 | TPY102: Saldo anterior | TQF102: 0 | TQG102: Saldo anterior | TQN102: 0 | TQO102: Saldo anterior | TQV102: 0 | TQW102: Saldo anterior | TRD102: 0 | TRE102: Saldo anterior | TRL102: 0 | TRM102: Saldo anterior | TRT102: 0 | TRU102: Saldo anterior | TSB102: 0 | TSC102: Saldo anterior | TSJ102: 0 | TSK102: Saldo anterior | TSR102: 0 | TSS102: Saldo anterior | TSZ102: 0 | TTA102: Saldo anterior | TTH102: 0 | TTI102: Saldo anterior | TTP102: 0 | TTQ102: Saldo anterior | TTX102: 0 | TTY102: Saldo anterior | TUF102: 0 | TUG102: Saldo anterior | TUN102: 0 | TUO102: Saldo anterior | TUV102: 0 | TUW102: Saldo anterior | TVD102: 0 | TVE102: Saldo anterior | TVL102: 0 | TVM102: Saldo anterior | TVT102: 0 | TVU102: Saldo anterior | TWB102: 0 | TWC102: Saldo anterior | TWJ102: 0 | TWK102: Saldo anterior | TWR102: 0 | TWS102: Saldo anterior | TWZ102: 0 | TXA102: Saldo anterior | TXH102: 0 | TXI102: Saldo anterior | TXP102: 0 | TXQ102: Saldo anterior | TXX102: 0 | TXY102: Saldo anterior | TYF102: 0 | TYG102: Saldo anterior | TYN102: 0 | TYO102: Saldo anterior | TYV102: 0 | TYW102: Saldo anterior | TZD102: 0 | TZE102: Saldo anterior | TZL102: 0 | TZM102: Saldo anterior | TZT102: 0 | TZU102: Saldo anterior | UAB102: 0 | UAC102: Saldo anterior | UAJ102: 0 | UAK102: Saldo anterior | UAR102: 0 | UAS102: Saldo anterior | UAZ102: 0 | UBA102: Saldo anterior | UBH102: 0 | UBI102: Saldo anterior | UBP102: 0 | UBQ102: Saldo anterior | UBX102: 0 | UBY102: Saldo anterior | UCF102: 0 | UCG102: Saldo anterior | UCN102: 0 | UCO102: Saldo anterior | UCV102: 0 | UCW102: Saldo anterior | UDD102: 0 | UDE102: Saldo anterior | UDL102: 0 | UDM102: Saldo anterior | UDT102: 0 | UDU102: Saldo anterior | UEB102: 0 | UEC102: Saldo anterior | UEJ102: 0 | UEK102: Saldo anterior | UER102: 0 | UES102: Saldo anterior | UEZ102: 0 | UFA102: Saldo anterior | UFH102: 0 | UFI102: Saldo anterior | UFP102: 0 | UFQ102: Saldo anterior | UFX102: 0 | UFY102: Saldo anterior | UGF102: 0 | UGG102: Saldo anterior | UGN102: 0 | UGO102: Saldo anterior | UGV102: 0 | UGW102: Saldo anterior | UHD102: 0 | UHE102: Saldo anterior | UHL102: 0 | UHM102: Saldo anterior | UHT102: 0 | UHU102: Saldo anterior | UIB102: 0 | UIC102: Saldo anterior | UIJ102: 0 | UIK102: Saldo anterior | UIR102: 0 | UIS102: Saldo anterior | UIZ102: 0 | UJA102: Saldo anterior | UJH102: 0 | UJI102: Saldo anterior | UJP102: 0 | UJQ102: Saldo anterior | UJX102: 0 | UJY102: Saldo anterior | UKF102: 0 | UKG102: Saldo anterior | UKN102: 0 | UKO102: Saldo anterior | UKV102: 0 | UKW102: Saldo anterior | ULD102: 0 | ULE102: Saldo anterior | ULL102: 0 | ULM102: Saldo anterior | ULT102: 0 | ULU102: Saldo anterior | UMB102: 0 | UMC102: Saldo anterior | UMJ102: 0 | UMK102: Saldo anterior | UMR102: 0 | UMS102: Saldo anterior | UMZ102: 0 | UNA102: Saldo anterior | UNH102: 0 | UNI102: Saldo anterior | UNP102: 0 | UNQ102: Saldo anterior | UNX102: 0 | UNY102: Saldo anterior | UOF102: 0 | UOG102: Saldo anterior | UON102: 0 | UOO102: Saldo anterior | UOV102: 0 | UOW102: Saldo anterior | UPD102: 0 | UPE102: Saldo anterior | UPL102: 0 | UPM102: Saldo anterior | UPT102: 0 | UPU102: Saldo anterior | UQB102: 0 | UQC102: Saldo anterior | UQJ102: 0 | UQK102: Saldo anterior | UQR102: 0 | UQS102: Saldo anterior | UQZ102: 0 | URA102: Saldo anterior | URH102: 0 | URI102: Saldo anterior | URP102: 0 | URQ102: Saldo anterior | URX102: 0 | URY102: Saldo anterior | USF102: 0 | USG102: Saldo anterior | USN102: 0 | USO102: Saldo anterior | USV102: 0 | USW102: Saldo anterior | UTD102: 0 | UTE102: Saldo anterior | UTL102: 0 | UTM102: Saldo anterior | UTT102: 0 | UTU102: Saldo anterior | UUB102: 0 | UUC102: Saldo anterior | UUJ102: 0 | UUK102: Saldo anterior | UUR102: 0 | UUS102: Saldo anterior | UUZ102: 0 | UVA102: Saldo anterior | UVH102: 0 | UVI102: Saldo anterior | UVP102: 0 | UVQ102: Saldo anterior | UVX102: 0 | UVY102: Saldo anterior | UWF102: 0 | UWG102: Saldo anterior | UWN102: 0 | UWO102: Saldo anterior | UWV102: 0 | UWW102: Saldo anterior | UXD102: 0 | UXE102: Saldo anterior | UXL102: 0 | UXM102: Saldo anterior | UXT102: 0 | UXU102: Saldo anterior | UYB102: 0 | UYC102: Saldo anterior | UYJ102: 0 | UYK102: Saldo anterior | UYR102: 0 | UYS102: Saldo anterior | UYZ102: 0 | UZA102: Saldo anterior | UZH102: 0 | UZI102: Saldo anterior | UZP102: 0 | UZQ102: Saldo anterior | UZX102: 0 | UZY102: Saldo anterior | VAF102: 0 | VAG102: Saldo anterior | VAN102: 0 | VAO102: Saldo anterior | VAV102: 0 | VAW102: Saldo anterior | VBD102: 0 | VBE102: Saldo anterior | VBL102: 0 | VBM102: Saldo anterior | VBT102: 0 | VBU102: Saldo anterior | VCB102: 0 | VCC102: Saldo anterior | VCJ102: 0 | VCK102: Saldo anterior | VCR102: 0 | VCS102: Saldo anterior | VCZ102: 0 | VDA102: Saldo anterior | VDH102: 0 | VDI102: Saldo anterior | VDP102: 0 | VDQ102: Saldo anterior | VDX102: 0 | VDY102: Saldo anterior | VEF102: 0 | VEG102: Saldo anterior | VEN102: 0 | VEO102: Saldo anterior | VEV102: 0 | VEW102: Saldo anterior | VFD102: 0 | VFE102: Saldo anterior | VFL102: 0 | VFM102: Saldo anterior | VFT102: 0 | VFU102: Saldo anterior | VGB102: 0 | VGC102: Saldo anterior | VGJ102: 0 | VGK102: Saldo anterior | VGR102: 0 | VGS102: Saldo anterior | VGZ102: 0 | VHA102: Saldo anterior | VHH102: 0 | VHI102: Saldo anterior | VHP102: 0 | VHQ102: Saldo anterior | VHX102: 0 | VHY102: Saldo anterior | VIF102: 0 | VIG102: Saldo anterior | VIN102: 0 | VIO102: Saldo anterior | VIV102: 0 | VIW102: Saldo anterior | VJD102: 0 | VJE102: Saldo anterior | VJL102: 0 | VJM102: Saldo anterior | VJT102: 0 | VJU102: Saldo anterior | VKB102: 0 | VKC102: Saldo anterior | VKJ102: 0 | VKK102: Saldo anterior | VKR102: 0 | VKS102: Saldo anterior | VKZ102: 0 | VLA102: Saldo anterior | VLH102: 0 | VLI102: Saldo anterior | VLP102: 0 | VLQ102: Saldo anterior | VLX102: 0 | VLY102: Saldo anterior | VMF102: 0 | VMG102: Saldo anterior | VMN102: 0 | VMO102: Saldo anterior | VMV102: 0 | VMW102: Saldo anterior | VND102: 0 | VNE102: Saldo anterior | VNL102: 0 | VNM102: Saldo anterior | VNT102: 0 | VNU102: Saldo anterior | VOB102: 0 | VOC102: Saldo anterior | VOJ102: 0 | VOK102: Saldo anterior | VOR102: 0 | VOS102: Saldo anterior | VOZ102: 0 | VPA102: Saldo anterior | VPH102: 0 | VPI102: Saldo anterior | VPP102: 0 | VPQ102: Saldo anterior | VPX102: 0 | VPY102: Saldo anterior | VQF102: 0 | VQG102: Saldo anterior | VQN102: 0 | VQO102: Saldo anterior | VQV102: 0 | VQW102: Saldo anterior | VRD102: 0 | VRE102: Saldo anterior | VRL102: 0 | VRM102: Saldo anterior | VRT102: 0 | VRU102: Saldo anterior | VSB102: 0 | VSC102: Saldo anterior | VSJ102: 0 | VSK102: Saldo anterior | VSR102: 0 | VSS102: Saldo anterior | VSZ102: 0 | VTA102: Saldo anterior | VTH102: 0 | VTI102: Saldo anterior | VTP102: 0 | VTQ102: Saldo anterior | VTX102: 0 | VTY102: Saldo anterior | VUF102: 0 | VUG102: Saldo anterior | VUN102: 0 | VUO102: Saldo anterior | VUV102: 0 | VUW102: Saldo anterior | VVD102: 0 | VVE102: Saldo anterior | VVL102: 0 | VVM102: Saldo anterior | VVT102: 0 | VVU102: Saldo anterior | VWB102: 0 | VWC102: Saldo anterior | VWJ102: 0 | VWK102: Saldo anterior | VWR102: 0 | VWS102: Saldo anterior | VWZ102: 0 | VXA102: Saldo anterior | VXH102: 0 | VXI102: Saldo anterior | VXP102: 0 | VXQ102: Saldo anterior | VXX102: 0 | VXY102: Saldo anterior | VYF102: 0 | VYG102: Saldo anterior | VYN102: 0 | VYO102: Saldo anterior | VYV102: 0 | VYW102: Saldo anterior | VZD102: 0 | VZE102: Saldo anterior | VZL102: 0 | VZM102: Saldo anterior | VZT102: 0 | VZU102: Saldo anterior | WAB102: 0 | WAC102: Saldo anterior | WAJ102: 0 | WAK102: Saldo anterior | WAR102: 0 | WAS102: Saldo anterior | WAZ102: 0 | WBA102: Saldo anterior | WBH102: 0 | WBI102: Saldo anterior | WBP102: 0 | WBQ102: Saldo anterior | WBX102: 0 | WBY102: Saldo anterior | WCF102: 0 | WCG102: Saldo anterior | WCN102: 0 | WCO102: Saldo anterior | WCV102: 0 | WCW102: Saldo anterior | WDD102: 0 | WDE102: Saldo anterior | WDL102: 0 | WDM102: Saldo anterior | WDT102: 0 | WDU102: Saldo anterior | WEB102: 0 | WEC102: Saldo anterior | WEJ102: 0 | WEK102: Saldo anterior | WER102: 0 | WES102: Saldo anterior | WEZ102: 0 | WFA102: Saldo anterior | WFH102: 0 | WFI102: Saldo anterior | WFP102: 0 | WFQ102: Saldo anterior | WFX102: 0 | WFY102: Saldo anterior | WGF102: 0 | WGG102: Saldo anterior | WGN102: 0 | WGO102: Saldo anterior | WGV102: 0 | WGW102: Saldo anterior | WHD102: 0 | WHE102: Saldo anterior | WHL102: 0 | WHM102: Saldo anterior | WHT102: 0 | WHU102: Saldo anterior | WIB102: 0 | WIC102: Saldo anterior | WIJ102: 0 | WIK102: Saldo anterior | WIR102: 0 | WIS102: Saldo anterior | WIZ102: 0 | WJA102: Saldo anterior | WJH102: 0 | WJI102: Saldo anterior | WJP102: 0 | WJQ102: Saldo anterior | WJX102: 0 | WJY102: Saldo anterior | WKF102: 0 | WKG102: Saldo anterior | WKN102: 0 | WKO102: Saldo anterior | WKV102: 0 | WKW102: Saldo anterior | WLD102: 0 | WLE102: Saldo anterior | WLL102: 0 | WLM102: Saldo anterior | WLT102: 0 | WLU102: Saldo anterior | WMB102: 0 | WMC102: Saldo anterior | WMJ102: 0 | WMK102: Saldo anterior | WMR102: 0 | WMS102: Saldo anterior | WMZ102: 0 | WNA102: Saldo anterior | WNH102: 0 | WNI102: Saldo anterior | WNP102: 0 | WNQ102: Saldo anterior | WNX102: 0 | WNY102: Saldo anterior | WOF102: 0 | WOG102: Saldo anterior | WON102: 0 | WOO102: Saldo anterior | WOV102: 0 | WOW102: Saldo anterior | WPD102: 0 | WPE102: Saldo anterior | WPL102: 0 | WPM102: Saldo anterior | WPT102: 0 | WPU102: Saldo anterior | WQB102: 0 | WQC102: Saldo anterior | WQJ102: 0 | WQK102: Saldo anterior | WQR102: 0 | WQS102: Saldo anterior | WQZ102: 0 | WRA102: Saldo anterior | WRH102: 0 | WRI102: Saldo anterior | WRP102: 0 | WRQ102: Saldo anterior | WRX102: 0 | WRY102: Saldo anterior | WSF102: 0 | WSG102: Saldo anterior | WSN102: 0 | WSO102: Saldo anterior | WSV102: 0 | WSW102: Saldo anterior | WTD102: 0 | WTE102: Saldo anterior | WTL102: 0 | WTM102: Saldo anterior | WTT102: 0 | WTU102: Saldo anterior | WUB102: 0 | WUC102: Saldo anterior | WUJ102: 0 | WUK102: Saldo anterior | WUR102: 0 | WUS102: Saldo anterior | WUZ102: 0 | WVA102: Saldo anterior | WVH102: 0 | WVI102: Saldo anterior | WVP102: 0 | WVQ102: Saldo anterior | WVX102: 0 | WVY102: Saldo anterior | WWF102: 0 | WWG102: Saldo anterior | WWN102: 0 | WWO102: Saldo anterior | WWV102: 0 | WWW102: Saldo anterior | WXD102: 0 | WXE102: Saldo anterior | WXL102: 0 | WXM102: Saldo anterior | WXT102: 0 | WXU102: Saldo anterior | WYB102: 0 | WYC102: Saldo anterior | WYJ102: 0 | WYK102: Saldo anterior | WYR102: 0 | WYS102: Saldo anterior | WYZ102: 0 | WZA102: Saldo anterior | WZH102: 0 | WZI102: Saldo anterior | WZP102: 0 | WZQ102: Saldo anterior | WZX102: 0 | WZY102: Saldo anterior | XAF102: 0 | XAG102: Saldo anterior | XAN102: 0 | XAO102: Saldo anterior | XAV102: 0 | XAW102: Saldo anterior | XBD102: 0 | XBE102: Saldo anterior | XBL102: 0 | XBM102: Saldo anterior | XBT102: 0 | XBU102: Saldo anterior | XCB102: 0 | XCC102: Saldo anterior | XCJ102: 0 | XCK102: Saldo anterior | XCR102: 0 | XCS102: Saldo anterior | XCZ102: 0 | XDA102: Saldo anterior | XDH102: 0 | XDI102: Saldo anterior | XDP102: 0 | XDQ102: Saldo anterior | XDX102: 0 | XDY102: Saldo anterior | XEF102: 0 | XEG102: Saldo anterior | XEN102: 0 | XEO102: Saldo anterior | XEV102: 0 | XEW102: Saldo anterior | XFD102: 0
A103: Ingreso SUM | H103: 0
A104: Reparacion puerta Sum | H104: -55000
