Workbook

Sheet RESUMEN
C1: MAIL: elmiradorconsorcios@gmail.com
C2: CUIT ADMINISTRACION: 27231256879
C3: CBU: | E3: TELEFONO: 11 5320-2676
C4: ADMINISTRADORA: CAROLINA CANCIANI MP:1148
C5: PERÍODO: JULIO | E5: HORARIOS DE ATENCION: LUNES A VIERNES - 10 A 16HS - EMERGENCIAS 24HS
C6: LIQUIDACION DE EXPENSAS
A14: Importante para dueños o inquilinos de departamentos o coheras: Queremos recordarles una cuestión importante respecto a los pagos de expensas que ayuda a evitar errores en la imputación de los mismos. El sistema que utilizamos asigna centavos únicos a cada Unidad Funcional (UF), lo cual nos permite identificar automáticamente a qué unidad corresponde cada transferencia. Es decir, cada UF tiene un número específico de centavos que actúa como "identificador". Por ejemplo, si tu UF es la 45, el importe a abonar debería terminar en $...,45. Si tenés más de una unidad (por ejemplo, un departamento y una cochera), cada una tiene su propio código de centavos. En esos casos, te pedimos por favor que realices una transferencia por cada UF, respetando el importe con sus centavos correspondientes. Sabemos que a veces por comodidad se suele enviar todo junto en una sola transferencia, pero esto puede generar confusión o errores en la imputación automática. Realizar los pagos por separado nos permite asegurar que cada importe se asigne correctamente. Agradecemos muchísimo la colaboración para seguir manteniendo todo ordenado. Saludos cordiales.
A21: GASTOS ORDINARIOS UNIDADES FUNCIONALES: | E21: UF 93,20% | F21: LOCAL 1 (1,08%) | G21: LOCAL 2 (1,28%) | H21: LOCAL 3 (1,21%) | I21: LOCAL 4 (1,49%) | J21: LOCAL 5 (1,74%)
A22: Sueldo encargada Sonia Arzamendia Galeano
A23: Haberes | D23: =481500*2 -> 963000
A24: Plus pileta | D24: 33606.9
A25: Plus retiro de basura | D25: 111256.4
A26: Plus cochera | D26: 19877.4
A27: Adicional remuneracion | D27: 50000
A28: SAC | D28: 410000
A29: SUBTOTAL | D29: =SUM(D23:D28) -> 1587740.7
A30: Sueldo encargada Miriam
A31: Haberes | D31: =240732 -> 240732
A32: Plus pileta | D32: 33606.9
A33: Plus retiro de basura | D33: 111256.4
A34: Plus cochera | D34: 19877.4
A35: Adicional remuneracion | D35: 50000
A36: SUBTOTAL | D36: =SUM(D31:D35) -> 455472.7
A37: TOTAL SUELDO | D37: =D29+D36 -> 2043213.4 | E37: =D37*93.2% -> 1904274.9 | F37: =$D37*1.08% -> 22066.705 | G37: =$D37*1.28% -> 26153.132 | H37: =$D37*1.21% -> 24722.882 | I37: =$D37*1.49% -> 30443.88 | J37: =D37*1.74% -> 35551.913 | K37: =E37+J37+F37+G37+H37+I37 -> 2043213.4 | L37: =IF(D37=K37, "", "Error")
A38: SAC | D38: 0 | E38: =D38*91.91% -> 0 | J38: =D38*8.09% -> 0
D39: 0 | E39: =D39*91.91% -> 0 | J39: =D39*8.09% -> 0
A42: TOTAL | D42: =SUM(D38:D40) -> 0 | E42: =SUM(E38:E40) -> 0 | J42: =SUM(J38:J40) -> 0 | K42: =E42+J42 -> 0 | L42: =IF(D42=K42, "", "Error")
A43: COMBUSTIBLE PARA GRUPO ELECTROGENO | E43: =D43*91.91% -> 0 | J43: =D43*8.09% -> 0
A44: Gas Lanus SA - Compra infinia diesel | C44: Efect 02/07 | D44: 79500.01 | E44: =D44 -> 79500.01
E45: =D45*91.91% -> 0 | J45: =D45*8.09% -> 0
A46: TOTAL SAC | D46: =SUM(D39:D45) -> 79500.01 | E46: =SUM(E39:E45) -> 79500.01 | K46: =E46+J46+F46+G46+H46+I46 -> 79500.01 | L46: =IF(D46=K46, "", "Error")
A47: IMPUESTOS
A48: ARBA - Impuesto inmobiliario partida 025024270-0 | C48: PMC 10/06 | D48: 132512.6
A49: TSG - Partida 197229000 | C49: PMC 09/06 | D49: 669159
A50: TSG - Partida 197227000 | C50: PMC 09/06 | D50: 643422
A51: TOTAL IMPUESTOS | D51: =SUM(D48:D50) -> 1445093.6 | E51: =D51*93.2% -> 1346827.2 | F51: =$D51*1.08% -> 15607.011 | G51: =$D51*1.28% -> 18497.198 | H51: =$D51*1.21% -> 17485.633 | I51: =$D51*1.49% -> 21531.895 | J51: =D51*1.74% -> 25144.629 | K51: =E51+J51+F51+G51+H51+I51 -> 1445093.6 | L51: =IF(D51=K51, "", "Error")
A52: APORTES Y CONTRIBUCIONES
A53: Monotributo Sra. Sonia | D53: 48854
A55: TOTAL APORTES Y CONTRIBUCIONES | D55: =SUM(D52:D54) -> 48854 | E55: =D55*93.2% -> 45531.928 | F55: =$D55*1.08% -> 527.6232 | G55: =$D55*1.28% -> 625.3312 | H55: =$D55*1.21% -> 591.1334 | I55: =$D55*1.49% -> 727.9246 | J55: =D55*1.74% -> 850.0596 | K55: =E55+J55+F55+G55+H55+I55 -> 48854 | L55: =IF(D55=K55, "", "Error")
A56: SEGUROS
A57: Federacion patronal - Poliza integral para consorcios nro. 2152393 | C57: Efec. 12/06 | D57: 160913 | E57: =D57*93.2% -> 149970.92 | F57: =$D57*1.08% -> 1737.8604 | G57: =$D57*1.28% -> 2059.6864 | H57: =$D57*1.21% -> 1947.0473 | I57: =$D57*1.49% -> 2397.6037 | J57: =D57*1.74% -> 2799.8862 | K57: =SUM(E57:J57) -> 160913
A58: Federacion patronal - Poliza accidentes personales Sra. Sonia - nro. 9559834 | C58: Efec. 10/06 | D58: 7907 | E58: =D58*93.2% -> 7369.324 | F58: =$D58*1.08% -> 85.3956 | G58: =$D58*1.28% -> 101.2096 | H58: =$D58*1.21% -> 95.6747 | I58: =$D58*1.49% -> 117.8143 | J58: =D58*1.74% -> 137.5818 | K58: =SUM(E58:J58) -> 7907
A59: Federacion patronal - Poliza accidentes personales Sra. Miriam - nro. 9559886 | C59: Efec. 17/06 | D59: 7907 | E59: =D59*93.2% -> 7369.324 | F59: =$D59*1.08% -> 85.3956 | G59: =$D59*1.28% -> 101.2096 | H59: =$D59*1.21% -> 95.6747 | I59: =$D59*1.49% -> 117.8143 | J59: =D59*1.74% -> 137.5818 | K59: =SUM(E59:J59) -> 7907
A60: TOTAL Aportes y Contribuciones - Sindicato | D60: =SUM(D57:D59) -> 176727 | E60: =SUM(E57:E59) -> 164709.56 | F60: =SUM(F57:F59) -> 1908.6516 | G60: =SUM(G57:G59) -> 2262.1056 | H60: =SUM(H57:H59) -> 2138.3967 | I60: =SUM(I57:I59) -> 2633.2323 | J60: =SUM(J57:J59) -> 3075.0498 | K60: =E60+J60+F60+G60+H60+I60 -> 176727 | L60: =IF(D60=K60, "", "Error")
A61: ABONOS Y SERVICIOS
A62: Aysa - Cuenta 249011 | C62: Efect. 03/06 | D62: 27920.59 | E62: =D62*93.2% -> 26021.99 | F62: =$D62*1.08% -> 301.54237 | G62: =$D62*1.28% -> 357.38355 | H62: =$D62*1.21% -> 337.83914 | I62: =$D62*1.49% -> 416.01679 | J62: =D62*1.74% -> 485.81827 | K62: =D62 -> 27920.59 | L62: =SUM(E62:J62) -> 27920.59 | M62: =L62-D62 -> 0 | N62: =K62-D62 -> 0
A63: Edesur - Cliente 01291636 | C63: Efect. 06/06 | D63: 1233986 | E63: =D63*93.2% -> 1150075 | F63: =$D63*1.08% -> 13327.049 | G63: =$D63*1.28% -> 15795.021 | H63: =$D63*1.21% -> 14931.231 | I63: =$D63*1.49% -> 18386.392 | J63: =D63*1.74% -> 21471.357 | K63: =D63 -> 1233986 | L63: =E63+J63+I63+H63+G63+F63 -> 1233986 | M63: =L63-D63 -> 0 | N63: =K63-D63 -> 0
A64: Telecentro - Zona coworking - Cliente 7725479 | C64: Efect. 23/06 | D64: 96208.3 | E64: =D64 -> 96208.3 | K64: =D64 -> 96208.3 | L64: =E64+J64+I64+H64+G64+F64 -> 96208.3 | M64: =L64-D64 -> 0 | N64: =K64-D64 -> 0
A65: ADS - Abono de mantenimiento ascensores JULIO del 2025 | C65: Transf 25/06 | D65: 149126.03 | E65: =D65 -> 149126.03 | K65: =D65 -> 149126.03 | L65: =E65+J65+I65+H65+G65+F65 -> 149126.03
A66: Victor Martinez - Abono mantenimiento control de accesos | D66: 30000 | E66: =D66 -> 30000 | K66: =D66 -> 30000 | L66: =E66+J66+I66+H66+G66+F66 -> 30000 | M66: =L66-D66 -> 0 | N66: =K66-D66 -> 0
A67: Metrogas - No llego la factura | E67: =D67 -> 0 | K67: =D67 -> 0 | L67: =E67+J67+I67+H67+G67+F67 -> 0 | N67: =K67-D67 -> 0
A68: Mantenimiento grupo electrogeno - No llego factura | E68: =D68 -> 0 | K68: =D68 -> 0 | L68: =E68+J68+I68+H68+G68+F68 -> 0 | M68: =L68-D68 -> 0 | N68: =K68-D68 -> 0
E69: =D69 -> 0 | K69: =D69 -> 0 | L69: =E69+J69+I69+H69+G69+F69 -> 0 | M69: =L69-D69 -> 0 | N69: =K69-D69 -> 0
M70: =IF(K70=L70, "", "Error")
A71: TOTAL ABONOS Y SERVICIOS | D71: =SUM(D62:D70) -> 1537241 | E71: =SUM(E62:E70) -> 1451431.3 | F71: =SUM(F62:F70) -> 13628.591 | G71: =SUM(G62:G70) -> 16152.405 | H71: =SUM(H62:H70) -> 15269.07 | I71: =SUM(I62:I70) -> 18802.409 | J71: =SUM(J62:J70) -> 21957.175 | K71: =E71+J71+F71+G71+H71+I71 -> 1537241 | L71: =IF(D71=K71, "", "Error") | M71: =D71-K71 -> 0
A74: GASTOS VARIOS
A75: Articulos de limpieza | B75: No llego factura | E75: =D75*93.2% -> 0 | F75: =$D75*1.08% -> 0 | G75: =$D75*1.28% -> 0 | H75: =$D75*1.21% -> 0 | I75: =$D75*1.49% -> 0 | J75: =D75*1.74% -> 0
A76: Ferreteria CyR - Compra embudo | D76: 1800 | E76: =D76*93.2% -> 1677.6 | F76: =$D76*1.08% -> 19.44 | G76: =$D76*1.28% -> 23.04 | H76: =$D76*1.21% -> 21.78 | I76: =$D76*1.49% -> 26.82 | J76: =D76*1.74% -> 31.32
A77: Cerrajeria V&A - Compra candado tacho de basura | D77: 6600 | E77: =D77 -> 6600
A78: Tags - Sra Miriam | D78: 9000 | E78: =D78*93.2% -> 8388 | F78: =$D78*1.08% -> 97.2 | G78: =$D78*1.28% -> 115.2 | H78: =$D78*1.21% -> 108.9 | I78: =$D78*1.49% -> 134.1 | J78: =D78*1.74% -> 156.6
A79: Cerrajeria Citta - Copias de llaves | D79: 8000 | E79: =D79*93.2% -> 7456 | F79: =$D79*1.08% -> 86.4 | G79: =$D79*1.28% -> 102.4 | H79: =$D79*1.21% -> 96.8 | I79: =$D79*1.49% -> 119.2 | J79: =D79*1.74% -> 139.2
A80: Mundo plus - adelanto compra tachos de basuras | D80: 707200 | E80: =D80 -> 707200
A81: Papelera - compra libro de actas, sopapas, carteles porteria | D81: =9500+1900 -> 11400 | E81: =D81*93.2% -> 10624.8 | F81: =$D81*1.08% -> 123.12 | G81: =$D81*1.28% -> 145.92 | H81: =$D81*1.21% -> 137.94 | I81: =$D81*1.49% -> 169.86 | J81: =D81*1.74% -> 198.36
A82: TOTAL GASTOS VARIOS | D82: =SUM(D75:D81) -> 744000 | E82: =SUM(E75:E81) -> 741946.4 | F82: =SUM(F75:F81) -> 326.16 | G82: =SUM(G75:G81) -> 386.56 | H82: =SUM(H75:H81) -> 365.42 | I82: =SUM(I75:I81) -> 449.98 | J82: =SUM(J75:J81) -> 525.48 | K82: =E82+J82+F82+G82+H82+I82 -> 744000 | L82: =IF(D82=K82, "", "Error")
A85: GASTOS DE ADMINISTRACION
A86: RC Adm Cons. CANCIANI, Carolina | B86: MP:1148 | D86: 700000 | E86: =D86*93.2% -> 652400 | F86: =$D86*1.08% -> 7560 | G86: =$D86*1.28% -> 8960 | H86: =$D86*1.21% -> 8470 | I86: =$D86*1.49% -> 10430 | J86: =D86*1.74% -> 12180
A89: TOTAL GASTOS DE ADMINISTRACION | D89: =SUM(D86:D88) -> 700000 | E89: =SUM(E86:E88) -> 652400 | F89: =SUM(F86:F88) -> 7560 | G89: =SUM(G86:G88) -> 8960 | H89: =SUM(H86:H88) -> 8470 | I89: =SUM(I86:I88) -> 10430 | J89: =SUM(J86:J88) -> 12180 | K89: =E89+J89+F89+G89+H89+I89 -> 700000 | L89: =IF(D89=K89, "", "Error")
A90: Gastos bancarios | E90: =D90*93.2% -> 0 | F90: =$D90*1.08% -> 0 | G90: =$D90*1.28% -> 0 | H90: =$D90*1.21% -> 0 | I90: =$D90*1.49% -> 0 | J90: =D90*1.74% -> 0
A91: Mantenimiento de cuenta | E91: =D91*93.2% -> 0 | F91: =$D91*1.08% -> 0 | G91: =$D91*1.28% -> 0 | H91: =$D91*1.21% -> 0 | I91: =$D91*1.49% -> 0 | J91: =D91*1.74% -> 0
A92: TOTAL GASTOS BANCARIOS | D92: =SUM(D90:D91) -> 0 | E92: =SUM(E90:E91) -> 0 | F92: =SUM(F90:F91) -> 0 | G92: =SUM(G90:G91) -> 0 | H92: =SUM(H90:H91) -> 0 | I92: =SUM(I90:I91) -> 0 | J92: =SUM(J90:J91) -> 0 | K92: =E92+J92+F92+G92+H92+I92 -> 0 | L92: =IF(D92=K92, "", "Error")
A94: FONDO DE GASTOS ORDINARIOS | D94: 1500000 | E94: =D94*93.2% -> 1398000 | F94: =$D94*1.08% -> 16200 | G94: =$D94*1.28% -> 19200 | H94: =$D94*1.21% -> 18150 | I94: =$D94*1.49% -> 22350 | J94: =D94*1.74% -> 26100 | K94: =E94+J94+F94+G94+H94+I94 -> 1500000 | L94: =IF(D94=K94, "", "Error")
A96: TOTAL ORDINARIOS | D96: =SUM(D94+D51+D46+D92+D89+D82+D71+D60+D42+D37+D55) -> 8274629 | E96: =SUM(E94+E51+E46+E92+E89+E82+E71+E60+E42+E37+E55) -> 7784621.3 | F96: =SUM(F94+F51+F46+F92+F89+F82+F71+F60+F42+F37+F55) -> 77824.742 | G96: =SUM(G94+G51+G46+G92+G89+G82+G71+G60+G42+G37+G55) -> 92236.731 | H96: =SUM(H94+H51+H46+H92+H89+H82+H71+H60+H42+H37+H55) -> 87192.535 | I96: =SUM(I94+I51+I46+I92+I89+I82+I71+I60+I42+I37+I55) -> 107369.32 | J96: =SUM(J94+J51+J46+J92+J89+J82+J71+J60+J42+J37+J55) -> 125384.31 | K96: =E96+J96+F96+G96+H96+I96 -> 8274629 | L96: =IF(D96=K96, "", "Error") | M96: =D96-K96 -> 0
A98: Gastos particulares
A99: Victor Martinez - Tags | C99: =90000-9000 -> 81000
A101: TOTAL | C101: =SUM(C99:C100) -> 81000
A104: GASTOS EXTRAORDINARIOS | E104: UF | F104: LOCAL 1 (1,08%) | G104: LOCAL 2 (1,28%) | H104: LOCAL 3 (1,21%) | I104: LOCAL 4 (1,49%) | J104: LOCAL 5 (1,74%)
E105: =D105 -> 0
A107: TOTAL | D107: =SUM(D105:D106) -> 0 | E107: =SUM(E105:E106) -> 0 | J107: =SUM(J105:J106) -> 0 | L107: =E107+J107 -> 0 | M107: =IF(D107=L107, "", "Error")
A110: GASTOS ORDINARIOS + PREVISION : | B110: =D96 -> 8274629
A111: GASTOS ORDINARIOS SIN PREVISION: | B111: =D96-D94 -> 6774629
A113: CAJA EFECTIVO $ (pesos)
A114: Saldo anterior | B114: 7250000
A115: Ingresos | B115: =PRORRATEO!G126 -> 0
A116: Egresos Ordinarios | B116: =-B111 -> -6774629
A117: Egresos Extraordinarios | B117: =-D107 -> 0
A118: Dinero ingreso SUM | B118: =-B125 -> 0
A119: Gastos particulares | B119: =-C101 -> -81000
A121: Saldo al cierre | B121: =SUM(B114:B120) -> 394371.04
A124: CAJA EFECTIVO SUM $ (pesos) | B124: 0
A125: Ingreso
A127: TOTAL | B127: =SUM(B124:B126) -> 0

Sheet PRORRATEO
F1: ESTADO DE CUENTA Y PRORRATEO | J1: SE GASTO: | K1: =RESUMEN!D96-RESUMEN!D94 -> 6774629
J2: SE PRORRATEA EN LAS UF: | L2: 7142595.9
A3: =RESUMEN!C5 -> PERÍODO: JULIO
I4: =(I3*8.09%)/44 -> 0 | O4: =K1-J126 -> -315014.57
A5: Piso | B5: Dpto. | C5: UF | D5: Propietario | E5: (%) | F5: Saldo | G5: Ingreso | H5: SALDO | I5: Expensas extraor. | J5: Expensas ord | K5: SUM/ GASTOS PART | L5: TOTAL EXPENSAS 1er VTO | M5: TOTAL EXPENSAS 2do VTO
A7: conf sup | C7: LOC 1 | D7: Fernandez, Cristian | E7: 0.0108 | H7: =F7-G7 -> 0 | I7: 0 | J7: 70998.784 | K7: 0 | L7: =J7+I7+H7+K7 -> 70998.784 | M7: =L7*6% + L7 -> 75258.711 | P7: para copias y pegar las expensas ord del local
C8: LOC 2 | D8: Sr propietario | E8: 0.013 | H8: =F8-G8 -> 0 | I8: 0 | J8: 84146.707 | K8: =I$3*E8%+I$4 -> 0 | L8: =J8+I8+H8+K8 -> 84146.707 | M8: =L8*6% + L8 -> 89195.51
A9: conf sup | C9: LOC 3 | D9: Passeri, Hernán | E9: 0.0121 | H9: =F9-G9 -> 0 | I9: 0 | J9: 79544.934 | K9: =I$3*E9%+I$4 -> 0 | L9: =J9+I9+H9+K9 -> 79544.934 | M9: =L9*6% + L9 -> 84317.63 | P9: LOCAL 1 | Q9: =RESUMEN!F96 -> 77824.742
A10: conf sup | C10: LOC 4 | D10: Cordero, Leandro Emanuel - Orona, Victoria | E10: 0.0149 | H10: =F10-G10 -> 0 | I10: 0 | J10: 97952.027 | K10: =I$3*E10%+I$4 -> 0 | L10: =J10+I10+H10+K10 -> 97952.027 | M10: =L10*6% + L10 -> 103829.15 | P10: LOCAL 2 | Q10: =RESUMEN!G96 -> 92236.731
A11: conf sup | C11: LOC 5 | D11: Sr propietario | E11: 0.0174 | H11: =F11-G11 -> 0 | I11: 0 | J11: 114386.93 | K11: =I$3*E11%+I$4 -> 0 | L11: =J11+I11+H11+K11 -> 114386.93 | M11: =L11*6% + L11 -> 121250.15 | P11: LOCAL 3 | Q11: =RESUMEN!H96 -> 87192.535
A12: 3 amb | C12: 2ºA | D12: Franco, Lucas Fabián | E12: 0.0188 | H12: =F12-G12 -> 0 | I12: =L$4*E12 -> 0 | J12: =L$2*E12 -> 134280.8 | K12: =I$3*E12%+I$4 -> 0 | L12: =ROUND((J12+I12+H12+K12),0) + N12 -> 134281.01 | M12: =ROUND((L12*6% + L12 ),0) + N12 -> 142338.01 | N12: 0.01 | P12: LOCAL 4 | Q12: =RESUMEN!I96 -> 107369.32
A13: 1 amb | C13: 2ºB | D13: Martinez, Diego | E13: 0.0084 | H13: =F13-G13 -> 0 | I13: =L$4*E13 -> 0 | J13: =L$2*E13 -> 59997.805 | K13: =I$3*E13%+I$4 -> 0 | L13: =ROUND((J13+I13+H13+K13),0) + N13 -> 59998.02 | M13: =ROUND((L13*6% + L13 ),0) + N13 -> 63598.02 | N13: =N12+0.01 -> 0.02 | P13: LOCAL 5 | Q13: =RESUMEN!J96 -> 125384.31
A14: 3 amb | C14: 2ºC | D14: Rodriguez, Carlos Alberto Miguel | E14: 0.0201 | H14: =F14-G14 -> 0 | I14: =L$4*E14 -> 0 | J14: =L$2*E14 -> 143566.18 | K14: =I$3*E14%+I$4 -> 0 | L14: =ROUND((J14+I14+H14+K14),0) + N14 -> 143566.03 | M14: =ROUND((L14*6% + L14 ),0) + N14 -> 152180.03 | N14: =N13+0.01 -> 0.03
A15: 2 amb | C15: 2ºD | D15: Ferraro, José | E15: 0.0094 | H15: =F15-G15 -> 0 | I15: =L$4*E15 -> 0 | J15: =L$2*E15 -> 67140.401 | K15: =I$3*E15%+I$4 -> 0 | L15: =ROUND((J15+I15+H15+K15),0) + N15 -> 67140.04 | M15: =ROUND((L15*6% + L15 ),0) + N15 -> 71168.04 | N15: =N14+0.01 -> 0.04
A16: 2 amb | C16: 2ºE | D16: Dieci, Matias Orlando | E16: 0.0087 | H16: =F16-G16 -> 0 | I16: =L$4*E16 -> 0 | J16: =L$2*E16 -> 62140.584 | K16: 0 | L16: =ROUND((J16+I16+H16+K16),0) + N16 -> 62141.05 | M16: =ROUND((L16*6% + L16 ),0) + N16 -> 65870.05 | N16: =N15+0.01 -> 0.05
A17: 2 amb | C17: 2ºF | D17: Ferraro, Jose | E17: 0.0095 | H17: =F17-G17 -> 0 | I17: =L$4*E17 -> 0 | J17: =L$2*E17 -> 67854.661 | K17: =I$3*E17%+I$4 -> 0 | L17: =ROUND((J17+I17+H17+K17),0) + N17 -> 67855.06 | M17: =ROUND((L17*6% + L17 ),0) + N17 -> 71926.06 | N17: =N16+0.01 -> 0.06
A18: 3 amb | C18: 3ºA | D18: Ferraro, Jose | E18: 0.0165 | H18: =F18-G18 -> 0 | I18: =L$4*E18 -> 0 | J18: =L$2*E18 -> 117852.83 | K18: =I$3*E18%+I$4 -> 0 | L18: =ROUND((J18+I18+H18+K18),0) + N18 -> 117853.07 | M18: =ROUND((L18*6% + L18 ),0) + N18 -> 124924.07 | N18: =N17+0.01 -> 0.07
A19: 1 amb | C19: 3ºB | D19: Ayala, Roberto Adrian | E19: 0.0073 | H19: =F19-G19 -> 0 | I19: =L$4*E19 -> 0 | J19: =L$2*E19 -> 52140.95 | K19: =I$3*E19%+I$4 -> 0 | L19: =ROUND((J19+I19+H19+K19),0) + N19 -> 52141.08 | M19: =ROUND((L19*6% + L19 ),0) + N19 -> 55270.08 | N19: =N18+0.01 -> 0.08
A20: 3 amb | C20: 3ºC | D20: Ferraro, Jose | E20: 0.0178 | H20: =F20-G20 -> 0 | I20: =L$4*E20 -> 0 | J20: =L$2*E20 -> 127138.21 | K20: =I$3*E20%+I$4 -> 0 | L20: =ROUND((J20+I20+H20+K20),0) + N20 -> 127138.09 | M20: =ROUND((L20*6% + L20 ),0) + N20 -> 134766.09 | N20: =N19+0.01 -> 0.09
A21: 2 amb | C21: 3ºD | D21: Ayala, Roberto Adrian | E21: 0.0094 | H21: =F21-G21 -> 0 | I21: =L$4*E21 -> 0 | J21: =L$2*E21 -> 67140.401 | K21: =I$3*E21%+I$4 -> 0 | L21: =ROUND((J21+I21+H21+K21),0) + N21 -> 67140.1 | M21: =ROUND((L21*6% + L21 ),0) + N21 -> 71169.1 | N21: =N20+0.01 -> 0.1
A22: 2 amb | C22: 3ºE | D22: Ayala, Roberto Adrian | E22: 0.0087 | H22: =F22-G22 -> 0 | I22: =L$4*E22 -> 0 | J22: =L$2*E22 -> 62140.584 | K22: =I$3*E22%+I$4 -> 0 | L22: =ROUND((J22+I22+H22+K22),0) + N22 -> 62141.11 | M22: =ROUND((L22*6% + L22 ),0) + N22 -> 65870.11 | N22: =N21+0.01 -> 0.11
A23: 2 amb | C23: 3ºF | D23: Ayala, Roberto Adrian | E23: 0.0095 | H23: =F23-G23 -> 0 | I23: =L$4*E23 -> 0 | J23: =L$2*E23 -> 67854.661 | K23: 0 | L23: =ROUND((J23+I23+H23+K23),0) + N23 -> 67855.12 | M23: =ROUND((L23*6% + L23 ),0) + N23 -> 71926.12 | N23: =N22+0.01 -> 0.12
A24: 3 amb | C24: 4ºA | D24: Barral, Carlos Daniel | E24: 0.0164 | H24: =F24-G24 -> 0 | I24: =L$4*E24 -> 0 | J24: =L$2*E24 -> 117138.57 | K24: =2*9000 -> 18000 | L24: =ROUND((J24+I24+H24+K24),0) + N24 -> 135139.13 | M24: =ROUND((L24*6% + L24 ),0) + N24 -> 143247.13 | N24: =N23+0.01 -> 0.13
A25: 1 amb | C25: 4ºB | D25: Sr. Propietario | E25: 0.0072 | H25: =F25-G25 -> 0 | I25: =L$4*E25 -> 0 | J25: =L$2*E25 -> 51426.69 | K25: =I$3*E25%+I$4 -> 0 | L25: =ROUND((J25+I25+H25+K25),0) + N25 -> 51427.14 | M25: =ROUND((L25*6% + L25 ),0) + N25 -> 54513.14 | N25: =N24+0.01 -> 0.14
A26: 3 amb | C26: 4ºC | D26: Osipowicz, Ariel Marcelo | E26: 0.0173 | H26: =F26-G26 -> 0 | I26: =L$4*E26 -> 0 | J26: =L$2*E26 -> 123566.91 | K26: =3*9000 -> 27000 | L26: =ROUND((J26+I26+H26+K26),0) + N26 -> 150567.15 | M26: =ROUND((L26*6% + L26 ),0) + N26 -> 159601.15 | N26: =N25+0.01 -> 0.15
A27: 2 amb | C27: 4ºD | D27: Ayala, Roberto Adrian | E27: 0.0094 | H27: =F27-G27 -> 0 | I27: =L$4*E27 -> 0 | J27: =L$2*E27 -> 67140.401 | K27: =I$3*E27%+I$4 -> 0 | L27: =ROUND((J27+I27+H27+K27),0) + N27 -> 67140.16 | M27: =ROUND((L27*6% + L27 ),0) + N27 -> 71169.16 | N27: =N26+0.01 -> 0.16
A28: 2 amb | C28: 4ºE | D28: Ayala, Roberto Adrian | E28: 0.0087 | H28: =F28-G28 -> 0 | I28: =L$4*E28 -> 0 | J28: =L$2*E28 -> 62140.584 | K28: =I$3*E28%+I$4 -> 0 | L28: =ROUND((J28+I28+H28+K28),0) + N28 -> 62141.17 | M28: =ROUND((L28*6% + L28 ),0) + N28 -> 65870.17 | N28: =N27+0.01 -> 0.17
A29: 2 amb | C29: 4ºF | D29: Ayala, Roberto Adrian | E29: 0.0095 | H29: =F29-G29 -> 0 | I29: =L$4*E29 -> 0 | J29: =L$2*E29 -> 67854.661 | K29: =I$3*E29%+I$4 -> 0 | L29: =ROUND((J29+I29+H29+K29),0) + N29 -> 67855.18 | M29: =ROUND((L29*6% + L29 ),0) + N29 -> 71926.18 | N29: =N28+0.01 -> 0.18
A30: 3 amb | C30: 5ºA | D30: Chehab, Gabriel Adrian | E30: 0.0164 | H30: =F30-G30 -> 0 | I30: =L$4*E30 -> 0 | J30: =L$2*E30 -> 117138.57 | K30: =I$3*E30%+I$4 -> 0 | L30: =ROUND((J30+I30+H30+K30),0) + N30 -> 117139.19 | M30: =ROUND((L30*6% + L30 ),0) + N30 -> 124168.19 | N30: =N29+0.01 -> 0.19
A31: 1 amb | C31: 5ºB | D31: Mesa, Mariano | E31: 0.0072 | H31: =F31-G31 -> 0 | I31: =L$4*E31 -> 0 | J31: =L$2*E31 -> 51426.69 | K31: =I$3*E31%+I$4 -> 0 | L31: =ROUND((J31+I31+H31+K31),0) + N31 -> 51427.2 | M31: =ROUND((L31*6% + L31 ),0) + N31 -> 54513.2 | N31: =N30+0.01 -> 0.2
A32: 3 amb | C32: 5ºC | D32: Di Mito, Vicente Argentino - Serantes, Mabel | E32: 0.0173 | H32: =F32-G32 -> 0 | I32: =L$4*E32 -> 0 | J32: =L$2*E32 -> 123566.91 | K32: =I$3*E32%+I$4 -> 0 | L32: =ROUND((J32+I32+H32+K32),0) + N32 -> 123567.21 | M32: =ROUND((L32*6% + L32 ),0) + N32 -> 130981.21 | N32: =N31+0.01 -> 0.21
A33: 2 amb | C33: 5ºD | D33: Ayala, Roberto Adrian | E33: 0.0094 | H33: =F33-G33 -> 0 | I33: =L$4*E33 -> 0 | J33: =L$2*E33 -> 67140.401 | K33: =I$3*E33%+I$4 -> 0 | L33: =ROUND((J33+I33+H33+K33),0) + N33 -> 67140.22 | M33: =ROUND((L33*6% + L33 ),0) + N33 -> 71169.22 | N33: =N32+0.01 -> 0.22
A34: 2 amb | C34: 5ºE | D34: Ayala, Roberto Adrian | E34: 0.0087 | H34: =F34-G34 -> 0 | I34: =L$4*E34 -> 0 | J34: =L$2*E34 -> 62140.584 | K34: =I$3*E34%+I$4 -> 0 | L34: =ROUND((J34+I34+H34+K34),0) + N34 -> 62141.23 | M34: =ROUND((L34*6% + L34 ),0) + N34 -> 65870.23 | N34: =N33+0.01 -> 0.23
A35: 2 amb | C35: 5ºF | D35: Ayala, Roberto Adrian | E35: 0.0095 | H35: =F35-G35 -> 0 | I35: =L$4*E35 -> 0 | J35: =L$2*E35 -> 67854.661 | K35: =I$3*E35%+I$4 -> 0 | L35: =ROUND((J35+I35+H35+K35),0) + N35 -> 67855.24 | M35: =ROUND((L35*6% + L35 ),0) + N35 -> 71927.24 | N35: =N34+0.01 -> 0.24
A36: 3 amb | C36: 6ºA | D36: Morandi, Victoria Ayelen | Calvo, Luciano Ezequiel | E36: 0.0164 | H36: =F36-G36 -> 0 | I36: =L$4*E36 -> 0 | J36: =L$2*E36 -> 117138.57 | K36: =I$3*E36%+I$4 -> 0 | L36: =ROUND((J36+I36+H36+K36),0) + N36 -> 117139.25 | M36: =ROUND((L36*6% + L36 ),0) + N36 -> 124168.25 | N36: =N35+0.01 -> 0.25
A37: 1 amb | C37: 6ºB | D37: Grizak Ruben | E37: 0.0072 | H37: =F37-G37 -> 0 | I37: =L$4*E37 -> 0 | J37: =L$2*E37 -> 51426.69 | K37: =9000*3 -> 27000 | L37: =ROUND((J37+I37+H37+K37),0) + N37 -> 78427.26 | M37: =ROUND((L37*6% + L37 ),0) + N37 -> 83133.26 | N37: =N36+0.01 -> 0.26
A38: 3 amb | C38: 6ºC | D38: Nuñez Leonel - Corrieri Giuliana | E38: 0.0173 | H38: =F38-G38 -> 0 | I38: =L$4*E38 -> 0 | J38: =L$2*E38 -> 123566.91 | K38: =I$3*E38%+I$4 -> 0 | L38: =ROUND((J38+I38+H38+K38),0) + N38 -> 123567.27 | M38: =ROUND((L38*6% + L38 ),0) + N38 -> 130981.27 | N38: =N37+0.01 -> 0.27
A39: 2 amb | C39: 6ºD | D39: Sr propietario | E39: 0.0094 | H39: =F39-G39 -> 0 | I39: =L$4*E39 -> 0 | J39: =L$2*E39 -> 67140.401 | K39: =I$3*E39%+I$4 -> 0 | L39: =ROUND((J39+I39+H39+K39),0) + N39 -> 67140.28 | M39: =ROUND((L39*6% + L39 ),0) + N39 -> 71169.28 | N39: =N38+0.01 -> 0.28 | P39: mariano hecimovic
A40: 2 amb | C40: 6ºE | D40: Dieci, Matias Orlando | E40: 0.0087 | H40: =F40-G40 -> 0 | I40: =L$4*E40 -> 0 | J40: =L$2*E40 -> 62140.584 | K40: =I$3*E40%+I$4 -> 0 | L40: =ROUND((J40+I40+H40+K40),0) + N40 -> 62141.29 | M40: =ROUND((L40*6% + L40 ),0) + N40 -> 65870.29 | N40: =N39+0.01 -> 0.29
A41: 2 amb | C41: 6ºF | D41: Mazzia Alexia | E41: 0.0095 | H41: =F41-G41 -> 0 | I41: =L$4*E41 -> 0 | J41: =L$2*E41 -> 67854.661 | K41: =I$3*E41%+I$4 -> 0 | L41: =ROUND((J41+I41+H41+K41),0) + N41 -> 67855.3 | M41: =ROUND((L41*6% + L41 ),0) + N41 -> 71927.3 | N41: =N40+0.01 -> 0.3
A42: 3 amb | C42: 7ºA | D42: Campelo, Mariano | E42: 0.0164 | H42: =F42-G42 -> 0 | I42: =L$4*E42 -> 0 | J42: =L$2*E42 -> 117138.57 | K42: =I$3*E42%+I$4 -> 0 | L42: =ROUND((J42+I42+H42+K42),0) + N42 -> 117139.31 | M42: =ROUND((L42*6% + L42 ),0) + N42 -> 124168.31 | N42: =N41+0.01 -> 0.31
A43: 1 amb | C43: 7ºB | D43: Paes, Yazmin Luciana | E43: 0.0072 | H43: =F43-G43 -> 0 | I43: =L$4*E43 -> 0 | J43: =L$2*E43 -> 51426.69 | K43: =I$3*E43%+I$4 -> 0 | L43: =ROUND((J43+I43+H43+K43),0) + N43 -> 51427.32 | M43: =ROUND((L43*6% + L43 ),0) + N43 -> 54513.32 | N43: =N42+0.01 -> 0.32
A44: 3 amb | C44: 7ºC | D44: Gonzalez Fedullo, Roxana y Valeria | E44: 0.0173 | H44: =F44-G44 -> 0 | I44: =L$4*E44 -> 0 | J44: =L$2*E44 -> 123566.91 | K44: =I$3*E44%+I$4 -> 0 | L44: =ROUND((J44+I44+H44+K44),0) + N44 -> 123567.33 | M44: =ROUND((L44*6% + L44 ),0) + N44 -> 130981.33 | N44: =N43+0.01 -> 0.33
A45: 2 amb | C45: 7ºD | D45: Acosta, Daniela Pilar | E45: 0.0094 | H45: =F45-G45 -> 0 | I45: =L$4*E45 -> 0 | J45: =L$2*E45 -> 67140.401 | K45: =I$3*E45%+I$4 -> 0 | L45: =ROUND((J45+I45+H45+K45),0) + N45 -> 67140.34 | M45: =ROUND((L45*6% + L45 ),0) + N45 -> 71169.34 | N45: =N44+0.01 -> 0.34
A46: 2 amb | C46: 7ºE | D46: Leyes, Javier | E46: 0.0087 | H46: =F46-G46 -> 0 | I46: =L$4*E46 -> 0 | J46: =L$2*E46 -> 62140.584 | K46: =I$3*E46%+I$4 -> 0 | L46: =ROUND((J46+I46+H46+K46),0) + N46 -> 62141.35 | M46: =ROUND((L46*6% + L46 ),0) + N46 -> 65870.35 | N46: =N45+0.01 -> 0.35
A47: 2 amb | C47: 7ºF | D47: Puente, Matias | E47: 0.0095 | H47: =F47-G47 -> 0 | I47: =L$4*E47 -> 0 | J47: =L$2*E47 -> 67854.661 | K47: =I$3*E47%+I$4 -> 0 | L47: =ROUND((J47+I47+H47+K47),0) + N47 -> 67855.36 | M47: =ROUND((L47*6% + L47 ),0) + N47 -> 71927.36 | N47: =N46+0.01 -> 0.36
A48: 3 amb | C48: 8ºA | D48: Campelo, Mariano | E48: 0.0164 | H48: =F48-G48 -> 0 | I48: =L$4*E48 -> 0 | J48: =L$2*E48 -> 117138.57 | K48: =I$3*E48%+I$4 -> 0 | L48: =ROUND((J48+I48+H48+K48),0) + N48 -> 117139.37 | M48: =ROUND((L48*6% + L48 ),0) + N48 -> 124168.37 | N48: =N47+0.01 -> 0.37
A49: 1 amb | C49: 8ºB | D49: Morvillo, Mariana Yanil | E49: 0.0072 | H49: =F49-G49 -> 0 | I49: =L$4*E49 -> 0 | J49: =L$2*E49 -> 51426.69 | K49: =I$3*E49%+I$4 -> 0 | L49: =ROUND((J49+I49+H49+K49),0) + N49 -> 51427.38 | M49: =ROUND((L49*6% + L49 ),0) + N49 -> 54513.38 | N49: =N48+0.01 -> 0.38
A50: 3 amb | C50: 8ºC | D50: Frontale, Federico Carlos | Celentano, Alejandra Verónica | E50: 0.0173 | H50: =F50-G50 -> 0 | I50: =L$4*E50 -> 0 | J50: =L$2*E50 -> 123566.91 | K50: =I$3*E50%+I$4 -> 0 | L50: =ROUND((J50+I50+H50+K50),0) + N50 -> 123567.39 | M50: =ROUND((L50*6% + L50 ),0) + N50 -> 130981.39 | N50: =N49+0.01 -> 0.39
A51: 2 amb | C51: 8ºD | D51: Argul, Sergio Walter - Taboada, María Paz | E51: 0.0094 | H51: =F51-G51 -> 0 | I51: =L$4*E51 -> 0 | J51: =L$2*E51 -> 67140.401 | K51: =I$3*E51%+I$4 -> 0 | L51: =ROUND((J51+I51+H51+K51),0) + N51 -> 67140.4 | M51: =ROUND((L51*6% + L51 ),0) + N51 -> 71169.4 | N51: =N50+0.01 -> 0.4
A52: 2 amb | C52: 8ºE | D52: Sr propietario | E52: 0.0087 | H52: =F52-G52 -> 0 | I52: =L$4*E52 -> 0 | J52: =L$2*E52 -> 62140.584 | K52: =I$3*E52%+I$4 -> 0 | L52: =ROUND((J52+I52+H52+K52),0) + N52 -> 62141.41 | M52: =ROUND((L52*6% + L52 ),0) + N52 -> 65870.41 | N52: =N51+0.01 -> 0.41 | P52: el de sergio
A53: 2 amb | C53: 8ºF | D53: Arias, Mariana Laura | E53: 0.0095 | H53: =F53-G53 -> 0 | I53: =L$4*E53 -> 0 | J53: =L$2*E53 -> 67854.661 | K53: =I$3*E53%+I$4 -> 0 | L53: =ROUND((J53+I53+H53+K53),0) + N53 -> 67855.42 | M53: =ROUND((L53*6% + L53 ),0) + N53 -> 71927.42 | N53: =N52+0.01 -> 0.42
A54: 3 amb | C54: 9ºA | D54: Fanjul, Alejandro Rubén Marcelo | E54: 0.0164 | H54: =F54-G54 -> 0 | I54: =L$4*E54 -> 0 | J54: =L$2*E54 -> 117138.57 | K54: =I$3*E54%+I$4 -> 0 | L54: =ROUND((J54+I54+H54+K54),0) + N54 -> 117139.43 | M54: =ROUND((L54*6% + L54 ),0) + N54 -> 124168.43 | N54: =N53+0.01 -> 0.43
A55: 1 amb | C55: 9ºB | D55: Fanjul, Alejandro Rubén Marcelo | E55: 0.0072 | H55: =F55-G55 -> 0 | I55: =L$4*E55 -> 0 | J55: =L$2*E55 -> 51426.69 | K55: =I$3*E55%+I$4 -> 0 | L55: =ROUND((J55+I55+H55+K55),0) + N55 -> 51427.44 | M55: =ROUND((L55*6% + L55 ),0) + N55 -> 54513.44 | N55: =N54+0.01 -> 0.44
A56: 3 amb | C56: 9ºC | D56: Franchino, Mauro | E56: 0.0173 | H56: =F56-G56 -> 0 | I56: =L$4*E56 -> 0 | J56: =L$2*E56 -> 123566.91 | K56: =I$3*E56%+I$4 -> 0 | L56: =ROUND((J56+I56+H56+K56),0) + N56 -> 123567.45 | M56: =ROUND((L56*6% + L56 ),0) + N56 -> 130981.45 | N56: =N55+0.01 -> 0.45
A57: 2 amb | C57: 9ºD | D57: Cerra, Antonio Osvaldo | E57: 0.0094 | H57: =F57-G57 -> 0 | I57: =L$4*E57 -> 0 | J57: =L$2*E57 -> 67140.401 | K57: =I$3*E57%+I$4 -> 0 | L57: =ROUND((J57+I57+H57+K57),0) + N57 -> 67140.46 | M57: =ROUND((L57*6% + L57 ),0) + N57 -> 71169.46 | N57: =N56+0.01 -> 0.46
A58: 2 amb | C58: 9ºE | D58: Dieci, Matias Orlando | E58: 0.0087 | H58: =F58-G58 -> 0 | I58: =L$4*E58 -> 0 | J58: =L$2*E58 -> 62140.584 | K58: =I$3*E58%+I$4 -> 0 | L58: =ROUND((J58+I58+H58+K58),0) + N58 -> 62141.47 | M58: =ROUND((L58*6% + L58 ),0) + N58 -> 65870.47 | N58: =N57+0.01 -> 0.47
A59: 2 amb | C59: 9ºF | D59: Rosales, Rubén Darío | E59: 0.0095 | H59: =F59-G59 -> 0 | I59: =L$4*E59 -> 0 | J59: =L$2*E59 -> 67854.661 | K59: =I$3*E59%+I$4 -> 0 | L59: =ROUND((J59+I59+H59+K59),0) + N59 -> 67855.48 | M59: =ROUND((L59*6% + L59 ),0) + N59 -> 71927.48 | N59: =N58+0.01 -> 0.48
A60: 3 amb | C60: 10ºA | D60: Puisys Guillermo Antonio | E60: 0.0164 | H60: =F60-G60 -> 0 | I60: =L$4*E60 -> 0 | J60: =L$2*E60 -> 117138.57 | K60: =I$3*E60%+I$4 -> 0 | L60: =ROUND((J60+I60+H60+K60),0) + N60 -> 117139.49 | M60: =ROUND((L60*6% + L60 ),0) + N60 -> 124168.49 | N60: =N59+0.01 -> 0.49
A61: 1 amb | C61: 10ºB | D61: Lange, Gustavo Daniel | E61: 0.0072 | H61: =F61-G61 -> 0 | I61: =L$4*E61 -> 0 | J61: =L$2*E61 -> 51426.69 | K61: =I$3*E61%+I$4 -> 0 | L61: =ROUND((J61+I61+H61+K61),0) + N61 -> 51427.5 | M61: =ROUND((L61*6% + L61 ),0) + N61 -> 54513.5 | N61: =N60+0.01 -> 0.5
A62: 3 amb | C62: 10ºC | D62: Espósito, Franco Ezequiel | E62: 0.0173 | H62: =F62-G62 -> 0 | I62: =L$4*E62 -> 0 | J62: =L$2*E62 -> 123566.91 | K62: =I$3*E62%+I$4 -> 0 | L62: =ROUND((J62+I62+H62+K62),0) + N62 -> 123567.51 | M62: =ROUND((L62*6% + L62 ),0) + N62 -> 130982.51 | N62: =N61+0.01 -> 0.51
A63: 2 amb | C63: 10ºD | D63: Lobato, Lorena - Vega, Maximiliano | E63: 0.0094 | H63: =F63-G63 -> 0 | I63: =L$4*E63 -> 0 | J63: =L$2*E63 -> 67140.401 | K63: =I$3*E63%+I$4 -> 0 | L63: =ROUND((J63+I63+H63+K63),0) + N63 -> 67140.52 | M63: =ROUND((L63*6% + L63 ),0) + N63 -> 71169.52 | N63: =N62+0.01 -> 0.52
A64: 2 amb | C64: 10ºE | D64: Sr propietario | E64: 0.0087 | H64: =F64-G64 -> 0 | I64: =L$4*E64 -> 0 | J64: =L$2*E64 -> 62140.584 | K64: =I$3*E64%+I$4 -> 0 | L64: =ROUND((J64+I64+H64+K64),0) + N64 -> 62141.53 | M64: =ROUND((L64*6% + L64 ),0) + N64 -> 65870.53 | N64: =N63+0.01 -> 0.53 | P64: mariano hecimovic
A65: 2 amb | C65: 10ºF | D65: Ramos, Sergio Eugenio | E65: 0.0095 | H65: =F65-G65 -> 0 | I65: =L$4*E65 -> 0 | J65: =L$2*E65 -> 67854.661 | K65: =I$3*E65%+I$4 -> 0 | L65: =ROUND((J65+I65+H65+K65),0) + N65 -> 67855.54 | M65: =ROUND((L65*6% + L65 ),0) + N65 -> 71927.54 | N65: =N64+0.01 -> 0.54
A66: 4 amb | C66: 11ºA/B | D66: Mosquera, Julio Rodolfo | Cuzzolino, Daniela Carol | E66: 0.0235 | H66: =F66-G66 -> 0 | I66: =L$4*E66 -> 0 | J66: =L$2*E66 -> 167851 | K66: =I$3*E66%+I$4 -> 0 | L66: =ROUND((J66+I66+H66+K66),0) + N66 -> 167851.55 | M66: =ROUND((L66*6% + L66 ),0) + N66 -> 177923.55 | N66: =N65+0.01 -> 0.55
A67: 3 amb | C67: 11ºC | D67: Silvestre Villarruel Eduardo | E67: 0.0173 | H67: =F67-G67 -> 0 | I67: =L$4*E67 -> 0 | J67: =L$2*E67 -> 123566.91 | K67: =I$3*E67%+I$4 -> 0 | L67: =ROUND((J67+I67+H67+K67),0) + N67 -> 123567.56 | M67: =ROUND((L67*6% + L67 ),0) + N67 -> 130982.56 | N67: =N66+0.01 -> 0.56
A68: 2 amb | C68: 11ºD | D68: Cadahia, Rosanna Patricia | E68: 0.0094 | H68: =F68-G68 -> 0 | I68: =L$4*E68 -> 0 | J68: =L$2*E68 -> 67140.401 | K68: =I$3*E68%+I$4 -> 0 | L68: =ROUND((J68+I68+H68+K68),0) + N68 -> 67140.57 | M68: =ROUND((L68*6% + L68 ),0) + N68 -> 71169.57 | N68: =N67+0.01 -> 0.57
A69: 2 amb | C69: 11ºE | D69: Argúl, Adrián Norberto | E69: 0.0087 | H69: =F69-G69 -> 0 | I69: =L$4*E69 -> 0 | J69: =L$2*E69 -> 62140.584 | K69: =I$3*E69%+I$4 -> 0 | L69: =ROUND((J69+I69+H69+K69),0) + N69 -> 62141.58 | M69: =ROUND((L69*6% + L69 ),0) + N69 -> 65870.58 | N69: =N68+0.01 -> 0.58
A70: 2 amb | C70: 11ºF | D70: Lobato, Lorena - Vega, Maximiliano | E70: 0.0095 | H70: =F70-G70 -> 0 | I70: =L$4*E70 -> 0 | J70: =L$2*E70 -> 67854.661 | K70: =I$3*E70%+I$4 -> 0 | L70: =ROUND((J70+I70+H70+K70),0) + N70 -> 67855.59 | M70: =ROUND((L70*6% + L70 ),0) + N70 -> 71927.59 | N70: =N69+0.01 -> 0.59
A71: 4 amb | C71: 12ºA/B | D71: Luciano, Carmen Veronica - Rey, Javier Pablo | E71: 0.0235 | H71: =F71-G71 -> 0 | I71: =L$4*E71 -> 0 | J71: =L$2*E71 -> 167851 | K71: =I$3*E71%+I$4 -> 0 | L71: =ROUND((J71+I71+H71+K71),0) + N71 -> 167851.6 | M71: =ROUND((L71*6% + L71 ),0) + N71 -> 177923.6 | N71: =N70+0.01 -> 0.6
A72: 3 amb | C72: 12ºC | D72: Hernandez, Marisa Beatriz - Hernandez, Adrian Jose | E72: 0.0173 | H72: =F72-G72 -> 0 | I72: =L$4*E72 -> 0 | J72: =L$2*E72 -> 123566.91 | K72: =I$3*E72%+I$4 -> 0 | L72: =ROUND((J72+I72+H72+K72),0) + N72 -> 123567.61 | M72: =ROUND((L72*6% + L72 ),0) + N72 -> 130982.61 | N72: =N71+0.01 -> 0.61
A73: 2 amb | C73: 12ºD | D73: Morini, Micaela | E73: 0.0094 | H73: =F73-G73 -> 0 | I73: =L$4*E73 -> 0 | J73: =L$2*E73 -> 67140.401 | K73: =I$3*E73%+I$4 -> 0 | L73: =ROUND((J73+I73+H73+K73),0) + N73 -> 67140.62 | M73: =ROUND((L73*6% + L73 ),0) + N73 -> 71169.62 | N73: =N72+0.01 -> 0.62
A74: 2 amb | C74: 12ºE | D74: Armerding, Jorge | E74: 0.0087 | H74: =F74-G74 -> 0 | I74: =L$4*E74 -> 0 | J74: =L$2*E74 -> 62140.584 | K74: =I$3*E74%+I$4 -> 0 | L74: =ROUND((J74+I74+H74+K74),0) + N74 -> 62141.63 | M74: =ROUND((L74*6% + L74 ),0) + N74 -> 65870.63 | N74: =N73+0.01 -> 0.63
A75: 2 amb | C75: 12ºF | D75: Bilyj, Josefa Catalina | E75: 0.0095 | H75: =F75-G75 -> 0 | I75: =L$4*E75 -> 0 | J75: =L$2*E75 -> 67854.661 | K75: 9000 | L75: =ROUND((J75+I75+H75+K75),0) + N75 -> 76855.64 | M75: =ROUND((L75*6% + L75 ),0) + N75 -> 81467.64 | N75: =N74+0.01 -> 0.64
A76: 4 amb | C76: 13ºA/B | D76: Sr propietario | E76: 0.0235 | H76: =F76-G76 -> 0 | I76: =L$4*E76 -> 0 | J76: =L$2*E76 -> 167851 | K76: =I$3*E76%+I$4 -> 0 | L76: =ROUND((J76+I76+H76+K76),0) + N76 -> 167851.65 | M76: =ROUND((L76*6% + L76 ),0) + N76 -> 177923.65 | N76: =N75+0.01 -> 0.65
A77: 3 amb | C77: 13ºC | D77: Argentino, Javier Leonardo | E77: 0.0173 | H77: =F77-G77 -> 0 | I77: =L$4*E77 -> 0 | J77: =L$2*E77 -> 123566.91 | K77: =I$3*E77%+I$4 -> 0 | L77: =ROUND((J77+I77+H77+K77),0) + N77 -> 123567.66 | M77: =ROUND((L77*6% + L77 ),0) + N77 -> 130982.66 | N77: =N76+0.01 -> 0.66
A78: 2 amb | C78: 13ºD | D78: Scardigno, Gabriela Susana - Ripoll, Luis Alberto | E78: 0.0094 | H78: =F78-G78 -> 0 | I78: =L$4*E78 -> 0 | J78: =L$2*E78 -> 67140.401 | K78: =I$3*E78%+I$4 -> 0 | L78: =ROUND((J78+I78+H78+K78),0) + N78 -> 67140.67 | M78: =ROUND((L78*6% + L78 ),0) + N78 -> 71169.67 | N78: =N77+0.01 -> 0.67
A79: 2 amb | C79: 13ºE | D79: Quiñones, Carlos Eduardo | E79: 0.0087 | H79: =F79-G79 -> 0 | I79: =L$4*E79 -> 0 | J79: =L$2*E79 -> 62140.584 | K79: =I$3*E79%+I$4 -> 0 | L79: =ROUND((J79+I79+H79+K79),0) + N79 -> 62141.68 | M79: =ROUND((L79*6% + L79 ),0) + N79 -> 65870.68 | N79: =N78+0.01 -> 0.68
A80: 2 amb | C80: 13ºF | D80: Mosquera, José Elias | E80: 0.0095 | H80: =F80-G80 -> 0 | I80: =L$4*E80 -> 0 | J80: =L$2*E80 -> 67854.661 | K80: =I$3*E80%+I$4 -> 0 | L80: =ROUND((J80+I80+H80+K80),0) + N80 -> 67855.69 | M80: =ROUND((L80*6% + L80 ),0) + N80 -> 71927.69 | N80: =N79+0.01 -> 0.69
C81: COCH 1 | D81: Osipowicz, Ariel Marcelo | E81: 0.0023 | H81: =F81-G81 -> 0 | I81: =L$4*E81 -> 0 | J81: =L$2*E81 -> 16427.97 | K81: =I$3*E81%+I$4 -> 0 | L81: =ROUND((J81+I81+H81+K81),0) + N81 -> 16428.7 | M81: =ROUND((L81*6% + L81 ),0) + N81 -> 17414.7 | N81: =N80+0.01 -> 0.7
C82: COCH 2 | D82: Sr propietario | E82: 0.0023 | H82: =F82-G82 -> 0 | I82: =L$4*E82 -> 0 | J82: =L$2*E82 -> 16427.97 | K82: =I$3*E82%+I$4 -> 0 | L82: =ROUND((J82+I82+H82+K82),0) + N82 -> 16428.71 | M82: =ROUND((L82*6% + L82 ),0) + N82 -> 17414.71 | N82: =N81+0.01 -> 0.71
C83: COCH 3 | D83: Paes, Yazmin Luciana | E83: 0.0023 | H83: =F83-G83 -> 0 | I83: =L$4*E83 -> 0 | J83: =L$2*E83 -> 16427.97 | K83: =I$3*E83%+I$4 -> 0 | L83: =ROUND((J83+I83+H83+K83),0) + N83 -> 16428.72 | M83: =ROUND((L83*6% + L83 ),0) + N83 -> 17414.72 | N83: =N82+0.01 -> 0.72
C84: COCH 4 | D84: Puisys Guillermo Antonio | E84: 0.0023 | H84: =F84-G84 -> 0 | I84: =L$4*E84 -> 0 | J84: =L$2*E84 -> 16427.97 | K84: =I$3*E84%+I$4 -> 0 | L84: =ROUND((J84+I84+H84+K84),0) + N84 -> 16428.73 | M84: =ROUND((L84*6% + L84 ),0) + N84 -> 17414.73 | N84: =N83+0.01 -> 0.73
C85: COCH 5 | D85: Arias, Mariana Laura | E85: 0.0023 | H85: =F85-G85 -> 0 | I85: =L$4*E85 -> 0 | J85: =L$2*E85 -> 16427.97 | K85: =I$3*E85%+I$4 -> 0 | L85: =ROUND((J85+I85+H85+K85),0) + N85 -> 16428.74 | M85: =ROUND((L85*6% + L85 ),0) + N85 -> 17414.74 | N85: =N84+0.01 -> 0.74
C86: COCH 6 | D86: Dimito, Vicente Argentino - Cerantes , Mabel | E86: 0.0023 | H86: =F86-G86 -> 0 | I86: =L$4*E86 -> 0 | J86: =L$2*E86 -> 16427.97 | K86: =I$3*E86%+I$4 -> 0 | L86: =ROUND((J86+I86+H86+K86),0) + N86 -> 16428.75 | M86: =ROUND((L86*6% + L86 ),0) + N86 -> 17414.75 | N86: =N85+0.01 -> 0.75
C87: COCH 7 | D87: Campelo, Mariano | E87: 0.0023 | H87: =F87-G87 -> 0 | I87: =L$4*E87 -> 0 | J87: =L$2*E87 -> 16427.97 | K87: =I$3*E87%+I$4 -> 0 | L87: =ROUND((J87+I87+H87+K87),0) + N87 -> 16428.76 | M87: =ROUND((L87*6% + L87 ),0) + N87 -> 17414.76 | N87: =N86+0.01 -> 0.76
C88: COCH 8 | D88: Campelo, Mariano | E88: 0.0023 | H88: =F88-G88 -> 0 | I88: =L$4*E88 -> 0 | J88: =L$2*E88 -> 16427.97 | K88: =I$3*E88%+I$4 -> 0 | L88: =ROUND((J88+I88+H88+K88),0) + N88 -> 16428.77 | M88: =ROUND((L88*6% + L88 ),0) + N88 -> 17414.77 | N88: =N87+0.01 -> 0.77
C89: COCH 9 | D89: Sr propietario | E89: 0.0023 | H89: =F89-G89 -> 0 | I89: =L$4*E89 -> 0 | J89: =L$2*E89 -> 16427.97 | K89: =I$3*E89%+I$4 -> 0 | L89: =ROUND((J89+I89+H89+K89),0) + N89 -> 16428.78 | M89: =ROUND((L89*6% + L89 ),0) + N89 -> 17415.78 | N89: =N88+0.01 -> 0.78
C90: COCH 10 | D90: Cerra, Antonio Osvaldo | E90: 0.0023 | H90: =F90-G90 -> 0 | I90: =L$4*E90 -> 0 | J90: =L$2*E90 -> 16427.97 | K90: =I$3*E90%+I$4 -> 0 | L90: =ROUND((J90+I90+H90+K90),0) + N90 -> 16428.79 | M90: =ROUND((L90*6% + L90 ),0) + N90 -> 17415.79 | N90: =N89+0.01 -> 0.79
C91: COCH 11 | D91: Osipowicz, Ariel Marcelo | E91: 0.0023 | H91: =F91-G91 -> 0 | I91: =L$4*E91 -> 0 | J91: =L$2*E91 -> 16427.97 | K91: =I$3*E91%+I$4 -> 0 | L91: =ROUND((J91+I91+H91+K91),0) + N91 -> 16428.8 | M91: =ROUND((L91*6% + L91 ),0) + N91 -> 17415.8 | N91: =N90+0.01 -> 0.8
C92: COCH 12 | D92: Dieci, Matias Orlando | E92: 0.0023 | H92: =F92-G92 -> 0 | I92: =L$4*E92 -> 0 | J92: =L$2*E92 -> 16427.97 | K92: =I$3*E92%+I$4 -> 0 | L92: =ROUND((J92+I92+H92+K92),0) + N92 -> 16428.81 | M92: =ROUND((L92*6% + L92 ),0) + N92 -> 17415.81 | N92: =N91+0.01 -> 0.81
... C122: COCH 42 | D122: Quiñones, Carlos Eduardo | E122: 0.0023 | H122: =F122-G122 -> 0 | I122: =L$4*E122 -> 0 | J122: =L$2*E122 -> 16427.97 | K122: =I$3*E122%+I$4 -> 0 | L122: =ROUND((J122+I122+H122+K122),0) + N122 -> 16429.11 | M122: =ROUND((L122*6% + L122 ),0) + N122 -> 17416.11 | N122: =N121+0.01 -> 1.11
A123: COC | C123: COCH 43 | D123: Franchino, Mauro | E123: 0.0023 | G123: =F123 -> 0 | H123: =F123-G123 -> 0 | I123: =L$4*E123 -> 0 | J123: =L$2*E123 -> 16427.97 | K123: =I$3*E123%+I$4 -> 0 | L123: =ROUND((J123+I123+H123+K123),0) + N123 -> 16429.12 | M123: =ROUND((L123*6% + L123 ),0) + N123 -> 17416.12 | N123: =N122+0.01 -> 1.12
A124: COC | C124: COCH 44 | D124: Sr propietario | E124: 0.0023 | G124: =F124 -> 0 | H124: =F124-G124 -> 0 | I124: =L$4*E124 -> 0 | J124: =L$2*E124 -> 16427.97 | K124: =I$3*E124%+I$4 -> 0 | L124: =ROUND((J124+I124+H124+K124),0) + N124 -> 16429.13 | M124: =ROUND((L124*6% + L124 ),0) + N124 -> 17416.13 | N124: =N123+0.01 -> 1.13
A125: COC
E126: =SUM(E7:E125) -> 0.9982 | F126: =SUM(F7:F125) -> 0 | G126: =SUM(G7:G125) -> 0 | I126: =SUM(I7:I125) -> 0 | J126: =SUM(J7:J125) -> 7089643.5 | K126: =SUM(K7:K125) -> 81000 | L126: =SUM(L7:L125) -> 7170719.8 | M126: =SUM(M7:M125) -> 7601040.6
J127: =J126-K1 -> 315014.57
C131: Importante para dueños o inquilinos de departamentos o coheras: Queremos recordarles una cuestión importante respecto a los pagos de expensas que ayuda a evitar errores en la imputación de los mismos. El sistema que utilizamos asigna centavos únicos a cada Unidad Funcional (UF), lo cual nos permite identificar automáticamente a qué unidad corresponde cada transferencia. Es decir, cada UF tiene un número específico de centavos que actúa como "identificador". Por ejemplo, si tu UF es la 45, el importe a abonar debería terminar en $...,45. Si tenés más de una unidad (por ejemplo, un departamento y una cochera), cada una tiene su propio código de centavos. En esos casos, te pedimos por favor que realices una transferencia por cada UF, respetando el importe con sus centavos correspondientes. Sabemos que a veces por comodidad se suele enviar todo junto en una sola transferencia, pero esto puede generar confusión o errores en la imputación automática. Realizar los pagos por separado nos permite asegurar que cada importe se asigne correctamente. Agradecemos muchísimo la colaboración para seguir manteniendo todo ordenado. Saludos cordiales.
C141: El monto que se prorratea entre las unidades funcionales resulta mayor al gasto efectivamente realizado. Esto se debe a que, al prorratear únicamente el monto gastado, no se logra recaudar el total necesario para cubrir el 100% de los gastos. La razón principal es que los locales no abonan estrictamente el porcentaje que les corresponde según la liquidación; en algunos casos, aportan solo el 6,8% de ciertos gastos y en otros no realizan abonos ya que segun reglamento, los mismos se encuentran excentos de abonar gastos de los cuales no participaran en el uso (ej: pileta). Por esta razón, es necesario prorratear un monto superior al gasto real, con el objetivo de que, al finalizar el período, se pueda recaudar en su totalidad el importe correspondiente a los gastos realizados.
O143: =K1-J126 -> -315014.57

Sheet ANOTACIONES
B4: AGREGAR MAILS DEL FOLEO

Sheet SUELDOS
C3: =RESUMEN!C5 -> PERÍODO: JULIO | F3: =RESUMEN!A22 -> Sueldo encargada Sonia Arzamendia Galeano
C5: =RESUMEN!A23 -> Haberes | G5: =RESUMEN!D23 -> 963000 | H5: Firma
C6: =RESUMEN!A24 -> Plus pileta | G6: =RESUMEN!D24 -> 33606.9 | H6: __________________________________
C7: =RESUMEN!A25 -> Plus retiro de basura | G7: =RESUMEN!D25 -> 111256.4
C8: =RESUMEN!A26 -> Plus cochera | G8: =RESUMEN!D26 -> 19877.4
C9: =RESUMEN!A27 -> Adicional remuneracion | G9: =RESUMEN!D27 -> 50000 | H9: Aclaracion
C10: =RESUMEN!A28 -> SAC | G10: =RESUMEN!D28 -> 410000 | H10: __________________________________
C12: TOTAL | G12: =SUM(G5:G11) -> 1587740.7
C16: =RESUMEN!C5 -> PERÍODO: JULIO | F16: =RESUMEN!A30 -> Sueldo encargada Miriam
C18: =RESUMEN!A30 -> Sueldo encargada Miriam | H18: Firma
C19: =RESUMEN!A31 -> Haberes | G19: =RESUMEN!D31 -> 240732 | H19: __________________________________
C20: =RESUMEN!A32 -> Plus pileta | G20: =RESUMEN!D32 -> 33606.9
C21: =RESUMEN!A33 -> Plus retiro de basura | G21: =RESUMEN!D33 -> 111256.4
C22: =RESUMEN!A34 -> Plus cochera | G22: =RESUMEN!D34 -> 19877.4 | H22: Aclaracion
C23: =RESUMEN!A35 -> Adicional remuneracion | G23: =RESUMEN!D35 -> 50000 | H23: __________________________________
C25: TOTAL | G25: =SUM(G18:G24) -> 455472.7
