Workbook

Sheet RESUMEN
C1: MAIL: elmiradorconsorcios@gmail.com
C2: CUIT ADMINISTRACION: 27231256879
C3: CBU: 0720039720000002171436 | E3: TELEFONO: 11 5320-2676
C4: ADMINISTRADORA: CAROLINA CANCIANI MP:1148
C5: PERÍODO: MAYO | E5: HORARIOS DE ATENCION: LUNES A VIERNES - 10 A 15HS - EMERGENCIAS 24HS
C6: LIQUIDACION DE EXPENSAS
A14: Importante para dueños o inquilinos de departamentos o coheras: Queremos recordarles una cuestión importante respecto a los pagos de expensas que ayuda a evitar errores en la imputación de los mismos. El sistema que utilizamos asigna centavos únicos a cada Unidad Funcional (UF), lo cual nos permite identificar automáticamente a qué unidad corresponde cada transferencia. Es decir, cada UF tiene un número específico de centavos que actúa como "identificador". Por ejemplo, si tu UF es la 45, el importe a abonar debería terminar en $...,45. Si tenés más de una unidad (por ejemplo, un departamento y una cochera), cada una tiene su propio código de centavos. En esos casos, te pedimos por favor que realices una transferencia por cada UF, respetando el importe con sus centavos correspondientes. Sabemos que a veces por comodidad se suele enviar todo junto en una sola transferencia, pero esto puede generar confusión o errores en la imputación automática. Realizar los pagos por separado nos permite asegurar que cada importe se asigne correctamente. Agradecemos muchísimo la colaboración para seguir manteniendo todo ordenado. Saludos cordiales.
A20: VTO 18/06
A24: GASTOS ORDINARIOS UNIDADES FUNCIONALES: | E24: UF 93,20% | F24: LOCAL 1 (1,08%) | G24: LOCAL 2 (1,28%) | H24: LOCAL 3 (1,21%) | I24: LOCAL 4 (1,49%) | J24: LOCAL 5 (1,74%)
A25: Salvati - Servicios de limpieza
A26: Servicio de limpieza | C26: Transf 04/05 | D26: 3000000
A27: TOTAL | D27: =SUM(D25:D26) -> 3000000 | E27: =D27*93.2% -> 2796000 | F27: =$D27*1.08% -> 32400 | G27: =$D27*1.28% -> 38400 | H27: =$D27*1.21% -> 36300 | I27: =$D27*1.49% -> 44700 | J27: =D27*1.74% -> 52200 | K27: =E27+J27+F27+G27+H27+I27 -> 3000000 | L27: =IF(D27=K27, "", "Error")
A28: COMBUSTIBLE PARA GRUPO ELECTROGENO
A29: Combustible - Compra | B29: 07/05 Compra Sr. Ariel Osipowicz | D29: 63630
A30: Combustible - Compra | B30: 08/05 Compra Sr. Mariano Campelo - Abono Efectivo | D30: 60000
A31: Combustible - Compra | B31: 07/05 Compra Sr. Carlos Rodriguez -Abono Efectivo | D31: 99726.06
A32: Combustible - Compra | B32: 07/05 Compra Sr. Carlos Rodriguez -Abono Efectivo | D32: 44990.07
A33: Combustible - Compra | B33: 07/05 Compra Sr. Carlos Rodriguez -Abono Efectivo | D33: 70000.03
A34: Combustible - Compra | B34: 08/05 Compra Sr. Mariano Campelo - Abono Efectivo | D34: 60015.95
A36: TOTAL | D36: =SUM(D29:D35) -> 398362.11 | E36: =D36 -> 398362.11 | K36: =E36+J36+F36+G36+H36+I36 -> 398362.11 | L36: =IF(D36=K36, "", "Error")
A37: IMPUESTOS
A38: ARBA - Impuesto inmobiliario partida 025024270-0 | D38: 0
A39: TSG - Partida 197227000 | B39: Mes de MAYO | C39: Transf 22/05 | D39: 1742902
A40: TSG - Partida 197229000 | B40: Mes de MAYO | C40: Transf 22/05 | D40: 1742902
A42: TOTAL IMPUESTOS | D42: =SUM(D38:D41) -> 3485804 | E42: =D42*93.2% -> 3248769.3 | F42: =$D42*1.08% -> 37646.683 | G42: =$D42*1.28% -> 44618.291 | H42: =$D42*1.21% -> 42178.228 | I42: =$D42*1.49% -> 51938.48 | J42: =D42*1.74% -> 60652.99 | K42: =E42+J42+F42+G42+H42+I42 -> 3485804 | L42: =IF(D42=K42, "", "Error")
A43: APORTES Y CONTRIBUCIONES
A47: TOTAL APORTES Y CONTRIBUCIONES | D47: =SUM(D43:D46) -> 0 | E47: =D47*93.2% -> 0 | F47: =$D47*1.08% -> 0 | G47: =$D47*1.28% -> 0 | H47: =$D47*1.21% -> 0 | I47: =$D47*1.49% -> 0 | J47: =D47*1.74% -> 0 | K47: =E47+J47+F47+G47+H47+I47 -> 0 | L47: =IF(D47=K47, "", "Error")
A48: SEGUROS
A49: Federacion patronal - Poliza integral para consorcios nro. 2152393 | C49: Debito autom. | D49: 214371 | E49: =D49*93.2% -> 199793.77 | F49: =$D49*1.08% -> 2315.2068 | G49: =$D49*1.28% -> 2743.9488 | H49: =$D49*1.21% -> 2593.8891 | I49: =$D49*1.49% -> 3194.1279 | J49: =D49*1.74% -> 3730.0554 | K49: =SUM(E49:J49) -> 214371
A51: TOTAL Aportes y Contribuciones - Sindicato | D51: =SUM(D49:D50) -> 214371 | E51: =SUM(E49:E50) -> 199793.77 | F51: =SUM(F49:F50) -> 2315.2068 | G51: =SUM(G49:G50) -> 2743.9488 | H51: =SUM(H49:H50) -> 2593.8891 | I51: =SUM(I49:I50) -> 3194.1279 | J51: =SUM(J49:J50) -> 3730.0554 | K51: =E51+J51+F51+G51+H51+I51 -> 214371 | L51: =IF(D51=K51, "", "Error")
A52: ABONOS Y SERVICIOS
A53: Aysa - Cuenta 249011 | C53: Transf 11/5 | D53: 36079.1 | E53: =D53*93.2% -> 33625.721 | F53: =$D53*1.08% -> 389.65428 | G53: =$D53*1.28% -> 461.81248 | H53: =$D53*1.21% -> 436.55711 | I53: =$D53*1.49% -> 537.57859 | J53: =D53*1.74% -> 627.77634 | K53: =D53 -> 36079.1 | L53: =SUM(E53:J53) -> 36079.1
A54: Edesur - Cliente 01291636 | C54: Transf 12/5 | D54: 3898893.1 | E54: =D54*93.2% -> 3633768.4 | F54: =$D54*1.08% -> 42108.045 | G54: =$D54*1.28% -> 49905.832 | H54: =$D54*1.21% -> 47176.607 | I54: =$D54*1.49% -> 58093.507 | J54: =D54*1.74% -> 67840.74 | K54: =D54 -> 3898893.1 | L54: =E54+J54+I54+H54+G54+F54 -> 3898893.1
A55: Telecentro - Zona coworking - Cliente 7725479 | C55: Debito 19/05 | D55: 151564.8 | E55: =D55 -> 151564.8 | K55: =D55 -> 151564.8 | L55: =E55+J55+I55+H55+G55+F55 -> 151564.8 | M55: =L55-D55 -> 0 | N55: =K55-D55 -> 0
A56: ADS - Abono de mantenimiento ascensores MAYO del 2025 | C56: Transf 08/04 | D56: 359504.14 | E56: =D56 -> 359504.14 | K56: =D56 -> 359504.14 | L56: =E56+J56+I56+H56+G56+F56 -> 359504.14
A57: Victor Martinez - Abono mantenimiento control de accesos - 2 Meses | C57: Transf 11/05 | D57: 50000 | E57: =D57 -> 50000 | K57: =D57 -> 50000 | L57: =E57+J57+I57+H57+G57+F57 -> 50000 | M57: =L57-D57 -> 0 | N57: =K57-D57 -> 0
A58: Metrogas - Cliente nro. 40000496339 | C58: Transf 13/05 | D58: 5760.01 | E58: =D58*93.2% -> 5368.3293 | F58: =$D58*1.08% -> 62.208108 | G58: =$D58*1.28% -> 73.728128 | H58: =$D58*1.21% -> 69.696121 | I58: =$D58*1.49% -> 85.824149 | J58: =D58*1.74% -> 100.22417 | K58: =D58 -> 5760.01 | L58: =E58+J58+I58+H58+G58+F58 -> 5760.01 | M58: =L58-D58 -> 0 | N58: =K58-D58 -> 0
A59: Metrogas - Cliente nro. 40000497007 | C59: Transf 13/05 | D59: 907421.13 | E59: =D59 -> 907421.13 | K59: =D59 -> 907421.13 | L59: =E59+J59+I59+H59+G59+F59 -> 907421.13 | M59: =L59-D59 -> 0 | N59: =K59-D59 -> 0
A60: Loschi Mantenimiento grupo electrogeno - Abono bimestral | C60: Transf 18/05 | D60: 120000 | E60: =D60 -> 120000 | K60: =D60 -> 120000 | L60: =E60+J60+I60+H60+G60+F60 -> 120000 | M60: =L60-D60 -> 0 | N60: =K60-D60 -> 0
A61: TOTAL ABONOS Y SERVICIOS | D61: =SUM(D53:D60) -> 5529222.3 | E61: =SUM(E53:E60) -> 5261252.5 | F61: =SUM(F53:F60) -> 42559.908 | G61: =SUM(G53:G60) -> 50441.372 | H61: =SUM(H53:H60) -> 47682.86 | I61: =SUM(I53:I60) -> 58716.91 | J61: =SUM(J53:J60) -> 68568.74 | K61: =E61+J61+F61+G61+H61+I61 -> 5529222.3 | L61: =IF(D61=K61, "", "Error") | M61: =D61-K61 -> 0
A64: GASTOS VARIOS
A65: Fumigacion - Silva Nicolas | C65: Transf 21/05 | D65: 200000 | E65: =D65 -> 200000 | K65: =D65 -> 200000 | L65: =SUM(E65:J65) -> 200000
A66: Articulos de limpieza | C66: Transf 06/5 | D66: 314672.6 | E66: =D66*93.2% -> 293274.86 | F66: =$D66*1.08% -> 3398.4641 | G66: =$D66*1.28% -> 4027.8093 | H66: =$D66*1.21% -> 3807.5385 | I66: =$D66*1.49% -> 4688.6217 | J66: =D66*1.74% -> 5475.3032 | K66: =D66 -> 314672.6 | L66: =SUM(E66:J66) -> 314672.6
A67: Articulos de limpieza | C67: Transf 26/05 | D67: 313198 | E67: =D67 -> 313198
A68: Articulos de limpieza - Factura atrasada del mes de Abril | C68: Transf 08/5 | D68: 597500 | E68: =D68*93.2% -> 556870 | F68: =$D68*1.08% -> 6453 | G68: =$D68*1.28% -> 7648 | H68: =$D68*1.21% -> 7229.75 | I68: =$D68*1.49% -> 8902.75 | J68: =D68*1.74% -> 10396.5 | K68: =D68 -> 597500
A69: Ferreteria V&A | C69: Transf 08/05 | D69: 21000 | E69: =D69 -> 21000 | K69: =D69 -> 21000 | L69: =SUM(E69:J69) -> 21000
A70: Maximiliano - Elecitricista - Reconexion palo de luz Edesur | C70: Efectivo | D70: 200000 | E70: =D70 -> 200000 | K70: =D70 -> 200000
A71: Doartero Julio - Revision de medidores de gas ajustado por perdida | C71: Transf 07/05 | D71: 125000 | E71: =D71 -> 125000 | K71: =D71 -> 125000
A72: Doartero Julio - Visita electrica | C72: Transf 11/05 | D72: 25000 | E72: =D72 -> 25000 | K72: =D72 -> 25000
A73: Cuello natalia - Desobstruccion de columna baño 5D | C73: Transf 13/05 | D73: 46200 | E73: =D73 -> 46200 | K73: =D73 -> 46200
A74: Cuello natalia - Desobstruccion de colectora cloacal locales | C74: Transf 22/05 | D74: 191400 | E74: =D74*93.2% -> 178384.8 | F74: =$D74*1.08% -> 2067.12 | G74: =$D74*1.28% -> 2449.92 | H74: =$D74*1.21% -> 2315.94 | I74: =$D74*1.49% -> 2851.86 | J74: =D74*1.74% -> 3330.36
A75: TOTAL GASTOS VARIOS | D75: =SUM(D65:D74) -> 2033970.6 | E75: =SUM(E65:E74) -> 1958927.7 | F75: =SUM(F65:F74) -> 11918.584 | G75: =SUM(G65:G74) -> 14125.729 | H75: =SUM(H65:H74) -> 13353.228 | I75: =SUM(I65:I74) -> 16443.232 | J75: =SUM(J65:J74) -> 19202.163 | K75: =E75+J75+F75+G75+H75+I75 -> 2033970.6 | L75: =IF(D75=K75, "", "Error")
A78: GASTOS DE ADMINISTRACION
A79: RC Adm Cons. CANCIANI, Carolina | B79: MP:1148 - SE ADEUDA MAYO | C79: Transf 07/05 | D79: 860560 | E79: =D79*93.2% -> 802041.92 | F79: =$D79*1.08% -> 9294.048 | G79: =$D79*1.28% -> 11015.168 | H79: =$D79*1.21% -> 10412.776 | I79: =$D79*1.49% -> 12822.344 | J79: =D79*1.74% -> 14973.744 | L79: M4rz0
E80: =D80*93.2% -> 0 | F80: =$D80*1.08% -> 0 | G80: =$D80*1.28% -> 0 | H80: =$D80*1.21% -> 0 | I80: =$D80*1.49% -> 0 | J80: =D80*1.74% -> 0
A82: TOTAL GASTOS DE ADMINISTRACION | D82: =SUM(D79:D81) -> 860560 | E82: =SUM(E79:E81) -> 802041.92 | F82: =SUM(F79:F81) -> 9294.048 | G82: =SUM(G79:G81) -> 11015.168 | H82: =SUM(H79:H81) -> 10412.776 | I82: =SUM(I79:I81) -> 12822.344 | J82: =SUM(J79:J81) -> 14973.744 | K82: =E82+J82+F82+G82+H82+I82 -> 860560 | L82: =IF(D82=K82, "", "Error")
A83: Gastos bancarios | D83: =256650.95-853 -> 255797.95 | E83: =D83*93.2% -> 238403.69 | F83: =$D83*1.08% -> 2762.6179 | G83: =$D83*1.28% -> 3274.2138 | H83: =$D83*1.21% -> 3095.1552 | I83: =$D83*1.49% -> 3811.3895 | J83: =D83*1.74% -> 4450.8843
A84: Mantenimiento de cuenta | D84: 69000 | E84: =D84*93.2% -> 64308 | F84: =$D84*1.08% -> 745.2 | G84: =$D84*1.28% -> 883.2 | H84: =$D84*1.21% -> 834.9 | I84: =$D84*1.49% -> 1028.1 | J84: =D84*1.74% -> 1200.6
A85: TOTAL GASTOS BANCARIOS | D85: =SUM(D83:D84) -> 324797.95 | E85: =SUM(E83:E84) -> 302711.69 | F85: =SUM(F83:F84) -> 3507.8179 | G85: =SUM(G83:G84) -> 4157.4138 | H85: =SUM(H83:H84) -> 3930.0552 | I85: =SUM(I83:I84) -> 4839.4895 | J85: =SUM(J83:J84) -> 5651.4843 | K85: =E85+J85+F85+G85+H85+I85 -> 324797.95 | L85: =IF(D85=K85, "", "Error")
A87: FONDO DE GASTOS ORDINARIOS | E87: =D87*93.2% -> 0 | F87: =$D87*1.08% -> 0 | G87: =$D87*1.28% -> 0 | H87: =$D87*1.21% -> 0 | I87: =$D87*1.49% -> 0 | J87: =D87*1.74% -> 0 | K87: =E87+J87+F87+G87+H87+I87 -> 0 | L87: =IF(D87=K87, "", "Error")
A89: TOTAL ORDINARIOS | D89: =SUM(D87+D42+D36+D85+D82+D75+D61+D51+D27++D47) -> 15847088 | E89: =SUM(E87+E42+E36+E85+E82+E75+E61+E51+E27++E47) -> 14967859 | F89: =SUM(F87+F42+F36+F85+F82+F75+F61+F51+F27++F47) -> 139642.25 | G89: =SUM(G87+G42+G36+G85+G82+G75+G61+G51+G27++G47) -> 165501.92 | H89: =SUM(H87+H42+H36+H85+H82+H75+H61+H51+H27++H47) -> 156451.04 | I89: =SUM(I87+I42+I36+I85+I82+I75+I61+I51+I27++I47) -> 192654.58 | J89: =SUM(J87+J42+J36+J85+J82+J75+J61+J51+J27++J47) -> 224979.18 | K89: =E89+J89+F89+G89+H89+I89 -> 15847088 | L89: =IF(D89=K89, "", "Error") | M89: =D89-K89 -> 0
A91: Gastos particulares
A95: TOTAL | C95: =SUM(C92:C94) -> 0
A98: GASTOS EXTRAORDINARIOS | E98: UF | F98: LOCAL 1 (1,08%) | G98: LOCAL 2 (1,28%) | H98: LOCAL 3 (1,21%) | I98: LOCAL 4 (1,49%) | J98: LOCAL 5 (1,74%)
E99: =D99 -> 0
A101: TOTAL | D101: =SUM(D99:D100) -> 0 | E101: =SUM(E99:E100) -> 0 | J101: =SUM(J99:J100) -> 0 | L101: =E101+J101 -> 0 | M101: =IF(D101=L101, "", "Error")
A104: GASTOS ORDINARIOS + PREVISION : | B104: =D89 -> 15847088
A105: GASTOS ORDINARIOS SIN PREVISION: | B105: =D89-D87 -> 15847088 | D105: Se recuerda a todos los propietarios que, en caso de producirse la venta o transferencia de una unidad funcional, es obligatorio informar a la Administración los datos de los nuevos titulares. Dicha notificación resulta indispensable para actualizar los registros del consorcio, emitir correctamente las expensas y garantizar que toda comunicación formal llegue a quienes correspondan. La información a presentar deberá incluir al menos: * Nombre y apellido de los nuevos propietarios. * Domicilio de contacto (en caso de ser distinto de la unidad funcional). * Correo electrónico y/o teléfono de contacto. * Copia de la escritura, acta notarial o documentación que acredite la transferencia. Hasta tanto no se reciba la notificación formal, toda comunicación y responsabilidad respecto de la unidad seguirá dirigida al propietario anterior.
A108: CAJA EFECTIVO $ (pesos)
A109: Saldo anterior | B109: 4948144.8
A110: Ingresos | B110: =PRORRATEO!H133 -> 20855142
A111: Ingreso por pago de ARBA | B111: =ARBA!L82 -> 1031545.1
A112: Egresos Ordinarios | B112: =-B105 -> -15847088
A113: Egresos Extraordinarios | B113: =-D101 -> 0
A114: Pago en efectivo (UF 39) | B114: =-PRORRATEO!H57 -> -640914.39
A115: Pago de productos y servicios en efectivo del mes (se restan de la caja en efectivo y se suman en la caja bancaria para no doble contabilizar) | B115: =-B131 -> 534732.11
A116: Dinero sin identificar | B116: =B126 -> 0
A117: Dinero ingreso SUM | B117: =-B138 -> -60000
A118: Error computo de transferencia correspondiente al 6D (07/04) | B118: -39639
A119: Gastos particulares | B119: =-C95 -> 0
A120: Ingreso mal registrado como cobro de ARBA mes anterior 10B (Correspondia a ingreso de expenas) | B120: -81371
A121: Transferencia a la desarrolladora (20/05) - ARBA pago parcial | B121: -10013539
A122: Saldo al cierre | B122: =SUM(B109:B121) -> 687013.09
A124: TRANSFERENCIAS SIN IDENTIFICAR
A126: TOTAL | B126: =SUM(B124:B125) -> 0
A129: CAJA EFECTIVO $ (pesos) | B129: 0
A130: Ingreso UF 39 (Pago de expensas) | B130: =-B114 -> 640914.39
A131: Pago de productos y servicios en efectivo del mes | B131: =-(D30+D31+D32+D33+D34+D70) -> -534732.11
A132: TOTAL | B132: =SUM(B129:B131) -> 106182.28
A137: CAJA SUM $ (pesos) | B137: 438840 | D137: Del total de caja ($1.292.035,37) $$1.031.545,12 corresponde devolver a la desarrolladora, por ende la caja real del consorcio es de $260.490,25
A138: Ingreso | B138: 60000
A140: TOTAL | B140: =SUM(B137:B139) -> 498840
A142: Caja Real -Banco - SUM + Ordinaria | B142: =B140+B122+B132 -> 1292035.4

Sheet PRORRATEO
A1: Las casillas coloreadas en la columna Gastos Par/SUM de color rojo corresponden a multas aplicadas por el uso del SUM. En consecuencia, la unidad funcional involucrada no podrá acceder al uso del mismo por tiempo indeterminado. Por otro lado, las casillas coloreadas en amarillo, corresponden a llaves y las verdes corresponden al mal uso del coworking. | F1: Banco Santander Rio. | L1: SE GASTO: | M1: =RESUMEN!D89-N3 -> 15847088
F2: CBU: 0720039720000002171436 | L2: SE PRORRATEA EN LAS UF: | N2: 15000000
F3: CTA CTE $ 0039 - 21714/3 FIDEICOMISO 25 DE MAYO 837 LAN 30716676737 | L3: ARBA: | N3: 0
C5: IMPORTANTE: Las personas marcadas en color naranja abonaron de forma incorrecta mediante Mercado Pago. A partir de ahora (incluso desde hace meses), ya se encuentra habilitada la cuenta bancaria correspondiente, por lo que todos los pagos deben realizarse exclusivamente a través de dicha cuenta. Los datos de la misma se encuentran justo arriba de este aviso. Quienes abonen por Mercado Pago corren el riesgo de que su pago no sea imputado correctamente.
C9: IMPORTANTE: Quienes estan en violeta NO ha respetado los centavos al abonar. Para la proxima oportunidad, solicitamos que los respeten. | Q9: LOCAL 1 | R9: =RESUMEN!F89 -> 139642.25
Q10: LOCAL 2 | R10: =RESUMEN!G89 -> 165501.92
A11: Piso | B11: Dpto. | C11: UF | D11: Propietario | E11: Inquilinos | F11: (%) | G11: Saldo | H11: Ingreso | I11: SALDO | J11: Expensas extraor. | K11: Cuota ARBA | L11: Expensas ord | M11: SUM/ GASTOS PART | N11: TOTAL A ABONAR HASTA | O11: TOTAL A ABONAR 2DO VTO - DESDE EL | Q11: LOCAL 3 | R11: =RESUMEN!H89 -> 156451.04
Q12: LOCAL 4 | R12: =RESUMEN!I89 -> 192654.58
N13: =RESUMEN!A20 -> VTO 18/06 | O13: =RESUMEN!A20 -> VTO 18/06 | Q13: LOCAL 5 | R13: =RESUMEN!J89 -> 224979.18
A14: conf sup | C14: LOC 1 | D14: Fernandez, Cristian | E14: Gladys ojeda Britez - Exequiel alexis giuliani | F14: 0.0108 | G14: 267664.48 | H14: 206250 | I14: =G14-H14 -> 61414.477 | J14: 0 | K14: =N$3*F14 -> 0 | L14: 206250.12 | M14: 0 | N14: =L14+J14+I14+M14+K14 -> 267664.6 | O14: =N14*6% + N14 -> 283724.47 | P14: Bezzo Jorge
C15: LOC 2 | D15: Fridgi, Guillermo Ariel | F15: 0.013 | G15: 388046.4 | H15: =244445+178355 -> 422800 | I15: =G15-H15 -> -34753.596 | J15: 0 | K15: =N$3*F15 -> 0 | L15: 244444.58 | M15: 0 | N15: =L15+J15+I15+M15+K15 -> 209690.99 | O15: =N15*6% + N15 -> 222272.45 | P15: Lucas Rocha
A16: conf sup | C16: LOC 3 | D16: Patricia Mainieri | E16: Cristina andrea Massa | F16: 0.0121 | G16: 299883.35 | H16: =231077+68807 -> 299884 | I16: =G16-H16 -> -0.650652 | J16: 0 | K16: =N$3*F16 -> 0 | L16: 231076.52 | M16: 0 | N16: =L16+J16+I16+M16+K16 -> 231075.87 | O16: =N16*6% + N16 -> 244940.42
A17: conf sup | C17: LOC 4 | D17: Cordero, Leandro Emanuel - Orona, Victoria | F17: 0.0149 | G17: 1661074 | H17: =1932950.72-271877 -> 1661073.7 | I17: =G17-H17 -> 0.29529238 | J17: 0 | K17: =N$3*F17 -> 0 | L17: 284548.77 | M17: 0 | N17: =L17+J17+I17+M17+K17 -> 284549.07 | O17: =N17*6% + N17 -> 301622.01
A18: conf sup | C18: LOC 5 | D18: Orsi, Jose Luis - Fernandez, Cristian Gabriel | F18: 0.0174 | G18: 391506.51 | H18: 98945 | I18: =G18-H18 -> 292561.51 | J18: 0 | K18: =N$3*F18 -> 0 | L18: 332291.86 | M18: 0 | N18: =L18+J18+I18+M18+K18 -> 624853.37 | O18: =N18*6% + N18 -> 662344.57
A19: 3 amb | C19: 2ºA | D19: Franco, Lucas Fabián | F19: 0.0188 | G19: 388906.01 | H19: =G19 -> 388906.01 | I19: =G19-H19 -> 0 | J19: =N$8*F19 -> 0 | K19: =N$3*F19 -> 0 | L19: =N$2*F19 -> 282000 | M19: 0 | N19: =ROUND((L19+J19+I19+K19+M19),0) + P19 -> 282000.01 | O19: =ROUND((N19*6% + N19 ),0) + P19 -> 298920.01 | P19: 0.01
A20: 1 amb | C20: 2ºB | D20: Martinez, Diego | F20: 0.0084 | G20: 173767.02 | H20: =G20 -> 173767.02 | I20: =G20-H20 -> 0 | J20: =N$8*F20 -> 0 | K20: =N$3*F20 -> 0 | L20: =N$2*F20 -> 126000 | M20: 0 | N20: =ROUND((L20+J20+I20+K20+M20),0) + P20 -> 126000.02 | O20: =ROUND((N20*6% + N20 ),0) + P20 -> 133560.02 | P20: =P19+0.01 -> 0.02
A21: 3 amb | C21: 2ºC | D21: Rodriguez, Carlos Alberto Miguel | F21: 0.0201 | G21: 440747.03 | H21: =G21 -> 440747.03 | I21: =G21-H21 -> 0 | J21: =N$8*F21 -> 0 | K21: =N$3*F21 -> 0 | L21: =N$2*F21 -> 301500 | M21: 0 | N21: =ROUND((L21+J21+I21+K21+M21),0) + P21 -> 301500.03 | O21: =ROUND((N21*6% + N21 ),0) + P21 -> 319590.03 | P21: =P20+0.01 -> 0.03
A22: 2 amb | C22: 2ºD | D22: Ferraro, José | E22: Matias Cuevas | F22: 0.0094 | G22: 143675.04 | H22: =53453+143675.04 -> 197128.04 | I22: =G22-H22 -> -53453 | J22: =N$8*F22 -> 0 | K22: =N$3*F22 -> 0 | L22: =N$2*F22 -> 141000 | M22: 0 | N22: =ROUND((L22+J22+I22+K22+M22),0) + P22 -> 87547.04 | O22: =ROUND((N22*6% + N22 ),0) + P22 -> 92800.04 | P22: =P21+0.01 -> 0.04 | Q22: Matias alejandro ezequiel
A23: 2 amb | C23: 2ºE | D23: Dieci, Matias Orlando | E23: Julieta Damiano/Damiani | F23: 0.0087 | G23: 179973.05 | H23: =G23 -> 179973.05 | I23: =G23-H23 -> 0 | J23: =N$8*F23 -> 0 | K23: =N$3*F23 -> 0 | L23: =N$2*F23 -> 130500 | M23: 0 | N23: =ROUND((L23+J23+I23+K23+M23),0) + P23 -> 130500.05 | O23: =ROUND((N23*6% + N23 ),0) + P23 -> 138330.05 | P23: =P22+0.01 -> 0.05
A24: 2 amb | C24: 2ºF | D24: Ferraro, Jose | E24: Carolina Massa | F24: 0.0095 | G24: 145604.06 | H24: =54022+33595.06+145604.06 -> 233221.12 | I24: =G24-H24 -> -87617.06 | J24: =N$8*F24 -> 0 | K24: =N$3*F24 -> 0 | L24: =N$2*F24 -> 142500 | M24: 20000 | N24: =ROUND((L24+J24+I24+K24+M24),0) + P24 -> 74883.06 | O24: =ROUND((N24*6% + N24 ),0) + P24 -> 79376.06 | P24: =P23+0.01 -> 0.06
A25: 3 amb | C25: 3ºA | D25: Ferraro, Jose | E25: Walter Gabriel Ledesma | F25: 0.0165 | G25: 268063.07 | H25: =93827+268063.07 -> 361890.07 | I25: =G25-H25 -> -93827 | J25: =N$8*F25 -> 0 | K25: =N$3*F25 -> 0 | L25: =N$2*F25 -> 247500 | M25: 20000 | N25: =ROUND((L25+J25+I25+K25+M25),0) + P25 -> 173673.07 | O25: =ROUND((N25*6% + N25 ),0) + P25 -> 184093.07 | P25: =P24+0.01 -> 0.07
A26: 1 amb | C26: 3ºB | D26: Balduzzi, Stella Maris | F26: 0.0073 | G26: 151012.08 | H26: =G26 -> 151012.08 | I26: =G26-H26 -> 0 | J26: =N$8*F26 -> 0 | K26: =N$3*F26 -> 0 | L26: =N$2*F26 -> 109500 | M26: 0 | N26: =ROUND((L26+J26+I26+K26+M26),0) + P26 -> 109500.08 | O26: =ROUND((N26*6% + N26 ),0) + P26 -> 116070.08 | P26: =P25+0.01 -> 0.08
A27: 3 amb | C27: 3ºC | D27: Ferraro, Jose | E27: Gustavo Oscar Fernandez | F27: 0.0178 | G27: 272815.09 | H27: =101220 -> 101220 | I27: =G27-H27 -> 171595.09 | J27: =N$8*F27 -> 0 | K27: =N$3*F27 -> 0 | L27: =N$2*F27 -> 267000 | M27: 0 | N27: =ROUND((L27+J27+I27+K27+M27),0) + P27 -> 438595.09 | O27: =ROUND((N27*6% + N27 ),0) + P27 -> 464911.09 | P27: =P26+0.01 -> 0.09
A28: 2 amb | C28: 3ºD | D28: Fernandez, Christian Norberto | F28: 0.0094 | G28: 194453.1 | H28: =G28 -> 194453.1 | I28: =G28-H28 -> 0 | J28: =N$8*F28 -> 0 | K28: =N$3*F28 -> 0 | L28: =N$2*F28 -> 141000 | M28: 0 | N28: =ROUND((L28+J28+I28+K28+M28),0) + P28 -> 141000.1 | O28: =ROUND((N28*6% + N28 ),0) + P28 -> 149460.1 | P28: =P27+0.01 -> 0.1
A29: 2 amb | C29: 3ºE | D29: Dallorso, Maria Ines - Dallorso, Ana Paula | F29: 0.0087 | G29: 179973.11 | H29: =G29 -> 179973.11 | I29: =G29-H29 -> 0 | J29: =N$8*F29 -> 0 | K29: =N$3*F29 -> 0 | L29: =N$2*F29 -> 130500 | M29: 0 | N29: =ROUND((L29+J29+I29+K29+M29),0) + P29 -> 130500.11 | O29: =ROUND((N29*6% + N29 ),0) + P29 -> 138330.11 | P29: =P28+0.01 -> 0.11
A30: 2 amb | C30: 3ºF | D30: Ayala, Roberto Adrian | F30: 0.0095 | G30: 1271868.1 | I30: =G30-H30 -> 1271868.1 | J30: =N$8*F30 -> 0 | K30: =N$3*F30 -> 0 | L30: =N$2*F30 -> 142500 | M30: 0 | N30: =ROUND((L30+J30+I30+K30+M30),0) + P30 -> 1414368.1 | O30: =ROUND((N30*6% + N30 ),0) + P30 -> 1499230.1 | P30: =P29+0.01 -> 0.12
A31: 3 amb | C31: 4ºA | D31: Barral, Carlos Daniel | F31: 0.0164 | G31: 339259.13 | H31: =G31 -> 339259.13 | I31: =G31-H31 -> 0 | J31: =N$8*F31 -> 0 | K31: =N$3*F31 -> 0 | L31: =N$2*F31 -> 246000 | M31: 0 | N31: =ROUND((L31+J31+I31+K31+M31),0) + P31 -> 246000.13 | O31: =ROUND((N31*6% + N31 ),0) + P31 -> 260760.13 | P31: =P30+0.01 -> 0.13
A32: 1 amb | C32: 4ºB | D32: Sr. Propietario | E32: Liria | F32: 0.0072 | G32: 148943.14 | H32: =G32 -> 148943.14 | I32: =G32-H32 -> 0 | J32: =N$8*F32 -> 0 | K32: =N$3*F32 -> 0 | L32: =N$2*F32 -> 108000 | M32: 0 | N32: =ROUND((L32+J32+I32+K32+M32),0) + P32 -> 108000.14 | O32: =ROUND((N32*6% + N32 ),0) + P32 -> 114480.14 | P32: =P31+0.01 -> 0.14
A33: 3 amb | C33: 4ºC | D33: Osipowicz, Ariel Marcelo | F33: 0.0173 | G33: 357877.15 | H33: =G33+63630 -> 421507.15 | I33: =G33-H33 -> -63630 | J33: =N$8*F33 -> 0 | K33: =N$3*F33 -> 0 | L33: =N$2*F33 -> 259500 | M33: 0 | N33: =ROUND((L33+J33+I33+K33+M33),0) + P33 -> 195870.15 | O33: =ROUND((N33*6% + N33 ),0) + P33 -> 207622.15 | P33: =P32+0.01 -> 0.15
A34: 2 amb | C34: 4ºD | D34: Ruiz, Juana Del Valle | F34: 0.0094 | G34: 187685.16 | H34: =G34 -> 187685.16 | I34: =G34-H34 -> 0 | J34: =N$8*F34 -> 0 | K34: =N$3*F34 -> 0 | L34: =N$2*F34 -> 141000 | M34: 0 | N34: =ROUND((L34+J34+I34+K34+M34),0) + P34 -> 141000.16 | O34: =ROUND((N34*6% + N34 ),0) + P34 -> 149460.16 | P34: =P33+0.01 -> 0.16 | Q34: Pablo Amarilla
A35: 2 amb | C35: 4ºE | D35: Szkarlatiuk, Carina Sonia | E35: Iara | F35: 0.0087 | G35: 284373.17 | H35: =234900.17 -> 234900.17 | I35: =G35-H35 -> 49473 | J35: =N$8*F35 -> 0 | K35: =N$3*F35 -> 0 | L35: =N$2*F35 -> 130500 | M35: 0 | N35: =ROUND((L35+J35+I35+K35+M35),0) + P35 -> 179973.17 | O35: =ROUND((N35*6% + N35 ),0) + P35 -> 190772.17 | P35: =P34+0.01 -> 0.17
A36: 2 amb | C36: 4ºF | D36: Ayala, Roberto Adrian | F36: 0.0095 | G36: 754117.18 | I36: =G36-H36 -> 754117.18 | J36: =N$8*F36 -> 0 | K36: =N$3*F36 -> 0 | L36: =N$2*F36 -> 142500 | M36: 0 | N36: =ROUND((L36+J36+I36+K36+M36),0) + P36 -> 896617.18 | O36: =ROUND((N36*6% + N36 ),0) + P36 -> 950414.18 | P36: =P35+0.01 -> 0.18
A37: 3 amb | C37: 5ºA | D37: Chehab, Gabriel Adrian | E37: Santiago Rodriguez | F37: 0.0164 | G37: 339259.19 | H37: =G37 -> 339259.19 | I37: =G37-H37 -> 0 | J37: =N$8*F37 -> 0 | K37: =N$3*F37 -> 0 | L37: =N$2*F37 -> 246000 | M37: 0 | N37: =ROUND((L37+J37+I37+K37+M37),0) + P37 -> 246000.19 | O37: =ROUND((N37*6% + N37 ),0) + P37 -> 260760.19 | P37: =P36+0.01 -> 0.19 | Q37: Cochera 38
A38: 1 amb | C38: 5ºB | D38: Mesa, Mariano | F38: 0.0072 | G38: 148943.2 | H38: =G38 -> 148943.2 | I38: =G38-H38 -> 0 | J38: =N$8*F38 -> 0 | K38: =N$3*F38 -> 0 | L38: =N$2*F38 -> 108000 | M38: 0 | N38: =ROUND((L38+J38+I38+K38+M38),0) + P38 -> 108000.2 | O38: =ROUND((N38*6% + N38 ),0) + P38 -> 114480.2 | P38: =P37+0.01 -> 0.2
A39: 3 amb | C39: 5ºC | D39: Di Mito, Vicente Argentino - Serantes, Mabel | F39: 0.0173 | G39: 534246.21 | H39: =G39 -> 534246.21 | I39: =G39-H39 -> 0 | J39: =N$8*F39 -> 0 | K39: =N$3*F39 -> 0 | L39: =N$2*F39 -> 259500 | M39: 20000 | N39: =ROUND((L39+J39+I39+K39+M39),0) + P39 -> 279500.21 | O39: =ROUND((N39*6% + N39 ),0) + P39 -> 296270.21 | P39: =P38+0.01 -> 0.21
A40: 2 amb | C40: 5ºD | D40: Ayala, Agustin | F40: 0.0094 | G40: 819814.22 | I40: =G40-H40 -> 819814.22 | J40: =N$8*F40 -> 0 | K40: =N$3*F40 -> 0 | L40: =N$2*F40 -> 141000 | M40: 0 | N40: =ROUND((L40+J40+I40+K40+M40),0) + P40 -> 960814.22 | O40: =ROUND((N40*6% + N40 ),0) + P40 -> 1018463.2 | P40: =P39+0.01 -> 0.22 | Q40: Ayala paga 5D, 5F y 4F
A41: 2 amb | C41: 5ºE | D41: Basaez, Rogelio Luis - Savino, Cecilia | F41: 0.0087 | G41: 179973.23 | H41: =G41 -> 179973.23 | I41: =G41-H41 -> 0 | J41: =N$8*F41 -> 0 | K41: =N$3*F41 -> 0 | L41: =N$2*F41 -> 130500 | M41: 0 | N41: =ROUND((L41+J41+I41+K41+M41),0) + P41 -> 130500.23 | O41: =ROUND((N41*6% + N41 ),0) + P41 -> 138330.23 | P41: =P40+0.01 -> 0.23 | Q41: COCHERA 31
A42: 2 amb | C42: 5ºF | D42: Ayala, Agustin | F42: 0.0095 | G42: 499337.24 | H42: 0 | I42: =G42-H42 -> 499337.24 | J42: =N$8*F42 -> 0 | K42: =N$3*F42 -> 0 | L42: =N$2*F42 -> 142500 | M42: 0 | N42: =ROUND((L42+J42+I42+K42+M42),0) + P42 -> 641837.24 | O42: =ROUND((N42*6% + N42 ),0) + P42 -> 680347.24 | P42: =P41+0.01 -> 0.24
A43: 3 amb | C43: 6ºA | D43: Morandi, Victoria Ayelen | Calvo, Luciano Ezequiel | F43: 0.0164 | G43: 339259.25 | H43: =G43 -> 339259.25 | I43: =G43-H43 -> 0 | J43: =N$8*F43 -> 0 | K43: =N$3*F43 -> 0 | L43: =N$2*F43 -> 246000 | M43: 0 | N43: =ROUND((L43+J43+I43+K43+M43),0) + P43 -> 246000.25 | O43: =ROUND((N43*6% + N43 ),0) + P43 -> 260760.25 | P43: =P42+0.01 -> 0.25
A44: 1 amb | C44: 6ºB | D44: Grizak Ruben | E44: Christian | F44: 0.0072 | G44: 148943.26 | H44: =G44 -> 148943.26 | I44: =G44-H44 -> 0 | J44: =N$8*F44 -> 0 | K44: =N$3*F44 -> 0 | L44: =N$2*F44 -> 108000 | M44: 0 | N44: =ROUND((L44+J44+I44+K44+M44),0) + P44 -> 108000.26 | O44: =ROUND((N44*6% + N44 ),0) + P44 -> 114480.26 | P44: =P43+0.01 -> 0.26
A45: 3 amb | C45: 6ºC | D45: Nuñez Leonel - Corrieri Giuliana | F45: 0.0173 | G45: 381877.27 | H45: =G45 -> 381877.27 | I45: =G45-H45 -> 0 | J45: =N$8*F45 -> 0 | K45: =N$3*F45 -> 0 | L45: =N$2*F45 -> 259500 | M45: 0 | N45: =ROUND((L45+J45+I45+K45+M45),0) + P45 -> 259500.27 | O45: =ROUND((N45*6% + N45 ),0) + P45 -> 275070.27 | P45: =P44+0.01 -> 0.27 | Q45: COCHERA 33 | R45: COCHERA 33
A46: 2 amb | C46: 6ºD | D46: Anchipi, Gaston Nicolas | F46: 0.0094 | G46: 352629.28 | H46: =238828+113801 -> 352629 | I46: =G46-H46 -> 0.28 | J46: =N$8*F46 -> 0 | K46: =N$3*F46 -> 0 | L46: =N$2*F46 -> 141000 | M46: 0 | N46: =ROUND((L46+J46+I46+K46+M46),0) + P46 -> 141000.28 | O46: =ROUND((N46*6% + N46 ),0) + P46 -> 149460.28 | P46: =P45+0.01 -> 0.28
A47: 2 amb | C47: 6ºE | D47: Dieci, Matias Orlando | E47: Gaston Smith | F47: 0.0087 | G47: 296355.29 | H47: =199973.29+102165.29 -> 302138.58 | I47: =G47-H47 -> -5783.29 | J47: =N$8*F47 -> 0 | K47: =N$3*F47 -> 0 | L47: =N$2*F47 -> 130500 | M47: 0 | N47: =ROUND((L47+J47+I47+K47+M47),0) + P47 -> 124717.29 | O47: =ROUND((N47*6% + N47 ),0) + P47 -> 132200.29 | P47: =P46+0.01 -> 0.29
A48: 2 amb | C48: 6ºF | D48: Mazzia Alexia | F48: 0.0095 | G48: 196522.3 | H48: =G48 -> 196522.3 | I48: =G48-H48 -> 0 | J48: =N$8*F48 -> 0 | K48: =N$3*F48 -> 0 | L48: =N$2*F48 -> 142500 | M48: 0 | N48: =ROUND((L48+J48+I48+K48+M48),0) + P48 -> 142500.3 | O48: =ROUND((N48*6% + N48 ),0) + P48 -> 151050.3 | P48: =P47+0.01 -> 0.3
A49: 3 amb | C49: 7ºA | D49: Campelo, Mariano | F49: 0.0164 | G49: 339259.31 | H49: =G49 -> 339259.31 | I49: =G49-H49 -> 0 | J49: =N$8*F49 -> 0 | K49: =N$3*F49 -> 0 | L49: =N$2*F49 -> 246000 | M49: 0 | N49: =ROUND((L49+J49+I49+K49+M49),0) + P49 -> 246000.31 | O49: =ROUND((N49*6% + N49 ),0) + P49 -> 260760.31 | P49: =P48+0.01 -> 0.31
A50: 1 amb | C50: 7ºB | D50: Paes, Yazmin Luciana | F50: 0.0072 | G50: 148943.32 | H50: =G50 -> 148943.32 | I50: =G50-H50 -> 0 | J50: =N$8*F50 -> 0 | K50: =N$3*F50 -> 0 | L50: =N$2*F50 -> 108000 | M50: 0 | N50: =ROUND((L50+J50+I50+K50+M50),0) + P50 -> 108000.32 | O50: =ROUND((N50*6% + N50 ),0) + P50 -> 114480.32 | P50: =P49+0.01 -> 0.32
A51: 3 amb | C51: 7ºC | D51: Gonzalez Fedullo, Roxana y Valeria | F51: 0.0173 | G51: 357877.33 | H51: =G51 -> 357877.33 | I51: =G51-H51 -> 0 | J51: =N$8*F51 -> 0 | K51: =N$3*F51 -> 0 | L51: =N$2*F51 -> 259500 | M51: 0 | N51: =ROUND((L51+J51+I51+K51+M51),0) + P51 -> 259500.33 | O51: =ROUND((N51*6% + N51 ),0) + P51 -> 275070.33 | P51: =P50+0.01 -> 0.33
A52: 2 amb | C52: 7ºD | D52: Solleiro, Carolina Mabel | E52: Rosana Cavallero | F52: 0.0094 | G52: 194453.34 | H52: =141000 -> 141000 | I52: =G52-H52 -> 53453.34 | J52: =N$8*F52 -> 0 | K52: =N$3*F52 -> 0 | L52: =N$2*F52 -> 141000 | M52: 0 | N52: =ROUND((L52+J52+I52+K52+M52),0) + P52 -> 194453.34 | O52: =ROUND((N52*6% + N52 ),0) + P52 -> 206121.34 | P52: =P51+0.01 -> 0.34 | Q52: Walter Javier Dimiziunas - Rosana Cavallero
A53: 2 amb | C53: 7ºE | D53: Leyes, Javier | F53: 0.0087 | G53: 179973.35 | H53: =G53 -> 179973.35 | I53: =G53-H53 -> 0 | J53: =N$8*F53 -> 0 | K53: =N$3*F53 -> 0 | L53: =N$2*F53 -> 130500 | M53: 0 | N53: =ROUND((L53+J53+I53+K53+M53),0) + P53 -> 130500.35 | O53: =ROUND((N53*6% + N53 ),0) + P53 -> 138330.35 | P53: =P52+0.01 -> 0.35
A54: 2 amb | C54: 7ºF | D54: Puente, Matias | F54: 0.0095 | G54: 304575.36 | I54: =G54-H54 -> 304575.36 | J54: =N$8*F54 -> 0 | K54: =N$3*F54 -> 0 | L54: =N$2*F54 -> 142500 | M54: 0 | N54: =ROUND((L54+J54+I54+K54+M54),0) + P54 -> 447075.36 | O54: =ROUND((N54*6% + N54 ),0) + P54 -> 473900.36 | P54: =P53+0.01 -> 0.36
A55: 3 amb | C55: 8ºA | D55: Campelo, Mariano | F55: 0.0164 | G55: 339259.37 | H55: =G55 -> 339259.37 | I55: =G55-H55 -> 0 | J55: =N$8*F55 -> 0 | K55: =N$3*F55 -> 0 | L55: =N$2*F55 -> 246000 | M55: 0 | N55: =ROUND((L55+J55+I55+K55+M55),0) + P55 -> 246000.37 | O55: =ROUND((N55*6% + N55 ),0) + P55 -> 260760.37 | P55: =P54+0.01 -> 0.37
A56: 1 amb | C56: 8ºB | D56: Morvillo, Mariana Yanil | E56: Aylen | F56: 0.0072 | G56: 148943.38 | H56: =G56 -> 148943.38 | I56: =G56-H56 -> 0 | J56: =N$8*F56 -> 0 | K56: =N$3*F56 -> 0 | L56: =N$2*F56 -> 108000 | M56: 0 | N56: =ROUND((L56+J56+I56+K56+M56),0) + P56 -> 108000.38 | O56: =ROUND((N56*6% + N56 ),0) + P56 -> 114480.38 | P56: =P55+0.01 -> 0.38
A57: 3 amb | C57: 8ºC | D57: Frontale, Federico Carlos | Celentano, Alejandra Verónica | F57: 0.0173 | G57: 640914.39 | H57: 640914.39 | I57: =G57-H57 -> 0 | J57: =N$8*F57 -> 0 | K57: =N$3*F57 -> 0 | L57: =N$2*F57 -> 259500 | M57: 0 | N57: =ROUND((L57+J57+I57+K57+M57),0) + P57 -> 259500.39 | O57: =ROUND((N57*6% + N57 ),0) + P57 -> 275070.39 | P57: =P56+0.01 -> 0.39
A58: 2 amb | C58: 8ºD | D58: Argul, Sergio Walter - Taboada, María Paz | E58: Nahuel | F58: 0.0094 | G58: 206121.4 | I58: =G58-H58 -> 206121.4 | J58: =N$8*F58 -> 0 | K58: =N$3*F58 -> 0 | L58: =N$2*F58 -> 141000 | M58: 0 | N58: =ROUND((L58+J58+I58+K58+M58),0) + P58 -> 347121.4 | O58: =ROUND((N58*6% + N58 ),0) + P58 -> 367949.4 | P58: =P57+0.01 -> 0.4
A59: 2 amb | C59: 8ºE | D59: Lorenzo, Sergio | F59: 0.0087 | G59: 179053.41 | H59: =G59 -> 179053.41 | I59: =G59-H59 -> 0 | J59: =N$8*F59 -> 0 | K59: =N$3*F59 -> 0 | L59: =N$2*F59 -> 130500 | M59: 0 | N59: =ROUND((L59+J59+I59+K59+M59),0) + P59 -> 130500.41 | O59: =ROUND((N59*6% + N59 ),0) + P59 -> 138330.41 | P59: =P58+0.01 -> 0.41 | R59: el de sergio
A60: 2 amb | C60: 8ºF | D60: Arias, Mariana Laura | F60: 0.0095 | G60: 196522.42 | H60: =G60 -> 196522.42 | I60: =G60-H60 -> 0 | J60: =N$8*F60 -> 0 | K60: =N$3*F60 -> 0 | L60: =N$2*F60 -> 142500 | M60: 0 | N60: =ROUND((L60+J60+I60+K60+M60),0) + P60 -> 142500.42 | O60: =ROUND((N60*6% + N60 ),0) + P60 -> 151050.42 | P60: =P59+0.01 -> 0.42 | Q60: alonso sabrina eugenia
A61: 3 amb | C61: 9ºA | D61: Fanjul, Alejandro Rubén Marcelo | F61: 0.0164 | G61: 339259.43 | H61: =G61 -> 339259.43 | I61: =G61-H61 -> 0 | J61: =N$8*F61 -> 0 | K61: =N$3*F61 -> 0 | L61: =N$2*F61 -> 246000 | M61: 20000 | N61: =ROUND((L61+J61+I61+K61+M61),0) + P61 -> 266000.43 | O61: =ROUND((N61*6% + N61 ),0) + P61 -> 281960.43 | P61: =P60+0.01 -> 0.43
A62: 1 amb | C62: 9ºB | D62: Fanjul, Alejandro Rubén Marcelo | F62: 0.0072 | G62: 148943.44 | H62: =G62 -> 148943.44 | I62: =G62-H62 -> 0 | J62: =N$8*F62 -> 0 | K62: =N$3*F62 -> 0 | L62: =N$2*F62 -> 108000 | M62: 0 | N62: =ROUND((L62+J62+I62+K62+M62),0) + P62 -> 108000.44 | O62: =ROUND((N62*6% + N62 ),0) + P62 -> 114480.44 | P62: =P61+0.01 -> 0.44
A63: 3 amb | C63: 9ºC | D63: Franchino, Mauro | F63: 0.0173 | G63: 379350.45 | H63: 357877.45 | I63: =G63-H63 -> 21473 | J63: =N$8*F63 -> 0 | K63: =N$3*F63 -> 0 | L63: =N$2*F63 -> 259500 | M63: 0 | N63: =ROUND((L63+J63+I63+K63+M63),0) + P63 -> 280973.45 | O63: =ROUND((N63*6% + N63 ),0) + P63 -> 297832.45 | P63: =P62+0.01 -> 0.45
A64: 2 amb | C64: 9ºD | D64: Cerra, Antonio Osvaldo | E64: Mario Gomez Alejandro | F64: 0.0094 | G64: 162871.46 | H64: 141000 | I64: =G64-H64 -> 21871.46 | J64: =N$8*F64 -> 0 | K64: =N$3*F64 -> 0 | L64: =N$2*F64 -> 141000 | M64: 0 | N64: =ROUND((L64+J64+I64+K64+M64),0) + P64 -> 162871.46 | O64: =ROUND((N64*6% + N64 ),0) + P64 -> 172644.46 | P64: =P63+0.01 -> 0.46
A65: 2 amb | C65: 9ºE | D65: Dieci, Matias Orlando | F65: 0.0087 | G65: 200352.47 | H65: =G65 -> 200352.47 | I65: =G65-H65 -> 0 | J65: =N$8*F65 -> 0 | K65: =N$3*F65 -> 0 | L65: =N$2*F65 -> 130500 | M65: 0 | N65: =ROUND((L65+J65+I65+K65+M65),0) + P65 -> 130500.47 | O65: =ROUND((N65*6% + N65 ),0) + P65 -> 138330.47 | P65: =P64+0.01 -> 0.47
A66: 2 amb | C66: 9ºF | D66: Rosales, Rubén Darío | F66: 0.0095 | G66: 196522.48 | H66: =142500 -> 142500 | I66: =G66-H66 -> 54022.48 | J66: =N$8*F66 -> 0 | K66: =N$3*F66 -> 0 | L66: =N$2*F66 -> 142500 | M66: 0 | N66: =ROUND((L66+J66+I66+K66+M66),0) + P66 -> 196522.48 | O66: =ROUND((N66*6% + N66 ),0) + P66 -> 208314.48 | P66: =P65+0.01 -> 0.48
A67: 3 amb | C67: 10ºA | D67: Puisys Guillermo Antonio | F67: 0.0164 | G67: 339259.49 | H67: =G67 -> 339259.49 | I67: =G67-H67 -> 0 | J67: =N$8*F67 -> 0 | K67: =N$3*F67 -> 0 | L67: =N$2*F67 -> 246000 | M67: 0 | N67: =ROUND((L67+J67+I67+K67+M67),0) + P67 -> 246000.49 | O67: =ROUND((N67*6% + N67 ),0) + P67 -> 260761.49 | P67: =P66+0.01 -> 0.49
A68: 1 amb | C68: 10ºB | D68: Guerra Karina, Alejandra | F68: 0.0072 | G68: 148943.5 | H68: =G68+81371 -> 230314.5 | I68: =G68-H68 -> -81371 | J68: =N$8*F68 -> 0 | K68: =N$3*F68 -> 0 | L68: =N$2*F68 -> 108000 | M68: 0 | N68: =ROUND((L68+J68+I68+K68+M68),0) + P68 -> 26629.5 | O68: =ROUND((N68*6% + N68 ),0) + P68 -> 28227.5 | P68: =P67+0.01 -> 0.5
A69: 3 amb | C69: 10ºC | D69: Espósito, Franco Ezequiel | F69: 0.0173 | G69: 377877.51 | H69: =G69 -> 377877.51 | I69: =G69-H69 -> 0 | J69: =N$8*F69 -> 0 | K69: =N$3*F69 -> 0 | L69: =N$2*F69 -> 259500 | M69: 20000 | N69: =ROUND((L69+J69+I69+K69+M69),0) + P69 -> 279500.51 | O69: =ROUND((N69*6% + N69 ),0) + P69 -> 296271.51 | P69: =P68+0.01 -> 0.51
A70: 2 amb | C70: 10ºD | D70: Lobato, Lorena - Vega, Maximiliano | F70: 0.0094 | G70: 307254.52 | H70: =325690.52 -> 325690.52 | I70: =G70-H70 -> -18436 | J70: =N$8*F70 -> 0 | K70: =N$3*F70 -> 0 | L70: =N$2*F70 -> 141000 | M70: 0 | N70: =ROUND((L70+J70+I70+K70+M70),0) + P70 -> 122564.52 | O70: =ROUND((N70*6% + N70 ),0) + P70 -> 129918.52 | P70: =P69+0.01 -> 0.52
A71: 2 amb | C71: 10ºE | D71: Sr propietario | F71: 0.0087 | G71: 179973.53 | H71: =G71 -> 179973.53 | I71: =G71-H71 -> 0 | J71: =N$8*F71 -> 0 | K71: =N$3*F71 -> 0 | L71: =N$2*F71 -> 130500 | M71: 0 | N71: =ROUND((L71+J71+I71+K71+M71),0) + P71 -> 130500.53 | O71: =ROUND((N71*6% + N71 ),0) + P71 -> 138331.53 | P71: =P70+0.01 -> 0.53 | R71: mariano hecimovic
A72: 2 amb | C72: 10ºF | D72: Ramos, Sergio Eugenio | F72: 0.0095 | G72: 301766.54 | I72: =G72-H72 -> 301766.54 | J72: =N$8*F72 -> 0 | K72: =N$3*F72 -> 0 | L72: =N$2*F72 -> 142500 | M72: 0 | N72: =ROUND((L72+J72+I72+K72+M72),0) + P72 -> 444267.54 | O72: =ROUND((N72*6% + N72 ),0) + P72 -> 470924.54 | P72: =P71+0.01 -> 0.54
A73: 4 amb | C73: 11ºA/B | D73: Mosquera, Julio Rodolfo | Cuzzolino, Daniela Carol | F73: 0.0235 | G73: 486133.55 | H73: =G73 -> 486133.55 | I73: =G73-H73 -> 0 | J73: =N$8*F73 -> 0 | K73: =N$3*F73 -> 0 | L73: =N$2*F73 -> 352500 | M73: 0 | N73: =ROUND((L73+J73+I73+K73+M73),0) + P73 -> 352500.55 | O73: =ROUND((N73*6% + N73 ),0) + P73 -> 373651.55 | P73: =P72+0.01 -> 0.55
A74: 3 amb | C74: 11ºC | D74: Silvestre Villarruel Eduardo | F74: 0.0173 | G74: 379350.56 | H74: 357877.56 | I74: =G74-H74 -> 21473 | J74: =N$8*F74 -> 0 | K74: =N$3*F74 -> 0 | L74: =N$2*F74 -> 259500 | M74: 0 | N74: =ROUND((L74+J74+I74+K74+M74),0) + P74 -> 280973.56 | O74: =ROUND((N74*6% + N74 ),0) + P74 -> 297832.56 | P74: =P73+0.01 -> 0.56
A75: 2 amb | C75: 11ºD | D75: Sr. Propietario | F75: 0.0094 | G75: 194453.57 | H75: =289613.15-H89-H105 -> 194453.57 | I75: =G75-H75 -> 0 | J75: =N$8*F75 -> 0 | K75: =N$3*F75 -> 0 | L75: =N$2*F75 -> 141000 | M75: 0 | N75: =ROUND((L75+J75+I75+K75+M75),0) + P75 -> 141000.57 | O75: =ROUND((N75*6% + N75 ),0) + P75 -> 149461.57 | P75: =P74+0.01 -> 0.57
A76: 2 amb | C76: 11ºE | D76: Argúl, Adrián Norberto | E76: Lara | F76: 0.0087 | G76: 459999.58 | I76: =G76-H76 -> 459999.58 | J76: =N$8*F76 -> 0 | K76: =N$3*F76 -> 0 | L76: =N$2*F76 -> 130500 | M76: 0 | N76: =ROUND((L76+J76+I76+K76+M76),0) + P76 -> 590500.58 | O76: =ROUND((N76*6% + N76 ),0) + P76 -> 625931.58 | P76: =P75+0.01 -> 0.58
A77: 2 amb | C77: 11ºF | D77: Lobato, Lorena - Vega, Maximiliano | F77: 0.0095 | G77: 310522.59 | H77: 329154.59 | I77: =G77-H77 -> -18632 | J77: =N$8*F77 -> 0 | K77: =N$3*F77 -> 0 | L77: =N$2*F77 -> 142500 | M77: 0 | N77: =ROUND((L77+J77+I77+K77+M77),0) + P77 -> 123868.59 | O77: =ROUND((N77*6% + N77 ),0) + P77 -> 131301.59 | P77: =P76+0.01 -> 0.59
A78: 4 amb | C78: 12ºA/B | D78: Luciano, Carmen Veronica - Rey, Javier Pablo | F78: 0.0235 | G78: 464376.6 | H78: =467897.6 -> 467897.6 | I78: =G78-H78 -> -3521 | J78: =N$8*F78 -> 0 | K78: =N$3*F78 -> 0 | L78: =N$2*F78 -> 352500 | M78: 0 | N78: =ROUND((L78+J78+I78+K78+M78),0) + P78 -> 348979.6 | O78: =ROUND((N78*6% + N78 ),0) + P78 -> 369918.6 | P78: =P77+0.01 -> 0.6
A79: 3 amb | C79: 12ºC | D79: Hernandez, Marisa Beatriz - Hernandez, Adrian Jose | F79: 0.0173 | G79: 357877.61 | H79: =G79 -> 357877.61 | I79: =G79-H79 -> 0 | J79: =N$8*F79 -> 0 | K79: =N$3*F79 -> 0 | L79: =N$2*F79 -> 259500 | M79: 0 | N79: =ROUND((L79+J79+I79+K79+M79),0) + P79 -> 259500.61 | O79: =ROUND((N79*6% + N79 ),0) + P79 -> 275071.61 | P79: =P78+0.01 -> 0.61
A80: 2 amb | C80: 12ºD | D80: Morini, Micaela | F80: 0.0094 | G80: 913849.62 | I80: =G80-H80 -> 913849.62 | J80: =N$8*F80 -> 0 | K80: =N$3*F80 -> 0 | L80: =N$2*F80 -> 141000 | M80: 0 | N80: =ROUND((L80+J80+I80+K80+M80),0) + P80 -> 1054850.6 | O80: =ROUND((N80*6% + N80 ),0) + P80 -> 1118142.6 | P80: =P79+0.01 -> 0.62
A81: 2 amb | C81: 12ºE | D81: Armerding, Jorge | E81: Agustina | F81: 0.0087 | G81: 179973.63 | H81: =G81 -> 179973.63 | I81: =G81-H81 -> 0 | J81: =N$8*F81 -> 0 | K81: =N$3*F81 -> 0 | L81: =N$2*F81 -> 130500 | M81: 0 | N81: =ROUND((L81+J81+I81+K81+M81),0) + P81 -> 130500.63 | O81: =ROUND((N81*6% + N81 ),0) + P81 -> 138331.63 | P81: =P80+0.01 -> 0.63
A82: 2 amb | C82: 12ºF | D82: Bilyj, Josefa Catalina | F82: 0.0095 | G82: 196522.64 | H82: =G82 -> 196522.64 | I82: =G82-H82 -> 0 | J82: =N$8*F82 -> 0 | K82: =N$3*F82 -> 0 | L82: =N$2*F82 -> 142500 | M82: 0 | N82: =ROUND((L82+J82+I82+K82+M82),0) + P82 -> 142500.64 | O82: =ROUND((N82*6% + N82 ),0) + P82 -> 151051.64 | P82: =P81+0.01 -> 0.64 | Q82: Laura Quintas Perez
A83: 4 amb | C83: 13ºA/B | D83: Gazzaneo, Francisco | F83: 0.0235 | G83: 486133.65 | H83: =G83 -> 486133.65 | I83: =G83-H83 -> 0 | J83: =N$8*F83 -> 0 | K83: =N$3*F83 -> 0 | L83: =N$2*F83 -> 352500 | M83: 0 | N83: =ROUND((L83+J83+I83+K83+M83),0) + P83 -> 352500.65 | O83: =ROUND((N83*6% + N83 ),0) + P83 -> 373651.65 | P83: =P82+0.01 -> 0.65
A84: 3 amb | C84: 13ºC | D84: Argentino, Javier Leonardo | F84: 0.0173 | G84: 403252.66 | H84: =G84 -> 403252.66 | I84: =G84-H84 -> 0 | J84: =N$8*F84 -> 0 | K84: =N$3*F84 -> 0 | L84: =N$2*F84 -> 259500 | M84: 0 | N84: =ROUND((L84+J84+I84+K84+M84),0) + P84 -> 259500.66 | O84: =ROUND((N84*6% + N84 ),0) + P84 -> 275071.66 | P84: =P83+0.01 -> 0.66
A85: 2 amb | C85: 13ºD | D85: Scardigno, Gabriela Susana - Ripoll, Luis Alberto | F85: 0.0094 | G85: 194453.67 | H85: =G85 -> 194453.67 | I85: =G85-H85 -> 0 | J85: =N$8*F85 -> 0 | K85: =N$3*F85 -> 0 | L85: =N$2*F85 -> 141000 | M85: 0 | N85: =ROUND((L85+J85+I85+K85+M85),0) + P85 -> 141000.67 | O85: =ROUND((N85*6% + N85 ),0) + P85 -> 149461.67 | P85: =P84+0.01 -> 0.67
A86: 2 amb | C86: 13ºE | D86: Quiñones, Carlos Eduardo | F86: 0.0087 | G86: 179973.68 | H86: =G86 -> 179973.68 | I86: =G86-H86 -> 0 | J86: =N$8*F86 -> 0 | K86: =N$3*F86 -> 0 | L86: =N$2*F86 -> 130500 | M86: 0 | N86: =ROUND((L86+J86+I86+K86+M86),0) + P86 -> 130500.68 | O86: =ROUND((N86*6% + N86 ),0) + P86 -> 138331.68 | P86: =P85+0.01 -> 0.68
A87: 2 amb | C87: 13ºF | D87: Mosquera, José Elias | F87: 0.0095 | G87: 208314.69 | H87: =G87 -> 208314.69 | I87: =G87-H87 -> 0 | J87: =N$8*F87 -> 0 | K87: =N$3*F87 -> 0 | L87: =N$2*F87 -> 142500 | M87: 0 | N87: =ROUND((L87+J87+I87+K87+M87),0) + P87 -> 142500.69 | O87: =ROUND((N87*6% + N87 ),0) + P87 -> 151051.69 | P87: =P86+0.01 -> 0.69
C88: COCH 1 | D88: Osipowicz, Ariel Marcelo | F88: 0.0023 | G88: 47579.7 | H88: =G88 -> 47579.7 | I88: =G88-H88 -> 0 | J88: =N$8*F88 -> 0 | K88: =N$3*F88 -> 0 | L88: =N$2*F88 -> 34500 | M88: 0 | N88: =ROUND((L88+J88+I88+K88+M88),0) + P88 -> 34500.7 | O88: =ROUND((N88*6% + N88 ),0) + P88 -> 36571.7 | P88: =P87+0.01 -> 0.7
C89: COCH 2 | D89: Sr propietario | F89: 0.0023 | G89: 47579.71 | H89: =G89 -> 47579.71 | I89: =G89-H89 -> 0 | J89: =N$8*F89 -> 0 | K89: =N$3*F89 -> 0 | L89: =N$2*F89 -> 34500 | M89: 0 | N89: =ROUND((L89+J89+I89+K89+M89),0) + P89 -> 34500.71 | O89: =ROUND((N89*6% + N89 ),0) + P89 -> 36571.71 | P89: =P88+0.01 -> 0.71
C90: COCH 3 | D90: Paes, Yazmin Luciana | F90: 0.0023 | G90: 50435.72 | H90: =G90 -> 50435.72 | I90: =G90-H90 -> 0 | J90: =N$8*F90 -> 0 | K90: =N$3*F90 -> 0 | L90: =N$2*F90 -> 34500 | M90: 0 | N90: =ROUND((L90+J90+I90+K90+M90),0) + P90 -> 34500.72 | O90: =ROUND((N90*6% + N90 ),0) + P90 -> 36571.72 | P90: =P89+0.01 -> 0.72
C91: COCH 4 | D91: Puisys Guillermo Antonio | F91: 0.0023 | G91: 47579.73 | H91: =G91 -> 47579.73 | I91: =G91-H91 -> 0 | J91: =N$8*F91 -> 0 | K91: =N$3*F91 -> 0 | L91: =N$2*F91 -> 34500 | M91: 0 | N91: =ROUND((L91+J91+I91+K91+M91),0) + P91 -> 34500.73 | O91: =ROUND((N91*6% + N91 ),0) + P91 -> 36571.73 | P91: =P90+0.01 -> 0.73
C92: COCH 5 | D92: Arias, Mariana Laura | F92: 0.0023 | G92: 47579.74 | H92: =G92 -> 47579.74 | I92: =G92-H92 -> 0 | J92: =N$8*F92 -> 0 | K92: =N$3*F92 -> 0 | L92: =N$2*F92 -> 34500 | M92: 0 | N92: =ROUND((L92+J92+I92+K92+M92),0) + P92 -> 34500.74 | O92: =ROUND((N92*6% + N92 ),0) + P92 -> 36571.74 | P92: =P91+0.01 -> 0.74 | Q92: alonso sabrina eugenia
C93: COCH 6 | D93: Dimito, Vicente Argentino - Cerantes , Mabel | F93: 0.0023 | G93: 73059.75 | I93: =G93-H93 -> 73059.75 | J93: =N$8*F93 -> 0 | K93: =N$3*F93 -> 0 | L93: =N$2*F93 -> 34500 | M93: 0 | N93: =ROUND((L93+J93+I93+K93+M93),0) + P93 -> 107560.75 | O93: =ROUND((N93*6% + N93 ),0) + P93 -> 114014.75 | P93: =P92+0.01 -> 0.75
C94: COCH 7 | D94: Campelo, Mariano | F94: 0.0023 | G94: 47579.76 | H94: =G94 -> 47579.76 | I94: =G94-H94 -> 0 | J94: =N$8*F94 -> 0 | K94: =N$3*F94 -> 0 | L94: =N$2*F94 -> 34500 | M94: 0 | N94: =ROUND((L94+J94+I94+K94+M94),0) + P94 -> 34500.76 | O94: =ROUND((N94*6% + N94 ),0) + P94 -> 36571.76 | P94: =P93+0.01 -> 0.76
C95: COCH 8 | D95: Campelo, Mariano | F95: 0.0023 | G95: 47579.77 | H95: =G95 -> 47579.77 | I95: =G95-H95 -> 0 | J95: =N$8*F95 -> 0 | K95: =N$3*F95 -> 0 | L95: =N$2*F95 -> 34500 | M95: 0 | N95: =ROUND((L95+J95+I95+K95+M95),0) + P95 -> 34500.77 | O95: =ROUND((N95*6% + N95 ),0) + P95 -> 36571.77 | P95: =P94+0.01 -> 0.77
C96: COCH 9 | D96: Gazzaneo, Francisco | F96: 0.0023 | G96: 47579.78 | H96: =G96 -> 47579.78 | I96: =G96-H96 -> 0 | J96: =N$8*F96 -> 0 | K96: =N$3*F96 -> 0 | L96: =N$2*F96 -> 34500 | M96: 0 | N96: =ROUND((L96+J96+I96+K96+M96),0) + P96 -> 34500.78 | O96: =ROUND((N96*6% + N96 ),0) + P96 -> 36571.78 | P96: =P95+0.01 -> 0.78
C97: COCH 10 | D97: Cerra, Antonio Osvaldo | F97: 0.0023 | G97: 324362.79 | I97: =G97-H97 -> 324362.79 | J97: =N$8*F97 -> 0 | K97: =N$3*F97 -> 0 | L97: =N$2*F97 -> 34500 | M97: 0 | N97: =ROUND((L97+J97+I97+K97+M97),0) + P97 -> 358863.79 | O97: =ROUND((N97*6% + N97 ),0) + P97 -> 380396.79 | P97: =P96+0.01 -> 0.79
C98: COCH 11 | D98: Osipowicz, Ariel Marcelo | F98: 0.0023 | G98: 47579.8 | H98: =G98 -> 47579.8 | I98: =G98-H98 -> 0 | J98: =N$8*F98 -> 0 | K98: =N$3*F98 -> 0 | L98: =N$2*F98 -> 34500 | M98: 0 | N98: =ROUND((L98+J98+I98+K98+M98),0) + P98 -> 34500.8 | O98: =ROUND((N98*6% + N98 ),0) + P98 -> 36571.8 | P98: =P97+0.01 -> 0.8
C99: COCH 12 | D99: Dieci, Matias Orlando | F99: 0.0023 | G99: 47579.81 | H99: =G99 -> 47579.81 | I99: =G99-H99 -> 0 | J99: =N$8*F99 -> 0 | K99: =N$3*F99 -> 0 | L99: =N$2*F99 -> 34500 | M99: 0 | N99: =ROUND((L99+J99+I99+K99+M99),0) + P99 -> 34500.81 | O99: =ROUND((N99*6% + N99 ),0) + P99 -> 36571.81 | P99: =P98+0.01 -> 0.81
C100: COCH 13 | D100: Scardigno, Gabriela Susana - Ripoli, Luis Alberto | F100: 0.0023 | G100: 47579.82 | H100: =G100 -> 47579.82 | I100: =G100-H100 -> 0 | J100: =N$8*F100 -> 0 | K100: =N$3*F100 -> 0 | L100: =N$2*F100 -> 34500 | M100: 0 | N100: =ROUND((L100+J100+I100+K100+M100),0) + P100 -> 34500.82 | O100: =ROUND((N100*6% + N100 ),0) + P100 -> 36571.82 | P100: =P99+0.01 -> 0.82
C101: COCH 14 | D101: Fontale Federico Carlos - Celentano Alejandra Veronica | F101: 0.0023 | G101: 75180.83 | I101: =G101-H101 -> 75180.83 | J101: =N$8*F101 -> 0 | K101: =N$3*F101 -> 0 | L101: =N$2*F101 -> 34500 | M101: 0 | N101: =ROUND((L101+J101+I101+K101+M101),0) + P101 -> 109681.83 | O101: =ROUND((N101*6% + N101 ),0) + P101 -> 116263.83 | P101: =P100+0.01 -> 0.83
C102: COCH 15 | D102: Hernandez, Marisa Beatriz - Hernandez, Adrian Jose | F102: 0.0023 | G102: 47579.84 | H102: =G102 -> 47579.84 | I102: =G102-H102 -> 0 | J102: =N$8*F102 -> 0 | K102: =N$3*F102 -> 0 | L102: =N$2*F102 -> 34500 | M102: 0 | N102: =ROUND((L102+J102+I102+K102+M102),0) + P102 -> 34500.84 | O102: =ROUND((N102*6% + N102 ),0) + P102 -> 36571.84 | P102: =P101+0.01 -> 0.84
C103: COCH 16 | D103: Mesa, Mariano | F103: 0.0023 | G103: 47579.85 | H103: =G103 -> 47579.85 | I103: =G103-H103 -> 0 | J103: =N$8*F103 -> 0 | K103: =N$3*F103 -> 0 | L103: =N$2*F103 -> 34500 | M103: 0 | N103: =ROUND((L103+J103+I103+K103+M103),0) + P103 -> 34500.85 | O103: =ROUND((N103*6% + N103 ),0) + P103 -> 36571.85 | P103: =P102+0.01 -> 0.85
C104: COCH 17 | D104: Espósito, Franco Ezequiel | F104: 0.0023 | G104: 47579.86 | I104: =G104-H104 -> 47579.86 | J104: =N$8*F104 -> 0 | K104: =N$3*F104 -> 0 | L104: =N$2*F104 -> 34500 | M104: 0 | N104: =ROUND((L104+J104+I104+K104+M104),0) + P104 -> 82080.86 | O104: =ROUND((N104*6% + N104 ),0) + P104 -> 87006.86 | P104: =P103+0.01 -> 0.86
...

Sheet ARBA
A1: IMPORTANTE: RESPETAR CENTAVOS AL ABONAR.
A3: Quienes adeudan ARBA deben abonar el monto coloreado en ROSADO si es que en el trancurso del mes 3 y 4 del 2026 no abonaron ninguna cuota.
A4: DPTOS | B4: COCH | C4: Propietario | D4: (%) | E4: ARBA REVALUO | F4: POSESION | G4: TOTAL A ABONAR HASTA | H4: TOTAL A ABONAR 1ERA CUOTA - VTO. 31/03 | I4: TOTAL A ABONAR 2DA CUOTA - VTO. 30/04 | J4: A PAGAR PROPIETARIO | L4: ABONADO POR PROPIETARIO | M4: AL PROPIETARIO LE RESTA ABONAR | N4: A PAGAR CONSTRUCTORA | O4: TOTAL
A7: LOC 1 | C7: Fernandez, Cristian | D7: 0.0108 | E7: 282914.38 | F7: 45856 | G7: -197064.48 | H7: =J7/2 -> 98532.35 | I7: =H7 -> 98532.35 | J7: =ROUND((-G7),0)+P7 -> 197064.7 | K7: -85849.897 | L7: 0 | M7: 98532.35 | N7: =-K7 -> 85849.897 | O7: =ROUND((J7+N7),0) + P7 -> 282915.7 | P7: 0.7
A8: LOC 2 | C8: Frigidi Guillermo Ariel | D8: 0.0128 | E8: 335305.93 | F8: 46001 | G8: -34751.379 | H8: =J8/2 -> 17375.855 | I8: =H8 -> 17375.855 | J8: =ROUND((-G8),0)+P8 -> 34751.71 | K8: -300554.55 | M8: =IF(L8=H8,I8,J8) -> 34751.71 | N8: =-K8 -> 300554.55 | O8: =ROUND((J8+N8),0) + P8 -> 335306.71 | P8: =P7+0.01 -> 0.71
A9: LOC 3 | C9: Patricia Mainieri | D9: 0.0121 | E9: 316968.89 | F9: 45856 | G9: -220785.21 | H9: =J9/2 -> 110392.86 | I9: =H9 -> 110392.86 | J9: =ROUND((-G9),0)+P9 -> 220785.72 | K9: -96183.681 | M9: =IF(L9=H9,I9,J9) -> 220785.72 | N9: =-K9 -> 96183.681 | O9: =ROUND((J9+N9),0) + P9 -> 316969.72 | P9: =P8+0.01 -> 0.72
A10: LOC 4 | C10: Cordero, Leandro Emanuel - Orona, Victoria | D10: 0.0149 | E10: 390317.06 | F10: 45856 | G10: -271876 | H10: =J10/2 -> 135938.36 | I10: =H10 -> 135938.36 | J10: =ROUND((-G10),0)+P10 -> 271876.73 | K10: -118441.06 | L10: =J10 -> 271876.73 | M10: 0 | N10: =-K10 -> 118441.06 | O10: =ROUND((J10+N10),0) + P10 -> 390318.73 | P10: =P9+0.01 -> 0.73
A11: LOC 5 | C11: Orsi, José Luis - Fernández, Cristián Gabriel | D11: 0.0175 | E11: 458426.08 | F11: 45856 | G11: -319317.45 | H11: =J11/2 -> 159658.87 | I11: =H11 -> 159658.87 | J11: =ROUND((-G11),0)+P11 -> 319317.74 | K11: -139108.63 | L11: 0 | M11: 159658.87 | N11: =-K11 -> 139108.63 | O11: =ROUND((J11+N11),0) + P11 -> 458426.74 | P11: =P10+0.01 -> 0.74
A12: 2ºA | B12: 25 | C12: Franco, Lucas Fabián | D12: 0.0212 | E12: 555350.45 | F12: 45777 | G12: -519626.97 | H12: =ROUND((J12/2),0)+P12 -> 259814.01 | I12: =H12 -> 259814.01 | J12: =ROUND((-G12),0)+P12 -> 519627.01 | K12: -35723.479 | L12: 0 | M12: 0 | N12: =-K12 -> 35723.479 | O12: =ROUND((J12+N12),0) + P12 -> 555350.01 | P12: 0.01
A13: 2ºB | C13: Martinez, Diego | D13: 0.0084 | E13: 220044.52 | F13: 45775 | G13: -206492.25 | H13: =ROUND((J13/2),0)+P13 -> 103246.02 | I13: =H13 -> 103246.02 | J13: =ROUND((-G13),0)+P13 -> 206492.02 | K13: -13552.263 | M13: 0 | N13: =-K13 -> 13552.263 | O13: =ROUND((J13+N13),0) + P13 -> 220044.02 | P13: =P12+0.01 -> 0.02
A14: 2ºC | B14: 22 | C14: Rodriguez, Carlos Alberto Miguel | D14: 0.0225 | E14: 589404.96 | F14: 45770 | G14: -557137.66 | H14: =ROUND((J14/2),0)+P14 -> 278569.03 | I14: =H14 -> 278569.03 | J14: =ROUND((-G14),0)+P14 -> 557138.03 | K14: -32267.294 | M14: 0 | N14: =-K14 -> 32267.294 | O14: =ROUND((J14+N14),0) + P14 -> 589405.03 | P14: =P13+0.01 -> 0.03
A15: 2ºD | B15: 29-30 | C15: Ferraro, José | D15: 0.014 | E15: 366740.86 | F15: 45805 | G15: -327282.74 | H15: =ROUND((J15/2),0)+P15 -> 163642.04 | I15: =H15 -> 163642.04 | J15: =ROUND((-G15),0)+P15 -> 327283.04 | K15: -39458.12 | M15: 0 | N15: =-K15 -> 39458.12 | O15: =ROUND((J15+N15),0) + P15 -> 366741.04 | P15: =P14+0.01 -> 0.04
A16: 2ºE | C16: Dieci, Matias Orlando | D16: 0.0087 | E16: 227903.25 | F16: 45800 | G16: -206069.05 | H16: =ROUND((J16/2),0)+P16 -> 103035.05 | I16: =H16 -> 103035.05 | J16: =ROUND((-G16),0)+P16 -> 206069.05 | K16: -21834.202 | M16: 0 | N16: =-K16 -> 21834.202 | O16: =ROUND((J16+N16),0) + P16 -> 227903.05 | P16: =P15+0.01 -> 0.05
A17: 2ºF | B17: 34-39 | C17: Ferraro, Jose | D17: 0.0141 | E17: 369360.44 | F17: 45805 | G17: -329620.48 | H17: =ROUND((J17/2),0)+P17 -> 164810.06 | I17: =H17 -> 164810.06 | J17: =ROUND((-G17),0)+P17 -> 329620.06 | K17: -39739.963 | M17: 0 | N17: =-K17 -> 39739.963 | O17: =ROUND((J17+N17),0) + P17 -> 369360.06 | P17: =P16+0.01 -> 0.06
A18: 3ºA | B18: 37-38 | C18: Ferraro, Jose - ------ALEJANDRO | D18: 0.0211 | E18: 552730.87 | F18: 45805 | G18: -493261.85 | H18: =ROUND((J18/2),0)+P18 -> 246631.07 | I18: =H18 -> 246631.07 | J18: =ROUND((-G18),0)+P18 -> 493262.07 | K18: -59469.023 | M18: 0 | N18: =-K18 -> 59469.023 | O18: =ROUND((J18+N18),0) + P18 -> 552731.07 | P18: =P17+0.01 -> 0.07
A19: 3ºB | C19: Ayala, Roberto Adrian/BALDUZZI | D19: 0.0074 | E19: 193848.74 | F19: 45839 | G19: -147681.21 | H19: =ROUND((J19/2),0)+P19 -> 73841.08 | I19: =H19 -> 73841.08 | J19: =ROUND((-G19),0)+P19 -> 147681.08 | K19: -46167.53 | M19: 0 | N19: =-K19 -> 46167.53 | O19: =ROUND((J19+N19),0) + P19 -> 193849.08 | P19: =P18+0.01 -> 0.08
A20: 3ºC | C20: Ferraro, Jose | D20: 0.0179 | E20: 468904.39 | F20: 45805 | G20: -418454.36 | H20: =ROUND((J20/2),0)+P20 -> 209227.09 | I20: =H20 -> 209227.09 | J20: =ROUND((-G20),0)+P20 -> 418454.09 | K20: -50450.024 | M20: 0 | N20: =-K20 -> 50450.024 | O20: =ROUND((J20+N20),0) + P20 -> 468904.09 | P20: =P19+0.01 -> 0.09
A21: 3ºD | C21: Ayala, Roberto Adrian | D21: 0.0094 | E21: 246240.29 | F21: 45839 | G21: -187595.05 | H21: =ROUND((J21/2),0)+P21 -> 93798.1 | I21: =H21 -> 93798.1 | J21: =ROUND((-G21),0)+P21 -> 187595.1 | K21: -58645.241 | M21: 0 | N21: =-K21 -> 58645.241 | O21: =ROUND((J21+N21),0) + P21 -> 246240.1 | P21: =P20+0.01 -> 0.1
A22: 3ºE | C22: Ayala, Roberto Adrian /CALZETTA | D22: 0.0087 | E22: 227903.25 | F22: 45839 | G22: -173625.21 | H22: =ROUND((J22/2),0)+P22 -> 86813.11 | I22: =H22 -> 86813.11 | J22: =ROUND((-G22),0)+P22 -> 173625.11 | K22: -54278.042 | M22: 0 | N22: =-K22 -> 54278.042 | O22: =ROUND((J22+N22),0) + P22 -> 227903.11 | P22: =P21+0.01 -> 0.11
A23: 3ºF | C23: Ayala, Roberto Adrian | D23: 0.0095 | E23: 248859.87 | F23: 45839 | G23: -189590.74 | H23: =ROUND((J23/2),0)+P23 -> 94796.12 | I23: =H23 -> 94796.12 | J23: =ROUND((-G23),0)+P23 -> 189591.12 | K23: -59269.126 | M23: =IF(L23=H23,I23,J23) -> 189591.12 | N23: =-K23 -> 59269.126 | O23: =ROUND((J23+N23),0) + P23 -> 248860.12 | P23: =P22+0.01 -> 0.12
A24: 4ºA | C24: Barral, Carlos Daniel | D24: 0.0164 | E24: 429610.72 | F24: 45775 | G24: -403151.54 | H24: =ROUND((J24/2),0)+P24 -> 201576.13 | I24: =H24 -> 201576.13 | J24: =ROUND((-G24),0)+P24 -> 403152.13 | K24: -26459.181 | M24: 0 | N24: =-K24 -> 26459.181 | O24: =ROUND((J24+N24),0) + P24 -> 429611.13 | P24: =P23+0.01 -> 0.13
A25: 4ºB | C25: Calzetta, Gabriel Andrés Felipe | D25: 0.0073 | E25: 191229.16 | F25: 45800 | G25: -172908.51 | H25: =ROUND((J25/2),0)+P25 -> 86455.14 | I25: =H25 -> 86455.14 | J25: =ROUND((-G25),0)+P25 -> 172909.14 | K25: -18320.652 | L25: =H25 -> 86455.14 | M25: 0 | N25: =-K25 -> 18320.652 | O25: =ROUND((J25+N25),0) + P25 -> 191230.14 | P25: =P24+0.01 -> 0.14
A26: 4ºC | B26: 1-11 | C26: Osipowicz, Ariel Marcelo | D26: 0.022 | E26: 576307.07 | F26: 45775 | G26: -540813.05 | H26: =ROUND((J26/2),0)+P26 -> 270407.15 | I26: =H26 -> 270407.15 | J26: =ROUND((-G26),0)+P26 -> 540813.15 | K26: -35494.023 | M26: 0 | N26: =-K26 -> 35494.023 | O26: =ROUND((J26+N26),0) + P26 -> 576307.15 | P26: =P25+0.01 -> 0.15
A27: 4ºD | C27: Ayala, Roberto Adrian | D27: 0.0094 | E27: 246240.29 | F27: 45839 | G27: -187595.05 | H27: =ROUND((J27/2),0)+P27 -> 93798.16 | I27: =H27 -> 93798.16 | J27: =ROUND((-G27),0)+P27 -> 187595.16 | K27: -58645.241 | M27: =IF(L27=H27,I27,J27) -> 187595.16 | N27: =-K27 -> 58645.241 | O27: =ROUND((J27+N27),0) + P27 -> 246240.16 | P27: =P26+0.01 -> 0.16 | Q27: Pablo Amarilla
A28: 4ºE | C28: Ayala, Roberto Adrian/SKARLATIUK | D28: 0.0087 | E28: 227903.25 | F28: 45839 | G28: -173625.21 | H28: =ROUND((J28/2),0)+P28 -> 86813.17 | I28: =H28 -> 86813.17 | J28: =ROUND((-G28),0)+P28 -> 173625.17 | K28: -54278.042 | M28: 0 | N28: =-K28 -> 54278.042 | O28: =ROUND((J28+N28),0) + P28 -> 227903.17 | P28: =P27+0.01 -> 0.17
A29: 4ºF | C29: Ayala, Roberto Adrian | D29: 0.0095 | E29: 248859.87 | F29: 45839 | G29: -189590.74 | H29: =ROUND((J29/2),0)+P29 -> 94796.18 | I29: =H29 -> 94796.18 | J29: =ROUND((-G29),0)+P29 -> 189591.18 | K29: -59269.126 | M29: =IF(L29=H29,I29,J29) -> 189591.18 | N29: =-K29 -> 59269.126 | O29: =ROUND((J29+N29),0) + P29 -> 248860.18 | P29: =P28+0.01 -> 0.18
A30: 5ºA | C30: Chehab, Gabriel Adrian | D30: 0.0164 | E30: 429610.72 | F30: 45800 | G30: -388452 | H30: =ROUND((J30/2),0)+P30 -> 194226.19 | I30: =H30 -> 194226.19 | J30: =ROUND((-G30),0)+P30 -> 388452.19 | K30: -41158.726 | M30: 0 | N30: =-K30 -> 41158.726 | O30: =ROUND((J30+N30),0) + P30 -> 429611.19 | P30: =P29+0.01 -> 0.19 | Q30: Cochera 38
A31: 5ºB | B31: 16 | C31: Mesa, Mariano | D31: 0.0096 | E31: 251479.45 | F31: 45805 | G31: -224422.45 | H31: =ROUND((J31/2),0)+P31 -> 112211.2 | I31: =H31 -> 112211.2 | J31: =ROUND((-G31),0)+P31 -> 224422.2 | K31: -27056.996 | M31: 0 | N31: =-K31 -> 27056.996 | O31: =ROUND((J31+N31),0) + P31 -> 251479.2 | P31: =P30+0.01 -> 0.2
A32: 5ºC | B32: 6 | C32: Di Mito, Vicente Argentino - Serantes, Mabel | D32: 0.0197 | E32: 516056.79 | F32: 45805 | G32: -460533.57 | H32: =ROUND((J32/2),0)+P32 -> 230267.21 | I32: =H32 -> 230267.21 | J32: =ROUND((-G32),0)+P32 -> 460534.21 | K32: -55523.211 | M32: =IF(L32=H32,I32,J32) -> 460534.21 | N32: =-K32 -> 55523.211 | O32: =ROUND((J32+N32),0) + P32 -> 516057.21 | P32: =P31+0.01 -> 0.21
A33: 5ºD | C33: Ayala, Roberto Adrian | D33: 0.0094 | E33: 246240.29 | F33: 45839 | G33: -187595.05 | H33: =ROUND((J33/2),0)+P33 -> 93798.22 | I33: =H33 -> 93798.22 | J33: =ROUND((-G33),0)+P33 -> 187595.22 | K33: -58645.241 | L33: =J33 -> 187595.22 | M33: 0 | N33: =-K33 -> 58645.241 | O33: =ROUND((J33+N33),0) + P33 -> 246240.22 | P33: =P32+0.01 -> 0.22 | Q33: Ayala paga 5D, 5F y 4F
A34: 5ºE | B34: 31 | C34: Ayala, Roberto Adrian/CALZETTA/ BASAEZ ROGELIO | D34: 0.011 | E34: 288153.53 | F34: 45839 | G34: -219526.13 | H34: =ROUND((J34/2),0)+P34 -> 109763.23 | I34: =H34 -> 109763.23 | J34: =ROUND((-G34),0)+P34 -> 219526.23 | K34: -68627.409 | M34: 0 | N34: =-K34 -> 68627.409 | O34: =ROUND((J34+N34),0) + P34 -> 288154.23 | P34: =P33+0.01 -> 0.23 | Q34: COCHERA 31
A35: 5ºF | C35: Ayala, Roberto Adrian | D35: 0.0095 | E35: 248859.87 | F35: 45839 | G35: -189590.74 | H35: =ROUND((J35/2),0)+P35 -> 94796.24 | I35: =H35 -> 94796.24 | J35: =ROUND((-G35),0)+P35 -> 189591.24 | K35: -59269.126 | M35: =IF(L35=H35,I35,J35) -> 189591.24 | N35: =-K35 -> 59269.126 | O35: =ROUND((J35+N35),0) + P35 -> 248860.24 | P35: =P34+0.01 -> 0.24
A36: 6ºA | B36: 28 | C36: Morandi, Victoria Ayelen | Calvo, Luciano Ezequiel | D36: 0.0187 | E36: 489861.01 | F36: 45786 | G36: -452316.22 | H36: =ROUND((J36/2),0)+P36 -> 226158.25 | I36: =H36 -> 226158.25 | J36: =ROUND((-G36),0)+P36 -> 452316.25 | K36: -37544.789 | M36: 0 | N36: =-K36 -> 37544.789 | O36: =ROUND((J36+N36),0) + P36 -> 489861.25 | P36: =P35+0.01 -> 0.25
A37: 6ºB | C37: GRIZEK RUBEN EDUARDO (ex Orellano) | D37: 0.0073 | E37: 191229.16 | F37: 45789 | G37: -175787.47 | H37: =ROUND((J37/2),0)+P37 -> 87894.26 | I37: =H37 -> 87894.26 | J37: =ROUND((-G37),0)+P37 -> 175787.26 | K37: -15441.693 | L37: 0 | M37: 0 | N37: =-K37 -> 15441.693 | O37: =ROUND((J37+N37),0) + P37 -> 191229.26 | P37: =P36+0.01 -> 0.26
A38: 6ºC | B38: 33 | C38: Nuñez Leonel - Corrieri Giuliana | D38: 0.0197 | E38: 516056.79 | F38: 45793 | G38: -471560.19 | H38: =ROUND((J38/2),0)+P38 -> 235780.27 | I38: =H38 -> 235780.27 | J38: =ROUND((-G38),0)+P38 -> 471560.27 | K38: -44496.598 | M38: 0 | N38: =-K38 -> 44496.598 | O38: =ROUND((J38+N38),0) + P38 -> 516057.27 | P38: =P37+0.01 -> 0.27 | Q38: COCHERA 33 | R38: COCHERA 33
A39: 6ºD | B39: 44 | C39: ANCHIPI GASTON (Cedido x Hecimovic)Hecimovic, Mariano Hernán (Cedido x Lopez Malara, Ramiro Alejandro) | D39: 0.0117 | E39: 306490.58 | F39: 45800 | G39: -277127.34 | H39: =ROUND((J39/2),0)+P39 -> 138564.28 | I39: =H39 -> 138564.28 | J39: =ROUND((-G39),0)+P39 -> 277127.28 | K39: -29363.237 | M39: 238127.28 | N39: =-K39 -> 29363.237 | O39: =ROUND((J39+N39),0) + P39 -> 306491.28 | P39: =P38+0.01 -> 0.28
A40: 6ºE | C40: Dieci, Matias Orlando | D40: 0.0087 | E40: 227903.25 | F40: 45800 | G40: -206069.05 | H40: =ROUND((J40/2),0)+P40 -> 103035.29 | I40: =H40 -> 103035.29 | J40: =ROUND((-G40),0)+P40 -> 206069.29 | K40: -21834.202 | M40: 0 | N40: =-K40 -> 21834.202 | O40: =ROUND((J40+N40),0) + P40 -> 227903.29 | P40: =P39+0.01 -> 0.29
A41: 6ºF | C41: ALEXIA JOANA MAZZIA | D41: 0.0095 | E41: 248859.87 | F41: 45800 | G41: -225017.93 | H41: =ROUND((J41/2),0)+P41 -> 112509.3 | I41: =H41 -> 112509.3 | J41: =ROUND((-G41),0)+P41 -> 225018.3 | K41: -23841.945 | M41: 0 | N41: =-K41 -> 23841.945 | O41: =ROUND((J41+N41),0) + P41 -> 248860.3 | P41: =P40+0.01 -> 0.3
A42: 7ºA | B42: 7 | C42: Campelo, Mariano | D42: 0.0187 | E42: 489861.01 | F42: 45806 | G42: -435275.01 | H42: =ROUND((J42/2),0)+P42 -> 217638.31 | I42: =H42 -> 217638.31 | J42: =ROUND((-G42),0)+P42 -> 435275.31 | K42: -54586.004 | M42: 0 | N42: =-K42 -> 54586.004 | O42: =ROUND((J42+N42),0) + P42 -> 489861.31 | P42: =P41+0.01 -> 0.31
A43: 7ºB | B43: 3 | C43: Paes, Yazmin Luciana | D43: 0.0096 | E43: 251479.45 | F43: 45775 | G43: -235991.15 | H43: =ROUND((J43/2),0)+P43 -> 117996.32 | I43: =H43 -> 117996.32 | J43: =ROUND((-G43),0)+P43 -> 235991.32 | K43: -15488.301 | M43: 0 | N43: =-K43 -> 15488.301 | O43: =ROUND((J43+N43),0) + P43 -> 251480.32 | P43: =P42+0.01 -> 0.32
A44: 7ºC | B44: 24 | C44: Gonzalez Fedullo, Roxana y Valeria | D44: 0.0197 | E44: 516056.79 | F44: 45793 | G44: -471560.19 | H44: =ROUND((J44/2),0)+P44 -> 235780.33 | I44: =H44 -> 235780.33 | J44: =ROUND((-G44),0)+P44 -> 471560.33 | K44: -44496.598 | M44: 0 | N44: =-K44 -> 44496.598 | O44: =ROUND((J44+N44),0) + P44 -> 516057.33 | P44: =P43+0.01 -> 0.33
A45: 7ºD | C45: Solleiro, Carolina Mabel | D45: 0.0094 | E45: 246240.29 | F45: 45786 | G45: -227367.51 | H45: =ROUND((J45/2),0)+P45 -> 113684.34 | I45: =H45 -> 113684.34 | J45: =ROUND((-G45),0)+P45 -> 227368.34 | K45: -18872.782 | L45: 206121.34 | M45: 21247 | N45: =-K45 -> 18872.782 | O45: =ROUND((J45+N45),0) + P45 -> 246241.34 | P45: =P44+0.01 -> 0.34 | Q45: Walter Javier Dimiziunas
A46: 7ºE | C46: Nuñez Leyes Javier Damian | D46: 0.0087 | E46: 227903.25 | F46: 45807 | G46: -201632.4 | H46: =ROUND((J46/2),0)+P46 -> 100816.35 | I46: =H46 -> 100816.35 | J46: =ROUND((-G46),0)+P46 -> 201632.35 | K46: -26270.852 | M46: 0 | N46: =-K46 -> 26270.852 | O46: =ROUND((J46+N46),0) + P46 -> 227903.35 | P46: =P45+0.01 -> 0.35
A47: 7ºF | C47: Puente, Matias | D47: 0.0095 | E47: 248859.87 | F47: 45786 | G47: -229786.32 | H47: =ROUND((J47/2),0)+P47 -> 114893.36 | I47: =H47 -> 114893.36 | J47: =ROUND((-G47),0)+P47 -> 229786.36 | K47: -19073.556 | M47: 0 | N47: =-K47 -> 19073.556 | O47: =ROUND((J47+N47),0) + P47 -> 248860.36 | P47: =P46+0.01 -> 0.36
A48: 8ºA | B48: 8 | C48: Campelo, Mariano | D48: 0.0187 | E48: 489861.01 | F48: 45793 | G48: -447623.12 | H48: =ROUND((J48/2),0)+P48 -> 223812.37 | I48: =H48 -> 223812.37 | J48: =ROUND((-G48),0)+P48 -> 447623.37 | K48: -42237.887 | M48: 0 | N48: =-K48 -> 42237.887 | O48: =ROUND((J48+N48),0) + P48 -> 489861.37 | P48: =P47+0.01 -> 0.37
A49: 8ºB | C49: Morvillo, Mariana Yanil | D49: 0.0073 | E49: 191229.16 | F49: 45805 | G49: -170654.57 | H49: =ROUND((J49/2),0)+P49 -> 85328.38 | I49: =H49 -> 85328.38 | J49: =ROUND((-G49),0)+P49 -> 170655.38 | K49: -20574.591 | M49: 0 | N49: =-K49 -> 20574.591 | O49: =ROUND((J49+N49),0) + P49 -> 191230.38 | P49: =P48+0.01 -> 0.38
A50: 8ºC | B50: 14 | C50: Frontale, Federico Carlos | Celentano, Alejandra Verónica | D50: 0.0197 | E50: 516056.79 | F50: 45805 | G50: -460533.57 | H50: =ROUND((J50/2),0)+P50 -> 230267.39 | I50: =H50 -> 230267.39 | J50: =ROUND((-G50),0)+P50 -> 460534.39 | K50: -55523.211 | M50: =IF(L50=H50,I50,J50) -> 460534.39 | N50: =-K50 -> 55523.211 | O50: =ROUND((J50+N50),0) + P50 -> 516058.39 | P50: =P49+0.01 -> 0.39
A51: 8ºD | C51: Argul, Sergio Walter - Taboada, María Paz | D51: 0.0094 | E51: 246240.29 | F51: 45793 | G51: -225008.41 | H51: =ROUND((J51/2),0)+P51 -> 112504.4 | I51: =H51 -> 112504.4 | J51: =ROUND((-G51),0)+P51 -> 225008.4 | K51: -21231.879 | M51: 0 | N51: =-K51 -> 21231.879 | O51: =ROUND((J51+N51),0) + P51 -> 246240.4 | P51: =P50+0.01 -> 0.4
A52: 8ºE | C52: Lorenzo, Sergio Ariel | D52: 0.0087 | E52: 227903.25 | F52: 45800 | G52: -206069.05 | H52: =ROUND((J52/2),0)+P52 -> 103035.41 | I52: =H52 -> 103035.41 | J52: =ROUND((-G52),0)+P52 -> 206069.41 | K52: -21834.202 | M52: 0 | N52: =-K52 -> 21834.202 | O52: =ROUND((J52+N52),0) + P52 -> 227904.41 | P52: =P51+0.01 -> 0.41 | R52: el de sergio
A53: 8ºF | B53: 5 | C53: Arias, Mariana Laura | D53: 0.0118 | E53: 309110.16 | F53: 45793 | G53: -282457.37 | H53: =ROUND((J53/2),0)+P53 -> 141229.42 | I53: =H53 -> 141229.42 | J53: =ROUND((-G53),0)+P53 -> 282457.42 | K53: -26652.785 | M53: 0 | N53: =-K53 -> 26652.785 | O53: =ROUND((J53+N53),0) + P53 -> 309110.42 | P53: =P52+0.01 -> 0.42 | Q53: alonso sabrina eugenia
A54: 9ºA | B54: 26 | C54: Fanjul, Alejandro Rubén Marcelo | D54: 0.0187 | E54: 489861.01 | F54: 45793 | G54: -447623.12 | H54: =ROUND((J54/2),0)+P54 -> 223812.43 | I54: =H54 -> 223812.43 | J54: =ROUND((-G54),0)+P54 -> 447623.43 | K54: -42237.887 | M54: 0 | N54: =-K54 -> 42237.887 | O54: =ROUND((J54+N54),0) + P54 -> 489861.43 | P54: =P53+0.01 -> 0.43
A55: 9ºB | C55: Fanjul, Alejandro Rubén Marcelo | D55: 0.0073 | E55: 191229.16 | F55: 45793 | G55: -174740.58 | H55: =ROUND((J55/2),0)+P55 -> 87371.44 | I55: =H55 -> 87371.44 | J55: =ROUND((-G55),0)+P55 -> 174741.44 | K55: -16488.587 | M55: 0 | N55: =-K55 -> 16488.587 | O55: =ROUND((J55+N55),0) + P55 -> 191230.44 | P55: =P54+0.01 -> 0.44
A56: 9ºC | B56: 43 | C56: Franchino, Mauro | D56: 0.0197 | E56: 516056.79 | F56: 45770 | G56: -487804.98 | H56: =ROUND((J56/2),0)+P56 -> 243903.45 | I56: =H56 -> 243903.45 | J56: =ROUND((-G56),0)+P56 -> 487805.45 | K56: -28251.808 | M56: 0 | N56: =-K56 -> 28251.808 | O56: =ROUND((J56+N56),0) + P56 -> 516057.45 | P56: =P55+0.01 -> 0.45
A57: 9ºD | B57: 10 | C57: Cerra, Antonio Osvaldo | D57: 0.0117 | E57: 306490.58 | F57: 45793 | G57: -280063.66 | H57: =ROUND((J57/2),0)+P57 -> 140032.46 | I57: =H57 -> 140032.46 | J57: =ROUND((-G57),0)+P57 -> 280064.46 | K57: -26426.913 | M57: 0 | N57: =-K57 -> 26426.913 | O57: =ROUND((J57+N57),0) + P57 -> 306491.46 | P57: =P56+0.01 -> 0.46
A58: 9ºE | B58: 12 | C58: Dieci, Matias Orlando | D58: 0.011 | E58: 288153.53 | F58: 45800 | G58: -260547.07 | H58: =ROUND((J58/2),0)+P58 -> 130274.47 | I58: =H58 -> 130274.47 | J58: =ROUND((-G58),0)+P58 -> 260547.47 | K58: -27606.462 | M58: 0 | N58: =-K58 -> 27606.462 | O58: =ROUND((J58+N58),0) + P58 -> 288154.47 | P58: =P57+0.01 -> 0.47
A59: 9ºF | B59: 20 | C59: Rosales, Rubén Darío | D59: 0.0118 | E59: 309110.16 | F59: 45805 | G59: -275852.6 | H59: =ROUND((J59/2),0)+P59 -> 137927.48 | I59: =H59 -> 137927.48 | J59: =ROUND((-G59),0)+P59 -> 275853.48 | K59: -33257.558 | M59: =IF(L59=H59,I59,J59) -> 275853.48 | N59: =-K59 -> 33257.558 | O59: =ROUND((J59+N59),0) + P59 -> 309111.48 | P59: =P58+0.01 -> 0.48
A60: 10ºA | B60: 4 | C60: Guillermo Antonio PUISYS (EX Fernández, Marcela Fabiana) | D60: 0.0187 | E60: 489861.01 | F60: 45793 | G60: -447623.12 | H60: =ROUND((J60/2),0)+P60 -> 223812.49 | I60: =H60 -> 223812.49 | J60: =ROUND((-G60),0)+P60 -> 447623.49 | K60: -42237.887 | M60: 0 | N60: =-K60 -> 42237.887 | O60: =ROUND((J60+N60),0) + P60 -> 489861.49 | P60: =P59+0.01 -> 0.49
A61: 10ºB | C61: Lange, Gustavo Daniel | D61: 0.0073 | E61: 191229.16 | F61: 45793 | G61: -174740.58 | H61: =ROUND((J61/2),0)+P61 -> 87371.5 | I61: =H61 -> 87371.5 | J61: =ROUND((-G61),0)+P61 -> 174741.5 | K61: -16488.587 | M61: =IF(L61=H61,I61,J61) -> 174741.5 | N61: =-K61 -> 16488.587 | O61: =ROUND((J61+N61),0) + P61 -> 191230.5 | P61: =P60+0.01 -> 0.5
A62: 10ºC | B62: 17 | C62: Espósito, Franco Ezequiel | D62: 0.0197 | E62: 516056.79 | F62: 45796 | G62: -469441.3 | H62: =ROUND((J62/2),0)+P62 -> 234721.51 | I62: =H62 -> 234721.51 | J62: =ROUND((-G62),0)+P62 -> 469441.51 | K62: -46615.483 | M62: 0 | N62: =-K62 -> 46615.483 | O62: =ROUND((J62+N62),0) + P62 -> 516057.51 | P62: =P61+0.01 -> 0.51
A63: 10ºD | C63: Lobato, Lorena - Vega, Maximiliano | D63: 0.0094 | E63: 246240.29 | F63: 45863 | G63: -164899.57 | H63: =ROUND((J63/2),0)+P63 -> 82450.52 | I63: =H63 -> 82450.52 | J63: =ROUND((-G63),0)+P63 -> 164900.52 | K63: -81340.722 | M63: 0 | N63: =-K63 -> 81340.722 | O63: =ROUND((J63+N63),0) + P63 -> 246241.52 | P63: =P62+0.01 -> 0.52
A64: 10ºE | C64: Hecimovic, Mariano Hernán | D64: 0.0087 | E64: 227903.25 | F64: 45800 | G64: -206069.05 | H64: =ROUND((J64/2),0)+P64 -> 103035.53 | I64: =H64 -> 103035.53 | J64: =ROUND((-G64),0)+P64 -> 206069.53 | K64: -21834.202 | M64: 0 | N64: =-K64 -> 21834.202 | O64: =ROUND((J64+N64),0) + P64 -> 227904.53 | P64: =P63+0.01 -> 0.53 | R64: mariano hecimovic
A65: 10ºF | B65: 23 | C65: Ramos, Sergio Eugenio | D65: 0.0118 | E65: 309110.16 | F65: 45786 | G65: -285418.79 | H65: =ROUND((J65/2),0)+P65 -> 142710.54 | I65: =H65 -> 142710.54 | J65: =ROUND((-G65),0)+P65 -> 285419.54 | K65: -23691.364 | M65: =IF(L65=H65,I65,J65) -> 285419.54 | N65: =-K65 -> 23691.364 | O65: =ROUND((J65+N65),0) + P65 -> 309111.54 | P65: =P64+0.01 -> 0.54
A66: 11ºA/B | B66: 21 | C66: Mosquera, Julio Rodolfo | Cuzzolino, Daniela Carol | D66: 0.0258 | E66: 675851.02 | F66: 45775 | G66: -634226.21 | H66: =ROUND((J66/2),0)+P66 -> 317113.55 | I66: =H66 -> 317113.55 | J66: =ROUND((-G66),0)+P66 -> 634226.55 | K66: -41624.809 | M66: 0 | N66: =-K66 -> 41624.809 | O66: =ROUND((J66+N66),0) + P66 -> 675851.55 | P66: =P65+0.01 -> 0.55
A67: 11ºC | B67: 41 | C67: Silvestre Villarruel Eduardo (EX De Mieri, Fernando Emanuel | D67: 0.0197 | E67: 516056.79 | F67: 45790 | G67: -473679.07 | H67: =ROUND((J67/2),0)+P67 -> 236840.56 | I67: =H67 -> 236840.56 | J67: =ROUND((-G67),0)+P67 -> 473679.56 | K67: -42377.712 | M67: 0 | N67: =-K67 -> 42377.712 | O67: =ROUND((J67+N67),0) + P67 -> 516057.56 | P67: =P66+0.01 -> 0.56
A68: 11ºD | B68: 2 | C68: Yudchak, Carlos Alberto | D68: 0.0117 | E68: 306490.58 | G68: 0 | K68: -306490.58 | M68: =IF(L68=H68,I68,J68) -> 0 | N68: =-K68 -> 306490.58 | O68: =ROUND((J68+N68),0) + P68 -> 306491.57 | P68: =P67+0.01 -> 0.57
A69: 11ºE | C69: Argúl, Adrián Norberto | D69: 0.0087 | E69: 227903.25 | F69: 45775 | G69: -213866.98 | H69: =ROUND((J69/2),0)+P69 -> 106934.58 | I69: =H69 -> 106934.58 | J69: =ROUND((-G69),0)+P69 -> 213867.58 | K69: -14036.273 | M69: =IF(L69=H69,I69,J69) -> 213867.58 | N69: =-K69 -> 14036.273 | O69: =ROUND((J69+N69),0) + P69 -> 227904.58 | P69: =P68+0.01 -> 0.58
A70: 11ºF | B70: 19 | C70: Lobato, Lorena - Vega, Maximiliano | D70: 0.0118 | E70: 309110.16 | F70: 45821 | G70: -256859.22 | H70: =ROUND((J70/2),0)+P70 -> 128430.59 | I70: =H70 -> 128430.59 | J70: =ROUND((-G70),0)+P70 -> 256859.59 | K70: -52250.939 | M70: 0 | N70: =-K70 -> 52250.939 | O70: =ROUND((J70+N70),0) + P70 -> 309111.59 | P70: =P69+0.01 -> 0.59
A71: 12ºA/B | B71: 36 | C71: Luciano, Carmen Veronica - Rey, Javier Pablo | D71: 0.0258 | E71: 675851.02 | F71: 45891 | G71: -382821.8 | H71: =ROUND((J71/2),0)+P71 -> 191411.6 | I71: =H71 -> 191411.6 | J71: =ROUND((-G71),0)+P71 -> 382822.6 | K71: -293029.22 | M71: 0 | N71: =-K71 -> 293029.22 | O71: =ROUND((J71+N71),0) + P71 -> 675852.6 | P71: =P70+0.01 -> 0.6
A72: 12ºC | B72: 15 | C72: Hernandez, Marisa Beatriz - Hernandez, Adrian Jose | D72: 0.0197 | E72: 516056.79 | F72: 45800 | G72: -466616.12 | H72: =ROUND((J72/2),0)+P72 -> 233308.61 | I72: =H72 -> 233308.61 | J72: =ROUND((-G72),0)+P72 -> 466616.61 | K72: -49440.664 | M72: 0 | N72: =-K72 -> 49440.664 | O72: =ROUND((J72+N72),0) + P72 -> 516057.61 | P72: =P71+0.01 -> 0.61
A73: 12ºD | C73: Morini, Micaela | D73: 0.0094 | E73: 246240.29 | F73: 45784 | G73: -228041.54 | H73: =ROUND((J73/2),0)+P73 -> 114021.62 | I73: =H73 -> 114021.62 | J73: =ROUND((-G73),0)+P73 -> 228042.62 | K73: -18198.754 | M73: =IF(L73=H73,I73,J73) -> 228042.62 | N73: =-K73 -> 18198.754 | O73: =ROUND((J73+N73),0) + P73 -> 246241.62 | P73: =P72+0.01 -> 0.62
A74: 12ºE | B74: 40 | C74: Armerding, Jorge | D74: 0.011 | E74: 288153.53 | F74: 45784 | G74: -266857.12 | H74: =ROUND((J74/2),0)+P74 -> 133429.63 | I74: =H74 -> 133429.63 | J74: =ROUND((-G74),0)+P74 -> 266857.63 | K74: -21296.414 | M74: 133429.63 | N74: =-K74 -> 21296.414 | O74: =ROUND((J74+N74),0) + P74 -> 288154.63 | P74: =P73+0.01 -> 0.63
A75: 12ºF | C75: Bilyj, Josefa Catalina | D75: 0.0095 | E75: 248859.87 | F75: 45786 | G75: -229786.32 | H75: =ROUND((J75/2),0)+P75 -> 114893.64 | I75: =H75 -> 114893.64 | J75: =ROUND((-G75),0)+P75 -> 229786.64 | K75: -19073.556 | M75: 0 | N75: =-K75 -> 19073.556 | O75: =ROUND((J75+N75),0) + P75 -> 248860.64 | P75: =P74+0.01 -> 0.64
A76: 13ºA/B | B76: 9 | C76: Gazzaneo Francisco | D76: 0.0258 | E76: 675851.02 | F76: 45835 | G76: -525270.52 | H76: =ROUND((J76/2),0)+P76 -> 262636.65 | I76: =H76 -> 262636.65 | J76: =ROUND((-G76),0)+P76 -> 525271.65 | K76: -150580.49 | M76: 0 | N76: =-K76 -> 150580.49 | O76: =ROUND((J76+N76),0) + P76 -> 675852.65 | P76: =P75+0.01 -> 0.65
A77: 13ºC | B77: 35 | C77: Argentino, Javier Leonardo | D77: 0.0197 | E77: 516056.79 | F77: 45784 | G77: -477916.84 | H77: =ROUND((J77/2),0)+P77 -> 238959.66 | I77: =H77 -> 238959.66 | J77: =ROUND((-G77),0)+P77 -> 477917.66 | K77: -38139.941 | M77: =I77-L77 -> 238959.66 | N77: =-K77 -> 38139.941 | O77: =ROUND((J77+N77),0) + P77 -> 516058.66 | P77: =P76+0.01 -> 0.66
A78: 13ºD | B78: 13-32 | C78: Scardigno, Gabriela Susana - Ripoll, Luis Alberto | D78: 0.014 | E78: 366740.86 | F78: 45786 | G78: -338632.46 | H78: =ROUND((J78/2),0)+P78 -> 169316.67 | I78: =H78 -> 169316.67 | J78: =ROUND((-G78),0)+P78 -> 338632.67 | K78: -28108.398 | M78: 0 | N78: =-K78 -> 28108.398 | O78: =ROUND((J78+N78),0) + P78 -> 366741.67 | P78: =P77+0.01 -> 0.67
A79: 13ºE | B79: 42 | C79: Quiñones, Carlos Eduardo | D79: 0.011 | E79: 288153.53 | F79: 45777 | G79: -269617.77 | H79: =ROUND((J79/2),0)+P79 -> 134809.68 | I79: =H79 -> 134809.68 | J79: =ROUND((-G79),0)+P79 -> 269618.68 | K79: -18535.768 | M79: 0 | N79: =-K79 -> 18535.768 | O79: =ROUND((J79+N79),0) + P79 -> 288154.68 | P79: =P78+0.01 -> 0.68
A80: 13ºF | B80: 27 | C80: Mosquera, José Elias | D80: 0.0118 | E80: 309110.16 | F80: 45800 | G80: -279495.95 | H80: =ROUND((J80/2),0)+P80 -> 139748.69 | I80: =H80 -> 139748.69 | J80: =ROUND((-G80),0)+P80 -> 279496.69 | K80: -29614.205 | L80: =J80 -> 279496.69 | M80: 0 | N80: =-K80 -> 29614.205 | O80: =ROUND((J80+N80),0) + P80 -> 309111.69 | P80: =P79+0.01 -> 0.69
D82: =SUM(D7:D81) -> 0.9979 | E82: =SUM(E7:E81) -> 26140765 | F82: =SUM(F7:F81) -> 3344000 | G82: =SUM(G7:G81) -> -22258385 | L82: =SUM(L7:L80) -> 1031545.1 | M82: =SUM(M7:M80) -> 4000854.2 | O82: =SUM(O7:O81) -> 26140812

Sheet ANOTACIONES
C2: ANOTACION | D2: 1
C3: FECHA DE LA ANOTACION: | E3: 0 | G3: NOMBRE: | H3: Ferraro jose
C4: QUEJA VIA: | D4: WHATSAPP | E4: MAIL | G4: LOTE:
C5: MOTIVO DE LA QUEJA:
C6: Adjunto el comprobante de pago de las expensas netas de la cochera 30 , $58.102,08 07/05
C11: ANOTACION | D11: =D2+1 -> 2
C12: FECHA DE LA ANOTACION: | E12: 0 | G12: NOMBRE: | H12: Ferraro jose
C13: QUEJA VIA: | D13: WHATSAPP | E13: MAIL | G13: LOTE:
C14: MOTIVO DE LA QUEJA:
C15: Deposito $382.000 el 08/05: Dto 2D. 53.453 Dto 2F. 54.022 Dto3A. 93.827 Dto3C. 101.220 ———————- 302.522.- Más 78.474.- ——————- 382.000.- Las cocheras son 29/30/34/37/38/39 6 X 13.079=78.474
C20: ANOTACION | D20: =D11+1 -> 3
C21: FECHA DE LA ANOTACION: | E21: 0 | G21: NOMBRE: | H21: Gaston Smith
C22: QUEJA VIA: | D22: WHATSAPP | E22: MAIL | G22: LOTE: | H22: 6E y Cochera 12
C23: MOTIVO DE LA QUEJA:
C24: El ultimo dia de abril el abono 102.165,29 para el 6E y 27.009,81 para la cochera 12 corregir
C29: ANOTACION | D29: =D20+1 -> 4
C30: FECHA DE LA ANOTACION: | E30: 0 | G30: NOMBRE: | H30: Local 2
C31: QUEJA VIA: | D31: WHATSAPP | E31: MAIL | G31: LOTE: | H31: Local 2
C32: MOTIVO DE LA QUEJA:
C33: Pago $244.445 el 19/05
C38: ANOTACION | D38: =D29+1 -> 5
C39: FECHA DE LA ANOTACION: | E39: 0 | G39: NOMBRE: | H39: 10B
C40: QUEJA VIA: | D40: WHATSAPP | E40: MAIL | G40: LOTE: | H40: 10B | I40: IMPORTANTE!
C41: MOTIVO DE LA QUEJA:
C42: 10B en marzo pago $81.371,5 y se lo pusimos en ARBA cuando le tenia que quedar a favor en las expensas
