Workbook

Sheet RESUMEN
B1: MAIL: consorciovergara1670@gmail.com
B2: CUIT ADMINISTRACION: 27231256879
B3: CBU: 2990024602400258030006 | D3: TELEFONO: 11 5320-2676
A4: LIQUIDACION DE EXPENSAS | B4: ALIAS: VERGARA.1670
A5: CUIT DEL EDIFICIO: 30-71802922-4 | B5: PERÍODO: MARZO - ADMINISTRADORA: CAROLINA CANCIANI MP:1148
A6: CONSORCIO DE PROPIETARIOS DEL EDIFICIO CALLE VERGARA 1670 | D6: HORARIOS DE ATENCION: LUNES A VIERNES
B8: VTO 14/04
A13: ESTIMADOS PROPIETARIOS E INQUILINOS: POR FAVOR LOS QUE ABONAN EN PRIMER VENCIMIENTO ABONEN EL MONTO DE PRIMER VENCIMIENTO, ASI AGILIZAN LA LIQUIDACION, LES PEDIMOS ENCARECIDAMENTE QUE RESPETEN LOS CENTAVOS CORRESPONDIENTES A LA UNIDAD FUNCIONAL. ES DE CARÁCTER OBLIGATORIO INFORMAR VIA MAIL LAS EXPENSAS.
A20: GASTOS ORDINARIOS UNIDADES FUNCIONALES:
A21: HABERES ENCARGADOS
A22: Remunerativos encargado Gonzalo Guenaga | D22: 590585.1
A23: Deducciones | D23: -138117.69
A24: Redondeo | D24: 0.59
A25: Neto | D25: =SUM(D22:D24) -> 452468
A26: Sueldo a pagar por la administracion saliente ya abonado | D26: 445381
A27: TOTAL SUELDO | E27: =D25+D26 -> 897849
A28: HONORARIOS
A29: Marcela De Biase- Sra. Contadora - Mes de Marzo | D29: 28000 | E29: Transf 19/03
A30: Honorarios administracion - Mes de Marzo - No se abonan por falta de caja
A31: TOTAL | E31: =SUM(D29:D30) -> 28000
A32: SEGUROS
A33: Seguro integral consorcio. Póliza 346504 Mapfre (4116-6397/6652 4458-5065) | D33: 226692
A34: Seguro de accidentes personales. Póliza 2151088 Mapfre | D34: 719.9
A35: TOTAL IMPUESTO | E35: =SUM(D33:D34) -> 227411.9
A36: APORTES Y CONTRIBUCIONES
A37: ARCA | D37: 299291.16 | E37: Debito 19/03
A38: Sindicatos mes de MARZO | B38: Fatheryh | D38: 26307.3 | E38: Debito 13/03
A39: =A38 -> Sindicatos mes de MARZO | B39: Suther | D39: 54080.16 | E39: =E38 -> Debito 13/03
A40: =A39 -> Sindicatos mes de MARZO | B40: Seracarh | D40: 2923 | E40: =E38 -> Debito 13/03
A41: TOTAL Aportes y Contribuciones - Sindicato | E41: =SUM(D37:D40) -> 382601.62
A42: ABONOS Y SERVICIOS
A43: AYSA - Nro de cliente. 318350 | D43: 38133.98 | E43: Transf 19/03
A44: Servicio de mantenimiento de ascensores - ADS | D44: 35000 | E44: Transf 25/03
A47: TOTAL ABONOS Y SERVICIOS | E47: =SUM(D43:D46) -> 73133.98
A48: GASTOS GENERALES / MANTENIMIENTO
A49: Extintores triclase ABC x 5kg - recarga anual | D49: 181500 | E49: Transf 19/03
A50: Mano de obra emergencias plomeria - Doartero Julio | D50: 185000 | E50: Transf 19/03
A51: Reparacion rampa de cocheras | D51: 110000 | E51: Transf 19/03
A52: JPL articulos de limpieza - NO SE ABONAN POR FALTA DE CAJA
A53: Ajuste de medidores | D53: 110000 | E53: Transf 31/03
A54: TOTAL | E54: =SUM(D49:D53) -> 586500
A55: GASTOS BANCARIOS
A56: Gastos banacarios | D56: 105511.99
A57: Mantenimiento de cuenta | D57: 46304
A58: TOTAL | E58: =SUM(D56:D57) -> 151815.99
A60: PREVISION ORDINARIA - metrogas | E60: 1252687.5
A62: TOTAL ORDINARIOS | E62: =(SUM(E27:E60)) -> 3600000
A65: GASTOS EXTRAORDINARIOS:
E70: =SUM(D66:D69) -> 0
A73: PREVISION EXTRAORDINARIA
A75: TOTAL EXTRAORDINARIOS | E75: =E70+E73 -> 0
A77: GASTOS ORDINARIOS + PREVISION : | B77: =E62 -> 3600000
A78: GASTOS ORDINARIOS SIN PREVISION: | B78: =E62-E60 -> 2347312.5
A79: GASTOS EXTRAORDINARIOS SIN PREVISION: | B79: =E75-E73 -> 0
A80: GASTOS EXTRAORDINARIOS CON PREVISION: | B80: =E75 -> 0
A82: RESUMEN
A83: Saldo anterior | B83: -155475.3
A84: Ingreso | B84: =PRORRATEO!H92 -> 4833106.7
A85: Deposito sin identificar | B85: =B105 -> 674116
A86: Punitorios mal cobrados | B86: =0 -> 0
A87: Egresos Ordinarios | B87: =-B78 -> -2347312.5
A88: Edesur - cliente nro. 01469567 | B88: =-PRORRATEO!F1 -> -2306985.9
A89: Metrogas - Cliente nro. 30015090344 | B89: =-PRORRATEO!F2 -> -566376.62
A90: Egresos Extraordinarios | B90: =-(B79) -> 0
A91: TOTAL | B91: =SUM(B83:B90) -> 131072.42
A94: DEPOSITOS NO IDENTIFICADOS
A96: Tranferencia no identificada - 7/3 - Santiago Torregarosa | B96: 28214 | C96: 11948.17
A97: Transferencia a nombre de Mirta Castarol - 6/03 | B97: 44900 | C97: 52000
A98: Transferencia a nombre de Norberto Omar Picin - 10/03 | B98: 48097
A99: Transferencia a nombre de Norberto Omar Picin - 31/03 | B99: 20000
A100: Transferencia a nombre de Guillermo Rosenth Walter - 10/03 | B100: 1065
A101: Transferencia sin identificar a nombre de Rosa Magdalena - 19/03 | B101: 113493
A102: Transferencia sin identificar a nombre de Agustina Martinez - 25/03 | B102: 141707
A103: Transferencia a nombre de Avido Laura - 12/03 | B103: 163147
A104: Transferencia a nombre de Jefferson Barreto - 12/03 | B104: 113493 | C104: 61209
A105: TOTAL | B105: =SUM(B96:B104) -> 674116

Sheet PRORRATEO
D1: EDESUR | E1: EDESUR: | F1: 2306985.9 | J1: EXPENSAS ORD | K1: Gastos Ordinarios: | M1: =P1 -> 3600000 | P1: 3600000
D2: METROGAS | E2: METROGAS: | F2: 566376.62 | J2: EXPENSAS EXTRAORD | K2: Gastos extraordinarios:
A3: Dpto. | C3: UF | D3: Propietario | E3: Inquilinos | F3: (%) | G3: Saldo Ord | H3: Ingreso | I3: Deuda o Saldo a favor | J3: Interes 3% | K3: Expensas extraor. | L3: Expensas ord. | M3: EDESUR | N3: METROGAS | O3: Total 1er Vto | P3: Total 2do Vto
O4: =RESUMEN!B8 -> VTO 14/04
B5: 1°A | C5: 33 | D5: Alejandro Raul Cuezzo | F5: 0.0202 | G5: 113493.34 | H5: =G5 -> 113493.34 | I5: =G5-H5 -> 0 | J5: =IF(I5>0,I5*3%,0) -> 0 | K5: =M$2*F5 -> 0 | L5: =M$1*F5 -> 72720 | M5: =F$1*F5 -> 46601.115 | N5: =F$2*F5 -> 11440.808 | O5: =ROUND(SUM(I5:N5),0) + Q5 -> 130762.33 | P5: =ROUND(O5*3%,0) + O5 -> 134685.33 | Q5: =ROUND(0.001+C5/100,2) -> 0.33
B6: 1°B | C6: 34 | D6: Daniel Julian Guzzo | F6: 0.0139 | G6: 134635.46 | H6: 54364 | I6: =G6-H6 -> 80271.464 | J6: =IF(I6>0,I6*3%,0) -> 2408.1439 | K6: =M$2*F6 -> 0 | L6: =M$1*F6 -> 50040 | M6: =F$1*F6 -> 32067.104 | N6: =F$2*F6 -> 7872.635 | O6: =ROUND(SUM(I6:N6),0) + Q6 -> 172659.34 | P6: =ROUND(O6*3%,0) + O6 -> 177839.34 | Q6: =ROUND(0.001+C6/100,2) -> 0.34
A7: 1 | B7: 1°C | C7: 35 | D7: Pablo Plebs | F7: 0.0142 | G7: 79782.449 | H7: =G7 -> 79782.449 | I7: =G7-H7 -> 0 | J7: =IF(I7>0,I7*3%,0) -> 0 | K7: =M$2*F7 -> 0 | L7: =M$1*F7 -> 51120 | M7: =F$1*F7 -> 32759.2 | N7: =F$2*F7 -> 8042.548 | O7: =ROUND(SUM(I7:N7),0) + Q7 -> 91922.35 | P7: =ROUND(O7*3%,0) + O7 -> 94680.35 | Q7: =ROUND(0.001+C7/100,2) -> 0.35
A8: 2 | B8: 1°D | C8: 36 | D8: Adrian Alejandro Pozo | F8: 0.0202 | G8: 195164.54 | H8: =196966-H64 -> 195165 | I8: =G8-H8 -> -0.45268608 | J8: =IF(I8>0,I8*3%,0) -> 0 | K8: =M$2*F8 -> 0 | L8: =M$1*F8 -> 72720 | M8: =F$1*F8 -> 46601.115 | N8: =F$2*F8 -> 11440.808 | O8: =ROUND(SUM(I8:N8),0) + Q8 -> 130761.36 | P8: =ROUND(O8*3%,0) + O8 -> 134684.36 | Q8: =ROUND(0.001+C8/100,2) -> 0.36
A9: 3 | B9: 2°A | C9: 37 | D9: Guillen Maria / Alejandro DI LEO | E9: Claudia | F9: 0.0202 | G9: 113493.34 | I9: =G9-H9 -> 113493.34 | J9: =IF(I9>0,I9*3%,0) -> 3404.8003 | K9: =M$2*F9 -> 0 | L9: =M$1*F9 -> 72720 | M9: =F$1*F9 -> 46601.115 | N9: =F$2*F9 -> 11440.808 | O9: =ROUND(SUM(I9:N9),0) + Q9 -> 247660.37 | P9: =ROUND(O9*3%,0) + O9 -> 255090.37 | Q9: =ROUND(0.001+C9/100,2) -> 0.37
A10: 4 | B10: 2°B | C10: 38 | D10: Jose Luis Gurtubay | E10: Santiago Flores | F10: 0.0139 | G10: 78096.904 | H10: =106311 -> 106311 | I10: =G10-H10 -> -28214.096 | J10: =IF(I10>0,I10*3%,0) -> 0 | K10: =M$2*F10 -> 0 | L10: =M$1*F10 -> 50040 | M10: =F$1*F10 -> 32067.104 | N10: =F$2*F10 -> 7872.635 | O10: =ROUND(SUM(I10:N10),0) + Q10 -> 61766.38 | P10: =ROUND(O10*3%,0) + O10 -> 63619.38 | Q10: =ROUND(0.001+C10/100,2) -> 0.38
A11: 5 | B11: 2°C | C11: 39 | D11: Magali Carrivale | F11: 0.0139 | G11: 78096.904 | H11: =G11 -> 78096.904 | I11: =G11-H11 -> 0 | J11: =IF(I11>0,I11*3%,0) -> 0 | K11: =M$2*F11 -> 0 | L11: =M$1*F11 -> 50040 | M11: =F$1*F11 -> 32067.104 | N11: =F$2*F11 -> 7872.635 | O11: =ROUND(SUM(I11:N11),0) + Q11 -> 89980.39 | P11: =ROUND(O11*3%,0) + O11 -> 92679.39 | Q11: =ROUND(0.001+C11/100,2) -> 0.39
A12: 6 | B12: 2°D | C12: 40 | D12: Juan Carlos Alonso | F12: 0.0202 | G12: 113493.34 | H12: =141707-H78 -> 113492.86 | I12: =G12-H12 -> 0.47951392 | J12: =IF(I12>0,I12*3%,0) -> 0.014385418 | K12: =M$2*F12 -> 0 | L12: =M$1*F12 -> 72720 | M12: =F$1*F12 -> 46601.115 | N12: =F$2*F12 -> 11440.808 | O12: =ROUND(SUM(I12:N12),0) + Q12 -> 130762.4 | P12: =ROUND(O12*3%,0) + O12 -> 134685.4 | Q12: =ROUND(0.001+C12/100,2) -> 0.4
A13: 7 | B13: 3°A | C13: 41 | D13: Lucas Oscar Ramil | E13: Camila Benitez | F13: 0.0202 | G13: 113493.34 | H13: =G13 -> 113493.34 | I13: =G13-H13 -> 0 | J13: =IF(I13>0,I13*3%,0) -> 0 | K13: =M$2*F13 -> 0 | L13: =M$1*F13 -> 72720 | M13: =F$1*F13 -> 46601.115 | N13: =F$2*F13 -> 11440.808 | O13: =ROUND(SUM(I13:N13),0) + Q13 -> 130762.41 | P13: =ROUND(O13*3%,0) + O13 -> 134685.41 | Q13: =ROUND(0.001+C13/100,2) -> 0.41
A14: 8 | B14: 3°B | C14: 42 | D14: Raul Boffi | E14: Gian y Micaela Parra | F14: 0.0139 | G14: 78096.904 | H14: =G14 -> 78096.904 | I14: =G14-H14 -> 0 | J14: =IF(I14>0,I14*3%,0) -> 0 | K14: =M$2*F14 -> 0 | L14: =M$1*F14 -> 50040 | M14: =F$1*F14 -> 32067.104 | N14: =F$2*F14 -> 7872.635 | O14: =ROUND(SUM(I14:N14),0) + Q14 -> 89980.42 | P14: =ROUND(O14*3%,0) + O14 -> 92679.42 | Q14: =ROUND(0.001+C14/100,2) -> 0.42
A15: 1 | B15: 3°C | C15: 43 | D15: Raul Boffi | E15: Lujan / Natalia Capece | F15: 0.0139 | G15: 78096.904 | H15: 78097 | I15: =G15-H15 -> -0.095717646 | J15: =IF(I15>0,I15*3%,0) -> 0 | K15: =M$2*F15 -> 0 | L15: =M$1*F15 -> 50040 | M15: =F$1*F15 -> 32067.104 | N15: =F$2*F15 -> 7872.635 | O15: =ROUND(SUM(I15:N15),0) + Q15 -> 89980.43 | P15: =ROUND(O15*3%,0) + O15 -> 92679.43 | Q15: =ROUND(0.001+C15/100,2) -> 0.43
A16: 1 | B16: 3°D | C16: 44 | D16: Roxana Elena Maya | E16: Daniela Bernabe | F16: 0.0202 | G16: 113493.34 | H16: =G16 -> 113493.34 | I16: =G16-H16 -> 0 | J16: =IF(I16>0,I16*3%,0) -> 0 | K16: =M$2*F16 -> 0 | L16: =M$1*F16 -> 72720 | M16: =F$1*F16 -> 46601.115 | N16: =F$2*F16 -> 11440.808 | O16: =ROUND(SUM(I16:N16),0) + Q16 -> 130762.44 | P16: =ROUND(O16*3%,0) + O16 -> 134685.44 | Q16: =ROUND(0.001+C16/100,2) -> 0.44
A17: 2 | B17: 4°A | C17: 45 | D17: Raul Boffi | E17: Paula Murado | F17: 0.0202 | G17: 113493.34 | H17: =G17 -> 113493.34 | I17: =G17-H17 -> 0 | J17: =IF(I17>0,I17*3%,0) -> 0 | K17: =M$2*F17 -> 0 | L17: =M$1*F17 -> 72720 | M17: =F$1*F17 -> 46601.115 | N17: =F$2*F17 -> 11440.808 | O17: =ROUND(SUM(I17:N17),0) + Q17 -> 130762.45 | P17: =ROUND(O17*3%,0) + O17 -> 134685.45 | Q17: =ROUND(0.001+C17/100,2) -> 0.45
A18: 2 | B18: 4°B | C18: 46 | D18: Raul Boffi | E18: Maria Florencia Boffi | F18: 0.0139 | G18: 78096.904 | H18: =G18 -> 78096.904 | I18: =G18-H18 -> 0 | J18: =IF(I18>0,I18*3%,0) -> 0 | K18: =M$2*F18 -> 0 | L18: =M$1*F18 -> 50040 | M18: =F$1*F18 -> 32067.104 | N18: =F$2*F18 -> 7872.635 | O18: =ROUND(SUM(I18:N18),0) + Q18 -> 89980.46 | P18: =ROUND(O18*3%,0) + O18 -> 92679.46 | Q18: =ROUND(0.001+C18/100,2) -> 0.46
A19: 3 | B19: 4°C | C19: 47 | D19: Raul Boffi | F19: 0.0139 | G19: 48096.904 | I19: =G19-H19 -> 48096.904 | J19: =IF(I19>0,I19*3%,0) -> 1442.9071 | K19: =M$2*F19 -> 0 | L19: =M$1*F19 -> 50040 | M19: =F$1*F19 -> 32067.104 | N19: =F$2*F19 -> 7872.635 | O19: =ROUND(SUM(I19:N19),0) + Q19 -> 139520.47 | P19: =ROUND(O19*3%,0) + O19 -> 143706.47 | Q19: =ROUND(0.001+C19/100,2) -> 0.47
A20: 3 | B20: 4°D | C20: 48 | D20: Hernán Gastón Padilla | E20: Armando Ezequiel Garro | F20: 0.0202 | G20: 113493.34 | H20: =141707-H89 -> 113492.86 | I20: =G20-H20 -> 0.47951392 | J20: =IF(I20>0,I20*3%,0) -> 0.014385418 | K20: =M$2*F20 -> 0 | L20: =M$1*F20 -> 72720 | M20: =F$1*F20 -> 46601.115 | N20: =F$2*F20 -> 11440.808 | O20: =ROUND(SUM(I20:N20),0) + Q20 -> 130762.48 | P20: =ROUND(O20*3%,0) + O20 -> 134685.48 | Q20: =ROUND(0.001+C20/100,2) -> 0.48
A21: 4 | B21: 5°A | C21: 49 | D21: Raul Boffi | E21: Barbara y Ezequiel | F21: 0.0202 | G21: 113493.34 | H21: =G21 -> 113493.34 | I21: =G21-H21 -> 0 | J21: =IF(I21>0,I21*3%,0) -> 0 | K21: =M$2*F21 -> 0 | L21: =M$1*F21 -> 72720 | M21: =F$1*F21 -> 46601.115 | N21: =F$2*F21 -> 11440.808 | O21: =ROUND(SUM(I21:N21),0) + Q21 -> 130762.49 | P21: =ROUND(O21*3%,0) + O21 -> 134685.49 | Q21: =ROUND(0.001+C21/100,2) -> 0.49
A22: 4 | B22: 5°B | C22: 50 | D22: Raul Boffi | F22: 0.0139 | G22: 134635.46 | I22: =G22-H22 -> 134635.46 | J22: =IF(I22>0,I22*3%,0) -> 4039.0639 | K22: =M$2*F22 -> 0 | L22: =M$1*F22 -> 50040 | M22: =F$1*F22 -> 32067.104 | N22: =F$2*F22 -> 7872.635 | O22: =ROUND(SUM(I22:N22),0) + Q22 -> 228654.5 | P22: =ROUND(O22*3%,0) + O22 -> 235514.5 | Q22: =ROUND(0.001+C22/100,2) -> 0.5
A23: 5 | B23: 5°C | C23: 51 | D23: Raul Boffi | F23: 0.0139 | G23: 78096.904 | I23: =G23-H23 -> 78096.904 | J23: =IF(I23>0,I23*3%,0) -> 2342.9071 | K23: =M$2*F23 -> 0 | L23: =M$1*F23 -> 50040 | M23: =F$1*F23 -> 32067.104 | N23: =F$2*F23 -> 7872.635 | O23: =ROUND(SUM(I23:N23),0) + Q23 -> 170420.51 | P23: =ROUND(O23*3%,0) + O23 -> 175533.51 | Q23: =ROUND(0.001+C23/100,2) -> 0.51
A24: 5 | B24: 5°D | C24: 52 | D24: Fernando Andres Canepa | E24: Matias / Carla Esteves | F24: 0.0202 | G24: 113493.34 | H24: =28214+113493-G86 -> 113492.86 | I24: =G24-H24 -> 0.47951392 | J24: =IF(I24>0,I24*3%,0) -> 0.014385418 | K24: =M$2*F24 -> 0 | L24: =M$1*F24 -> 72720 | M24: =F$1*F24 -> 46601.115 | N24: =F$2*F24 -> 11440.808 | O24: =ROUND(SUM(I24:N24),0) + Q24 -> 130762.52 | P24: =ROUND(O24*3%,0) + O24 -> 134685.52 | Q24: =ROUND(0.001+C24/100,2) -> 0.52
A25: 6 | B25: 6°A | C25: 53 | D25: Andres Gabriel Devouassoux | F25: 0.0202 | G25: 113493.34 | H25: =G25 -> 113493.34 | I25: =G25-H25 -> 0 | J25: =IF(I25>0,I25*3%,0) -> 0 | K25: =M$2*F25 -> 0 | L25: =M$1*F25 -> 72720 | M25: =F$1*F25 -> 46601.115 | N25: =F$2*F25 -> 11440.808 | O25: =ROUND(SUM(I25:N25),0) + Q25 -> 130762.53 | P25: =ROUND(O25*3%,0) + O25 -> 134685.53 | Q25: =ROUND(0.001+C25/100,2) -> 0.53
A26: 6 | B26: 6°B | C26: 54 | D26: Raul Boffi | E26: Nicolas Iudice | F26: 0.0139 | G26: 78096.904 | H26: =G26 -> 78096.904 | I26: =G26-H26 -> 0 | J26: =IF(I26>0,I26*3%,0) -> 0 | K26: =M$2*F26 -> 0 | L26: =M$1*F26 -> 50040 | M26: =F$1*F26 -> 32067.104 | N26: =F$2*F26 -> 7872.635 | O26: =ROUND(SUM(I26:N26),0) + Q26 -> 89980.54 | P26: =ROUND(O26*3%,0) + O26 -> 92679.54 | Q26: =ROUND(0.001+C26/100,2) -> 0.54
A27: 7 | B27: 6°C | C27: 55 | D27: Barbara Eugenia GARCIA FONTENLA | E27: Diego Coronel | F27: 0.0139 | G27: 134635.46 | H27: =79635 -> 79635 | I27: =G27-H27 -> 55000.464 | J27: =IF(I27>0,I27*3%,0) -> 1650.0139 | K27: =M$2*F27 -> 0 | L27: =M$1*F27 -> 50040 | M27: =F$1*F27 -> 32067.104 | N27: =F$2*F27 -> 7872.635 | O27: =ROUND(SUM(I27:N27),0) + Q27 -> 146630.55 | P27: =ROUND(O27*3%,0) + O27 -> 151029.55 | Q27: =ROUND(0.001+C27/100,2) -> 0.55
A28: 7 | B28: 6°D | C28: 56 | D28: Javier Alejandro Panaccio | F28: 0.0202 | G28: 195657.5 | H28: =79712-H65 -> 77910.996 | I28: =G28-H28 -> 117746.51 | J28: =IF(I28>0,I28*3%,0) -> 3532.3952 | K28: =M$2*F28 -> 0 | L28: =M$1*F28 -> 72720 | M28: =F$1*F28 -> 46601.115 | N28: =F$2*F28 -> 11440.808 | O28: =ROUND(SUM(I28:N28),0) + Q28 -> 252041.56 | P28: =ROUND(O28*3%,0) + O28 -> 259602.56 | Q28: =ROUND(0.001+C28/100,2) -> 0.56
A29: 8 | B29: 7°A | C29: 57 | D29: Mirta Isabel Asturino | F29: 0.0202 | G29: 113493.34 | H29: =G29 -> 113493.34 | I29: =G29-H29 -> 0 | J29: =IF(I29>0,I29*3%,0) -> 0 | K29: =M$2*F29 -> 0 | L29: =M$1*F29 -> 72720 | M29: =F$1*F29 -> 46601.115 | N29: =F$2*F29 -> 11440.808 | O29: =ROUND(SUM(I29:N29),0) + Q29 -> 130762.57 | P29: =ROUND(O29*3%,0) + O29 -> 134685.57 | Q29: =ROUND(0.001+C29/100,2) -> 0.57
A30: 8 | B30: 7°B | C30: 58 | D30: Jorge Antonio Mendiola | E30: Carlos Mehinger | F30: 0.0139 | G30: 393923.06 | H30: =78097 -> 78097 | I30: =G30-H30 -> 315826.06 | J30: =IF(I30>0,I30*3%,0) -> 9474.7819 | K30: =M$2*F30 -> 0 | L30: =M$1*F30 -> 50040 | M30: =F$1*F30 -> 32067.104 | N30: =F$2*F30 -> 7872.635 | O30: =ROUND(SUM(I30:N30),0) + Q30 -> 415281.58 | P30: =ROUND(O30*3%,0) + O30 -> 427739.58 | Q30: =ROUND(0.001+C30/100,2) -> 0.58
A31: 9 | B31: 7°C | C31: 59 | D31: Nelson Ariel FRAGA | F31: 0.0139 | G31: 135451.86 | H31: 135000 | I31: =G31-H31 -> 451.86428 | J31: =IF(I31>0,I31*3%,0) -> 13.555928 | K31: =M$2*F31 -> 0 | L31: =M$1*F31 -> 50040 | M31: =F$1*F31 -> 32067.104 | N31: =F$2*F31 -> 7872.635 | O31: =ROUND(SUM(I31:N31),0) + Q31 -> 90445.59 | P31: =ROUND(O31*3%,0) + O31 -> 93158.59 | Q31: =ROUND(0.001+C31/100,2) -> 0.59
A32: 9 | B32: 7°D | C32: 60 | D32: Domingo Alifraco | E32: Micaela Contreras | F32: 0.0202 | G32: 113493.34 | H32: =G32 -> 113493.34 | I32: =G32-H32 -> 0 | J32: =IF(I32>0,I32*3%,0) -> 0 | K32: =M$2*F32 -> 0 | L32: =M$1*F32 -> 72720 | M32: =F$1*F32 -> 46601.115 | N32: =F$2*F32 -> 11440.808 | O32: =ROUND(SUM(I32:N32),0) + Q32 -> 130762.6 | P32: =ROUND(O32*3%,0) + O32 -> 134685.6 | Q32: =ROUND(0.001+C32/100,2) -> 0.6
A33: 10 | B33: 8°A | C33: 61 | D33: Juan Pablo Charpin | F33: 0.0202 | G33: 113493.34 | H33: =141707-H87 -> 113492.86 | I33: =G33-H33 -> 0.47951392 | J33: =IF(I33>0,I33*3%,0) -> 0.014385418 | K33: =M$2*F33 -> 0 | L33: =M$1*F33 -> 72720 | M33: =F$1*F33 -> 46601.115 | N33: =F$2*F33 -> 11440.808 | O33: =ROUND(SUM(I33:N33),0) + Q33 -> 130762.61 | P33: =ROUND(O33*3%,0) + O33 -> 134685.61 | Q33: =ROUND(0.001+C33/100,2) -> 0.61
A34: 10 | B34: 8°B | C34: 62 | D34: Adriana Del Bagno | E34: Fanta / Alejandro Gabriel Lopez | F34: 0.0139 | G34: 78096.904 | H34: =G34 -> 78096.904 | I34: =G34-H34 -> 0 | J34: =IF(I34>0,I34*3%,0) -> 0 | K34: =M$2*F34 -> 0 | L34: =M$1*F34 -> 50040 | M34: =F$1*F34 -> 32067.104 | N34: =F$2*F34 -> 7872.635 | O34: =ROUND(SUM(I34:N34),0) + Q34 -> 89980.62 | P34: =ROUND(O34*3%,0) + O34 -> 92679.62 | Q34: =ROUND(0.001+C34/100,2) -> 0.62
A35: 11 | B35: 8°C | C35: 63 | D35: Claudio Moroni | E35: Macarena Barraza | F35: 0.0139 | G35: 78096.904 | H35: =G35 -> 78096.904 | I35: =G35-H35 -> 0 | J35: =IF(I35>0,I35*3%,0) -> 0 | K35: =M$2*F35 -> 0 | L35: =M$1*F35 -> 50040 | M35: =F$1*F35 -> 32067.104 | N35: =F$2*F35 -> 7872.635 | O35: =ROUND(SUM(I35:N35),0) + Q35 -> 89980.63 | P35: =ROUND(O35*3%,0) + O35 -> 92679.63 | Q35: =ROUND(0.001+C35/100,2) -> 0.63
A36: 11 | B36: 8°D | C36: 64 | D36: Karina Edith Mastandrea | E36: Ayelen | F36: 0.0202 | G36: 113493.34 | I36: =G36-H36 -> 113493.34 | J36: =IF(I36>0,I36*3%,0) -> 3404.8003 | K36: =M$2*F36 -> 0 | L36: =M$1*F36 -> 72720 | M36: =F$1*F36 -> 46601.115 | N36: =F$2*F36 -> 11440.808 | O36: =ROUND(SUM(I36:N36),0) + Q36 -> 247660.64 | P36: =ROUND(O36*3%,0) + O36 -> 255090.64 | Q36: =ROUND(0.001+C36/100,2) -> 0.64
A37: 12 | B37: 9°A | C37: 65 | D37: Fernando Fernandez | E37: Olivera Rodrigo | F37: 0.0202 | G37: 113493.34 | H37: =G37 -> 113493.34 | I37: =G37-H37 -> 0 | J37: =IF(I37>0,I37*3%,0) -> 0 | K37: =M$2*F37 -> 0 | L37: =M$1*F37 -> 72720 | M37: =F$1*F37 -> 46601.115 | N37: =F$2*F37 -> 11440.808 | O37: =ROUND(SUM(I37:N37),0) + Q37 -> 130762.65 | P37: =ROUND(O37*3%,0) + O37 -> 134685.65 | Q37: =ROUND(0.001+C37/100,2) -> 0.65
A38: 12 | B38: 9°B | C38: 66 | D38: Gonzalo Cadiz | E38: Micaela Dib | F38: 0.0139 | G38: 78096.904 | H38: =G38 -> 78096.904 | I38: =G38-H38 -> 0 | J38: =IF(I38>0,I38*3%,0) -> 0 | K38: =M$2*F38 -> 0 | L38: =M$1*F38 -> 50040 | M38: =F$1*F38 -> 32067.104 | N38: =F$2*F38 -> 7872.635 | O38: =ROUND(SUM(I38:N38),0) + Q38 -> 89980.66 | P38: =ROUND(O38*3%,0) + O38 -> 92679.66 | Q38: =ROUND(0.001+C38/100,2) -> 0.66
A39: 1 | B39: 9°C | C39: 67 | D39: Hernan Miñambres | E39: Laura Quintana | F39: 0.0139 | G39: 78096.904 | H39: =G39 -> 78096.904 | I39: =G39-H39 -> 0 | J39: =IF(I39>0,I39*3%,0) -> 0 | K39: =M$2*F39 -> 0 | L39: =M$1*F39 -> 50040 | M39: =F$1*F39 -> 32067.104 | N39: =F$2*F39 -> 7872.635 | O39: =ROUND(SUM(I39:N39),0) + Q39 -> 89980.67 | P39: =ROUND(O39*3%,0) + O39 -> 92679.67 | Q39: =ROUND(0.001+C39/100,2) -> 0.67
A40: 1 | B40: 9°D | C40: 68 | D40: Matías Ezequiel Tobío | E40: Jesica Romina | F40: 0.0202 | G40: 113493.34 | H40: =147563-H76 -> 113493.1 | I40: =G40-H40 -> 0.24371392 | J40: =IF(I40>0,I40*3%,0) -> 0.0073114177 | K40: =M$2*F40 -> 0 | L40: =M$1*F40 -> 72720 | M40: =F$1*F40 -> 46601.115 | N40: =F$2*F40 -> 11440.808 | O40: =ROUND(SUM(I40:N40),0) + Q40 -> 130762.68 | P40: =ROUND(O40*3%,0) + O40 -> 134685.68 | Q40: =ROUND(0.001+C40/100,2) -> 0.68
A41: 1 | B41: 10°A | C41: 69 | D41: Ariel Marcelo FERNANDEZ | E41: Sol Gatti Maria | F41: 0.0202 | G41: 113493.34 | H41: =G41 -> 113493.34 | I41: =G41-H41 -> 0 | J41: =IF(I41>0,I41*3%,0) -> 0 | K41: =M$2*F41 -> 0 | L41: =M$1*F41 -> 72720 | M41: =F$1*F41 -> 46601.115 | N41: =F$2*F41 -> 11440.808 | O41: =ROUND(SUM(I41:N41),0) + Q41 -> 130762.69 | P41: =ROUND(O41*3%,0) + O41 -> 134685.69 | Q41: =ROUND(0.001+C41/100,2) -> 0.69
A42: 2 | B42: 10°B | C42: 70 | D42: Jose Luis Gurtubay | E42: Antonela escobar | F42: 0.0139 | G42: 78096.904 | H42: =G42 -> 78096.904 | I42: =G42-H42 -> 0 | J42: =IF(I42>0,I42*3%,0) -> 0 | K42: =M$2*F42 -> 0 | L42: =M$1*F42 -> 50040 | M42: =F$1*F42 -> 32067.104 | N42: =F$2*F42 -> 7872.635 | O42: =ROUND(SUM(I42:N42),0) + Q42 -> 89980.7 | P42: =ROUND(O42*3%,0) + O42 -> 92679.7 | Q42: =ROUND(0.001+C42/100,2) -> 0.7
A43: 2 | B43: 10°C | C43: 71 | D43: Antonio Carlos Caputo | E43: Benitez Gabriela | F43: 0.0139 | G43: 78096.904 | H43: =G43 -> 78096.904 | I43: =G43-H43 -> 0 | J43: =IF(I43>0,I43*3%,0) -> 0 | K43: =M$2*F43 -> 0 | L43: =M$1*F43 -> 50040 | M43: =F$1*F43 -> 32067.104 | N43: =F$2*F43 -> 7872.635 | O43: =ROUND(SUM(I43:N43),0) + Q43 -> 89980.71 | P43: =ROUND(O43*3%,0) + O43 -> 92679.71 | Q43: =ROUND(0.001+C43/100,2) -> 0.71
A44: 2 | B44: 10°D | C44: 72 | D44: Antonio Carlos Caputo | E44: Agustina y Alan Pons | F44: 0.0202 | G44: 113493.34 | H44: =141707-H83 -> 113492.86 | I44: =G44-H44 -> 0.47951392 | J44: =IF(I44>0,I44*3%,0) -> 0.014385418 | K44: =M$2*F44 -> 0 | L44: =M$1*F44 -> 72720 | M44: =F$1*F44 -> 46601.115 | N44: =F$2*F44 -> 11440.808 | O44: =ROUND(SUM(I44:N44),0) + Q44 -> 130762.72 | P44: =ROUND(O44*3%,0) + O44 -> 134685.72 | Q44: =ROUND(0.001+C44/100,2) -> 0.72
A45: 3 | B45: 11°A | C45: 73 | D45: Manuel Salvador FERNANDEZ | E45: Nadia Santillan | F45: 0.0202 | G45: 276428.06 | H45: 156668 | I45: =G45-H45 -> 119760.06 | J45: =IF(I45>0,I45*3%,0) -> 3592.8019 | K45: =M$2*F45 -> 0 | L45: =M$1*F45 -> 72720 | M45: =F$1*F45 -> 46601.115 | N45: =F$2*F45 -> 11440.808 | O45: =ROUND(SUM(I45:N45),0) + Q45 -> 254115.73 | P45: =ROUND(O45*3%,0) + O45 -> 261738.73 | Q45: =ROUND(0.001+C45/100,2) -> 0.73
A46: 3 | B46: 11°B | C46: 74 | D46: Jorge Antonio VILLONE | E46: Micaela Acevedo | F46: 0.0139 | G46: 78096.904 | H46: =G46 -> 78096.904 | I46: =G46-H46 -> 0 | J46: =IF(I46>0,I46*3%,0) -> 0 | K46: =M$2*F46 -> 0 | L46: =M$1*F46 -> 50040 | M46: =F$1*F46 -> 32067.104 | N46: =F$2*F46 -> 7872.635 | O46: =ROUND(SUM(I46:N46),0) + Q46 -> 89980.74 | P46: =ROUND(O46*3%,0) + O46 -> 92679.74 | Q46: =ROUND(0.001+C46/100,2) -> 0.74
A47: 3 | B47: 11°C | C47: 75 | D47: Daniela Noemi Araujo | E47: Araceli | F47: 0.0139 | G47: 78096.904 | I47: =G47-H47 -> 78096.904 | J47: =IF(I47>0,I47*3%,0) -> 2342.9071 | K47: =M$2*F47 -> 0 | L47: =M$1*F47 -> 50040 | M47: =F$1*F47 -> 32067.104 | N47: =F$2*F47 -> 7872.635 | O47: =ROUND(SUM(I47:N47),0) + Q47 -> 170420.75 | P47: =ROUND(O47*3%,0) + O47 -> 175533.75 | Q47: =ROUND(0.001+C47/100,2) -> 0.75
A48: 4 | B48: 11°D | C48: 76 | D48: Gabriela Santiso/Claudio Touzon | E48: Ignacio Touzon | F48: 0.0202 | G48: 195657.5 | H48: =G48 -> 195657.5 | I48: =G48-H48 -> 0 | J48: =IF(I48>0,I48*3%,0) -> 0 | K48: =M$2*F48 -> 0 | L48: =M$1*F48 -> 72720 | M48: =F$1*F48 -> 46601.115 | N48: =F$2*F48 -> 11440.808 | O48: =ROUND(SUM(I48:N48),0) + Q48 -> 130762.76 | P48: =ROUND(O48*3%,0) + O48 -> 134685.76 | Q48: =ROUND(0.001+C48/100,2) -> 0.76
A49: 4 | B49: 12°A | C49: 77 | D49: Antonio Carlos Caputo | E49: Ezequiel / Delfina Saavedra | F49: 0.0202 | G49: 284438.14 | H49: 113493 | I49: =G49-H49 -> 170945.14 | J49: =IF(I49>0,I49*3%,0) -> 5128.3543 | K49: =M$2*F49 -> 0 | L49: =M$1*F49 -> 72720 | M49: =F$1*F49 -> 46601.115 | N49: =F$2*F49 -> 11440.808 | O49: =ROUND(SUM(I49:N49),0) + Q49 -> 306835.77 | P49: =ROUND(O49*3%,0) + O49 -> 316040.77 | Q49: =ROUND(0.001+C49/100,2) -> 0.77
A50: 4 | B50: 12°B | C50: 78 | D50: Antonio Carlos Caputo | E50: Mayne | F50: 0.0139 | G50: 134635.46 | H50: =54364 -> 54364 | I50: =G50-H50 -> 80271.464 | J50: =IF(I50>0,I50*3%,0) -> 2408.1439 | K50: =M$2*F50 -> 0 | L50: =M$1*F50 -> 50040 | M50: =F$1*F50 -> 32067.104 | N50: =F$2*F50 -> 7872.635 | O50: =ROUND(SUM(I50:N50),0) + Q50 -> 172659.78 | P50: =ROUND(O50*3%,0) + O50 -> 177839.78 | Q50: =ROUND(0.001+C50/100,2) -> 0.78
A51: 5 | B51: 12°C | C51: 79 | D51: Pedro Eugenio Negri | F51: 0.0139 | G51: 78096.904 | H51: =79162-G66 -> 78097.316 | I51: =G51-H51 -> -0.41131765 | J51: =IF(I51>0,I51*3%,0) -> 0 | K51: =M$2*F51 -> 0 | L51: =M$1*F51 -> 50040 | M51: =F$1*F51 -> 32067.104 | N51: =F$2*F51 -> 7872.635 | O51: =ROUND(SUM(I51:N51),0) + Q51 -> 89979.79 | P51: =ROUND(O51*3%,0) + O51 -> 92678.79 | Q51: =ROUND(0.001+C51/100,2) -> 0.79
A52: 5 | B52: 12°D | C52: 80 | D52: Luis Alberto Guarch | E52: Biyik | F52: 0.0202 | G52: 113493.34 | I52: =G52-H52 -> 113493.34 | J52: =IF(I52>0,I52*3%,0) -> 3404.8003 | K52: =M$2*F52 -> 0 | L52: =M$1*F52 -> 72720 | M52: =F$1*F52 -> 46601.115 | N52: =F$2*F52 -> 11440.808 | O52: =ROUND(SUM(I52:N52),0) + Q52 -> 247660.8 | P52: =ROUND(O52*3%,0) + O52 -> 255090.8 | Q52: =ROUND(0.001+C52/100,2) -> 0.8
A53: 5 | B53: 13°A | C53: 81 | D53: Soraya Mariel Varela | F53: 0.0202 | G53: 113493.34 | I53: =G53-H53 -> 113493.34 | J53: =IF(I53>0,I53*3%,0) -> 3404.8003 | K53: =M$2*F53 -> 0 | L53: =M$1*F53 -> 72720 | M53: =F$1*F53 -> 46601.115 | N53: =F$2*F53 -> 11440.808 | O53: =ROUND(SUM(I53:N53),0) + Q53 -> 247660.81 | P53: =ROUND(O53*3%,0) + O53 -> 255090.81 | Q53: =ROUND(0.001+C53/100,2) -> 0.81
A54: 6 | B54: 13°B | C54: 82 | D54: Rubén Dario LIBERALI | F54: 0.0139 | G54: 78096.904 | H54: =G54 -> 78096.904 | I54: =G54-H54 -> 0 | J54: =IF(I54>0,I54*3%,0) -> 0 | K54: =M$2*F54 -> 0 | L54: =M$1*F54 -> 50040 | M54: =F$1*F54 -> 32067.104 | N54: =F$2*F54 -> 7872.635 | O54: =ROUND(SUM(I54:N54),0) + Q54 -> 89980.82 | P54: =ROUND(O54*3%,0) + O54 -> 92679.82 | Q54: =ROUND(0.001+C54/100,2) -> 0.82
A55: 6 | B55: 13°C | C55: 83 | D55: Maria Gabriela Diaz | E55: Clobas Ezequiel | F55: 0.0139 | G55: 190216.18 | H55: =G55 -> 190216.18 | I55: =G55-H55 -> 0 | J55: =IF(I55>0,I55*3%,0) -> 0 | K55: =M$2*F55 -> 0 | L55: =M$1*F55 -> 50040 | M55: =F$1*F55 -> 32067.104 | N55: =F$2*F55 -> 7872.635 | O55: =ROUND(SUM(I55:N55),0) + Q55 -> 89980.83 | P55: =ROUND(O55*3%,0) + O55 -> 92679.83 | Q55: =ROUND(0.001+C55/100,2) -> 0.83
A56: 6 | B56: 13°D | C56: 84 | D56: Fabiana Besteiro | F56: 0.0202 | G56: 113493.34 | H56: =G56 -> 113493.34 | I56: =G56-H56 -> 0 | J56: =IF(I56>0,I56*3%,0) -> 0 | K56: =M$2*F56 -> 0 | L56: =M$1*F56 -> 72720 | M56: =F$1*F56 -> 46601.115 | N56: =F$2*F56 -> 11440.808 | O56: =ROUND(SUM(I56:N56),0) + Q56 -> 130762.84 | P56: =ROUND(O56*3%,0) + O56 -> 134685.84 | Q56: =ROUND(0.001+C56/100,2) -> 0.84
A57: 7 | L57: =M$1*F57 -> 0 | O57: =ROUND(SUM(I57:N57),0) + Q57 -> 0 | Q57: =ROUND(0.001+C57/100,2) -> 0
A58: 7 | L58: =M$1*F58 -> 0 | O58: =ROUND(SUM(I58:N58),0) + Q58 -> 0 | Q58: =ROUND(0.001+C58/100,2) -> 0
A59: 7 | B59: P.B.1 | C59: 17 | D59: Antonio Carlos Caputo | E59: Barbara Bañon / Delia Martinez | F59: 0.0032 | G59: 17034.95 | H59: =18100-H72 -> 17035.316 | I59: =G59-H59 -> -0.3652 | J59: =IF(I59>0,I59*3%,0) -> 0 | K59: =M$2*F59 -> 0 | L59: =M$1*F59 -> 11520 | M59: =F$1*F59 -> 7382.3549 | N59: =F$2*F59 -> 1812.4052 | O59: =ROUND(SUM(I59:N59),0) + Q59 -> 20714.17 | P59: =ROUND(O59*3%,0) + O59 -> 21335.17 | Q59: =ROUND(0.001+C59/100,2) -> 0.17
A60: 8 | B60: P.B.2 | C60: 18 | D60: Osvaldo Ricardo Colombo | F60: 0.0033 | G60: 90176.973 | I60: =G60-H60 -> 90176.973 | J60: =IF(I60>0,I60*3%,0) -> 2705.3092 | K60: =M$2*F60 -> 0 | L60: =M$1*F60 -> 11880 | M60: =F$1*F60 -> 7613.0535 | N60: =F$2*F60 -> 1869.0428 | O60: =ROUND(SUM(I60:N60),0) + Q60 -> 114244.18 | P60: =ROUND(O60*3%,0) + O60 -> 117671.18 | Q60: =ROUND(0.001+C60/100,2) -> 0.18
A61: 8 | B61: P.B.3 | C61: 19 | D61: Fernando Saavedra | F61: 0.0004 | G61: 2129.3688 | H61: =3194-H62 -> 5933.3156 | I61: =G61-H61 -> -3803.9468 | J61: =IF(I61>0,I61*3%,0) -> 0 | K61: =M$2*F61 -> 0 | L61: =M$1*F61 -> 1440 | M61: =F$1*F61 -> 922.79436 | N61: =F$2*F61 -> 226.55065 | O61: =ROUND(SUM(I61:N61),0) + Q61 -> -1214.81 | P61: =ROUND(O61*3%,0) + O61 -> -1250.81 | Q61: =ROUND(0.001+C61/100,2) -> 0.19
A62: 8 | B62: P.B.4 | C62: 20 | D62: Fernando Saavedra | F62: 0.0002 | G62: -2739.3156 | H62: =G62 -> -2739.3156 | I62: =G62-H62 -> 0 | J62: =IF(I62>0,I62*3%,0) -> 0 | K62: =M$2*F62 -> 0 | L62: =M$1*F62 -> 720 | M62: =F$1*F62 -> 461.39718 | N62: =F$2*F62 -> 113.27532 | O62: =ROUND(SUM(I62:N62),0) + Q62 -> 1295.2 | P62: =ROUND(O62*3%,0) + O62 -> 1334.2 | Q62: =ROUND(0.001+C62/100,2) -> 0.2
A63: 9 | B63: P.B.5 | C63: 21 | D63: Ayelen Bárbara Kisch | F63: 0.0002 | G63: 1064.6844 | I63: =G63-H63 -> 1064.6844 | J63: =IF(I63>0,I63*3%,0) -> 31.940532 | K63: =M$2*F63 -> 0 | L63: =M$1*F63 -> 720 | M63: =F$1*F63 -> 461.39718 | N63: =F$2*F63 -> 113.27532 | O63: =ROUND(SUM(I63:N63),0) + Q63 -> 2391.21 | P63: =ROUND(O63*3%,0) + O63 -> 2463.21 | Q63: =ROUND(0.001+C63/100,2) -> 0.21
A64: 9 | B64: P.B.6 | C64: 22 | D64: Adrian Alejandro Pozo | F64: 0.0002 | G64: 1801.0044 | H64: =G64 -> 1801.0044 | I64: =G64-H64 -> 0 | J64: =IF(I64>0,I64*3%,0) -> 0 | K64: =M$2*F64 -> 0 | L64: =M$1*F64 -> 720 | M64: =F$1*F64 -> 461.39718 | N64: =F$2*F64 -> 113.27532 | O64: =ROUND(SUM(I64:N64),0) + Q64 -> 1295.22 | P64: =ROUND(O64*3%,0) + O64 -> 1334.22 | Q64: =ROUND(0.001+C64/100,2) -> 0.22
A65: 9 | B65: P.B.7 | C65: 23 | D65: Javier Alejandro Panaccio | F65: 0.0002 | G65: 1801.0044 | H65: =G65 -> 1801.0044 | I65: =G65-H65 -> 0 | J65: =IF(I65>0,I65*3%,0) -> 0 | K65: =M$2*F65 -> 0 | L65: =M$1*F65 -> 720 | M65: =F$1*F65 -> 461.39718 | N65: =F$2*F65 -> 113.27532 | O65: =ROUND(SUM(I65:N65),0) + Q65 -> 1295.23 | P65: =ROUND(O65*3%,0) + O65 -> 1334.23 | Q65: =ROUND(0.001+C65/100,2) -> 0.23
A66: 10 | B66: P.B.8 | C66: 24 | D66: Pedro Eugenio Negri | F66: 0.0002 | G66: 1064.6844 | H66: =G66 -> 1064.6844 | I66: =G66-H66 -> 0 | J66: =IF(I66>0,I66*3%,0) -> 0 | K66: =M$2*F66 -> 0 | L66: =M$1*F66 -> 720 | M66: =F$1*F66 -> 461.39718 | N66: =F$2*F66 -> 113.27532 | O66: =ROUND(SUM(I66:N66),0) + Q66 -> 1295.24 | P66: =ROUND(O66*3%,0) + O66 -> 1334.24 | Q66: =ROUND(0.001+C66/100,2) -> 0.24
A67: 10 | B67: P.B.9 | C67: 25 | D67: Laura Natalia Carrillo | E67: Emiliano Calderon Alberto | F67: 0.0002 | G67: 1064.6844 | H67: =G67 -> 1064.6844 | I67: =G67-H67 -> 0 | J67: =IF(I67>0,I67*3%,0) -> 0 | K67: =M$2*F67 -> 0 | L67: =M$1*F67 -> 720 | M67: =F$1*F67 -> 461.39718 | N67: =F$2*F67 -> 113.27532 | O67: =ROUND(SUM(I67:N67),0) + Q67 -> 1295.25 | P67: =ROUND(O67*3%,0) + O67 -> 1334.25 | Q67: =ROUND(0.001+C67/100,2) -> 0.25
A68: 10 | B68: P.B.10 | C68: 26 | D68: Jorge Antonio Mendiola | F68: 0.0002 | G68: 1064.6844 | H68: =G68 -> 1064.6844 | I68: =G68-H68 -> 0 | J68: =IF(I68>0,I68*3%,0) -> 0 | K68: =M$2*F68 -> 0 | L68: =M$1*F68 -> 720 | M68: =F$1*F68 -> 461.39718 | N68: =F$2*F68 -> 113.27532 | O68: =ROUND(SUM(I68:N68),0) + Q68 -> 1295.26 | P68: =ROUND(O68*3%,0) + O68 -> 1334.26 | Q68: =ROUND(0.001+C68/100,2) -> 0.26
A69: 11 | B69: P.B.11 | C69: 27 | D69: García | F69: 0.0002 | G69: 6788.8444 | I69: =G69-H69 -> 6788.8444 | J69: =IF(I69>0,I69*3%,0) -> 203.66533 | K69: =M$2*F69 -> 0 | L69: =M$1*F69 -> 720 | M69: =F$1*F69 -> 461.39718 | N69: =F$2*F69 -> 113.27532 | O69: =ROUND(SUM(I69:N69),0) + Q69 -> 8287.27 | P69: =ROUND(O69*3%,0) + O69 -> 8536.27 | Q69: =ROUND(0.001+C69/100,2) -> 0.27
A70: 11 | B70: P.B.12 | C70: 28 | D70: García | F70: 0.0002 | G70: 6788.8444 | I70: =G70-H70 -> 6788.8444 | J70: =IF(I70>0,I70*3%,0) -> 203.66533 | K70: =M$2*F70 -> 0 | L70: =M$1*F70 -> 720 | M70: =F$1*F70 -> 461.39718 | N70: =F$2*F70 -> 113.27532 | O70: =ROUND(SUM(I70:N70),0) + Q70 -> 8287.28 | P70: =ROUND(O70*3%,0) + O70 -> 8536.28 | Q70: =ROUND(0.001+C70/100,2) -> 0.28
A71: 11 | B71: P.B.13 | C71: 29 | D71: Raul Boffi | E71: Dario Javier Flecha | F71: 0.0002 | G71: 4302.2044 | H71: =G71 -> 4302.2044 | I71: =G71-H71 -> 0 | J71: =IF(I71>0,I71*3%,0) -> 0 | K71: =M$2*F71 -> 0 | L71: =M$1*F71 -> 720 | M71: =F$1*F71 -> 461.39718 | N71: =F$2*F71 -> 113.27532 | O71: =ROUND(SUM(I71:N71),0) + Q71 -> 1295.29 | P71: =ROUND(O71*3%,0) + O71 -> 1334.29 | Q71: =ROUND(0.001+C71/100,2) -> 0.29
B72: P.B.14 | C72: 30 | D72: Raul Boffi | E72: Barbara Bañon / Delia Martinez | F72: 0.0002 | G72: 1064.6844 | H72: =G72 -> 1064.6844 | I72: =G72-H72 -> 0 | J72: =IF(I72>0,I72*3%,0) -> 0 | K72: =M$2*F72 -> 0 | L72: =M$1*F72 -> 720 | M72: =F$1*F72 -> 461.39718 | N72: =F$2*F72 -> 113.27532 | O72: =ROUND(SUM(I72:N72),0) + Q72 -> 1295.3 | P72: =ROUND(O72*3%,0) + O72 -> 1334.3 | Q72: =ROUND(0.001+C72/100,2) -> 0.3
B73: P.B.15 | C73: 31 | D73: Raul Boffi | F73: 0.0002 | G73: 1064.6844 | I73: =G73-H73 -> 1064.6844 | J73: =IF(I73>0,I73*3%,0) -> 31.940532 | K73: =M$2*F73 -> 0 | L73: =M$1*F73 -> 720 | M73: =F$1*F73 -> 461.39718 | N73: =F$2*F73 -> 113.27532 | O73: =ROUND(SUM(I73:N73),0) + Q73 -> 2391.31 | P73: =ROUND(O73*3%,0) + O73 -> 2463.31 | Q73: =ROUND(0.001+C73/100,2) -> 0.31
B74: GALPON | C74: 32 | D74: Club Atlético Banfield | F74: 0.0158 | G74: 1900511.7 | I74: =G74-H74 -> 1900511.7 | J74: =IF(I74>0,I74*3%,0) -> 57015.35 | K74: =M$2*F74 -> 0 | L74: =M$1*F74 -> 56880 | M74: =F$1*F74 -> 36450.377 | N74: =F$2*F74 -> 8948.7506 | O74: =ROUND(SUM(I74:N74),0) + Q74 -> 2059806.3 | P74: =ROUND(O74*3%,0) + O74 -> 2121600.3 | Q74: =ROUND(0.001+C74/100,2) -> 0.32
B75: S.S.16 | C75: 1 | D75: Antonio Carlos Caputo | F75: 0.0061 | G75: 137437.99 | I75: =G75-H75 -> 137437.99 | J75: =IF(I75>0,I75*3%,0) -> 4123.1398 | K75: =M$2*F75 -> 0 | L75: =M$1*F75 -> 21960 | M75: =F$1*F75 -> 14072.614 | N75: =F$2*F75 -> 3454.8974 | O75: =ROUND(SUM(I75:N75),0) + Q75 -> 181049.01 | P75: =ROUND(O75*3%,0) + O75 -> 186480.01 | Q75: =ROUND(0.001+C75/100,2) -> 0.01
B76: S.S.17 | C76: 2 | D76: Jesica Romina Tobio | F76: 0.0064 | G76: 34069.901 | H76: =G76 -> 34069.901 | I76: =G76-H76 -> 0 | J76: =IF(I76>0,I76*3%,0) -> 0 | K76: =M$2*F76 -> 0 | L76: =M$1*F76 -> 23040 | M76: =F$1*F76 -> 14764.71 | N76: =F$2*F76 -> 3624.8104 | O76: =ROUND(SUM(I76:N76),0) + Q76 -> 41430.02 | P76: =ROUND(O76*3%,0) + O76 -> 42673.02 | Q76: =ROUND(0.001+C76/100,2) -> 0.02
B77: S.S.18 | C77: 3 | D77: Diaz Laura Natalia | F77: 0.0057 | G77: 30343.505 | H77: =G77 -> 30343.505 | I77: =G77-H77 -> 0 | J77: =IF(I77>0,I77*3%,0) -> 0 | K77: =M$2*F77 -> 0 | L77: =M$1*F77 -> 20520 | M77: =F$1*F77 -> 13149.82 | N77: =F$2*F77 -> 3228.3467 | O77: =ROUND(SUM(I77:N77),0) + Q77 -> 36898.03 | P77: =ROUND(O77*3%,0) + O77 -> 38005.03 | Q77: =ROUND(0.001+C77/100,2) -> 0.03
B78: S.S.19 | C78: 4 | D78: Juan Carlos Alonso | F78: 0.0053 | G78: 28214.137 | H78: =G78 -> 28214.137 | I78: =G78-H78 -> 0 | J78: =IF(I78>0,I78*3%,0) -> 0 | K78: =M$2*F78 -> 0 | L78: =M$1*F78 -> 19080 | M78: =F$1*F78 -> 12227.025 | N78: =F$2*F78 -> 3001.7961 | O78: =ROUND(SUM(I78:N78),0) + Q78 -> 34309.04 | P78: =ROUND(O78*3%,0) + O78 -> 35338.04 | Q78: =ROUND(0.001+C78/100,2) -> 0.04
B79: S.S.20 | C79: 5 | D79: Jose Luis Gurtubay | F79: 0.0053 | G79: 28214.137 | I79: =G79-H79 -> 28214.137 | J79: =IF(I79>0,I79*3%,0) -> 846.4241 | K79: =M$2*F79 -> 0 | L79: =M$1*F79 -> 19080 | M79: =F$1*F79 -> 12227.025 | N79: =F$2*F79 -> 3001.7961 | O79: =ROUND(SUM(I79:N79),0) + Q79 -> 63369.05 | P79: =ROUND(O79*3%,0) + O79 -> 65270.05 | Q79: =ROUND(0.001+C79/100,2) -> 0.05
B80: S.S.21 | C80: 6 | D80: Alejandro DI LEO - | F80: 0.0053 | G80: 28214.137 | I80: =G80-H80 -> 28214.137 | J80: =IF(I80>0,I80*3%,0) -> 846.4241 | K80: =M$2*F80 -> 0 | L80: =M$1*F80 -> 19080 | M80: =F$1*F80 -> 12227.025 | N80: =F$2*F80 -> 3001.7961 | O80: =ROUND(SUM(I80:N80),0) + Q80 -> 63369.06 | P80: =ROUND(O80*3%,0) + O80 -> 65270.06 | Q80: =ROUND(0.001+C80/100,2) -> 0.06
A81: 12 | B81: S.S.22 | C81: 7 | D81: Karina Edith Mastandrea | F81: 0.0053 | G81: 28214.137 | I81: =G81-H81 -> 28214.137 | J81: =IF(I81>0,I81*3%,0) -> 846.4241 | K81: =M$2*F81 -> 0 | L81: =M$1*F81 -> 19080 | M81: =F$1*F81 -> 12227.025 | N81: =F$2*F81 -> 3001.7961 | O81: =ROUND(SUM(I81:N81),0) + Q81 -> 63369.07 | P81: =ROUND(O81*3%,0) + O81 -> 65270.07 | Q81: =ROUND(0.001+C81/100,2) -> 0.07
A82: 12 | B82: S.S.23 | C82: 8 | D82: Antonio Carlos Caputo | F82: 0.0053 | G82: 28214.137 | I82: =G82-H82 -> 28214.137 | J82: =IF(I82>0,I82*3%,0) -> 846.4241 | K82: =M$2*F82 -> 0 | L82: =M$1*F82 -> 19080 | M82: =F$1*F82 -> 12227.025 | N82: =F$2*F82 -> 3001.7961 | O82: =ROUND(SUM(I82:N82),0) + Q82 -> 63369.08 | P82: =ROUND(O82*3%,0) + O82 -> 65270.08 | Q82: =ROUND(0.001+C82/100,2) -> 0.08
A83: 12 | B83: S.S.24 | C83: 9 | D83: Antonio Carlos Caputo | F83: 0.0053 | G83: 28214.137 | H83: =G83 -> 28214.137 | I83: =G83-H83 -> 0 | J83: =IF(I83>0,I83*3%,0) -> 0 | K83: =M$2*F83 -> 0 | L83: =M$1*F83 -> 19080 | M83: =F$1*F83 -> 12227.025 | N83: =F$2*F83 -> 3001.7961 | O83: =ROUND(SUM(I83:N83),0) + Q83 -> 34309.09 | P83: =ROUND(O83*3%,0) + O83 -> 35338.09 | Q83: =ROUND(0.001+C83/100,2) -> 0.09
B84: S.S.25 | C84: 10 | D84: Antonio Carlos Caputo | F84: 0.0053 | G84: 116341.66 | I84: =G84-H84 -> 116341.66 | J84: =IF(I84>0,I84*3%,0) -> 3490.2497 | K84: =M$2*F84 -> 0 | L84: =M$1*F84 -> 19080 | M84: =F$1*F84 -> 12227.025 | N84: =F$2*F84 -> 3001.7961 | O84: =ROUND(SUM(I84:N84),0) + Q84 -> 154141.1 | P84: =ROUND(O84*3%,0) + O84 -> 158765.1 | Q84: =ROUND(0.001+C84/100,2) -> 0.1
B85: S.S.26 | C85: 11 | D85: Antonio Carlos Caputo | F85: 0.0053 | G85: 77961.497 | I85: =G85-H85 -> 77961.497 | J85: =IF(I85>0,I85*3%,0) -> 2338.8449 | K85: =M$2*F85 -> 0 | L85: =M$1*F85 -> 19080 | M85: =F$1*F85 -> 12227.025 | N85: =F$2*F85 -> 3001.7961 | O85: =ROUND(SUM(I85:N85),0) + Q85 -> 114609.11 | P85: =ROUND(O85*3%,0) + O85 -> 118047.11 | Q85: =ROUND(0.001+C85/100,2) -> 0.11
B86: S.S.27 | C86: 12 | D86: Fernando Andres Canepa | E86: Matias / Carla Esteves | F86: 0.0053 | G86: 28214.137 | H86: =G86 -> 28214.137 | I86: =G86-H86 -> 0 | J86: =IF(I86>0,I86*3%,0) -> 0 | K86: =M$2*F86 -> 0 | L86: =M$1*F86 -> 19080 | M86: =F$1*F86 -> 12227.025 | N86: =F$2*F86 -> 3001.7961 | O86: =ROUND(SUM(I86:N86),0) + Q86 -> 34309.12 | P86: =ROUND(O86*3%,0) + O86 -> 35338.12 | Q86: =ROUND(0.001+C86/100,2) -> 0.12
B87: S.S.28 | C87: 13 | D87: Juan Pablo Charpin | F87: 0.0053 | G87: 28214.137 | H87: =G87 -> 28214.137 | I87: =G87-H87 -> 0 | J87: =IF(I87>0,I87*3%,0) -> 0 | K87: =M$2*F87 -> 0 | L87: =M$1*F87 -> 19080 | M87: =F$1*F87 -> 12227.025 | N87: =F$2*F87 -> 3001.7961 | O87: =ROUND(SUM(I87:N87),0) + Q87 -> 34309.13 | P87: =ROUND(O87*3%,0) + O87 -> 35338.13 | Q87: =ROUND(0.001+C87/100,2) -> 0.13
B88: S.S.29 | C88: 14 | D88: Javier Alejandro Panaccio | F88: 0.0053 | G88: 47721.417 | I88: =G88-H88 -> 47721.417 | J88: =IF(I88>0,I88*3%,0) -> 1431.6425 | K88: =M$2*F88 -> 0 | L88: =M$1*F88 -> 19080 | M88: =F$1*F88 -> 12227.025 | N88: =F$2*F88 -> 3001.7961 | O88: =ROUND(SUM(I88:N88),0) + Q88 -> 83462.14 | P88: =ROUND(O88*3%,0) + O88 -> 85966.14 | Q88: =ROUND(0.001+C88/100,2) -> 0.14
B89: S.S.30 | C89: 15 | D89: Hernán Gastón Padilla | E89: =E20 -> Armando Ezequiel Garro | F89: 0.0053 | G89: 28214.137 | H89: =G89 -> 28214.137 | I89: =G89-H89 -> 0 | J89: =IF(I89>0,I89*3%,0) -> 0 | K89: =M$2*F89 -> 0 | L89: =M$1*F89 -> 19080 | M89: =F$1*F89 -> 12227.025 | N89: =F$2*F89 -> 3001.7961 | O89: =ROUND(SUM(I89:N89),0) + Q89 -> 34309.15 | P89: =ROUND(O89*3%,0) + O89 -> 35338.15 | Q89: =ROUND(0.001+C89/100,2) -> 0.15
B90: S.S.31 | C90: 16 | D90: Domingo Alifraco | E90: Aranda Jonhatan | F90: 0.0062 | G90: 55824.896 | H90: =G90 -> 55824.896 | I90: =G90-H90 -> 0 | J90: =IF(I90>0,I90*3%,0) -> 0 | K90: =M$2*F90 -> 0 | L90: =M$1*F90 -> 22320 | M90: =F$1*F90 -> 14303.313 | N90: =F$2*F90 -> 3511.535 | O90: =ROUND(SUM(I90:N90),0) + Q90 -> 40135.16 | P90: =ROUND(O90*3%,0) + O90 -> 41339.16 | Q90: =ROUND(0.001+C90/100,2) -> 0.16
F92: =SUM(F5:F91) -> 1 | G92: =SUM(G5:G91) -> 9032977.4 | H92: =SUM(H5:H91) -> 4833106.7 | I92: =SUM(I5:I91) -> 4199870.7 | J92: =SUM(J5:J91) -> 126956.7 | K92: =SUM(K5:K91) -> 0 | L92: =SUM(L5:L91) -> 3600000 | M92: =SUM(M5:M90) -> 2306985.9 | N92: =SUM(N5:N90) -> 566376.62 | O92: =SUM(O5:O91) -> 10800229 | P92: =SUM(P5:P91) -> 11124233
D95: =RESUMEN!A13 -> ESTIMADOS PROPIETARIOS E INQUILINOS: POR FAVOR LOS QUE ABONAN EN PRIMER VENCIMIENTO ABONEN EL MONTO DE PRIMER VENCIMIENTO, ASI AGILIZAN LA LIQUIDACION, LES PEDIMOS ENCARECIDAMENTE QUE RESPETEN LOS CENTAVOS CORRESPONDIENTES A LA UNIDAD FUNCIONAL. ES DE CARÁCTER OBLIGATORIO INFORMAR VIA MAIL LAS EXPENSAS.
