Workbook

Sheet RESUMEN
C1: MAIL: elmiradorconsorcios@gmail.com
C2: CUIT ADMINISTRACION: 27231256879
C3: CBU: 0720039720000002171436 | E3: TELEFONO: 11 5320-2676
C4: ADMINISTRADORA: CAROLINA CANCIANI MP:1148
C5: PERÍODO: ENERO | E5: HORARIOS DE ATENCION: LUNES A VIERNES - 10 A 16HS - EMERGENCIAS 24HS
C6: LIQUIDACION DE EXPENSAS
A14: Importante para dueños o inquilinos de departamentos o coheras: Queremos recordarles una cuestión importante respecto a los pagos de expensas que ayuda a evitar errores en la imputación de los mismos. El sistema que utilizamos asigna centavos únicos a cada Unidad Funcional (UF), lo cual nos permite identificar automáticamente a qué unidad corresponde cada transferencia. Es decir, cada UF tiene un número específico de centavos que actúa como "identificador". Por ejemplo, si tu UF es la 45, el importe a abonar debería terminar en $...,45. Si tenés más de una unidad (por ejemplo, un departamento y una cochera), cada una tiene su propio código de centavos. En esos casos, te pedimos por favor que realices una transferencia por cada UF, respetando el importe con sus centavos correspondientes. Sabemos que a veces por comodidad se suele enviar todo junto en una sola transferencia, pero esto puede generar confusión o errores en la imputación automática. Realizar los pagos por separado nos permite asegurar que cada importe se asigne correctamente. Agradecemos muchísimo la colaboración para seguir manteniendo todo ordenado. Saludos cordiales.
A20: VTO 16/02
A24: GASTOS ORDINARIOS UNIDADES FUNCIONALES: | E24: UF 93,20% | F24: LOCAL 1 (1,08%) | G24: LOCAL 2 (1,28%) | H24: LOCAL 3 (1,21%) | I24: LOCAL 4 (1,49%) | J24: LOCAL 5 (1,74%)
A25: Sueldo encargada Sonia Arzamendia Galeano
A26: Haberes | D26: 1124512
A27: Plus pileta | D27: 39622.7
A28: Plus retiro de basura | D28: =1726*80 -> 138080
A29: Plus cochera | D29: 23553.4
A30: Adicional Viaticos | D30: 65596.5
A31: Adicional remuneracion | D31: 120000
A32: Descuento Dia Sabado 31/01 | D32: -44192.27
A33: SUBTOTAL | D33: =SUM(D26:D32) -> 1467172.3
A34: Sueldo encargada Miriam
A35: Haberes | D35: 562256
A36: Plus pileta | D36: =D27 -> 39622.7
A37: Plus retiro de basura | D37: =D28 -> 138080
A38: Plus cochera | D38: =D29 -> 23553.4
A39: Adicional Viaticos | D39: =D30 -> 65596.5
A40: Adicional remuneracion | D40: 60000
A41: Descuento 4 dias | D41: -101801.65
A42: SUBTOTAL | D42: =SUM(D35:D41) -> 787306.95
A43: TOTAL SUELDO | D43: =D33+D42 -> 2254479.3 | E43: =D43*93.2% -> 2101174.7 | F43: =$D43*1.08% -> 24348.376 | G43: =$D43*1.28% -> 28857.335 | H43: =$D43*1.21% -> 27279.199 | I43: =$D43*1.49% -> 33591.741 | J43: =D43*1.74% -> 39227.939 | K43: =E43+J43+F43+G43+H43+I43 -> 2254479.3 | L43: =IF(D43=K43, "", "Error")
A44: Reemplazo Sra. Miriam - Sr. Cristian | D44: 254504.03
A46: TOTAL | D46: =SUM(D44:D44) -> 254504.03 | E46: =D46*93.2% -> 237197.76 | F46: =$D46*1.08% -> 2748.6435 | G46: =$D46*1.28% -> 3257.6516 | H46: =$D46*1.21% -> 3079.4988 | I46: =$D46*1.49% -> 3792.11 | J46: =D46*1.74% -> 4428.3701 | K46: =E46+J46+F46+G46+H46+I46 -> 254504.03 | L46: =IF(D46=K46, "", "Error")
A47: COMBUSTIBLE PARA GRUPO ELECTROGENO | E47: =D47*91.91% -> 0
A48: Combustible | C48: 46024 | D48: 71000 | E48: =D48 -> 71000
A49: Combustible | C49: 46024 | D49: 71000 | E49: =D49 -> 71000
A50: Combustible | C50: 46024 | D50: 36025 | E50: =D50 -> 36025
A51: Combustible | C51: 46024 | D51: 78006.05 | E51: =D51 -> 78006.05
A52: Combustible | C52: 46025 | D52: 37040 | E52: =D52 -> 37040
A54: TOTAL | D54: =SUM(D48:D53) -> 293071.05 | E54: =D54 -> 293071.05 | K54: =E54+J54+F54+G54+H54+I54 -> 293071.05 | L54: =IF(D54=K54, "", "Error")
A55: IMPUESTOS
A56: ARBA - Impuesto inmobiliario partida 025024270-0
A57: TSG - Partida 197229000 | B57: Mes de ENERO | C57: Pago Ef. Por adm. | D57: 249469
A58: TSG - Partida 197229000 | B58: Mes de ENERO | C58: Transf 12/01 | D58: 249469
A59: TOTAL IMPUESTOS | D59: =SUM(D56:D58) -> 498938 | E59: =D59*93.2% -> 465010.22 | F59: =$D59*1.08% -> 5388.5304 | G59: =$D59*1.28% -> 6386.4064 | H59: =$D59*1.21% -> 6037.1498 | I59: =$D59*1.49% -> 7434.1762 | J59: =D59*1.74% -> 8681.5212 | K59: =E59+J59+F59+G59+H59+I59 -> 498938 | L59: =IF(D59=K59, "", "Error")
A60: APORTES Y CONTRIBUCIONES
A61: Monotributo Sra. Sonia | C61: Transf 23/01 | D61: 56231.41
A62: Monotributo Sra. Miriam | C62: Transf 23/01 | D62: 64941
A63: Monotributo Sra. Miriam | B63: Mes de Diciembre - Adeudado | C63: Transf 07/01 | D63: 64941
A64: TOTAL APORTES Y CONTRIBUCIONES | D64: =SUM(D60:D63) -> 186113.41 | E64: =D64*93.2% -> 173457.7 | F64: =$D64*1.08% -> 2010.0248 | G64: =$D64*1.28% -> 2382.2516 | H64: =$D64*1.21% -> 2251.9723 | I64: =$D64*1.49% -> 2773.0898 | J64: =D64*1.74% -> 3238.3733 | K64: =E64+J64+F64+G64+H64+I64 -> 186113.41 | L64: =IF(D64=K64, "", "Error")
A65: SEGUROS
A66: Federacion patronal - Poliza integral para consorcios nro. 2152393 | C66: Debito autom. | D66: 160913 | E66: =D66*93.2% -> 149970.92 | F66: =$D66*1.08% -> 1737.8604 | G66: =$D66*1.28% -> 2059.6864 | H66: =$D66*1.21% -> 1947.0473 | I66: =$D66*1.49% -> 2397.6037 | J66: =D66*1.74% -> 2799.8862 | K66: =SUM(E66:J66) -> 160913
A67: Federacion patronal - Poliza accidentes personales Sra. Sonia - nro. 9559834 | C67: Debito autom. | D67: 7907 | E67: =D67*93.2% -> 7369.324 | F67: =$D67*1.08% -> 85.3956 | G67: =$D67*1.28% -> 101.2096 | H67: =$D67*1.21% -> 95.6747 | I67: =$D67*1.49% -> 117.8143 | J67: =D67*1.74% -> 137.5818 | K67: =SUM(E67:J67) -> 7907 | L67: Pendiente mes de febrer0 el 02/02 se debito federacional patronal
A68: Federacion patronal - Poliza accidentes personales Sra. Miriam - nro. 9559886 | C68: Debito autom. | D68: 7907 | E68: =D68*93.2% -> 7369.324 | F68: =$D68*1.08% -> 85.3956 | G68: =$D68*1.28% -> 101.2096 | H68: =$D68*1.21% -> 95.6747 | I68: =$D68*1.49% -> 117.8143 | J68: =D68*1.74% -> 137.5818 | K68: =SUM(E68:J68) -> 7907
A69: TOTAL Aportes y Contribuciones - Sindicato | D69: =SUM(D66:D68) -> 176727 | E69: =SUM(E66:E68) -> 164709.56 | F69: =SUM(F66:F68) -> 1908.6516 | G69: =SUM(G66:G68) -> 2262.1056 | H69: =SUM(H66:H68) -> 2138.3967 | I69: =SUM(I66:I68) -> 2633.2323 | J69: =SUM(J66:J68) -> 3075.0498 | K69: =E69+J69+F69+G69+H69+I69 -> 176727 | L69: =IF(D69=K69, "", "Error")
A70: ABONOS Y SERVICIOS
A71: Aysa - Cuenta 249011 | C71: Transf 15/01 | D71: 1469353.3 | E71: =D71*93.2% -> 1369437.3 | F71: =$D71*1.08% -> 15869.016 | G71: =$D71*1.28% -> 18807.722 | H71: =$D71*1.21% -> 17779.175 | I71: =$D71*1.49% -> 21893.364 | J71: =D71*1.74% -> 25566.748 | K71: =D71 -> 1469353.3 | L71: =SUM(E71:J71) -> 1469353.3
A72: Edesur - Cliente 01291636 | C72: Transf 12/01 | D72: 2331402.6 | E72: =D72*93.2% -> 2172867.2 | F72: =$D72*1.08% -> 25179.148 | G72: =$D72*1.28% -> 29841.953 | H72: =$D72*1.21% -> 28209.971 | I72: =$D72*1.49% -> 34737.899 | J72: =D72*1.74% -> 40566.405 | K72: =D72 -> 2331402.6 | L72: =E72+J72+I72+H72+G72+F72 -> 2331402.6
A73: Telecentro - Zona coworking - Cliente 7725479 | C73: Debito autom. | D73: 124753.28 | E73: =D73 -> 124753.28 | K73: =D73 -> 124753.28 | L73: =E73+J73+I73+H73+G73+F73 -> 124753.28 | M73: =L73-D73 -> 0 | N73: =K73-D73 -> 0
A74: ADS - Abono de mantenimiento ascensores ENERO del 2025 | C74: Transf 09/01 | D74: 352314.06 | E74: =D74 -> 352314.06 | K74: =D74 -> 352314.06 | L74: =E74+J74+I74+H74+G74+F74 -> 352314.06
A75: Victor Martinez - Abono mantenimiento control de accesos - Mes de ENERO | C75: Transf 12/01 | D75: 40000 | E75: =D75 -> 40000 | K75: =D75 -> 40000 | L75: =E75+J75+I75+H75+G75+F75 -> 40000 | M75: =L75-D75 -> 0 | N75: =K75-D75 -> 0
A76: Victor Martinez - Compra de TAGS | C76: Transf 30/01 | D76: 130000 | E76: =D76 -> 130000 | K76: =D76 -> 130000
A77: Metrogas - Cliente nro. 40000496339 | C77: Transf 07/01 | D77: 993952.65 | E77: =D77*93.2% -> 926363.87 | F77: =$D77*1.08% -> 10734.689 | G77: =$D77*1.28% -> 12722.594 | H77: =$D77*1.21% -> 12026.827 | I77: =$D77*1.49% -> 14809.894 | J77: =D77*1.74% -> 17294.776 | K77: =D77 -> 993952.65 | L77: =E77+J77+I77+H77+G77+F77 -> 993952.65 | M77: =L77-D77 -> 0 | N77: =K77-D77 -> 0
A78: Metrogas - Cliente nro. 40000497007 | C78: Transf 07/01 | D78: 5460.69 | E78: =D78*93.2% -> 5089.3631 | F78: =$D78*1.08% -> 58.975452 | G78: =$D78*1.28% -> 69.896832 | H78: =$D78*1.21% -> 66.074349 | I78: =$D78*1.49% -> 81.364281 | J78: =D78*1.74% -> 95.016006 | K78: =D78 -> 5460.69 | L78: =E78+J78+I78+H78+G78+F78 -> 5460.69 | M78: =L78-D78 -> 0 | N78: =K78-D78 -> 0
A79: Loschi Mantenimiento grupo electrogeno - Abono bimestral | C79: Transf 23/01 | D79: 100000 | E79: =D79*93.2% -> 93200 | F79: =$D79*1.08% -> 1080 | G79: =$D79*1.28% -> 1280 | H79: =$D79*1.21% -> 1210 | I79: =$D79*1.49% -> 1490 | J79: =D79*1.74% -> 1740 | K79: =D79 -> 100000 | L79: =E79+J79+I79+H79+G79+F79 -> 100000 | M79: =L79-D79 -> 0 | N79: =K79-D79 -> 0
A80: TOTAL ABONOS Y SERVICIOS | D80: =SUM(D71:D79) -> 5547236.6 | E80: =SUM(E71:E79) -> 5214025.1 | F80: =SUM(F71:F79) -> 52921.828 | G80: =SUM(G71:G79) -> 62722.167 | H80: =SUM(H71:H79) -> 59292.048 | I80: =SUM(I71:I79) -> 73012.522 | J80: =SUM(J71:J79) -> 85262.945 | K80: =E80+J80+F80+G80+H80+I80 -> 5547236.6 | L80: =IF(D80=K80, "", "Error") | M80: =D80-K80 -> 0
A83: GASTOS VARIOS
A84: Articulos de limpieza - Mes de ENERO | C84: Transf 12/01 | D84: 606800 | E84: =D84*93.2% -> 565537.6 | F84: =$D84*1.08% -> 6553.44 | G84: =$D84*1.28% -> 7767.04 | H84: =$D84*1.21% -> 7342.28 | I84: =$D84*1.49% -> 9041.32 | J84: =D84*1.74% -> 10558.32
A85: Articulos de limpieza para pileta - Mes de ENERO | C85: Transf 12/01 | D85: 216800 | E85: =D85 -> 216800
A86: Compra de Sal Gruesa | C86: Efectivo | D86: 1300 | E86: =D86*93.2% -> 1211.6 | F86: =$D86*1.08% -> 14.04 | G86: =$D86*1.28% -> 16.64 | H86: =$D86*1.21% -> 15.73 | I86: =$D86*1.49% -> 19.37 | J86: =D86*1.74% -> 22.62
A87: Julio Doartero - Emergencia electrica | C87: Transf 07/01 - Efectivo | D87: 350000 | E87: =D87 -> 350000
A88: Servisur - Reparacion lampara colgante transformador 12v, reconexion tablero electronico | C88: Transf 12/01 | D88: 250000 | E88: =D88 -> 250000
A89: Casa Ruan - Fuente de 12V | C89: Transf 12/01 | D89: 32800 | E89: =D89 -> 32800
A90: Alejandro Majnemer - Compra de control para porton | C90: Transf 07/01 | D90: 50000 | E90: =D90 -> 50000
A91: Destapaciones - Camion AySa | C91: Pago Ef. | D91: 60000 | E91: =D91 -> 60000
A92: Destapaciones - Camion AySa | C92: Pago Ef. | D92: 50000 | E92: =D92 -> 50000
A93: Cuello Natalia - Servicio de emergencia - Desobstruccion de colectora cloacal y repaso de tramos de colectora en local 1 y 3. Cuota 1 de 2 | C93: Transf 20/01 | D93: 307200 | E93: =D93 -> 307200
A94: Cuello natalia - Servicio de emergencia - Desobstruccion de colectora cloacal | C94: Transf 20/01 | D94: 191400 | E94: =D94 -> 191400
A95: Cuello Natalia - Desobstruccion de tramo colectora cloacal. Desde local 5 | C95: Transf 20/01 | D95: 95700 | E95: =D95 -> 95700
A96: TOTAL GASTOS VARIOS | D96: =SUM(D84:D95) -> 2212000 | E96: =SUM(E84:E95) -> 2170649.2 | F96: =SUM(F84:F95) -> 6567.48 | G96: =SUM(G84:G95) -> 7783.68 | H96: =SUM(H84:H95) -> 7358.01 | I96: =SUM(I84:I95) -> 9060.69 | J96: =SUM(J84:J95) -> 10580.94 | K96: =E96+J96+F96+G96+H96+I96 -> 2212000 | L96: =IF(D96=K96, "", "Error")
A99: GASTOS DE ADMINISTRACION
A100: RC Adm Cons. CANCIANI, Carolina | B100: MP:1148 | D100: 753700 | E100: =D100*93.2% -> 702448.4 | F100: =$D100*1.08% -> 8139.96 | G100: =$D100*1.28% -> 9647.36 | H100: =$D100*1.21% -> 9119.77 | I100: =$D100*1.49% -> 11230.13 | J100: =D100*1.74% -> 13114.38 | L100: 0CTtubr3
A103: TOTAL GASTOS DE ADMINISTRACION | D103: =SUM(D100:D102) -> 753700 | E103: =SUM(E100:E102) -> 702448.4 | F103: =SUM(F100:F102) -> 8139.96 | G103: =SUM(G100:G102) -> 9647.36 | H103: =SUM(H100:H102) -> 9119.77 | I103: =SUM(I100:I102) -> 11230.13 | J103: =SUM(J100:J102) -> 13114.38 | K103: =E103+J103+F103+G103+H103+I103 -> 753700 | L103: =IF(D103=K103, "", "Error")
A104: Gastos bancarios | D104: =720+151.2+166246.56 -> 167117.76 | E104: =D104*93.2% -> 155753.75 | F104: =$D104*1.08% -> 1804.8718 | G104: =$D104*1.28% -> 2139.1073 | H104: =$D104*1.21% -> 2022.1249 | I104: =$D104*1.49% -> 2490.0546 | J104: =D104*1.74% -> 2907.849
A105: Mantenimiento de cuenta | E105: =D105*93.2% -> 0 | F105: =$D105*1.08% -> 0 | G105: =$D105*1.28% -> 0 | H105: =$D105*1.21% -> 0 | I105: =$D105*1.49% -> 0 | J105: =D105*1.74% -> 0
A106: TOTAL GASTOS BANCARIOS | D106: =SUM(D104:D105) -> 167117.76 | E106: =SUM(E104:E105) -> 155753.75 | F106: =SUM(F104:F105) -> 1804.8718 | G106: =SUM(G104:G105) -> 2139.1073 | H106: =SUM(H104:H105) -> 2022.1249 | I106: =SUM(I104:I105) -> 2490.0546 | J106: =SUM(J104:J105) -> 2907.849 | K106: =E106+J106+F106+G106+H106+I106 -> 167117.76 | L106: =IF(D106=K106, "", "Error")
A108: FONDO DE GASTOS ORDINARIOS | D108: =15667206.09-12343887.13 -> 3323319 | E108: =D108*93.2% -> 3097333.3 | F108: =$D108*1.08% -> 35891.845 | G108: =$D108*1.28% -> 42538.483 | H108: =$D108*1.21% -> 40212.159 | I108: =$D108*1.49% -> 49517.453 | J108: =D108*1.74% -> 57825.75 | K108: =E108+J108+F108+G108+H108+I108 -> 3323319 | L108: =IF(D108=K108, "", "Error")
A110: TOTAL ORDINARIOS | D110: =SUM(D108+D59+D54+D106+D103+D96+D80+D69+D46+D43+D64) -> 15667206 | E110: =SUM(E108+E59+E54+E106+E103+E96+E80+E69+E46+E43+E64) -> 14774831 | F110: =SUM(F108+F59+F54+F106+F103+F96+F80+F69+F46+F43+F64) -> 141730.21 | G110: =SUM(G108+G59+G54+G106+G103+G96+G80+G69+G46+G43+G64) -> 167976.55 | H110: =SUM(H108+H59+H54+H106+H103+H96+H80+H69+H46+H43+H64) -> 158790.33 | I110: =SUM(I108+I59+I54+I106+I103+I96+I80+I69+I46+I43+I64) -> 195535.2 | J110: =SUM(J108+J59+J54+J106+J103+J96+J80+J69+J46+J43+J64) -> 228343.12 | K110: =E110+J110+F110+G110+H110+I110 -> 15667206 | L110: =IF(D110=K110, "", "Error") | M110: =D110-K110 -> 0
A112: Gastos particulares
A113: Control para porton - 4C | B113: Efectivo | C113: 25000
A115: TOTAL | C115: =SUM(C113:C114) -> 25000
A118: GASTOS EXTRAORDINARIOS | E118: UF | F118: LOCAL 1 (1,08%) | G118: LOCAL 2 (1,28%) | H118: LOCAL 3 (1,21%) | I118: LOCAL 4 (1,49%) | J118: LOCAL 5 (1,74%)
E119: =D119 -> 0
A121: TOTAL | D121: =SUM(D119:D120) -> 0 | E121: =SUM(E119:E120) -> 0 | J121: =SUM(J119:J120) -> 0 | L121: =E121+J121 -> 0 | M121: =IF(D121=L121, "", "Error")
A124: GASTOS ORDINARIOS + PREVISION : | B124: =D110 -> 15667206
A125: GASTOS ORDINARIOS SIN PREVISION: | B125: =D110-D108 -> 12343887 | D125: Se recuerda a todos los propietarios que, en caso de producirse la venta o transferencia de una unidad funcional, es obligatorio informar a la Administración los datos de los nuevos titulares. Dicha notificación resulta indispensable para actualizar los registros del consorcio, emitir correctamente las expensas y garantizar que toda comunicación formal llegue a quienes correspondan. La información a presentar deberá incluir al menos: * Nombre y apellido de los nuevos propietarios. * Domicilio de contacto (en caso de ser distinto de la unidad funcional). * Correo electrónico y/o teléfono de contacto. * Copia de la escritura, acta notarial o documentación que acredite la transferencia. Hasta tanto no se reciba la notificación formal, toda comunicación y responsabilidad respecto de la unidad seguirá dirigida al propietario anterior.
A127: CAJA EFECTIVO $ (pesos)
A128: Saldo anterior | B128: -1002261.6
A129: Ingresos | B129: =PRORRATEO!H133 -> 14775654
A130: Egresos Ordinarios | B130: =-B125 -> -12343887
A131: Egresos Extraordinarios | B131: =-D121 -> 0
A132: Dinero sin identificar | B132: =B142 -> 143267
A133: Dinero ingreso SUM | B133: =-B147 -> -120000
...

Sheet PRORRATEO
A1: Las casillas coloreadas en la columna Gastos Par/SUM de color rojo corresponden a multas aplicadas por el uso del SUM. En consecuencia, la unidad funcional involucrada no podrá acceder al uso del mismo por tiempo indeterminado. Por otro lado, las casillas coloreadas en amarillo, corresponden a llaves y las verdes corresponden al mal uso del coworking. | F1: Banco Santander Rio. | K1: SE GASTO: | L1: =RESUMEN!D110-RESUMEN!D108 -> 12343887
F2: CBU: 0720039720000002171436 | K2: SE PRORRATEA EN LAS UF: | M2: 15667206
F3: CTA CTE $ 0039 - 21714/3 FIDEICOMISO 25 DE MAYO 837 LAN 30716676737
C5: IMPORTANTE: Las personas marcadas en color naranja abonaron de forma incorrecta mediante Mercado Pago. A partir de ahora (incluso desde hace meses), ya se encuentra habilitada la cuenta bancaria correspondiente, por lo que todos los pagos deben realizarse exclusivamente a través de dicha cuenta. Los datos de la misma se encuentran justo arriba de este aviso. Quienes abonen por Mercado Pago corren el riesgo de que su pago no sea imputado correctamente.
C9: IMPORTANTE: Quienes estan en violeta NO ha respetado los centavos al abonar. Para la proxima oportunidad, solicitamos que los respeten. | P9: LOCAL 1 | Q9: =RESUMEN!F110 -> 141730.21
P10: LOCAL 2 | Q10: =RESUMEN!G110 -> 167976.55
A11: Piso | B11: Dpto. | C11: UF | D11: Propietario | E11: Inquilinos | F11: (%) | G11: Saldo | H11: Ingreso | I11: SALDO | J11: Expensas extraor. | K11: Expensas ord | L11: SUM/ GASTOS PART | M11: TOTAL A ABONAR HASTA | N11: TOTAL A ABONAR 2DO VTO - DESDE EL | P11: LOCAL 3 | Q11: =RESUMEN!H110 -> 158790.33
P12: LOCAL 4 | Q12: =RESUMEN!I110 -> 195535.2
M13: =RESUMEN!A20 -> VTO 16/02 | N13: =RESUMEN!A20 -> VTO 16/02 | P13: LOCAL 5 | Q13: =RESUMEN!J110 -> 228343.12
A14: conf sup | C14: LOC 1 | D14: Fernandez, Cristian | E14: Gladys ojeda Britez - Exequiel alexis giuliani | F14: 0.0108 | G14: 274719.32 | I14: =G14-H14 -> 274719.32 | J14: 0 | K14: 141730.21 | L14: 0 | M14: =K14+J14+I14+L14 -> 416449.53 | N14: =M14*6% + M14 -> 441436.51
C15: LOC 2 | D15: Fridgi, Guillermo Ariel | F15: 0.013 | G15: 183831.27 | H15: 61277 | I15: =G15-H15 -> 122554.27 | J15: 0 | K15: 167976.55 | L15: 0 | M15: =K15+J15+I15+L15 -> 290530.82 | N15: =M15*6% + M15 -> 307962.67
A16: conf sup | C16: LOC 3 | D16: Schiaffino, Edgardo Angel | E16: Cristina andrea Massa | F16: 0.0121 | G16: 160512.29 | H16: =G16 -> 160512.29 | I16: =G16-H16 -> 0 | J16: 0 | K16: 158790.33 | L16: 0 | M16: =K16+J16+I16+L16 -> 158790.33 | N16: =M16*6% + M16 -> 168317.75
A17: conf sup | C17: LOC 4 | D17: Cordero, Leandro Emanuel - Orona, Victoria | F17: 0.0149 | G17: 551052.92 | I17: =G17-H17 -> 551052.92 | J17: 0 | K17: 195535.2 | L17: 0 | M17: =K17+J17+I17+L17 -> 746588.12 | N17: =M17*6% + M17 -> 791383.4
A18: conf sup | C18: LOC 5 | D18: Orsi, Jose Luis - Fernandez, Cristian Gabriel | F18: 0.0174 | G18: 469159.56 | H18: =G18 -> 469159.56 | I18: =G18-H18 -> 0 | J18: 0 | K18: 228343.12 | L18: 0 | M18: =K18+J18+I18+L18 -> 228343.12 | N18: =M18*6% + M18 -> 242043.71
A19: 3 amb | C19: 2ºA | D19: Franco, Lucas Fabián | F19: 0.0188 | G19: 261193.01 | H19: =G19 -> 261193.01 | I19: =G19-H19 -> 0 | J19: =M$8*F19 -> 0 | K19: =M$2*F19 -> 294543.47 | L19: 0 | M19: =ROUND((K19+J19+I19+L19),0) + O19 -> 294543.01 | N19: =ROUND((M19*6% + M19 ),0) + O19 -> 312216.01 | O19: 0.01 | P19: Constructora: paga ademas del 2A la cochera 25
A20: 1 amb | C20: 2ºB | D20: Martinez, Diego | F20: 0.0084 | G20: 131605.02 | H20: =G20 -> 131605.02 | I20: =G20-H20 -> 0 | J20: =M$8*F20 -> 0 | K20: =M$2*F20 -> 131604.53 | L20: 0 | M20: =ROUND((K20+J20+I20+L20),0) + O20 -> 131605.02 | N20: =ROUND((M20*6% + M20 ),0) + O20 -> 139501.02 | O20: =O19+0.01 -> 0.02
A21: 3 amb | C21: 2ºC | D21: Rodriguez, Carlos Alberto Miguel | F21: 0.0201 | G21: 333806.03 | H21: =G21 -> 333806.03 | I21: =G21-H21 -> 0 | J21: =M$8*F21 -> 0 | K21: =M$2*F21 -> 314910.84 | L21: 20000 | M21: =ROUND((K21+J21+I21+L21),0) + O21 -> 334911.03 | N21: =ROUND((M21*6% + M21 ),0) + O21 -> 355006.03 | O21: =O20+0.01 -> 0.03
A22: 2 amb | C22: 2ºD | D22: Ferraro, José | E22: Matias Cuevas | F22: 0.0094 | G22: 146444.04 | H22: 147222 | I22: =G22-H22 -> -777.96 | J22: =M$8*F22 -> 0 | K22: =M$2*F22 -> 147271.74 | L22: 0 | M22: =ROUND((K22+J22+I22+L22),0) + O22 -> 146494.04 | N22: =ROUND((M22*6% + M22 ),0) + O22 -> 155284.04 | O22: =O21+0.01 -> 0.04 | P22: Matias alejandro ezequiel
A23: 2 amb | C23: 2ºE | D23: Dieci, Matias Orlando | E23: Julieta Damiano/Damiani | F23: 0.0087 | G23: 156305.05 | H23: =19700+136605.05 -> 156305.05 | I23: =G23-H23 -> 0 | J23: =M$8*F23 -> 0 | K23: =M$2*F23 -> 136304.69 | M23: =ROUND((K23+J23+I23+L23),0) + O23 -> 136305.05 | N23: =ROUND((M23*6% + M23 ),0) + O23 -> 144483.05 | O23: =O22+0.01 -> 0.05
A24: 2 amb | C24: 2ºF | D24: Ferraro, Jose | E24: Carolina Massa | F24: 0.0095 | G24: 148838.06 | H24: =G24 -> 148838.06 | I24: =G24-H24 -> 0 | J24: =M$8*F24 -> 0 | K24: =M$2*F24 -> 148838.46 | L24: 0 | M24: =ROUND((K24+J24+I24+L24),0) + O24 -> 148838.06 | N24: =ROUND((M24*6% + M24 ),0) + O24 -> 157768.06 | O24: =O23+0.01 -> 0.06
A25: 3 amb | C25: 3ºA | D25: Ferraro, Jose | E25: Walter Gabriel Ledesma | F25: 0.0165 | G25: 300495.07 | H25: =G25 -> 300495.07 | I25: =G25-H25 -> 0 | J25: =M$8*F25 -> 0 | K25: =M$2*F25 -> 258508.9 | L25: 0 | M25: =ROUND((K25+J25+I25+L25),0) + O25 -> 258509.07 | N25: =ROUND((M25*6% + M25 ),0) + O25 -> 274020.07 | O25: =O24+0.01 -> 0.07
A26: 1 amb | C26: 3ºB | D26: Balduzzi, Stella Maris | F26: 0.0073 | G26: 114371.08 | H26: =G26 -> 114371.08 | I26: =G26-H26 -> 0 | J26: =M$8*F26 -> 0 | K26: =M$2*F26 -> 114370.6 | L26: 20000 | M26: =ROUND((K26+J26+I26+L26),0) + O26 -> 134371.08 | N26: =ROUND((M26*6% + M26 ),0) + O26 -> 142433.08 | O26: =O25+0.01 -> 0.08
A27: 3 amb | C27: 3ºC | D27: Ferraro, Jose | E27: Gustavo Oscar Fernandez | F27: 0.0178 | G27: 535348.09 | H27: =278876+258100 -> 536976 | I27: =G27-H27 -> -1627.91 | J27: =M$8*F27 -> 0 | K27: =M$2*F27 -> 278876.27 | L27: =13000*3 -> 39000 | M27: =ROUND((K27+J27+I27+L27),0) + O27 -> 316248.09 | N27: =ROUND((M27*6% + M27 ),0) + O27 -> 335223.09 | O27: =O26+0.01 -> 0.09
A28: 2 amb | C28: 3ºD | D28: Heredia, Christian | F28: 0.0094 | G28: 133172.1 | H28: =G28 -> 133172.1 | I28: =G28-H28 -> 0 | J28: =M$8*F28 -> 0 | K28: =M$2*F28 -> 147271.74 | L28: 0 | M28: =ROUND((K28+J28+I28+L28),0) + O28 -> 147272.1 | N28: =ROUND((M28*6% + M28 ),0) + O28 -> 156108.1 | O28: =O27+0.01 -> 0.1
A29: 2 amb | C29: 3ºE | D29: Dallorso, Maria Ines - Dallorso, Ana Paula | F29: 0.0087 | G29: 136305.11 | H29: =G29 -> 136305.11 | I29: =G29-H29 -> 0 | J29: =M$8*F29 -> 0 | K29: =M$2*F29 -> 136304.69 | L29: 20000 | M29: =ROUND((K29+J29+I29+L29),0) + O29 -> 156305.11 | N29: =ROUND((M29*6% + M29 ),0) + O29 -> 165683.11 | O29: =O28+0.01 -> 0.11
A30: 2 amb | C30: 3ºF | D30: Ayala, Roberto Adrian | F30: 0.0095 | G30: 666589.12 | I30: =G30-H30 -> 666589.12 | J30: =M$8*F30 -> 0 | K30: =M$2*F30 -> 148838.46 | L30: 0 | M30: =ROUND((K30+J30+I30+L30),0) + O30 -> 815428.12 | N30: =ROUND((M30*6% + M30 ),0) + O30 -> 864354.12 | O30: =O29+0.01 -> 0.12
A31: 3 amb | C31: 4ºA | D31: Barral, Carlos Daniel | F31: 0.0164 | G31: 276942.13 | H31: =G31 -> 276942.13 | I31: =G31-H31 -> 0 | J31: =M$8*F31 -> 0 | K31: =M$2*F31 -> 256942.18 | L31: 0 | M31: =ROUND((K31+J31+I31+L31),0) + O31 -> 256942.13 | N31: =ROUND((M31*6% + M31 ),0) + O31 -> 272359.13 | O31: =O30+0.01 -> 0.13
A32: 1 amb | C32: 4ºB | D32: Sr. Propietario | E32: Liria | F32: 0.0072 | G32: 112804.14 | H32: =G32 -> 112804.14 | I32: =G32-H32 -> 0 | J32: =M$8*F32 -> 0 | K32: =M$2*F32 -> 112803.88 | L32: 0 | M32: =ROUND((K32+J32+I32+L32),0) + O32 -> 112804.14 | N32: =ROUND((M32*6% + M32 ),0) + O32 -> 119572.14 | O32: =O31+0.01 -> 0.14
A33: 3 amb | C33: 4ºC | D33: Osipowicz, Ariel Marcelo | F33: 0.0173 | G33: 271043.15 | H33: =G33 -> 271043.15 | I33: =G33-H33 -> 0 | J33: =M$8*F33 -> 0 | K33: =M$2*F33 -> 271042.67 | L33: 25000 | M33: =ROUND((K33+J33+I33+L33),0) + O33 -> 296043.15 | N33: =ROUND((M33*6% + M33 ),0) + O33 -> 313806.15 | O33: =O32+0.01 -> 0.15
A34: 2 amb | C34: 4ºD | D34: Ruiz, Juana Del Valle | F34: 0.0094 | G34: 139543.16 | H34: =G34 -> 139543.16 | I34: =G34-H34 -> 0 | J34: =M$8*F34 -> 0 | K34: =M$2*F34 -> 147271.74 | L34: 0 | M34: =ROUND((K34+J34+I34+L34),0) + O34 -> 147272.16 | N34: =ROUND((M34*6% + M34 ),0) + O34 -> 156108.16 | O34: =O33+0.01 -> 0.16 | P34: Pablo Amarilla
A35: 2 amb | C35: 4ºE | D35: Ayala, Roberto Adrian | E35: Iara | F35: 0.0087 | G35: 136305.17 | H35: =G35 -> 136305.17 | I35: =G35-H35 -> 0 | J35: =M$8*F35 -> 0 | K35: =M$2*F35 -> 136304.69 | L35: 0 | M35: =ROUND((K35+J35+I35+L35),0) + O35 -> 136305.17 | N35: =ROUND((M35*6% + M35 ),0) + O35 -> 144483.17 | O35: =O34+0.01 -> 0.17
A36: 2 amb | C36: 4ºF | D36: Ayala, Roberto Adrian | F36: 0.0095 | G36: 148838.18 | I36: =G36-H36 -> 148838.18 | J36: =M$8*F36 -> 0 | K36: =M$2*F36 -> 148838.46 | L36: 0 | M36: =ROUND((K36+J36+I36+L36),0) + O36 -> 297677.18 | N36: =ROUND((M36*6% + M36 ),0) + O36 -> 315538.18 | O36: =O35+0.01 -> 0.18
A37: 3 amb | C37: 5ºA | D37: Chehab, Gabriel Adrian | E37: Santiago Rodriguez | F37: 0.0164 | G37: 256942.19 | H37: =G37 -> 256942.19 | I37: =G37-H37 -> 0 | J37: =M$8*F37 -> 0 | K37: =M$2*F37 -> 256942.18 | M37: =ROUND((K37+J37+I37+L37),0) + O37 -> 256942.19 | N37: =ROUND((M37*6% + M37 ),0) + O37 -> 272359.19 | O37: =O36+0.01 -> 0.19 | P37: Cochera 38
A38: 1 amb | C38: 5ºB | D38: Mesa, Mariano | F38: 0.0072 | G38: 112804.2 | H38: =G38 -> 112804.2 | I38: =G38-H38 -> 0 | J38: =M$8*F38 -> 0 | K38: =M$2*F38 -> 112803.88 | L38: 20000 | M38: =ROUND((K38+J38+I38+L38),0) + O38 -> 132804.2 | N38: =ROUND((M38*6% + M38 ),0) + O38 -> 140772.2 | O38: =O37+0.01 -> 0.2
A39: 3 amb | C39: 5ºC | D39: Di Mito, Vicente Argentino - Serantes, Mabel | F39: 0.0173 | G39: 271043.21 | H39: 287306.21 | I39: =G39-H39 -> -16263 | J39: =M$8*F39 -> 0 | K39: =M$2*F39 -> 271042.67 | L39: 0 | M39: =ROUND((K39+J39+I39+L39),0) + O39 -> 254780.21 | N39: =ROUND((M39*6% + M39 ),0) + O39 -> 270067.21 | O39: =O38+0.01 -> 0.21
A40: 2 amb | C40: 5ºD | D40: Ayala, Agustin | F40: 0.0094 | G40: 220907.22 | I40: =G40-H40 -> 220907.22 | J40: =M$8*F40 -> 0 | K40: =M$2*F40 -> 147271.74 | M40: =ROUND((K40+J40+I40+L40),0) + O40 -> 368179.22 | N40: =ROUND((M40*6% + M40 ),0) + O40 -> 390270.22 | O40: =O39+0.01 -> 0.22 | P40: Ayala paga 5D, 5F y 4F
A41: 2 amb | C41: 5ºE | D41: Ayala, Roberto Adrian | F41: 0.0087 | G41: 136305.23 | H41: =G41 -> 136305.23 | I41: =G41-H41 -> 0 | J41: =M$8*F41 -> 0 | K41: =M$2*F41 -> 136304.69 | L41: 0 | M41: =ROUND((K41+J41+I41+L41),0) + O41 -> 136305.23 | N41: =ROUND((M41*6% + M41 ),0) + O41 -> 144484.23 | O41: =O40+0.01 -> 0.23 | P41: COCHERA 31
A42: 2 amb | C42: 5ºF | D42: Ayala, Agustin | F42: 0.0095 | G42: 148838.24 | I42: =G42-H42 -> 148838.24 | J42: =M$8*F42 -> 0 | K42: =M$2*F42 -> 148838.46 | L42: 0 | M42: =ROUND((K42+J42+I42+L42),0) + O42 -> 297677.24 | N42: =ROUND((M42*6% + M42 ),0) + O42 -> 315538.24 | O42: =O41+0.01 -> 0.24
A43: 3 amb | C43: 6ºA | D43: Morandi, Victoria Ayelen | Calvo, Luciano Ezequiel | F43: 0.0164 | G43: 256942.25 | H43: =G43 -> 256942.25 | I43: =G43-H43 -> 0 | J43: =M$8*F43 -> 0 | K43: =M$2*F43 -> 256942.18 | L43: 0 | M43: =ROUND((K43+J43+I43+L43),0) + O43 -> 256942.25 | N43: =ROUND((M43*6% + M43 ),0) + O43 -> 272359.25 | O43: =O42+0.01 -> 0.25
A44: 1 amb | C44: 6ºB | D44: Grizak Ruben | E44: Christian | F44: 0.0072 | G44: 112804.26 | H44: =G44 -> 112804.26 | I44: =G44-H44 -> 0 | J44: =M$8*F44 -> 0 | K44: =M$2*F44 -> 112803.88 | L44: 0 | M44: =ROUND((K44+J44+I44+L44),0) + O44 -> 112804.26 | N44: =ROUND((M44*6% + M44 ),0) + O44 -> 119573.26 | O44: =O43+0.01 -> 0.26
A45: 3 amb | C45: 6ºC | D45: Nuñez Leonel - Corrieri Giuliana | F45: 0.0173 | G45: 271043.27 | H45: =G45 -> 271043.27 | I45: =G45-H45 -> 0 | J45: =M$8*F45 -> 0 | K45: =M$2*F45 -> 271042.67 | L45: 0 | M45: =ROUND((K45+J45+I45+L45),0) + O45 -> 271043.27 | N45: =ROUND((M45*6% + M45 ),0) + O45 -> 287306.27 | O45: =O44+0.01 -> 0.27 | P45: COCHERA 33 | Q45: COCHERA 33
A46: 2 amb | C46: 6ºD | D46: Anchipi, Gaston Nicolas | F46: 0.0094 | G46: 147272.28 | H46: =G46 -> 147272.28 | I46: =G46-H46 -> 0 | J46: =M$8*F46 -> 0 | K46: =M$2*F46 -> 147271.74 | L46: 0 | M46: =ROUND((K46+J46+I46+L46),0) + O46 -> 147272.28 | N46: =ROUND((M46*6% + M46 ),0) + O46 -> 156109.28 | O46: =O45+0.01 -> 0.28
A47: 2 amb | C47: 6ºE | D47: Dieci, Matias Orlando | E47: Gaston Smith | F47: 0.0087 | G47: 136305.29 | I47: =G47-H47 -> 136305.29 | J47: =M$8*F47 -> 0 | K47: =M$2*F47 -> 136304.69 | L47: 0 | M47: =ROUND((K47+J47+I47+L47),0) + O47 -> 272610.29 | N47: =ROUND((M47*6% + M47 ),0) + O47 -> 288967.29 | O47: =O46+0.01 -> 0.29
A48: 2 amb | C48: 6ºF | D48: Mazzia Alexia | F48: 0.0095 | G48: 148838.3 | H48: =G48 -> 148838.3 | I48: =G48-H48 -> 0 | J48: =M$8*F48 -> 0 | K48: =M$2*F48 -> 148838.46 | L48: 0 | M48: =ROUND((K48+J48+I48+L48),0) + O48 -> 148838.3 | N48: =ROUND((M48*6% + M48 ),0) + O48 -> 157769.3 | O48: =O47+0.01 -> 0.3
A49: 3 amb | C49: 7ºA | D49: Campelo, Mariano | F49: 0.0164 | G49: 256942.31 | H49: =G49 -> 256942.31 | I49: =G49-H49 -> 0 | J49: =M$8*F49 -> 0 | K49: =M$2*F49 -> 256942.18 | L49: 0 | M49: =ROUND((K49+J49+I49+L49),0) + O49 -> 256942.31 | N49: =ROUND((M49*6% + M49 ),0) + O49 -> 272359.31 | O49: =O48+0.01 -> 0.31
A50: 1 amb | C50: 7ºB | D50: Paes, Yazmin Luciana | F50: 0.0072 | G50: 127620.32 | H50: =G50 -> 127620.32 | I50: =G50-H50 -> 0 | J50: =M$8*F50 -> 0 | K50: =M$2*F50 -> 112803.88 | M50: =ROUND((K50+J50+I50+L50),0) + O50 -> 112804.32 | N50: =ROUND((M50*6% + M50 ),0) + O50 -> 119573.32 | O50: =O49+0.01 -> 0.32
A51: 3 amb | C51: 7ºC | D51: Gonzalez Fedullo, Roxana y Valeria | F51: 0.0173 | G51: 271043.33 | H51: =G51 -> 271043.33 | I51: =G51-H51 -> 0 | J51: =M$8*F51 -> 0 | K51: =M$2*F51 -> 271042.67 | L51: 0 | M51: =ROUND((K51+J51+I51+L51),0) + O51 -> 271043.33 | N51: =ROUND((M51*6% + M51 ),0) + O51 -> 287306.33 | O51: =O50+0.01 -> 0.33
A52: 2 amb | C52: 7ºD | D52: Solleiro, Carolina Mabel | F52: 0.0094 | G52: 147272.34 | H52: =G52 -> 147272.34 | I52: =G52-H52 -> 0 | J52: =M$8*F52 -> 0 | K52: =M$2*F52 -> 147271.74 | M52: =ROUND((K52+J52+I52+L52),0) + O52 -> 147272.34 | N52: =ROUND((M52*6% + M52 ),0) + O52 -> 156109.34 | O52: =O51+0.01 -> 0.34 | P52: Walter Javier Dimiziunas
A53: 2 amb | C53: 7ºE | D53: Leyes, Javier | F53: 0.0087 | G53: 136305.35 | H53: =G53 -> 136305.35 | I53: =G53-H53 -> 0 | J53: =M$8*F53 -> 0 | K53: =M$2*F53 -> 136304.69 | L53: 0 | M53: =ROUND((K53+J53+I53+L53),0) + O53 -> 136305.35 | N53: =ROUND((M53*6% + M53 ),0) + O53 -> 144484.35 | O53: =O52+0.01 -> 0.35
A54: 2 amb | C54: 7ºF | D54: Puente, Matias | F54: 0.0095 | G54: 122573.36 | H54: =G54 -> 122573.36 | I54: =G54-H54 -> 0 | J54: =M$8*F54 -> 0 | K54: =M$2*F54 -> 148838.46 | L54: 0 | M54: =ROUND((K54+J54+I54+L54),0) + O54 -> 148838.36 | N54: =ROUND((M54*6% + M54 ),0) + O54 -> 157769.36 | O54: =O53+0.01 -> 0.36
A55: 3 amb | C55: 8ºA | D55: Campelo, Mariano | F55: 0.0164 | G55: 256942.37 | H55: =G55 -> 256942.37 | I55: =G55-H55 -> 0 | J55: =M$8*F55 -> 0 | K55: =M$2*F55 -> 256942.18 | L55: 0 | M55: =ROUND((K55+J55+I55+L55),0) + O55 -> 256942.37 | N55: =ROUND((M55*6% + M55 ),0) + O55 -> 272359.37 | O55: =O54+0.01 -> 0.37
A56: 1 amb | C56: 8ºB | D56: Morvillo, Mariana Yanil | E56: Aylen | F56: 0.0072 | G56: 112804.38 | H56: =G56 -> 112804.38 | I56: =G56-H56 -> 0 | J56: =M$8*F56 -> 0 | K56: =M$2*F56 -> 112803.88 | L56: 0 | M56: =ROUND((K56+J56+I56+L56),0) + O56 -> 112804.38 | N56: =ROUND((M56*6% + M56 ),0) + O56 -> 119573.38 | O56: =O55+0.01 -> 0.38
A57: 3 amb | C57: 8ºC | D57: Frontale, Federico Carlos | Celentano, Alejandra Verónica | F57: 0.0173 | G57: 271043.39 | H57: 271043 | I57: =G57-H57 -> 0.39 | J57: =M$8*F57 -> 0 | K57: =M$2*F57 -> 271042.67 | L57: 0 | M57: =ROUND((K57+J57+I57+L57),0) + O57 -> 271043.39 | N57: =ROUND((M57*6% + M57 ),0) + O57 -> 287306.39 | O57: =O56+0.01 -> 0.39
A58: 2 amb | C58: 8ºD | D58: Argul, Sergio Walter - Taboada, María Paz | E58: Nahuel | F58: 0.0094 | G58: 147272.4 | H58: =G58 -> 147272.4 | I58: =G58-H58 -> 0 | J58: =M$8*F58 -> 0 | K58: =M$2*F58 -> 147271.74 | L58: =13000*2 -> 26000 | M58: =ROUND((K58+J58+I58+L58),0) + O58 -> 173272.4 | N58: =ROUND((M58*6% + M58 ),0) + O58 -> 183669.4 | O58: =O57+0.01 -> 0.4
A59: 2 amb | C59: 8ºE | D59: Lorenzo, Sergio | F59: 0.0087 | G59: 136305.41 | H59: =G59 -> 136305.41 | I59: =G59-H59 -> 0 | J59: =M$8*F59 -> 0 | K59: =M$2*F59 -> 136304.69 | L59: 0 | M59: =ROUND((K59+J59+I59+L59),0) + O59 -> 136305.41 | N59: =ROUND((M59*6% + M59 ),0) + O59 -> 144484.41 | O59: =O58+0.01 -> 0.41 | Q59: el de sergio
A60: 2 amb | C60: 8ºF | D60: Arias, Mariana Laura | F60: 0.0095 | G60: 148838.42 | H60: =G60 -> 148838.42 | I60: =G60-H60 -> 0 | J60: =M$8*F60 -> 0 | K60: =M$2*F60 -> 148838.46 | M60: =ROUND((K60+J60+I60+L60),0) + O60 -> 148838.42 | N60: =ROUND((M60*6% + M60 ),0) + O60 -> 157769.42 | O60: =O59+0.01 -> 0.42 | P60: alonso sabrina eugenia
A61: 3 amb | C61: 9ºA | D61: Fanjul, Alejandro Rubén Marcelo | F61: 0.0164 | G61: 256942.43 | H61: =G61 -> 256942.43 | I61: =G61-H61 -> 0 | J61: =M$8*F61 -> 0 | K61: =M$2*F61 -> 256942.18 | L61: 0 | M61: =ROUND((K61+J61+I61+L61),0) + O61 -> 256942.43 | N61: =ROUND((M61*6% + M61 ),0) + O61 -> 272359.43 | O61: =O60+0.01 -> 0.43
A62: 1 amb | C62: 9ºB | D62: Fanjul, Alejandro Rubén Marcelo | F62: 0.0072 | G62: 112804.44 | H62: =G62 -> 112804.44 | I62: =G62-H62 -> 0 | J62: =M$8*F62 -> 0 | K62: =M$2*F62 -> 112803.88 | L62: 0 | M62: =ROUND((K62+J62+I62+L62),0) + O62 -> 112804.44 | N62: =ROUND((M62*6% + M62 ),0) + O62 -> 119573.44 | O62: =O61+0.01 -> 0.44
A63: 3 amb | C63: 9ºC | D63: Franchino, Mauro | F63: 0.0173 | G63: 271043.45 | H63: =G63 -> 271043.45 | I63: =G63-H63 -> 0 | J63: =M$8*F63 -> 0 | K63: =M$2*F63 -> 271042.67 | L63: 0 | M63: =ROUND((K63+J63+I63+L63),0) + O63 -> 271043.45 | N63: =ROUND((M63*6% + M63 ),0) + O63 -> 287306.45 | O63: =O62+0.01 -> 0.45
A64: 2 amb | C64: 9ºD | D64: Cerra, Antonio Osvaldo | E64: Adrian | F64: 0.0094 | G64: 283572.46 | H64: 147272.46 | I64: =G64-H64 -> 136300 | J64: =M$8*F64 -> 0 | K64: =M$2*F64 -> 147271.74 | L64: =13000+K64*0.1 -> 27727.174 | M64: =ROUND((K64+J64+I64+L64),0) + O64 -> 311299.46 | N64: =ROUND((M64*6% + M64 ),0) + O64 -> 329977.46 | O64: =O63+0.01 -> 0.46
A65: 2 amb | C65: 9ºE | D65: Dieci, Matias Orlando | F65: 0.0087 | G65: 144484.47 | H65: =G65 -> 144484.47 | I65: =G65-H65 -> 0 | J65: =M$8*F65 -> 0 | K65: =M$2*F65 -> 136304.69 | L65: 0 | M65: =ROUND((K65+J65+I65+L65),0) + O65 -> 136305.47 | N65: =ROUND((M65*6% + M65 ),0) + O65 -> 144484.47 | O65: =O64+0.01 -> 0.47
A66: 2 amb | C66: 9ºF | D66: Rosales, Rubén Darío | F66: 0.0095 | G66: 167838.48 | H66: 148838.48 | I66: =G66-H66 -> 19000 | J66: =M$8*F66 -> 0 | K66: =M$2*F66 -> 148838.46 | L66: 0 | M66: =ROUND((K66+J66+I66+L66),0) + O66 -> 167838.48 | N66: =ROUND((M66*6% + M66 ),0) + O66 -> 177909.48 | O66: =O65+0.01 -> 0.48
A67: 3 amb | C67: 10ºA | D67: Puisys Guillermo Antonio | F67: 0.0164 | G67: 268942.49 | H67: =G67 -> 268942.49 | I67: =G67-H67 -> 0 | J67: =M$8*F67 -> 0 | K67: =M$2*F67 -> 256942.18 | M67: =ROUND((K67+J67+I67+L67),0) + O67 -> 256942.49 | N67: =ROUND((M67*6% + M67 ),0) + O67 -> 272359.49 | O67: =O66+0.01 -> 0.49
A68: 1 amb | C68: 10ºB | D68: Lange, Gustavo Daniel | F68: 0.0072 | G68: 556636.5 | I68: =G68-H68 -> 556636.5 | J68: =M$8*F68 -> 0 | K68: =M$2*F68 -> 112803.88 | L68: 0 | M68: =ROUND((K68+J68+I68+L68),0) + O68 -> 669440.5 | N68: =ROUND((M68*6% + M68 ),0) + O68 -> 709607.5 | O68: =O67+0.01 -> 0.5
A69: 3 amb | C69: 10ºC | D69: Espósito, Franco Ezequiel | F69: 0.0173 | G69: 271043.51 | H69: =G69 -> 271043.51 | I69: =G69-H69 -> 0 | J69: =M$8*F69 -> 0 | K69: =M$2*F69 -> 271042.67 | L69: 0 | M69: =ROUND((K69+J69+I69+L69),0) + O69 -> 271043.51 | N69: =ROUND((M69*6% + M69 ),0) + O69 -> 287306.51 | O69: =O68+0.01 -> 0.51
A70: 2 amb | C70: 10ºD | D70: Lobato, Lorena - Vega, Maximiliano | F70: 0.0094 | G70: 419357.52 | H70: =G70 -> 419357.52 | I70: =G70-H70 -> 0 | J70: =M$8*F70 -> 0 | K70: =M$2*F70 -> 147271.74 | L70: 0 | M70: =ROUND((K70+J70+I70+L70),0) + O70 -> 147272.52 | N70: =ROUND((M70*6% + M70 ),0) + O70 -> 156109.52 | O70: =O69+0.01 -> 0.52
A71: 2 amb | C71: 10ºE | D71: Sr propietario | F71: 0.0087 | G71: 136305.53 | H71: =G71 -> 136305.53 | I71: =G71-H71 -> 0 | J71: =M$8*F71 -> 0 | K71: =M$2*F71 -> 136304.69 | L71: 20000 | M71: =ROUND((K71+J71+I71+L71),0) + O71 -> 156305.53 | N71: =ROUND((M71*6% + M71 ),0) + O71 -> 165684.53 | O71: =O70+0.01 -> 0.53 | Q71: mariano hecimovic
A72: 2 amb | C72: 10ºF | D72: Ramos, Sergio Eugenio | F72: 0.0095 | G72: 148838.54 | H72: =G72 -> 148838.54 | I72: =G72-H72 -> 0 | J72: =M$8*F72 -> 0 | K72: =M$2*F72 -> 148838.46 | L72: 0 | M72: =ROUND((K72+J72+I72+L72),0) + O72 -> 148838.54 | N72: =ROUND((M72*6% + M72 ),0) + O72 -> 157769.54 | O72: =O71+0.01 -> 0.54
A73: 4 amb | C73: 11ºA/B | D73: Mosquera, Julio Rodolfo | Cuzzolino, Daniela Carol | F73: 0.0235 | G73: 388179.55 | H73: =G73 -> 388179.55 | I73: =G73-H73 -> 0 | J73: =M$8*F73 -> 0 | K73: =M$2*F73 -> 368179.34 | M73: =ROUND((K73+J73+I73+L73),0) + O73 -> 368179.55 | N73: =ROUND((M73*6% + M73 ),0) + O73 -> 390270.55 | O73: =O72+0.01 -> 0.55
A74: 3 amb | C74: 11ºC | D74: Silvestre Villarruel Eduardo | F74: 0.0173 | G74: 271043.56 | H74: =G74 -> 271043.56 | I74: =G74-H74 -> 0 | J74: =M$8*F74 -> 0 | K74: =M$2*F74 -> 271042.67 | L74: 0 | M74: =ROUND((K74+J74+I74+L74),0) + O74 -> 271043.56 | N74: =ROUND((M74*6% + M74 ),0) + O74 -> 287306.56 | O74: =O73+0.01 -> 0.56
A75: 2 amb | C75: 11ºD | D75: Sr. Propietario | F75: 0.0094 | G75: 147272.57 | H75: =G75 -> 147272.57 | I75: =G75-H75 -> 0 | J75: =M$8*F75 -> 0 | K75: =M$2*F75 -> 147271.74 | L75: 0 | M75: =ROUND((K75+J75+I75+L75),0) + O75 -> 147272.57 | N75: =ROUND((M75*6% + M75 ),0) + O75 -> 156109.57 | O75: =O74+0.01 -> 0.57
A76: 2 amb | C76: 11ºE | D76: Argúl, Adrián Norberto | E76: Lara | F76: 0.0087 | G76: 136305.58 | I76: =G76-H76 -> 136305.58 | J76: =M$8*F76 -> 0 | K76: =M$2*F76 -> 136304.69 | L76: 0 | M76: =ROUND((K76+J76+I76+L76),0) + O76 -> 272610.58 | N76: =ROUND((M76*6% + M76 ),0) + O76 -> 288967.58 | O76: =O75+0.01 -> 0.58
A77: 2 amb | C77: 11ºF | D77: Lobato, Lorena - Vega, Maximiliano | F77: 0.0095 | G77: 149007.59 | H77: =G77 -> 149007.59 | I77: =G77-H77 -> 0 | J77: =M$8*F77 -> 0 | K77: =M$2*F77 -> 148838.46 | L77: 0 | M77: =ROUND((K77+J77+I77+L77),0) + O77 -> 148838.59 | N77: =ROUND((M77*6% + M77 ),0) + O77 -> 157769.59 | O77: =O76+0.01 -> 0.59
A78: 4 amb | C78: 12ºA/B | D78: Luciano, Carmen Veronica - Rey, Javier Pablo | F78: 0.0235 | G78: 368179.6 | H78: =G78 -> 368179.6 | I78: =G78-H78 -> 0 | J78: =M$8*F78 -> 0 | K78: =M$2*F78 -> 368179.34 | L78: 0 | M78: =ROUND((K78+J78+I78+L78),0) + O78 -> 368179.6 | N78: =ROUND((M78*6% + M78 ),0) + O78 -> 390270.6 | O78: =O77+0.01 -> 0.6
A79: 3 amb | C79: 12ºC | D79: Hernandez, Marisa Beatriz - Hernandez, Adrian Jose | F79: 0.0173 | G79: 271043.61 | H79: =G79 -> 271043.61 | I79: =G79-H79 -> 0 | J79: =M$8*F79 -> 0 | K79: =M$2*F79 -> 271042.67 | L79: 0 | M79: =ROUND((K79+J79+I79+L79),0) + O79 -> 271043.61 | N79: =ROUND((M79*6% + M79 ),0) + O79 -> 287306.61 | O79: =O78+0.01 -> 0.61
A80: 2 amb | C80: 12ºD | D80: Morini, Micaela | F80: 0.0094 | G80: 408372.62 | I80: =G80-H80 -> 408372.62 | J80: =M$8*F80 -> 0 | K80: =M$2*F80 -> 147271.74 | L80: 0 | M80: =ROUND((K80+J80+I80+L80),0) + O80 -> 555644.62 | N80: =ROUND((M80*6% + M80 ),0) + O80 -> 588983.62 | O80: =O79+0.01 -> 0.62
A81: 2 amb | C81: 12ºE | D81: Armerding, Jorge | E81: Agustina | F81: 0.0087 | G81: 204457.63 | H81: =G81 -> 204457.63 | I81: =G81-H81 -> 0 | J81: =M$8*F81 -> 0 | K81: =M$2*F81 -> 136304.69 | L81: 20000 | M81: =ROUND((K81+J81+I81+L81),0) + O81 -> 156305.63 | N81: =ROUND((M81*6% + M81 ),0) + O81 -> 165684.63 | O81: =O80+0.01 -> 0.63
A82: 2 amb | C82: 12ºF | D82: Bilyj, Josefa Catalina | F82: 0.0095 | G82: 148838.64 | H82: =G82 -> 148838.64 | I82: =G82-H82 -> 0 | J82: =M$8*F82 -> 0 | K82: =M$2*F82 -> 148838.46 | L82: 0 | M82: =ROUND((K82+J82+I82+L82),0) + O82 -> 148838.64 | N82: =ROUND((M82*6% + M82 ),0) + O82 -> 157769.64 | O82: =O81+0.01 -> 0.64 | P82: Laura Quintas Perez
A83: 4 amb | C83: 13ºA/B | D83: Gazzaneo, Francisco | F83: 0.0235 | G83: 368179.65 | H83: =G83 -> 368179.65 | I83: =G83-H83 -> 0 | J83: =M$8*F83 -> 0 | K83: =M$2*F83 -> 368179.34 | L83: 0 | M83: =ROUND((K83+J83+I83+L83),0) + O83 -> 368179.65 | N83: =ROUND((M83*6% + M83 ),0) + O83 -> 390270.65 | O83: =O82+0.01 -> 0.65
A84: 3 amb | C84: 13ºC | D84: Argentino, Javier Leonardo | F84: 0.0173 | G84: 311043.66 | H84: =G84 -> 311043.66 | I84: =G84-H84 -> 0 | J84: =M$8*F84 -> 0 | K84: =M$2*F84 -> 271042.67 | M84: =ROUND((K84+J84+I84+L84),0) + O84 -> 271043.66 | N84: =ROUND((M84*6% + M84 ),0) + O84 -> 287306.66 | O84: =O83+0.01 -> 0.66
A85: 2 amb | C85: 13ºD | D85: Scardigno, Gabriela Susana - Ripoll, Luis Alberto | F85: 0.0094 | G85: 147272.67 | H85: =G85 -> 147272.67 | I85: =G85-H85 -> 0 | J85: =M$8*F85 -> 0 | K85: =M$2*F85 -> 147271.74 | M85: =ROUND((K85+J85+I85+L85),0) + O85 -> 147272.67 | N85: =ROUND((M85*6% + M85 ),0) + O85 -> 156109.67 | O85: =O84+0.01 -> 0.67
A86: 2 amb | C86: 13ºE | D86: Quiñones, Carlos Eduardo | F86: 0.0087 | G86: 136305.68 | H86: =G86 -> 136305.68 | I86: =G86-H86 -> 0 | J86: =M$8*F86 -> 0 | K86: =M$2*F86 -> 136304.69 | L86: 0 | M86: =ROUND((K86+J86+I86+L86),0) + O86 -> 136305.68 | N86: =ROUND((M86*6% + M86 ),0) + O86 -> 144484.68 | O86: =O85+0.01 -> 0.68
A87: 2 amb | C87: 13ºF | D87: Mosquera, José Elias | F87: 0.0095 | G87: 148838.69 | H87: =G87 -> 148838.69 | I87: =G87-H87 -> 0 | J87: =M$8*F87 -> 0 | K87: =M$2*F87 -> 148838.46 | L87: 0 | M87: =ROUND((K87+J87+I87+L87),0) + O87 -> 148838.69 | N87: =ROUND((M87*6% + M87 ),0) + O87 -> 157769.69 | O87: =O86+0.01 -> 0.69
C88: COCH 1 | D88: Osipowicz, Ariel Marcelo | F88: 0.0023 | G88: 36035.7 | H88: =G88 -> 36035.7 | I88: =G88-H88 -> 0 | J88: =M$8*F88 -> 0 | K88: =M$2*F88 -> 36034.574 | L88: 0 | M88: =ROUND((K88+J88+I88+L88),0) + O88 -> 36035.7 | N88: =ROUND((M88*6% + M88 ),0) + O88 -> 38198.7 | O88: =O87+0.01 -> 0.7
C89: COCH 2 | D89: Sr propietario | F89: 0.0023 | G89: 36035.71 | H89: =G89 -> 36035.71 | I89: =G89-H89 -> 0 | J89: =M$8*F89 -> 0 | K89: =M$2*F89 -> 36034.574 | L89: 0 | M89: =ROUND((K89+J89+I89+L89),0) + O89 -> 36035.71 | N89: =ROUND((M89*6% + M89 ),0) + O89 -> 38198.71 | O89: =O88+0.01 -> 0.71
C90: COCH 3 | D90: Paes, Yazmin Luciana | F90: 0.0023 | G90: 38198.72 | H90: =G90 -> 38198.72 | I90: =G90-H90 -> 0 | J90: =M$8*F90 -> 0 | K90: =M$2*F90 -> 36034.574 | L90: 0 | M90: =ROUND((K90+J90+I90+L90),0) + O90 -> 36035.72 | N90: =ROUND((M90*6% + M90 ),0) + O90 -> 38198.72 | O90: =O89+0.01 -> 0.72
C91: COCH 4 | D91: Puisys Guillermo Antonio | F91: 0.0023 | G91: 36035.73 | H91: =G91 -> 36035.73 | I91: =G91-H91 -> 0 | J91: =M$8*F91 -> 0 | K91: =M$2*F91 -> 36034.574 | L91: 0 | M91: =ROUND((K91+J91+I91+L91),0) + O91 -> 36035.73 | N91: =ROUND((M91*6% + M91 ),0) + O91 -> 38198.73 | O91: =O90+0.01 -> 0.73
C92: COCH 5 | D92: Arias, Mariana Laura | F92: 0.0023 | G92: 36035.74 | H92: =G92 -> 36035.74 | I92: =G92-H92 -> 0 | J92: =M$8*F92 -> 0 | K92: =M$2*F92 -> 36034.574 | L92: 0 | M92: =ROUND((K92+J92+I92+L92),0) + O92 -> 36035.74 | N92: =ROUND((M92*6% + M92 ),0) + O92 -> 38198.74 | O92: =O91+0.01 -> 0.74 | P92: alonso sabrina eugenia
C93: COCH 6 | D93: Dimito, Vicente Argentino - Cerantes , Mabel | F93: 0.0023 | G93: 36035.75 | H93: 38198.75 | I93: =G93-H93 -> -2163 | J93: =M$8*F93 -> 0 | K93: =M$2*F93 -> 36034.574 | L93: 0 | M93: =ROUND((K93+J93+I93+L93),0) + O93 -> 33872.75 | N93: =ROUND((M93*6% + M93 ),0) + O93 -> 35905.75 | O93: =O92+0.01 -> 0.75
C94: COCH 7 | D94: Campelo, Mariano | F94: 0.0023 | G94: 36035.76 | H94: =G94 -> 36035.76 | I94: =G94-H94 -> 0 | J94: =M$8*F94 -> 0 | K94: =M$2*F94 -> 36034.574 | L94: 0 | M94: =ROUND((K94+J94+I94+L94),0) + O94 -> 36035.76 | N94: =ROUND((M94*6% + M94 ),0) + O94 -> 38198.76 | O94: =O93+0.01 -> 0.76
C95: COCH 8 | D95: Campelo, Mariano | F95: 0.0023 | G95: 36035.77 | H95: =G95 -> 36035.77 | I95: =G95-H95 -> 0 | J95: =M$8*F95 -> 0 | K95: =M$2*F95 -> 36034.574 | L95: 0 | M95: =ROUND((K95+J95+I95+L95),0) + O95 -> 36035.77 | N95: =ROUND((M95*6% + M95 ),0) + O95 -> 38198.77 | O95: =O94+0.01 -> 0.77
C96: COCH 9 | D96: Gazzaneo, Francisco | F96: 0.0023 | G96: 36035.78 | H96: =G96 -> 36035.78 | I96: =G96-H96 -> 0 | J96: =M$8*F96 -> 0 | K96: =M$2*F96 -> 36034.574 | L96: 0 | M96: =ROUND((K96+J96+I96+L96),0) + O96 -> 36035.78 | N96: =ROUND((M96*6% + M96 ),0) + O96 -> 38198.78 | O96: =O95+0.01 -> 0.78
C97: COCH 10 | D97: Cerra, Antonio Osvaldo | F97: 0.0023 | G97: 177818.79 | I97: =G97-H97 -> 177818.79 | J97: =M$8*F97 -> 0 | K97: =M$2*F97 -> 36034.574 | L97: 0 | M97: =ROUND((K97+J97+I97+L97),0) + O97 -> 213853.79 | N97: =ROUND((M97*6% + M97 ),0) + O97 -> 226685.79 | O97: =O96+0.01 -> 0.79
C98: COCH 11 | D98: Osipowicz, Ariel Marcelo | F98: 0.0023 | G98: 36035.8 | H98: =G98 -> 36035.8 | I98: =G98-H98 -> 0 | J98: =M$8*F98 -> 0 | K98: =M$2*F98 -> 36034.574 | L98: 0 | M98: =ROUND((K98+J98+I98+L98),0) + O98 -> 36035.8 | N98: =ROUND((M98*6% + M98 ),0) + O98 -> 38198.8 | O98: =O97+0.01 -> 0.8
C99: COCH 12 | D99: Dieci, Matias Orlando | F99: 0.0023 | G99: 36035.81 | I99: =G99-H99 -> 36035.81 | J99: =M$8*F99 -> 0 | K99: =M$2*F99 -> 36034.574 | L99: 0 | M99: =ROUND((K99+J99+I99+L99),0) + O99 -> 72070.81 | N99: =ROUND((M99*6% + M99 ),0) + O99 -> 76395.81 | O99: =O98+0.01 -> 0.81
C100: COCH 13 | D100: Scardigno, Gabriela Susana - Ripoli, Luis Alberto | F100: 0.0023 | G100: 36035.82 | H100: =G100 -> 36035.82 | I100: =G100-H100 -> 0 | J100: =M$8*F100 -> 0 | K100: =M$2*F100 -> 36034.574 | L100: 0 | M100: =ROUND((K100+J100+I100+L100),0) + O100 -> 36035.82 | N100: =ROUND((M100*6% + M100 ),0) + O100 -> 38198.82 | O100: =O99+0.01 -> 0.82
C101: COCH 14 | D101: Fontale Federico Carlos - Celentano Alejandra Veronica | F101: 0.0023 | G101: 36035.83 | H101: =G101 -> 36035.83 | I101: =G101-H101 -> 0 | J101: =M$8*F101 -> 0 | K101: =M$2*F101 -> 36034.574 | L101: 0 | M101: =ROUND((K101+J101+I101+L101),0) + O101 -> 36035.83 | N101: =ROUND((M101*6% + M101 ),0) + O101 -> 38198.83 | O101: =O100+0.01 -> 0.83
C102: COCH 15 | D102: Hernandez, Marisa Beatriz - Hernandez, Adrian Jose | F102: 0.0023 | G102: 36035.84 | H102: =G102 -> 36035.84 | I102: =G102-H102 -> 0 | J102: =M$8*F102 -> 0 | K102: =M$2*F102 -> 36034.574 | L102: 0 | M102: =ROUND((K102+J102+I102+L102),0) + O102 -> 36035.84 | N102: =ROUND((M102*6% + M102 ),0) + O102 -> 38198.84 | O102: =O101+0.01 -> 0.84
C103: COCH 16 | D103: Mesa, Mariano | F103: 0.0023 | G103: 36035.85 | H103: =G103 -> 36035.85 | I103: =G103-H103 -> 0 | J103: =M$8*F103 -> 0 | K103: =M$2*F103 -> 36034.574 | L103: 0 | M103: =ROUND((K103+J103+I103+L103),0) + O103 -> 36035.85 | N103: =ROUND((M103*6% + M103 ),0) + O103 -> 38198.85 | O103: =O102+0.01 -> 0.85
C104: COCH 17 | D104: Espósito, Franco Ezequiel | F104: 0.0023 | G104: 36035.86 | H104: =G104 -> 36035.86 | I104: =G104-H104 -> 0 | J104: =M$8*F104 -> 0 | K104: =M$2*F104 -> 36034.574 | L104: 0 | M104: =ROUND((K104+J104+I104+L104),0) + O104 -> 36035.86 | N104: =ROUND((M104*6% + M104 ),0) + O104 -> 38198.86 | O104: =O103+0.01 -> 0.86
...

Sheet ANOTACIONES
