Workbook

Sheet RESUMEN
B2: MAIL: consorcioloria185@gmail.com
B3: CUIT ADMINISTRACION: 27231256879
B4: CBU: 0720740420000001577204 | D4: TELEFONO: 11 5320-2676
A5: LIQUIDACION DE EXPENSAS | B5: ADMINISTRADORA: CAROLINA CANCIANI MP:1148
A6: CUIT DEL EDIFICIO: 30-57464592-8 | B6: PERÍODO: FEBRERO | D6: HORARIOS DE ATENCION: LUNES A VIERNES
A7: CONSORCIO DE PROPIETARIOS DEL EDIFICIO CALLE LORIA 185 | D7: 10 A 16HS - EMERGENCIAS 24HS
B9: VTO 13/03
A14: ESTIMADOS PROPIETARIOS E INQUILINOS: POR FAVOR LOS QUE ABONAN EN PRIMER VENCIMIENTO ABONEN EL MONTO DE PRIMER VENCIMIENTO, ASI AGILIZAN LA LIQUIDACION, RESPETEN LOS CENTAVOS CORRESPONDIENTES A LA UNIDAD FUNCIONAL. ES DE CARÁCTER OBLIGATORIO INFORMAR VIA MAIL LAS EXPENSAS. CASO CONTRARIO SE INFORMARA VIA CARTA DOCUMENTO A LA UNIDAD FUNCIONAL QUE CREEMOS QUE CORRESPONDE, CUYO COSTO SERA IMPUTADO A LA UNIDAD FUNCIONAL SOSPECHADA.
A21: GASTOS ORDINARIOS UNIDADES FUNCIONALES:
A22: HABERES ENCARGADOS
A23: Claudio Sosa Periodo | D23: 872997.6
A24: Retenciones | D24: -216066.92
A25: Redondeo | D25: 0.32
A29: Neto | D29: =SUM(D23:D28) -> 656931
A30: Cabaña Julian Periodo | D30: 675086.75
A33: Retenciones | D33: -167083.97
A34: Redondeo | D34: 0.22
H35: =D35+D36+D37 -> 0
A38: Neto | D38: =SUM(D30:D37) -> 508003
A39: TOTAL SUELDO | E39: =D29+D38 -> 1164934
A40: HONORARIOS
A41: Gustavo Padron | B41: MES DE FEBRERO | D41: 50000
A42: HONORARIOS administracion RC | B42: MES DE FEBRERO | D42: 349599.31 | H42: SUBIDOS EN dic 2024
A43: TOTAL | E43: =SUM(D41:D42) -> 399599.31
A44: SEGUROS
A45: La Holando seguro colectivo - Poliza 595009.8 | D45: 3220.27 | E45: =E46 -> Debito 6/02
A46: Mercantil Andina - Poliza nro 001167435 | D46: 67361.59 | E46: Debito 6/02
A47: TOTAL IMPUESTO | E47: =SUM(D45:D46) -> 70581.86
A48: APORTES Y CONTRIBUCIONES
A49: A.F.I.P | B49: Periodo ENERO | D49: 634480 | E49: Pago 10/2 | G49: EL MES QUE VIENE HAY QUE LICUAR UNA DEUDA DE AFIP
A50: Sindicatos mes de FEBRERO | B50: Suther | D50: 84389 | E50: Debito 13/02
A51: =A50 -> Sindicatos mes de FEBRERO | B51: Fatheryh | D51: 52436.66 | E51: =E50 -> Debito 13/02
A52: =A51 -> Sindicatos mes de FEBRERO | B52: Seracarh | D52: 5826.3 | E52: =E51 -> Debito 13/02
A53: TOTAL Aportes y Contribuciones - Sindicato | E53: =SUM(D49:D52) -> 777131.96
A54: ABONOS Y SERVICIOS
A55: AYSA | B55: Periodo FEBRERO | D55: 1189255.9 | E55: PMC 14/2
A56: METROGAS | B56: Periodo FEBRERO | D56: 7206.55 | E56: Efectivo 5/2
A57: EDESUR PORTERIA | B57: Periodo FEBRERO | D57: 11894.4 | E57: Transf 10/2
A58: EDESUR | B58: =B57 -> Periodo FEBRERO | D58: 483825.04 | E58: Debito 05/02
A59: Telecentro | B59: =B58 -> Periodo FEBRERO | D59: 43063.9 | E59: Efectivo 26/02
A60: Servi Rod ascensores | B60: NO LLEGO FACTURA | D60: 0
A61: Servisur emergencia 5A - 8/2 - se desconecta circuito eletcrico por humedad en pared | D61: 28000 | E61: Transf 11/2
A62: Servisur - cambio de luces de emergencia, colocacion de termica y disyuntor | D62: 320000 | E62: Transf 14/02
A63: Servisur - cambio de cable que abastece de electricidad al automatico del tanque superior, reconexion en el piso 9, reconexion del 5A | D63: 95000 | E63: Transf 2/03
A64: Servisur reemplazo timer hall de entrada | D64: 30000 | E64: Transf 14/02
A65: Fumigacion | D65: 65000 | E65: Transf 10/2
A66: Casa Ruan - Articulos de electricidad | D66: 222500 | E66: Transf 10/2
A67: Tecmo destapaciones - 6A | D67: 33000 | E67: Transf 17/2
A68: Fernando Parra - trabajo realizado dias 8,10,11,12,13,14,15 y 17 de Febrero - sellados de grietas montante, aperturas de paredes, desconexion del 10A, etc | D68: 334500 | E68: Transf 19/02
A69: GRP Energia servicio tecnico - service, cambio de valvulas, reparacion cargador de flote - cuota 1 de 2 | D69: 260000 | E69: Efectivo
A70: Fernando Parra - mano de obra reconexion 5A | D70: 75000 | E70: Transf 23/02
A71: Ferreteria Beta - compra de mensulas, masilla y flexibles | D71: 28700 | E71: Transf 23/02
A72: Casa Ruan compra timer | D72: 20000 | E72: Transf 14/02
A73: Casa Ruan compra de cable para trabajo realizado en tanques | D73: 19600 | E73: Transf 02/03
A75: TOTAL ABONOS Y SERVICIOS | E75: =SUM(D55:D74) -> 3266545.8
A76: GASTOS GENERALES / MANTENIMIENTO
A78: ART DE LIMPIEZA - FEBRERO | D78: 171000 | E78: Transf 10/2
A80: Fotocopias - Periodo FEBRERO | D80: =840+280+18240+1640 -> 21000 | E80: Efectivo
A83: TOTAL | E83: =SUM(D77:D82) -> 192000
A84: GASTOS BANCARIOS
A85: GASTOS BANCARIOS | D85: =582+720+151.2+2839.28+1931.28+8453.87+315+66.15+5736.87+21.61+4903.79+15775.7+8738.84+720+151.2+720+151.2+720+151.2+183.69+5984.12+315+66+858.21+1244.33+6680.93+996+2220+7333.54+1647+1014.39+720+151.2+845.23+644.1+1260+622.2+2840+7455+1263.43+1474.77 -> 98668.33
A86: COMISION POR CUENTA | D86: 35500
A87: TOTAL | E87: =SUM(D85:D86) -> 134168.33
A89: PREVISION ORDINARIA | E89: 1495038.7
A91: TOTAL ORDINARIOS | E91: =(SUM(E32:E89)) -> 7500000
A94: GASTOS EXTRAORDINARIOS UNIDADES FUNCIONALES:
E100: =SUM(D95:D99) -> 0
A103: PREVISION EXTRAORDINARIA | E103: 2000000
A105: TOTAL EXTRAORDINARIOS | E105: =E100+E103 -> 2000000
A107: GASTOS ORDINARIOS + PREVISION : | B107: =E91 -> 7500000
A108: GASTOS ORDINARIOS SIN PREVISION: | B108: =E91-E89 -> 6004961.3
A109: GASTOS EXTRAORDINARIOS SIN PREVISION: | B109: =E105-E103 -> 0
A110: GASTOS EXTRAORDINARIOS CON PREVISION: | B110: =E105 -> 2000000
A117: RESUMEN
A118: Saldo anterior | B118: 752075.62
A119: Ingreso Ordinarias | B119: =PRORRATEO!H81 -> 9062894.1
A120: Ingreso Extraordinarias | B120: ='PRORRATEO (2)'!H81 -> 0
A121: Deposito sin identificar | B121: =B145 -> 260039
A123: Egresos Ordinarios | B123: =-B108 -> -6004961.3
A124: Egresos Extraordinarios | B124: =-(B109) -> 0
A125: TOTAL | B125: =SUM(B118:B124) -> 4070047.4
A129: RESUMEN CAJA
A130: Saldo anterior | B130: 0
A131: Ingresos | B131: 0
A132: Egresos Ordinarios | B132: 0
A133: Egresos Extraordinarios | B133: 0
A134: Saldo final | B134: =SUM(B130:B133) -> 0
A137: DEPOSITOS NO IDENTIFICADOS
C139: 11948.17
C140: 52000
C141: 61209
A142: 12/02 Transferencia UQMS Sociedad Anonima no identificada | B142: 100039
A143: Tranferencia del 13/02 no identificada -Carlo De Egro Fabian | B143: 144000 | C143: 40000
A144: Tranferencia del 13/02 no identificada -Carlo De Egro Fabian | B144: 16000
A145: TOTAL | B145: =SUM(B142:B144) -> 260039

Sheet PRORRATEO
D1: Formas de Pago: | F1: Cuenta corriente Nro. 740-015772/0 Santander
D2: =RESUMEN!B4 -> CBU: 0720740420000001577204 | L2: Gastos Ordinarios: | O2: 7500000
D3: Efectivo | L3: Gastos Extraordinarios: | O3: 2000000
A4: Piso | B4: Dpto. | C4: UF | D4: Propietario | E4: Inquilinos | F4: (%) | G4: Saldo Ord | H4: Ingreso | I4: Pago por | J4: Deuda o Saldo a favor | K4: Interes | L4: Expensas extraor. | M4: Expensas ord. | N4: Gastos part. | O4: Total 1er Vto | P4: Total 2do Vto. | Q4: Total 2do Vto
O5: =RESUMEN!B9 -> VTO 13/03
A6: PB | B6: PB B | C6: 1 | D6: TULA CARLOS (2) | F6: 1.65 | G6: 292821.01 | H6: =200000 -> 200000 | J6: =G6-H6 -> 92821.01 | K6: =IF(J6>0,J6*3%,0) -> 2784.6303 | L6: =O$3*F6% -> 33000 | M6: =O$2*F6% -> 123750 | N6: 0 | O6: =ROUND(SUM(J6:N6),0) + R6 -> 252356.01 | P6: =ROUND(O6*6% + O6,0) + R6 -> 267497.01 | Q6: =ROUND(O6*3%,0) + O6 -> 259927.01 | R6: 0.01
A7: 3º | B7: PB C | C7: =C6+1 -> 2 | D7: COMBRE ALFREDO | F7: 1.16 | G7: 110200.02 | H7: =G7 -> 110200.02 | J7: =G7-H7 -> 0 | K7: =IF(J7>0,J7*3%,0) -> 0 | L7: =O$3*F7% -> 23200 | M7: =O$2*F7% -> 87000 | N7: 0 | O7: =ROUND(SUM(J7:N7),0) + R7 -> 110200.02 | P7: =ROUND(O7*6% + O7,0) + R7 -> 116812.02 | Q7: =ROUND(O7*3%,0) + O7 -> 113506.02 | R7: =R6+0.01 -> 0.02
A8: 3º | B8: PB D | C8: =C7+1 -> 3 | D8: PRGICH FEDERICO | F8: 1.19 | G8: 192314.03 | H8: 198083.03 | J8: =G8-H8 -> -5769 | K8: =IF(J8>0,J8*3%,0) -> 0 | L8: =O$3*F8% -> 23800 | M8: =O$2*F8% -> 89250 | N8: 0 | O8: =ROUND(SUM(J8:N8),0) + R8 -> 107281.03 | P8: =ROUND(O8*6% + O8,0) + R8 -> 113718.03 | Q8: =ROUND(O8*3%,0) + O8 -> 110499.03 | R8: =R7+0.01 -> 0.03
A9: 4º | B9: PB E | C9: =C8+1 -> 4 | D9: SRUGO DAMIAN | F9: 1.22 | G9: 115900.04 | H9: =G9-'PRORRATEO (2)'!H9 -> 115900.04 | J9: =G9-H9 -> 0 | K9: =IF(J9>0,J9*3%,0) -> 0 | L9: =O$3*F9% -> 24400 | M9: =O$2*F9% -> 91500 | N9: 0 | O9: =ROUND(SUM(J9:N9),0) + R9 -> 115900.04 | P9: =ROUND(O9*6% + O9,0) + R9 -> 122854.04 | Q9: =ROUND(O9*3%,0) + O9 -> 119377.04 | R9: =R8+0.01 -> 0.04
A10: 4º | B10: 1-A | C10: =C9+1 -> 5 | D10: ZELANSNY SILVIA | F10: 1.67 | G10: 158650.05 | H10: =108576.05-'PRORRATEO (2)'!H10 -> 108576.05 | J10: =G10-H10 -> 50074 | K10: =IF(J10>0,J10*3%,0) -> 1502.22 | L10: =O$3*F10% -> 33400 | M10: =O$2*F10% -> 125250 | N10: 0 | O10: =ROUND(SUM(J10:N10),0) + R10 -> 210226.05 | P10: =ROUND(O10*6% + O10,0) + R10 -> 222840.05 | Q10: =ROUND(O10*3%,0) + O10 -> 216533.05 | R10: =R9+0.01 -> 0.05
A11: 5º | B11: 1-B | C11: =C10+1 -> 6 | D11: PICO HEBE | F11: 1.71 | G11: 282780.06 | J11: =G11-H11 -> 282780.06 | K11: =IF(J11>0,J11*3%,0) -> 8483.4018 | L11: =O$3*F11% -> 34200 | M11: =O$2*F11% -> 128250 | N11: 0 | O11: =ROUND(SUM(J11:N11),0) + R11 -> 453713.06 | P11: =ROUND(O11*6% + O11,0) + R11 -> 480936.06 | Q11: =ROUND(O11*3%,0) + O11 -> 467324.06 | R11: =R10+0.01 -> 0.06
A12: 5º | B12: 1-C | C12: =C11+1 -> 7 | D12: RAMOS ROSA | F12: 1.13 | G12: 107350.07 | H12: =G12-'PRORRATEO (2)'!H12 -> 107350.07 | J12: =G12-H12 -> 0 | K12: =IF(J12>0,J12*3%,0) -> 0 | L12: =O$3*F12% -> 22600 | M12: =O$2*F12% -> 84750 | N12: 0 | O12: =ROUND(SUM(J12:N12),0) + R12 -> 107350.07 | P12: =ROUND(O12*6% + O12,0) + R12 -> 113791.07 | Q12: =ROUND(O12*3%,0) + O12 -> 110571.07 | R12: =R11+0.01 -> 0.07
A13: 6º | B13: 1-D | C13: =C12+1 -> 8 | D13: MASIMO HUGO | F13: 1.13 | G13: 107350.08 | H13: =110571.08-'PRORRATEO (2)'!H13 -> 110571.08 | J13: =G13-H13 -> -3221 | K13: =IF(J13>0,J13*3%,0) -> 0 | L13: =O$3*F13% -> 22600 | M13: =O$2*F13% -> 84750 | N13: 0 | O13: =ROUND(SUM(J13:N13),0) + R13 -> 104129.08 | P13: =ROUND(O13*6% + O13,0) + R13 -> 110377.08 | Q13: =ROUND(O13*3%,0) + O13 -> 107253.08 | R13: =R12+0.01 -> 0.08
A14: 6º | B14: 1-E | C14: =C13+1 -> 9 | D14: BARONE GERARDO | F14: 1.13 | G14: 107350.09 | H14: =G14-'PRORRATEO (2)'!H14 -> 107350.09 | J14: =G14-H14 -> 0 | K14: =IF(J14>0,J14*3%,0) -> 0 | L14: =O$3*F14% -> 22600 | M14: =O$2*F14% -> 84750 | N14: 0 | O14: =ROUND(SUM(J14:N14),0) + R14 -> 107350.09 | P14: =ROUND(O14*6% + O14,0) + R14 -> 113791.09 | Q14: =ROUND(O14*3%,0) + O14 -> 110571.09 | R14: =R13+0.01 -> 0.09
A15: 7º | B15: 2-A | C15: =C14+1 -> 10 | D15: MONGIELLO CARLOS (2) | F15: 1.67 | G15: 161729.1 | H15: =167000-'PRORRATEO (2)'!H15 -> 167000 | J15: =G15-H15 -> -5270.9 | K15: =IF(J15>0,J15*3%,0) -> 0 | L15: =O$3*F15% -> 33400 | M15: =O$2*F15% -> 125250 | N15: 0 | O15: =ROUND(SUM(J15:N15),0) + R15 -> 153379.1 | P15: =ROUND(O15*6% + O15,0) + R15 -> 162582.1 | Q15: =ROUND(O15*3%,0) + O15 -> 157980.1 | R15: =R14+0.01 -> 0.1
A16: 7º | B16: 2-B | C16: =C15+1 -> 11 | D16: COSTA MONICA | F16: 1.71 | G16: 162450.11 | H16: =167324.11-'PRORRATEO (2)'!H16 -> 167324.11 | J16: =G16-H16 -> -4874 | K16: =IF(J16>0,J16*3%,0) -> 0 | L16: =O$3*F16% -> 34200 | M16: =O$2*F16% -> 128250 | N16: 0 | O16: =ROUND(SUM(J16:N16),0) + R16 -> 157576.11 | P16: =ROUND(O16*6% + O16,0) + R16 -> 167031.11 | Q16: =ROUND(O16*3%,0) + O16 -> 162303.11 | R16: =R15+0.01 -> 0.11
A17: 8º | B17: 2-C | C17: =C16+1 -> 12 | D17: LOPEZ GUILLERMON | F17: 1.13 | G17: 107350.12 | H17: =110000-'PRORRATEO (2)'!H17 -> 110000 | J17: =G17-H17 -> -2649.88 | K17: =IF(J17>0,J17*3%,0) -> 0 | L17: =O$3*F17% -> 22600 | M17: =O$2*F17% -> 84750 | N17: 0 | O17: =ROUND(SUM(J17:N17),0) + R17 -> 104700.12 | P17: =ROUND(O17*6% + O17,0) + R17 -> 110982.12 | Q17: =ROUND(O17*3%,0) + O17 -> 107841.12 | R17: =R16+0.01 -> 0.12
A18: 8º | B18: 2-D | C18: =C17+1 -> 13 | D18: MARTINEZ ADELINA | F18: 1.13 | G18: 182617.13 | H18: 85750.13 | J18: =G18-H18 -> 96867 | K18: =IF(J18>0,J18*3%,0) -> 2906.01 | L18: =O$3*F18% -> 22600 | M18: =O$2*F18% -> 84750 | N18: 0 | O18: =ROUND(SUM(J18:N18),0) + R18 -> 207123.13 | P18: =ROUND(O18*6% + O18,0) + R18 -> 219551.13 | Q18: =ROUND(O18*3%,0) + O18 -> 213337.13 | R18: =R17+0.01 -> 0.13
A19: 9º | B19: 2-E | C19: =C18+1 -> 14 | D19: QUIROGA ALBA | F19: 1.13 | G19: 99126.14 | H19: =100000.14 -> 100000.14 | J19: =G19-H19 -> -874 | K19: =IF(J19>0,J19*3%,0) -> 0 | L19: =O$3*F19% -> 22600 | M19: =O$2*F19% -> 84750 | N19: 0 | O19: =ROUND(SUM(J19:N19),0) + R19 -> 106476.14 | P19: =ROUND(O19*6% + O19,0) + R19 -> 112865.14 | Q19: =ROUND(O19*3%,0) + O19 -> 109670.14 | R19: =R18+0.01 -> 0.14
A20: 9º | B20: 3-A | C20: =C19+1 -> 15 | D20: MADAR MARIANA | F20: 1.67 | G20: 158650.15 | H20: =G20-'PRORRATEO (2)'!H20 -> 158650.15 | J20: =G20-H20 -> 0 | K20: =IF(J20>0,J20*3%,0) -> 0 | L20: =O$3*F20% -> 33400 | M20: =O$2*F20% -> 125250 | N20: 0 | O20: =ROUND(SUM(J20:N20),0) + R20 -> 158650.15 | P20: =ROUND(O20*6% + O20,0) + R20 -> 168169.15 | Q20: =ROUND(O20*3%,0) + O20 -> 163410.15 | R20: =R19+0.01 -> 0.15
A21: 10º | B21: 3-B | C21: =C20+1 -> 16 | D21: PIRES NABAIS | F21: 1.71 | G21: 162450.16 | H21: =G21-'PRORRATEO (2)'!H21 -> 162450.16 | J21: =G21-H21 -> 0 | K21: =IF(J21>0,J21*3%,0) -> 0 | L21: =O$3*F21% -> 34200 | M21: =O$2*F21% -> 128250 | N21: 0 | O21: =ROUND(SUM(J21:N21),0) + R21 -> 162450.16 | P21: =ROUND(O21*6% + O21,0) + R21 -> 172197.16 | Q21: =ROUND(O21*3%,0) + O21 -> 167324.16 | R21: =R20+0.01 -> 0.16
A22: 10º | B22: 3-C | C22: =C21+1 -> 17 | D22: SANABRIA MARIO | F22: 1.13 | G22: 99120.17 | H22: =102094.17-'PRORRATEO (2)'!H22 -> 102094.17 | J22: =G22-H22 -> -2974 | K22: =IF(J22>0,J22*3%,0) -> 0 | L22: =O$3*F22% -> 22600 | M22: =O$2*F22% -> 84750 | N22: 0 | O22: =ROUND(SUM(J22:N22),0) + R22 -> 104376.17 | P22: =ROUND(O22*6% + O22,0) + R22 -> 110639.17 | Q22: =ROUND(O22*3%,0) + O22 -> 107507.17 | R22: =R21+0.01 -> 0.17
A23: 11º | B23: 3-D | C23: =C22+1 -> 18 | D23: PEROTTI | F23: 1.13 | G23: 107350.18 | H23: =G23-'PRORRATEO (2)'!H23 -> 107350.18 | J23: =G23-H23 -> 0 | K23: =IF(J23>0,J23*3%,0) -> 0 | L23: =O$3*F23% -> 22600 | M23: =O$2*F23% -> 84750 | N23: 0 | O23: =ROUND(SUM(J23:N23),0) + R23 -> 107350.18 | P23: =ROUND(O23*6% + O23,0) + R23 -> 113791.18 | Q23: =ROUND(O23*3%,0) + O23 -> 110571.18 | R23: =R22+0.01 -> 0.18
A24: 11º | B24: 3-E | C24: =C23+1 -> 19 | D24: GOITEA ANTONIO | F24: 1.13 | G24: 107350.19 | H24: =G24-'PRORRATEO (2)'!H24 -> 107350.19 | J24: =G24-H24 -> 0 | K24: =IF(J24>0,J24*3%,0) -> 0 | L24: =O$3*F24% -> 22600 | M24: =O$2*F24% -> 84750 | N24: 0 | O24: =ROUND(SUM(J24:N24),0) + R24 -> 107350.19 | P24: =ROUND(O24*6% + O24,0) + R24 -> 113791.19 | Q24: =ROUND(O24*3%,0) + O24 -> 110571.19 | R24: =R23+0.01 -> 0.19
A25: 12º | B25: 4-A | C25: =C24+1 -> 20 | D25: BIDABE LOMO | F25: 1.67 | G25: 158650.2 | H25: =124250.2-'PRORRATEO (2)'!H25 -> 124250.2 | J25: =G25-H25 -> 34400 | K25: =IF(J25>0,J25*3%,0) -> 1032 | L25: =O$3*F25% -> 33400 | M25: =O$2*F25% -> 125250 | N25: 0 | O25: =ROUND(SUM(J25:N25),0) + R25 -> 194082.2 | P25: =ROUND(O25*6% + O25,0) + R25 -> 205727.2 | Q25: =ROUND(O25*3%,0) + O25 -> 199904.2 | R25: =R24+0.01 -> 0.2
A26: 13º | B26: 4-B | C26: =C25+1 -> 21 | D26: SICILIANO GRACIELA (2) | F26: 1.71 | G26: 54094.21 | J26: =G26-H26 -> 54094.21 | K26: =IF(J26>0,J26*3%,0) -> 1622.8263 | L26: =O$3*F26% -> 34200 | M26: =O$2*F26% -> 128250 | N26: 0 | O26: =ROUND(SUM(J26:N26),0) + R26 -> 218167.21 | P26: =ROUND(O26*6% + O26,0) + R26 -> 231257.21 | Q26: =ROUND(O26*3%,0) + O26 -> 224712.21 | R26: =R25+0.01 -> 0.21
A27: 14º | B27: 4-C | C27: =C26+1 -> 22 | D27: SANCHEZ NELIDA | F27: 1.13 | G27: 107350.22 | H27: =G27-'PRORRATEO (2)'!H27 -> 107350.22 | J27: =G27-H27 -> 0 | K27: =IF(J27>0,J27*3%,0) -> 0 | L27: =O$3*F27% -> 22600 | M27: =O$2*F27% -> 84750 | N27: 0 | O27: =ROUND(SUM(J27:N27),0) + R27 -> 107350.22 | P27: =ROUND(O27*6% + O27,0) + R27 -> 113791.22 | Q27: =ROUND(O27*3%,0) + O27 -> 110571.22 | R27: =R26+0.01 -> 0.22
A28: 15º | B28: 4-D | C28: =C27+1 -> 23 | D28: TABOADA MARIA (2) | F28: 1.13 | G28: 182617.23 | J28: =G28-H28 -> 182617.23 | K28: =IF(J28>0,J28*3%,0) -> 5478.5169 | L28: =O$3*F28% -> 22600 | M28: =O$2*F28% -> 84750 | N28: 0 | O28: =ROUND(SUM(J28:N28),0) + R28 -> 295446.23 | P28: =ROUND(O28*6% + O28,0) + R28 -> 313173.23 | Q28: =ROUND(O28*3%,0) + O28 -> 304309.23 | R28: =R27+0.01 -> 0.23
A29: COC | B29: 4-E | C29: =C28+1 -> 24 | D29: BEDOYA BEATRIZ | F29: 1.13 | G29: 383577.24 | H29: =G29 -> 383577.24 | J29: =G29-H29 -> 0 | K29: =IF(J29>0,J29*3%,0) -> 0 | L29: =O$3*F29% -> 22600 | M29: =O$2*F29% -> 84750 | N29: 0 | O29: =ROUND(SUM(J29:N29),0) + R29 -> 107350.24 | P29: =ROUND(O29*6% + O29,0) + R29 -> 113791.24 | Q29: =ROUND(O29*3%,0) + O29 -> 110571.24 | R29: =R28+0.01 -> 0.24
A30: COC | B30: 5-A | C30: =C29+1 -> 25 | D30: RIZOLI VICTOR | F30: 1.67 | G30: 158650.25 | H30: =G30-'PRORRATEO (2)'!H30 -> 158650.25 | J30: =G30-H30 -> 0 | K30: =IF(J30>0,J30*3%,0) -> 0 | L30: =O$3*F30% -> 33400 | M30: =O$2*F30% -> 125250 | N30: 0 | O30: =ROUND(SUM(J30:N30),0) + R30 -> 158650.25 | P30: =ROUND(O30*6% + O30,0) + R30 -> 168169.25 | Q30: =ROUND(O30*3%,0) + O30 -> 163410.25 | R30: =R29+0.01 -> 0.25
A31: COC | B31: 5-B | C31: =C30+1 -> 26 | D31: HOREN KRASNOBRODA | F31: 1.71 | G31: 36751.26 | H31: =210000.26 -> 210000.26 | J31: =G31-H31 -> -173249 | K31: =IF(J31>0,J31*3%,0) -> 0 | L31: =O$3*F31% -> 34200 | M31: =O$2*F31% -> 128250 | N31: 0 | O31: =ROUND(SUM(J31:N31),0) + R31 -> -10798.74 | P31: =ROUND(O31*6% + O31,0) + R31 -> -11446.74 | Q31: =ROUND(O31*3%,0) + O31 -> -11122.74 | R31: =R30+0.01 -> 0.26
A32: COC | B32: 5-C | C32: =C31+1 -> 27 | D32: MUÑOZ HERNAN | F32: 1.13 | G32: 107350.27 | H32: =G32-'PRORRATEO (2)'!H32 -> 107350.27 | J32: =G32-H32 -> 0 | K32: =IF(J32>0,J32*3%,0) -> 0 | L32: =O$3*F32% -> 22600 | M32: =O$2*F32% -> 84750 | N32: 0 | O32: =ROUND(SUM(J32:N32),0) + R32 -> 107350.27 | P32: =ROUND(O32*6% + O32,0) + R32 -> 113791.27 | Q32: =ROUND(O32*3%,0) + O32 -> 110571.27 | R32: =R31+0.01 -> 0.27
A33: COC | B33: 5-D | C33: =C32+1 -> 28 | D33: VASTA NANCY | F33: 1.13 | G33: 182618.28 | H33: 188097.28 | J33: =G33-H33 -> -5479 | K33: =IF(J33>0,J33*3%,0) -> 0 | L33: =O$3*F33% -> 22600 | M33: =O$2*F33% -> 84750 | O33: =ROUND(SUM(J33:N33),0) + R33 -> 101871.28 | P33: =ROUND(O33*6% + O33,0) + R33 -> 107984.28 | Q33: =ROUND(O33*3%,0) + O33 -> 104927.28 | R33: =R32+0.01 -> 0.28
A34: COC | B34: 5-E | C34: =C33+1 -> 29 | D34: TRAVERSA | F34: 1.13 | G34: 105217.29 | H34: =108374.29-'PRORRATEO (2)'!H34 -> 108374.29 | J34: =G34-H34 -> -3157 | K34: =IF(J34>0,J34*3%,0) -> 0 | L34: =O$3*F34% -> 22600 | M34: =O$2*F34% -> 84750 | N34: 0 | O34: =ROUND(SUM(J34:N34),0) + R34 -> 104193.29 | P34: =ROUND(O34*6% + O34,0) + R34 -> 110445.29 | Q34: =ROUND(O34*3%,0) + O34 -> 107319.29 | R34: =R33+0.01 -> 0.29
A35: COC | B35: 6-A | C35: =C34+1 -> 30 | D35: BAFFONI FABIAN | F35: 1.67 | G35: 158650.3 | H35: =G35-'PRORRATEO (2)'!H35 -> 158650.3 | J35: =G35-H35 -> 0 | K35: =IF(J35>0,J35*3%,0) -> 0 | L35: =O$3*F35% -> 33400 | M35: =O$2*F35% -> 125250 | N35: 0 | O35: =ROUND(SUM(J35:N35),0) + R35 -> 158650.3 | P35: =ROUND(O35*6% + O35,0) + R35 -> 168169.3 | Q35: =ROUND(O35*3%,0) + O35 -> 163410.3 | R35: =R34+0.01 -> 0.3
A36: COC | G36: 0 | H36: 0 | J36: =G36-H36 -> 0 | K36: =IF(J36>0,J36*3%,0) -> 0 | L36: =O$3*F36% -> 0 | M36: =O$2*F36% -> 0 | N36: 0 | O36: =ROUND(SUM(J36:N36),0) + R36 -> 0 | P36: =ROUND(O36*6% + O36,0) + R36 -> 0 | Q36: =ROUND(O36*3%,0) + O36 -> 0
A37: COC | B37: 6-B | C37: 31 | D37: PAQUET DE LOPEZ | F37: 1.71 | G37: 159269.31 | H37: =G37-'PRORRATEO (2)'!H37 -> 159269.31 | J37: =G37-H37 -> 0 | K37: =IF(J37>0,J37*3%,0) -> 0 | L37: =O$3*F37% -> 34200 | M37: =O$2*F37% -> 128250 | N37: 0 | O37: =ROUND(SUM(J37:N37),0) + R37 -> 162450.31 | P37: =ROUND(O37*6% + O37,0) + R37 -> 172197.31 | Q37: =ROUND(O37*3%,0) + O37 -> 167324.31 | R37: 0.31
A38: COC | B38: 6-C | C38: =C37+1 -> 32 | D38: BLANCO MABEL | F38: 1.13 | G38: 107350.32 | H38: =G38-'PRORRATEO (2)'!H38 -> 107350.32 | J38: =G38-H38 -> 0 | K38: =IF(J38>0,J38*3%,0) -> 0 | L38: =O$3*F38% -> 22600 | M38: =O$2*F38% -> 84750 | N38: 0 | O38: =ROUND(SUM(J38:N38),0) + R38 -> 107350.32 | P38: =ROUND(O38*6% + O38,0) + R38 -> 113791.32 | Q38: =ROUND(O38*3%,0) + O38 -> 110571.32 | R38: =R37+0.01 -> 0.32
A39: COC | B39: 6-D | C39: =C38+1 -> 33 | D39: TESTA IRENE | F39: 1.13 | G39: 107350.33 | H39: =G39-'PRORRATEO (2)'!H39 -> 107350.33 | J39: =G39-H39 -> 0 | K39: =IF(J39>0,J39*3%,0) -> 0 | L39: =O$3*F39% -> 22600 | M39: =O$2*F39% -> 84750 | N39: 0 | O39: =ROUND(SUM(J39:N39),0) + R39 -> 107350.33 | P39: =ROUND(O39*6% + O39,0) + R39 -> 113791.33 | Q39: =ROUND(O39*3%,0) + O39 -> 110571.33 | R39: =R38+0.01 -> 0.33
A40: COC | B40: 6-E | C40: =C39+1 -> 34 | D40: QUIROGA ENRIQUE | F40: 1.13 | G40: 474364.34 | H40: 276348 | J40: =G40-H40 -> 198016.34 | K40: =IF(J40>0,J40*3%,0) -> 5940.4902 | L40: =O$3*F40% -> 22600 | M40: =O$2*F40% -> 84750 | N40: 0 | O40: =ROUND(SUM(J40:N40),0) + R40 -> 311307.34 | P40: =ROUND(O40*6% + O40,0) + R40 -> 329986.34 | Q40: =ROUND(O40*3%,0) + O40 -> 320646.34 | R40: =R39+0.01 -> 0.34
A41: COC | B41: 7-A | C41: =C40+1 -> 35 | D41: ALVAREZ VERONICA (2) | F41: 1.67 | G41: 262565.35 | H41: =169065.35-'PRORRATEO (2)'!H41 -> 169065.35 | J41: =G41-H41 -> 93500 | K41: =IF(J41>0,J41*3%,0) -> 2805 | L41: =O$3*F41% -> 33400 | M41: =O$2*F41% -> 125250 | N41: 0 | O41: =ROUND(SUM(J41:N41),0) + R41 -> 254955.35 | P41: =ROUND(O41*6% + O41,0) + R41 -> 270253.35 | Q41: =ROUND(O41*3%,0) + O41 -> 262604.35 | R41: =R40+0.01 -> 0.35
B42: 7-B | C42: =C41+1 -> 36 | D42: ROJAS CARMEN | F42: 1.71 | G42: 397331.36 | J42: =G42-H42 -> 397331.36 | K42: =IF(J42>0,J42*3%,0) -> 11919.941 | L42: =O$3*F42% -> 34200 | M42: =O$2*F42% -> 128250 | N42: 0 | O42: =ROUND(SUM(J42:N42),0) + R42 -> 571701.36 | P42: =ROUND(O42*6% + O42,0) + R42 -> 606003.36 | Q42: =ROUND(O42*3%,0) + O42 -> 588852.36 | R42: =R41+0.01 -> 0.36
B43: 7-C | C43: =C42+1 -> 37 | D43: JUCHNO IRENE | F43: 1.13 | G43: 107350.37 | H43: =57000+50350.32-'PRORRATEO (2)'!H43 -> 107350.32 | J43: =G43-H43 -> 0.05 | K43: =IF(J43>0,J43*3%,0) -> 0.0015 | L43: =O$3*F43% -> 22600 | M43: =O$2*F43% -> 84750 | N43: 0 | O43: =ROUND(SUM(J43:N43),0) + R43 -> 107350.37 | P43: =ROUND(O43*6% + O43,0) + R43 -> 113791.37 | Q43: =ROUND(O43*3%,0) + O43 -> 110571.37 | R43: =R42+0.01 -> 0.37
B44: 7-D | C44: =C43+1 -> 38 | D44: URIZAR LUQUES | F44: 1.13 | G44: 107350.38 | J44: =G44-H44 -> 107350.38 | K44: =IF(J44>0,J44*3%,0) -> 3220.5114 | L44: =O$3*F44% -> 22600 | M44: =O$2*F44% -> 84750 | N44: 0 | O44: =ROUND(SUM(J44:N44),0) + R44 -> 217921.38 | P44: =ROUND(O44*6% + O44,0) + R44 -> 230997.38 | Q44: =ROUND(O44*3%,0) + O44 -> 224459.38 | R44: =R43+0.01 -> 0.38
B45: 7-E | C45: =C44+1 -> 39 | D45: RIPA NELLY | F45: 1.13 | G45: 282004.39 | J45: =G45-H45 -> 282004.39 | K45: =IF(J45>0,J45*3%,0) -> 8460.1317 | L45: =O$3*F45% -> 22600 | M45: =O$2*F45% -> 84750 | N45: 0 | O45: =ROUND(SUM(J45:N45),0) + R45 -> 397815.39 | P45: =ROUND(O45*6% + O45,0) + R45 -> 421684.39 | Q45: =ROUND(O45*3%,0) + O45 -> 409749.39 | R45: =R44+0.01 -> 0.39
B46: 8-A | C46: =C45+1 -> 40 | D46: SORIA GODOY | F46: 1.67 | G46: 229439.4 | J46: =G46-H46 -> 229439.4 | K46: =IF(J46>0,J46*3%,0) -> 6883.182 | L46: =O$3*F46% -> 33400 | M46: =O$2*F46% -> 125250 | N46: 0 | O46: =ROUND(SUM(J46:N46),0) + R46 -> 394973.4 | P46: =ROUND(O46*6% + O46,0) + R46 -> 418672.4 | Q46: =ROUND(O46*3%,0) + O46 -> 406822.4 | R46: =R45+0.01 -> 0.4
B47: 8-B | C47: =C46+1 -> 41 | D47: D´ALOIA GABRIELA (2) | F47: 1.71 | G47: 162450.41 | H47: =167324.41-'PRORRATEO (2)'!H47 -> 167324.41 | J47: =G47-H47 -> -4874 | K47: =IF(J47>0,J47*3%,0) -> 0 | L47: =O$3*F47% -> 34200 | M47: =O$2*F47% -> 128250 | N47: 0 | O47: =ROUND(SUM(J47:N47),0) + R47 -> 157576.41 | P47: =ROUND(O47*6% + O47,0) + R47 -> 167031.41 | Q47: =ROUND(O47*3%,0) + O47 -> 162303.41 | R47: =R46+0.01 -> 0.41
B48: 8-C | C48: =C47+1 -> 42 | D48: MIÑO GRACIELA (2) | F48: 1.13 | G48: 105158.42 | H48: 73075.42 | J48: =G48-H48 -> 32083 | K48: =IF(J48>0,J48*3%,0) -> 962.49 | L48: =O$3*F48% -> 22600 | M48: =O$2*F48% -> 84750 | N48: 0 | O48: =ROUND(SUM(J48:N48),0) + R48 -> 140395.42 | P48: =ROUND(O48*6% + O48,0) + R48 -> 148819.42 | Q48: =ROUND(O48*3%,0) + O48 -> 144607.42 | R48: =R47+0.01 -> 0.42
B49: 8-D | C49: =C48+1 -> 43 | D49: CATALANO CLAUDIA | F49: 1.13 | G49: 107350.43 | H49: =G49-'PRORRATEO (2)'!H49 -> 107350.43 | J49: =G49-H49 -> 0 | K49: =IF(J49>0,J49*3%,0) -> 0 | L49: =O$3*F49% -> 22600 | M49: =O$2*F49% -> 84750 | N49: 0 | O49: =ROUND(SUM(J49:N49),0) + R49 -> 107350.43 | P49: =ROUND(O49*6% + O49,0) + R49 -> 113791.43 | Q49: =ROUND(O49*3%,0) + O49 -> 110571.43 | R49: =R48+0.01 -> 0.43
B50: 8-E | C50: =C49+1 -> 44 | D50: ROCA MARISA | F50: 1.13 | G50: 107350.44 | H50: =G50-'PRORRATEO (2)'!H50 -> 107350.44 | J50: =G50-H50 -> 0 | K50: =IF(J50>0,J50*3%,0) -> 0 | L50: =O$3*F50% -> 22600 | M50: =O$2*F50% -> 84750 | N50: 0 | O50: =ROUND(SUM(J50:N50),0) + R50 -> 107350.44 | P50: =ROUND(O50*6% + O50,0) + R50 -> 113791.44 | Q50: =ROUND(O50*3%,0) + O50 -> 110571.44 | R50: =R49+0.01 -> 0.44
B51: 9-A | C51: =C50+1 -> 45 | D51: TINEO | F51: 1.67 | G51: 158650.45 | H51: =G51-'PRORRATEO (2)'!H51 -> 158650.45 | J51: =G51-H51 -> 0 | K51: =IF(J51>0,J51*3%,0) -> 0 | L51: =O$3*F51% -> 33400 | M51: =O$2*F51% -> 125250 | N51: 0 | O51: =ROUND(SUM(J51:N51),0) + R51 -> 158650.45 | P51: =ROUND(O51*6% + O51,0) + R51 -> 168169.45 | Q51: =ROUND(O51*3%,0) + O51 -> 163410.45 | R51: =R50+0.01 -> 0.45
B52: 9-B | C52: =C51+1 -> 46 | D52: MAZZEO CECILIA | F52: 1.71 | G52: 162450.46 | H52: =G52-'PRORRATEO (2)'!H52 -> 162450.46 | J52: =G52-H52 -> 0 | K52: =IF(J52>0,J52*3%,0) -> 0 | L52: =O$3*F52% -> 34200 | M52: =O$2*F52% -> 128250 | N52: 0 | O52: =ROUND(SUM(J52:N52),0) + R52 -> 162450.46 | P52: =ROUND(O52*6% + O52,0) + R52 -> 172197.46 | Q52: =ROUND(O52*3%,0) + O52 -> 167324.46 | R52: =R51+0.01 -> 0.46
B53: 9-C | C53: =C52+1 -> 47 | D53: GARCIA JORGE | F53: 1.13 | G53: 107350.47 | H53: =G53-'PRORRATEO (2)'!H53 -> 107350.47 | J53: =G53-H53 -> 0 | K53: =IF(J53>0,J53*3%,0) -> 0 | L53: =O$3*F53% -> 22600 | M53: =O$2*F53% -> 84750 | N53: 0 | O53: =ROUND(SUM(J53:N53),0) + R53 -> 107350.47 | P53: =ROUND(O53*6% + O53,0) + R53 -> 113791.47 | Q53: =ROUND(O53*3%,0) + O53 -> 110571.47 | R53: =R52+0.01 -> 0.47
B54: 9-D | C54: =C53+1 -> 48 | D54: ROSSI NORMA | F54: 1.13 | G54: 105220.48 | H54: =108377.48-'PRORRATEO (2)'!H54 -> 108377.48 | J54: =G54-H54 -> -3157 | K54: =IF(J54>0,J54*3%,0) -> 0 | L54: =O$3*F54% -> 22600 | M54: =O$2*F54% -> 84750 | N54: 0 | O54: =ROUND(SUM(J54:N54),0) + R54 -> 104193.48 | P54: =ROUND(O54*6% + O54,0) + R54 -> 110445.48 | Q54: =ROUND(O54*3%,0) + O54 -> 107319.48 | R54: =R53+0.01 -> 0.48
B55: 9-E | C55: =C54+1 -> 49 | D55: AGNESE PEDRO | F55: 1.13 | G55: 107350.49 | H55: =G55-'PRORRATEO (2)'!H55 -> 107350.49 | J55: =G55-H55 -> 0 | K55: =IF(J55>0,J55*3%,0) -> 0 | L55: =O$3*F55% -> 22600 | M55: =O$2*F55% -> 84750 | N55: 0 | O55: =ROUND(SUM(J55:N55),0) + R55 -> 107350.49 | P55: =ROUND(O55*6% + O55,0) + R55 -> 113792.49 | Q55: =ROUND(O55*3%,0) + O55 -> 110571.49 | R55: =R54+0.01 -> 0.49
B56: 10-A | C56: =C55+1 -> 50 | D56: ABDALA (1) | F56: 1.67 | G56: 158641.5 | H56: 166000 | J56: =G56-H56 -> -7358.5 | K56: =IF(J56>0,J56*3%,0) -> 0 | L56: =O$3*F56% -> 33400 | M56: =O$2*F56% -> 125250 | N56: 0 | O56: =ROUND(SUM(J56:N56),0) + R56 -> 151292.5 | P56: =ROUND(O56*6% + O56,0) + R56 -> 160370.5 | Q56: =ROUND(O56*3%,0) + O56 -> 155831.5 | R56: =R55+0.01 -> 0.5
B57: 10-B | C57: =C56+1 -> 51 | D57: DEL RIO GUSTAVO | F57: 1.71 | G57: 162450.51 | J57: =G57-H57 -> 162450.51 | K57: =IF(J57>0,J57*3%,0) -> 4873.5153 | L57: =O$3*F57% -> 34200 | M57: =O$2*F57% -> 128250 | N57: 0 | O57: =ROUND(SUM(J57:N57),0) + R57 -> 329774.51 | P57: =ROUND(O57*6% + O57,0) + R57 -> 349561.51 | Q57: =ROUND(O57*3%,0) + O57 -> 339667.51 | R57: =R56+0.01 -> 0.51
B58: 10-C | C58: =C57+1 -> 52 | D58: MIGLIORISI ANDREA | F58: 1.13 | G58: 107350.52 | H58: =G58-'PRORRATEO (2)'!H58 -> 107350.52 | J58: =G58-H58 -> 0 | K58: =IF(J58>0,J58*3%,0) -> 0 | L58: =O$3*F58% -> 22600 | M58: =O$2*F58% -> 84750 | N58: 0 | O58: =ROUND(SUM(J58:N58),0) + R58 -> 107350.52 | P58: =ROUND(O58*6% + O58,0) + R58 -> 113792.52 | Q58: =ROUND(O58*3%,0) + O58 -> 110571.52 | R58: =R57+0.01 -> 0.52
B59: 10-D | C59: =C58+1 -> 53 | D59: EHGATNER ANA | F59: 1.13 | G59: 107350.53 | H59: =G59-'PRORRATEO (2)'!H59 -> 107350.53 | J59: =G59-H59 -> 0 | K59: =IF(J59>0,J59*3%,0) -> 0 | L59: =O$3*F59% -> 22600 | M59: =O$2*F59% -> 84750 | N59: 0 | O59: =ROUND(SUM(J59:N59),0) + R59 -> 107350.53 | P59: =ROUND(O59*6% + O59,0) + R59 -> 113792.53 | Q59: =ROUND(O59*3%,0) + O59 -> 110571.53 | R59: =R58+0.01 -> 0.53
B60: 10-E | C60: =C59+1 -> 54 | D60: DEBENEDETTI C | F60: 1.13 | G60: 107350.54 | H60: =G60-'PRORRATEO (2)'!H60 -> 107350.54 | J60: =G60-H60 -> 0 | K60: =IF(J60>0,J60*3%,0) -> 0 | L60: =O$3*F60% -> 22600 | M60: =O$2*F60% -> 84750 | N60: 0 | O60: =ROUND(SUM(J60:N60),0) + R60 -> 107350.54 | P60: =ROUND(O60*6% + O60,0) + R60 -> 113792.54 | Q60: =ROUND(O60*3%,0) + O60 -> 110571.54 | R60: =R59+0.01 -> 0.54
B61: 11-A | C61: =C60+1 -> 55 | D61: MENDIBURU JORGE | F61: 1.67 | G61: 158650.55 | H61: =G61-'PRORRATEO (2)'!H61 -> 158650.55 | J61: =G61-H61 -> 0 | K61: =IF(J61>0,J61*3%,0) -> 0 | L61: =O$3*F61% -> 33400 | M61: =O$2*F61% -> 125250 | O61: =ROUND(SUM(J61:N61),0) + R61 -> 158650.55 | P61: =ROUND(O61*6% + O61,0) + R61 -> 168170.55 | Q61: =ROUND(O61*3%,0) + O61 -> 163410.55 | R61: =R60+0.01 -> 0.55
B62: 11-B | C62: =C61+1 -> 56 | D62: GALLUCCI CARMELA | F62: 1.71 | G62: 170321.56 | J62: =G62-H62 -> 170321.56 | K62: =IF(J62>0,J62*3%,0) -> 5109.6468 | L62: =O$3*F62% -> 34200 | M62: =O$2*F62% -> 128250 | N62: 0 | O62: =ROUND(SUM(J62:N62),0) + R62 -> 337881.56 | P62: =ROUND(O62*6% + O62,0) + R62 -> 358154.56 | Q62: =ROUND(O62*3%,0) + O62 -> 348017.56 | R62: =R61+0.01 -> 0.56
B63: 11-C | C63: =C62+1 -> 57 | D63: CABAÑAS MARIA SOLEDAD | F63: 1.13 | G63: 107350.57 | H63: =G63-'PRORRATEO (2)'!H63 -> 107350.57 | J63: =G63-H63 -> 0 | K63: =IF(J63>0,J63*3%,0) -> 0 | L63: =O$3*F63% -> 22600 | M63: =O$2*F63% -> 84750 | N63: 0 | O63: =ROUND(SUM(J63:N63),0) + R63 -> 107350.57 | P63: =ROUND(O63*6% + O63,0) + R63 -> 113792.57 | Q63: =ROUND(O63*3%,0) + O63 -> 110571.57 | R63: =R62+0.01 -> 0.57
B64: 11-D | C64: =C63+1 -> 58 | D64: GUARINO | F64: 1.13 | G64: 105158.58 | H64: =108313.58-'PRORRATEO (2)'!H64 -> 108313.58 | J64: =G64-H64 -> -3155 | K64: =IF(J64>0,J64*3%,0) -> 0 | L64: =O$3*F64% -> 22600 | M64: =O$2*F64% -> 84750 | N64: 0 | O64: =ROUND(SUM(J64:N64),0) + R64 -> 104195.58 | P64: =ROUND(O64*6% + O64,0) + R64 -> 110447.58 | Q64: =ROUND(O64*3%,0) + O64 -> 107321.58 | R64: =R63+0.01 -> 0.58
B65: 11-E | C65: =C64+1 -> 59 | D65: MARQUEZ VERONICA | F65: 1.13 | G65: 184810.59 | H65: =G65 -> 184810.59 | J65: =G65-H65 -> 0 | K65: =IF(J65>0,J65*3%,0) -> 0 | L65: =O$3*F65% -> 22600 | M65: =O$2*F65% -> 84750 | N65: 0 | O65: =ROUND(SUM(J65:N65),0) + R65 -> 107350.59 | P65: =ROUND(O65*6% + O65,0) + R65 -> 113792.59 | Q65: =ROUND(O65*3%,0) + O65 -> 110571.59 | R65: =R64+0.01 -> 0.59
B66: 12-A | C66: =C65+1 -> 60 | D66: BRAU HECTOR | F66: 1.67 | G66: 158650.6 | H66: =G66-'PRORRATEO (2)'!H66 -> 158650.6 | J66: =G66-H66 -> 0 | K66: =IF(J66>0,J66*3%,0) -> 0 | L66: =O$3*F66% -> 33400 | M66: =O$2*F66% -> 125250 | N66: 0 | O66: =ROUND(SUM(J66:N66),0) + R66 -> 158650.6 | P66: =ROUND(O66*6% + O66,0) + R66 -> 168170.6 | Q66: =ROUND(O66*3%,0) + O66 -> 163410.6 | R66: =R65+0.01 -> 0.6
B67: 12-B | C67: =C66+1 -> 61 | D67: ZERBA MARCELO | F67: 1.71 | G67: 162450.61 | J67: =G67-H67 -> 162450.61 | K67: =IF(J67>0,J67*3%,0) -> 4873.5183 | L67: =O$3*F67% -> 34200 | M67: =O$2*F67% -> 128250 | N67: 0 | O67: =ROUND(SUM(J67:N67),0) + R67 -> 329774.61 | P67: =ROUND(O67*6% + O67,0) + R67 -> 349561.61 | Q67: =ROUND(O67*3%,0) + O67 -> 339667.61 | R67: =R66+0.01 -> 0.61
B68: 12-C | C68: =C67+1 -> 62 | D68: VERMINETTI | F68: 1.13 | G68: 105220.62 | H68: =108377.62-'PRORRATEO (2)'!H68 -> 108377.62 | J68: =G68-H68 -> -3157 | K68: =IF(J68>0,J68*3%,0) -> 0 | L68: =O$3*F68% -> 22600 | M68: =O$2*F68% -> 84750 | N68: 0 | O68: =ROUND(SUM(J68:N68),0) + R68 -> 104193.62 | P68: =ROUND(O68*6% + O68,0) + R68 -> 110445.62 | Q68: =ROUND(O68*3%,0) + O68 -> 107319.62 | R68: =R67+0.01 -> 0.62
B69: 12-D | C69: =C68+1 -> 63 | D69: RIQUELME | F69: 1.13 | G69: 106051.63 | H69: =G69 -> 106051.63 | J69: =G69-H69 -> 0 | K69: =IF(J69>0,J69*3%,0) -> 0 | L69: =O$3*F69% -> 22600 | M69: =O$2*F69% -> 84750 | N69: 0 | O69: =ROUND(SUM(J69:N69),0) + R69 -> 107350.63 | P69: =ROUND(O69*6% + O69,0) + R69 -> 113792.63 | Q69: =ROUND(O69*3%,0) + O69 -> 110571.63 | R69: =R68+0.01 -> 0.63
B70: 12-E | C70: =C69+1 -> 64 | D70: RODRIGUEZ NESTOR | F70: 1.13 | G70: 107350.64 | H70: =G70-'PRORRATEO (2)'!H70 -> 107350.64 | J70: =G70-H70 -> 0 | K70: =IF(J70>0,J70*3%,0) -> 0 | L70: =O$3*F70% -> 22600 | M70: =O$2*F70% -> 84750 | N70: 0 | O70: =ROUND(SUM(J70:N70),0) + R70 -> 107350.64 | P70: =ROUND(O70*6% + O70,0) + R70 -> 113792.64 | Q70: =ROUND(O70*3%,0) + O70 -> 110571.64 | R70: =R69+0.01 -> 0.64
B71: 13-A | C71: =C70+1 -> 65 | D71: ZIMERMANN LEON (2) | F71: 1.67 | G71: 474447.65 | H71: =315800.65+158650.65-'PRORRATEO (2)'!H71 -> 474451.3 | J71: =G71-H71 -> -3.65 | K71: =IF(J71>0,J71*3%,0) -> 0 | L71: =O$3*F71% -> 33400 | M71: =O$2*F71% -> 125250 | N71: 0 | O71: =ROUND(SUM(J71:N71),0) + R71 -> 158646.65 | P71: =ROUND(O71*6% + O71,0) + R71 -> 168165.65 | Q71: =ROUND(O71*3%,0) + O71 -> 163405.65 | R71: =R70+0.01 -> 0.65
B72: 13-B | C72: =C71+1 -> 66 | D72: DE GRACIA | F72: 1.71 | G72: 159132.66 | H72: =163906.66-'PRORRATEO (2)'!H72 -> 163906.66 | J72: =G72-H72 -> -4774 | K72: =IF(J72>0,J72*3%,0) -> 0 | L72: =O$3*F72% -> 34200 | M72: =O$2*F72% -> 128250 | N72: 0 | O72: =ROUND(SUM(J72:N72),0) + R72 -> 157676.66 | P72: =ROUND(O72*6% + O72,0) + R72 -> 167137.66 | Q72: =ROUND(O72*3%,0) + O72 -> 162406.66 | R72: =R71+0.01 -> 0.66
B73: 13-C | C73: =C72+1 -> 67 | D73: LAUMAN JOSE | F73: 1.13 | G73: 110571.67 | H73: =G73-'PRORRATEO (2)'!H73 -> 110571.67 | J73: =G73-H73 -> 0 | K73: =IF(J73>0,J73*3%,0) -> 0 | L73: =O$3*F73% -> 22600 | M73: =O$2*F73% -> 84750 | N73: 0 | O73: =ROUND(SUM(J73:N73),0) + R73 -> 107350.67 | P73: =ROUND(O73*6% + O73,0) + R73 -> 113792.67 | Q73: =ROUND(O73*3%,0) + O73 -> 110571.67 | R73: =R72+0.01 -> 0.67
B74: 13-D | C74: =C73+1 -> 68 | D74: MARENZI MARIA | F74: 1.13 | G74: 107350.68 | H74: =G74-'PRORRATEO (2)'!H74 -> 107350.68 | J74: =G74-H74 -> 0 | K74: =IF(J74>0,J74*3%,0) -> 0 | L74: =O$3*F74% -> 22600 | M74: =O$2*F74% -> 84750 | N74: 0 | O74: =ROUND(SUM(J74:N74),0) + R74 -> 107350.68 | P74: =ROUND(O74*6% + O74,0) + R74 -> 113792.68 | Q74: =ROUND(O74*3%,0) + O74 -> 110571.68 | R74: =R73+0.01 -> 0.68
B75: 13-E | C75: =C74+1 -> 69 | D75: DI SERA VANESA | F75: 1.13 | G75: 105220.69 | H75: =108377.69-'PRORRATEO (2)'!H75 -> 108377.69 | J75: =G75-H75 -> -3157 | K75: =IF(J75>0,J75*3%,0) -> 0 | L75: =O$3*F75% -> 22600 | M75: =O$2*F75% -> 84750 | N75: 0 | O75: =ROUND(SUM(J75:N75),0) + R75 -> 104193.69 | P75: =ROUND(O75*6% + O75,0) + R75 -> 110445.69 | Q75: =ROUND(O75*3%,0) + O75 -> 107319.69 | R75: =R74+0.01 -> 0.69
B76: 14-A | C76: =C75+1 -> 70 | D76: GUASTAVINO ELSA | F76: 1.67 | G76: 362587.7 | H76: =G76 -> 362587.7 | J76: =G76-H76 -> 0 | K76: =IF(J76>0,J76*3%,0) -> 0 | L76: =O$3*F76% -> 33400 | M76: =O$2*F76% -> 125250 | N76: 0 | O76: =ROUND(SUM(J76:N76),0) + R76 -> 158650.7 | P76: =ROUND(O76*6% + O76,0) + R76 -> 168170.7 | Q76: =ROUND(O76*3%,0) + O76 -> 163410.7 | R76: =R75+0.01 -> 0.7
B77: 14-B | C77: =C76+1 -> 71 | D77: RODRIGUEZ CARLOS | F77: 1.71 | G77: 162450.71 | H77: =G77-'PRORRATEO (2)'!H77 -> 162450.71 | J77: =G77-H77 -> 0 | K77: =IF(J77>0,J77*3%,0) -> 0 | L77: =O$3*F77% -> 34200 | M77: =O$2*F77% -> 128250 | N77: 0 | O77: =ROUND(SUM(J77:N77),0) + R77 -> 162450.71 | P77: =ROUND(O77*6% + O77,0) + R77 -> 172198.71 | Q77: =ROUND(O77*3%,0) + O77 -> 167324.71 | R77: =R76+0.01 -> 0.71
B78: 14-C | C78: =C77+1 -> 72 | D78: FERNANDEZ MONICA (EN JUICIO) | F78: 1.13 | G78: 2494064.7 | H78: 0 | J78: =G78-H78 -> 2494064.7 | K78: =IF(J78>0,J78*3%,0) -> 74821.942 | L78: =O$3*F78% -> 22600 | M78: =O$2*F78% -> 84750 | N78: 0 | O78: =ROUND(SUM(J78:N78),0) + R78 -> 2676237.7 | P78: =ROUND(O78*6% + O78,0) + R78 -> 2836812.7 | Q78: =ROUND(O78*3%,0) + O78 -> 2756524.7 | R78: =R77+0.01 -> 0.72
B79: 14-D | C79: =C78+1 -> 73 | D79: DE PAVIK ANGELA | F79: 1.13 | G79: 38624.73 | H79: =40000-'PRORRATEO (2)'!H79 -> 40000 | J79: =G79-H79 -> -1375.27 | K79: =IF(J79>0,J79*3%,0) -> 0 | L79: =O$3*F79% -> 22600 | M79: =O$2*F79% -> 84750 | N79: 0 | O79: =ROUND(SUM(J79:N79),0) + R79 -> 105975.73 | P79: =ROUND(O79*6% + O79,0) + R79 -> 112334.73 | Q79: =ROUND(O79*3%,0) + O79 -> 109154.73 | R79: =R78+0.01 -> 0.73
B80: 14-E | C80: =C79+1 -> 74 | D80: EMA ALVAREZ | F80: 1.13 | G80: 107276.74 | H80: =G80-'PRORRATEO (2)'!H80 -> 107276.74 | J80: =G80-H80 -> 0 | K80: =IF(J80>0,J80*3%,0) -> 0 | L80: =O$3*F80% -> 22600 | M80: =O$2*F80% -> 84750 | N80: 0 | O80: =ROUND(SUM(J80:N80),0) + R80 -> 107350.74 | P80: =ROUND(O80*6% + O80,0) + R80 -> 113792.74 | Q80: =ROUND(O80*3%,0) + O80 -> 110571.74 | R80: =R79+0.01 -> 0.74
F81: =SUM(F6:F80) -> 100 | G81: =SUM(G6:G80) -> 13947031 | H81: =SUM(H6:H80) -> 9062894.1 | I81: =SUM(I6:I80) -> 0 | J81: =SUM(J6:J80) -> 4884136.6 | K81: =SUM(K6:K80) -> 153679.97 | L81: =SUM(L6:L80) -> 2000000 | M81: =SUM(M6:M80) -> 7500000 | ... Q81: =SUM(Q6:Q80) -> 14973994

Sheet PRORRATEO (2)
D1: Formas de Pago: Cuenta corriente Nro. 740-015772/0 Santander
D2: =RESUMEN!B4 -> CBU: 0720740420000001577204 | L2: Gastos extraordinarios: | O2: 0
D3: Efectivo
A4: Piso | B4: Dpto. | C4: UF | D4: Propietario | E4: Inquilinos | F4: (%) | G4: Saldo Extraord | H4: Ingreso | I4: Pago por | J4: Deuda o Saldo a favor | K4: Interes | L4: Expensas extraor. | M4: Expensas extraord | N4: Gastos part. | O4: Total 1er Vto | P4: Total 2do Vto. | Q4: Total 2do Vto
O5: =RESUMEN!B9 -> VTO 13/03
A6: PB | B6: PB B | C6: 1 | D6: TULA CARLOS (2) | F6: 1.65 | G6: 0 | H6: =G6 -> 0 | J6: =G6-H6 -> 0 | K6: =IF(J6>0,J6*3%,0) -> 0 | L6: 0 | M6: =O$2*F6% -> 0 | N6: 0 | O6: =ROUND(SUM(J6:N6),0) + R6 -> 0.01 | P6: =ROUND(O6*6% + O6,0) + R6 -> 0.01 | Q6: =ROUND(O6*3%,0) + O6 -> 0.01 | R6: 0.01
A7: 3º | B7: PB C | C7: =C6+1 -> 2 | D7: COMBRE ALFREDO | F7: 1.16 | G7: 0 | H7: =G7 -> 0 | J7: =G7-H7 -> 0 | K7: =IF(J7>0,J7*3%,0) -> 0 | L7: 0 | M7: =O$2*F7% -> 0 | N7: 0 | O7: =ROUND(SUM(J7:N7),0) + R7 -> 0.02 | P7: =ROUND(O7*6% + O7,0) + R7 -> 0.02 | Q7: =ROUND(O7*3%,0) + O7 -> 0.02 | R7: =R6+0.01 -> 0.02
A8: 3º | B8: PB D | C8: =C7+1 -> 3 | D8: PRGICH FEDERICO | F8: 1.19 | G8: 0 | H8: =G8 -> 0 | J8: =G8-H8 -> 0 | K8: =IF(J8>0,J8*3%,0) -> 0 | L8: 0 | M8: =O$2*F8% -> 0 | N8: 0 | O8: =ROUND(SUM(J8:N8),0) + R8 -> 0.03 | P8: =ROUND(O8*6% + O8,0) + R8 -> 0.03 | Q8: =ROUND(O8*3%,0) + O8 -> 0.03 | R8: =R7+0.01 -> 0.03
A9: 4º | B9: PB E | C9: =C8+1 -> 4 | D9: SRUGO DAMIAN | F9: 1.22 | G9: 0 | H9: =G9 -> 0 | J9: =G9-H9 -> 0 | K9: =IF(J9>0,J9*3%,0) -> 0 | L9: 0 | M9: =O$2*F9% -> 0 | N9: 0 | O9: =ROUND(SUM(J9:N9),0) + R9 -> 0.04 | P9: =ROUND(O9*6% + O9,0) + R9 -> 0.04 | Q9: =ROUND(O9*3%,0) + O9 -> 0.04 | R9: =R8+0.01 -> 0.04
A10: 4º | B10: 1-A | C10: =C9+1 -> 5 | D10: ZELANSNY SILVIA | F10: 1.67 | J10: =G10-H10 -> 0 | K10: =IF(J10>0,J10*3%,0) -> 0 | L10: 0 | M10: =O$2*F10% -> 0 | N10: 0 | O10: =ROUND(SUM(J10:N10),0) + R10 -> 0.05 | P10: =ROUND(O10*6% + O10,0) + R10 -> 0.05 | Q10: =ROUND(O10*3%,0) + O10 -> 0.05 | R10: =R9+0.01 -> 0.05
A11: 5º | B11: 1-B | C11: =C10+1 -> 6 | D11: PICO HEBE | F11: 1.71 | G11: 0 | H11: =G11 -> 0 | J11: =G11-H11 -> 0 | K11: =IF(J11>0,J11*3%,0) -> 0 | L11: 0 | M11: =O$2*F11% -> 0 | N11: 0 | O11: =ROUND(SUM(J11:N11),0) + R11 -> 0.06 | P11: =ROUND(O11*6% + O11,0) + R11 -> 0.06 | Q11: =ROUND(O11*3%,0) + O11 -> 0.06 | R11: =R10+0.01 -> 0.06
A12: 5º | B12: 1-C | C12: =C11+1 -> 7 | D12: RAMOS ROSA | F12: 1.13 | G12: 0 | H12: =G12 -> 0 | J12: =G12-H12 -> 0 | K12: =IF(J12>0,J12*3%,0) -> 0 | L12: 0 | M12: =O$2*F12% -> 0 | N12: 0 | O12: =ROUND(SUM(J12:N12),0) + R12 -> 0.07 | P12: =ROUND(O12*6% + O12,0) + R12 -> 0.07 | Q12: =ROUND(O12*3%,0) + O12 -> 0.07 | R12: =R11+0.01 -> 0.07
A13: 6º | B13: 1-D | C13: =C12+1 -> 8 | D13: MASIMO HUGO | F13: 1.13 | G13: 0 | H13: =G13 -> 0 | J13: =G13-H13 -> 0 | K13: =IF(J13>0,J13*3%,0) -> 0 | L13: 0 | M13: =O$2*F13% -> 0 | N13: 0 | O13: =ROUND(SUM(J13:N13),0) + R13 -> 0.08 | P13: =ROUND(O13*6% + O13,0) + R13 -> 0.08 | Q13: =ROUND(O13*3%,0) + O13 -> 0.08 | R13: =R12+0.01 -> 0.08
A14: 6º | B14: 1-E | C14: =C13+1 -> 9 | D14: BARONE GERARDO | F14: 1.13 | G14: 0 | H14: =G14 -> 0 | J14: =G14-H14 -> 0 | K14: =IF(J14>0,J14*3%,0) -> 0 | L14: 0 | M14: =O$2*F14% -> 0 | N14: 0 | O14: =ROUND(SUM(J14:N14),0) + R14 -> 0.09 | P14: =ROUND(O14*6% + O14,0) + R14 -> 0.09 | Q14: =ROUND(O14*3%,0) + O14 -> 0.09 | R14: =R13+0.01 -> 0.09
A15: 7º | B15: 2-A | C15: =C14+1 -> 10 | D15: MONGIELLO CARLOS (2) | F15: 1.67 | G15: 0 | H15: =G15 -> 0 | J15: =G15-H15 -> 0 | K15: =IF(J15>0,J15*3%,0) -> 0 | L15: 0 | M15: =O$2*F15% -> 0 | N15: 0 | O15: =ROUND(SUM(J15:N15),0) + R15 -> 0.1 | P15: =ROUND(O15*6% + O15,0) + R15 -> 0.1 | Q15: =ROUND(O15*3%,0) + O15 -> 0.1 | R15: =R14+0.01 -> 0.1
A16: 7º | B16: 2-B | C16: =C15+1 -> 11 | D16: COSTA MONICA | F16: 1.71 | G16: 0 | H16: =G16 -> 0 | J16: =G16-H16 -> 0 | K16: =IF(J16>0,J16*3%,0) -> 0 | L16: 0 | M16: =O$2*F16% -> 0 | N16: 0 | O16: =ROUND(SUM(J16:N16),0) + R16 -> 0.11 | P16: =ROUND(O16*6% + O16,0) + R16 -> 0.11 | Q16: =ROUND(O16*3%,0) + O16 -> 0.11 | R16: =R15+0.01 -> 0.11
A17: 8º | B17: 2-C | C17: =C16+1 -> 12 | D17: LOPEZ GUILLERMON | F17: 1.13 | G17: 0 | H17: =G17 -> 0 | J17: =G17-H17 -> 0 | K17: =IF(J17>0,J17*3%,0) -> 0 | L17: 0 | M17: =O$2*F17% -> 0 | N17: 0 | O17: =ROUND(SUM(J17:N17),0) + R17 -> 0.12 | P17: =ROUND(O17*6% + O17,0) + R17 -> 0.12 | Q17: =ROUND(O17*3%,0) + O17 -> 0.12 | R17: =R16+0.01 -> 0.12
A18: 8º | B18: 2-D | C18: =C17+1 -> 13 | D18: MARTINEZ ADELINA | F18: 1.13 | G18: 0 | H18: =G18 -> 0 | J18: =G18-H18 -> 0 | K18: =IF(J18>0,J18*3%,0) -> 0 | L18: 0 | M18: =O$2*F18% -> 0 | N18: 0 | O18: =ROUND(SUM(J18:N18),0) + R18 -> 0.13 | P18: =ROUND(O18*6% + O18,0) + R18 -> 0.13 | Q18: =ROUND(O18*3%,0) + O18 -> 0.13 | R18: =R17+0.01 -> 0.13
A19: 9º | B19: 2-E | C19: =C18+1 -> 14 | D19: QUIROGA ALBA | F19: 1.13 | J19: =G19-H19 -> 0 | K19: =IF(J19>0,J19*3%,0) -> 0 | L19: 0 | M19: =O$2*F19% -> 0 | N19: 0 | O19: =ROUND(SUM(J19:N19),0) + R19 -> 0.14 | P19: =ROUND(O19*6% + O19,0) + R19 -> 0.14 | Q19: =ROUND(O19*3%,0) + O19 -> 0.14 | R19: =R18+0.01 -> 0.14
A20: 9º | B20: 3-A | C20: =C19+1 -> 15 | D20: MADAR MARIANA | F20: 1.67 | G20: 0 | H20: =G20 -> 0 | J20: =G20-H20 -> 0 | K20: =IF(J20>0,J20*3%,0) -> 0 | L20: 0 | M20: =O$2*F20% -> 0 | N20: 0 | O20: =ROUND(SUM(J20:N20),0) + R20 -> 0.15 | P20: =ROUND(O20*6% + O20,0) + R20 -> 0.15 | Q20: =ROUND(O20*3%,0) + O20 -> 0.15 | R20: =R19+0.01 -> 0.15
A21: 10º | B21: 3-B | C21: =C20+1 -> 16 | D21: PIRES NABAIS | F21: 1.71 | G21: 0 | H21: =G21 -> 0 | J21: =G21-H21 -> 0 | K21: =IF(J21>0,J21*3%,0) -> 0 | L21: 0 | M21: =O$2*F21% -> 0 | N21: 0 | O21: =ROUND(SUM(J21:N21),0) + R21 -> 0.16 | P21: =ROUND(O21*6% + O21,0) + R21 -> 0.16 | Q21: =ROUND(O21*3%,0) + O21 -> 0.16 | R21: =R20+0.01 -> 0.16
A22: 10º | B22: 3-C | C22: =C21+1 -> 17 | D22: SANABRIA MARIO | F22: 1.13 | G22: 0 | H22: =G22 -> 0 | J22: =G22-H22 -> 0 | K22: =IF(J22>0,J22*3%,0) -> 0 | L22: 0 | M22: =O$2*F22% -> 0 | N22: 0 | O22: =ROUND(SUM(J22:N22),0) + R22 -> 0.17 | P22: =ROUND(O22*6% + O22,0) + R22 -> 0.17 | Q22: =ROUND(O22*3%,0) + O22 -> 0.17 | R22: =R21+0.01 -> 0.17
A23: 11º | B23: 3-D | C23: =C22+1 -> 18 | D23: PEROTTI | F23: 1.13 | G23: 0 | H23: =G23 -> 0 | J23: =G23-H23 -> 0 | K23: =IF(J23>0,J23*3%,0) -> 0 | L23: 0 | M23: =O$2*F23% -> 0 | N23: 0 | O23: =ROUND(SUM(J23:N23),0) + R23 -> 0.18 | P23: =ROUND(O23*6% + O23,0) + R23 -> 0.18 | Q23: =ROUND(O23*3%,0) + O23 -> 0.18 | R23: =R22+0.01 -> 0.18
A24: 11º | B24: 3-E | C24: =C23+1 -> 19 | D24: GOITEA ANTONIO | F24: 1.13 | G24: 0 | H24: =G24 -> 0 | J24: =G24-H24 -> 0 | K24: =IF(J24>0,J24*3%,0) -> 0 | L24: 0 | M24: =O$2*F24% -> 0 | N24: 0 | O24: =ROUND(SUM(J24:N24),0) + R24 -> 0.19 | P24: =ROUND(O24*6% + O24,0) + R24 -> 0.19 | Q24: =ROUND(O24*3%,0) + O24 -> 0.19 | R24: =R23+0.01 -> 0.19
A25: 12º | B25: 4-A | C25: =C24+1 -> 20 | D25: BIDABE LOMO | F25: 1.67 | G25: 0 | H25: =G25 -> 0 | J25: =G25-H25 -> 0 | K25: =IF(J25>0,J25*3%,0) -> 0 | L25: 0 | M25: =O$2*F25% -> 0 | N25: 0 | O25: =ROUND(SUM(J25:N25),0) + R25 -> 0.2 | P25: =ROUND(O25*6% + O25,0) + R25 -> 0.2 | Q25: =ROUND(O25*3%,0) + O25 -> 0.2 | R25: =R24+0.01 -> 0.2
A26: 13º | B26: 4-B | C26: =C25+1 -> 21 | D26: SICILIANO GRACIELA (2) | F26: 1.71 | G26: 0 | H26: =G26 -> 0 | J26: =G26-H26 -> 0 | K26: =IF(J26>0,J26*3%,0) -> 0 | L26: 0 | M26: =O$2*F26% -> 0 | N26: 0 | O26: =ROUND(SUM(J26:N26),0) + R26 -> 0.21 | P26: =ROUND(O26*6% + O26,0) + R26 -> 0.21 | Q26: =ROUND(O26*3%,0) + O26 -> 0.21 | R26: =R25+0.01 -> 0.21
A27: 14º | B27: 4-C | C27: =C26+1 -> 22 | D27: SANCHEZ NELIDA | F27: 1.13 | G27: 0 | H27: =G27 -> 0 | J27: =G27-H27 -> 0 | K27: =IF(J27>0,J27*3%,0) -> 0 | L27: 0 | M27: =O$2*F27% -> 0 | N27: 0 | O27: =ROUND(SUM(J27:N27),0) + R27 -> 0.22 | P27: =ROUND(O27*6% + O27,0) + R27 -> 0.22 | Q27: =ROUND(O27*3%,0) + O27 -> 0.22 | R27: =R26+0.01 -> 0.22
A28: 15º | B28: 4-D | C28: =C27+1 -> 23 | D28: TABOADA MARIA (2) | F28: 1.13 | G28: 0 | H28: =G28 -> 0 | J28: =G28-H28 -> 0 | K28: =IF(J28>0,J28*3%,0) -> 0 | L28: 0 | M28: =O$2*F28% -> 0 | N28: 0 | O28: =ROUND(SUM(J28:N28),0) + R28 -> 0.23 | P28: =ROUND(O28*6% + O28,0) + R28 -> 0.23 | Q28: =ROUND(O28*3%,0) + O28 -> 0.23 | R28: =R27+0.01 -> 0.23
A29: COC | B29: 4-E | C29: =C28+1 -> 24 | D29: BEDOYA BEATRIZ | F29: 1.13 | H29: =G29 -> 0 | J29: =G29-H29 -> 0 | K29: =IF(J29>0,J29*3%,0) -> 0 | L29: 0 | M29: =O$2*F29% -> 0 | N29: 0 | O29: =ROUND(SUM(J29:N29),0) + R29 -> 0.24 | P29: =ROUND(O29*6% + O29,0) + R29 -> 0.24 | Q29: =ROUND(O29*3%,0) + O29 -> 0.24 | R29: =R28+0.01 -> 0.24
A30: COC | B30: 5-A | C30: =C29+1 -> 25 | D30: RIZOLI VICTOR | F30: 1.67 | G30: 0 | H30: =G30 -> 0 | J30: =G30-H30 -> 0 | K30: =IF(J30>0,J30*3%,0) -> 0 | L30: 0 | M30: =O$2*F30% -> 0 | N30: 0 | O30: =ROUND(SUM(J30:N30),0) + R30 -> 0.25 | P30: =ROUND(O30*6% + O30,0) + R30 -> 0.25 | Q30: =ROUND(O30*3%,0) + O30 -> 0.25 | R30: =R29+0.01 -> 0.25
A31: COC | B31: 5-B | C31: =C30+1 -> 26 | D31: HOREN KRASNOBRODA | F31: 1.71 | G31: 0 | H31: =G31 -> 0 | J31: =G31-H31 -> 0 | K31: =IF(J31>0,J31*3%,0) -> 0 | L31: 0 | M31: =O$2*F31% -> 0 | N31: 0 | O31: =ROUND(SUM(J31:N31),0) + R31 -> 0.26 | P31: =ROUND(O31*6% + O31,0) + R31 -> 0.26 | Q31: =ROUND(O31*3%,0) + O31 -> 0.26 | R31: =R30+0.01 -> 0.26
A32: COC | B32: 5-C | C32: =C31+1 -> 27 | D32: MUÑOZ HERNAN | F32: 1.13 | G32: 0 | H32: =G32 -> 0 | J32: =G32-H32 -> 0 | K32: =IF(J32>0,J32*3%,0) -> 0 | L32: 0 | M32: =O$2*F32% -> 0 | N32: 0 | O32: =ROUND(SUM(J32:N32),0) + R32 -> 0.27 | P32: =ROUND(O32*6% + O32,0) + R32 -> 0.27 | Q32: =ROUND(O32*3%,0) + O32 -> 0.27 | R32: =R31+0.01 -> 0.27
A33: COC | B33: 5-D | C33: =C32+1 -> 28 | D33: VASTA NANCY | F33: 1.13 | G33: 0 | H33: =G33 -> 0 | J33: =G33-H33 -> 0 | K33: =IF(J33>0,J33*3%,0) -> 0 | L33: 0 | M33: =O$2*F33% -> 0 | N33: 42488 | O33: =ROUND(SUM(J33:N33),0) + R33 -> 42488.28 | P33: =ROUND(O33*6% + O33,0) + R33 -> 45038.28 | Q33: =ROUND(O33*3%,0) + O33 -> 43763.28 | R33: =R32+0.01 -> 0.28
A34: COC | B34: 5-E | C34: =C33+1 -> 29 | D34: TRAVERSA | F34: 1.13 | G34: 0 | H34: =G34 -> 0 | J34: =G34-H34 -> 0 | K34: =IF(J34>0,J34*3%,0) -> 0 | L34: 0 | M34: =O$2*F34% -> 0 | N34: 0 | O34: =ROUND(SUM(J34:N34),0) + R34 -> 0.29 | P34: =ROUND(O34*6% + O34,0) + R34 -> 0.29 | Q34: =ROUND(O34*3%,0) + O34 -> 0.29 | R34: =R33+0.01 -> 0.29
A35: COC | B35: 6-A | C35: =C34+1 -> 30 | D35: BAFFONI FABIAN | F35: 1.67 | G35: 0 | H35: =G35 -> 0 | J35: =G35-H35 -> 0 | K35: =IF(J35>0,J35*3%,0) -> 0 | L35: 0 | M35: =O$2*F35% -> 0 | N35: 0 | O35: =ROUND(SUM(J35:N35),0) + R35 -> 0.3 | P35: =ROUND(O35*6% + O35,0) + R35 -> 0.3 | Q35: =ROUND(O35*3%,0) + O35 -> 0.3 | R35: =R34+0.01 -> 0.3
A36: COC | G36: 0 | J36: =G36-H36 -> 0 | K36: =IF(J36>0,J36*3%,0) -> 0 | L36: 0 | M36: =O$2*F36% -> 0 | N36: 0 | O36: =ROUND(SUM(J36:N36),0) + R36 -> 0 | P36: =ROUND(O36*6% + O36,0) + R36 -> 0 | Q36: =ROUND(O36*3%,0) + O36 -> 0
A37: COC | B37: 6-B | C37: 31 | D37: PAQUET DE LOPEZ | F37: 1.71 | G37: 0 | H37: =G37 -> 0 | J37: =G37-H37 -> 0 | K37: =IF(J37>0,J37*3%,0) -> 0 | L37: 0 | M37: =O$2*F37% -> 0 | N37: 0 | O37: =ROUND(SUM(J37:N37),0) + R37 -> 0.31 | P37: =ROUND(O37*6% + O37,0) + R37 -> 0.31 | Q37: =ROUND(O37*3%,0) + O37 -> 0.31 | R37: 0.31
A38: COC | B38: 6-C | C38: =C37+1 -> 32 | D38: BLANCO MABEL | F38: 1.13 | G38: 0 | H38: =G38 -> 0 | J38: =G38-H38 -> 0 | K38: =IF(J38>0,J38*3%,0) -> 0 | L38: 0 | M38: =O$2*F38% -> 0 | N38: 0 | O38: =ROUND(SUM(J38:N38),0) + R38 -> 0.32 | P38: =ROUND(O38*6% + O38,0) + R38 -> 0.32 | Q38: =ROUND(O38*3%,0) + O38 -> 0.32 | R38: =R37+0.01 -> 0.32
A39: COC | B39: 6-D | C39: =C38+1 -> 33 | D39: TESTA IRENE | F39: 1.13 | G39: 0 | H39: =G39 -> 0 | J39: =G39-H39 -> 0 | K39: =IF(J39>0,J39*3%,0) -> 0 | L39: 0 | M39: =O$2*F39% -> 0 | N39: 0 | O39: =ROUND(SUM(J39:N39),0) + R39 -> 0.33 | P39: =ROUND(O39*6% + O39,0) + R39 -> 0.33 | Q39: =ROUND(O39*3%,0) + O39 -> 0.33 | R39: =R38+0.01 -> 0.33
A40: COC | B40: 6-E | C40: =C39+1 -> 34 | D40: QUIROGA ENRIQUE | F40: 1.13 | G40: 0 | H40: =G40 -> 0 | J40: =G40-H40 -> 0 | K40: =IF(J40>0,J40*3%,0) -> 0 | L40: 0 | M40: =O$2*F40% -> 0 | N40: 0 | O40: =ROUND(SUM(J40:N40),0) + R40 -> 0.34 | P40: =ROUND(O40*6% + O40,0) + R40 -> 0.34 | Q40: =ROUND(O40*3%,0) + O40 -> 0.34 | R40: =R39+0.01 -> 0.34
A41: COC | B41: 7-A | C41: =C40+1 -> 35 | D41: ALVAREZ VERONICA (2) | F41: 1.67 | G41: 0 | H41: =G41 -> 0 | J41: =G41-H41 -> 0 | K41: =IF(J41>0,J41*3%,0) -> 0 | L41: 0 | M41: =O$2*F41% -> 0 | N41: 0 | O41: =ROUND(SUM(J41:N41),0) + R41 -> 0.35 | P41: =ROUND(O41*6% + O41,0) + R41 -> 0.35 | Q41: =ROUND(O41*3%,0) + O41 -> 0.35 | R41: =R40+0.01 -> 0.35
B42: 7-B | C42: =C41+1 -> 36 | D42: ROJAS CARMEN | F42: 1.71 | G42: 0 | H42: =G42 -> 0 | J42: =G42-H42 -> 0 | K42: =IF(J42>0,J42*3%,0) -> 0 | L42: 0 | M42: =O$2*F42% -> 0 | N42: 0 | O42: =ROUND(SUM(J42:N42),0) + R42 -> 0.36 | P42: =ROUND(O42*6% + O42,0) + R42 -> 0.36 | Q42: =ROUND(O42*3%,0) + O42 -> 0.36 | R42: =R41+0.01 -> 0.36
B43: 7-C | C43: =C42+1 -> 37 | D43: JUCHNO IRENE | F43: 1.13 | G43: 0 | H43: =G43 -> 0 | J43: =G43-H43 -> 0 | K43: =IF(J43>0,J43*3%,0) -> 0 | L43: 0 | M43: =O$2*F43% -> 0 | N43: 0 | O43: =ROUND(SUM(J43:N43),0) + R43 -> 0.37 | P43: =ROUND(O43*6% + O43,0) + R43 -> 0.37 | Q43: =ROUND(O43*3%,0) + O43 -> 0.37 | R43: =R42+0.01 -> 0.37
B44: 7-D | C44: =C43+1 -> 38 | D44: URIZAR LUQUES | F44: 1.13 | G44: 0 | H44: =G44 -> 0 | J44: =G44-H44 -> 0 | K44: =IF(J44>0,J44*3%,0) -> 0 | L44: 0 | M44: =O$2*F44% -> 0 | N44: 0 | O44: =ROUND(SUM(J44:N44),0) + R44 -> 0.38 | P44: =ROUND(O44*6% + O44,0) + R44 -> 0.38 | Q44: =ROUND(O44*3%,0) + O44 -> 0.38 | R44: =R43+0.01 -> 0.38
B45: 7-E | C45: =C44+1 -> 39 | D45: RIPA NELLY | F45: 1.13 | G45: 0 | H45: =G45 -> 0 | J45: =G45-H45 -> 0 | K45: =IF(J45>0,J45*3%,0) -> 0 | L45: 0 | M45: =O$2*F45% -> 0 | N45: 0 | O45: =ROUND(SUM(J45:N45),0) + R45 -> 0.39 | P45: =ROUND(O45*6% + O45,0) + R45 -> 0.39 | Q45: =ROUND(O45*3%,0) + O45 -> 0.39 | R45: =R44+0.01 -> 0.39
B46: 8-A | C46: =C45+1 -> 40 | D46: SORIA GODOY | F46: 1.67 | H46: =G46 -> 0 | J46: =G46-H46 -> 0 | K46: =IF(J46>0,J46*3%,0) -> 0 | L46: 0 | M46: =O$2*F46% -> 0 | N46: 0 | O46: =ROUND(SUM(J46:N46),0) + R46 -> 0.4 | P46: =ROUND(O46*6% + O46,0) + R46 -> 0.4 | Q46: =ROUND(O46*3%,0) + O46 -> 0.4 | R46: =R45+0.01 -> 0.4
B47: 8-B | C47: =C46+1 -> 41 | D47: D´ALOIA GABRIELA (2) | F47: 1.71 | G47: 0 | H47: =G47 -> 0 | J47: =G47-H47 -> 0 | K47: =IF(J47>0,J47*3%,0) -> 0 | L47: 0 | M47: =O$2*F47% -> 0 | N47: 0 | O47: =ROUND(SUM(J47:N47),0) + R47 -> 0.41 | P47: =ROUND(O47*6% + O47,0) + R47 -> 0.41 | Q47: =ROUND(O47*3%,0) + O47 -> 0.41 | R47: =R46+0.01 -> 0.41
B48: 8-C | C48: =C47+1 -> 42 | D48: MIÑO GRACIELA (2) | F48: 1.13 | G48: 0 | H48: =G48 -> 0 | J48: =G48-H48 -> 0 | K48: =IF(J48>0,J48*3%,0) -> 0 | L48: 0 | M48: =O$2*F48% -> 0 | N48: 0 | O48: =ROUND(SUM(J48:N48),0) + R48 -> 0.42 | P48: =ROUND(O48*6% + O48,0) + R48 -> 0.42 | Q48: =ROUND(O48*3%,0) + O48 -> 0.42 | R48: =R47+0.01 -> 0.42
B49: 8-D | C49: =C48+1 -> 43 | D49: CATALANO CLAUDIA | F49: 1.13 | G49: 0 | H49: =G49 -> 0 | J49: =G49-H49 -> 0 | K49: =IF(J49>0,J49*3%,0) -> 0 | L49: 0 | M49: =O$2*F49% -> 0 | N49: 0 | O49: =ROUND(SUM(J49:N49),0) + R49 -> 0.43 | P49: =ROUND(O49*6% + O49,0) + R49 -> 0.43 | Q49: =ROUND(O49*3%,0) + O49 -> 0.43 | R49: =R48+0.01 -> 0.43
B50: 8-E | C50: =C49+1 -> 44 | D50: ROCA MARISA | F50: 1.13 | G50: 0 | H50: =G50 -> 0 | J50: =G50-H50 -> 0 | K50: =IF(J50>0,J50*3%,0) -> 0 | L50: 0 | M50: =O$2*F50% -> 0 | N50: 0 | O50: =ROUND(SUM(J50:N50),0) + R50 -> 0.44 | P50: =ROUND(O50*6% + O50,0) + R50 -> 0.44 | Q50: =ROUND(O50*3%,0) + O50 -> 0.44 | R50: =R49+0.01 -> 0.44
B51: 9-A | C51: =C50+1 -> 45 | D51: TINEO | F51: 1.67 | G51: 0 | H51: =G51 -> 0 | J51: =G51-H51 -> 0 | K51: =IF(J51>0,J51*3%,0) -> 0 | L51: 0 | M51: =O$2*F51% -> 0 | N51: 0 | O51: =ROUND(SUM(J51:N51),0) + R51 -> 0.45 | P51: =ROUND(O51*6% + O51,0) + R51 -> 0.45 | Q51: =ROUND(O51*3%,0) + O51 -> 0.45 | R51: =R50+0.01 -> 0.45
B52: 9-B | C52: =C51+1 -> 46 | D52: MAZZEO CECILIA | F52: 1.71 | G52: 0 | H52: =G52 -> 0 | J52: =G52-H52 -> 0 | K52: =IF(J52>0,J52*3%,0) -> 0 | L52: 0 | M52: =O$2*F52% -> 0 | N52: 0 | O52: =ROUND(SUM(J52:N52),0) + R52 -> 0.46 | P52: =ROUND(O52*6% + O52,0) + R52 -> 0.46 | Q52: =ROUND(O52*3%,0) + O52 -> 0.46 | R52: =R51+0.01 -> 0.46
B53: 9-C | C53: =C52+1 -> 47 | D53: GARCIA JORGE | F53: 1.13 | G53: 0 | H53: =G53 -> 0 | J53: =G53-H53 -> 0 | K53: =IF(J53>0,J53*3%,0) -> 0 | L53: 0 | M53: =O$2*F53% -> 0 | N53: 0 | O53: =ROUND(SUM(J53:N53),0) + R53 -> 0.47 | P53: =ROUND(O53*6% + O53,0) + R53 -> 0.47 | Q53: =ROUND(O53*3%,0) + O53 -> 0.47 | R53: =R52+0.01 -> 0.47
B54: 9-D | C54: =C53+1 -> 48 | D54: ROSSI NORMA | F54: 1.13 | G54: 0 | H54: =G54 -> 0 | J54: =G54-H54 -> 0 | K54: =IF(J54>0,J54*3%,0) -> 0 | L54: 0 | M54: =O$2*F54% -> 0 | N54: 0 | O54: =ROUND(SUM(J54:N54),0) + R54 -> 0.48 | P54: =ROUND(O54*6% + O54,0) + R54 -> 1.48 | Q54: =ROUND(O54*3%,0) + O54 -> 0.48 | R54: =R53+0.01 -> 0.48
B55: 9-E | C55: =C54+1 -> 49 | D55: AGNESE PEDRO | F55: 1.13 | G55: 0 | H55: =G55 -> 0 | J55: =G55-H55 -> 0 | K55: =IF(J55>0,J55*3%,0) -> 0 | L55: 0 | M55: =O$2*F55% -> 0 | N55: 0 | O55: =ROUND(SUM(J55:N55),0) + R55 -> 0.49 | P55: =ROUND(O55*6% + O55,0) + R55 -> 1.49 | Q55: =ROUND(O55*3%,0) + O55 -> 0.49 | R55: =R54+0.01 -> 0.49
B56: 10-A | C56: =C55+1 -> 50 | D56: ABDALA (1) | F56: 1.67 | G56: 0 | H56: =G56 -> 0 | J56: =G56-H56 -> 0 | K56: =IF(J56>0,J56*3%,0) -> 0 | L56: 0 | M56: =O$2*F56% -> 0 | N56: 0 | O56: =ROUND(SUM(J56:N56),0) + R56 -> 0.5 | P56: =ROUND(O56*6% + O56,0) + R56 -> 1.5 | Q56: =ROUND(O56*3%,0) + O56 -> 0.5 | R56: =R55+0.01 -> 0.5
B57: 10-B | C57: =C56+1 -> 51 | D57: DEL RIO GUSTAVO | F57: 1.71 | G57: 0 | H57: =G57 -> 0 | J57: =G57-H57 -> 0 | K57: =IF(J57>0,J57*3%,0) -> 0 | L57: 0 | M57: =O$2*F57% -> 0 | N57: 0 | O57: =ROUND(SUM(J57:N57),0) + R57 -> 0.51 | P57: =ROUND(O57*6% + O57,0) + R57 -> 1.51 | Q57: =ROUND(O57*3%,0) + O57 -> 0.51 | R57: =R56+0.01 -> 0.51
B58: 10-C | C58: =C57+1 -> 52 | D58: MIGLIORISI ANDREA | F58: 1.13 | G58: 0 | H58: =G58 -> 0 | J58: =G58-H58 -> 0 | K58: =IF(J58>0,J58*3%,0) -> 0 | L58: 0 | M58: =O$2*F58% -> 0 | N58: 0 | O58: =ROUND(SUM(J58:N58),0) + R58 -> 0.52 | P58: =ROUND(O58*6% + O58,0) + R58 -> 1.52 | Q58: =ROUND(O58*3%,0) + O58 -> 0.52 | R58: =R57+0.01 -> 0.52
... B60: 10-E | C60: =C59+1 -> 54 | D60: DEBENEDETTI C | F60: 1.13 | G60: 0 | H60: =G60 -> 0 | J60: =G60-H60 -> 0 | K60: =IF(J60>0,J60*3%,0) -> 0 | L60: 0 | M60: =O$2*F60% -> 0 | N60: 0 | O60: =ROUND(SUM(J60:N60),0) + R60 -> 0.54 | P60: =ROUND(O60*6% + O60,0) + R60 -> 1.54 | Q60: =ROUND(O60*3%,0) + O60 -> 0.54 | R60: =R59+0.01 -> 0.54
B61: 11-A | C61: =C60+1 -> 55 | D61: MENDIBURU JORGE | F61: 1.67 | H61: =G61 -> 0 | J61: =G61-H61 -> 0 | K61: =IF(J61>0,J61*3%,0) -> 0 | L61: 0 | M61: =O$2*F61% -> 0 | O61: =ROUND(SUM(J61:N61),0) + R61 -> 0.55 | P61: =ROUND(O61*6% + O61,0) + R61 -> 1.55 | Q61: =ROUND(O61*3%,0) + O61 -> 0.55 | R61: =R60+0.01 -> 0.55
B62: 11-B | C62: =C61+1 -> 56 | D62: GALLUCCI CARMELA | F62: 1.71 | G62: 0 | H62: =G62 -> 0 | J62: =G62-H62 -> 0 | K62: =IF(J62>0,J62*3%,0) -> 0 | L62: 0 | M62: =O$2*F62% -> 0 | N62: 0 | O62: =ROUND(SUM(J62:N62),0) + R62 -> 0.56 | P62: =ROUND(O62*6% + O62,0) + R62 -> 1.56 | Q62: =ROUND(O62*3%,0) + O62 -> 0.56 | R62: =R61+0.01 -> 0.56
B63: 11-C | C63: =C62+1 -> 57 | D63: CABAÑAS MARIA SOLEDAD | F63: 1.13 | G63: 0 | H63: =G63 -> 0 | J63: =G63-H63 -> 0 | K63: =IF(J63>0,J63*3%,0) -> 0 | L63: 0 | M63: =O$2*F63% -> 0 | N63: 0 | O63: =ROUND(SUM(J63:N63),0) + R63 -> 0.57 | P63: =ROUND(O63*6% + O63,0) + R63 -> 1.57 | Q63: =ROUND(O63*3%,0) + O63 -> 0.57 | R63: =R62+0.01 -> 0.57
B64: 11-D | C64: =C63+1 -> 58 | D64: GUARINO | F64: 1.13 | G64: 0 | H64: =G64 -> 0 | J64: =G64-H64 -> 0 | K64: =IF(J64>0,J64*3%,0) -> 0 | L64: 0 | M64: =O$2*F64% -> 0 | N64: 0 | O64: =ROUND(SUM(J64:N64),0) + R64 -> 0.58 | P64: =ROUND(O64*6% + O64,0) + R64 -> 1.58 | Q64: =ROUND(O64*3%,0) + O64 -> 0.58 | R64: =R63+0.01 -> 0.58
B65: 11-E | C65: =C64+1 -> 59 | D65: MARQUEZ VERONICA | F65: 1.13 | G65: 0 | H65: =G65 -> 0 | J65: =G65-H65 -> 0 | K65: =IF(J65>0,J65*3%,0) -> 0 | L65: 0 | M65: =O$2*F65% -> 0 | N65: 0 | O65: =ROUND(SUM(J65:N65),0) + R65 -> 0.59 | P65: =ROUND(O65*6% + O65,0) + R65 -> 1.59 | Q65: =ROUND(O65*3%,0) + O65 -> 0.59 | R65: =R64+0.01 -> 0.59
B66: 12-A | C66: =C65+1 -> 60 | D66: BRAU HECTOR | F66: 1.67 | G66: 0 | H66: =G66 -> 0 | J66: =G66-H66 -> 0 | K66: =IF(J66>0,J66*3%,0) -> 0 | L66: 0 | M66: =O$2*F66% -> 0 | N66: 0 | O66: =ROUND(SUM(J66:N66),0) + R66 -> 0.6 | P66: =ROUND(O66*6% + O66,0) + R66 -> 1.6 | Q66: =ROUND(O66*3%,0) + O66 -> 0.6 | R66: =R65+0.01 -> 0.6
B67: 12-B | C67: =C66+1 -> 61 | D67: ZERBA MARCELO | F67: 1.71 | G67: 0 | H67: =G67 -> 0 | J67: =G67-H67 -> 0 | K67: =IF(J67>0,J67*3%,0) -> 0 | L67: 0 | M67: =O$2*F67% -> 0 | N67: 0 | O67: =ROUND(SUM(J67:N67),0) + R67 -> 0.61 | P67: =ROUND(O67*6% + O67,0) + R67 -> 1.61 | Q67: =ROUND(O67*3%,0) + O67 -> 0.61 | R67: =R66+0.01 -> 0.61
B68: 12-C | C68: =C67+1 -> 62 | D68: VERMINETTI | F68: 1.13 | G68: 0 | H68: =G68 -> 0 | J68: =G68-H68 -> 0 | K68: =IF(J68>0,J68*3%,0) -> 0 | L68: 0 | M68: =O$2*F68% -> 0 | N68: 0 | O68: =ROUND(SUM(J68:N68),0) + R68 -> 0.62 | P68: =ROUND(O68*6% + O68,0) + R68 -> 1.62 | Q68: =ROUND(O68*3%,0) + O68 -> 0.62 | R68: =R67+0.01 -> 0.62
B69: 12-D | C69: =C68+1 -> 63 | D69: RIQUELME | F69: 1.13 | G69: 0 | H69: =G69 -> 0 | J69: =G69-H69 -> 0 | K69: =IF(J69>0,J69*3%,0) -> 0 | L69: 0 | M69: =O$2*F69% -> 0 | N69: 0 | O69: =ROUND(SUM(J69:N69),0) + R69 -> 0.63 | P69: =ROUND(O69*6% + O69,0) + R69 -> 1.63 | Q69: =ROUND(O69*3%,0) + O69 -> 0.63 | R69: =R68+0.01 -> 0.63
B70: 12-E | C70: =C69+1 -> 64 | D70: RODRIGUEZ NESTOR | F70: 1.13 | G70: 0 | H70: =G70 -> 0 | J70: =G70-H70 -> 0 | K70: =IF(J70>0,J70*3%,0) -> 0 | L70: 0 | M70: =O$2*F70% -> 0 | N70: 0 | O70: =ROUND(SUM(J70:N70),0) + R70 -> 0.64 | P70: =ROUND(O70*6% + O70,0) + R70 -> 1.64 | Q70: =ROUND(O70*3%,0) + O70 -> 0.64 | R70: =R69+0.01 -> 0.64
B71: 13-A | C71: =C70+1 -> 65 | D71: ZIMERMANN LEON (2) | F71: 1.67 | G71: 0 | H71: =G71 -> 0 | J71: =G71-H71 -> 0 | K71: =IF(J71>0,J71*3%,0) -> 0 | L71: 0 | M71: =O$2*F71% -> 0 | N71: 0 | O71: =ROUND(SUM(J71:N71),0) + R71 -> 0.65 | P71: =ROUND(O71*6% + O71,0) + R71 -> 1.65 | Q71: =ROUND(O71*3%,0) + O71 -> 0.65 | R71: =R70+0.01 -> 0.65
B72: 13-B | C72: =C71+1 -> 66 | D72: DE GRACIA | F72: 1.71 | G72: 0 | H72: =G72 -> 0 | J72: =G72-H72 -> 0 | K72: =IF(J72>0,J72*3%,0) -> 0 | L72: 0 | M72: =O$2*F72% -> 0 | N72: 0 | O72: =ROUND(SUM(J72:N72),0) + R72 -> 0.66 | P72: =ROUND(O72*6% + O72,0) + R72 -> 1.66 | Q72: =ROUND(O72*3%,0) + O72 -> 0.66 | R72: =R71+0.01 -> 0.66
B73: 13-C | C73: =C72+1 -> 67 | D73: LAUMAN JOSE | F73: 1.13 | G73: 0 | H73: =G73 -> 0 | J73: =G73-H73 -> 0 | K73: =IF(J73>0,J73*3%,0) -> 0 | L73: 0 | M73: =O$2*F73% -> 0 | N73: 0 | O73: =ROUND(SUM(J73:N73),0) + R73 -> 0.67 | P73: =ROUND(O73*6% + O73,0) + R73 -> 1.67 | Q73: =ROUND(O73*3%,0) + O73 -> 0.67 | R73: =R72+0.01 -> 0.67
... B77: 14-B | C77: =C76+1 -> 71 | D77: RODRIGUEZ CARLOS | F77: 1.71 | G77: 0 | H77: =G77 -> 0 | J77: =G77-H77 -> 0 | K77: =IF(J77>0,J77*3%,0) -> 0 | L77: 0 | M77: =O$2*F77% -> 0 | N77: 0 | O77: =ROUND(SUM(J77:N77),0) + R77 -> 0.71 | P77: =ROUND(O77*6% + O77,0) + R77 -> 1.71 | Q77: =ROUND(O77*3%,0) + O77 -> 0.71 | R77: =R76+0.01 -> 0.71
B78: 14-C | C78: =C77+1 -> 72 | D78: FERNANDEZ MONICA (EN JUICIO) | F78: 1.13 | J78: =G78-H78 -> 0 | K78: =IF(J78>0,J78*3%,0) -> 0 | L78: 0 | M78: =O$2*F78% -> 0 | N78: 0 | O78: =ROUND(SUM(J78:N78),0) + R78 -> 0.72 | P78: =ROUND(O78*6% + O78,0) + R78 -> 1.72 | Q78: =ROUND(O78*3%,0) + O78 -> 0.72 | R78: =R77+0.01 -> 0.72
B79: 14-D | C79: =C78+1 -> 73 | D79: DE PAVIK ANGELA | F79: 1.13 | G79: 0 | H79: =G79 -> 0 | J79: =G79-H79 -> 0 | K79: =IF(J79>0,J79*3%,0) -> 0 | L79: 0 | M79: =O$2*F79% -> 0 | N79: 0 | O79: =ROUND(SUM(J79:N79),0) + R79 -> 0.73 | P79: =ROUND(O79*6% + O79,0) + R79 -> 1.73 | Q79: =ROUND(O79*3%,0) + O79 -> 0.73 | R79: =R78+0.01 -> 0.73
B80: 14-E | C80: =C79+1 -> 74 | D80: EMA ALVAREZ | F80: 1.13 | G80: 0 | H80: =G80 -> 0 | J80: =G80-H80 -> 0 | K80: =IF(J80>0,J80*3%,0) -> 0 | L80: 0 | M80: =O$2*F80% -> 0 | N80: 0 | O80: =ROUND(SUM(J80:N80),0) + R80 -> 0.74 | P80: =ROUND(O80*6% + O80,0) + R80 -> 1.74 | Q80: =ROUND(O80*3%,0) + O80 -> 0.74 | R80: =R79+0.01 -> 0.74
F81: =SUM(F6:F80) -> 100 | G81: =SUM(G6:G80) -> 0 | H81: =SUM(H6:H80) -> 0 | I81: =SUM(I6:I80) -> 0 | J81: =SUM(J6:J80) -> 0 | K81: =SUM(K6:K80) -> 0 | L81: =SUM(L6:L80) -> 0 | M81: =SUM(M6:M80) -> 0 | ... Q81: =SUM(Q6:Q80) -> 43790.75

Sheet TOTAL EXPENSAS
A2: Dpto. | B2: UF | C2: Propietario | D2: Inquilinos | E2: (%) | F2: TOTAL EXPENSAS (ESTRAORDINARIAS + ORDINARIAS)
A4: PB B | B4: 1 | C4: TULA CARLOS (2) | E4: 1.65 | F4: =PRORRATEO!O6+'PRORRATEO (2)'!O6 -> 252356.02
A5: PB C | B5: =B4+1 -> 2 | C5: COMBRE ALFREDO | E5: 1.16 | F5: =PRORRATEO!O7+'PRORRATEO (2)'!O7 -> 110200.04
A6: PB D | B6: =B5+1 -> 3 | C6: PRGICH FEDERICO | E6: 1.19 | F6: =PRORRATEO!O8+'PRORRATEO (2)'!O8 -> 107281.06
A7: PB E | B7: =B6+1 -> 4 | C7: SRUGO DAMIAN | E7: 1.22 | F7: =PRORRATEO!O9+'PRORRATEO (2)'!O9 -> 115900.08
A8: 1-A | B8: =B7+1 -> 5 | C8: ZELANSNY SILVIA | E8: 1.67 | F8: =PRORRATEO!O10+'PRORRATEO (2)'!O10 -> 210226.1
A9: 1-B | B9: =B8+1 -> 6 | C9: PICO HEBE | E9: 1.71 | F9: =PRORRATEO!O11+'PRORRATEO (2)'!O11 -> 453713.12
A10: 1-C | B10: =B9+1 -> 7 | C10: RAMOS ROSA | E10: 1.13 | F10: =PRORRATEO!O12+'PRORRATEO (2)'!O12 -> 107350.14
A11: 1-D | B11: =B10+1 -> 8 | C11: MASIMO HUGO | E11: 1.13 | F11: =PRORRATEO!O13+'PRORRATEO (2)'!O13 -> 104129.16
A12: 1-E | B12: =B11+1 -> 9 | C12: BARONE GERARDO | E12: 1.13 | F12: =PRORRATEO!O14+'PRORRATEO (2)'!O14 -> 107350.18
A13: 2-A | B13: =B12+1 -> 10 | C13: MONGIELLO CARLOS (2) | E13: 1.67 | F13: =PRORRATEO!O15+'PRORRATEO (2)'!O15 -> 153379.2
A14: 2-B | B14: =B13+1 -> 11 | C14: COSTA MONICA | E14: 1.71 | F14: =PRORRATEO!O16+'PRORRATEO (2)'!O16 -> 157576.22
A15: 2-C | B15: =B14+1 -> 12 | C15: LOPEZ GUILLERMON | E15: 1.13 | F15: =PRORRATEO!O17+'PRORRATEO (2)'!O17 -> 104700.24
A16: 2-D | B16: =B15+1 -> 13 | C16: MARTINEZ ADELINA | E16: 1.13 | F16: =PRORRATEO!O18+'PRORRATEO (2)'!O18 -> 207123.26
... A33: 6-A | B33: =B32+1 -> 30 | C33: BAFFONI FABIAN | E33: 1.67 | F33: =PRORRATEO!O35+'PRORRATEO (2)'!O35 -> 158650.6
F34: =PRORRATEO!O36+'PRORRATEO (2)'!O36 -> 0
A35: 6-B | B35: 31 | C35: PAQUET DE LOPEZ | E35: 1.71 | F35: =PRORRATEO!O37+'PRORRATEO (2)'!O37 -> 162450.62
A36: 6-C | B36: =B35+1 -> 32 | C36: BLANCO MABEL | E36: 1.13 | F36: =PRORRATEO!O38+'PRORRATEO (2)'!O38 -> 107350.64
A37: 6-D | B37: =B36+1 -> 33 | C37: TESTA IRENE | E37: 1.13 | F37: =PRORRATEO!O39+'PRORRATEO (2)'!O39 -> 107350.66
A38: 6-E | B38: =B37+1 -> 34 | C38: QUIROGA ENRIQUE | E38: 1.13 | F38: =PRORRATEO!O40+'PRORRATEO (2)'!O40 -> 311307.68
A39: 7-A | B39: =B38+1 -> 35 | C39: ALVAREZ VERONICA (2) | E39: 1.67 | F39: =PRORRATEO!O41+'PRORRATEO (2)'!O41 -> 254955.7
A40: 7-B | B40: =B39+1 -> 36 | C40: ROJAS CARMEN | E40: 1.71 | F40: =PRORRATEO!O42+'PRORRATEO (2)'!O42 -> 571701.72
A41: 7-C | B41: =B40+1 -> 37 | C41: JUCHNO IRENE | E41: 1.13 | F41: =PRORRATEO!O43+'PRORRATEO (2)'!O43 -> 107350.74
A42: 7-D | B42: =B41+1 -> 38 | C42: URIZAR LUQUES | E42: 1.13 | F42: =PRORRATEO!O44+'PRORRATEO (2)'!O44 -> 217921.76
A43: 7-E | B43: =B42+1 -> 39 | C43: RIPA NELLY | E43: 1.13 | F43: =PRORRATEO!O45+'PRORRATEO (2)'!O45 -> 397815.78
A44: 8-A | B44: =B43+1 -> 40 | C44: SORIA GODOY | E44: 1.67 | F44: =PRORRATEO!O46+'PRORRATEO (2)'!O46 -> 394973.8
A45: 8-B | B45: =B44+1 -> 41 | C45: D´ALOIA GABRIELA (2) | E45: 1.71 | F45: =PRORRATEO!O47+'PRORRATEO (2)'!O47 -> 157576.82
A46: 8-C | B46: =B45+1 -> 42 | C46: MIÑO GRACIELA (2) | E46: 1.13 | F46: =PRORRATEO!O48+'PRORRATEO (2)'!O48 -> 140395.84
A47: 8-D | B47: =B46+1 -> 43 | C47: CATALANO CLAUDIA | E47: 1.13 | F47: =PRORRATEO!O49+'PRORRATEO (2)'!O49 -> 107350.86
... A78: 14-E | B78: =B77+1 -> 74 | C78: EMA ALVAREZ | E78: 1.13 | F78: =PRORRATEO!O80+'PRORRATEO (2)'!O80 -> 107351.48
E79: =SUM(E4:E78) -> 100

Sheet Recibos 1
B3: RECIBO DE EXPENSAS
B4: CONSORCIO DE PROPIETARIOS DEL EDIFICIO CALLE LORIA 185
B5: CUIT DEL EDIFICIO: 30-57461192-8 | G5: =RESUMEN!B5 -> ADMINISTRADORA: CAROLINA CANCIANI MP:1148
B6: Adminstradora: Carolina Canciani
B8: Metodo de pago: Transferencia
B10: Nombre y apellido: | E10: =PRORRATEO!D6 -> TULA CARLOS (2) | I10: Sello o firma autoriada:
B11: UF: | C11: =PRORRATEO!C6 -> 1 | D11: Dpto: | E11: =PRORRATEO!B6 -> PB B
B16: Total recibido: | G16: =PRORRATEO!O6 -> 252356.01
B20: RECIBO DE EXPENSAS
B21: CONSORCIO DE PROPIETARIOS DEL EDIFICIO CALLE LORIA 185
B22: CUIT DEL EDIFICIO: 30-57461192-8 | G22: PERÍODO: ABRIL
B23: Adminstradora: Carolina Canciani
B25: Metodo de pago: Transferencia
B27: Nombre y apellido: | E27: =PRORRATEO!D7 -> COMBRE ALFREDO | I27: Sello o firma autoriada:
B28: UF: | C28: =PRORRATEO!C7 -> 2 | D28: Dpto: | E28: =PRORRATEO!B7 -> PB C
B33: Total recibido: | G33: =PRORRATEO!O7 -> 110200.02
B38: RECIBO DE EXPENSAS
B39: CONSORCIO DE PROPIETARIOS DEL EDIFICIO CALLE LORIA 185
B40: CUIT DEL EDIFICIO: 30-57461192-8 | G40: PERÍODO: ABRIL
B41: Adminstradora: Carolina Canciani
B43: Metodo de pago: Transferencia
B45: Nombre y apellido: | E45: =PRORRATEO!D8 -> PRGICH FEDERICO | I45: Sello o firma autoriada:
B46: UF: | C46: =PRORRATEO!C8 -> 3 | D46: Dpto: | E46: =PRORRATEO!B8 -> PB D
B51: Total recibido: | G51: =PRORRATEO!O8 -> 107281.03
B55: RECIBO DE EXPENSAS
B56: CONSORCIO DE PROPIETARIOS DEL EDIFICIO CALLE LORIA 185
B57: CUIT DEL EDIFICIO: 30-57461192-8 | G57: PERÍODO: ABRIL
B58: Adminstradora: Carolina Canciani
B60: Metodo de pago: Transferencia
B62: Nombre y apellido: | E62: =PRORRATEO!D9 -> SRUGO DAMIAN | I62: Sello o firma autoriada:
B63: UF: | C63: =PRORRATEO!C9 -> 4 | D63: Dpto: | E63: =PRORRATEO!B9 -> PB E
B68: Total recibido: | G68: =PRORRATEO!O9 -> 115900.04
B73: RECIBO DE EXPENSAS
B74: CONSORCIO DE PROPIETARIOS DEL EDIFICIO CALLE LORIA 185
B75: CUIT DEL EDIFICIO: 30-57461192-8 | G75: PERÍODO: ABRIL
B76: Adminstradora: Carolina Canciani
B78: Metodo de pago: Transferencia
B80: Nombre y apellido: | E80: =PRORRATEO!D10 -> ZELANSNY SILVIA | I80: Sello o firma autoriada:
B81: UF: | C81: =PRORRATEO!C10 -> 5 | D81: Dpto: | E81: =PRORRATEO!B10 -> 1-A
B86: Total recibido: | G86: =PRORRATEO!O10 -> 210226.05
B91: RECIBO DE EXPENSAS
B92: CONSORCIO DE PROPIETARIOS DEL EDIFICIO CALLE LORIA 185
B93: CUIT DEL EDIFICIO: 30-57461192-8 | G93: PERÍODO: ABRIL
B94: Adminstradora: Carolina Canciani
B96: Metodo de pago: Transferencia
B98: Nombre y apellido: | E98: =PRORRATEO!D11 -> PICO HEBE | I98: Sello o firma autoriada:
B99: UF: | C99: =PRORRATEO!C11 -> 6 | D99: Dpto: | E99: =PRORRATEO!B11 -> 1-B
B104: Total recibido: | G104: =PRORRATEO!O11 -> 453713.06

Sheet Recibos 2
B3: RECIBO DE EXPENSAS
B4: CONSORCIO DE PROPIETARIOS DEL EDIFICIO CALLE LORIA 185
B5: CUIT DEL EDIFICIO: 14-57461192-8 | G5: PERÍODO: ABRIL
B6: Adminstradora: Carolina Canciani
B8: Metodo de pago: Transferencia
B10: Nombre y apellido: | E10: =PRORRATEO!D12 -> RAMOS ROSA | I10: Sello o firma autoriada:
B11: UF: | C11: =PRORRATEO!C12 -> 7 | D11: Dpto: | E11: =PRORRATEO!B12 -> 1-C
B16: Total recibido: | G16: =PRORRATEO!O12 -> 107350.07
B20: RECIBO DE EXPENSAS
B21: CONSORCIO DE PROPIETARIOS DEL EDIFICIO CALLE LORIA 185
B22: CUIT DEL EDIFICIO: 14-57461192-8 | G22: PERÍODO: ABRIL
B23: Adminstradora: Carolina Canciani
B25: Metodo de pago: Transferencia
B27: Nombre y apellido: | E27: =PRORRATEO!D13 -> MASIMO HUGO | I27: Sello o firma autoriada:
B28: UF: | C28: =PRORRATEO!C13 -> 8 | D28: Dpto: | E28: =PRORRATEO!B13 -> 1-D
B33: Total recibido: | G33: =PRORRATEO!O13 -> 104129.08
B37: RECIBO DE EXPENSAS
B38: CONSORCIO DE PROPIETARIOS DEL EDIFICIO CALLE LORIA 185
B39: CUIT DEL EDIFICIO: 14-57461192-8 | G39: PERÍODO: ABRIL
B40: Adminstradora: Carolina Canciani
B42: Metodo de pago: Transferencia
B44: Nombre y apellido: | E44: =PRORRATEO!D14 -> BARONE GERARDO | I44: Sello o firma autoriada:
B45: UF: | C45: =PRORRATEO!C14 -> 9 | D45: Dpto: | E45: =PRORRATEO!B14 -> 1-E
B50: Total recibido: | G50: =PRORRATEO!O14 -> 107350.09
B54: RECIBO DE EXPENSAS
B55: CONSORCIO DE PROPIETARIOS DEL EDIFICIO CALLE LORIA 185
B56: CUIT DEL EDIFICIO: 14-57461192-8 | G56: PERÍODO: ABRIL
B57: Adminstradora: Carolina Canciani
B59: Metodo de pago: Transferencia
B61: Nombre y apellido: | E61: =PRORRATEO!D15 -> MONGIELLO CARLOS (2) | I61: Sello o firma autoriada:
B62: UF: | C62: =PRORRATEO!C15 -> 10 | D62: Dpto: | E62: =PRORRATEO!B15 -> 2-A
B67: Total recibido: | G67: =PRORRATEO!O15 -> 153379.1
B72: RECIBO DE EXPENSAS
B73: CONSORCIO DE PROPIETARIOS DEL EDIFICIO CALLE LORIA 185
B74: CUIT DEL EDIFICIO: 14-57461192-8 | G74: PERÍODO: ABRIL
B75: Adminstradora: Carolina Canciani
B77: Metodo de pago: Transferencia
B79: Nombre y apellido: | E79: =PRORRATEO!D16 -> COSTA MONICA | I79: Sello o firma autoriada:
B80: UF: | C80: =PRORRATEO!C16 -> 11 | D80: Dpto: | E80: =PRORRATEO!B16 -> 2-B
B85: Total recibido: | G85: =PRORRATEO!O16 -> 157576.11
B90: RECIBO DE EXPENSAS
B91: CONSORCIO DE PROPIETARIOS DEL EDIFICIO CALLE LORIA 185
B92: CUIT DEL EDIFICIO: 14-57461192-8 | G92: PERÍODO: ABRIL
B93: Adminstradora: Carolina Canciani
B95: Metodo de pago: Transferencia
B97: Nombre y apellido: | E97: =PRORRATEO!D17 -> LOPEZ GUILLERMON | I97: Sello o firma autoriada:
B98: UF: | C98: =PRORRATEO!C17 -> 12 | D98: Dpto: | E98: =PRORRATEO!B17 -> 2-C
B103: Total recibido: | G103: =PRORRATEO!O17 -> 104700.12

Sheet Recibos 3
B3: RECIBO DE EXPENSAS
B4: CONSORCIO DE PROPIETARIOS DEL EDIFICIO CALLE LORIA 185
B5: CUIT DEL EDIFICIO: 14-57461192-8 | G5: PERÍODO: ABRIL
B6: Adminstradora: Carolina Canciani
B8: Metodo de pago: Transferencia
B10: Nombre y apellido: | E10: =PRORRATEO!D18 -> MARTINEZ ADELINA | I10: Sello o firma autoriada:
B11: UF: | C11: =PRORRATEO!C18 -> 13 | D11: Dpto: | E11: =PRORRATEO!B18 -> 2-D
B16: Total recibido: | G16: =PRORRATEO!O18 -> 207123.13
B21: RECIBO DE EXPENSAS
B22: CONSORCIO DE PROPIETARIOS DEL EDIFICIO CALLE LORIA 185
B23: CUIT DEL EDIFICIO: 14-57461192-8 | G23: PERÍODO: ABRIL
B24: Adminstradora: Carolina Canciani
B26: Metodo de pago: Transferencia
B28: Nombre y apellido: | E28: =PRORRATEO!D19 -> QUIROGA ALBA | I28: Sello o firma autoriada:
B29: UF: | C29: =PRORRATEO!C19 -> 14 | D29: Dpto: | E29: =PRORRATEO!B19 -> 2-E
B34: Total recibido: | G34: =PRORRATEO!O19 -> 106476.14
B39: RECIBO DE EXPENSAS
B40: CONSORCIO DE PROPIETARIOS DEL EDIFICIO CALLE LORIA 185
B41: CUIT DEL EDIFICIO: 14-57461192-8 | G41: PERÍODO: ABRIL
B42: Adminstradora: Carolina Canciani
B44: Metodo de pago: Transferencia
B46: Nombre y apellido: | E46: =PRORRATEO!D20 -> MADAR MARIANA | I46: Sello o firma autoriada:
B47: UF: | C47: =PRORRATEO!C20 -> 15 | D47: Dpto: | E47: =PRORRATEO!B20 -> 3-A
B52: Total recibido: | G52: =PRORRATEO!O20 -> 158650.15
B57: RECIBO DE EXPENSAS
B58: CONSORCIO DE PROPIETARIOS DEL EDIFICIO CALLE LORIA 185
B59: CUIT DEL EDIFICIO: 14-57461192-8 | G59: PERÍODO: ABRIL
B60: Adminstradora: Carolina Canciani
B62: Metodo de pago: Transferencia
B64: Nombre y apellido: | E64: =PRORRATEO!D21 -> PIRES NABAIS | I64: Sello o firma autoriada:
B65: UF: | C65: =PRORRATEO!C21 -> 16 | D65: Dpto: | E65: =PRORRATEO!B21 -> 3-B
B70: Total recibido: | G70: =PRORRATEO!O21 -> 162450.16
B75: RECIBO DE EXPENSAS
B76: CONSORCIO DE PROPIETARIOS DEL EDIFICIO CALLE LORIA 185
B77: CUIT DEL EDIFICIO: 14-57461192-8 | G77: PERÍODO: ABRIL
B78: Adminstradora: Carolina Canciani
B80: Metodo de pago: Transferencia
B82: Nombre y apellido: | E82: =PRORRATEO!D22 -> SANABRIA MARIO | I82: Sello o firma autoriada:
B83: UF: | C83: =PRORRATEO!C22 -> 17 | D83: Dpto: | E83: =PRORRATEO!B22 -> 3-C
B88: Total recibido: | G88: =PRORRATEO!O22 -> 104376.17
B93: RECIBO DE EXPENSAS
B94: CONSORCIO DE PROPIETARIOS DEL EDIFICIO CALLE LORIA 185
B95: CUIT DEL EDIFICIO: 14-57461192-8 | G95: PERÍODO: ABRIL
B96: Adminstradora: Carolina Canciani
B98: Metodo de pago: Transferencia
B100: Nombre y apellido: | E100: =PRORRATEO!D23 -> PEROTTI | I100: Sello o firma autoriada:
B101: UF: | C101: =PRORRATEO!C23 -> 18 | D101: Dpto: | E101: =PRORRATEO!B23 -> 3-D
B106: Total recibido: | G106: =PRORRATEO!O23 -> 107350.18

Sheet Recibos 4
B3: RECIBO DE EXPENSAS
B4: CONSORCIO DE PROPIETARIOS DEL EDIFICIO CALLE LORIA 185
B5: CUIT DEL EDIFICIO: 14-57461192-8 | G5: PERÍODO: ABRIL
B6: Adminstradora: Carolina Canciani
B8: Metodo de pago: Transferencia
B10: Nombre y apellido: | E10: =PRORRATEO!D24 -> GOITEA ANTONIO | I10: Sello o firma autoriada:
B11: UF: | C11: =PRORRATEO!C24 -> 19 | D11: Dpto: | E11: =PRORRATEO!B24 -> 3-E
B16: Total recibido: | G16: =PRORRATEO!O24 -> 107350.19
B21: RECIBO DE EXPENSAS
B22: CONSORCIO DE PROPIETARIOS DEL EDIFICIO CALLE LORIA 185
B23: CUIT DEL EDIFICIO: 14-57461192-8 | G23: PERÍODO: ABRIL
B24: Adminstradora: Carolina Canciani
B26: Metodo de pago: Transferencia
B28: Nombre y apellido: | E28: =PRORRATEO!D25 -> BIDABE LOMO | I28: Sello o firma autoriada:
B29: UF: | C29: =PRORRATEO!C25 -> 20 | D29: Dpto: | E29: =PRORRATEO!B25 -> 4-A
B34: Total recibido: | G34: =PRORRATEO!O25 -> 194082.2
B38: RECIBO DE EXPENSAS
B39: CONSORCIO DE PROPIETARIOS DEL EDIFICIO CALLE LORIA 185
B40: CUIT DEL EDIFICIO: 14-57461192-8 | G40: PERÍODO: ABRIL
B41: Adminstradora: Carolina Canciani
B43: Metodo de pago: Transferencia
B45: Nombre y apellido: | E45: =PRORRATEO!D26 -> SICILIANO GRACIELA (2) | I45: Sello o firma autoriada:
B46: UF: | C46: =PRORRATEO!C26 -> 21 | D46: Dpto: | E46: =PRORRATEO!B26 -> 4-B
B51: Total recibido: | G51: =PRORRATEO!O26 -> 218167.21
B57: RECIBO DE EXPENSAS
B58: CONSORCIO DE PROPIETARIOS DEL EDIFICIO CALLE LORIA 185
B59: CUIT DEL EDIFICIO: 14-57461192-8 | G59: PERÍODO: ABRIL
B60: Adminstradora: Carolina Canciani
B62: Metodo de pago: Transferencia
B64: Nombre y apellido: | E64: =PRORRATEO!D27 -> SANCHEZ NELIDA | I64: Sello o firma autoriada:
B65: UF: | C65: =PRORRATEO!C27 -> 22 | D65: Dpto: | E65: =PRORRATEO!B27 -> 4-C
B70: Total recibido: | G70: =PRORRATEO!O27 -> 107350.22
B74: RECIBO DE EXPENSAS
B75: CONSORCIO DE PROPIETARIOS DEL EDIFICIO CALLE LORIA 185
B76: CUIT DEL EDIFICIO: 14-57461192-8 | G76: PERÍODO: ABRIL
B77: Adminstradora: Carolina Canciani
B79: Metodo de pago: Transferencia
B81: Nombre y apellido: | E81: =PRORRATEO!D28 -> TABOADA MARIA (2) | I81: Sello o firma autoriada:
B82: UF: | C82: =PRORRATEO!C28 -> 23 | D82: Dpto: | E82: =PRORRATEO!B28 -> 4-D
B87: Total recibido: | G87: =PRORRATEO!O28 -> 295446.23
B91: RECIBO DE EXPENSAS
B92: CONSORCIO DE PROPIETARIOS DEL EDIFICIO CALLE LORIA 185
B93: CUIT DEL EDIFICIO: 14-57461192-8 | G93: PERÍODO: ABRIL
B94: Adminstradora: Carolina Canciani
B96: Metodo de pago: Transferencia
B98: Nombre y apellido: | E98: =PRORRATEO!D29 -> BEDOYA BEATRIZ | I98: Sello o firma autoriada:
B99: UF: | C99: =PRORRATEO!C29 -> 24 | D99: Dpto: | E99: =PRORRATEO!B29 -> 4-E
B104: Total recibido: | G104: =PRORRATEO!O29 -> 107350.24

Sheet Recibos 5
B4: RECIBO DE EXPENSAS
B5: CONSORCIO DE PROPIETARIOS DEL EDIFICIO CALLE LORIA 185
B6: CUIT DEL EDIFICIO: 14-57461192-8 | G6: PERÍODO: ABRIL
B7: Adminstradora: Carolina Canciani
B9: Metodo de pago: Transferencia
B11: Nombre y apellido: | E11: =PRORRATEO!D30 -> RIZOLI VICTOR | I11: Sello o firma autoriada:
B12: UF: | C12: =PRORRATEO!C30 -> 25 | D12: Dpto: | E12: =PRORRATEO!B30 -> 5-A
B17: Total recibido: | G17: =PRORRATEO!O30 -> 158650.25
B22: RECIBO DE EXPENSAS
B23: CONSORCIO DE PROPIETARIOS DEL EDIFICIO CALLE LORIA 185
B24: CUIT DEL EDIFICIO: 14-57461192-8 | G24: PERÍODO: ABRIL
B25: Adminstradora: Carolina Canciani
B27: Metodo de pago: Transferencia
B29: Nombre y apellido: | E29: =PRORRATEO!D31 -> HOREN KRASNOBRODA | I29: Sello o firma autoriada:
B30: UF: | C30: =PRORRATEO!C31 -> 26 | D30: Dpto: | E30: =PRORRATEO!B31 -> 5-B
B35: Total recibido: | G35: =PRORRATEO!O31 -> -10798.74
B40: RECIBO DE EXPENSAS
B41: CONSORCIO DE PROPIETARIOS DEL EDIFICIO CALLE LORIA 185
B42: CUIT DEL EDIFICIO: 14-57461192-8 | G42: PERÍODO: ABRIL
B43: Adminstradora: Carolina Canciani
B45: Metodo de pago: Transferencia
B47: Nombre y apellido: | E47: =PRORRATEO!D32 -> MUÑOZ HERNAN | I47: Sello o firma autoriada:
B48: UF: | C48: =PRORRATEO!C32 -> 27 | D48: Dpto: | E48: =PRORRATEO!B32 -> 5-C
B53: Total recibido: | G53: =PRORRATEO!O32 -> 107350.27
B57: RECIBO DE EXPENSAS
B58: CONSORCIO DE PROPIETARIOS DEL EDIFICIO CALLE LORIA 185
B59: CUIT DEL EDIFICIO: 14-57461192-8 | G59: PERÍODO: ABRIL
B60: Adminstradora: Carolina Canciani
B62: Metodo de pago: Transferencia
B64: Nombre y apellido: | E64: =PRORRATEO!D33 -> VASTA NANCY | I64: Sello o firma autoriada:
B65: UF: | C65: =PRORRATEO!C33 -> 28 | D65: Dpto: | E65: =PRORRATEO!B33 -> 5-D
B70: Total recibido: | G70: =PRORRATEO!O33 -> 101871.28
B74: RECIBO DE EXPENSAS
B75: CONSORCIO DE PROPIETARIOS DEL EDIFICIO CALLE LORIA 185
B76: CUIT DEL EDIFICIO: 14-57461192-8 | G76: PERÍODO: ABRIL
B77: Adminstradora: Carolina Canciani
B79: Metodo de pago: Transferencia
B81: Nombre y apellido: | E81: =PRORRATEO!D34 -> TRAVERSA | I81: Sello o firma autoriada:
B82: UF: | C82: =PRORRATEO!C34 -> 29 | D82: Dpto: | E82: =PRORRATEO!B34 -> 5-E
B87: Total recibido: | G87: =PRORRATEO!O34 -> 104193.29
B91: RECIBO DE EXPENSAS
B92: CONSORCIO DE PROPIETARIOS DEL EDIFICIO CALLE LORIA 185
B93: CUIT DEL EDIFICIO: 14-57461192-8 | G93: PERÍODO: ABRIL
B94: Adminstradora: Carolina Canciani
B96: Metodo de pago: Transferencia
B98: Nombre y apellido: | E98: =PRORRATEO!D35 -> BAFFONI FABIAN | I98: Sello o firma autoriada:
B99: UF: | C99: =PRORRATEO!C35 -> 30 | D99: Dpto: | E99: =PRORRATEO!B35 -> 6-A
B104: Total recibido: | G104: =PRORRATEO!O35 -> 158650.3
B108: RECIBO DE EXPENSAS
B109: CONSORCIO DE PROPIETARIOS DEL EDIFICIO CALLE LORIA 185
B110: CUIT DEL EDIFICIO: 14-57461192-8 | G110: PERÍODO: ABRIL
B111: Adminstradora: Carolina Canciani
B113: Metodo de pago: Transferencia
B115: Nombre y apellido: | E115: =PRORRATEO!D37 -> PAQUET DE LOPEZ | I115: Sello o firma autoriada:
B116: UF: | C116: =PRORRATEO!C37 -> 31 | D116: Dpto: | E116: =PRORRATEO!B37 -> 6-B
B121: Total recibido: | G121: =PRORRATEO!O37 -> 162450.31

Sheet Recibos 6 
B2: RECIBO DE EXPENSAS
B3: CONSORCIO DE PROPIETARIOS DEL EDIFICIO CALLE LORIA 185
B4: CUIT DEL EDIFICIO: 14-57461192-8 | G4: PERÍODO: ABRIL
B5: Adminstradora: Carolina Canciani
B7: Metodo de pago: Transferencia
B9: Nombre y apellido: | E9: =PRORRATEO!D38 -> BLANCO MABEL | I9: Sello o firma autoriada:
B10: UF: | C10: =PRORRATEO!C38 -> 32 | D10: Dpto: | E10: =PRORRATEO!B38 -> 6-C
B15: Total recibido: | G15: =PRORRATEO!O38 -> 107350.32
B18: RECIBO DE EXPENSAS
B19: CONSORCIO DE PROPIETARIOS DEL EDIFICIO CALLE LORIA 185
B20: CUIT DEL EDIFICIO: 14-57461192-8 | G20: PERÍODO: ABRIL
B21: Adminstradora: Carolina Canciani
B23: Metodo de pago: Transferencia
B25: Nombre y apellido: | E25: =PRORRATEO!D39 -> TESTA IRENE | I25: Sello o firma autoriada:
B26: UF: | C26: =PRORRATEO!C39 -> 33 | D26: Dpto: | E26: =PRORRATEO!B39 -> 6-D
B31: Total recibido: | G31: =PRORRATEO!O39 -> 107350.33
B36: RECIBO DE EXPENSAS
B37: CONSORCIO DE PROPIETARIOS DEL EDIFICIO CALLE LORIA 185
B38: CUIT DEL EDIFICIO: 14-57461192-8 | G38: PERÍODO: ABRIL
B39: Adminstradora: Carolina Canciani
B41: Metodo de pago: Transferencia
B43: Nombre y apellido: | E43: =PRORRATEO!D40 -> QUIROGA ENRIQUE | I43: Sello o firma autoriada:
B44: UF: | C44: =PRORRATEO!C40 -> 34 | D44: Dpto: | E44: =PRORRATEO!B40 -> 6-E
B49: Total recibido: | G49: =PRORRATEO!O40 -> 311307.34
B53: RECIBO DE EXPENSAS
B54: CONSORCIO DE PROPIETARIOS DEL EDIFICIO CALLE LORIA 185
B55: CUIT DEL EDIFICIO: 14-57461192-8 | G55: PERÍODO: ABRIL
B56: Adminstradora: Carolina Canciani
B58: Metodo de pago: Transferencia
B60: Nombre y apellido: | E60: =PRORRATEO!D41 -> ALVAREZ VERONICA (2) | I60: Sello o firma autoriada:
B61: UF: | C61: =PRORRATEO!C41 -> 35 | D61: Dpto: | E61: =PRORRATEO!B41 -> 7-A
B66: Total recibido: | G66: =PRORRATEO!O41 -> 254955.35
B71: RECIBO DE EXPENSAS
B72: CONSORCIO DE PROPIETARIOS DEL EDIFICIO CALLE LORIA 185
B73: CUIT DEL EDIFICIO: 14-57461192-8 | G73: PERÍODO: ABRIL
B74: Adminstradora: Carolina Canciani
B76: Metodo de pago: Transferencia
B78: Nombre y apellido: | E78: =PRORRATEO!D42 -> ROJAS CARMEN | I78: Sello o firma autoriada:
B79: UF: | C79: =PRORRATEO!C42 -> 36 | D79: Dpto: | E79: =PRORRATEO!B42 -> 7-B
B84: Total recibido: | G84: =PRORRATEO!O42 -> 571701.36
B89: RECIBO DE EXPENSAS
B90: CONSORCIO DE PROPIETARIOS DEL EDIFICIO CALLE LORIA 185
B91: CUIT DEL EDIFICIO: 14-57461192-8 | G91: PERÍODO: ABRIL
B92: Adminstradora: Carolina Canciani
B94: Metodo de pago: Transferencia
B96: Nombre y apellido: | E96: =PRORRATEO!D43 -> JUCHNO IRENE | I96: Sello o firma autoriada:
B97: UF: | C97: =PRORRATEO!C43 -> 37 | D97: Dpto: | E97: =PRORRATEO!B43 -> 7-C
B102: Total recibido: | G102: =PRORRATEO!O43 -> 107350.37
B106: RECIBO DE EXPENSAS
B107: CONSORCIO DE PROPIETARIOS DEL EDIFICIO CALLE LORIA 185
B108: CUIT DEL EDIFICIO: 14-57461192-8 | G108: PERÍODO: ABRIL
B109: Adminstradora: Carolina Canciani
B111: Metodo de pago: Transferencia
B113: Nombre y apellido: | E113: =PRORRATEO!D44 -> URIZAR LUQUES | I113: Sello o firma autoriada:
B114: UF: | C114: =PRORRATEO!C44 -> 38 | D114: Dpto: | E114: =PRORRATEO!B44 -> 7-D
B119: Total recibido: | G119: =PRORRATEO!O44 -> 217921.38
B123: RECIBO DE EXPENSAS
B124: CONSORCIO DE PROPIETARIOS DEL EDIFICIO CALLE LORIA 185
B125: CUIT DEL EDIFICIO: 14-57461192-8 | G125: PERÍODO: ABRIL
B126: Adminstradora: Carolina Canciani
B128: Metodo de pago: Transferencia
B130: Nombre y apellido: | E130: =PRORRATEO!D45 -> RIPA NELLY | I130: Sello o firma autoriada:
B131: UF: | C131: =PRORRATEO!C45 -> 39 | D131: Dpto: | E131: =PRORRATEO!B45 -> 7-E
B136: Total recibido: | G136: =PRORRATEO!O45 -> 397815.39
B141: RECIBO DE EXPENSAS
B142: CONSORCIO DE PROPIETARIOS DEL EDIFICIO CALLE LORIA 185
B143: CUIT DEL EDIFICIO: 14-57461192-8 | G143: PERÍODO: ABRIL
B144: Adminstradora: Carolina Canciani
B146: Metodo de pago: Transferencia
B148: Nombre y apellido: | E148: =PRORRATEO!D46 -> SORIA GODOY | I148: Sello o firma autoriada:
B149: UF: | C149: =PRORRATEO!C46 -> 40 | D149: Dpto: | E149: =PRORRATEO!B46 -> 8-A
B154: Total recibido: | G154: =PRORRATEO!O46 -> 394973.4
B158: RECIBO DE EXPENSAS
B159: CONSORCIO DE PROPIETARIOS DEL EDIFICIO CALLE LORIA 185
B160: CUIT DEL EDIFICIO: 14-57461192-8 | G160: PERÍODO: ABRIL
B161: Adminstradora: Carolina Canciani
B163: Metodo de pago: Transferencia
B165: Nombre y apellido: | E165: =PRORRATEO!D47 -> D´ALOIA GABRIELA (2) | I165: Sello o firma autoriada:
B166: UF: | C166: =PRORRATEO!C47 -> 41 | D166: Dpto: | E166: =PRORRATEO!B47 -> 8-B
B171: Total recibido: | G171: =PRORRATEO!O47 -> 157576.41

Sheet Recibos 7
B4: RECIBO DE EXPENSAS
B5: CONSORCIO DE PROPIETARIOS DEL EDIFICIO CALLE LORIA 185
B6: CUIT DEL EDIFICIO: 14-57461192-8 | G6: PERÍODO: ABRIL
B7: Adminstradora: Carolina Canciani
B9: Metodo de pago: Transferencia
B11: Nombre y apellido: | E11: =PRORRATEO!D48 -> MIÑO GRACIELA (2) | I11: Sello o firma autoriada:
B12: UF: | C12: =PRORRATEO!C48 -> 42 | D12: Dpto: | E12: =PRORRATEO!B48 -> 8-C
B17: Total recibido: | G17: =PRORRATEO!O48 -> 140395.42
B20: RECIBO DE EXPENSAS
B21: CONSORCIO DE PROPIETARIOS DEL EDIFICIO CALLE LORIA 185
B22: CUIT DEL EDIFICIO: 14-57461192-8 | G22: PERÍODO: ABRIL
B23: Adminstradora: Carolina Canciani
B25: Metodo de pago: Transferencia
B27: Nombre y apellido: | E27: =PRORRATEO!D49 -> CATALANO CLAUDIA | I27: Sello o firma autoriada:
B28: UF: | C28: =PRORRATEO!C49 -> 43 | D28: Dpto: | E28: =PRORRATEO!B49 -> 8-D
B33: Total recibido: | G33: =PRORRATEO!O49 -> 107350.43
B37: RECIBO DE EXPENSAS
B38: CONSORCIO DE PROPIETARIOS DEL EDIFICIO CALLE LORIA 185
B39: CUIT DEL EDIFICIO: 14-57461192-8 | G39: PERÍODO: ABRIL
B40: Adminstradora: Carolina Canciani
B42: Metodo de pago: Transferencia
B44: Nombre y apellido: | E44: =PRORRATEO!D50 -> ROCA MARISA | I44: Sello o firma autoriada:
B45: UF: | C45: =PRORRATEO!C50 -> 44 | D45: Dpto: | E45: =PRORRATEO!B50 -> 8-E
B50: Total recibido: | G50: =PRORRATEO!O50 -> 107350.44
B54: RECIBO DE EXPENSAS
B55: CONSORCIO DE PROPIETARIOS DEL EDIFICIO CALLE LORIA 185
B56: CUIT DEL EDIFICIO: 14-57461192-8 | G56: PERÍODO: ABRIL
B57: Adminstradora: Carolina Canciani
B59: Metodo de pago: Transferencia
B61: Nombre y apellido: | E61: =PRORRATEO!D51 -> TINEO | I61: Sello o firma autoriada:
B62: UF: | C62: =PRORRATEO!C51 -> 45 | D62: Dpto: | E62: =PRORRATEO!B51 -> 9-A
B67: Total recibido: | G67: =PRORRATEO!O51 -> 158650.45
B71: RECIBO DE EXPENSAS
B72: CONSORCIO DE PROPIETARIOS DEL EDIFICIO CALLE LORIA 185
B73: CUIT DEL EDIFICIO: 14-57461192-8 | G73: PERÍODO: ABRIL
B74: Adminstradora: Carolina Canciani
B76: Metodo de pago: Transferencia
B78: Nombre y apellido: | E78: =PRORRATEO!D52 -> MAZZEO CECILIA | I78: Sello o firma autoriada:
B79: UF: | C79: =PRORRATEO!C52 -> 46 | D79: Dpto: | E79: =PRORRATEO!B52 -> 9-B
B84: Total recibido: | G84: =PRORRATEO!O52 -> 162450.46
B89: RECIBO DE EXPENSAS
B90: CONSORCIO DE PROPIETARIOS DEL EDIFICIO CALLE LORIA 185
B91: CUIT DEL EDIFICIO: 14-57461192-8 | G91: PERÍODO: ABRIL
B92: Adminstradora: Carolina Canciani
B94: Metodo de pago: Transferencia
B96: Nombre y apellido: | E96: =PRORRATEO!D53 -> GARCIA JORGE | I96: Sello o firma autoriada:
B97: UF: | C97: =PRORRATEO!C53 -> 47 | D97: Dpto: | E97: =PRORRATEO!B53 -> 9-C
B102: Total recibido: | G102: =PRORRATEO!O53 -> 107350.47
B107: RECIBO DE EXPENSAS
B108: CONSORCIO DE PROPIETARIOS DEL EDIFICIO CALLE LORIA 185
B109: CUIT DEL EDIFICIO: 14-57461192-8 | G109: PERÍODO: ABRIL
B110: Adminstradora: Carolina Canciani
B112: Metodo de pago: Transferencia
B114: Nombre y apellido: | E114: =PRORRATEO!D54 -> ROSSI NORMA | I114: Sello o firma autoriada:
B115: UF: | C115: =PRORRATEO!C54 -> 48 | D115: Dpto: | E115: =PRORRATEO!B54 -> 9-D
B120: Total recibido: | G120: =PRORRATEO!O54 -> 104193.48
B125: RECIBO DE EXPENSAS
B126: CONSORCIO DE PROPIETARIOS DEL EDIFICIO CALLE LORIA 185
B127: CUIT DEL EDIFICIO: 14-57461192-8 | G127: PERÍODO: ABRIL
B128: Adminstradora: Carolina Canciani
B130: Metodo de pago: Transferencia
B132: Nombre y apellido: | E132: =PRORRATEO!D55 -> AGNESE PEDRO | I132: Sello o firma autoriada:
B133: UF: | C133: =PRORRATEO!C55 -> 49 | D133: Dpto: | E133: =PRORRATEO!B55 -> 9-E
B138: Total recibido: | G138: =PRORRATEO!O55 -> 107350.49
B142: RECIBO DE EXPENSAS
B143: CONSORCIO DE PROPIETARIOS DEL EDIFICIO CALLE LORIA 185
B144: CUIT DEL EDIFICIO: 14-57461192-8 | G144: PERÍODO: ABRIL
B145: Adminstradora: Carolina Canciani
B147: Metodo de pago: Transferencia
B149: Nombre y apellido: | E149: =PRORRATEO!D56 -> ABDALA (1) | I149: Sello o firma autoriada:
B150: UF: | C150: =PRORRATEO!C56 -> 50 | D150: Dpto: | E150: =PRORRATEO!B56 -> 10-A
B155: Total recibido: | G155: =PRORRATEO!O56 -> 151292.5
B160: RECIBO DE EXPENSAS
B161: CONSORCIO DE PROPIETARIOS DEL EDIFICIO CALLE LORIA 185
B162: CUIT DEL EDIFICIO: 14-57461192-8 | G162: PERÍODO: ABRIL
B163: Adminstradora: Carolina Canciani
B165: Metodo de pago: Transferencia
B167: Nombre y apellido: | E167: =PRORRATEO!D57 -> DEL RIO GUSTAVO | I167: Sello o firma autoriada:
B168: UF: | C168: =PRORRATEO!C57 -> 51 | D168: Dpto: | E168: =PRORRATEO!B57 -> 10-B
B173: Total recibido: | G173: =PRORRATEO!O57 -> 329774.51

Sheet Recibos 8
B3: RECIBO DE EXPENSAS
B4: CONSORCIO DE PROPIETARIOS DEL EDIFICIO CALLE LORIA 185
B5: CUIT DEL EDIFICIO: 14-57466192-8 | G5: PERÍODO: ABRIL
B6: Adminstradora: Carolina Canciani
B8: Metodo de pago: Transferencia
B10: Nombre y apellido: | E10: =PRORRATEO!D58 -> MIGLIORISI ANDREA | I10: Sello o firma autoriada:
B11: UF: | C11: =PRORRATEO!C58 -> 52 | D11: Dpto: | E11: =PRORRATEO!B58 -> 10-C
B16: Total recibido: | G16: =PRORRATEO!O58 -> 107350.52
B20: RECIBO DE EXPENSAS
B21: CONSORCIO DE PROPIETARIOS DEL EDIFICIO CALLE LORIA 185
B22: CUIT DEL EDIFICIO: 14-57466192-8 | G22: PERÍODO: ABRIL
B23: Adminstradora: Carolina Canciani
B25: Metodo de pago: Transferencia
B27: Nombre y apellido: | E27: =PRORRATEO!D59 -> EHGATNER ANA | I27: Sello o firma autoriada:
B28: UF: | C28: =PRORRATEO!C59 -> 53 | D28: Dpto: | E28: =PRORRATEO!B59 -> 10-D
B33: Total recibido: | G33: =PRORRATEO!O59 -> 107350.53
B38: RECIBO DE EXPENSAS
B39: CONSORCIO DE PROPIETARIOS DEL EDIFICIO CALLE LORIA 185
B40: CUIT DEL EDIFICIO: 14-57466192-8 | G40: PERÍODO: ABRIL
B41: Adminstradora: Carolina Canciani
B43: Metodo de pago: Transferencia
B45: Nombre y apellido: | E45: =PRORRATEO!D60 -> DEBENEDETTI C | I45: Sello o firma autoriada:
B46: UF: | C46: =PRORRATEO!C60 -> 54 | D46: Dpto: | E46: =PRORRATEO!B60 -> 10-E
B51: Total recibido: | G51: =PRORRATEO!O60 -> 107350.54
B56: RECIBO DE EXPENSAS
B57: CONSORCIO DE PROPIETARIOS DEL EDIFICIO CALLE LORIA 185
B58: CUIT DEL EDIFICIO: 14-57466192-8 | G58: PERÍODO: ABRIL
B59: Adminstradora: Carolina Canciani
B61: Metodo de pago: Transferencia
B63: Nombre y apellido: | E63: =PRORRATEO!D61 -> MENDIBURU JORGE | I63: Sello o firma autoriada:
B64: UF: | C64: =PRORRATEO!C61 -> 55 | D64: Dpto: | E64: =PRORRATEO!B61 -> 11-A
B69: Total recibido: | G69: =PRORRATEO!O61 -> 158650.55
B73: RECIBO DE EXPENSAS
B74: CONSORCIO DE PROPIETARIOS DEL EDIFICIO CALLE LORIA 185
B75: CUIT DEL EDIFICIO: 14-57466192-8 | G75: PERÍODO: ABRIL
B76: Adminstradora: Carolina Canciani
B78: Metodo de pago: Transferencia
B80: Nombre y apellido: | E80: =PRORRATEO!D62 -> GALLUCCI CARMELA | I80: Sello o firma autoriada:
B81: UF: | C81: =PRORRATEO!C62 -> 56 | D81: Dpto: | E81: =PRORRATEO!B62 -> 11-B
B86: Total recibido: | G86: =PRORRATEO!O62 -> 337881.56
B91: RECIBO DE EXPENSAS
B92: CONSORCIO DE PROPIETARIOS DEL EDIFICIO CALLE LORIA 185
B93: CUIT DEL EDIFICIO: 14-57466192-8 | G93: PERÍODO: ABRIL
B94: Adminstradora: Carolina Canciani
B96: Metodo de pago: Transferencia
B98: Nombre y apellido: | E98: =PRORRATEO!D63 -> CABAÑAS MARIA SOLEDAD | I98: Sello o firma autoriada:
B99: UF: | C99: =PRORRATEO!C63 -> 57 | D99: Dpto: | E99: =PRORRATEO!B63 -> 11-C
B104: Total recibido: | G104: =PRORRATEO!O63 -> 107350.57
B108: RECIBO DE EXPENSAS
B109: CONSORCIO DE PROPIETARIOS DEL EDIFICIO CALLE LORIA 185
B110: CUIT DEL EDIFICIO: 14-57466192-8 | G110: PERÍODO: ABRIL
B111: Adminstradora: Carolina Canciani
B113: Metodo de pago: Transferencia
B115: Nombre y apellido: | E115: =PRORRATEO!D64 -> GUARINO | I115: Sello o firma autoriada:
B116: UF: | C116: =PRORRATEO!C64 -> 58 | D116: Dpto: | E116: =PRORRATEO!B64 -> 11-D
B121: Total recibido: | G121: =PRORRATEO!O64 -> 104195.58
B125: RECIBO DE EXPENSAS
B126: CONSORCIO DE PROPIETARIOS DEL EDIFICIO CALLE LORIA 185
B127: CUIT DEL EDIFICIO: 14-57466192-8 | G127: PERÍODO: ABRIL
B128: Adminstradora: Carolina Canciani
B130: Metodo de pago: Transferencia
B132: Nombre y apellido: | E132: =PRORRATEO!D65 -> MARQUEZ VERONICA | I132: Sello o firma autoriada:
B133: UF: | C133: =PRORRATEO!C65 -> 59 | D133: Dpto: | E133: =PRORRATEO!B65 -> 11-E
B138: Total recibido: | G138: =PRORRATEO!O65 -> 107350.59

Sheet Recibos 9
B3: RECIBO DE EXPENSAS
B4: CONSORCIO DE PROPIETARIOS DEL EDIFICIO CALLE LORIA 185
B5: CUIT DEL EDIFICIO: 14-57466192-8 | G5: PERÍODO: ABRIL
B6: Adminstradora: Carolina Canciani
B8: Metodo de pago: Transferencia
B10: Nombre y apellido: | E10: =PRORRATEO!D66 -> BRAU HECTOR | I10: Sello o firma autoriada:
B11: UF: | C11: =PRORRATEO!C66 -> 60 | D11: Dpto: | E11: =PRORRATEO!B66 -> 12-A
B16: Total recibido: | G16: =PRORRATEO!O66 -> 158650.6
B21: RECIBO DE EXPENSAS
B22: CONSORCIO DE PROPIETARIOS DEL EDIFICIO CALLE LORIA 185
B23: CUIT DEL EDIFICIO: 14-57466192-8 | G23: PERÍODO: ABRIL
B24: Adminstradora: Carolina Canciani
B26: Metodo de pago: Transferencia
B28: Nombre y apellido: | E28: =PRORRATEO!D67 -> ZERBA MARCELO | I28: Sello o firma autoriada:
B29: UF: | C29: =PRORRATEO!C67 -> 61 | D29: Dpto: | E29: =PRORRATEO!B67 -> 12-B
B34: Total recibido: | G34: =PRORRATEO!O67 -> 329774.61
B38: RECIBO DE EXPENSAS
B39: CONSORCIO DE PROPIETARIOS DEL EDIFICIO CALLE LORIA 185
B40: CUIT DEL EDIFICIO: 14-57466192-8 | G40: PERÍODO: ABRIL
B41: Adminstradora: Carolina Canciani
B43: Metodo de pago: Transferencia
B45: Nombre y apellido: | E45: =PRORRATEO!D68 -> VERMINETTI | I45: Sello o firma autoriada:
B46: UF: | C46: =PRORRATEO!C68 -> 62 | D46: Dpto: | E46: =PRORRATEO!B68 -> 12-C
B51: Total recibido: | G51: =PRORRATEO!O68 -> 104193.62
B54: RECIBO DE EXPENSAS
B55: CONSORCIO DE PROPIETARIOS DEL EDIFICIO CALLE LORIA 185
B56: CUIT DEL EDIFICIO: 14-57466192-8 | G56: PERÍODO: ABRIL
B57: Adminstradora: Carolina Canciani
B59: Metodo de pago: Transferencia
B61: Nombre y apellido: | E61: =PRORRATEO!D69 -> RIQUELME | I61: Sello o firma autoriada:
B62: UF: | C62: =PRORRATEO!C69 -> 63 | D62: Dpto: | E62: =PRORRATEO!B69 -> 12-D
B67: Total recibido: | G67: =PRORRATEO!O69 -> 107350.63
B71: RECIBO DE EXPENSAS
B72: CONSORCIO DE PROPIETARIOS DEL EDIFICIO CALLE LORIA 185
B73: CUIT DEL EDIFICIO: 14-57466192-8 | G73: PERÍODO: ABRIL
B74: Adminstradora: Carolina Canciani
B76: Metodo de pago: Transferencia
B78: Nombre y apellido: | E78: =PRORRATEO!D70 -> RODRIGUEZ NESTOR | I78: Sello o firma autoriada:
B79: UF: | C79: =PRORRATEO!C70 -> 64 | D79: Dpto: | E79: =PRORRATEO!B70 -> 12-E
B84: Total recibido: | G84: =PRORRATEO!O70 -> 107350.64
B88: RECIBO DE EXPENSAS
B89: CONSORCIO DE PROPIETARIOS DEL EDIFICIO CALLE LORIA 185
B90: CUIT DEL EDIFICIO: 14-57466192-8 | G90: PERÍODO: ABRIL
B91: Adminstradora: Carolina Canciani
B93: Metodo de pago: Transferencia
B95: Nombre y apellido: | E95: =PRORRATEO!D71 -> ZIMERMANN LEON (2) | I95: Sello o firma autoriada:
B96: UF: | C96: =PRORRATEO!C71 -> 65 | D96: Dpto: | E96: =PRORRATEO!B71 -> 13-A
B101: Total recibido: | G101: =PRORRATEO!O71 -> 158646.65

Sheet Recibos 10
B2: RECIBO DE EXPENSAS
B3: CONSORCIO DE PROPIETARIOS DEL EDIFICIO CALLE LORIA 185
B4: CUIT DEL EDIFICIO: 14-57466192-8 | G4: PERÍODO: ABRIL
B5: Adminstradora: Carolina Canciani
B7: Metodo de pago: Transferencia
B9: Nombre y apellido: | E9: =PRORRATEO!D72 -> DE GRACIA | I9: Sello o firma autoriada:
B10: UF: | C10: =PRORRATEO!C72 -> 66 | D10: Dpto: | E10: =PRORRATEO!B72 -> 13-B
B15: Total recibido: | G15: =PRORRATEO!O72 -> 157676.66
B18: RECIBO DE EXPENSAS
B19: CONSORCIO DE PROPIETARIOS DEL EDIFICIO CALLE LORIA 185
B20: CUIT DEL EDIFICIO: 14-57466192-8 | G20: PERÍODO: ABRIL
B21: Adminstradora: Carolina Canciani
B23: Metodo de pago: Transferencia
B25: Nombre y apellido: | E25: =PRORRATEO!D73 -> LAUMAN JOSE | I25: Sello o firma autoriada:
B26: UF: | C26: =PRORRATEO!C73 -> 67 | D26: Dpto: | E26: =PRORRATEO!B73 -> 13-C
B31: Total recibido: | G31: =PRORRATEO!O73 -> 107350.67
B34: RECIBO DE EXPENSAS
B35: CONSORCIO DE PROPIETARIOS DEL EDIFICIO CALLE LORIA 185
B36: CUIT DEL EDIFICIO: 14-57466192-8 | G36: PERÍODO: ABRIL
B37: Adminstradora: Carolina Canciani
B39: Metodo de pago: Transferencia
B41: Nombre y apellido: | E41: =PRORRATEO!D74 -> MARENZI MARIA | I41: Sello o firma autoriada:
B42: UF: | C42: =PRORRATEO!C74 -> 68 | D42: Dpto: | E42: =PRORRATEO!B74 -> 13-D
B47: Total recibido: | G47: =PRORRATEO!O74 -> 107350.68
B52: RECIBO DE EXPENSAS
B53: CONSORCIO DE PROPIETARIOS DEL EDIFICIO CALLE LORIA 185
B54: CUIT DEL EDIFICIO: 14-57466192-8 | G54: PERÍODO: ABRIL
B55: Adminstradora: Carolina Canciani
B57: Metodo de pago: Transferencia
B59: Nombre y apellido: | E59: =PRORRATEO!D75 -> DI SERA VANESA | I59: Sello o firma autoriada:
B60: UF: | C60: =PRORRATEO!C75 -> 69 | D60: Dpto: | E60: =PRORRATEO!B75 -> 13-E
B65: Total recibido: | G65: =PRORRATEO!O75 -> 104193.69
B70: RECIBO DE EXPENSAS
B71: CONSORCIO DE PROPIETARIOS DEL EDIFICIO CALLE LORIA 185
B72: CUIT DEL EDIFICIO: 14-57466192-8 | G72: PERÍODO: ABRIL
B73: Adminstradora: Carolina Canciani
B75: Metodo de pago: Transferencia
B77: Nombre y apellido: | E77: =PRORRATEO!D76 -> GUASTAVINO ELSA | I77: Sello o firma autoriada:
B78: UF: | C78: =PRORRATEO!C76 -> 70 | D78: Dpto: | E78: =PRORRATEO!B76 -> 14-A
B83: Total recibido: | G83: =PRORRATEO!O76 -> 158650.7
B87: RECIBO DE EXPENSAS
B88: CONSORCIO DE PROPIETARIOS DEL EDIFICIO CALLE LORIA 185
B89: CUIT DEL EDIFICIO: 14-57466192-8 | G89: PERÍODO: ABRIL
B90: Adminstradora: Carolina Canciani
B92: Metodo de pago: Transferencia
B94: Nombre y apellido: | E94: =PRORRATEO!D77 -> RODRIGUEZ CARLOS | I94: Sello o firma autoriada:
B95: UF: | C95: =PRORRATEO!C77 -> 71 | D95: Dpto: | E95: =PRORRATEO!B77 -> 14-B
B100: Total recibido: | G100: =PRORRATEO!O77 -> 162450.71
B104: RECIBO DE EXPENSAS
B105: CONSORCIO DE PROPIETARIOS DEL EDIFICIO CALLE LORIA 185
B106: CUIT DEL EDIFICIO: 14-57466192-8 | G106: PERÍODO: ABRIL
B107: Adminstradora: Carolina Canciani
B109: Metodo de pago: Transferencia
B111: Nombre y apellido: | E111: =PRORRATEO!D78 -> FERNANDEZ MONICA (EN JUICIO) | I111: Sello o firma autoriada:
B112: UF: | C112: =PRORRATEO!C78 -> 72 | D112: Dpto: | E112: =PRORRATEO!B78 -> 14-C
B117: Total recibido: | G117: =PRORRATEO!O78 -> 2676237.7
B121: RECIBO DE EXPENSAS
B122: CONSORCIO DE PROPIETARIOS DEL EDIFICIO CALLE LORIA 185
B123: CUIT DEL EDIFICIO: 14-57466192-8 | G123: PERÍODO: ABRIL
B124: Adminstradora: Carolina Canciani
B126: Metodo de pago: Transferencia
B128: Nombre y apellido: | E128: =PRORRATEO!D79 -> DE PAVIK ANGELA | I128: Sello o firma autoriada:
B129: UF: | C129: =PRORRATEO!C79 -> 73 | D129: Dpto: | E129: =PRORRATEO!B79 -> 14-D
B134: Total recibido: | G134: =PRORRATEO!O79 -> 105975.73
B139: RECIBO DE EXPENSAS
B140: CONSORCIO DE PROPIETARIOS DEL EDIFICIO CALLE LORIA 185
B141: CUIT DEL EDIFICIO: 14-57466192-8 | G141: PERÍODO: ABRIL
B142: Adminstradora: Carolina Canciani
B144: Metodo de pago: Transferencia
B146: Nombre y apellido: | E146: =PRORRATEO!D80 -> EMA ALVAREZ | I146: Sello o firma autoriada:
B147: UF: | C147: =PRORRATEO!C80 -> 74 | D147: Dpto: | E147: =PRORRATEO!B80 -> 14-E
B152: Total recibido: | G152: =PRORRATEO!O80 -> 107350.74
