Workbook

Sheet detalle y gastos
B1: Domicilio : Dr melo 2958 - 8vo piso - con cita previa
B2: CANCIANI, Carolina | C2: MP:1148
B3: Tel. 11 5320-2676
B4: consorciosrc13@gmail.com
A7: PICHINCHA 267 - LANUS OESTE | E7: Liquidacion mes de JUNIO | F7: Vto. 14/07
A10: GASTOS ORDINARIOS
A11: ABONOS y SERVICIOS | E11: ESTADO FINACIERO
A12: AYSA | C12: 78921.33 | E12: Saldo anterior - | F12: =-1484152 -> -1484152
A13: FEDERACION PATRONAL SEGUROS S.A. | C13: 92086 | E13: Ingreso por pago de expensas en término | F13: ='prorrateo '!F10 -> 856053.07
A14: RC Adm Cons CANCIANI, Carolina | B14: Honorarios Administracion | C14: 33600 | E14: Egresos por gastos del mes | F14: =-(C38) -> -535928.1
A15: FLOW - INTERNET CAMARA | C15: 39299 | E15: Edesur | F15: =-EDESUR!E7 -> -196109.41
A16: METROGAS | C16: 70904.02 | E16: Total abonado de Edesur | F16: =EDESUR!E24 -> 648604.23
A17: FERRETERIA V&A | C17: 5000
A18: TSG - MES DE JUNIO | C18: 12287
A19: ARBA - CUOTA 2 | C19: 6317.6 | H19: tsg y flow a ajustar - repetimos montos
C20: =SUM(C12:C19) -> 338414.95 | E20: Saldo al cierre $ (pesos) | F20: =SUM(F12:F19) -> -711532.21
A21: LIMPIEZA / MANTENIMIENTO / GASTOS GENERALES
A22: SERVICIO DE LIMPIEZA SRA. MONICA GOROSITO | C22: =65203*5%+65203 -> 68463.15
A23: CERRRAJERIA - ARREGLO CERRADURA PORTON | C23: 40000
A24: SERVISUR - CAMBIO DE FOTCELULA - MANO DE OBRA Y MATERIAL | C24: =25000+7500 -> 32500
A25: SALVATIERRA MATIAS - DESOBSTRUCCION COLECTORA CLOACAL | C25: 56550
A26: PREVISION ORDINARIA | C26: 0
C27: =SUM(C21:C26) -> 197513.15
A28: TOTAL GASTOS ORDINARIOS (A) | C28: =+C27+C20 -> 535928.1
A29: GASTOS EXTRAORDINARIOS
A30: GASTOS EXTRAORDINARIOS
C32: 0
C33: 0
C36: 0
A37: TOTAL GASTOS EXTRAORDINARIOS (B) | C37: =SUM(C32:C36) -> 0
A38: Egresos ordinarios | C38: =C28-C26 -> 535928.1
A39: Total gastos ordinarios a prorratear | C39: =+C28 -> 535928.1
A40: TOTAL GENERAL DE GASTOS (A) + (B) | C40: =+C28+C37 -> 535928.1

Sheet prorrateo 
A1: CORRESPONDE A: | G1: GASTOS ORDINARIOS A PRORRATEAR: | K1: 550928.1
A2: ='detalle y gastos'!E7 -> Liquidacion mes de JUNIO | G2: GASTOS EXTRAORDINARIOS A PRORRATEAR:
A3: UF | B3: Dpto. | C3: Propietario | D3: porcentaje | E3: Saldo | F3: Pagos | G3: DEUDA | H3: Intereses | I3: Expensa | J3: Expensas | K3: Expensas | L3: PRIMER VTO | M3: SEGUNDO
D4: % | E4: Anterior | F4: Exp. | H4: 0.04 | I4: Ext. Por OBRA | J4: Ordinarias | K4: Extraordinarias | L4: ='detalle y gastos'!F7 -> Vto. 14/07 | M4: VTO
A5: 1 | B5: 1 | C5: GABRIEL | E5: 86036.752 | F5: =E5 -> 86036.752 | G5: =E5-F5 -> 0 | H5: =IF(G5>0,G5*4%,0) -> 0 | I5: 0 | J5: =K$1/5 -> 110185.62 | K5: =K2*D5 -> 0 | L5: =J5+K5+H5+G5 -> 110185.62 | M5: =L5*4%+L5 -> 114593.04
A6: 2 | B6: 2 | C6: CAMILA | E6: 86036.752 | F6: =E6 -> 86036.752 | G6: =E6-F6 -> 0 | H6: =IF(G6>0,G6*4%,0) -> 0 | I6: 0 | J6: =K$1/5 -> 110185.62 | K6: =K2*D6 -> 0 | L6: =J6+K6+H6+G6 -> 110185.62 | M6: =L6*4%+L6 -> 114593.04
A7: 3 | B7: 3 | C7: MARY | E7: 159545.88 | F7: =E7 -> 159545.88 | G7: =E7-F7 -> 0 | H7: =IF(G7>0,G7*4%,0) -> 0 | I7: 0 | J7: =K$1/5 -> 110185.62 | K7: =K2*D7 -> 0 | L7: =J7+K7+H7+G7 -> 110185.62 | M7: =L7*4%+L7 -> 114593.04
A8: 4 | B8: 4 | C8: AGUSTIN | E8: 438396.93 | F8: =E8 -> 438396.93 | G8: =E8-F8 -> 0 | H8: =IF(G8>0,G8*4%,0) -> 0 | I8: 0 | J8: =K$1/5 -> 110185.62 | K8: =K2*D8 -> 0 | L8: =J8+K8+H8+G8 -> 110185.62 | M8: =L8*4%+L8 -> 114593.04
A9: 5 | B9: 5 | C9: MARTIN | E9: 86036.752 | F9: =E9 -> 86036.752 | G9: =E9-F9 -> 0 | H9: =IF(G9>0,G9*4%,0) -> 0 | I9: 0 | J9: =K$1/5 -> 110185.62 | K9: =K2*D9 -> 0 | L9: =J9+K9+H9+G9 -> 110185.62 | M9: =L9*4%+L9 -> 114593.04
A10: TOTALES | D10: =SUM(D5:D9) -> 0 | E10: =SUM(E5:E9) -> 856053.07 | F10: =SUM(F5:F9) -> 856053.07 | G10: =SUM(G5:G9) -> 0 | H10: =SUM(H5:H9) -> 0 | I10: =SUM(I5:I9) -> 0 | J10: =SUM(J5:J9) -> 550928.1 | K10: =SUM(K5:K9) -> 0 | ... M10: =SUM(M5:M9) -> 572965.22

Sheet EDESUR
K3: GASTOS COMUNES | M3: =E6 -> 59261.97
C4: EDESUR FACTURA 1: | E4: 79470.88 | G4: UF | H4: Dpto. | I4: Propietario | K4: GASTOS COMUNES (SIN INCLUIR CONSUMO DE UF 3) | O4: =M3-K8 -> -23231.48
C5: EDESUR FACTURA 2: | E5: 57376.56
C6: EDESUR FACTURA 3: | E6: 59261.97 | G6: 1 | H6: 1 | I6: GABRIEL | J6: GABRIEL | K6: =E4/2 -> 39735.44 | L6: =O$4/5 -> -4646.296 | N6: =SUM(K6:M6) -> 35089.144
E7: =SUM(E4:E6) -> 196109.41 | G7: 2 | H7: 2 | I7: CAMILA | J7: CAMILA | K7: =E5/2 -> 28688.28 | L7: =O$4/5 -> -4646.296 | N7: =SUM(K7:M7) -> 24041.984
G8: 3 | H8: 3 | I8: MARY | J8: MARY | K8: 82493.45 | L8: =O$4/5 -> -4646.296 | N8: =SUM(K8:M8) -> 77847.154
G9: 4 | H9: 4 | I9: AGUSTIN | J9: AGUSTIN | K9: =E5/2 -> 28688.28 | L9: =O$4/5 -> -4646.296 | N9: =SUM(K9:M9) -> 24041.984
G10: 5 | H10: 5 | I10: MARTIN | J10: MARTIN | K10: =E4/2 -> 39735.44 | L10: =O$4/5 -> -4646.296 | N10: =SUM(K10:M10) -> 35089.144
L11: =O$4/5 -> -4646.296
C13: LOS GASTOS COMUNES INCLUYEN: CONSUMO DE LA BOMBA, LUCES DE ESCALERAS, TERRAZAS, COCHERAS Y PUERTAS, CAMARAS E INTERNET
N14: =SUM(N6:N13) -> 196109.41
C17: SALDO ANTERIOR | E17: ABONADO | F17: SALDO A ABONAR | H17: TOTAL
C18: 199078.77 | E18: =C18 -> 199078.77 | F18: =N6 -> 35089.144 | H18: =C18-E18+F18 -> 35089.144
C19: 131973.81 | E19: =C19 -> 131973.81 | F19: =N7 -> 24041.984 | H19: =C19-E19+F19 -> 24041.984
C20: 96846.074 | E20: =C20 -> 96846.074 | F20: =N8 -> 77847.154 | H20: =C20-E20+F20 -> 77847.154
C21: 131973.81 | E21: =C21 -> 131973.81 | F21: =N9 -> 24041.984 | H21: =C21-E21+F21 -> 24041.984
C22: 88731.754 | E22: =C22 -> 88731.754 | F22: =N10 -> 35089.144 | H22: =C22-E22+F22 -> 35089.144
E24: =SUM(E18:E23) -> 648604.23

Sheet Hoja1

Sheet extraordinaria
A1: GASTOS EXTRAORDINARIOS
A2: USD: | D2: 565
A3: UF | B3: Dpto. | C3: Propietario | D3: porcentaje | E3: CUOTA 1 | F3: INTERES | G3: DEUDA
A5: 1 | B5: A | C5: DUARTE | D5: 0.1512 | E5: 85 | F5: 0 | G5: 0
A6: 2 | B6: B | C6: BESARON | D6: 0.1569 | E6: 89 | F6: 0 | G6: 0
A7: 3 | B7: C | C7: LASTERO | D7: 0.1582 | E7: 89 | F7: 0 | G7: 0
A8: 4 | B8: D | C8: ECHICHURRE | D8: 0.198 | E8: 112 | F8: 0 | G8: 0
A9: 5 | B9: E | C9: SPERANZA | D9: 0.1592 | E9: 90 | F9: 0 | G9: 0
A10: 6 | B10: F | C10: BACHETTI | D10: 0.1765 | E10: 100 | F10: 0 | G10: 0
A11: TOTALES | D11: 1 | E11: 565 | F11: $ - | G11: $ -
