Workbook

Sheet RESUMEN
B1: MAIL: brisasdeadroguerc@gmail.com
B2: CELULAR: +54 9 11 2640-1829
B3: Titular: CONSORCIO DE PROPIETARIOS LAS BRISAS - ADROGUE - Santander Río - Cuenta Corriente Nº 221-007370/9
B4: CBU.: 0720221820000000737090 * ALIAS: MARTES.POLO.IDEAL
B5: PERÍODO: Agosto - ADMINISTRADORA: CAROLINA CANCIANI MP:1148
B6: CUIT.: 30-71618269-6
B7: CONSORCIO DE PROPIETARIOS LAS BRISAS - ADROGUE
A9: VTO 30/09
A14: ESTIMADOS: LES RECORDAMOS QUE ES OBLIGATORIO INFORMAR POR CORREO ELECTRÓNICO EL PAGO DE LAS EXPENSAS. APROVECHAMOS LA OCASIÓN PARA REITERAR UN PUNTO CLAVE QUE AYUDA A EVITAR ERRORES EN LA IMPUTACIÓN DE LOS PAGOS. EL SISTEMA QUE UTILIZAMOS ASIGNA CENTAVOS ÚNICOS A CADA UNIDAD FUNCIONAL (UF) O LOTE, LO QUE NOS PERMITE IDENTIFICAR AUTOMÁTICAMENTE A CUÁL CORRESPONDE CADA TRANSFERENCIA. ES DECIR, CADA UF/LOTE TIENE UN NÚMERO ESPECÍFICO DE CENTAVOS QUE FUNCIONA COMO IDENTIFICADOR. POR EJEMPLO, SI SU LOTE ES EL 45, EL IMPORTE A ABONAR DEBERÁ TERMINAR EN $...,45. EN CASO DE TENER MÁS DE UN LOTE (POR EJEMPLO, EL 3 Y EL 78), CADA UNO TENDRÁ SU PROPIO CÓDIGO DE CENTAVOS. EN ESTOS CASOS, LES PEDIMOS QUE REALICEN UNA TRANSFERENCIA INDIVIDUAL POR CADA LOTE, RESPETANDO LOS IMPORTES CON SUS CENTAVOS CORRESPONDIENTES. SABEMOS QUE, POR COMODIDAD, A VECES SE OPTA POR ENVIAR TODO EN UNA ÚNICA TRANSFERENCIA, PERO ESTO PUEDE GENERAR CONFUSIÓN O ERRORES EN LA ASIGNACIÓN AUTOMÁTICA. SEPARAR LOS PAGOS NOS PERMITE ASEGURAR QUE CADA UNO SE IMPUTE CORRECTAMENTE. AGRADECEMOS MUCHÍSIMO SU COLABORACIÓN PARA SEGUIR MANTENIENDO EL ORDEN. MUCHAS GRACIAS.
A21: GASTOS ORDINARIOS UNIDADES FUNCIONALES:
A22: HABERES ENCARGADOS
A23: Sueldo intendencia - Maximiliano Abbruzzese - Agosto | D23: 1311455.5
A24: Deducciones mes de Agosto | D24: -285241.6
A25: Redondeo mes de Agosto | D25: 0.1
A26: Neto | D26: =SUM(D23:D25) -> 1026214 | E26: Aun no se transf
A27: Honorarios arquitectura - Srta. Burgos Oros Johanna Melanie - Fc. 00000085 | D27: 630000 | E27: Transf 06/08
A28: Neto | D28: =SUM(D27:D27) -> 630000
A29: TOTAL SUELDOS | E29: =D26+D28 -> 1656214
A30: CARGAS SOCIALES - APORTES Y CONTRIBUCIONES
A31: ARCA - Mes de Julio | D31: 601216.04 | E31: Debito 07/08
A32: Sindicatos mes de Julio | B32: Fatheryh | D32: 59015.5 | E32: Debito 12/08
A33: =A32 -> Sindicatos mes de Julio | B33: Suther | D33: 109872.62 | E33: =E32 -> Debito 12/08
A34: =A33 -> Sindicatos mes de Julio | B34: Seracarh | D34: 6557.28 | E34: =E33 -> Debito 12/08
A35: TOTAL SEGUROS | E35: =SUM(D31:D34) -> 776661.44
A36: SEGUROS
A37: Federacion patronal - Poliza nro. 1-2195343-0 - Riesgo integral de barrios privados | D37: 148964 | E37: Debito 04/08
A38: Federacion patronal - Poliza nro. 1-77459-6 - Seguro de vida obligatorio Sr. Maximiliano Abbruzzese | D38: 5619 | E38: Debito 04/08
A39: Allianz (Cuit.: 30--50003721-7) - Seguro Técnico - Póliza N° 240210705270; Vto.01/09/2025 | D39: 14585.38 | E39: Debito 14/08
A40: Allianz (Cuit.: 30--50003721-7) - Seguro Técnico - Póliza N° 240210705270; Vto.01/09/2025 | D40: 18195 | E40: Debito 06/08
A41: TOTAL APORTES Y CONTRIBUCIONES | E41: =SUM(D37:D40) -> 187363.38
A42: SEGURIDAD
A43: GOLD (Cuit.: 33-71225773-9) - Fc.0000402 (Servicio de Seguridad Julio 2025) | D43: 40494443 | E43: Transf 04/08
A44: Servicio Polad - Mes de Julio - Valor de la hora $6.110,08 (742hs en total) | D44: 4533679.4 | E44: Transf 14/08
A45: TOTAL GASTOS SEGURIDAD | E45: =SUM(D43:D44) -> 45028122
A46: LIMPIEZA - MANTENIMIENTO DE ALUMBRADO | C46: SEGURIDAD
A47: OMS (Cuit.: 30-71568933-9) - Fc.00002637 (Abono mantenimiento planta de tratamiento) | D47: 984870 | E47: Transf 27/08
A48: Induser - Muestreo analisis e informe de pozo 1 y 2 - CUIT: 30707887008 - Fc. 3054 | D48: 902866 | E48: Transf 01/08
A49: Armella Cristian - CUIT: 20371419234 - Fc. 0004 - Mantenimiento espacios verdes | D49: 5500000 | E49: Transf 04/08
A50: Armella Cristian - CUIT: 20371419234 - Fc. 00010 - Recoleccion de basura mes de julio | D50: 250000 | E50: Transf 26/08
A51: Armella Cristian - CUIT: 20371419234 - Fc. 00014 - Extraccion de arboles | D51: 1500000 | E51: Transf 26/08
A52: Recicla Brown- CUIT: 30-71633401-1 - Servicio de recoleccion de residuos solidos urbanos con frecuencia de un retiro a la semana correspondiente al mes de Julio - Fc. 0000000056 | D52: 228690 | E52: Transf 12/08
A53: El imperio RYL - Fc. 000006432 - Articulos de limpieza | D53: 38000 | E53: Transf 19/08
A54: El imperio RYL - Ticket 7149 - Veneno para fumigar | D54: 120000 | E54: Transf 06/08
A55: El imperio RYL - Ticket 7146 - Articulos de limpieza | D55: 209800 | E55: Transf 06/08
A56: Vazquez (Cuit.: 30-55987767-7) - Fc. 00000206 (Prestación servicio de contenedores - Julio + Servicio de descarga) | D56: 636901.37 | E56: Transf 12/08
A57: La imperial - CUIT: 20386056359 - Trabajo de herreria , reparacion y puesta a punto de vallas y porton puesto 1 - Fc.0133 | D57: 2848824 | E57: Transf 06/08 - 12/08 -18/08
A58: La imperial - CUIT: 20386056359 - Adelanto arreglo de vallas | D58: 700000 | E58: Transf 22/08
... A67: Covelia SA - Camion recoleccion de ramas | D67: 200000 | E67: Transf 19/08
A68: TOTAL GASTOS LIMPIEZA Y MANTENIMIENTO DE ALUMBRADO | E68: =SUM(D47:D67) -> 16392017
A69: GASTOS DE MANTENIMIENTO GENERAL
A70: Matafuegos Fire SRL - Fc. 00023002 - CUIT: 30716182696 - Compra de uniformes Sr Intendente | D70: 178789.97 | E70: Transf 19/08
A71: Mirez Segio - Fc. 00000043 - Colocacion de toma correinte y emprolijado de clabes en puesto 2 | D71: 175000 | E71: Transf 26/08
A72: Mirez Segio - Fc. 00000041 - Instalacion de toma corriente en puesto 1 junto a cambio de reflector en el ingreso de dicho puesto | D72: 250000 | E72: Transf 12/08
A73: Mirez Segio - Fc. 00000039 - Reparacion de 8 farolas negras en calles internas (incluye materiales) | D73: 134900 | E73: Transf 01/08
A74: Mirez Segio - Fc. 00000042 - Cambio de reflector (11 - Reparacion de artefactos en calles internas (5) | D74: 310000 | E74: Transf 26/08
A75: Electro DRF - Compra de materiales (Dicro, conector, ficha, tomas, cinta, etc) - Fc. 00035720 | D75: 104687 | E75: Transf 19/08
A76: Electro DRF - Compra de interruptor tetrapolar - Fc. 0036310 | D76: 75114.45 | E76: Transf 22/08
A77: Electro DRF - Compra interruptor TMG tetrapolar - Fc. 000305360 | D77: 12141 | E77: Transf 22/08
A78: Electro DRF - Compra bastidor, tapas, cajas, proyectores led - Fc. 00036661 | D78: 285396.43 | E78: Transf 26/08
A79: Indrieri Leandro Maximiliano - Fc.15175 - CUIT: 20328418518 - Compra poleas maquina gimnasio | D79: 56785.98 | E79: Transf 13/08
A80: Insuma SRL - CUIT:33610485869 - Fc. 2246 - Compra de placas y adhesivo gimnasio | D80: 648796.9 | E80: Transf 29/08
A81: Dilmar Bulonera - Fc. 00053001 - CUIT: 30716182696 - Compra de insumos | D81: 5222.92 | E81: Transf 12/08
... A85: Pareyos - Ticket 28245 - Fertilizante para jardineria puesto 1 | D85: 3780 | E85: Efectivo
A86: TOTAL GASTOS DE MANTENIMIENTO GENERAL | E86: =SUM(D70:D85) -> 2904854.6
A87: HONORARIOS
A88: Honorarios administracion - Mes de Agosto Fc. 00001 - Mes de julio transferido | D88: 1780000 | E88: Aun no se transf
A89: TOTAL HONORARIOS | E89: =SUM(D88:D88) -> 1780000
A90: GASTOS BANCARIOS
A91: Gastos banacarios | D91: =89813.13+3892.72+1295401.62 -> 1389107.5
A92: Mantenimiento de cuenta | D92: 44400
A93: TOTAL GASTOS BANCARIOS | E93: =SUM(D91:D92) -> 1433507.5
A96: TOTAL ORDINARIOS | E96: =(SUM(E29:E94)) -> 70158740
A99: ABONOS Y SERVICIOS
A100: Edesur (Cuit.: 30-65511652-1) - Periodo liquidado 2do tramo bimestre 3 del 2025 | D100: 59651.94 | E100: Debito autom.
A101: Axin (Cuit.: 30-70858249-9) - No se abona este mes | D101: 0
A102: Telecom (Cuit.: 30-63945373-8) - (Abono celular Intendencia) | D102: 5668.02 | E102: =E100 -> Debito autom.
A103: Flow (Cuit: 30-63945373-8) - Fc.05443741 (Servicio de WIFI 2025) | D103: 32649.38 | E103: Efectivo 20/08
A104: TOTAL | E104: =SUM(D100:D103) -> 97969.34
A106: GASTOS EXTRAORDINARIOS:
A107: JC construcciones (Cuit.: 30-71620247-6) - (6°/6 Etapa 1 Paredon Calle Pino) | D107: 15451039 | E107: Transf 04/08 | F107: =15541039-D107 -> 90000
A108: JC construcciones (Cuit.: 30-71620247-6) - Diferencia cuota sin IVA | D108: 2149900 | E108: Transf 04/08
A109: Pelex S.A - Fc. 000000011 - 1 cuota de 6 etapa 2 - Obra paredon Perimetal | D109: 16863793 | E109: Transf 11/08
A110: Grey Brick - Fc. 000000921 - Certificacion de ibra pavimento correspondiente a Julio y Agosto | D110: 8035496.4 | E110: Transf 18/08
A113: TOTAL | E113: =SUM(D107:D112) -> 42500228
A117: TOTAL EXTRAORDINARIOS | E117: =E113 -> 42500228
A119: GASTOS PARTICULARES:
A120: Servicios arquitectura - Srita. Melanie Burgos Oros - Lotes 9 - 13 - 16 - 48 - 51 - 56 - 68 - 146 - 62 - 94 | D120: =599624 -> 599624 | E120: =E27 -> Transf 06/08
A121: Evento 08/07/2025 - UF 32 de 19 a 02 hs | D121: 82593.56 | E121: Transf 04/08
A122: Evento 19/07/2025 - UF 23 de 19 a 02 hs | D122: 82593.56 | E122: Transf 04/08
A123: TOTAL | E123: =SUM(D120:D122) -> 764811.12
A127: TOTAL PARTICULARES | E127: =E123 -> 764811.12
A130: GASTOS ORDINARIOS: | B130: =E96 -> 70158740
A131: GASTOS EXTRAORDINARIOS: | B131: =E117 -> 42500228
A132: SUMA DE GASTOS - ABONOS DE SERVICIOS | B132: =E104 -> 97969.34
A133: TOTAL GASTOS ORDINARIOS + ABONOS Y SERVICIOS | B133: =B132+B130 -> 70256710
A134: SE PRORRATEA COMO EXPENSAS ORDINARIAS MENOS DEL MONTO TOTAL GASTADO ($70.256.709,57) CON LA INTENCION DE SOSTENER EL MONTO DE LAS EXPENSAS ETENDIENDO QUE SE PUEDE CONTINUAR AVANZANDO EN MEJORAS CON LA CAJA DISPONIBLE ACTUAL.
A135: RESUMEN CAJA GENERAL
A136: Saldo anterior total | B136: 86876529
A137: Ingreso total | B137: =PRORRATEO!F159 -> 1.1626666e+08
A138: Deposito sin identificar - correspondientes a estas expensas | B138: =B187 -> 4060000
...

Sheet PRORRATEO
N1: Fondo de reserva: | P1: 30000000 | U1: 71243590
C2: Compensacion expensas lote 140 - 141: | G2: =W2 -> 23535900 | I2: Ordinarios: | K2: 69000000 | N2: Extraordinarios: | P2: 0 | T2: COMPENSACION EXP. LOTE 140/141 | W2: =((K2+P2)*D144)+((K2+P2)*D145) -> 23535900
A3: Dpto. | B3: UF | C3: Propietario | D3: (%) | E3: Saldo | F3: Ingreso | G3: Deuda o Saldo a favor | H3: Interes | I3: Expensas ord. | K3: Compensacion expensas lote 140/141 | L3: Fondo de reserva | M3: Gastos exclusivos de lotes (honorarios arquitecturas, intimaciones, etc) | N3: Canon de obra | O3: Gastos particulares / Multas / SUM | P3: Total | S3: LOTE
B5: 1 | C5: Lettieri, Miguel Angel | D5: 0.0046 | E5: 665352.01 | F5: =E5 -> 665352.01 | G5: =E5-F5 -> 0 | H5: =IF(G5>0,G5*3.087%,0) -> 0 | I5: =K$2*D5 -> 317400 | J5: =P$2*D5 -> 0 | K5: =G$2*0.675675676% -> 159026.35 | L5: =P$1*0.675675676% -> 202702.7 | M5: =G$1*D5 -> 0 | N5: 0 | P5: =ROUND(SUM(G5:O5),0) + R5 -> 679129.01 | R5: =ROUND(0.001+B5/100,2) -> 0.01 | S5: =B5 -> 1 | T5: Patricia Sobol <patriciasobol@hotmail.com> - - tambien tiene lote 127
B6: =B5+1 -> 2 | C6: Basile, Santiago | D6: 0.0046 | E6: 1712716 | G6: =E6-F6 -> 1712716 | H6: =IF(G6>0,G6*3.087%,0) -> 52871.544 | I6: =K$2*D6 -> 317400 | J6: =P$2*D6 -> 0 | K6: =G$2*0.675675676% -> 159026.35 | L6: =P$1*0.675675676% -> 202702.7 | M6: =G$1*D6 -> 0 | N6: 0 | P6: =ROUND(SUM(G6:O6),0) + R6 -> 2444717 | R6: =ROUND(0.001+B6/100,2) -> 0.02 | S6: =B6 -> 2
B7: =B6+1 -> 3 | C7: Garcia, Stella Maris | D7: 0.0046 | E7: 665352.03 | F7: =E7 -> 665352.03 | G7: =E7-F7 -> 0 | H7: =IF(G7>0,G7*3.087%,0) -> 0 | I7: =K$2*D7 -> 317400 | J7: =P$2*D7 -> 0 | K7: =G$2*0.675675676% -> 159026.35 | L7: =P$1*0.675675676% -> 202702.7 | M7: =G$1*D7 -> 0 | N7: 0 | P7: =ROUND(SUM(G7:O7),0) + R7 -> 679129.03 | R7: =ROUND(0.001+B7/100,2) -> 0.03 | S7: =B7 -> 3 | U7: avicola lanus a nombre de tamara en el mail
B8: =B7+1 -> 4 | C8: Reyes, Damian | D8: 0.0047 | E8: 687953.04 | F8: =E8 -> 687953.04 | G8: =E8-F8 -> 0 | H8: =IF(G8>0,G8*3.087%,0) -> 0 | I8: =K$2*D8 -> 324300 | J8: =P$2*D8 -> 0 | K8: =G$2*0.675675676% -> 159026.35 | L8: =P$1*0.675675676% -> 202702.7 | M8: =G$1*D8 -> 0 | N8: 0 | P8: =ROUND(SUM(G8:O8),0) + R8 -> 686029.04 | R8: =ROUND(0.001+B8/100,2) -> 0.04 | S8: =B8 -> 4 | T8: Ad Premed SRL
B9: =B8+1 -> 5 | C9: Tamburrino, Javier | D9: 0.0047 | E9: 672052.05 | F9: =E9 -> 672052.05 | G9: =E9-F9 -> 0 | H9: =IF(G9>0,G9*3.087%,0) -> 0 | I9: =K$2*D9 -> 324300 | J9: =P$2*D9 -> 0 | K9: =G$2*0.675675676% -> 159026.35 | L9: =P$1*0.675675676% -> 202702.7 | M9: =G$1*D9 -> 0 | N9: 0 | P9: =ROUND(SUM(G9:O9),0) + R9 -> 686029.05 | R9: =ROUND(0.001+B9/100,2) -> 0.05 | S9: =B9 -> 5
B10: =B9+1 -> 6 | C10: Marquez, Florencia | D10: 0.0045 | E10: 658651.06 | F10: =E10 -> 658651.06 | G10: =E10-F10 -> 0 | H10: =IF(G10>0,G10*3.087%,0) -> 0 | I10: =K$2*D10 -> 310500 | J10: =P$2*D10 -> 0 | K10: =G$2*0.675675676% -> 159026.35 | L10: =P$1*0.675675676% -> 202702.7 | M10: =G$1*D10 -> 0 | N10: 0 | P10: =ROUND(SUM(G10:O10),0) + R10 -> 672229.06 | R10: =ROUND(0.001+B10/100,2) -> 0.06 | S10: =B10 -> 6 | U10: Fattorini sergio
B11: =B10+1 -> 7 | C11: Olmedo, Alberto | D11: 0.0043 | E11: 1337245.1 | F11: =670000+680000 -> 1350000 | G11: =E11-F11 -> -12754.93 | H11: =IF(G11>0,G11*3.087%,0) -> 0 | I11: =K$2*D11 -> 296700 | J11: =P$2*D11 -> 0 | K11: =G$2*0.675675676% -> 159026.35 | L11: =P$1*0.675675676% -> 202702.7 | M11: =G$1*D11 -> 0 | N11: 0 | P11: =ROUND(SUM(G11:O11),0) + R11 -> 645674.07 | R11: =ROUND(0.001+B11/100,2) -> 0.07 | S11: =B11 -> 7 | T11: Cristian Colson
B12: =B11+1 -> 8 | C12: Troppelli, R. / Segura, J. | D12: 0.0047 | E12: 671974.08 | F12: =E12 -> 671974.08 | G12: =E12-F12 -> 0 | H12: =IF(G12>0,G12*3.087%,0) -> 0 | I12: =K$2*D12 -> 324300 | J12: =P$2*D12 -> 0 | K12: =G$2*0.675675676% -> 159026.35 | L12: =P$1*0.675675676% -> 202702.7 | M12: =G$1*D12 -> 0 | N12: 0 | P12: =ROUND(SUM(G12:O12),0) + R12 -> 686029.08 | R12: =ROUND(0.001+B12/100,2) -> 0.08 | S12: =B12 -> 8 | T12: Romina Troppelli - Deposita
B13: =B12+1 -> 9 | C13: Ferraris, Sergio | D13: 0.0047 | E13: 4421406.1 | F13: =1000000+1000000+1500000 -> 3500000 | G13: =E13-F13 -> 921406.09 | H13: =IF(G13>0,G13*3.087%,0) -> 28443.806 | I13: =K$2*D13 -> 324300 | J13: =P$2*D13 -> 0 | K13: =G$2*0.675675676% -> 159026.35 | L13: =P$1*0.675675676% -> 202702.7 | M13: 59274 | N13: =(I13+K13)/2 -> 241663.18 | P13: =ROUND(SUM(G13:O13),0) + R13 -> 1936816.1 | R13: =ROUND(0.001+B13/100,2) -> 0.09 | S13: =B13 -> 9
B14: =B13+1 -> 10 | C14: Schunk, Andrea | D14: 0.0047 | E14: 672052.1 | F14: =E14 -> 672052.1 | G14: =E14-F14 -> 0 | H14: =IF(G14>0,G14*3.087%,0) -> 0 | I14: =K$2*D14 -> 324300 | J14: =P$2*D14 -> 0 | K14: =G$2*0.675675676% -> 159026.35 | L14: =P$1*0.675675676% -> 202702.7 | M14: =G$1*D14 -> 0 | N14: 0 | P14: =ROUND(SUM(G14:O14),0) + R14 -> 686029.1 | R14: =ROUND(0.001+B14/100,2) -> 0.1 | S14: =B14 -> 10 | T14: Ariel Sposito
B15: =B14+1 -> 11 | C15: Arrom, Tamara | D15: 0.0047 | E15: -27946.89 | F15: =-700000+672053.11 -> -27946.89 | G15: =E15-F15 -> 0 | H15: =IF(G15>0,G15*3.087%,0) -> 0 | I15: =K$2*D15 -> 324300 | J15: =P$2*D15 -> 0 | K15: =G$2*0.675675676% -> 159026.35 | L15: =P$1*0.675675676% -> 202702.7 | M15: =G$1*D15 -> 0 | N15: 0 | P15: =ROUND(SUM(G15:O15),0) + R15 -> 686029.11 | R15: =ROUND(0.001+B15/100,2) -> 0.11 | S15: =B15 -> 11 | T15: maranata perfumeria
B16: =B15+1 -> 12 | C16: ADVC SRL. | D16: 0.0043 | E16: 1926403.1 | F16: =700000+21608 -> 721608 | G16: =E16-F16 -> 1204795.1 | H16: =IF(G16>0,G16*3.087%,0) -> 37192.025 | I16: =K$2*D16 -> 296700 | J16: =P$2*D16 -> 0 | K16: =G$2*0.675675676% -> 159026.35 | L16: =P$1*0.675675676% -> 202702.7 | M16: =G$1*D16 -> 0 | N16: 0 | P16: =ROUND(SUM(G16:O16),0) + R16 -> 1900416.1 | R16: =ROUND(0.001+B16/100,2) -> 0.12 | S16: =B16 -> 12 | T16: Gustavo Kearney <gkearney@batt.com.ar> - maranata perfumeria
B17: =B16+1 -> 13 | C17: Huenchupan, Alejandro | D17: 0.0046 | E17: 954689.13 | F17: =E17 -> 954689.13 | G17: =E17-F17 -> 0 | H17: =IF(G17>0,G17*3.087%,0) -> 0 | I17: =K$2*D17 -> 317400 | J17: =P$2*D17 -> 0 | K17: =G$2*0.675675676% -> 159026.35 | L17: =P$1*0.675675676% -> 202702.7 | M17: 58013 | N17: =(I17+K17)/2 -> 238213.18 | P17: =ROUND(SUM(G17:O17),0) + R17 -> 975355.13 | R17: =ROUND(0.001+B17/100,2) -> 0.13 | S17: =B17 -> 13
B18: =B17+1 -> 14 | C18: De Lucas, S. | D18: 0.0047 | E18: 695292.14 | F18: =E18 -> 695292.14 | G18: =E18-F18 -> 0 | H18: =IF(G18>0,G18*3.087%,0) -> 0 | I18: =K$2*D18 -> 324300 | J18: =P$2*D18 -> 0 | K18: =G$2*0.675675676% -> 159026.35 | L18: =P$1*0.675675676% -> 202702.7 | M18: =G$1*D18 -> 0 | N18: 0 | P18: =ROUND(SUM(G18:O18),0) + R18 -> 686029.14 | R18: =ROUND(0.001+B18/100,2) -> 0.14 | S18: =B18 -> 14 | T18: PAGOS UNIVERSALES SA/ GLOBAL TT S.A. / GLOBAT
B19: =B18+1 -> 15 | C19: Berlotti, Maria Laura | D19: 0.0044 | E19: 1439200.1 | F19: =763674.15+675526.15+23575 -> 1462775.3 | G19: =E19-F19 -> -23575.15 | H19: =IF(G19>0,G19*3.087%,0) -> 0 | I19: =K$2*D19 -> 303600 | J19: =P$2*D19 -> 0 | K19: =G$2*0.675675676% -> 159026.35 | L19: =P$1*0.675675676% -> 202702.7 | M19: =G$1*D19 -> 0 | N19: 0 | P19: =ROUND(SUM(G19:O19),0) + R19 -> 641754.15 | R19: =ROUND(0.001+B19/100,2) -> 0.15 | S19: =B19 -> 15 | T19: Adminar SA y Lobison
B20: =B19+1 -> 16 | C20: Giordano, Juan Pablo | D20: 0.0046 | E20: 954689.16 | F20: =E20 -> 954689.16 | G20: =E20-F20 -> 0 | H20: =IF(G20>0,G20*3.087%,0) -> 0 | I20: =K$2*D20 -> 317400 | J20: =P$2*D20 -> 0 | K20: =G$2*0.675675676% -> 159026.35 | L20: =P$1*0.675675676% -> 202702.7 | M20: 58013 | N20: =(I20+K20)/2 -> 238213.18 | P20: =ROUND(SUM(G20:O20),0) + R20 -> 975355.16 | R20: =ROUND(0.001+B20/100,2) -> 0.16 | S20: =B20 -> 16
B21: =B20+1 -> 17 | C21: Zacharias, Valeria | D21: 0.0046 | E21: 1365134.2 | F21: 765860.17 | G21: =E21-F21 -> 599274 | H21: =IF(G21>0,G21*3.087%,0) -> 18499.588 | I21: =K$2*D21 -> 317400 | J21: =P$2*D21 -> 0 | K21: =G$2*0.675675676% -> 159026.35 | L21: =P$1*0.675675676% -> 202702.7 | M21: =G$1*D21 -> 0 | N21: 0 | P21: =ROUND(SUM(G21:O21),0) + R21 -> 1296903.2 | R21: =ROUND(0.001+B21/100,2) -> 0.17 | S21: =B21 -> 17 | T21: Deposita MECANICA VANDEN BOSCH <mecanicavandenbosch@gmail.com>
B22: =B21+1 -> 18 | C22: De Nardi, Mario | D22: 0.0046 | E22: 665352.18 | F22: =E22 -> 665352.18 | G22: =E22-F22 -> 0 | H22: =IF(G22>0,G22*3.087%,0) -> 0 | I22: =K$2*D22 -> 317400 | J22: =P$2*D22 -> 0 | K22: =G$2*0.675675676% -> 159026.35 | L22: =P$1*0.675675676% -> 202702.7 | M22: =G$1*D22 -> 0 | N22: 0 | P22: =ROUND(SUM(G22:O22),0) + R22 -> 679129.18 | R22: =ROUND(0.001+B22/100,2) -> 0.18 | S22: =B22 -> 18 | T22: Deposita, tambien paga el 132
B23: =B22+1 -> 19 | C23: Oniszczuk, Sebastian | D23: 0.0047 | E23: 672011.19 | F23: =E23 -> 672011.19 | G23: =E23-F23 -> 0 | H23: =IF(G23>0,G23*3.087%,0) -> 0 | I23: =K$2*D23 -> 324300 | J23: =P$2*D23 -> 0 | K23: =G$2*0.675675676% -> 159026.35 | L23: =P$1*0.675675676% -> 202702.7 | M23: =G$1*D23 -> 0 | N23: 0 | P23: =ROUND(SUM(G23:O23),0) + R23 -> 686029.19 | R23: =ROUND(0.001+B23/100,2) -> 0.19 | S23: =B23 -> 19
B24: =B23+1 -> 20 | C24: Gomez, Jose Luis | D24: 0.0047 | E24: 672052.2 | F24: =E24 -> 672052.2 | G24: =E24-F24 -> 0 | H24: =IF(G24>0,G24*3.087%,0) -> 0 | I24: =K$2*D24 -> 324300 | J24: =P$2*D24 -> 0 | K24: =G$2*0.675675676% -> 159026.35 | L24: =P$1*0.675675676% -> 202702.7 | M24: =G$1*D24 -> 0 | N24: 0 | P24: =ROUND(SUM(G24:O24),0) + R24 -> 686029.2 | R24: =ROUND(0.001+B24/100,2) -> 0.2 | S24: =B24 -> 20
B25: =B24+1 -> 21 | C25: Carcioni, Jose | D25: 0.0047 | E25: 672052.21 | G25: =E25-F25 -> 672052.21 | H25: =IF(G25>0,G25*3.087%,0) -> 20746.252 | I25: =K$2*D25 -> 324300 | J25: =P$2*D25 -> 0 | K25: =G$2*0.675675676% -> 159026.35 | L25: =P$1*0.675675676% -> 202702.7 | M25: =G$1*D25 -> 0 | N25: 0 | P25: =ROUND(SUM(G25:O25),0) + R25 -> 1378828.2 | R25: =ROUND(0.001+B25/100,2) -> 0.21 | S25: =B25 -> 21 | U25: Suavenol
B26: =B25+1 -> 22 | C26: Oniszczuk, Esteban | D26: 0.0047 | E26: 672052.22 | F26: =E26 -> 672052.22 | G26: =E26-F26 -> 0 | H26: =IF(G26>0,G26*3.087%,0) -> 0 | I26: =K$2*D26 -> 324300 | J26: =P$2*D26 -> 0 | K26: =G$2*0.675675676% -> 159026.35 | L26: =P$1*0.675675676% -> 202702.7 | M26: =G$1*D26 -> 0 | N26: 0 | P26: =ROUND(SUM(G26:O26),0) + R26 -> 686029.22 | R26: =ROUND(0.001+B26/100,2) -> 0.22 | S26: =B26 -> 22 | T26: Nicolas Cecilia Andrea
B27: =B26+1 -> 23 | C27: Dominguez, Javier | D27: 0.0047 | E27: 2241707.2 | F27: =E27 -> 2241707.2 | G27: =E27-F27 -> 0 | H27: =IF(G27>0,G27*3.087%,0) -> 0 | I27: =K$2*D27 -> 324300 | J27: =P$2*D27 -> 0 | K27: =G$2*0.675675676% -> 159026.35 | L27: =P$1*0.675675676% -> 202702.7 | M27: =G$1*D27 -> 0 | N27: 0 | P27: =ROUND(SUM(G27:O27),0) + R27 -> 686029.23 | R27: =ROUND(0.001+B27/100,2) -> 0.23 | S27: =B27 -> 23
B28: =B27+1 -> 24 | C28: Calviño, Eduardo | D28: 0.0047 | E28: 2326863.2 | F28: =703707+49554+1533990.24 -> 2287251.2 | G28: =E28-F28 -> 39612 | H28: =IF(G28>0,G28*3.087%,0) -> 1222.8224 | I28: =K$2*D28 -> 324300 | J28: =P$2*D28 -> 0 | K28: =G$2*0.675675676% -> 159026.35 | L28: =P$1*0.675675676% -> 202702.7 | M28: =G$1*D28 -> 0 | N28: 0 | P28: =ROUND(SUM(G28:O28),0) + R28 -> 726864.24 | R28: =ROUND(0.001+B28/100,2) -> 0.24 | S28: =B28 -> 24
B29: =B28+1 -> 25 | C29: Cejas, Nicolas | D29: 0.0048 | E29: 1436837.2 | F29: =636837.25+800000 -> 1436837.2 | G29: =E29-F29 -> 0 | H29: =IF(G29>0,G29*3.087%,0) -> 0 | I29: =K$2*D29 -> 331200 | J29: =P$2*D29 -> 0 | K29: =G$2*0.675675676% -> 159026.35 | L29: =P$1*0.675675676% -> 202702.7 | M29: =G$1*D29 -> 0 | N29: 0 | P29: =ROUND(SUM(G29:O29),0) + R29 -> 692929.25 | R29: =ROUND(0.001+B29/100,2) -> 0.25 | S29: =B29 -> 25 | U29: Agustina Palermo
B30: =B29+1 -> 26 | C30: De Nardi, Karina | D30: 0.0048 | E30: 672746.26 | F30: 675000 | G30: =E30-F30 -> -2253.74 | H30: =IF(G30>0,G30*3.087%,0) -> 0 | I30: =K$2*D30 -> 331200 | J30: =P$2*D30 -> 0 | K30: =G$2*0.675675676% -> 159026.35 | L30: =P$1*0.675675676% -> 202702.7 | M30: =G$1*D30 -> 0 | N30: 0 | P30: =ROUND(SUM(G30:O30),0) + R30 -> 690675.26 | R30: =ROUND(0.001+B30/100,2) -> 0.26 | S30: =B30 -> 26 | U30: Luis Grecco Y Karina
B31: =B30+1 -> 27 | C31: Montero, Pablo | D31: 0.0048 | E31: 678753.27 | F31: =E31 -> 678753.27 | G31: =E31-F31 -> 0 | H31: =IF(G31>0,G31*3.087%,0) -> 0 | I31: =K$2*D31 -> 331200 | J31: =P$2*D31 -> 0 | K31: =G$2*0.675675676% -> 159026.35 | L31: =P$1*0.675675676% -> 202702.7 | M31: =G$1*D31 -> 0 | N31: 0 | P31: =ROUND(SUM(G31:O31),0) + R31 -> 692929.27 | R31: =ROUND(0.001+B31/100,2) -> 0.27 | S31: =B31 -> 27
B32: =B31+1 -> 28 | C32: Gariotto, Salvador | D32: 0.0045 | E32: 2668040.3 | F32: =670000+20000 -> 690000 | G32: =E32-F32 -> 1978040.3 | H32: =IF(G32>0,G32*3.087%,0) -> 61062.103 | I32: =K$2*D32 -> 310500 | J32: =P$2*D32 -> 0 | K32: =G$2*0.675675676% -> 159026.35 | L32: =P$1*0.675675676% -> 202702.7 | M32: =G$1*D32 -> 0 | N32: 0 | P32: =ROUND(SUM(G32:O32),0) + R32 -> 2711331.3 | R32: =ROUND(0.001+B32/100,2) -> 0.28 | S32: =B32 -> 28 | T32: Deposita - pamela
B33: =B32+1 -> 29 | C33: Aducci, Marcelo | D33: 0.0048 | E33: 678753.29 | F33: =E33 -> 678753.29 | G33: =E33-F33 -> 0 | H33: =IF(G33>0,G33*3.087%,0) -> 0 | I33: =K$2*D33 -> 331200 | J33: =P$2*D33 -> 0 | K33: =G$2*0.675675676% -> 159026.35 | L33: =P$1*0.675675676% -> 202702.7 | M33: =G$1*D33 -> 0 | N33: 0 | P33: =ROUND(SUM(G33:O33),0) + R33 -> 692929.29 | R33: =ROUND(0.001+B33/100,2) -> 0.29 | S33: =B33 -> 29 | T33: IGLE SA
B34: =B33+1 -> 30 | C34: Petrucchi, Hernan | D34: 0.0045 | E34: 658651.3 | F34: =E34 -> 658651.3 | G34: =E34-F34 -> 0 | H34: =IF(G34>0,G34*3.087%,0) -> 0 | I34: =K$2*D34 -> 310500 | J34: =P$2*D34 -> 0 | K34: =G$2*0.675675676% -> 159026.35 | L34: =P$1*0.675675676% -> 202702.7 | M34: =G$1*D34 -> 0 | N34: 0 | P34: =ROUND(SUM(G34:O34),0) + R34 -> 672229.3 | R34: =ROUND(0.001+B34/100,2) -> 0.3 | S34: =B34 -> 30 | T34: ConstruHap - Veronica Laura Maggiot
B35: =B34+1 -> 31 | C35: Rosi, Martin | D35: 0.0045 | E35: 1351585.3 | F35: =672184 -> 672184 | G35: =E35-F35 -> 679401.31 | H35: =IF(G35>0,G35*3.087%,0) -> 20973.118 | I35: =K$2*D35 -> 310500 | J35: =P$2*D35 -> 0 | K35: =G$2*0.675675676% -> 159026.35 | L35: =P$1*0.675675676% -> 202702.7 | M35: =G$1*D35 -> 0 | N35: 0 | P35: =ROUND(SUM(G35:O35),0) + R35 -> 1372603.3 | R35: =ROUND(0.001+B35/100,2) -> 0.31 | S35: =B35 -> 31 | T35: ventas@quimicaros.com.ar
B36: =B35+1 -> 32 | C36: Bernardez, M. / Giordano, J. | D36: 0.0045 | E36: 658651.32 | F36: =5888095-F17-F20-F37-F90-F149-F150-F152 -> 658651.67 | G36: =E36-F36 -> -0.35 | H36: =IF(G36>0,G36*3.087%,0) -> 0 | I36: =K$2*D36 -> 310500 | J36: =P$2*D36 -> 0 | K36: =G$2*0.675675676% -> 159026.35 | L36: =P$1*0.675675676% -> 202702.7 | M36: =G$1*D36 -> 0 | N36: 0 | O36: 150760 | P36: =ROUND(SUM(G36:O36),0) + R36 -> 822989.32 | R36: =ROUND(0.001+B36/100,2) -> 0.32 | S36: =B36 -> 32
B37: 33 | C37: Giordano, Juan Pablo | D37: 0.0045 | E37: 658651.33 | F37: =E37 -> 658651.33 | G37: =E37-F37 -> 0 | H37: =IF(G37>0,G37*3.087%,0) -> 0 | I37: =K$2*D37 -> 310500 | J37: =P$2*D37 -> 0 | K37: =G$2*0.675675676% -> 159026.35 | L37: =P$1*0.675675676% -> 202702.7 | M37: =G$1*D37 -> 0 | N37: 0 | P37: =ROUND(SUM(G37:O37),0) + R37 -> 672229.33 | R37: =ROUND(0.001+B37/100,2) -> 0.33 | S37: =B37 -> 33
B38: 34 | C38: Rosi, Martin | D38: 0.0045 | E38: 1351585.3 | F38: =672184 -> 672184 | G38: =E38-F38 -> 679401.34 | H38: =IF(G38>0,G38*3.087%,0) -> 20973.119 | I38: =K$2*D38 -> 310500 | J38: =P$2*D38 -> 0 | K38: =G$2*0.675675676% -> 159026.35 | L38: =P$1*0.675675676% -> 202702.7 | M38: =G$1*D38 -> 0 | N38: 0 | P38: =ROUND(SUM(G38:O38),0) + R38 -> 1372604.3 | R38: =ROUND(0.001+B38/100,2) -> 0.34 | S38: =B38 -> 34
A39: 1 | B39: 35 | C39: Di Biase, Diego | D39: 0.0046 | E39: 665352.35 | F39: =E39 -> 665352.35 | G39: =E39-F39 -> 0 | H39: =IF(G39>0,G39*3.087%,0) -> 0 | I39: =K$2*D39 -> 317400 | J39: =P$2*D39 -> 0 | K39: =G$2*0.675675676% -> 159026.35 | L39: =P$1*0.675675676% -> 202702.7 | M39: =G$1*D39 -> 0 | N39: 0 | P39: =ROUND(SUM(G39:O39),0) + R39 -> 679129.35 | R39: =ROUND(0.001+B39/100,2) -> 0.35 | S39: =B39 -> 35 | T39: Velazco Velasco Gisela
A40: 2 | B40: 36 | C40: Acosta, Claudio | D40: 0.0046 | E40: 2057458.4 | G40: =E40-F40 -> 2057458.4 | H40: =IF(G40>0,G40*3.087%,0) -> 63513.74 | I40: =K$2*D40 -> 317400 | J40: =P$2*D40 -> 0 | K40: =G$2*0.675675676% -> 159026.35 | L40: =P$1*0.675675676% -> 202702.7 | M40: =G$1*D40 -> 0 | N40: 0 | P40: =ROUND(SUM(G40:O40),0) + R40 -> 2800101.4 | R40: =ROUND(0.001+B40/100,2) -> 0.36 | S40: =B40 -> 36
A41: 3 | B41: 37 | C41: Caiz, Ariel | D41: 0.0045 | E41: 658651.37 | F41: 718953.37 | G41: =E41-F41 -> -60302 | H41: =IF(G41>0,G41*3.087%,0) -> 0 | I41: =K$2*D41 -> 310500 | J41: =P$2*D41 -> 0 | K41: =G$2*0.675675676% -> 159026.35 | L41: =P$1*0.675675676% -> 202702.7 | M41: =G$1*D41 -> 0 | N41: 0 | P41: =ROUND(SUM(G41:O41),0) + R41 -> 611927.37 | R41: =ROUND(0.001+B41/100,2) -> 0.37 | S41: =B41 -> 37
A42: 4 | B42: 38 | C42: Tortorisi, Antonio | D42: 0.0045 | E42: 1306476.4 | F42: =150760+752056 -> 902816 | G42: =E42-F42 -> 403660.38 | H42: =IF(G42>0,G42*3.087%,0) -> 12460.996 | I42: =K$2*D42 -> 310500 | J42: =P$2*D42 -> 0 | K42: =G$2*0.675675676% -> 159026.35 | L42: =P$1*0.675675676% -> 202702.7 | M42: =G$1*D42 -> 0 | N42: 0 | P42: =ROUND(SUM(G42:O42),0) + R42 -> 1088350.4 | R42: =ROUND(0.001+B42/100,2) -> 0.38 | S42: =B42 -> 38 | T42: Maria Ximena Vizzini / P Sur Srl
A43: 5 | B43: 39 | C43: Balghera, Lucas | D43: 0.0045 | E43: 659873.39 | F43: 660000 | G43: =E43-F43 -> -126.61 | H43: =IF(G43>0,G43*3.087%,0) -> 0 | I43: =K$2*D43 -> 310500 | J43: =P$2*D43 -> 0 | K43: =G$2*0.675675676% -> 159026.35 | L43: =P$1*0.675675676% -> 202702.7 | M43: =G$1*D43 -> 0 | N43: 0 | P43: =ROUND(SUM(G43:O43),0) + R43 -> 672102.39 | R43: =ROUND(0.001+B43/100,2) -> 0.39 | S43: =B43 -> 39 | T43: Lorena Mazzeo
A44: 6 | B44: 40 | C44: Olivero, Marcelo | D44: 0.0045 | E44: 621806.4 | F44: =E44 -> 621806.4 | G44: =E44-F44 -> 0 | H44: =IF(G44>0,G44*3.087%,0) -> 0 | I44: =K$2*D44 -> 310500 | J44: =P$2*D44 -> 0 | K44: =G$2*0.675675676% -> 159026.35 | L44: =P$1*0.675675676% -> 202702.7 | M44: =G$1*D44 -> 0 | N44: 0 | P44: =ROUND(SUM(G44:O44),0) + R44 -> 672229.4 | R44: =ROUND(0.001+B44/100,2) -> 0.4 | S44: =B44 -> 40
A45: 7 | B45: 41 | C45: Papa, V. / Sotelo, E. | D45: 0.0045 | E45: 658651.41 | F45: =E45 -> 658651.41 | G45: =E45-F45 -> 0 | H45: =IF(G45>0,G45*3.087%,0) -> 0 | I45: =K$2*D45 -> 310500 | J45: =P$2*D45 -> 0 | K45: =G$2*0.675675676% -> 159026.35 | L45: =P$1*0.675675676% -> 202702.7 | M45: =G$1*D45 -> 0 | N45: 0 | P45: =ROUND(SUM(G45:O45),0) + R45 -> 672229.41 | R45: =ROUND(0.001+B45/100,2) -> 0.41 | S45: =B45 -> 41 | T45: vivibpapa@gmail.com - Viviana papa
A46: 8 | B46: 42 | C46: Lopez Zevallo, Martin | D46: 0.0045 | E46: 658651.42 | F46: =E46 -> 658651.42 | G46: =E46-F46 -> 0 | H46: =IF(G46>0,G46*3.087%,0) -> 0 | I46: =K$2*D46 -> 310500 | J46: =P$2*D46 -> 0 | K46: =G$2*0.675675676% -> 159026.35 | L46: =P$1*0.675675676% -> 202702.7 | M46: =G$1*D46 -> 0 | N46: 0 | P46: =ROUND(SUM(G46:O46),0) + R46 -> 672229.42 | R46: =ROUND(0.001+B46/100,2) -> 0.42 | S46: =B46 -> 42 | T46: Maria Eugenia Bachratz
A47: 1 | B47: 43 | C47: Gaspari, Federico | D47: 0.0036 | E47: 598347.43 | F47: =E47 -> 598347.43 | G47: =E47-F47 -> 0 | H47: =IF(G47>0,G47*3.087%,0) -> 0 | I47: =K$2*D47 -> 248400 | J47: =P$2*D47 -> 0 | K47: =G$2*0.675675676% -> 159026.35 | L47: =P$1*0.675675676% -> 202702.7 | M47: =G$1*D47 -> 0 | N47: 0 | P47: =ROUND(SUM(G47:O47),0) + R47 -> 610129.43 | R47: =ROUND(0.001+B47/100,2) -> 0.43 | S47: =B47 -> 43
A48: 1 | B48: 44 | C48: Gutierrez, Maria Soledad | D48: 0.0041 | E48: 1268920.4 | G48: =E48-F48 -> 1268920.4 | H48: =IF(G48>0,G48*3.087%,0) -> 39171.574 | I48: =K$2*D48 -> 282900 | J48: =P$2*D48 -> 0 | K48: =G$2*0.675675676% -> 159026.35 | L48: =P$1*0.675675676% -> 202702.7 | M48: =G$1*D48 -> 0 | N48: 0 | P48: =ROUND(SUM(G48:O48),0) + R48 -> 1952721.4 | R48: =ROUND(0.001+B48/100,2) -> 0.44 | S48: =B48 -> 44
A49: 2 | B49: 45 | C49: Giallonardo, Ariel | D49: 0.0049 | E49: 685453.45 | F49: =E49 -> 685453.45 | G49: =E49-F49 -> 0 | H49: =IF(G49>0,G49*3.087%,0) -> 0 | I49: =K$2*D49 -> 338100 | J49: =P$2*D49 -> 0 | K49: =G$2*0.675675676% -> 159026.35 | L49: =P$1*0.675675676% -> 202702.7 | M49: =G$1*D49 -> 0 | N49: 0 | P49: =ROUND(SUM(G49:O49),0) + R49 -> 699829.45 | R49: =ROUND(0.001+B49/100,2) -> 0.45 | S49: =B49 -> 45
A50: 2 | B50: 46 | C50: Orso, Graciela | D50: 0.0039 | E50: 1288078.5 | G50: =E50-F50 -> 1288078.5 | H50: =IF(G50>0,G50*3.087%,0) -> 39762.982 | I50: =K$2*D50 -> 269100 | J50: =P$2*D50 -> 0 | K50: =G$2*0.675675676% -> 159026.35 | L50: =P$1*0.675675676% -> 202702.7 | M50: =G$1*D50 -> 0 | N50: 0 | P50: =ROUND(SUM(G50:O50),0) + R50 -> 1958670.5 | R50: =ROUND(0.001+B50/100,2) -> 0.46 | S50: =B50 -> 46 | T50: HUANG (CHINO)
A51: 3 | B51: 47 | C51: Topino, Maximiliano | D51: 0.0045 | E51: 3535756.5 | F51: =750000+1500000+2055315+86157-F8 -> 3703519 | G51: =E51-F51 -> -167762.49 | H51: =IF(G51>0,G51*3.087%,0) -> 0 | I51: =K$2*D51 -> 310500 | J51: =P$2*D51 -> 0 | K51: =G$2*0.675675676% -> 159026.35 | L51: =P$1*0.675675676% -> 202702.7 | M51: =G$1*D51 -> 0 | N51: 0 | P51: =ROUND(SUM(G51:O51),0) + R51 -> 504467.47 | R51: =ROUND(0.001+B51/100,2) -> 0.47 | S51: =B51 -> 47 | T51: Ad Premed SRL
A52: 3 | B52: 48 | C52: Pucheta, Cristian Oscar | D52: 0.0045 | E52: 971753.48 | F52: =E52 -> 971753.48 | G52: =E52-F52 -> 0 | H52: =IF(G52>0,G52*3.087%,0) -> 0 | I52: =K$2*D52 -> 310500 | J52: =P$2*D52 -> 0 | K52: =G$2*0.675675676% -> 159026.35 | L52: =P$1*0.675675676% -> 202702.7 | M52: 85127 | N52: =(I52+K52)/2 -> 234763.18 | P52: =ROUND(SUM(G52:O52),0) + R52 -> 992119.48 | R52: =ROUND(0.001+B52/100,2) -> 0.48 | S52: =B52 -> 48
A53: 4 | B53: 49 | C53: Pucci, C. / Celeiro, N. | D53: 0.0045 | E53: 658651.49 | F53: =E53 -> 658651.49 | G53: =E53-F53 -> 0 | H53: =IF(G53>0,G53*3.087%,0) -> 0 | I53: =K$2*D53 -> 310500 | J53: =P$2*D53 -> 0 | K53: =G$2*0.675675676% -> 159026.35 | L53: =P$1*0.675675676% -> 202702.7 | M53: =G$1*D53 -> 0 | N53: 0 | P53: =ROUND(SUM(G53:O53),0) + R53 -> 672229.49 | R53: =ROUND(0.001+B53/100,2) -> 0.49 | S53: =B53 -> 49 | T53: Pablo huerta
A54: 4 | B54: 50 | C54: Varoli, Elina | D54: 0.0045 | E54: 658651.5 | F54: =E54 -> 658651.5 | G54: =E54-F54 -> 0 | H54: =IF(G54>0,G54*3.087%,0) -> 0 | I54: =K$2*D54 -> 310500 | J54: =P$2*D54 -> 0 | K54: =G$2*0.675675676% -> 159026.35 | L54: =P$1*0.675675676% -> 202702.7 | M54: =G$1*D54 -> 0 | N54: 0 | P54: =ROUND(SUM(G54:O54),0) + R54 -> 672229.5 | R54: =ROUND(0.001+B54/100,2) -> 0.5 | S54: =B54 -> 50 | T54: Medizin - ProlijoLimp SA - COBRO EXPRESS BUENOS AIRES SA
A55: 5 | B55: 51 | C55: Picciuolo, Nicolas | D55: 0.0045 | E55: 1980054.5 | G55: =E55-F55 -> 1980054.5 | H55: =IF(G55>0,G55*3.087%,0) -> 61124.283 | I55: =K$2*D55 -> 310500 | J55: =P$2*D55 -> 0 | K55: =G$2*0.675675676% -> 159026.35 | L55: =P$1*0.675675676% -> 202702.7 | M55: 56751 | N55: =(I55+K55)/2 -> 234763.18 | P55: =ROUND(SUM(G55:O55),0) + R55 -> 3004922.5 | R55: =ROUND(0.001+B55/100,2) -> 0.51 | S55: =B55 -> 51 | T55: CAROLINA GIACCHETTI carolinagiacchetti@hotmail.com / Maria alejandra Ceballos
A56: 5 | B56: 52 | C56: de la Calle, Miguel Angel | D56: 0.0046 | E56: 688537.52 | F56: =688537.52+679085.52 -> 1367623 | G56: =E56-F56 -> -679085.52 | H56: =IF(G56>0,G56*3.087%,0) -> 0 | I56: =K$2*D56 -> 317400 | J56: =P$2*D56 -> 0 | K56: =G$2*0.675675676% -> 159026.35 | L56: =P$1*0.675675676% -> 202702.7 | M56: =G$1*D56 -> 0 | N56: 0 | P56: =ROUND(SUM(G56:O56),0) + R56 -> 44.52 | R56: =ROUND(0.001+B56/100,2) -> 0.52 | S56: =B56 -> 52 | T56: Ezequiel De la calle
A57: 6 | B57: 53 | C57: Carrasco, Mariela | D57: 0.0045 | E57: 1895678.5 | G57: =E57-F57 -> 1895678.5 | H57: =IF(G57>0,G57*3.087%,0) -> 58519.596 | I57: =K$2*D57 -> 310500 | J57: =P$2*D57 -> 0 | K57: =G$2*0.675675676% -> 159026.35 | L57: =P$1*0.675675676% -> 202702.7 | M57: =G$1*D57 -> 0 | N57: 0 | P57: =ROUND(SUM(G57:O57),0) + R57 -> 2626427.5 | R57: =ROUND(0.001+B57/100,2) -> 0.53 | S57: =B57 -> 53
A58: 6 | B58: 54 | C58: Ruiz, Sebastian | D58: 0.0045 | E58: 1351587.5 | F58: 672185.54 | G58: =E58-F58 -> 679402 | H58: =IF(G58>0,G58*3.087%,0) -> 20973.14 | I58: =K$2*D58 -> 310500 | J58: =P$2*D58 -> 0 | K58: =G$2*0.675675676% -> 159026.35 | L58: =P$1*0.675675676% -> 202702.7 | M58: =G$1*D58 -> 0 | N58: 0 | P58: =ROUND(SUM(G58:O58),0) + R58 -> 1372604.5 | R58: =ROUND(0.001+B58/100,2) -> 0.54 | S58: =B58 -> 54 | T58: LBEG SERO SRL
A59: 7 | B59: 55 | C59: Itoiz, Juan Pablo | D59: 0.0045 | E59: 2042070.6 | F59: =41427+703707+1180132.55 -> 1925266.6 | G59: =E59-F59 -> 116804 | H59: =IF(G59>0,G59*3.087%,0) -> 3605.7395 | I59: =K$2*D59 -> 310500 | J59: =P$2*D59 -> 0 | K59: =G$2*0.675675676% -> 159026.35 | L59: =P$1*0.675675676% -> 202702.7 | M59: =G$1*D59 -> 0 | N59: 0 | P59: =ROUND(SUM(G59:O59),0) + R59 -> 792639.55 | R59: =ROUND(0.001+B59/100,2) -> 0.55 | S59: =B59 -> 55 | T59: De mela Innovaciones SRL tiene el 24 y 58
A60: 7 | B60: 56 | C60: Carderi, Damian | D60: 0.0045 | E60: 943377.56 | F60: =E60 -> 943377.56 | G60: =E60-F60 -> 0 | H60: =IF(G60>0,G60*3.087%,0) -> 0 | I60: =K$2*D60 -> 310500 | J60: =P$2*D60 -> 0 | K60: =G$2*0.675675676% -> 159026.35 | L60: =P$1*0.675675676% -> 202702.7 | M60: 56751 | N60: =(I60+K60)/2 -> 234763.18 | O60: =I60*10% -> 31050 | P60: =ROUND(SUM(G60:O60),0) + R60 -> 994793.56 | R60: =ROUND(0.001+B60/100,2) -> 0.56 | S60: =B60 -> 56 | T60: ROSSI PATRICIA
A61: 8 | B61: 57 | C61: Didio Bonasera, Gaston | D61: 0.0045 | E61: 658651.57 | F61: 672185.57 | G61: =E61-F61 -> -13534 | H61: =IF(G61>0,G61*3.087%,0) -> 0 | I61: =K$2*D61 -> 310500 | J61: =P$2*D61 -> 0 | K61: =G$2*0.675675676% -> 159026.35 | L61: =P$1*0.675675676% -> 202702.7 | M61: =G$1*D61 -> 0 | N61: 0 | P61: =ROUND(SUM(G61:O61),0) + R61 -> 658695.57 | R61: =ROUND(0.001+B61/100,2) -> 0.57 | S61: =B61 -> 57
A62: 8 | B62: 58 | C62: Calviño, Eduardo | D62: 0.0045 | E62: 2042070.6 | F62: =703707+41427+658651 -> 1403785 | G62: =E62-F62 -> 638285.58 | H62: =IF(G62>0,G62*3.087%,0) -> 19703.876 | I62: =K$2*D62 -> 310500 | J62: =P$2*D62 -> 0 | K62: =G$2*0.675675676% -> 159026.35 | L62: =P$1*0.675675676% -> 202702.7 | M62: =G$1*D62 -> 0 | N62: 0 | P62: =ROUND(SUM(G62:O62),0) + R62 -> 1330219.6 | R62: =ROUND(0.001+B62/100,2) -> 0.58 | S62: =B62 -> 58
A63: 9 | B63: 59 | C63: Korin, Alejandro | D63: 0.0041 | E63: 625482.59 | F63: =E63 -> 625482.59 | G63: =E63-F63 -> 0 | H63: =IF(G63>0,G63*3.087%,0) -> 0 | I63: =K$2*D63 -> 282900 | J63: =P$2*D63 -> 0 | K63: =G$2*0.675675676% -> 159026.35 | L63: =P$1*0.675675676% -> 202702.7 | M63: =G$1*D63 -> 0 | N63: 0 | P63: =ROUND(SUM(G63:O63),0) + R63 -> 644629.59 | R63: =ROUND(0.001+B63/100,2) -> 0.59 | S63: =B63 -> 59 | T63: Analía Celeste Cáceres
A64: 9 | B64: 60 | C64: Desantis, Julieta | D64: 0.0045 | E64: 658450.6 | F64: =296000+242000+147000 -> 685000 | G64: =E64-F64 -> -26549.4 | H64: =IF(G64>0,G64*3.087%,0) -> 0 | I64: =K$2*D64 -> 310500 | J64: =P$2*D64 -> 0 | K64: =G$2*0.675675676% -> 159026.35 | L64: =P$1*0.675675676% -> 202702.7 | M64: =G$1*D64 -> 0 | N64: 0 | P64: =ROUND(SUM(G64:O64),0) + R64 -> 645680.6 | R64: =ROUND(0.001+B64/100,2) -> 0.6 | S64: =B64 -> 60 | T64: Deposita, Julieta De Santis <julietadesan@gmail.com>
A65: 10 | B65: 61 | C65: Dimunzio Ayaso, Ivana | D65: 0.0045 | E65: 658586.61 | F65: =339000+243000+76586.61 -> 658586.61 | G65: =E65-F65 -> 0 | H65: =IF(G65>0,G65*3.087%,0) -> 0 | I65: =K$2*D65 -> 310500 | J65: =P$2*D65 -> 0 | K65: =G$2*0.675675676% -> 159026.35 | L65: =P$1*0.675675676% -> 202702.7 | M65: =G$1*D65 -> 0 | N65: 0 | P65: =ROUND(SUM(G65:O65),0) + R65 -> 672229.61 | R65: =ROUND(0.001+B65/100,2) -> 0.61 | S65: =B65 -> 61 | T65: polypeirano@yahoo.com
A66: 10 | B66: 62 | C66: Kanhan, Carlos | D66: 0.0041 | E66: 898130.62 | F66: =E66 -> 898130.62 | G66: =E66-F66 -> 0 | H66: =IF(G66>0,G66*3.087%,0) -> 0 | I66: =K$2*D66 -> 282900 | J66: =P$2*D66 -> 0 | K66: =G$2*0.675675676% -> 159026.35 | L66: =P$1*0.675675676% -> 202702.7 | M66: 51707 | N66: =(I66+K66)/2 -> 220963.18 | P66: =ROUND(SUM(G66:O66),0) + R66 -> 917299.62 | R66: =ROUND(0.001+B66/100,2) -> 0.62 | S66: =B66 -> 62
A67: 11 | B67: 63 | C67: Rudi, Marcela | D67: 0.0045 | E67: 658651.63 | F67: =E67 -> 658651.63 | G67: =E67-F67 -> 0 | H67: =IF(G67>0,G67*3.087%,0) -> 0 | I67: =K$2*D67 -> 310500 | J67: =P$2*D67 -> 0 | K67: =G$2*0.675675676% -> 159026.35 | L67: =P$1*0.675675676% -> 202702.7 | M67: =G$1*D67 -> 0 | N67: 0 | P67: =ROUND(SUM(G67:O67),0) + R67 -> 672229.63 | R67: =ROUND(0.001+B67/100,2) -> 0.63 | S67: =B67 -> 63 | T67: Flores javier roberto
A68: 11 | B68: 64 | C68: Molina, Leonardo | D68: 0.0045 | E68: 658651.64 | F68: =E68 -> 658651.64 | G68: =E68-F68 -> 0 | H68: =IF(G68>0,G68*3.087%,0) -> 0 | I68: =K$2*D68 -> 310500 | J68: =P$2*D68 -> 0 | K68: =G$2*0.675675676% -> 159026.35 | L68: =P$1*0.675675676% -> 202702.7 | M68: =G$1*D68 -> 0 | N68: 0 | P68: =ROUND(SUM(G68:O68),0) + R68 -> 672229.64 | R68: =ROUND(0.001+B68/100,2) -> 0.64 | S68: =B68 -> 64 | T68: Maria Laura Lopez
A69: 12 | B69: 65 | C69: Sallaberry, Pablo | D69: 0.0045 | E69: 658651.65 | F69: =E69 -> 658651.65 | G69: =E69-F69 -> 0 | H69: =IF(G69>0,G69*3.087%,0) -> 0 | I69: =K$2*D69 -> 310500 | J69: =P$2*D69 -> 0 | K69: =G$2*0.675675676% -> 159026.35 | L69: =P$1*0.675675676% -> 202702.7 | M69: =G$1*D69 -> 0 | N69: 0 | P69: =ROUND(SUM(G69:O69),0) + R69 -> 672229.65 | R69: =ROUND(0.001+B69/100,2) -> 0.65 | S69: =B69 -> 65
A70: 12 | B70: 66 | C70: Varela, E. / De Caria, S. | D70: 0.0045 | E70: 658651.66 | F70: =E70 -> 658651.66 | G70: =E70-F70 -> 0 | H70: =IF(G70>0,G70*3.087%,0) -> 0 | I70: =K$2*D70 -> 310500 | J70: =P$2*D70 -> 0 | K70: =G$2*0.675675676% -> 159026.35 | L70: =P$1*0.675675676% -> 202702.7 | M70: =G$1*D70 -> 0 | N70: 0 | P70: =ROUND(SUM(G70:O70),0) + R70 -> 672229.66 | R70: =ROUND(0.001+B70/100,2) -> 0.66 | S70: =B70 -> 66 | T70: Sergio Decaira / De caira
A71: 1 | B71: 67 | C71: Carnevale, Yesica | D71: 0.0045 | E71: 1372264.7 | F71: =E71 -> 1372264.7 | G71: =E71-F71 -> 0 | H71: =IF(G71>0,G71*3.087%,0) -> 0 | I71: =K$2*D71 -> 310500 | J71: =P$2*D71 -> 0 | K71: =G$2*0.675675676% -> 159026.35 | L71: =P$1*0.675675676% -> 202702.7 | M71: =G$1*D71 -> 0 | N71: 0 | P71: =ROUND(SUM(G71:O71),0) + R71 -> 672229.67 | R71: =ROUND(0.001+B71/100,2) -> 0.67 | S71: =B71 -> 67 | T71: Gonzalo Raul Fernandez - ivanalagolosinerasrl@gmail.com
B72: =B71+1 -> 68 | C72: Agüero, Paula | D72: 0.0045 | E72: 2889655.7 | F72: =E72 -> 2889655.7 | G72: =E72-F72 -> 0 | H72: =IF(G72>0,G72*3.087%,0) -> 0 | I72: =K$2*D72 -> 310500 | J72: =P$2*D72 -> 0 | K72: =G$2*0.675675676% -> 159026.35 | L72: =P$1*0.675675676% -> 202702.7 | M72: 56751 | N72: =(I72+K72)/2 -> 234763.18 | P72: =ROUND(SUM(G72:O72),0) + R72 -> 963743.68 | R72: =ROUND(0.001+B72/100,2) -> 0.68 | S72: =B72 -> 68
B73: =B72+1 -> 69 | C73: Fayanas, Santiago | D73: 0.0036 | E73: 598347.69 | F73: =E73 -> 598347.69 | G73: =E73-F73 -> 0 | H73: =IF(G73>0,G73*3.087%,0) -> 0 | I73: =K$2*D73 -> 248400 | J73: =P$2*D73 -> 0 | K73: =G$2*0.675675676% -> 159026.35 | L73: =P$1*0.675675676% -> 202702.7 | M73: =G$1*D73 -> 0 | N73: 0 | P73: =ROUND(SUM(G73:O73),0) + R73 -> 610129.69 | R73: =ROUND(0.001+B73/100,2) -> 0.69 | S73: =B73 -> 69 | T73: Lucila Martinez Rey
B74: =B73+1 -> 70 | C74: Amenta, Cristian | D74: 0.0044 | E74: 651952.7 | G74: =E74-F74 -> 651952.7 | H74: =IF(G74>0,G74*3.087%,0) -> 20125.78 | I74: =K$2*D74 -> 303600 | J74: =P$2*D74 -> 0 | K74: =G$2*0.675675676% -> 159026.35 | L74: =P$1*0.675675676% -> 202702.7 | M74: =G$1*D74 -> 0 | N74: 0 | P74: =ROUND(SUM(G74:O74),0) + R74 -> 1337408.7 | R74: =ROUND(0.001+B74/100,2) -> 0.7 | S74: =B74 -> 70 | T74: Horacio oscar brescia - Estefania Tortorisi
B75: =B74+1 -> 71 | C75: Mon, Fernando | D75: 0.004 | E75: 625149.71 | F75: 625150 | G75: =E75-F75 -> -0.29 | H75: =IF(G75>0,G75*3.087%,0) -> 0 | I75: =K$2*D75 -> 276000 | J75: =P$2*D75 -> 0 | K75: =G$2*0.675675676% -> 159026.35 | L75: =P$1*0.675675676% -> 202702.7 | M75: =G$1*D75 -> 0 | N75: 0 | P75: =ROUND(SUM(G75:O75),0) + R75 -> 637729.71 | R75: =ROUND(0.001+B75/100,2) -> 0.71 | S75: =B75 -> 71 | T75: Andrea Juarez Cecilia
B76: =B75+1 -> 72 | C76: Strianese, Marcos | D76: 0.004 | E76: 1246505.7 | F76: =650000*2 -> 1300000 | G76: =E76-F76 -> -53494.28 | H76: =IF(G76>0,G76*3.087%,0) -> 0 | I76: =K$2*D76 -> 276000 | J76: =P$2*D76 -> 0 | K76: =G$2*0.675675676% -> 159026.35 | L76: =P$1*0.675675676% -> 202702.7 | M76: =G$1*D76 -> 0 | N76: 0 | P76: =ROUND(SUM(G76:O76),0) + R76 -> 584235.72 | R76: =ROUND(0.001+B76/100,2) -> 0.72 | S76: =B76 -> 72 | T76: RECAUDACIONES Y PAGOS SA
B77: =B76+1 -> 73 | C77: Toniutti, Silvana | D77: 0.004 | E77: 1276337.7 | F77: =625000+620000+31338 -> 1276338 | G77: =E77-F77 -> -0.27 | H77: =IF(G77>0,G77*3.087%,0) -> 0 | I77: =K$2*D77 -> 276000 | J77: =P$2*D77 -> 0 | K77: =G$2*0.675675676% -> 159026.35 | L77: =P$1*0.675675676% -> 202702.7 | M77: =G$1*D77 -> 0 | N77: 0 | P77: =ROUND(SUM(G77:O77),0) + R77 -> 637729.73 | R77: =ROUND(0.001+B77/100,2) -> 0.73 | S77: =B77 -> 73
B78: =B77+1 -> 74 | C78: Morante, Julian | D78: 0.0044 | E78: 651951.74 | F78: =E78 -> 651951.74 | G78: =E78-F78 -> 0 | H78: =IF(G78>0,G78*3.087%,0) -> 0 | I78: =K$2*D78 -> 303600 | J78: =P$2*D78 -> 0 | K78: =G$2*0.675675676% -> 159026.35 | L78: =P$1*0.675675676% -> 202702.7 | M78: =G$1*D78 -> 0 | N78: 0 | P78: =ROUND(SUM(G78:O78),0) + R78 -> 665329.74 | R78: =ROUND(0.001+B78/100,2) -> 0.74 | S78: =B78 -> 74
B79: =B78+1 -> 75 | C79: Fernando Rivero y Mónica Cádiz | D79: 0.0041 | E79: 631849.75 | F79: =E79 -> 631849.75 | G79: =E79-F79 -> 0 | H79: =IF(G79>0,G79*3.087%,0) -> 0 | I79: =K$2*D79 -> 282900 | J79: =P$2*D79 -> 0 | K79: =G$2*0.675675676% -> 159026.35 | L79: =P$1*0.675675676% -> 202702.7 | M79: =G$1*D79 -> 0 | N79: 0 | P79: =ROUND(SUM(G79:O79),0) + R79 -> 644629.75 | R79: =ROUND(0.001+B79/100,2) -> 0.75 | S79: =B79 -> 75 | T79: Fernando Rivero
B80: =B79+1 -> 76 | C80: Hecimovic, Mariano | D80: 0.0045 | E80: 658651.76 | F80: =E80 -> 658651.76 | G80: =E80-F80 -> 0 | H80: =IF(G80>0,G80*3.087%,0) -> 0 | I80: =K$2*D80 -> 310500 | J80: =P$2*D80 -> 0 | K80: =G$2*0.675675676% -> 159026.35 | L80: =P$1*0.675675676% -> 202702.7 | M80: =G$1*D80 -> 0 | N80: 0 | P80: =ROUND(SUM(G80:O80),0) + R80 -> 672229.76 | R80: =ROUND(0.001+B80/100,2) -> 0.76 | S80: =B80 -> 76
B81: =B80+1 -> 77 | C81: Pantografos Master SRL. | D81: 0.0061 | E81: 1572593.8 | F81: =782575.77+765859.77+24158 -> 1572593.5 | G81: =E81-F81 -> 0.23 | H81: =IF(G81>0,G81*3.087%,0) -> 0.0071001 | I81: =K$2*D81 -> 420900 | J81: =P$2*D81 -> 0 | K81: =G$2*0.675675676% -> 159026.35 | L81: =P$1*0.675675676% -> 202702.7 | M81: =G$1*D81 -> 0 | N81: 0 | P81: =ROUND(SUM(G81:O81),0) + R81 -> 782629.77 | R81: =ROUND(0.001+B81/100,2) -> 0.77 | S81: =B81 -> 77 | T81: Diego Damino
B82: =B81+1 -> 78 | C82: Gimenez, Martin | D82: 0.0048 | E82: 677670.78 | F82: =E82 -> 677670.78 | G82: =E82-F82 -> 0 | H82: =IF(G82>0,G82*3.087%,0) -> 0 | I82: =K$2*D82 -> 331200 | J82: =P$2*D82 -> 0 | K82: =G$2*0.675675676% -> 159026.35 | L82: =P$1*0.675675676% -> 202702.7 | M82: =G$1*D82 -> 0 | N82: 0 | P82: =ROUND(SUM(G82:O82),0) + R82 -> 692929.78 | R82: =ROUND(0.001+B82/100,2) -> 0.78 | S82: =B82 -> 78 | T82: Potes Paula Vanesa
B83: =B82+1 -> 79 | C83: Soto Hinojosa, Porfirio | D83: 0.0045 | E83: 1383904.8 | F83: =357633+314553+263206+408980 -> 1344372 | G83: =E83-F83 -> 39532.79 | H83: =IF(G83>0,G83*3.087%,0) -> 1220.3772 | I83: =K$2*D83 -> 310500 | J83: =P$2*D83 -> 0 | K83: =G$2*0.675675676% -> 159026.35 | L83: =P$1*0.675675676% -> 202702.7 | M83: =G$1*D83 -> 0 | N83: 0 | P83: =ROUND(SUM(G83:O83),0) + R83 -> 712982.79 | R83: =ROUND(0.001+B83/100,2) -> 0.79 | S83: =B83 -> 79 | T83: Diego Soto y Hernan Soto | X83: Gergoff Ninoff Milagros Florencia / Diego soto / Profirio Soto
B84: =B83+1 -> 80 | C84: Mozzi, German | D84: 0.0045 | E84: 658651.8 | F84: =E84 -> 658651.8 | G84: =E84-F84 -> 0 | H84: =IF(G84>0,G84*3.087%,0) -> 0 | I84: =K$2*D84 -> 310500 | J84: =P$2*D84 -> 0 | K84: =G$2*0.675675676% -> 159026.35 | L84: =P$1*0.675675676% -> 202702.7 | M84: =G$1*D84 -> 0 | N84: 0 | P84: =ROUND(SUM(G84:O84),0) + R84 -> 672229.8 | R84: =ROUND(0.001+B84/100,2) -> 0.8 | S84: =B84 -> 80 | T84: ad RUIZ DIAZ - Maria agustina Falcone
B85: =B84+1 -> 81 | C85: De Nardi, Maria Rosa | D85: 0.0045 | E85: 679558.81 | G85: =E85-F85 -> 679558.81 | H85: =IF(G85>0,G85*3.087%,0) -> 20977.98 | I85: =K$2*D85 -> 310500 | J85: =P$2*D85 -> 0 | K85: =G$2*0.675675676% -> 159026.35 | L85: =P$1*0.675675676% -> 202702.7 | M85: =G$1*D85 -> 0 | N85: 0 | P85: =ROUND(SUM(G85:O85),0) + R85 -> 1372766.8 | R85: =ROUND(0.001+B85/100,2) -> 0.81 | S85: =B85 -> 81 | T85: Santiago Roman Ramirez
B86: =B85+1 -> 82 | C86: Castro, Alejandra | D86: 0.0042 | E86: 2612682.8 | F86: =638566.82+1915000 -> 2553566.8 | G86: =E86-F86 -> 59116 | H86: =IF(G86>0,G86*3.087%,0) -> 1824.9109 | I86: =K$2*D86 -> 289800 | J86: =P$2*D86 -> 0 | K86: =G$2*0.675675676% -> 159026.35 | L86: =P$1*0.675675676% -> 202702.7 | M86: =G$1*D86 -> 0 | N86: 0 | P86: =ROUND(SUM(G86:O86),0) + R86 -> 712470.82 | R86: =ROUND(0.001+B86/100,2) -> 0.82 | S86: =B86 -> 82 | T86: Montenievas SRL
B87: =B86+1 -> 83 | C87: Tapia, Sergio | D87: 0.0048 | E87: 678753.83 | F87: =E87 -> 678753.83 | G87: =E87-F87 -> 0 | H87: =IF(G87>0,G87*3.087%,0) -> 0 | I87: =K$2*D87 -> 331200 | J87: =P$2*D87 -> 0 | K87: =G$2*0.675675676% -> 159026.35 | L87: =P$1*0.675675676% -> 202702.7 | M87: =G$1*D87 -> 0 | N87: 0 | P87: =ROUND(SUM(G87:O87),0) + R87 -> 692929.83 | R87: =ROUND(0.001+B87/100,2) -> 0.83 | S87: =B87 -> 83
B88: =B87+1 -> 84 | C88: Tapia, Sergio | D88: 0.0048 | E88: 678753.84 | F88: =E88 -> 678753.84 | G88: =E88-F88 -> 0 | H88: =IF(G88>0,G88*3.087%,0) -> 0 | I88: =K$2*D88 -> 331200 | J88: =P$2*D88 -> 0 | K88: =G$2*0.675675676% -> 159026.35 | L88: =P$1*0.675675676% -> 202702.7 | M88: =G$1*D88 -> 0 | N88: 0 | P88: =ROUND(SUM(G88:O88),0) + R88 -> 692929.84 | R88: =ROUND(0.001+B88/100,2) -> 0.84 | S88: =B88 -> 84
B89: =B88+1 -> 85 | C89: Albornoz, M. / Rodriguez, G. | D89: 0.0048 | E89: 678753.85 | F89: =E89 -> 678753.85 | G89: =E89-F89 -> 0 | H89: =IF(G89>0,G89*3.087%,0) -> 0 | I89: =K$2*D89 -> 331200 | J89: =P$2*D89 -> 0 | K89: =G$2*0.675675676% -> 159026.35 | L89: =P$1*0.675675676% -> 202702.7 | M89: =G$1*D89 -> 0 | N89: 0 | P89: =ROUND(SUM(G89:O89),0) + R89 -> 692929.85 | R89: =ROUND(0.001+B89/100,2) -> 0.85 | S89: =B89 -> 85 | T89: Guillermo rodriguez
B90: =B89+1 -> 86 | C90: Bernardez, Diego | D90: 0.0048 | E90: 678753.86 | F90: =E90 -> 678753.86 | G90: =E90-F90 -> 0 | H90: =IF(G90>0,G90*3.087%,0) -> 0 | I90: =K$2*D90 -> 331200 | J90: =P$2*D90 -> 0 | K90: =G$2*0.675675676% -> 159026.35 | L90: =P$1*0.675675676% -> 202702.7 | M90: =G$1*D90 -> 0 | N90: 0 | P90: =ROUND(SUM(G90:O90),0) + R90 -> 692929.86 | R90: =ROUND(0.001+B90/100,2) -> 0.86 | S90: =B90 -> 86
B91: =B90+1 -> 87 | C91: Repetto, Mariano | D91: 0.0048 | E91: 678753.87 | F91: =E91 -> 678753.87 | G91: =E91-F91 -> 0 | H91: =IF(G91>0,G91*3.087%,0) -> 0 | I91: =K$2*D91 -> 331200 | J91: =P$2*D91 -> 0 | K91: =G$2*0.675675676% -> 159026.35 | L91: =P$1*0.675675676% -> 202702.7 | M91: =G$1*D91 -> 0 | N91: 0 | P91: =ROUND(SUM(G91:O91),0) + R91 -> 692929.87 | R91: =ROUND(0.001+B91/100,2) -> 0.87 | S91: =B91 -> 87
B92: =B91+1 -> 88 | C92: Escudero, Ignacio | D92: 0.0048 | E92: 671637.88 | F92: 672000 | G92: =E92-F92 -> -362.12 | H92: =IF(G92>0,G92*3.087%,0) -> 0 | I92: =K$2*D92 -> 331200 | J92: =P$2*D92 -> 0 | K92: =G$2*0.675675676% -> 159026.35 | L92: =P$1*0.675675676% -> 202702.7 | M92: =G$1*D92 -> 0 | N92: 0 | P92: =ROUND(SUM(G92:O92),0) + R92 -> 692567.88 | R92: =ROUND(0.001+B92/100,2) -> 0.88 | S92: =B92 -> 88
B93: =B92+1 -> 89 | C93: Calabro, Evangelina | D93: 0.0048 | E93: 678753.89 | F93: =E93 -> 678753.89 | G93: =E93-F93 -> 0 | H93: =IF(G93>0,G93*3.087%,0) -> 0 | I93: =K$2*D93 -> 331200 | J93: =P$2*D93 -> 0 | K93: =G$2*0.675675676% -> 159026.35 | L93: =P$1*0.675675676% -> 202702.7 | M93: =G$1*D93 -> 0 | N93: 0 | P93: =ROUND(SUM(G93:O93),0) + R93 -> 692929.89 | R93: =ROUND(0.001+B93/100,2) -> 0.89 | S93: =B93 -> 89
B94: =B93+1 -> 90 | C94: Shunk, Dora | D94: 0.0048 | E94: 1445406.9 | F94: 700000 | G94: =E94-F94 -> 745406.9 | H94: =IF(G94>0,G94*3.087%,0) -> 23010.711 | I94: =K$2*D94 -> 331200 | J94: =P$2*D94 -> 0 | K94: =G$2*0.675675676% -> 159026.35 | L94: =P$1*0.675675676% -> 202702.7 | M94: =G$1*D94 -> 0 | N94: 0 | P94: =ROUND(SUM(G94:O94),0) + R94 -> 1461347.9 | R94: =ROUND(0.001+B94/100,2) -> 0.9 | S94: =B94 -> 90 | T94: de nardi paula andrea
B95: =B94+1 -> 91 | C95: Gutierrez, Nicolas | D95: 0.0048 | E95: 678753.91 | G95: =E95-F95 -> 678753.91 | H95: =IF(G95>0,G95*3.087%,0) -> 20953.133 | I95: =K$2*D95 -> 331200 | J95: =P$2*D95 -> 0 | K95: =G$2*0.675675676% -> 159026.35 | L95: =P$1*0.675675676% -> 202702.7 | M95: =G$1*D95 -> 0 | N95: 0 | P95: =ROUND(SUM(G95:O95),0) + R95 -> 1392636.9 | R95: =ROUND(0.001+B95/100,2) -> 0.91 | S95: =B95 -> 91 | T95: Nicolas Esteban Gutierrez
B96: =B95+1 -> 92 | C96: Fino, Claudia | D96: 0.0048 | E96: 2956805.9 | G96: =E96-F96 -> 2956805.9 | H96: =IF(G96>0,G96*3.087%,0) -> 91276.599 | I96: =K$2*D96 -> 331200 | J96: =P$2*D96 -> 0 | K96: =G$2*0.675675676% -> 159026.35 | L96: =P$1*0.675675676% -> 202702.7 | M96: =G$1*D96 -> 0 | N96: 0 | P96: =ROUND(SUM(G96:O96),0) + R96 -> 3741012.9 | R96: =ROUND(0.001+B96/100,2) -> 0.92 | S96: =B96 -> 92 | T96: Ines / Jorge o Ayestaran Melanie que es la inquilina
B97: =B96+1 -> 93 | C97: Arderiu, Marcelo | D97: 0.0046 | E97: -660.07 | G97: =E97-F97 -> -660.07 | H97: =IF(G97>0,G97*3.087%,0) -> 0 | I97: =K$2*D97 -> 317400 | J97: =P$2*D97 -> 0 | K97: =G$2*0.675675676% -> 159026.35 | L97: =P$1*0.675675676% -> 202702.7 | M97: =G$1*D97 -> 0 | N97: 0 | P97: =ROUND(SUM(G97:O97),0) + R97 -> 678469.93 | R97: =ROUND(0.001+B97/100,2) -> 0.93 | S97: =B97 -> 93
B98: =B97+1 -> 94 | C98: Loray, Ana Laura | D98: 0.0048 | E98: 710915.94 | F98: =E98 -> 710915.94 | G98: =E98-F98 -> 0 | H98: =IF(G98>0,G98*3.087%,0) -> 0 | I98: =K$2*D98 -> 331200 | J98: =P$2*D98 -> 0 | K98: =G$2*0.675675676% -> 159026.35 | L98: =P$1*0.675675676% -> 202702.7 | M98: =G$1*D98 -> 0 | N98: 0 | O98: 150760 | P98: =ROUND(SUM(G98:O98),0) + R98 -> 843689.94 | R98: =ROUND(0.001+B98/100,2) -> 0.94 | S98: =B98 -> 94 | T98: Imsael Matta
B99: =B98+1 -> 95 | C99: Manzo, Dominguez | D99: 0.0048 | E99: 2264087 | F99: 800000 | G99: =E99-F99 -> 1464087 | H99: =IF(G99>0,G99*3.087%,0) -> 45196.364 | I99: =K$2*D99 -> 331200 | J99: =P$2*D99 -> 0 | K99: =G$2*0.675675676% -> 159026.35 | L99: =P$1*0.675675676% -> 202702.7 | M99: =G$1*D99 -> 0 | N99: 0 | P99: =ROUND(SUM(G99:O99),0) + R99 -> 2202213 | R99: =ROUND(0.001+B99/100,2) -> 0.95 | S99: =B99 -> 95
B100: =B99+1 -> 96 | C100: Perri, Antonio | D100: 0.0048 | E100: 1392050 | F100: =200000+200000+120000+180000+21360 -> 721360 | G100: =E100-F100 -> 670689.96 | H100: =IF(G100>0,G100*3.087%,0) -> 20704.199 | I100: =K$2*D100 -> 331200 | J100: =P$2*D100 -> 0 | K100: =G$2*0.675675676% -> 159026.35 | L100: =P$1*0.675675676% -> 202702.7 | M100: =G$1*D100 -> 0 | N100: 0 | P100: =ROUND(SUM(G100:O100),0) + R100 -> 1384324 | R100: =ROUND(0.001+B100/100,2) -> 0.96 | S100: =B100 -> 96 | T100: Deposita - Andrea Iglesias
B101: =B100+1 -> 97 | C101: Rosemberg, Alejandro | D101: 0.0048 | E101: 678753.97 | F101: =678754 -> 678754 | G101: =E101-F101 -> -0.03 | H101: =IF(G101>0,G101*3.087%,0) -> 0 | I101: =K$2*D101 -> 331200 | J101: =P$2*D101 -> 0 | K101: =G$2*0.675675676% -> 159026.35 | L101: =P$1*0.675675676% -> 202702.7 | M101: =G$1*D101 -> 0 | N101: 0 | P101: =ROUND(SUM(G101:O101),0) + R101 -> 692929.97 | R101: =ROUND(0.001+B101/100,2) -> 0.97 | S101: =B101 -> 97 | T101: PAYMENTS GROUP SA
...

Sheet anotaciones
C1: ANOTACION | D1: 1
C2: FECHA DE LA ANOTACION: | E2: 45874 | G2: NOMBRE: | H2: Daiana Casas
C3: QUEJA VIA: | D3: WHATSAPP | E3: MAIL | G3: LOTE: | H3: 109
C4: FECHA DE LA QUEJA: | E4: 45874
C5: MOTIVO DE LA QUEJA:
C6: Deposito el 05/08 $722.000 y 2000
C11: ANOTACION | D11: =D1+1 -> 2
C12: FECHA DE LA ANOTACION: | E12: 45875 | G12: NOMBRE: | H12: Marcos Strianese
C13: QUEJA VIA: | D13: WHATSAPP | E13: MAIL | G13: LOTE: | H13: 72
C14: FECHA DE LA QUEJA: | E14: 45874
C15: MOTIVO DE LA QUEJA:
C16: Deposito 650 mil el 5/8 y Deposito 650 mil el 25/8
C21: ANOTACION | D21: =D11+1 -> 3
C22: FECHA DE LA ANOTACION: | E22: 45883 | G22: NOMBRE: | H22: ALEJANDRA CASTRO
C23: QUEJA VIA: | D23: WHATSAPP | E23: MAIL | G23: LOTE: | H23: 82
C24: FECHA DE LA QUEJA: | E24: 45871
C25: MOTIVO DE LA QUEJA:
C26: Deposito el 01/08 $1.915.000 - tiene pdf con desglose a abonar
C31: ANOTACION | D31: =D21+1 -> 4
C32: FECHA DE LA ANOTACION: | E32: 45887 | G32: NOMBRE: | H32: ventas@quimicaros.com.ar
C33: QUEJA VIA: | D33: WHATSAPP | E33: MAIL | G33: LOTE: | H33: 31
C34: FECHA DE LA QUEJA: | E34: 45871
C35: MOTIVO DE LA QUEJA:
C36: 672184 el 12/08
C41: ANOTACION | D41: =D31+1 -> 5
C42: FECHA DE LA ANOTACION: | E42: 45887 | G42: NOMBRE: | H42: Juan ignacio santangelo
C43: QUEJA VIA: | D43: WHATSAPP | E43: MAIL | G43: LOTE: | H43: 105
C44: FECHA DE LA QUEJA:
C45: MOTIVO DE LA QUEJA:
C46: El mes pasado le pusimos dinero de mas que no correspondia. Ademas, no le pusimossu deposito de 651498 y le estabamos cobrando intereses mal cobrados de 37738 - debe abonar $638.551,05. y quedar en 0
C51: ANOTACION | D51: =D41+1 -> 6
C52: FECHA DE LA ANOTACION: | E52: 45887 | G52: NOMBRE: | H52: Gustavo kearney
C53: QUEJA VIA: | D53: WHATSAPP | E53: MAIL | G53: LOTE: | H53: 12 y 11
C54: FECHA DE LA QUEJA: | E54: 45887
C55: MOTIVO DE LA QUEJA:
C56: El 31/07 deposito $700.000 pesos y se lo pusimos al lote 11 cuando era al lote 12
C61: ANOTACION | D61: =D51+1 -> 7
C62: FECHA DE LA ANOTACION: | E62: 45888 | G62: NOMBRE: | H62: Sergio Ferraris
C63: QUEJA VIA: | D63: WHATSAPP | E63: MAIL | G63: LOTE: | H63: 9
C64: FECHA DE LA QUEJA: | E64: 45887
C65: MOTIVO DE LA QUEJA:
C66: 18/08 Tres depositos: dos de 1.000.000 y uno de 1.500.000
C71: ANOTACION | D71: =D61+1 -> 8
C72: FECHA DE LA ANOTACION: | E72: 45888 | G72: NOMBRE: | H72: Maria Jose
C73: QUEJA VIA: | D73: WHATSAPP | E73: MAIL | G73: LOTE: | H73: 110
C74: FECHA DE LA QUEJA: | E74: 45887
C75: MOTIVO DE LA QUEJA:
C76: Hay que quitarle los punitorios - Hizo un pago de $679.085,10 el 13/08 si realiza otro de aca a que termine agosto por 665.352,10 su saldo debe quedar en 0 quitando punitorios
C81: ANOTACION | D81: =D71+1 -> 9
C82: FECHA DE LA ANOTACION: | E82: 45889 | G82: NOMBRE: | H82: Rito nicolas
C83: QUEJA VIA: | D83: WHATSAPP | E83: MAIL | G83: LOTE: | H83: 126
C84: FECHA DE LA QUEJA: | E84: 45889
C85: MOTIVO DE LA QUEJA:
C86: Hay que quitarle los punitorios - si realiza otro de aca a que termine agosto por $666.672,26. su saldo debe quedar en 0 quitando punitorios
C91: ANOTACION | D91: =D81+1 -> 10
C92: FECHA DE LA ANOTACION: | E92: 45889 | G92: NOMBRE: | H92: Topino maximiliano
C93: QUEJA VIA: | D93: WHATSAPP | E93: MAIL | G93: LOTE: | H93: 47
C94: FECHA DE LA QUEJA: | E94: 45889
C95: MOTIVO DE LA QUEJA:
C96: un deposito no identificado del mes anterior es de el $2055315 - HICIMOS UN PDF (EN EL CHAT DE MATEO Y CAROLINA DE WHATSAPP) EN DONDE SE DESGLOSA SU SITUACION E IMPORTE A PAGAR DEL LOTE 47 Y 4
C101: ANOTACION | D101: =D91+1 -> 11
C102: FECHA DE LA ANOTACION: | E102: 45889 | G102: NOMBRE:
C103: QUEJA VIA: | D103: WHATSAPP | E103: MAIL | G103: LOTE: | H103: 24/55/58
C104: FECHA DE LA QUEJA: | E104: 45889
C105: MOTIVO DE LA QUEJA:
C106: un deposito no identificado del mes anterior es de el $2055315 - HICIMOS UN PDF (EN EL CHAT DE MATEO Y CAROLINA DE WHATSAPP) EN DONDE SE DESGLOSA SU SITUACION E IMPORTE A PAGAR DEL LOTE 24 55 y 58
C111: ANOTACION | D111: =D101+1 -> 12
C112: FECHA DE LA ANOTACION: | E112: 45889 | G112: NOMBRE: | H112: hugoecarnevaleok@gmail.com+
C113: QUEJA VIA: | D113: WHATSAPP | E113: MAIL | G113: LOTE: | H113: 68
C114: FECHA DE LA QUEJA: | E114: 45889
C115: MOTIVO DE LA QUEJA:
C116: $2.889.655,68 LOTE 68 DEPOSITO EL 20/8
C121: ANOTACION | D121: =D111+1 -> 13
C122: FECHA DE LA ANOTACION: | E122: 45889 | G122: NOMBRE: | H122: JP GIORDANO
C123: QUEJA VIA: | D123: WHATSAPP | E123: MAIL | G123: LOTE: | H123: 32 Y MUCHOS MAS
C124: FECHA DE LA QUEJA: | E124: 45889
C125: MOTIVO DE LA QUEJA:
C126: PAGA LOTES 13 16 32 33 86 158 159 168 $5.888.095: SOBRAN CENTAVOS QUE HAY QUE PONERLOS EN EL LOTE 32
C131: ANOTACION | D131: =D111+1 -> 13
C132: FECHA DE LA ANOTACION: | E132: 45889 | G132: NOMBRE: | H132: DANIEL PERFUMO
C133: QUEJA VIA: | D133: WHATSAPP | E133: MAIL | G133: LOTE: | H133: 104
C134: FECHA DE LA QUEJA: | E134: 45889
C135: MOTIVO DE LA QUEJA:
C136: Pago sin centavos $672.053
C141: ANOTACION | D141: =D121+1 -> 14
C142: FECHA DE LA ANOTACION: | E142: 45889 | G142: NOMBRE: | H142: Diego Damino
C143: QUEJA VIA: | D143: WHATSAPP | E143: MAIL | G143: LOTE: | H143: 77
C144: FECHA DE LA QUEJA: | E144: 45889
C145: MOTIVO DE LA QUEJA:
C146: El mes enterior pago en tiempo y forma $782575,77 y no lo pusimos pago
C151: ANOTACION | D151: =D141+1 -> 15
C152: FECHA DE LA ANOTACION: | E152: 45890 | G152: NOMBRE: | H152: Andrea iglesias
C153: QUEJA VIA: | D153: WHATSAPP | E153: MAIL | G153: LOTE: | H153: 96
C154: FECHA DE LA QUEJA: | E154: 45890
C155: MOTIVO DE LA QUEJA:
C156: Los depositos del 30/7 no identificados son de ella: 2 de 200mil, uno de 120mil y uno de 180 mil
C161: ANOTACION | D161: =D151+1 -> 16
C162: FECHA DE LA ANOTACION: | E162: 45894 | G162: NOMBRE: | H162: Luis y karina Grecco
C163: QUEJA VIA: | D163: WHATSAPP | E163: MAIL | G163: LOTE: | H163: 26
C164: FECHA DE LA QUEJA: | E164: 45893
...

Sheet suzel
D5: CIERRE EXPENSAS JULIO
D6: LOTE | E6: MONTO A ABONAR
D7: =PRORRATEO!S122 -> 118 | E7: =PRORRATEO!P122 -> 1077853.2
D8: =PRORRATEO!S124 -> 120 | E8: =PRORRATEO!P124 -> 679130.2
D9: =PRORRATEO!S125 -> 121 | E9: =PRORRATEO!P125 -> 679130.21
D10: TOTAL | E10: =SUM(E7:E9) -> 2436113.6
D12: 25/8 DEPOSITO | E12: 1770000
D13: RESTA ABONAR | E13: =E10-E12 -> 666113.59

Sheet SUMS A CORREGIR
B9: al lote 38 le cobramos una deuda (bien cobrada) y un sum por 150.760 MAL COBRADO, este sum que le cobramos mal al 38 era para el 32
