Workbook

Sheet RESUMEN
C1: MAIL: elmiradorconsorcios@gmail.com
C2: CUIT ADMINISTRACION: 27231256879
C3: CBU: | E3: TELEFONO: 11 5320-2676
C4: ADMINISTRADORA: CAROLINA CANCIANI MP:1148
C5: PERÍODO: JULIO | E5: HORARIOS DE ATENCION: LUNES A VIERNES - 10 A 16HS - EMERGENCIAS 24HS
C6: LIQUIDACION DE EXPENSAS
A14: Importante para dueños o inquilinos de departamentos o coheras: Queremos recordarles una cuestión importante respecto a los pagos de expensas que ayuda a evitar errores en la imputación de los mismos. El sistema que utilizamos asigna centavos únicos a cada Unidad Funcional (UF), lo cual nos permite identificar automáticamente a qué unidad corresponde cada transferencia. Es decir, cada UF tiene un número específico de centavos que actúa como "identificador". Por ejemplo, si tu UF es la 45, el importe a abonar debería terminar en $...,45. Si tenés más de una unidad (por ejemplo, un departamento y una cochera), cada una tiene su propio código de centavos. En esos casos, te pedimos por favor que realices una transferencia por cada UF, respetando el importe con sus centavos correspondientes. Sabemos que a veces por comodidad se suele enviar todo junto en una sola transferencia, pero esto puede generar confusión o errores en la imputación automática. Realizar los pagos por separado nos permite asegurar que cada importe se asigne correctamente. Agradecemos muchísimo la colaboración para seguir manteniendo todo ordenado. Saludos cordiales.
A20: VTO 14/08
A24: GASTOS ORDINARIOS UNIDADES FUNCIONALES: | E24: UF 93,20% | F24: LOCAL 1 (1,08%) | G24: LOCAL 2 (1,28%) | H24: LOCAL 3 (1,21%) | I24: LOCAL 4 (1,49%) | J24: LOCAL 5 (1,74%)
A25: Sueldo encargada Sonia Arzamendia Galeano
A26: Haberes | D26: 977372
A27: Plus pileta | D27: 34111
A28: Plus retiro de basura | D28: 111256.4
A29: Plus cochera | D29: 20777
A30: Adicional remuneracion | D30: 50000
A31: SUBTOTAL | D31: =SUM(D26:D30) -> 1193516.4
A32: Sueldo encargada Miriam
A33: Haberes | D33: 488686
A34: Plus pileta | D34: 34111
A35: Plus retiro de basura | D35: 111256.4
A36: Plus cochera | D36: 20777
A37: Adicional remuneracion | D37: 50000
A38: SUBTOTAL | D38: =SUM(D33:D37) -> 704830.4
A39: TOTAL SUELDO | D39: =D31+D38 -> 1898346.8 | E39: =D39*93.2% -> 1769259.2 | F39: =$D39*1.08% -> 20502.145 | G39: =$D39*1.28% -> 24298.839 | H39: =$D39*1.21% -> 22969.996 | I39: =$D39*1.49% -> 28285.367 | J39: =D39*1.74% -> 33031.234 | K39: =E39+J39+F39+G39+H39+I39 -> 1898346.8 | L39: =IF(D39=K39, "", "Error")
A40: SAC | D40: 0 | E40: =D40*91.91% -> 0 | J40: =D40*8.09% -> 0
D41: 0 | E41: =D41*91.91% -> 0 | J41: =D41*8.09% -> 0
A44: TOTAL | D44: =SUM(D40:D42) -> 0 | E44: =SUM(E40:E42) -> 0 | J44: =SUM(J40:J42) -> 0 | K44: =E44+J44 -> 0 | L44: =IF(D44=K44, "", "Error")
A45: COMBUSTIBLE PARA GRUPO ELECTROGENO | E45: =D45*91.91% -> 0 | J45: =D45*8.09% -> 0
A46: Gas Lanus SA - Compra infinia diesel | C46: Efect 24/07 | D46: 37011.99 | E46: =D46 -> 37011.99
A47: Gas Lanus SA - Compra infinia diesel | C47: Efect 24/07 | D47: 65006.06 | E47: =D47 -> 65006.06
A48: Gas Lanus SA - Compra infinia diesel | C48: Efect 26/07 | D48: 26019.04 | E48: =D48 -> 26019.04
A49: Gas Lanus SA - Compra infinia diesel | C49: Efect 28/07 | D49: 23000 | E49: =D49 -> 23000
A50: Gas Lanus SA - Compra infinia diesel | C50: Efect 31/07 | D50: 27002.95 | E50: =D50 -> 27002.95
E51: =D51*91.91% -> 0 | J51: =D51*8.09% -> 0
A52: TOTAL SAC | D52: =SUM(D41:D51) -> 178040.04 | E52: =SUM(E41:E51) -> 178040.04 | K52: =E52+J52+F52+G52+H52+I52 -> 178040.04 | L52: =IF(D52=K52, "", "Error")
A53: IMPUESTOS
A54: ARBA - Impuesto inmobiliario partida 025024270-0
A55: TSG - Partida 197229000 | C55: PMC 10/07 | D55: 643422
A56: TSG - Partida 197227000 | C56: PMC 10/07 | D56: 643422
A57: TOTAL IMPUESTOS | D57: =SUM(D54:D56) -> 1286844 | E57: =D57*93.2% -> 1199338.6 | F57: =$D57*1.08% -> 13897.915 | G57: =$D57*1.28% -> 16471.603 | H57: =$D57*1.21% -> 15570.812 | I57: =$D57*1.49% -> 19173.976 | J57: =D57*1.74% -> 22391.086 | K57: =E57+J57+F57+G57+H57+I57 -> 1286844 | L57: =IF(D57=K57, "", "Error")
A58: APORTES Y CONTRIBUCIONES
A59: Monotributo Sra. Sonia | C59: Mercado P. 30/07 | D59: 49257.04
A60: Monotributo Sra. Miriam | C60: Transf 21/07 | D60: 56422.63
A61: TOTAL APORTES Y CONTRIBUCIONES | D61: =SUM(D58:D60) -> 105679.67 | E61: =D61*93.2% -> 98493.452 | F61: =$D61*1.08% -> 1141.3404 | G61: =$D61*1.28% -> 1352.6998 | H61: =$D61*1.21% -> 1278.724 | I61: =$D61*1.49% -> 1574.6271 | J61: =D61*1.74% -> 1838.8263 | K61: =E61+J61+F61+G61+H61+I61 -> 105679.67 | L61: =IF(D61=K61, "", "Error")
A62: SEGUROS
A63: Federacion patronal - Poliza integral para consorcios nro. 2152393 | C63: Mercado P. 09/07 | D63: 160913 | E63: =D63*93.2% -> 149970.92 | F63: =$D63*1.08% -> 1737.8604 | G63: =$D63*1.28% -> 2059.6864 | H63: =$D63*1.21% -> 1947.0473 | I63: =$D63*1.49% -> 2397.6037 | J63: =D63*1.74% -> 2799.8862 | K63: =SUM(E63:J63) -> 160913
A64: Federacion patronal - Poliza accidentes personales Sra. Sonia - nro. 9559834 | C64: Mercado P. 09/07 | D64: 7907 | E64: =D64*93.2% -> 7369.324 | F64: =$D64*1.08% -> 85.3956 | G64: =$D64*1.28% -> 101.2096 | H64: =$D64*1.21% -> 95.6747 | I64: =$D64*1.49% -> 117.8143 | J64: =D64*1.74% -> 137.5818 | K64: =SUM(E64:J64) -> 7907
A65: Federacion patronal - Poliza accidentes personales Sra. Miriam - nro. 9559886 | C65: Mercado P. 09/07 | D65: 7907 | E65: =D65*93.2% -> 7369.324 | F65: =$D65*1.08% -> 85.3956 | G65: =$D65*1.28% -> 101.2096 | H65: =$D65*1.21% -> 95.6747 | I65: =$D65*1.49% -> 117.8143 | J65: =D65*1.74% -> 137.5818 | K65: =SUM(E65:J65) -> 7907
A66: TOTAL Aportes y Contribuciones - Sindicato | D66: =SUM(D63:D65) -> 176727 | E66: =SUM(E63:E65) -> 164709.56 | F66: =SUM(F63:F65) -> 1908.6516 | G66: =SUM(G63:G65) -> 2262.1056 | H66: =SUM(H63:H65) -> 2138.3967 | I66: =SUM(I63:I65) -> 2633.2323 | J66: =SUM(J63:J65) -> 3075.0498 | K66: =E66+J66+F66+G66+H66+I66 -> 176727 | L66: =IF(D66=K66, "", "Error")
A67: ABONOS Y SERVICIOS
A68: Aysa - Cuenta 249011 | C68: Efect. 29/07 | D68: 161756.56 | E68: =D68*93.2% -> 150757.11 | F68: =$D68*1.08% -> 1746.9708 | G68: =$D68*1.28% -> 2070.484 | H68: =$D68*1.21% -> 1957.2544 | I68: =$D68*1.49% -> 2410.1727 | J68: =D68*1.74% -> 2814.5641 | K68: =D68 -> 161756.56 | L68: =SUM(E68:J68) -> 161756.56 | M68: =L68-D68 -> 0 | N68: =K68-D68 -> 0
A69: Edesur - Cliente 01291636 | C69: Efect. 18/07 | D69: 1233986 | E69: =D69*93.2% -> 1150075 | F69: =$D69*1.08% -> 13327.049 | G69: =$D69*1.28% -> 15795.021 | H69: =$D69*1.21% -> 14931.231 | I69: =$D69*1.49% -> 18386.392 | J69: =D69*1.74% -> 21471.357 | K69: =D69 -> 1233986 | L69: =E69+J69+I69+H69+G69+F69 -> 1233986 | M69: =L69-D69 -> 0 | N69: =K69-D69 -> 0
A70: Telecentro - Zona coworking - Cliente 7725479 | C70: Efect. 24/07 | D70: 100525.5 | E70: =D70 -> 100525.5 | K70: =D70 -> 100525.5 | L70: =E70+J70+I70+H70+G70+F70 -> 100525.5 | M70: =L70-D70 -> 0 | N70: =K70-D70 -> 0
A71: ADS - Abono de mantenimiento ascensores JULIO del 2025 | C71: Transf 05/07 | D71: 263223.14 | E71: =D71 -> 263223.14 | K71: =D71 -> 263223.14 | L71: =E71+J71+I71+H71+G71+F71 -> 263223.14
A72: Victor Martinez - Abono mantenimiento control de accesos - No llego factura | D72: 0 | E72: =D72 -> 0 | K72: =D72 -> 0 | L72: =E72+J72+I72+H72+G72+F72 -> 0 | M72: =L72-D72 -> 0 | N72: =K72-D72 -> 0
A73: Metrogas - Cliente nro. 40000496339 | C73: Vt. 02/07 | D73: 25666.87 | E73: =D73*93.2% -> 23921.523 | F73: =$D73*1.08% -> 277.2022 | G73: =$D73*1.28% -> 328.53594 | H73: =$D73*1.21% -> 310.56913 | I73: =$D73*1.49% -> 382.43636 | J73: =D73*1.74% -> 446.60354 | K73: =D73 -> 25666.87 | L73: =E73+J73+I73+H73+G73+F73 -> 25666.87 | M73: =L73-D73 -> 0 | N73: =K73-D73 -> 0
A74: Metrogas - Cliente nro. 40000497007 | C74: Vt. 02/07 | D74: 32660.43 | E74: =D74*93.2% -> 30439.521 | F74: =$D74*1.08% -> 352.73264 | G74: =$D74*1.28% -> 418.0535 | H74: =$D74*1.21% -> 395.1912 | I74: =$D74*1.49% -> 486.64041 | J74: =D74*1.74% -> 568.29148 | K74: =D74 -> 32660.43 | L74: =E74+J74+I74+H74+G74+F74 -> 32660.43 | M74: =L74-D74 -> 0 | N74: =K74-D74 -> 0
A75: Loschi Mantenimiento grupo electrogeno - Abono bimestral | D75: 100000 | E75: =D75 -> 100000 | K75: =D75 -> 100000 | L75: =E75+J75+I75+H75+G75+F75 -> 100000 | M75: =L75-D75 -> 0 | N75: =K75-D75 -> 0
A76: Loschi - Provision bomba electrica para carga de combustible | D76: 80000 | E76: =D76 -> 80000 | K76: =D76 -> 80000 | L76: =E76+J76+I76+H76+G76+F76 -> 80000 | M76: =L76-D76 -> 0 | N76: =K76-D76 -> 0
M77: =IF(K77=L77, "", "Error")
A78: TOTAL ABONOS Y SERVICIOS | D78: =SUM(D68:D77) -> 1997818.5 | E78: =SUM(E68:E77) -> 1898941.8 | F78: =SUM(F68:F77) -> 15703.955 | G78: =SUM(G68:G77) -> 18612.095 | H78: =SUM(H68:H77) -> 17594.246 | I78: =SUM(I68:I77) -> 21665.641 | J78: =SUM(J68:J77) -> 25300.816 | K78: =E78+J78+F78+G78+H78+I78 -> 1997818.5 | L78: =IF(D78=K78, "", "Error") | M78: =D78-K78 -> 0
A81: GASTOS VARIOS
A82: Articulos de limpieza - Mes de Junio | D82: =184000 -> 184000 | E82: =D82*93.2% -> 171488 | F82: =$D82*1.08% -> 1987.2 | G82: =$D82*1.28% -> 2355.2 | H82: =$D82*1.21% -> 2226.4 | I82: =$D82*1.49% -> 2741.6 | J82: =D82*1.74% -> 3201.6
A83: Articulos de limpieza - Mes de Julio | D83: 191550 | E83: =D83*93.2% -> 178524.6 | F83: =$D83*1.08% -> 2068.74 | G83: =$D83*1.28% -> 2451.84 | H83: =$D83*1.21% -> 2317.755 | I83: =$D83*1.49% -> 2854.095 | J83: =D83*1.74% -> 3332.97
A84: Buenas ondas - Compra de guantes mapa negros | D84: 9800 | E84: =D84*93.2% -> 9133.6 | F84: =$D84*1.08% -> 105.84 | G84: =$D84*1.28% -> 125.44 | H84: =$D84*1.21% -> 118.58 | I84: =$D84*1.49% -> 146.02 | J84: =D84*1.74% -> 170.52
A85: Sra Miriam - Control para apertura de cochera | D85: 21780 | E85: =D85*93.2% -> 20298.96 | F85: =$D85*1.08% -> 235.224 | G85: =$D85*1.28% -> 278.784 | H85: =$D85*1.21% -> 263.538 | I85: =$D85*1.49% -> 324.522 | J85: =D85*1.74% -> 378.972
A86: Baez Veronica Anabella - Compra limpiadores de acero y pilas | D86: 78800 | E86: =D86*93.2% -> 73441.6 | F86: =$D86*1.08% -> 851.04 | G86: =$D86*1.28% -> 1008.64 | H86: =$D86*1.21% -> 953.48 | I86: =$D86*1.49% -> 1174.12 | J86: =D86*1.74% -> 1371.12
A87: Mundo plus - cancelacion compra tachos de basura | D87: 813200 | E87: =D87 -> 813200
A89: TOTAL GASTOS VARIOS | D89: =SUM(D82:D88) -> 1299130 | E89: =SUM(E82:E88) -> 1266086.8 | F89: =SUM(F82:F88) -> 5248.044 | G89: =SUM(G82:G88) -> 6219.904 | H89: =SUM(H82:H88) -> 5879.753 | I89: =SUM(I82:I88) -> 7240.357 | J89: =SUM(J82:J88) -> 8455.182 | K89: =E89+J89+F89+G89+H89+I89 -> 1299130 | L89: =IF(D89=K89, "", "Error")
A92: GASTOS DE ADMINISTRACION
A93: RC Adm Cons. CANCIANI, Carolina | B93: MP:1148 | D93: 700000 | E93: =D93*93.2% -> 652400 | F93: =$D93*1.08% -> 7560 | G93: =$D93*1.28% -> 8960 | H93: =$D93*1.21% -> 8470 | I93: =$D93*1.49% -> 10430 | J93: =D93*1.74% -> 12180
A96: TOTAL GASTOS DE ADMINISTRACION | D96: =SUM(D93:D95) -> 700000 | E96: =SUM(E93:E95) -> 652400 | F96: =SUM(F93:F95) -> 7560 | G96: =SUM(G93:G95) -> 8960 | H96: =SUM(H93:H95) -> 8470 | I96: =SUM(I93:I95) -> 10430 | J96: =SUM(J93:J95) -> 12180 | K96: =E96+J96+F96+G96+H96+I96 -> 700000 | L96: =IF(D96=K96, "", "Error")
A97: Gastos bancarios | B97: No hay cuenta aun | E97: =D97*93.2% -> 0 | F97: =$D97*1.08% -> 0 | G97: =$D97*1.28% -> 0 | H97: =$D97*1.21% -> 0 | I97: =$D97*1.49% -> 0 | J97: =D97*1.74% -> 0
A98: Mantenimiento de cuenta | B98: No hay cuenta aun | E98: =D98*93.2% -> 0 | F98: =$D98*1.08% -> 0 | G98: =$D98*1.28% -> 0 | H98: =$D98*1.21% -> 0 | I98: =$D98*1.49% -> 0 | J98: =D98*1.74% -> 0
A99: TOTAL GASTOS BANCARIOS | D99: =SUM(D97:D98) -> 0 | E99: =SUM(E97:E98) -> 0 | F99: =SUM(F97:F98) -> 0 | G99: =SUM(G97:G98) -> 0 | H99: =SUM(H97:H98) -> 0 | I99: =SUM(I97:I98) -> 0 | J99: =SUM(J97:J98) -> 0 | K99: =E99+J99+F99+G99+H99+I99 -> 0 | L99: =IF(D99=K99, "", "Error")
A101: FONDO DE GASTOS ORDINARIOS | D101: 1500000 | E101: =D101*93.2% -> 1398000 | F101: =$D101*1.08% -> 16200 | G101: =$D101*1.28% -> 19200 | H101: =$D101*1.21% -> 18150 | I101: =$D101*1.49% -> 22350 | J101: =D101*1.74% -> 26100 | K101: =E101+J101+F101+G101+H101+I101 -> 1500000 | L101: =IF(D101=K101, "", "Error")
A103: TOTAL ORDINARIOS | D103: =SUM(D101+D57+D52+D99+D96+D89+D78+D66+D44+D39+D61) -> 9142586 | E103: =SUM(E101+E57+E52+E99+E96+E89+E78+E66+E44+E39+E61) -> 8625269.4 | F103: =SUM(F101+F57+F52+F99+F96+F89+F78+F66+F44+F39+F61) -> 82162.051 | G103: =SUM(G101+G57+G52+G99+G96+G89+G78+G66+G44+G39+G61) -> 97377.246 | H103: =SUM(H101+H57+H52+H99+H96+H89+H78+H66+H44+H39+H61) -> 92051.928 | I103: =SUM(I101+I57+I52+I99+I96+I89+I78+I66+I44+I39+I61) -> 113353.2 | J103: =SUM(J101+J57+J52+J99+J96+J89+J78+J66+J44+J39+J61) -> 132372.19 | K103: =E103+J103+F103+G103+H103+I103 -> 9142586 | L103: =IF(D103=K103, "", "Error") | M103: =D103-K103 -> 0
A105: Gastos particulares
A106: 2 controles de cochera - UF 13F | C106: =21780*2 -> 43560
A107: 1 control de cochera - UF 7A | C107: 21780
A108: LLaves 6C | C108: 18000
A109: Llaves 7A | C109: 9000
A110: Llaves 9A | C110: 18000
A111: Llaves 7C | C111: 18000
A112: Llaves 2F | C112: 9000
A113: Llaves 2E | C113: 9000
A114: Llaves 13D | C114: 9000
A115: Llaves 13F | C115: 9000
A118: TOTAL | C118: =SUM(C106:C116) -> 164340
A121: GASTOS EXTRAORDINARIOS | E121: UF | F121: LOCAL 1 (1,08%) | G121: LOCAL 2 (1,28%) | H121: LOCAL 3 (1,21%) | I121: LOCAL 4 (1,49%) | J121: LOCAL 5 (1,74%)
E122: =D122 -> 0
A124: TOTAL | D124: =SUM(D122:D123) -> 0 | E124: =SUM(E122:E123) -> 0 | J124: =SUM(J122:J123) -> 0 | L124: =E124+J124 -> 0 | M124: =IF(D124=L124, "", "Error")
A127: GASTOS ORDINARIOS + PREVISION : | B127: =D103 -> 9142586
A128: GASTOS ORDINARIOS SIN PREVISION: | B128: =D103-D101 -> 7642586
A130: CAJA EFECTIVO $ (pesos)
A131: Saldo anterior | B131: 394371.04
A132: Ingresos | B132: =PRORRATEO!H127 -> 5931731
A133: Egresos Ordinarios | B133: =-B128 -> -7642586
A134: Egresos Extraordinarios | B134: =-D124 -> 0
A135: Dinero ingreso SUM | B135: =-B142 -> 0
...

Sheet PRORRATEO
G1: ESTADO DE CUENTA Y PRORRATEO | K1: SE GASTO: | L1: =RESUMEN!D103-RESUMEN!D101 -> 7642586
K2: SE PRORRATEA EN LAS UF: | M2: 9000000
A3: =RESUMEN!C5 -> PERÍODO: JULIO
J4: =(J3*8.09%)/44 -> 0 | P4: =L1-K127 -> -1240893.8
A5: Piso | B5: Dpto. | C5: UF | D5: Propietario | E5: Inquilinos | F5: (%) | G5: Saldo | H5: Ingreso | I5: SALDO | J5: Expensas extraor. | K5: Expensas ord | L5: SUM/ GASTOS PART | M5: TOTAL A ABONAR HASTA | N5: TOTAL A ABONAR 2DO VTO - DESDE EL
M7: =RESUMEN!A20 -> VTO 14/08 | N7: =RESUMEN!A20 -> VTO 14/08
A8: conf sup | C8: LOC 1 | D8: Fernandez, Cristian | F8: 0.0108 | G8: 70998.784 | H8: =G8 -> 70998.784 | I8: =G8-H8 -> 0 | J8: 0 | K8: 81552.687 | L8: =J$3*F8%+J$4 -> 0 | M8: =K8+J8+I8+L8 -> 81552.687 | N8: =M8*6% + M8 -> 86445.848 | Q8: para copias y pegar las expensas ord del local
C9: LOC 2 | D9: Sr propietario | F9: 0.013 | G9: 84146.707 | H9: =G9 -> 84146.707 | I9: =G9-H9 -> 0 | J9: 0 | K9: 96655.037 | L9: =J$3*F9%+J$4 -> 0 | M9: =K9+J9+I9+L9 -> 96655.037 | N9: =M9*6% + M9 -> 102454.34
A10: conf sup | C10: LOC 3 | D10: Schiaffino, Edgardo Angel | F10: 0.0121 | G10: 79544.934 | H10: =G10 -> 79544.934 | I10: =G10-H10 -> 0 | J10: 0 | K10: 91369.214 | L10: =J$3*F10%+J$4 -> 0 | M10: =K10+J10+I10+L10 -> 91369.214 | N10: =M10*6% + M10 -> 96851.367 | Q10: LOCAL 1 | R10: =RESUMEN!F103 -> 82162.051
A11: conf sup | C11: LOC 4 | D11: Cordero, Leandro Emanuel - Orona, Victoria | F11: 0.0149 | G11: 97952.027 | H11: =G11 -> 97952.027 | I11: =G11-H11 -> 0 | J11: 0 | K11: 112512.5 | L11: =J$3*F11%+J$4 -> 0 | M11: =K11+J11+I11+L11 -> 112512.5 | N11: =M11*6% + M11 -> 119263.25 | Q11: LOCAL 2 | R11: =RESUMEN!G103 -> 97377.246
A12: conf sup | C12: LOC 5 | D12: Orsi, Jose Luis - Fernandez, Cristian Gabriel | F12: 0.0174 | G12: 114386.93 | H12: =G12 -> 114386.93 | I12: =G12-H12 -> 0 | J12: 0 | K12: 131390.44 | L12: =J$3*F12%+J$4 -> 0 | M12: =K12+J12+I12+L12 -> 131390.44 | N12: =M12*6% + M12 -> 139273.87 | Q12: LOCAL 3 | R12: =RESUMEN!H103 -> 92051.928
A13: 3 amb | C13: 2ºA | D13: Franco, Lucas Fabián | F13: 0.0188 | G13: 134281.01 | H13: =G13 -> 134281.01 | I13: =G13-H13 -> 0 | J13: =M$4*F13 -> 0 | K13: =M$2*F13 -> 169200 | L13: =J$3*F13%+J$4 -> 0 | M13: =ROUND((K13+J13+I13+L13),0) + O13 -> 169200.01 | N13: =ROUND((M13*6% + M13 ),0) + O13 -> 179352.01 | O13: 0.01 | Q13: LOCAL 4 | R13: =RESUMEN!I103 -> 113353.2
A14: 1 amb | C14: 2ºB | D14: Martinez, Diego | F14: 0.0084 | G14: 59998.02 | H14: 63598.02 | I14: =G14-H14 -> -3600 | J14: =M$4*F14 -> 0 | K14: =M$2*F14 -> 75600 | L14: =J$3*F14%+J$4 -> 0 | M14: =ROUND((K14+J14+I14+L14),0) + O14 -> 72000.02 | N14: =ROUND((M14*6% + M14 ),0) + O14 -> 76320.02 | O14: =O13+0.01 -> 0.02 | Q14: LOCAL 5 | R14: =RESUMEN!J103 -> 132372.19
A15: 3 amb | C15: 2ºC | D15: Rodriguez, Carlos Alberto Miguel | F15: 0.0201 | G15: 143566.03 | H15: =G15 -> 143566.03 | I15: =G15-H15 -> 0 | J15: =M$4*F15 -> 0 | K15: =M$2*F15 -> 180900 | L15: =J$3*F15%+J$4 -> 0 | M15: =ROUND((K15+J15+I15+L15),0) + O15 -> 180900.03 | N15: =ROUND((M15*6% + M15 ),0) + O15 -> 191754.03 | O15: =O14+0.01 -> 0.03
A16: 2 amb | C16: 2ºD | D16: Ferraro, José | F16: 0.0094 | G16: 67140.04 | I16: =G16-H16 -> 67140.04 | J16: =M$4*F16 -> 0 | K16: =M$2*F16 -> 84600 | L16: =J$3*F16%+J$4 -> 0 | M16: =ROUND((K16+J16+I16+L16),0) + O16 -> 151740.04 | N16: =ROUND((M16*6% + M16 ),0) + O16 -> 160844.04 | O16: =O15+0.01 -> 0.04
A17: 2 amb | C17: 2ºE | D17: Dieci, Matias Orlando | F17: 0.0087 | G17: 62141.05 | H17: =G17 -> 62141.05 | I17: =G17-H17 -> 0 | J17: =M$4*F17 -> 0 | K17: =M$2*F17 -> 78300 | L17: 9000 | M17: =ROUND((K17+J17+I17+L17),0) + O17 -> 87300.05 | N17: =ROUND((M17*6% + M17 ),0) + O17 -> 92538.05 | O17: =O16+0.01 -> 0.05
A18: 2 amb | C18: 2ºF | D18: Ferraro, Jose | E18: Carolina | F18: 0.0095 | G18: 67855.06 | I18: =G18-H18 -> 67855.06 | J18: =M$4*F18 -> 0 | K18: =M$2*F18 -> 85500 | L18: 9000 | M18: =ROUND((K18+J18+I18+L18),0) + O18 -> 162355.06 | N18: =ROUND((M18*6% + M18 ),0) + O18 -> 172096.06 | O18: =O17+0.01 -> 0.06
A19: 3 amb | C19: 3ºA | D19: Ferraro, Jose | F19: 0.0165 | G19: 117853.07 | I19: =G19-H19 -> 117853.07 | J19: =M$4*F19 -> 0 | K19: =M$2*F19 -> 148500 | L19: =J$3*F19%+J$4 -> 0 | M19: =ROUND((K19+J19+I19+L19),0) + O19 -> 266353.07 | N19: =ROUND((M19*6% + M19 ),0) + O19 -> 282334.07 | O19: =O18+0.01 -> 0.07
A20: 1 amb | C20: 3ºB | D20: Balduzzi, Stella Maris | F20: 0.0073 | G20: 52141.08 | H20: =G20 -> 52141.08 | I20: =G20-H20 -> 0 | J20: =M$4*F20 -> 0 | K20: =M$2*F20 -> 65700 | L20: =J$3*F20%+J$4 -> 0 | M20: =ROUND((K20+J20+I20+L20),0) + O20 -> 65700.08 | N20: =ROUND((M20*6% + M20 ),0) + O20 -> 69642.08 | O20: =O19+0.01 -> 0.08
A21: 3 amb | C21: 3ºC | D21: Ferraro, Jose | F21: 0.0178 | G21: 127138.09 | I21: =G21-H21 -> 127138.09 | J21: =M$4*F21 -> 0 | K21: =M$2*F21 -> 160200 | L21: =J$3*F21%+J$4 -> 0 | M21: =ROUND((K21+J21+I21+L21),0) + O21 -> 287338.09 | N21: =ROUND((M21*6% + M21 ),0) + O21 -> 304578.09 | O21: =O20+0.01 -> 0.09
A22: 2 amb | C22: 3ºD | D22: Ayala, Roberto Adrian | F22: 0.0094 | G22: 67140.1 | H22: =G22 -> 67140.1 | I22: =G22-H22 -> 0 | J22: =M$4*F22 -> 0 | K22: =M$2*F22 -> 84600 | L22: =J$3*F22%+J$4 -> 0 | M22: =ROUND((K22+J22+I22+L22),0) + O22 -> 84600.1 | N22: =ROUND((M22*6% + M22 ),0) + O22 -> 89676.1 | O22: =O21+0.01 -> 0.1
A23: 2 amb | C23: 3ºE | D23: Ayala, Roberto Adrian | F23: 0.0087 | G23: 62141.11 | H23: =G23 -> 62141.11 | I23: =G23-H23 -> 0 | J23: =M$4*F23 -> 0 | K23: =M$2*F23 -> 78300 | L23: =J$3*F23%+J$4 -> 0 | M23: =ROUND((K23+J23+I23+L23),0) + O23 -> 78300.11 | N23: =ROUND((M23*6% + M23 ),0) + O23 -> 82998.11 | O23: =O22+0.01 -> 0.11
A24: 2 amb | C24: 3ºF | D24: Ayala, Roberto Adrian | F24: 0.0095 | G24: 67855.12 | H24: =G24 -> 67855.12 | I24: =G24-H24 -> 0 | J24: =M$4*F24 -> 0 | K24: =M$2*F24 -> 85500 | L24: =J$3*F24%+J$4 -> 0 | M24: =ROUND((K24+J24+I24+L24),0) + O24 -> 85500.12 | N24: =ROUND((M24*6% + M24 ),0) + O24 -> 90630.12 | O24: =O23+0.01 -> 0.12
A25: 3 amb | C25: 4ºA | D25: Barral, Carlos Daniel | F25: 0.0164 | G25: 135139.13 | H25: =G25 -> 135139.13 | I25: =G25-H25 -> 0 | J25: =M$4*F25 -> 0 | K25: =M$2*F25 -> 147600 | L25: =J$3*F25%+J$4 -> 0 | M25: =ROUND((K25+J25+I25+L25),0) + O25 -> 147600.13 | N25: =ROUND((M25*6% + M25 ),0) + O25 -> 156456.13 | O25: =O24+0.01 -> 0.13
A26: 1 amb | C26: 4ºB | D26: Sr. Propietario | E26: Liria | F26: 0.0072 | G26: 51427.14 | I26: =G26-H26 -> 51427.14 | J26: =M$4*F26 -> 0 | K26: =M$2*F26 -> 64800 | L26: =J$3*F26%+J$4 -> 0 | M26: =ROUND((K26+J26+I26+L26),0) + O26 -> 116227.14 | N26: =ROUND((M26*6% + M26 ),0) + O26 -> 123201.14 | O26: =O25+0.01 -> 0.14
A27: 3 amb | C27: 4ºC | D27: Osipowicz, Ariel Marcelo | F27: 0.0173 | G27: 150567.15 | H27: =G27 -> 150567.15 | I27: =G27-H27 -> 0 | J27: =M$4*F27 -> 0 | K27: =M$2*F27 -> 155700 | L27: =J$3*F27%+J$4 -> 0 | M27: =ROUND((K27+J27+I27+L27),0) + O27 -> 155700.15 | N27: =ROUND((M27*6% + M27 ),0) + O27 -> 165042.15 | O27: =O26+0.01 -> 0.15
A28: 2 amb | C28: 4ºD | D28: Ayala, Roberto Adrian | F28: 0.0094 | G28: 67140.16 | H28: =G28 -> 67140.16 | I28: =G28-H28 -> 0 | J28: =M$4*F28 -> 0 | K28: =M$2*F28 -> 84600 | L28: =J$3*F28%+J$4 -> 0 | M28: =ROUND((K28+J28+I28+L28),0) + O28 -> 84600.16 | N28: =ROUND((M28*6% + M28 ),0) + O28 -> 89676.16 | O28: =O27+0.01 -> 0.16
A29: 2 amb | C29: 4ºE | D29: Ayala, Roberto Adrian | F29: 0.0087 | G29: 62141.17 | H29: =G29 -> 62141.17 | I29: =G29-H29 -> 0 | J29: =M$4*F29 -> 0 | K29: =M$2*F29 -> 78300 | L29: =J$3*F29%+J$4 -> 0 | M29: =ROUND((K29+J29+I29+L29),0) + O29 -> 78300.17 | N29: =ROUND((M29*6% + M29 ),0) + O29 -> 82998.17 | O29: =O28+0.01 -> 0.17
A30: 2 amb | C30: 4ºF | D30: Ayala, Roberto Adrian | F30: 0.0095 | G30: 67855.18 | H30: =G30 -> 67855.18 | I30: =G30-H30 -> 0 | J30: =M$4*F30 -> 0 | K30: =M$2*F30 -> 85500 | L30: =J$3*F30%+J$4 -> 0 | M30: =ROUND((K30+J30+I30+L30),0) + O30 -> 85500.18 | N30: =ROUND((M30*6% + M30 ),0) + O30 -> 90630.18 | O30: =O29+0.01 -> 0.18
A31: 3 amb | C31: 5ºA | D31: Chehab, Gabriel Adrian | F31: 0.0164 | G31: 117139.19 | H31: =G31 -> 117139.19 | I31: =G31-H31 -> 0 | J31: =M$4*F31 -> 0 | K31: =M$2*F31 -> 147600 | L31: =J$3*F31%+J$4 -> 0 | M31: =ROUND((K31+J31+I31+L31),0) + O31 -> 147600.19 | N31: =ROUND((M31*6% + M31 ),0) + O31 -> 156456.19 | O31: =O30+0.01 -> 0.19
A32: 1 amb | C32: 5ºB | D32: Mesa, Mariano | F32: 0.0072 | G32: 51427.2 | H32: =G32 -> 51427.2 | I32: =G32-H32 -> 0 | J32: =M$4*F32 -> 0 | K32: =M$2*F32 -> 64800 | L32: =J$3*F32%+J$4 -> 0 | M32: =ROUND((K32+J32+I32+L32),0) + O32 -> 64800.2 | N32: =ROUND((M32*6% + M32 ),0) + O32 -> 68688.2 | O32: =O31+0.01 -> 0.2
A33: 3 amb | C33: 5ºC | D33: Di Mito, Vicente Argentino - Serantes, Mabel | F33: 0.0173 | G33: 123567.21 | I33: =G33-H33 -> 123567.21 | J33: =M$4*F33 -> 0 | K33: =M$2*F33 -> 155700 | L33: =J$3*F33%+J$4 -> 0 | M33: =ROUND((K33+J33+I33+L33),0) + O33 -> 279267.21 | N33: =ROUND((M33*6% + M33 ),0) + O33 -> 296023.21 | O33: =O32+0.01 -> 0.21
A34: 2 amb | C34: 5ºD | D34: Ayala, Agustin | F34: 0.0094 | G34: 67140.22 | H34: =G34 -> 67140.22 | I34: =G34-H34 -> 0 | J34: =M$4*F34 -> 0 | K34: =M$2*F34 -> 84600 | L34: =J$3*F34%+J$4 -> 0 | M34: =ROUND((K34+J34+I34+L34),0) + O34 -> 84600.22 | N34: =ROUND((M34*6% + M34 ),0) + O34 -> 89676.22 | O34: =O33+0.01 -> 0.22
A35: 2 amb | C35: 5ºE | D35: Ayala, Roberto Adrian | F35: 0.0087 | G35: 62141.23 | H35: =G35 -> 62141.23 | I35: =G35-H35 -> 0 | J35: =M$4*F35 -> 0 | K35: =M$2*F35 -> 78300 | L35: =J$3*F35%+J$4 -> 0 | M35: =ROUND((K35+J35+I35+L35),0) + O35 -> 78300.23 | N35: =ROUND((M35*6% + M35 ),0) + O35 -> 82998.23 | O35: =O34+0.01 -> 0.23
A36: 2 amb | C36: 5ºF | D36: Ayala, Agustin | F36: 0.0095 | G36: 67855.24 | H36: =G36 -> 67855.24 | I36: =G36-H36 -> 0 | J36: =M$4*F36 -> 0 | K36: =M$2*F36 -> 85500 | L36: =J$3*F36%+J$4 -> 0 | M36: =ROUND((K36+J36+I36+L36),0) + O36 -> 85500.24 | N36: =ROUND((M36*6% + M36 ),0) + O36 -> 90630.24 | O36: =O35+0.01 -> 0.24
A37: 3 amb | C37: 6ºA | D37: Morandi, Victoria Ayelen | Calvo, Luciano Ezequiel | F37: 0.0164 | G37: 117139.25 | H37: =G37 -> 117139.25 | I37: =G37-H37 -> 0 | J37: =M$4*F37 -> 0 | K37: =M$2*F37 -> 147600 | L37: =J$3*F37%+J$4 -> 0 | M37: =ROUND((K37+J37+I37+L37),0) + O37 -> 147600.25 | N37: =ROUND((M37*6% + M37 ),0) + O37 -> 156456.25 | O37: =O36+0.01 -> 0.25
A38: 1 amb | C38: 6ºB | D38: Grizak Ruben | E38: Christian | F38: 0.0072 | G38: 78427.26 | H38: 78430 | I38: =G38-H38 -> -2.74 | J38: =M$4*F38 -> 0 | K38: =M$2*F38 -> 64800 | L38: =J$3*F38%+J$4 -> 0 | M38: =ROUND((K38+J38+I38+L38),0) + O38 -> 64797.26 | N38: =ROUND((M38*6% + M38 ),0) + O38 -> 68685.26 | O38: =O37+0.01 -> 0.26
A39: 3 amb | C39: 6ºC | D39: Nuñez Leonel - Corrieri Giuliana | F39: 0.0173 | G39: 123567.27 | H39: =G39 -> 123567.27 | I39: =G39-H39 -> 0 | J39: =M$4*F39 -> 0 | K39: =M$2*F39 -> 155700 | L39: 18000 | M39: =ROUND((K39+J39+I39+L39),0) + O39 -> 173700.27 | N39: =ROUND((M39*6% + M39 ),0) + O39 -> 184122.27 | O39: =O38+0.01 -> 0.27 | P39: COCHERA 33 | Q39: COCHERA 33
A40: 2 amb | C40: 6ºD | D40: Sr propietario | F40: 0.0094 | G40: 67140.28 | H40: =G40 -> 67140.28 | I40: =G40-H40 -> 0 | J40: =M$4*F40 -> 0 | K40: =M$2*F40 -> 84600 | L40: =J$3*F40%+J$4 -> 0 | M40: =ROUND((K40+J40+I40+L40),0) + O40 -> 84600.28 | N40: =ROUND((M40*6% + M40 ),0) + O40 -> 89676.28 | O40: =O39+0.01 -> 0.28 | Q40: mariano hecimovic
A41: 2 amb | C41: 6ºE | D41: Dieci, Matias Orlando | F41: 0.0087 | G41: 62141.29 | H41: =G41 -> 62141.29 | I41: =G41-H41 -> 0 | J41: =M$4*F41 -> 0 | K41: =M$2*F41 -> 78300 | L41: =J$3*F41%+J$4 -> 0 | M41: =ROUND((K41+J41+I41+L41),0) + O41 -> 78300.29 | N41: =ROUND((M41*6% + M41 ),0) + O41 -> 82998.29 | O41: =O40+0.01 -> 0.29
A42: 2 amb | C42: 6ºF | D42: Mazzia Alexia | F42: 0.0095 | G42: 67855.3 | H42: =G42 -> 67855.3 | I42: =G42-H42 -> 0 | J42: =M$4*F42 -> 0 | K42: =M$2*F42 -> 85500 | L42: =J$3*F42%+J$4 -> 0 | M42: =ROUND((K42+J42+I42+L42),0) + O42 -> 85500.3 | N42: =ROUND((M42*6% + M42 ),0) + O42 -> 90630.3 | O42: =O41+0.01 -> 0.3
A43: 3 amb | C43: 7ºA | D43: Campelo, Mariano | F43: 0.0164 | G43: 117139.31 | H43: =G43 -> 117139.31 | I43: =G43-H43 -> 0 | J43: =M$4*F43 -> 0 | K43: =M$2*F43 -> 147600 | L43: 9000 | M43: =ROUND((K43+J43+I43+L43),0) + O43 -> 156600.31 | N43: =ROUND((M43*6% + M43 ),0) + O43 -> 165996.31 | O43: =O42+0.01 -> 0.31
A44: 1 amb | C44: 7ºB | D44: Paes, Yazmin Luciana | F44: 0.0072 | G44: 51427.32 | H44: =G44 -> 51427.32 | I44: =G44-H44 -> 0 | J44: =M$4*F44 -> 0 | K44: =M$2*F44 -> 64800 | L44: =J$3*F44%+J$4 -> 0 | M44: =ROUND((K44+J44+I44+L44),0) + O44 -> 64800.32 | N44: =ROUND((M44*6% + M44 ),0) + O44 -> 68688.32 | O44: =O43+0.01 -> 0.32
A45: 3 amb | C45: 7ºC | D45: Gonzalez Fedullo, Roxana y Valeria | F45: 0.0173 | G45: 123567.33 | H45: =G45 -> 123567.33 | I45: =G45-H45 -> 0 | J45: =M$4*F45 -> 0 | K45: =M$2*F45 -> 155700 | L45: 18000 | M45: =ROUND((K45+J45+I45+L45),0) + O45 -> 173700.33 | N45: =ROUND((M45*6% + M45 ),0) + O45 -> 184122.33 | O45: =O44+0.01 -> 0.33
A46: 2 amb | C46: 7ºD | D46: Acosta, Daniela Pilar | F46: 0.0094 | G46: 67140.34 | H46: =G46 -> 67140.34 | I46: =G46-H46 -> 0 | J46: =M$4*F46 -> 0 | K46: =M$2*F46 -> 84600 | L46: =J$3*F46%+J$4 -> 0 | M46: =ROUND((K46+J46+I46+L46),0) + O46 -> 84600.34 | N46: =ROUND((M46*6% + M46 ),0) + O46 -> 89676.34 | O46: =O45+0.01 -> 0.34
A47: 2 amb | C47: 7ºE | D47: Leyes, Javier | F47: 0.0087 | G47: 62141.35 | H47: =G47 -> 62141.35 | I47: =G47-H47 -> 0 | J47: =M$4*F47 -> 0 | K47: =M$2*F47 -> 78300 | L47: =J$3*F47%+J$4 -> 0 | M47: =ROUND((K47+J47+I47+L47),0) + O47 -> 78300.35 | N47: =ROUND((M47*6% + M47 ),0) + O47 -> 82998.35 | O47: =O46+0.01 -> 0.35
A48: 2 amb | C48: 7ºF | D48: Puente, Matias | F48: 0.0095 | G48: 67855.36 | I48: =G48-H48 -> 67855.36 | J48: =M$4*F48 -> 0 | K48: =M$2*F48 -> 85500 | L48: =J$3*F48%+J$4 -> 0 | M48: =ROUND((K48+J48+I48+L48),0) + O48 -> 153355.36 | N48: =ROUND((M48*6% + M48 ),0) + O48 -> 162557.36 | O48: =O47+0.01 -> 0.36
A49: 3 amb | C49: 8ºA | D49: Campelo, Mariano | F49: 0.0164 | G49: 117139.37 | H49: =G49 -> 117139.37 | I49: =G49-H49 -> 0 | J49: =M$4*F49 -> 0 | K49: =M$2*F49 -> 147600 | L49: =J$3*F49%+J$4 -> 0 | M49: =ROUND((K49+J49+I49+L49),0) + O49 -> 147600.37 | N49: =ROUND((M49*6% + M49 ),0) + O49 -> 156456.37 | O49: =O48+0.01 -> 0.37
A50: 1 amb | C50: 8ºB | D50: Morvillo, Mariana Yanil | E50: Aylen | F50: 0.0072 | G50: 51427.38 | H50: 54513.38 | I50: =G50-H50 -> -3086 | J50: =M$4*F50 -> 0 | K50: =M$2*F50 -> 64800 | L50: =J$3*F50%+J$4 -> 0 | M50: =ROUND((K50+J50+I50+L50),0) + O50 -> 61714.38 | N50: =ROUND((M50*6% + M50 ),0) + O50 -> 65417.38 | O50: =O49+0.01 -> 0.38
A51: 3 amb | C51: 8ºC | D51: Frontale, Federico Carlos | Celentano, Alejandra Verónica | F51: 0.0173 | G51: 123567.39 | H51: =G51 -> 123567.39 | I51: =G51-H51 -> 0 | J51: =M$4*F51 -> 0 | K51: =M$2*F51 -> 155700 | L51: =J$3*F51%+J$4 -> 0 | M51: =ROUND((K51+J51+I51+L51),0) + O51 -> 155700.39 | N51: =ROUND((M51*6% + M51 ),0) + O51 -> 165042.39 | O51: =O50+0.01 -> 0.39
A52: 2 amb | C52: 8ºD | D52: Argul, Sergio Walter - Taboada, María Paz | F52: 0.0094 | G52: 67140.4 | I52: =G52-H52 -> 67140.4 | J52: =M$4*F52 -> 0 | K52: =M$2*F52 -> 84600 | L52: =J$3*F52%+J$4 -> 0 | M52: =ROUND((K52+J52+I52+L52),0) + O52 -> 151740.4 | N52: =ROUND((M52*6% + M52 ),0) + O52 -> 160845.4 | O52: =O51+0.01 -> 0.4
A53: 2 amb | C53: 8ºE | D53: Sr propietario | F53: 0.0087 | G53: 62141.41 | H53: =G53 -> 62141.41 | I53: =G53-H53 -> 0 | J53: =M$4*F53 -> 0 | K53: =M$2*F53 -> 78300 | L53: =J$3*F53%+J$4 -> 0 | M53: =ROUND((K53+J53+I53+L53),0) + O53 -> 78300.41 | N53: =ROUND((M53*6% + M53 ),0) + O53 -> 82998.41 | O53: =O52+0.01 -> 0.41 | Q53: el de sergio
A54: 2 amb | C54: 8ºF | D54: Arias, Mariana Laura | F54: 0.0095 | G54: 67855.42 | I54: =G54-H54 -> 67855.42 | J54: =M$4*F54 -> 0 | K54: =M$2*F54 -> 85500 | L54: =J$3*F54%+J$4 -> 0 | M54: =ROUND((K54+J54+I54+L54),0) + O54 -> 153355.42 | N54: =ROUND((M54*6% + M54 ),0) + O54 -> 162557.42 | O54: =O53+0.01 -> 0.42
A55: 3 amb | C55: 9ºA | D55: Fanjul, Alejandro Rubén Marcelo | F55: 0.0164 | G55: 117139.43 | H55: =G55 -> 117139.43 | I55: =G55-H55 -> 0 | J55: =M$4*F55 -> 0 | K55: =M$2*F55 -> 147600 | L55: 18000 | M55: =ROUND((K55+J55+I55+L55),0) + O55 -> 165600.43 | N55: =ROUND((M55*6% + M55 ),0) + O55 -> 175536.43 | O55: =O54+0.01 -> 0.43
A56: 1 amb | C56: 9ºB | D56: Fanjul, Alejandro Rubén Marcelo | F56: 0.0072 | G56: 51427.44 | H56: =G56 -> 51427.44 | I56: =G56-H56 -> 0 | J56: =M$4*F56 -> 0 | K56: =M$2*F56 -> 64800 | L56: =J$3*F56%+J$4 -> 0 | M56: =ROUND((K56+J56+I56+L56),0) + O56 -> 64800.44 | N56: =ROUND((M56*6% + M56 ),0) + O56 -> 68688.44 | O56: =O55+0.01 -> 0.44
A57: 3 amb | C57: 9ºC | D57: Franchino, Mauro | F57: 0.0173 | G57: 123567.45 | H57: =G57 -> 123567.45 | I57: =G57-H57 -> 0 | J57: =M$4*F57 -> 0 | K57: =M$2*F57 -> 155700 | L57: =J$3*F57%+J$4 -> 0 | M57: =ROUND((K57+J57+I57+L57),0) + O57 -> 155700.45 | N57: =ROUND((M57*6% + M57 ),0) + O57 -> 165042.45 | O57: =O56+0.01 -> 0.45
A58: 2 amb | C58: 9ºD | D58: Cerra, Antonio Osvaldo | E58: Adrian | F58: 0.0094 | G58: 67140.46 | I58: =G58-H58 -> 67140.46 | J58: =M$4*F58 -> 0 | K58: =M$2*F58 -> 84600 | L58: =J$3*F58%+J$4 -> 0 | M58: =ROUND((K58+J58+I58+L58),0) + O58 -> 151740.46 | N58: =ROUND((M58*6% + M58 ),0) + O58 -> 160845.46 | O58: =O57+0.01 -> 0.46
A59: 2 amb | C59: 9ºE | D59: Dieci, Matias Orlando | F59: 0.0087 | G59: 62141.47 | H59: 65870.47 | I59: =G59-H59 -> -3729 | J59: =M$4*F59 -> 0 | K59: =M$2*F59 -> 78300 | L59: =J$3*F59%+J$4 -> 0 | M59: =ROUND((K59+J59+I59+L59),0) + O59 -> 74571.47 | N59: =ROUND((M59*6% + M59 ),0) + O59 -> 79046.47 | O59: =O58+0.01 -> 0.47
A60: 2 amb | C60: 9ºF | D60: Rosales, Rubén Darío | F60: 0.0095 | G60: 67855.48 | H60: 71927.48 | I60: =G60-H60 -> -4072 | J60: =M$4*F60 -> 0 | K60: =M$2*F60 -> 85500 | L60: =J$3*F60%+J$4 -> 0 | M60: =ROUND((K60+J60+I60+L60),0) + O60 -> 81428.48 | N60: =ROUND((M60*6% + M60 ),0) + O60 -> 86314.48 | O60: =O59+0.01 -> 0.48
A61: 3 amb | C61: 10ºA | D61: Puisys Guillermo Antonio | F61: 0.0164 | G61: 117139.49 | H61: =G61 -> 117139.49 | I61: =G61-H61 -> 0 | J61: =M$4*F61 -> 0 | K61: =M$2*F61 -> 147600 | L61: =J$3*F61%+J$4 -> 0 | M61: =ROUND((K61+J61+I61+L61),0) + O61 -> 147600.49 | N61: =ROUND((M61*6% + M61 ),0) + O61 -> 156457.49 | O61: =O60+0.01 -> 0.49
A62: 1 amb | C62: 10ºB | D62: Lange, Gustavo Daniel | F62: 0.0072 | G62: 51427.5 | I62: =G62-H62 -> 51427.5 | J62: =M$4*F62 -> 0 | K62: =M$2*F62 -> 64800 | L62: =J$3*F62%+J$4 -> 0 | M62: =ROUND((K62+J62+I62+L62),0) + O62 -> 116228.5 | N62: =ROUND((M62*6% + M62 ),0) + O62 -> 123202.5 | O62: =O61+0.01 -> 0.5
A63: 3 amb | C63: 10ºC | D63: Espósito, Franco Ezequiel | F63: 0.0173 | G63: 123567.51 | H63: =G63 -> 123567.51 | I63: =G63-H63 -> 0 | J63: =M$4*F63 -> 0 | K63: =M$2*F63 -> 155700 | L63: =J$3*F63%+J$4 -> 0 | M63: =ROUND((K63+J63+I63+L63),0) + O63 -> 155700.51 | N63: =ROUND((M63*6% + M63 ),0) + O63 -> 165043.51 | O63: =O62+0.01 -> 0.51
A64: 2 amb | C64: 10ºD | D64: Lobato, Lorena - Vega, Maximiliano | F64: 0.0094 | G64: 67140.52 | I64: =G64-H64 -> 67140.52 | J64: =M$4*F64 -> 0 | K64: =M$2*F64 -> 84600 | L64: =J$3*F64%+J$4 -> 0 | M64: =ROUND((K64+J64+I64+L64),0) + O64 -> 151741.52 | N64: =ROUND((M64*6% + M64 ),0) + O64 -> 160846.52 | O64: =O63+0.01 -> 0.52
A65: 2 amb | C65: 10ºE | D65: Sr propietario | F65: 0.0087 | G65: 62141.53 | H65: =G65 -> 62141.53 | I65: =G65-H65 -> 0 | J65: =M$4*F65 -> 0 | K65: =M$2*F65 -> 78300 | L65: =J$3*F65%+J$4 -> 0 | M65: =ROUND((K65+J65+I65+L65),0) + O65 -> 78300.53 | N65: =ROUND((M65*6% + M65 ),0) + O65 -> 82999.53 | O65: =O64+0.01 -> 0.53 | Q65: mariano hecimovic
A66: 2 amb | C66: 10ºF | D66: Ramos, Sergio Eugenio | F66: 0.0095 | G66: 67855.54 | H66: =G66 -> 67855.54 | I66: =G66-H66 -> 0 | J66: =M$4*F66 -> 0 | K66: =M$2*F66 -> 85500 | L66: =J$3*F66%+J$4 -> 0 | M66: =ROUND((K66+J66+I66+L66),0) + O66 -> 85500.54 | N66: =ROUND((M66*6% + M66 ),0) + O66 -> 90631.54 | O66: =O65+0.01 -> 0.54
A67: 4 amb | C67: 11ºA/B | D67: Mosquera, Julio Rodolfo | Cuzzolino, Daniela Carol | F67: 0.0235 | G67: 167851.55 | H67: 177923.55 | I67: =G67-H67 -> -10072 | J67: =M$4*F67 -> 0 | K67: =M$2*F67 -> 211500 | L67: =J$3*F67%+J$4 -> 0 | M67: =ROUND((K67+J67+I67+L67),0) + O67 -> 201428.55 | N67: =ROUND((M67*6% + M67 ),0) + O67 -> 213514.55 | O67: =O66+0.01 -> 0.55
A68: 3 amb | C68: 11ºC | D68: Silvestre Villarruel Eduardo | F68: 0.0173 | G68: 123567.56 | H68: =G68 -> 123567.56 | I68: =G68-H68 -> 0 | J68: =M$4*F68 -> 0 | K68: =M$2*F68 -> 155700 | L68: =J$3*F68%+J$4 -> 0 | M68: =ROUND((K68+J68+I68+L68),0) + O68 -> 155700.56 | N68: =ROUND((M68*6% + M68 ),0) + O68 -> 165043.56 | O68: =O67+0.01 -> 0.56
A69: 2 amb | C69: 11ºD | D69: Cadahia, Rosanna Patricia | F69: 0.0094 | G69: 67140.57 | I69: =G69-H69 -> 67140.57 | J69: =M$4*F69 -> 0 | K69: =M$2*F69 -> 84600 | L69: =J$3*F69%+J$4 -> 0 | M69: =ROUND((K69+J69+I69+L69),0) + O69 -> 151741.57 | N69: =ROUND((M69*6% + M69 ),0) + O69 -> 160846.57 | O69: =O68+0.01 -> 0.57
A70: 2 amb | C70: 11ºE | D70: Argúl, Adrián Norberto | F70: 0.0087 | G70: 62141.58 | I70: =G70-H70 -> 62141.58 | J70: =M$4*F70 -> 0 | K70: =M$2*F70 -> 78300 | L70: =J$3*F70%+J$4 -> 0 | M70: =ROUND((K70+J70+I70+L70),0) + O70 -> 140442.58 | N70: =ROUND((M70*6% + M70 ),0) + O70 -> 148869.58 | O70: =O69+0.01 -> 0.58
A71: 2 amb | C71: 11ºF | D71: Lobato, Lorena - Vega, Maximiliano | F71: 0.0095 | G71: 67855.59 | H71: 71927.59 | I71: =G71-H71 -> -4072 | J71: =M$4*F71 -> 0 | K71: =M$2*F71 -> 85500 | L71: =J$3*F71%+J$4 -> 0 | M71: =ROUND((K71+J71+I71+L71),0) + O71 -> 81428.59 | N71: =ROUND((M71*6% + M71 ),0) + O71 -> 86314.59 | O71: =O70+0.01 -> 0.59
A72: 4 amb | C72: 12ºA/B | D72: Luciano, Carmen Veronica - Rey, Javier Pablo | F72: 0.0235 | G72: 167851.6 | H72: =G72 -> 167851.6 | I72: =G72-H72 -> 0 | J72: =M$4*F72 -> 0 | K72: =M$2*F72 -> 211500 | L72: =J$3*F72%+J$4 -> 0 | M72: =ROUND((K72+J72+I72+L72),0) + O72 -> 211500.6 | N72: =ROUND((M72*6% + M72 ),0) + O72 -> 224191.6 | O72: =O71+0.01 -> 0.6
A73: 3 amb | C73: 12ºC | D73: Hernandez, Marisa Beatriz - Hernandez, Adrian Jose | F73: 0.0173 | G73: 123567.61 | H73: =G73 -> 123567.61 | I73: =G73-H73 -> 0 | J73: =M$4*F73 -> 0 | K73: =M$2*F73 -> 155700 | L73: =J$3*F73%+J$4 -> 0 | M73: =ROUND((K73+J73+I73+L73),0) + O73 -> 155700.61 | N73: =ROUND((M73*6% + M73 ),0) + O73 -> 165043.61 | O73: =O72+0.01 -> 0.61
A74: 2 amb | C74: 12ºD | D74: Morini, Micaela | F74: 0.0094 | G74: 67140.62 | H74: =G74 -> 67140.62 | I74: =G74-H74 -> 0 | J74: =M$4*F74 -> 0 | K74: =M$2*F74 -> 84600 | L74: =J$3*F74%+J$4 -> 0 | M74: =ROUND((K74+J74+I74+L74),0) + O74 -> 84600.62 | N74: =ROUND((M74*6% + M74 ),0) + O74 -> 89677.62 | O74: =O73+0.01 -> 0.62
A75: 2 amb | C75: 12ºE | D75: Armerding, Jorge | E75: Agustina | F75: 0.0087 | G75: 62141.63 | H75: =G75 -> 62141.63 | I75: =G75-H75 -> 0 | J75: =M$4*F75 -> 0 | K75: =M$2*F75 -> 78300 | L75: =J$3*F75%+J$4 -> 0 | M75: =ROUND((K75+J75+I75+L75),0) + O75 -> 78300.63 | N75: =ROUND((M75*6% + M75 ),0) + O75 -> 82999.63 | O75: =O74+0.01 -> 0.63
A76: 2 amb | C76: 12ºF | D76: Bilyj, Josefa Catalina | F76: 0.0095 | G76: 76855.64 | H76: 81467.64 | I76: =G76-H76 -> -4612 | J76: =M$4*F76 -> 0 | K76: =M$2*F76 -> 85500 | L76: =J$3*F76%+J$4 -> 0 | M76: =ROUND((K76+J76+I76+L76),0) + O76 -> 80888.64 | N76: =ROUND((M76*6% + M76 ),0) + O76 -> 85742.64 | O76: =O75+0.01 -> 0.64
A77: 4 amb | C77: 13ºA/B | D77: Sr propietario | F77: 0.0235 | G77: 167851.65 | H77: 81467.64 | I77: =G77-H77 -> 86384.01 | J77: =M$4*F77 -> 0 | K77: =M$2*F77 -> 211500 | L77: =J$3*F77%+J$4 -> 0 | M77: =ROUND((K77+J77+I77+L77),0) + O77 -> 297884.65 | N77: =ROUND((M77*6% + M77 ),0) + O77 -> 315758.65 | O77: =O76+0.01 -> 0.65
A78: 3 amb | C78: 13ºC | D78: Argentino, Javier Leonardo | F78: 0.0173 | G78: 123567.66 | H78: =G78 -> 123567.66 | I78: =G78-H78 -> 0 | J78: =M$4*F78 -> 0 | K78: =M$2*F78 -> 155700 | L78: =J$3*F78%+J$4 -> 0 | M78: =ROUND((K78+J78+I78+L78),0) + O78 -> 155700.66 | N78: =ROUND((M78*6% + M78 ),0) + O78 -> 165043.66 | O78: =O77+0.01 -> 0.66
A79: 2 amb | C79: 13ºD | D79: Scardigno, Gabriela Susana - Ripoll, Luis Alberto | F79: 0.0094 | G79: 67140.67 | H79: =G79 -> 67140.67 | I79: =G79-H79 -> 0 | J79: =M$4*F79 -> 0 | K79: =M$2*F79 -> 84600 | L79: 9000 | M79: =ROUND((K79+J79+I79+L79),0) + O79 -> 93600.67 | N79: =ROUND((M79*6% + M79 ),0) + O79 -> 99217.67 | O79: =O78+0.01 -> 0.67
A80: 2 amb | C80: 13ºE | D80: Quiñones, Carlos Eduardo | F80: 0.0087 | G80: 62141.68 | H80: =G80 -> 62141.68 | I80: =G80-H80 -> 0 | J80: =M$4*F80 -> 0 | K80: =M$2*F80 -> 78300 | L80: 9000 | M80: =ROUND((K80+J80+I80+L80),0) + O80 -> 87300.68 | N80: =ROUND((M80*6% + M80 ),0) + O80 -> 92539.68 | O80: =O79+0.01 -> 0.68
A81: 2 amb | C81: 13ºF | D81: Mosquera, José Elias | F81: 0.0095 | G81: 67855.69 | H81: =G81 -> 67855.69 | I81: =G81-H81 -> 0 | J81: =M$4*F81 -> 0 | K81: =M$2*F81 -> 85500 | L81: 43560 | M81: =ROUND((K81+J81+I81+L81),0) + O81 -> 129060.69 | N81: =ROUND((M81*6% + M81 ),0) + O81 -> 136804.69 | O81: =O80+0.01 -> 0.69
C82: COCH 1 | D82: Osipowicz, Ariel Marcelo | F82: 0.0023 | G82: 16428.7 | H82: =G82 -> 16428.7 | I82: =G82-H82 -> 0 | J82: =M$4*F82 -> 0 | K82: =M$2*F82 -> 20700 | L82: =J$3*F82%+J$4 -> 0 | M82: =ROUND((K82+J82+I82+L82),0) + O82 -> 20700.7 | N82: =ROUND((M82*6% + M82 ),0) + O82 -> 21943.7 | O82: =O81+0.01 -> 0.7
C83: COCH 2 | D83: Sr propietario | F83: 0.0023 | G83: 16428.71 | H83: =G83 -> 16428.71 | I83: =G83-H83 -> 0 | J83: =M$4*F83 -> 0 | K83: =M$2*F83 -> 20700 | L83: =J$3*F83%+J$4 -> 0 | M83: =ROUND((K83+J83+I83+L83),0) + O83 -> 20700.71 | N83: =ROUND((M83*6% + M83 ),0) + O83 -> 21943.71 | O83: =O82+0.01 -> 0.71
C84: COCH 3 | D84: Paes, Yazmin Luciana | F84: 0.0023 | G84: 16428.72 | H84: =G84 -> 16428.72 | I84: =G84-H84 -> 0 | J84: =M$4*F84 -> 0 | K84: =M$2*F84 -> 20700 | L84: =J$3*F84%+J$4 -> 0 | M84: =ROUND((K84+J84+I84+L84),0) + O84 -> 20700.72 | N84: =ROUND((M84*6% + M84 ),0) + O84 -> 21943.72 | O84: =O83+0.01 -> 0.72
C85: COCH 4 | D85: Puisys Guillermo Antonio | F85: 0.0023 | G85: 16428.73 | H85: =G85 -> 16428.73 | I85: =G85-H85 -> 0 | J85: =M$4*F85 -> 0 | K85: =M$2*F85 -> 20700 | L85: =J$3*F85%+J$4 -> 0 | M85: =ROUND((K85+J85+I85+L85),0) + O85 -> 20700.73 | N85: =ROUND((M85*6% + M85 ),0) + O85 -> 21943.73 | O85: =O84+0.01 -> 0.73
C86: COCH 5 | D86: Arias, Mariana Laura | F86: 0.0023 | G86: 16428.74 | H86: =G86 -> 16428.74 | I86: =G86-H86 -> 0 | J86: =M$4*F86 -> 0 | K86: =M$2*F86 -> 20700 | L86: =J$3*F86%+J$4 -> 0 | M86: =ROUND((K86+J86+I86+L86),0) + O86 -> 20700.74 | N86: =ROUND((M86*6% + M86 ),0) + O86 -> 21943.74 | O86: =O85+0.01 -> 0.74
C87: COCH 6 | D87: Dimito, Vicente Argentino - Cerantes , Mabel | F87: 0.0023 | G87: 16428.75 | I87: =G87-H87 -> 16428.75 | J87: =M$4*F87 -> 0 | K87: =M$2*F87 -> 20700 | L87: =J$3*F87%+J$4 -> 0 | M87: =ROUND((K87+J87+I87+L87),0) + O87 -> 37129.75 | N87: =ROUND((M87*6% + M87 ),0) + O87 -> 39358.75 | O87: =O86+0.01 -> 0.75
C88: COCH 7 | D88: Campelo, Mariano | F88: 0.0023 | G88: 16428.76 | H88: =G88 -> 16428.76 | I88: =G88-H88 -> 0 | J88: =M$4*F88 -> 0 | K88: =M$2*F88 -> 20700 | L88: =J$3*F88%+J$4 -> 0 | M88: =ROUND((K88+J88+I88+L88),0) + O88 -> 20700.76 | N88: =ROUND((M88*6% + M88 ),0) + O88 -> 21943.76 | O88: =O87+0.01 -> 0.76
C89: COCH 8 | D89: Campelo, Mariano | F89: 0.0023 | G89: 16428.77 | H89: =G89 -> 16428.77 | I89: =G89-H89 -> 0 | J89: =M$4*F89 -> 0 | K89: =M$2*F89 -> 20700 | L89: =J$3*F89%+J$4 -> 0 | M89: =ROUND((K89+J89+I89+L89),0) + O89 -> 20700.77 | N89: =ROUND((M89*6% + M89 ),0) + O89 -> 21943.77 | O89: =O88+0.01 -> 0.77
C90: COCH 9 | D90: Sr propietario | F90: 0.0023 | G90: 16428.78 | I90: =G90-H90 -> 16428.78 | J90: =M$4*F90 -> 0 | K90: =M$2*F90 -> 20700 | L90: =J$3*F90%+J$4 -> 0 | M90: =ROUND((K90+J90+I90+L90),0) + O90 -> 37129.78 | N90: =ROUND((M90*6% + M90 ),0) + O90 -> 39358.78 | O90: =O89+0.01 -> 0.78
C91: COCH 10 | D91: Cerra, Antonio Osvaldo | F91: 0.0023 | G91: 16428.79 | I91: =G91-H91 -> 16428.79 | J91: =M$4*F91 -> 0 | K91: =M$2*F91 -> 20700 | L91: =J$3*F91%+J$4 -> 0 | M91: =ROUND((K91+J91+I91+L91),0) + O91 -> 37129.79 | N91: =ROUND((M91*6% + M91 ),0) + O91 -> 39358.79 | O91: =O90+0.01 -> 0.79
C92: COCH 11 | D92: Osipowicz, Ariel Marcelo | F92: 0.0023 | G92: 16428.8 | H92: =G92 -> 16428.8 | I92: =G92-H92 -> 0 | J92: =M$4*F92 -> 0 | K92: =M$2*F92 -> 20700 | L92: =J$3*F92%+J$4 -> 0 | M92: =ROUND((K92+J92+I92+L92),0) + O92 -> 20700.8 | N92: =ROUND((M92*6% + M92 ),0) + O92 -> 21943.8 | O92: =O91+0.01 -> 0.8
C93: COCH 12 | D93: Dieci, Matias Orlando | F93: 0.0023 | G93: 16428.81 | H93: =G93 -> 16428.81 | I93: =G93-H93 -> 0 | J93: =M$4*F93 -> 0 | K93: =M$2*F93 -> 20700 | L93: =J$3*F93%+J$4 -> 0 | M93: =ROUND((K93+J93+I93+L93),0) + O93 -> 20700.81 | N93: =ROUND((M93*6% + M93 ),0) + O93 -> 21943.81 | O93: =O92+0.01 -> 0.81
C94: COCH 13 | D94: Scardigno, Gabriela Susana - Ripoll, Luis Alberto | F94: 0.0023 | G94: 16428.82 | H94: =G94 -> 16428.82 | I94: =G94-H94 -> 0 | J94: =M$4*F94 -> 0 | K94: =M$2*F94 -> 20700 | L94: =J$3*F94%+J$4 -> 0 | M94: =ROUND((K94+J94+I94+L94),0) + O94 -> 20700.82 | N94: =ROUND((M94*6% + M94 ),0) + O94 -> 21943.82 | O94: =O93+0.01 -> 0.82
C95: COCH 14 | D95: Fontale Federico Carlos - Celentano Alejandra Veronica | F95: 0.0023 | G95: 16428.83 | H95: =G95 -> 16428.83 | I95: =G95-H95 -> 0 | J95: =M$4*F95 -> 0 | K95: =M$2*F95 -> 20700 | L95: =J$3*F95%+J$4 -> 0 | M95: =ROUND((K95+J95+I95+L95),0) + O95 -> 20700.83 | N95: =ROUND((M95*6% + M95 ),0) + O95 -> 21943.83 | O95: =O94+0.01 -> 0.83
C96: COCH 15 | D96: Hernandez, Marisa Beatriz - Hernandez, Adrian Jose | F96: 0.0023 | G96: 16428.84 | H96: =G96 -> 16428.84 | I96: =G96-H96 -> 0 | J96: =M$4*F96 -> 0 | K96: =M$2*F96 -> 20700 | L96: =J$3*F96%+J$4 -> 0 | M96: =ROUND((K96+J96+I96+L96),0) + O96 -> 20700.84 | N96: =ROUND((M96*6% + M96 ),0) + O96 -> 21943.84 | O96: =O95+0.01 -> 0.84
C97: COCH 16 | D97: Mesa, Mariano | F97: 0.0023 | G97: 16428.85 | H97: =G97 -> 16428.85 | I97: =G97-H97 -> 0 | J97: =M$4*F97 -> 0 | K97: =M$2*F97 -> 20700 | L97: =J$3*F97%+J$4 -> 0 | M97: =ROUND((K97+J97+I97+L97),0) + O97 -> 20700.85 | N97: =ROUND((M97*6% + M97 ),0) + O97 -> 21943.85 | O97: =O96+0.01 -> 0.85
C98: COCH 17 | D98: Espósito, Franco Ezequiel | F98: 0.0023 | G98: 16428.86 | H98: =G98 -> 16428.86 | I98: =G98-H98 -> 0 | J98: =M$4*F98 -> 0 | K98: =M$2*F98 -> 20700 | L98: =J$3*F98%+J$4 -> 0 | M98: =ROUND((K98+J98+I98+L98),0) + O98 -> 20700.86 | N98: =ROUND((M98*6% + M98 ),0) + O98 -> 21943.86 | O98: =O97+0.01 -> 0.86
C99: COCH 18 | D99: Sr propietario | F99: 0.0023 | G99: 16428.87 | I99: =G99-H99 -> 16428.87 | J99: =M$4*F99 -> 0 | K99: =M$2*F99 -> 20700 | L99: =J$3*F99%+J$4 -> 0 | M99: =ROUND((K99+J99+I99+L99),0) + O99 -> 37129.87 | N99: =ROUND((M99*6% + M99 ),0) + O99 -> 39358.87 | O99: =O98+0.01 -> 0.87
C100: COCH 19 | D100: Lobalo Lorena - Vega Maximiliano | F100: 0.0023 | G100: 16428.88 | I100: =G100-H100 -> 16428.88 | J100: =M$4*F100 -> 0 | K100: =M$2*F100 -> 20700 | L100: =J$3*F100%+J$4 -> 0 | M100: =ROUND((K100+J100+I100+L100),0) + O100 -> 37129.88 | N100: =ROUND((M100*6% + M100 ),0) + O100 -> 39358.88 | O100: =O99+0.01 -> 0.88
C101: COCH 20 | D101: Rosales, Rubén Darío | F101: 0.0023 | G101: 16428.89 | H101: 17415.89 | I101: =G101-H101 -> -987 | J101: =M$4*F101 -> 0 | K101: =M$2*F101 -> 20700 | L101: =J$3*F101%+J$4 -> 0 | M101: =ROUND((K101+J101+I101+L101),0) + O101 -> 19713.89 | N101: =ROUND((M101*6% + M101 ),0) + O101 -> 20897.89 | O101: =O100+0.01 -> 0.89
...

Sheet Hoja1
C4: AYALA
C5: 52141.08 | D5: 3B
C6: 67140.1 | D6: 3D
C7: 52121.11 | D7: 3E
C8: 67885.12 | D8: 3F
C9: 67140.16 | D9: 4D
C10: 62141.17 | D10: 4E
C11: 67855.18 | D11: 4F
C12: 62141.23 | D12: 5E
C13: 67855.24 | D13: 5F
C14: =SUM(C5:C13) -> 566420.39

Sheet ANOTACIONES
B4: AGREGAR MAILS DEL FOLEO
