Workbook

Sheet RESUMEN
B2: MAIL: consorciogorriti368@gmail.com
B3: CUIT ADMINISTRACION: 27231256879
B4: CBU: 0290034600000502294350 | D4: TELEFONO: 11 5320-2676
A5: LIQUIDACION DE EXPENSAS | B5: ADMINISTRADORA: CAROLINA CANCIANI MP:1148
A6: CUIT DEL EDIFICIO: 30583957819 | B6: PERÍODO: MARZO | D6: HORARIOS DE ATENCION: LUNES A VIERNES
A7: CONSORCIO DE PROPIETARIOS DEL EDIFICIO CALLE GORRITI 368 | D7: 10 A 16HS - EMERGENCIAS 24HS
B9: VTO 14/04
A14: ESTIMADOS PROPIETARIOS E INQUILINOS: POR FAVOR LOS QUE ABONAN EN PRIMER VENCIMIENTO ABONEN EL MONTO DE PRIMER VENCIMIENTO, ASI AGILIZAN LA LIQUIDACION, RESPETEN LOS CENTAVOS CORRESPONDIENTES A LA UNIDAD FUNCIONAL. ES DE CARÁCTER OBLIGATORIO INFORMAR VIA MAIL LAS EXPENSAS. CASO CONTRARIO SE INFORMARA VIA CARTA DOCUMENTO A LA UNIDAD FUNCIONAL QUE CREEMOS QUE CORRESPONDE, CUYO COSTO SERA IMPUTADO A LA UNIDAD FUNCIONAL SOSPECHADA.
A21: GASTOS ORDINARIOS UNIDADES FUNCIONALES:
A22: HABERES ENCARGADOS
A23: Sueldo encargado Colmiero Oscar | D23: 1227647
A26: Retenciones | D26: 0
A28: Neto | D28: =SUM(D23:D27) -> 1227647 | G28: =D28+D37 -> 2231706
A29: Sueldo encargado Balcazza Leonardo | D29: 1004059
A33: SAC
A34: Retenciones SAC
A35: Retenciones | D35: 0
A37: Neto | D37: =SUM(D29:D36) -> 1004059
A38: TOTAL SUELDO | E38: =D28+D37 -> 2231706
A39: HONORARIOS
A40: GUSTAVO PADRON - SE ABONA MES 12/2024 - MES 1 Y 2 DEL 2025 - SE DEBE MES DE MARZO 2025 | D40: 150000 | E40: Transf 13/02
A41: HONORARIOS ADMINISTRACION RC - SE ABONA EL MES 1 Y 2 DEL 2025 - SE ADEUDA MES 3 | D41: 460000 | E41: =E40 -> Transf 13/02
A42: TOTAL | E42: =SUM(D40:D41) -> 610000
A43: SEGUROS
A44: Seguro Integral consorcio San Cristobal - Poliza 01-05-07-30183461 | D44: 120974 | E44: Debito 10/03
A46: TOTAL IMPUESTO | E46: =SUM(D44:D45) -> 120974
A47: APORTES Y CONTRIBUCIONES
A48: ARCA | D48: 1425903 | E48: PMC 13/03
A49: Sindicatos mes de MARZO | B49: Fatheryh | D49: 130033.66 | E49: Debito 12/03
A50: =A49 -> Sindicatos mes de MARZO | B50: Suther | D50: 263175.12 | E50: =E49 -> Debito 12/03
A51: =A50 -> Sindicatos mes de MARZO | B51: Seracarh | D51: 14448.18 | E51: =E50 -> Debito 12/03
A52: TOTAL Aportes y Contribuciones - Sindicato | E52: =SUM(D48:D51) -> 1833560
A53: ABONOS Y SERVICIOS
A54: EDESUR - Cliente nro. 828563 | D54: 684571.44 | E54: PMC 10/03
A55: EDESUR - Cliente nro. 01672309 | D55: 22935.54 | E55: =E54 -> PMC 10/03
A56: EDESUR - Cliente nro. 01672321 | D56: 16991 | E56: =E55 -> PMC 10/03
A57: EDESUR - Cliente nro. 01672319 | D57: 11712.22 | E57: =E56 -> PMC 10/03
A58: Metrogas - Cliente nro. 20463936100 | D58: =8218.47 -> 8218.47 | E58: PMC 19/03
A59: Metrogas Plan de pagos cuota 1 de 4 - Cliente nro. 020495697900 | D59: 571923.58 | E59: Efect 31/03
A60: EL EFECTIVO FUE ABONADO POR LA ADMINISTRACION Y SE RECUPERARA MEDIANTE TRANSFERENCIA YA QUE LOS PLANES DE PAGO SE ABONAN CON TARJETA DE CREDITO, DEBITO O EFECTIVO.
A61: Personal Flow - Debito automatico | D61: 13674.01 | E61: Debito 25/03
A62: AYSA - Nro de cliente 3888610 | D62: 2285959.9 | E62: PMC 13/03
A64: TOTAL ABONOS Y SERVICIOS | E64: =SUM(D54:D63) -> 3615986.2
A65: GASTOS GENERALES / MANTENIMIENTO
A66: Castellano Alejandro - Abono parcial de servicio de mantenimiento de grupo electrogeno y porton - Meses Septiembre a Marzo 2025 ( Restan $38.800) | D66: 300000 | E66: Transf 28/03
A67: Control de plagas 26/3 - Servicio Viturro Alberto | D67: 49400 | E67: Transf 26/3
A68: Arreglo terraza Sergio - Resto del pago de la factura presentada en el drive | D68: 300000 | E68: Transf 19/03
A69: Acesur compra de termoestato y vaina - 27/03 | D69: 76658.35 | E69: Transf 27/03
A70: Toto Calderista - Cambio de presostato de calefaccion en colector de caldera, purga - Mano de obra | D70: 460000 | E70: Tranfs 31/03
A71: Toto Calderista - Limpieza y puesta en marcha de caldera anual 2025 (verificacion de automaticos por corte de temperatura, limpieza de tubos, etc) | D71: 420000 | E71: Tranfs 26/03
A72: JPL articulos de limpieza (cera, blem, rejillas, detergente, desengrasante, bolsas, trapos, etc) | D72: 250400 | E72: Tranfs 21/3
A73: TOTAL | E73: =SUM(D66:D72) -> 1856458.4
A74: GASTOS BANCARIOS
A75: GASTOS BANCARIOS | D75: =8907.49+5230.62+29148.47+20852.71+40446.28+2323.01-7800-1473.52-1710.35+10419.95+1802.27 -> 108146.93
A77: TOTAL | E77: =SUM(D75:D76) -> 108146.93
A79: PREVISION ORDINARIA | E79: 1000000
A81: TOTAL ORDINARIOS | E81: =(SUM(E31:E79)) -> 11376831
A84: GASTOS EXTRAORDINARIOS:
E89: =SUM(D85:D88) -> 0
A92: PREVISION EXTRAORDINARIA
A94: TOTAL EXTRAORDINARIOS | E94: =E89+E92 -> 0
A96: GASTOS ORDINARIOS + PREVISION : | B96: =E81 -> 11376831
A97: GASTOS ORDINARIOS SIN PREVISION: | B97: =E81-E79 -> 10376831
A98: GASTOS EXTRAORDINARIOS SIN PREVISION: | B98: =E94-E92 -> 0
A99: GASTOS EXTRAORDINARIOS CON PREVISION: | B99: =E94 -> 0
A106: RESUMEN
B107: 0
A108: Ingreso | B108: =PRORRATEO!I81 -> 9620855.2
B109: 0
A110: Deposito sin identificar | B110: =B132 -> 0
A112: Punitorios mal cobrados
A113: Egresos Ordinarios | B113: =-B97 -> -10376831
A114: Egresos Extraordinarios | B114: =-(B98) -> 0
A115: TOTAL | B115: =SUM(B107:B114) -> -755976.28
A119: SALDO EN BANCO ANTERIOR REAL | B119: 1141207.4
A120: Egresos del mes ordinarios | B120: =-B97 -> -10376831
A121: Egresos del mes extrordinarios | B121: =-B98 -> 0
A122: Sanitarios Millie - Compra materiales para obra ascendente de agua 21/3 | B122: -318300
A123: Ingresos | B123: =PRORRATEO!I81 -> 9620855.2
A124: Punitorios mal cobrados | B124: -618
A125: CAJA REAL | B125: =SUM(B119:C124) -> 66313.09
A128: DEPOSITOS NO IDENTIFICADOS
C130: 40000
A132: TOTAL | B132: =SUM(B130:B131) -> 0

Sheet PRORRATEO
E2: =RESUMEN!B4 -> CBU: 0290034600000502294350 | L2: Gastos ordinarios: | P2: 11376831
A4: Piso | B4: Dpto. | D4: UF | E4: Propietario | F4: Inquilinos | G4: (%) | H4: Saldo Ord | I4: Ingreso | J4: Pago por | K4: Deuda o Saldo a favor | L4: Interes 3% | M4: Expensas extraor. | N4: Expensas ord. | O4: Gastos part. | P4: Total 1er Vto | Q4: Total 2do Vto. | R4: Total 2do Vto
P5: =RESUMEN!B9 -> VTO 14/04
A6: PB | C6: LOC | D6: 1 | E6: GEFFNER SILVIA E. | G6: 0.5131 | H6: 53269.01 | I6: =659558-I13-I7-I47-I48-I59-I69-I73 -> 53269.19 | K6: =H6-I6 -> -0.18 | L6: =IF(K6>0,K6*3%,0) -> 0 | M6: 0 | N6: =P$2*G6% -> 58374.522 | O6: 0 | P6: =ROUND(SUM(K6:O6),0) + S6 -> 58374.01 | Q6: =ROUND(P6*6% + P6,0) + S6 -> 61876.01 | R6: =ROUND(P6*3%,0) + P6 -> 60125.01 | S6: 0.01 | U6: este es el candel que tiene a todas sus demas ufs relacionadas
A7: 3º | C7: LOC | D7: =D6+1 -> 2 | E7: COVILOZA S. A. | G7: 0.6119 | H7: 63526.02 | I7: =H7 -> 63526.02 | K7: =H7-I7 -> 0 | L7: =IF(K7>0,K7*3%,0) -> 0 | M7: 0 | N7: =P$2*G7% -> 69614.832 | O7: 0 | P7: =ROUND(SUM(K7:O7),0) + S7 -> 69615.02 | Q7: =ROUND(P7*6% + P7,0) + S7 -> 73792.02 | R7: =ROUND(P7*3%,0) + P7 -> 71703.02 | S7: =S6+0.01 -> 0.02
A8: 3º | B8: 1 | D8: =D7+1 -> 3 | E8: ASIST Y TRAB. | G8: 0.6115 | H8: 63485.03 | K8: =H8-I8 -> 63485.03 | L8: =IF(K8>0,K8*3%,0) -> 1904.5509 | M8: 0 | N8: =P$2*G8% -> 69569.324 | O8: 0 | P8: =ROUND(SUM(K8:O8),0) + S8 -> 134959.03 | Q8: =ROUND(P8*6% + P8,0) + S8 -> 143057.03 | R8: =ROUND(P8*3%,0) + P8 -> 139008.03 | S8: =S7+0.01 -> 0.03
A9: 4º | B9: 2 | D9: =D8+1 -> 4 | E9: ASIST Y TRAB. | G9: 0.5033 | H9: 52252.04 | K9: =H9-I9 -> 52252.04 | L9: =IF(K9>0,K9*3%,0) -> 1567.5612 | M9: 0 | N9: =P$2*G9% -> 57259.593 | O9: 0 | P9: =ROUND(SUM(K9:O9),0) + S9 -> 111079.04 | Q9: =ROUND(P9*6% + P9,0) + S9 -> 117744.04 | R9: =ROUND(P9*3%,0) + P9 -> 114411.04 | S9: =S8+0.01 -> 0.04
A10: 4º | B10: 3 | D10: =D9+1 -> 5 | E10: ASIST Y TRAB. | G10: 0.5033 | H10: 46711.05 | K10: =H10-I10 -> 46711.05 | L10: =IF(K10>0,K10*3%,0) -> 1401.3315 | M10: 0 | N10: =P$2*G10% -> 57259.593 | O10: 0 | P10: =ROUND(SUM(K10:O10),0) + S10 -> 105372.05 | Q10: =ROUND(P10*6% + P10,0) + S10 -> 111694.05 | R10: =ROUND(P10*3%,0) + P10 -> 108533.05 | S10: =S9+0.01 -> 0.05
A11: 5º | B11: 4 | D11: =D10+1 -> 6 | E11: BENMAOR D. | F11: Cristian Requelme | G11: 0.7499 | H11: 77853.06 | I11: =H11 -> 77853.06 | K11: =H11-I11 -> 0 | L11: =IF(K11>0,K11*3%,0) -> 0 | M11: 0 | N11: =P$2*G11% -> 85314.859 | O11: 0 | P11: =ROUND(SUM(K11:O11),0) + S11 -> 85315.06 | Q11: =ROUND(P11*6% + P11,0) + S11 -> 90434.06 | R11: =ROUND(P11*3%,0) + P11 -> 87874.06 | S11: =S10+0.01 -> 0.06
A12: 5º | B12: 5 | D12: =D11+1 -> 7 | E12: GALANTERNIK A | F12: Miriam Larken | G12: 0.5425 | H12: 56321.07 | I12: =H12 -> 56321.07 | K12: =H12-I12 -> 0 | L12: =IF(K12>0,K12*3%,0) -> 0 | M12: 0 | N12: =P$2*G12% -> 61719.311 | O12: 0 | P12: =ROUND(SUM(K12:O12),0) + S12 -> 61719.07 | Q12: =ROUND(P12*6% + P12,0) + S12 -> 65422.07 | R12: =ROUND(P12*3%,0) + P12 -> 63571.07 | S12: =S11+0.01 -> 0.07
A13: 6º | B13: 6 | D13: =D12+1 -> 8 | E13: CANDEL JORGE ISAAC | G13: 0.4537 | H13: 47102.08 | I13: =H13 -> 47102.08 | K13: =H13-I13 -> 0 | L13: =IF(K13>0,K13*3%,0) -> 0 | M13: 0 | N13: =P$2*G13% -> 51616.684 | O13: 0 | P13: =ROUND(SUM(K13:O13),0) + S13 -> 51617.08 | Q13: =ROUND(P13*6% + P13,0) + S13 -> 54714.08 | R13: =ROUND(P13*3%,0) + P13 -> 53166.08 | S13: =S12+0.01 -> 0.08
A14: 6º | B14: 7 | D14: =D13+1 -> 9 | E14: BORTZ SERGIO | G14: 0.5244 | H14: 54442.09 | K14: =H14-I14 -> 54442.09 | L14: =IF(K14>0,K14*3%,0) -> 1633.2627 | M14: 0 | N14: =P$2*G14% -> 59660.104 | O14: 0 | P14: =ROUND(SUM(K14:O14),0) + S14 -> 115735.09 | Q14: =ROUND(P14*6% + P14,0) + S14 -> 122679.09 | R14: =ROUND(P14*3%,0) + P14 -> 119207.09 | S14: =S13+0.01 -> 0.09 | U14: ESTA ES LA FUNDACION DE MEDICOS
A15: 7º | B15: 8 | D15: =D14+1 -> 10 | E15: BORTZ SERGIO | G15: 0.424 | H15: 44019.1 | K15: =H15-I15 -> 44019.1 | L15: =IF(K15>0,K15*3%,0) -> 1320.573 | M15: 0 | N15: =P$2*G15% -> 48237.765 | O15: 0 | P15: =ROUND(SUM(K15:O15),0) + S15 -> 93577.1 | Q15: =ROUND(P15*6% + P15,0) + S15 -> 99192.1 | R15: =ROUND(P15*3%,0) + P15 -> 96384.1 | S15: =S14+0.01 -> 0.1 | U15: ESTA ES LA FUNDACION DE MEDICOS
A16: 7º | B16: 1 | C16: A | D16: =D15+1 -> 11 | E16: KIM SOON LEO | G16: 2.3033 | H16: 2218018.1 | K16: =H16-I16 -> 2218018.1 | L16: =IF(K16>0,K16*3%,0) -> 66540.543 | M16: 0 | N16: =P$2*G16% -> 262042.56 | O16: 0 | P16: =ROUND(SUM(K16:O16),0) + S16 -> 2546601.1 | Q16: =ROUND(P16*6% + P16,0) + S16 -> 2699397.1 | R16: =ROUND(P16*3%,0) + P16 -> 2622999.1 | S16: =S15+0.01 -> 0.11
A17: 8º | B17: 1 | C17: B | D17: =D16+1 -> 12 | E17: CANDEL MARCELO | F17: Florencia Fucci | G17: 2.7493 | H17: 293990.12 | I17: =H17 -> 293990.12 | K17: =H17-I17 -> 0 | L17: =IF(K17>0,K17*3%,0) -> 0 | M17: 0 | N17: =P$2*G17% -> 312783.23 | O17: 0 | P17: =ROUND(SUM(K17:O17),0) + S17 -> 312783.12 | Q17: =ROUND(P17*6% + P17,0) + S17 -> 331550.12 | R17: =ROUND(P17*3%,0) + P17 -> 322166.12 | S17: =S16+0.01 -> 0.12
A18: 8º | B18: 2 | C18: A | D18: =D17+1 -> 13 | E18: TRIPODI | F18: Mariela Pricolo | G18: 2.3033 | H18: 239124.13 | I18: =H18 -> 239124.13 | K18: =H18-I18 -> 0 | L18: =IF(K18>0,K18*3%,0) -> 0 | M18: 0 | N18: =P$2*G18% -> 262042.56 | O18: 0 | P18: =ROUND(SUM(K18:O18),0) + S18 -> 262043.13 | Q18: =ROUND(P18*6% + P18,0) + S18 -> 277766.13 | R18: =ROUND(P18*3%,0) + P18 -> 269904.13 | S18: =S17+0.01 -> 0.13
A19: 9º | B19: 2 | C19: B | D19: =D18+1 -> 14 | E19: MIRANDA DE GIL | F19: Susana | G19: 2.6368 | H19: 314618.14 | I19: =234000+80618 -> 314618 | K19: =H19-I19 -> 0.14 | L19: =IF(K19>0,K19*3%,0) -> 0.0042 | M19: 0 | N19: =P$2*G19% -> 299984.29 | O19: 0 | P19: =ROUND(SUM(K19:O19),0) + S19 -> 299984.14 | Q19: =ROUND(P19*6% + P19,0) + S19 -> 317983.14 | R19: =ROUND(P19*3%,0) + P19 -> 308984.14 | S19: =S18+0.01 -> 0.14 | U19: MAXIMO
A20: 9º | B20: 3 | C20: A | D20: =D19+1 -> 15 | E20: FRAGA DORA | G20: 2.3537 | H20: 236299.15 | I20: 243388.15 | K20: =H20-I20 -> -7089 | L20: =IF(K20>0,K20*3%,0) -> 0 | M20: 0 | N20: =P$2*G20% -> 267776.48 | O20: 0 | P20: =ROUND(SUM(K20:O20),0) + S20 -> 260687.15 | Q20: =ROUND(P20*6% + P20,0) + S20 -> 276328.15 | R20: =ROUND(P20*3%,0) + P20 -> 268508.15 | S20: =S19+0.01 -> 0.15
A21: 10º | B21: 3 | C21: B | D21: =D20+1 -> 16 | E21: SARUBBI MARTIN | F21: Sarubbi Adriana | G21: 2.6477 | H21: 274879.16 | I21: =H21 -> 274879.16 | K21: =H21-I21 -> 0 | L21: =IF(K21>0,K21*3%,0) -> 0 | M21: 0 | N21: =P$2*G21% -> 301224.37 | O21: 0 | P21: =ROUND(SUM(K21:O21),0) + S21 -> 301224.16 | Q21: =ROUND(P21*6% + P21,0) + S21 -> 319298.16 | R21: =ROUND(P21*3%,0) + P21 -> 310261.16 | S21: =S20+0.01 -> 0.16
A22: 10º | B22: 4 | C22: A | D22: =D21+1 -> 17 | E22: LACENTRE | F22: Gabriela Tamara | G22: 2.3235 | H22: 241222.17 | I22: =H22 -> 241222.17 | K22: =H22-I22 -> 0 | L22: =IF(K22>0,K22*3%,0) -> 0 | M22: 0 | N22: =P$2*G22% -> 264340.68 | O22: 0 | P22: =ROUND(SUM(K22:O22),0) + S22 -> 264341.17 | Q22: =ROUND(P22*6% + P22,0) + S22 -> 280202.17 | R22: =ROUND(P22*3%,0) + P22 -> 272271.17 | S22: =S21+0.01 -> 0.17
A23: 11º | B23: 4 | C23: B | D23: =D22+1 -> 18 | E23: FERNANDEZ BERTA | F23: KRAVETZ | G23: 2.688 | H23: 599159.18 | I23: =200000*2+217134 -> 617134 | K23: =H23-I23 -> -17974.82 | L23: =IF(K23>0,K23*3%,0) -> 0 | M23: 0 | N23: =P$2*G23% -> 305809.23 | O23: 0 | P23: =ROUND(SUM(K23:O23),0) + S23 -> 287834.18 | Q23: =ROUND(P23*6% + P23,0) + S23 -> 305104.18 | R23: =ROUND(P23*3%,0) + P23 -> 296469.18 | S23: =S22+0.01 -> 0.18 | U23: KRAVETZ
A24: 11º | B24: 5 | C24: A | D24: =D23+1 -> 19 | E24: VERONES JOSE MARIA | G24: 2.36 | H24: 245011.19 | I24: =345011.19 -> 345011.19 | K24: =H24-I24 -> -100000 | L24: =IF(K24>0,K24*3%,0) -> 0 | M24: 0 | N24: =P$2*G24% -> 268493.22 | O24: 0 | P24: =ROUND(SUM(K24:O24),0) + S24 -> 168493.19 | Q24: =ROUND(P24*6% + P24,0) + S24 -> 178603.19 | R24: =ROUND(P24*3%,0) + P24 -> 173548.19 | S24: =S23+0.01 -> 0.19
A25: 12º | B25: 5 | C25: B | D25: =D24+1 -> 20 | E25: SRUGO CARLOS | G25: 2.7183 | H25: 365245.2 | I25: 365300 | K25: =H25-I25 -> -54.8 | L25: =IF(K25>0,K25*3%,0) -> 0 | M25: 0 | N25: =P$2*G25% -> 309256.41 | O25: 0 | P25: =ROUND(SUM(K25:O25),0) + S25 -> 309202.2 | Q25: =ROUND(P25*6% + P25,0) + S25 -> 327754.2 | R25: =ROUND(P25*3%,0) + P25 -> 318478.2 | S25: =S24+0.01 -> 0.2
A26: 13º | B26: 6 | C26: A | D26: =D25+1 -> 21 | E26: DINOTO | G26: 2.3033 | H26: -6461.79 | K26: =H26-I26 -> -6461.79 | L26: =IF(K26>0,K26*3%,0) -> 0 | M26: 0 | N26: =P$2*G26% -> 262042.56 | O26: 0 | P26: =ROUND(SUM(K26:O26),0) + S26 -> 255581.21 | Q26: =ROUND(P26*6% + P26,0) + S26 -> 270916.21 | R26: =ROUND(P26*3%,0) + P26 -> 263248.21 | S26: =S25+0.01 -> 0.21
A27: 14º | B27: 6 | C27: B | D27: =D26+1 -> 22 | E27: BORTZ ESTHER | F27: Daniel | G27: 2.636 | H27: 273665.22 | K27: =H27-I27 -> 273665.22 | L27: =IF(K27>0,K27*3%,0) -> 8209.9566 | M27: 0 | N27: =P$2*G27% -> 299893.28 | O27: 0 | P27: =ROUND(SUM(K27:O27),0) + S27 -> 581768.22 | Q27: =ROUND(P27*6% + P27,0) + S27 -> 616674.22 | R27: =ROUND(P27*3%,0) + P27 -> 599221.22 | S27: =S26+0.01 -> 0.22 | U27: ESTA ES LA FUNDACION DE MEDICOS
A28: 15º | B28: 7 | C28: A | D28: =D27+1 -> 23 | E28: COUSO MARIA CRISTINA | G28: 2.3033 | H28: 239124.23 | I28: =H28 -> 239124.23 | K28: =H28-I28 -> 0 | L28: =IF(K28>0,K28*3%,0) -> 0 | M28: 0 | N28: =P$2*G28% -> 262042.56 | O28: 0 | P28: =ROUND(SUM(K28:O28),0) + S28 -> 262043.23 | Q28: =ROUND(P28*6% + P28,0) + S28 -> 277766.23 | R28: =ROUND(P28*3%,0) + P28 -> 269904.23 | S28: =S27+0.01 -> 0.23
A29: COC | B29: 7 | C29: B | D29: =D28+1 -> 24 | E29: POSSENTI JUAN JOSE | G29: 2.6159 | H29: 271578.24 | I29: =H29 -> 271578.24 | K29: =H29-I29 -> 0 | L29: =IF(K29>0,K29*3%,0) -> 0 | M29: 0 | N29: =P$2*G29% -> 297606.53 | O29: 0 | P29: =ROUND(SUM(K29:O29),0) + S29 -> 297607.24 | Q29: =ROUND(P29*6% + P29,0) + S29 -> 315464.24 | R29: =ROUND(P29*3%,0) + P29 -> 306535.24 | S29: =S28+0.01 -> 0.24
A30: COC | B30: 8 | C30: A | D30: =D29+1 -> 25 | E30: VANNI KARINA | G30: 2.3537 | H30: 244357.25 | I30: =H30 -> 244357.25 | K30: =H30-I30 -> 0 | L30: =IF(K30>0,K30*3%,0) -> 0 | M30: 0 | N30: =P$2*G30% -> 267776.48 | O30: 0 | P30: =ROUND(SUM(K30:O30),0) + S30 -> 267776.25 | Q30: =ROUND(P30*6% + P30,0) + S30 -> 283843.25 | R30: =ROUND(P30*3%,0) + P30 -> 275809.25 | S30: =S29+0.01 -> 0.25
A31: COC | B31: 8 | C31: B | D31: =D30+1 -> 26 | E31: CARRIZO RAÚL | F31: Noelia Villarino | G31: 2.6469 | H31: 274796.26 | I31: =H31 -> 274796.26 | K31: =H31-I31 -> 0 | L31: =IF(K31>0,K31*3%,0) -> 0 | M31: 0 | N31: =P$2*G31% -> 301133.35 | O31: 0 | P31: =ROUND(SUM(K31:O31),0) + S31 -> 301133.26 | Q31: =ROUND(P31*6% + P31,0) + S31 -> 319201.26 | R31: =ROUND(P31*3%,0) + P31 -> 310167.26 | S31: =S30+0.01 -> 0.26
A32: COC | B32: 9 | C32: A | D32: =D31+1 -> 27 | E32: BLANCO | G32: 2.3537 | H32: 244357.27 | I32: =H32 -> 244357.27 | K32: =H32-I32 -> 0 | L32: =IF(K32>0,K32*3%,0) -> 0 | M32: 0 | N32: =P$2*G32% -> 267776.48 | O32: 0 | P32: =ROUND(SUM(K32:O32),0) + S32 -> 267776.27 | Q32: =ROUND(P32*6% + P32,0) + S32 -> 283843.27 | R32: =ROUND(P32*3%,0) + P32 -> 275809.27 | S32: =S31+0.01 -> 0.27
A33: COC | B33: 9 | C33: B | D33: =D32+1 -> 28 | E33: GALANTE CELIA | G33: 2.6663 | H33: 267682.28 | I33: 275712.28 | K33: =H33-I33 -> -8030 | L33: =IF(K33>0,K33*3%,0) -> 0 | M33: 0 | N33: =P$2*G33% -> 303340.46 | O33: 0 | P33: =ROUND(SUM(K33:O33),0) + S33 -> 295310.28 | Q33: =ROUND(P33*6% + P33,0) + S33 -> 313029.28 | R33: =ROUND(P33*3%,0) + P33 -> 304169.28 | S33: =S32+0.01 -> 0.28
A34: COC | B34: 10 | C34: A | D34: =D33+1 -> 29 | E34: LEGUIZAMON PABLO | F34: Carla | G34: 2.4476 | H34: 254105.29 | I34: =H34 -> 254105.29 | K34: =H34-I34 -> 0 | L34: =IF(K34>0,K34*3%,0) -> 0 | M34: 0 | N34: =P$2*G34% -> 278459.33 | O34: 0 | P34: =ROUND(SUM(K34:O34),0) + S34 -> 278459.29 | Q34: =ROUND(P34*6% + P34,0) + S34 -> 295167.29 | R34: =ROUND(P34*3%,0) + P34 -> 286813.29 | S34: =S33+0.01 -> 0.29
A35: COC | B35: 10 | C35: B | D35: =D34+1 -> 30 | E35: CANDEL E. MARCELO | G35: 2.7183 | H35: 601724.3 | I35: 619776.3 | K35: =H35-I35 -> -18052 | L35: =IF(K35>0,K35*3%,0) -> 0 | M35: 0 | N35: =P$2*G35% -> 309256.41 | O35: 0 | P35: =ROUND(SUM(K35:O35),0) + S35 -> 291204.3 | Q35: =ROUND(P35*6% + P35,0) + S35 -> 308677.3 | R35: =ROUND(P35*3%,0) + P35 -> 299940.3 | S35: =S34+0.01 -> 0.3
A36: COC | B36: 11 | C36: A | D36: =D35+1 -> 31 | E36: DAVICCA MIGUEL | F36: Romina Navarro | G36: 2.3026 | H36: 231323.31 | I36: =H36 -> 231323.31 | K36: =H36-I36 -> 0 | L36: =IF(K36>0,K36*3%,0) -> 0 | M36: 0 | N36: =P$2*G36% -> 261962.92 | O36: 0 | P36: =ROUND(SUM(K36:O36),0) + S36 -> 261963.31 | Q36: =ROUND(P36*6% + P36,0) + S36 -> 277681.31 | R36: =ROUND(P36*3%,0) + P36 -> 269822.31 | S36: =S35+0.01 -> 0.31
A37: COC | B37: 11 | C37: B | D37: =D36+1 -> 32 | E37: GUTMAN MARIO | G37: 2.6562 | H37: 376989.32 | I37: 275762.32 | K37: =H37-I37 -> 101227 | L37: =IF(K37>0,K37*3%,0) -> 3036.81 | M37: 0 | N37: =P$2*G37% -> 302191.4 | O37: 0 | P37: =ROUND(SUM(K37:O37),0) + S37 -> 406455.32 | Q37: =ROUND(P37*6% + P37,0) + S37 -> 430843.32 | R37: =ROUND(P37*3%,0) + P37 -> 418649.32 | S37: =S36+0.01 -> 0.32
A38: COC | B38: 12 | C38: A | D38: =D37+1 -> 33 | E38: PRATOLONGO EDUARDO | G38: 2.3343 | H38: 242343.33 | I38: =H38 -> 242343.33 | K38: =H38-I38 -> 0 | L38: =IF(K38>0,K38*3%,0) -> 0 | M38: 0 | N38: =P$2*G38% -> 265569.38 | O38: 0 | P38: =ROUND(SUM(K38:O38),0) + S38 -> 265569.33 | Q38: =ROUND(P38*6% + P38,0) + S38 -> 281503.33 | R38: =ROUND(P38*3%,0) + P38 -> 273536.33 | S38: =S37+0.01 -> 0.33
A39: COC | B39: 12 | C39: B | D39: =D38+1 -> 34 | E39: CARTABBIA MARIO | G39: 2.6259 | H39: 272616.34 | I39: =H39 -> 272616.34 | K39: =H39-I39 -> 0 | L39: =IF(K39>0,K39*3%,0) -> 0 | M39: 0 | N39: =P$2*G39% -> 298744.22 | O39: 0 | P39: =ROUND(SUM(K39:O39),0) + S39 -> 298744.34 | Q39: =ROUND(P39*6% + P39,0) + S39 -> 316669.34 | R39: =ROUND(P39*3%,0) + P39 -> 307706.34 | S39: =S38+0.01 -> 0.34
A40: COC | B40: 1 | C40: C | D40: =D39+1 -> 35 | E40: NAVA HECTOR | F40: Marcos | G40: 1.007 | H40: 107681.35 | I40: =104545.35 -> 104545.35 | K40: =H40-I40 -> 3136 | L40: =IF(K40>0,K40*3%,0) -> 94.08 | M40: 0 | N40: =P$2*G40% -> 114564.69 | O40: 0 | P40: =ROUND(SUM(K40:O40),0) + S40 -> 117795.35 | Q40: =ROUND(P40*6% + P40,0) + S40 -> 124863.35 | R40: =ROUND(P40*3%,0) + P40 -> 121329.35 | S40: =S39+0.01 -> 0.35
A41: COC | B41: 1 | C41: D | D41: =D40+1 -> 36 | E41: BRATTOLI | F41: Palermo Hernan | G41: 0.7812 | H41: 81103.36 | I41: =H41 -> 81103.36 | K41: =H41-I41 -> 0 | L41: =IF(K41>0,K41*3%,0) -> 0 | M41: 0 | N41: =P$2*G41% -> 88875.807 | O41: 0 | P41: =ROUND(SUM(K41:O41),0) + S41 -> 88876.36 | Q41: =ROUND(P41*6% + P41,0) + S41 -> 94209.36 | R41: =ROUND(P41*3%,0) + P41 -> 91542.36 | S41: =S40+0.01 -> 0.36 | U41: PALERMO
B42: 1 | C42: E | D42: =D41+1 -> 37 | E42: BRATTOLI | F42: Palermo Hernan | G42: 1.2153 | H42: 126170.37 | I42: =H42 -> 126170.37 | K42: =H42-I42 -> 0 | L42: =IF(K42>0,K42*3%,0) -> 0 | M42: 0 | N42: =P$2*G42% -> 138262.63 | O42: 0 | P42: =ROUND(SUM(K42:O42),0) + S42 -> 138263.37 | Q42: =ROUND(P42*6% + P42,0) + S42 -> 146559.37 | R42: =ROUND(P42*3%,0) + P42 -> 142411.37 | S42: =S41+0.01 -> 0.37 | U42: PALERMO
B43: 2 | C43: C | D43: =D42+1 -> 38 | E43: MARIA I. ROTTA | F43: Mabel Rodríguez | G43: 0.9549 | H43: 102110.38 | I43: =H43 -> 102110.38 | K43: =H43-I43 -> 0 | L43: =IF(K43>0,K43*3%,0) -> 0 | M43: 0 | N43: =P$2*G43% -> 108637.36 | O43: 0 | P43: =ROUND(SUM(K43:O43),0) + S43 -> 108637.38 | Q43: =ROUND(P43*6% + P43,0) + S43 -> 115156.38 | R43: =ROUND(P43*3%,0) + P43 -> 111896.38 | S43: =S42+0.01 -> 0.38
B44: 2 | C44: D | D44: =D43+1 -> 39 | E44: SAIN GUILLERMO | G44: 0.7552 | H44: 240619.39 | K44: =H44-I44 -> 240619.39 | L44: =IF(K44>0,K44*3%,0) -> 7218.5817 | M44: 0 | N44: =P$2*G44% -> 85917.831 | O44: 0 | P44: =ROUND(SUM(K44:O44),0) + S44 -> 333756.39 | Q44: =ROUND(P44*6% + P44,0) + S44 -> 353782.39 | R44: =ROUND(P44*3%,0) + P44 -> 343769.39 | S44: =S43+0.01 -> 0.39
B45: 2 | C45: E | D45: =D44+1 -> 40 | E45: BLANCO | F45: Jose Medina | G45: 1.1545 | H45: 132107.4 | I45: 119858 | K45: =H45-I45 -> 12249.4 | L45: =IF(K45>0,K45*3%,0) -> 367.482 | M45: 0 | N45: =P$2*G45% -> 131345.52 | O45: 0 | P45: =ROUND(SUM(K45:O45),0) + S45 -> 143962.4 | Q45: =ROUND(P45*6% + P45,0) + S45 -> 152600.4 | R45: =ROUND(P45*3%,0) + P45 -> 148281.4 | S45: =S44+0.01 -> 0.4
B46: 3 | C46: C | D46: =D45+1 -> 41 | E46: GOLBERG DIEGO | F46: Isabel Infante | G46: 0.9549 | H46: 102054.41 | I46: =H46 -> 102054.41 | K46: =H46-I46 -> 0 | L46: =IF(K46>0,K46*3%,0) -> 0 | M46: 0 | N46: =P$2*G46% -> 108637.36 | O46: 0 | P46: =ROUND(SUM(K46:O46),0) + S46 -> 108637.41 | Q46: =ROUND(P46*6% + P46,0) + S46 -> 115156.41 | R46: =ROUND(P46*3%,0) + P46 -> 111896.41 | S46: =S45+0.01 -> 0.41
B47: 3 | C47: D | D47: =D46+1 -> 42 | E47: CANDEL RAÚL F. | G47: 0.7552 | H47: 78403.42 | I47: =H47 -> 78403.42 | K47: =H47-I47 -> 0 | L47: =IF(K47>0,K47*3%,0) -> 0 | M47: 0 | N47: =P$2*G47% -> 85917.831 | O47: 0 | P47: =ROUND(SUM(K47:O47),0) + S47 -> 85918.42 | Q47: =ROUND(P47*6% + P47,0) + S47 -> 91074.42 | R47: =ROUND(P47*3%,0) + P47 -> 88496.42 | S47: =S46+0.01 -> 0.42
B48: 3 | C48: E | D48: =D47+1 -> 43 | E48: AZCARATE DIEGO | G48: 1.1545 | H48: 119858.43 | I48: =H48 -> 119858.43 | K48: =H48-I48 -> 0 | L48: =IF(K48>0,K48*3%,0) -> 0 | M48: 0 | N48: =P$2*G48% -> 131345.52 | O48: 0 | P48: =ROUND(SUM(K48:O48),0) + S48 -> 131346.43 | Q48: =ROUND(P48*6% + P48,0) + S48 -> 139227.43 | R48: =ROUND(P48*3%,0) + P48 -> 135286.43 | S48: =S47+0.01 -> 0.43
B49: 4 | C49: C | D49: =D48+1 -> 44 | E49: MORONI MABEL | F49: Ines Telo | G49: 0.9549 | H49: 99136.44 | I49: =H49 -> 99136.44 | K49: =H49-I49 -> 0 | L49: =IF(K49>0,K49*3%,0) -> 0 | M49: 0 | N49: =P$2*G49% -> 108637.36 | O49: 0 | P49: =ROUND(SUM(K49:O49),0) + S49 -> 108637.44 | Q49: =ROUND(P49*6% + P49,0) + S49 -> 115156.44 | R49: =ROUND(P49*3%,0) + P49 -> 111896.44 | S49: =S48+0.01 -> 0.44
B50: 4 | C50: D | D50: =D49+1 -> 45 | E50: BELEN CIACCIARELLI | G50: 0.7552 | H50: 86417.45 | I50: =H50 -> 86417.45 | K50: =H50-I50 -> 0 | L50: =IF(K50>0,K50*3%,0) -> 0 | M50: 0 | N50: =P$2*G50% -> 85917.831 | O50: 0 | P50: =ROUND(SUM(K50:O50),0) + S50 -> 85918.45 | Q50: =ROUND(P50*6% + P50,0) + S50 -> 91074.45 | R50: =ROUND(P50*3%,0) + P50 -> 88496.45 | S50: =S49+0.01 -> 0.45 | U50: ESTA ES MARIA BELEN CIACCARELLI
B51: 4 | C51: E | D51: =D50+1 -> 46 | E51: PARMA | F51: Ezequiel Caputo | G51: 1.1545 | H51: 115905.46 | K51: =H51-I51 -> 115905.46 | L51: =IF(K51>0,K51*3%,0) -> 3477.1638 | M51: 0 | N51: =P$2*G51% -> 131345.52 | O51: 0 | P51: =ROUND(SUM(K51:O51),0) + S51 -> 250728.46 | Q51: =ROUND(P51*6% + P51,0) + S51 -> 265772.46 | R51: =ROUND(P51*3%,0) + P51 -> 258250.46 | S51: =S50+0.01 -> 0.46
B52: 5 | C52: C | D52: =D51+1 -> 47 | E52: TORRES BASSO RUBEN | F52: Andrea | G52: 0.9549 | H52: 99136.47 | I52: =H52 -> 99136.47 | K52: =H52-I52 -> 0 | L52: =IF(K52>0,K52*3%,0) -> 0 | M52: 0 | N52: =P$2*G52% -> 108637.36 | O52: 0 | P52: =ROUND(SUM(K52:O52),0) + S52 -> 108637.47 | Q52: =ROUND(P52*6% + P52,0) + S52 -> 115156.47 | R52: =ROUND(P52*3%,0) + P52 -> 111896.47 | S52: =S51+0.01 -> 0.47
B53: 5 | C53: D | D53: =D52+1 -> 48 | E53: CANDEL MARCELO | F53: Romina Barbara Lotfi | G53: 0.7552 | H53: 78403.48 | I53: =H53 -> 78403.48 | K53: =H53-I53 -> 0 | L53: =IF(K53>0,K53*3%,0) -> 0 | M53: 0 | N53: =P$2*G53% -> 85917.831 | O53: 0 | P53: =ROUND(SUM(K53:O53),0) + S53 -> 85918.48 | Q53: =ROUND(P53*6% + P53,0) + S53 -> 91074.48 | R53: =ROUND(P53*3%,0) + P53 -> 88496.48 | S53: =S52+0.01 -> 0.48
B54: 5 | C54: E | D54: =D53+1 -> 49 | E54: WAINBERG LUIS | F54: Lionel Giglia | G54: 1.1545 | H54: 119858.49 | I54: =H54 -> 119858.49 | K54: =H54-I54 -> 0 | L54: =IF(K54>0,K54*3%,0) -> 0 | M54: 0 | N54: =P$2*G54% -> 131345.52 | O54: 0 | P54: =ROUND(SUM(K54:O54),0) + S54 -> 131346.49 | Q54: =ROUND(P54*6% + P54,0) + S54 -> 139227.49 | R54: =ROUND(P54*3%,0) + P54 -> 135286.49 | S54: =S53+0.01 -> 0.49
B55: 6 | C55: C | D55: =D54+1 -> 50 | E55: STELLISANO VICTORIA | G55: 0.9549 | H55: 99136.5 | I55: =H55 -> 99136.5 | K55: =H55-I55 -> 0 | L55: =IF(K55>0,K55*3%,0) -> 0 | M55: 0 | N55: =P$2*G55% -> 108637.36 | O55: 0 | P55: =ROUND(SUM(K55:O55),0) + S55 -> 108637.5 | Q55: =ROUND(P55*6% + P55,0) + S55 -> 115156.5 | R55: =ROUND(P55*3%,0) + P55 -> 111896.5 | S55: =S54+0.01 -> 0.5
B56: 6 | C56: D | D56: =D55+1 -> 51 | E56: GEFFNER JORGE RAÚL | G56: 0.7552 | H56: 83223.51 | K56: =H56-I56 -> 83223.51 | L56: =IF(K56>0,K56*3%,0) -> 2496.7053 | M56: 0 | N56: =P$2*G56% -> 85917.831 | O56: 0 | P56: =ROUND(SUM(K56:O56),0) + S56 -> 171638.51 | Q56: =ROUND(P56*6% + P56,0) + S56 -> 181937.51 | R56: =ROUND(P56*3%,0) + P56 -> 176787.51 | S56: =S55+0.01 -> 0.51
B57: 6 | C57: E | D57: =D56+1 -> 52 | E57: REY ALICIA | G57: 1.1545 | H57: 125228.52 | K57: =H57-I57 -> 125228.52 | L57: =IF(K57>0,K57*3%,0) -> 3756.8556 | M57: 0 | N57: =P$2*G57% -> 131345.52 | O57: 0 | P57: =ROUND(SUM(K57:O57),0) + S57 -> 260331.52 | Q57: =ROUND(P57*6% + P57,0) + S57 -> 275951.52 | R57: =ROUND(P57*3%,0) + P57 -> 268141.52 | S57: =S56+0.01 -> 0.52
B58: 7 | C58: C | D58: =D57+1 -> 53 | E58: DE SERIO BOFFA | G58: 0.9549 | H58: 102110.53 | I58: =H58 -> 102110.53 | K58: =H58-I58 -> 0 | L58: =IF(K58>0,K58*3%,0) -> 0 | M58: 0 | N58: =P$2*G58% -> 108637.36 | O58: 0 | P58: =ROUND(SUM(K58:O58),0) + S58 -> 108637.53 | Q58: =ROUND(P58*6% + P58,0) + S58 -> 115156.53 | R58: =ROUND(P58*3%,0) + P58 -> 111896.53 | S58: =S57+0.01 -> 0.53
B59: 7 | C59: D | D59: =D58+1 -> 54 | E59: ALVAREZ EDUARDO | G59: 0.7552 | H59: 78403.54 | I59: =H59 -> 78403.54 | K59: =H59-I59 -> 0 | L59: =IF(K59>0,K59*3%,0) -> 0 | M59: 0 | N59: =P$2*G59% -> 85917.831 | O59: 0 | P59: =ROUND(SUM(K59:O59),0) + S59 -> 85918.54 | Q59: =ROUND(P59*6% + P59,0) + S59 -> 91074.54 | R59: =ROUND(P59*3%,0) + P59 -> 88496.54 | S59: =S58+0.01 -> 0.54
B60: 7 | C60: E | D60: =D59+1 -> 55 | E60: MANDELLI MARIA | F60: Analía | G60: 1.1545 | H60: 369102.55 | K60: =H60-I60 -> 369102.55 | L60: =IF(K60>0,K60*3%,0) -> 11073.076 | M60: 0 | N60: =P$2*G60% -> 131345.52 | O60: 0 | P60: =ROUND(SUM(K60:O60),0) + S60 -> 511521.55 | Q60: =ROUND(P60*6% + P60,0) + S60 -> 542213.55 | R60: =ROUND(P60*3%,0) + P60 -> 526867.55 | S60: =S59+0.01 -> 0.55
B61: 8 | C61: C | D61: =D60+1 -> 56 | E61: BRITEZ M. | F61: Francini IGNACIO | G61: 0.9549 | H61: 99136.56 | I61: 108972.56 | K61: =H61-I61 -> -9836 | L61: =IF(K61>0,K61*3%,0) -> 0 | M61: 0 | N61: =P$2*G61% -> 108637.36 | P61: =ROUND(SUM(K61:O61),0) + S61 -> 98801.56 | Q61: =ROUND(P61*6% + P61,0) + S61 -> 104730.56 | R61: =ROUND(P61*3%,0) + P61 -> 101765.56 | S61: =S60+0.01 -> 0.56
B62: 8 | C62: D | D62: =D61+1 -> 57 | E62: FERREIRO MARTA | F62: Jorge Sicilia | G62: 0.7552 | H62: 78403.57 | I62: =H62 -> 78403.57 | K62: =H62-I62 -> 0 | L62: =IF(K62>0,K62*3%,0) -> 0 | M62: 0 | N62: =P$2*G62% -> 85917.831 | O62: 0 | P62: =ROUND(SUM(K62:O62),0) + S62 -> 85918.57 | Q62: =ROUND(P62*6% + P62,0) + S62 -> 91074.57 | R62: =ROUND(P62*3%,0) + P62 -> 88496.57 | S62: =S61+0.01 -> 0.57
B63: 8 | C63: E | D63: =D62+1 -> 58 | E63: VENTIMIGLIA SILVANA | G63: 1.1545 | H63: 123562.58 | I63: =H63 -> 123562.58 | K63: =H63-I63 -> 0 | L63: =IF(K63>0,K63*3%,0) -> 0 | M63: 0 | N63: =P$2*G63% -> 131345.52 | O63: 0 | P63: =ROUND(SUM(K63:O63),0) + S63 -> 131346.58 | Q63: =ROUND(P63*6% + P63,0) + S63 -> 139227.58 | R63: =ROUND(P63*3%,0) + P63 -> 135286.58 | S63: =S62+0.01 -> 0.58
B64: 9 | C64: C | D64: =D63+1 -> 59 | E64: CIGNOLI | F64: Pablo Coiro | G64: 0.9549 | H64: 99136.59 | I64: =H64 -> 99136.59 | K64: =H64-I64 -> 0 | L64: =IF(K64>0,K64*3%,0) -> 0 | M64: 0 | N64: =P$2*G64% -> 108637.36 | O64: 0 | P64: =ROUND(SUM(K64:O64),0) + S64 -> 108637.59 | Q64: =ROUND(P64*6% + P64,0) + S64 -> 115156.59 | R64: =ROUND(P64*3%,0) + P64 -> 111896.59 | S64: =S63+0.01 -> 0.59
B65: 9 | C65: D | D65: =D64+1 -> 60 | E65: RECHIMUZZI | G65: 0.7552 | H65: 78403.6 | I65: =H65 -> 78403.6 | K65: =H65-I65 -> 0 | L65: =IF(K65>0,K65*3%,0) -> 0 | M65: 0 | N65: =P$2*G65% -> 85917.831 | O65: 0 | P65: =ROUND(SUM(K65:O65),0) + S65 -> 85918.6 | Q65: =ROUND(P65*6% + P65,0) + S65 -> 91074.6 | R65: =ROUND(P65*3%,0) + P65 -> 88496.6 | S65: =S64+0.01 -> 0.6 | U65: ESTA ES WANDA VERON
B66: 9 | C66: E | D66: =D65+1 -> 61 | E66: RIVA MÓNICA | G66: 1.1545 | H66: 119858.61 | I66: =H66 -> 119858.61 | K66: =H66-I66 -> 0 | L66: =IF(K66>0,K66*3%,0) -> 0 | M66: 0 | N66: =P$2*G66% -> 131345.52 | O66: 0 | P66: =ROUND(SUM(K66:O66),0) + S66 -> 131346.61 | Q66: =ROUND(P66*6% + P66,0) + S66 -> 139227.61 | R66: =ROUND(P66*3%,0) + P66 -> 135286.61 | S66: =S65+0.01 -> 0.61 | U66: PUED ETRANSFERIR DESDE GALI NELLY MABEL
B67: 10 | C67: C | D67: =D66+1 -> 62 | E67: GENTILE EDUARDO | F67: Aldana | G67: 0.9549 | H67: 200517.62 | I67: 99136.62 | K67: =H67-I67 -> 101381 | L67: =IF(K67>0,K67*3%,0) -> 3041.43 | M67: 0 | N67: =P$2*G67% -> 108637.36 | O67: 0 | P67: =ROUND(SUM(K67:O67),0) + S67 -> 213060.62 | Q67: =ROUND(P67*6% + P67,0) + S67 -> 225844.62 | R67: =ROUND(P67*3%,0) + P67 -> 219452.62 | S67: =S66+0.01 -> 0.62 | U67: GABRIEL TORRANDELLA
B68: 10 | C68: D | D68: =D67+1 -> 63 | E68: CANDEL MARCELO | F68: Brian Alvarez | G68: 0.7552 | H68: 80755.63 | I68: 78403.63 | K68: =H68-I68 -> 2352 | L68: =IF(K68>0,K68*3%,0) -> 70.56 | M68: 0 | N68: =P$2*G68% -> 85917.831 | O68: 0 | P68: =ROUND(SUM(K68:O68),0) + S68 -> 88340.63 | Q68: =ROUND(P68*6% + P68,0) + S68 -> 93641.63 | R68: =ROUND(P68*3%,0) + P68 -> 90990.63 | S68: =S67+0.01 -> 0.63
B69: 10 | C69: E | D69: =D68+1 -> 64 | E69: CANDEL RAÚL F. | G69: 1.1545 | H69: 119858.64 | I69: =H69 -> 119858.64 | K69: =H69-I69 -> 0 | L69: =IF(K69>0,K69*3%,0) -> 0 | M69: 0 | N69: =P$2*G69% -> 131345.52 | O69: 0 | P69: =ROUND(SUM(K69:O69),0) + S69 -> 131346.64 | Q69: =ROUND(P69*6% + P69,0) + S69 -> 139227.64 | R69: =ROUND(P69*3%,0) + P69 -> 135286.64 | S69: =S68+0.01 -> 0.64
B70: 11 | C70: C | D70: =D69+1 -> 65 | E70: LORUSSO DORA | G70: 0.9549 | H70: 99136.65 | I70: =H70 -> 99136.65 | K70: =H70-I70 -> 0 | L70: =IF(K70>0,K70*3%,0) -> 0 | M70: 0 | N70: =P$2*G70% -> 108637.36 | O70: 0 | P70: =ROUND(SUM(K70:O70),0) + S70 -> 108637.65 | Q70: =ROUND(P70*6% + P70,0) + S70 -> 115156.65 | R70: =ROUND(P70*3%,0) + P70 -> 111896.65 | S70: =S69+0.01 -> 0.65
B71: 11 | C71: D | D71: =D70+1 -> 66 | E71: FERÁNDEZ HÉCTOR | F71: Melina Navarro | G71: 0.7552 | H71: 83244.66 | I71: =H71 -> 83244.66 | K71: =H71-I71 -> 0 | L71: =IF(K71>0,K71*3%,0) -> 0 | M71: 0 | N71: =P$2*G71% -> 85917.831 | O71: 0 | P71: =ROUND(SUM(K71:O71),0) + S71 -> 85918.66 | Q71: =ROUND(P71*6% + P71,0) + S71 -> 91074.66 | R71: =ROUND(P71*3%,0) + P71 -> 88496.66 | S71: =S70+0.01 -> 0.66
B72: 11 | C72: E | D72: =D71+1 -> 67 | E72: KARGODORIAN SILVIA | G72: 1.1545 | H72: 262505.67 | K72: =H72-I72 -> 262505.67 | L72: =IF(K72>0,K72*3%,0) -> 7875.1701 | M72: 0 | N72: =P$2*G72% -> 131345.52 | O72: 0 | P72: =ROUND(SUM(K72:O72),0) + S72 -> 401726.67 | Q72: =ROUND(P72*6% + P72,0) + S72 -> 425830.67 | R72: =ROUND(P72*3%,0) + P72 -> 413778.67 | S72: =S71+0.01 -> 0.67
B73: 12 | C73: C | D73: =D72+1 -> 68 | E73: ALVAREZ | G73: 0.9549 | H73: 99136.68 | I73: =H73 -> 99136.68 | K73: =H73-I73 -> 0 | L73: =IF(K73>0,K73*3%,0) -> 0 | M73: 0 | N73: =P$2*G73% -> 108637.36 | O73: 0 | P73: =ROUND(SUM(K73:O73),0) + S73 -> 108637.68 | Q73: =ROUND(P73*6% + P73,0) + S73 -> 115156.68 | R73: =ROUND(P73*3%,0) + P73 -> 111896.68 | S73: =S72+0.01 -> 0.68
B74: 12 | C74: D | D74: =D73+1 -> 69 | E74: RIVA MÓNICA | G74: 0.7552 | H74: 78403.69 | I74: =H74 -> 78403.69 | K74: =H74-I74 -> 0 | L74: =IF(K74>0,K74*3%,0) -> 0 | M74: 0 | N74: =P$2*G74% -> 85917.831 | O74: 0 | P74: =ROUND(SUM(K74:O74),0) + S74 -> 85918.69 | Q74: =ROUND(P74*6% + P74,0) + S74 -> 91074.69 | R74: =ROUND(P74*3%,0) + P74 -> 88496.69 | S74: =S73+0.01 -> 0.69
B75: 12 | C75: E | D75: =D74+1 -> 70 | E75: DE BIAGGIO PABLO | G75: 1.1549 | H75: 79899.7 | I75: =79899.7 -> 79899.7 | K75: =H75-I75 -> 0 | L75: =IF(K75>0,K75*3%,0) -> 0 | M75: 0 | N75: =P$2*G75% -> 131391.03 | O75: 0 | P75: =ROUND(SUM(K75:O75),0) + S75 -> 131391.7 | Q75: =ROUND(P75*6% + P75,0) + S75 -> 139275.7 | R75: =ROUND(P75*3%,0) + P75 -> 135333.7 | S75: =S74+0.01 -> 0.7
H76: 0
G81: =SUM(G6:G80) -> 100 | H81: =SUM(H6:H80) -> 13622880 | I81: =SUM(I6:I80) -> 9620855.2 | J81: =SUM(J6:J80) -> 0 | K81: =SUM(K6:K80) -> 4002024.7 | L81: =SUM(L6:L80) -> 125085.7 | M81: =SUM(M6:M80) -> 0 | N81: =SUM(N6:N80) -> 11376831 | ... R81: =SUM(R6:R80) -> 15969080
E84: =RESUMEN!A14 -> ESTIMADOS PROPIETARIOS E INQUILINOS: POR FAVOR LOS QUE ABONAN EN PRIMER VENCIMIENTO ABONEN EL MONTO DE PRIMER VENCIMIENTO, ASI AGILIZAN LA LIQUIDACION, RESPETEN LOS CENTAVOS CORRESPONDIENTES A LA UNIDAD FUNCIONAL. ES DE CARÁCTER OBLIGATORIO INFORMAR VIA MAIL LAS EXPENSAS. CASO CONTRARIO SE INFORMARA VIA CARTA DOCUMENTO A LA UNIDAD FUNCIONAL QUE CREEMOS QUE CORRESPONDE, CUYO COSTO SERA IMPUTADO A LA UNIDAD FUNCIONAL SOSPECHADA.
