Workbook

Sheet detalle y gastos
B2: CANCIANI, Carolina | C2: MP 1148
B3: Tel. 11 5320-2676
B4: consorciosrc13@gmail.com
A7: LIQUIDACIÓN EXPENSAS ENERO 2026
A10: Teléfonos útiles
A11: EDESUR 0800-333-3787
A12: AySA 0800-321-2482
A13: Metrogas 0800-333-6427
A15: GASTOS ORDINARIOS
A16: ABONOS y SERVICIOS
A17: AYSA - DICIEMBRE | B17: Pago efectivo | C17: 35799
C18: =SUM(C17:C17) -> 35799
A19: LIMPIEZA / MANTENIMIENTO / GASTOS GENERALES
A20: Honorarios Administracion | C20: 37000
A21: Poliza de Seguro Obligatoria Mercantil andina N. 1181593 | C21: 36534.6
A22: Prevision ordinaria
C23: =SUM(C19:C22) -> 73534.6
A24: TOTAL GASTOS ORDINARIOS (A) - SIN CONTAR EDESUR | C24: =+C23+C18 -> 109333.6
A26: GASTOS EXTRAORDINARIOS
A31: TOTAL GASTOS EXTRAORDINARIOS (B) | C31: =+C27+C28+C29+C30 -> 0
A33: TOTAL GENERAL DE GASTOS (A) + (B) | C33: =+C31+C24 -> 109333.6
A35: ESTADO FINACIERO
A36: Saldo anterior | C36: -782106.08
A37: Ingreso por pago de expensas en término | C37: ='prorrateo '!F15 -> 1216661.5
A38: Ingresos que no corresponden al periodo liquidado | C38: -761194
A39: Edesur - DICIEMBRE | C39: =-(281988.92-122970.95) -> -159017.97
A40: Egresos por gastos del mes ordinarios | C40: =-C24 -> -109333.6
A41: Saldo al cierre $ (pesos) | C41: =SUM(C36:C40) -> -594990.17
A43: ='prorrateo '!A16:L16 -> Atención: se han reliquidado todas las deudas correspondientes a cada unidad funcional, dejando reflejados los saldos reales de cada una. A partir de este mes se aplicarán intereses a quienes no abonen las expensas en tiempo y forma. La columna Ingresos registra pagos efectuados tanto durante el mes de enero como en meses anteriores. Por este motivo, en la caja general se han descontado aquellos pagos que no corresponden al período liquidado, a fin de evitar su doble contabilización, ya que los mismos fueron imputados oportunamente en expensas anteriores. Del mismo modo, los saldos anteriores incluyen montos correspondientes a expensas adeudadas no solo del mes de diciembre, sino también de meses posteriores.
A53: CAJA EXTRAORDINARIA | C53: 0
A54: Egreso extraordinario | C54: =-C31 -> 0
A57: TOTAL | C57: =SUM(C53:C56) -> 0

Sheet prorrateo 
A1: EXPENSAS ORDINARIAS | E1: 109333.6 | H1: EDESUR: | J1: 159017.97
A2: ='detalle y gastos'!B7 -> 0
A3: Dpto. | C3: Propietario | D3: Inquilinos | E3: Saldo | F3: Pagos | G3: DEUDA | H3: Intereses | I3: % | J3: Expensas ord. | K3: EDESUR | L3: TOTAL
E4: Anterior | F4: Exp. Ord. | L4: EXPENSAS
A5: 1 | C5: Gomez Elizabeth | E5: 46673.998 | F5: =E5 -> 46673.998 | G5: =E5-F5 -> 0 | H5: =IF(G5>0,G5*6%,0) -> 0 | I5: 13.8 | J5: =E$1*I5/100 -> 15088.037 | K5: =edesur!H5 -> 9493.6101 | L5: =G5+H5+J5+K5 -> 24581.647
A6: 2 | C6: Maceyle Gabriela | E6: 93174.075 | G6: =E6-F6 -> 93174.075 | H6: =IF(G6>0,G6*6%,0) -> 5590.4445 | I6: 11.86 | J6: =E$1*I6/100 -> 12966.965 | K6: =edesur!H6 -> 46518.69 | L6: =G6+H6+J6+K6 -> 158250.17
A7: 3 | C7: Maceyle Gabriela | D7: Pereyra Amanda | E7: =404493.75+44569.42 -> 449063.17 | F7: =120000+50000+114600 -> 284600 | G7: =E7-F7 -> 164463.17 | H7: =IF(G7>0,G7*6%,0) -> 9867.7902 | I7: 12.46 | J7: =E$1*I7/100 -> 13622.967 | K7: =edesur!H7 -> 46044.009 | L7: =G7+H7+J7+K7 -> 233997.94
A8: 4 | C8: Castelao Lorena | D8: Elida | E8: =410990.58+104559.2 -> 515549.78 | F8: =128678+49000+128000 -> 305678 | G8: =E8-F8 -> 209871.78 | H8: =IF(G8>0,G8*6%,0) -> 12592.307 | I8: 14.75 | J8: =E$1*I8/100 -> 16126.706 | K8: =edesur!H8 -> 9493.6101 | L8: =G8+H8+J8+K8 -> 248084.4
A9: 5 | C9: Grand Jorge | D9: Enciso Marisa | E9: =65135.91+199803.65 -> 264939.56 | F9: =145436.21+54367.43+65136 -> 264939.64 | G9: =E9-F9 -> -0.08 | H9: =IF(G9>0,G9*6%,0) -> 0 | I9: 12.41 | J9: =E$1*I9/100 -> 13568.3 | K9: =edesur!H9 -> 28480.83 | L9: =G9+H9+J9+K9 -> 42049.05
A10: 6 | C10: Valdez Norberto | E10: =44600+399309.33 -> 443909.33 | F10: =4150+26423+54675+85000+44601-F14 -> 169324.31 | G10: =E10-F10 -> 274585.02 | H10: =IF(G10>0,G10*6%,0) -> 16475.101 | I10: 12.48 | J10: =E$1*I10/100 -> 13644.833 | K10: =edesur!H10 -> 9493.6101 | L10: =G10+H10+J10+K10 -> 314198.56
A11: 7 | C11: Lean Cosenza | E11: 53678.783 | F11: =E11 -> 53678.783 | G11: =E11-F11 -> 0 | H11: =IF(G11>0,G11*6%,0) -> 0 | I11: 18.26 | J11: =E$1*I11/100 -> 19964.315 | K11: =edesur!H11 -> 9493.6101 | L11: =G11+H11+J11+K11 -> 29457.926
A12: COCH A | C12: =C9 -> Grand Jorge | D12: Enciso Marisa | E12: =44137.05+2104.58 -> 46241.63 | F12: =44137.05+2105 -> 46242.05 | G12: =E12-F12 -> -0.42 | H12: =IF(G12>0,G12*6%,0) -> 0 | I12: 1.34 | J12: =E$1*I12/100 -> 1465.0702 | L12: =G12+H12+J12+K12 -> 1464.6502
A13: COCH B | C13: =C6 -> Maceyle Gabriela | E13: 41426.1 | G13: =E13-F13 -> 41426.1 | H13: =IF(G13>0,G13*6%,0) -> 2485.566 | I13: 1.32 | J13: =E$1*I13/100 -> 1443.2035 | L13: =G13+H13+J13+K13 -> 45354.87
A14: COCH C | C14: =C6 -> Maceyle Gabriela | D14: Norberto | E14: =43451.53+2073.16 -> 45524.69 | F14: =E14 -> 45524.69 | G14: =E14-F14 -> 0 | H14: =IF(G14>0,G14*6%,0) -> 0 | I14: 1.32 | J14: =E$1*I14/100 -> 1443.2035 | L14: =G14+H14+J14+K14 -> 1443.2035
A15: TOTALES | E15: =SUM(E5:E14) -> 2000181.1 | F15: =SUM(F5:F14) -> 1216661.5 | H15: =SUM(H5:H14) -> 47011.209 | I15: =SUM(I5:I14) -> 100 | J15: =SUM(J5:J14) -> 109333.6 | K15: =SUM(K5:K11) -> 159017.97 | L15: =SUM(L5:L14) -> 1098882.4
A16: Atención: se han reliquidado todas las deudas correspondientes a cada unidad funcional, dejando reflejados los saldos reales de cada una. A partir de este mes se aplicarán intereses a quienes no abonen las expensas en tiempo y forma. La columna Ingresos registra pagos efectuados tanto durante el mes de enero como en meses anteriores. Por este motivo, en la caja general se han descontado aquellos pagos que no corresponden al período liquidado, a fin de evitar su doble contabilización, ya que los mismos fueron imputados oportunamente en expensas anteriores. Del mismo modo, los saldos anteriores incluyen montos correspondientes a expensas adeudadas no solo del mes de diciembre, sino también de meses posteriores.

Sheet edesur
B1: PATXOT | C1: ENERO 2025 | F1: EDESUR | G1: BOLETA | H1: 159017.97
B3: UNIDAD | C3: MEDIDOR | D3: MEDIDOR | E3: CONSUMO | F3: PORCENTAJE | G3: BOLETA TOTAL | H3: TOTAL A ABONAR
C4: ANTERIOR | D4: ACTUAL | H4: =H1 -> 159017.97
A5: GOMEZ | B5: 1 | C5: 7817 | D5: =C5+20 -> 7837 | E5: =D5-C5 -> 20 | F5: =E5*100/D14 -> 5.9701493 | H5: =H4*(F5/100) -> 9493.6101
A6: CARA | B6: 2 | C6: 7174 | D6: =C6+98 -> 7272 | E6: =D6-C6 -> 98 | F6: =E6*100/D14 -> 29.253731 | H6: =H4*(F6/100) -> 46518.69
A7: PEREYRA | B7: 3 | C7: 7791 | D7: =C7+97 -> 7888 | E7: =D7-C7 -> 97 | F7: =E7*100/D14 -> 28.955224 | H7: =H4*(F7/100) -> 46044.009
A8: MARTINEZ | B8: 4 | C8: 9369 | D8: =C8+20 -> 9389 | E8: =D8-C8 -> 20 | F8: =E8*100/D14 -> 5.9701493 | H8: =H4*(F8/100) -> 9493.6101
A9: ENCISO ROTELA | B9: 5 | C9: 10695 | D9: =C9+60 -> 10755 | E9: =D9-C9 -> 60 | F9: =E9*100/D14 -> 17.910448 | H9: =H4*(F9/100) -> 28480.83
A10: VALDEZ | B10: 6 | C10: 10767 | D10: =C10+20 -> 10787 | E10: =D10-C10 -> 20 | F10: =E10*100/D14 -> 5.9701493 | H10: =H4*(F10/100) -> 9493.6101
A11: COSENZA | B11: 7 | C11: 13240 | D11: =C11+20 -> 13260 | E11: =D11-C11 -> 20 | F11: =E11*100/D14 -> 5.9701493 | H11: =H4*(F11/100) -> 9493.6101
C12: =SUM(C5:C11) -> 66853 | D12: =SUM(D5:D11) -> 67188 | E12: =SUM(E5:E11) -> 335 | F12: =SUM(F5:F11) -> 100 | H12: =SUM(H5:H11) -> 159017.97
B14: CONSUMO TOTAL KW | D14: =D12-C12 -> 335
B15: EDIFICIO
E20: EN TOTAL LOS DEPARTAMENTOS USARON | H20: =D14 -> 335 | K20: KW
D21: DEPARTAMENTO | E21: 7 | F21: CONSUMIO | G21: 197 | H21: KW | K21: EL 14,96% DE TOTAL CONSUMIDO
K25: NOVIEMBRE 2024
I27: ELECTRICIDAD | J27: EXPENSAS | K27: TOTAL
H28: VALDEZ | I28: 29829 | J28: 16000 | K28: =I28+J28 -> 45829
J31: saldo OCTUBRE 24 | K31: 117067
J32: ABONASTE OCTUBRE 24 | K32: -55000
J33: NOVIEMBRE 24 | K33: 43965
K34: =SUM(K31:K33) -> 106032
