Workbook

Sheet RESUMEN
C1: MAIL: elmiradorconsorcios@gmail.com
C2: CUIT ADMINISTRACION: 27231256879
C3: CBU: 0720039720000002171436 | E3: TELEFONO: 11 5320-2676
C4: ADMINISTRADORA: CAROLINA CANCIANI MP:1148
C5: PERÍODO: SEPTIEMBRE | E5: HORARIOS DE ATENCION: LUNES A VIERNES - 10 A 15HS - EMERGENCIAS 24HS
C6: LIQUIDACION DE EXPENSAS
A14: Importante para dueños o inquilinos de departamentos o coheras: Queremos recordarles una cuestión importante respecto a los pagos de expensas que ayuda a evitar errores en la imputación de los mismos. El sistema que utilizamos asigna centavos únicos a cada Unidad Funcional (UF), lo cual nos permite identificar automáticamente a qué unidad corresponde cada transferencia. Es decir, cada UF tiene un número específico de centavos que actúa como "identificador". Por ejemplo, si tu UF es la 45, el importe a abonar debería terminar en $...,45. Si tenés más de una unidad (por ejemplo, un departamento y una cochera), cada una tiene su propio código de centavos. En esos casos, te pedimos por favor que realices una transferencia por cada UF, respetando el importe con sus centavos correspondientes. Sabemos que a veces por comodidad se suele enviar todo junto en una sola transferencia, pero esto puede generar confusión o errores en la imputación automática. Realizar los pagos por separado nos permite asegurar que cada importe se asigne correctamente. Agradecemos muchísimo la colaboración para seguir manteniendo todo ordenado. Saludos cordiales.
A20: VTO 16/10
A24: GASTOS ORDINARIOS UNIDADES FUNCIONALES: | E24: UF 93,20% | F24: LOCAL 1 (1,08%) | G24: LOCAL 2 (1,28%) | H24: LOCAL 3 (1,21%) | I24: LOCAL 4 (1,49%) | J24: LOCAL 5 (1,74%)
A25: Salvati - Servicios de limpieza
A26: Servicio de limpieza | B26: SE ADEUDA SEPTIEMBRE | C26: Transf 09/09 | D26: 2966292
A27: Sr. Piletero 12/09 | C27: Transf 25/09 | D27: 120000
A28: TOTAL | D28: =SUM(D25:D27) -> 3086292 | E28: =D28*93.2% -> 2876424.1 | F28: =$D28*1.08% -> 33331.954 | G28: =$D28*1.28% -> 39504.538 | H28: =$D28*1.21% -> 37344.133 | I28: =$D28*1.49% -> 45985.751 | J28: =D28*1.74% -> 53701.481 | K28: =E28+J28+F28+G28+H28+I28 -> 3086292 | L28: =IF(D28=K28, "", "Error")
A29: COMBUSTIBLE PARA GRUPO ELECTROGENO
A31: TOTAL | D31: =SUM(D30:D30) -> 0 | E31: =D31 -> 0 | K31: =E31+J31+F31+G31+H31+I31 -> 0 | L31: =IF(D31=K31, "", "Error")
A32: IMPUESTOS
A33: TSG - Partida 197227000 | B33: Mes 9 | C33: Transf 07/09 | D33: 1916441
A34: TSG - Partida 197229000 | B34: Mes 9 | C34: Transf 07/09 | D34: 1916441
A35: TSG - Partida 197227000 | B35: Mes 8 | C35: Transf 11/09 | D35: =3791724/2 -> 1895862
A36: TSG - Partida 197229000 | B36: Mes 8 | C36: Transf 11/09 | D36: =3791724/2 -> 1895862
A38: TOTAL IMPUESTOS | D38: =SUM(D33:D37) -> 7624606 | E38: =D38*93.2% -> 7106132.8 | F38: =$D38*1.08% -> 82345.745 | G38: =$D38*1.28% -> 97594.957 | H38: =$D38*1.21% -> 92257.733 | I38: =$D38*1.49% -> 113606.63 | J38: =D38*1.74% -> 132668.14 | K38: =E38+J38+F38+G38+H38+I38 -> 7624606 | L38: =IF(D38=K38, "", "Error")
A39: APORTES Y CONTRIBUCIONES
A41: TOTAL APORTES Y CONTRIBUCIONES | D41: =SUM(D39:D40) -> 0 | E41: =D41*93.2% -> 0 | F41: =$D41*1.08% -> 0 | G41: =$D41*1.28% -> 0 | H41: =$D41*1.21% -> 0 | I41: =$D41*1.49% -> 0 | J41: =D41*1.74% -> 0 | K41: =E41+J41+F41+G41+H41+I41 -> 0 | L41: =IF(D41=K41, "", "Error")
A42: SEGUROS
A43: Federacion patronal - Poliza integral para consorcios nro. 2152393 | C43: Debito autom. | D43: 214371 | E43: =D43*93.2% -> 199793.77 | F43: =$D43*1.08% -> 2315.2068 | G43: =$D43*1.28% -> 2743.9488 | H43: =$D43*1.21% -> 2593.8891 | I43: =$D43*1.49% -> 3194.1279 | J43: =D43*1.74% -> 3730.0554 | K43: =SUM(E43:J43) -> 214371
A45: TOTAL Aportes y Contribuciones - Sindicato | D45: =SUM(D43:D44) -> 214371 | E45: =SUM(E43:E44) -> 199793.77 | F45: =SUM(F43:F44) -> 2315.2068 | G45: =SUM(G43:G44) -> 2743.9488 | H45: =SUM(H43:H44) -> 2593.8891 | I45: =SUM(I43:I44) -> 3194.1279 | J45: =SUM(J43:J44) -> 3730.0554 | K45: =E45+J45+F45+G45+H45+I45 -> 214371 | L45: =IF(D45=K45, "", "Error")
A46: ABONOS Y SERVICIOS
A47: Aysa - Cuenta 2490112 | C47: Transf 16/09 | D47: 2645102.9 | E47: =D47*93.2% -> 2465235.9 | F47: =$D47*1.08% -> 28567.111 | G47: =$D47*1.28% -> 33857.317 | H47: =$D47*1.21% -> 32005.745 | I47: =$D47*1.49% -> 39412.033 | J47: =D47*1.74% -> 46024.79 | K47: =D47 -> 2645102.9 | L47: =SUM(E47:J47) -> 2645102.9
A48: Edesur - Cliente 01291636 | C48: Transf 15/09 | D48: 7010415.1 | E48: =D48*93.2% -> 6533706.9 | F48: =$D48*1.08% -> 75712.483 | G48: =$D48*1.28% -> 89733.313 | H48: =$D48*1.21% -> 84826.023 | I48: =$D48*1.49% -> 104455.18 | J48: =D48*1.74% -> 121981.22 | K48: =D48 -> 7010415.1 | L48: =E48+J48+I48+H48+G48+F48 -> 7010415.1
A49: Telecentro - Zona coworking - Cliente 7725479 | C49: Debito 17/09 | D49: 176275.21 | E49: =D49 -> 176275.21 | K49: =D49 -> 176275.21 | L49: =E49+J49+I49+H49+G49+F49 -> 176275.21 | M49: =L49-D49 -> 0 | N49: =K49-D49 -> 0
A50: ADS - Abono de mantenimiento ascensores SEPTIEMBRE | C50: Transf 16/09 | D50: 427893 | E50: =D50 -> 427893 | K50: =D50 -> 427893 | L50: =E50+J50+I50+H50+G50+F50 -> 427893
A51: Victor Martinez - Abono mantenimiento control de accesos - AGOSTO | C51: Transf 11/09 | D51: 55000 | E51: =D51 -> 55000 | K51: =D51 -> 55000 | L51: =E51+J51+I51+H51+G51+F51 -> 55000 | M51: =L51-D51 -> 0 | N51: =K51-D51 -> 0
A52: Metrogas - Cliente nro. 40000496339 | C52: Transf 09/09 | D52: 8144.29 | E52: =D52 -> 8144.29 | K52: =D52 -> 8144.29 | L52: =E52+J52+I52+H52+G52+F52 -> 8144.29
A53: Metrogas - Cliente nro. 40000497007 | C53: Transf 09/09 | D53: 1751133.8 | E53: =D53*93.2% -> 1632056.7 | F53: =$D53*1.08% -> 18912.245 | G53: =$D53*1.28% -> 22414.513 | H53: =$D53*1.21% -> 21188.719 | I53: =$D53*1.49% -> 26091.894 | J53: =D53*1.74% -> 30469.729 | K53: =D53 -> 1751133.8 | L53: =E53+J53+I53+H53+G53+F53 -> 1751133.8 | M53: =L53-D53 -> 0 | N53: =K53-D53 -> 0
A54: Loschi Mantenimiento grupo electrogeno - Abono bimestral | C54: Transf 30/09 | D54: 120000 | E54: =D54 -> 120000 | K54: =D54 -> 120000 | L54: =E54+J54+I54+H54+G54+F54 -> 120000 | M54: =L54-D54 -> 0 | N54: =K54-D54 -> 0
A55: TOTAL ABONOS Y SERVICIOS | D55: =SUM(D47:D54) -> 12193964 | E55: =SUM(E47:E54) -> 11418312 | F55: =SUM(F47:F54) -> 123191.84 | G55: =SUM(G47:G54) -> 146005.14 | H55: =SUM(H47:H54) -> 138020.49 | I55: =SUM(I47:I54) -> 169959.11 | J55: =SUM(J47:J54) -> 198475.74 | K55: =E55+J55+F55+G55+H55+I55 -> 12193964 | L55: =IF(D55=K55, "", "Error") | M55: =D55-K55 -> 0
A58: GASTOS VARIOS
A59: Fumigacion - Silva Nicolas | C59: Transf 28/09 | D59: 230000 | E59: =D59 -> 230000 | K59: =D59 -> 230000 | L59: =SUM(E59:J59) -> 230000
A60: Fidiax Argentina - Redaccion, gestion y envio carta documento Aysa | C60: Transf 07/09 | D60: 130000 | E60: =D60*93.2% -> 121160 | F60: =$D60*1.08% -> 1404 | G60: =$D60*1.28% -> 1664 | H60: =$D60*1.21% -> 1573 | I60: =$D60*1.49% -> 1937 | J60: =D60*1.74% -> 2262 | K60: =D60 -> 130000 | L60: =SUM(E60:J60) -> 130000
A61: Rosales Dario - Herrero : Fc. 00000325 - Realizacion de tapas nodo gas | C61: Transf 18/09 - 30/09 | D61: 1379400 | E61: =D61*93.2% -> 1285600.8 | F61: =$D61*1.08% -> 14897.52 | G61: =$D61*1.28% -> 17656.32 | H61: =$D61*1.21% -> 16690.74 | I61: =$D61*1.49% -> 20553.06 | J61: =D61*1.74% -> 24001.56 | K61: =D61 -> 1379400 | L61: =SUM(E61:J61) -> 1379400
A62: Locos por la limpieza - Articulos de limpieza | C62: Transf 30/09 | D62: 516621.6 | E62: =D62*93.2% -> 481491.33 | F62: =$D62*1.08% -> 5579.5133 | G62: =$D62*1.28% -> 6612.7565 | H62: =$D62*1.21% -> 6251.1214 | I62: =$D62*1.49% -> 7697.6618 | J62: =D62*1.74% -> 8989.2158 | K62: =D62 -> 516621.6 | L62: =SUM(E62:J62) -> 516621.6
A63: Locos por la limpieza - Articulos de limpieza | C63: Transf 09/09 | D63: 373188.2 | E63: =D63*93.2% -> 347811.4 | F63: =$D63*1.08% -> 4030.4326 | G63: =$D63*1.28% -> 4776.809 | H63: =$D63*1.21% -> 4515.5772 | I63: =$D63*1.49% -> 5560.5042 | J63: =D63*1.74% -> 6493.4747 | K63: =D63 -> 373188.2 | L63: =SUM(E63:J63) -> 373188.2
A64: TOTAL GASTOS VARIOS | D64: =SUM(D59:D63) -> 2629209.8 | E64: =SUM(E59:E63) -> 2466063.5 | F64: =SUM(F59:F63) -> 25911.466 | G64: =SUM(G59:G63) -> 30709.885 | H64: =SUM(H59:H63) -> 29030.439 | I64: =SUM(I59:I63) -> 35748.226 | J64: =SUM(J59:J63) -> 41746.251 | K64: =E64+J64+F64+G64+H64+I64 -> 2629209.8 | L64: =IF(D64=K64, "", "Error")
A65: GASTOS DE ADMINISTRACION
A66: RC Adm Cons. CANCIANI, Carolina - MP:1148 - AGOSTO - SE ADEUDA SEPTIEMBRE | C66: Transf 10/09 | D66: 949849 | E66: =D66*93.2% -> 885259.27 | F66: =$D66*1.08% -> 10258.369 | G66: =$D66*1.28% -> 12158.067 | H66: =$D66*1.21% -> 11493.173 | I66: =$D66*1.49% -> 14152.75 | J66: =D66*1.74% -> 16527.373 | L66: En Jul1o deben subir a 949.849,3 + $99.000 de escaneo de documentacio
A67: RPAC: Escaneo mensual sobre toda la documentación que incluyen las expensas - Mes de AGOSTO - SE ADEUDA SEPTIEMBRE | C67: Transf 30/09 | D67: 103000 | E67: =D67*93.2% -> 95996 | F67: =$D67*1.08% -> 1112.4 | G67: =$D67*1.28% -> 1318.4 | H67: =$D67*1.21% -> 1246.3 | I67: =$D67*1.49% -> 1534.7 | J67: =D67*1.74% -> 1792.2
A69: TOTAL GASTOS DE ADMINISTRACION | D69: =SUM(D66:D68) -> 1052849 | E69: =SUM(E66:E68) -> 981255.27 | F69: =SUM(F66:F68) -> 11370.769 | G69: =SUM(G66:G68) -> 13476.467 | H69: =SUM(H66:H68) -> 12739.473 | I69: =SUM(I66:I68) -> 15687.45 | J69: =SUM(J66:J68) -> 18319.573 | K69: =E69+J69+F69+G69+H69+I69 -> 1052849 | L69: =IF(D69=K69, "", "Error")
A70: Gastos bancarios | D70: 69000 | E70: =D70*93.2% -> 64308 | F70: =$D70*1.08% -> 745.2 | G70: =$D70*1.28% -> 883.2 | H70: =$D70*1.21% -> 834.9 | I70: =$D70*1.49% -> 1028.1 | J70: =D70*1.74% -> 1200.6
A71: Mantenimiento de cuenta | D71: 621677.73 | E71: =D71*93.2% -> 579403.64 | F71: =$D71*1.08% -> 6714.1195 | G71: =$D71*1.28% -> 7957.4749 | H71: =$D71*1.21% -> 7522.3005 | I71: =$D71*1.49% -> 9262.9982 | J71: =D71*1.74% -> 10817.193
A72: TOTAL GASTOS BANCARIOS | D72: =SUM(D70:D71) -> 690677.73 | E72: =SUM(E70:E71) -> 643711.64 | F72: =SUM(F70:F71) -> 7459.3195 | G72: =SUM(G70:G71) -> 8840.6749 | H72: =SUM(H70:H71) -> 8357.2005 | I72: =SUM(I70:I71) -> 10291.098 | J72: =SUM(J70:J71) -> 12017.793 | K72: =E72+J72+F72+G72+H72+I72 -> 690677.73 | L72: =IF(D72=K72, "", "Error")
A74: RECUPERO DE PREVISION - OBRA REPOSICION TAPA DE GAS HURTADA | D74: =-D61 -> -1379400 | E74: =D74*93.2% -> -1285600.8 | F74: =$D74*1.08% -> -14897.52 | G74: =$D74*1.28% -> -17656.32 | H74: =$D74*1.21% -> -16690.74 | I74: =$D74*1.49% -> -20553.06 | J74: =D74*1.74% -> -24001.56 | K74: =E74+J74+F74+G74+H74+I74 -> -1379400 | L74: =IF(D74=K74, "", "Error")
A76: TOTAL ORDINARIOS | D76: =SUM(D74+D38+D31+D72+D69+D64+D55+D45+D28++D41) -> 26112570 | E76: =SUM(E74+E38+E31+E72+E69+E64+E55+E45+E28++E41) -> 24406092 | F76: =SUM(F74+F38+F31+F72+F69+F64+F55+F45+F28++F41) -> 271028.78 | G76: =SUM(G74+G38+G31+G72+G69+G64+G55+G45+G28++G41) -> 321219.29 | H76: =SUM(H74+H38+H31+H72+H69+H64+H55+H45+H28++H41) -> 303652.61 | I76: =SUM(I74+I38+I31+I72+I69+I64+I55+I45+I28++I41) -> 373919.33 | J76: =SUM(J74+J38+J31+J72+J69+J64+J55+J45+J28++J41) -> 436657.48 | K76: =E76+J76+F76+G76+H76+I76 -> 26112570 | L76: =K76-D38 -> 18487964 | M76: =D76-K76 -> 0
A78: Gastos particulares
A81: TOTAL | C81: =SUM(C79:C80) -> 0
A84: GASTOS EXTRAORDINARIOS | E84: UF | F84: LOCAL 1 (1,08%) | G84: LOCAL 2 (1,28%) | H84: LOCAL 3 (1,21%) | I84: LOCAL 4 (1,49%) | J84: LOCAL 5 (1,74%)
E85: =D85 -> 0
A87: TOTAL | D87: =SUM(D85:D86) -> 0 | E87: =SUM(E85:E86) -> 0 | J87: =SUM(J85:J86) -> 0 | L87: =E87+J87 -> 0 | M87: =IF(D87=L87, "", "Error")
A90: GASTOS ORDINARIOS + PREVISION : | B90: =D76 -> 26112570
A91: GASTOS ORDINARIOS SIN PREVISION: | B91: =D76-D74 -> 27491970 | D91: Se recuerda a todos los propietarios que, en caso de producirse la venta o transferencia de una unidad funcional, es obligatorio informar a la Administración los datos de los nuevos titulares. Dicha notificación resulta indispensable para actualizar los registros del consorcio, emitir correctamente las expensas y garantizar que toda comunicación formal llegue a quienes correspondan. La información a presentar deberá incluir al menos: * Nombre y apellido de los nuevos propietarios. * Domicilio de contacto (en caso de ser distinto de la unidad funcional). * Correo electrónico y/o teléfono de contacto. * Copia de la escritura, acta notarial o documentación que acredite la transferencia. Hasta tanto no se reciba la notificación formal, toda comunicación y responsabilidad respecto de la unidad seguirá dirigida al propietario anterior.
A94: CAJA BANCARIA $ (pesos)
A95: Saldo anterior | B95: 2575051.8
A96: Ingresos | B96: =PRORRATEO!H134 -> 31902350
A97: Ingreso por pago de ARBA | B97: =ARBA!L82 -> 34752
A98: Egresos Ordinarios | B98: =-B91 -> -27491970
A99: Egresos Extraordinarios | B99: =-D87 -> 0
A100: ARBA inmobiliario - Partida Nro. 024-171499-1 | B100: -209759.2
A101: Dinero sin identificar | B101: =B108 -> 0
A102: Dinero ingreso SUM | B102: =-B120 -> 0
A103: Gastos particulares | B103: =-C81 -> 0
A104: Saldo al cierre | B104: =SUM(B95:B103) -> 6810425.1
A106: TRANSFERENCIAS SIN IDENTIFICAR
B107: 0
A108: TOTAL | B108: =SUM(B106:B107) -> 0
A111: CAJA EFECTIVO $ (pesos) | B111: -73817.72 | D111: LA CAJA EN EFECTIVO SE ELIMINARA - LOS $97.817,72 QUE SE ADEUDAN A LA ADMINISTRACION SE RECUPERARAN MEDIANTE TRANSFERENCIA
A112: Envio carta documento correo Argentino - AYSA | B112: -24000
A113: Grafica Tauge - Fotocopias BYN | B113: -1500
A114: TOTAL | B114: =SUM(B111:B112) -> -97817.72
A119: CAJA SUM $ (pesos) | B119: 598840 | D119: Se adeudan a la desarrolladora las cuotas correspondientes a ARBA, debido a la falta de disponibilidad de fondos, la desarrolladora aceptó diferir el cobro de dichos importes para permitir que el consorcio pudiera afrontar gastos de carácter obligatorio e indispensables para su normal funcionamiento
A120: Ingreso | B120: 0
A121: TOTAL | B121: =SUM(B119:B120) -> 598840
A123: Caja Real -Banco - SUM + Ordinaria | B123: =B121+B104+B114 -> 7311447.4

Sheet PRORRATEO
A1: Las casillas coloreadas en la columna Gastos Par/SUM de color rojo corresponden a multas aplicadas por el uso del SUM. En consecuencia, la unidad funcional involucrada no podrá acceder al uso del mismo por tiempo indeterminado. Por otro lado, las casillas coloreadas en amarillo, corresponden a llaves y las verdes corresponden al mal uso del coworking. | F1: Banco Santander Rio. | L1: SE GASTO: | M1: =RESUMEN!D76-N4 -> 18487964
F2: CBU: 0720039720000002171436 | L2: SE PRORRATEA EN LAS UF: | N2: =M1 -> 18487964
L3: SE PRORRATEA EN LOCALES: | N3: =L15+L16+L17+L18+L19 -> 1706477.5
F4: CTA CTE $ 0039 - 21714/3 FIDEICOMISO 25 DE MAYO 837 LAN 30716676737 | L4: TSG: | N4: 7624606
C6: IMPORTANTE: Si en la columna SALDO a su unidad funcional le figura un monto en negativo, significa que usted abono mas dinero del que debia abonar. Si figura un monto en positivo significa que usted abono menos de lo que realmente debia abonar. Sea positivo o negativo el numero, es contemplado en las columnas de total a abonar para al siguiente mes.
C10: IMPORTANTE: Quienes estan en violeta NO ha respetado los centavos al abonar. Para la proxima oportunidad, solicitamos que los respeten. | Q10: LOCAL 1 | R10: =RESUMEN!F76 -> 271028.78
Q11: LOCAL 2 | R11: =RESUMEN!G76 -> 321219.29
A12: Piso | B12: Dpto. | C12: UF | D12: Propietario | E12: Inquilinos | F12: (%) | G12: Saldo | H12: Ingreso | I12: SALDO | J12: Expensas extraor. | K12: Cuota TSG | L12: Expensas ord | M12: SUM/ GASTOS PART | N12: TOTAL A ABONAR HASTA | O12: TOTAL A ABONAR 2DO VTO - DESDE EL | Q12: LOCAL 3 | R12: =RESUMEN!H76 -> 303652.61
Q13: LOCAL 4 | R13: =RESUMEN!I76 -> 373919.33
N14: =RESUMEN!A20 -> VTO 16/10 | O14: =RESUMEN!A20 -> VTO 16/10 | Q14: LOCAL 5 | R14: =RESUMEN!J76 -> 436657.48
A15: conf sup | C15: LOC 1 | D15: Fernandez, Cristian | E15: Gladys ojeda Britez - Exequiel alexis giuliani | F15: 0.0108 | G15: 332345.89 | H15: 267678 | I15: =G15-H15 -> 64667.889 | J15: 0 | K15: 82345.745 | L15: 271028.78 | M15: 0 | N15: =L15+J15+I15+M15+K15 -> 418042.41 | O15: =N15*6% + N15 -> 443124.96 | P15: Bezzo Jorge
C16: LOC 2 | D16: Fridgi, Guillermo Ariel | F16: 0.013 | G16: 770503.97 | H16: =G16 -> 770503.97 | I16: =G16-H16 -> 0 | J16: 0 | L16: 321219.29 | M16: 0 | N16: =L16+J16+I16+M16+K16 -> 321219.29 | O16: =N16*6% + N16 -> 340492.45 | P16: Lucas Rocha
A17: conf sup | C17: LOC 3 | D17: Grispino, Eduardo Claudio | E17: Cristina andrea Massa | F17: 0.0121 | G17: 299898.61 | H17: =G17 -> 299898.61 | I17: =G17-H17 -> 0 | J17: 0 | L17: 303652.61 | M17: 0 | N17: =L17+J17+I17+M17+K17 -> 303652.61 | O17: =N17*6% + N17 -> 321871.77
A18: conf sup | C18: LOC 4 | D18: Cordero, Leandro Emanuel - Orona, Victoria | F18: 0.0149 | G18: 1318197.1 | I18: =G18-H18 -> 1318197.1 | J18: 0 | K18: 113606.63 | L18: 373919.33 | M18: 0 | N18: =L18+J18+I18+M18+K18 -> 1805723.1 | O18: =N18*6% + N18 -> 1914066.5
A19: conf sup | C19: LOC 5 | D19: Orsi, Jose Luis - Fernandez, Cristian Gabriel | F19: 0.0174 | G19: 727422.31 | H19: 374000 | I19: =G19-H19 -> 353422.31 | J19: 0 | K19: 132668.14 | L19: 436657.48 | M19: 0 | N19: =L19+J19+I19+M19+K19 -> 922747.93 | O19: =N19*6% + N19 -> 978112.81
A20: 3 amb | C20: 2ºA | D20: Franco, Lucas Fabián | F20: 0.0188 | G20: 508048.01 | H20: =G20 -> 508048.01 | I20: =G20-H20 -> 0 | J20: =N$9*F20 -> 0 | L20: =N$2*F20 -> 347573.72 | M20: 0 | N20: =ROUND((L20+J20+I20+K20+M20),0) + P20 -> 347574.01 | O20: =ROUND((N20*6% + N20 ),0) + P20 -> 368428.01 | P20: 0.01
A21: 1 amb | C21: 2ºB | D21: Martinez, Diego | F21: 0.0084 | G21: 220298.02 | H21: =G21 -> 220298.02 | I21: =G21-H21 -> 0 | J21: =N$9*F21 -> 0 | K21: =N$4*F21 -> 64046.69 | L21: =N$2*F21 -> 155298.9 | M21: 0 | N21: =ROUND((L21+J21+I21+K21+M21),0) + P21 -> 219346.02 | O21: =ROUND((N21*6% + N21 ),0) + P21 -> 232507.02 | P21: =P20+0.01 -> 0.02
A22: 3 amb | C22: 2ºC | D22: Rodriguez, Carlos Alberto Miguel | F22: 0.0201 | G22: 558771.03 | H22: =G22 -> 558771.03 | I22: =G22-H22 -> 0 | J22: =N$9*F22 -> 0 | L22: =N$2*F22 -> 371608.07 | M22: 0 | N22: =ROUND((L22+J22+I22+K22+M22),0) + P22 -> 371608.03 | O22: =ROUND((N22*6% + N22 ),0) + P22 -> 393905.03 | P22: =P21+0.01 -> 0.03
A23: 2 amb | C23: 2ºD | D23: Gomez, Adriana | E23: Matias Cuevas | F23: 0.0094 | G23: 246524.04 | H23: =G23 -> 246524.04 | I23: =G23-H23 -> 0 | J23: =N$9*F23 -> 0 | L23: =N$2*F23 -> 173786.86 | M23: 0 | N23: =ROUND((L23+J23+I23+K23+M23),0) + P23 -> 173787.04 | O23: =ROUND((N23*6% + N23 ),0) + P23 -> 184214.04 | P23: =P22+0.01 -> 0.04 | Q23: Matias alejandro ezequiel
A24: 2 amb | C24: 2ºE | D24: Dieci, Matias Orlando | E24: Julieta Damiano/Damiani | F24: 0.0087 | G24: 228166.05 | H24: 146784.05 | I24: =G24-H24 -> 81382 | J24: =N$9*F24 -> 0 | K24: =N$4*F24 -> 66334.072 | L24: =N$2*F24 -> 160845.29 | M24: 0 | N24: =ROUND((L24+J24+I24+K24+M24),0) + P24 -> 308561.05 | O24: =ROUND((N24*6% + N24 ),0) + P24 -> 327075.05 | P24: =P23+0.01 -> 0.05
A25: 2 amb | C25: 2ºF | D25: Gomez, Adriana | E25: Carolina Massa | F25: 0.0095 | G25: 339801.06 | H25: =G25 -> 339801.06 | I25: =G25-H25 -> 0 | J25: =N$9*F25 -> 0 | L25: =N$2*F25 -> 175635.66 | M25: 0 | N25: =ROUND((L25+J25+I25+K25+M25),0) + P25 -> 175636.06 | O25: =ROUND((N25*6% + N25 ),0) + P25 -> 186174.06 | P25: =P24+0.01 -> 0.06
A26: 3 amb | C26: 3ºA | D26: Gomez, Adriana | E26: Walter Gabriel Ledesma | F26: 0.0165 | G26: 717781.07 | H26: 302156.07 | I26: =G26-H26 -> 415625 | J26: =N$9*F26 -> 0 | L26: =N$2*F26 -> 305051.4 | M26: 0 | N26: =ROUND((L26+J26+I26+K26+M26),0) + P26 -> 720676.07 | O26: =ROUND((N26*6% + N26 ),0) + P26 -> 763917.07 | P26: =P25+0.01 -> 0.07
A27: 1 amb | C27: 3ºB | D27: Balduzzi, Stella Maris | F27: 0.0073 | G27: 224136.08 | H27: =G27 -> 224136.08 | I27: =G27-H27 -> 0 | J27: =N$9*F27 -> 0 | K27: =N$4*F27 -> 55659.624 | L27: =N$2*F27 -> 134962.14 | M27: 0 | N27: =ROUND((L27+J27+I27+K27+M27),0) + P27 -> 190622.08 | O27: =ROUND((N27*6% + N27 ),0) + P27 -> 202059.08 | P27: =P26+0.01 -> 0.08
A28: 3 amb | C28: 3ºC | D28: Gomez, Adriana | E28: Gustavo Oscar Fernandez | F28: 0.0178 | G28: 1109042.1 | H28: =728003.08+(526500-G118) -> 1108399.1 | I28: =G28-H28 -> 643 | J28: =N$9*F28 -> 0 | L28: =N$2*F28 -> 329085.76 | M28: 0 | N28: =ROUND((L28+J28+I28+K28+M28),0) + P28 -> 329729.09 | O28: =ROUND((N28*6% + N28 ),0) + P28 -> 349513.09 | P28: =P27+0.01 -> 0.09
A29: 2 amb | C29: 3ºD | D29: Fernandez, Christian Norberto | F29: 0.0094 | G29: 246524.1 | H29: =G29 -> 246524.1 | I29: =G29-H29 -> 0 | J29: =N$9*F29 -> 0 | K29: =N$4*F29 -> 71671.296 | L29: =N$2*F29 -> 173786.86 | M29: 0 | N29: =ROUND((L29+J29+I29+K29+M29),0) + P29 -> 245458.1 | O29: =ROUND((N29*6% + N29 ),0) + P29 -> 260186.1 | P29: =P28+0.01 -> 0.1
A30: 2 amb | C30: 3ºE | D30: Dallorso, Maria Ines - Dallorso, Ana Paula | F30: 0.0087 | G30: 243166.11 | H30: =G30 -> 243166.11 | I30: =G30-H30 -> 0 | J30: =N$9*F30 -> 0 | K30: =N$4*F30 -> 66334.072 | L30: =N$2*F30 -> 160845.29 | M30: 0 | N30: =ROUND((L30+J30+I30+K30+M30),0) + P30 -> 227179.11 | O30: =ROUND((N30*6% + N30 ),0) + P30 -> 240810.11 | P30: =P29+0.01 -> 0.11
A31: 2 amb | C31: 3ºF | D31: Campelo, Mariano | F31: 0.0095 | G31: 2272449.1 | H31: =G31+182709 -> 2455158.1 | I31: =G31-H31 -> -182709 | J31: =N$9*F31 -> 0 | L31: =N$2*F31 -> 175635.66 | M31: 0 | N31: =ROUND((L31+J31+I31+K31+M31),0) + P31 -> -7072.88 | O31: =ROUND((N31*6% + N31 ),0) + P31 -> -7496.88 | P31: =P30+0.01 -> 0.12
A32: 3 amb | C32: 4ºA | D32: Barral, Carlos Daniel | F32: 0.0164 | G32: 430106.13 | H32: =G32 -> 430106.13 | I32: =G32-H32 -> 0 | J32: =N$9*F32 -> 0 | L32: =N$2*F32 -> 303202.61 | M32: 0 | N32: =ROUND((L32+J32+I32+K32+M32),0) + P32 -> 303203.13 | O32: =ROUND((N32*6% + N32 ),0) + P32 -> 321395.13 | P32: =P31+0.01 -> 0.13
A33: 1 amb | C33: 4ºB | D33: Viegas, Nancy Noemi | E33: Liria | F33: 0.0072 | G33: 189183.14 | H33: 188471.14 | I33: =G33-H33 -> 712 | J33: =N$9*F33 -> 0 | L33: =N$2*F33 -> 133113.34 | M33: 0 | N33: =ROUND((L33+J33+I33+K33+M33),0) + P33 -> 133825.14 | O33: =ROUND((N33*6% + N33 ),0) + P33 -> 141855.14 | P33: =P32+0.01 -> 0.14
A34: 3 amb | C34: 4ºC | D34: Osipowicz, Ariel Marcelo | F34: 0.0173 | G34: 483709.15 | H34: =G34 -> 483709.15 | I34: =G34-H34 -> 0 | J34: =N$9*F34 -> 0 | L34: =N$2*F34 -> 319841.77 | M34: 0 | N34: =ROUND((L34+J34+I34+K34+M34),0) + P34 -> 319842.15 | O34: =ROUND((N34*6% + N34 ),0) + P34 -> 339033.15 | P34: =P33+0.01 -> 0.15
A35: 2 amb | C35: 4ºD | D35: Ruiz, Juana Del Valle | F35: 0.0094 | G35: 246524.16 | H35: =G35 -> 246524.16 | I35: =G35-H35 -> 0 | J35: =N$9*F35 -> 0 | L35: =N$2*F35 -> 173786.86 | M35: 0 | N35: =ROUND((L35+J35+I35+K35+M35),0) + P35 -> 173787.16 | O35: =ROUND((N35*6% + N35 ),0) + P35 -> 184214.16 | P35: =P34+0.01 -> 0.16 | Q35: Pablo Amarilla
A36: 2 amb | C36: 4ºE | D36: Szkarlatiuk, Carina Sonia | E36: Iara | F36: 0.0087 | G36: 228166.17 | H36: =G36 -> 228166.17 | I36: =G36-H36 -> 0 | J36: =N$9*F36 -> 0 | K36: =N$4*F36 -> 66334.072 | L36: =N$2*F36 -> 160845.29 | M36: 0 | N36: =ROUND((L36+J36+I36+K36+M36),0) + P36 -> 227179.17 | O36: =ROUND((N36*6% + N36 ),0) + P36 -> 240810.17 | P36: =P35+0.01 -> 0.17
A37: 2 amb | C37: 4ºF | D37: Campelo, Mariano | F37: 0.0095 | G37: 1723633.2 | H37: =G37+182708 -> 1906341.2 | I37: =G37-H37 -> -182708 | J37: =N$9*F37 -> 0 | L37: =N$2*F37 -> 175635.66 | M37: 0 | N37: =ROUND((L37+J37+I37+K37+M37),0) + P37 -> -7071.82 | O37: =ROUND((N37*6% + N37 ),0) + P37 -> -7495.82 | P37: =P36+0.01 -> 0.18
A38: 3 amb | C38: 5ºA | D38: Chehab, Gabriel Adrian | E38: Santiago Rodriguez | F38: 0.0164 | G38: 430106.19 | H38: =G38 -> 430106.19 | I38: =G38-H38 -> 0 | J38: =N$9*F38 -> 0 | L38: =N$2*F38 -> 303202.61 | M38: 0 | N38: =ROUND((L38+J38+I38+K38+M38),0) + P38 -> 303203.19 | O38: =ROUND((N38*6% + N38 ),0) + P38 -> 321395.19 | P38: =P37+0.01 -> 0.19 | Q38: Cochera 38
A39: 1 amb | C39: 5ºB | D39: Mesa, Mariano | F39: 0.0072 | G39: 200157.2 | H39: 188827.2 | I39: =G39-H39 -> 11330 | J39: =N$9*F39 -> 0 | K39: =N$4*F39 -> 54897.163 | L39: =N$2*F39 -> 133113.34 | M39: 0 | N39: =ROUND((L39+J39+I39+K39+M39),0) + P39 -> 199341.2 | O39: =ROUND((N39*6% + N39 ),0) + P39 -> 211302.2 | P39: =P38+0.01 -> 0.2
A40: 3 amb | C40: 5ºC | D40: Lasarte, Leda Isabel y Grossa, Raul Ariel | F40: 0.0173 | G40: 468710.21 | H40: =529029.96-H94 -> 468709.21 | I40: =G40-H40 -> 1 | J40: =N$9*F40 -> 0 | L40: =N$2*F40 -> 319841.77 | M40: 0 | N40: =ROUND((L40+J40+I40+K40+M40),0) + P40 -> 319843.21 | O40: =ROUND((N40*6% + N40 ),0) + P40 -> 339034.21 | P40: =P39+0.01 -> 0.21 | Q40: Gossa Raul Ariel
A41: 2 amb | C41: 5ºD | D41: Ayala, Roberto Adrian | F41: 0.0094 | G41: 246524.22 | H41: =G41 -> 246524.22 | I41: =G41-H41 -> 0 | J41: =N$9*F41 -> 0 | K41: =N$4*F41 -> 71671.296 | L41: =N$2*F41 -> 173786.86 | M41: 0 | N41: =ROUND((L41+J41+I41+K41+M41),0) + P41 -> 245458.22 | O41: =ROUND((N41*6% + N41 ),0) + P41 -> 260186.22 | P41: =P40+0.01 -> 0.22 | Q41: Ayala paga 5D, 5F y 4F
A42: 2 amb | C42: 5ºE | D42: Basaez, Rogelio Luis - Savino, Cecilia | F42: 0.0087 | G42: 228166.23 | H42: =G42 -> 228166.23 | I42: =G42-H42 -> 0 | J42: =N$9*F42 -> 0 | K42: =N$4*F42 -> 66334.072 | L42: =N$2*F42 -> 160845.29 | M42: 0 | N42: =ROUND((L42+J42+I42+K42+M42),0) + P42 -> 227179.23 | O42: =ROUND((N42*6% + N42 ),0) + P42 -> 240810.23 | P42: =P41+0.01 -> 0.23 | Q42: COCHERA 31
A43: 2 amb | C43: 5ºF | D43: Ayala, Roberto Adrian | F43: 0.0095 | G43: 1453566.2 | H43: =182708.22+1453566.24 -> 1636274.5 | I43: =G43-H43 -> -182708.22 | J43: =N$9*F43 -> 0 | L43: =N$2*F43 -> 175635.66 | M43: 0 | N43: =ROUND((L43+J43+I43+K43+M43),0) + P43 -> -7072.76 | O43: =ROUND((N43*6% + N43 ),0) + P43 -> -7496.76 | P43: =P42+0.01 -> 0.24
A44: 3 amb | C44: 6ºA | D44: Morandi, Victoria Ayelen | Calvo, Luciano Ezequiel | F44: 0.0164 | G44: 430106.25 | H44: =G44 -> 430106.25 | I44: =G44-H44 -> 0 | J44: =N$9*F44 -> 0 | K44: =N$4*F44 -> 125043.54 | L44: =N$2*F44 -> 303202.61 | M44: 0 | N44: =ROUND((L44+J44+I44+K44+M44),0) + P44 -> 428246.25 | O44: =ROUND((N44*6% + N44 ),0) + P44 -> 453941.25 | P44: =P43+0.01 -> 0.25
A45: 1 amb | C45: 6ºB | D45: Grizak Ruben | E45: Christian | F45: 0.0072 | G45: 188827.26 | H45: =G45 -> 188827.26 | I45: =G45-H45 -> 0 | J45: =N$9*F45 -> 0 | L45: =N$2*F45 -> 133113.34 | M45: 0 | N45: =ROUND((L45+J45+I45+K45+M45),0) + P45 -> 133113.26 | O45: =ROUND((N45*6% + N45 ),0) + P45 -> 141100.26 | P45: =P44+0.01 -> 0.26
A46: 3 amb | C46: 6ºC | D46: Nuñez Leonel - Corrieri Giuliana | F46: 0.0173 | G46: 453709.27 | H46: =G46 -> 453709.27 | I46: =G46-H46 -> 0 | J46: =N$9*F46 -> 0 | L46: =N$2*F46 -> 319841.77 | M46: 0 | N46: =ROUND((L46+J46+I46+K46+M46),0) + P46 -> 319842.27 | O46: =ROUND((N46*6% + N46 ),0) + P46 -> 339033.27 | P46: =P45+0.01 -> 0.27 | Q46: COCHERA 33 | R46: COCHERA 33
A47: 2 amb | C47: 6ºD | D47: Anchipi, Gaston Nicolas | F47: 0.0094 | G47: 261524.28 | H47: =G47 -> 261524.28 | I47: =G47-H47 -> 0 | J47: =N$9*F47 -> 0 | L47: =N$2*F47 -> 173786.86 | M47: 0 | N47: =ROUND((L47+J47+I47+K47+M47),0) + P47 -> 173787.28 | O47: =ROUND((N47*6% + N47 ),0) + P47 -> 184215.28 | P47: =P46+0.01 -> 0.28
A48: 2 amb | C48: 6ºE | D48: Dieci, Matias Orlando | E48: Gaston Smith | F48: 0.0087 | G48: 284256.29 | H48: =G48 -> 284256.29 | I48: =G48-H48 -> 0 | J48: =N$9*F48 -> 0 | K48: =N$4*F48 -> 66334.072 | L48: =N$2*F48 -> 160845.29 | M48: 0 | N48: =ROUND((L48+J48+I48+K48+M48),0) + P48 -> 227179.29 | O48: =ROUND((N48*6% + N48 ),0) + P48 -> 240810.29 | P48: =P47+0.01 -> 0.29
A49: 2 amb | C49: 6ºF | D49: Mazzia Alexia | F49: 0.0095 | G49: 249147.3 | H49: =G49 -> 249147.3 | I49: =G49-H49 -> 0 | J49: =N$9*F49 -> 0 | L49: =N$2*F49 -> 175635.66 | M49: 0 | N49: =ROUND((L49+J49+I49+K49+M49),0) + P49 -> 175636.3 | O49: =ROUND((N49*6% + N49 ),0) + P49 -> 186174.3 | P49: =P48+0.01 -> 0.3
A50: 3 amb | C50: 7ºA | D50: Munsch, Walter Marcelo | F50: 0.0164 | G50: 445106.31 | H50: =G50 -> 445106.31 | I50: =G50-H50 -> 0 | J50: =N$9*F50 -> 0 | L50: =N$2*F50 -> 303202.61 | M50: 0 | N50: =ROUND((L50+J50+I50+K50+M50),0) + P50 -> 303203.31 | O50: =ROUND((N50*6% + N50 ),0) + P50 -> 321396.31 | P50: =P49+0.01 -> 0.31
A51: 1 amb | C51: 7ºB | D51: Paes, Yazmin Luciana | F51: 0.0072 | G51: 313214.32 | H51: 332007.32 | I51: =G51-H51 -> -18793 | J51: =N$9*F51 -> 0 | K51: =N$4*F51 -> 54897.163 | L51: =N$2*F51 -> 133113.34 | M51: 0 | N51: =ROUND((L51+J51+I51+K51+M51),0) + P51 -> 169218.32 | O51: =ROUND((N51*6% + N51 ),0) + P51 -> 179371.32 | P51: =P50+0.01 -> 0.32
A52: 3 amb | C52: 7ºC | D52: Gonzalez Fedullo, Valeria | F52: 0.0173 | G52: 468709.33 | H52: =G52 -> 468709.33 | I52: =G52-H52 -> 0 | J52: =N$9*F52 -> 0 | L52: =N$2*F52 -> 319841.77 | M52: 0 | N52: =ROUND((L52+J52+I52+K52+M52),0) + P52 -> 319842.33 | O52: =ROUND((N52*6% + N52 ),0) + P52 -> 339033.33 | P52: =P51+0.01 -> 0.33
A53: 2 amb | C53: 7ºD | D53: Solleiro, Carolina Mabel | E53: Rosana Cavallero | F53: 0.0094 | G53: 246524.34 | H53: =G53 -> 246524.34 | I53: =G53-H53 -> 0 | J53: =N$9*F53 -> 0 | L53: =N$2*F53 -> 173786.86 | M53: 0 | N53: =ROUND((L53+J53+I53+K53+M53),0) + P53 -> 173787.34 | O53: =ROUND((N53*6% + N53 ),0) + P53 -> 184215.34 | P53: =P52+0.01 -> 0.34 | Q53: Walter Javier Dimiziunas - Rosana Cavallero
A54: 2 amb | C54: 7ºE | D54: Leyes, Javier | F54: 0.0087 | G54: 228166.35 | H54: =G54 -> 228166.35 | I54: =G54-H54 -> 0 | J54: =N$9*F54 -> 0 | L54: =N$2*F54 -> 160845.29 | M54: 0 | N54: =ROUND((L54+J54+I54+K54+M54),0) + P54 -> 160845.35 | O54: =ROUND((N54*6% + N54 ),0) + P54 -> 170496.35 | P54: =P53+0.01 -> 0.35
A55: 2 amb | C55: 7ºF | D55: Puente, Matias | F55: 0.0095 | G55: 249147.36 | H55: =G55 -> 249147.36 | I55: =G55-H55 -> 0 | J55: =N$9*F55 -> 0 | K55: =N$4*F55 -> 72433.757 | L55: =N$2*F55 -> 175635.66 | M55: 20000 | N55: =ROUND((L55+J55+I55+K55+M55),0) + P55 -> 268069.36 | O55: =ROUND((N55*6% + N55 ),0) + P55 -> 284154.36 | P55: =P54+0.01 -> 0.36
A56: 3 amb | C56: 8ºA | D56: Campelo, Mariano | F56: 0.0164 | G56: 430106.37 | H56: =G56 -> 430106.37 | I56: =G56-H56 -> 0 | J56: =N$9*F56 -> 0 | L56: =N$2*F56 -> 303202.61 | M56: 15000 | N56: =ROUND((L56+J56+I56+K56+M56),0) + P56 -> 318203.37 | O56: =ROUND((N56*6% + N56 ),0) + P56 -> 337296.37 | P56: =P55+0.01 -> 0.37
A57: 1 amb | C57: 8ºB | D57: Morvillo, Mariana Yanil | E57: Aylen | F57: 0.0072 | G57: 188827.38 | H57: =G57 -> 188827.38 | I57: =G57-H57 -> 0 | J57: =N$9*F57 -> 0 | L57: =N$2*F57 -> 133113.34 | M57: 0 | N57: =ROUND((L57+J57+I57+K57+M57),0) + P57 -> 133113.38 | O57: =ROUND((N57*6% + N57 ),0) + P57 -> 141100.38 | P57: =P56+0.01 -> 0.38
A58: 3 amb | C58: 8ºC | D58: Colantuono , Juan | F58: 0.0173 | G58: 453709.39 | H58: =G58 -> 453709.39 | I58: =G58-H58 -> 0 | J58: =N$9*F58 -> 0 | L58: =N$2*F58 -> 319841.77 | M58: 0 | N58: =ROUND((L58+J58+I58+K58+M58),0) + P58 -> 319842.39 | O58: =ROUND((N58*6% + N58 ),0) + P58 -> 339033.39 | P58: =P57+0.01 -> 0.39
A59: 2 amb | C59: 8ºD | D59: Argul, Sergio Walter | E59: Nahuel | F59: 0.0094 | G59: 261524.4 | H59: =G59 -> 261524.4 | I59: =G59-H59 -> 0 | J59: =N$9*F59 -> 0 | K59: =N$4*F59 -> 71671.296 | L59: =N$2*F59 -> 173786.86 | M59: 0 | N59: =ROUND((L59+J59+I59+K59+M59),0) + P59 -> 245458.4 | O59: =ROUND((N59*6% + N59 ),0) + P59 -> 260186.4 | P59: =P58+0.01 -> 0.4
A60: 2 amb | C60: 8ºE | D60: Di Sabato, Guillermo | F60: 0.0087 | G60: 228166.41 | H60: =G60 -> 228166.41 | I60: =G60-H60 -> 0 | J60: =N$9*F60 -> 0 | K60: =N$4*F60 -> 66334.072 | L60: =N$2*F60 -> 160845.29 | M60: 0 | N60: =ROUND((L60+J60+I60+K60+M60),0) + P60 -> 227179.41 | O60: =ROUND((N60*6% + N60 ),0) + P60 -> 240810.41 | P60: =P59+0.01 -> 0.41 | R60: el de sergio
A61: 2 amb | C61: 8ºF | D61: Alonso, Gustavo y Sra. | F61: 0.0095 | G61: 249147.42 | H61: =G61 -> 249147.42 | I61: =G61-H61 -> 0 | J61: =N$9*F61 -> 0 | L61: =N$2*F61 -> 175635.66 | M61: 0 | N61: =ROUND((L61+J61+I61+K61+M61),0) + P61 -> 175636.42 | O61: =ROUND((N61*6% + N61 ),0) + P61 -> 186175.42 | P61: =P60+0.01 -> 0.42 | Q61: alonso sabrina eugenia
A62: 3 amb | C62: 9ºA | D62: Fanjul, Alejandro Rubén Marcelo | F62: 0.0164 | G62: 413109.43 | H62: =G62 -> 413109.43 | I62: =G62-H62 -> 0 | J62: =N$9*F62 -> 0 | L62: =N$2*F62 -> 303202.61 | M62: 0 | N62: =ROUND((L62+J62+I62+K62+M62),0) + P62 -> 303203.43 | O62: =ROUND((N62*6% + N62 ),0) + P62 -> 321396.43 | P62: =P61+0.01 -> 0.43
A63: 1 amb | C63: 9ºB | D63: Fanjul, Alejandro Rubén Marcelo | F63: 0.0072 | G63: 181363.44 | H63: =G63 -> 181363.44 | I63: =G63-H63 -> 0 | J63: =N$9*F63 -> 0 | L63: =N$2*F63 -> 133113.34 | M63: 0 | N63: =ROUND((L63+J63+I63+K63+M63),0) + P63 -> 133113.44 | O63: =ROUND((N63*6% + N63 ),0) + P63 -> 141100.44 | P63: =P62+0.01 -> 0.44
A64: 3 amb | C64: 9ºC | D64: Franchino, Mauro | F64: 0.0173 | G64: 473709.45 | H64: =G64 -> 473709.45 | I64: =G64-H64 -> 0 | J64: =N$9*F64 -> 0 | K64: =N$4*F64 -> 131905.68 | L64: =N$2*F64 -> 319841.77 | M64: 0 | N64: =ROUND((L64+J64+I64+K64+M64),0) + P64 -> 451747.45 | O64: =ROUND((N64*6% + N64 ),0) + P64 -> 478852.45 | P64: =P63+0.01 -> 0.45
A65: 2 amb | C65: 9ºD | D65: Cerra, Antonio Osvaldo | E65: Mario Gomez Alejandro | F65: 0.0094 | G65: 261524.46 | H65: =G65+15000 -> 276524.46 | I65: =G65-H65 -> -15000 | J65: =N$9*F65 -> 0 | L65: =N$2*F65 -> 173786.86 | M65: 0 | N65: =ROUND((L65+J65+I65+K65+M65),0) + P65 -> 158787.46 | O65: =ROUND((N65*6% + N65 ),0) + P65 -> 168315.46 | P65: =P64+0.01 -> 0.46
A66: 2 amb | C66: 9ºE | D66: Dieci, Matias Orlando | F66: 0.0087 | G66: 241856.47 | H66: =G66 -> 241856.47 | I66: =G66-H66 -> 0 | J66: =N$9*F66 -> 0 | K66: =N$4*F66 -> 66334.072 | L66: =N$2*F66 -> 160845.29 | M66: 0 | N66: =ROUND((L66+J66+I66+K66+M66),0) + P66 -> 227179.47 | O66: =ROUND((N66*6% + N66 ),0) + P66 -> 240810.47 | P66: =P65+0.01 -> 0.47
A67: 2 amb | C67: 9ºF | D67: Rosales, Rubén Darío | F67: 0.0095 | G67: 360229.48 | H67: =249147+111082.48 -> 360229.48 | I67: =G67-H67 -> 0 | J67: =N$9*F67 -> 0 | L67: =N$2*F67 -> 175635.66 | M67: 0 | N67: =ROUND((L67+J67+I67+K67+M67),0) + P67 -> 175636.48 | O67: =ROUND((N67*6% + N67 ),0) + P67 -> 186175.48 | P67: =P66+0.01 -> 0.48
A68: 3 amb | C68: 10ºA | D68: Puisys Guillermo Antonio | F68: 0.0164 | G68: 445106.49 | H68: =G68 -> 445106.49 | I68: =G68-H68 -> 0 | J68: =N$9*F68 -> 0 | K68: =N$4*F68 -> 125043.54 | L68: =N$2*F68 -> 303202.61 | M68: 0 | N68: =ROUND((L68+J68+I68+K68+M68),0) + P68 -> 428246.49 | O68: =ROUND((N68*6% + N68 ),0) + P68 -> 453941.49 | P68: =P67+0.01 -> 0.49
A69: 1 amb | C69: 10ºB | D69: Guerra Karina, Alejandra | F69: 0.0072 | G69: 188827.5 | H69: =G69 -> 188827.5 | I69: =G69-H69 -> 0 | J69: =N$9*F69 -> 0 | K69: =N$4*F69 -> 54897.163 | L69: =N$2*F69 -> 133113.34 | M69: 0 | N69: =ROUND((L69+J69+I69+K69+M69),0) + P69 -> 188011.5 | O69: =ROUND((N69*6% + N69 ),0) + P69 -> 199292.5 | P69: =P68+0.01 -> 0.5
A70: 3 amb | C70: 10ºC | D70: Espósito, Franco Ezequiel | F70: 0.0173 | G70: 453709.51 | H70: =G70 -> 453709.51 | I70: =G70-H70 -> 0 | J70: =N$9*F70 -> 0 | K70: =N$4*F70 -> 131905.68 | L70: =N$2*F70 -> 319841.77 | M70: 0 | N70: =ROUND((L70+J70+I70+K70+M70),0) + P70 -> 451747.51 | O70: =ROUND((N70*6% + N70 ),0) + P70 -> 478852.51 | P70: =P69+0.01 -> 0.51
A71: 2 amb | C71: 10ºD | D71: Lobato, Lorena - Vega, Maximiliano | F71: 0.0094 | G71: 408919.52 | H71: 172138.52 | I71: =G71-H71 -> 236781 | J71: =N$9*F71 -> 0 | K71: =N$4*F71 -> 71671.296 | L71: =N$2*F71 -> 173786.86 | M71: 0 | N71: =ROUND((L71+J71+I71+K71+M71),0) + P71 -> 482239.52 | O71: =ROUND((N71*6% + N71 ),0) + P71 -> 511174.52 | P71: =P70+0.01 -> 0.52
A72: 2 amb | C72: 10ºE | D72: Sr propietario | F72: 0.0087 | G72: 241857.53 | H72: 228166.53 | I72: =G72-H72 -> 13691 | J72: =N$9*F72 -> 0 | K72: =N$4*F72 -> 66334.072 | L72: =N$2*F72 -> 160845.29 | N72: =ROUND((L72+J72+I72+K72+M72),0) + P72 -> 240870.53 | O72: =ROUND((N72*6% + N72 ),0) + P72 -> 255323.53 | P72: =P71+0.01 -> 0.53 | R72: ex mariano hecimovic
A73: 2 amb | C73: 10ºF | D73: Ramos, Sergio Eugenio | F73: 0.0095 | G73: 1050218.5 | I73: =G73-H73 -> 1050218.5 | J73: =N$9*F73 -> 0 | K73: =N$4*F73 -> 72433.757 | L73: =N$2*F73 -> 175635.66 | M73: 0 | N73: =ROUND((L73+J73+I73+K73+M73),0) + P73 -> 1298288.5 | O73: =ROUND((N73*6% + N73 ),0) + P73 -> 1376186.5 | P73: =P72+0.01 -> 0.54
A74: 4 amb | C74: 11ºA/B | D74: Cuzzolino, Daniela Carolina | F74: 0.0235 | G74: 616310.55 | H74: =G74 -> 616310.55 | I74: =G74-H74 -> 0 | J74: =N$9*F74 -> 0 | L74: =N$2*F74 -> 434467.15 | M74: 0 | N74: =ROUND((L74+J74+I74+K74+M74),0) + P74 -> 434467.55 | O74: =ROUND((N74*6% + N74 ),0) + P74 -> 460536.55 | P74: =P73+0.01 -> 0.55
A75: 3 amb | C75: 11ºC | D75: Silvestre Villarruel Eduardo | F75: 0.0173 | G75: 393398.56 | H75: =G75 -> 393398.56 | I75: =G75-H75 -> 0 | J75: =N$9*F75 -> 0 | L75: =N$2*F75 -> 319841.77 | M75: 0 | N75: =ROUND((L75+J75+I75+K75+M75),0) + P75 -> 319842.56 | O75: =ROUND((N75*6% + N75 ),0) + P75 -> 339033.56 | P75: =P74+0.01 -> 0.56
A76: 2 amb | C76: 11ºD | D76: Scaglia, Marcela | F76: 0.0094 | G76: 246524.57 | H76: =366657.15-H90-H106 -> 246015.57 | I76: =G76-H76 -> 509 | J76: =N$9*F76 -> 0 | K76: =N$4*F76 -> 71671.296 | L76: =N$2*F76 -> 173786.86 | M76: 15000 | N76: =ROUND((L76+J76+I76+K76+M76),0) + P76 -> 260967.57 | O76: =ROUND((N76*6% + N76 ),0) + P76 -> 276626.57 | P76: =P75+0.01 -> 0.57
A77: 2 amb | C77: 11ºE | D77: Argúl, Adrián Norberto | E77: Lara | F77: 0.0087 | G77: 241857.58 | H77: =G77 -> 241857.58 | I77: =G77-H77 -> 0 | J77: =N$9*F77 -> 0 | K77: =N$4*F77 -> 66334.072 | L77: =N$2*F77 -> 160845.29 | M77: 0 | N77: =ROUND((L77+J77+I77+K77+M77),0) + P77 -> 227179.58 | O77: =ROUND((N77*6% + N77 ),0) + P77 -> 240810.58 | P77: =P76+0.01 -> 0.58
A78: 2 amb | C78: 11ºF | D78: Lobato, Lorena - Vega, Maximiliano | F78: 0.0095 | G78: 413269.59 | H78: 173970.59 | I78: =G78-H78 -> 239299 | J78: =N$9*F78 -> 0 | L78: =N$2*F78 -> 175635.66 | M78: 0 | N78: =ROUND((L78+J78+I78+K78+M78),0) + P78 -> 414935.59 | O78: =ROUND((N78*6% + N78 ),0) + P78 -> 439832.59 | P78: =P77+0.01 -> 0.59
A79: 4 amb | C79: 12ºA/B | D79: Luciano, Carmen Veronica - Rey, Javier Pablo | F79: 0.0235 | G79: 616310.6 | H79: =G79 -> 616310.6 | I79: =G79-H79 -> 0 | J79: =N$9*F79 -> 0 | K79: =N$4*F79 -> 179178.24 | L79: =N$2*F79 -> 434467.15 | M79: 20000 | N79: =ROUND((L79+J79+I79+K79+M79),0) + P79 -> 633645.6 | O79: =ROUND((N79*6% + N79 ),0) + P79 -> 671664.6 | P79: =P78+0.01 -> 0.6
A80: 3 amb | C80: 12ºC | D80: Hernandez, Marisa Beatriz | F80: 0.0173 | G80: 453709.61 | H80: =G80 -> 453709.61 | I80: =G80-H80 -> 0 | J80: =N$9*F80 -> 0 | L80: =N$2*F80 -> 319841.77 | M80: 0 | N80: =ROUND((L80+J80+I80+K80+M80),0) + P80 -> 319842.61 | O80: =ROUND((N80*6% + N80 ),0) + P80 -> 339033.61 | P80: =P79+0.01 -> 0.61
A81: 2 amb | C81: 12ºD | D81: Morini, Micaela | F81: 0.0094 | G81: 1372493.6 | H81: 246524.62 | I81: =G81-H81 -> 1125969 | J81: =N$9*F81 -> 0 | K81: =N$4*F81 -> 71671.296 | L81: =N$2*F81 -> 173786.86 | M81: 0 | N81: =ROUND((L81+J81+I81+K81+M81),0) + P81 -> 1371427.6 | O81: =ROUND((N81*6% + N81 ),0) + P81 -> 1453713.6 | P81: =P80+0.01 -> 0.62
A82: 2 amb | C82: 12ºE | D82: Armerding, Jorge | E82: Agustina | F82: 0.0087 | G82: 146991.63 | H82: =G82 -> 146991.63 | I82: =G82-H82 -> 0 | J82: =N$9*F82 -> 0 | L82: =N$2*F82 -> 160845.29 | M82: 0 | N82: =ROUND((L82+J82+I82+K82+M82),0) + P82 -> 160845.63 | O82: =ROUND((N82*6% + N82 ),0) + P82 -> 170496.63 | P82: =P81+0.01 -> 0.63
A83: 2 amb | C83: 12ºF | D83: Bilyj, Josefa Catalina | F83: 0.0095 | G83: 249147.64 | H83: =G83 -> 249147.64 | I83: =G83-H83 -> 0 | J83: =N$9*F83 -> 0 | K83: =N$4*F83 -> 72433.757 | L83: =N$2*F83 -> 175635.66 | M83: 0 | N83: =ROUND((L83+J83+I83+K83+M83),0) + P83 -> 248069.64 | O83: =ROUND((N83*6% + N83 ),0) + P83 -> 262954.64 | P83: =P82+0.01 -> 0.64 | Q83: Laura Quintas Perez
A84: 4 amb | C84: 13ºA/B | D84: Gazzaneo, Francisco y Sra. | F84: 0.0235 | G84: 631310.65 | H84: =G84 -> 631310.65 | I84: =G84-H84 -> 0 | J84: =N$9*F84 -> 0 | K84: =N$4*F84 -> 179178.24 | L84: =N$2*F84 -> 434467.15 | N84: =ROUND((L84+J84+I84+K84+M84),0) + P84 -> 613645.65 | O84: =ROUND((N84*6% + N84 ),0) + P84 -> 650464.65 | P84: =P83+0.01 -> 0.65
A85: 3 amb | C85: 13ºC | D85: Argentino, Javier Leonardo y Sra. | F85: 0.0173 | G85: 453709.66 | H85: =G85 -> 453709.66 | I85: =G85-H85 -> 0 | J85: =N$9*F85 -> 0 | L85: =N$2*F85 -> 319841.77 | N85: =ROUND((L85+J85+I85+K85+M85),0) + P85 -> 319842.66 | O85: =ROUND((N85*6% + N85 ),0) + P85 -> 339033.66 | P85: =P84+0.01 -> 0.66
A86: 2 amb | C86: 13ºD | D86: Scardigno, Gabriela Susana - Ripoll, Luis Alberto | F86: 0.0094 | G86: 246524.67 | H86: =G86 -> 246524.67 | I86: =G86-H86 -> 0 | J86: =N$9*F86 -> 0 | L86: =N$2*F86 -> 173786.86 | N86: =ROUND((L86+J86+I86+K86+M86),0) + P86 -> 173787.67 | O86: =ROUND((N86*6% + N86 ),0) + P86 -> 184215.67 | P86: =P85+0.01 -> 0.67
A87: 2 amb | C87: 13ºE | D87: Quiñones, Carlos Eduardo | F87: 0.0087 | G87: 228166.68 | H87: =G87 -> 228166.68 | I87: =G87-H87 -> 0 | J87: =N$9*F87 -> 0 | L87: =N$2*F87 -> 160845.29 | N87: =ROUND((L87+J87+I87+K87+M87),0) + P87 -> 160845.68 | O87: =ROUND((N87*6% + N87 ),0) + P87 -> 170496.68 | P87: =P86+0.01 -> 0.68
A88: 2 amb | C88: 13ºF | D88: Mosquera, José Elias | F88: 0.0095 | G88: 289147.69 | H88: =G88 -> 289147.69 | I88: =G88-H88 -> 0 | J88: =N$9*F88 -> 0 | K88: =N$4*F88 -> 72433.757 | L88: =N$2*F88 -> 175635.66 | M88: 20000 | N88: =ROUND((L88+J88+I88+K88+M88),0) + P88 -> 268069.69 | O88: =ROUND((N88*6% + N88 ),0) + P88 -> 284154.69 | P88: =P87+0.01 -> 0.69
C89: COCH 1 | D89: Osipowicz, Ariel Marcelo | F89: 0.0023 | G89: 60320.7 | H89: =G89 -> 60320.7 | I89: =G89-H89 -> 0 | J89: =N$9*F89 -> 0 | L89: =N$2*F89 -> 42522.317 | N89: =ROUND((L89+J89+I89+K89+M89),0) + P89 -> 42522.7 | O89: =ROUND((N89*6% + N89 ),0) + P89 -> 45074.7 | P89: =P88+0.01 -> 0.7
C90: COCH 2 | D90: Sr propietario | F90: 0.0023 | G90: 60320.71 | H90: =G90 -> 60320.71 | I90: =G90-H90 -> 0 | J90: =N$9*F90 -> 0 | K90: =N$4*F90 -> 17536.594 | L90: =N$2*F90 -> 42522.317 | M90: 0 | N90: =ROUND((L90+J90+I90+K90+M90),0) + P90 -> 60059.71 | O90: =ROUND((N90*6% + N90 ),0) + P90 -> 63663.71 | P90: =P89+0.01 -> 0.71
C91: COCH 3 | D91: Paes, Yazmin Luciana | F91: 0.0023 | G91: 60320.72 | H91: =G91 -> 60320.72 | I91: =G91-H91 -> 0 | J91: =N$9*F91 -> 0 | K91: =N$4*F91 -> 17536.594 | L91: =N$2*F91 -> 42522.317 | M91: 0 | N91: =ROUND((L91+J91+I91+K91+M91),0) + P91 -> 60059.72 | O91: =ROUND((N91*6% + N91 ),0) + P91 -> 63663.72 | P91: =P90+0.01 -> 0.72
C92: COCH 4 | D92: Puisys Guillermo Antonio | F92: 0.0023 | G92: 60320.73 | H92: =G92 -> 60320.73 | I92: =G92-H92 -> 0 | J92: =N$9*F92 -> 0 | K92: =N$4*F92 -> 17536.594 | L92: =N$2*F92 -> 42522.317 | M92: 0 | N92: =ROUND((L92+J92+I92+K92+M92),0) + P92 -> 60059.73 | O92: =ROUND((N92*6% + N92 ),0) + P92 -> 63663.73 | P92: =P91+0.01 -> 0.73
C93: COCH 5 | D93: Alonso, Gustavo y Sra. | F93: 0.0023 | G93: 60320.74 | H93: =G93 -> 60320.74 | I93: =G93-H93 -> 0 | J93: =N$9*F93 -> 0 | K93: =N$4*F93 -> 17536.594 | L93: =N$2*F93 -> 42522.317 | M93: 0 | N93: =ROUND((L93+J93+I93+K93+M93),0) + P93 -> 60059.74 | O93: =ROUND((N93*6% + N93 ),0) + P93 -> 63663.74 | P93: =P92+0.01 -> 0.74 | Q93: alonso sabrina eugenia
C94: COCH 6 | D94: Lasarte, Leda Isabel y Grossa, Raul Ariel | F94: 0.0023 | G94: 60320.75 | H94: =G94 -> 60320.75 | I94: =G94-H94 -> 0 | J94: =N$9*F94 -> 0 | L94: =N$2*F94 -> 42522.317 | M94: 0 | N94: =ROUND((L94+J94+I94+K94+M94),0) + P94 -> 42522.75 | O94: =ROUND((N94*6% + N94 ),0) + P94 -> 45074.75 | P94: =P93+0.01 -> 0.75
C95: COCH 7 | D95: Munsch, Walter Marcelo | F95: 0.0023 | G95: 60320.76 | H95: =G95 -> 60320.76 | I95: =G95-H95 -> 0 | J95: =N$9*F95 -> 0 | L95: =N$2*F95 -> 42522.317 | M95: 0 | N95: =ROUND((L95+J95+I95+K95+M95),0) + P95 -> 42522.76 | O95: =ROUND((N95*6% + N95 ),0) + P95 -> 45074.76 | P95: =P94+0.01 -> 0.76
C96: COCH 8 | D96: Campelo, Mariano | F96: 0.0023 | G96: 60320.77 | H96: =G96 -> 60320.77 | I96: =G96-H96 -> 0 | J96: =N$9*F96 -> 0 | L96: =N$2*F96 -> 42522.317 | M96: 0 | N96: =ROUND((L96+J96+I96+K96+M96),0) + P96 -> 42522.77 | O96: =ROUND((N96*6% + N96 ),0) + P96 -> 45074.77 | P96: =P95+0.01 -> 0.77
C97: COCH 9 | D97: Gazzaneo, Francisco y Sra. | F97: 0.0023 | G97: 60320.78 | H97: =G97 -> 60320.78 | I97: =G97-H97 -> 0 | J97: =N$9*F97 -> 0 | L97: =N$2*F97 -> 42522.317 | M97: 0 | N97: =ROUND((L97+J97+I97+K97+M97),0) + P97 -> 42522.78 | O97: =ROUND((N97*6% + N97 ),0) + P97 -> 45074.78 | P97: =P96+0.01 -> 0.78
C98: COCH 10 | D98: Cerra, Antonio Osvaldo | F98: 0.0023 | G98: 60320.79 | H98: 0 | I98: =G98-H98 -> 60320.79 | J98: =N$9*F98 -> 0 | L98: =N$2*F98 -> 42522.317 | M98: 0 | N98: =ROUND((L98+J98+I98+K98+M98),0) + P98 -> 102843.79 | O98: =ROUND((N98*6% + N98 ),0) + P98 -> 109014.79 | P98: =P97+0.01 -> 0.79
C99: COCH 11 | D99: Osipowicz, Ariel Marcelo | F99: 0.0023 | G99: 60320.8 | H99: =G99 -> 60320.8 | I99: =G99-H99 -> 0 | J99: =N$9*F99 -> 0 | L99: =N$2*F99 -> 42522.317 | M99: 0 | N99: =ROUND((L99+J99+I99+K99+M99),0) + P99 -> 42522.8 | O99: =ROUND((N99*6% + N99 ),0) + P99 -> 45074.8 | P99: =P98+0.01 -> 0.8
C100: COCH 12 | D100: Dieci, Matias Orlando | F100: 0.0023 | G100: 63940.81 | H100: =G100 -> 63940.81 | I100: =G100-H100 -> 0 | J100: =N$9*F100 -> 0 | K100: =N$4*F100 -> 17536.594 | L100: =N$2*F100 -> 42522.317 | M100: 0 | N100: =ROUND((L100+J100+I100+K100+M100),0) + P100 -> 60059.81 | O100: =ROUND((N100*6% + N100 ),0) + P100 -> 63663.81 | P100: =P99+0.01 -> 0.81
C101: COCH 13 | D101: Scardigno, Gabriela Susana - Ripoli, Luis Alberto | F101: 0.0023 | G101: 60320.82 | H101: =G101 -> 60320.82 | I101: =G101-H101 -> 0 | J101: =N$9*F101 -> 0 | L101: =N$2*F101 -> 42522.317 | M101: 0 | N101: =ROUND((L101+J101+I101+K101+M101),0) + P101 -> 42522.82 | O101: =ROUND((N101*6% + N101 ),0) + P101 -> 45074.82 | P101: =P100+0.01 -> 0.82
C102: COCH 14 | D102: Colantuono , Juan | F102: 0.0023 | G102: 60320.83 | H102: =G102 -> 60320.83 | I102: =G102-H102 -> 0 | J102: =N$9*F102 -> 0 | L102: =N$2*F102 -> 42522.317 | M102: 0 | N102: =ROUND((L102+J102+I102+K102+M102),0) + P102 -> 42522.83 | O102: =ROUND((N102*6% + N102 ),0) + P102 -> 45074.83 | P102: =P101+0.01 -> 0.83
C103: COCH 15 | D103: Hernandez, Marisa Beatriz | F103: 0.0023 | G103: 60320.84 | H103: =G103 -> 60320.84 | I103: =G103-H103 -> 0 | J103: =N$9*F103 -> 0 | K103: =N$4*F103 -> 17536.594 | L103: =N$2*F103 -> 42522.317 | M103: 0 | N103: =ROUND((L103+J103+I103+K103+M103),0) + P103 -> 60059.84 | O103: =ROUND((N103*6% + N103 ),0) + P103 -> 63663.84 | P103: =P102+0.01 -> 0.84
C104: COCH 16 | D104: Mesa, Mariano | F104: 0.0023 | G104: 63940.85 | H104: 60320.85 | I104: =G104-H104 -> 3620 | J104: =N$9*F104 -> 0 | K104: =N$4*F104 -> 17536.594 | L104: =N$2*F104 -> 42522.317 | M104: 0 | N104: =ROUND((L104+J104+I104+K104+M104),0) + P104 -> 63679.85 | O104: =ROUND((N104*6% + N104 ),0) + P104 -> 67501.85 | P104: =P103+0.01 -> 0.85
...

Sheet ANOTACIONES
C2: ANOTACION | D2: 1
C3: FECHA DE LA ANOTACION: | E3: 0 | G3: NOMBRE:
C4: QUEJA VIA: | D4: WHATSAPP | E4: MAIL | G4: LOTE: | H4: Cochera 32
C5: MOTIVO DE LA QUEJA:
C6: A la cochera 32 no le debemos cobrar el TSG, debe abonar: $42.523,01
C11: ANOTACION | D11: 1
C12: FECHA DE LA ANOTACION: | E12: 0 | G12: NOMBRE: | H12: Javier Argentino
C13: QUEJA VIA: | D13: WHATSAPP | E13: MAIL | G13: LOTE: | H13: 13C
C14: MOTIVO DE LA QUEJA:
C15: 13C transfirio $319.842 el 09/10
C19: ANOTACION | D19: 1
C20: FECHA DE LA ANOTACION: | E20: 0 | G20: NOMBRE: | H20: Javier Argentino
C21: QUEJA VIA: | D21: WHATSAPP | E21: MAIL | G21: LOTE: | H21: Cocher 35
C22: MOTIVO DE LA QUEJA:
C23: Cochera 35 transfirio el 09/10 $42.523

Sheet ARBA
A1: IMPORTANTE: RESPETAR CENTAVOS AL ABONAR.
A3: Quienes adeudan ARBA deben abonar el monto coloreado en ROSADO si es que en el trancurso del mes 3 y 4 del 2026 no abonaron ninguna cuota.
A4: DPTOS | B4: COCH | C4: Propietario | D4: (%) | E4: ARBA REVALUO | F4: POSESION | G4: TOTAL A ABONAR HASTA | H4: TOTAL A ABONAR 1ERA CUOTA - VTO. 31/03 | I4: TOTAL A ABONAR 2DA CUOTA - VTO. 30/04 | J4: A PAGAR PROPIETARIO | L4: ABONADO POR PROPIETARIO | M4: AL PROPIETARIO LE RESTA ABONAR | N4: A PAGAR CONSTRUCTORA | O4: TOTAL
A7: LOC 1 | C7: Fernandez, Cristian | D7: 0.0108 | E7: 282914.38 | F7: 45856 | G7: -197064.48 | H7: =J7/2 -> 98532.35 | I7: =H7 -> 98532.35 | J7: =ROUND((-G7),0)+P7 -> 197064.7 | K7: -85849.897 | L7: 0 | M7: 98532.35 | N7: =-K7 -> 85849.897 | O7: =ROUND((J7+N7),0) + P7 -> 282915.7 | P7: 0.7
A8: LOC 2 | C8: Frigidi Guillermo Ariel | D8: 0.0128 | E8: 335305.93 | F8: 46001 | G8: -34751.379 | H8: =J8/2 -> 17375.855 | I8: =H8 -> 17375.855 | J8: =ROUND((-G8),0)+P8 -> 34751.71 | K8: -300554.55 | L8: 34752 | M8: 0 | N8: =-K8 -> 300554.55 | O8: =ROUND((J8+N8),0) + P8 -> 335306.71 | P8: =P7+0.01 -> 0.71
A9: LOC 3 | C9: Patricia Mainieri | D9: 0.0121 | E9: 316968.89 | F9: 45856 | G9: -220785.21 | H9: =J9/2 -> 110392.86 | I9: =H9 -> 110392.86 | J9: =ROUND((-G9),0)+P9 -> 220785.72 | K9: -96183.681 | L9: 0 | M9: =IF(L9=H9,I9,J9) -> 220785.72 | N9: =-K9 -> 96183.681 | O9: =ROUND((J9+N9),0) + P9 -> 316969.72 | P9: =P8+0.01 -> 0.72
A10: LOC 4 | C10: Cordero, Leandro Emanuel - Orona, Victoria | D10: 0.0149 | E10: 390317.06 | F10: 45856 | G10: -271876 | H10: =J10/2 -> 135938.36 | I10: =H10 -> 135938.36 | J10: =ROUND((-G10),0)+P10 -> 271876.73 | K10: -118441.06 | L10: 0 | M10: 0 | N10: =-K10 -> 118441.06 | O10: =ROUND((J10+N10),0) + P10 -> 390318.73 | P10: =P9+0.01 -> 0.73
A11: LOC 5 | C11: Orsi, José Luis - Fernández, Cristián Gabriel | D11: 0.0175 | E11: 458426.08 | F11: 45856 | G11: -319317.45 | H11: =J11/2 -> 159658.87 | I11: =H11 -> 159658.87 | J11: =ROUND((-G11),0)+P11 -> 319317.74 | K11: -139108.63 | L11: 0 | M11: 159658.87 | N11: =-K11 -> 139108.63 | O11: =ROUND((J11+N11),0) + P11 -> 458426.74 | P11: =P10+0.01 -> 0.74
A12: 2ºA | B12: 25 | C12: Franco, Lucas Fabián | D12: 0.0212 | E12: 555350.45 | F12: 45777 | G12: -519626.97 | H12: =ROUND((J12/2),0)+P12 -> 259814.01 | I12: =H12 -> 259814.01 | J12: =ROUND((-G12),0)+P12 -> 519627.01 | K12: -35723.479 | L12: 0 | M12: 0 | N12: =-K12 -> 35723.479 | O12: =ROUND((J12+N12),0) + P12 -> 555350.01 | P12: 0.01
A13: 2ºB | C13: Martinez, Diego | D13: 0.0084 | E13: 220044.52 | F13: 45775 | G13: -206492.25 | H13: =ROUND((J13/2),0)+P13 -> 103246.02 | I13: =H13 -> 103246.02 | J13: =ROUND((-G13),0)+P13 -> 206492.02 | K13: -13552.263 | L13: 0 | M13: 0 | N13: =-K13 -> 13552.263 | O13: =ROUND((J13+N13),0) + P13 -> 220044.02 | P13: =P12+0.01 -> 0.02
A14: 2ºC | B14: 22 | C14: Rodriguez, Carlos Alberto Miguel | D14: 0.0225 | E14: 589404.96 | F14: 45770 | G14: -557137.66 | H14: =ROUND((J14/2),0)+P14 -> 278569.03 | I14: =H14 -> 278569.03 | J14: =ROUND((-G14),0)+P14 -> 557138.03 | K14: -32267.294 | L14: 0 | M14: 0 | N14: =-K14 -> 32267.294 | O14: =ROUND((J14+N14),0) + P14 -> 589405.03 | P14: =P13+0.01 -> 0.03
A15: 2ºD | B15: 29-30 | C15: Ferraro, José | D15: 0.014 | E15: 366740.86 | F15: 45805 | G15: -327282.74 | H15: =ROUND((J15/2),0)+P15 -> 163642.04 | I15: =H15 -> 163642.04 | J15: =ROUND((-G15),0)+P15 -> 327283.04 | K15: -39458.12 | L15: 0 | M15: 0 | N15: =-K15 -> 39458.12 | O15: =ROUND((J15+N15),0) + P15 -> 366741.04 | P15: =P14+0.01 -> 0.04
A16: 2ºE | C16: Dieci, Matias Orlando | D16: 0.0087 | E16: 227903.25 | F16: 45800 | G16: -206069.05 | H16: =ROUND((J16/2),0)+P16 -> 103035.05 | I16: =H16 -> 103035.05 | J16: =ROUND((-G16),0)+P16 -> 206069.05 | K16: -21834.202 | L16: 0 | M16: 0 | N16: =-K16 -> 21834.202 | O16: =ROUND((J16+N16),0) + P16 -> 227903.05 | P16: =P15+0.01 -> 0.05
A17: 2ºF | B17: 34-39 | C17: Ferraro, Jose | D17: 0.0141 | E17: 369360.44 | F17: 45805 | G17: -329620.48 | H17: =ROUND((J17/2),0)+P17 -> 164810.06 | I17: =H17 -> 164810.06 | J17: =ROUND((-G17),0)+P17 -> 329620.06 | K17: -39739.963 | L17: 0 | M17: 0 | N17: =-K17 -> 39739.963 | O17: =ROUND((J17+N17),0) + P17 -> 369360.06 | P17: =P16+0.01 -> 0.06
A18: 3ºA | B18: 37-38 | C18: Ferraro, Jose - ------ALEJANDRO | D18: 0.0211 | E18: 552730.87 | F18: 45805 | G18: -493261.85 | H18: =ROUND((J18/2),0)+P18 -> 246631.07 | I18: =H18 -> 246631.07 | J18: =ROUND((-G18),0)+P18 -> 493262.07 | K18: -59469.023 | L18: 0 | M18: 0 | N18: =-K18 -> 59469.023 | O18: =ROUND((J18+N18),0) + P18 -> 552731.07 | P18: =P17+0.01 -> 0.07
A19: 3ºB | C19: Ayala, Roberto Adrian/BALDUZZI | D19: 0.0074 | E19: 193848.74 | F19: 45839 | G19: -147681.21 | H19: =ROUND((J19/2),0)+P19 -> 73841.08 | I19: =H19 -> 73841.08 | J19: =ROUND((-G19),0)+P19 -> 147681.08 | K19: -46167.53 | L19: 0 | M19: 0 | N19: =-K19 -> 46167.53 | O19: =ROUND((J19+N19),0) + P19 -> 193849.08 | P19: =P18+0.01 -> 0.08
A20: 3ºC | C20: Ferraro, Jose | D20: 0.0179 | E20: 468904.39 | F20: 45805 | G20: -418454.36 | H20: =ROUND((J20/2),0)+P20 -> 209227.09 | I20: =H20 -> 209227.09 | J20: =ROUND((-G20),0)+P20 -> 418454.09 | K20: -50450.024 | L20: 0 | M20: 0 | N20: =-K20 -> 50450.024 | O20: =ROUND((J20+N20),0) + P20 -> 468904.09 | P20: =P19+0.01 -> 0.09
A21: 3ºD | C21: Ayala, Roberto Adrian | D21: 0.0094 | E21: 246240.29 | F21: 45839 | G21: -187595.05 | H21: =ROUND((J21/2),0)+P21 -> 93798.1 | I21: =H21 -> 93798.1 | J21: =ROUND((-G21),0)+P21 -> 187595.1 | K21: -58645.241 | L21: 0 | M21: 0 | N21: =-K21 -> 58645.241 | O21: =ROUND((J21+N21),0) + P21 -> 246240.1 | P21: =P20+0.01 -> 0.1
A22: 3ºE | C22: Ayala, Roberto Adrian /CALZETTA | D22: 0.0087 | E22: 227903.25 | F22: 45839 | G22: -173625.21 | H22: =ROUND((J22/2),0)+P22 -> 86813.11 | I22: =H22 -> 86813.11 | J22: =ROUND((-G22),0)+P22 -> 173625.11 | K22: -54278.042 | L22: 0 | M22: 0 | N22: =-K22 -> 54278.042 | O22: =ROUND((J22+N22),0) + P22 -> 227903.11 | P22: =P21+0.01 -> 0.11
A23: 3ºF | C23: Ayala, Roberto Adrian | D23: 0.0095 | E23: 248859.87 | F23: 45839 | G23: -189590.74 | H23: =ROUND((J23/2),0)+P23 -> 94796.12 | I23: =H23 -> 94796.12 | J23: =ROUND((-G23),0)+P23 -> 189591.12 | K23: -59269.126 | L23: 0 | M23: 0 | N23: =-K23 -> 59269.126 | O23: =ROUND((J23+N23),0) + P23 -> 248860.12 | P23: =P22+0.01 -> 0.12
A24: 4ºA | C24: Barral, Carlos Daniel | D24: 0.0164 | E24: 429610.72 | F24: 45775 | G24: -403151.54 | H24: =ROUND((J24/2),0)+P24 -> 201576.13 | I24: =H24 -> 201576.13 | J24: =ROUND((-G24),0)+P24 -> 403152.13 | K24: -26459.181 | L24: 0 | M24: 0 | N24: =-K24 -> 26459.181 | O24: =ROUND((J24+N24),0) + P24 -> 429611.13 | P24: =P23+0.01 -> 0.13
A25: 4ºB | C25: Calzetta, Gabriel Andrés Felipe | D25: 0.0073 | E25: 191229.16 | F25: 45800 | G25: -172908.51 | H25: =ROUND((J25/2),0)+P25 -> 86455.14 | I25: =H25 -> 86455.14 | J25: =ROUND((-G25),0)+P25 -> 172909.14 | K25: -18320.652 | L25: 0 | M25: 0 | N25: =-K25 -> 18320.652 | O25: =ROUND((J25+N25),0) + P25 -> 191230.14 | P25: =P24+0.01 -> 0.14
A26: 4ºC | B26: 1-11 | C26: Osipowicz, Ariel Marcelo | D26: 0.022 | E26: 576307.07 | F26: 45775 | G26: -540813.05 | H26: =ROUND((J26/2),0)+P26 -> 270407.15 | I26: =H26 -> 270407.15 | J26: =ROUND((-G26),0)+P26 -> 540813.15 | K26: -35494.023 | L26: 0 | M26: 0 | N26: =-K26 -> 35494.023 | O26: =ROUND((J26+N26),0) + P26 -> 576307.15 | P26: =P25+0.01 -> 0.15
A27: 4ºD | C27: Ayala, Roberto Adrian | D27: 0.0094 | E27: 246240.29 | F27: 45839 | G27: -187595.05 | H27: =ROUND((J27/2),0)+P27 -> 93798.16 | I27: =H27 -> 93798.16 | J27: =ROUND((-G27),0)+P27 -> 187595.16 | K27: -58645.241 | L27: 0 | M27: 0 | N27: =-K27 -> 58645.241 | O27: =ROUND((J27+N27),0) + P27 -> 246240.16 | P27: =P26+0.01 -> 0.16 | Q27: Pablo Amarilla
A28: 4ºE | C28: Ayala, Roberto Adrian/SKARLATIUK | D28: 0.0087 | E28: 227903.25 | F28: 45839 | G28: -173625.21 | H28: =ROUND((J28/2),0)+P28 -> 86813.17 | I28: =H28 -> 86813.17 | J28: =ROUND((-G28),0)+P28 -> 173625.17 | K28: -54278.042 | L28: 0 | M28: 0 | N28: =-K28 -> 54278.042 | O28: =ROUND((J28+N28),0) + P28 -> 227903.17 | P28: =P27+0.01 -> 0.17
A29: 4ºF | C29: Ayala, Roberto Adrian | D29: 0.0095 | E29: 248859.87 | F29: 45839 | G29: -189590.74 | H29: =ROUND((J29/2),0)+P29 -> 94796.18 | I29: =H29 -> 94796.18 | J29: =ROUND((-G29),0)+P29 -> 189591.18 | K29: -59269.126 | L29: 0 | N29: =-K29 -> 59269.126 | O29: =ROUND((J29+N29),0) + P29 -> 248860.18 | P29: =P28+0.01 -> 0.18
A30: 5ºA | C30: Chehab, Gabriel Adrian | D30: 0.0164 | E30: 429610.72 | F30: 45800 | G30: -388452 | H30: =ROUND((J30/2),0)+P30 -> 194226.19 | I30: =H30 -> 194226.19 | J30: =ROUND((-G30),0)+P30 -> 388452.19 | K30: -41158.726 | L30: 0 | M30: 0 | N30: =-K30 -> 41158.726 | O30: =ROUND((J30+N30),0) + P30 -> 429611.19 | P30: =P29+0.01 -> 0.19 | Q30: Cochera 38
A31: 5ºB | B31: 16 | C31: Mesa, Mariano | D31: 0.0096 | E31: 251479.45 | F31: 45805 | G31: -224422.45 | H31: =ROUND((J31/2),0)+P31 -> 112211.2 | I31: =H31 -> 112211.2 | J31: =ROUND((-G31),0)+P31 -> 224422.2 | K31: -27056.996 | L31: 0 | M31: 0 | N31: =-K31 -> 27056.996 | O31: =ROUND((J31+N31),0) + P31 -> 251479.2 | P31: =P30+0.01 -> 0.2
A32: 5ºC | B32: 6 | C32: Di Mito, Vicente Argentino - Serantes, Mabel | D32: 0.0197 | E32: 516056.79 | F32: 45805 | G32: -460533.57 | H32: =ROUND((J32/2),0)+P32 -> 230267.21 | I32: =H32 -> 230267.21 | J32: =ROUND((-G32),0)+P32 -> 460534.21 | K32: -55523.211 | L32: 0 | M32: =IF(L32=H32,I32,J32) -> 460534.21 | N32: =-K32 -> 55523.211 | O32: =ROUND((J32+N32),0) + P32 -> 516057.21 | P32: =P31+0.01 -> 0.21
A33: 5ºD | C33: Ayala, Roberto Adrian | D33: 0.0094 | E33: 246240.29 | F33: 45839 | G33: -187595.05 | H33: =ROUND((J33/2),0)+P33 -> 93798.22 | I33: =H33 -> 93798.22 | J33: =ROUND((-G33),0)+P33 -> 187595.22 | K33: -58645.241 | L33: 0 | M33: 0 | N33: =-K33 -> 58645.241 | O33: =ROUND((J33+N33),0) + P33 -> 246240.22 | P33: =P32+0.01 -> 0.22 | Q33: Ayala paga 5D, 5F y 4F
A34: 5ºE | B34: 31 | C34: Ayala, Roberto Adrian/CALZETTA/ BASAEZ ROGELIO | D34: 0.011 | E34: 288153.53 | F34: 45839 | G34: -219526.13 | H34: =ROUND((J34/2),0)+P34 -> 109763.23 | I34: =H34 -> 109763.23 | J34: =ROUND((-G34),0)+P34 -> 219526.23 | K34: -68627.409 | L34: 0 | M34: 0 | N34: =-K34 -> 68627.409 | O34: =ROUND((J34+N34),0) + P34 -> 288154.23 | P34: =P33+0.01 -> 0.23 | Q34: COCHERA 31
A35: 5ºF | C35: Ayala, Roberto Adrian | D35: 0.0095 | E35: 248859.87 | F35: 45839 | G35: -189590.74 | H35: =ROUND((J35/2),0)+P35 -> 94796.24 | I35: =H35 -> 94796.24 | J35: =ROUND((-G35),0)+P35 -> 189591.24 | K35: -59269.126 | L35: 0 | N35: =-K35 -> 59269.126 | O35: =ROUND((J35+N35),0) + P35 -> 248860.24 | P35: =P34+0.01 -> 0.24
A36: 6ºA | B36: 28 | C36: Morandi, Victoria Ayelen | Calvo, Luciano Ezequiel | D36: 0.0187 | E36: 489861.01 | F36: 45786 | G36: -452316.22 | H36: =ROUND((J36/2),0)+P36 -> 226158.25 | I36: =H36 -> 226158.25 | J36: =ROUND((-G36),0)+P36 -> 452316.25 | K36: -37544.789 | L36: 0 | M36: 0 | N36: =-K36 -> 37544.789 | O36: =ROUND((J36+N36),0) + P36 -> 489861.25 | P36: =P35+0.01 -> 0.25
A37: 6ºB | C37: GRIZEK RUBEN EDUARDO (ex Orellano) | D37: 0.0073 | E37: 191229.16 | F37: 45789 | G37: -175787.47 | H37: =ROUND((J37/2),0)+P37 -> 87894.26 | I37: =H37 -> 87894.26 | J37: =ROUND((-G37),0)+P37 -> 175787.26 | K37: -15441.693 | L37: 0 | M37: 0 | N37: =-K37 -> 15441.693 | O37: =ROUND((J37+N37),0) + P37 -> 191229.26 | P37: =P36+0.01 -> 0.26
A38: 6ºC | B38: 33 | C38: Nuñez Leonel - Corrieri Giuliana | D38: 0.0197 | E38: 516056.79 | F38: 45793 | G38: -471560.19 | H38: =ROUND((J38/2),0)+P38 -> 235780.27 | I38: =H38 -> 235780.27 | J38: =ROUND((-G38),0)+P38 -> 471560.27 | K38: -44496.598 | L38: 0 | M38: 0 | N38: =-K38 -> 44496.598 | O38: =ROUND((J38+N38),0) + P38 -> 516057.27 | P38: =P37+0.01 -> 0.27 | Q38: COCHERA 33 | R38: COCHERA 33
A39: 6ºD | B39: 44 | C39: ANCHIPI GASTON (Cedido x Hecimovic)Hecimovic, Mariano Hernán (Cedido x Lopez Malara, Ramiro Alejandro) | D39: 0.0117 | E39: 306490.58 | F39: 45800 | G39: -277127.34 | H39: =ROUND((J39/2),0)+P39 -> 138564.28 | I39: =H39 -> 138564.28 | J39: =ROUND((-G39),0)+P39 -> 277127.28 | K39: -29363.237 | L39: 0 | M39: 238127.28 | N39: =-K39 -> 29363.237 | O39: =ROUND((J39+N39),0) + P39 -> 306491.28 | P39: =P38+0.01 -> 0.28
A40: 6ºE | C40: Dieci, Matias Orlando | D40: 0.0087 | E40: 227903.25 | F40: 45800 | G40: -206069.05 | H40: =ROUND((J40/2),0)+P40 -> 103035.29 | I40: =H40 -> 103035.29 | J40: =ROUND((-G40),0)+P40 -> 206069.29 | K40: -21834.202 | L40: 0 | M40: 0 | N40: =-K40 -> 21834.202 | O40: =ROUND((J40+N40),0) + P40 -> 227903.29 | P40: =P39+0.01 -> 0.29
A41: 6ºF | C41: ALEXIA JOANA MAZZIA | D41: 0.0095 | E41: 248859.87 | F41: 45800 | G41: -225017.93 | H41: =ROUND((J41/2),0)+P41 -> 112509.3 | I41: =H41 -> 112509.3 | J41: =ROUND((-G41),0)+P41 -> 225018.3 | K41: -23841.945 | L41: 0 | M41: 0 | N41: =-K41 -> 23841.945 | O41: =ROUND((J41+N41),0) + P41 -> 248860.3 | P41: =P40+0.01 -> 0.3
A42: 7ºA | B42: 7 | C42: Campelo, Mariano | D42: 0.0187 | E42: 489861.01 | F42: 45806 | G42: -435275.01 | H42: =ROUND((J42/2),0)+P42 -> 217638.31 | I42: =H42 -> 217638.31 | J42: =ROUND((-G42),0)+P42 -> 435275.31 | K42: -54586.004 | L42: 0 | M42: 0 | N42: =-K42 -> 54586.004 | O42: =ROUND((J42+N42),0) + P42 -> 489861.31 | P42: =P41+0.01 -> 0.31
A43: 7ºB | B43: 3 | C43: Paes, Yazmin Luciana | D43: 0.0096 | E43: 251479.45 | F43: 45775 | G43: -235991.15 | H43: =ROUND((J43/2),0)+P43 -> 117996.32 | I43: =H43 -> 117996.32 | J43: =ROUND((-G43),0)+P43 -> 235991.32 | K43: -15488.301 | L43: 0 | M43: 0 | N43: =-K43 -> 15488.301 | O43: =ROUND((J43+N43),0) + P43 -> 251480.32 | P43: =P42+0.01 -> 0.32
A44: 7ºC | B44: 24 | C44: Gonzalez Fedullo, Roxana y Valeria | D44: 0.0197 | E44: 516056.79 | F44: 45793 | G44: -471560.19 | H44: =ROUND((J44/2),0)+P44 -> 235780.33 | I44: =H44 -> 235780.33 | J44: =ROUND((-G44),0)+P44 -> 471560.33 | K44: -44496.598 | L44: 0 | M44: 0 | N44: =-K44 -> 44496.598 | O44: =ROUND((J44+N44),0) + P44 -> 516057.33 | P44: =P43+0.01 -> 0.33
A45: 7ºD | C45: Solleiro, Carolina Mabel | D45: 0.0094 | E45: 246240.29 | F45: 45786 | G45: -227367.51 | H45: =ROUND((J45/2),0)+P45 -> 113684.34 | I45: =H45 -> 113684.34 | J45: =ROUND((-G45),0)+P45 -> 227368.34 | K45: -18872.782 | L45: 0 | M45: 21247 | N45: =-K45 -> 18872.782 | O45: =ROUND((J45+N45),0) + P45 -> 246241.34 | P45: =P44+0.01 -> 0.34 | Q45: Walter Javier Dimiziunas
A46: 7ºE | C46: Nuñez Leyes Javier Damian | D46: 0.0087 | E46: 227903.25 | F46: 45807 | G46: -201632.4 | H46: =ROUND((J46/2),0)+P46 -> 100816.35 | I46: =H46 -> 100816.35 | J46: =ROUND((-G46),0)+P46 -> 201632.35 | K46: -26270.852 | L46: 0 | M46: 0 | N46: =-K46 -> 26270.852 | O46: =ROUND((J46+N46),0) + P46 -> 227903.35 | P46: =P45+0.01 -> 0.35
A47: 7ºF | C47: Puente, Matias | D47: 0.0095 | E47: 248859.87 | F47: 45786 | G47: -229786.32 | H47: =ROUND((J47/2),0)+P47 -> 114893.36 | I47: =H47 -> 114893.36 | J47: =ROUND((-G47),0)+P47 -> 229786.36 | K47: -19073.556 | L47: 0 | M47: 0 | N47: =-K47 -> 19073.556 | O47: =ROUND((J47+N47),0) + P47 -> 248860.36 | P47: =P46+0.01 -> 0.36
A48: 8ºA | B48: 8 | C48: Campelo, Mariano | D48: 0.0187 | E48: 489861.01 | F48: 45793 | G48: -447623.12 | H48: =ROUND((J48/2),0)+P48 -> 223812.37 | I48: =H48 -> 223812.37 | J48: =ROUND((-G48),0)+P48 -> 447623.37 | K48: -42237.887 | L48: 0 | M48: 0 | N48: =-K48 -> 42237.887 | O48: =ROUND((J48+N48),0) + P48 -> 489861.37 | P48: =P47+0.01 -> 0.37
A49: 8ºB | C49: Morvillo, Mariana Yanil | D49: 0.0073 | E49: 191229.16 | F49: 45805 | G49: -170654.57 | H49: =ROUND((J49/2),0)+P49 -> 85328.38 | I49: =H49 -> 85328.38 | J49: =ROUND((-G49),0)+P49 -> 170655.38 | K49: -20574.591 | L49: 0 | M49: 0 | N49: =-K49 -> 20574.591 | O49: =ROUND((J49+N49),0) + P49 -> 191230.38 | P49: =P48+0.01 -> 0.38
A50: 8ºC | B50: 14 | C50: Frontale, Federico Carlos | Celentano, Alejandra Verónica | D50: 0.0197 | E50: 516056.79 | F50: 45805 | G50: -460533.57 | H50: =ROUND((J50/2),0)+P50 -> 230267.39 | I50: =H50 -> 230267.39 | J50: =ROUND((-G50),0)+P50 -> 460534.39 | K50: -55523.211 | L50: 0 | M50: =IF(L50=H50,I50,J50) -> 460534.39 | N50: =-K50 -> 55523.211 | O50: =ROUND((J50+N50),0) + P50 -> 516058.39 | P50: =P49+0.01 -> 0.39
A51: 8ºD | C51: Argul, Sergio Walter - Taboada, María Paz | D51: 0.0094 | E51: 246240.29 | F51: 45793 | G51: -225008.41 | H51: =ROUND((J51/2),0)+P51 -> 112504.4 | I51: =H51 -> 112504.4 | J51: =ROUND((-G51),0)+P51 -> 225008.4 | K51: -21231.879 | L51: 0 | M51: 0 | N51: =-K51 -> 21231.879 | O51: =ROUND((J51+N51),0) + P51 -> 246240.4 | P51: =P50+0.01 -> 0.4
A52: 8ºE | C52: Lorenzo, Sergio Ariel | D52: 0.0087 | E52: 227903.25 | F52: 45800 | G52: -206069.05 | H52: =ROUND((J52/2),0)+P52 -> 103035.41 | I52: =H52 -> 103035.41 | J52: =ROUND((-G52),0)+P52 -> 206069.41 | K52: -21834.202 | L52: 0 | M52: 0 | N52: =-K52 -> 21834.202 | O52: =ROUND((J52+N52),0) + P52 -> 227904.41 | P52: =P51+0.01 -> 0.41 | R52: el de sergio
A53: 8ºF | B53: 5 | C53: Arias, Mariana Laura | D53: 0.0118 | E53: 309110.16 | F53: 45793 | G53: -282457.37 | H53: =ROUND((J53/2),0)+P53 -> 141229.42 | I53: =H53 -> 141229.42 | J53: =ROUND((-G53),0)+P53 -> 282457.42 | K53: -26652.785 | L53: 0 | M53: 0 | N53: =-K53 -> 26652.785 | O53: =ROUND((J53+N53),0) + P53 -> 309110.42 | P53: =P52+0.01 -> 0.42 | Q53: alonso sabrina eugenia
A54: 9ºA | B54: 26 | C54: Fanjul, Alejandro Rubén Marcelo | D54: 0.0187 | E54: 489861.01 | F54: 45793 | G54: -447623.12 | H54: =ROUND((J54/2),0)+P54 -> 223812.43 | I54: =H54 -> 223812.43 | J54: =ROUND((-G54),0)+P54 -> 447623.43 | K54: -42237.887 | L54: 0 | M54: 0 | N54: =-K54 -> 42237.887 | O54: =ROUND((J54+N54),0) + P54 -> 489861.43 | P54: =P53+0.01 -> 0.43
A55: 9ºB | C55: Fanjul, Alejandro Rubén Marcelo | D55: 0.0073 | E55: 191229.16 | F55: 45793 | G55: -174740.58 | H55: =ROUND((J55/2),0)+P55 -> 87371.44 | I55: =H55 -> 87371.44 | J55: =ROUND((-G55),0)+P55 -> 174741.44 | K55: -16488.587 | L55: 0 | M55: 0 | N55: =-K55 -> 16488.587 | O55: =ROUND((J55+N55),0) + P55 -> 191230.44 | P55: =P54+0.01 -> 0.44
A56: 9ºC | B56: 43 | C56: Franchino, Mauro | D56: 0.0197 | E56: 516056.79 | F56: 45770 | G56: -487804.98 | H56: =ROUND((J56/2),0)+P56 -> 243903.45 | I56: =H56 -> 243903.45 | J56: =ROUND((-G56),0)+P56 -> 487805.45 | K56: -28251.808 | L56: 0 | M56: 0 | N56: =-K56 -> 28251.808 | O56: =ROUND((J56+N56),0) + P56 -> 516057.45 | P56: =P55+0.01 -> 0.45
A57: 9ºD | B57: 10 | C57: Cerra, Antonio Osvaldo | D57: 0.0117 | E57: 306490.58 | F57: 45793 | G57: -280063.66 | H57: =ROUND((J57/2),0)+P57 -> 140032.46 | I57: =H57 -> 140032.46 | J57: =ROUND((-G57),0)+P57 -> 280064.46 | K57: -26426.913 | L57: 0 | M57: 0 | N57: =-K57 -> 26426.913 | O57: =ROUND((J57+N57),0) + P57 -> 306491.46 | P57: =P56+0.01 -> 0.46
A58: 9ºE | B58: 12 | C58: Dieci, Matias Orlando | D58: 0.011 | E58: 288153.53 | F58: 45800 | G58: -260547.07 | H58: =ROUND((J58/2),0)+P58 -> 130274.47 | I58: =H58 -> 130274.47 | J58: =ROUND((-G58),0)+P58 -> 260547.47 | K58: -27606.462 | L58: 0 | M58: 0 | N58: =-K58 -> 27606.462 | O58: =ROUND((J58+N58),0) + P58 -> 288154.47 | P58: =P57+0.01 -> 0.47
A59: 9ºF | B59: 20 | C59: Rosales, Rubén Darío | D59: 0.0118 | E59: 309110.16 | F59: 45805 | G59: -275852.6 | H59: =ROUND((J59/2),0)+P59 -> 137927.48 | I59: =H59 -> 137927.48 | J59: =ROUND((-G59),0)+P59 -> 275853.48 | K59: -33257.558 | L59: 0 | M59: 0 | N59: =-K59 -> 33257.558 | O59: =ROUND((J59+N59),0) + P59 -> 309111.48 | P59: =P58+0.01 -> 0.48
A60: 10ºA | B60: 4 | C60: Guillermo Antonio PUISYS (EX Fernández, Marcela Fabiana) | D60: 0.0187 | E60: 489861.01 | F60: 45793 | G60: -447623.12 | H60: =ROUND((J60/2),0)+P60 -> 223812.49 | I60: =H60 -> 223812.49 | J60: =ROUND((-G60),0)+P60 -> 447623.49 | K60: -42237.887 | L60: 0 | M60: 0 | N60: =-K60 -> 42237.887 | O60: =ROUND((J60+N60),0) + P60 -> 489861.49 | P60: =P59+0.01 -> 0.49
A61: 10ºB | C61: Lange, Gustavo Daniel | D61: 0.0073 | E61: 191229.16 | F61: 45793 | G61: -174740.58 | H61: =ROUND((J61/2),0)+P61 -> 87371.5 | I61: =H61 -> 87371.5 | J61: =ROUND((-G61),0)+P61 -> 174741.5 | K61: -16488.587 | L61: 0 | M61: =IF(L61=H61,I61,J61) -> 174741.5 | N61: =-K61 -> 16488.587 | O61: =ROUND((J61+N61),0) + P61 -> 191230.5 | P61: =P60+0.01 -> 0.5
A62: 10ºC | B62: 17 | C62: Espósito, Franco Ezequiel | D62: 0.0197 | E62: 516056.79 | F62: 45796 | G62: -469441.3 | H62: =ROUND((J62/2),0)+P62 -> 234721.51 | I62: =H62 -> 234721.51 | J62: =ROUND((-G62),0)+P62 -> 469441.51 | K62: -46615.483 | L62: 0 | M62: 0 | N62: =-K62 -> 46615.483 | O62: =ROUND((J62+N62),0) + P62 -> 516057.51 | P62: =P61+0.01 -> 0.51
A63: 10ºD | C63: Lobato, Lorena - Vega, Maximiliano | D63: 0.0094 | E63: 246240.29 | F63: 45863 | G63: -164899.57 | H63: =ROUND((J63/2),0)+P63 -> 82450.52 | I63: =H63 -> 82450.52 | J63: =ROUND((-G63),0)+P63 -> 164900.52 | K63: -81340.722 | L63: 0 | M63: 0 | N63: =-K63 -> 81340.722 | O63: =ROUND((J63+N63),0) + P63 -> 246241.52 | P63: =P62+0.01 -> 0.52
A64: 10ºE | C64: Hecimovic, Mariano Hernán | D64: 0.0087 | E64: 227903.25 | F64: 45800 | G64: -206069.05 | H64: =ROUND((J64/2),0)+P64 -> 103035.53 | I64: =H64 -> 103035.53 | J64: =ROUND((-G64),0)+P64 -> 206069.53 | K64: -21834.202 | L64: 0 | M64: 0 | N64: =-K64 -> 21834.202 | O64: =ROUND((J64+N64),0) + P64 -> 227904.53 | P64: =P63+0.01 -> 0.53 | R64: mariano hecimovic
A65: 10ºF | B65: 23 | C65: Ramos, Sergio Eugenio | D65: 0.0118 | E65: 309110.16 | F65: 45786 | G65: -285418.79 | H65: =ROUND((J65/2),0)+P65 -> 142710.54 | I65: =H65 -> 142710.54 | J65: =ROUND((-G65),0)+P65 -> 285419.54 | K65: -23691.364 | L65: 0 | M65: =IF(L65=H65,I65,J65) -> 285419.54 | N65: =-K65 -> 23691.364 | O65: =ROUND((J65+N65),0) + P65 -> 309111.54 | P65: =P64+0.01 -> 0.54
A66: 11ºA/B | B66: 21 | C66: Mosquera, Julio Rodolfo | Cuzzolino, Daniela Carol | D66: 0.0258 | E66: 675851.02 | F66: 45775 | G66: -634226.21 | H66: =ROUND((J66/2),0)+P66 -> 317113.55 | I66: =H66 -> 317113.55 | J66: =ROUND((-G66),0)+P66 -> 634226.55 | K66: -41624.809 | L66: 0 | M66: 0 | N66: =-K66 -> 41624.809 | O66: =ROUND((J66+N66),0) + P66 -> 675851.55 | P66: =P65+0.01 -> 0.55
A67: 11ºC | B67: 41 | C67: Silvestre Villarruel Eduardo (EX De Mieri, Fernando Emanuel | D67: 0.0197 | E67: 516056.79 | F67: 45790 | G67: -473679.07 | H67: =ROUND((J67/2),0)+P67 -> 236840.56 | I67: =H67 -> 236840.56 | J67: =ROUND((-G67),0)+P67 -> 473679.56 | K67: -42377.712 | L67: 0 | M67: 0 | N67: =-K67 -> 42377.712 | O67: =ROUND((J67+N67),0) + P67 -> 516057.56 | P67: =P66+0.01 -> 0.56
A68: 11ºD | B68: 2 | C68: Yudchak, Carlos Alberto | D68: 0.0117 | E68: 306490.58 | G68: 0 | K68: -306490.58 | L68: 0 | M68: =IF(L68=H68,I68,J68) -> 0 | N68: =-K68 -> 306490.58 | O68: =ROUND((J68+N68),0) + P68 -> 306491.57 | P68: =P67+0.01 -> 0.57
A69: 11ºE | C69: Argúl, Adrián Norberto | D69: 0.0087 | E69: 227903.25 | F69: 45775 | G69: -213866.98 | H69: =ROUND((J69/2),0)+P69 -> 106934.58 | I69: =H69 -> 106934.58 | J69: =ROUND((-G69),0)+P69 -> 213867.58 | K69: -14036.273 | L69: 0 | M69: =IF(L69=H69,I69,J69) -> 213867.58 | N69: =-K69 -> 14036.273 | O69: =ROUND((J69+N69),0) + P69 -> 227904.58 | P69: =P68+0.01 -> 0.58
A70: 11ºF | B70: 19 | C70: Lobato, Lorena - Vega, Maximiliano | D70: 0.0118 | E70: 309110.16 | F70: 45821 | G70: -256859.22 | H70: =ROUND((J70/2),0)+P70 -> 128430.59 | I70: =H70 -> 128430.59 | J70: =ROUND((-G70),0)+P70 -> 256859.59 | K70: -52250.939 | L70: 0 | M70: 0 | N70: =-K70 -> 52250.939 | O70: =ROUND((J70+N70),0) + P70 -> 309111.59 | P70: =P69+0.01 -> 0.59
A71: 12ºA/B | B71: 36 | C71: Luciano, Carmen Veronica - Rey, Javier Pablo | D71: 0.0258 | E71: 675851.02 | F71: 45891 | G71: -382821.8 | H71: =ROUND((J71/2),0)+P71 -> 191411.6 | I71: =H71 -> 191411.6 | J71: =ROUND((-G71),0)+P71 -> 382822.6 | K71: -293029.22 | L71: 0 | M71: 0 | N71: =-K71 -> 293029.22 | O71: =ROUND((J71+N71),0) + P71 -> 675852.6 | P71: =P70+0.01 -> 0.6
A72: 12ºC | B72: 15 | C72: Hernandez, Marisa Beatriz - Hernandez, Adrian Jose | D72: 0.0197 | E72: 516056.79 | F72: 45800 | G72: -466616.12 | H72: =ROUND((J72/2),0)+P72 -> 233308.61 | I72: =H72 -> 233308.61 | J72: =ROUND((-G72),0)+P72 -> 466616.61 | K72: -49440.664 | L72: 0 | M72: 0 | N72: =-K72 -> 49440.664 | O72: =ROUND((J72+N72),0) + P72 -> 516057.61 | P72: =P71+0.01 -> 0.61
A73: 12ºD | C73: Morini, Micaela | D73: 0.0094 | E73: 246240.29 | F73: 45784 | G73: -228041.54 | H73: =ROUND((J73/2),0)+P73 -> 114021.62 | I73: =H73 -> 114021.62 | J73: =ROUND((-G73),0)+P73 -> 228042.62 | K73: -18198.754 | L73: 0 | M73: =IF(L73=H73,I73,J73) -> 228042.62 | N73: =-K73 -> 18198.754 | O73: =ROUND((J73+N73),0) + P73 -> 246241.62 | P73: =P72+0.01 -> 0.62
A74: 12ºE | B74: 40 | C74: Armerding, Jorge | D74: 0.011 | E74: 288153.53 | F74: 45784 | G74: -266857.12 | H74: =ROUND((J74/2),0)+P74 -> 133429.63 | I74: =H74 -> 133429.63 | J74: =ROUND((-G74),0)+P74 -> 266857.63 | K74: -21296.414 | L74: 0 | M74: 133429.63 | N74: =-K74 -> 21296.414 | O74: =ROUND((J74+N74),0) + P74 -> 288154.63 | P74: =P73+0.01 -> 0.63
A75: 12ºF | C75: Bilyj, Josefa Catalina | D75: 0.0095 | E75: 248859.87 | F75: 45786 | G75: -229786.32 | H75: =ROUND((J75/2),0)+P75 -> 114893.64 | I75: =H75 -> 114893.64 | J75: =ROUND((-G75),0)+P75 -> 229786.64 | K75: -19073.556 | L75: 0 | M75: 0 | N75: =-K75 -> 19073.556 | O75: =ROUND((J75+N75),0) + P75 -> 248860.64 | P75: =P74+0.01 -> 0.64
A76: 13ºA/B | B76: 9 | C76: Gazzaneo Francisco | D76: 0.0258 | E76: 675851.02 | F76: 45835 | G76: -525270.52 | H76: =ROUND((J76/2),0)+P76 -> 262636.65 | I76: =H76 -> 262636.65 | J76: =ROUND((-G76),0)+P76 -> 525271.65 | K76: -150580.49 | L76: 0 | M76: 0 | N76: =-K76 -> 150580.49 | O76: =ROUND((J76+N76),0) + P76 -> 675852.65 | P76: =P75+0.01 -> 0.65
A77: 13ºC | B77: 35 | C77: Argentino, Javier Leonardo | D77: 0.0197 | E77: 516056.79 | F77: 45784 | G77: -477916.84 | H77: =ROUND((J77/2),0)+P77 -> 238959.66 | I77: =H77 -> 238959.66 | J77: =ROUND((-G77),0)+P77 -> 477917.66 | K77: -38139.941 | L77: 0 | M77: 238959.66 | N77: =-K77 -> 38139.941 | O77: =ROUND((J77+N77),0) + P77 -> 516058.66 | P77: =P76+0.01 -> 0.66
A78: 13ºD | B78: 13-32 | C78: Scardigno, Gabriela Susana - Ripoll, Luis Alberto | D78: 0.014 | E78: 366740.86 | F78: 45786 | G78: -338632.46 | H78: =ROUND((J78/2),0)+P78 -> 169316.67 | I78: =H78 -> 169316.67 | J78: =ROUND((-G78),0)+P78 -> 338632.67 | K78: -28108.398 | L78: 0 | M78: 0 | N78: =-K78 -> 28108.398 | O78: =ROUND((J78+N78),0) + P78 -> 366741.67 | P78: =P77+0.01 -> 0.67
A79: 13ºE | B79: 42 | C79: Quiñones, Carlos Eduardo | D79: 0.011 | E79: 288153.53 | F79: 45777 | G79: -269617.77 | H79: =ROUND((J79/2),0)+P79 -> 134809.68 | I79: =H79 -> 134809.68 | J79: =ROUND((-G79),0)+P79 -> 269618.68 | K79: -18535.768 | L79: 0 | M79: 0 | N79: =-K79 -> 18535.768 | O79: =ROUND((J79+N79),0) + P79 -> 288154.68 | P79: =P78+0.01 -> 0.68
A80: 13ºF | B80: 27 | C80: Mosquera, José Elias | D80: 0.0118 | E80: 309110.16 | F80: 45800 | G80: -279495.95 | H80: =ROUND((J80/2),0)+P80 -> 139748.69 | I80: =H80 -> 139748.69 | J80: =ROUND((-G80),0)+P80 -> 279496.69 | K80: -29614.205 | L80: 0 | M80: 0 | N80: =-K80 -> 29614.205 | O80: =ROUND((J80+N80),0) + P80 -> 309111.69 | P80: =P79+0.01 -> 0.69
D82: =SUM(D7:D81) -> 0.9979 | E82: =SUM(E7:E81) -> 26140765 | F82: =SUM(F7:F81) -> 3344000 | G82: =SUM(G7:G81) -> -22258385 | L82: =SUM(L7:L80) -> 34752 | M82: =SUM(M7:M80) -> 2933880.4 | O82: =SUM(O7:O81) -> 26140812

Sheet DEUDA AYALA
C3: DEUDA SR. AYALA AL 04/09/2026
C4: UF: | D4: Propietario: | G4: Deuda a abonar antes del 17/09
C5: =PRORRATEO!C31 -> 3ºF | D5: =PRORRATEO!D31 -> Campelo, Mariano | G5: =PRORRATEO!N31 -> -7072.88
G7: Deuda ARBA 3F
G8: 0
C9: UF: | D9: Propietario: | G9: Deuda a abonar antes del 17/09
C10: =PRORRATEO!C37 -> 4ºF | D10: =PRORRATEO!D37 -> Campelo, Mariano | G10: =PRORRATEO!N37 -> -7071.82
G12: Deuda ARBA 4F
G13: 0
C14: UF: | D14: Propietario: | G14: Deuda a abonar antes del 17/09
C15: =PRORRATEO!C43 -> 5ºF | D15: =PRORRATEO!D43 -> Ayala, Roberto Adrian | G15: =PRORRATEO!N43 -> -7072.76
G17: Deuda ARBA 5F
G18: 0
C20: TOTAL DEUDA | G20: =G15+G10+G5 -> -21217.46
