Workbook

Sheet detalle y gastos
B2: CANCIANI, Carolina | C2: MP 1148
B3: Tel. 11 5320-2676
B4: consorciosrc13@gmail.com
A7: EDIFICIO ROSALES 624 | B7: LIQUIDACIÓN EXPENSAS MARZO 2025 | C7: Vto. 17/04
A10: Teléfonos útiles
A11: EDESUR 0800-333-3787
A12: AySA 0800-321-2482
A13: Metrogas 0800-333-6427
A15: GASTOS ORDINARIOS
A16: ABONOS y SERVICIOS
A18: Seguro de consorcio obligatorio - federacion patronal - poliza nro. 2027630 | C18: 76654
A19: AYSA | C19: 372886.04
A20: Ascensores Lema | C20: 85000
A21: ARBA - Cuota 4 del plan | C21: 1034026.5
A22: Gastos administrativos - Traspaso de administracion | C22: 200000
A23: RC Adm Cons CANCIANI, Carolina | B23: Honorarios administracion | C23: 89200 | F23: Subidos en EN3R0
C24: =SUM(C17:C23) -> 1857766.5
A25: LIMPIEZA / MANTENIMIENTO / GASTOS GENERALES
A26: Sueldo personal de limpieza y maestranza | C26: =384067+ (384067*3%) -> 395589.01
A27: Seguro de vida Sra encargada | C27: 7458
A28: Articulos de limpieza | C28: 0
A29: Fumigacion - Mes anterior | C29: 55000
A30: Fumigacion | C30: 55000
A31: PREVISION ORDINARIA
C32: =SUM(C25:C31) -> 513047.01
A33: TOTAL GASTOS ORDINARIOS (A) | C33: =+C32+C24 -> 2370813.5
A35: GASTOS EXTRAORDINARIOS
A40: PREVISION EXTRAORDINARIA - ARBA | C40: 0
A42: TOTAL GASTOS EXTRAORDINARIOS (B) | C42: =+C36+C37+C38+C41 -> 0
A44: TOTAL GENERAL DE GASTOS (A) + (B) | C44: =+C42+C33 -> 2370813.5
A47: CAJA ANTERIOR | C47: 1039280.7
A48: EGRESOS DEL MES DE MARZO | C48: =-(C44-C31) -> -2370813.5
A49: INGRESOS CORRESPONDIENTES AL PAGO DE EXPENSAS | C49: ='prorrateo '!F31 -> 3661916.3
A50: EDESUR | C50: -1024355.4
A51: PUNITORIOS MAL COBRADOS | C51: 0
A52: Saldo al cierre $ (pesos) | C52: =SUM(C47:C51) -> 1306028
A56: CAJA EXTRAORDINARIA
A57: Egreso extraordinario | C57: =-C42 -> 0
A60: TOTAL | C60: =SUM(C56:C59) -> 0
A61: ATENCIÓN: Al momento de abonar en efectivo las expensas (dado que no se dispone de cuenta bancaria), deberán cancelar el monto total correspondiente, que incluye tanto las expensas como el consumo de Edesur de cada unidad funcional. Les recordamos que el pago debe realizarse con dinero justo.

Sheet prorrateo 
A1: Expensas ordinarias: | B1: =N1-L1 -> 1336787 | D1: 1667839.1 | E1: Gastos extraordinarios: | G1: 0 | I1: ARBA: | L1: =O1 -> 1034026.5 | N1: 2370813.5 | O1: 1034026.5
A2: Propietarios | B2: Inquilinos | C2: UNIDAD FUNCIONAL | D2: % | E2: SALDO ANTERIOR | F2: SALDO ABONADO | G2: SALDO | H2: PUNITORIOS 4% | I2: ORDINARIAS | J2: EDESUR | K2: EXTRAORD. | L2: ARBA | M2: A PAGAR | O2: SIN EDESUR
A3: Ferrea Nestor | B3: Gabriel | C3: 1ro. "A" | D3: 5.11 | E3: 196577.36 | F3: =E3 -> 196577.36 | G3: =E3-F3 -> 0 | H3: =IF(G3>0,G3*4%,0) -> 0 | I3: =B$1*D3/100 -> 68309.818 | J3: =Edesur!N10 -> 54290.038 | K3: =G$1*D3/100 -> 0 | L3: =L$1*D3/100 -> 52838.754 | M3: =I3+G3+L3+K3+H3+J3 -> 175438.61 | O3: =M3-J3 -> 121148.57
A4: Gnecchi Nicolas | C4: 1ro. "B" | D4: 5.09 | E4: 305245.84 | G4: =E4-F4 -> 305245.84 | H4: =IF(G4>0,G4*4%,0) -> 12209.833 | I4: =B$1*D4/100 -> 68042.461 | J4: =Edesur!N11 -> 45259.409 | K4: =G$1*D4/100 -> 0 | L4: =L$1*D4/100 -> 52631.949 | M4: =I4+G4+L4+K4+H4+J4 -> 483389.49 | O4: =M4-J4 -> 438130.08
A5: Triñanes Gaston | C5: 2do. "A" | D5: 5.04 | E5: 204343.44 | F5: =240944.56-F23 -> 204343.44 | G5: =E5-F5 -> -0.0052311113 | H5: =IF(G5>0,G5*4%,0) -> 0 | I5: =B$1*D5/100 -> 67374.067 | J5: =Edesur!N12 -> 53829.498 | K5: =G$1*D5/100 -> 0 | L5: =L$1*D5/100 -> 52114.936 | M5: =I5+G5+L5+K5+H5+J5 -> 173318.5 | O5: =M5-J5 -> 119489
A6: Nuñez Eva | C6: 2do. "B" | D6: 5.21 | E6: 188205.46 | F6: =E6 -> 188205.46 | G6: =E6-F6 -> 0 | H6: =IF(G6>0,G6*4%,0) -> 0 | I6: =B$1*D6/100 -> 69646.605 | J6: =Edesur!N13 -> 51555.542 | K6: =G$1*D6/100 -> 0 | L6: =L$1*D6/100 -> 53872.781 | M6: =I6+G6+L6+K6+H6+J6 -> 175074.93 | O6: =M6-J6 -> 123519.39
A7: Triñanes Gaston | B7: Leandro | C7: 3ro. "A" | D7: 5.11 | E7: 199212.77 | F7: =235813.89-F28 -> 199212.77 | G7: =E7-F7 -> -0.0027831 | H7: =IF(G7>0,G7*4%,0) -> 0 | I7: =B$1*D7/100 -> 68309.818 | J7: =Edesur!N14 -> 56850.423 | K7: =G$1*D7/100 -> 0 | L7: =L$1*D7/100 -> 52838.754 | M7: =I7+G7+L7+K7+H7+J7 -> 177998.99 | O7: =M7-J7 -> 121148.57
A8: Grecco Pedro | C8: 3ro. "B" | D8: 5.09 | E8: 202248.94 | F8: =E8 -> 202248.94 | G8: =E8-F8 -> 0 | H8: =IF(G8>0,G8*4%,0) -> 0 | I8: =B$1*D8/100 -> 68042.461 | J8: =Edesur!N15 -> 52602.931 | K8: =G$1*D8/100 -> 0 | L8: =L$1*D8/100 -> 52631.949 | M8: =I8+G8+L8+K8+H8+J8 -> 173277.34 | O8: =M8-J8 -> 120674.41
A9: Mteljan Barbara | C9: 4to. "A" | D9: 5.11 | E9: 186016.94 | F9: =E9 -> 186016.94 | G9: =E9-F9 -> 0 | H9: =IF(G9>0,G9*4%,0) -> 0 | I9: =B$1*D9/100 -> 68309.818 | J9: =Edesur!N16 -> 52948.884 | K9: =G$1*D9/100 -> 0 | L9: =L$1*D9/100 -> 52838.754 | M9: =I9+G9+L9+K9+H9+J9 -> 174097.46 | O9: =M9-J9 -> 121148.57
A10: Carnevalli Christian | C10: 4to. "B" | D10: 5.09 | E10: 176391.67 | F10: =212992.98-F22 -> 176391.86 | G10: =E10-F10 -> -0.19544614 | I10: =B$1*D10/100 -> 68042.461 | J10: =Edesur!N17 -> 46563.048 | K10: =G$1*D10/100 -> 0 | L10: =L$1*D10/100 -> 52631.949 | M10: =I10+G10+L10+K10+H10+J10 -> 167237.26 | O10: =M10-J10 -> 120674.21
A11: Leonor | C11: 5to. "A" | D11: 5.04 | E11: 182106.54 | F11: =E11 -> 182106.54 | G11: =E11-F11 -> 0 | H11: =IF(G11>0,G11*4%,0) -> 0 | I11: =B$1*D11/100 -> 67374.067 | J11: =Edesur!N18 -> 50340.622 | K11: =G$1*D11/100 -> 0 | L11: =L$1*D11/100 -> 52114.936 | M11: =I11+G11+L11+K11+H11+J11 -> 169829.62 | O11: =M11-J11 -> 119489
A12: Strangio Federico | C12: 5to. "B" | D12: 5.21 | E12: 211989.84 | F12: =E12 -> 211989.84 | G12: =E12-F12 -> 0 | H12: =IF(G12>0,G12*4%,0) -> 0 | I12: =B$1*D12/100 -> 69646.605 | J12: =Edesur!N19 -> 62941.283 | K12: =G$1*D12/100 -> 0 | L12: =L$1*D12/100 -> 53872.781 | M12: =I12+G12+L12+K12+H12+J12 -> 186460.67 | O12: =M12-J12 -> 123519.39
A13: Senderowicz Rosalia | B13: Alejo | C13: 6to. "A" | D13: 5.11 | E13: 205111.98 | F13: =241713-F24 -> 205111.88 | G13: =E13-F13 -> 0.0966912 | H13: =IF(G13>0,G13*4%,0) -> 0.003867648 | I13: =B$1*D13/100 -> 68309.818 | J13: =Edesur!N20 -> 60142.347 | K13: =G$1*D13/100 -> 0 | L13: =L$1*D13/100 -> 52838.754 | M13: =I13+G13+L13+K13+H13+J13 -> 181291.02 | O13: =M13-J13 -> 121148.67
A14: Senderowicz Rosalia | B14: Anabella | C14: 6to. "B" | D14: 5.09 | E14: 180752.96 | G14: =E14-F14 -> 180752.96 | H14: =IF(G14>0,G14*4%,0) -> 7230.1185 | I14: =B$1*D14/100 -> 68042.461 | J14: =Edesur!N21 -> 50126.954 | K14: =G$1*D14/100 -> 0 | L14: =L$1*D14/100 -> 52631.949 | M14: =I14+G14+L14+K14+H14+J14 -> 358784.44 | O14: =M14-J14 -> 308657.49
A15: Alonso Graciela | B15: Facundo | C15: 7mo. "A" | D15: 5.04 | E15: 441931.81 | F15: =490000-F29 -> 404371.57 | G15: =E15-F15 -> 37560.244 | H15: =IF(G15>0,G15*4%,0) -> 1502.4098 | I15: =B$1*D15/100 -> 67374.067 | J15: =Edesur!N22 -> 55808.404 | K15: =G$1*D15/100 -> 0 | L15: =L$1*D15/100 -> 52114.936 | M15: =I15+G15+L15+K15+H15+J15 -> 214360.06 | O15: =M15-J15 -> 158551.66
A16: Perez Rodriguez | B16: Mariel | C16: 7mo. "B" | D16: 5.21 | E16: 200838.57 | F16: =237500-F21 -> 200898.88 | G16: =E16-F16 -> -60.311453 | H16: =IF(G16>0,G16*4%,0) -> 0 | I16: =B$1*D16/100 -> 69646.605 | J16: =Edesur!N23 -> 59171.046 | K16: =G$1*D16/100 -> 0 | L16: =L$1*D16/100 -> 53872.781 | M16: =I16+G16+L16+K16+H16+J16 -> 182630.12 | O16: =M16-J16 -> 123459.07
A17: Mourelos Pablo | C17: 8vo. "A" | D17: 5.04 | E17: 276073.05 | F17: =E17 -> 276073.05 | G17: =E17-F17 -> 0 | H17: =IF(G17>0,G17*4%,0) -> 0 | I17: =B$1*D17/100 -> 67374.067 | J17: =Edesur!N24 -> 46701.686 | K17: =G$1*D17/100 -> 0 | L17: =L$1*D17/100 -> 52114.936 | M17: =I17+G17+L17+K17+H17+J17 -> 166190.69 | O17: =M17-J17 -> 119489
A18: Calabria Carlos/Giarrizzo Silvia | C18: 8vo. "B" | D18: 5.21 | E18: 191713.1 | F18: =E18 -> 191713.1 | G18: =E18-F18 -> 0 | H18: =IF(G18>0,G18*4%,0) -> 0 | I18: =B$1*D18/100 -> 69646.605 | J18: =Edesur!N25 -> 52333.974 | K18: =G$1*D18/100 -> 0 | L18: =L$1*D18/100 -> 53872.781 | M18: =I18+G18+L18+K18+H18+J18 -> 175853.36 | O18: =M18-J18 -> 123519.39
A19: Ariel | C19: 9no. "A" | D19: 7.4 | E19: 294818.42 | F19: =E19 -> 294818.42 | G19: =E19-F19 -> 0 | H19: =IF(G19>0,G19*4%,0) -> 0 | I19: =B$1*D19/100 -> 98922.242 | J19: =Edesur!N26 -> 77235.706 | K19: =G$1*D19/100 -> 0 | L19: =L$1*D19/100 -> 76517.961 | M19: =I19+G19+L19+K19+H19+J19 -> 252675.91 | O19: =M19-J19 -> 175440.2
A20: Espacio Edesur | C20: COCHERA 1 | D20: 1.08 | E20: 435982.32 | F20: 0 | G20: =E20-F20 -> 435982.32 | I20: =B$1*D20/100 -> 14437.3 | J20: =Edesur!N27 -> 9565.3655 | K20: =G$1*D20/100 -> 0 | L20: =L$1*D20/100 -> 11167.486 | M20: =I20+G20+L20+K20+H20+J20 -> 471152.47 | O20: =M20-J20 -> 461587.1
B21: Mariel | C21: COCHERA 2 | D21: 1.08 | E21: 36601.116 | F21: =E21 -> 36601.116 | G21: =E21-F21 -> 0 | H21: =IF(G21>0,G21*4%,0) -> 0 | I21: =B$1*D21/100 -> 14437.3 | J21: =Edesur!N28 -> 9565.3655 | K21: =G$1*D21/100 -> 0 | L21: =L$1*D21/100 -> 11167.486 | M21: =I21+G21+L21+K21+H21+J21 -> 35170.152 | O21: =M21-J21 -> 25604.786
A22: Carnevalli Christian | C22: COCHERA 3 | D22: 1.08 | E22: 36601.116 | F22: =E22 -> 36601.116 | G22: =E22-F22 -> 0 | H22: =IF(G22>0,G22*4%,0) -> 0 | I22: =B$1*D22/100 -> 14437.3 | J22: =Edesur!N29 -> 9565.3655 | K22: =G$1*D22/100 -> 0 | L22: =L$1*D22/100 -> 11167.486 | M22: =I22+G22+L22+K22+H22+J22 -> 35170.152 | O22: =M22-J22 -> 25604.786
A23: Triñanes Gaston | C23: COCHERA 4 | D23: 1.08 | E23: 36601.116 | F23: =E23 -> 36601.116 | G23: =E23-F23 -> 0 | H23: =IF(G23>0,G23*4%,0) -> 0 | I23: =B$1*D23/100 -> 14437.3 | J23: =Edesur!N30 -> 9565.3655 | K23: =G$1*D23/100 -> 0 | L23: =L$1*D23/100 -> 11167.486 | M23: =I23+G23+L23+K23+H23+J23 -> 35170.152 | O23: =M23-J23 -> 25604.786
A24: Senderowicz Rosalia | B24: Alejo | C24: COCHERA 5 | D24: 1.08 | E24: 36601.116 | F24: =E24 -> 36601.116 | G24: =E24-F24 -> 0 | H24: =IF(G24>0,G24*4%,0) -> 0 | I24: =B$1*D24/100 -> 14437.3 | J24: =Edesur!N31 -> 9565.3655 | K24: =G$1*D24/100 -> 0 | L24: =L$1*D24/100 -> 11167.486 | M24: =I24+G24+L24+K24+H24+J24 -> 35170.152 | O24: =M24-J24 -> 25604.786
A25: Senderowicz Rosalia | B25: Anabella | C25: COCHERA 6 | D25: 1.08 | E25: 36601.116 | G25: =E25-F25 -> 36601.116 | H25: =IF(G25>0,G25*4%,0) -> 1464.0446 | I25: =B$1*D25/100 -> 14437.3 | J25: =Edesur!N32 -> 9565.3655 | K25: =G$1*D25/100 -> 0 | L25: =L$1*D25/100 -> 11167.486 | M25: =I25+G25+L25+K25+H25+J25 -> 73235.313 | O25: =M25-J25 -> 63669.947
A26: Ariel | C26: COCHERA 7 | D26: 1.08 | E26: 36601.116 | F26: =E26 -> 36601.116 | G26: =E26-F26 -> 0 | H26: =IF(G26>0,G26*4%,0) -> 0 | I26: =B$1*D26/100 -> 14437.3 | J26: =Edesur!N33 -> 9565.3655 | K26: =G$1*D26/100 -> 0 | L26: =L$1*D26/100 -> 11167.486 | M26: =I26+G26+L26+K26+H26+J26 -> 35170.152 | O26: =M26-J26 -> 25604.786
A27: Ariel | C27: COCHERA 8 | D27: 1.08 | E27: 36601.116 | F27: =E27 -> 36601.116 | G27: =E27-F27 -> 0 | H27: =IF(G27>0,G27*4%,0) -> 0 | I27: =B$1*D27/100 -> 14437.3 | J27: =Edesur!N34 -> 9565.3655 | K27: =G$1*D27/100 -> 0 | L27: =L$1*D27/100 -> 11167.486 | M27: =I27+G27+L27+K27+H27+J27 -> 35170.152 | O27: =M27-J27 -> 25604.786 | P27: =F27+F26+F19 -> 368020.65
B28: =B7 -> Leandro | C28: COCHERA 9 | D28: 1.08 | E28: 36601.116 | F28: =E28 -> 36601.116 | G28: =E28-F28 -> 0 | H28: =IF(G28>0,G28*4%,0) -> 0 | I28: =B$1*D28/100 -> 14437.3 | J28: =Edesur!N35 -> 9565.3655 | K28: =G$1*D28/100 -> 0 | L28: =L$1*D28/100 -> 11167.486 | M28: =I28+G28+L28+K28+H28+J28 -> 35170.152 | O28: =M28-J28 -> 25604.786
A29: Alonso Graciela | B29: Facundo | C29: COCHERA 10 | D29: 1.08 | E29: 85628.433 | F29: =E29 -> 85628.433 | G29: =E29-F29 -> 0 | H29: =IF(G29>0,G29*4%,0) -> 0 | I29: =B$1*D29/100 -> 14437.3 | J29: =Edesur!N36 -> 9565.3655 | K29: =G$1*D29/100 -> 0 | L29: =L$1*D29/100 -> 11167.486 | M29: =I29+G29+L29+K29+H29+J29 -> 35170.152 | O29: =M29-J29 -> 25604.786
C31: TOTAL EXPENSAS | D31: =SUM(D3:D30) -> 100 | F31: =SUM(F3:F30) -> 3661916.3 | I31: =SUM(I3:I30) -> 1336787 | K31: =SUM(K3:K30) -> 0 | M31: =SUM(M3:M29) -> 4413657.5

Sheet Edesur
A1: EDESUR
C6: ='detalle y gastos'!C7 -> Vto. 17/04
B7: EDESUR | C7: =-'detalle y gastos'!C50 -> 1024355.4
B8: EDESUR | K8: =C8-J38 -> -138673.46 | L8: =C7-J38 -> 885681.99
A9: U.F. | B9: U.F. | C9: PISO - DEPTO | D9: PROPIETARIOS | E9: % | F9: CONSUMO ANT. | G9: CONSUMO ACTUAL | H9: KWH | I9: INTERES POR MORA 7% | J9: EDESUR | K9: PARTES COMUNES | L9: PARTES COMUNES | M9: KWH | N9: EDESUR FINAL
A10: 1 | B10: 1 | C10: 1ro. "A" | D10: Ferrea Nestor | E10: 5.11 | F10: 5143 | G10: 5239.3 | H10: =G10-F10 -> 96.3 | I10: =H10*7% -> 6.741 | J10: =M10*93.787 -> 9031.6881 | K10: =K8*E10% -> -7086.2137 | L10: =L$8*E10/S$12 -> 45258.35 | M10: =G10-F10 -> 96.3 | N10: =J10+L10 -> 54290.038 | O10: =N10+'prorrateo '!M3 -> 229728.65
A11: 2 | B11: 2 | C11: 1ro. "B" | D11: Gnecchi Nicolas | E11: 5.09 | F11: 4548.1 | G11: 4550 | H11: =G11-F11 -> 1.9 | I11: =H11*7% -> 0.133 | J11: =M11*93.787 -> 178.1953 | K11: =K8*E11% -> -7058.479 | L11: =L$8*E11/S$12 -> 45081.213 | M11: =G11-F11 -> 1.9 | N11: =J11+L11 -> 45259.409 | O11: =N11+'prorrateo '!M4 -> 528648.9
A12: 3 | B12: 3 | C12: 2do. "A" | D12: Triñanes Gaston | E12: 5.04 | F12: 2710.5 | G12: 2808.5 | H12: =G12-F12 -> 98 | I12: =H12*7% -> 6.86 | J12: =M12*93.787 -> 9191.126 | K12: =K8*E12% -> -6989.1423 | L12: =L$8*E12/S$12 -> 44638.372 | M12: =G12-F12 -> 98 | N12: =J12+L12 -> 53829.498 | O12: =N12+'prorrateo '!M5 -> 227147.99 | S12: 100
A13: 4 | B13: 4 Y 5 | C13: 2do. "B" | D13: Nuñez Eva | E13: 5.21 | F13: 1635.6 | G13: 1693.3 | H13: =G13-F13 -> 57.7 | I13: =H13*7% -> 4.039 | J13: =M13*93.787 -> 5411.5099 | K13: =K8*E13% -> -7224.8872 | L13: =L$8*E13/S$12 -> 46144.032 | M13: =G13-F13 -> 57.7 | N13: =J13+L13 -> 51555.542 | O13: =N13+'prorrateo '!M6 -> 226630.47
A14: 6 | B14: 6 | C14: 3ro. "A" | D14: Triñanes Gaston | E14: 5.11 | F14: 2641.2 | G14: 2764.8 | H14: =G14-F14 -> 123.6 | I14: =H14*7% -> 8.652 | J14: =M14*93.787 -> 11592.073 | K14: =K8*E14% -> -7086.2137 | L14: =L$8*E14/S$12 -> 45258.35 | M14: =G14-F14 -> 123.6 | N14: =J14+L14 -> 56850.423 | O14: =N14+'prorrateo '!M7 -> 234849.42
A15: 7 | B15: 7 | C15: 3ro. "B" | D15: Grecco Pedro | E15: 5.09 | F15: 3881.5 | G15: 3961.7 | H15: =G15-F15 -> 80.2 | I15: =H15*7% -> 5.614 | J15: =M15*93.787 -> 7521.7174 | K15: =K8*E15% -> -7058.479 | L15: =L$8*E15/S$12 -> 45081.213 | M15: =G15-F15 -> 80.2 | N15: =J15+L15 -> 52602.931 | O15: =N15+'prorrateo '!M8 -> 225880.27
A16: 8 | B16: 8 | C16: 4to. "A" | D16: Mteljan Barbara | E16: 5.11 | F16: 2973.6 | G16: 3055.6 | H16: =G16-F16 -> 82 | I16: =H16*7% -> 5.74 | J16: =M16*93.787 -> 7690.534 | K16: =K8*E16% -> -7086.2137 | L16: =L$8*E16/S$12 -> 45258.35 | M16: =G16-F16 -> 82 | N16: =J16+L16 -> 52948.884 | O16: =N16+'prorrateo '!M9 -> 227046.34
A17: 9 | B17: 9 | C17: 4to. "B" | D17: Carnevalli | E17: 5.09 | F17: 3501 | G17: 3516.8 | H17: =G17-F17 -> 15.8 | I17: =H17*7% -> 1.106 | J17: =M17*93.787 -> 1481.8346 | K17: =K8*E17% -> -7058.479 | L17: =L$8*E17/S$12 -> 45081.213 | M17: =G17-F17 -> 15.8 | N17: =J17+L17 -> 46563.048 | O17: =N17+'prorrateo '!M10 -> 213800.31
A18: 10 | B18: 10 | C18: 5to. "A" | D18: Leonor | E18: 5.04 | F18: 2722.4 | G18: 2783.2 | H18: =G18-F18 -> 60.8 | I18: =H18*7% -> 4.256 | J18: =M18*93.787 -> 5702.2496 | K18: =K8*E18% -> -6989.1423 | L18: =L$8*E18/S$12 -> 44638.372 | M18: =G18-F18 -> 60.8 | N18: =J18+L18 -> 50340.622 | O18: =N18+'prorrateo '!M11 -> 220170.25
A19: 11 | B19: 11 | C19: 5to. "B" | D19: Strangio Federico | E19: 5.21 | F19: 5568.7 | G19: 5747.8 | H19: =G19-F19 -> 179.1 | I19: =H19*7% -> 12.537 | J19: =M19*93.787 -> 16797.252 | K19: =K8*E19% -> -7224.8872 | L19: =L$8*E19/S$12 -> 46144.032 | M19: =G19-F19 -> 179.1 | N19: =J19+L19 -> 62941.283 | O19: =N19+'prorrateo '!M12 -> 249401.95
A20: 12 | B20: 12 | C20: 6to. "A" | D20: Senderowicz Rosalia | E20: 5.11 | F20: 7045.5 | G20: 7204.2 | H20: =G20-F20 -> 158.7 | I20: =H20*7% -> 11.109 | J20: =M20*93.787 -> 14883.997 | K20: =K8*E20% -> -7086.2137 | L20: =L$8*E20/S$12 -> 45258.35 | M20: =G20-F20 -> 158.7 | N20: =J20+L20 -> 60142.347 | O20: =N20+'prorrateo '!M13 -> 241433.37
A21: 13 | B21: 13 | C21: 6to. "B" | D21: Senderowicz Rosalia | E21: 5.09 | F21: 4426.3 | G21: 4480.1 | H21: =G21-F21 -> 53.8 | I21: =H21*7% -> 3.766 | J21: =M21*93.787 -> 5045.7406 | K21: =K8*E21% -> -7058.479 | L21: =L$8*E21/S$12 -> 45081.213 | M21: =G21-F21 -> 53.8 | N21: =J21+L21 -> 50126.954 | O21: =N21+'prorrateo '!M14 -> 408911.4
A22: 14 | B22: 14 | C22: 7mo. "A" | D22: Alonso Graciela | E22: 5.04 | F22: 3145.8 | G22: 3264.9 | H22: =G22-F22 -> 119.1 | I22: =H22*7% -> 8.337 | J22: =M22*93.787 -> 11170.032 | K22: =K8*E22% -> -6989.1423 | L22: =L$8*E22/S$12 -> 44638.372 | M22: =G22-F22 -> 119.1 | N22: =J22+L22 -> 55808.404 | O22: =N22+'prorrateo '!M15 -> 270168.46
A23: 15 | B23: 15 | C23: 7mo. "B" | D23: Perez Rodriguez | E23: 5.21 | F23: 5835.3 | G23: 5974.2 | H23: =G23-F23 -> 138.9 | I23: =H23*7% -> 9.723 | J23: =M23*93.787 -> 13027.014 | K23: =K8*E23% -> -7224.8872 | L23: =L$8*E23/S$12 -> 46144.032 | M23: =G23-F23 -> 138.9 | N23: =J23+L23 -> 59171.046 | O23: =N23+'prorrateo '!M16 -> 241801.17
A24: 16 | B24: 16 | C24: 8vo. "A" | D24: Mourelos Pablo | E24: 5.04 | F24: 2020.8 | G24: 2042.8 | H24: =G24-F24 -> 22 | I24: =H24*7% -> 1.54 | J24: =M24*93.787 -> 2063.314 | K24: =K8*E24% -> -6989.1423 | L24: =L$8*E24/S$12 -> 44638.372 | M24: =G24-F24 -> 22 | N24: =J24+L24 -> 46701.686 | O24: =N24+'prorrateo '!M17 -> 212892.38
A25: 17 | B25: 17 | C25: 8vo. "B" | D25: Calabria Carlos/Giarrizzo Silvia | E25: 5.21 | F25: 2317.3 | G25: 2383.3 | H25: =G25-F25 -> 66 | I25: =H25*7% -> 4.62 | J25: =M25*93.787 -> 6189.942 | K25: =K8*E25% -> -7224.8872 | L25: =L$8*E25/S$12 -> 46144.032 | M25: =G25-F25 -> 66 | N25: =J25+L25 -> 52333.974 | O25: =N25+'prorrateo '!M18 -> 228187.33
A26: 18 | B26: 18 | C26: 9no. "A" | D26: Ariel | E26: 7.4 | F26: 10444 | G26: 10568.7 | H26: =G26-F26 -> 124.7 | I26: =H26*7% -> 8.729 | J26: =M26*93.787 -> 11695.239 | K26: =K8*E26% -> -10261.836 | L26: =L$8*E26/S$12 -> 65540.467 | M26: =G26-F26 -> 124.7 | N26: =J26+L26 -> 77235.706 | O26: =N26+'prorrateo '!M19 -> 329911.62
A27: 19 | B27: 19 | C27: COCHERA 1 | E27: 1.08 | H27: =G27-F27 -> 0 | I27: =H27*7% -> 0 | L27: =L$8*E27/S$12 -> 9565.3655 | M27: 0 | N27: =J27+L27 -> 9565.3655 | O27: =N27+'prorrateo '!M20 -> 480717.84
A28: 20 | C28: COCHERA 2 | E28: 1.08 | H28: 0 | I28: =H28*7% -> 0 | L28: =L$8*E28/S$12 -> 9565.3655 | M28: 0 | N28: =J28+L28 -> 9565.3655 | O28: =N28+'prorrateo '!M21 -> 44735.517
C29: COCHERA 3 | E29: 1.08 | L29: =L$8*E29/S$12 -> 9565.3655 | M29: 0 | N29: =J29+L29 -> 9565.3655 | O29: =N29+'prorrateo '!M22 -> 44735.517
C30: COCHERA 4 | E30: 1.08 | L30: =L$8*E30/S$12 -> 9565.3655 | M30: 0 | N30: =J30+L30 -> 9565.3655 | O30: =N30+'prorrateo '!M23 -> 44735.517
C31: COCHERA 5 | D31: Senderowicz Rosalia | E31: 1.08 | L31: =L$8*E31/S$12 -> 9565.3655 | M31: 0 | N31: =J31+L31 -> 9565.3655 | O31: =N31+'prorrateo '!M24 -> 44735.517
C32: COCHERA 6 | D32: Senderowicz Rosalia | E32: 1.08 | L32: =L$8*E32/S$12 -> 9565.3655 | M32: 0 | N32: =J32+L32 -> 9565.3655 | O32: =N32+'prorrateo '!M25 -> 82800.678
C33: COCHERA 7 | D33: Ariel | E33: 1.08 | L33: =L$8*E33/S$12 -> 9565.3655 | M33: 0 | N33: =J33+L33 -> 9565.3655 | O33: =N33+'prorrateo '!M26 -> 44735.517
C34: COCHERA 8 | D34: Ariel | E34: 1.08 | L34: =L$8*E34/S$12 -> 9565.3655 | M34: 0 | N34: =J34+L34 -> 9565.3655 | O34: =N34+'prorrateo '!M27 -> 44735.517
A35: 21 | C35: COCHERA 9 | E35: 1.08 | H35: 0 | I35: =H35*7% -> 0 | L35: =L$8*E35/S$12 -> 9565.3655 | M35: 0 | N35: =J35+L35 -> 9565.3655 | O35: =N35+'prorrateo '!M28 -> 44735.517
A36: 22 | C36: COCHERA 10 | D36: Alonso Graciela | E36: 1.08 | H36: 0 | I36: =H36*7% -> 0 | L36: =L$8*E36/S$12 -> 9565.3655 | M36: 0 | N36: =J36+L36 -> 9565.3655 | O36: =N36+'prorrateo '!M29 -> 44735.517
A37: 23 | H37: 0 | I37: =H37*7% -> 0 | L37: 0 | M37: 0 | N37: =J37+L37 -> 0
A38: 24 | J38: =SUM(J10:J37) -> 138673.46 | L38: =SUM(L10:L37) -> 885681.99 | N38: =SUM(N10:N37) -> 1024355.4
E39: =SUM(E10:E38) -> 100 | I39: =SUM(I10:I38) -> 103.502 | L39: =L38+J38 -> 1024355.4
A40: NOTA:

Sheet SITUACION ARIEL
D4: En Febrero debia abonar: | F4: 374177.79 | G4: 9A
F5: 47141.651 | G5: Cochera 7
F6: 47141.651 | G6: Cochera 8
F8: =SUM(F4:F7) -> 468461.1 | G8: TOTAL
D10: Abona: | F10: -55000 | G10: Fumigacion
F11: -384067 | G11: Portera
D13: TOTAL AL FINALIZAR FEBRERO (DEUDA) | F13: =SUM(F8:F12) -> 29394.096
D16: En marzo debia abonar: | F16: ='prorrateo '!E19 -> 294818.42 | G16: 9A
F17: 36601.116 | G17: Cochera 7
F18: 36601.116 | G18: Cochera 8
F20: =SUM(F13:F19) -> 397414.75 | G20: TOTAL + DEUDA FEB
