Workbook

Sheet RESUMEN
B2: MAIL: consorciogorriti368@gmail.com
B3: CUIT ADMINISTRACION: 27231256879
B4: CBU: 0290034600000502294350 | D4: TELEFONO: 11 5320-2676
A5: LIQUIDACION DE EXPENSAS | B5: ADMINISTRADORA: CAROLINA CANCIANI MP:1148
A6: CUIT DEL EDIFICIO: 30583957819 | B6: PERÍODO: ENERO | D6: HORARIOS DE ATENCION: LUNES A VIERNES
A7: CONSORCIO DE PROPIETARIOS DEL EDIFICIO CALLE GORRITI 368 | D7: 10 A 16HS - EMERGENCIAS 24HS
B9: VTO 13/02
A14: ESTIMADOS PROPIETARIOS E INQUILINOS: POR FAVOR LOS QUE ABONAN EN PRIMER VENCIMIENTO ABONEN EL MONTO DE PRIMER VENCIMIENTO, ASI AGILIZAN LA LIQUIDACION, RESPETEN LOS CENTAVOS CORRESPONDIENTES A LA UNIDAD FUNCIONAL. ES DE CARÁCTER OBLIGATORIO INFORMAR VIA MAIL LAS EXPENSAS. CASO CONTRARIO SE INFORMARA VIA CARTA DOCUMENTO A LA UNIDAD FUNCIONAL QUE CREEMOS QUE CORRESPONDE, CUYO COSTO SERA IMPUTADO A LA UNIDAD FUNCIONAL SOSPECHADA.
A21: GASTOS ORDINARIOS UNIDADES FUNCIONALES:
A22: HABERES ENCARGADOS
A23: Sueldo encargado Colmiero Oscar | D23: 1158217
A26: Retenciones | D26: 0
A28: Neto | D28: =SUM(D23:D27) -> 1158217 | G28: =D28+D37 -> 2218075
A29: Sueldo encargado Balcazza Leonardo | D29: 1059858
A33: SAC
A34: Retenciones SAC
A35: Retenciones | D35: 0
A37: Neto | D37: =SUM(D29:D36) -> 1059858
A38: TOTAL SUELDO | E38: =D28+D37 -> 2218075
A39: HONORARIOS
A40: GUSTAVO PADRON - NO SE COBRAN HONORARIOS HASTA TENER EL CONTROL DE LA CUENTA - SE ADEUDA MES 12/24 Y MES 1/25
A41: HONORARIOS ADMINISTRACION RC - NO SE COBRAN HONORARIOS HASTA TENER EL CONTROL DE LA CUENTA - SE ADEUDA MES 1/25 | D41: 230000
A42: TOTAL | E42: =SUM(D40:D41) -> 230000
A43: SEGUROS
A44: Seguro Integral consorcio San Cristobal - Poliza 01-05-07-30183461 | D44: 120974 | E44: Debito 10/01
A46: TOTAL IMPUESTO | E46: =SUM(D44:D45) -> 120974
A47: APORTES Y CONTRIBUCIONES
A48: ARCA | D48: 2255205.5 | E48: PMC 24/01
A49: ARCA - Empleada que realizo el reemplazo en Noviembre | D49: 66437.69 | E49: PMC 24/01
A50: Sindicatos mes de ENERO | B50: Fatheryh | D50: 328236.93 | E50: Debito 20/01
A51: =A50 -> Sindicatos mes de ENERO | B51: Suther | D51: 209289.75 | E51: =E50 -> Debito 20/01
A52: =A51 -> Sindicatos mes de ENERO | B52: Seracarh | D52: 23254.21 | E52: =E51 -> Debito 20/01
A53: TOTAL Aportes y Contribuciones - Sindicato | E53: =SUM(D48:D52) -> 2882424.1
A54: ABONOS Y SERVICIOS
A55: EDESUR - Cliente nro. 828563 | D55: 835158.74 | E55: PMC 13/01
A56: EDESUR - Cliente nro. 01672309 | D56: 1120.25 | E56: =E55 -> PMC 13/01
A57: EDESUR - Cliente nro. 01672321 | D57: 13712.85 | E57: =E56 -> PMC 13/01
A58: EDESUR - Cliente nro. 01672319 | D58: 6514.33 | E58: =E57 -> PMC 13/01
A59: Metrogas - Cliente nro. 20495697900 | D59: 5186.14 | E59: PMC 17/01
A60: Metrogas - Cliente nro. 20463936100 | B60: No hay factura
A61: Personal Flow - Debito automatico | D61: 13674.01 | E61: Debito 13/12
A62: AYSA - Nro de cliente 3888610 | D62: 1947353.8 | E62: PMC 23/01
A63: Ascensores Zuazola Paulo - Sin factura - 50% del trabajo a realizar en el ascensor | D63: 900000 | E63: Transf 23/01
A64: TOTAL ABONOS Y SERVICIOS | E64: =SUM(D55:D63) -> 3722720.1
A65: GASTOS GENERALES / MANTENIMIENTO
A67: Doartero - Reparacion caño de subida en emergencia 28/1 | D67: 55000
A69: Calman - Articulos de limpieza (a cargo de la Sra. Adriana) - Factura 19/20 | D69: 18000
A70: Compra de caja navideña (a cargo de la Sra. Adriana) | D70: 29980 | H70: PENDIENTE | I70: Romanatti Carlos - Certificacion digital del reglamento, acta de designacion para presentar en ARCA
A71: TOTAL | E71: =SUM(D66:D70) -> 102980
A72: GASTOS BANCARIOS
A73: GASTOS BANCARIOS | D73: =612.68+3455.33+10361.01+11715.24+2269.38+13929.86+4860+82.04+159.39+5284.68+1220.91+3000+33.53+330+57.3+1582.35+6000+856.31+5985.52+2866.33+739.74+7350.17+401.9+1914+11507.67+8070.53 -> 104645.87
A75: TOTAL | E75: =SUM(D73:D74) -> 104645.87
A77: PREVISION ORDINARIA - PARA ASCENSOR | E77: 1000000
A79: TOTAL ORDINARIOS | E79: =(SUM(E31:E77)) -> 10381819
A82: GASTOS EXTRAORDINARIOS:
E87: =SUM(D83:D86) -> 0
A90: PREVISION EXTRAORDINARIA
A92: TOTAL EXTRAORDINARIOS | E92: =E87+E90 -> 0
A94: GASTOS ORDINARIOS + PREVISION : | B94: =E79 -> 10381819
A95: GASTOS ORDINARIOS SIN PREVISION: | B95: =E79-E77 -> 9381819.1
A96: GASTOS EXTRAORDINARIOS SIN PREVISION: | B96: =E92-E90 -> 0
A97: GASTOS EXTRAORDINARIOS CON PREVISION: | B97: =E92 -> 0
A100: ESTIMADOS PROPIETARIOS E INQUILINOS; ENTENDIENDO QUE AL PRORRATEAR EL GASTO JUSTO QUE SE REALIZO DURANTE EL MES SIN TENER EN CUENTA LOS DEUDORES HISTORICOS DEL CONSORCIO SE HACE DEFICITARIA LA CAJA, YA QUE NUNCA SE CUBREN EL MONTO REAL GASTADO MEDIANTE LOS INGRESOS. ESTA RAZON ES EL MOTIVO POR EL CUAL SE COMIENZA A HACER UN FONDO DE GASTOS ORDINARIOS DESANDO QUE UNA VEZ COBRADAS LAS EXPENSAS DEUDORAS, LA CAJA QUEDE A FAVOR DEL CONSORCIO PARA IMPLEMENTAR MEJORAS. SE TOMA EL SALDO DE BANCO REAL AL 05/02 (RESUMEN BANCARIO) YA QUE NO HABIA CAJAS ANTERIORES. A PARTIR DE ESTE MOMENTO, TENDRAN RENDIDA LA CAJA AL FINAL DE LAS EXPENSAS.
A104: RESUMEN
B105: 0
A106: Ingreso | B106: =PRORRATEO!I81 -> 9182407.9
B107: 0
A108: Deposito sin identificar | B108: =B136 -> 67214
A110: Punitorios mal cobrados
A111: Egresos Ordinarios | B111: =-B95 -> -9381819.1
A112: Egresos Extraordinarios | B112: =-(B96) -> 0
A113: TOTAL | B113: =SUM(B105:B112) -> -132197.17
A117: SALDO EN BANCO AL 5/2/25 | B117: 698091.7
A118: LA SUMA DE LOS SUELDOS DE LOS PORTEROS, EQUIVALE A $2.218.075, Y TAN SOLO SE DEPOSITO $500,000 A CUENTA. EL SALDO DE CAJA SON $698091,7 MENOS LO QUE RESTA DEPOSITAR ($1.718.075)
A125: CAJA REAL | B125: =698091.7-1718075 -> -1019983.3
A128: DEPOSITOS NO IDENTIFICADOS
C130: 11948.17
C131: 52000
C132: 61209
A134: Deposito sin identificar a nombre de Veron Wanda 10/01 | B134: 67214 | C134: 40000
A136: TOTAL | B136: =SUM(B134:B135) -> 67214

Sheet PRORRATEO
E2: =RESUMEN!B4 -> CBU: 0290034600000502294350 | M2: Gastos Ordinarios: | P2: 10381819
A4: Piso | B4: Dpto. | D4: UF | E4: Propietario | F4: Inquilinos | G4: (%) | H4: Saldo Ord + EXP DE URGENCIA | I4: Ingreso | J4: Pago por | K4: Deuda o Saldo a favor | L4: Interes 3% | M4: Expensas extraor. | N4: Expensas ord. | O4: Gastos part. | P4: Total 1er Vto | Q4: Total 2do Vto. | R4: Total 2do Vto
P5: =RESUMEN!B9 -> VTO 13/02
A6: PB | C6: LOC | D6: 1 | E6: GEFFNER SILVIA E. | G6: 0.5131 | H6: 50798.02 | I6: =640937-I13-I7-I47-I48-I56-I59-I69-I73+65440 -> 53236.87 | K6: =H6-I6 -> -2438.85 | L6: =IF(K6>0,K6*3%,0) -> 0 | M6: 0 | N6: =P$2*G6% -> 53269.114 | O6: 0 | P6: =ROUND(SUM(K6:O6),0) + S6 -> 50830.01 | Q6: =ROUND(P6*6% + P6,0) + S6 -> 53880.01 | R6: =ROUND(P6*3%,0) + P6 -> 52355.01 | S6: 0.01
A7: 3º | C7: LOC | D7: =D6+1 -> 2 | E7: COVILOZA S. A. | G7: 0.6119 | H7: 60579.04 | I7: =H7 -> 60579.04 | K7: =H7-I7 -> 0 | L7: =IF(K7>0,K7*3%,0) -> 0 | M7: 0 | N7: =P$2*G7% -> 63526.351 | O7: 0 | P7: =ROUND(SUM(K7:O7),0) + S7 -> 63526.02 | Q7: =ROUND(P7*6% + P7,0) + S7 -> 67338.02 | R7: =ROUND(P7*3%,0) + P7 -> 65432.02 | S7: =S6+0.01 -> 0.02
A8: 3º | B8: 1 | D8: =D7+1 -> 3 | E8: ASIST Y TRAB. | G8: 0.6115 | H8: 60540.06 | I8: =H8 -> 60540.06 | K8: =H8-I8 -> 0 | L8: =IF(K8>0,K8*3%,0) -> 0 | M8: 0 | N8: =P$2*G8% -> 63484.824 | O8: 0 | P8: =ROUND(SUM(K8:O8),0) + S8 -> 63485.03 | Q8: =ROUND(P8*6% + P8,0) + S8 -> 67294.03 | R8: =ROUND(P8*3%,0) + P8 -> 65390.03 | S8: =S7+0.01 -> 0.03
A9: 4º | B9: 2 | D9: =D8+1 -> 4 | E9: ASIST Y TRAB. | G9: 0.5033 | H9: 49828.08 | I9: =H9 -> 49828.08 | K9: =H9-I9 -> 0 | L9: =IF(K9>0,K9*3%,0) -> 0 | M9: 0 | N9: =P$2*G9% -> 52251.695 | O9: 0 | P9: =ROUND(SUM(K9:O9),0) + S9 -> 52252.04 | Q9: =ROUND(P9*6% + P9,0) + S9 -> 55387.04 | R9: =ROUND(P9*3%,0) + P9 -> 53820.04 | S9: =S8+0.01 -> 0.04
A10: 4º | B10: 3 | D10: =D9+1 -> 5 | E10: ASIST Y TRAB. | G10: 0.5033 | H10: 49828.1 | I10: =144015-I9-I8 -> 33646.86 | K10: =H10-I10 -> 16181.24 | L10: =IF(K10>0,K10*3%,0) -> 485.4372 | M10: 0 | N10: =P$2*G10% -> 52251.695 | O10: 0 | P10: =ROUND(SUM(K10:O10),0) + S10 -> 68918.05 | Q10: =ROUND(P10*6% + P10,0) + S10 -> 73053.05 | R10: =ROUND(P10*3%,0) + P10 -> 70986.05 | S10: =S9+0.01 -> 0.05
A11: 5º | B11: 4 | D11: =D10+1 -> 6 | E11: BENMAOR D. | F11: Cristian Requelme | G11: 0.7499 | H11: 74242.12 | I11: =66743.06 -> 66743.06 | K11: =H11-I11 -> 7499.06 | L11: =IF(K11>0,K11*3%,0) -> 224.9718 | M11: 0 | N11: =P$2*G11% -> 77853.261 | O11: 0 | P11: =ROUND(SUM(K11:O11),0) + S11 -> 85577.06 | Q11: =ROUND(P11*6% + P11,0) + S11 -> 90712.06 | R11: =ROUND(P11*3%,0) + P11 -> 88144.06 | S11: =S10+0.01 -> 0.06
A12: 5º | B12: 5 | D12: =D11+1 -> 7 | E12: GALANTERNIK A | F12: Miriam Larken | G12: 0.5425 | H12: 53709.14 | I12: =48284.07+5588.07 -> 53872.14 | K12: =H12-I12 -> -163 | L12: =IF(K12>0,K12*3%,0) -> 0 | M12: 0 | N12: =P$2*G12% -> 56321.368 | O12: 0 | P12: =ROUND(SUM(K12:O12),0) + S12 -> 56158.07 | Q12: =ROUND(P12*6% + P12,0) + S12 -> 59528.07 | R12: =ROUND(P12*3%,0) + P12 -> 57843.07 | S12: =S11+0.01 -> 0.07
A13: 6º | B13: 6 | D13: =D12+1 -> 8 | E13: CANDEL JORGE ISAAC | G13: 0.4537 | H13: 44917.16 | I13: =H13 -> 44917.16 | K13: =H13-I13 -> 0 | L13: =IF(K13>0,K13*3%,0) -> 0 | M13: 0 | N13: =P$2*G13% -> 47102.313 | O13: 0 | P13: =ROUND(SUM(K13:O13),0) + S13 -> 47102.08 | Q13: =ROUND(P13*6% + P13,0) + S13 -> 49928.08 | R13: =ROUND(P13*3%,0) + P13 -> 48515.08 | S13: =S12+0.01 -> 0.08
A14: 6º | B14: 7 | D14: =D13+1 -> 9 | E14: BORTZ SERGIO | G14: 0.5244 | H14: 51917.18 | I14: =46673.09 -> 46673.09 | K14: =H14-I14 -> 5244.09 | L14: =IF(K14>0,K14*3%,0) -> 157.3227 | M14: 0 | N14: =P$2*G14% -> 54442.259 | O14: 0 | P14: =ROUND(SUM(K14:O14),0) + S14 -> 59844.09 | Q14: =ROUND(P14*6% + P14,0) + S14 -> 63435.09 | R14: =ROUND(P14*3%,0) + P14 -> 61639.09 | S14: =S13+0.01 -> 0.09 | U14: ESTA ES LA FUNDACION DE MEDICOS
A15: 7º | B15: 8 | D15: =D14+1 -> 10 | E15: BORTZ SERGIO | G15: 0.424 | H15: 41977.2 | I15: =37737.1 -> 37737.1 | K15: =H15-I15 -> 4240.1 | L15: =IF(K15>0,K15*3%,0) -> 127.203 | M15: 0 | N15: =P$2*G15% -> 44018.913 | O15: 0 | P15: =ROUND(SUM(K15:O15),0) + S15 -> 48386.1 | Q15: =ROUND(P15*6% + P15,0) + S15 -> 51289.1 | R15: =ROUND(P15*3%,0) + P15 -> 49838.1 | S15: =S14+0.01 -> 0.1 | U15: ESTA ES LA FUNDACION DE MEDICOS
A16: 7º | B16: 1 | C16: A | D16: =D15+1 -> 11 | E16: KIM SOON LEO | G16: 2.3033 | H16: 1633137.2 | K16: =H16-I16 -> 1633137.2 | L16: =IF(K16>0,K16*3%,0) -> 48994.117 | M16: 0 | N16: =P$2*G16% -> 239124.44 | O16: 0 | P16: =ROUND(SUM(K16:O16),0) + S16 -> 1921256.1 | Q16: =ROUND(P16*6% + P16,0) + S16 -> 2036531.1 | R16: =ROUND(P16*3%,0) + P16 -> 1978894.1 | S16: =S15+0.01 -> 0.11
A17: 8º | B17: 1 | C17: B | D17: =D16+1 -> 12 | E17: CANDEL MARCELO | F17: Florencia Fucci | G17: 2.7493 | H17: 279528.24 | I17: =244694 -> 244694 | K17: =H17-I17 -> 34834.24 | L17: =IF(K17>0,K17*3%,0) -> 1045.0272 | M17: 0 | N17: =P$2*G17% -> 285427.35 | O17: 0 | P17: =ROUND(SUM(K17:O17),0) + S17 -> 321307.12 | Q17: =ROUND(P17*6% + P17,0) + S17 -> 340586.12 | R17: =ROUND(P17*3%,0) + P17 -> 330946.12 | S17: =S16+0.01 -> 0.12
A18: 8º | B18: 2 | C18: A | D18: =D17+1 -> 13 | E18: TRIPODI | F18: Mariela Pricolo | G18: 2.3033 | H18: 228032.26 | I18: =214999.13 -> 214999.13 | K18: =H18-I18 -> 13033.13 | L18: =IF(K18>0,K18*3%,0) -> 390.9939 | M18: 0 | N18: =P$2*G18% -> 239124.44 | O18: 0 | P18: =ROUND(SUM(K18:O18),0) + S18 -> 252549.13 | Q18: =ROUND(P18*6% + P18,0) + S18 -> 267702.13 | R18: =ROUND(P18*3%,0) + P18 -> 260125.13 | S18: =S17+0.01 -> 0.13
A19: 9º | B19: 2 | C19: B | D19: =D18+1 -> 14 | E19: MIRANDA DE GIL | F19: Susana | G19: 2.6368 | H19: 268089.28 | I19: =200000+40000 -> 240000 | K19: =H19-I19 -> 28089.28 | L19: =IF(K19>0,K19*3%,0) -> 842.6784 | M19: 0 | N19: =P$2*G19% -> 273747.81 | O19: 0 | P19: =ROUND(SUM(K19:O19),0) + S19 -> 302680.14 | Q19: =ROUND(P19*6% + P19,0) + S19 -> 320841.14 | R19: =ROUND(P19*3%,0) + P19 -> 311760.14 | S19: =S18+0.01 -> 0.14 | U19: MAXIMO
A20: 9º | B20: 3 | C20: A | D20: =D19+1 -> 15 | E20: FRAGA DORA | G20: 2.3537 | H20: 233021.3 | I20: =209484.15 -> 209484.15 | K20: =H20-I20 -> 23537.15 | L20: =IF(K20>0,K20*3%,0) -> 706.1145 | M20: 0 | N20: =P$2*G20% -> 244356.88 | O20: 0 | P20: =ROUND(SUM(K20:O20),0) + S20 -> 268600.15 | Q20: =ROUND(P20*6% + P20,0) + S20 -> 284716.15 | R20: =ROUND(P20*3%,0) + P20 -> 276658.15 | S20: =S19+0.01 -> 0.15
A21: 10º | B21: 3 | C21: B | D21: =D20+1 -> 16 | E21: SARUBBI MARTIN | F21: Sarubbi Adriana | G21: 2.6477 | H21: 262128.32 | I21: =235651.16+27271.26+RESUMEN!D70+RESUMEN!D69 -> 310902.42 | K21: =H21-I21 -> -48774.1 | L21: =IF(K21>0,K21*3%,0) -> 0 | M21: 0 | N21: =P$2*G21% -> 274879.42 | O21: 0 | P21: =ROUND(SUM(K21:O21),0) + S21 -> 226105.16 | Q21: =ROUND(P21*6% + P21,0) + S21 -> 239671.16 | R21: =ROUND(P21*3%,0) + P21 -> 232888.16 | S21: =S20+0.01 -> 0.16
A22: 10º | B22: 4 | C22: A | D22: =D21+1 -> 17 | E22: LACENTRE | F22: Gabriela Tamara | G22: 2.3235 | H22: 230031.34 | I22: =206796.17 -> 206796.17 | K22: =H22-I22 -> 23235.17 | L22: =IF(K22>0,K22*3%,0) -> 697.0551 | M22: 0 | N22: =P$2*G22% -> 241221.57 | O22: 0 | P22: =ROUND(SUM(K22:O22),0) + S22 -> 265154.17 | Q22: =ROUND(P22*6% + P22,0) + S22 -> 281063.17 | R22: =ROUND(P22*3%,0) + P22 -> 273109.17 | S22: =S21+0.01 -> 0.17
A23: 11º | B23: 4 | C23: B | D23: =D22+1 -> 18 | E23: FERNANDEZ BERTA | F23: KRAVETZ | G23: 2.688 | H23: 160942.36 | I23: =130157 -> 130157 | K23: =H23-I23 -> 30785.36 | L23: =IF(K23>0,K23*3%,0) -> 923.5608 | M23: 0 | N23: =P$2*G23% -> 279063.3 | O23: 0 | P23: =ROUND(SUM(K23:O23),0) + S23 -> 310772.18 | Q23: =ROUND(P23*6% + P23,0) + S23 -> 329419.18 | R23: =ROUND(P23*3%,0) + P23 -> 320095.18 | S23: =S22+0.01 -> 0.18
A24: 11º | B24: 5 | C24: A | D24: =D23+1 -> 19 | E24: VERONES JOSE MARIA | G24: 2.36 | H24: 233645.38 | I24: =210045.19+23600 -> 233645.19 | K24: =H24-I24 -> 0.19 | L24: =IF(K24>0,K24*3%,0) -> 0.0057 | M24: 0 | N24: =P$2*G24% -> 245010.93 | O24: 0 | P24: =ROUND(SUM(K24:O24),0) + S24 -> 245011.19 | Q24: =ROUND(P24*6% + P24,0) + S24 -> 259712.19 | R24: =ROUND(P24*3%,0) + P24 -> 252361.19 | S24: =S23+0.01 -> 0.19
A25: 12º | B25: 5 | C25: B | D25: =D24+1 -> 20 | E25: SRUGO CARLOS | G25: 2.7183 | H25: 276376.4 | I25: =242000 -> 242000 | K25: =H25-I25 -> 34376.4 | L25: =IF(K25>0,K25*3%,0) -> 1031.292 | M25: 0 | N25: =P$2*G25% -> 282208.99 | O25: 0 | P25: =ROUND(SUM(K25:O25),0) + S25 -> 317617.2 | Q25: =ROUND(P25*6% + P25,0) + S25 -> 336674.2 | R25: =ROUND(P25*3%,0) + P25 -> 327146.2 | S25: =S24+0.01 -> 0.2
A26: 13º | B26: 6 | C26: A | D26: =D25+1 -> 21 | E26: DINOTO | G26: 2.3033 | H26: 228032.42 | I26: =204999.21+23724.21 -> 228723.42 | K26: =H26-I26 -> -691 | L26: =IF(K26>0,K26*3%,0) -> 0 | M26: 0 | N26: =P$2*G26% -> 239124.44 | O26: 0 | P26: =ROUND(SUM(K26:O26),0) + S26 -> 238433.21 | Q26: =ROUND(P26*6% + P26,0) + S26 -> 252739.21 | R26: =ROUND(P26*3%,0) + P26 -> 245586.21 | S26: =S25+0.01 -> 0.21
A27: 14º | B27: 6 | C27: B | D27: =D26+1 -> 22 | E27: BORTZ ESTHER | F27: Daniel | G27: 2.636 | H27: 260970.44 | I27: =234610.22 -> 234610.22 | K27: =H27-I27 -> 26360.22 | L27: =IF(K27>0,K27*3%,0) -> 790.8066 | M27: 0 | N27: =P$2*G27% -> 273664.75 | O27: 0 | P27: =ROUND(SUM(K27:O27),0) + S27 -> 300816.22 | Q27: =ROUND(P27*6% + P27,0) + S27 -> 318865.22 | R27: =ROUND(P27*3%,0) + P27 -> 309840.22 | S27: =S26+0.01 -> 0.22 | U27: ESTA ES LA FUNDACION DE MEDICOS
A28: 15º | B28: 7 | C28: A | D28: =D27+1 -> 23 | E28: COUSO MARIA CRISTINA | G28: 2.3033 | H28: 228032.46 | I28: =204999.23+23724.23 -> 228723.46 | K28: =H28-I28 -> -691 | L28: =IF(K28>0,K28*3%,0) -> 0 | M28: 0 | N28: =P$2*G28% -> 239124.44 | O28: 0 | P28: =ROUND(SUM(K28:O28),0) + S28 -> 238433.23 | Q28: =ROUND(P28*6% + P28,0) + S28 -> 252739.23 | R28: =ROUND(P28*3%,0) + P28 -> 245586.23 | S28: =S27+0.01 -> 0.23
A29: COC | B29: 7 | C29: B | D29: =D28+1 -> 24 | E29: POSSENTI JUAN JOSE | G29: 2.6159 | H29: 258980.48 | I29: =232821.24+6159.24 -> 238980.48 | K29: =H29-I29 -> 20000 | L29: =IF(K29>0,K29*3%,0) -> 600 | M29: 0 | N29: =P$2*G29% -> 271578.01 | O29: 0 | P29: =ROUND(SUM(K29:O29),0) + S29 -> 292178.24 | Q29: =ROUND(P29*6% + P29,0) + S29 -> 309709.24 | R29: =ROUND(P29*3%,0) + P29 -> 300943.24 | S29: =S28+0.01 -> 0.24
A30: COC | B30: 8 | C30: A | D30: =D29+1 -> 25 | E30: VANNI KARINA | G30: 2.3537 | H30: 233021.5 | I30: =209484.25+24243.25 -> 233727.5 | K30: =H30-I30 -> -706 | L30: =IF(K30>0,K30*3%,0) -> 0 | M30: 0 | N30: =P$2*G30% -> 244356.88 | O30: 0 | P30: =ROUND(SUM(K30:O30),0) + S30 -> 243651.25 | Q30: =ROUND(P30*6% + P30,0) + S30 -> 258270.25 | R30: =ROUND(P30*3%,0) + P30 -> 250961.25 | S30: =S29+0.01 -> 0.25
A31: COC | B31: 8 | C31: B | D31: =D30+1 -> 26 | E31: CARRIZO RAÚL | F31: Noelia Villarino | G31: 2.6469 | H31: 262049.52 | I31: =235580.26+26469 -> 262049.26 | K31: =H31-I31 -> 0.26 | L31: =IF(K31>0,K31*3%,0) -> 0.0078 | M31: 0 | N31: =P$2*G31% -> 274796.37 | O31: 0 | P31: =ROUND(SUM(K31:O31),0) + S31 -> 274797.26 | Q31: =ROUND(P31*6% + P31,0) + S31 -> 291285.26 | R31: =ROUND(P31*3%,0) + P31 -> 283041.26 | S31: =S30+0.01 -> 0.26
A32: COC | B32: 9 | C32: A | D32: =D31+1 -> 27 | E32: BLANCO | G32: 2.3537 | H32: 233021.54 | I32: =209484.27 -> 209484.27 | K32: =H32-I32 -> 23537.27 | L32: =IF(K32>0,K32*3%,0) -> 706.1181 | M32: 0 | N32: =P$2*G32% -> 244356.88 | O32: 0 | P32: =ROUND(SUM(K32:O32),0) + S32 -> 268600.27 | Q32: =ROUND(P32*6% + P32,0) + S32 -> 284716.27 | R32: =ROUND(P32*3%,0) + P32 -> 276658.27 | S32: =S31+0.01 -> 0.27
A33: COC | B33: 9 | C33: B | D33: =D32+1 -> 28 | E33: GALANTE CELIA | G33: 2.6663 | H33: 263969.56 | I33: =237306.28 -> 237306.28 | K33: =H33-I33 -> 26663.28 | L33: =IF(K33>0,K33*3%,0) -> 799.8984 | M33: 0 | N33: =P$2*G33% -> 276810.44 | O33: 0 | P33: =ROUND(SUM(K33:O33),0) + S33 -> 304274.28 | Q33: =ROUND(P33*6% + P33,0) + S33 -> 322531.28 | R33: =ROUND(P33*3%,0) + P33 -> 313402.28 | S33: =S32+0.01 -> 0.28
A34: COC | B34: 10 | C34: A | D34: =D33+1 -> 29 | E34: LEGUIZAMON PABLO | F34: Carla | G34: 2.4476 | H34: 242318.58 | I34: =217842.29+25210.29 -> 243052.58 | K34: =H34-I34 -> -734 | L34: =IF(K34>0,K34*3%,0) -> 0 | M34: 0 | N34: =P$2*G34% -> 254105.4 | O34: 0 | P34: =ROUND(SUM(K34:O34),0) + S34 -> 253371.29 | Q34: =ROUND(P34*6% + P34,0) + S34 -> 268574.29 | R34: =ROUND(P34*3%,0) + P34 -> 260972.29 | S34: =S33+0.01 -> 0.29
A35: COC | B35: 10 | C35: B | D35: =D34+1 -> 30 | E35: CANDEL E. MARCELO | G35: 2.7183 | H35: 269118.6 | I35: =241935.3 -> 241935.3 | K35: =H35-I35 -> 27183.3 | L35: =IF(K35>0,K35*3%,0) -> 815.499 | M35: 0 | N35: =P$2*G35% -> 282208.99 | O35: 0 | P35: =ROUND(SUM(K35:O35),0) + S35 -> 310208.3 | Q35: =ROUND(P35*6% + P35,0) + S35 -> 328821.3 | R35: =ROUND(P35*3%,0) + P35 -> 319514.3 | S35: =S34+0.01 -> 0.3
A36: COC | B36: 11 | C36: A | D36: =D35+1 -> 31 | E36: DAVICCA MIGUEL | F36: Romina Navarro | G36: 2.3026 | H36: 227962.62 | I36: =209936.31 -> 209936.31 | K36: =H36-I36 -> 18026.31 | L36: =IF(K36>0,K36*3%,0) -> 540.7893 | M36: 0 | N36: =P$2*G36% -> 239051.77 | O36: 0 | P36: =ROUND(SUM(K36:O36),0) + S36 -> 257619.31 | Q36: =ROUND(P36*6% + P36,0) + S36 -> 273076.31 | R36: =ROUND(P36*3%,0) + P36 -> 265348.31 | S36: =S35+0.01 -> 0.31
A37: COC | B37: 11 | C37: B | D37: =D36+1 -> 32 | E37: GUTMAN MARIO | G37: 2.6562 | H37: 358385.64 | I37: =236407.32+26562.32 -> 262969.64 | K37: =H37-I37 -> 95416 | L37: =IF(K37>0,K37*3%,0) -> 2862.48 | M37: 0 | N37: =P$2*G37% -> 275761.88 | O37: 0 | P37: =ROUND(SUM(K37:O37),0) + S37 -> 374040.32 | Q37: =ROUND(P37*6% + P37,0) + S37 -> 396483.32 | R37: =ROUND(P37*3%,0) + P37 -> 385261.32 | S37: =S36+0.01 -> 0.32
A38: COC | B38: 12 | C38: A | D38: =D37+1 -> 33 | E38: PRATOLONGO EDUARDO | G38: 2.3343 | H38: 231101.66 | I38: =207758.33+23343 -> 231101.33 | K38: =H38-I38 -> 0.33 | L38: =IF(K38>0,K38*3%,0) -> 0.0099 | M38: 0 | N38: =P$2*G38% -> 242342.8 | O38: 0 | P38: =ROUND(SUM(K38:O38),0) + S38 -> 242343.33 | Q38: =ROUND(P38*6% + P38,0) + S38 -> 256884.33 | R38: =ROUND(P38*3%,0) + P38 -> 249613.33 | S38: =S37+0.01 -> 0.33
A39: COC | B39: 12 | C39: B | D39: =D38+1 -> 34 | E39: CARTABBIA MARIO | G39: 2.6259 | H39: 259970.68 | I39: =233711.34 -> 233711.34 | K39: =H39-I39 -> 26259.34 | L39: =IF(K39>0,K39*3%,0) -> 787.7802 | M39: 0 | N39: =P$2*G39% -> 272616.19 | O39: 0 | P39: =ROUND(SUM(K39:O39),0) + S39 -> 299663.34 | Q39: =ROUND(P39*6% + P39,0) + S39 -> 317643.34 | R39: =ROUND(P39*3%,0) + P39 -> 308653.34 | S39: =S38+0.01 -> 0.34
A40: COC | B40: 1 | C40: C | D40: =D39+1 -> 35 | E40: NAVA HECTOR | F40: Marcos | G40: 1.007 | H40: 99695.7 | I40: =89625.35 -> 89625.35 | K40: =H40-I40 -> 10070.35 | L40: =IF(K40>0,K40*3%,0) -> 302.1105 | M40: 0 | N40: =P$2*G40% -> 104544.92 | O40: 0 | P40: =ROUND(SUM(K40:O40),0) + S40 -> 114917.35 | Q40: =ROUND(P40*6% + P40,0) + S40 -> 121812.35 | R40: =ROUND(P40*3%,0) + P40 -> 118365.35 | S40: =S39+0.01 -> 0.35
A41: COC | B41: 1 | C41: D | D41: =D40+1 -> 36 | E41: BRATTOLI | F41: Palermo Hernan | G41: 0.7812 | H41: 77340.72 | I41: =H41 -> 77340.72 | K41: =H41-I41 -> 0 | L41: =IF(K41>0,K41*3%,0) -> 0 | M41: 0 | N41: =P$2*G41% -> 81102.771 | O41: 0 | P41: =ROUND(SUM(K41:O41),0) + S41 -> 81103.36 | Q41: =ROUND(P41*6% + P41,0) + S41 -> 85970.36 | R41: =ROUND(P41*3%,0) + P41 -> 83536.36 | S41: =S40+0.01 -> 0.36 | U41: PALERMO
B42: 1 | C42: E | D42: =D41+1 -> 37 | E42: BRATTOLI | F42: Palermo Hernan | G42: 1.2153 | H42: 120317.74 | I42: =178000-I41+20570 -> 121229.28 | K42: =H42-I42 -> -911.54 | L42: =IF(K42>0,K42*3%,0) -> 0 | M42: 0 | N42: =P$2*G42% -> 126170.25 | O42: 0 | P42: =ROUND(SUM(K42:O42),0) + S42 -> 125259.37 | Q42: =ROUND(P42*6% + P42,0) + S42 -> 132775.37 | R42: =ROUND(P42*3%,0) + P42 -> 129017.37 | S42: =S41+0.01 -> 0.37 | U42: PALERMO
B43: 2 | C43: C | D43: =D42+1 -> 38 | E43: MARIA I. ROTTA | F43: Mabel Rodríguez | G43: 0.9549 | H43: 97087.76 | I43: =9835.38 -> 9835.38 | K43: =H43-I43 -> 87252.38 | L43: =IF(K43>0,K43*3%,0) -> 2617.5714 | M43: 0 | N43: =P$2*G43% -> 99135.99 | O43: 0 | P43: =ROUND(SUM(K43:O43),0) + S43 -> 189006.38 | Q43: =ROUND(P43*6% + P43,0) + S43 -> 200347.38 | R43: =ROUND(P43*3%,0) + P43 -> 194676.38 | S43: =S42+0.01 -> 0.38
B44: 2 | C44: D | D44: =D43+1 -> 39 | E44: SAIN GUILLERMO | G44: 0.7552 | H44: 76782.78 | K44: =H44-I44 -> 76782.78 | L44: =IF(K44>0,K44*3%,0) -> 2303.4834 | M44: 0 | N44: =P$2*G44% -> 78403.498 | O44: 0 | P44: =ROUND(SUM(K44:O44),0) + S44 -> 157490.39 | Q44: =ROUND(P44*6% + P44,0) + S44 -> 166940.39 | R44: =ROUND(P44*3%,0) + P44 -> 162215.39 | S44: =S43+0.01 -> 0.39
B45: 2 | C45: E | D45: =D44+1 -> 40 | E45: BLANCO | F45: Jose Medina | G45: 1.1545 | H45: 114298.8 | I45: =102753.4 -> 102753.4 | K45: =H45-I45 -> 11545.4 | L45: =IF(K45>0,K45*3%,0) -> 346.362 | M45: 0 | N45: =P$2*G45% -> 119858.1 | O45: 0 | P45: =ROUND(SUM(K45:O45),0) + S45 -> 131750.4 | Q45: =ROUND(P45*6% + P45,0) + S45 -> 139655.4 | R45: =ROUND(P45*3%,0) + P45 -> 135703.4 | S45: =S44+0.01 -> 0.4
B46: 3 | C46: C | D46: =D45+1 -> 41 | E46: GOLBERG DIEGO | F46: Isabel Infante | G46: 0.9549 | H46: 97087.82 | I46: =84988.41 -> 84988.41 | K46: =H46-I46 -> 12099.41 | L46: =IF(K46>0,K46*3%,0) -> 362.9823 | M46: 0 | N46: =P$2*G46% -> 99135.99 | O46: 0 | P46: =ROUND(SUM(K46:O46),0) + S46 -> 111598.41 | Q46: =ROUND(P46*6% + P46,0) + S46 -> 118294.41 | R46: =ROUND(P46*3%,0) + P46 -> 114946.41 | S46: =S45+0.01 -> 0.41
B47: 3 | C47: D | D47: =D46+1 -> 42 | E47: CANDEL RAÚL F. | G47: 0.7552 | H47: 74766.84 | I47: =H47 -> 74766.84 | K47: =H47-I47 -> 0 | L47: =IF(K47>0,K47*3%,0) -> 0 | M47: 0 | N47: =P$2*G47% -> 78403.498 | O47: 0 | P47: =ROUND(SUM(K47:O47),0) + S47 -> 78403.42 | Q47: =ROUND(P47*6% + P47,0) + S47 -> 83108.42 | R47: =ROUND(P47*3%,0) + P47 -> 80755.42 | S47: =S46+0.01 -> 0.42
B48: 3 | C48: E | D48: =D47+1 -> 43 | E48: AZCARATE DIEGO | G48: 1.1545 | H48: 114298.86 | I48: =H48 -> 114298.86 | K48: =H48-I48 -> 0 | L48: =IF(K48>0,K48*3%,0) -> 0 | M48: 0 | N48: =P$2*G48% -> 119858.1 | O48: 0 | P48: =ROUND(SUM(K48:O48),0) + S48 -> 119858.43 | Q48: =ROUND(P48*6% + P48,0) + S48 -> 127050.43 | R48: =ROUND(P48*3%,0) + P48 -> 123454.43 | S48: =S47+0.01 -> 0.43
B49: 4 | C49: C | D49: =D48+1 -> 44 | E49: MORONI MABEL | F49: Ines Telo | G49: 0.9549 | H49: 94537.88 | I49: =84988.44+9549 -> 94537.44 | K49: =H49-I49 -> 0.44 | L49: =IF(K49>0,K49*3%,0) -> 0.0132 | M49: 0 | N49: =P$2*G49% -> 99135.99 | O49: 0 | P49: =ROUND(SUM(K49:O49),0) + S49 -> 99136.44 | Q49: =ROUND(P49*6% + P49,0) + S49 -> 105085.44 | R49: =ROUND(P49*3%,0) + P49 -> 102110.44 | S49: =S48+0.01 -> 0.44
B50: 4 | C50: D | D50: =D49+1 -> 45 | E50: BELEN CICCIARELLI | G50: 0.7552 | H50: 74766.9 | I50: =67214.45 -> 67214.45 | K50: =H50-I50 -> 7552.45 | L50: =IF(K50>0,K50*3%,0) -> 226.5735 | M50: 0 | N50: =P$2*G50% -> 78403.498 | O50: 0 | P50: =ROUND(SUM(K50:O50),0) + S50 -> 86183.45 | Q50: =ROUND(P50*6% + P50,0) + S50 -> 91354.45 | R50: =ROUND(P50*3%,0) + P50 -> 88769.45 | S50: =S49+0.01 -> 0.45
B51: 4 | C51: E | D51: =D50+1 -> 46 | E51: PARMA | F51: Ezequiel Caputo | G51: 1.1545 | H51: 114298.92 | I51: =102753.46 -> 102753.46 | K51: =H51-I51 -> 11545.46 | L51: =IF(K51>0,K51*3%,0) -> 346.3638 | M51: 0 | N51: =P$2*G51% -> 119858.1 | O51: 0 | P51: =ROUND(SUM(K51:O51),0) + S51 -> 131750.46 | Q51: =ROUND(P51*6% + P51,0) + S51 -> 139655.46 | R51: =ROUND(P51*3%,0) + P51 -> 135703.46 | S51: =S50+0.01 -> 0.46
B52: 5 | C52: C | D52: =D51+1 -> 47 | E52: TORRES BASSO RUBEN | F52: Andrea | G52: 0.9549 | H52: 106340.94 | I52: =9549+96791.47 -> 106340.47 | K52: =H52-I52 -> 0.47 | L52: =IF(K52>0,K52*3%,0) -> 0.0141 | M52: 0 | N52: =P$2*G52% -> 99135.99 | O52: 0 | P52: =ROUND(SUM(K52:O52),0) + S52 -> 99136.47 | Q52: =ROUND(P52*6% + P52,0) + S52 -> 105085.47 | R52: =ROUND(P52*3%,0) + P52 -> 102110.47 | S52: =S51+0.01 -> 0.47
B53: 5 | C53: D | D53: =D52+1 -> 48 | E53: CANDEL MARCELO | F53: Romina Barbara Lotfi | G53: 0.7552 | H53: 74766.96 | I53: =67215+7552 -> 74767 | K53: =H53-I53 -> -0.04 | L53: =IF(K53>0,K53*3%,0) -> 0 | M53: 0 | N53: =P$2*G53% -> 78403.498 | O53: 0 | P53: =ROUND(SUM(K53:O53),0) + S53 -> 78403.48 | Q53: =ROUND(P53*6% + P53,0) + S53 -> 83108.48 | R53: =ROUND(P53*3%,0) + P53 -> 80755.48 | S53: =S52+0.01 -> 0.48
B54: 5 | C54: E | D54: =D53+1 -> 49 | E54: WAINBERG LUIS | F54: Lionel Giglia | G54: 1.1545 | H54: 117381.98 | I54: =102753.49+11545.49+3083 -> 117381.98 | K54: =H54-I54 -> 0 | L54: =IF(K54>0,K54*3%,0) -> 0 | M54: 0 | N54: =P$2*G54% -> 119858.1 | O54: 0 | P54: =ROUND(SUM(K54:O54),0) + S54 -> 119858.49 | Q54: =ROUND(P54*6% + P54,0) + S54 -> 127050.49 | R54: =ROUND(P54*3%,0) + P54 -> 123454.49 | S54: =S53+0.01 -> 0.49
B55: 6 | C55: C | D55: =D54+1 -> 50 | E55: STELLISANO VICTORIA | G55: 0.9549 | H55: 94538 | I55: =84988.5+9835.5 -> 94824 | K55: =H55-I55 -> -286 | L55: =IF(K55>0,K55*3%,0) -> 0 | M55: 0 | N55: =P$2*G55% -> 99135.99 | O55: 0 | P55: =ROUND(SUM(K55:O55),0) + S55 -> 98850.5 | Q55: =ROUND(P55*6% + P55,0) + S55 -> 104782.5 | R55: =ROUND(P55*3%,0) + P55 -> 101816.5 | S55: =S54+0.01 -> 0.5
B56: 6 | C56: D | D56: =D55+1 -> 51 | E56: GEFFNER JORGE RAÚL | G56: 0.7552 | H56: 150272.02 | I56: =67214+7759.51 -> 74973.51 | K56: =H56-I56 -> 75298.51 | L56: =IF(K56>0,K56*3%,0) -> 2258.9553 | M56: 0 | N56: =P$2*G56% -> 78403.498 | O56: 0 | P56: =ROUND(SUM(K56:O56),0) + S56 -> 155961.51 | Q56: =ROUND(P56*6% + P56,0) + S56 -> 165319.51 | R56: =ROUND(P56*3%,0) + P56 -> 160640.51 | S56: =S55+0.01 -> 0.51
B57: 6 | C57: E | D57: =D56+1 -> 52 | E57: REY ALICIA | G57: 1.1545 | H57: 114299.04 | I57: =102753.52+11891.52 -> 114645.04 | K57: =H57-I57 -> -346 | L57: =IF(K57>0,K57*3%,0) -> 0 | M57: 0 | N57: =P$2*G57% -> 119858.1 | O57: 0 | P57: =ROUND(SUM(K57:O57),0) + S57 -> 119512.52 | Q57: =ROUND(P57*6% + P57,0) + S57 -> 126683.52 | R57: =ROUND(P57*3%,0) + P57 -> 123097.52 | S57: =S56+0.01 -> 0.52
B58: 7 | C58: C | D58: =D57+1 -> 53 | E58: DE SERIO BOFFA | G58: 0.9549 | H58: 94538.06 | I58: =84988.53+9549.53 -> 94538.06 | K58: =H58-I58 -> 0 | L58: =IF(K58>0,K58*3%,0) -> 0 | M58: 0 | N58: =P$2*G58% -> 99135.99 | O58: 0 | P58: =ROUND(SUM(K58:O58),0) + S58 -> 99136.53 | Q58: =ROUND(P58*6% + P58,0) + S58 -> 105085.53 | R58: =ROUND(P58*3%,0) + P58 -> 102110.53 | S58: =S57+0.01 -> 0.53
B59: 7 | C59: D | D59: =D58+1 -> 54 | E59: ALVAREZ EDUARDO | G59: 0.7552 | H59: 74767.08 | I59: =H59 -> 74767.08 | K59: =H59-I59 -> 0 | L59: =IF(K59>0,K59*3%,0) -> 0 | M59: 0 | N59: =P$2*G59% -> 78403.498 | O59: 0 | P59: =ROUND(SUM(K59:O59),0) + S59 -> 78403.54 | Q59: =ROUND(P59*6% + P59,0) + S59 -> 83108.54 | R59: =ROUND(P59*3%,0) + P59 -> 80755.54 | S59: =S58+0.01 -> 0.54
B60: 7 | C60: E | D60: =D59+1 -> 55 | E60: MANDELLI MARIA | F60: Analía | G60: 1.1545 | H60: 337689.1 | I60: =102753 -> 102753 | K60: =H60-I60 -> 234936.1 | L60: =IF(K60>0,K60*3%,0) -> 7048.083 | M60: 0 | N60: =P$2*G60% -> 119858.1 | O60: 0 | P60: =ROUND(SUM(K60:O60),0) + S60 -> 361842.55 | Q60: =ROUND(P60*6% + P60,0) + S60 -> 383553.55 | R60: =ROUND(P60*3%,0) + P60 -> 372697.55 | S60: =S59+0.01 -> 0.55
B61: 8 | C61: C | D61: =D60+1 -> 56 | E61: BRITEZ M. | F61: Francini IGNACIO | G61: 0.9549 | H61: 94538.12 | I61: =84988.56 -> 84988.56 | K61: =H61-I61 -> 9549.56 | L61: =IF(K61>0,K61*3%,0) -> 286.4868 | M61: 0 | N61: =P$2*G61% -> 99135.99 | P61: =ROUND(SUM(K61:O61),0) + S61 -> 108972.56 | Q61: =ROUND(P61*6% + P61,0) + S61 -> 115511.56 | R61: =ROUND(P61*3%,0) + P61 -> 112241.56 | S61: =S60+0.01 -> 0.56
B62: 8 | C62: D | D62: =D61+1 -> 57 | E62: FERREIRO MARTA | F62: Jorge Sicilia | G62: 0.7552 | H62: 76783.14 | K62: =H62-I62 -> 76783.14 | L62: =IF(K62>0,K62*3%,0) -> 2303.4942 | M62: 0 | N62: =P$2*G62% -> 78403.498 | O62: 0 | P62: =ROUND(SUM(K62:O62),0) + S62 -> 157490.57 | Q62: =ROUND(P62*6% + P62,0) + S62 -> 166940.57 | R62: =ROUND(P62*3%,0) + P62 -> 162215.57 | S62: =S61+0.01 -> 0.57
B63: 8 | C63: E | D63: =D62+1 -> 58 | E63: VENTIMIGLIA SILVANA | G63: 1.1545 | H63: 114299.16 | I63: =102753.58+11546 -> 114299.58 | K63: =H63-I63 -> -0.42 | L63: =IF(K63>0,K63*3%,0) -> 0 | M63: 0 | N63: =P$2*G63% -> 119858.1 | O63: 0 | P63: =ROUND(SUM(K63:O63),0) + S63 -> 119858.58 | Q63: =ROUND(P63*6% + P63,0) + S63 -> 127050.58 | R63: =ROUND(P63*3%,0) + P63 -> 123454.58 | S63: =S62+0.01 -> 0.58
B64: 9 | C64: C | D64: =D63+1 -> 59 | E64: CIGNOLI | F64: Pablo Coiro | G64: 0.9549 | H64: 94538.18 | I64: =84988.59 -> 84988.59 | K64: =H64-I64 -> 9549.59 | L64: =IF(K64>0,K64*3%,0) -> 286.4877 | M64: 0 | N64: =P$2*G64% -> 99135.99 | O64: 0 | P64: =ROUND(SUM(K64:O64),0) + S64 -> 108972.59 | Q64: =ROUND(P64*6% + P64,0) + S64 -> 115511.59 | R64: =ROUND(P64*3%,0) + P64 -> 112241.59 | S64: =S63+0.01 -> 0.59
B65: 9 | C65: D | D65: =D64+1 -> 60 | E65: RECHIMUZZI | G65: 0.7552 | H65: 150272.2 | I65: =75505 -> 75505 | K65: =H65-I65 -> 74767.2 | L65: =IF(K65>0,K65*3%,0) -> 2243.016 | M65: 0 | N65: =P$2*G65% -> 78403.498 | O65: 0 | P65: =ROUND(SUM(K65:O65),0) + S65 -> 155414.6 | Q65: =ROUND(P65*6% + P65,0) + S65 -> 164739.6 | R65: =ROUND(P65*3%,0) + P65 -> 160076.6 | S65: =S64+0.01 -> 0.6
B66: 9 | C66: E | D66: =D65+1 -> 61 | E66: RIVA MÓNICA | G66: 1.1545 | H66: 114299.22 | I66: =102753.61+11546 -> 114299.61 | K66: =H66-I66 -> -0.39 | L66: =IF(K66>0,K66*3%,0) -> 0 | M66: 0 | N66: =P$2*G66% -> 119858.1 | O66: 0 | P66: =ROUND(SUM(K66:O66),0) + S66 -> 119858.61 | Q66: =ROUND(P66*6% + P66,0) + S66 -> 127050.61 | R66: =ROUND(P66*3%,0) + P66 -> 123454.61 | S66: =S65+0.01 -> 0.61
B67: 10 | C67: C | D67: =D66+1 -> 62 | E67: GENTILE EDUARDO | F67: Aldana | G67: 0.9549 | H67: 190009.24 | I67: =84988+9459.62 -> 94447.62 | K67: =H67-I67 -> 95561.62 | L67: =IF(K67>0,K67*3%,0) -> 2866.8486 | M67: 0 | N67: =P$2*G67% -> 99135.99 | O67: 0 | P67: =ROUND(SUM(K67:O67),0) + S67 -> 197564.62 | Q67: =ROUND(P67*6% + P67,0) + S67 -> 209418.62 | R67: =ROUND(P67*3%,0) + P67 -> 203491.62 | S67: =S66+0.01 -> 0.62
B68: 10 | C68: D | D68: =D67+1 -> 63 | E68: CANDEL MARCELO | F68: Brian Alvarez | G68: 0.7552 | H68: 142719.63 | I68: =H68 -> 142719.63 | K68: =H68-I68 -> 0 | L68: =IF(K68>0,K68*3%,0) -> 0 | M68: 0 | N68: =P$2*G68% -> 78403.498 | O68: 0 | P68: =ROUND(SUM(K68:O68),0) + S68 -> 78403.63 | Q68: =ROUND(P68*6% + P68,0) + S68 -> 83108.63 | R68: =ROUND(P68*3%,0) + P68 -> 80755.63 | S68: =S67+0.01 -> 0.63 | U68: brian exige plata a favor pero desde donde tenemos entendido NO PAGO DICIEMBRE
B69: 10 | C69: E | D69: =D68+1 -> 64 | E69: CANDEL RAÚL F. | G69: 1.1545 | H69: 114299.28 | I69: =H69 -> 114299.28 | K69: =H69-I69 -> 0 | L69: =IF(K69>0,K69*3%,0) -> 0 | M69: 0 | N69: =P$2*G69% -> 119858.1 | O69: 0 | P69: =ROUND(SUM(K69:O69),0) + S69 -> 119858.64 | Q69: =ROUND(P69*6% + P69,0) + S69 -> 127050.64 | R69: =ROUND(P69*3%,0) + P69 -> 123454.64 | S69: =S68+0.01 -> 0.64
B70: 11 | C70: C | D70: =D69+1 -> 65 | E70: LORUSSO DORA | G70: 0.9549 | H70: 94538.3 | I70: =84988.65 -> 84988.65 | K70: =H70-I70 -> 9549.65 | L70: =IF(K70>0,K70*3%,0) -> 286.4895 | M70: 0 | N70: =P$2*G70% -> 99135.99 | O70: 0 | P70: =ROUND(SUM(K70:O70),0) + S70 -> 108972.65 | Q70: =ROUND(P70*6% + P70,0) + S70 -> 115511.65 | R70: =ROUND(P70*3%,0) + P70 -> 112241.65 | S70: =S69+0.01 -> 0.65
B71: 11 | C71: D | D71: =D70+1 -> 66 | E71: FERÁNDEZ HÉCTOR | F71: Melina Navarro | G71: 0.7552 | H71: 150272.32 | I71: =75504.66+67214+7779.66 -> 150498.32 | K71: =H71-I71 -> -226 | L71: =IF(K71>0,K71*3%,0) -> 0 | M71: 0 | N71: =P$2*G71% -> 78403.498 | O71: 0 | P71: =ROUND(SUM(K71:O71),0) + S71 -> 78177.66 | Q71: =ROUND(P71*6% + P71,0) + S71 -> 82868.66 | R71: =ROUND(P71*3%,0) + P71 -> 80522.66 | S71: =S70+0.01 -> 0.66
B72: 11 | C72: E | D72: =D71+1 -> 67 | E72: KARGODORIAN SILVIA | G72: 1.1545 | H72: 236271.34 | I72: =218180.67 -> 218180.67 | K72: =H72-I72 -> 18090.67 | L72: =IF(K72>0,K72*3%,0) -> 542.7201 | M72: 0 | N72: =P$2*G72% -> 119858.1 | O72: 0 | P72: =ROUND(SUM(K72:O72),0) + S72 -> 138491.67 | Q72: =ROUND(P72*6% + P72,0) + S72 -> 146801.67 | R72: =ROUND(P72*3%,0) + P72 -> 142646.67 | S72: =S71+0.01 -> 0.67
B73: 12 | C73: C | D73: =D72+1 -> 68 | E73: ALVAREZ | G73: 0.9549 | H73: 94538.36 | I73: =H73 -> 94538.36 | K73: =H73-I73 -> 0 | L73: =IF(K73>0,K73*3%,0) -> 0 | M73: 0 | N73: =P$2*G73% -> 99135.99 | O73: 0 | P73: =ROUND(SUM(K73:O73),0) + S73 -> 99136.68 | Q73: =ROUND(P73*6% + P73,0) + S73 -> 105085.68 | R73: =ROUND(P73*3%,0) + P73 -> 102110.68 | S73: =S72+0.01 -> 0.68
B74: 12 | C74: D | D74: =D73+1 -> 69 | E74: RIVA MÓNICA | G74: 0.7552 | H74: 74767.38 | I74: =67214.69+7553 -> 74767.69 | K74: =H74-I74 -> -0.31 | L74: =IF(K74>0,K74*3%,0) -> 0 | M74: 0 | N74: =P$2*G74% -> 78403.498 | O74: 0 | P74: =ROUND(SUM(K74:O74),0) + S74 -> 78403.69 | Q74: =ROUND(P74*6% + P74,0) + S74 -> 83108.69 | R74: =ROUND(P74*3%,0) + P74 -> 80755.69 | S74: =S73+0.01 -> 0.69
B75: 12 | C75: E | D75: =D74+1 -> 70 | E75: DE BIAGGIO PABLO | G75: 1.1549 | H75: 114339.4 | I75: =102789.7 -> 102789.7 | K75: =H75-I75 -> 11549.7 | L75: =IF(K75>0,K75*3%,0) -> 346.491 | M75: 0 | N75: =P$2*G75% -> 119899.63 | O75: 0 | P75: =ROUND(SUM(K75:O75),0) + S75 -> 131796.7 | Q75: =ROUND(P75*6% + P75,0) + S75 -> 139705.7 | R75: =ROUND(P75*3%,0) + P75 -> 135750.7 | S75: =S74+0.01 -> 0.7
H76: 0
G81: =SUM(G6:G80) -> 100 | H81: =SUM(H6:H80) -> 12076563 | I81: =SUM(I6:I80) -> 9182407.9 | J81: =SUM(J6:J80) -> 0 | K81: =SUM(K6:K80) -> 2894155.2 | L81: =SUM(L6:L80) -> 88503.715 | M81: =SUM(M6:M80) -> 0 | N81: =SUM(N6:N80) -> 10381819 | ... R81: =SUM(R6:R80) -> 13765435
E84: =RESUMEN!A14 -> ESTIMADOS PROPIETARIOS E INQUILINOS: POR FAVOR LOS QUE ABONAN EN PRIMER VENCIMIENTO ABONEN EL MONTO DE PRIMER VENCIMIENTO, ASI AGILIZAN LA LIQUIDACION, RESPETEN LOS CENTAVOS CORRESPONDIENTES A LA UNIDAD FUNCIONAL. ES DE CARÁCTER OBLIGATORIO INFORMAR VIA MAIL LAS EXPENSAS. CASO CONTRARIO SE INFORMARA VIA CARTA DOCUMENTO A LA UNIDAD FUNCIONAL QUE CREEMOS QUE CORRESPONDE, CUYO COSTO SERA IMPUTADO A LA UNIDAD FUNCIONAL SOSPECHADA.
