Workbook

Sheet RESUMEN
B2: MAIL: consorciogorriti368@gmail.com
B3: CUIT ADMINISTRACION: 27231256879
B4: CBU: 0290034600000502294350 | D4: TELEFONO: 11 5320-2676
A5: LIQUIDACION DE EXPENSAS | B5: ADMINISTRADORA: CAROLINA CANCIANI MP:1148
A6: CUIT DEL EDIFICIO: 30583957819 | B6: PERÍODO: AGOSTO | D6: HORARIOS DE ATENCION: LUNES A VIERNES
A7: CONSORCIO DE PROPIETARIOS DEL EDIFICIO CALLE GORRITI 368 | D7: 10 A 16HS - EMERGENCIAS 24HS
B9: VTO 15/09
A14: ESTIMADOS PROPIETARIOS E INQUILINOS: POR FAVOR LOS QUE ABONAN EN PRIMER VENCIMIENTO ABONEN EL MONTO DE PRIMER VENCIMIENTO, ASI AGILIZAN LA LIQUIDACION, RESPETEN LOS CENTAVOS CORRESPONDIENTES A LA UNIDAD FUNCIONAL. ES DE CARÁCTER OBLIGATORIO INFORMAR VIA MAIL LAS EXPENSAS. CASO CONTRARIO SE INFORMARA VIA CARTA DOCUMENTO A LA UNIDAD FUNCIONAL QUE CREEMOS QUE CORRESPONDE, CUYO COSTO SERA IMPUTADO A LA UNIDAD FUNCIONAL SOSPECHADA.
A21: GASTOS ORDINARIOS UNIDADES FUNCIONALES:
A22: HABERES ENCARGADOS
A23: Sueldo encargado Colmiero Oscar | D23: 1271490
A26: Retenciones | D26: 0
A28: Neto | D28: =SUM(D23:D27) -> 1271490 | G28: =D28+D30 -> 2313543
A29: Sueldo encargado Balcazza Leonardo | D29: 1042053 | G29: =700000 -> 700000
A30: Neto | D30: =SUM(D29:D29) -> 1042053 | G30: =G28-G29 -> 1613543
A31: Sueldo Alcaraz Gisela - Reemplazo del Sr. Leonardo | D31: 98440 | G31: -500000 | H31: Efectivo
A32: Neto | D32: =SUM(D31) -> 98440 | G32: =G30+G31 -> 1113543
A33: TOTAL SUELDO | E33: =D28+D30+D32 -> 2411983
A34: HONORARIOS
A35: HONORARIOS CONTADOR GUSTAVO PADRON | D35: 90000 | E35: Transf 14/07
A36: HONORARIOS ADMINISTRACION RC - SE ABONA EL MES JULIO - SE DEBE AGOSTO | D36: 249000 | E36: Transf 14/07
A37: TOTAL | E37: =SUM(D35:D36) -> 339000
A38: SEGUROS
A39: Seguro Integral consorcio San Cristobal - Poliza 01-05-07-30183461 | D39: 144149 | E39: Debito 10/07
A41: TOTAL IMPUESTO | E41: =SUM(D39:D40) -> 144149
A42: APORTES Y CONTRIBUCIONES
A43: ARCA | D43: 1843741.1 | E43: PMC 12/08
A44: Sindicatos mes de AGOSTO | B44: Fatheryh | D44: 133047.14 | E44: Debito 14/07
A45: =A44 -> Sindicatos mes de AGOSTO | B45: Suther | D45: 241435.09 | E45: =E44 -> Debito 14/07
A46: =A45 -> Sindicatos mes de AGOSTO | B46: Seracarh | D46: 14783.02 | E46: =E45 -> Debito 14/07
A47: TOTAL Aportes y Contribuciones - Sindicato | E47: =SUM(D43:D46) -> 2233006.4
A48: ABONOS Y SERVICIOS
A49: EDESUR - Cliente nro. 828563 | D49: 1002998.2 | E49: Transf 19/08
A50: EDESUR - Cliente nro. 01672309 | D50: 23385.69 | E50: Transf 11/08
A51: EDESUR - Cliente nro. 01672321 | D51: 14748.22 | E51: =E50 -> Transf 11/08
A52: EDESUR - Cliente nro. 01672319 | D52: 12432.23 | E52: =E51 -> Transf 11/08
A53: Metrogas - Cliente nro. 20463936100 | D53: 5586.39 | E53: Transf 18/08
A54: Metrogas - Cliente nro. 20495697900 | D54: 2046270.6 | E54: Debito 17/07
A55: Personal Flow - Debito automatico | D55: 23728.51 | E55: Debito 21/07
A56: AYSA - Nro de cliente 3888610 | D56: 2168902.4 | E56: Debito 17/07
A58: TOTAL ABONOS Y SERVICIOS | E58: =SUM(D49:D57) -> 5298052.2
A59: GASTOS GENERALES / MANTENIMIENTO
A60: Castellano Alejandro - Abono de servicio de mantenimiento de grupo electrogeno y porton | D60: 48400 | E60: Transf 30/07
A61: Fumigacion Viturro Alberto | D61: 56800 | E61: Transf 19/08
A62: Ascensores Lema mantenimiento | D62: 135000 | E62: Transf 21/07
A63: Ascensores Lema - Provision y colocacion de 95mts de cable de acero para sistema de caida de frenos mecanico | D63: 770000 | E63: Transf 17/07
A64: Doartero Mano de obra cañeria principal de subida de tanque | D64: 300000 | E64: Transf 21/07
A65: Doartero Mano de obra y materiales recubrimiento de caño bajada | D65: 300000 | E65: Transf 22/08
A66: Doartero Mano de obra reparacion y cambio de luces piso 13 | D66: 150000 | E66: Transf 01/08
A67: Doartero mano de obra reparacion de portero | D67: 150000 | E67: Transf 10/07
A68: Articulos de limpieza | D68: =65050+57650 -> 122700 | E68: Transf 21/07
A69: Sanitarios roma - Materiales | D69: 95706.73
A70: Matafuegos FIRE - Recarga | D70: 481849.77 | E70: Transf 21/07
A71: TOTAL | E71: =SUM(D60:D70) -> 2610456.5
A72: GASTOS BANCARIOS
A73: GASTOS BANCARIOS | D73: =156032.49 -> 156032.49
A74: MANTENIMIENTO DE CUENTA - NO SE DEBITO NUEVAMENTE | G74: EN MAY, JUNI, JULI NO SE DEBITA EL MANTENIMIENTO DE CUENTA
A75: TOTAL | E75: =SUM(D73:D74) -> 156032.49
A77: PREVISION ORDINARIA - ADECUACION EDESUR - LIMPIEZA DE TANQUES - GASTOS VARIOS QUE NO SE REALIZAN POR FALTA DE CAJA | E77: 1500000
A79: TOTAL ORDINARIOS | E79: =(SUM(E30:E77)) -> 14692680
A82: GASTOS EXTRAORDINARIOS:
E87: =SUM(D83:D86) -> 0
A90: PREVISION EXTRAORDINARIA
A92: TOTAL EXTRAORDINARIOS | E92: =E87+E90 -> 0
A94: GASTOS ORDINARIOS + PREVISION : | B94: =E79 -> 14692680
A95: GASTOS ORDINARIOS SIN PREVISION: | B95: =E79-E77 -> 13192680
A96: GASTOS EXTRAORDINARIOS SIN PREVISION: | B96: =E92-E90 -> 0
A97: GASTOS EXTRAORDINARIOS CON PREVISION: | B97: =E92 -> 0
A103: RESUMEN
B104: 0
A105: Ingreso | B105: =PRORRATEO!I81 -> 12230350
B106: 0
A107: Deposito sin identificar | B107: =B130 -> 0
A109: Punitorios mal cobrados
A110: Egresos Ordinarios | B110: =-B95 -> -13192680
A111: Egresos Extraordinarios | B111: =-(B96) -> 0
A112: TOTAL | B112: =SUM(B104:B111) -> -962329.47
A116: SALDO ANTERIOR | B116: 412214.68
A117: Egresos del mes ordinarios | B117: =-B95 -> -13192680
A118: Egresos del mes extrordinarios | B118: =-B96 -> 0
A119: Ingresos sin identificar | B119: =B130 -> 0
A120: Ingreso sin identificar ya identificado Diciembre 24 | B120: -112065.15
A121: Ingresos | B121: =PRORRATEO!I81 -> 12230350
A122: Punitorios mal cobrados
A123: CAJA REAL | B123: =SUM(B116:C122) -> -662179.94
A126: DEPOSITOS NO IDENTIFICADOS
C128: 40000
A130: TOTAL | B130: =SUM(B128:B129) -> 0

Sheet PRORRATEO
E2: =RESUMEN!B4 -> CBU: 0290034600000502294350 | L2: Gastos ordinarios: | P2: =U2 -> 14485791 | U2: 14485791
A4: Piso | B4: Dpto. | D4: UF | E4: Propietario | F4: Inquilinos | G4: (%) | H4: Saldo Ord | I4: Ingreso | J4: Pago por | K4: Deuda o Saldo a favor | L4: Interes 3% | M4: Expensas extraor. | N4: Expensas ord. | O4: Gastos part. | P4: Total 1er Vto | Q4: Total 2do Vto. | R4: Total 2do Vto
P5: =RESUMEN!B9 -> VTO 15/09
A6: PB | C6: LOC | D6: 1 | E6: GEFFNER SILVIA E. | G6: 0.5131 | H6: 63505.01 | I6: =786304-I13-I7-I47-I48-I59-I69-I73 -> 63505.19 | K6: =H6-I6 -> -0.18 | L6: =IF(K6>0,K6*3%,0) -> 0 | M6: 0 | N6: =P$2*G6% -> 74326.596 | O6: 0 | P6: =ROUND(SUM(K6:O6),0) + S6 -> 74326.01 | Q6: =ROUND(P6*6% + P6,0) + S6 -> 78786.01 | R6: =ROUND(P6*3%,0) + P6 -> 76556.01 | S6: 0.01 | U6: este es el candel que tiene a todas sus demas ufs relacionadas
A7: 3º | C7: LOC | D7: =D6+1 -> 2 | E7: COVILOZA S. A. | G7: 0.6119 | H7: 75734.02 | I7: =H7 -> 75734.02 | K7: =H7-I7 -> 0 | L7: =IF(K7>0,K7*3%,0) -> 0 | M7: 0 | N7: =P$2*G7% -> 88638.558 | O7: 0 | P7: =ROUND(SUM(K7:O7),0) + S7 -> 88639.02 | Q7: =ROUND(P7*6% + P7,0) + S7 -> 93957.02 | R7: =ROUND(P7*3%,0) + P7 -> 91298.02 | S7: =S6+0.01 -> 0.02
A8: 3º | B8: 1 | D8: =D7+1 -> 3 | E8: ASIST Y TRAB. | G8: 0.6115 | H8: 75684.03 | I8: =H8 -> 75684.03 | K8: =H8-I8 -> 0 | L8: =IF(K8>0,K8*3%,0) -> 0 | M8: 0 | N8: =P$2*G8% -> 88580.614 | O8: 0 | P8: =ROUND(SUM(K8:O8),0) + S8 -> 88581.03 | Q8: =ROUND(P8*6% + P8,0) + S8 -> 93896.03 | R8: =ROUND(P8*3%,0) + P8 -> 91238.03 | S8: =S7+0.01 -> 0.03
A9: 4º | B9: 2 | D9: =D8+1 -> 4 | E9: ASIST Y TRAB. | G9: 0.5033 | H9: 62293.04 | I9: =H9 -> 62293.04 | K9: =H9-I9 -> 0 | L9: =IF(K9>0,K9*3%,0) -> 0 | M9: 0 | N9: =P$2*G9% -> 72906.988 | O9: 0 | P9: =ROUND(SUM(K9:O9),0) + S9 -> 72907.04 | Q9: =ROUND(P9*6% + P9,0) + S9 -> 77281.04 | R9: =ROUND(P9*3%,0) + P9 -> 75094.04 | S9: =S8+0.01 -> 0.04
A10: 4º | B10: 3 | D10: =D9+1 -> 5 | E10: ASIST Y TRAB. | G10: 0.5033 | H10: 62293.05 | I10: =H10 -> 62293.05 | K10: =H10-I10 -> 0 | L10: =IF(K10>0,K10*3%,0) -> 0 | M10: 0 | N10: =P$2*G10% -> 72906.988 | O10: 0 | P10: =ROUND(SUM(K10:O10),0) + S10 -> 72907.05 | Q10: =ROUND(P10*6% + P10,0) + S10 -> 77281.05 | R10: =ROUND(P10*3%,0) + P10 -> 75094.05 | S10: =S9+0.01 -> 0.05
A11: 5º | B11: 4 | D11: =D10+1 -> 6 | E11: BENMAOR D. | F11: Cristian Requelme | G11: 0.7499 | H11: 92814.06 | I11: =H11 -> 92814.06 | K11: =H11-I11 -> 0 | L11: =IF(K11>0,K11*3%,0) -> 0 | M11: 0 | N11: =P$2*G11% -> 108628.95 | O11: 0 | P11: =ROUND(SUM(K11:O11),0) + S11 -> 108629.06 | Q11: =ROUND(P11*6% + P11,0) + S11 -> 115147.06 | R11: =ROUND(P11*3%,0) + P11 -> 111888.06 | S11: =S10+0.01 -> 0.06
A12: 5º | B12: 5 | D12: =D11+1 -> 7 | E12: GALANTERNIK A | F12: Miriam Larken | G12: 0.5425 | H12: 67144.07 | I12: =H12 -> 67144.07 | K12: =H12-I12 -> 0 | L12: =IF(K12>0,K12*3%,0) -> 0 | M12: 0 | N12: =P$2*G12% -> 78585.418 | O12: 0 | P12: =ROUND(SUM(K12:O12),0) + S12 -> 78585.07 | Q12: =ROUND(P12*6% + P12,0) + S12 -> 83300.07 | R12: =ROUND(P12*3%,0) + P12 -> 80943.07 | S12: =S11+0.01 -> 0.07
A13: 6º | B13: 6 | D13: =D12+1 -> 8 | E13: CANDEL JORGE ISAAC | G13: 0.4537 | H13: 56154.08 | I13: =H13 -> 56154.08 | K13: =H13-I13 -> 0 | L13: =IF(K13>0,K13*3%,0) -> 0 | M13: 0 | N13: =P$2*G13% -> 65722.036 | O13: 0 | P13: =ROUND(SUM(K13:O13),0) + S13 -> 65722.08 | Q13: =ROUND(P13*6% + P13,0) + S13 -> 69665.08 | R13: =ROUND(P13*3%,0) + P13 -> 67694.08 | S13: =S12+0.01 -> 0.08
A14: 6º | B14: 7 | D14: =D13+1 -> 9 | E14: BORTZ SERGIO | F14: Luciana | G14: 0.5244 | H14: 131755.09 | I14: 200000.09 | K14: =H14-I14 -> -68245 | L14: =IF(K14>0,K14*3%,0) -> 0 | M14: 0 | N14: =P$2*G14% -> 75963.49 | O14: 0 | P14: =ROUND(SUM(K14:O14),0) + S14 -> 7718.09 | Q14: =ROUND(P14*6% + P14,0) + S14 -> 8181.09 | R14: =ROUND(P14*3%,0) + P14 -> 7950.09 | S14: =S13+0.01 -> 0.09 | U14: ESTA ES LA FUNDACION DE MEDICOS
A15: 7º | B15: 8 | D15: =D14+1 -> 10 | E15: BORTZ SERGIO | F15: Luciana | G15: 0.424 | H15: 106530.1 | I15: 200000.1 | K15: =H15-I15 -> -93470 | L15: =IF(K15>0,K15*3%,0) -> 0 | M15: 0 | N15: =P$2*G15% -> 61419.756 | O15: 0 | P15: =ROUND(SUM(K15:O15),0) + S15 -> -32049.9 | Q15: =ROUND(P15*6% + P15,0) + S15 -> -33972.9 | R15: =ROUND(P15*3%,0) + P15 -> -33010.9 | S15: =S14+0.01 -> 0.1 | U15: ESTA ES LA FUNDACION DE MEDICOS
A16: 7º | B16: 1 | C16: A | D16: =D15+1 -> 11 | E16: KIM SOON LEO | G16: 2.3033 | H16: 3639445.1 | K16: =H16-I16 -> 3639445.1 | L16: =IF(K16>0,K16*3%,0) -> 109183.35 | M16: 0 | N16: =P$2*G16% -> 333651.23 | O16: 0 | P16: =ROUND(SUM(K16:O16),0) + S16 -> 4082280.1 | Q16: =ROUND(P16*6% + P16,0) + S16 -> 4327217.1 | R16: =ROUND(P16*3%,0) + P16 -> 4204748.1 | S16: =S15+0.01 -> 0.11
A17: 8º | B17: 1 | C17: B | D17: =D16+1 -> 12 | E17: CANDEL MARCELO | F17: Florencia Fucci | G17: 2.7493 | H17: 350484.12 | I17: =H17 -> 350484.12 | K17: =H17-I17 -> 0 | L17: =IF(K17>0,K17*3%,0) -> 0 | M17: 0 | N17: =P$2*G17% -> 398257.86 | O17: 0 | P17: =ROUND(SUM(K17:O17),0) + S17 -> 398258.12 | Q17: =ROUND(P17*6% + P17,0) + S17 -> 422154.12 | R17: =ROUND(P17*3%,0) + P17 -> 410206.12 | S17: =S16+0.01 -> 0.12
A18: 8º | B18: 2 | C18: A | D18: =D17+1 -> 13 | E18: TRIPODI | F18: Mariela Pricolo | G18: 2.3033 | H18: 285076.13 | I18: =H18 -> 285076.13 | K18: =H18-I18 -> 0 | L18: =IF(K18>0,K18*3%,0) -> 0 | M18: 0 | N18: =P$2*G18% -> 333651.23 | O18: 0 | P18: =ROUND(SUM(K18:O18),0) + S18 -> 333651.13 | Q18: =ROUND(P18*6% + P18,0) + S18 -> 353670.13 | R18: =ROUND(P18*3%,0) + P18 -> 343661.13 | S18: =S17+0.01 -> 0.13
A19: 9º | B19: 2 | C19: B | D19: =D18+1 -> 14 | E19: MIRANDA DE GIL | F19: Susana | G19: 2.6368 | H19: 621056.14 | I19: =40000 -> 40000 | K19: =H19-I19 -> 581056.14 | L19: =IF(K19>0,K19*3%,0) -> 17431.684 | M19: 0 | N19: =P$2*G19% -> 381961.35 | O19: 0 | P19: =ROUND(SUM(K19:O19),0) + S19 -> 980449.14 | Q19: =ROUND(P19*6% + P19,0) + S19 -> 1039276.1 | R19: =ROUND(P19*3%,0) + P19 -> 1009862.1 | S19: =S18+0.01 -> 0.14 | U19: MAXIMO
A20: 9º | B20: 3 | C20: A | D20: =D19+1 -> 15 | E20: FRAGA DORA | G20: 2.3537 | H20: 291313.15 | I20: =H20 -> 291313.15 | K20: =H20-I20 -> 0 | L20: =IF(K20>0,K20*3%,0) -> 0 | M20: 0 | N20: =P$2*G20% -> 340952.07 | O20: 0 | P20: =ROUND(SUM(K20:O20),0) + S20 -> 340952.15 | Q20: =ROUND(P20*6% + P20,0) + S20 -> 361409.15 | R20: =ROUND(P20*3%,0) + P20 -> 351181.15 | S20: =S19+0.01 -> 0.15
A21: 10º | B21: 3 | C21: B | D21: =D20+1 -> 16 | E21: SARUBBI MARTIN | F21: Sarubbi Adriana | G21: 2.6477 | H21: 327701.16 | I21: =H21 -> 327701.16 | K21: =H21-I21 -> 0 | L21: =IF(K21>0,K21*3%,0) -> 0 | M21: 0 | N21: =P$2*G21% -> 383540.3 | O21: 0 | P21: =ROUND(SUM(K21:O21),0) + S21 -> 383540.16 | Q21: =ROUND(P21*6% + P21,0) + S21 -> 406553.16 | R21: =ROUND(P21*3%,0) + P21 -> 395046.16 | S21: =S20+0.01 -> 0.16
A22: 10º | B22: 4 | C22: A | D22: =D21+1 -> 17 | E22: LACENTRE | F22: Gabriela Tamara | G22: 2.3235 | H22: 287576.17 | I22: =H22 -> 287576.17 | K22: =H22-I22 -> 0 | L22: =IF(K22>0,K22*3%,0) -> 0 | M22: 0 | N22: =P$2*G22% -> 336577.36 | O22: 0 | P22: =ROUND(SUM(K22:O22),0) + S22 -> 336577.17 | Q22: =ROUND(P22*6% + P22,0) + S22 -> 356772.17 | R22: =ROUND(P22*3%,0) + P22 -> 346674.17 | S22: =S21+0.01 -> 0.17
A23: 11º | B23: 4 | C23: B | D23: =D22+1 -> 18 | E23: FERNANDEZ BERTA | F23: KRAVETZ | G23: 2.688 | H23: 342670.18 | I23: =H23 -> 342670.18 | K23: =H23-I23 -> 0 | L23: =IF(K23>0,K23*3%,0) -> 0 | M23: 0 | N23: =P$2*G23% -> 389378.07 | O23: 0 | P23: =ROUND(SUM(K23:O23),0) + S23 -> 389378.18 | Q23: =ROUND(P23*6% + P23,0) + S23 -> 412741.18 | R23: =ROUND(P23*3%,0) + P23 -> 401059.18 | S23: =S22+0.01 -> 0.18 | U23: KRAVETZ
A24: 11º | B24: 5 | C24: A | D24: =D23+1 -> 19 | E24: VERONES JOSE MARIA | G24: 2.36 | H24: 292093.19 | I24: =H24+100000 -> 392093.19 | K24: =H24-I24 -> -100000 | L24: =IF(K24>0,K24*3%,0) -> 0 | M24: 0 | N24: =P$2*G24% -> 341864.68 | O24: 0 | P24: =ROUND(SUM(K24:O24),0) + S24 -> 241865.19 | Q24: =ROUND(P24*6% + P24,0) + S24 -> 256377.19 | R24: =ROUND(P24*3%,0) + P24 -> 249121.19 | S24: =S23+0.01 -> 0.19
A25: 12º | B25: 5 | C25: B | D25: =D24+1 -> 20 | E25: SRUGO CARLOS | G25: 2.7183 | H25: 326615.2 | I25: 327000 | K25: =H25-I25 -> -384.8 | L25: =IF(K25>0,K25*3%,0) -> 0 | M25: 0 | N25: =P$2*G25% -> 393767.27 | O25: 0 | P25: =ROUND(SUM(K25:O25),0) + S25 -> 393382.2 | Q25: =ROUND(P25*6% + P25,0) + S25 -> 416985.2 | R25: =ROUND(P25*3%,0) + P25 -> 405183.2 | S25: =S24+0.01 -> 0.2
A26: 13º | B26: 6 | C26: A | D26: =D25+1 -> 21 | E26: DINOTO | G26: 2.3033 | H26: 285076.21 | I26: =H26 -> 285076.21 | K26: =H26-I26 -> 0 | L26: =IF(K26>0,K26*3%,0) -> 0 | M26: 0 | N26: =P$2*G26% -> 333651.23 | O26: 0 | P26: =ROUND(SUM(K26:O26),0) + S26 -> 333651.21 | Q26: =ROUND(P26*6% + P26,0) + S26 -> 353670.21 | R26: =ROUND(P26*3%,0) + P26 -> 343661.21 | S26: =S25+0.01 -> 0.21
A27: 14º | B27: 6 | C27: B | D27: =D26+1 -> 22 | E27: BORTZ ESTHER | F27: Daniel / Luciana | G27: 2.636 | H27: 653120.22 | I27: =885587.22 -> 885587.22 | K27: =H27-I27 -> -232467 | L27: =IF(K27>0,K27*3%,0) -> 0 | M27: 0 | N27: =P$2*G27% -> 381845.46 | O27: 0 | P27: =ROUND(SUM(K27:O27),0) + S27 -> 149378.22 | Q27: =ROUND(P27*6% + P27,0) + S27 -> 158341.22 | R27: =ROUND(P27*3%,0) + P27 -> 153859.22 | S27: =S26+0.01 -> 0.22 | T27: Luciana | U27: ESTA ES LA FUNDACION DE MEDICOS
A28: 15º | B28: 7 | C28: A | D28: =D27+1 -> 23 | E28: COUSO MARIA CRISTINA | G28: 2.3033 | H28: 285076.23 | I28: 290000.23 | K28: =H28-I28 -> -4924 | L28: =IF(K28>0,K28*3%,0) -> 0 | M28: 0 | N28: =P$2*G28% -> 333651.23 | O28: 0 | P28: =ROUND(SUM(K28:O28),0) + S28 -> 328727.23 | Q28: =ROUND(P28*6% + P28,0) + S28 -> 348451.23 | R28: =ROUND(P28*3%,0) + P28 -> 338589.23 | S28: =S27+0.01 -> 0.23
A29: COC | B29: 7 | C29: B | D29: =D28+1 -> 24 | E29: POSSENTI JUAN JOSE | G29: 2.6159 | H29: 323766.24 | I29: =H29 -> 323766.24 | K29: =H29-I29 -> 0 | L29: =IF(K29>0,K29*3%,0) -> 0 | M29: 0 | N29: =P$2*G29% -> 378933.82 | O29: 0 | P29: =ROUND(SUM(K29:O29),0) + S29 -> 378934.24 | Q29: =ROUND(P29*6% + P29,0) + S29 -> 401670.24 | R29: =ROUND(P29*3%,0) + P29 -> 390302.24 | S29: =S28+0.01 -> 0.24
A30: COC | B30: 8 | C30: A | D30: =D29+1 -> 25 | E30: VANNI KARINA | G30: 2.3537 | H30: 291313.25 | I30: =H30 -> 291313.25 | K30: =H30-I30 -> 0 | L30: =IF(K30>0,K30*3%,0) -> 0 | M30: 0 | N30: =P$2*G30% -> 340952.07 | O30: 0 | P30: =ROUND(SUM(K30:O30),0) + S30 -> 340952.25 | Q30: =ROUND(P30*6% + P30,0) + S30 -> 361409.25 | R30: =ROUND(P30*3%,0) + P30 -> 351181.25 | S30: =S29+0.01 -> 0.25
A31: COC | B31: 8 | C31: B | D31: =D30+1 -> 26 | E31: CARRIZO RAÚL | F31: Noelia Villarino | G31: 2.6469 | H31: 327602.26 | I31: =H31 -> 327602.26 | K31: =H31-I31 -> 0 | L31: =IF(K31>0,K31*3%,0) -> 0 | M31: 0 | N31: =P$2*G31% -> 383424.41 | O31: 0 | P31: =ROUND(SUM(K31:O31),0) + S31 -> 383424.26 | Q31: =ROUND(P31*6% + P31,0) + S31 -> 406430.26 | R31: =ROUND(P31*3%,0) + P31 -> 394927.26 | S31: =S30+0.01 -> 0.26
A32: COC | B32: 9 | C32: A | D32: =D31+1 -> 27 | E32: BLANCO | G32: 2.3537 | H32: 291313.27 | I32: 300052.27 | K32: =H32-I32 -> -8739 | L32: =IF(K32>0,K32*3%,0) -> 0 | M32: 0 | N32: =P$2*G32% -> 340952.07 | O32: 0 | P32: =ROUND(SUM(K32:O32),0) + S32 -> 332213.27 | Q32: =ROUND(P32*6% + P32,0) + S32 -> 352146.27 | R32: =ROUND(P32*3%,0) + P32 -> 342179.27 | S32: =S31+0.01 -> 0.27
A33: COC | B33: 9 | C33: B | D33: =D32+1 -> 28 | E33: GALANTE CELIA | G33: 2.6663 | H33: 330003.28 | I33: =H33 -> 330003.28 | K33: =H33-I33 -> 0 | L33: =IF(K33>0,K33*3%,0) -> 0 | M33: 0 | N33: =P$2*G33% -> 386234.66 | O33: 0 | P33: =ROUND(SUM(K33:O33),0) + S33 -> 386235.28 | Q33: =ROUND(P33*6% + P33,0) + S33 -> 409409.28 | R33: =ROUND(P33*3%,0) + P33 -> 397822.28 | S33: =S32+0.01 -> 0.28
A34: COC | B34: 10 | C34: A | D34: =D33+1 -> 29 | E34: LEGUIZAMON PABLO | F34: Carla | G34: 2.4476 | H34: 321435.29 | I34: =H34 -> 321435.29 | K34: =H34-I34 -> 0 | L34: =IF(K34>0,K34*3%,0) -> 0 | M34: 0 | N34: =P$2*G34% -> 354554.23 | O34: 18500 | P34: =ROUND(SUM(K34:O34),0) + S34 -> 373054.29 | Q34: =ROUND(P34*6% + P34,0) + S34 -> 395438.29 | R34: =ROUND(P34*3%,0) + P34 -> 384246.29 | S34: =S33+0.01 -> 0.29
A35: COC | B35: 10 | C35: B | D35: =D34+1 -> 30 | E35: CANDEL E. MARCELO | G35: 2.7183 | H35: 336439.3 | I35: =H35 -> 336439.3 | K35: =H35-I35 -> 0 | L35: =IF(K35>0,K35*3%,0) -> 0 | M35: 0 | N35: =P$2*G35% -> 393767.27 | O35: 0 | P35: =ROUND(SUM(K35:O35),0) + S35 -> 393767.3 | Q35: =ROUND(P35*6% + P35,0) + S35 -> 417393.3 | R35: =ROUND(P35*3%,0) + P35 -> 405580.3 | S35: =S34+0.01 -> 0.3
A36: COC | B36: 11 | C36: A | D36: =D35+1 -> 31 | E36: DAVICCA MIGUEL | F36: Romina Navarro | G36: 2.3026 | H36: 284989.31 | I36: =H36 -> 284989.31 | K36: =H36-I36 -> 0 | L36: =IF(K36>0,K36*3%,0) -> 0 | M36: 0 | N36: =P$2*G36% -> 333549.83 | O36: 0 | P36: =ROUND(SUM(K36:O36),0) + S36 -> 333550.31 | Q36: =ROUND(P36*6% + P36,0) + S36 -> 353563.31 | R36: =ROUND(P36*3%,0) + P36 -> 343557.31 | S36: =S35+0.01 -> 0.31
A37: COC | B37: 11 | C37: B | D37: =D36+1 -> 32 | E37: GUTMAN MARIO | G37: 2.6562 | H37: 456011.32 | I37: 328753.32 | K37: =H37-I37 -> 127258 | L37: =IF(K37>0,K37*3%,0) -> 3817.74 | M37: 0 | N37: =P$2*G37% -> 384771.59 | O37: 0 | P37: =ROUND(SUM(K37:O37),0) + S37 -> 515847.32 | Q37: =ROUND(P37*6% + P37,0) + S37 -> 546798.32 | R37: =ROUND(P37*3%,0) + P37 -> 531322.32 | S37: =S36+0.01 -> 0.32
A38: COC | B38: 12 | C38: A | D38: =D37+1 -> 33 | E38: PRATOLONGO EDUARDO | G38: 2.3343 | H38: 288912.33 | I38: =H38 -> 288912.33 | K38: =H38-I38 -> 0 | L38: =IF(K38>0,K38*3%,0) -> 0 | M38: 0 | N38: =P$2*G38% -> 338141.83 | O38: 0 | P38: =ROUND(SUM(K38:O38),0) + S38 -> 338142.33 | Q38: =ROUND(P38*6% + P38,0) + S38 -> 358431.33 | R38: =ROUND(P38*3%,0) + P38 -> 348286.33 | S38: =S37+0.01 -> 0.33
A39: COC | B39: 12 | C39: B | D39: =D38+1 -> 34 | E39: CARTABBIA MARIO | G39: 2.6259 | H39: 325003.34 | I39: =H39 -> 325003.34 | K39: =H39-I39 -> 0 | L39: =IF(K39>0,K39*3%,0) -> 0 | M39: 0 | N39: =P$2*G39% -> 380382.4 | O39: 0 | P39: =ROUND(SUM(K39:O39),0) + S39 -> 380382.34 | Q39: =ROUND(P39*6% + P39,0) + S39 -> 403205.34 | R39: =ROUND(P39*3%,0) + P39 -> 391793.34 | S39: =S38+0.01 -> 0.34
A40: COC | B40: 1 | C40: C | D40: =D39+1 -> 35 | E40: NAVA HECTOR | F40: Marcos | G40: 1.007 | H40: 128374.35 | I40: =H40 -> 128374.35 | K40: =H40-I40 -> 0 | L40: =IF(K40>0,K40*3%,0) -> 0 | M40: 0 | N40: =P$2*G40% -> 145871.92 | O40: 0 | P40: =ROUND(SUM(K40:O40),0) + S40 -> 145872.35 | Q40: =ROUND(P40*6% + P40,0) + S40 -> 154625.35 | R40: =ROUND(P40*3%,0) + P40 -> 150248.35 | S40: =S39+0.01 -> 0.35
A41: COC | B41: 1 | C41: D | D41: =D40+1 -> 36 | E41: BRATTOLI | F41: Palermo Hernan | G41: 0.7812 | H41: 99589.36 | I41: =H41 -> 99589.36 | K41: =H41-I41 -> 0 | L41: =IF(K41>0,K41*3%,0) -> 0 | M41: 0 | N41: =P$2*G41% -> 113163 | O41: 0 | P41: =ROUND(SUM(K41:O41),0) + S41 -> 113163.36 | Q41: =ROUND(P41*6% + P41,0) + S41 -> 119953.36 | R41: =ROUND(P41*3%,0) + P41 -> 116558.36 | S41: =S40+0.01 -> 0.36 | U41: PALERMO
B42: 1 | C42: E | D42: =D41+1 -> 37 | E42: BRATTOLI | F42: Palermo Hernan | G42: 1.2153 | H42: 154928.37 | I42: =H42 -> 154928.37 | K42: =H42-I42 -> 0 | L42: =IF(K42>0,K42*3%,0) -> 0 | M42: 0 | N42: =P$2*G42% -> 176045.82 | O42: 0 | P42: =ROUND(SUM(K42:O42),0) + S42 -> 176046.37 | Q42: =ROUND(P42*6% + P42,0) + S42 -> 186609.37 | R42: =ROUND(P42*3%,0) + P42 -> 181327.37 | S42: =S41+0.01 -> 0.37 | U42: PALERMO
B43: 2 | C43: C | D43: =D42+1 -> 38 | E43: MARIA I. ROTTA | F43: Mabel Rodríguez | G43: 0.9549 | H43: 124665.38 | I43: =H43 -> 124665.38 | K43: =H43-I43 -> 0 | L43: =IF(K43>0,K43*3%,0) -> 0 | M43: 0 | N43: =P$2*G43% -> 138324.82 | O43: 0 | P43: =ROUND(SUM(K43:O43),0) + S43 -> 138325.38 | Q43: =ROUND(P43*6% + P43,0) + S43 -> 146625.38 | R43: =ROUND(P43*3%,0) + P43 -> 142475.38 | S43: =S42+0.01 -> 0.38
B44: 2 | C44: D | D44: =D43+1 -> 39 | E44: SAIN GUILLERMO | G44: 0.7552 | H44: 645600.39 | K44: =H44-I44 -> 645600.39 | L44: =IF(K44>0,K44*3%,0) -> 19368.012 | M44: 0 | N44: =P$2*G44% -> 109396.7 | O44: 0 | P44: =ROUND(SUM(K44:O44),0) + S44 -> 774365.39 | Q44: =ROUND(P44*6% + P44,0) + S44 -> 820827.39 | R44: =ROUND(P44*3%,0) + P44 -> 797596.39 | S44: =S43+0.01 -> 0.39
B45: 2 | C45: E | D45: =D44+1 -> 40 | E45: BLANCO | F45: Jose Medina | G45: 1.1545 | H45: 142891.4 | I45: 147148.4 | K45: =H45-I45 -> -4257 | L45: =IF(K45>0,K45*3%,0) -> 0 | M45: 0 | N45: =P$2*G45% -> 167238.46 | O45: 0 | P45: =ROUND(SUM(K45:O45),0) + S45 -> 162981.4 | Q45: =ROUND(P45*6% + P45,0) + S45 -> 172760.4 | R45: =ROUND(P45*3%,0) + P45 -> 167870.4 | S45: =S44+0.01 -> 0.4
B46: 3 | C46: C | D46: =D45+1 -> 41 | E46: GOLBERG DIEGO | F46: Isabel Infante | G46: 0.9549 | H46: 114738.41 | I46: 118180.41 | K46: =H46-I46 -> -3442 | L46: =IF(K46>0,K46*3%,0) -> 0 | M46: 0 | N46: =P$2*G46% -> 138324.82 | O46: 0 | P46: =ROUND(SUM(K46:O46),0) + S46 -> 134883.41 | Q46: =ROUND(P46*6% + P46,0) + S46 -> 142976.41 | R46: =ROUND(P46*3%,0) + P46 -> 138930.41 | S46: =S45+0.01 -> 0.41
B47: 3 | C47: D | D47: =D46+1 -> 42 | E47: CANDEL RAÚL F. | G47: 0.7552 | H47: 93470.42 | I47: =H47 -> 93470.42 | K47: =H47-I47 -> 0 | L47: =IF(K47>0,K47*3%,0) -> 0 | M47: 0 | N47: =P$2*G47% -> 109396.7 | O47: 0 | P47: =ROUND(SUM(K47:O47),0) + S47 -> 109397.42 | Q47: =ROUND(P47*6% + P47,0) + S47 -> 115961.42 | R47: =ROUND(P47*3%,0) + P47 -> 112679.42 | S47: =S46+0.01 -> 0.42
B48: 3 | C48: E | D48: =D47+1 -> 43 | E48: AZCARATE DIEGO | G48: 1.1545 | H48: 142891.43 | I48: =H48 -> 142891.43 | K48: =H48-I48 -> 0 | L48: =IF(K48>0,K48*3%,0) -> 0 | M48: 0 | N48: =P$2*G48% -> 167238.46 | O48: 0 | P48: =ROUND(SUM(K48:O48),0) + S48 -> 167238.43 | Q48: =ROUND(P48*6% + P48,0) + S48 -> 177273.43 | R48: =ROUND(P48*3%,0) + P48 -> 172255.43 | S48: =S47+0.01 -> 0.43
B49: 4 | C49: C | D49: =D48+1 -> 44 | E49: MORONI MABEL | F49: Ines Telo | G49: 0.9549 | H49: 118186.44 | I49: =H49 -> 118186.44 | K49: =H49-I49 -> 0 | L49: =IF(K49>0,K49*3%,0) -> 0 | M49: 0 | N49: =P$2*G49% -> 138324.82 | O49: 0 | P49: =ROUND(SUM(K49:O49),0) + S49 -> 138325.44 | Q49: =ROUND(P49*6% + P49,0) + S49 -> 146625.44 | R49: =ROUND(P49*3%,0) + P49 -> 142475.44 | S49: =S48+0.01 -> 0.44
B50: 4 | C50: D | D50: =D49+1 -> 45 | E50: BELEN CIACCIARELLI | G50: 0.7552 | H50: 93468.45 | I50: =93470 -> 93470 | K50: =H50-I50 -> -1.55 | L50: =IF(K50>0,K50*3%,0) -> 0 | M50: 0 | N50: =P$2*G50% -> 109396.7 | O50: 0 | P50: =ROUND(SUM(K50:O50),0) + S50 -> 109395.45 | Q50: =ROUND(P50*6% + P50,0) + S50 -> 115959.45 | R50: =ROUND(P50*3%,0) + P50 -> 112677.45 | S50: =S49+0.01 -> 0.45 | U50: ESTA ES MARIA BELEN CIACCARELLI
B51: 4 | C51: E | D51: =D50+1 -> 46 | E51: PARMA | F51: Ezequiel Caputo | G51: 1.1545 | H51: 142891.46 | K51: =H51-I51 -> 142891.46 | L51: =IF(K51>0,K51*3%,0) -> 4286.7438 | M51: 0 | N51: =P$2*G51% -> 167238.46 | O51: 0 | P51: =ROUND(SUM(K51:O51),0) + S51 -> 314417.46 | Q51: =ROUND(P51*6% + P51,0) + S51 -> 333283.46 | R51: =ROUND(P51*3%,0) + P51 -> 323850.46 | S51: =S50+0.01 -> 0.46
B52: 5 | C52: C | D52: =D51+1 -> 47 | E52: TORRES BASSO RUBEN | F52: Andrea | G52: 0.9549 | H52: 118186.47 | I52: =H52 -> 118186.47 | K52: =H52-I52 -> 0 | L52: =IF(K52>0,K52*3%,0) -> 0 | M52: 0 | N52: =P$2*G52% -> 138324.82 | O52: 0 | P52: =ROUND(SUM(K52:O52),0) + S52 -> 138325.47 | Q52: =ROUND(P52*6% + P52,0) + S52 -> 146625.47 | R52: =ROUND(P52*3%,0) + P52 -> 142475.47 | S52: =S51+0.01 -> 0.47
B53: 5 | C53: D | D53: =D52+1 -> 48 | E53: CANDEL MARCELO | F53: Romina Barbara Lotfi | G53: 0.7552 | H53: 93470.48 | I53: =H53 -> 93470.48 | K53: =H53-I53 -> 0 | L53: =IF(K53>0,K53*3%,0) -> 0 | M53: 0 | N53: =P$2*G53% -> 109396.7 | O53: 0 | P53: =ROUND(SUM(K53:O53),0) + S53 -> 109397.48 | Q53: =ROUND(P53*6% + P53,0) + S53 -> 115961.48 | R53: =ROUND(P53*3%,0) + P53 -> 112679.48 | S53: =S52+0.01 -> 0.48
B54: 5 | C54: E | D54: =D53+1 -> 49 | E54: WAINBERG LUIS | F54: Lionel Giglia | G54: 1.1545 | H54: 142891.49 | I54: =H54 -> 142891.49 | K54: =H54-I54 -> 0 | L54: =IF(K54>0,K54*3%,0) -> 0 | M54: 0 | N54: =P$2*G54% -> 167238.46 | O54: 0 | P54: =ROUND(SUM(K54:O54),0) + S54 -> 167238.49 | Q54: =ROUND(P54*6% + P54,0) + S54 -> 177273.49 | R54: =ROUND(P54*3%,0) + P54 -> 172255.49 | S54: =S53+0.01 -> 0.49
B55: 6 | C55: C | D55: =D54+1 -> 50 | E55: STELLISANO VICTORIA | G55: 0.9549 | H55: 118186.5 | I55: =H55 -> 118186.5 | K55: =H55-I55 -> 0 | L55: =IF(K55>0,K55*3%,0) -> 0 | M55: 0 | N55: =P$2*G55% -> 138324.82 | O55: 0 | P55: =ROUND(SUM(K55:O55),0) + S55 -> 138325.5 | Q55: =ROUND(P55*6% + P55,0) + S55 -> 146625.5 | R55: =ROUND(P55*3%,0) + P55 -> 142475.5 | S55: =S54+0.01 -> 0.5
B56: 6 | C56: D | D56: =D55+1 -> 51 | E56: GEFFNER JORGE RAÚL | G56: 0.7552 | H56: 99249.51 | I56: 96358 | K56: =H56-I56 -> 2891.51 | L56: =IF(K56>0,K56*3%,0) -> 86.7453 | M56: 0 | N56: =P$2*G56% -> 109396.7 | O56: 0 | P56: =ROUND(SUM(K56:O56),0) + S56 -> 112375.51 | Q56: =ROUND(P56*6% + P56,0) + S56 -> 119118.51 | R56: =ROUND(P56*3%,0) + P56 -> 115746.51 | S56: =S55+0.01 -> 0.51 | U56: LUIS SAAVEDRA FERNANDO ESPINO
B57: 6 | C57: E | D57: =D56+1 -> 52 | E57: REY ALICIA | G57: 1.1545 | H57: 142891.52 | I57: =H57 -> 142891.52 | K57: =H57-I57 -> 0 | L57: =IF(K57>0,K57*3%,0) -> 0 | M57: 0 | N57: =P$2*G57% -> 167238.46 | O57: 0 | P57: =ROUND(SUM(K57:O57),0) + S57 -> 167238.52 | Q57: =ROUND(P57*6% + P57,0) + S57 -> 177273.52 | R57: =ROUND(P57*3%,0) + P57 -> 172255.52 | S57: =S56+0.01 -> 0.52
B58: 7 | C58: C | D58: =D57+1 -> 53 | E58: DE SERIO BOFFA | G58: 0.9549 | H58: 118186.53 | I58: =H58 -> 118186.53 | K58: =H58-I58 -> 0 | L58: =IF(K58>0,K58*3%,0) -> 0 | M58: 0 | N58: =P$2*G58% -> 138324.82 | O58: 0 | P58: =ROUND(SUM(K58:O58),0) + S58 -> 138325.53 | Q58: =ROUND(P58*6% + P58,0) + S58 -> 146625.53 | R58: =ROUND(P58*3%,0) + P58 -> 142475.53 | S58: =S57+0.01 -> 0.53
B59: 7 | C59: D | D59: =D58+1 -> 54 | E59: ALVAREZ EDUARDO | G59: 0.7552 | H59: 93470.54 | I59: =H59 -> 93470.54 | K59: =H59-I59 -> 0 | L59: =IF(K59>0,K59*3%,0) -> 0 | M59: 0 | N59: =P$2*G59% -> 109396.7 | O59: 0 | P59: =ROUND(SUM(K59:O59),0) + S59 -> 109397.54 | Q59: =ROUND(P59*6% + P59,0) + S59 -> 115961.54 | R59: =ROUND(P59*3%,0) + P59 -> 112679.54 | S59: =S58+0.01 -> 0.54
B60: 7 | C60: E | D60: =D59+1 -> 55 | E60: MANDELLI MARIA | F60: Analía Ayelen Camera | G60: 1.1545 | H60: 730237.55 | K60: =H60-I60 -> 730237.55 | L60: =IF(K60>0,K60*3%,0) -> 21907.127 | M60: 0 | N60: =P$2*G60% -> 167238.46 | O60: 0 | P60: =ROUND(SUM(K60:O60),0) + S60 -> 919383.55 | Q60: =ROUND(P60*6% + P60,0) + S60 -> 974547.55 | R60: =ROUND(P60*3%,0) + P60 -> 946965.55 | S60: =S59+0.01 -> 0.55
B61: 8 | C61: C | D61: =D60+1 -> 56 | E61: BRITEZ M. | F61: Francini IGNACIO | G61: 0.9549 | H61: 118186.56 | I61: =H61 -> 118186.56 | K61: =H61-I61 -> 0 | L61: =IF(K61>0,K61*3%,0) -> 0 | M61: 0 | N61: =P$2*G61% -> 138324.82 | P61: =ROUND(SUM(K61:O61),0) + S61 -> 138325.56 | Q61: =ROUND(P61*6% + P61,0) + S61 -> 146625.56 | R61: =ROUND(P61*3%,0) + P61 -> 142475.56 | S61: =S60+0.01 -> 0.56
B62: 8 | C62: D | D62: =D61+1 -> 57 | E62: FERREIRO MARTA | F62: Jorge Sicilia | G62: 0.7552 | H62: 90653.57 | I62: 96721.57 | K62: =H62-I62 -> -6068 | L62: =IF(K62>0,K62*3%,0) -> 0 | M62: 0 | N62: =P$2*G62% -> 109396.7 | O62: 0 | P62: =ROUND(SUM(K62:O62),0) + S62 -> 103329.57 | Q62: =ROUND(P62*6% + P62,0) + S62 -> 109529.57 | R62: =ROUND(P62*3%,0) + P62 -> 106429.57 | S62: =S61+0.01 -> 0.57
B63: 8 | C63: E | D63: =D62+1 -> 58 | E63: VENTIMIGLIA SILVANA | G63: 1.1545 | H63: 142891.58 | I63: =H63 -> 142891.58 | K63: =H63-I63 -> 0 | L63: =IF(K63>0,K63*3%,0) -> 0 | M63: 0 | N63: =P$2*G63% -> 167238.46 | O63: 0 | P63: =ROUND(SUM(K63:O63),0) + S63 -> 167238.58 | Q63: =ROUND(P63*6% + P63,0) + S63 -> 177273.58 | R63: =ROUND(P63*3%,0) + P63 -> 172255.58 | S63: =S62+0.01 -> 0.58
B64: 9 | C64: C | D64: =D63+1 -> 59 | E64: CIGNOLI | F64: Pablo Coiro | G64: 0.9549 | H64: 118186.59 | I64: =RESUMEN!D69 -> 95706.73 | K64: =H64-I64 -> 22479.86 | L64: =IF(K64>0,K64*3%,0) -> 674.3958 | M64: 0 | N64: =P$2*G64% -> 138324.82 | O64: 0 | P64: =ROUND(SUM(K64:O64),0) + S64 -> 161479.59 | Q64: =ROUND(P64*6% + P64,0) + S64 -> 171168.59 | R64: =ROUND(P64*3%,0) + P64 -> 166323.59 | S64: =S63+0.01 -> 0.59
B65: 9 | C65: D | D65: =D64+1 -> 60 | E65: RECHIMUZZI | G65: 0.7552 | H65: 192479.6 | K65: =H65-I65 -> 192479.6 | L65: =IF(K65>0,K65*3%,0) -> 5774.388 | M65: 0 | N65: =P$2*G65% -> 109396.7 | O65: 0 | P65: =ROUND(SUM(K65:O65),0) + S65 -> 307651.6 | Q65: =ROUND(P65*6% + P65,0) + S65 -> 326111.6 | R65: =ROUND(P65*3%,0) + P65 -> 316881.6 | S65: =S64+0.01 -> 0.6 | U65: ESTA ES WANDA VERON
B66: 9 | C66: E | D66: =D65+1 -> 61 | E66: RIVA MÓNICA | G66: 1.1545 | H66: 142891.61 | I66: =H66 -> 142891.61 | K66: =H66-I66 -> 0 | L66: =IF(K66>0,K66*3%,0) -> 0 | M66: 0 | N66: =P$2*G66% -> 167238.46 | O66: 0 | P66: =ROUND(SUM(K66:O66),0) + S66 -> 167238.61 | Q66: =ROUND(P66*6% + P66,0) + S66 -> 177273.61 | R66: =ROUND(P66*3%,0) + P66 -> 172255.61 | S66: =S65+0.01 -> 0.61 | U66: PUED ETRANSFERIR DESDE GALI NELLY MABEL
B67: 10 | C67: C | D67: =D66+1 -> 62 | E67: GENTILE EDUARDO | F67: Aldana | G67: 0.9549 | H67: 118186.62 | I67: =H67 -> 118186.62 | K67: =H67-I67 -> 0 | L67: =IF(K67>0,K67*3%,0) -> 0 | M67: 0 | N67: =P$2*G67% -> 138324.82 | O67: 0 | P67: =ROUND(SUM(K67:O67),0) + S67 -> 138325.62 | Q67: =ROUND(P67*6% + P67,0) + S67 -> 146625.62 | R67: =ROUND(P67*3%,0) + P67 -> 142475.62 | S67: =S66+0.01 -> 0.62 | U67: GABRIEL TORRANDELLA
B68: 10 | C68: D | D68: =D67+1 -> 63 | E68: CANDEL MARCELO | F68: Brian Alvarez | G68: 0.7552 | H68: 93470.63 | I68: =H68 -> 93470.63 | K68: =H68-I68 -> 0 | L68: =IF(K68>0,K68*3%,0) -> 0 | M68: 0 | N68: =P$2*G68% -> 109396.7 | O68: 0 | P68: =ROUND(SUM(K68:O68),0) + S68 -> 109397.63 | Q68: =ROUND(P68*6% + P68,0) + S68 -> 115961.63 | R68: =ROUND(P68*3%,0) + P68 -> 112679.63 | S68: =S67+0.01 -> 0.63
B69: 10 | C69: E | D69: =D68+1 -> 64 | E69: CANDEL RAÚL F. | G69: 1.1545 | H69: 142891.64 | I69: =H69 -> 142891.64 | K69: =H69-I69 -> 0 | L69: =IF(K69>0,K69*3%,0) -> 0 | M69: 0 | N69: =P$2*G69% -> 167238.46 | O69: 0 | P69: =ROUND(SUM(K69:O69),0) + S69 -> 167238.64 | Q69: =ROUND(P69*6% + P69,0) + S69 -> 177273.64 | R69: =ROUND(P69*3%,0) + P69 -> 172255.64 | S69: =S68+0.01 -> 0.64
B70: 11 | C70: C | D70: =D69+1 -> 65 | E70: LORUSSO DORA | G70: 0.9549 | H70: 114640.65 | I70: =H70 -> 114640.65 | K70: =H70-I70 -> 0 | L70: =IF(K70>0,K70*3%,0) -> 0 | M70: 0 | N70: =P$2*G70% -> 138324.82 | O70: 0 | P70: =ROUND(SUM(K70:O70),0) + S70 -> 138325.65 | Q70: =ROUND(P70*6% + P70,0) + S70 -> 146625.65 | R70: =ROUND(P70*3%,0) + P70 -> 142475.65 | S70: =S69+0.01 -> 0.65
B71: 11 | C71: D | D71: =D70+1 -> 66 | E71: FERÁNDEZ HÉCTOR | F71: Melina Navarro | G71: 0.7552 | H71: 187089.66 | K71: =H71-I71 -> 187089.66 | L71: =IF(K71>0,K71*3%,0) -> 5612.6898 | M71: 0 | N71: =P$2*G71% -> 109396.7 | O71: 0 | P71: =ROUND(SUM(K71:O71),0) + S71 -> 302099.66 | Q71: =ROUND(P71*6% + P71,0) + S71 -> 320226.66 | R71: =ROUND(P71*3%,0) + P71 -> 311162.66 | S71: =S70+0.01 -> 0.66
B72: 11 | C72: E | D72: =D71+1 -> 67 | E72: KARGODORIAN SILVIA | G72: 1.1545 | H72: 142891.67 | I72: 147148.67 | K72: =H72-I72 -> -4257 | L72: =IF(K72>0,K72*3%,0) -> 0 | M72: 0 | N72: =P$2*G72% -> 167238.46 | O72: 0 | P72: =ROUND(SUM(K72:O72),0) + S72 -> 162981.67 | Q72: =ROUND(P72*6% + P72,0) + S72 -> 172761.67 | R72: =ROUND(P72*3%,0) + P72 -> 167870.67 | S72: =S71+0.01 -> 0.67
B73: 12 | C73: C | D73: =D72+1 -> 68 | E73: ALVAREZ | G73: 0.9549 | H73: 118186.68 | I73: =H73 -> 118186.68 | K73: =H73-I73 -> 0 | L73: =IF(K73>0,K73*3%,0) -> 0 | M73: 0 | N73: =P$2*G73% -> 138324.82 | O73: 0 | P73: =ROUND(SUM(K73:O73),0) + S73 -> 138325.68 | Q73: =ROUND(P73*6% + P73,0) + S73 -> 146625.68 | R73: =ROUND(P73*3%,0) + P73 -> 142475.68 | S73: =S72+0.01 -> 0.68
B74: 12 | C74: D | D74: =D73+1 -> 69 | E74: RIVA MÓNICA | G74: 0.7552 | H74: 93470.69 | I74: =H74 -> 93470.69 | K74: =H74-I74 -> 0 | L74: =IF(K74>0,K74*3%,0) -> 0 | M74: 0 | N74: =P$2*G74% -> 109396.7 | O74: 0 | P74: =ROUND(SUM(K74:O74),0) + S74 -> 109397.69 | Q74: =ROUND(P74*6% + P74,0) + S74 -> 115962.69 | R74: =ROUND(P74*3%,0) + P74 -> 112679.69 | S74: =S73+0.01 -> 0.69
B75: 12 | C75: E | D75: =D74+1 -> 70 | E75: DE BIAGGIO PABLO | G75: 1.1549 | H75: 142940.7 | I75: =H75 -> 142940.7 | K75: =H75-I75 -> 0 | L75: =IF(K75>0,K75*3%,0) -> 0 | M75: 0 | N75: =P$2*G75% -> 167296.4 | O75: 0 | P75: =ROUND(SUM(K75:O75),0) + S75 -> 167296.7 | Q75: =ROUND(P75*6% + P75,0) + S75 -> 177335.7 | R75: =ROUND(P75*3%,0) + P75 -> 172315.7 | S75: =S74+0.01 -> 0.7
G81: =SUM(G6:G80) -> 100 | H81: =SUM(H6:H80) -> 17975524 | I81: =SUM(I6:I80) -> 12230350 | J81: =SUM(J6:J80) -> 0 | K81: =SUM(K6:K80) -> 5745173.8 | M81: =SUM(M6:M80) -> 0 | N81: =SUM(N6:N80) -> 14485791 | O81: =SUM(O6:O80) -> 18500 | P81: =SUM(P6:P80) -> 20437630 | Q81: =SUM(Q6:Q80) -> 21663910
E84: =RESUMEN!A14 -> ESTIMADOS PROPIETARIOS E INQUILINOS: POR FAVOR LOS QUE ABONAN EN PRIMER VENCIMIENTO ABONEN EL MONTO DE PRIMER VENCIMIENTO, ASI AGILIZAN LA LIQUIDACION, RESPETEN LOS CENTAVOS CORRESPONDIENTES A LA UNIDAD FUNCIONAL. ES DE CARÁCTER OBLIGATORIO INFORMAR VIA MAIL LAS EXPENSAS. CASO CONTRARIO SE INFORMARA VIA CARTA DOCUMENTO A LA UNIDAD FUNCIONAL QUE CREEMOS QUE CORRESPONDE, CUYO COSTO SERA IMPUTADO A LA UNIDAD FUNCIONAL SOSPECHADA.

Sheet Hoja1

Sheet PRORRATEO DE PRUEBA  EMERGENCIA
E2: PRESUPUESTO LEMA | L2: PRESUPUESTO LEMA | P2: =16770000+7700000 -> 24470000
A4: Piso | B4: Dpto. | D4: UF | E4: Propietario | F4: Inquilinos | G4: (%) | H4: Saldo Ord | I4: Ingreso | J4: Pago por | K4: Deuda o Saldo a favor | L4: Interes 3% | M4: Expensas extraor. | N4: Presupuesto | P4: Total 1er Vto | Q4: Total 2do Vto. | R4: Total 2do Vto
A6: PB | C6: LOC | D6: 1 | E6: GEFFNER SILVIA E. | G6: 0.5131 | M6: 0 | N6: =P$2*G6% -> 125555.57 | O6: 0 | P6: =ROUND(SUM(K6:O6),0) + S6 -> 125556.01 | Q6: =ROUND(P6*6% + P6,0) + S6 -> 133089.01 | R6: =ROUND(P6*3%,0) + P6 -> 129323.01 | S6: 0.01 | U6: este es el candel que tiene a todas sus demas ufs relacionadas
A7: 3º | C7: LOC | D7: =D6+1 -> 2 | E7: COVILOZA S. A. | G7: 0.6119 | M7: 0 | N7: =P$2*G7% -> 149731.93 | O7: 0 | P7: =ROUND(SUM(K7:O7),0) + S7 -> 149732.02 | Q7: =ROUND(P7*6% + P7,0) + S7 -> 158716.02 | R7: =ROUND(P7*3%,0) + P7 -> 154224.02 | S7: =S6+0.01 -> 0.02
A8: 3º | B8: 1 | D8: =D7+1 -> 3 | E8: ASIST Y TRAB. | G8: 0.6115 | M8: 0 | N8: =P$2*G8% -> 149634.05 | O8: 0 | P8: =ROUND(SUM(K8:O8),0) + S8 -> 149634.03 | Q8: =ROUND(P8*6% + P8,0) + S8 -> 158612.03 | R8: =ROUND(P8*3%,0) + P8 -> 154123.03 | S8: =S7+0.01 -> 0.03
A9: 4º | B9: 2 | D9: =D8+1 -> 4 | E9: ASIST Y TRAB. | G9: 0.5033 | M9: 0 | N9: =P$2*G9% -> 123157.51 | O9: 0 | P9: =ROUND(SUM(K9:O9),0) + S9 -> 123158.04 | Q9: =ROUND(P9*6% + P9,0) + S9 -> 130548.04 | R9: =ROUND(P9*3%,0) + P9 -> 126853.04 | S9: =S8+0.01 -> 0.04
A10: 4º | B10: 3 | D10: =D9+1 -> 5 | E10: ASIST Y TRAB. | G10: 0.5033 | M10: 0 | N10: =P$2*G10% -> 123157.51 | O10: 0 | P10: =ROUND(SUM(K10:O10),0) + S10 -> 123158.05 | Q10: =ROUND(P10*6% + P10,0) + S10 -> 130548.05 | R10: =ROUND(P10*3%,0) + P10 -> 126853.05 | S10: =S9+0.01 -> 0.05
A11: 5º | B11: 4 | D11: =D10+1 -> 6 | E11: BENMAOR D. | F11: Cristian Requelme | G11: 0.7499 | M11: 0 | N11: =P$2*G11% -> 183500.53 | O11: 0 | P11: =ROUND(SUM(K11:O11),0) + S11 -> 183501.06 | Q11: =ROUND(P11*6% + P11,0) + S11 -> 194511.06 | R11: =ROUND(P11*3%,0) + P11 -> 189006.06 | S11: =S10+0.01 -> 0.06
A12: 5º | B12: 5 | D12: =D11+1 -> 7 | E12: GALANTERNIK A | F12: Miriam Larken | G12: 0.5425 | M12: 0 | N12: =P$2*G12% -> 132749.75 | O12: 0 | P12: =ROUND(SUM(K12:O12),0) + S12 -> 132750.07 | Q12: =ROUND(P12*6% + P12,0) + S12 -> 140715.07 | R12: =ROUND(P12*3%,0) + P12 -> 136733.07 | S12: =S11+0.01 -> 0.07
A13: 6º | B13: 6 | D13: =D12+1 -> 8 | E13: CANDEL JORGE ISAAC | G13: 0.4537 | M13: 0 | N13: =P$2*G13% -> 111020.39 | O13: 0 | P13: =ROUND(SUM(K13:O13),0) + S13 -> 111020.08 | Q13: =ROUND(P13*6% + P13,0) + S13 -> 117681.08 | R13: =ROUND(P13*3%,0) + P13 -> 114351.08 | S13: =S12+0.01 -> 0.08
A14: 6º | B14: 7 | D14: =D13+1 -> 9 | E14: BORTZ SERGIO | F14: Luciana | G14: 0.5244 | M14: 0 | N14: =P$2*G14% -> 128320.68 | O14: 0 | P14: =ROUND(SUM(K14:O14),0) + S14 -> 128321.09 | Q14: =ROUND(P14*6% + P14,0) + S14 -> 136020.09 | R14: =ROUND(P14*3%,0) + P14 -> 132171.09 | S14: =S13+0.01 -> 0.09 | U14: ESTA ES LA FUNDACION DE MEDICOS
A15: 7º | B15: 8 | D15: =D14+1 -> 10 | E15: BORTZ SERGIO | F15: Luciana | G15: 0.424 | M15: 0 | N15: =P$2*G15% -> 103752.8 | O15: 0 | P15: =ROUND(SUM(K15:O15),0) + S15 -> 103753.1 | Q15: =ROUND(P15*6% + P15,0) + S15 -> 109978.1 | R15: =ROUND(P15*3%,0) + P15 -> 106866.1 | S15: =S14+0.01 -> 0.1 | U15: ESTA ES LA FUNDACION DE MEDICOS
A16: 7º | B16: 1 | C16: A | D16: =D15+1 -> 11 | E16: KIM SOON LEO | G16: 2.3033 | M16: 0 | N16: =P$2*G16% -> 563617.51 | O16: 0 | P16: =ROUND(SUM(K16:O16),0) + S16 -> 563618.11 | Q16: =ROUND(P16*6% + P16,0) + S16 -> 597435.11 | R16: =ROUND(P16*3%,0) + P16 -> 580527.11 | S16: =S15+0.01 -> 0.11
A17: 8º | B17: 1 | C17: B | D17: =D16+1 -> 12 | E17: CANDEL MARCELO | F17: Florencia Fucci | G17: 2.7493 | M17: 0 | N17: =P$2*G17% -> 672753.71 | O17: 0 | P17: =ROUND(SUM(K17:O17),0) + S17 -> 672754.12 | Q17: =ROUND(P17*6% + P17,0) + S17 -> 713119.12 | R17: =ROUND(P17*3%,0) + P17 -> 692937.12 | S17: =S16+0.01 -> 0.12
A18: 8º | B18: 2 | C18: A | D18: =D17+1 -> 13 | E18: TRIPODI | F18: Mariela Pricolo | G18: 2.3033 | M18: 0 | N18: =P$2*G18% -> 563617.51 | O18: 0 | P18: =ROUND(SUM(K18:O18),0) + S18 -> 563618.13 | Q18: =ROUND(P18*6% + P18,0) + S18 -> 597435.13 | R18: =ROUND(P18*3%,0) + P18 -> 580527.13 | S18: =S17+0.01 -> 0.13
A19: 9º | B19: 2 | C19: B | D19: =D18+1 -> 14 | E19: MIRANDA DE GIL | F19: Susana | G19: 2.6368 | M19: 0 | N19: =P$2*G19% -> 645224.96 | O19: 0 | P19: =ROUND(SUM(K19:O19),0) + S19 -> 645225.14 | Q19: =ROUND(P19*6% + P19,0) + S19 -> 683939.14 | R19: =ROUND(P19*3%,0) + P19 -> 664582.14 | S19: =S18+0.01 -> 0.14 | U19: MAXIMO
A20: 9º | B20: 3 | C20: A | D20: =D19+1 -> 15 | E20: FRAGA DORA | G20: 2.3537 | M20: 0 | N20: =P$2*G20% -> 575950.39 | O20: 0 | P20: =ROUND(SUM(K20:O20),0) + S20 -> 575950.15 | Q20: =ROUND(P20*6% + P20,0) + S20 -> 610507.15 | R20: =ROUND(P20*3%,0) + P20 -> 593229.15 | S20: =S19+0.01 -> 0.15
A21: 10º | B21: 3 | C21: B | D21: =D20+1 -> 16 | E21: SARUBBI MARTIN | F21: Sarubbi Adriana | G21: 2.6477 | M21: 0 | N21: =P$2*G21% -> 647892.19 | O21: 0 | P21: =ROUND(SUM(K21:O21),0) + S21 -> 647892.16 | Q21: =ROUND(P21*6% + P21,0) + S21 -> 686766.16 | R21: =ROUND(P21*3%,0) + P21 -> 667329.16 | S21: =S20+0.01 -> 0.16
A22: 10º | B22: 4 | C22: A | D22: =D21+1 -> 17 | E22: LACENTRE | F22: Gabriela Tamara | G22: 2.3235 | M22: 0 | N22: =P$2*G22% -> 568560.45 | O22: 0 | P22: =ROUND(SUM(K22:O22),0) + S22 -> 568560.17 | Q22: =ROUND(P22*6% + P22,0) + S22 -> 602674.17 | R22: =ROUND(P22*3%,0) + P22 -> 585617.17 | S22: =S21+0.01 -> 0.17
A23: 11º | B23: 4 | C23: B | D23: =D22+1 -> 18 | E23: FERNANDEZ BERTA | F23: KRAVETZ | G23: 2.688 | M23: 0 | N23: =P$2*G23% -> 657753.6 | O23: 0 | P23: =ROUND(SUM(K23:O23),0) + S23 -> 657754.18 | Q23: =ROUND(P23*6% + P23,0) + S23 -> 697219.18 | R23: =ROUND(P23*3%,0) + P23 -> 677487.18 | S23: =S22+0.01 -> 0.18 | U23: KRAVETZ
A24: 11º | B24: 5 | C24: A | D24: =D23+1 -> 19 | E24: VERONES JOSE MARIA | G24: 2.36 | M24: 0 | N24: =P$2*G24% -> 577492 | O24: 0 | P24: =ROUND(SUM(K24:O24),0) + S24 -> 577492.19 | Q24: =ROUND(P24*6% + P24,0) + S24 -> 612142.19 | R24: =ROUND(P24*3%,0) + P24 -> 594817.19 | S24: =S23+0.01 -> 0.19
A25: 12º | B25: 5 | C25: B | D25: =D24+1 -> 20 | E25: SRUGO CARLOS | G25: 2.7183 | M25: 0 | N25: =P$2*G25% -> 665168.01 | O25: 0 | P25: =ROUND(SUM(K25:O25),0) + S25 -> 665168.2 | Q25: =ROUND(P25*6% + P25,0) + S25 -> 705078.2 | R25: =ROUND(P25*3%,0) + P25 -> 685123.2 | S25: =S24+0.01 -> 0.2
A26: 13º | B26: 6 | C26: A | D26: =D25+1 -> 21 | E26: DINOTO | G26: 2.3033 | M26: 0 | N26: =P$2*G26% -> 563617.51 | O26: 0 | P26: =ROUND(SUM(K26:O26),0) + S26 -> 563618.21 | Q26: =ROUND(P26*6% + P26,0) + S26 -> 597435.21 | R26: =ROUND(P26*3%,0) + P26 -> 580527.21 | S26: =S25+0.01 -> 0.21
A27: 14º | B27: 6 | C27: B | D27: =D26+1 -> 22 | E27: BORTZ ESTHER | F27: Daniel / Luciana | G27: 2.636 | M27: 0 | N27: =P$2*G27% -> 645029.2 | O27: 0 | P27: =ROUND(SUM(K27:O27),0) + S27 -> 645029.22 | Q27: =ROUND(P27*6% + P27,0) + S27 -> 683731.22 | R27: =ROUND(P27*3%,0) + P27 -> 664380.22 | S27: =S26+0.01 -> 0.22 | T27: Luciana | U27: ESTA ES LA FUNDACION DE MEDICOS
A28: 15º | B28: 7 | C28: A | D28: =D27+1 -> 23 | E28: COUSO MARIA CRISTINA | G28: 2.3033 | M28: 0 | N28: =P$2*G28% -> 563617.51 | O28: 0 | P28: =ROUND(SUM(K28:O28),0) + S28 -> 563618.23 | Q28: =ROUND(P28*6% + P28,0) + S28 -> 597435.23 | R28: =ROUND(P28*3%,0) + P28 -> 580527.23 | S28: =S27+0.01 -> 0.23
A29: COC | B29: 7 | C29: B | D29: =D28+1 -> 24 | E29: POSSENTI JUAN JOSE | G29: 2.6159 | M29: 0 | N29: =P$2*G29% -> 640110.73 | O29: 0 | P29: =ROUND(SUM(K29:O29),0) + S29 -> 640111.24 | Q29: =ROUND(P29*6% + P29,0) + S29 -> 678518.24 | R29: =ROUND(P29*3%,0) + P29 -> 659314.24 | S29: =S28+0.01 -> 0.24
A30: COC | B30: 8 | C30: A | D30: =D29+1 -> 25 | E30: VANNI KARINA | G30: 2.3537 | M30: 0 | N30: =P$2*G30% -> 575950.39 | O30: 0 | P30: =ROUND(SUM(K30:O30),0) + S30 -> 575950.25 | Q30: =ROUND(P30*6% + P30,0) + S30 -> 610507.25 | R30: =ROUND(P30*3%,0) + P30 -> 593229.25 | S30: =S29+0.01 -> 0.25
A31: COC | B31: 8 | C31: B | D31: =D30+1 -> 26 | E31: CARRIZO RAÚL | F31: Noelia Villarino | G31: 2.6469 | M31: 0 | N31: =P$2*G31% -> 647696.43 | O31: 0 | P31: =ROUND(SUM(K31:O31),0) + S31 -> 647696.26 | Q31: =ROUND(P31*6% + P31,0) + S31 -> 686558.26 | R31: =ROUND(P31*3%,0) + P31 -> 667127.26 | S31: =S30+0.01 -> 0.26
A32: COC | B32: 9 | C32: A | D32: =D31+1 -> 27 | E32: BLANCO | G32: 2.3537 | M32: 0 | N32: =P$2*G32% -> 575950.39 | O32: 0 | P32: =ROUND(SUM(K32:O32),0) + S32 -> 575950.27 | Q32: =ROUND(P32*6% + P32,0) + S32 -> 610507.27 | R32: =ROUND(P32*3%,0) + P32 -> 593229.27 | S32: =S31+0.01 -> 0.27
A33: COC | B33: 9 | C33: B | D33: =D32+1 -> 28 | E33: GALANTE CELIA | G33: 2.6663 | M33: 0 | N33: =P$2*G33% -> 652443.61 | O33: 0 | P33: =ROUND(SUM(K33:O33),0) + S33 -> 652444.28 | Q33: =ROUND(P33*6% + P33,0) + S33 -> 691591.28 | R33: =ROUND(P33*3%,0) + P33 -> 672017.28 | S33: =S32+0.01 -> 0.28
A34: COC | B34: 10 | C34: A | D34: =D33+1 -> 29 | E34: LEGUIZAMON PABLO | F34: Carla | G34: 2.4476 | M34: 0 | N34: =P$2*G34% -> 598927.72 | O34: 18500 | P34: =ROUND(SUM(K34:O34),0) + S34 -> 617428.29 | Q34: =ROUND(P34*6% + P34,0) + S34 -> 654474.29 | R34: =ROUND(P34*3%,0) + P34 -> 635951.29 | S34: =S33+0.01 -> 0.29
A35: COC | B35: 10 | C35: B | D35: =D34+1 -> 30 | E35: CANDEL E. MARCELO | G35: 2.7183 | M35: 0 | N35: =P$2*G35% -> 665168.01 | O35: 0 | P35: =ROUND(SUM(K35:O35),0) + S35 -> 665168.3 | Q35: =ROUND(P35*6% + P35,0) + S35 -> 705078.3 | R35: =ROUND(P35*3%,0) + P35 -> 685123.3 | S35: =S34+0.01 -> 0.3
A36: COC | B36: 11 | C36: A | D36: =D35+1 -> 31 | E36: DAVICCA MIGUEL | F36: Romina Navarro | G36: 2.3026 | M36: 0 | N36: =P$2*G36% -> 563446.22 | O36: 0 | P36: =ROUND(SUM(K36:O36),0) + S36 -> 563446.31 | Q36: =ROUND(P36*6% + P36,0) + S36 -> 597253.31 | R36: =ROUND(P36*3%,0) + P36 -> 580349.31 | S36: =S35+0.01 -> 0.31
A37: COC | B37: 11 | C37: B | D37: =D36+1 -> 32 | E37: GUTMAN MARIO | G37: 2.6562 | M37: 0 | N37: =P$2*G37% -> 649972.14 | O37: 0 | P37: =ROUND(SUM(K37:O37),0) + S37 -> 649972.32 | Q37: =ROUND(P37*6% + P37,0) + S37 -> 688971.32 | R37: =ROUND(P37*3%,0) + P37 -> 669471.32 | S37: =S36+0.01 -> 0.32
A38: COC | B38: 12 | C38: A | D38: =D37+1 -> 33 | E38: PRATOLONGO EDUARDO | G38: 2.3343 | M38: 0 | N38: =P$2*G38% -> 571203.21 | O38: 0 | P38: =ROUND(SUM(K38:O38),0) + S38 -> 571203.33 | Q38: =ROUND(P38*6% + P38,0) + S38 -> 605476.33 | R38: =ROUND(P38*3%,0) + P38 -> 588339.33 | S38: =S37+0.01 -> 0.33
A39: COC | B39: 12 | C39: B | D39: =D38+1 -> 34 | E39: CARTABBIA MARIO | G39: 2.6259 | M39: 0 | N39: =P$2*G39% -> 642557.73 | O39: 0 | P39: =ROUND(SUM(K39:O39),0) + S39 -> 642558.34 | Q39: =ROUND(P39*6% + P39,0) + S39 -> 681112.34 | R39: =ROUND(P39*3%,0) + P39 -> 661835.34 | S39: =S38+0.01 -> 0.34
A40: COC | B40: 1 | C40: C | D40: =D39+1 -> 35 | E40: NAVA HECTOR | F40: Marcos | G40: 1.007 | M40: 0 | N40: =P$2*G40% -> 246412.9 | O40: 0 | P40: =ROUND(SUM(K40:O40),0) + S40 -> 246413.35 | Q40: =ROUND(P40*6% + P40,0) + S40 -> 261198.35 | R40: =ROUND(P40*3%,0) + P40 -> 253805.35 | S40: =S39+0.01 -> 0.35
A41: COC | B41: 1 | C41: D | D41: =D40+1 -> 36 | E41: BRATTOLI | F41: Palermo Hernan | G41: 0.7812 | M41: 0 | N41: =P$2*G41% -> 191159.64 | O41: 0 | P41: =ROUND(SUM(K41:O41),0) + S41 -> 191160.36 | Q41: =ROUND(P41*6% + P41,0) + S41 -> 202630.36 | R41: =ROUND(P41*3%,0) + P41 -> 196895.36 | S41: =S40+0.01 -> 0.36 | U41: PALERMO
B42: 1 | C42: E | D42: =D41+1 -> 37 | E42: BRATTOLI | F42: Palermo Hernan | G42: 1.2153 | M42: 0 | N42: =P$2*G42% -> 297383.91 | O42: 0 | P42: =ROUND(SUM(K42:O42),0) + S42 -> 297384.37 | Q42: =ROUND(P42*6% + P42,0) + S42 -> 315227.37 | R42: =ROUND(P42*3%,0) + P42 -> 306306.37 | S42: =S41+0.01 -> 0.37 | U42: PALERMO
B43: 2 | C43: C | D43: =D42+1 -> 38 | E43: MARIA I. ROTTA | F43: Mabel Rodríguez | G43: 0.9549 | M43: 0 | N43: =P$2*G43% -> 233664.03 | O43: 0 | P43: =ROUND(SUM(K43:O43),0) + S43 -> 233664.38 | Q43: =ROUND(P43*6% + P43,0) + S43 -> 247684.38 | R43: =ROUND(P43*3%,0) + P43 -> 240674.38 | S43: =S42+0.01 -> 0.38
B44: 2 | C44: D | D44: =D43+1 -> 39 | E44: SAIN GUILLERMO | G44: 0.7552 | M44: 0 | N44: =P$2*G44% -> 184797.44 | O44: 0 | P44: =ROUND(SUM(K44:O44),0) + S44 -> 184797.39 | Q44: =ROUND(P44*6% + P44,0) + S44 -> 195885.39 | R44: =ROUND(P44*3%,0) + P44 -> 190341.39 | S44: =S43+0.01 -> 0.39
B45: 2 | C45: E | D45: =D44+1 -> 40 | E45: BLANCO | F45: Jose Medina | G45: 1.1545 | M45: 0 | N45: =P$2*G45% -> 282506.15 | O45: 0 | P45: =ROUND(SUM(K45:O45),0) + S45 -> 282506.4 | Q45: =ROUND(P45*6% + P45,0) + S45 -> 299457.4 | R45: =ROUND(P45*3%,0) + P45 -> 290981.4 | S45: =S44+0.01 -> 0.4
B46: 3 | C46: C | D46: =D45+1 -> 41 | E46: GOLBERG DIEGO | F46: Isabel Infante | G46: 0.9549 | M46: 0 | N46: =P$2*G46% -> 233664.03 | O46: 0 | P46: =ROUND(SUM(K46:O46),0) + S46 -> 233664.41 | Q46: =ROUND(P46*6% + P46,0) + S46 -> 247684.41 | R46: =ROUND(P46*3%,0) + P46 -> 240674.41 | S46: =S45+0.01 -> 0.41
B47: 3 | C47: D | D47: =D46+1 -> 42 | E47: CANDEL RAÚL F. | G47: 0.7552 | M47: 0 | N47: =P$2*G47% -> 184797.44 | O47: 0 | P47: =ROUND(SUM(K47:O47),0) + S47 -> 184797.42 | Q47: =ROUND(P47*6% + P47,0) + S47 -> 195885.42 | R47: =ROUND(P47*3%,0) + P47 -> 190341.42 | S47: =S46+0.01 -> 0.42
B48: 3 | C48: E | D48: =D47+1 -> 43 | E48: AZCARATE DIEGO | G48: 1.1545 | M48: 0 | N48: =P$2*G48% -> 282506.15 | O48: 0 | P48: =ROUND(SUM(K48:O48),0) + S48 -> 282506.43 | Q48: =ROUND(P48*6% + P48,0) + S48 -> 299457.43 | R48: =ROUND(P48*3%,0) + P48 -> 290981.43 | S48: =S47+0.01 -> 0.43
B49: 4 | C49: C | D49: =D48+1 -> 44 | E49: MORONI MABEL | F49: Ines Telo | G49: 0.9549 | M49: 0 | N49: =P$2*G49% -> 233664.03 | O49: 0 | P49: =ROUND(SUM(K49:O49),0) + S49 -> 233664.44 | Q49: =ROUND(P49*6% + P49,0) + S49 -> 247684.44 | R49: =ROUND(P49*3%,0) + P49 -> 240674.44 | S49: =S48+0.01 -> 0.44
B50: 4 | C50: D | D50: =D49+1 -> 45 | E50: BELEN CIACCIARELLI | G50: 0.7552 | M50: 0 | N50: =P$2*G50% -> 184797.44 | O50: 0 | P50: =ROUND(SUM(K50:O50),0) + S50 -> 184797.45 | Q50: =ROUND(P50*6% + P50,0) + S50 -> 195885.45 | R50: =ROUND(P50*3%,0) + P50 -> 190341.45 | S50: =S49+0.01 -> 0.45 | U50: ESTA ES MARIA BELEN CIACCARELLI
B51: 4 | C51: E | D51: =D50+1 -> 46 | E51: PARMA | F51: Ezequiel Caputo | G51: 1.1545 | M51: 0 | N51: =P$2*G51% -> 282506.15 | O51: 0 | P51: =ROUND(SUM(K51:O51),0) + S51 -> 282506.46 | Q51: =ROUND(P51*6% + P51,0) + S51 -> 299457.46 | R51: =ROUND(P51*3%,0) + P51 -> 290981.46 | S51: =S50+0.01 -> 0.46
B52: 5 | C52: C | D52: =D51+1 -> 47 | E52: TORRES BASSO RUBEN | F52: Andrea | G52: 0.9549 | M52: 0 | N52: =P$2*G52% -> 233664.03 | O52: 0 | P52: =ROUND(SUM(K52:O52),0) + S52 -> 233664.47 | Q52: =ROUND(P52*6% + P52,0) + S52 -> 247684.47 | R52: =ROUND(P52*3%,0) + P52 -> 240674.47 | S52: =S51+0.01 -> 0.47
B53: 5 | C53: D | D53: =D52+1 -> 48 | E53: CANDEL MARCELO | F53: Romina Barbara Lotfi | G53: 0.7552 | M53: 0 | N53: =P$2*G53% -> 184797.44 | O53: 0 | P53: =ROUND(SUM(K53:O53),0) + S53 -> 184797.48 | Q53: =ROUND(P53*6% + P53,0) + S53 -> 195885.48 | R53: =ROUND(P53*3%,0) + P53 -> 190341.48 | S53: =S52+0.01 -> 0.48
B54: 5 | C54: E | D54: =D53+1 -> 49 | E54: WAINBERG LUIS | F54: Lionel Giglia | G54: 1.1545 | M54: 0 | N54: =P$2*G54% -> 282506.15 | O54: 0 | P54: =ROUND(SUM(K54:O54),0) + S54 -> 282506.49 | Q54: =ROUND(P54*6% + P54,0) + S54 -> 299457.49 | R54: =ROUND(P54*3%,0) + P54 -> 290981.49 | S54: =S53+0.01 -> 0.49
B55: 6 | C55: C | D55: =D54+1 -> 50 | E55: STELLISANO VICTORIA | G55: 0.9549 | M55: 0 | N55: =P$2*G55% -> 233664.03 | O55: 0 | P55: =ROUND(SUM(K55:O55),0) + S55 -> 233664.5 | Q55: =ROUND(P55*6% + P55,0) + S55 -> 247684.5 | R55: =ROUND(P55*3%,0) + P55 -> 240674.5 | S55: =S54+0.01 -> 0.5
B56: 6 | C56: D | D56: =D55+1 -> 51 | E56: GEFFNER JORGE RAÚL | G56: 0.7552 | M56: 0 | N56: =P$2*G56% -> 184797.44 | O56: 0 | P56: =ROUND(SUM(K56:O56),0) + S56 -> 184797.51 | Q56: =ROUND(P56*6% + P56,0) + S56 -> 195885.51 | R56: =ROUND(P56*3%,0) + P56 -> 190341.51 | S56: =S55+0.01 -> 0.51 | U56: LUIS SAAVEDRA FERNANDO ESPINO
B57: 6 | C57: E | D57: =D56+1 -> 52 | E57: REY ALICIA | G57: 1.1545 | M57: 0 | N57: =P$2*G57% -> 282506.15 | O57: 0 | P57: =ROUND(SUM(K57:O57),0) + S57 -> 282506.52 | Q57: =ROUND(P57*6% + P57,0) + S57 -> 299457.52 | R57: =ROUND(P57*3%,0) + P57 -> 290981.52 | S57: =S56+0.01 -> 0.52
B58: 7 | C58: C | D58: =D57+1 -> 53 | E58: DE SERIO BOFFA | G58: 0.9549 | M58: 0 | N58: =P$2*G58% -> 233664.03 | O58: 0 | P58: =ROUND(SUM(K58:O58),0) + S58 -> 233664.53 | Q58: =ROUND(P58*6% + P58,0) + S58 -> 247684.53 | R58: =ROUND(P58*3%,0) + P58 -> 240674.53 | S58: =S57+0.01 -> 0.53
B59: 7 | C59: D | D59: =D58+1 -> 54 | E59: ALVAREZ EDUARDO | G59: 0.7552 | M59: 0 | N59: =P$2*G59% -> 184797.44 | O59: 0 | P59: =ROUND(SUM(K59:O59),0) + S59 -> 184797.54 | Q59: =ROUND(P59*6% + P59,0) + S59 -> 195885.54 | R59: =ROUND(P59*3%,0) + P59 -> 190341.54 | S59: =S58+0.01 -> 0.54
B60: 7 | C60: E | D60: =D59+1 -> 55 | E60: MANDELLI MARIA | F60: Analía Ayelen Camera | G60: 1.1545 | M60: 0 | N60: =P$2*G60% -> 282506.15 | O60: 0 | P60: =ROUND(SUM(K60:O60),0) + S60 -> 282506.55 | Q60: =ROUND(P60*6% + P60,0) + S60 -> 299457.55 | R60: =ROUND(P60*3%,0) + P60 -> 290981.55 | S60: =S59+0.01 -> 0.55
B61: 8 | C61: C | D61: =D60+1 -> 56 | E61: BRITEZ M. | F61: Francini IGNACIO | G61: 0.9549 | M61: 0 | N61: =P$2*G61% -> 233664.03 | P61: =ROUND(SUM(K61:O61),0) + S61 -> 233664.56 | Q61: =ROUND(P61*6% + P61,0) + S61 -> 247684.56 | R61: =ROUND(P61*3%,0) + P61 -> 240674.56 | S61: =S60+0.01 -> 0.56
B62: 8 | C62: D | D62: =D61+1 -> 57 | E62: FERREIRO MARTA | F62: Jorge Sicilia | G62: 0.7552 | M62: 0 | N62: =P$2*G62% -> 184797.44 | O62: 0 | P62: =ROUND(SUM(K62:O62),0) + S62 -> 184797.57 | Q62: =ROUND(P62*6% + P62,0) + S62 -> 195885.57 | R62: =ROUND(P62*3%,0) + P62 -> 190341.57 | S62: =S61+0.01 -> 0.57
B63: 8 | C63: E | D63: =D62+1 -> 58 | E63: VENTIMIGLIA SILVANA | G63: 1.1545 | M63: 0 | N63: =P$2*G63% -> 282506.15 | O63: 0 | P63: =ROUND(SUM(K63:O63),0) + S63 -> 282506.58 | Q63: =ROUND(P63*6% + P63,0) + S63 -> 299457.58 | R63: =ROUND(P63*3%,0) + P63 -> 290981.58 | S63: =S62+0.01 -> 0.58
B64: 9 | C64: C | D64: =D63+1 -> 59 | E64: CIGNOLI | F64: Pablo Coiro | G64: 0.9549 | M64: 0 | N64: =P$2*G64% -> 233664.03 | O64: 0 | P64: =ROUND(SUM(K64:O64),0) + S64 -> 233664.59 | Q64: =ROUND(P64*6% + P64,0) + S64 -> 247684.59 | R64: =ROUND(P64*3%,0) + P64 -> 240674.59 | S64: =S63+0.01 -> 0.59
B65: 9 | C65: D | D65: =D64+1 -> 60 | E65: RECHIMUZZI | G65: 0.7552 | M65: 0 | N65: =P$2*G65% -> 184797.44 | O65: 0 | P65: =ROUND(SUM(K65:O65),0) + S65 -> 184797.6 | Q65: =ROUND(P65*6% + P65,0) + S65 -> 195885.6 | R65: =ROUND(P65*3%,0) + P65 -> 190341.6 | S65: =S64+0.01 -> 0.6 | U65: ESTA ES WANDA VERON
B66: 9 | C66: E | D66: =D65+1 -> 61 | E66: RIVA MÓNICA | G66: 1.1545 | M66: 0 | N66: =P$2*G66% -> 282506.15 | O66: 0 | P66: =ROUND(SUM(K66:O66),0) + S66 -> 282506.61 | Q66: =ROUND(P66*6% + P66,0) + S66 -> 299457.61 | R66: =ROUND(P66*3%,0) + P66 -> 290981.61 | S66: =S65+0.01 -> 0.61 | U66: PUED ETRANSFERIR DESDE GALI NELLY MABEL
B67: 10 | C67: C | D67: =D66+1 -> 62 | E67: GENTILE EDUARDO | F67: Aldana | G67: 0.9549 | M67: 0 | N67: =P$2*G67% -> 233664.03 | O67: 0 | P67: =ROUND(SUM(K67:O67),0) + S67 -> 233664.62 | Q67: =ROUND(P67*6% + P67,0) + S67 -> 247684.62 | R67: =ROUND(P67*3%,0) + P67 -> 240674.62 | S67: =S66+0.01 -> 0.62 | U67: GABRIEL TORRANDELLA
B68: 10 | C68: D | D68: =D67+1 -> 63 | E68: CANDEL MARCELO | F68: Brian Alvarez | G68: 0.7552 | M68: 0 | N68: =P$2*G68% -> 184797.44 | O68: 0 | P68: =ROUND(SUM(K68:O68),0) + S68 -> 184797.63 | Q68: =ROUND(P68*6% + P68,0) + S68 -> 195885.63 | R68: =ROUND(P68*3%,0) + P68 -> 190341.63 | S68: =S67+0.01 -> 0.63
B69: 10 | C69: E | D69: =D68+1 -> 64 | E69: CANDEL RAÚL F. | G69: 1.1545 | M69: 0 | N69: =P$2*G69% -> 282506.15 | O69: 0 | P69: =ROUND(SUM(K69:O69),0) + S69 -> 282506.64 | Q69: =ROUND(P69*6% + P69,0) + S69 -> 299457.64 | R69: =ROUND(P69*3%,0) + P69 -> 290981.64 | S69: =S68+0.01 -> 0.64
B70: 11 | C70: C | D70: =D69+1 -> 65 | E70: LORUSSO DORA | G70: 0.9549 | M70: 0 | N70: =P$2*G70% -> 233664.03 | O70: 0 | P70: =ROUND(SUM(K70:O70),0) + S70 -> 233664.65 | Q70: =ROUND(P70*6% + P70,0) + S70 -> 247685.65 | R70: =ROUND(P70*3%,0) + P70 -> 240674.65 | S70: =S69+0.01 -> 0.65
B71: 11 | C71: D | D71: =D70+1 -> 66 | E71: FERÁNDEZ HÉCTOR | F71: Melina Navarro | G71: 0.7552 | M71: 0 | N71: =P$2*G71% -> 184797.44 | O71: 0 | P71: =ROUND(SUM(K71:O71),0) + S71 -> 184797.66 | Q71: =ROUND(P71*6% + P71,0) + S71 -> 195886.66 | R71: =ROUND(P71*3%,0) + P71 -> 190341.66 | S71: =S70+0.01 -> 0.66
B72: 11 | C72: E | D72: =D71+1 -> 67 | E72: KARGODORIAN SILVIA | G72: 1.1545 | M72: 0 | N72: =P$2*G72% -> 282506.15 | O72: 0 | P72: =ROUND(SUM(K72:O72),0) + S72 -> 282506.67 | Q72: =ROUND(P72*6% + P72,0) + S72 -> 299457.67 | R72: =ROUND(P72*3%,0) + P72 -> 290981.67 | S72: =S71+0.01 -> 0.67
B73: 12 | C73: C | D73: =D72+1 -> 68 | E73: ALVAREZ | G73: 0.9549 | M73: 0 | N73: =P$2*G73% -> 233664.03 | O73: 0 | P73: =ROUND(SUM(K73:O73),0) + S73 -> 233664.68 | Q73: =ROUND(P73*6% + P73,0) + S73 -> 247685.68 | R73: =ROUND(P73*3%,0) + P73 -> 240674.68 | S73: =S72+0.01 -> 0.68
B74: 12 | C74: D | D74: =D73+1 -> 69 | E74: RIVA MÓNICA | G74: 0.7552 | M74: 0 | N74: =P$2*G74% -> 184797.44 | O74: 0 | P74: =ROUND(SUM(K74:O74),0) + S74 -> 184797.69 | Q74: =ROUND(P74*6% + P74,0) + S74 -> 195886.69 | R74: =ROUND(P74*3%,0) + P74 -> 190341.69 | S74: =S73+0.01 -> 0.69
B75: 12 | C75: E | D75: =D74+1 -> 70 | E75: DE BIAGGIO PABLO | G75: 1.1549 | M75: 0 | N75: =P$2*G75% -> 282604.03 | O75: 0 | P75: =ROUND(SUM(K75:O75),0) + S75 -> 282604.7 | Q75: =ROUND(P75*6% + P75,0) + S75 -> 299561.7 | R75: =ROUND(P75*3%,0) + P75 -> 291082.7 | S75: =S74+0.01 -> 0.7
G81: =SUM(G6:G80) -> 100 | H81: =SUM(H6:H80) -> 0 | I81: =SUM(I6:I80) -> 0 | J81: =SUM(J6:J80) -> 0 | K81: =SUM(K6:K80) -> 0 | M81: =SUM(M6:M80) -> 0 | N81: =SUM(N6:N80) -> 24470000 | O81: =SUM(O6:O80) -> 18500 | P81: =SUM(P6:P80) -> 24488522 | Q81: =SUM(Q6:Q80) -> 25957852
E84: =RESUMEN!A14 -> ESTIMADOS PROPIETARIOS E INQUILINOS: POR FAVOR LOS QUE ABONAN EN PRIMER VENCIMIENTO ABONEN EL MONTO DE PRIMER VENCIMIENTO, ASI AGILIZAN LA LIQUIDACION, RESPETEN LOS CENTAVOS CORRESPONDIENTES A LA UNIDAD FUNCIONAL. ES DE CARÁCTER OBLIGATORIO INFORMAR VIA MAIL LAS EXPENSAS. CASO CONTRARIO SE INFORMARA VIA CARTA DOCUMENTO A LA UNIDAD FUNCIONAL QUE CREEMOS QUE CORRESPONDE, CUYO COSTO SERA IMPUTADO A LA UNIDAD FUNCIONAL SOSPECHADA.
