Workbook

Sheet RESUMEN
C1: MAIL: elmiradorconsorcios@gmail.com
C2: CUIT ADMINISTRACION: 27231256879
C3: CBU: 0720039720000002171436 | E3: TELEFONO: 11 5320-2676
C4: ADMINISTRADORA: CAROLINA CANCIANI MP:1148
C5: PERÍODO: ABRIL | E5: HORARIOS DE ATENCION: LUNES A VIERNES - 10 A 15HS - EMERGENCIAS 24HS
C6: LIQUIDACION DE EXPENSAS
A14: Importante para dueños o inquilinos de departamentos o coheras: Queremos recordarles una cuestión importante respecto a los pagos de expensas que ayuda a evitar errores en la imputación de los mismos. El sistema que utilizamos asigna centavos únicos a cada Unidad Funcional (UF), lo cual nos permite identificar automáticamente a qué unidad corresponde cada transferencia. Es decir, cada UF tiene un número específico de centavos que actúa como "identificador". Por ejemplo, si tu UF es la 45, el importe a abonar debería terminar en $...,45. Si tenés más de una unidad (por ejemplo, un departamento y una cochera), cada una tiene su propio código de centavos. En esos casos, te pedimos por favor que realices una transferencia por cada UF, respetando el importe con sus centavos correspondientes. Sabemos que a veces por comodidad se suele enviar todo junto en una sola transferencia, pero esto puede generar confusión o errores en la imputación automática. Realizar los pagos por separado nos permite asegurar que cada importe se asigne correctamente. Agradecemos muchísimo la colaboración para seguir manteniendo todo ordenado. Saludos cordiales.
A20: VTO 15/05
A24: GASTOS ORDINARIOS UNIDADES FUNCIONALES: | E24: UF 93,20% | F24: LOCAL 1 (1,08%) | G24: LOCAL 2 (1,28%) | H24: LOCAL 3 (1,21%) | I24: LOCAL 4 (1,49%) | J24: LOCAL 5 (1,74%)
A25: Salvati - Servicios de limpieza
A27: TOTAL | D27: =SUM(D25:D25) -> 0 | E27: =D27*93.2% -> 0 | F27: =$D27*1.08% -> 0 | G27: =$D27*1.28% -> 0 | H27: =$D27*1.21% -> 0 | I27: =$D27*1.49% -> 0 | J27: =D27*1.74% -> 0 | K27: =E27+J27+F27+G27+H27+I27 -> 0 | L27: =IF(D27=K27, "", "Error")
A28: COMBUSTIBLE PARA GRUPO ELECTROGENO | E28: =D28*91.91% -> 0
A30: TOTAL | D30: =SUM(D29:D29) -> 0 | E30: =D30 -> 0 | K30: =E30+J30+F30+G30+H30+I30 -> 0 | L30: =IF(D30=K30, "", "Error")
A31: IMPUESTOS
A32: ARBA - Impuesto inmobiliario partida 025024270-0 | C32: Transf 13/4 | D32: 5686514.7
A33: TSG - Partida 197227000 | B33: Mes de ABRIL | C33: Transf 29/04 | D33: 1609398
A34: TSG - Partida 197229000 | B34: Mes de Marzo | C34: Efectivo 07/04 | D34: 1609398
A35: TSG - Partida 197229000 | B35: Mes de ABRIL | C35: =C33 -> Transf 29/04 | D35: 1609398
A36: TOTAL IMPUESTOS | D36: =SUM(D32:D35) -> 10514709 | E36: =D36*93.2% -> 9799708.5 | F36: =$D36*1.08% -> 113558.85 | G36: =$D36*1.28% -> 134588.27 | H36: =$D36*1.21% -> 127227.98 | I36: =$D36*1.49% -> 156669.16 | J36: =D36*1.74% -> 182955.93 | K36: =E36+J36+F36+G36+H36+I36 -> 10514709 | L36: =IF(D36=K36, "", "Error")
A37: APORTES Y CONTRIBUCIONES
A41: TOTAL APORTES Y CONTRIBUCIONES | D41: =SUM(D37:D40) -> 0 | E41: =D41*93.2% -> 0 | F41: =$D41*1.08% -> 0 | G41: =$D41*1.28% -> 0 | H41: =$D41*1.21% -> 0 | I41: =$D41*1.49% -> 0 | J41: =D41*1.74% -> 0 | K41: =E41+J41+F41+G41+H41+I41 -> 0 | L41: =IF(D41=K41, "", "Error")
A42: SEGUROS
A43: Federacion patronal - Poliza integral para consorcios nro. 2152393 | C43: Debito autom. | D43: 160913 | E43: =D43*93.2% -> 149970.92 | F43: =$D43*1.08% -> 1737.8604 | G43: =$D43*1.28% -> 2059.6864 | H43: =$D43*1.21% -> 1947.0473 | I43: =$D43*1.49% -> 2397.6037 | J43: =D43*1.74% -> 2799.8862 | K43: =SUM(E43:J43) -> 160913
A44: Federacion patronal - Poliza integral para consorcios nro. 2152393 | C44: Debito autom. | D44: 160913 | E44: =D44*93.2% -> 149970.92 | F44: =$D44*1.08% -> 1737.8604 | G44: =$D44*1.28% -> 2059.6864 | H44: =$D44*1.21% -> 1947.0473 | I44: =$D44*1.49% -> 2397.6037 | J44: =D44*1.74% -> 2799.8862
A45: TOTAL Aportes y Contribuciones - Sindicato | D45: =SUM(D43:D44) -> 321826 | E45: =SUM(E43:E44) -> 299941.83 | F45: =SUM(F43:F44) -> 3475.7208 | G45: =SUM(G43:G44) -> 4119.3728 | H45: =SUM(H43:H44) -> 3894.0946 | I45: =SUM(I43:I44) -> 4795.2074 | J45: =SUM(J43:J44) -> 5599.7724 | K45: =E45+J45+F45+G45+H45+I45 -> 321826 | L45: =IF(D45=K45, "", "Error")
A46: ABONOS Y SERVICIOS
A47: Aysa - Cuenta 249011 | C47: Transf 06/04 | D47: 1095070.2 | E47: =D47*93.2% -> 1020605.5 | F47: =$D47*1.08% -> 11826.758 | G47: =$D47*1.28% -> 14016.899 | H47: =$D47*1.21% -> 13250.35 | I47: =$D47*1.49% -> 16316.546 | J47: =D47*1.74% -> 19054.222 | K47: =D47 -> 1095070.2 | L47: =SUM(E47:J47) -> 1095070.2
A48: Edesur - Cliente 01291636 | C48: Transf 15/04 | D48: 3904854.4 | E48: =D48*93.2% -> 3639324.3 | F48: =$D48*1.08% -> 42172.427 | G48: =$D48*1.28% -> 49982.136 | H48: =$D48*1.21% -> 47248.738 | I48: =$D48*1.49% -> 58182.33 | J48: =D48*1.74% -> 67944.466 | K48: =D48 -> 3904854.4 | L48: =E48+J48+I48+H48+G48+F48 -> 3904854.4
A49: Telecentro - Zona coworking - Cliente 7725479 | C49: Debito autom. | D49: 144486.4 | E49: =D49 -> 144486.4 | K49: =D49 -> 144486.4 | L49: =E49+J49+I49+H49+G49+F49 -> 144486.4 | M49: =L49-D49 -> 0 | N49: =K49-D49 -> 0
A50: ADS - Abono de mantenimiento ascensores ABRIL del 2025 | C50: Transf 08/04 | D50: 359504.14 | E50: =D50 -> 359504.14 | K50: =D50 -> 359504.14 | L50: =E50+J50+I50+H50+G50+F50 -> 359504.14
A51: Victor Martinez - Abono mantenimiento control de accesos - 2 Meses | C51: Transf 20/04 | D51: 90000 | E51: =D51 -> 90000 | K51: =D51 -> 90000 | L51: =E51+J51+I51+H51+G51+F51 -> 90000 | M51: =L51-D51 -> 0 | N51: =K51-D51 -> 0
A52: Metrogas - Cliente nro. 40000496339 | C52: Transf 06/04 | D52: 6132.87 | E52: =D52*93.2% -> 5715.8348 | F52: =$D52*1.08% -> 66.234996 | G52: =$D52*1.28% -> 78.500736 | H52: =$D52*1.21% -> 74.207727 | I52: =$D52*1.49% -> 91.379763 | J52: =D52*1.74% -> 106.71194 | K52: =D52 -> 6132.87 | L52: =E52+J52+I52+H52+G52+F52 -> 6132.87 | M52: =L52-D52 -> 0 | N52: =K52-D52 -> 0
A53: Metrogas - Cliente nro. 40000497007 | C53: Transf 06/04 | D53: 910081.41 | E53: =D53 -> 910081.41 | K53: =D53 -> 910081.41 | L53: =E53+J53+I53+H53+G53+F53 -> 910081.41 | M53: =L53-D53 -> 0 | N53: =K53-D53 -> 0
A54: Loschi Mantenimiento grupo electrogeno - Abono bimestral | E54: =D54 -> 0 | K54: =D54 -> 0 | L54: =E54+J54+I54+H54+G54+F54 -> 0 | M54: =L54-D54 -> 0 | N54: =K54-D54 -> 0
A55: TOTAL ABONOS Y SERVICIOS | D55: =SUM(D47:D54) -> 6510129.4 | E55: =SUM(E47:E54) -> 6169717.5 | F55: =SUM(F47:F54) -> 54065.421 | G55: =SUM(G47:G54) -> 64077.536 | H55: =SUM(H47:H54) -> 60573.296 | I55: =SUM(I47:I54) -> 74590.256 | J55: =SUM(J47:J54) -> 87105.4 | K55: =E55+J55+F55+G55+H55+I55 -> 6510129.4 | L55: =IF(D55=K55, "", "Error") | M55: =D55-K55 -> 0
A58: GASTOS VARIOS
A59: Fumigacion - Silva Nicolas | C59: Transf 21/04 | D59: 200000 | E59: =D59 -> 200000 | K59: =D59 -> 200000 | L59: =SUM(E59:J59) -> 200000
A60: Fumigacion - Silva Nicolas | C60: Transf 06/04 | D60: 200000 | E60: =D60 -> 200000 | K60: =D60 -> 200000 | L60: =SUM(E60:J60) -> 200000
A61: SGP Reparacion de perdidas de agua y gas en termotanques | C61: Transf 08/04 | D61: 180000 | E61: =D61*93.2% -> 167760 | F61: =$D61*1.08% -> 1944 | G61: =$D61*1.28% -> 2304 | H61: =$D61*1.21% -> 2178 | I61: =$D61*1.49% -> 2682 | J61: =D61*1.74% -> 3132 | K61: =D61 -> 180000 | L61: =SUM(E61:J61) -> 180000
A62: Articulos de limpieza | C62: Transf 15/04 | D62: 228448 | E62: =D62*93.2% -> 212913.54 | F62: =$D62*1.08% -> 2467.2384 | G62: =$D62*1.28% -> 2924.1344 | H62: =$D62*1.21% -> 2764.2208 | I62: =$D62*1.49% -> 3403.8752 | J62: =D62*1.74% -> 3974.9952 | K62: =D62 -> 228448 | L62: =SUM(E62:J62) -> 228448
A63: Galvan Zaffalon Micaela - Plan Canje Rowa bomba recilculadora | C63: Transf 24/04 | D63: 1471770 | E63: =D63*93.2% -> 1371689.6 | F63: =$D63*1.08% -> 15895.116 | G63: =$D63*1.28% -> 18838.656 | H63: =$D63*1.21% -> 17808.417 | I63: =$D63*1.49% -> 21929.373 | J63: =D63*1.74% -> 25608.798 | K63: =D63 -> 1471770 | L63: =SUM(E63:J63) -> 1471770
A64: Galvan Zaffalon Micaela - Instalacion Bomba | C64: Transf 30/04 | D64: 250000 | E64: =D64 -> 250000 | K64: =D64 -> 250000 | L64: =SUM(E64:J64) -> 250000
A65: Cuello natalia - Desobstruccion de columna baño 5D | C65: Transf 24/04 | D65: 46200 | E65: =D65*93.2% -> 43058.4 | F65: =$D65*1.08% -> 498.96 | G65: =$D65*1.28% -> 591.36 | H65: =$D65*1.21% -> 559.02 | I65: =$D65*1.49% -> 688.38 | J65: =D65*1.74% -> 803.88
A66: TOTAL GASTOS VARIOS | D66: =SUM(D59:D65) -> 2576418 | E66: =SUM(E59:E65) -> 2445421.6 | F66: =SUM(F59:F65) -> 20805.314 | G66: =SUM(G59:G65) -> 24658.15 | H66: =SUM(H59:H65) -> 23309.658 | I66: =SUM(I59:I65) -> 28703.628 | J66: =SUM(J59:J65) -> 33519.673 | K66: =E66+J66+F66+G66+H66+I66 -> 2576418 | L66: =IF(D66=K66, "", "Error")
A69: GASTOS DE ADMINISTRACION
A70: RC Adm Cons. CANCIANI, Carolina | B70: MP:1148 | C70: Se adeuda ABRIL | D70: 860560 | E70: =D70*93.2% -> 802041.92 | F70: =$D70*1.08% -> 9294.048 | G70: =$D70*1.28% -> 11015.168 | H70: =$D70*1.21% -> 10412.776 | I70: =$D70*1.49% -> 12822.344 | J70: =D70*1.74% -> 14973.744 | L70: M4rz0
E71: =D71*93.2% -> 0 | F71: =$D71*1.08% -> 0 | G71: =$D71*1.28% -> 0 | H71: =$D71*1.21% -> 0 | I71: =$D71*1.49% -> 0 | J71: =D71*1.74% -> 0
A73: TOTAL GASTOS DE ADMINISTRACION | D73: =SUM(D70:D72) -> 860560 | E73: =SUM(E70:E72) -> 802041.92 | F73: =SUM(F70:F72) -> 9294.048 | G73: =SUM(G70:G72) -> 11015.168 | H73: =SUM(H70:H72) -> 10412.776 | I73: =SUM(I70:I72) -> 12822.344 | J73: =SUM(J70:J72) -> 14973.744 | K73: =E73+J73+F73+G73+H73+I73 -> 860560 | L73: =IF(D73=K73, "", "Error")
A74: Gastos bancarios | D74: =411981-1818 -> 410163 | E74: =D74*93.2% -> 382271.92 | F74: =$D74*1.08% -> 4429.7604 | G74: =$D74*1.28% -> 5250.0864 | H74: =$D74*1.21% -> 4962.9723 | I74: =$D74*1.49% -> 6111.4287 | J74: =D74*1.74% -> 7136.8362
A75: Mantenimiento de cuenta | D75: 57500 | E75: =D75*93.2% -> 53590 | F75: =$D75*1.08% -> 621 | G75: =$D75*1.28% -> 736 | H75: =$D75*1.21% -> 695.75 | I75: =$D75*1.49% -> 856.75 | J75: =D75*1.74% -> 1000.5
A76: TOTAL GASTOS BANCARIOS | D76: =SUM(D74:D75) -> 467663 | E76: =SUM(E74:E75) -> 435861.92 | F76: =SUM(F74:F75) -> 5050.7604 | G76: =SUM(G74:G75) -> 5986.0864 | H76: =SUM(H74:H75) -> 5658.7223 | I76: =SUM(I74:I75) -> 6968.1787 | J76: =SUM(J74:J75) -> 8137.3362 | K76: =E76+J76+F76+G76+H76+I76 -> 467663 | L76: =IF(D76=K76, "", "Error")
A78: FONDO DE GASTOS ORDINARIOS | E78: =D78*93.2% -> 0 | F78: =$D78*1.08% -> 0 | G78: =$D78*1.28% -> 0 | H78: =$D78*1.21% -> 0 | I78: =$D78*1.49% -> 0 | J78: =D78*1.74% -> 0 | K78: =E78+J78+F78+G78+H78+I78 -> 0 | L78: =IF(D78=K78, "", "Error")
A80: TOTAL ORDINARIOS | D80: =SUM(D78+D36+D30+D76+D73+D66+D55+D45+D27++D41) -> 21251305 | E80: =SUM(E78+E36+E30+E76+E73+E66+E55+E45+E27++E41) -> 19952693 | F80: =SUM(F78+F36+F30+F76+F73+F66+F55+F45+F27++F41) -> 206250.12 | G80: =SUM(G78+G36+G30+G76+G73+G66+G55+G45+G27++G41) -> 244444.58 | H80: =SUM(H78+H36+H30+H76+H73+H66+H55+H45+H27++H41) -> 231076.52 | I80: =SUM(I78+I36+I30+I76+I73+I66+I55+I45+I27++I41) -> 284548.77 | J80: =SUM(J78+J36+J30+J76+J73+J66+J55+J45+J27++J41) -> 332291.86 | K80: =E80+J80+F80+G80+H80+I80 -> 21251305 | L80: =IF(D80=K80, "", "Error") | M80: =D80-K80 -> 0
A82: Gastos particulares
A83: Control para porton - 6C | C83: 24200
A84: Control para porton - 13C | C84: =90750/2 -> 45375
A85: Control para porton - 6D | C85: =90750/2 -> 45375
A86: TOTAL | C86: =SUM(C83:C85) -> 114950
A89: GASTOS EXTRAORDINARIOS | E89: UF | F89: LOCAL 1 (1,08%) | G89: LOCAL 2 (1,28%) | H89: LOCAL 3 (1,21%) | I89: LOCAL 4 (1,49%) | J89: LOCAL 5 (1,74%)
E90: =D90 -> 0
A92: TOTAL | D92: =SUM(D90:D91) -> 0 | E92: =SUM(E90:E91) -> 0 | J92: =SUM(J90:J91) -> 0 | L92: =E92+J92 -> 0 | M92: =IF(D92=L92, "", "Error")
A95: GASTOS ORDINARIOS + PREVISION : | B95: =D80 -> 21251305
A96: GASTOS ORDINARIOS SIN PREVISION: | B96: =D80-D78 -> 21251305 | D96: Se recuerda a todos los propietarios que, en caso de producirse la venta o transferencia de una unidad funcional, es obligatorio informar a la Administración los datos de los nuevos titulares. Dicha notificación resulta indispensable para actualizar los registros del consorcio, emitir correctamente las expensas y garantizar que toda comunicación formal llegue a quienes correspondan. La información a presentar deberá incluir al menos: * Nombre y apellido de los nuevos propietarios. * Domicilio de contacto (en caso de ser distinto de la unidad funcional). * Correo electrónico y/o teléfono de contacto. * Copia de la escritura, acta notarial o documentación que acredite la transferencia. Hasta tanto no se reciba la notificación formal, toda comunicación y responsabilidad respecto de la unidad seguirá dirigida al propietario anterior.
A99: CAJA EFECTIVO $ (pesos)
A100: Saldo anterior | B100: 12236086
A101: Ingresos | B101: =PRORRATEO!H133 -> 12108632
A102: Ingreso por pago de ARBA | B102: =ARBA!L82 -> 10374975
A103: UF 46 Transfiere ARBA directo a la constructora | B103: -280064.46
A104: Egresos Ordinarios | B104: =-B96 -> -21251305
A105: Egresos Extraordinarios | B105: =-D92 -> 0
A106: Dinero en efectivo | B106: 90602
A107: Dinero sin identificar | B107: =B116 -> 0
A108: Dinero ingreso SUM | B108: =-B121 -> -113840
A109: Gastos particulares | B109: =-C86 -> -114950
A110: Deposito ya identificado mes anterior | B110: -673000
A111: Transferencia a la desarrolladora (15/04) - ARBA pago parcial | B111: -7428991
A112: Saldo al cierre | B112: =SUM(B100:B111) -> 4948144.8
A114: TRANSFERENCIAS SIN IDENTIFICAR
A116: TOTAL | B116: =SUM(B114:B115) -> 0
A120: CAJA SUM $ (pesos) | B120: 325000
A121: Ingreso | B121: 113840
A123: TOTAL | B123: =SUM(B120:B122) -> 438840
A125: Caja Real -Banco - SUM + Ordinaria | B125: =B123+B112 -> 5386984.8
A127: IMPORTANTE: SE LE DEBE A LA DESARROLLADORA EL MONTO DE $10.094.910,3 (INGRESO DE ARBA) - LA CAJA REAL : -$4.707.925,49

Sheet PRORRATEO
A1: Las casillas coloreadas en la columna Gastos Par/SUM de color rojo corresponden a multas aplicadas por el uso del SUM. En consecuencia, la unidad funcional involucrada no podrá acceder al uso del mismo por tiempo indeterminado. Por otro lado, las casillas coloreadas en amarillo, corresponden a llaves y las verdes corresponden al mal uso del coworking. | F1: Banco Santander Rio. | L1: SE GASTO: | M1: =RESUMEN!D80-N3 -> 15564790
F2: CBU: 0720039720000002171436 | L2: SE PRORRATEA EN LAS UF: | N2: 15000000
F3: CTA CTE $ 0039 - 21714/3 FIDEICOMISO 25 DE MAYO 837 LAN 30716676737 | L3: ARBA: | N3: 5686514.7
C5: IMPORTANTE: Las personas marcadas en color naranja abonaron de forma incorrecta mediante Mercado Pago. A partir de ahora (incluso desde hace meses), ya se encuentra habilitada la cuenta bancaria correspondiente, por lo que todos los pagos deben realizarse exclusivamente a través de dicha cuenta. Los datos de la misma se encuentran justo arriba de este aviso. Quienes abonen por Mercado Pago corren el riesgo de que su pago no sea imputado correctamente.
C9: IMPORTANTE: Quienes estan en violeta NO ha respetado los centavos al abonar. Para la proxima oportunidad, solicitamos que los respeten. | Q9: LOCAL 1 | R9: =RESUMEN!F80 -> 206250.12
Q10: LOCAL 2 | R10: =RESUMEN!G80 -> 244444.58
A11: Piso | B11: Dpto. | C11: UF | D11: Propietario | E11: Inquilinos | F11: (%) | G11: Saldo | H11: Ingreso | I11: SALDO | J11: Expensas extraor. | K11: Cuota 2/2026 ARBA | L11: Expensas ord | M11: SUM/ GASTOS PART | N11: TOTAL A ABONAR HASTA | O11: TOTAL A ABONAR 2DO VTO - DESDE EL | Q11: LOCAL 3 | R11: =RESUMEN!H80 -> 231076.52
Q12: LOCAL 4 | R12: =RESUMEN!I80 -> 284548.77
N13: =RESUMEN!A20 -> VTO 15/05 | O13: =RESUMEN!A20 -> VTO 15/05 | Q13: LOCAL 5 | R13: =RESUMEN!J80 -> 332291.86
A14: conf sup | C14: LOC 1 | D14: Fernandez, Cristian | E14: Gladys ojeda Britez - Exequiel alexis giuliani | F14: 0.0108 | G14: 269607.96 | H14: =G14 -> 269607.96 | I14: =G14-H14 -> 0 | J14: 0 | K14: =N$3*F14 -> 61414.359 | L14: 206250.12 | M14: 0 | N14: =L14+J14+I14+M14+K14 -> 267664.48 | O14: =N14*6% + N14 -> 283724.35 | P14: Bezzo Jorge
C15: LOC 2 | D15: Fridgi, Guillermo Ariel | F15: 0.013 | G15: 217781.13 | H15: 148104 | I15: =G15-H15 -> 69677.129 | J15: 0 | K15: =N$3*F15 -> 73924.691 | L15: 244444.58 | M15: 0 | N15: =L15+J15+I15+M15+K15 -> 388046.4 | O15: =N15*6% + N15 -> 411329.19 | P15: Lucas Rocha
A16: conf sup | C16: LOC 3 | D16: Patricia Mainieri | E16: Cristina andrea Massa | F16: 0.0121 | G16: 140004.56 | H16: =G16 -> 140004.56 | I16: =G16-H16 -> 0 | J16: 0 | K16: =N$3*F16 -> 68806.828 | L16: 231076.52 | M16: 0 | N16: =L16+J16+I16+M16+K16 -> 299883.35 | O16: =N16*6% + N16 -> 317876.35
A17: conf sup | C17: LOC 4 | D17: Cordero, Leandro Emanuel - Orona, Victoria | F17: 0.0149 | G17: 1197773.1 | I17: =G17-H17 -> 1197773.1 | J17: 0 | K17: =N$3*F17 -> 84729.069 | L17: 284548.77 | M17: 0 | N17: =L17+J17+I17+M17+K17 -> 1567051 | O17: =N17*6% + N17 -> 1661074
A18: conf sup | C18: LOC 5 | D18: Orsi, Jose Luis - Fernandez, Cristian Gabriel | F18: 0.0174 | G18: 661969.3 | H18: =701700 -> 701700 | I18: =G18-H18 -> -39730.703 | J18: 0 | K18: =N$3*F18 -> 98945.356 | L18: 332291.86 | M18: 0 | N18: =L18+J18+I18+M18+K18 -> 391506.51 | O18: =N18*6% + N18 -> 414996.9
A19: 3 amb | C19: 2ºA | D19: Franco, Lucas Fabián | F19: 0.0188 | G19: 225600.01 | H19: =G19 -> 225600.01 | I19: =G19-H19 -> 0 | J19: =N$8*F19 -> 0 | K19: =N$3*F19 -> 106906.48 | L19: =N$2*F19 -> 282000 | M19: 0 | N19: =ROUND((L19+J19+I19+K19+M19),0) + P19 -> 388906.01 | O19: =ROUND((N19*6% + N19 ),0) + P19 -> 412240.01 | P19: 0.01
A20: 1 amb | C20: 2ºB | D20: Martinez, Diego | F20: 0.0084 | G20: 100800.02 | H20: =G20 -> 100800.02 | I20: =G20-H20 -> 0 | J20: =N$8*F20 -> 0 | K20: =N$3*F20 -> 47766.723 | L20: =N$2*F20 -> 126000 | M20: 0 | N20: =ROUND((L20+J20+I20+K20+M20),0) + P20 -> 173767.02 | O20: =ROUND((N20*6% + N20 ),0) + P20 -> 184193.02 | P20: =P19+0.01 -> 0.02
A21: 3 amb | C21: 2ºC | D21: Rodriguez, Carlos Alberto Miguel | F21: 0.0201 | G21: 276872.03 | H21: =G21 -> 276872.03 | I21: =G21-H21 -> 0 | J21: =N$8*F21 -> 0 | K21: =N$3*F21 -> 114298.95 | L21: =N$2*F21 -> 301500 | M21: 0 | N21: =ROUND((L21+J21+I21+K21+M21),0) + P21 -> 415799.03 | O21: =ROUND((N21*6% + N21 ),0) + P21 -> 440747.03 | P21: =P20+0.01 -> 0.03
A22: 2 amb | C22: 2ºD | D22: Ferraro, José | E22: Matias Cuevas | F22: 0.0094 | G22: 112404.04 | H22: =50382+112800 -> 163182 | I22: =G22-H22 -> -50777.96 | J22: =N$8*F22 -> 0 | K22: =N$3*F22 -> 53453.238 | L22: =N$2*F22 -> 141000 | M22: 0 | N22: =ROUND((L22+J22+I22+K22+M22),0) + P22 -> 143675.04 | O22: =ROUND((N22*6% + N22 ),0) + P22 -> 152296.04 | P22: =P21+0.01 -> 0.04 | Q22: Matias alejandro ezequiel
A23: 2 amb | C23: 2ºE | D23: Dieci, Matias Orlando | E23: Julieta Damiano/Damiani | F23: 0.0087 | G23: 104400.05 | H23: =G23 -> 104400.05 | I23: =G23-H23 -> 0 | J23: =N$8*F23 -> 0 | K23: =N$3*F23 -> 49472.678 | L23: =N$2*F23 -> 130500 | M23: 0 | N23: =ROUND((L23+J23+I23+K23+M23),0) + P23 -> 179973.05 | O23: =ROUND((N23*6% + N23 ),0) + P23 -> 190771.05 | P23: =P22+0.01 -> 0.05
A24: 2 amb | C24: 2ºF | D24: Ferraro, Jose | E24: Carolina Massa | F24: 0.0095 | G24: 114000.06 | H24: =G24+50918 -> 164918.06 | I24: =G24-H24 -> -50918 | J24: =N$8*F24 -> 0 | K24: =N$3*F24 -> 54021.89 | L24: =N$2*F24 -> 142500 | M24: 0 | N24: =ROUND((L24+J24+I24+K24+M24),0) + P24 -> 145604.06 | O24: =ROUND((N24*6% + N24 ),0) + P24 -> 154340.06 | P24: =P23+0.01 -> 0.06
A25: 3 amb | C25: 3ºA | D25: Ferraro, Jose | E25: Walter Gabriel Ledesma | F25: 0.0165 | G25: 198000.07 | H25: =G25+88437 -> 286437.07 | I25: =G25-H25 -> -88437 | J25: =N$8*F25 -> 0 | K25: =N$3*F25 -> 93827.493 | L25: =N$2*F25 -> 247500 | M25: 0 | N25: =ROUND((L25+J25+I25+K25+M25),0) + P25 -> 252890.07 | O25: =ROUND((N25*6% + N25 ),0) + P25 -> 268063.07 | P25: =P24+0.01 -> 0.07
A26: 1 amb | C26: 3ºB | D26: Balduzzi, Stella Maris | F26: 0.0073 | G26: 87600.08 | H26: =G26 -> 87600.08 | I26: =G26-H26 -> 0 | J26: =N$8*F26 -> 0 | K26: =N$3*F26 -> 41511.557 | L26: =N$2*F26 -> 109500 | M26: 0 | N26: =ROUND((L26+J26+I26+K26+M26),0) + P26 -> 151012.08 | O26: =ROUND((N26*6% + N26 ),0) + P26 -> 160073.08 | P26: =P25+0.01 -> 0.08
A27: 3 amb | C27: 3ºC | D27: Ferraro, Jose | E27: Gustavo Oscar Fernandez | F27: 0.0178 | G27: 468030.09 | H27: =G27+95405 -> 563435.09 | I27: =G27-H27 -> -95405 | J27: =N$8*F27 -> 0 | K27: =N$3*F27 -> 101219.96 | L27: =N$2*F27 -> 267000 | M27: 0 | N27: =ROUND((L27+J27+I27+K27+M27),0) + P27 -> 272815.09 | O27: =ROUND((N27*6% + N27 ),0) + P27 -> 289184.09 | P27: =P26+0.01 -> 0.09
A28: 2 amb | C28: 3ºD | D28: Fernandez, Christian Norberto | F28: 0.0094 | G28: 257182.1 | H28: =G28 -> 257182.1 | I28: =G28-H28 -> 0 | J28: =N$8*F28 -> 0 | K28: =N$3*F28 -> 53453.238 | L28: =N$2*F28 -> 141000 | M28: 0 | N28: =ROUND((L28+J28+I28+K28+M28),0) + P28 -> 194453.1 | O28: =ROUND((N28*6% + N28 ),0) + P28 -> 206120.1 | P28: =P27+0.01 -> 0.1
A29: 2 amb | C29: 3ºE | D29: Dallorso, Maria Ines - Dallorso, Ana Paula | F29: 0.0087 | G29: 104400.11 | H29: =G29 -> 104400.11 | I29: =G29-H29 -> 0 | J29: =N$8*F29 -> 0 | K29: =N$3*F29 -> 49472.678 | L29: =N$2*F29 -> 130500 | M29: 0 | N29: =ROUND((L29+J29+I29+K29+M29),0) + P29 -> 179973.11 | O29: =ROUND((N29*6% + N29 ),0) + P29 -> 190771.11 | P29: =P28+0.01 -> 0.11
A30: 2 amb | C30: 3ºF | D30: Ayala, Roberto Adrian | F30: 0.0095 | G30: 1075346.1 | I30: =G30-H30 -> 1075346.1 | J30: =N$8*F30 -> 0 | K30: =N$3*F30 -> 54021.89 | L30: =N$2*F30 -> 142500 | M30: 0 | N30: =ROUND((L30+J30+I30+K30+M30),0) + P30 -> 1271868.1 | O30: =ROUND((N30*6% + N30 ),0) + P30 -> 1348180.1 | P30: =P29+0.01 -> 0.12
A31: 3 amb | C31: 4ºA | D31: Barral, Carlos Daniel | F31: 0.0164 | G31: 231914.13 | H31: =G31 -> 231914.13 | I31: =G31-H31 -> 0 | J31: =N$8*F31 -> 0 | K31: =N$3*F31 -> 93258.841 | L31: =N$2*F31 -> 246000 | M31: 0 | N31: =ROUND((L31+J31+I31+K31+M31),0) + P31 -> 339259.13 | O31: =ROUND((N31*6% + N31 ),0) + P31 -> 359615.13 | P31: =P30+0.01 -> 0.13
A32: 1 amb | C32: 4ºB | D32: Sr. Propietario | E32: Liria | F32: 0.0072 | G32: 86400.14 | H32: =G32 -> 86400.14 | I32: =G32-H32 -> 0 | J32: =N$8*F32 -> 0 | K32: =N$3*F32 -> 40942.906 | L32: =N$2*F32 -> 108000 | M32: 0 | N32: =ROUND((L32+J32+I32+K32+M32),0) + P32 -> 148943.14 | O32: =ROUND((N32*6% + N32 ),0) + P32 -> 157880.14 | P32: =P31+0.01 -> 0.14
A33: 3 amb | C33: 4ºC | D33: Osipowicz, Ariel Marcelo | F33: 0.0173 | G33: 207600.15 | H33: =G33 -> 207600.15 | I33: =G33-H33 -> 0 | J33: =N$8*F33 -> 0 | K33: =N$3*F33 -> 98376.704 | L33: =N$2*F33 -> 259500 | M33: 0 | N33: =ROUND((L33+J33+I33+K33+M33),0) + P33 -> 357877.15 | O33: =ROUND((N33*6% + N33 ),0) + P33 -> 379350.15 | P33: =P32+0.01 -> 0.15
A34: 2 amb | C34: 4ºD | D34: Ruiz, Juana Del Valle | F34: 0.0094 | G34: 112800.16 | H34: 119568.16 | I34: =G34-H34 -> -6768 | J34: =N$8*F34 -> 0 | K34: =N$3*F34 -> 53453.238 | L34: =N$2*F34 -> 141000 | M34: 0 | N34: =ROUND((L34+J34+I34+K34+M34),0) + P34 -> 187685.16 | O34: =ROUND((N34*6% + N34 ),0) + P34 -> 198946.16 | P34: =P33+0.01 -> 0.16 | Q34: Pablo Amarilla
A35: 2 amb | C35: 4ºE | D35: Ayala, Roberto Adrian | E35: Iara | F35: 0.0087 | G35: 104400.17 | I35: =G35-H35 -> 104400.17 | J35: =N$8*F35 -> 0 | K35: =N$3*F35 -> 49472.678 | L35: =N$2*F35 -> 130500 | M35: 0 | N35: =ROUND((L35+J35+I35+K35+M35),0) + P35 -> 284373.17 | O35: =ROUND((N35*6% + N35 ),0) + P35 -> 301436.17 | P35: =P34+0.01 -> 0.17
A36: 2 amb | C36: 4ºF | D36: Ayala, Roberto Adrian | F36: 0.0095 | G36: 557595.18 | I36: =G36-H36 -> 557595.18 | J36: =N$8*F36 -> 0 | K36: =N$3*F36 -> 54021.89 | L36: =N$2*F36 -> 142500 | M36: 0 | N36: =ROUND((L36+J36+I36+K36+M36),0) + P36 -> 754117.18 | O36: =ROUND((N36*6% + N36 ),0) + P36 -> 799364.18 | P36: =P35+0.01 -> 0.18
A37: 3 amb | C37: 5ºA | D37: Chehab, Gabriel Adrian | E37: Santiago Rodriguez | F37: 0.0164 | G37: 196800.19 | H37: =G37 -> 196800.19 | I37: =G37-H37 -> 0 | J37: =N$8*F37 -> 0 | K37: =N$3*F37 -> 93258.841 | L37: =N$2*F37 -> 246000 | M37: 0 | N37: =ROUND((L37+J37+I37+K37+M37),0) + P37 -> 339259.19 | O37: =ROUND((N37*6% + N37 ),0) + P37 -> 359615.19 | P37: =P36+0.01 -> 0.19 | Q37: Cochera 38
A38: 1 amb | C38: 5ºB | D38: Mesa, Mariano | F38: 0.0072 | G38: 86400.2 | H38: =G38 -> 86400.2 | I38: =G38-H38 -> 0 | J38: =N$8*F38 -> 0 | K38: =N$3*F38 -> 40942.906 | L38: =N$2*F38 -> 108000 | M38: 0 | N38: =ROUND((L38+J38+I38+K38+M38),0) + P38 -> 148943.2 | O38: =ROUND((N38*6% + N38 ),0) + P38 -> 157880.2 | P38: =P37+0.01 -> 0.2
A39: 3 amb | C39: 5ºC | D39: Di Mito, Vicente Argentino - Serantes, Mabel | F39: 0.0173 | G39: 176369.21 | I39: =G39-H39 -> 176369.21 | J39: =N$8*F39 -> 0 | K39: =N$3*F39 -> 98376.704 | L39: =N$2*F39 -> 259500 | M39: 0 | N39: =ROUND((L39+J39+I39+K39+M39),0) + P39 -> 534246.21 | O39: =ROUND((N39*6% + N39 ),0) + P39 -> 566301.21 | P39: =P38+0.01 -> 0.21
A40: 2 amb | C40: 5ºD | D40: Ayala, Agustin | F40: 0.0094 | G40: 625361.22 | I40: =G40-H40 -> 625361.22 | J40: =N$8*F40 -> 0 | K40: =N$3*F40 -> 53453.238 | L40: =N$2*F40 -> 141000 | M40: 0 | N40: =ROUND((L40+J40+I40+K40+M40),0) + P40 -> 819814.22 | O40: =ROUND((N40*6% + N40 ),0) + P40 -> 869003.22 | P40: =P39+0.01 -> 0.22 | Q40: Ayala paga 5D, 5F y 4F
A41: 2 amb | C41: 5ºE | D41: Ayala, Roberto Adrian | E41: Savino Cecilia | F41: 0.0087 | G41: 104400.23 | H41: =G41 -> 104400.23 | I41: =G41-H41 -> 0 | J41: =N$8*F41 -> 0 | K41: =N$3*F41 -> 49472.678 | L41: =N$2*F41 -> 130500 | M41: 0 | N41: =ROUND((L41+J41+I41+K41+M41),0) + P41 -> 179973.23 | O41: =ROUND((N41*6% + N41 ),0) + P41 -> 190772.23 | P41: =P40+0.01 -> 0.23 | Q41: COCHERA 31
A42: 2 amb | C42: 5ºF | D42: Ayala, Agustin | F42: 0.0095 | G42: 302815.24 | H42: 0 | I42: =G42-H42 -> 302815.24 | J42: =N$8*F42 -> 0 | K42: =N$3*F42 -> 54021.89 | L42: =N$2*F42 -> 142500 | M42: 0 | N42: =ROUND((L42+J42+I42+K42+M42),0) + P42 -> 499337.24 | O42: =ROUND((N42*6% + N42 ),0) + P42 -> 529297.24 | P42: =P41+0.01 -> 0.24
A43: 3 amb | C43: 6ºA | D43: Morandi, Victoria Ayelen | Calvo, Luciano Ezequiel | F43: 0.0164 | G43: 196800.25 | H43: =G43 -> 196800.25 | I43: =G43-H43 -> 0 | J43: =N$8*F43 -> 0 | K43: =N$3*F43 -> 93258.841 | L43: =N$2*F43 -> 246000 | M43: 0 | N43: =ROUND((L43+J43+I43+K43+M43),0) + P43 -> 339259.25 | O43: =ROUND((N43*6% + N43 ),0) + P43 -> 359615.25 | P43: =P42+0.01 -> 0.25
A44: 1 amb | C44: 6ºB | D44: Grizak Ruben | E44: Christian | F44: 0.0072 | G44: 86400.26 | H44: =G44 -> 86400.26 | I44: =G44-H44 -> 0 | J44: =N$8*F44 -> 0 | K44: =N$3*F44 -> 40942.906 | L44: =N$2*F44 -> 108000 | M44: 0 | N44: =ROUND((L44+J44+I44+K44+M44),0) + P44 -> 148943.26 | O44: =ROUND((N44*6% + N44 ),0) + P44 -> 157880.26 | P44: =P43+0.01 -> 0.26
A45: 3 amb | C45: 6ºC | D45: Nuñez Leonel - Corrieri Giuliana | F45: 0.0173 | G45: 207600.27 | H45: =G45 -> 207600.27 | I45: =G45-H45 -> 0 | J45: =N$8*F45 -> 0 | K45: =N$3*F45 -> 98376.704 | L45: =N$2*F45 -> 259500 | M45: 24000 | N45: =ROUND((L45+J45+I45+K45+M45),0) + P45 -> 381877.27 | O45: =ROUND((N45*6% + N45 ),0) + P45 -> 404790.27 | P45: =P44+0.01 -> 0.27 | Q45: COCHERA 33 | R45: COCHERA 33
A46: 2 amb | C46: 6ºD | D46: Anchipi, Gaston Nicolas | F46: 0.0094 | G46: 112800.28 | I46: =G46-H46 -> 112800.28 | J46: =N$8*F46 -> 0 | K46: =N$3*F46 -> 53453.238 | L46: =N$2*F46 -> 141000 | M46: 45375 | N46: =ROUND((L46+J46+I46+K46+M46),0) + P46 -> 352629.28 | O46: =ROUND((N46*6% + N46 ),0) + P46 -> 373787.28 | P46: =P45+0.01 -> 0.28
A47: 2 amb | C47: 6ºE | D47: Dieci, Matias Orlando | E47: Gaston Smith | F47: 0.0087 | G47: 96382.29 | I47: =G47-H47 -> 96382.29 | J47: =N$8*F47 -> 0 | K47: =N$3*F47 -> 49472.678 | L47: =N$2*F47 -> 130500 | M47: 20000 | N47: =ROUND((L47+J47+I47+K47+M47),0) + P47 -> 296355.29 | O47: =ROUND((N47*6% + N47 ),0) + P47 -> 314137.29 | P47: =P46+0.01 -> 0.29
A48: 2 amb | C48: 6ºF | D48: Mazzia Alexia | F48: 0.0095 | G48: 114000.3 | H48: =G48 -> 114000.3 | I48: =G48-H48 -> 0 | J48: =N$8*F48 -> 0 | K48: =N$3*F48 -> 54021.89 | L48: =N$2*F48 -> 142500 | M48: 0 | N48: =ROUND((L48+J48+I48+K48+M48),0) + P48 -> 196522.3 | O48: =ROUND((N48*6% + N48 ),0) + P48 -> 208314.3 | P48: =P47+0.01 -> 0.3
A49: 3 amb | C49: 7ºA | D49: Campelo, Mariano | F49: 0.0164 | G49: 196800.31 | H49: =G49 -> 196800.31 | I49: =G49-H49 -> 0 | J49: =N$8*F49 -> 0 | K49: =N$3*F49 -> 93258.841 | L49: =N$2*F49 -> 246000 | M49: 0 | N49: =ROUND((L49+J49+I49+K49+M49),0) + P49 -> 339259.31 | O49: =ROUND((N49*6% + N49 ),0) + P49 -> 359615.31 | P49: =P48+0.01 -> 0.31
A50: 1 amb | C50: 7ºB | D50: Paes, Yazmin Luciana | F50: 0.0072 | G50: 86400.32 | H50: =G50 -> 86400.32 | I50: =G50-H50 -> 0 | J50: =N$8*F50 -> 0 | K50: =N$3*F50 -> 40942.906 | L50: =N$2*F50 -> 108000 | M50: 0 | N50: =ROUND((L50+J50+I50+K50+M50),0) + P50 -> 148943.32 | O50: =ROUND((N50*6% + N50 ),0) + P50 -> 157880.32 | P50: =P49+0.01 -> 0.32
A51: 3 amb | C51: 7ºC | D51: Gonzalez Fedullo, Roxana y Valeria | F51: 0.0173 | G51: 207600.33 | H51: =G51 -> 207600.33 | I51: =G51-H51 -> 0 | J51: =N$8*F51 -> 0 | K51: =N$3*F51 -> 98376.704 | L51: =N$2*F51 -> 259500 | M51: 0 | N51: =ROUND((L51+J51+I51+K51+M51),0) + P51 -> 357877.33 | O51: =ROUND((N51*6% + N51 ),0) + P51 -> 379350.33 | P51: =P50+0.01 -> 0.33
A52: 2 amb | C52: 7ºD | D52: Solleiro, Carolina Mabel | F52: 0.0094 | G52: 112800.34 | H52: =G52 -> 112800.34 | I52: =G52-H52 -> 0 | J52: =N$8*F52 -> 0 | K52: =N$3*F52 -> 53453.238 | L52: =N$2*F52 -> 141000 | M52: 0 | N52: =ROUND((L52+J52+I52+K52+M52),0) + P52 -> 194453.34 | O52: =ROUND((N52*6% + N52 ),0) + P52 -> 206121.34 | P52: =P51+0.01 -> 0.34 | Q52: Walter Javier Dimiziunas
A53: 2 amb | C53: 7ºE | D53: Leyes, Javier | F53: 0.0087 | G53: 104400.35 | H53: =G53 -> 104400.35 | I53: =G53-H53 -> 0 | J53: =N$8*F53 -> 0 | K53: =N$3*F53 -> 49472.678 | L53: =N$2*F53 -> 130500 | M53: 0 | N53: =ROUND((L53+J53+I53+K53+M53),0) + P53 -> 179973.35 | O53: =ROUND((N53*6% + N53 ),0) + P53 -> 190772.35 | P53: =P52+0.01 -> 0.35
A54: 2 amb | C54: 7ºF | D54: Puente, Matias | F54: 0.0095 | G54: 114000.36 | H54: 5947.36 | I54: =G54-H54 -> 108053 | J54: =N$8*F54 -> 0 | K54: =N$3*F54 -> 54021.89 | L54: =N$2*F54 -> 142500 | M54: 0 | N54: =ROUND((L54+J54+I54+K54+M54),0) + P54 -> 304575.36 | O54: =ROUND((N54*6% + N54 ),0) + P54 -> 322850.36 | P54: =P53+0.01 -> 0.36
A55: 3 amb | C55: 8ºA | D55: Campelo, Mariano | F55: 0.0164 | G55: 196800.37 | H55: =G55 -> 196800.37 | I55: =G55-H55 -> 0 | J55: =N$8*F55 -> 0 | K55: =N$3*F55 -> 93258.841 | L55: =N$2*F55 -> 246000 | M55: 0 | N55: =ROUND((L55+J55+I55+K55+M55),0) + P55 -> 339259.37 | O55: =ROUND((N55*6% + N55 ),0) + P55 -> 359615.37 | P55: =P54+0.01 -> 0.37
A56: 1 amb | C56: 8ºB | D56: Morvillo, Mariana Yanil | E56: Aylen | F56: 0.0072 | G56: 86400.38 | H56: =G56 -> 86400.38 | I56: =G56-H56 -> 0 | J56: =N$8*F56 -> 0 | K56: =N$3*F56 -> 40942.906 | L56: =N$2*F56 -> 108000 | M56: 0 | N56: =ROUND((L56+J56+I56+K56+M56),0) + P56 -> 148943.38 | O56: =ROUND((N56*6% + N56 ),0) + P56 -> 157880.38 | P56: =P55+0.01 -> 0.38
A57: 3 amb | C57: 8ºC | D57: Frontale, Federico Carlos | Celentano, Alejandra Verónica | F57: 0.0173 | G57: 246758.39 | H57: 0 | I57: =G57-H57 -> 246758.39 | J57: =N$8*F57 -> 0 | K57: =N$3*F57 -> 98376.704 | L57: =N$2*F57 -> 259500 | M57: 0 | N57: =ROUND((L57+J57+I57+K57+M57),0) + P57 -> 604635.39 | O57: =ROUND((N57*6% + N57 ),0) + P57 -> 640914.39 | P57: =P56+0.01 -> 0.39
A58: 2 amb | C58: 8ºD | D58: Argul, Sergio Walter - Taboada, María Paz | E58: Nahuel | F58: 0.0094 | G58: 246785.4 | H58: =G58 -> 246785.4 | I58: =G58-H58 -> 0 | J58: =N$8*F58 -> 0 | K58: =N$3*F58 -> 53453.238 | L58: =N$2*F58 -> 141000 | M58: 0 | N58: =ROUND((L58+J58+I58+K58+M58),0) + P58 -> 194453.4 | O58: =ROUND((N58*6% + N58 ),0) + P58 -> 206121.4 | P58: =P57+0.01 -> 0.4
A59: 2 amb | C59: 8ºE | D59: Lorenzo, Sergio | F59: 0.0087 | G59: 252312.41 | H59: =459281-206049.41 -> 253231.59 | I59: =G59-H59 -> -919.18 | J59: =N$8*F59 -> 0 | K59: =N$3*F59 -> 49472.678 | L59: =N$2*F59 -> 130500 | M59: 0 | N59: =ROUND((L59+J59+I59+K59+M59),0) + P59 -> 179053.41 | O59: =ROUND((N59*6% + N59 ),0) + P59 -> 189797.41 | P59: =P58+0.01 -> 0.41 | R59: el de sergio
A60: 2 amb | C60: 8ºF | D60: Arias, Mariana Laura | F60: 0.0095 | G60: 114000.42 | H60: =G60 -> 114000.42 | I60: =G60-H60 -> 0 | J60: =N$8*F60 -> 0 | K60: =N$3*F60 -> 54021.89 | L60: =N$2*F60 -> 142500 | M60: 0 | N60: =ROUND((L60+J60+I60+K60+M60),0) + P60 -> 196522.42 | O60: =ROUND((N60*6% + N60 ),0) + P60 -> 208314.42 | P60: =P59+0.01 -> 0.42 | Q60: alonso sabrina eugenia
A61: 3 amb | C61: 9ºA | D61: Fanjul, Alejandro Rubén Marcelo | F61: 0.0164 | G61: 216800.43 | H61: =G61 -> 216800.43 | I61: =G61-H61 -> 0 | J61: =N$8*F61 -> 0 | K61: =N$3*F61 -> 93258.841 | L61: =N$2*F61 -> 246000 | M61: 0 | N61: =ROUND((L61+J61+I61+K61+M61),0) + P61 -> 339259.43 | O61: =ROUND((N61*6% + N61 ),0) + P61 -> 359615.43 | P61: =P60+0.01 -> 0.43
A62: 1 amb | C62: 9ºB | D62: Fanjul, Alejandro Rubén Marcelo | F62: 0.0072 | G62: 86400.44 | H62: =G62 -> 86400.44 | I62: =G62-H62 -> 0 | J62: =N$8*F62 -> 0 | K62: =N$3*F62 -> 40942.906 | L62: =N$2*F62 -> 108000 | M62: 0 | N62: =ROUND((L62+J62+I62+K62+M62),0) + P62 -> 148943.44 | O62: =ROUND((N62*6% + N62 ),0) + P62 -> 157880.44 | P62: =P61+0.01 -> 0.44
A63: 3 amb | C63: 9ºC | D63: Franchino, Mauro | F63: 0.0173 | G63: 207600.45 | H63: =G63 -> 207600.45 | I63: =G63-H63 -> 0 | J63: =N$8*F63 -> 0 | K63: =N$3*F63 -> 98376.704 | L63: =N$2*F63 -> 259500 | M63: 0 | N63: =ROUND((L63+J63+I63+K63+M63),0) + P63 -> 357877.45 | O63: =ROUND((N63*6% + N63 ),0) + P63 -> 379350.45 | P63: =P62+0.01 -> 0.45
A64: 2 amb | C64: 9ºD | D64: Cerra, Antonio Osvaldo | E64: Adrian | F64: 0.0094 | G64: 112800.46 | H64: 144382.46 | I64: =G64-H64 -> -31582 | J64: =N$8*F64 -> 0 | K64: =N$3*F64 -> 53453.238 | L64: =N$2*F64 -> 141000 | M64: 0 | N64: =ROUND((L64+J64+I64+K64+M64),0) + P64 -> 162871.46 | O64: =ROUND((N64*6% + N64 ),0) + P64 -> 172644.46 | P64: =P63+0.01 -> 0.46
A65: 2 amb | C65: 9ºE | D65: Dieci, Matias Orlando | F65: 0.0087 | G65: 104400.47 | H65: =120841.48-G99 -> 95361.67 | I65: =G65-H65 -> 9038.8 | J65: =N$8*F65 -> 0 | K65: =N$3*F65 -> 49472.678 | L65: =N$2*F65 -> 130500 | M65: 0 | N65: =ROUND((L65+J65+I65+K65+M65),0) + P65 -> 189011.47 | O65: =ROUND((N65*6% + N65 ),0) + P65 -> 200352.47 | P65: =P64+0.01 -> 0.47
A66: 2 amb | C66: 9ºF | D66: Rosales, Rubén Darío | F66: 0.0095 | G66: 114000.48 | H66: =G66 -> 114000.48 | I66: =G66-H66 -> 0 | J66: =N$8*F66 -> 0 | K66: =N$3*F66 -> 54021.89 | L66: =N$2*F66 -> 142500 | M66: 0 | N66: =ROUND((L66+J66+I66+K66+M66),0) + P66 -> 196522.48 | O66: =ROUND((N66*6% + N66 ),0) + P66 -> 208314.48 | P66: =P65+0.01 -> 0.48
A67: 3 amb | C67: 10ºA | D67: Puisys Guillermo Antonio | F67: 0.0164 | G67: 196800.49 | H67: =G67 -> 196800.49 | I67: =G67-H67 -> 0 | J67: =N$8*F67 -> 0 | K67: =N$3*F67 -> 93258.841 | L67: =N$2*F67 -> 246000 | M67: 0 | N67: =ROUND((L67+J67+I67+K67+M67),0) + P67 -> 339259.49 | O67: =ROUND((N67*6% + N67 ),0) + P67 -> 359615.49 | P67: =P66+0.01 -> 0.49
A68: 1 amb | C68: 10ºB | D68: Lange, Gustavo Daniel | F68: 0.0072 | G68: 86400.5 | H68: =G68 -> 86400.5 | I68: =G68-H68 -> 0 | J68: =N$8*F68 -> 0 | K68: =N$3*F68 -> 40942.906 | L68: =N$2*F68 -> 108000 | M68: 0 | N68: =ROUND((L68+J68+I68+K68+M68),0) + P68 -> 148943.5 | O68: =ROUND((N68*6% + N68 ),0) + P68 -> 157880.5 | P68: =P67+0.01 -> 0.5
A69: 3 amb | C69: 10ºC | D69: Espósito, Franco Ezequiel | F69: 0.0173 | G69: 220057.51 | H69: =G69 -> 220057.51 | I69: =G69-H69 -> 0 | J69: =N$8*F69 -> 0 | K69: =N$3*F69 -> 98376.704 | L69: =N$2*F69 -> 259500 | M69: 20000 | N69: =ROUND((L69+J69+I69+K69+M69),0) + P69 -> 377877.51 | O69: =ROUND((N69*6% + N69 ),0) + P69 -> 400550.51 | P69: =P68+0.01 -> 0.51
A70: 2 amb | C70: 10ºD | D70: Lobato, Lorena - Vega, Maximiliano | F70: 0.0094 | G70: 112800.52 | I70: =G70-H70 -> 112800.52 | J70: =N$8*F70 -> 0 | K70: =N$3*F70 -> 53453.238 | L70: =N$2*F70 -> 141000 | M70: 0 | N70: =ROUND((L70+J70+I70+K70+M70),0) + P70 -> 307254.52 | O70: =ROUND((N70*6% + N70 ),0) + P70 -> 325690.52 | P70: =P69+0.01 -> 0.52
A71: 2 amb | C71: 10ºE | D71: Sr propietario | F71: 0.0087 | G71: 104400.53 | H71: =G71 -> 104400.53 | I71: =G71-H71 -> 0 | J71: =N$8*F71 -> 0 | K71: =N$3*F71 -> 49472.678 | L71: =N$2*F71 -> 130500 | M71: 0 | N71: =ROUND((L71+J71+I71+K71+M71),0) + P71 -> 179973.53 | O71: =ROUND((N71*6% + N71 ),0) + P71 -> 190772.53 | P71: =P70+0.01 -> 0.53 | R71: mariano hecimovic
A72: 2 amb | C72: 10ºF | D72: Ramos, Sergio Eugenio | F72: 0.0095 | G72: 105244.54 | I72: =G72-H72 -> 105244.54 | J72: =N$8*F72 -> 0 | K72: =N$3*F72 -> 54021.89 | L72: =N$2*F72 -> 142500 | M72: 0 | N72: =ROUND((L72+J72+I72+K72+M72),0) + P72 -> 301766.54 | O72: =ROUND((N72*6% + N72 ),0) + P72 -> 319873.54 | P72: =P71+0.01 -> 0.54
A73: 4 amb | C73: 11ºA/B | D73: Mosquera, Julio Rodolfo | Cuzzolino, Daniela Carol | F73: 0.0235 | G73: 302000.55 | H73: =G73 -> 302000.55 | I73: =G73-H73 -> 0 | J73: =N$8*F73 -> 0 | K73: =N$3*F73 -> 133633.1 | L73: =N$2*F73 -> 352500 | M73: 0 | N73: =ROUND((L73+J73+I73+K73+M73),0) + P73 -> 486133.55 | O73: =ROUND((N73*6% + N73 ),0) + P73 -> 515302.55 | P73: =P72+0.01 -> 0.55
A74: 3 amb | C74: 11ºC | D74: Silvestre Villarruel Eduardo | F74: 0.0173 | G74: 207600.56 | H74: =G74 -> 207600.56 | I74: =G74-H74 -> 0 | J74: =N$8*F74 -> 0 | K74: =N$3*F74 -> 98376.704 | L74: =N$2*F74 -> 259500 | M74: 0 | N74: =ROUND((L74+J74+I74+K74+M74),0) + P74 -> 357877.56 | O74: =ROUND((N74*6% + N74 ),0) + P74 -> 379350.56 | P74: =P73+0.01 -> 0.56
A75: 2 amb | C75: 11ºD | D75: Sr. Propietario | F75: 0.0094 | G75: 112800.57 | H75: =168002.15-H89-H105 -> 112800.57 | I75: =G75-H75 -> 0 | J75: =N$8*F75 -> 0 | K75: =N$3*F75 -> 53453.238 | L75: =N$2*F75 -> 141000 | M75: 0 | N75: =ROUND((L75+J75+I75+K75+M75),0) + P75 -> 194453.57 | O75: =ROUND((N75*6% + N75 ),0) + P75 -> 206121.57 | P75: =P74+0.01 -> 0.57
A76: 2 amb | C76: 11ºE | D76: Argúl, Adrián Norberto | E76: Lara | F76: 0.0087 | G76: 510642.58 | H76: 230616.58 | I76: =G76-H76 -> 280026 | J76: =N$8*F76 -> 0 | K76: =N$3*F76 -> 49472.678 | L76: =N$2*F76 -> 130500 | M76: 0 | N76: =ROUND((L76+J76+I76+K76+M76),0) + P76 -> 459999.58 | O76: =ROUND((N76*6% + N76 ),0) + P76 -> 487600.58 | P76: =P75+0.01 -> 0.58
A77: 2 amb | C77: 11ºF | D77: Lobato, Lorena - Vega, Maximiliano | F77: 0.0095 | G77: 114000.59 | I77: =G77-H77 -> 114000.59 | J77: =N$8*F77 -> 0 | K77: =N$3*F77 -> 54021.89 | L77: =N$2*F77 -> 142500 | M77: 0 | N77: =ROUND((L77+J77+I77+K77+M77),0) + P77 -> 310522.59 | O77: =ROUND((N77*6% + N77 ),0) + P77 -> 329154.59 | P77: =P76+0.01 -> 0.59
A78: 4 amb | C78: 12ºA/B | D78: Luciano, Carmen Veronica - Rey, Javier Pablo | F78: 0.0235 | G78: 281957.6 | H78: =191411.6*2-52822.6 -> 330000.6 | I78: =G78-H78 -> -48043 | J78: =N$8*F78 -> 0 | K78: =N$3*F78 -> 133633.1 | L78: =N$2*F78 -> 352500 | M78: 0 | N78: =ROUND((L78+J78+I78+K78+M78),0) + P78 -> 438090.6 | O78: =ROUND((N78*6% + N78 ),0) + P78 -> 464376.6 | P78: =P77+0.01 -> 0.6
A79: 3 amb | C79: 12ºC | D79: Hernandez, Marisa Beatriz - Hernandez, Adrian Jose | F79: 0.0173 | G79: 207600.61 | H79: =G79 -> 207600.61 | I79: =G79-H79 -> 0 | J79: =N$8*F79 -> 0 | K79: =N$3*F79 -> 98376.704 | L79: =N$2*F79 -> 259500 | M79: 0 | N79: =ROUND((L79+J79+I79+K79+M79),0) + P79 -> 357877.61 | O79: =ROUND((N79*6% + N79 ),0) + P79 -> 379350.61 | P79: =P78+0.01 -> 0.61
A80: 2 amb | C80: 12ºD | D80: Morini, Micaela | F80: 0.0094 | G80: 699395.62 | I80: =G80-H80 -> 699395.62 | J80: =N$8*F80 -> 0 | K80: =N$3*F80 -> 53453.238 | L80: =N$2*F80 -> 141000 | M80: 20000 | N80: =ROUND((L80+J80+I80+K80+M80),0) + P80 -> 913849.62 | O80: =ROUND((N80*6% + N80 ),0) + P80 -> 968681.62 | P80: =P79+0.01 -> 0.62
A81: 2 amb | C81: 12ºE | D81: Armerding, Jorge | E81: Agustina | F81: 0.0087 | G81: 104400.63 | H81: =G81 -> 104400.63 | I81: =G81-H81 -> 0 | J81: =N$8*F81 -> 0 | K81: =N$3*F81 -> 49472.678 | L81: =N$2*F81 -> 130500 | M81: 0 | N81: =ROUND((L81+J81+I81+K81+M81),0) + P81 -> 179973.63 | O81: =ROUND((N81*6% + N81 ),0) + P81 -> 190772.63 | P81: =P80+0.01 -> 0.63
A82: 2 amb | C82: 12ºF | D82: Bilyj, Josefa Catalina | F82: 0.0095 | G82: 111080.64 | H82: =G82 -> 111080.64 | I82: =G82-H82 -> 0 | J82: =N$8*F82 -> 0 | K82: =N$3*F82 -> 54021.89 | L82: =N$2*F82 -> 142500 | M82: 0 | N82: =ROUND((L82+J82+I82+K82+M82),0) + P82 -> 196522.64 | O82: =ROUND((N82*6% + N82 ),0) + P82 -> 208314.64 | P82: =P81+0.01 -> 0.64 | Q82: Laura Quintas Perez
A83: 4 amb | C83: 13ºA/B | D83: Gazzaneo, Francisco | F83: 0.0235 | G83: 282000.65 | H83: =G83 -> 282000.65 | I83: =G83-H83 -> 0 | J83: =N$8*F83 -> 0 | K83: =N$3*F83 -> 133633.1 | L83: =N$2*F83 -> 352500 | M83: 0 | N83: =ROUND((L83+J83+I83+K83+M83),0) + P83 -> 486133.65 | O83: =ROUND((N83*6% + N83 ),0) + P83 -> 515302.65 | P83: =P82+0.01 -> 0.65
A84: 3 amb | C84: 13ºC | D84: Argentino, Javier Leonardo | F84: 0.0173 | G84: 207600.66 | H84: =G84 -> 207600.66 | I84: =G84-H84 -> 0 | J84: =N$8*F84 -> 0 | K84: =N$3*F84 -> 98376.704 | L84: =N$2*F84 -> 259500 | M84: 45375 | N84: =ROUND((L84+J84+I84+K84+M84),0) + P84 -> 403252.66 | O84: =ROUND((N84*6% + N84 ),0) + P84 -> 427448.66 | P84: =P83+0.01 -> 0.66
A85: 2 amb | C85: 13ºD | D85: Scardigno, Gabriela Susana - Ripoll, Luis Alberto | F85: 0.0094 | G85: 112800.67 | H85: =G85 -> 112800.67 | I85: =G85-H85 -> 0 | J85: =N$8*F85 -> 0 | K85: =N$3*F85 -> 53453.238 | L85: =N$2*F85 -> 141000 | M85: 0 | N85: =ROUND((L85+J85+I85+K85+M85),0) + P85 -> 194453.67 | O85: =ROUND((N85*6% + N85 ),0) + P85 -> 206121.67 | P85: =P84+0.01 -> 0.67
A86: 2 amb | C86: 13ºE | D86: Quiñones, Carlos Eduardo | F86: 0.0087 | G86: 104400.68 | H86: =G86 -> 104400.68 | I86: =G86-H86 -> 0 | J86: =N$8*F86 -> 0 | K86: =N$3*F86 -> 49472.678 | L86: =N$2*F86 -> 130500 | M86: 0 | N86: =ROUND((L86+J86+I86+K86+M86),0) + P86 -> 179973.68 | O86: =ROUND((N86*6% + N86 ),0) + P86 -> 190772.68 | P86: =P85+0.01 -> 0.68
A87: 2 amb | C87: 13ºF | D87: Mosquera, José Elias | F87: 0.0095 | G87: 114000.69 | H87: =G87 -> 114000.69 | I87: =G87-H87 -> 0 | J87: =N$8*F87 -> 0 | K87: =N$3*F87 -> 54021.89 | L87: =N$2*F87 -> 142500 | M87: 0 | N87: =ROUND((L87+J87+I87+K87+M87),0) + P87 -> 196522.69 | O87: =ROUND((N87*6% + N87 ),0) + P87 -> 208314.69 | P87: =P86+0.01 -> 0.69
C88: COCH 1 | D88: Osipowicz, Ariel Marcelo | F88: 0.0023 | G88: 27600.7 | H88: =G88 -> 27600.7 | I88: =G88-H88 -> 0 | J88: =N$8*F88 -> 0 | K88: =N$3*F88 -> 13078.984 | L88: =N$2*F88 -> 34500 | M88: 0 | N88: =ROUND((L88+J88+I88+K88+M88),0) + P88 -> 47579.7 | O88: =ROUND((N88*6% + N88 ),0) + P88 -> 50434.7 | P88: =P87+0.01 -> 0.7
C89: COCH 2 | D89: Sr propietario | F89: 0.0023 | G89: 27600.71 | H89: =G89 -> 27600.71 | I89: =G89-H89 -> 0 | J89: =N$8*F89 -> 0 | K89: =N$3*F89 -> 13078.984 | L89: =N$2*F89 -> 34500 | M89: 0 | N89: =ROUND((L89+J89+I89+K89+M89),0) + P89 -> 47579.71 | O89: =ROUND((N89*6% + N89 ),0) + P89 -> 50434.71 | P89: =P88+0.01 -> 0.71
C90: COCH 3 | D90: Paes, Yazmin Luciana | F90: 0.0023 | G90: 27600.72 | H90: =G90 -> 27600.72 | I90: =G90-H90 -> 0 | J90: =N$8*F90 -> 0 | K90: =N$3*F90 -> 13078.984 | L90: =N$2*F90 -> 34500 | M90: 0 | N90: =ROUND((L90+J90+I90+K90+M90),0) + P90 -> 47579.72 | O90: =ROUND((N90*6% + N90 ),0) + P90 -> 50435.72 | P90: =P89+0.01 -> 0.72
C91: COCH 4 | D91: Puisys Guillermo Antonio | F91: 0.0023 | G91: 27600.73 | H91: =G91 -> 27600.73 | I91: =G91-H91 -> 0 | J91: =N$8*F91 -> 0 | K91: =N$3*F91 -> 13078.984 | L91: =N$2*F91 -> 34500 | M91: 0 | N91: =ROUND((L91+J91+I91+K91+M91),0) + P91 -> 47579.73 | O91: =ROUND((N91*6% + N91 ),0) + P91 -> 50435.73 | P91: =P90+0.01 -> 0.73
C92: COCH 5 | D92: Arias, Mariana Laura | F92: 0.0023 | G92: 27600.74 | H92: =G92 -> 27600.74 | I92: =G92-H92 -> 0 | J92: =N$8*F92 -> 0 | K92: =N$3*F92 -> 13078.984 | L92: =N$2*F92 -> 34500 | M92: 0 | N92: =ROUND((L92+J92+I92+K92+M92),0) + P92 -> 47579.74 | O92: =ROUND((N92*6% + N92 ),0) + P92 -> 50435.74 | P92: =P91+0.01 -> 0.74 | Q92: alonso sabrina eugenia
C93: COCH 6 | D93: Dimito, Vicente Argentino - Cerantes , Mabel | F93: 0.0023 | G93: 25479.75 | I93: =G93-H93 -> 25479.75 | J93: =N$8*F93 -> 0 | K93: =N$3*F93 -> 13078.984 | L93: =N$2*F93 -> 34500 | M93: 0 | N93: =ROUND((L93+J93+I93+K93+M93),0) + P93 -> 73059.75 | O93: =ROUND((N93*6% + N93 ),0) + P93 -> 77443.75 | P93: =P92+0.01 -> 0.75
C94: COCH 7 | D94: Campelo, Mariano | F94: 0.0023 | G94: 27600.76 | H94: =G94 -> 27600.76 | I94: =G94-H94 -> 0 | J94: =N$8*F94 -> 0 | K94: =N$3*F94 -> 13078.984 | L94: =N$2*F94 -> 34500 | M94: 0 | N94: =ROUND((L94+J94+I94+K94+M94),0) + P94 -> 47579.76 | O94: =ROUND((N94*6% + N94 ),0) + P94 -> 50435.76 | P94: =P93+0.01 -> 0.76
C95: COCH 8 | D95: Campelo, Mariano | F95: 0.0023 | G95: 27600.77 | H95: =G95 -> 27600.77 | I95: =G95-H95 -> 0 | J95: =N$8*F95 -> 0 | K95: =N$3*F95 -> 13078.984 | L95: =N$2*F95 -> 34500 | M95: 0 | N95: =ROUND((L95+J95+I95+K95+M95),0) + P95 -> 47579.77 | O95: =ROUND((N95*6% + N95 ),0) + P95 -> 50435.77 | P95: =P94+0.01 -> 0.77
C96: COCH 9 | D96: Gazzaneo, Francisco | F96: 0.0023 | G96: 27600.78 | H96: =G96 -> 27600.78 | I96: =G96-H96 -> 0 | J96: =N$8*F96 -> 0 | K96: =N$3*F96 -> 13078.984 | L96: =N$2*F96 -> 34500 | M96: 0 | N96: =ROUND((L96+J96+I96+K96+M96),0) + P96 -> 47579.78 | O96: =ROUND((N96*6% + N96 ),0) + P96 -> 50435.78 | P96: =P95+0.01 -> 0.78
C97: COCH 10 | D97: Cerra, Antonio Osvaldo | F97: 0.0023 | G97: 276782.79 | I97: =G97-H97 -> 276782.79 | J97: =N$8*F97 -> 0 | K97: =N$3*F97 -> 13078.984 | L97: =N$2*F97 -> 34500 | M97: 0 | N97: =ROUND((L97+J97+I97+K97+M97),0) + P97 -> 324362.79 | O97: =ROUND((N97*6% + N97 ),0) + P97 -> 343825.79 | P97: =P96+0.01 -> 0.79
C98: COCH 11 | D98: Osipowicz, Ariel Marcelo | F98: 0.0023 | G98: 27600.8 | H98: =G98 -> 27600.8 | I98: =G98-H98 -> 0 | J98: =N$8*F98 -> 0 | K98: =N$3*F98 -> 13078.984 | L98: =N$2*F98 -> 34500 | M98: 0 | N98: =ROUND((L98+J98+I98+K98+M98),0) + P98 -> 47579.8 | O98: =ROUND((N98*6% + N98 ),0) + P98 -> 50435.8 | P98: =P97+0.01 -> 0.8
C99: COCH 12 | D99: Dieci, Matias Orlando | F99: 0.0023 | G99: 25479.81 | H99: =G99 -> 25479.81 | I99: =G99-H99 -> 0 | J99: =N$8*F99 -> 0 | K99: =N$3*F99 -> 13078.984 | L99: =N$2*F99 -> 34500 | M99: 0 | N99: =ROUND((L99+J99+I99+K99+M99),0) + P99 -> 47579.81 | O99: =ROUND((N99*6% + N99 ),0) + P99 -> 50435.81 | P99: =P98+0.01 -> 0.81
C100: COCH 13 | D100: Scardigno, Gabriela Susana - Ripoli, Luis Alberto | F100: 0.0023 | G100: 27600.82 | H100: =G100 -> 27600.82 | I100: =G100-H100 -> 0 | J100: =N$8*F100 -> 0 | K100: =N$3*F100 -> 13078.984 | L100: =N$2*F100 -> 34500 | M100: 0 | N100: =ROUND((L100+J100+I100+K100+M100),0) + P100 -> 47579.82 | O100: =ROUND((N100*6% + N100 ),0) + P100 -> 50435.82 | P100: =P99+0.01 -> 0.82
C101: COCH 14 | D101: Fontale Federico Carlos - Celentano Alejandra Veronica | F101: 0.0023 | G101: 27600.83 | I101: =G101-H101 -> 27600.83 | J101: =N$8*F101 -> 0 | K101: =N$3*F101 -> 13078.984 | L101: =N$2*F101 -> 34500 | M101: 0 | N101: =ROUND((L101+J101+I101+K101+M101),0) + P101 -> 75180.83 | O101: =ROUND((N101*6% + N101 ),0) + P101 -> 79692.83 | P101: =P100+0.01 -> 0.83
C102: COCH 15 | D102: Hernandez, Marisa Beatriz - Hernandez, Adrian Jose | F102: 0.0023 | G102: 27600.84 | H102: =G102 -> 27600.84 | I102: =G102-H102 -> 0 | J102: =N$8*F102 -> 0 | K102: =N$3*F102 -> 13078.984 | L102: =N$2*F102 -> 34500 | M102: 0 | N102: =ROUND((L102+J102+I102+K102+M102),0) + P102 -> 47579.84 | O102: =ROUND((N102*6% + N102 ),0) + P102 -> 50435.84 | P102: =P101+0.01 -> 0.84
C103: COCH 16 | D103: Mesa, Mariano | F103: 0.0023 | G103: 27600.85 | H103: =G103 -> 27600.85 | I103: =G103-H103 -> 0 | J103: =N$8*F103 -> 0 | K103: =N$3*F103 -> 13078.984 | L103: =N$2*F103 -> 34500 | M103: 0 | N103: =ROUND((L103+J103+I103+K103+M103),0) + P103 -> 47579.85 | O103: =ROUND((N103*6% + N103 ),0) + P103 -> 50435.85 | P103: =P102+0.01 -> 0.85
C104: COCH 17 | D104: Espósito, Franco Ezequiel | F104: 0.0023 | G104: 29257.86 | H104: =G104 -> 29257.86 | I104: =G104-H104 -> 0 | J104: =N$8*F104 -> 0 | K104: =N$3*F104 -> 13078.984 | L104: =N$2*F104 -> 34500 | M104: 0 | N104: =ROUND((L104+J104+I104+K104+M104),0) + P104 -> 47579.86 | O104: =ROUND((N104*6% + N104 ),0) + P104 -> 50435.86 | P104: =P103+0.01 -> 0.86
...

Sheet ARBA
A1: IMPORTANTE: RESPETAR CENTAVOS AL ABONAR.
A3: Quienes adeudan ARBA deben abonar el monto coloreado en ROSADO si es que en el trancurso del mes 3 y 4 del 2026 no abonaron ninguna cuota.
A4: DPTOS | B4: COCH | C4: Propietario | D4: (%) | E4: ARBA REVALUO | F4: POSESION | G4: TOTAL A ABONAR HASTA | H4: TOTAL A ABONAR 1ERA CUOTA - VTO. 31/03 | I4: TOTAL A ABONAR 2DA CUOTA - VTO. 30/04 | J4: A PAGAR PROPIETARIO | L4: ABONADO POR PROPIETARIO | M4: AL PROPIETARIO LE RESTA ABONAR | N4: A PAGAR CONSTRUCTORA | O4: TOTAL
A7: LOC 1 | C7: Fernandez, Cristian | D7: 0.0108 | E7: 282914.38 | F7: 45856 | G7: -197064.48 | H7: =J7/2 -> 98532.35 | I7: =H7 -> 98532.35 | J7: =ROUND((-G7),0)+P7 -> 197064.7 | K7: -85849.897 | L7: =H7 -> 98532.35 | M7: 98532.35 | N7: =-K7 -> 85849.897 | O7: =ROUND((J7+N7),0) + P7 -> 282915.7 | P7: 0.7
A8: LOC 2 | C8: Frigidi Guillermo Ariel | D8: 0.0128 | E8: 335305.93 | F8: 46001 | G8: -34751.379 | H8: =J8/2 -> 17375.855 | I8: =H8 -> 17375.855 | J8: =ROUND((-G8),0)+P8 -> 34751.71 | K8: -300554.55 | M8: =IF(L8=H8,I8,J8) -> 34751.71 | N8: =-K8 -> 300554.55 | O8: =ROUND((J8+N8),0) + P8 -> 335306.71 | P8: =P7+0.01 -> 0.71
A9: LOC 3 | C9: Patricia Mainieri | D9: 0.0121 | E9: 316968.89 | F9: 45856 | G9: -220785.21 | H9: =J9/2 -> 110392.86 | I9: =H9 -> 110392.86 | J9: =ROUND((-G9),0)+P9 -> 220785.72 | K9: -96183.681 | M9: =IF(L9=H9,I9,J9) -> 220785.72 | N9: =-K9 -> 96183.681 | O9: =ROUND((J9+N9),0) + P9 -> 316969.72 | P9: =P8+0.01 -> 0.72
A10: LOC 4 | C10: Cordero, Leandro Emanuel - Orona, Victoria | D10: 0.0149 | E10: 390317.06 | F10: 45856 | G10: -271876 | H10: =J10/2 -> 135938.36 | I10: =H10 -> 135938.36 | J10: =ROUND((-G10),0)+P10 -> 271876.73 | K10: -118441.06 | M10: =IF(L10=H10,I10,J10) -> 271876.73 | N10: =-K10 -> 118441.06 | O10: =ROUND((J10+N10),0) + P10 -> 390318.73 | P10: =P9+0.01 -> 0.73
A11: LOC 5 | C11: Orsi, José Luis - Fernández, Cristián Gabriel | D11: 0.0175 | E11: 458426.08 | F11: 45856 | G11: -319317.45 | H11: =J11/2 -> 159658.87 | I11: =H11 -> 159658.87 | J11: =ROUND((-G11),0)+P11 -> 319317.74 | K11: -139108.63 | L11: 159659 | M11: 159658.87 | N11: =-K11 -> 139108.63 | O11: =ROUND((J11+N11),0) + P11 -> 458426.74 | P11: =P10+0.01 -> 0.74
A12: 2ºA | B12: 25 | C12: Franco, Lucas Fabián | D12: 0.0212 | E12: 555350.45 | F12: 45777 | G12: -519626.97 | H12: =ROUND((J12/2),0)+P12 -> 259814.01 | I12: =H12 -> 259814.01 | J12: =ROUND((-G12),0)+P12 -> 519627.01 | K12: -35723.479 | M12: 0 | N12: =-K12 -> 35723.479 | O12: =ROUND((J12+N12),0) + P12 -> 555350.01 | P12: 0.01
A13: 2ºB | C13: Martinez, Diego | D13: 0.0084 | E13: 220044.52 | F13: 45775 | G13: -206492.25 | H13: =ROUND((J13/2),0)+P13 -> 103246.02 | I13: =H13 -> 103246.02 | J13: =ROUND((-G13),0)+P13 -> 206492.02 | K13: -13552.263 | L13: =H13 -> 103246.02 | M13: 0 | N13: =-K13 -> 13552.263 | O13: =ROUND((J13+N13),0) + P13 -> 220044.02 | P13: =P12+0.01 -> 0.02
A14: 2ºC | B14: 22 | C14: Rodriguez, Carlos Alberto Miguel | D14: 0.0225 | E14: 589404.96 | F14: 45770 | G14: -557137.66 | H14: =ROUND((J14/2),0)+P14 -> 278569.03 | I14: =H14 -> 278569.03 | J14: =ROUND((-G14),0)+P14 -> 557138.03 | K14: -32267.294 | L14: =H14 -> 278569.03 | M14: 0 | N14: =-K14 -> 32267.294 | O14: =ROUND((J14+N14),0) + P14 -> 589405.03 | P14: =P13+0.01 -> 0.03
A15: 2ºD | B15: 29-30 | C15: Ferraro, José | D15: 0.014 | E15: 366740.86 | F15: 45805 | G15: -327282.74 | H15: =ROUND((J15/2),0)+P15 -> 163642.04 | I15: =H15 -> 163642.04 | J15: =ROUND((-G15),0)+P15 -> 327283.04 | K15: -39458.12 | L15: =J15 -> 327283.04 | M15: 0 | N15: =-K15 -> 39458.12 | O15: =ROUND((J15+N15),0) + P15 -> 366741.04 | P15: =P14+0.01 -> 0.04
A16: 2ºE | C16: Dieci, Matias Orlando | D16: 0.0087 | E16: 227903.25 | F16: 45800 | G16: -206069.05 | H16: =ROUND((J16/2),0)+P16 -> 103035.05 | I16: =H16 -> 103035.05 | J16: =ROUND((-G16),0)+P16 -> 206069.05 | K16: -21834.202 | L16: =J16 -> 206069.05 | M16: 0 | N16: =-K16 -> 21834.202 | O16: =ROUND((J16+N16),0) + P16 -> 227903.05 | P16: =P15+0.01 -> 0.05
A17: 2ºF | B17: 34-39 | C17: Ferraro, Jose | D17: 0.0141 | E17: 369360.44 | F17: 45805 | G17: -329620.48 | H17: =ROUND((J17/2),0)+P17 -> 164810.06 | I17: =H17 -> 164810.06 | J17: =ROUND((-G17),0)+P17 -> 329620.06 | K17: -39739.963 | L17: =J17 -> 329620.06 | M17: 0 | N17: =-K17 -> 39739.963 | O17: =ROUND((J17+N17),0) + P17 -> 369360.06 | P17: =P16+0.01 -> 0.06
A18: 3ºA | B18: 37-38 | C18: Ferraro, Jose - ------ALEJANDRO | D18: 0.0211 | E18: 552730.87 | F18: 45805 | G18: -493261.85 | H18: =ROUND((J18/2),0)+P18 -> 246631.07 | I18: =H18 -> 246631.07 | J18: =ROUND((-G18),0)+P18 -> 493262.07 | K18: -59469.023 | L18: =J18 -> 493262.07 | M18: 0 | N18: =-K18 -> 59469.023 | O18: =ROUND((J18+N18),0) + P18 -> 552731.07 | P18: =P17+0.01 -> 0.07
A19: 3ºB | C19: Ayala, Roberto Adrian/BALDUZZI | D19: 0.0074 | E19: 193848.74 | F19: 45839 | G19: -147681.21 | H19: =ROUND((J19/2),0)+P19 -> 73841.08 | I19: =H19 -> 73841.08 | J19: =ROUND((-G19),0)+P19 -> 147681.08 | K19: -46167.53 | L19: =H19 -> 73841.08 | M19: 0 | N19: =-K19 -> 46167.53 | O19: =ROUND((J19+N19),0) + P19 -> 193849.08 | P19: =P18+0.01 -> 0.08
A20: 3ºC | C20: Ferraro, Jose | D20: 0.0179 | E20: 468904.39 | F20: 45805 | G20: -418454.36 | H20: =ROUND((J20/2),0)+P20 -> 209227.09 | I20: =H20 -> 209227.09 | J20: =ROUND((-G20),0)+P20 -> 418454.09 | K20: -50450.024 | L20: =J20 -> 418454.09 | M20: 0 | N20: =-K20 -> 50450.024 | O20: =ROUND((J20+N20),0) + P20 -> 468904.09 | P20: =P19+0.01 -> 0.09
A21: 3ºD | C21: Ayala, Roberto Adrian | D21: 0.0094 | E21: 246240.29 | F21: 45839 | G21: -187595.05 | H21: =ROUND((J21/2),0)+P21 -> 93798.1 | I21: =H21 -> 93798.1 | J21: =ROUND((-G21),0)+P21 -> 187595.1 | K21: -58645.241 | L21: =J21 -> 187595.1 | M21: 0 | N21: =-K21 -> 58645.241 | O21: =ROUND((J21+N21),0) + P21 -> 246240.1 | P21: =P20+0.01 -> 0.1
A22: 3ºE | C22: Ayala, Roberto Adrian /CALZETTA | D22: 0.0087 | E22: 227903.25 | F22: 45839 | G22: -173625.21 | H22: =ROUND((J22/2),0)+P22 -> 86813.11 | I22: =H22 -> 86813.11 | J22: =ROUND((-G22),0)+P22 -> 173625.11 | K22: -54278.042 | L22: =J22 -> 173625.11 | M22: 0 | N22: =-K22 -> 54278.042 | O22: =ROUND((J22+N22),0) + P22 -> 227903.11 | P22: =P21+0.01 -> 0.11
A23: 3ºF | C23: Ayala, Roberto Adrian | D23: 0.0095 | E23: 248859.87 | F23: 45839 | G23: -189590.74 | H23: =ROUND((J23/2),0)+P23 -> 94796.12 | I23: =H23 -> 94796.12 | J23: =ROUND((-G23),0)+P23 -> 189591.12 | K23: -59269.126 | M23: =IF(L23=H23,I23,J23) -> 189591.12 | N23: =-K23 -> 59269.126 | O23: =ROUND((J23+N23),0) + P23 -> 248860.12 | P23: =P22+0.01 -> 0.12
A24: 4ºA | C24: Barral, Carlos Daniel | D24: 0.0164 | E24: 429610.72 | F24: 45775 | G24: -403151.54 | H24: =ROUND((J24/2),0)+P24 -> 201576.13 | I24: =H24 -> 201576.13 | J24: =ROUND((-G24),0)+P24 -> 403152.13 | K24: -26459.181 | L24: =J24 -> 403152.13 | M24: 0 | N24: =-K24 -> 26459.181 | O24: =ROUND((J24+N24),0) + P24 -> 429611.13 | P24: =P23+0.01 -> 0.13
A25: 4ºB | C25: Calzetta, Gabriel Andrés Felipe | D25: 0.0073 | E25: 191229.16 | F25: 45800 | G25: -172908.51 | H25: =ROUND((J25/2),0)+P25 -> 86455.14 | I25: =H25 -> 86455.14 | J25: =ROUND((-G25),0)+P25 -> 172909.14 | K25: -18320.652 | L25: =H25 -> 86455.14 | M25: =IF(L25=H25,I25,J25) -> 86455.14 | N25: =-K25 -> 18320.652 | O25: =ROUND((J25+N25),0) + P25 -> 191230.14 | P25: =P24+0.01 -> 0.14
A26: 4ºC | B26: 1-11 | C26: Osipowicz, Ariel Marcelo | D26: 0.022 | E26: 576307.07 | F26: 45775 | G26: -540813.05 | H26: =ROUND((J26/2),0)+P26 -> 270407.15 | I26: =H26 -> 270407.15 | J26: =ROUND((-G26),0)+P26 -> 540813.15 | K26: -35494.023 | L26: =H26 -> 270407.15 | M26: 0 | N26: =-K26 -> 35494.023 | O26: =ROUND((J26+N26),0) + P26 -> 576307.15 | P26: =P25+0.01 -> 0.15
A27: 4ºD | C27: Ayala, Roberto Adrian | D27: 0.0094 | E27: 246240.29 | F27: 45839 | G27: -187595.05 | H27: =ROUND((J27/2),0)+P27 -> 93798.16 | I27: =H27 -> 93798.16 | J27: =ROUND((-G27),0)+P27 -> 187595.16 | K27: -58645.241 | M27: =IF(L27=H27,I27,J27) -> 187595.16 | N27: =-K27 -> 58645.241 | O27: =ROUND((J27+N27),0) + P27 -> 246240.16 | P27: =P26+0.01 -> 0.16 | Q27: Pablo Amarilla
A28: 4ºE | C28: Ayala, Roberto Adrian/SKARLATIUK | D28: 0.0087 | E28: 227903.25 | F28: 45839 | G28: -173625.21 | H28: =ROUND((J28/2),0)+P28 -> 86813.17 | I28: =H28 -> 86813.17 | J28: =ROUND((-G28),0)+P28 -> 173625.17 | K28: -54278.042 | L28: =H28 -> 86813.17 | M28: 0 | N28: =-K28 -> 54278.042 | O28: =ROUND((J28+N28),0) + P28 -> 227903.17 | P28: =P27+0.01 -> 0.17
A29: 4ºF | C29: Ayala, Roberto Adrian | D29: 0.0095 | E29: 248859.87 | F29: 45839 | G29: -189590.74 | H29: =ROUND((J29/2),0)+P29 -> 94796.18 | I29: =H29 -> 94796.18 | J29: =ROUND((-G29),0)+P29 -> 189591.18 | K29: -59269.126 | M29: =IF(L29=H29,I29,J29) -> 189591.18 | N29: =-K29 -> 59269.126 | O29: =ROUND((J29+N29),0) + P29 -> 248860.18 | P29: =P28+0.01 -> 0.18
A30: 5ºA | C30: Chehab, Gabriel Adrian | D30: 0.0164 | E30: 429610.72 | F30: 45800 | G30: -388452 | H30: =ROUND((J30/2),0)+P30 -> 194226.19 | I30: =H30 -> 194226.19 | J30: =ROUND((-G30),0)+P30 -> 388452.19 | K30: -41158.726 | L30: =H30 -> 194226.19 | M30: 0 | N30: =-K30 -> 41158.726 | O30: =ROUND((J30+N30),0) + P30 -> 429611.19 | P30: =P29+0.01 -> 0.19 | Q30: Cochera 38
A31: 5ºB | B31: 16 | C31: Mesa, Mariano | D31: 0.0096 | E31: 251479.45 | F31: 45805 | G31: -224422.45 | H31: =ROUND((J31/2),0)+P31 -> 112211.2 | I31: =H31 -> 112211.2 | J31: =ROUND((-G31),0)+P31 -> 224422.2 | K31: -27056.996 | L31: =J31 -> 224422.2 | M31: 0 | N31: =-K31 -> 27056.996 | O31: =ROUND((J31+N31),0) + P31 -> 251479.2 | P31: =P30+0.01 -> 0.2
A32: 5ºC | B32: 6 | C32: Di Mito, Vicente Argentino - Serantes, Mabel | D32: 0.0197 | E32: 516056.79 | F32: 45805 | G32: -460533.57 | H32: =ROUND((J32/2),0)+P32 -> 230267.21 | I32: =H32 -> 230267.21 | J32: =ROUND((-G32),0)+P32 -> 460534.21 | K32: -55523.211 | M32: =IF(L32=H32,I32,J32) -> 460534.21 | N32: =-K32 -> 55523.211 | O32: =ROUND((J32+N32),0) + P32 -> 516057.21 | P32: =P31+0.01 -> 0.21
A33: 5ºD | C33: Ayala, Roberto Adrian | D33: 0.0094 | E33: 246240.29 | F33: 45839 | G33: -187595.05 | H33: =ROUND((J33/2),0)+P33 -> 93798.22 | I33: =H33 -> 93798.22 | J33: =ROUND((-G33),0)+P33 -> 187595.22 | K33: -58645.241 | M33: =IF(L33=H33,I33,J33) -> 187595.22 | N33: =-K33 -> 58645.241 | O33: =ROUND((J33+N33),0) + P33 -> 246240.22 | P33: =P32+0.01 -> 0.22 | Q33: Ayala paga 5D, 5F y 4F
A34: 5ºE | B34: 31 | C34: Ayala, Roberto Adrian/CALZETTA/ BASAEZ ROGELIO | D34: 0.011 | E34: 288153.53 | F34: 45839 | G34: -219526.13 | H34: =ROUND((J34/2),0)+P34 -> 109763.23 | I34: =H34 -> 109763.23 | J34: =ROUND((-G34),0)+P34 -> 219526.23 | K34: -68627.409 | M34: 0 | N34: =-K34 -> 68627.409 | O34: =ROUND((J34+N34),0) + P34 -> 288154.23 | P34: =P33+0.01 -> 0.23 | Q34: COCHERA 31
A35: 5ºF | C35: Ayala, Roberto Adrian | D35: 0.0095 | E35: 248859.87 | F35: 45839 | G35: -189590.74 | H35: =ROUND((J35/2),0)+P35 -> 94796.24 | I35: =H35 -> 94796.24 | J35: =ROUND((-G35),0)+P35 -> 189591.24 | K35: -59269.126 | M35: =IF(L35=H35,I35,J35) -> 189591.24 | N35: =-K35 -> 59269.126 | O35: =ROUND((J35+N35),0) + P35 -> 248860.24 | P35: =P34+0.01 -> 0.24
A36: 6ºA | B36: 28 | C36: Morandi, Victoria Ayelen | Calvo, Luciano Ezequiel | D36: 0.0187 | E36: 489861.01 | F36: 45786 | G36: -452316.22 | H36: =ROUND((J36/2),0)+P36 -> 226158.25 | I36: =H36 -> 226158.25 | J36: =ROUND((-G36),0)+P36 -> 452316.25 | K36: -37544.789 | L36: =H36 -> 226158.25 | M36: 0 | N36: =-K36 -> 37544.789 | O36: =ROUND((J36+N36),0) + P36 -> 489861.25 | P36: =P35+0.01 -> 0.25
A37: 6ºB | C37: GRIZEK RUBEN EDUARDO (ex Orellano) | D37: 0.0073 | E37: 191229.16 | F37: 45789 | G37: -175787.47 | H37: =ROUND((J37/2),0)+P37 -> 87894.26 | I37: =H37 -> 87894.26 | J37: =ROUND((-G37),0)+P37 -> 175787.26 | K37: -15441.693 | L37: =J37 -> 175787.26 | M37: 0 | N37: =-K37 -> 15441.693 | O37: =ROUND((J37+N37),0) + P37 -> 191229.26 | P37: =P36+0.01 -> 0.26
A38: 6ºC | B38: 33 | C38: Nuñez Leonel - Corrieri Giuliana | D38: 0.0197 | E38: 516056.79 | F38: 45793 | G38: -471560.19 | H38: =ROUND((J38/2),0)+P38 -> 235780.27 | I38: =H38 -> 235780.27 | J38: =ROUND((-G38),0)+P38 -> 471560.27 | K38: -44496.598 | L38: =H38 -> 235780.27 | M38: 0 | N38: =-K38 -> 44496.598 | O38: =ROUND((J38+N38),0) + P38 -> 516057.27 | P38: =P37+0.01 -> 0.27 | Q38: COCHERA 33 | R38: COCHERA 33
A39: 6ºD | B39: 44 | C39: ANCHIPI GASTON (Cedido x Hecimovic)Hecimovic, Mariano Hernán (Cedido x Lopez Malara, Ramiro Alejandro) | D39: 0.0117 | E39: 306490.58 | F39: 45800 | G39: -277127.34 | H39: =ROUND((J39/2),0)+P39 -> 138564.28 | I39: =H39 -> 138564.28 | J39: =ROUND((-G39),0)+P39 -> 277127.28 | K39: -29363.237 | M39: 238127.28 | N39: =-K39 -> 29363.237 | O39: =ROUND((J39+N39),0) + P39 -> 306491.28 | P39: =P38+0.01 -> 0.28
A40: 6ºE | C40: Dieci, Matias Orlando | D40: 0.0087 | E40: 227903.25 | F40: 45800 | G40: -206069.05 | H40: =ROUND((J40/2),0)+P40 -> 103035.29 | I40: =H40 -> 103035.29 | J40: =ROUND((-G40),0)+P40 -> 206069.29 | K40: -21834.202 | L40: =J40 -> 206069.29 | M40: 0 | N40: =-K40 -> 21834.202 | O40: =ROUND((J40+N40),0) + P40 -> 227903.29 | P40: =P39+0.01 -> 0.29
A41: 6ºF | C41: ALEXIA JOANA MAZZIA | D41: 0.0095 | E41: 248859.87 | F41: 45800 | G41: -225017.93 | H41: =ROUND((J41/2),0)+P41 -> 112509.3 | I41: =H41 -> 112509.3 | J41: =ROUND((-G41),0)+P41 -> 225018.3 | K41: -23841.945 | L41: =H41 -> 112509.3 | M41: 0 | N41: =-K41 -> 23841.945 | O41: =ROUND((J41+N41),0) + P41 -> 248860.3 | P41: =P40+0.01 -> 0.3
A42: 7ºA | B42: 7 | C42: Campelo, Mariano | D42: 0.0187 | E42: 489861.01 | F42: 45806 | G42: -435275.01 | H42: =ROUND((J42/2),0)+P42 -> 217638.31 | I42: =H42 -> 217638.31 | J42: =ROUND((-G42),0)+P42 -> 435275.31 | K42: -54586.004 | L42: =H42 -> 217638.31 | M42: 0 | N42: =-K42 -> 54586.004 | O42: =ROUND((J42+N42),0) + P42 -> 489861.31 | P42: =P41+0.01 -> 0.31
A43: 7ºB | B43: 3 | C43: Paes, Yazmin Luciana | D43: 0.0096 | E43: 251479.45 | F43: 45775 | G43: -235991.15 | H43: =ROUND((J43/2),0)+P43 -> 117996.32 | I43: =H43 -> 117996.32 | J43: =ROUND((-G43),0)+P43 -> 235991.32 | K43: -15488.301 | L43: =H43 -> 117996.32 | M43: 0 | N43: =-K43 -> 15488.301 | O43: =ROUND((J43+N43),0) + P43 -> 251480.32 | P43: =P42+0.01 -> 0.32
A44: 7ºC | B44: 24 | C44: Gonzalez Fedullo, Roxana y Valeria | D44: 0.0197 | E44: 516056.79 | F44: 45793 | G44: -471560.19 | H44: =ROUND((J44/2),0)+P44 -> 235780.33 | I44: =H44 -> 235780.33 | J44: =ROUND((-G44),0)+P44 -> 471560.33 | K44: -44496.598 | L44: =H44 -> 235780.33 | M44: 0 | N44: =-K44 -> 44496.598 | O44: =ROUND((J44+N44),0) + P44 -> 516057.33 | P44: =P43+0.01 -> 0.33
A45: 7ºD | C45: Solleiro, Carolina Mabel | D45: 0.0094 | E45: 246240.29 | F45: 45786 | G45: -227367.51 | H45: =ROUND((J45/2),0)+P45 -> 113684.34 | I45: =H45 -> 113684.34 | J45: =ROUND((-G45),0)+P45 -> 227368.34 | K45: -18872.782 | M45: =IF(L45=H45,I45,J45) -> 227368.34 | N45: =-K45 -> 18872.782 | O45: =ROUND((J45+N45),0) + P45 -> 246241.34 | P45: =P44+0.01 -> 0.34 | Q45: Walter Javier Dimiziunas
A46: 7ºE | C46: Nuñez Leyes Javier Damian | D46: 0.0087 | E46: 227903.25 | F46: 45807 | G46: -201632.4 | H46: =ROUND((J46/2),0)+P46 -> 100816.35 | I46: =H46 -> 100816.35 | J46: =ROUND((-G46),0)+P46 -> 201632.35 | K46: -26270.852 | L46: =H46 -> 100816.35 | M46: 0 | N46: =-K46 -> 26270.852 | O46: =ROUND((J46+N46),0) + P46 -> 227903.35 | P46: =P45+0.01 -> 0.35
A47: 7ºF | C47: Puente, Matias | D47: 0.0095 | E47: 248859.87 | F47: 45786 | G47: -229786.32 | H47: =ROUND((J47/2),0)+P47 -> 114893.36 | I47: =H47 -> 114893.36 | J47: =ROUND((-G47),0)+P47 -> 229786.36 | K47: -19073.556 | L47: =J47 -> 229786.36 | M47: 0 | N47: =-K47 -> 19073.556 | O47: =ROUND((J47+N47),0) + P47 -> 248860.36 | P47: =P46+0.01 -> 0.36
A48: 8ºA | B48: 8 | C48: Campelo, Mariano | D48: 0.0187 | E48: 489861.01 | F48: 45793 | G48: -447623.12 | H48: =ROUND((J48/2),0)+P48 -> 223812.37 | I48: =H48 -> 223812.37 | J48: =ROUND((-G48),0)+P48 -> 447623.37 | K48: -42237.887 | L48: =H48 -> 223812.37 | M48: 0 | N48: =-K48 -> 42237.887 | O48: =ROUND((J48+N48),0) + P48 -> 489861.37 | P48: =P47+0.01 -> 0.37
A49: 8ºB | C49: Morvillo, Mariana Yanil | D49: 0.0073 | E49: 191229.16 | F49: 45805 | G49: -170654.57 | H49: =ROUND((J49/2),0)+P49 -> 85328.38 | I49: =H49 -> 85328.38 | J49: =ROUND((-G49),0)+P49 -> 170655.38 | K49: -20574.591 | L49: =H49 -> 85328.38 | M49: 0 | N49: =-K49 -> 20574.591 | O49: =ROUND((J49+N49),0) + P49 -> 191230.38 | P49: =P48+0.01 -> 0.38
A50: 8ºC | B50: 14 | C50: Frontale, Federico Carlos | Celentano, Alejandra Verónica | D50: 0.0197 | E50: 516056.79 | F50: 45805 | G50: -460533.57 | H50: =ROUND((J50/2),0)+P50 -> 230267.39 | I50: =H50 -> 230267.39 | J50: =ROUND((-G50),0)+P50 -> 460534.39 | K50: -55523.211 | M50: =IF(L50=H50,I50,J50) -> 460534.39 | N50: =-K50 -> 55523.211 | O50: =ROUND((J50+N50),0) + P50 -> 516058.39 | P50: =P49+0.01 -> 0.39
A51: 8ºD | C51: Argul, Sergio Walter - Taboada, María Paz | D51: 0.0094 | E51: 246240.29 | F51: 45793 | G51: -225008.41 | H51: =ROUND((J51/2),0)+P51 -> 112504.4 | I51: =H51 -> 112504.4 | J51: =ROUND((-G51),0)+P51 -> 225008.4 | K51: -21231.879 | L51: =H51 -> 112504.4 | M51: 0 | N51: =-K51 -> 21231.879 | O51: =ROUND((J51+N51),0) + P51 -> 246240.4 | P51: =P50+0.01 -> 0.4
A52: 8ºE | C52: Lorenzo, Sergio Ariel | D52: 0.0087 | E52: 227903.25 | F52: 45800 | G52: -206069.05 | H52: =ROUND((J52/2),0)+P52 -> 103035.41 | I52: =H52 -> 103035.41 | J52: =ROUND((-G52),0)+P52 -> 206069.41 | K52: -21834.202 | L52: =J52 -> 206069.41 | M52: 0 | N52: =-K52 -> 21834.202 | O52: =ROUND((J52+N52),0) + P52 -> 227904.41 | P52: =P51+0.01 -> 0.41 | R52: el de sergio
A53: 8ºF | B53: 5 | C53: Arias, Mariana Laura | D53: 0.0118 | E53: 309110.16 | F53: 45793 | G53: -282457.37 | H53: =ROUND((J53/2),0)+P53 -> 141229.42 | I53: =H53 -> 141229.42 | J53: =ROUND((-G53),0)+P53 -> 282457.42 | K53: -26652.785 | L53: =H53 -> 141229.42 | M53: 0 | N53: =-K53 -> 26652.785 | O53: =ROUND((J53+N53),0) + P53 -> 309110.42 | P53: =P52+0.01 -> 0.42 | Q53: alonso sabrina eugenia
A54: 9ºA | B54: 26 | C54: Fanjul, Alejandro Rubén Marcelo | D54: 0.0187 | E54: 489861.01 | F54: 45793 | G54: -447623.12 | H54: =ROUND((J54/2),0)+P54 -> 223812.43 | I54: =H54 -> 223812.43 | J54: =ROUND((-G54),0)+P54 -> 447623.43 | K54: -42237.887 | L54: =H54 -> 223812.43 | M54: 0 | N54: =-K54 -> 42237.887 | O54: =ROUND((J54+N54),0) + P54 -> 489861.43 | P54: =P53+0.01 -> 0.43
A55: 9ºB | C55: Fanjul, Alejandro Rubén Marcelo | D55: 0.0073 | E55: 191229.16 | F55: 45793 | G55: -174740.58 | H55: =ROUND((J55/2),0)+P55 -> 87371.44 | I55: =H55 -> 87371.44 | J55: =ROUND((-G55),0)+P55 -> 174741.44 | K55: -16488.587 | L55: =H55 -> 87371.44 | M55: 0 | N55: =-K55 -> 16488.587 | O55: =ROUND((J55+N55),0) + P55 -> 191230.44 | P55: =P54+0.01 -> 0.44
A56: 9ºC | B56: 43 | C56: Franchino, Mauro | D56: 0.0197 | E56: 516056.79 | F56: 45770 | G56: -487804.98 | H56: =ROUND((J56/2),0)+P56 -> 243903.45 | I56: =H56 -> 243903.45 | J56: =ROUND((-G56),0)+P56 -> 487805.45 | K56: -28251.808 | L56: =H56 -> 243903.45 | M56: 0 | N56: =-K56 -> 28251.808 | O56: =ROUND((J56+N56),0) + P56 -> 516057.45 | P56: =P55+0.01 -> 0.45
A57: 9ºD | B57: 10 | C57: Cerra, Antonio Osvaldo | D57: 0.0117 | E57: 306490.58 | F57: 45793 | G57: -280063.66 | H57: =ROUND((J57/2),0)+P57 -> 140032.46 | I57: =H57 -> 140032.46 | J57: =ROUND((-G57),0)+P57 -> 280064.46 | K57: -26426.913 | L57: =J57 -> 280064.46 | M57: 0 | N57: =-K57 -> 26426.913 | O57: =ROUND((J57+N57),0) + P57 -> 306491.46 | P57: =P56+0.01 -> 0.46
A58: 9ºE | B58: 12 | C58: Dieci, Matias Orlando | D58: 0.011 | E58: 288153.53 | F58: 45800 | G58: -260547.07 | H58: =ROUND((J58/2),0)+P58 -> 130274.47 | I58: =H58 -> 130274.47 | J58: =ROUND((-G58),0)+P58 -> 260547.47 | K58: -27606.462 | L58: =J58 -> 260547.47 | M58: 0 | N58: =-K58 -> 27606.462 | O58: =ROUND((J58+N58),0) + P58 -> 288154.47 | P58: =P57+0.01 -> 0.47
A59: 9ºF | B59: 20 | C59: Rosales, Rubén Darío | D59: 0.0118 | E59: 309110.16 | F59: 45805 | G59: -275852.6 | H59: =ROUND((J59/2),0)+P59 -> 137927.48 | I59: =H59 -> 137927.48 | J59: =ROUND((-G59),0)+P59 -> 275853.48 | K59: -33257.558 | M59: =IF(L59=H59,I59,J59) -> 275853.48 | N59: =-K59 -> 33257.558 | O59: =ROUND((J59+N59),0) + P59 -> 309111.48 | P59: =P58+0.01 -> 0.48
A60: 10ºA | B60: 4 | C60: Guillermo Antonio PUISYS (EX Fernández, Marcela Fabiana) | D60: 0.0187 | E60: 489861.01 | F60: 45793 | G60: -447623.12 | H60: =ROUND((J60/2),0)+P60 -> 223812.49 | I60: =H60 -> 223812.49 | J60: =ROUND((-G60),0)+P60 -> 447623.49 | K60: -42237.887 | L60: =H60 -> 223812.49 | M60: 0 | N60: =-K60 -> 42237.887 | O60: =ROUND((J60+N60),0) + P60 -> 489861.49 | P60: =P59+0.01 -> 0.49
A61: 10ºB | C61: Lange, Gustavo Daniel | D61: 0.0073 | E61: 191229.16 | F61: 45793 | G61: -174740.58 | H61: =ROUND((J61/2),0)+P61 -> 87371.5 | I61: =H61 -> 87371.5 | J61: =ROUND((-G61),0)+P61 -> 174741.5 | K61: -16488.587 | M61: 93370.5 | N61: =-K61 -> 16488.587 | O61: =ROUND((J61+N61),0) + P61 -> 191230.5 | P61: =P60+0.01 -> 0.5
A62: 10ºC | B62: 17 | C62: Espósito, Franco Ezequiel | D62: 0.0197 | E62: 516056.79 | F62: 45796 | G62: -469441.3 | H62: =ROUND((J62/2),0)+P62 -> 234721.51 | I62: =H62 -> 234721.51 | J62: =ROUND((-G62),0)+P62 -> 469441.51 | K62: -46615.483 | L62: =H62 -> 234721.51 | M62: 0 | N62: =-K62 -> 46615.483 | O62: =ROUND((J62+N62),0) + P62 -> 516057.51 | P62: =P61+0.01 -> 0.51
A63: 10ºD | C63: Lobato, Lorena - Vega, Maximiliano | D63: 0.0094 | E63: 246240.29 | F63: 45863 | G63: -164899.57 | H63: =ROUND((J63/2),0)+P63 -> 82450.52 | I63: =H63 -> 82450.52 | J63: =ROUND((-G63),0)+P63 -> 164900.52 | K63: -81340.722 | M63: 0 | N63: =-K63 -> 81340.722 | O63: =ROUND((J63+N63),0) + P63 -> 246241.52 | P63: =P62+0.01 -> 0.52
A64: 10ºE | C64: Hecimovic, Mariano Hernán | D64: 0.0087 | E64: 227903.25 | F64: 45800 | G64: -206069.05 | H64: =ROUND((J64/2),0)+P64 -> 103035.53 | I64: =H64 -> 103035.53 | J64: =ROUND((-G64),0)+P64 -> 206069.53 | K64: -21834.202 | L64: =H64 -> 103035.53 | M64: 0 | N64: =-K64 -> 21834.202 | O64: =ROUND((J64+N64),0) + P64 -> 227904.53 | P64: =P63+0.01 -> 0.53 | R64: mariano hecimovic
A65: 10ºF | B65: 23 | C65: Ramos, Sergio Eugenio | D65: 0.0118 | E65: 309110.16 | F65: 45786 | G65: -285418.79 | H65: =ROUND((J65/2),0)+P65 -> 142710.54 | I65: =H65 -> 142710.54 | J65: =ROUND((-G65),0)+P65 -> 285419.54 | K65: -23691.364 | M65: =IF(L65=H65,I65,J65) -> 285419.54 | N65: =-K65 -> 23691.364 | O65: =ROUND((J65+N65),0) + P65 -> 309111.54 | P65: =P64+0.01 -> 0.54
A66: 11ºA/B | B66: 21 | C66: Mosquera, Julio Rodolfo | Cuzzolino, Daniela Carol | D66: 0.0258 | E66: 675851.02 | F66: 45775 | G66: -634226.21 | H66: =ROUND((J66/2),0)+P66 -> 317113.55 | I66: =H66 -> 317113.55 | J66: =ROUND((-G66),0)+P66 -> 634226.55 | K66: -41624.809 | L66: =H66 -> 317113.55 | M66: 0 | N66: =-K66 -> 41624.809 | O66: =ROUND((J66+N66),0) + P66 -> 675851.55 | P66: =P65+0.01 -> 0.55
A67: 11ºC | B67: 41 | C67: Silvestre Villarruel Eduardo (EX De Mieri, Fernando Emanuel | D67: 0.0197 | E67: 516056.79 | F67: 45790 | G67: -473679.07 | H67: =ROUND((J67/2),0)+P67 -> 236840.56 | I67: =H67 -> 236840.56 | J67: =ROUND((-G67),0)+P67 -> 473679.56 | K67: -42377.712 | L67: =H67 -> 236840.56 | M67: 0 | N67: =-K67 -> 42377.712 | O67: =ROUND((J67+N67),0) + P67 -> 516057.56 | P67: =P66+0.01 -> 0.56
A68: 11ºD | B68: 2 | C68: Yudchak, Carlos Alberto | D68: 0.0117 | E68: 306490.58 | G68: 0 | K68: -306490.58 | M68: =IF(L68=H68,I68,J68) -> 0 | N68: =-K68 -> 306490.58 | O68: =ROUND((J68+N68),0) + P68 -> 306491.57 | P68: =P67+0.01 -> 0.57
A69: 11ºE | C69: Argúl, Adrián Norberto | D69: 0.0087 | E69: 227903.25 | F69: 45775 | G69: -213866.98 | H69: =ROUND((J69/2),0)+P69 -> 106934.58 | I69: =H69 -> 106934.58 | J69: =ROUND((-G69),0)+P69 -> 213867.58 | K69: -14036.273 | M69: =IF(L69=H69,I69,J69) -> 213867.58 | N69: =-K69 -> 14036.273 | O69: =ROUND((J69+N69),0) + P69 -> 227904.58 | P69: =P68+0.01 -> 0.58
A70: 11ºF | B70: 19 | C70: Lobato, Lorena - Vega, Maximiliano | D70: 0.0118 | E70: 309110.16 | F70: 45821 | G70: -256859.22 | H70: =ROUND((J70/2),0)+P70 -> 128430.59 | I70: =H70 -> 128430.59 | J70: =ROUND((-G70),0)+P70 -> 256859.59 | K70: -52250.939 | M70: 0 | N70: =-K70 -> 52250.939 | O70: =ROUND((J70+N70),0) + P70 -> 309111.59 | P70: =P69+0.01 -> 0.59
A71: 12ºA/B | B71: 36 | C71: Luciano, Carmen Veronica - Rey, Javier Pablo | D71: 0.0258 | E71: 675851.02 | F71: 45891 | G71: -382821.8 | H71: =ROUND((J71/2),0)+P71 -> 191411.6 | I71: =H71 -> 191411.6 | J71: =ROUND((-G71),0)+P71 -> 382822.6 | K71: -293029.22 | L71: =330000+52822.6 -> 382822.6 | M71: 0 | N71: =-K71 -> 293029.22 | O71: =ROUND((J71+N71),0) + P71 -> 675852.6 | P71: =P70+0.01 -> 0.6
A72: 12ºC | B72: 15 | C72: Hernandez, Marisa Beatriz - Hernandez, Adrian Jose | D72: 0.0197 | E72: 516056.79 | F72: 45800 | G72: -466616.12 | H72: =ROUND((J72/2),0)+P72 -> 233308.61 | I72: =H72 -> 233308.61 | J72: =ROUND((-G72),0)+P72 -> 466616.61 | K72: -49440.664 | L72: =H72 -> 233308.61 | M72: 0 | N72: =-K72 -> 49440.664 | O72: =ROUND((J72+N72),0) + P72 -> 516057.61 | P72: =P71+0.01 -> 0.61
A73: 12ºD | C73: Morini, Micaela | D73: 0.0094 | E73: 246240.29 | F73: 45784 | G73: -228041.54 | H73: =ROUND((J73/2),0)+P73 -> 114021.62 | I73: =H73 -> 114021.62 | J73: =ROUND((-G73),0)+P73 -> 228042.62 | K73: -18198.754 | M73: =IF(L73=H73,I73,J73) -> 228042.62 | N73: =-K73 -> 18198.754 | O73: =ROUND((J73+N73),0) + P73 -> 246241.62 | P73: =P72+0.01 -> 0.62
A74: 12ºE | B74: 40 | C74: Armerding, Jorge | D74: 0.011 | E74: 288153.53 | F74: 45784 | G74: -266857.12 | H74: =ROUND((J74/2),0)+P74 -> 133429.63 | I74: =H74 -> 133429.63 | J74: =ROUND((-G74),0)+P74 -> 266857.63 | K74: -21296.414 | M74: 133429.63 | N74: =-K74 -> 21296.414 | O74: =ROUND((J74+N74),0) + P74 -> 288154.63 | P74: =P73+0.01 -> 0.63
A75: 12ºF | C75: Bilyj, Josefa Catalina | D75: 0.0095 | E75: 248859.87 | F75: 45786 | G75: -229786.32 | H75: =ROUND((J75/2),0)+P75 -> 114893.64 | I75: =H75 -> 114893.64 | J75: =ROUND((-G75),0)+P75 -> 229786.64 | K75: -19073.556 | M75: 0 | N75: =-K75 -> 19073.556 | O75: =ROUND((J75+N75),0) + P75 -> 248860.64 | P75: =P74+0.01 -> 0.64
A76: 13ºA/B | B76: 9 | C76: Gazzaneo Francisco | D76: 0.0258 | E76: 675851.02 | F76: 45835 | G76: -525270.52 | H76: =ROUND((J76/2),0)+P76 -> 262636.65 | I76: =H76 -> 262636.65 | J76: =ROUND((-G76),0)+P76 -> 525271.65 | K76: -150580.49 | L76: =H76 -> 262636.65 | M76: 0 | N76: =-K76 -> 150580.49 | O76: =ROUND((J76+N76),0) + P76 -> 675852.65 | P76: =P75+0.01 -> 0.65
A77: 13ºC | B77: 35 | C77: Argentino, Javier Leonardo | D77: 0.0197 | E77: 516056.79 | F77: 45784 | G77: -477916.84 | H77: =ROUND((J77/2),0)+P77 -> 238959.66 | I77: =H77 -> 238959.66 | J77: =ROUND((-G77),0)+P77 -> 477917.66 | K77: -38139.941 | L77: 238359.66 | M77: =I77-L77 -> 600 | N77: =-K77 -> 38139.941 | O77: =ROUND((J77+N77),0) + P77 -> 516058.66 | P77: =P76+0.01 -> 0.66
A78: 13ºD | B78: 13-32 | C78: Scardigno, Gabriela Susana - Ripoll, Luis Alberto | D78: 0.014 | E78: 366740.86 | F78: 45786 | G78: -338632.46 | H78: =ROUND((J78/2),0)+P78 -> 169316.67 | I78: =H78 -> 169316.67 | J78: =ROUND((-G78),0)+P78 -> 338632.67 | K78: -28108.398 | L78: =H78 -> 169316.67 | M78: 0 | N78: =-K78 -> 28108.398 | O78: =ROUND((J78+N78),0) + P78 -> 366741.67 | P78: =P77+0.01 -> 0.67
A79: 13ºE | B79: 42 | C79: Quiñones, Carlos Eduardo | D79: 0.011 | E79: 288153.53 | F79: 45777 | G79: -269617.77 | H79: =ROUND((J79/2),0)+P79 -> 134809.68 | I79: =H79 -> 134809.68 | J79: =ROUND((-G79),0)+P79 -> 269618.68 | K79: -18535.768 | L79: =H79 -> 134809.68 | M79: 0 | N79: =-K79 -> 18535.768 | O79: =ROUND((J79+N79),0) + P79 -> 288154.68 | P79: =P78+0.01 -> 0.68
A80: 13ºF | B80: 27 | C80: Mosquera, José Elias | D80: 0.0118 | E80: 309110.16 | F80: 45800 | G80: -279495.95 | H80: =ROUND((J80/2),0)+P80 -> 139748.69 | I80: =H80 -> 139748.69 | J80: =ROUND((-G80),0)+P80 -> 279496.69 | K80: -29614.205 | M80: =IF(L80=H80,I80,J80) -> 279496.69 | N80: =-K80 -> 29614.205 | O80: =ROUND((J80+N80),0) + P80 -> 309111.69 | P80: =P79+0.01 -> 0.69
D82: =SUM(D7:D81) -> 0.9979 | E82: =SUM(E7:E81) -> 26140765 | F82: =SUM(F7:F81) -> 3344000 | G82: =SUM(G7:G81) -> -22258385 | L82: =SUM(L7:L80) -> 10374975 | M82: =SUM(M7:M80) -> 4712668.7 | O82: =SUM(O7:O81) -> 26140812

Sheet ANOTACIONES
C3: ANOTACION | D3: 1
C4: FECHA DE LA ANOTACION: | E4: 0 | G4: NOMBRE: | H4: Anchipi
C5: QUEJA VIA: | D5: WHATSAPP | E5: MAIL | G5: LOTE: | H5: 6D
C6: MOTIVO DE LA QUEJA:
C7: El mes pasado en la planilla ARBA el pago $39.000 y no se le restaron de la columna "saldo total" para abonar - El adjudica que lo debe abonar el propietario anterior el restante.
C12: ANOTACION | D12: =D3+1 -> 2
C13: FECHA DE LA ANOTACION: | E13: 0 | G13: NOMBRE:
C14: QUEJA VIA: | D14: WHATSAPP | E14: MAIL | G14: LOTE: | H14: Local 1
C15: MOTIVO DE LA QUEJA:
C16: $269.608 el 08/04
C21: ANOTACION | D21: =D12+1 -> 3
C22: FECHA DE LA ANOTACION: | E22: 0 | G22: NOMBRE:
C23: QUEJA VIA: | D23: WHATSAPP | E23: MAIL | G23: LOTE: | H23: Local 2
C24: MOTIVO DE LA QUEJA:
C25: $148.104 el 17/04
C30: ANOTACION | D30: =D21+1 -> 4
C31: FECHA DE LA ANOTACION: | E31: 0 | G31: NOMBRE: | H31: Veronica(?)
C32: QUEJA VIA: | D32: WHATSAPP | E32: MAIL | G32: LOTE: | H32: No sabemos
C33: MOTIVO DE LA QUEJA:
C34: Deposito $300.000 y $30.000 23/04
C39: ANOTACION | D39: =D30+1 -> 5
C40: FECHA DE LA ANOTACION: | E40: 0 | G40: NOMBRE:
C41: QUEJA VIA: | D41: WHATSAPP | E41: MAIL | G41: LOTE: | H41: 2E, 6E, 9E y cochera 12
C42: MOTIVO DE LA QUEJA:
C43: Deposito $673.000 el 16/04
C48: ANOTACION | D48: =D39+1 -> 6
C49: FECHA DE LA ANOTACION: | E49: 0 | G49: NOMBRE:
C50: QUEJA VIA: | D50: WHATSAPP | E50: MAIL | G50: LOTE: | H50: 7D
C51: MOTIVO DE LA QUEJA:
C52: Cambiar titularidad x Walter nose
