Workbook

Sheet RESUMEN
C1: MAIL: elmiradorconsorcios@gmail.com
C2: CUIT ADMINISTRACION: 27231256879
C3: CBU: 0720039720000002171436 | E3: TELEFONO: 11 5320-2676
C4: ADMINISTRADORA: CAROLINA CANCIANI MP:1148
C5: PERÍODO: SEPTIEMBRE | E5: HORARIOS DE ATENCION: LUNES A VIERNES - 10 A 16HS - EMERGENCIAS 24HS
C6: LIQUIDACION DE EXPENSAS
A14: Importante para dueños o inquilinos de departamentos o coheras: Queremos recordarles una cuestión importante respecto a los pagos de expensas que ayuda a evitar errores en la imputación de los mismos. El sistema que utilizamos asigna centavos únicos a cada Unidad Funcional (UF), lo cual nos permite identificar automáticamente a qué unidad corresponde cada transferencia. Es decir, cada UF tiene un número específico de centavos que actúa como "identificador". Por ejemplo, si tu UF es la 45, el importe a abonar debería terminar en $...,45. Si tenés más de una unidad (por ejemplo, un departamento y una cochera), cada una tiene su propio código de centavos. En esos casos, te pedimos por favor que realices una transferencia por cada UF, respetando el importe con sus centavos correspondientes. Sabemos que a veces por comodidad se suele enviar todo junto en una sola transferencia, pero esto puede generar confusión o errores en la imputación automática. Realizar los pagos por separado nos permite asegurar que cada importe se asigne correctamente. Agradecemos muchísimo la colaboración para seguir manteniendo todo ordenado. Saludos cordiales.
A20: VTO 15/10
A24: GASTOS ORDINARIOS UNIDADES FUNCIONALES: | E24: UF 93,20% | F24: LOCAL 1 (1,08%) | G24: LOCAL 2 (1,28%) | H24: LOCAL 3 (1,21%) | I24: LOCAL 4 (1,49%) | J24: LOCAL 5 (1,74%)
A25: Sueldo encargada Sonia Arzamendia Galeano
A26: Haberes | D26: 1008894
A27: Plus pileta | D27: 35211
A28: Plus retiro de basura | D28: =1533.8*80 -> 122704
A29: Plus cochera | D29: 20931
A30: Adicional Viaticos | D30: 58852.2
A31: Adicional remuneracion | D31: 50000
A32: SUBTOTAL | D32: =SUM(D26:D31) -> 1296592.2
A33: Sueldo encargada Miriam
A34: Haberes | D34: 504447
A35: Horas extras
A36: Plus pileta | D36: =D27 -> 35211
A37: Plus retiro de basura | D37: =D28 -> 122704
A38: Plus cochera | D38: =D29 -> 20931
A39: Adicional Viaticos | D39: 58852.2
A40: Adicional remuneracion | D40: 50000
A41: SUBTOTAL | D41: =SUM(D34:D40) -> 792145.2
A42: TOTAL SUELDO | D42: =D32+D41 -> 2088737.4 | E42: =D42*93.2% -> 1946703.3 | F42: =$D42*1.08% -> 22558.364 | G42: =$D42*1.28% -> 26735.839 | H42: =$D42*1.21% -> 25273.723 | I42: =$D42*1.49% -> 31122.187 | J42: =D42*1.74% -> 36344.031 | K42: =E42+J42+F42+G42+H42+I42 -> 2088737.4 | L42: =K42-600000 -> 1488737.4
A43: SAC | D43: 0 | E43: =D43*91.91% -> 0 | J43: =D43*8.09% -> 0
D44: 0 | E44: =D44*91.91% -> 0 | J44: =D44*8.09% -> 0
A47: TOTAL | D47: =SUM(D43:D45) -> 0 | E47: =SUM(E43:E45) -> 0 | J47: =SUM(J43:J45) -> 0 | K47: =E47+J47 -> 0 | L47: =IF(D47=K47, "", "Error")
A48: COMBUSTIBLE PARA GRUPO ELECTROGENO | E48: =D48*91.91% -> 0 | J48: =D48*8.09% -> 0
E49: =D49 -> 0
E50: =D50 -> 0
E51: =D51*91.91% -> 0 | J51: =D51*8.09% -> 0
A52: TOTAL SAC | D52: =SUM(D44:D51) -> 0 | E52: =SUM(E44:E51) -> 0 | K52: =E52+J52+F52+G52+H52+I52 -> 0 | L52: =IF(D52=K52, "", "Error")
A53: IMPUESTOS
A54: ARBA - Impuesto inmobiliario partida 025024270-0 | C54: Mes de descanso
A55: TSG - Partida 197229000 | C55: PMC 08/09 | D55: 643422
A56: TSG - Partida 197227000 | C56: =C55 -> PMC 08/09 | D56: 643422
A57: TOTAL IMPUESTOS | D57: =SUM(D54:D56) -> 1286844 | E57: =D57*93.2% -> 1199338.6 | F57: =$D57*1.08% -> 13897.915 | G57: =$D57*1.28% -> 16471.603 | H57: =$D57*1.21% -> 15570.812 | I57: =$D57*1.49% -> 19173.976 | J57: =D57*1.74% -> 22391.086 | K57: =E57+J57+F57+G57+H57+I57 -> 1286844 | L57: =IF(D57=K57, "", "Error")
A58: APORTES Y CONTRIBUCIONES
A59: Monotributo Sra. Sonia | C59: Mercado P. 20/09 | D59: 56231.41
A60: Monotributo Sra. Miriam | C60: Mercado P. 20/09 | D60: 64940.71
A61: TOTAL APORTES Y CONTRIBUCIONES | D61: =SUM(D58:D60) -> 121172.12 | E61: =D61*93.2% -> 112932.42 | F61: =$D61*1.08% -> 1308.6589 | G61: =$D61*1.28% -> 1551.0031 | H61: =$D61*1.21% -> 1466.1827 | I61: =$D61*1.49% -> 1805.4646 | J61: =D61*1.74% -> 2108.3949 | K61: =E61+J61+F61+G61+H61+I61 -> 121172.12 | L61: =IF(D61=K61, "", "Error")
A62: SEGUROS
A63: Federacion patronal - Poliza integral para consorcios nro. 2152393 | C63: Mercado P. 08/09 | D63: 160913 | E63: =D63*93.2% -> 149970.92 | F63: =$D63*1.08% -> 1737.8604 | G63: =$D63*1.28% -> 2059.6864 | H63: =$D63*1.21% -> 1947.0473 | I63: =$D63*1.49% -> 2397.6037 | J63: =D63*1.74% -> 2799.8862 | K63: =SUM(E63:J63) -> 160913
A64: Federacion patronal - Poliza accidentes personales Sra. Sonia - nro. 9559834 | C64: Mercado P. 08/09 | D64: 7907 | E64: =D64*93.2% -> 7369.324 | F64: =$D64*1.08% -> 85.3956 | G64: =$D64*1.28% -> 101.2096 | H64: =$D64*1.21% -> 95.6747 | I64: =$D64*1.49% -> 117.8143 | J64: =D64*1.74% -> 137.5818 | K64: =SUM(E64:J64) -> 7907
A65: Federacion patronal - Poliza accidentes personales Sra. Miriam - nro. 9559886 | C65: Mercado P. 05/08 | D65: 7907 | E65: =D65*93.2% -> 7369.324 | F65: =$D65*1.08% -> 85.3956 | G65: =$D65*1.28% -> 101.2096 | H65: =$D65*1.21% -> 95.6747 | I65: =$D65*1.49% -> 117.8143 | J65: =D65*1.74% -> 137.5818 | K65: =SUM(E65:J65) -> 7907
A66: TOTAL Aportes y Contribuciones - Sindicato | D66: =SUM(D63:D65) -> 176727 | E66: =SUM(E63:E65) -> 164709.56 | F66: =SUM(F63:F65) -> 1908.6516 | G66: =SUM(G63:G65) -> 2262.1056 | H66: =SUM(H63:H65) -> 2138.3967 | I66: =SUM(I63:I65) -> 2633.2323 | J66: =SUM(J63:J65) -> 3075.0498 | K66: =E66+J66+F66+G66+H66+I66 -> 176727 | L66: =IF(D66=K66, "", "Error")
A67: ABONOS Y SERVICIOS
A68: Aysa - Cuenta 249011 | D68: 561764.05 | E68: =D68*93.2% -> 523564.09 | F68: =$D68*1.08% -> 6067.0517 | G68: =$D68*1.28% -> 7190.5798 | H68: =$D68*1.21% -> 6797.345 | I68: =$D68*1.49% -> 8370.2843 | J68: =D68*1.74% -> 9774.6945 | K68: =D68 -> 561764.05 | L68: =SUM(E68:J68) -> 561764.05 | M68: =L68-D68 -> 0 | N68: =K68-D68 -> 0
A69: Edesur - Cliente 01291636 | C69: Mercado P. 16/09 | D69: 2108365.6 | E69: =D69*93.2% -> 1964996.7 | F69: =$D69*1.08% -> 22770.348 | G69: =$D69*1.28% -> 26987.079 | H69: =$D69*1.21% -> 25511.223 | I69: =$D69*1.49% -> 31414.647 | J69: =D69*1.74% -> 36685.561 | K69: =D69 -> 2108365.6 | L69: =E69+J69+I69+H69+G69+F69 -> 2108365.6 | M69: =L69-D69 -> 0 | N69: =K69-D69 -> 0
A70: Telecentro - Zona coworking - Cliente 7725479 | C70: Mercado P. 16/09 | D70: 109824 | E70: =D70 -> 109824 | K70: =D70 -> 109824 | L70: =E70+J70+I70+H70+G70+F70 -> 109824 | M70: =L70-D70 -> 0 | N70: =K70-D70 -> 0
A71: ADS - Abono de mantenimiento ascensores SEPTIEMBRE del 2025 | C71: Transf 03/09 | D71: 268595.04 | E71: =D71 -> 268595.04 | K71: =D71 -> 268595.04 | L71: =E71+J71+I71+H71+G71+F71 -> 268595.04
A72: Victor Martinez - Abono mantenimiento control de accesos | C72: Mes de AGOSTO | D72: 30000 | E72: =D72 -> 30000 | K72: =D72 -> 30000 | L72: =E72+J72+I72+H72+G72+F72 -> 30000 | M72: =L72-D72 -> 0 | N72: =K72-D72 -> 0
A73: Victor Martinez - Instalacion de control de acceso puerta SUM e instalacion de alarmas | D73: 420000 | E73: =D73 -> 420000 | K73: =D73 -> 420000 | L73: =E73+J73+I73+H73+G73+F73 -> 420000
A74: Metrogas - Cliente nro. 40000496339 | C74: PMC 03/09 | D74: 9545.64 | E74: =D74*93.2% -> 8896.5365 | F74: =$D74*1.08% -> 103.09291 | G74: =$D74*1.28% -> 122.18419 | H74: =$D74*1.21% -> 115.50224 | I74: =$D74*1.49% -> 142.23004 | J74: =D74*1.74% -> 166.09414 | K74: =D74 -> 9545.64 | L74: =E74+J74+I74+H74+G74+F74 -> 9545.64 | M74: =L74-D74 -> 0 | N74: =K74-D74 -> 0
A75: Metrogas - Cliente nro. 40000497007 | C75: =C74 -> PMC 03/09 | D75: 829424.85 | E75: =D75*93.2% -> 773023.96 | F75: =$D75*1.08% -> 8957.7884 | G75: =$D75*1.28% -> 10616.638 | H75: =$D75*1.21% -> 10036.041 | I75: =$D75*1.49% -> 12358.43 | J75: =D75*1.74% -> 14431.992 | K75: =D75 -> 829424.85 | L75: =E75+J75+I75+H75+G75+F75 -> 829424.85 | M75: =L75-D75 -> 0 | N75: =K75-D75 -> 0
A76: Loschi Mantenimiento grupo electrogeno - Abono bimestral | C76: Transf 29/09 | D76: 100000 | E76: =D76 -> 100000 | K76: =D76 -> 100000 | L76: =E76+J76+I76+H76+G76+F76 -> 100000 | M76: =L76-D76 -> 0 | N76: =K76-D76 -> 0
A77: Doartero Julio - Mano de obra y reparacion desagote caño pileta | D77: 120000 | E77: =D77 -> 120000 | K77: =D77 -> 120000 | L77: =E77+J77+I77+H77+G77+F77 -> 120000 | N77: =K77-D77 -> 0
A78: Doartero Julio - Colocacion de placas antivibratorias para motor - mano de obra y materiales (sala de bombas) | D78: 200000 | E78: =D78 -> 200000 | K78: =D78 -> 200000 | L78: =E78+J78+I78+H78+G78+F78 -> 200000 | N78: =K78-D78 -> 0
A79: Servisur - reemplazo de 26 plafones led | D79: 410000 | E79: =D79 -> 410000 | K79: =D79 -> 410000 | L79: =E79+J79+I79+H79+G79+F79 -> 410000 | N79: =K79-D79 -> 0
A80: Barbiero - compra de 26 plafones | D80: 175724.97 | E80: =D80 -> 175724.97 | K80: =D80 -> 175724.97 | L80: =E80+J80+I80+H80+G80+F80 -> 175724.97 | N80: =K80-D80 -> 0
A81: Citta cerrajeria - Blindex hall cochera 28/08 | D81: 75000 | E81: =D81 -> 75000 | K81: =D81 -> 75000 | L81: =E81+J81+I81+H81+G81+F81 -> 75000 | M81: =L81-D81 -> 0 | N81: =K81-D81 -> 0
M82: =IF(K82=L82, "", "Error")
A83: TOTAL ABONOS Y SERVICIOS | D83: =SUM(D68:D82) -> 5418244.1 | E83: =SUM(E68:E82) -> 5179625.3 | F83: =SUM(F68:F82) -> 37898.281 | G83: =SUM(G68:G82) -> 44916.481 | H83: =SUM(H68:H82) -> 42460.111 | I83: =SUM(I68:I82) -> 52285.592 | J83: =SUM(J68:J82) -> 61058.342 | K83: =E83+J83+F83+G83+H83+I83 -> 5418244.1 | L83: =IF(D83=K83, "", "Error") | M83: =D83-K83 -> 0
A86: GASTOS VARIOS
A87: Articulos de limpieza - Mes de SEPTIEMBRE | D87: 489000 | E87: =D87*93.2% -> 455748 | F87: =$D87*1.08% -> 5281.2 | G87: =$D87*1.28% -> 6259.2 | H87: =$D87*1.21% -> 5916.9 | I87: =$D87*1.49% -> 7286.1 | J87: =D87*1.74% -> 8508.6
A88: Lomas metal compra alfombra entrada | D88: 83490 | E88: =D88 -> 83490
A93: TOTAL GASTOS VARIOS | D93: =SUM(D87:D92) -> 572490 | E93: =SUM(E87:E92) -> 539238 | F93: =SUM(F87:F92) -> 5281.2 | G93: =SUM(G87:G92) -> 6259.2 | H93: =SUM(H87:H92) -> 5916.9 | I93: =SUM(I87:I92) -> 7286.1 | J93: =SUM(J87:J92) -> 8508.6 | K93: =E93+J93+F93+G93+H93+I93 -> 572490 | L93: =IF(D93=K93, "", "Error")
A96: GASTOS DE ADMINISTRACION
A97: RC Adm Cons. CANCIANI, Carolina | B97: MP:1148 | D97: 700000 | E97: =D97*93.2% -> 652400 | F97: =$D97*1.08% -> 7560 | G97: =$D97*1.28% -> 8960 | H97: =$D97*1.21% -> 8470 | I97: =$D97*1.49% -> 10430 | J97: =D97*1.74% -> 12180
A100: TOTAL GASTOS DE ADMINISTRACION | D100: =SUM(D97:D99) -> 700000 | E100: =SUM(E97:E99) -> 652400 | F100: =SUM(F97:F99) -> 7560 | G100: =SUM(G97:G99) -> 8960 | H100: =SUM(H97:H99) -> 8470 | I100: =SUM(I97:I99) -> 10430 | J100: =SUM(J97:J99) -> 12180 | K100: =E100+J100+F100+G100+H100+I100 -> 700000 | L100: =IF(D100=K100, "", "Error")
A101: Gastos bancarios | B101: No hay cuenta aun | E101: =D101*93.2% -> 0 | F101: =$D101*1.08% -> 0 | G101: =$D101*1.28% -> 0 | H101: =$D101*1.21% -> 0 | I101: =$D101*1.49% -> 0 | J101: =D101*1.74% -> 0
A102: Mantenimiento de cuenta | B102: No hay cuenta aun | E102: =D102*93.2% -> 0 | F102: =$D102*1.08% -> 0 | G102: =$D102*1.28% -> 0 | H102: =$D102*1.21% -> 0 | I102: =$D102*1.49% -> 0 | J102: =D102*1.74% -> 0
A103: TOTAL GASTOS BANCARIOS | D103: =SUM(D101:D102) -> 0 | E103: =SUM(E101:E102) -> 0 | F103: =SUM(F101:F102) -> 0 | G103: =SUM(G101:G102) -> 0 | H103: =SUM(H101:H102) -> 0 | I103: =SUM(I101:I102) -> 0 | J103: =SUM(J101:J102) -> 0 | K103: =E103+J103+F103+G103+H103+I103 -> 0 | L103: =IF(D103=K103, "", "Error")
A105: FONDO DE GASTOS ORDINARIOS | E105: =D105*93.2% -> 0 | F105: =$D105*1.08% -> 0 | G105: =$D105*1.28% -> 0 | H105: =$D105*1.21% -> 0 | I105: =$D105*1.49% -> 0 | J105: =D105*1.74% -> 0 | K105: =E105+J105+F105+G105+H105+I105 -> 0 | L105: =IF(D105=K105, "", "Error")
A107: TOTAL ORDINARIOS | D107: =SUM(D105+D57+D52+D103+D100+D93+D83+D66+D47+D42+D61) -> 10364215 | E107: =SUM(E105+E57+E52+E103+E100+E93+E83+E66+E47+E42+E61) -> 9794947.2 | F107: =SUM(F105+F57+F52+F103+F100+F93+F83+F66+F47+F42+F61) -> 90413.071 | G107: =SUM(G105+G57+G52+G103+G100+G93+G83+G66+G47+G42+G61) -> 107156.23 | H107: =SUM(H105+H57+H52+H103+H100+H93+H83+H66+H47+H42+H61) -> 101296.13 | I107: =SUM(I105+I57+I52+I103+I100+I93+I83+I66+I47+I42+I61) -> 124736.55 | J107: =SUM(J105+J57+J52+J103+J100+J93+J83+J66+J47+J42+J61) -> 145665.5 | K107: =E107+J107+F107+G107+H107+I107 -> 10364215 | L107: =IF(D107=K107, "", "Error") | M107: =D107-K107 -> 0
A109: Gastos particulares
A114: TOTAL | C114: =SUM(C110:C113) -> 0
A117: GASTOS EXTRAORDINARIOS | E117: UF | F117: LOCAL 1 (1,08%) | G117: LOCAL 2 (1,28%) | H117: LOCAL 3 (1,21%) | I117: LOCAL 4 (1,49%) | J117: LOCAL 5 (1,74%)
E118: =D118 -> 0
A120: TOTAL | D120: =SUM(D118:D119) -> 0 | E120: =SUM(E118:E119) -> 0 | J120: =SUM(J118:J119) -> 0 | L120: =E120+J120 -> 0 | M120: =IF(D120=L120, "", "Error")
A123: GASTOS ORDINARIOS + PREVISION : | B123: =D107 -> 10364215
A124: GASTOS ORDINARIOS SIN PREVISION: | B124: =D107-D105 -> 10364215 | D124: Se recuerda a todos los propietarios que, en caso de producirse la venta o transferencia de una unidad funcional, es obligatorio informar a la Administración los datos de los nuevos titulares. Dicha notificación resulta indispensable para actualizar los registros del consorcio, emitir correctamente las expensas y garantizar que toda comunicación formal llegue a quienes correspondan. La información a presentar deberá incluir al menos: * Nombre y apellido de los nuevos propietarios. * Domicilio de contacto (en caso de ser distinto de la unidad funcional). * Correo electrónico y/o teléfono de contacto. * Copia de la escritura, acta notarial o documentación que acredite la transferencia. Hasta tanto no se reciba la notificación formal, toda comunicación y responsabilidad respecto de la unidad seguirá dirigida al propietario anterior.
A126: CAJA EFECTIVO $ (pesos)
A127: Saldo anterior | B127: -475577.81
A128: Ingresos | B128: =PRORRATEO!H127 -> 9271155.2
A129: Egresos Ordinarios | B129: =-B124 -> -10364215
A130: Egresos Extraordinarios | B130: =-D120 -> 0
A131: Dinero sin identificar | B131: =B141 -> 63085.21
A132: Dinero ingreso SUM | B132: =-B146 -> 0
A133: Punitorios mal cobrados | B133: 0
A134: Gastos particulares | B134: =-C114 -> 0
A136: Saldo al cierre | B136: =SUM(B127:B135) -> -1505552
A138: TRANSFERENCIAS SIN IDENTIFICAR
A139: Transferencia Nicolas Rey Mauro18/09 | B139: 63085.21
A141: TOTAL | B141: =SUM(B138:B140) -> 63085.21
A145: CAJA EFECTIVO SUM $ (pesos) | B145: 0
A146: Ingreso
...

Sheet PRORRATEO
F1: Banco Santander Rio. | K1: SE GASTO: | L1: =RESUMEN!D107-RESUMEN!D105 -> 10364215
F2: CBU: 0720039720000002171436 | K2: SE PRORRATEA EN LAS UF: | M2: 10000000
A3: =RESUMEN!C5 -> PERÍODO: SEPTIEMBRE | F3: CTA CTE $ 0039 - 21714/3 FIDEICOMISO 25 DE MAYO 837 LAN 30716676737
J4: =(J3*8.09%)/44 -> 0 | P4: =L1-K127 -> 494947.16
A5: Piso | B5: Dpto. | C5: UF | D5: Propietario | E5: Inquilinos | F5: (%) | G5: Saldo | H5: Ingreso | I5: SALDO | J5: Expensas extraor. | K5: Expensas ord | L5: SUM/ GASTOS PART | M5: TOTAL A ABONAR HASTA | N5: TOTAL A ABONAR 2DO VTO - DESDE EL
M7: =RESUMEN!A20 -> VTO 15/10 | N7: =RESUMEN!A20 -> VTO 15/10
A8: conf sup | C8: LOC 1 | D8: Fernandez, Cristian | E8: Gladys ojeda Britez - Exequiel alexis giuliani | F8: 0.0108 | G8: 120107.14 | H8: =G8 -> 120107.14 | I8: =G8-H8 -> 0 | J8: 0 | K8: 90413.071 | L8: =J$3*F8%+J$4 -> 0 | M8: =K8+J8+I8+L8 -> 90413.071 | N8: =M8*6% + M8 -> 95837.855 | Q8: para copias y pegar las expensas ord del local
C9: LOC 2 | D9: Sr propietario | F9: 0.013 | G9: 101816.28 | H9: =117355.87+16429-11268-H99 -> 101816 | I9: =G9-H9 -> 0.278848 | J9: 0 | K9: 107156.23 | L9: =J$3*F9%+J$4 -> 0 | M9: =K9+J9+I9+L9 -> 107156.51 | N9: =M9*6% + M9 -> 113585.9
A10: conf sup | C10: LOC 3 | D10: Schiaffino, Edgardo Angel | F10: 0.0121 | G10: 134565.38 | I10: =G10-H10 -> 134565.38 | J10: 0 | K10: 101296.13 | L10: =J$3*F10%+J$4 -> 0 | M10: =K10+J10+I10+L10 -> 235861.51 | N10: =M10*6% + M10 -> 250013.2 | Q10: LOCAL 1 | R10: =RESUMEN!F107 -> 90413.071
A11: conf sup | C11: LOC 4 | D11: Cordero, Leandro Emanuel - Orona, Victoria | F11: 0.0149 | G11: 165702.97 | I11: =G11-H11 -> 165702.97 | J11: 0 | K11: 124736.55 | L11: =J$3*F11%+J$4 -> 0 | M11: =K11+J11+I11+L11 -> 290439.52 | N11: =M11*6% + M11 -> 307865.9 | Q11: LOCAL 2 | R11: =RESUMEN!G107 -> 107156.23
A12: conf sup | C12: LOC 5 | D12: Orsi, Jose Luis - Fernandez, Cristian Gabriel | F12: 0.0174 | G12: 62115.895 | H12: =G12 -> 62115.895 | I12: =G12-H12 -> 0 | J12: 0 | K12: 145665.5 | L12: =J$3*F12%+J$4 -> 0 | M12: =K12+J12+I12+L12 -> 145665.5 | N12: =M12*6% + M12 -> 154405.43 | Q12: LOCAL 3 | R12: =RESUMEN!H107 -> 101296.13
A13: 3 amb | C13: 2ºA | D13: Franco, Lucas Fabián | F13: 0.0188 | G13: 169200.01 | H13: =G13 -> 169200.01 | I13: =G13-H13 -> 0 | J13: =M$4*F13 -> 0 | K13: =M$2*F13 -> 188000 | L13: =J$3*F13%+J$4 -> 0 | M13: =ROUND((K13+J13+I13+L13),0) + O13 -> 188000.01 | N13: =ROUND((M13*6% + M13 ),0) + O13 -> 199280.01 | O13: 0.01 | Q13: LOCAL 4 | R13: =RESUMEN!I107 -> 124736.55
A14: 1 amb | C14: 2ºB | D14: Martinez, Diego | F14: 0.0084 | G14: 75600.02 | H14: =G14 -> 75600.02 | I14: =G14-H14 -> 0 | J14: =M$4*F14 -> 0 | K14: =M$2*F14 -> 84000 | L14: =J$3*F14%+J$4 -> 0 | M14: =ROUND((K14+J14+I14+L14),0) + O14 -> 84000.02 | N14: =ROUND((M14*6% + M14 ),0) + O14 -> 89040.02 | O14: =O13+0.01 -> 0.02 | Q14: LOCAL 5 | R14: =RESUMEN!J107 -> 145665.5
A15: 3 amb | C15: 2ºC | D15: Rodriguez, Carlos Alberto Miguel | F15: 0.0201 | G15: 180900.03 | H15: =G15 -> 180900.03 | I15: =G15-H15 -> 0 | J15: =M$4*F15 -> 0 | K15: =M$2*F15 -> 201000 | L15: =J$3*F15%+J$4 -> 0 | M15: =ROUND((K15+J15+I15+L15),0) + O15 -> 201000.03 | N15: =ROUND((M15*6% + M15 ),0) + O15 -> 213060.03 | O15: =O14+0.01 -> 0.03
A16: 2 amb | C16: 2ºD | D16: Ferraro, José | E16: Matias Cuevas | F16: 0.0094 | G16: 165172.04 | I16: =G16-H16 -> 165172.04 | J16: =M$4*F16 -> 0 | K16: =M$2*F16 -> 94000 | L16: 0 | M16: =ROUND((K16+J16+I16+L16),0) + O16 -> 259172.04 | N16: =ROUND((M16*6% + M16 ),0) + O16 -> 274722.04 | O16: =O15+0.01 -> 0.04
A17: 2 amb | C17: 2ºE | D17: Dieci, Matias Orlando | E17: Julieta Damiano/Damiani | F17: 0.0087 | G17: 165600.05 | H17: =87300+78300 -> 165600 | I17: =G17-H17 -> 0.05 | J17: =M$4*F17 -> 0 | K17: =M$2*F17 -> 87000 | L17: =J$3*F17%+J$4 -> 0 | M17: =ROUND((K17+J17+I17+L17),0) + O17 -> 87000.05 | N17: =ROUND((M17*6% + M17 ),0) + O17 -> 92220.05 | O17: =O16+0.01 -> 0.05
A18: 2 amb | C18: 2ºF | D18: Ferraro, Jose | E18: Carolina Massa | F18: 0.0095 | G18: 81429.06 | H18: =G18 -> 81429.06 | I18: =G18-H18 -> 0 | J18: =M$4*F18 -> 0 | K18: =M$2*F18 -> 95000 | L18: =J$3*F18%+J$4 -> 0 | M18: =ROUND((K18+J18+I18+L18),0) + O18 -> 95000.06 | N18: =ROUND((M18*6% + M18 ),0) + O18 -> 100700.06 | O18: =O17+0.01 -> 0.06
A19: 3 amb | C19: 3ºA | D19: Ferraro, Jose | E19: Walter | F19: 0.0165 | G19: 307929.07 | H19: 184976.07 | I19: =G19-H19 -> 122953 | J19: =M$4*F19 -> 0 | K19: =M$2*F19 -> 165000 | L19: =J$3*F19%+J$4 -> 0 | M19: =ROUND((K19+J19+I19+L19),0) + O19 -> 287953.07 | N19: =ROUND((M19*6% + M19 ),0) + O19 -> 305230.07 | O19: =O18+0.01 -> 0.07
A20: 1 amb | C20: 3ºB | D20: Balduzzi, Stella Maris | F20: 0.0073 | G20: 65700.08 | H20: =G20 -> 65700.08 | I20: =G20-H20 -> 0 | J20: =M$4*F20 -> 0 | K20: =M$2*F20 -> 73000 | L20: =J$3*F20%+J$4 -> 0 | M20: =ROUND((K20+J20+I20+L20),0) + O20 -> 73000.08 | N20: =ROUND((M20*6% + M20 ),0) + O20 -> 77380.08 | O20: =O19+0.01 -> 0.08
A21: 3 amb | C21: 3ºC | D21: Ferraro, Jose | F21: 0.0178 | G21: 312772.09 | I21: =G21-H21 -> 312772.09 | J21: =M$4*F21 -> 0 | K21: =M$2*F21 -> 178000 | L21: =J$3*F21%+J$4 -> 0 | M21: =ROUND((K21+J21+I21+L21),0) + O21 -> 490772.09 | N21: =ROUND((M21*6% + M21 ),0) + O21 -> 520218.09 | O21: =O20+0.01 -> 0.09
A22: 2 amb | C22: 3ºD | D22: Heredia, Christian | F22: 0.0094 | G22: 169200.1 | I22: =G22-H22 -> 169200.1 | J22: =M$4*F22 -> 0 | K22: =M$2*F22 -> 94000 | L22: =J$3*F22%+J$4 -> 0 | M22: =ROUND((K22+J22+I22+L22),0) + O22 -> 263200.1 | N22: =ROUND((M22*6% + M22 ),0) + O22 -> 278992.1 | O22: =O21+0.01 -> 0.1
A23: 2 amb | C23: 3ºE | D23: Dallorso, Maria Ines - Dallorso, Ana Paula | F23: 0.0087 | G23: 156600.11 | H23: 165996.11 | I23: =G23-H23 -> -9396 | J23: =M$4*F23 -> 0 | K23: =M$2*F23 -> 87000 | L23: =J$3*F23%+J$4 -> 0 | M23: =ROUND((K23+J23+I23+L23),0) + O23 -> 77604.11 | N23: =ROUND((M23*6% + M23 ),0) + O23 -> 82260.11 | O23: =O22+0.01 -> 0.11
A24: 2 amb | C24: 3ºF | D24: Ayala, Roberto Adrian | F24: 0.0095 | G24: 171000.12 | I24: =G24-H24 -> 171000.12 | J24: =M$4*F24 -> 0 | K24: =M$2*F24 -> 95000 | L24: =J$3*F24%+J$4 -> 0 | M24: =ROUND((K24+J24+I24+L24),0) + O24 -> 266000.12 | N24: =ROUND((M24*6% + M24 ),0) + O24 -> 281960.12 | O24: =O23+0.01 -> 0.12
A25: 3 amb | C25: 4ºA | D25: Barral, Carlos Daniel | F25: 0.0164 | G25: 147600.13 | H25: =G25 -> 147600.13 | I25: =G25-H25 -> 0 | J25: =M$4*F25 -> 0 | K25: =M$2*F25 -> 164000 | L25: =J$3*F25%+J$4 -> 0 | M25: =ROUND((K25+J25+I25+L25),0) + O25 -> 164000.13 | N25: =ROUND((M25*6% + M25 ),0) + O25 -> 173840.13 | O25: =O24+0.01 -> 0.13
A26: 1 amb | C26: 4ºB | D26: Sr. Propietario | E26: Liria | F26: 0.0072 | G26: 64800.14 | H26: =G26 -> 64800.14 | I26: =G26-H26 -> 0 | J26: =M$4*F26 -> 0 | K26: =M$2*F26 -> 72000 | L26: =J$3*F26%+J$4 -> 0 | M26: =ROUND((K26+J26+I26+L26),0) + O26 -> 72000.14 | N26: =ROUND((M26*6% + M26 ),0) + O26 -> 76320.14 | O26: =O25+0.01 -> 0.14
A27: 3 amb | C27: 4ºC | D27: Osipowicz, Ariel Marcelo | F27: 0.0173 | G27: 155700.15 | H27: =G27 -> 155700.15 | I27: =G27-H27 -> 0 | J27: =M$4*F27 -> 0 | K27: =M$2*F27 -> 173000 | L27: =J$3*F27%+J$4 -> 0 | M27: =ROUND((K27+J27+I27+L27),0) + O27 -> 173000.15 | N27: =ROUND((M27*6% + M27 ),0) + O27 -> 183380.15 | O27: =O26+0.01 -> 0.15
A28: 2 amb | C28: 4ºD | D28: Ruiz, Juana Del Valle | F28: 0.0094 | G28: 179352.16 | H28: =G28 -> 179352.16 | I28: =G28-H28 -> 0 | J28: =M$4*F28 -> 0 | K28: =M$2*F28 -> 94000 | L28: =J$3*F28%+J$4 -> 0 | M28: =ROUND((K28+J28+I28+L28),0) + O28 -> 94000.16 | N28: =ROUND((M28*6% + M28 ),0) + O28 -> 99640.16 | O28: =O27+0.01 -> 0.16
A29: 2 amb | C29: 4ºE | D29: Ayala, Roberto Adrian | E29: Iara | F29: 0.0087 | G29: 78300.17 | H29: =G29 -> 78300.17 | I29: =G29-H29 -> 0 | J29: =M$4*F29 -> 0 | K29: =M$2*F29 -> 87000 | L29: =K29*0.1 -> 8700 | M29: =ROUND((K29+J29+I29+L29),0) + O29 -> 95700.17 | N29: =ROUND((M29*6% + M29 ),0) + O29 -> 101442.17 | O29: =O28+0.01 -> 0.17
A30: 2 amb | C30: 4ºF | D30: Ayala, Roberto Adrian | F30: 0.0095 | G30: 181260.18 | H30: =G30 -> 181260.18 | I30: =G30-H30 -> 0 | J30: =M$4*F30 -> 0 | K30: =M$2*F30 -> 95000 | L30: =J$3*F30%+J$4 -> 0 | M30: =ROUND((K30+J30+I30+L30),0) + O30 -> 95000.18 | N30: =ROUND((M30*6% + M30 ),0) + O30 -> 100700.18 | O30: =O29+0.01 -> 0.18
A31: 3 amb | C31: 5ºA | D31: Chehab, Gabriel Adrian | E31: Santiago Rodriguez | F31: 0.0164 | G31: 156600.19 | H31: =G31 -> 156600.19 | I31: =G31-H31 -> 0 | J31: =M$4*F31 -> 0 | K31: =M$2*F31 -> 164000 | L31: =J$3*F31%+J$4 -> 0 | M31: =ROUND((K31+J31+I31+L31),0) + O31 -> 164000.19 | N31: =ROUND((M31*6% + M31 ),0) + O31 -> 173840.19 | O31: =O30+0.01 -> 0.19
A32: 1 amb | C32: 5ºB | D32: Mesa, Mariano | F32: 0.0072 | G32: 64800.2 | H32: =G32 -> 64800.2 | I32: =G32-H32 -> 0 | J32: =M$4*F32 -> 0 | K32: =M$2*F32 -> 72000 | L32: =J$3*F32%+J$4 -> 0 | M32: =ROUND((K32+J32+I32+L32),0) + O32 -> 72000.2 | N32: =ROUND((M32*6% + M32 ),0) + O32 -> 76320.2 | O32: =O31+0.01 -> 0.2
A33: 3 amb | C33: 5ºC | D33: Di Mito, Vicente Argentino - Serantes, Mabel | F33: 0.0173 | G33: 434967.21 | I33: =G33-H33 -> 434967.21 | J33: =M$4*F33 -> 0 | K33: =M$2*F33 -> 173000 | L33: =J$3*F33%+J$4 -> 0 | M33: =ROUND((K33+J33+I33+L33),0) + O33 -> 607967.21 | N33: =ROUND((M33*6% + M33 ),0) + O33 -> 644445.21 | O33: =O32+0.01 -> 0.21
A34: 2 amb | C34: 5ºD | D34: Ayala, Agustin | F34: 0.0094 | G34: 179352.22 | H34: =G34 -> 179352.22 | I34: =G34-H34 -> 0 | J34: =M$4*F34 -> 0 | K34: =M$2*F34 -> 94000 | L34: =J$3*F34%+J$4 -> 0 | M34: =ROUND((K34+J34+I34+L34),0) + O34 -> 94000.22 | N34: =ROUND((M34*6% + M34 ),0) + O34 -> 99640.22 | O34: =O33+0.01 -> 0.22
A35: 2 amb | C35: 5ºE | D35: Ayala, Roberto Adrian | F35: 0.0087 | G35: 156600.23 | H35: =G35 -> 156600.23 | I35: =G35-H35 -> 0 | J35: =M$4*F35 -> 0 | K35: =M$2*F35 -> 87000 | L35: =J$3*F35%+J$4 -> 0 | M35: =ROUND((K35+J35+I35+L35),0) + O35 -> 87000.23 | N35: =ROUND((M35*6% + M35 ),0) + O35 -> 92220.23 | O35: =O34+0.01 -> 0.23 | P35: COCHERA 31
A36: 2 amb | C36: 5ºF | D36: Ayala, Agustin | F36: 0.0095 | G36: 181260.24 | H36: =G36 -> 181260.24 | I36: =G36-H36 -> 0 | J36: =M$4*F36 -> 0 | K36: =M$2*F36 -> 95000 | L36: =J$3*F36%+J$4 -> 0 | M36: =ROUND((K36+J36+I36+L36),0) + O36 -> 95000.24 | N36: =ROUND((M36*6% + M36 ),0) + O36 -> 100700.24 | O36: =O35+0.01 -> 0.24
A37: 3 amb | C37: 6ºA | D37: Morandi, Victoria Ayelen | Calvo, Luciano Ezequiel | F37: 0.0164 | G37: 147600.25 | H37: =G37 -> 147600.25 | I37: =G37-H37 -> 0 | J37: =M$4*F37 -> 0 | K37: =M$2*F37 -> 164000 | L37: =J$3*F37%+J$4 -> 0 | M37: =ROUND((K37+J37+I37+L37),0) + O37 -> 164000.25 | N37: =ROUND((M37*6% + M37 ),0) + O37 -> 173840.25 | O37: =O36+0.01 -> 0.25
A38: 1 amb | C38: 6ºB | D38: Grizak Ruben | E38: Christian | F38: 0.0072 | G38: 64800.26 | H38: =G38 -> 64800.26 | I38: =G38-H38 -> 0 | J38: =M$4*F38 -> 0 | K38: =M$2*F38 -> 72000 | L38: =J$3*F38%+J$4 -> 0 | M38: =ROUND((K38+J38+I38+L38),0) + O38 -> 72000.26 | N38: =ROUND((M38*6% + M38 ),0) + O38 -> 76320.26 | O38: =O37+0.01 -> 0.26
A39: 3 amb | C39: 6ºC | D39: Nuñez Leonel - Corrieri Giuliana | F39: 0.0173 | G39: 155700.27 | H39: =G39 -> 155700.27 | I39: =G39-H39 -> 0 | J39: =M$4*F39 -> 0 | K39: =M$2*F39 -> 173000 | L39: =J$3*F39%+J$4 -> 0 | M39: =ROUND((K39+J39+I39+L39),0) + O39 -> 173000.27 | N39: =ROUND((M39*6% + M39 ),0) + O39 -> 183380.27 | O39: =O38+0.01 -> 0.27 | P39: COCHERA 33 | Q39: COCHERA 33
A40: 2 amb | C40: 6ºD | D40: Sr propietario | F40: 0.0094 | G40: 84600.28 | H40: =G40 -> 84600.28 | I40: =G40-H40 -> 0 | J40: =M$4*F40 -> 0 | K40: =M$2*F40 -> 94000 | L40: =J$3*F40%+J$4 -> 0 | M40: =ROUND((K40+J40+I40+L40),0) + O40 -> 94000.28 | N40: =ROUND((M40*6% + M40 ),0) + O40 -> 99640.28 | O40: =O39+0.01 -> 0.28 | Q40: mariano hecimovic
A41: 2 amb | C41: 6ºE | D41: Dieci, Matias Orlando | E41: Gaston Smith | F41: 0.0087 | G41: 82998.29 | H41: =G41 -> 82998.29 | I41: =G41-H41 -> 0 | J41: =M$4*F41 -> 0 | K41: =M$2*F41 -> 87000 | L41: =J$3*F41%+J$4 -> 0 | M41: =ROUND((K41+J41+I41+L41),0) + O41 -> 87000.29 | N41: =ROUND((M41*6% + M41 ),0) + O41 -> 92220.29 | O41: =O40+0.01 -> 0.29
A42: 2 amb | C42: 6ºF | D42: Mazzia Alexia | F42: 0.0095 | G42: 85500.3 | H42: =G42 -> 85500.3 | I42: =G42-H42 -> 0 | J42: =M$4*F42 -> 0 | K42: =M$2*F42 -> 95000 | L42: =J$3*F42%+J$4 -> 0 | M42: =ROUND((K42+J42+I42+L42),0) + O42 -> 95000.3 | N42: =ROUND((M42*6% + M42 ),0) + O42 -> 100700.3 | O42: =O41+0.01 -> 0.3
A43: 3 amb | C43: 7ºA | D43: Campelo, Mariano | F43: 0.0164 | G43: 147600.31 | H43: =G43 -> 147600.31 | I43: =G43-H43 -> 0 | J43: =M$4*F43 -> 0 | K43: =M$2*F43 -> 164000 | L43: =J$3*F43%+J$4 -> 0 | M43: =ROUND((K43+J43+I43+L43),0) + O43 -> 164000.31 | N43: =ROUND((M43*6% + M43 ),0) + O43 -> 173840.31 | O43: =O42+0.01 -> 0.31
A44: 1 amb | C44: 7ºB | D44: Paes, Yazmin Luciana | F44: 0.0072 | G44: 64800.32 | H44: =G44 -> 64800.32 | I44: =G44-H44 -> 0 | J44: =M$4*F44 -> 0 | K44: =M$2*F44 -> 72000 | L44: =J$3*F44%+J$4 -> 0 | M44: =ROUND((K44+J44+I44+L44),0) + O44 -> 72000.32 | N44: =ROUND((M44*6% + M44 ),0) + O44 -> 76320.32 | O44: =O43+0.01 -> 0.32
A45: 3 amb | C45: 7ºC | D45: Gonzalez Fedullo, Roxana y Valeria | F45: 0.0173 | G45: 155700.33 | H45: =G45 -> 155700.33 | I45: =G45-H45 -> 0 | J45: =M$4*F45 -> 0 | K45: =M$2*F45 -> 173000 | L45: =J$3*F45%+J$4 -> 0 | M45: =ROUND((K45+J45+I45+L45),0) + O45 -> 173000.33 | N45: =ROUND((M45*6% + M45 ),0) + O45 -> 183380.33 | O45: =O44+0.01 -> 0.33
A46: 2 amb | C46: 7ºD | D46: Solleiro, Carolina Mabel | F46: 0.0094 | G46: 102059.34 | H46: 102060 | I46: =G46-H46 -> -0.66 | J46: =M$4*F46 -> 0 | K46: =M$2*F46 -> 94000 | L46: =J$3*F46%+J$4 -> 0 | M46: =ROUND((K46+J46+I46+L46),0) + O46 -> 93999.34 | N46: =ROUND((M46*6% + M46 ),0) + O46 -> 99639.34 | O46: =O45+0.01 -> 0.34 | P46: Walter Javier Dimiziunas
A47: 2 amb | C47: 7ºE | D47: Leyes, Javier | F47: 0.0087 | G47: 78300.35 | H47: =G47 -> 78300.35 | I47: =G47-H47 -> 0 | J47: =M$4*F47 -> 0 | K47: =M$2*F47 -> 87000 | L47: =J$3*F47%+J$4 -> 0 | M47: =ROUND((K47+J47+I47+L47),0) + O47 -> 87000.35 | N47: =ROUND((M47*6% + M47 ),0) + O47 -> 92220.35 | O47: =O46+0.01 -> 0.35
A48: 2 amb | C48: 7ºF | D48: Puente, Matias | F48: 0.0095 | G48: 85500.36 | H48: =G48 -> 85500.36 | I48: =G48-H48 -> 0 | J48: =M$4*F48 -> 0 | K48: =M$2*F48 -> 95000 | L48: =J$3*F48%+J$4 -> 0 | M48: =ROUND((K48+J48+I48+L48),0) + O48 -> 95000.36 | N48: =ROUND((M48*6% + M48 ),0) + O48 -> 100700.36 | O48: =O47+0.01 -> 0.36
A49: 3 amb | C49: 8ºA | D49: Campelo, Mariano | F49: 0.0164 | G49: 147600.37 | H49: =G49 -> 147600.37 | I49: =G49-H49 -> 0 | J49: =M$4*F49 -> 0 | K49: =M$2*F49 -> 164000 | L49: =J$3*F49%+J$4 -> 0 | M49: =ROUND((K49+J49+I49+L49),0) + O49 -> 164000.37 | N49: =ROUND((M49*6% + M49 ),0) + O49 -> 173840.37 | O49: =O48+0.01 -> 0.37
A50: 1 amb | C50: 8ºB | D50: Morvillo, Mariana Yanil | E50: Aylen | F50: 0.0072 | G50: 64800.38 | H50: =G50 -> 64800.38 | I50: =G50-H50 -> 0 | J50: =M$4*F50 -> 0 | K50: =M$2*F50 -> 72000 | L50: =J$3*F50%+J$4 -> 0 | M50: =ROUND((K50+J50+I50+L50),0) + O50 -> 72000.38 | N50: =ROUND((M50*6% + M50 ),0) + O50 -> 76320.38 | O50: =O49+0.01 -> 0.38
A51: 3 amb | C51: 8ºC | D51: Frontale, Federico Carlos | Celentano, Alejandra Verónica | F51: 0.0173 | G51: 155700.39 | H51: =G51 -> 155700.39 | I51: =G51-H51 -> 0 | J51: =M$4*F51 -> 0 | K51: =M$2*F51 -> 173000 | L51: =J$3*F51%+J$4 -> 0 | M51: =ROUND((K51+J51+I51+L51),0) + O51 -> 173000.39 | N51: =ROUND((M51*6% + M51 ),0) + O51 -> 183380.39 | O51: =O50+0.01 -> 0.39
A52: 2 amb | C52: 8ºD | D52: Argul, Sergio Walter - Taboada, María Paz | F52: 0.0094 | G52: 84600.4 | H52: 89676.4 | I52: =G52-H52 -> -5076 | J52: =M$4*F52 -> 0 | K52: =M$2*F52 -> 94000 | L52: =J$3*F52%+J$4 -> 0 | M52: =ROUND((K52+J52+I52+L52),0) + O52 -> 88924.4 | N52: =ROUND((M52*6% + M52 ),0) + O52 -> 94260.4 | O52: =O51+0.01 -> 0.4
A53: 2 amb | C53: 8ºE | D53: Sr propietario | F53: 0.0087 | G53: 78300.41 | H53: =G53 -> 78300.41 | I53: =G53-H53 -> 0 | J53: =M$4*F53 -> 0 | K53: =M$2*F53 -> 87000 | L53: =J$3*F53%+J$4 -> 0 | M53: =ROUND((K53+J53+I53+L53),0) + O53 -> 87000.41 | N53: =ROUND((M53*6% + M53 ),0) + O53 -> 92220.41 | O53: =O52+0.01 -> 0.41 | Q53: el de sergio
A54: 2 amb | C54: 8ºF | D54: Arias, Mariana Laura | F54: 0.0095 | G54: 85500.42 | H54: =G54 -> 85500.42 | I54: =G54-H54 -> 0 | J54: =M$4*F54 -> 0 | K54: =M$2*F54 -> 95000 | L54: =J$3*F54%+J$4 -> 0 | M54: =ROUND((K54+J54+I54+L54),0) + O54 -> 95000.42 | N54: =ROUND((M54*6% + M54 ),0) + O54 -> 100700.42 | O54: =O53+0.01 -> 0.42 | P54: alonso sabrina eugenia
A55: 3 amb | C55: 9ºA | D55: Fanjul, Alejandro Rubén Marcelo | F55: 0.0164 | G55: 147600.43 | H55: =G55 -> 147600.43 | I55: =G55-H55 -> 0 | J55: =M$4*F55 -> 0 | K55: =M$2*F55 -> 164000 | L55: =J$3*F55%+J$4 -> 0 | M55: =ROUND((K55+J55+I55+L55),0) + O55 -> 164000.43 | N55: =ROUND((M55*6% + M55 ),0) + O55 -> 173840.43 | O55: =O54+0.01 -> 0.43
A56: 1 amb | C56: 9ºB | D56: Fanjul, Alejandro Rubén Marcelo | F56: 0.0072 | G56: 64800.44 | H56: =G56 -> 64800.44 | I56: =G56-H56 -> 0 | J56: =M$4*F56 -> 0 | K56: =M$2*F56 -> 72000 | L56: =J$3*F56%+J$4 -> 0 | M56: =ROUND((K56+J56+I56+L56),0) + O56 -> 72000.44 | N56: =ROUND((M56*6% + M56 ),0) + O56 -> 76320.44 | O56: =O55+0.01 -> 0.44
A57: 3 amb | C57: 9ºC | D57: Franchino, Mauro | F57: 0.0173 | G57: 155700.45 | H57: =G57 -> 155700.45 | I57: =G57-H57 -> 0 | J57: =M$4*F57 -> 0 | K57: =M$2*F57 -> 173000 | L57: =J$3*F57%+J$4 -> 0 | M57: =ROUND((K57+J57+I57+L57),0) + O57 -> 173000.45 | N57: =ROUND((M57*6% + M57 ),0) + O57 -> 183380.45 | O57: =O56+0.01 -> 0.45
A58: 2 amb | C58: 9ºD | D58: Cerra, Antonio Osvaldo | E58: Adrian | F58: 0.0094 | G58: 236340.46 | H58: =G58 -> 236340.46 | I58: =G58-H58 -> 0 | J58: =M$4*F58 -> 0 | K58: =M$2*F58 -> 94000 | L58: =J$3*F58%+J$4 -> 0 | M58: =ROUND((K58+J58+I58+L58),0) + O58 -> 94000.46 | N58: =ROUND((M58*6% + M58 ),0) + O58 -> 99640.46 | O58: =O57+0.01 -> 0.46
A59: 2 amb | C59: 9ºE | D59: Dieci, Matias Orlando | F59: 0.0087 | G59: 78300.47 | H59: =G59+169200 -> 247500.47 | I59: =G59-H59 -> -169200 | J59: =M$4*F59 -> 0 | K59: =M$2*F59 -> 87000 | L59: =J$3*F59%+J$4 -> 0 | M59: =ROUND((K59+J59+I59+L59),0) + O59 -> -82199.53 | N59: =ROUND((M59*6% + M59 ),0) + O59 -> -87131.53 | O59: =O58+0.01 -> 0.47
A60: 2 amb | C60: 9ºF | D60: Rosales, Rubén Darío | F60: 0.0095 | G60: 85500.48 | H60: =G60 -> 85500.48 | I60: =G60-H60 -> 0 | J60: =M$4*F60 -> 0 | K60: =M$2*F60 -> 95000 | L60: =J$3*F60%+J$4 -> 0 | M60: =ROUND((K60+J60+I60+L60),0) + O60 -> 95000.48 | N60: =ROUND((M60*6% + M60 ),0) + O60 -> 100701.48 | O60: =O59+0.01 -> 0.48
A61: 3 amb | C61: 10ºA | D61: Puisys Guillermo Antonio | F61: 0.0164 | G61: 147600.49 | H61: =G61 -> 147600.49 | I61: =G61-H61 -> 0 | J61: =M$4*F61 -> 0 | K61: =M$2*F61 -> 164000 | L61: =J$3*F61%+J$4 -> 0 | M61: =ROUND((K61+J61+I61+L61),0) + O61 -> 164000.49 | N61: =ROUND((M61*6% + M61 ),0) + O61 -> 173841.49 | O61: =O60+0.01 -> 0.49
A62: 1 amb | C62: 10ºB | D62: Lange, Gustavo Daniel | F62: 0.0072 | G62: 181029.5 | I62: =G62-H62 -> 181029.5 | J62: =M$4*F62 -> 0 | K62: =M$2*F62 -> 72000 | L62: =J$3*F62%+J$4 -> 0 | M62: =ROUND((K62+J62+I62+L62),0) + O62 -> 253030.5 | N62: =ROUND((M62*6% + M62 ),0) + O62 -> 268212.5 | O62: =O61+0.01 -> 0.5
A63: 3 amb | C63: 10ºC | D63: Espósito, Franco Ezequiel | F63: 0.0173 | G63: 155700.51 | H63: =G63 -> 155700.51 | I63: =G63-H63 -> 0 | J63: =M$4*F63 -> 0 | K63: =M$2*F63 -> 173000 | L63: =J$3*F63%+J$4 -> 0 | M63: =ROUND((K63+J63+I63+L63),0) + O63 -> 173000.51 | N63: =ROUND((M63*6% + M63 ),0) + O63 -> 183381.51 | O63: =O62+0.01 -> 0.51
A64: 2 amb | C64: 10ºD | D64: Lobato, Lorena - Vega, Maximiliano | F64: 0.0094 | G64: 84600.52 | H64: 89677.52 | I64: =G64-H64 -> -5077 | J64: =M$4*F64 -> 0 | K64: =M$2*F64 -> 94000 | L64: =J$3*F64%+J$4 -> 0 | M64: =ROUND((K64+J64+I64+L64),0) + O64 -> 88923.52 | N64: =ROUND((M64*6% + M64 ),0) + O64 -> 94259.52 | O64: =O63+0.01 -> 0.52
A65: 2 amb | C65: 10ºE | D65: Sr propietario | F65: 0.0087 | G65: 78300.53 | H65: =G65 -> 78300.53 | I65: =G65-H65 -> 0 | J65: =M$4*F65 -> 0 | K65: =M$2*F65 -> 87000 | L65: =J$3*F65%+J$4 -> 0 | M65: =ROUND((K65+J65+I65+L65),0) + O65 -> 87000.53 | N65: =ROUND((M65*6% + M65 ),0) + O65 -> 92221.53 | O65: =O64+0.01 -> 0.53 | Q65: mariano hecimovic
A66: 2 amb | C66: 10ºF | D66: Ramos, Sergio Eugenio | F66: 0.0095 | G66: 85500.54 | H66: =G66 -> 85500.54 | I66: =G66-H66 -> 0 | J66: =M$4*F66 -> 0 | K66: =M$2*F66 -> 95000 | L66: =J$3*F66%+J$4 -> 0 | M66: =ROUND((K66+J66+I66+L66),0) + O66 -> 95000.54 | N66: =ROUND((M66*6% + M66 ),0) + O66 -> 100701.54 | O66: =O65+0.01 -> 0.54
A67: 4 amb | C67: 11ºA/B | D67: Mosquera, Julio Rodolfo | Cuzzolino, Daniela Carol | F67: 0.0235 | G67: 211500.55 | H67: =G67 -> 211500.55 | I67: =G67-H67 -> 0 | J67: =M$4*F67 -> 0 | K67: =M$2*F67 -> 235000 | L67: =J$3*F67%+J$4 -> 0 | M67: =ROUND((K67+J67+I67+L67),0) + O67 -> 235000.55 | N67: =ROUND((M67*6% + M67 ),0) + O67 -> 249101.55 | O67: =O66+0.01 -> 0.55
A68: 3 amb | C68: 11ºC | D68: Silvestre Villarruel Eduardo | F68: 0.0173 | G68: 155700.56 | H68: 165043.61 | I68: =G68-H68 -> -9343.05 | J68: =M$4*F68 -> 0 | K68: =M$2*F68 -> 173000 | L68: =J$3*F68%+J$4 -> 0 | M68: =ROUND((K68+J68+I68+L68),0) + O68 -> 163657.56 | N68: =ROUND((M68*6% + M68 ),0) + O68 -> 173477.56 | O68: =O67+0.01 -> 0.56
A69: 2 amb | C69: 11ºD | D69: Sr. Propietario | F69: 0.0094 | G69: 236342.57 | H69: =G69 -> 236342.57 | I69: =G69-H69 -> 0 | J69: =M$4*F69 -> 0 | K69: =M$2*F69 -> 94000 | L69: =J$3*F69%+J$4 -> 0 | M69: =ROUND((K69+J69+I69+L69),0) + O69 -> 94000.57 | N69: =ROUND((M69*6% + M69 ),0) + O69 -> 99641.57 | O69: =O68+0.01 -> 0.57
A70: 2 amb | C70: 11ºE | D70: Argúl, Adrián Norberto | E70: Lara | F70: 0.0087 | G70: 218743.58 | H70: =G70 -> 218743.58 | I70: =G70-H70 -> 0 | J70: =M$4*F70 -> 0 | K70: =M$2*F70 -> 87000 | L70: =J$3*F70%+J$4 -> 0 | M70: =ROUND((K70+J70+I70+L70),0) + O70 -> 87000.58 | N70: =ROUND((M70*6% + M70 ),0) + O70 -> 92221.58 | O70: =O69+0.01 -> 0.58
A71: 2 amb | C71: 11ºF | D71: Lobato, Lorena - Vega, Maximiliano | F71: 0.0095 | G71: 85500.59 | H71: 90631.59 | I71: =G71-H71 -> -5131 | J71: =M$4*F71 -> 0 | K71: =M$2*F71 -> 95000 | L71: =J$3*F71%+J$4 -> 0 | M71: =ROUND((K71+J71+I71+L71),0) + O71 -> 89869.59 | N71: =ROUND((M71*6% + M71 ),0) + O71 -> 95262.59 | O71: =O70+0.01 -> 0.59
A72: 4 amb | C72: 12ºA/B | D72: Luciano, Carmen Veronica - Rey, Javier Pablo | F72: 0.0235 | G72: 211500.6 | I72: =G72-H72 -> 211500.6 | J72: =M$4*F72 -> 0 | K72: =M$2*F72 -> 235000 | L72: =J$3*F72%+J$4 -> 0 | M72: =ROUND((K72+J72+I72+L72),0) + O72 -> 446501.6 | N72: =ROUND((M72*6% + M72 ),0) + O72 -> 473292.6 | O72: =O71+0.01 -> 0.6
A73: 3 amb | C73: 12ºC | D73: Hernandez, Marisa Beatriz - Hernandez, Adrian Jose | F73: 0.0173 | G73: 155700.61 | H73: =G73 -> 155700.61 | I73: =G73-H73 -> 0 | J73: =M$4*F73 -> 0 | K73: =M$2*F73 -> 173000 | L73: =J$3*F73%+J$4 -> 0 | M73: =ROUND((K73+J73+I73+L73),0) + O73 -> 173000.61 | N73: =ROUND((M73*6% + M73 ),0) + O73 -> 183381.61 | O73: =O72+0.01 -> 0.61
A74: 2 amb | C74: 12ºD | D74: Morini, Micaela | F74: 0.0094 | G74: 179354.62 | H74: =G74 -> 179354.62 | I74: =G74-H74 -> 0 | J74: =M$4*F74 -> 0 | K74: =M$2*F74 -> 94000 | L74: =K74*0.3 -> 28200 | M74: =ROUND((K74+J74+I74+L74),0) + O74 -> 122200.62 | N74: =ROUND((M74*6% + M74 ),0) + O74 -> 129533.62 | O74: =O73+0.01 -> 0.62
A75: 2 amb | C75: 12ºE | D75: Armerding, Jorge | E75: Agustina | F75: 0.0087 | G75: 78300.63 | H75: =G75 -> 78300.63 | I75: =G75-H75 -> 0 | J75: =M$4*F75 -> 0 | K75: =M$2*F75 -> 87000 | L75: =J$3*F75%+J$4 -> 0 | M75: =ROUND((K75+J75+I75+L75),0) + O75 -> 87000.63 | N75: =ROUND((M75*6% + M75 ),0) + O75 -> 92221.63 | O75: =O74+0.01 -> 0.63
A76: 2 amb | C76: 12ºF | D76: Bilyj, Josefa Catalina | F76: 0.0095 | G76: 80646.64 | H76: =G76 -> 80646.64 | I76: =G76-H76 -> 0 | J76: =M$4*F76 -> 0 | K76: =M$2*F76 -> 95000 | L76: =J$3*F76%+J$4 -> 0 | M76: =ROUND((K76+J76+I76+L76),0) + O76 -> 95000.64 | N76: =ROUND((M76*6% + M76 ),0) + O76 -> 100701.64 | O76: =O75+0.01 -> 0.64 | P76: Laura Quintas Perez
A77: 4 amb | C77: 13ºA/B | D77: Gazzaneo, Francisco | F77: 0.0235 | G77: 211500.65 | H77: =232202-H90 -> 211501.22 | I77: =G77-H77 -> -0.57 | J77: =M$4*F77 -> 0 | K77: =M$2*F77 -> 235000 | L77: =J$3*F77%+J$4 -> 0 | M77: =ROUND((K77+J77+I77+L77),0) + O77 -> 234999.65 | N77: =ROUND((M77*6% + M77 ),0) + O77 -> 249100.65 | O77: =O76+0.01 -> 0.65
A78: 3 amb | C78: 13ºC | D78: Argentino, Javier Leonardo | F78: 0.0173 | G78: 155700.66 | H78: =G78 -> 155700.66 | I78: =G78-H78 -> 0 | J78: =M$4*F78 -> 0 | K78: =M$2*F78 -> 173000 | L78: =J$3*F78%+J$4 -> 0 | M78: =ROUND((K78+J78+I78+L78),0) + O78 -> 173000.66 | N78: =ROUND((M78*6% + M78 ),0) + O78 -> 183381.66 | O78: =O77+0.01 -> 0.66
A79: 2 amb | C79: 13ºD | D79: Scardigno, Gabriela Susana - Ripoll, Luis Alberto | F79: 0.0094 | G79: 84600.67 | H79: =G79 -> 84600.67 | I79: =G79-H79 -> 0 | J79: =M$4*F79 -> 0 | K79: =M$2*F79 -> 94000 | L79: =J$3*F79%+J$4 -> 0 | M79: =ROUND((K79+J79+I79+L79),0) + O79 -> 94000.67 | N79: =ROUND((M79*6% + M79 ),0) + O79 -> 99641.67 | O79: =O78+0.01 -> 0.67
A80: 2 amb | C80: 13ºE | D80: Quiñones, Carlos Eduardo | F80: 0.0087 | G80: 78300.68 | H80: =G80 -> 78300.68 | I80: =G80-H80 -> 0 | J80: =M$4*F80 -> 0 | K80: =M$2*F80 -> 87000 | L80: =J$3*F80%+J$4 -> 0 | M80: =ROUND((K80+J80+I80+L80),0) + O80 -> 87000.68 | N80: =ROUND((M80*6% + M80 ),0) + O80 -> 92221.68 | O80: =O79+0.01 -> 0.68
A81: 2 amb | C81: 13ºF | D81: Mosquera, José Elias | F81: 0.0095 | G81: 249211.69 | H81: =G81 -> 249211.69 | I81: =G81-H81 -> 0 | J81: =M$4*F81 -> 0 | K81: =M$2*F81 -> 95000 | L81: =K81*0.3 -> 28500 | M81: =ROUND((K81+J81+I81+L81),0) + O81 -> 123500.69 | N81: =ROUND((M81*6% + M81 ),0) + O81 -> 130911.69 | O81: =O80+0.01 -> 0.69
C82: COCH 1 | D82: Osipowicz, Ariel Marcelo | F82: 0.0023 | G82: 20700.7 | H82: =G82 -> 20700.7 | I82: =G82-H82 -> 0 | J82: =M$4*F82 -> 0 | K82: =M$2*F82 -> 23000 | L82: =J$3*F82%+J$4 -> 0 | M82: =ROUND((K82+J82+I82+L82),0) + O82 -> 23000.7 | N82: =ROUND((M82*6% + M82 ),0) + O82 -> 24381.7 | O82: =O81+0.01 -> 0.7
C83: COCH 2 | D83: Sr propietario | F83: 0.0023 | G83: 20700.71 | H83: =G83 -> 20700.71 | I83: =G83-H83 -> 0 | J83: =M$4*F83 -> 0 | K83: =M$2*F83 -> 23000 | L83: =J$3*F83%+J$4 -> 0 | M83: =ROUND((K83+J83+I83+L83),0) + O83 -> 23000.71 | N83: =ROUND((M83*6% + M83 ),0) + O83 -> 24381.71 | O83: =O82+0.01 -> 0.71
C84: COCH 3 | D84: Paes, Yazmin Luciana | F84: 0.0023 | G84: 20700.72 | H84: 21943.72 | I84: =G84-H84 -> -1243 | J84: =M$4*F84 -> 0 | K84: =M$2*F84 -> 23000 | L84: =J$3*F84%+J$4 -> 0 | M84: =ROUND((K84+J84+I84+L84),0) + O84 -> 21757.72 | N84: =ROUND((M84*6% + M84 ),0) + O84 -> 23063.72 | O84: =O83+0.01 -> 0.72
C85: COCH 4 | D85: Puisys Guillermo Antonio | F85: 0.0023 | G85: 20700.73 | H85: =G85 -> 20700.73 | I85: =G85-H85 -> 0 | J85: =M$4*F85 -> 0 | K85: =M$2*F85 -> 23000 | L85: =J$3*F85%+J$4 -> 0 | M85: =ROUND((K85+J85+I85+L85),0) + O85 -> 23000.73 | N85: =ROUND((M85*6% + M85 ),0) + O85 -> 24381.73 | O85: =O84+0.01 -> 0.73
C86: COCH 5 | D86: Arias, Mariana Laura | F86: 0.0023 | G86: 20700.74 | H86: =G86 -> 20700.74 | I86: =G86-H86 -> 0 | J86: =M$4*F86 -> 0 | K86: =M$2*F86 -> 23000 | L86: =J$3*F86%+J$4 -> 0 | M86: =ROUND((K86+J86+I86+L86),0) + O86 -> 23000.74 | N86: =ROUND((M86*6% + M86 ),0) + O86 -> 24381.74 | O86: =O85+0.01 -> 0.74 | P86: alonso sabrina eugenia
C87: COCH 6 | D87: Dimito, Vicente Argentino - Cerantes , Mabel | F87: 0.0023 | G87: 57830.75 | I87: =G87-H87 -> 57830.75 | J87: =M$4*F87 -> 0 | K87: =M$2*F87 -> 23000 | L87: =J$3*F87%+J$4 -> 0 | M87: =ROUND((K87+J87+I87+L87),0) + O87 -> 80831.75 | N87: =ROUND((M87*6% + M87 ),0) + O87 -> 85682.75 | O87: =O86+0.01 -> 0.75
C88: COCH 7 | D88: Campelo, Mariano | F88: 0.0023 | G88: 20700.76 | H88: =G88 -> 20700.76 | I88: =G88-H88 -> 0 | J88: =M$4*F88 -> 0 | K88: =M$2*F88 -> 23000 | L88: =J$3*F88%+J$4 -> 0 | M88: =ROUND((K88+J88+I88+L88),0) + O88 -> 23000.76 | N88: =ROUND((M88*6% + M88 ),0) + O88 -> 24381.76 | O88: =O87+0.01 -> 0.76
C89: COCH 8 | D89: Campelo, Mariano | F89: 0.0023 | G89: 20700.77 | H89: =G89 -> 20700.77 | I89: =G89-H89 -> 0 | J89: =M$4*F89 -> 0 | K89: =M$2*F89 -> 23000 | L89: =J$3*F89%+J$4 -> 0 | M89: =ROUND((K89+J89+I89+L89),0) + O89 -> 23000.77 | N89: =ROUND((M89*6% + M89 ),0) + O89 -> 24381.77 | O89: =O88+0.01 -> 0.77
C90: COCH 9 | D90: Gazzaneo, Francisco | F90: 0.0023 | G90: 20700.78 | H90: =G90 -> 20700.78 | I90: =G90-H90 -> 0 | J90: =M$4*F90 -> 0 | K90: =M$2*F90 -> 23000 | L90: =J$3*F90%+J$4 -> 0 | M90: =ROUND((K90+J90+I90+L90),0) + O90 -> 23000.78 | N90: =ROUND((M90*6% + M90 ),0) + O90 -> 24381.78 | O90: =O89+0.01 -> 0.78
C91: COCH 10 | D91: Cerra, Antonio Osvaldo | F91: 0.0023 | G91: 57830.79 | I91: =G91-H91 -> 57830.79 | J91: =M$4*F91 -> 0 | K91: =M$2*F91 -> 23000 | L91: =J$3*F91%+J$4 -> 0 | M91: =ROUND((K91+J91+I91+L91),0) + O91 -> 80831.79 | N91: =ROUND((M91*6% + M91 ),0) + O91 -> 85682.79 | O91: =O90+0.01 -> 0.79
C92: COCH 11 | D92: Osipowicz, Ariel Marcelo | F92: 0.0023 | G92: 20700.8 | H92: =G92 -> 20700.8 | I92: =G92-H92 -> 0 | J92: =M$4*F92 -> 0 | K92: =M$2*F92 -> 23000 | L92: =J$3*F92%+J$4 -> 0 | M92: =ROUND((K92+J92+I92+L92),0) + O92 -> 23000.8 | N92: =ROUND((M92*6% + M92 ),0) + O92 -> 24381.8 | O92: =O91+0.01 -> 0.8
C93: COCH 12 | D93: Dieci, Matias Orlando | F93: 0.0023 | G93: 21943.81 | H93: =G93 -> 21943.81 | I93: =G93-H93 -> 0 | J93: =M$4*F93 -> 0 | K93: =M$2*F93 -> 23000 | L93: =J$3*F93%+J$4 -> 0 | M93: =ROUND((K93+J93+I93+L93),0) + O93 -> 23000.81 | N93: =ROUND((M93*6% + M93 ),0) + O93 -> 24381.81 | O93: =O92+0.01 -> 0.81
C94: COCH 13 | D94: Scardigno, Gabriela Susana - Ripoli, Luis Alberto | F94: 0.0023 | G94: 20700.82 | H94: =G94 -> 20700.82 | I94: =G94-H94 -> 0 | J94: =M$4*F94 -> 0 | K94: =M$2*F94 -> 23000 | L94: =J$3*F94%+J$4 -> 0 | M94: =ROUND((K94+J94+I94+L94),0) + O94 -> 23000.82 | N94: =ROUND((M94*6% + M94 ),0) + O94 -> 24381.82 | O94: =O93+0.01 -> 0.82
C95: COCH 14 | D95: Fontale Federico Carlos - Celentano Alejandra Veronica | F95: 0.0023 | G95: 20700.83 | H95: =G95 -> 20700.83 | I95: =G95-H95 -> 0 | J95: =M$4*F95 -> 0 | K95: =M$2*F95 -> 23000 | L95: =J$3*F95%+J$4 -> 0 | M95: =ROUND((K95+J95+I95+L95),0) + O95 -> 23000.83 | N95: =ROUND((M95*6% + M95 ),0) + O95 -> 24381.83 | O95: =O94+0.01 -> 0.83
C96: COCH 15 | D96: Hernandez, Marisa Beatriz - Hernandez, Adrian Jose | F96: 0.0023 | G96: 20700.84 | H96: =G96 -> 20700.84 | I96: =G96-H96 -> 0 | J96: =M$4*F96 -> 0 | K96: =M$2*F96 -> 23000 | L96: =J$3*F96%+J$4 -> 0 | M96: =ROUND((K96+J96+I96+L96),0) + O96 -> 23000.84 | N96: =ROUND((M96*6% + M96 ),0) + O96 -> 24381.84 | O96: =O95+0.01 -> 0.84
C97: COCH 16 | D97: Mesa, Mariano | F97: 0.0023 | G97: 20700.85 | H97: =G97 -> 20700.85 | I97: =G97-H97 -> 0 | J97: =M$4*F97 -> 0 | K97: =M$2*F97 -> 23000 | L97: =J$3*F97%+J$4 -> 0 | M97: =ROUND((K97+J97+I97+L97),0) + O97 -> 23000.85 | N97: =ROUND((M97*6% + M97 ),0) + O97 -> 24381.85 | O97: =O96+0.01 -> 0.85
C98: COCH 17 | D98: Espósito, Franco Ezequiel | F98: 0.0023 | G98: 20700.86 | H98: =G98 -> 20700.86 | I98: =G98-H98 -> 0 | J98: =M$4*F98 -> 0 | K98: =M$2*F98 -> 23000 | L98: =J$3*F98%+J$4 -> 0 | M98: =ROUND((K98+J98+I98+L98),0) + O98 -> 23000.86 | N98: =ROUND((M98*6% + M98 ),0) + O98 -> 24381.86 | O98: =O97+0.01 -> 0.86
C99: COCH 18 | D99: Sr propietario | F99: 0.0023 | G99: 20700.87 | H99: =G99 -> 20700.87 | I99: =G99-H99 -> 0 | J99: =M$4*F99 -> 0 | K99: =M$2*F99 -> 23000 | L99: =J$3*F99%+J$4 -> 0 | M99: =ROUND((K99+J99+I99+L99),0) + O99 -> 23000.87 | N99: =ROUND((M99*6% + M99 ),0) + O99 -> 24381.87 | O99: =O98+0.01 -> 0.87
C100: COCH 19 | D100: Lobalo Lorena - Vega Maximiliano | F100: 0.0023 | G100: 20700.88 | H100: 21943.88 | I100: =G100-H100 -> -1243 | J100: =M$4*F100 -> 0 | K100: =M$2*F100 -> 23000 | L100: =J$3*F100%+J$4 -> 0 | M100: =ROUND((K100+J100+I100+L100),0) + O100 -> 21757.88 | N100: =ROUND((M100*6% + M100 ),0) + O100 -> 23063.88 | O100: =O99+0.01 -> 0.88
C101: COCH 20 | D101: Rosales, Rubén Darío | F101: 0.0023 | G101: 20700.89 | H101: =G101 -> 20700.89 | I101: =G101-H101 -> 0 | J101: =M$4*F101 -> 0 | K101: =M$2*F101 -> 23000 | L101: =J$3*F101%+J$4 -> 0 | M101: =ROUND((K101+J101+I101+L101),0) + O101 -> 23000.89 | N101: =ROUND((M101*6% + M101 ),0) + O101 -> 24381.89 | O101: =O100+0.01 -> 0.89
...

Sheet ANOTACIONES

Sheet SUELDOS
C3: =RESUMEN!C5 -> PERÍODO: SEPTIEMBRE | F3: =[1]RESUMEN!A22 -> Sueldo encargada Sonia Arzamendia Galeano
C5: =RESUMEN!A26 -> Haberes | G5: =RESUMEN!D26 -> 1008894 | H5: Firma
C6: =RESUMEN!A27 -> Plus pileta | G6: =RESUMEN!D27 -> 35211 | H6: __________________________________
C7: =RESUMEN!A28 -> Plus retiro de basura | G7: =RESUMEN!D28 -> 122704
C8: =RESUMEN!A29 -> Plus cochera | G8: =RESUMEN!D29 -> 20931
C9: =RESUMEN!A30 -> Adicional Viaticos | G9: =RESUMEN!D30 -> 58852.2 | H9: Aclaracion
C10: =RESUMEN!A31 -> Adicional remuneracion | G10: =RESUMEN!D31 -> 50000 | H10: __________________________________
C12: TOTAL | G12: =SUM(G5:G11) -> 1296592.2
C16: =C3 -> PERÍODO: SEPTIEMBRE | F16: =[1]RESUMEN!A30 -> Sueldo encargada Miriam
H18: Firma
C19: =RESUMEN!A34 -> Haberes | G19: =RESUMEN!D34 -> 504447 | H19: __________________________________
C20: =RESUMEN!A35 -> Horas extras | G20: =RESUMEN!D35 -> 0
C21: =RESUMEN!A36 -> Plus pileta | G21: =RESUMEN!D36 -> 35211
C22: =RESUMEN!A37 -> Plus retiro de basura | G22: =RESUMEN!D37 -> 122704 | H22: Aclaracion
C23: =RESUMEN!A38 -> Plus cochera | G23: =RESUMEN!D38 -> 20931 | H23: __________________________________
C24: =RESUMEN!A39 -> Adicional Viaticos | G24: =RESUMEN!D39 -> 58852.2
C25: =RESUMEN!A40 -> Adicional remuneracion | G25: =RESUMEN!D40 -> 50000
C26: TOTAL | G26: =SUM(G18:G25) -> 792145.2

Sheet Hoja1
C4: AYALA
C5: 52141.08 | D5: 3B
C6: 67140.1 | D6: 3D
C7: 52121.11 | D7: 3E
C8: 67885.12 | D8: 3F
C9: 67140.16 | D9: 4D
C10: 62141.17 | D10: 4E
C11: 67855.18 | D11: 4F
C12: 62141.23 | D12: 5E
C13: 67855.24 | D13: 5F
C14: =SUM(C5:C13) -> 566420.39
