Workbook

Sheet RESUMEN
B1: MAIL: italia2156rc@gmail.com
B2: CUIT ADMINISTRACION: 27-23125687-9
B3: NÚMERO DE CUENTA: Cta. Cte. $ 191-054-034938/2 - BANCO CREDICOP - CBU : 1910054455005403493828
A4: LIQUIDACION DE EXPENSAS | B4: ADMINISTRADORA: CAROLINA CANCIANI MP:1148
A5: CUIT DEL EDIFICIO: 30-56229064-4 | B5: PERÍODO: FEBRERO | D5: HORARIOS DE ATENCION: LUNES A VIERNES
A6: CONS. DE PROP. ITALIA 2156 | D6: 10 A 15HS - EMERGENCIAS 24HS
B8: VTO 13/03
A13: ESTIMADOS PROPIETARIOS E INQUILINOS: POR FAVOR LOS QUE ABONAN EN PRIMER VENCIMIENTO ABONEN EL MONTO DE PRIMER VENCIMIENTO, ASI AGILIZAN LA LIQUIDACION, RESPETEN LOS CENTAVOS CORRESPONDIENTES A LA UNIDAD FUNCIONAL. ES DE CARÁCTER OBLIGATORIO INFORMAR VIA MAIL LAS EXPENSAS. PORFAVOR RESPETAR LOS CENTAVOS AL ABONAR.
A20: GASTOS A - UNIDADES FUNCIONALES:
A21: Cesar Alberto Britez - CUIL 20-23524002-6
A22: Haberes | D22: 1931623
A23: Descuentos | D23: -420128
A24: Redondeo | D24: 0
A25: TOTAL | E25: =SUM(D22:D24) -> 1511495
A26: Sra. Gisela Alcaraz reemplazo Vacaciones Sr. Cesar
A27: Honorarios Sra. Gisela | D27: 148000
A28: Seguro Sra. Gisela | D28: 5842.51 | E28: Efectivo
A29: TOTAL | E29: =D27+D28 -> 153842.51
A30: IMPUESTOS
A31: ARCA - Plan de pago - Cuota 43/60 | D31: 13757.84 | E31: Debito 18/02
A32: ARCA VEP | D32: 1235711 | E32: Debito 10/02
A33: Sindicato - Suther | D33: 225490.24 | E33: Debito 16/02
A34: Sindicato - Seracarh | D34: 98200.71 | E34: =E33 -> Debito 16/02
A35: Sindicato - Fathery | D35: 10911.19 | E35: =E33 -> Debito 16/02
A36: Municipalidad de avellaneda
A37: TOTAL IMPUESTOS | E37: =SUM(D31:D36) -> 1584071
A38: SEGUROS
A39: Allianz Arg. Cía. De Seguros - Seguro Integral del Edificio - Póliza Nro. 230230731426 | D39: 313739 | E39: Debito ROELA 06/02
A40: Federacion Patronal - Poliza 2280633 - Seguro integral para consorcio | D40: 214164 | E40: Debito 27/02
A41: Allianz Arg. Cía. De Seguros - Seguro Combinado Familiar - Póliza Nro. 240150822164 | D41: 5204 | E41: Debito ROELA 06/02
A42: TOTAL IMPUESTO | E42: =SUM(D39:D41) -> 533107
A43: ABONOS Y SERVICIOS
A44: Edesur | B44: Cliente 4873380 | D44: 542686.9 | E44: Debito 23/02
A45: Edesur | B45: Cliente 0304290 | D45: 0
A46: Edesur | B46: Cliente 1295184 | D46: 0
A47: Metrogas | D47: 10111.62 | E47: Debito 04/02
A48: AySa | D48: 4813938.3 | E48: PMC 03/02
A49: Servicio de interet Claro
A50: TOTAL ABONOS Y SERVICIOS | E50: =SUM(D44:D49) -> 5366736.8
A52: Abono ascensor - Lema Ascensores - Mantenimiento | D52: 225000 | E52: Transf 18/02
A53: Ascensores Lema - Provision y colocacion, regulacion y cambio de cintas de freno en ascensores 2 y 3 | D53: 500000 | E53: Transf 18/02
A54: Ascensores Lema - Acortamiento de cables de acero, previo dispositivo de suspender la cabina con un aparejo, desmontar los cables de la polea para hacer el acortamiento. Desmonte completo del regulador de velocidad, debido a que se desviaron los soportes del caballete del regulador. Tuvimos que usar el regulador original, acoplarlos y regularlos. Puesta en posicion de guiadores de abajo del contra peso y los suplementarios para que no se vuelvan a salir de posicion en el ascensor del medio | D54: 1520000 | E54: Transf 09/02 - 10/02 y Efectivo
A55: Andes Ascensores - Recambio de cintas de freno en ascensor 2 y 3 según presupuesto aceptado - Pago por el 12B y 12A | D55: =272252*2 -> 544504 | E55: Pago por el 12B y 12A mes de Noviembre
A56: Doartero julio - Trabajo de colocacion de llave de paso 3D | D56: 85000 | E56: Transf 23/02
A57: Doartero julio - Emergencia electrica y cambio de cables | D57: 120000 | E57: Transf 13/02
A58: Doartero Julio - Inspeccion de gas | D58: 35000 | E58: Transf 23/02
A59: Russo Ruben Alberto - 2 Cabos de madera | D59: 6000 | E59: Transf 23/02
A60: Oscar Colmeiro – Obra de plomería: se realiza el cambio de desagües de cocinas y lavaderos en las unidades E y F de los pisos 7°, 6°, 5°, 4°, 3°, incluyendo además el cambio de bajada y desagües de cocina y lavadero en las unidades E y F del piso 2°, del piso 1° y de Planta Baja, realizándose en todos los casos el mismo tipo de trabajo. | D60: 7000000 | E60: Transf 10/02-13/02/17/02-23/02
A61: Fotocopias - Librería | D61: 28000 | E61: Efectivo
A62: Montoya Alejandra - Articulos de limpieza | D62: 150800 | E62: Transf 23/02
A63: Destapacion Roman - Cuota 4/5 | D63: 910000 | E63: Transf 02/02
A64: Destapacion Roman -Destapación de cloaca Desde acceso en cámara del fondo hacia siguiente dos cámaras, 30 metros; desde cámara hacia cámara principal en sector patio – cámara estacionamiento, 20 metros. Total: 50 metros. | D64: 250000 | E64: Transf 24/02
A65: Suarez Agustin Ignacio - Fumigacion Febrero | D65: 133300 | E65: Transf 10/02
A66: InOut Control - Comodato control y camaras Enero | D66: 105602.65 | E66: Transf 19/02
A67: Matafuegos MegaSeg - Recarga de matafuegos | D67: 2022800 | E67: Transf 10/02
A68: TOTAL | E68: =SUM(D52:D67) -> 13636007
A69: HONORARIOS
A70: Honorarios administracion - Mes de FEBRERO | D70: 650000
A71: Sra. Abogada Lorena Ferreiro - Honorarios | D71: 125000 | E71: Trabsf 11/02
A72: Timbrado consorcio con / Lo Dico (Embargo) | D72: 62500 | E72: Trabsf 11/02
A73: Gustavo Padron - Sr. Contador - FEBRERO | D73: 45000 | E73: Transf 11/02
A74: TOTAL | E74: =SUM(D70:D73) -> 882500
A75: GASTOS BANCARIOS
A76: Mantenimiento de cuenta - Banco ROELA | D76: 18681.4
A77: Gastos bancarios - ROELA y cierre de cuenta | D77: =29633.91-18681.4+50000 -> 60952.51
A78: Mantenimiento de cuenta - Banco Credicop | D78: 45000
A79: Gastos bancarios - Credicop | D79: =9386+1200+193960.95+3629+1284.98 -> 209460.93
A80: TOTAL | E80: =SUM(D76:D79) -> 334094.84
A82: PREVISION GASTOS A
A84: TOTAL GASTOS A | E84: =(SUM(E21:E82)) -> 24001854
A87: GASTOS B:
A92: TOTAL GASTOS B | E92: =SUM(D88:D91) -> 0
A95: PREVISION GASTOS B
A97: TOTAL GASTOS B: | E97: =E92+E95 -> 0
A99: GASTOS A + PREVISION (A) : | B99: =E84 -> 24001854
A100: GASTOS A SIN PREVISION: | B100: =E84-E82 -> 24001854
A101: GASTOS B SIN PREVISION: | B101: =E97-E95 -> 0
A102: GASTOS B CON PREVISION (B): | B102: =E97 -> 0
A105: Plan de pago de 4G: Consta de 7 cuotas de $170.000 + expensas en curso
A109: Plan de pago de 11C: Consta de 11 cuotas de 250.000 + expensas en curso
A114: LA CUENTA DEL BANCO ROELA FUE CERRADA, SOLO SE PUEDE TRANSFERIR AL CREDICOP
A117: SALDO REAL RECIBIDO - BANCO ROELA - CREDICOP Y EFECTIVO | B117: 10597370
A118: Egresos del mes | B118: =-B100-B101 -> -24001854
A119: Pagos sin identificar | B119: =B142 -> 195940.3
A120: Transferencia imputada a la Unidad funcional incorrecta del mes anterior ya que la unidad funcional 59 abono con $,53 centavos | B120: -239116.53
A121: Deposito ya identificado del mes de Noviembre 10C | B121: =-119452 -> -119452
A122: Deposito ya identificado del mes de Diciembre 9C | B122: -123612
A123: Deposito ya identificado del mes de Diciembre 5F | B123: -168836.39
A124: Punitorios mal cobrados 5F | B124: -20871
A125: Punitorios mal cobrados 9C | B125: -3820
A126: Punitorios mal cobrados 10C | B126: -7274
A127: Punitorios mal cobrados 2C | B127: -7528
A128: Destapacion 9C | B128: -50000
A129: Ingresos | B129: =PRORRATEO!F118 -> 14531887
A130: Adelanto de plan de pagos 4G | B130: 300000
A131: Adelanto de plan de pagos 11C | B131: 250000
A132: Adelanto plan de pagos 6B | B132: 200000.42
A133: Acuerdo de deuda 4G - Plan de pago (Abonado por UF) | B133: -130000
A134: Acuerdo de deuda 6B - Plan de pago (Abonado por UF) | B134: -130000
A135: Acuerdo de deuda 11C - Plan de pago (Abonado por UF) | B135: -130000
...

Sheet PRORRATEO
D2: Gastos B | E2: 3000000 | I2: Gastos A | J2: 12074625
A4: ¡IMPORTANTE! Al momento de registrar los pagos de expensas de las distintas Unidades Funcionales, consideramos importante aclarar el siguiente procedimiento, a fin de evitar confusiones en la imputación de los mismos. El sistema que utilizamos asigna centavos únicos a cada Unidad Funcional (UF), los cuales funcionan como un identificador automático para reconocer a qué Unidad Funcional corresponde cada transferencia. Es decir, cada Unidad Funcional tiene asignado un número específico de centavos que debe respetarse al momento de realizar el pago. Ejemplo: Si la Unidad Funcional es la N.º 45, el importe a abonar deberá finalizar en $,45. En caso de poseer más de una Unidad Funcional, cada una contará con su propio código de centavos. En estas situaciones, solicitamos realizar una transferencia individual por cada UF, respetando el importe y los centavos correspondientes a cada una. Entendemos que, por una cuestión de practicidad, a veces se opta por realizar una única transferencia, pero esto puede generar errores o demoras en la imputación automática de los pagos. La separación de los mismos nos permite llevar un control ordenado y preciso. Por lo expuesto, solicitamos encarecidamente que, a partir de ahora, todas las transferencias se realicen respetando los centavos asignados a la Unidad Funcional correspondiente, a fin de asegurar su correcta imputación. Agradecemos desde ya su colaboración y comprensión. Muchas gracias.
A9: LA CUENTA BANCARIA DEL BANCO ROELA HA SIDO CERRADA, TRANSFERENCIAS SOLO AL CREDICOP
A10: QUIENES ESTAN COLOREADOS DE COLOR VIOLETA NO ESTAN RESPETANDO LOS CENTAVOS AL ABONAR
A11: QUIENES ESTAN EN COLOR ROSADO POSEEN UN PLAN DE PAGOS VIGENTE
A12: UF | B12: Propietario | C12: Inquilinos | D12: (%) | E12: Saldo Ord | F12: Ingreso | G12: Deuda o Saldo a favor | H12: Interes 3% | I12: Gastos A | J12: Gastos B | K12: Gasto particular | L12: Total 1er Vto | M12: Total 2do Vto
L13: =RESUMEN!B8 -> VTO 13/03
A14: 1 | B14: PB - A POLICHISO RAMOS | D14: 1.37 | E14: 206522.01 | F14: =E14 -> 206522.01 | G14: =E14-F14 -> 0 | H14: =IF(G14>0,G14*3%,0) -> 0 | I14: =J$2*D14/100 -> 165422.36 | J14: =E$2*D14/100 -> 41100 | L14: =ROUND(SUM(G14:K14),0) + N14 -> 206522.01 | M14: =ROUND(L14*3%,0) + L14 -> 212718.01 | N14: 0.01
A15: 2 | B15: PB - B BATTISTA OMAR R. | D15: 1.18 | E15: 2512429 | F15: 30000 | G15: =E15-F15 -> 2482429 | H15: =IF(G15>0,G15*3%,0) -> 74472.871 | I15: =J$2*D15/100 -> 142480.58 | J15: =E$2*D15/100 -> 35400 | L15: =ROUND(SUM(G15:K15),0) + N15 -> 2734782 | M15: =ROUND(L15*3%,0) + L15 -> 2816825 | N15: =N14+0.01 -> 0.02 | O15: AYALA GASTON
A16: 3 | B16: PB - C DIDIER OLGA | D16: 0.74 | E16: 111552.03 | F16: =E16 -> 111552.03 | G16: =E16-F16 -> 0 | H16: =IF(G16>0,G16*3%,0) -> 0 | I16: =J$2*D16/100 -> 89352.225 | J16: =E$2*D16/100 -> 22200 | L16: =ROUND(SUM(G16:K16),0) + N16 -> 111552.03 | M16: =ROUND(L16*3%,0) + L16 -> 114899.03 | N16: =N15+0.01 -> 0.03
A17: 4 | B17: PB - D XHARDEZ MARIA A. | D17: 1.47 | E17: 214949.04 | F17: =E17 -> 214949.04 | G17: =E17-F17 -> 0 | H17: =IF(G17>0,G17*3%,0) -> 0 | I17: =J$2*D17/100 -> 177496.99 | J17: =E$2*D17/100 -> 44100 | L17: =ROUND(SUM(G17:K17),0) + N17 -> 221597.04 | M17: =ROUND(L17*3%,0) + L17 -> 228245.04 | N17: =N16+0.01 -> 0.04
A18: 5 | B18: PB - E BRANDAN OSVALDO | D18: 1.12 | E18: 163771.05 | F18: 168684.05 | G18: =E18-F18 -> -4913 | H18: =IF(G18>0,G18*3%,0) -> 0 | I18: =J$2*D18/100 -> 135235.8 | J18: =E$2*D18/100 -> 33600 | L18: =ROUND(SUM(G18:K18),0) + N18 -> 163923.05 | M18: =ROUND(L18*3%,0) + L18 -> 168841.05 | N18: =N17+0.01 -> 0.05
A19: 6 | B19: 1 A VEGA RICARDO | D19: 1.35 | E19: 203507.06 | F19: =E19 -> 203507.06 | G19: =E19-F19 -> 0 | H19: =IF(G19>0,G19*3%,0) -> 0 | I19: =J$2*D19/100 -> 163007.44 | J19: =E$2*D19/100 -> 40500 | L19: =ROUND(SUM(G19:K19),0) + N19 -> 203507.06 | M19: =ROUND(L19*3%,0) + L19 -> 209612.06 | N19: =N18+0.01 -> 0.06
A20: 7 | B20: 1 B ASTARITA SUSANA L. | D20: 1.12 | E20: 168836.07 | F20: =E20 -> 168836.07 | G20: =E20-F20 -> 0 | H20: =IF(G20>0,G20*3%,0) -> 0 | I20: =J$2*D20/100 -> 135235.8 | J20: =E$2*D20/100 -> 33600 | L20: =ROUND(SUM(G20:K20),0) + N20 -> 168836.07 | M20: =ROUND(L20*3%,0) + L20 -> 173901.07 | N20: =N19+0.01 -> 0.07
A21: 8 | B21: 1 C GUGLIELMINI ANA M. | D21: 0.82 | E21: 123612.08 | F21: =E21 -> 123612.08 | G21: =E21-F21 -> 0 | H21: =IF(G21>0,G21*3%,0) -> 0 | I21: =J$2*D21/100 -> 99011.925 | J21: =E$2*D21/100 -> 24600 | L21: =ROUND(SUM(G21:K21),0) + N21 -> 123612.08 | M21: =ROUND(L21*3%,0) + L21 -> 127320.08 | N21: =N20+0.01 -> 0.08
A22: 9 | B22: 1 D SCARPATI LORENA P. | D22: 0.82 | E22: 119904.09 | F22: 123501.09 | G22: =E22-F22 -> -3597 | H22: =IF(G22>0,G22*3%,0) -> 0 | I22: =J$2*D22/100 -> 99011.925 | J22: =E$2*D22/100 -> 24600 | L22: =ROUND(SUM(G22:K22),0) + N22 -> 120015.09 | M22: =ROUND(L22*3%,0) + L22 -> 123615.09 | N22: =N21+0.01 -> 0.09
A23: 10 | B23: 1 E BAZAN JOSE | D23: 1.34 | E23: 202000.1 | F23: =E23 -> 202000.1 | G23: =E23-F23 -> 0 | H23: =IF(G23>0,G23*3%,0) -> 0 | I23: =J$2*D23/100 -> 161799.98 | J23: =E$2*D23/100 -> 40200 | L23: =ROUND(SUM(G23:K23),0) + N23 -> 202000.1 | M23: =ROUND(L23*3%,0) + L23 -> 208060.1 | N23: =N22+0.01 -> 0.1
A24: 11 | B24: 1 F KRAJCIR ERNESTO | D24: 1.12 | E24: 168836.11 | F24: =E24 -> 168836.11 | G24: =E24-F24 -> 0 | H24: =IF(G24>0,G24*3%,0) -> 0 | I24: =J$2*D24/100 -> 135235.8 | J24: =E$2*D24/100 -> 33600 | L24: =ROUND(SUM(G24:K24),0) + N24 -> 168836.11 | M24: =ROUND(L24*3%,0) + L24 -> 173901.11 | N24: =N23+0.01 -> 0.11
A25: 12 | B25: 1 G AGOSTINI ALONSO | D25: 1.17 | E25: 3280034.1 | F25: 0 | G25: =E25-F25 -> 3280034.1 | H25: =IF(G25>0,G25*3%,0) -> 98401.024 | I25: =J$2*D25/100 -> 141273.11 | J25: =E$2*D25/100 -> 35100 | L25: =ROUND(SUM(G25:K25),0) + N25 -> 3554808.1 | M25: =ROUND(L25*3%,0) + L25 -> 3661452.1 | N25: =N24+0.01 -> 0.12
A26: 13 | B26: 2 A LORENA ELIZABETH CASSERO | D26: 1.35 | E26: 206752.13 | F26: =E26 -> 206752.13 | G26: =E26-F26 -> 0 | H26: =IF(G26>0,G26*3%,0) -> 0 | I26: =J$2*D26/100 -> 163007.44 | J26: =E$2*D26/100 -> 40500 | L26: =ROUND(SUM(G26:K26),0) + N26 -> 203507.13 | M26: =ROUND(L26*3%,0) + L26 -> 209612.13 | N26: =N25+0.01 -> 0.13
A27: 14 | B27: 2 B BOQUETE ALFREDO | D27: 1.12 | E27: 179275.14 | F27: =E27 -> 179275.14 | G27: =E27-F27 -> 0 | H27: =IF(G27>0,G27*3%,0) -> 0 | I27: =J$2*D27/100 -> 135235.8 | J27: =E$2*D27/100 -> 33600 | L27: =ROUND(SUM(G27:K27),0) + N27 -> 168836.14 | M27: =ROUND(L27*3%,0) + L27 -> 173901.14 | N27: =N26+0.01 -> 0.14
A28: 15 | B28: 2 C DESIMONE ROBERTO | D28: 0.82 | E28: 382072.15 | F28: =123612.15+250932+7528 -> 382072.15 | G28: =E28-F28 -> 0 | H28: =IF(G28>0,G28*3%,0) -> 0 | I28: =J$2*D28/100 -> 99011.925 | J28: =E$2*D28/100 -> 24600 | L28: =ROUND(SUM(G28:K28),0) + N28 -> 123612.15 | M28: =ROUND(L28*3%,0) + L28 -> 127320.15 | N28: =N27+0.01 -> 0.15
A29: 16 | B29: 2 D KERULIS SILVIA | D29: 0.82 | E29: 758530.16 | F29: 400000.16 | G29: =E29-F29 -> 358530 | H29: =IF(G29>0,G29*3%,0) -> 10755.9 | I29: =J$2*D29/100 -> 99011.925 | J29: =E$2*D29/100 -> 24600 | L29: =ROUND(SUM(G29:K29),0) + N29 -> 492898.16 | M29: =ROUND(L29*3%,0) + L29 -> 507685.16 | N29: =N28+0.01 -> 0.16
A30: 17 | B30: 2 E GARCIA SILVIA | D30: 1.34 | E30: 202000.17 | F30: =E30 -> 202000.17 | G30: =E30-F30 -> 0 | H30: =IF(G30>0,G30*3%,0) -> 0 | I30: =J$2*D30/100 -> 161799.98 | J30: =E$2*D30/100 -> 40200 | L30: =ROUND(SUM(G30:K30),0) + N30 -> 202000.17 | M30: =ROUND(L30*3%,0) + L30 -> 208060.17 | N30: =N29+0.01 -> 0.17
A31: 18 | B31: 2 F LOPEZ MERCEDES R. | D31: 1.12 | E31: 168836.18 | F31: 173901.18 | G31: =E31-F31 -> -5065 | H31: =IF(G31>0,G31*3%,0) -> 0 | I31: =J$2*D31/100 -> 135235.8 | J31: =E$2*D31/100 -> 33600 | L31: =ROUND(SUM(G31:K31),0) + N31 -> 163771.18 | M31: =ROUND(L31*3%,0) + L31 -> 168684.18 | N31: =N30+0.01 -> 0.18
A32: 19 | B32: 2 G MENDEZ JORGE O. | D32: 1.17 | E32: 176373.19 | F32: =191448.19-F113 -> 176372.19 | G32: =E32-F32 -> 1 | H32: =IF(G32>0,G32*3%,0) -> 0.03 | I32: =J$2*D32/100 -> 141273.11 | J32: =E$2*D32/100 -> 35100 | L32: =ROUND(SUM(G32:K32),0) + N32 -> 176374.19 | M32: =ROUND(L32*3%,0) + L32 -> 181665.19 | N32: =N31+0.01 -> 0.19 | O32: Tiene la cochera uf 100
A33: 20 | B33: 3 A POLLIO RICARDO | D33: 1.35 | E33: 203507.2 | G33: =E33-F33 -> 203507.2 | H33: =IF(G33>0,G33*3%,0) -> 6105.216 | I33: =J$2*D33/100 -> 163007.44 | J33: =E$2*D33/100 -> 40500 | L33: =ROUND(SUM(G33:K33),0) + N33 -> 413120.2 | M33: =ROUND(L33*3%,0) + L33 -> 425514.2 | N33: =N32+0.01 -> 0.2 | O33: Efectivo
A34: 21 | B34: 3 B WASZNIEWSKI G. | D34: 1.12 | E34: 168836.21 | F34: =E34 -> 168836.21 | G34: =E34-F34 -> 0 | H34: =IF(G34>0,G34*3%,0) -> 0 | I34: =J$2*D34/100 -> 135235.8 | J34: =E$2*D34/100 -> 33600 | L34: =ROUND(SUM(G34:K34),0) + N34 -> 168836.21 | M34: =ROUND(L34*3%,0) + L34 -> 173901.21 | N34: =N33+0.01 -> 0.21
A35: =A34+1 -> 22 | B35: 3 C MAROTTA PABLO | D35: 0.82 | E35: 123612.22 | F35: 127320.22 | G35: =E35-F35 -> -3708 | H35: =IF(G35>0,G35*3%,0) -> 0 | I35: =J$2*D35/100 -> 99011.925 | J35: =E$2*D35/100 -> 24600 | L35: =ROUND(SUM(G35:K35),0) + N35 -> 119904.22 | M35: =ROUND(L35*3%,0) + L35 -> 123501.22 | N35: =N34+0.01 -> 0.22
A36: =A35+1 -> 23 | B36: 3 D GARCIA MANUELA | D36: 0.82 | E36: 119904.23 | F36: =E36 -> 119904.23 | G36: =E36-F36 -> 0 | H36: =IF(G36>0,G36*3%,0) -> 0 | I36: =J$2*D36/100 -> 99011.925 | J36: =E$2*D36/100 -> 24600 | L36: =ROUND(SUM(G36:K36),0) + N36 -> 123612.23 | M36: =ROUND(L36*3%,0) + L36 -> 127320.23 | N36: =N35+0.01 -> 0.23
A37: =A36+1 -> 24 | B37: 3 E LASTIRI DANIELA | D37: 1.34 | E37: 208060.24 | F37: =E37 -> 208060.24 | G37: =E37-F37 -> 0 | H37: =IF(G37>0,G37*3%,0) -> 0 | I37: =J$2*D37/100 -> 161799.98 | J37: =E$2*D37/100 -> 40200 | L37: =ROUND(SUM(G37:K37),0) + N37 -> 202000.24 | M37: =ROUND(L37*3%,0) + L37 -> 208060.24 | N37: =N36+0.01 -> 0.24
A38: =A37+1 -> 25 | B38: 3 F LOPEZ ESTEBAN | D38: 1.12 | E38: 150649.25 | G38: =E38-F38 -> 150649.25 | H38: =IF(G38>0,G38*3%,0) -> 4519.4775 | I38: =J$2*D38/100 -> 135235.8 | J38: =E$2*D38/100 -> 33600 | L38: =ROUND(SUM(G38:K38),0) + N38 -> 324005.25 | M38: =ROUND(L38*3%,0) + L38 -> 333725.25 | N38: =N37+0.01 -> 0.25
A39: =A38+1 -> 26 | B39: 3 G FONDACARO FEDERICO | D39: 1.17 | E39: 375264.26 | F39: =E39 -> 375264.26 | G39: =E39-F39 -> 0 | H39: =IF(G39>0,G39*3%,0) -> 0 | I39: =J$2*D39/100 -> 141273.11 | J39: =E$2*D39/100 -> 35100 | L39: =ROUND(SUM(G39:K39),0) + N39 -> 176373.26 | M39: =ROUND(L39*3%,0) + L39 -> 181664.26 | N39: =N38+0.01 -> 0.26
A40: =A39+1 -> 27 | B40: 4 A FERNANDEZ LUCAS M. | D40: 1.35 | E40: 197402.27 | F40: =E40 -> 197402.27 | G40: =E40-F40 -> 0 | H40: =IF(G40>0,G40*3%,0) -> 0 | I40: =J$2*D40/100 -> 163007.44 | J40: =E$2*D40/100 -> 40500 | L40: =ROUND(SUM(G40:K40),0) + N40 -> 203507.27 | M40: =ROUND(L40*3%,0) + L40 -> 209612.27 | N40: =N39+0.01 -> 0.27
A41: =A40+1 -> 28 | B41: 4 B FRIDMAN J. Y SRA. | D41: 1.12 | E41: 163771.28 | F41: 168684.28 | G41: =E41-F41 -> -4913 | H41: =IF(G41>0,G41*3%,0) -> 0 | I41: =J$2*D41/100 -> 135235.8 | J41: =E$2*D41/100 -> 33600 | L41: =ROUND(SUM(G41:K41),0) + N41 -> 163923.28 | M41: =ROUND(L41*3%,0) + L41 -> 168841.28 | N41: =N40+0.01 -> 0.28
A42: =A41+1 -> 29 | B42: 4 C FERREIRA DE SOUSA | D42: 0.82 | E42: 116843.29 | G42: =E42-F42 -> 116843.29 | H42: =IF(G42>0,G42*3%,0) -> 3505.2987 | I42: =J$2*D42/100 -> 99011.925 | J42: =E$2*D42/100 -> 24600 | L42: =ROUND(SUM(G42:K42),0) + N42 -> 243961.29 | M42: =ROUND(L42*3%,0) + L42 -> 251280.29 | N42: =N41+0.01 -> 0.29 | O42: Silvana Valeria Arredondo
A43: =A42+1 -> 30 | B43: 4 D DIAZ PETRONA A. | D43: 0.82 | E43: 120677.3 | F43: 125000 | G43: =E43-F43 -> -4322.7 | H43: =IF(G43>0,G43*3%,0) -> 0 | I43: =J$2*D43/100 -> 99011.925 | J43: =E$2*D43/100 -> 24600 | L43: =ROUND(SUM(G43:K43),0) + N43 -> 119289.3 | M43: =ROUND(L43*3%,0) + L43 -> 122868.3 | N43: =N42+0.01 -> 0.3
A44: =A43+1 -> 31 | B44: 4 E XHARDEZ MARIA E. | D44: 1.34 | E44: 202000.31 | F44: 208060.31 | G44: =E44-F44 -> -6060 | H44: =IF(G44>0,G44*3%,0) -> 0 | I44: =J$2*D44/100 -> 161799.98 | J44: =E$2*D44/100 -> 40200 | L44: =ROUND(SUM(G44:K44),0) + N44 -> 195940.31 | M44: =ROUND(L44*3%,0) + L44 -> 201818.31 | N44: =N43+0.01 -> 0.31
A45: =A44+1 -> 32 | B45: 4 F WASINGER ADRIANA B. | D45: 1.12 | E45: 158706.32 | G45: =E45-F45 -> 158706.32 | H45: =IF(G45>0,G45*3%,0) -> 4761.1896 | I45: =J$2*D45/100 -> 135235.8 | J45: =E$2*D45/100 -> 33600 | L45: =ROUND(SUM(G45:K45),0) + N45 -> 332303.32 | M45: =ROUND(L45*3%,0) + L45 -> 342272.32 | N45: =N44+0.01 -> 0.32
A46: =A45+1 -> 33 | B46: 4 G OLIVERA LORENZO | D46: 1.17 | E46: 176373.11 | G46: =E46-F46 -> 176373.11 | H46: =IF(G46>0,G46*3%,0) -> 5291.1934 | I46: =J$2*D46/100 -> 141273.11 | J46: =E$2*D46/100 -> 35100 | L46: =ROUND(SUM(G46:K46),0) + N46 -> 358037.33 | M46: =ROUND(L46*3%,0) + L46 -> 368778.33 | N46: =N45+0.01 -> 0.33
A47: =A46+1 -> 34 | B47: 5 A EL FASAH JORGE | D47: 1.35 | E47: 203507.34 | F47: =E47 -> 203507.34 | G47: =E47-F47 -> 0 | H47: =IF(G47>0,G47*3%,0) -> 0 | I47: =J$2*D47/100 -> 163007.44 | J47: =E$2*D47/100 -> 40500 | L47: =ROUND(SUM(G47:K47),0) + N47 -> 203507.34 | M47: =ROUND(L47*3%,0) + L47 -> 209612.34 | N47: =N46+0.01 -> 0.34
A48: =A47+1 -> 35 | B48: 5 B DAMONTE ANDREA | D48: 1.12 | E48: 341763.35 | F48: 200000 | G48: =E48-F48 -> 141763.35 | H48: =IF(G48>0,G48*3%,0) -> 4252.9005 | I48: =J$2*D48/100 -> 135235.8 | J48: =E$2*D48/100 -> 33600 | L48: =ROUND(SUM(G48:K48),0) + N48 -> 314852.35 | M48: =ROUND(L48*3%,0) + L48 -> 324298.35 | N48: =N47+0.01 -> 0.35 | O48: Cartegena Silvia jaqueline
A49: =A48+1 -> 36 | B49: 5 C LOPEZ MARCEL MABEL | D49: 0.82 | E49: 119904.36 | F49: =E49 -> 119904.36 | G49: =E49-F49 -> 0 | H49: =IF(G49>0,G49*3%,0) -> 0 | I49: =J$2*D49/100 -> 99011.925 | J49: =E$2*D49/100 -> 24600 | L49: =ROUND(SUM(G49:K49),0) + N49 -> 123612.36 | M49: =ROUND(L49*3%,0) + L49 -> 127320.36 | N49: =N48+0.01 -> 0.36 | O49: Paola Massielainy
A50: =A49+1 -> 37 | B50: 5 D BANFI SILVIA R. | D50: 0.82 | E50: 258461.37 | F50: =E50 -> 258461.37 | G50: =E50-F50 -> 0 | H50: =IF(G50>0,G50*3%,0) -> 0 | I50: =J$2*D50/100 -> 99011.925 | J50: =E$2*D50/100 -> 24600 | L50: =ROUND(SUM(G50:K50),0) + N50 -> 123612.37 | M50: =ROUND(L50*3%,0) + L50 -> 127320.37 | N50: =N49+0.01 -> 0.37
A51: =A50+1 -> 38 | B51: 5 E BUCETA M. ARACELI | D51: 1.34 | E51: 195940.38 | G51: =E51-F51 -> 195940.38 | H51: =IF(G51>0,G51*3%,0) -> 5878.2114 | I51: =J$2*D51/100 -> 161799.98 | J51: =E$2*D51/100 -> 40200 | L51: =ROUND(SUM(G51:K51),0) + N51 -> 403819.38 | M51: =ROUND(L51*3%,0) + L51 -> 415934.38 | N51: =N50+0.01 -> 0.38
A52: =A51+1 -> 39 | B52: 5 F BARABALLE OSCAR | D52: 1.12 | E52: 358543.39 | F52: =168836.39*2+20871 -> 358543.78 | G52: =E52-F52 -> -0.39 | H52: =IF(G52>0,G52*3%,0) -> 0 | I52: =J$2*D52/100 -> 135235.8 | J52: =E$2*D52/100 -> 33600 | L52: =ROUND(SUM(G52:K52),0) + N52 -> 168835.39 | M52: =ROUND(L52*3%,0) + L52 -> 173900.39 | N52: =N51+0.01 -> 0.39
A53: =A52+1 -> 40 | B53: 5 G IRAZABAL SUEIRO | D53: 1.17 | E53: 358038.4 | G53: =E53-F53 -> 358038.4 | H53: =IF(G53>0,G53*3%,0) -> 10741.152 | I53: =J$2*D53/100 -> 141273.11 | J53: =E$2*D53/100 -> 35100 | L53: =ROUND(SUM(G53:K53),0) + N53 -> 545153.4 | M53: =ROUND(L53*3%,0) + L53 -> 561508.4 | N53: =N52+0.01 -> 0.4
A54: =A53+1 -> 41 | B54: 6 A MILLEFANTI CARINA | D54: 1.35 | E54: 203507.41 | F54: 209612.41 | G54: =E54-F54 -> -6105 | H54: =IF(G54>0,G54*3%,0) -> 0 | I54: =J$2*D54/100 -> 163007.44 | J54: =E$2*D54/100 -> 40500 | L54: =ROUND(SUM(G54:K54),0) + N54 -> 197402.41 | M54: =ROUND(L54*3%,0) + L54 -> 203324.41 | N54: =N53+0.01 -> 0.41
A55: =A54+1 -> 42 | B55: 6 B SETTE HORACIO Y SRA. | D55: 1.12 | E55: 818744.42 | G55: =E55-F55 -> 818744.42 | H55: =IF(G55>0,G55*3%,0) -> 24562.333 | I55: =J$2*D55/100 -> 135235.8 | J55: =E$2*D55/100 -> 33600 | L55: =ROUND(SUM(G55:K55),0) + N55 -> 1012143.4 | M55: =ROUND(L55*3%,0) + L55 -> 1042507.4 | N55: =N54+0.01 -> 0.42
A56: =A55+1 -> 43 | B56: 6 C LEOBONO MIRIAM G, | D56: 0.82 | E56: 1684811.4 | F56: 0 | G56: =E56-F56 -> 1684811.4 | H56: =IF(G56>0,G56*3%,0) -> 50544.343 | I56: =J$2*D56/100 -> 99011.925 | J56: =E$2*D56/100 -> 24600 | L56: =ROUND(SUM(G56:K56),0) + N56 -> 1858968.4 | M56: =ROUND(L56*3%,0) + L56 -> 1914737.4 | N56: =N55+0.01 -> 0.43
A57: =A56+1 -> 44 | B57: 6 D BALBIN BEATRIZ DE | D57: 0.82 | E57: 250933.44 | G57: =E57-F57 -> 250933.44 | H57: =IF(G57>0,G57*3%,0) -> 7528.0032 | I57: =J$2*D57/100 -> 99011.925 | J57: =E$2*D57/100 -> 24600 | L57: =ROUND(SUM(G57:K57),0) + N57 -> 382073.44 | M57: =ROUND(L57*3%,0) + L57 -> 393535.44 | N57: =N56+0.01 -> 0.44
A58: =A57+1 -> 45 | B58: 6 E LEVY JORGE OSVALDO | D58: 1.34 | E58: 202000.45 | F58: =E58 -> 202000.45 | G58: =E58-F58 -> 0 | H58: =IF(G58>0,G58*3%,0) -> 0 | I58: =J$2*D58/100 -> 161799.98 | J58: =E$2*D58/100 -> 40200 | L58: =ROUND(SUM(G58:K58),0) + N58 -> 202000.45 | M58: =ROUND(L58*3%,0) + L58 -> 208060.45 | N58: =N57+0.01 -> 0.45
A59: =A58+1 -> 46 | B59: 6 F KUZIEMSKI ANGELICA | D59: 1.12 | E59: 191258.46 | F59: 150000 | G59: =E59-F59 -> 41258.46 | H59: =IF(G59>0,G59*3%,0) -> 1237.7538 | I59: =J$2*D59/100 -> 135235.8 | J59: =E$2*D59/100 -> 33600 | L59: =ROUND(SUM(G59:K59),0) + N59 -> 211332.46 | M59: =ROUND(L59*3%,0) + L59 -> 217672.46 | N59: =N58+0.01 -> 0.46 | O59: Deposita - Angelica Kuziemski
A60: =A59+1 -> 47 | B60: 6 G TULIPANI ANGELICA | D60: 1.17 | E60: 581351.47 | F60: 173374.17 | G60: =E60-F60 -> 407977.3 | H60: =IF(G60>0,G60*3%,0) -> 12239.319 | I60: =J$2*D60/100 -> 141273.11 | J60: =E$2*D60/100 -> 35100 | L60: =ROUND(SUM(G60:K60),0) + N60 -> 596590.47 | M60: =ROUND(L60*3%,0) + L60 -> 614488.47 | N60: =N59+0.01 -> 0.47 | O60: Macarena Crespo nueva inquilina - Sandra noemi crespo
A61: =A60+1 -> 48 | B61: 7 A OLIVERA JORGE | D61: 1.35 | E61: 209612.48 | F61: =E61 -> 209612.48 | G61: =E61-F61 -> 0 | H61: =IF(G61>0,G61*3%,0) -> 0 | I61: =J$2*D61/100 -> 163007.44 | J61: =E$2*D61/100 -> 40500 | L61: =ROUND(SUM(G61:K61),0) + N61 -> 203507.48 | M61: =ROUND(L61*3%,0) + L61 -> 209612.48 | N61: =N60+0.01 -> 0.48 | O61: Olivera Martin Sebastian
A62: =A61+1 -> 49 | B62: 7 B GASCON PAOLA V. | D62: 1.12 | E62: 163771.49 | F62: 168684.49 | G62: =E62-F62 -> -4913 | H62: =IF(G62>0,G62*3%,0) -> 0 | I62: =J$2*D62/100 -> 135235.8 | J62: =E$2*D62/100 -> 33600 | L62: =ROUND(SUM(G62:K62),0) + N62 -> 163923.49 | M62: =ROUND(L62*3%,0) + L62 -> 168841.49 | N62: =N61+0.01 -> 0.49
A63: =A62+1 -> 50 | B63: 7 C CASTALDI GUSTAVO | D63: 0.82 | E63: 250933.5 | F63: =E63 -> 250933.5 | G63: =E63-F63 -> 0 | H63: =IF(G63>0,G63*3%,0) -> 0 | I63: =J$2*D63/100 -> 99011.925 | J63: =E$2*D63/100 -> 24600 | L63: =ROUND(SUM(G63:K63),0) + N63 -> 123612.5 | M63: =ROUND(L63*3%,0) + L63 -> 127320.5 | N63: =N62+0.01 -> 0.5
A64: =A63+1 -> 51 | B64: 7 D SCUNIO HECTOR F. | D64: 0.82 | E64: 233265.51 | F64: 106459.51 | G64: =E64-F64 -> 126806 | H64: =IF(G64>0,G64*3%,0) -> 3804.18 | I64: =J$2*D64/100 -> 99011.925 | J64: =E$2*D64/100 -> 24600 | L64: =ROUND(SUM(G64:K64),0) + N64 -> 254222.51 | M64: =ROUND(L64*3%,0) + L64 -> 261849.51 | N64: =N63+0.01 -> 0.51
A65: =A64+1 -> 52 | B65: 7 E RODRIGUEZ FERNANDO | D65: 1.34 | E65: 202000.52 | F65: =E65 -> 202000.52 | G65: =E65-F65 -> 0 | H65: =IF(G65>0,G65*3%,0) -> 0 | I65: =J$2*D65/100 -> 161799.98 | J65: =E$2*D65/100 -> 40200 | L65: =ROUND(SUM(G65:K65),0) + N65 -> 202000.52 | M65: =ROUND(L65*3%,0) + L65 -> 208060.52 | N65: =N64+0.01 -> 0.52
A66: =A65+1 -> 53 | B66: 7 F MAONE OSVALDO | D66: 1.12 | E66: 300737.53 | F66: 98556.53 | G66: =E66-F66 -> 202181 | H66: =IF(G66>0,G66*3%,0) -> 6065.43 | I66: =J$2*D66/100 -> 135235.8 | J66: =E$2*D66/100 -> 33600 | L66: =ROUND(SUM(G66:K66),0) + N66 -> 377082.53 | M66: =ROUND(L66*3%,0) + L66 -> 388394.53 | N66: =N65+0.01 -> 0.53
A67: =A66+1 -> 54 | B67: 7 G MORALES MIRIAM M. | D67: 1.17 | E67: 171082.54 | F67: 176214.54 | G67: =E67-F67 -> -5132 | H67: =IF(G67>0,G67*3%,0) -> 0 | I67: =J$2*D67/100 -> 141273.11 | J67: =E$2*D67/100 -> 35100 | L67: =ROUND(SUM(G67:K67),0) + N67 -> 171241.54 | M67: =ROUND(L67*3%,0) + L67 -> 176378.54 | N67: =N66+0.01 -> 0.54
A68: =A67+1 -> 55 | B68: 8 A SANTOS PASCUAL | D68: 1.35 | E68: 197402.55 | F68: 203324.55 | G68: =E68-F68 -> -5922 | H68: =IF(G68>0,G68*3%,0) -> 0 | I68: =J$2*D68/100 -> 163007.44 | J68: =E$2*D68/100 -> 40500 | L68: =ROUND(SUM(G68:K68),0) + N68 -> 197585.55 | M68: =ROUND(L68*3%,0) + L68 -> 203513.55 | N68: =N67+0.01 -> 0.55
A69: =A68+1 -> 56 | B69: 8 B FANELLI EDITH | D69: 1.12 | E69: 168836.56 | F69: 173901.56 | G69: =E69-F69 -> -5065 | H69: =IF(G69>0,G69*3%,0) -> 0 | I69: =J$2*D69/100 -> 135235.8 | J69: =E$2*D69/100 -> 33600 | L69: =ROUND(SUM(G69:K69),0) + N69 -> 163771.56 | M69: =ROUND(L69*3%,0) + L69 -> 168684.56 | N69: =N68+0.01 -> 0.56
A70: =A69+1 -> 57 | B70: 8 C KRUK ANA MARIA | D70: 0.82 | E70: 119898.57 | F70: 120000 | G70: =E70-F70 -> -101.43 | H70: =IF(G70>0,G70*3%,0) -> 0 | I70: =J$2*D70/100 -> 99011.925 | J70: =E$2*D70/100 -> 24600 | L70: =ROUND(SUM(G70:K70),0) + N70 -> 123510.57 | M70: =ROUND(L70*3%,0) + L70 -> 127215.57 | N70: =N69+0.01 -> 0.57
A71: =A70+1 -> 58 | B71: 8 D RIOS ELIDA | D71: 0.82 | E71: 123612.58 | F71: =E71 -> 123612.58 | G71: =E71-F71 -> 0 | H71: =IF(G71>0,G71*3%,0) -> 0 | I71: =J$2*D71/100 -> 99011.925 | J71: =E$2*D71/100 -> 24600 | L71: =ROUND(SUM(G71:K71),0) + N71 -> 123612.58 | M71: =ROUND(L71*3%,0) + L71 -> 127320.58 | N71: =N70+0.01 -> 0.58
A72: =A71+1 -> 59 | B72: 8 E ALEJO HORACIO | D72: 1.34 | E72: 410061.59 | F72: =239116.53-PRORRATEO!F106-PRORRATEO!F114+194996.59+6100 -> 410061.18 | G72: =E72-F72 -> 0.41 | H72: =IF(G72>0,G72*3%,0) -> 0.0123 | I72: =J$2*D72/100 -> 161799.98 | J72: =E$2*D72/100 -> 40200 | L72: =ROUND(SUM(G72:K72),0) + N72 -> 202000.59 | M72: =ROUND(L72*3%,0) + L72 -> 208060.59 | N72: =N71+0.01 -> 0.59
A73: =A72+1 -> 60 | B73: 8 F BOSSETTI CARLOS E. | D73: 1.12 | E73: 163771.6 | F73: 168684.6 | G73: =E73-F73 -> -4913 | H73: =IF(G73>0,G73*3%,0) -> 0 | I73: =J$2*D73/100 -> 135235.8 | J73: =E$2*D73/100 -> 33600 | L73: =ROUND(SUM(G73:K73),0) + N73 -> 163923.6 | M73: =ROUND(L73*3%,0) + L73 -> 168841.6 | N73: =N72+0.01 -> 0.6
A74: =A73+1 -> 61 | B74: 8 G DE MATO Y SORRENTI | D74: 1.17 | E74: 176373.61 | F74: =E74 -> 176373.61 | G74: =E74-F74 -> 0 | H74: =IF(G74>0,G74*3%,0) -> 0 | I74: =J$2*D74/100 -> 141273.11 | J74: =E$2*D74/100 -> 35100 | L74: =ROUND(SUM(G74:K74),0) + N74 -> 176373.61 | M74: =ROUND(L74*3%,0) + L74 -> 181664.61 | N74: =N73+0.01 -> 0.61
A75: =A74+1 -> 62 | B75: 9 A SANTOS CARDOZO | D75: 1.35 | E75: 197402.62 | F75: 203325.62 | G75: =E75-F75 -> -5923 | H75: =IF(G75>0,G75*3%,0) -> 0 | I75: =J$2*D75/100 -> 163007.44 | J75: =E$2*D75/100 -> 40500 | L75: =ROUND(SUM(G75:K75),0) + N75 -> 197584.62 | M75: =ROUND(L75*3%,0) + L75 -> 203512.62 | N75: =N74+0.01 -> 0.62
A76: =A75+1 -> 63 | B76: 9 B BELIZAN RUBEN OMAR | D76: 1.12 | E76: 168836.63 | F76: =E76 -> 168836.63 | G76: =E76-F76 -> 0 | H76: =IF(G76>0,G76*3%,0) -> 0 | I76: =J$2*D76/100 -> 135235.8 | J76: =E$2*D76/100 -> 33600 | L76: =ROUND(SUM(G76:K76),0) + N76 -> 168836.63 | M76: =ROUND(L76*3%,0) + L76 -> 173901.63 | N76: =N75+0.01 -> 0.63
A77: =A76+1 -> 64 | B77: 9 C LOMBARDO MARIA DEL | D77: 0.82 | E77: 254752.64 | F77: =127320.64+123612+3820 -> 254752.64 | G77: =E77-F77 -> 0 | H77: =IF(G77>0,G77*3%,0) -> 0 | I77: =J$2*D77/100 -> 99011.925 | J77: =E$2*D77/100 -> 24600 | K77: 50000 | L77: =ROUND(SUM(G77:K77),0) + N77 -> 173612.64 | M77: =ROUND(L77*3%,0) + L77 -> 178820.64 | N77: =N76+0.01 -> 0.64
A78: =A77+1 -> 65 | B78: 9 D CALVIÑO LUCAS | D78: 0.82 | E78: 880370.65 | F78: 99011.93 | G78: =E78-F78 -> 781358.72 | H78: =IF(G78>0,G78*3%,0) -> 23440.762 | I78: =J$2*D78/100 -> 99011.925 | J78: =E$2*D78/100 -> 24600 | L78: =ROUND(SUM(G78:K78),0) + N78 -> 928411.65 | M78: =ROUND(L78*3%,0) + L78 -> 956263.65 | N78: =N77+0.01 -> 0.65 | O78: Taiel Alejandro Biscarra / Vizcarra
A79: =A78+1 -> 66 | B79: 9 E NOE FRANCISCO N. | D79: 1.34 | E79: 195940.66 | F79: 201818.66 | G79: =E79-F79 -> -5878 | H79: =IF(G79>0,G79*3%,0) -> 0 | I79: =J$2*D79/100 -> 161799.98 | J79: =E$2*D79/100 -> 40200 | L79: =ROUND(SUM(G79:K79),0) + N79 -> 196122.66 | M79: =ROUND(L79*3%,0) + L79 -> 202006.66 | N79: =N78+0.01 -> 0.66
A80: =A79+1 -> 67 | B80: 9 F DE MOGLIONI LORENZO | D80: 1.12 | E80: 347955.67 | F80: 180000.67 | G80: =E80-F80 -> 167955 | H80: =IF(G80>0,G80*3%,0) -> 5038.65 | I80: =J$2*D80/100 -> 135235.8 | J80: =E$2*D80/100 -> 33600 | L80: =ROUND(SUM(G80:K80),0) + N80 -> 341829.67 | M80: =ROUND(L80*3%,0) + L80 -> 352084.67 | N80: =N79+0.01 -> 0.67
A81: =A80+1 -> 68 | B81: 9 G MOLINA AMANDA | D81: 1.17 | E81: 5371080.7 | F81: 0 | G81: =E81-F81 -> 5371080.7 | H81: =IF(G81>0,G81*3%,0) -> 161132.42 | I81: =J$2*D81/100 -> 141273.11 | J81: =E$2*D81/100 -> 35100 | L81: =ROUND(SUM(G81:K81),0) + N81 -> 5708586.7 | M81: =ROUND(L81*3%,0) + L81 -> 5879844.7 | N81: =N80+0.01 -> 0.68
A82: =A81+1 -> 69 | B82: 10 A CARBAJALES JOSE | D82: 1.35 | E82: 197402.69 | F82: 203324.69 | G82: =E82-F82 -> -5922 | H82: =IF(G82>0,G82*3%,0) -> 0 | I82: =J$2*D82/100 -> 163007.44 | J82: =E$2*D82/100 -> 40500 | L82: =ROUND(SUM(G82:K82),0) + N82 -> 197585.69 | M82: =ROUND(L82*3%,0) + L82 -> 203513.69 | N82: =N81+0.01 -> 0.69
A83: =A82+1 -> 70 | B83: 10 B RAMOS ALBERTO | D83: 1.12 | E83: 142803.7 | G83: =E83-F83 -> 142803.7 | H83: =IF(G83>0,G83*3%,0) -> 4284.111 | I83: =J$2*D83/100 -> 135235.8 | J83: =E$2*D83/100 -> 33600 | L83: =ROUND(SUM(G83:K83),0) + N83 -> 315924.7 | M83: =ROUND(L83*3%,0) + L83 -> 325402.7 | N83: =N82+0.01 -> 0.7 | O83: Silvana Valeria Arredondo - Braian Brito
A84: =A83+1 -> 71 | B84: 10 C NANI DEL VALLE J. | D84: 0.82 | E84: 250338.71 | F84: =119452+123612.71+7274 -> 250338.71 | G84: =E84-F84 -> 0 | H84: =IF(G84>0,G84*3%,0) -> 0 | I84: =J$2*D84/100 -> 99011.925 | J84: =E$2*D84/100 -> 24600 | L84: =ROUND(SUM(G84:K84),0) + N84 -> 123612.71 | M84: =ROUND(L84*3%,0) + L84 -> 127320.71 | N84: =N83+0.01 -> 0.71
A85: =A84+1 -> 72 | B85: 10 D DE ALBA MARIA L. | D85: 0.82 | E85: 123612.72 | F85: =E85 -> 123612.72 | G85: =E85-F85 -> 0 | H85: =IF(G85>0,G85*3%,0) -> 0 | I85: =J$2*D85/100 -> 99011.925 | J85: =E$2*D85/100 -> 24600 | L85: =ROUND(SUM(G85:K85),0) + N85 -> 123612.72 | M85: =ROUND(L85*3%,0) + L85 -> 127320.72 | N85: =N84+0.01 -> 0.72
A86: =A85+1 -> 73 | B86: 10 E LANZILLOTA DIEGO J. | D86: 1.34 | E86: 202000.73 | G86: =E86-F86 -> 202000.73 | H86: =IF(G86>0,G86*3%,0) -> 6060.0219 | I86: =J$2*D86/100 -> 161799.98 | J86: =E$2*D86/100 -> 40200 | L86: =ROUND(SUM(G86:K86),0) + N86 -> 410061.73 | M86: =ROUND(L86*3%,0) + L86 -> 422363.73 | N86: =N85+0.01 -> 0.73
A87: =A86+1 -> 74 | B87: 10 F PEDROUZO JORGE LUIS | D87: 1.12 | E87: 153412.74 | G87: =E87-F87 -> 153412.74 | H87: =IF(G87>0,G87*3%,0) -> 4602.3822 | I87: =J$2*D87/100 -> 135235.8 | J87: =E$2*D87/100 -> 33600 | L87: =ROUND(SUM(G87:K87),0) + N87 -> 326851.74 | M87: =ROUND(L87*3%,0) + L87 -> 336657.74 | N87: =N86+0.01 -> 0.74
A88: =A87+1 -> 75 | B88: 10 G FANELLI EDITH | D88: 1.17 | E88: 176373.75 | F88: =E88 -> 176373.75 | G88: =E88-F88 -> 0 | H88: =IF(G88>0,G88*3%,0) -> 0 | I88: =J$2*D88/100 -> 141273.11 | J88: =E$2*D88/100 -> 35100 | L88: =ROUND(SUM(G88:K88),0) + N88 -> 176373.75 | M88: =ROUND(L88*3%,0) + L88 -> 181664.75 | N88: =N87+0.01 -> 0.75
A89: =A88+1 -> 76 | B89: 11 A LEOPARDI A. | D89: 1.35 | E89: 209612.76 | F89: =E89 -> 209612.76 | G89: =E89-F89 -> 0 | H89: =IF(G89>0,G89*3%,0) -> 0 | I89: =J$2*D89/100 -> 163007.44 | J89: =E$2*D89/100 -> 40500 | L89: =ROUND(SUM(G89:K89),0) + N89 -> 203507.76 | M89: =ROUND(L89*3%,0) + L89 -> 209612.76 | N89: =N88+0.01 -> 0.76
A90: =A89+1 -> 77 | B90: 11 B VILARDO LILIANA | D90: 1.12 | E90: 163771.77 | F90: 168684.77 | G90: =E90-F90 -> -4913 | H90: =IF(G90>0,G90*3%,0) -> 0 | I90: =J$2*D90/100 -> 135235.8 | J90: =E$2*D90/100 -> 33600 | L90: =ROUND(SUM(G90:K90),0) + N90 -> 163923.77 | M90: =ROUND(L90*3%,0) + L90 -> 168841.77 | N90: =N89+0.01 -> 0.77
A91: =A90+1 -> 78 | B91: 11 C LODICO HORACIO | D91: 0.82 | E91: 123611.93 | G91: =E91-F91 -> 123611.93 | H91: =IF(G91>0,G91*3%,0) -> 3708.3578 | I91: =J$2*D91/100 -> 99011.925 | J91: =E$2*D91/100 -> 24600 | L91: =ROUND(SUM(G91:K91),0) + N91 -> 250932.78 | M91: =ROUND(L91*3%,0) + L91 -> 258460.78 | N91: =N90+0.01 -> 0.78
A92: =A91+1 -> 79 | B92: 11 D ANTUNEZ RUBEN | D92: 0.82 | E92: 123612.79 | F92: =E92 -> 123612.79 | G92: =E92-F92 -> 0 | H92: =IF(G92>0,G92*3%,0) -> 0 | I92: =J$2*D92/100 -> 99011.925 | J92: =E$2*D92/100 -> 24600 | L92: =ROUND(SUM(G92:K92),0) + N92 -> 123612.79 | M92: =ROUND(L92*3%,0) + L92 -> 127320.79 | N92: =N91+0.01 -> 0.79
A93: =A92+1 -> 80 | B93: 11 E MIRAGAYA JORGE OMAR | D93: 1.34 | E93: 410061.8 | F93: 220400.8 | G93: =E93-F93 -> 189661 | H93: =IF(G93>0,G93*3%,0) -> 5689.83 | I93: =J$2*D93/100 -> 161799.98 | J93: =E$2*D93/100 -> 40200 | L93: =ROUND(SUM(G93:K93),0) + N93 -> 397351.8 | M93: =ROUND(L93*3%,0) + L93 -> 409272.8 | N93: =N92+0.01 -> 0.8
A94: =A93+1 -> 81 | B94: 11 F ANTUNEZ RUBEN DANIEL | D94: 1.12 | E94: 638725.81 | F94: 250000 | G94: =E94-F94 -> 388725.81 | H94: =IF(G94>0,G94*3%,0) -> 11661.774 | I94: =J$2*D94/100 -> 135235.8 | J94: =E$2*D94/100 -> 33600 | L94: =ROUND(SUM(G94:K94),0) + N94 -> 569223.81 | M94: =ROUND(L94*3%,0) + L94 -> 586300.81 | N94: =N93+0.01 -> 0.81 | O94: Fernando daniel Minxxo / Jeremy Naguel
A95: =A94+1 -> 82 | B95: 11 G POLONI JOSE | D95: 1.17 | E95: 181664.82 | F95: =E95 -> 181664.82 | G95: =E95-F95 -> 0 | H95: =IF(G95>0,G95*3%,0) -> 0 | I95: =J$2*D95/100 -> 141273.11 | J95: =E$2*D95/100 -> 35100 | L95: =ROUND(SUM(G95:K95),0) + N95 -> 176373.82 | M95: =ROUND(L95*3%,0) + L95 -> 181664.82 | N95: =N94+0.01 -> 0.82
A96: =A95+1 -> 83 | B96: 12 A TORRES G. ZULLY | D96: 1.35 | E96: 191113.83 | F96: =RESUMEN!D55/2+196846.93 -> 469098.93 | G96: =E96-F96 -> -277985.1 | H96: =IF(G96>0,G96*3%,0) -> 0 | I96: =J$2*D96/100 -> 163007.44 | J96: =E$2*D96/100 -> 40500 | L96: =ROUND(SUM(G96:K96),0) + N96 -> -74477.17 | M96: =ROUND(L96*3%,0) + L96 -> -76711.17 | N96: =N95+0.01 -> 0.83
A97: =A96+1 -> 84 | B97: 12 B BALLESTEROS SENCIO | D97: 1.12 | E97: 449255.84 | F97: =RESUMEN!D55/2+168836.84 -> 441088.84 | G97: =E97-F97 -> 8167 | H97: =IF(G97>0,G97*3%,0) -> 245.01 | I97: =J$2*D97/100 -> 135235.8 | J97: =E$2*D97/100 -> 33600 | L97: =ROUND(SUM(G97:K97),0) + N97 -> 177248.84 | M97: =ROUND(L97*3%,0) + L97 -> 182565.84 | N97: =N96+0.01 -> 0.84
A98: =A97+1 -> 85 | B98: 12 C SABHA DANIEL | D98: 0.82 | E98: 123612.85 | F98: =E98 -> 123612.85 | G98: =E98-F98 -> 0 | H98: =IF(G98>0,G98*3%,0) -> 0 | I98: =J$2*D98/100 -> 99011.925 | J98: =E$2*D98/100 -> 24600 | L98: =ROUND(SUM(G98:K98),0) + N98 -> 123612.85 | M98: =ROUND(L98*3%,0) + L98 -> 127320.85 | N98: =N97+0.01 -> 0.85
A99: =A98+1 -> 86 | B99: 12 D LANNI KARINA PAOLA | D99: 0.82 | E99: 123612.86 | F99: =E99 -> 123612.86 | G99: =E99-F99 -> 0 | H99: =IF(G99>0,G99*3%,0) -> 0 | I99: =J$2*D99/100 -> 99011.925 | J99: =E$2*D99/100 -> 24600 | L99: =ROUND(SUM(G99:K99),0) + N99 -> 123612.86 | M99: =ROUND(L99*3%,0) + L99 -> 127320.86 | N99: =N98+0.01 -> 0.86
A100: =A99+1 -> 87 | B100: 12 E DAVILA JUAN | D100: 1.34 | E100: 195940.87 | F100: 201818.87 | G100: =E100-F100 -> -5878 | H100: =IF(G100>0,G100*3%,0) -> 0 | I100: =J$2*D100/100 -> 161799.98 | J100: =E$2*D100/100 -> 40200 | L100: =ROUND(SUM(G100:K100),0) + N100 -> 196122.87 | M100: =ROUND(L100*3%,0) + L100 -> 202006.87 | N100: =N99+0.01 -> 0.87
A101: =A100+1 -> 88 | B101: 12 F SUC. DE F. CAMPOS | D101: 1.12 | E101: 163771.88 | F101: =E101 -> 163771.88 | G101: =E101-F101 -> 0 | H101: =IF(G101>0,G101*3%,0) -> 0 | I101: =J$2*D101/100 -> 135235.8 | J101: =E$2*D101/100 -> 33600 | L101: =ROUND(SUM(G101:K101),0) + N101 -> 168836.88 | M101: =ROUND(L101*3%,0) + L101 -> 173901.88 | N101: =N100+0.01 -> 0.88
A102: =A101+1 -> 89 | B102: 12 G NOSACH SERGIO | D102: 1.17 | E102: 176373.89 | F102: =E102 -> 176373.89 | G102: =E102-F102 -> 0 | H102: =IF(G102>0,G102*3%,0) -> 0 | I102: =J$2*D102/100 -> 141273.11 | J102: =E$2*D102/100 -> 35100 | L102: =ROUND(SUM(G102:K102),0) + N102 -> 176373.89 | M102: =ROUND(L102*3%,0) + L102 -> 181664.89 | N102: =N101+0.01 -> 0.89
A103: =A102+1 -> 90 | B103: 12 E COCHERA F. DAVILA JUAN | D103: 0.1 | E103: 14623.9 | F103: 15062.9 | G103: =E103-F103 -> -439 | H103: =IF(G103>0,G103*3%,0) -> 0 | I103: =J$2*D103/100 -> 12074.625 | J103: =E$2*D103/100 -> 3000 | L103: =ROUND(SUM(G103:K103),0) + N103 -> 14636.9 | M103: =ROUND(L103*3%,0) + L103 -> 15075.9 | N103: =N102+0.01 -> 0.9
A104: =A103+1 -> 91 | B104: 11 G COCHERA N. POLONI JOSE | D104: 0.1 | E104: 31068.91 | F104: 15528.91 | G104: =E104-F104 -> 15540 | H104: =IF(G104>0,G104*3%,0) -> 466.2 | I104: =J$2*D104/100 -> 12074.625 | J104: =E$2*D104/100 -> 3000 | L104: =ROUND(SUM(G104:K104),0) + N104 -> 31081.91 | M104: =ROUND(L104*3%,0) + L104 -> 32013.91 | N104: =N103+0.01 -> 0.91
A105: =A104+1 -> 92 | B105: 11 A COCHERA E LEOPARDI A. | D105: 0.1 | E105: 15527.92 | F105: =E105 -> 15527.92 | G105: =E105-F105 -> 0 | H105: =IF(G105>0,G105*3%,0) -> 0 | I105: =J$2*D105/100 -> 12074.625 | J105: =E$2*D105/100 -> 3000 | L105: =ROUND(SUM(G105:K105),0) + N105 -> 15075.92 | M105: =ROUND(L105*3%,0) + L105 -> 15527.92 | N105: =N104+0.01 -> 0.92
A106: =A105+1 -> 93 | B106: 8 E COCHERA G. ALEJO HORACIO | D106: 0.1 | E106: 15075.93 | F106: =E106 -> 15075.93 | G106: =E106-F106 -> 0 | H106: =IF(G106>0,G106*3%,0) -> 0 | I106: =J$2*D106/100 -> 12074.625 | J106: =E$2*D106/100 -> 3000 | L106: =ROUND(SUM(G106:K106),0) + N106 -> 15075.93 | M106: =ROUND(L106*3%,0) + L106 -> 15527.93 | N106: =N105+0.01 -> 0.93
...

Sheet ANOTACIONES
C4: Al 7F le hicimos su situacion detallada al pie de la letra debe abonar $371.016,53
C7: Al 7D le debemos poner el deposito no identificado de enero de $110,000 este mes debe abonar $123.612,51
C10: El 3C tiene nuevo propietario, Marotta Pablo, agregarlo a la cadena de mails pabloeze.marotta@gmail.com
C12: 8C deposito $132.520 el 12/03

Sheet 7F SITUACION
C4: En diciembre debia abonar | F4: Abono | H4: Deuda: | J4: Expensas para abonar en enero
C5: 168835.53 | F5: =C5 -> 168835.53 | H5: 0 | J5: =F5 -> 168835.53
M7: Total a abonar en febrero (expensas + deuda) - Descontamos punitorios
C8: En enero debia abonar: | F8: Abono | H8: Deuda: | J8: Expensas para abonar en Febrero
C9: 168836.53 | F9: 0 | H9: =C9-F9 -> 168836.53 | J9: =33600+135235.8 -> 168835.8 | M9: 300737.53
M11: Total a abonar en febrero (expensas + deuda) - Descontamos punitorios
C12: En febrero debia abonar: | F12: Abono | H12: Deuda: | J12: Expensas para abonar en Marzo
C13: =M9 -> 300737.53 | F13: 98556.53 | H13: =C13-F13 -> 202181 | J13: =33600+135235.8 -> 168835.8 | M13: =J13+H13-0.27 -> 371016.53
C15: Todo este problema con los números se origina en el mes de enero, cuando la unidad funcional 7°F no realizó ningún pago. En ese mismo período, otro propietario efectuó un pago con una terminacion de 53 centavos, lo que generó que el sistema de la administración imputara ese pago a la unidad funcional 7°F, cuando en realidad dicha unidad nunca abonó. Debido a que el inconveniente y la confusión se originan a partir de una situación ajena a la unidad funcional 7°F, la administración decidió no aplicar los punitorios correspondientes al momento de rehacer y corregir los cálculos.

Sheet SITUACION 6B
D4: Deuda a Financiar | F4: 843306.42 | G4: En el mes de febrero se abonaron $200.000,42 pesos que correspondieron $132.000 en concepto de honorarios de la Sra. Abogada y el restante ($68.000 en concepto de adelanto)
D5: Ingreso de convenio | F5: -68000
D6: Saldo | F6: =F4+F5 -> 775306.42
D8: Gastos A Febrero | F8: 135235.8
D9: Gastos B Febrero | F9: 33600
D11: Total | F11: =F6+F8+F9 -> 944142.22
D13: El saldo total sera abonado mediante 24 cuotas de $33.000
