Workbook

Sheet RESUMEN
B1: MAIL:consorcio2demayo2813.15@gmail.com
B2: CUIT ADMINISTRACION: 27231256879
B3: Banco SANTENDER -- Cta.Corr. Pesos N° 054-011139/1 -- CBU: 0720054020000001113918 -- Alias: BALA.EMPATE.MIXTO
A4: LIQUIDACION DE EXPENSAS | B4: ADMINISTRADORA: CAROLINA CANCIANI MP:1148
A5: CUIT DEL EDIFICIO: 30710914784 | B5: PERÍODO: MAYO | D5: HORARIOS DE ATENCION: LUNES A VIERNES
A6: CONSORCIO 2 DE MAYO 2813/15 - LIQUIDACIÓN DE GASTOS ABRIL 2026 | D6: 10 A 15HS - EMERGENCIAS 24HS
B8: VTO 18/06
A13: Importante para dueños o inquilinos de departamentos o coheras: Queremos recordarles una cuestión importante respecto a los pagos de expensas que ayuda a evitar errores en la imputación de los mismos. El sistema que utilizamos asigna centavos únicos a cada Unidad Funcional (UF), lo cual nos permite identificar automáticamente a qué unidad corresponde cada transferencia. Es decir, cada UF tiene un número específico de centavos que actúa como "identificador". Por ejemplo, si tu UF es la 45, el importe a abonar debería terminar en $...,45. Si tenés más de una unidad (por ejemplo, un departamento y una cochera), cada una tiene su propio código de centavos. En esos casos, te pedimos por favor que realices una transferencia por cada UF, respetando el importe con sus centavos correspondientes. Sabemos que a veces por comodidad se suele enviar todo junto en una sola transferencia, pero esto puede generar confusión o errores en la imputación automática. Realizar los pagos por separado nos permite asegurar que cada importe se asigne correctamente. Agradecemos muchísimo la colaboración para seguir manteniendo todo ordenado. Saludos cordiales.
A20: GASTOS ORDINARIOS UNIDADES FUNCIONALES:
A21: HABERES ENCARGADOS
A22: Sueldo Sra. Gomez Blanca Lucia | B22: Mes de MAYO | D22: 1122787.6
A23: Descuentos | D23: -277889.95
A24: Redondeo | D24: 0.33
A25: Neto | D25: =SUM(D22:D24) -> 844898
A26: Sueldo encargado Balcazza Leonardo
A30: SAC
A31: Neto | D31: =SUM(D26:D30) -> 0
A32: TOTAL SUELDO | E32: =D25+D31 -> 844898
A33: HONORARIOS
A34: Gustavo Padron - Sr. Contador | D34: 45000 | E34: Transf 07/05
A35: Honorarios administracion | D35: 120000
A36: TOTAL | E36: =SUM(D34:D35) -> 165000
A37: SEGUROS
A38: Seguros Integral de Consorcio BERKLEY INTERNATIONAL SEGUROS S.A. Poliza N° 13-228546 | D38: 65251.97 | E38: Transf 06/04
A40: TOTAL IMPUESTO | E40: =SUM(D38:D39) -> 65251.97
A41: APORTES Y CONTRIBUCIONES
A42: ARCA | D42: 646408.72 | E42: Transf 06/04
A43: Sindicatos mes de MAYO | B43: Suther | D43: 50525.44 | E43: Debito 13/04
A44: =A43 -> Sindicatos mes de MAYO | B44: Fathery | D44: 94598.2 | E44: =E43 -> Debito 13/04
A45: =A44 -> Sindicatos mes de MAYO | B45: Seracarh | D45: 5613.94 | E45: =E44 -> Debito 13/04
A46: TOTAL Aportes y Contribuciones - Sindicato | E46: =SUM(D42:D45) -> 797146.3
A47: ABONOS Y SERVICIOS
A48: Edesur | D48: 362202.08 | E48: Transf 05/05
A49: AySa | D49: 345591.71 | E49: Transf 06/04
A50: TOTAL ABONOS Y SERVICIOS | E50: =SUM(D48:D49) -> 707793.79
A52: Personal Flow (internet) para las Camaras de Seguridad | D52: 24292.79 | E52: Transf 06/04
A53: Contessi - Pago del abono del ascensor - Mantenimiento | D53: 105000 | E53: Transf 08/05
A54: ADS - Se adeudaba mantenimiento de ascensores Febrero | D54: 125300 | E54: Transf 21/04
A55: ADS - Se adeudaba mantenimiento de ascensores ABRIL | D55: 125300 | E55: Transf 21/04
A56: ADS - Se adeudaba suministro y colocacion de tubo led ABRIL | D56: 6534 | E56: Transf 21/04
A57: Servicios Sarcinelli - Trabajos en cambios de sensores de movimientos en palier | D57: 80700 | E57: Transf 12/05
A58: Andadino - 3 platos para postre de porcelana | D58: 27000
A59: Sucesion de Majic - baranda de acero inoxidable | D59: 666105 | E59: Transf 19/05
A60: Doartero Julio - Reparacion techo del baño | D60: 120000 | E60: Transf 21/04
A61: MAS Limpio - Articulos de limpieza | D61: 27200 | E61: Transf 19/05
A62: Papelera Mayor - Compra de bolsas de consorcio | D62: 11452.78
A64: TOTAL | E64: =SUM(D52:D63) -> 1318884.6
A65: GASTOS BANCARIOS
A66: Mantenimiento de cuenta | D66: 57500
A67: Gastos bancarios | D67: =65392.09-0.07 -> 65392.02
A68: TOTAL | E68: =SUM(D66:D67) -> 122892.02
A70: PREVISION ORDINARIA | E70: =4095718.96-3251841.04 -> 843877.92
A72: TOTAL ORDINARIOS | E72: =(SUM(E28:E70)) -> 4865744.6
A75: GASTOS EXTRAORDINARIOS:
E80: =SUM(D76:D79) -> 0
A83: PREVISION EXTRAORDINARIA | E83: 120000
A85: TOTAL EXTRAORDINARIOS | E85: =E80+E83 -> 120000
A87: GASTOS ORDINARIOS + PREVISION : | B87: =E72 -> 4865744.6
A88: GASTOS ORDINARIOS SIN PREVISION: | B88: =E72-E70 -> 4021866.7
A89: GASTOS EXTRAORDINARIOS SIN PREVISION: | B89: =E85-E83 -> 0
A90: GASTOS EXTRAORDINARIOS CON PREVISION: | B90: =E85 -> 120000
A93: Caja en efectivo | B93: 519937.4
A94: Ingreso por pago de expensas | B94: =PRORRATEO!G38 -> 290000
A95: Honorarios administracion ABRIL | B95: -120000
A96: Honorarios administracion MAYO | B96: -120000
A97: Andadino - Compra de 3 platos SUM (5A) | B97: -27000
A98: Articulos de limpieza - El boliche de Rivero | B98: -18000
A99: Articulos de limpieza -Mas limpio | B99: -31100
A100: CAJA REAL | B100: =SUM(B93:C99) -> 493837.4
A102: SALDO EN BANCO | B102: 560288.74
A103: Egresos del mes ordinarios | B103: =-B88 -> -4021866.7
A104: Egresos del mes extrordinarios | B104: =-B89 -> 0
A105: Pagos sin identificar | B105: =B114 -> 0
A106: Ingresos | B106: =PRORRATEO!G37 -> 4007972.1
A107: CAJA REAL | B107: =SUM(B102:C106) -> 546394.19
A110: DEPOSITOS NO IDENTIFICADOS
C112: 40000
A114: TOTAL | B114: =SUM(B112:B113) -> 0

Sheet PRORRATEO
C2: Extraordinarios: | D2: 120000 | L2: Ordinarios: | M2: =Q2 -> 4095719 | Q2: 4095719
A4: =RESUMEN!A13 -> Importante para dueños o inquilinos de departamentos o coheras: Queremos recordarles una cuestión importante respecto a los pagos de expensas que ayuda a evitar errores en la imputación de los mismos. El sistema que utilizamos asigna centavos únicos a cada Unidad Funcional (UF), lo cual nos permite identificar automáticamente a qué unidad corresponde cada transferencia. Es decir, cada UF tiene un número específico de centavos que actúa como "identificador". Por ejemplo, si tu UF es la 45, el importe a abonar debería terminar en $...,45. Si tenés más de una unidad (por ejemplo, un departamento y una cochera), cada una tiene su propio código de centavos. En esos casos, te pedimos por favor que realices una transferencia por cada UF, respetando el importe con sus centavos correspondientes. Sabemos que a veces por comodidad se suele enviar todo junto en una sola transferencia, pero esto puede generar confusión o errores en la imputación automática. Realizar los pagos por separado nos permite asegurar que cada importe se asigne correctamente. Agradecemos muchísimo la colaboración para seguir manteniendo todo ordenado. Saludos cordiales.
A9: UF | B9: Piso | C9: Propietario | E9: (%) | F9: Saldo Ord | G9: Ingreso | H9: Abona mediante | I9: Deuda o Saldo a favor | J9: Interes 3% | K9: Particular | L9: Expensas ord. | M9: Expensas extraord. | N9: Total 1er Vto | O9: Total 2do Vto
N10: =RESUMEN!B8 -> VTO 18/06
A11: 1° P. | B11: A | C11: CHAS Alejandro | E11: 6.18 | F11: 260531.01 | G11: =F11 -> 260531.01 | H11: B | I11: =F11-G11 -> 0 | J11: =IF(I11>0,I11*3%,0) -> 0 | L11: =M$2*E11/100 -> 253115.43 | M11: =D$2*E11/100 -> 7416 | N11: =ROUND(SUM(I11:M11),0) + P11 -> 260531.01 | O11: =ROUND(N11*3%,0) + N11 -> 268347.01 | P11: 0.01
A12: 1° P. | B12: B | C12: PELLEGRINI Cecilia | D12: Rojas Alejandro | E12: 4.33 | F12: 182541.02 | G12: 188017.02 | H12: B | I12: =F12-G12 -> -5476 | J12: =IF(I12>0,I12*3%,0) -> 0 | L12: =M$2*E12/100 -> 177344.63 | M12: =D$2*E12/100 -> 5196 | N12: =ROUND(SUM(I12:M12),0) + P12 -> 177065.02 | O12: =ROUND(N12*3%,0) + N12 -> 182377.02 | P12: =P11+0.01 -> 0.02
A13: 2° P. | B13: A | C13: MAZZUCO M. Gabriela | E13: 6.18 | F13: 258712.03 | G13: 270000.03 | H13: B | I13: =F13-G13 -> -11288 | J13: =IF(I13>0,I13*3%,0) -> 0 | L13: =M$2*E13/100 -> 253115.43 | M13: =D$2*E13/100 -> 7416 | N13: =ROUND(SUM(I13:M13),0) + P13 -> 249243.03 | O13: =ROUND(N13*3%,0) + N13 -> 256720.03 | P13: =P12+0.01 -> 0.03
A14: 2° P. | B14: B | C14: ORREF Cristina | E14: 4.33 | F14: 182541.04 | G14: =F14 -> 182541.04 | H14: B | I14: =F14-G14 -> 0 | J14: =IF(I14>0,I14*3%,0) -> 0 | L14: =M$2*E14/100 -> 177344.63 | M14: =D$2*E14/100 -> 5196 | N14: =ROUND(SUM(I14:M14),0) + P14 -> 182541.04 | O14: =ROUND(N14*3%,0) + N14 -> 188017.04 | P14: =P13+0.01 -> 0.04
A15: 3° P. | B15: A | C15: TARANTO / CASTRO | D15: Gisele Santillan | E15: 6.18 | F15: 260531.05 | G15: 253115.05 | H15: B | I15: =F15-G15 -> 7416 | J15: =IF(I15>0,I15*3%,0) -> 222.48 | L15: =M$2*E15/100 -> 253115.43 | M15: =D$2*E15/100 -> 7416 | N15: =ROUND(SUM(I15:M15),0) + P15 -> 268170.05 | O15: =ROUND(N15*3%,0) + N15 -> 276215.05 | P15: =P14+0.01 -> 0.05
A16: 3° P. | B16: B | C16: PALAVECINO Carina | E16: 4.33 | F16: 177605.06 | G16: 182933.06 | H16: B | I16: =F16-G16 -> -5328 | J16: =IF(I16>0,I16*3%,0) -> 0 | L16: =M$2*E16/100 -> 177344.63 | M16: =D$2*E16/100 -> 5196 | N16: =ROUND(SUM(I16:M16),0) + P16 -> 177213.06 | O16: =ROUND(N16*3%,0) + N16 -> 182529.06 | P16: =P15+0.01 -> 0.06
A17: 4° P. | B17: A | C17: TOTH Alvaro | E17: 6.18 | F17: 268348.07 | G17: =290000-G32 -> 256433.78 | H17: B | I17: =F17-G17 -> 11914.29 | J17: =IF(I17>0,I17*3%,0) -> 357.4287 | L17: =M$2*E17/100 -> 253115.43 | M17: =D$2*E17/100 -> 7416 | N17: =ROUND(SUM(I17:M17),0) + P17 -> 272803.07 | O17: =ROUND(N17*3%,0) + N17 -> 280987.07 | P17: =P16+0.01 -> 0.07
A18: 4° P. | B18: B | C18: TARRACINI Norma | E18: 4.33 | F18: 177605.08 | G18: =182933.08 -> 182933.08 | H18: B | I18: =F18-G18 -> -5328 | J18: =IF(I18>0,I18*3%,0) -> 0 | L18: =M$2*E18/100 -> 177344.63 | M18: =D$2*E18/100 -> 5196 | N18: =ROUND(SUM(I18:M18),0) + P18 -> 177213.08 | O18: =ROUND(N18*3%,0) + N18 -> 182529.08 | P18: =P17+0.01 -> 0.08
A19: 5° P. | B19: A | C19: ERRAMUSPE Alberto | E19: 6.18 | F19: 244746.09 | G19: =290000-G33 -> 256433.78 | H19: E | I19: =F19-G19 -> -11687.69 | J19: =IF(I19>0,I19*3%,0) -> 0 | K19: =80000+27000 -> 107000 | L19: =M$2*E19/100 -> 253115.43 | M19: =D$2*E19/100 -> 7416 | N19: =ROUND(SUM(I19:M19),0) + P19 -> 355844.09 | O19: =ROUND(N19*3%,0) + N19 -> 366519.09 | P19: =P18+0.01 -> 0.09
A20: 5° P. | B20: B | C20: TEJEIRO Pablo | E20: 4.33 | F20: 182393.1 | G20: =F20+RESUMEN!D58 -> 209393.1 | H20: B | I20: =F20-G20 -> -27000 | J20: =IF(I20>0,I20*3%,0) -> 0 | L20: =M$2*E20/100 -> 177344.63 | M20: =D$2*E20/100 -> 5196 | N20: =ROUND(SUM(I20:M20),0) + P20 -> 155541.1 | O20: =ROUND(N20*3%,0) + N20 -> 160207.1 | P20: =P19+0.01 -> 0.1
A21: 6° P. | B21: A | C21: VINCI M. Teresa | D21: Bruno Francisco Bonanno | E21: 6.18 | F21: 253486.11 | G21: 261091.11 | H21: B | I21: =F21-G21 -> -7605 | J21: =IF(I21>0,I21*3%,0) -> 0 | L21: =M$2*E21/100 -> 253115.43 | M21: =D$2*E21/100 -> 7416 | N21: =ROUND(SUM(I21:M21),0) + P21 -> 252926.11 | O21: =ROUND(N21*3%,0) + N21 -> 260514.11 | P21: =P20+0.01 -> 0.11
A22: 6° P. | B22: B | C22: DOVHUN PODLASKY Nina | E22: 4.33 | F22: 182582.12 | G22: 189000 | H22: B | I22: =F22-G22 -> -6417.88 | J22: =IF(I22>0,I22*3%,0) -> 0 | L22: =M$2*E22/100 -> 177344.63 | M22: =D$2*E22/100 -> 5196 | N22: =ROUND(SUM(I22:M22),0) + P22 -> 176123.12 | O22: =ROUND(N22*3%,0) + N22 -> 181407.12 | P22: =P21+0.01 -> 0.12
A23: 7° P. | B23: A | C23: MENDEZ Magali / GIL F. | D23: Matias Roig | E23: 6.18 | F23: 260531.13 | G23: =F23 -> 260531.13 | H23: B | I23: =F23-G23 -> 0 | J23: =IF(I23>0,I23*3%,0) -> 0 | L23: =M$2*E23/100 -> 253115.43 | M23: =D$2*E23/100 -> 7416 | N23: =ROUND(SUM(I23:M23),0) + P23 -> 260531.13 | O23: =ROUND(N23*3%,0) + N23 -> 268347.13 | P23: =P22+0.01 -> 0.13
A24: 7° P. | B24: B | C24: HERNANDEZ Antonella | E24: 4.33 | F24: 177605.14 | G24: =F24 -> 177605.14 | H24: B | I24: =F24-G24 -> 0 | J24: =IF(I24>0,I24*3%,0) -> 0 | L24: =M$2*E24/100 -> 177344.63 | M24: =D$2*E24/100 -> 5196 | N24: =ROUND(SUM(I24:M24),0) + P24 -> 182541.14 | O24: =ROUND(N24*3%,0) + N24 -> 188017.14 | P24: =P23+0.01 -> 0.14
A25: 8° P. | B25: A | C25: CARDINALE Horacio | E25: 6.18 | F25: 247669.15 | G25: =464798.38-G26-G35 -> 249668.97 | H25: B | I25: =F25-G25 -> -1999.82 | J25: =IF(I25>0,I25*3%,0) -> 0 | L25: =M$2*E25/100 -> 253115.43 | M25: =D$2*E25/100 -> 7416 | N25: =ROUND(SUM(I25:M25),0) + P25 -> 258532.15 | O25: =ROUND(N25*3%,0) + N25 -> 266288.15 | P25: =P24+0.01 -> 0.15
A26: 8° P. | B26: B | C26: CARDINALE Horacio | E26: 4.33 | F26: 182541.16 | G26: =F26 -> 182541.16 | H26: B | I26: =F26-G26 -> 0 | J26: =IF(I26>0,I26*3%,0) -> 0 | L26: =M$2*E26/100 -> 177344.63 | M26: =D$2*E26/100 -> 5196 | N26: =ROUND(SUM(I26:M26),0) + P26 -> 182541.16 | O26: =ROUND(N26*3%,0) + N26 -> 188017.16 | P26: =P25+0.01 -> 0.16
A27: 9° P. | B27: A | C27: SUAREZ Nicolas | D27: Jose L. Suarez Pena | E27: 6.18 | F27: 253582.17 | G27: 253582.17 | H27: B | I27: =F27-G27 -> 0 | J27: =IF(I27>0,I27*3%,0) -> 0 | L27: =M$2*E27/100 -> 253115.43 | M27: =D$2*E27/100 -> 7416 | N27: =ROUND(SUM(I27:M27),0) + P27 -> 260531.17 | O27: =ROUND(N27*3%,0) + N27 -> 268347.17 | P27: =P26+0.01 -> 0.17
A28: 9° P. | B28: B | C28: SOUTO Patricio | E28: 4.33 | F28: 177605.18 | G28: =F28 -> 177605.18 | H28: B | I28: =F28-G28 -> 0 | J28: =IF(I28>0,I28*3%,0) -> 0 | L28: =M$2*E28/100 -> 177344.63 | M28: =D$2*E28/100 -> 5196 | N28: =ROUND(SUM(I28:M28),0) + P28 -> 182541.18 | O28: =ROUND(N28*3%,0) + N28 -> 188017.18 | P28: =P27+0.01 -> 0.18
A29: Cochera 1 | C29: SUAREZ Nicolas | E29: 0.773 | F29: 31707.19 | G29: =F29 -> 31707.19 | H29: B | I29: =F29-G29 -> 0 | J29: =IF(I29>0,I29*3%,0) -> 0 | L29: =M$2*E29/100 -> 31659.908 | M29: =D$2*E29/100 -> 927.6 | N29: =ROUND(SUM(I29:M29),0) + P29 -> 32588.19 | O29: =ROUND(N29*3%,0) + N29 -> 33566.19 | P29: =P28+0.01 -> 0.19
A30: Cochera 2 | C30: MAZZUCO M. Gabriela | E30: 0.773 | F30: 31962.2 | G30: 40000.2 | H30: B | I30: =F30-G30 -> -8038 | J30: =IF(I30>0,I30*3%,0) -> 0 | L30: =M$2*E30/100 -> 31659.908 | M30: =D$2*E30/100 -> 927.6 | N30: =ROUND(SUM(I30:M30),0) + P30 -> 24550.2 | O30: =ROUND(N30*3%,0) + N30 -> 25287.2 | P30: =P29+0.01 -> 0.2
A31: Cochera 3 | C31: MENDEZ Mendez / GIL F. | D31: Matias Roig | E31: 0.773 | F31: 32588.21 | G31: =F31 -> 32588.21 | H31: B | I31: =F31-G31 -> 0 | J31: =IF(I31>0,I31*3%,0) -> 0 | L31: =M$2*E31/100 -> 31659.908 | M31: =D$2*E31/100 -> 927.6 | N31: =ROUND(SUM(I31:M31),0) + P31 -> 32588.21 | O31: =ROUND(N31*3%,0) + N31 -> 33566.21 | P31: =P30+0.01 -> 0.21
A32: Cochera 4 | C32: TOTH Alvaro | E32: 0.773 | F32: 33566.22 | G32: =F32 -> 33566.22 | H32: B | I32: =F32-G32 -> 0 | J32: =IF(I32>0,I32*3%,0) -> 0 | L32: =M$2*E32/100 -> 31659.908 | M32: =D$2*E32/100 -> 927.6 | N32: =ROUND(SUM(I32:M32),0) + P32 -> 32588.22 | O32: =ROUND(N32*3%,0) + N32 -> 33566.22 | P32: =P31+0.01 -> 0.22
A33: Cochera 5 | C33: ERRAMUSPE Alberto | E33: 0.773 | F33: 32588.23 | G33: =G32 -> 33566.22 | H33: E | I33: =F33-G33 -> -977.99 | J33: =IF(I33>0,I33*3%,0) -> 0 | L33: =M$2*E33/100 -> 31659.908 | M33: =D$2*E33/100 -> 927.6 | N33: =ROUND(SUM(I33:M33),0) + P33 -> 31610.23 | O33: =ROUND(N33*3%,0) + N33 -> 32558.23 | P33: =P32+0.01 -> 0.23
A34: Cochera 6 | C34: VINCI M. Teresa | D34: Vanesa | E34: 0.773 | F34: 99087.24 | G34: 100000 | H34: B | I34: =F34-G34 -> -912.76 | J34: =IF(I34>0,I34*3%,0) -> 0 | L34: =M$2*E34/100 -> 31659.908 | M34: =D$2*E34/100 -> 927.6 | N34: =ROUND(SUM(I34:M34),0) + P34 -> 31675.24 | O34: =ROUND(N34*3%,0) + N34 -> 32625.24 | P34: =P33+0.01 -> 0.24
A35: Cochera 7 | C35: CARDINALE Horacio | E35: 0.773 | F35: 32588.25 | G35: =F35 -> 32588.25 | H35: B | I35: =F35-G35 -> 0 | J35: =IF(I35>0,I35*3%,0) -> 0 | L35: =M$2*E35/100 -> 31659.908 | M35: =D$2*E35/100 -> 927.6 | N35: =ROUND(SUM(I35:M35),0) + P35 -> 32588.25 | O35: =ROUND(N35*3%,0) + N35 -> 33566.25 | P35: =P34+0.01 -> 0.25
A36: TOTALES | E36: =SUM(E11:E35) -> 100.001 | F36: =SUM(F11:F35) -> 4225243.3 | G36: =SUM(G11:G35) -> 4297972.1 | I36: =SUM(I11:I35) -> -72728.85 | J36: =SUM(J11:J35) -> 579.9087 | L36: =SUM(L11:L35) -> 4095759.9 | M36: =SUM(M11:M35) -> 120001.2 | N36: =SUM(N11:N28) -> 4032431.7 | O36: =SUM(O11:O35) -> 4378138.3
F37: Ingreso pago x banco | G37: =SUMIF(H11:H35,"B",G11:G35) -> 4007972.1
F38: Ingreso pago x efectivo | G38: =SUMIF(H11:H35,"E",G11:G35) -> 290000
G39: =SUM(G37:G38) -> 4297972.1
F50: =SUM(E48:E49) -> 0
A52: Personal Flow (internet) para las Camaras de Seguridad
A53: Pago del abono del ascensor ADS - Mantenimiento
F54: =SUM(E52:E53) -> 0

Sheet ANOTACIONES
