Workbook

Sheet detalle y gastos
B2: CANCIANI, Carolina | C2: MP 1148
B3: Tel. 11 5320-2676
B4: consorciosrc13@gmail.com
A7: EDIFICIO ROSALES 624 | B7: LIQUIDACIÓN EXPENSAS JUNIO 2025 | C7: Vto. 14/07
A10: Teléfonos útiles
A11: EDESUR 0800-333-3787
A12: AySA 0800-321-2482
A13: Metrogas 0800-333-6427
A15: GASTOS ORDINARIOS
A16: ABONOS y SERVICIOS
A18: Seguro de consorcio obligatorio - federacion patronal - poliza nro. 2027630 | C18: 76654
A19: AYSA | C19: 308535.11
A20: Ascensores Lema | C20: 65000
A21: RC Adm Cons CANCIANI, Carolina | B21: Honorarios administracion | C21: 78682.46 | F21: Subidos en ABR 2025
C22: =SUM(C17:C21) -> 528871.57
A23: LIMPIEZA / MANTENIMIENTO / GASTOS GENERALES
A24: Sueldo personal de limpieza y maestranza | C24: 349151.87
A25: Seguro de vida Sra encargada | C25: 5684
A26: Matias Salvatierra - Desobstruccion de colectora cloacal | C26: 56650
A27: Casa Koruk - Botas de encargada | C27: 20000
A28: Sebastian | C28: 65000
A29: Fumigacion mes de JUNIO | C29: 45000
A30: PREVISION ORDINARIA
C31: =SUM(C23:C30) -> 541485.87
A32: TOTAL GASTOS ORDINARIOS (A) | C32: =+C31+C22 -> 1070357.4
A34: GASTOS EXTRAORDINARIOS
A39: PREVISION EXTRAORDINARIA GASTOS A DEFINIR EN ASAMBLEA | C39: 1000000
A41: TOTAL GASTOS EXTRAORDINARIOS (B) | C41: =+C35+C36+C37+C40 -> 0
A43: TOTAL GENERAL DE GASTOS (A) + (B) | C43: =+C41+C32 -> 1070357.4
A48: CAJA ANTERIOR | C48: -664175.24
A49: EGRESOS DEL MES DE JUNIO | C49: =-(C32-C30) -> -1070357.4
A50: INGRESOS CORRESPONDIENTES AL PAGO DE EXPENSAS | C50: ='prorrateo '!F31 -> 1137720.8
A52: Saldo al cierre $ (pesos) | C52: =SUM(C46:C50) -> -596811.89
A56: CAJA EXTRAORDINARIA
A57: Egreso extraordinario | C57: =-C41 -> 0
A60: TOTAL | C60: =SUM(C56:C59) -> 0

Sheet prorrateo 
A1: Expensas ordinarias: | B1: =D1 -> 1436145.7 | D1: 1436145.7 | E1: Gastos extraordinarios: | G1: 1000000
A2: Propietarios | B2: Inquilinos | C2: UNIDAD FUNCIONAL | D2: % | E2: SALDO ANTERIOR | F2: SALDO ABONADO | G2: SALDO | H2: PUNITORIOS 4% | I2: ORDINARIAS | J2: EXTRAORDINARIAS | K2: EDESUR | L2: A PAGAR
A3: Ferrea Nestor | B3: Gabriel | C3: 1ro. "A" | D3: 5.11 | E3: 73387.046 | F3: =E3 -> 73387.046 | G3: =E3-F3 -> 0 | H3: =IF(G3>0,G3*4%,0) -> 0 | I3: =B$1*D3/100 -> 73387.046 | J3: =G$1*D3/100 -> 51100 | L3: =I3+G3+K3+J3+H3 -> 124487.05
A4: Gnecchi Nicolas | B4: Brian | C4: 1ro. "B" | D4: 5.09 | E4: 73099.817 | F4: =E4 -> 73099.817 | G4: =E4-F4 -> 0 | H4: =IF(G4>0,G4*4%,0) -> 0 | I4: =B$1*D4/100 -> 73099.817 | J4: =G$1*D4/100 -> 50900 | L4: =I4+G4+K4+J4+H4 -> 123999.82
A5: Triñanes Gaston | B5: Leila | C5: 2do. "A" | D5: 5.04 | E5: 72381.744 | G5: =E5-F5 -> 72381.744 | H5: =IF(G5>0,G5*4%,0) -> 2895.2698 | I5: =B$1*D5/100 -> 72381.744 | J5: =G$1*D5/100 -> 50400 | L5: =I5+G5+K5+J5+H5 -> 198058.76
A6: Nuñez Eva | C6: 2do. "B" | D6: 5.21 | E6: 74823.191 | F6: =E6 -> 74823.191 | G6: =E6-F6 -> 0 | H6: =IF(G6>0,G6*4%,0) -> 0 | I6: =B$1*D6/100 -> 74823.191 | J6: =G$1*D6/100 -> 52100 | L6: =I6+G6+K6+J6+H6 -> 126923.19
A7: Triñanes Gaston | B7: Leandro | C7: 3ro. "A" | D7: 5.11 | E7: 73387.046 | G7: =E7-F7 -> 73387.046 | H7: =IF(G7>0,G7*4%,0) -> 2935.4818 | I7: =B$1*D7/100 -> 73387.046 | J7: =G$1*D7/100 -> 51100 | L7: =I7+G7+K7+J7+H7 -> 200809.57
A8: Grecco Pedro | C8: 3ro. "B" | D8: 5.09 | E8: 73099.817 | F8: =E8 -> 73099.817 | G8: =E8-F8 -> 0 | H8: =IF(G8>0,G8*4%,0) -> 0 | I8: =B$1*D8/100 -> 73099.817 | J8: =G$1*D8/100 -> 50900 | L8: =I8+G8+K8+J8+H8 -> 123999.82
A9: Mteljan Barbara | C9: 4to. "A" | D9: 5.11 | E9: 73387.046 | F9: =E9 -> 73387.046 | G9: =E9-F9 -> 0 | H9: =IF(G9>0,G9*4%,0) -> 0 | I9: =B$1*D9/100 -> 73387.046 | J9: =G$1*D9/100 -> 51100 | L9: =I9+G9+K9+J9+H9 -> 124487.05
A10: Carnevalli | B10: Christian / Vanina | C10: 4to. "B" | D10: 5.09 | E10: 340386.25 | G10: =E10-F10 -> 340386.25 | H10: =IF(G10>0,G10*4%,0) -> 13615.45 | I10: =B$1*D10/100 -> 73099.817 | J10: =G$1*D10/100 -> 50900 | L10: =I10+G10+K10+J10+H10 -> 478001.52
A11: Leonor | C11: 5to. "A" | D11: 5.04 | E11: 72381.744 | F11: =E11 -> 72381.744 | G11: =E11-F11 -> 0 | H11: =IF(G11>0,G11*4%,0) -> 0 | I11: =B$1*D11/100 -> 72381.744 | J11: =G$1*D11/100 -> 50400 | L11: =I11+G11+K11+J11+H11 -> 122781.74
A12: Strangio Federico | C12: 5to. "B" | D12: 5.21 | E12: 74823.191 | F12: =E12 -> 74823.191 | G12: =E12-F12 -> 0 | H12: =IF(G12>0,G12*4%,0) -> 0 | I12: =B$1*D12/100 -> 74823.191 | J12: =G$1*D12/100 -> 52100 | L12: =I12+G12+K12+J12+H12 -> 126923.19
A13: Senderowicz Rosalia | B13: Alejo | C13: 6to. "A" | D13: 5.11 | E13: 73387.046 | F13: =E13 -> 73387.046 | G13: =E13-F13 -> 0 | H13: =IF(G13>0,G13*4%,0) -> 0 | I13: =B$1*D13/100 -> 73387.046 | J13: =G$1*D13/100 -> 51100 | L13: =I13+G13+K13+J13+H13 -> 124487.05
A14: Senderowicz Rosalia | C14: 6to. "B" | D14: 5.09 | E14: 73099.817 | G14: =E14-F14 -> 73099.817 | H14: =IF(G14>0,G14*4%,0) -> 2923.9927 | I14: =B$1*D14/100 -> 73099.817 | J14: =G$1*D14/100 -> 50900 | L14: =I14+G14+K14+J14+H14 -> 200023.63
A15: Alonso Graciela | B15: Facundo | C15: 7mo. "A" | D15: 5.04 | E15: 214265.93 | F15: =E15 -> 214265.93 | G15: =E15-F15 -> 0 | H15: =IF(G15>0,G15*4%,0) -> 0 | I15: =B$1*D15/100 -> 72381.744 | J15: =G$1*D15/100 -> 50400 | L15: =I15+G15+K15+J15+H15 -> 122781.74
A16: Perez Rodriguez | B16: Mariel | C16: 7mo. "B" | D16: 5.21 | E16: 74823.191 | G16: =E16-F16 -> 74823.191 | H16: =IF(G16>0,G16*4%,0) -> 2992.9277 | I16: =B$1*D16/100 -> 74823.191 | J16: =G$1*D16/100 -> 52100 | L16: =I16+G16+K16+J16+H16 -> 204739.31
A17: Mourelos Pablo | C17: 8vo. "A" | D17: 5.04 | E17: 72381.744 | F17: =E17 -> 72381.744 | G17: =E17-F17 -> 0 | H17: =IF(G17>0,G17*4%,0) -> 0 | I17: =B$1*D17/100 -> 72381.744 | J17: =G$1*D17/100 -> 50400 | L17: =I17+G17+K17+J17+H17 -> 122781.74
A18: Calabria Carlos/Giarrizzo Silvia | C18: 8vo. "B" | D18: 5.21 | E18: 74823.191 | F18: =E18 -> 74823.191 | G18: =E18-F18 -> 0 | H18: =IF(G18>0,G18*4%,0) -> 0 | I18: =B$1*D18/100 -> 74823.191 | J18: =G$1*D18/100 -> 52100 | L18: =I18+G18+K18+J18+H18 -> 126923.19
A19: Ariel | C19: 9no. "A" | D19: 7.4 | E19: 106274.78 | F19: =E19 -> 106274.78 | G19: =E19-F19 -> 0 | H19: =IF(G19>0,G19*4%,0) -> 0 | I19: =B$1*D19/100 -> 106274.78 | J19: =G$1*D19/100 -> 74000 | L19: =I19+G19+K19+J19+H19 -> 180274.78
B20: Christian / Vanina | C20: COCHERA 1 | D20: 1.08 | E20: 72223.408 | F20: 0 | G20: =E20-F20 -> 72223.408 | H20: =IF(G20>0,G20*4%,0) -> 2888.9363 | I20: =B$1*D20/100 -> 15510.374 | J20: =G$1*D20/100 -> 10800 | L20: =I20+G20+K20+J20+H20 -> 101422.72
B21: Mariel | C21: COCHERA 2 | D21: 1.08 | E21: 15510.374 | G21: =E21-F21 -> 15510.374 | H21: =IF(G21>0,G21*4%,0) -> 620.41495 | I21: =B$1*D21/100 -> 15510.374 | J21: =G$1*D21/100 -> 10800 | L21: =I21+G21+K21+J21+H21 -> 42441.162
C22: COCHERA 3 | D22: 1.08 | E22: 72223.408 | F22: 0 | G22: =E22-F22 -> 72223.408 | H22: =IF(G22>0,G22*4%,0) -> 2888.9363 | I22: =B$1*D22/100 -> 15510.374 | J22: =G$1*D22/100 -> 10800 | L22: =I22+G22+K22+J22+H22 -> 101422.72
B23: Leila | C23: COCHERA 4 | D23: 1.08 | E23: 15510.374 | G23: =E23-F23 -> 15510.374 | H23: =IF(G23>0,G23*4%,0) -> 620.41495 | I23: =B$1*D23/100 -> 15510.374 | J23: =G$1*D23/100 -> 10800 | L23: =I23+G23+K23+J23+H23 -> 42441.162
A24: Senderowicz Rosalia | B24: Alejo | C24: COCHERA 5 | D24: 1.08 | E24: 15510.374 | F24: =E24 -> 15510.374 | G24: =E24-F24 -> 0 | H24: =IF(G24>0,G24*4%,0) -> 0 | I24: =B$1*D24/100 -> 15510.374 | J24: =G$1*D24/100 -> 10800 | L24: =I24+G24+K24+J24+H24 -> 26310.374
A25: Senderowicz Rosalia | C25: COCHERA 6 | D25: 1.08 | E25: 15510.374 | G25: =E25-F25 -> 15510.374 | H25: =IF(G25>0,G25*4%,0) -> 620.41495 | I25: =B$1*D25/100 -> 15510.374 | J25: =G$1*D25/100 -> 10800 | L25: =I25+G25+K25+J25+H25 -> 42441.162
A26: Ariel | C26: COCHERA 7 | D26: 1.08 | E26: 15510.374 | F26: =E26 -> 15510.374 | G26: =E26-F26 -> 0 | H26: =IF(G26>0,G26*4%,0) -> 0 | I26: =B$1*D26/100 -> 15510.374 | J26: =G$1*D26/100 -> 10800 | L26: =I26+G26+K26+J26+H26 -> 26310.374
A27: Ariel | C27: COCHERA 8 | D27: 1.08 | E27: 15510.374 | F27: =E27 -> 15510.374 | G27: =E27-F27 -> 0 | H27: =IF(G27>0,G27*4%,0) -> 0 | I27: =B$1*D27/100 -> 15510.374 | J27: =G$1*D27/100 -> 10800 | L27: =I27+G27+K27+J27+H27 -> 26310.374 | O27: =F27+F26+F19 -> 137295.53
B28: =B7 -> Leandro | C28: COCHERA 9 | D28: 1.08 | E28: 15510.374 | G28: =E28-F28 -> 15510.374 | H28: =IF(G28>0,G28*4%,0) -> 620.41495 | I28: =B$1*D28/100 -> 15510.374 | J28: =G$1*D28/100 -> 10800 | L28: =I28+G28+K28+J28+H28 -> 42441.162
A29: Alonso Graciela | B29: Facundo | C29: COCHERA 10 | D29: 1.08 | E29: 35055.123 | F29: =E29 -> 35055.123 | G29: =E29-F29 -> 0 | H29: =IF(G29>0,G29*4%,0) -> 0 | I29: =B$1*D29/100 -> 15510.374 | J29: =G$1*D29/100 -> 10800 | L29: =I29+G29+K29+J29+H29 -> 26310.374
C31: TOTAL EXPENSAS | D31: =SUM(D3:D30) -> 100 | F31: =SUM(F3:F30) -> 1137720.8 | I31: =SUM(I3:I30) -> 1436145.7 | J31: =SUM(J3:J30) -> 1000000 | L31: =SUM(L3:L29) -> 3310334.7
A33: El 4B abonó parte de la deuda que tiene hasta Octubre de 2024 con la constructora, entendiendo que este mes cancela el resto

Sheet Edesur
A1: EDESUR
B7: EDESUR | C7: 265595.11 | F7: Se abona hasta el | J7: ='detalle y gastos'!C7 -> Vto. 14/07
B8: EDESUR | K8: =C8-J38 -> -159634.85 | L8: =C7-J38 -> 105960.26
A9: U.F. | B9: U.F. | C9: PISO - DEPTO | D9: PROPIETARIOS | E9: % | F9: CONSUMO ANT. | G9: CONSUMO ACTUAL | H9: KWH | I9: INTERES POR MORA 7% | J9: EDESUR | K9: PARTES COMUNES | L9: PARTES COMUNES | M9: KWH | N9: EDESUR FINAL
A10: 1 | B10: 1 | C10: 1ro. "A" | D10: ANA MARIA, MENDEZ | E10: 5.11 | F10: 3008.7 | G10: 3122.7 | H10: =G10-F10 -> 114 | I10: =H10*7% -> 7.98 | J10: =M10*93.787 -> 10691.718 | K10: =K8*E10% -> -8157.341 | L10: =L$8*E10/S$12 -> 5414.5691 | M10: =G10-F10 -> 114 | N10: =J10+L10 -> 16106.287 | O10: =N10+'prorrateo '!L3 -> 140593.33
A11: 2 | B11: 2 | C11: 1ro. "B" | D11: DANIEL, BALBIS | E11: 5.09 | F11: 3024.8 | G11: 3093.6 | H11: =G11-F11 -> 68.8 | I11: =H11*7% -> 4.816 | J11: =M11*93.787 -> 6452.5456 | K11: =K8*E11% -> -8125.414 | L11: =L$8*E11/S$12 -> 5393.3771 | M11: =G11-F11 -> 68.8 | N11: =J11+L11 -> 11845.923 | O11: =N11+'prorrateo '!L4 -> 135845.74
A12: 3 | B12: 3 | C12: 2do. "A" | D12: MIRTA SILVIA, BALBIS | E12: 5.04 | F12: 1270.2 | G12: 1314.5 | H12: =G12-F12 -> 44.3 | I12: =H12*7% -> 3.101 | J12: =M12*93.787 -> 4154.7641 | K12: =K8*E12% -> -8045.5966 | L12: =L$8*E12/S$12 -> 5340.397 | M12: =G12-F12 -> 44.3 | N12: =J12+L12 -> 9495.1611 | O12: =N12+'prorrateo '!L5 -> 207553.92 | S12: 100
A13: 4 | B13: 4 Y 5 | C13: 2do. "B" | D13: LUCILA Y MARINA LEONE | E13: 5.21 | F13: 706.3 | G13: 791.8 | H13: =G13-F13 -> 85.5 | I13: =H13*7% -> 5.985 | J13: =M13*93.787 -> 8018.7885 | K13: =K8*E13% -> -8316.9758 | L13: =L$8*E13/S$12 -> 5520.5294 | M13: =G13-F13 -> 85.5 | N13: =J13+L13 -> 13539.318 | O13: =N13+'prorrateo '!L6 -> 140462.51
A14: 6 | B14: 6 | C14: 3ro. "A" | D14: RICARDO, PLAUL | E14: 5.11 | F14: 1352.4 | G14: 1435.7 | H14: =G14-F14 -> 83.3 | I14: =H14*7% -> 5.831 | J14: =M14*93.787 -> 7812.4571 | K14: =K8*E14% -> -8157.341 | L14: =L$8*E14/S$12 -> 5414.5691 | M14: =G14-F14 -> 83.3 | N14: =J14+L14 -> 13227.026 | O14: =N14+'prorrateo '!L7 -> 214036.6
A15: 7 | B15: 7 | C15: 3ro. "B" | D15: RICARDO, PLAUL | E15: 5.09 | F15: 2383.2 | G15: 2418 | H15: =G15-F15 -> 34.8 | I15: =H15*7% -> 2.436 | J15: =M15*93.787 -> 3263.7876 | K15: =K8*E15% -> -8125.414 | L15: =L$8*E15/S$12 -> 5393.3771 | M15: =G15-F15 -> 34.8 | N15: =J15+L15 -> 8657.1647 | O15: =N15+'prorrateo '!L8 -> 132656.98
A16: 8 | B16: 8 | C16: 4to. "A" | D16: CLAUDIO ERNESTO, BICCAI | E16: 5.11 | F16: 1975.4 | G16: 2053.3 | H16: =G16-F16 -> 77.9 | I16: =H16*7% -> 5.453 | J16: =M16*93.787 -> 7306.0073 | K16: =K8*E16% -> -8157.341 | L16: =L$8*E16/S$12 -> 5414.5691 | M16: =G16-F16 -> 77.9 | N16: =J16+L16 -> 12720.576 | O16: =N16+'prorrateo '!L9 -> 137207.62
A17: 9 | B17: 9 | C17: 4to. "B" | D17: JAVIER, GASTON ESTELA | E17: 5.09 | F17: 3022.6 | G17: 3139.2 | H17: =G17-F17 -> 116.6 | I17: =H17*7% -> 8.162 | J17: =M17*93.787 -> 10935.564 | K17: =K8*E17% -> -8125.414 | L17: =L$8*E17/S$12 -> 5393.3771 | M17: =G17-F17 -> 116.6 | N17: =J17+L17 -> 16328.941 | O17: =N17+'prorrateo '!L10 -> 494330.46
A18: 10 | B18: 10 | C18: 5to. "A" | D18: VALENTINA SOL, DIRESE | E18: 5.04 | F18: 1692.8 | G18: 1790 | H18: =G18-F18 -> 97.2 | I18: =H18*7% -> 6.804 | J18: =M18*93.787 -> 9116.0964 | K18: =K8*E18% -> -8045.5966 | L18: =L$8*E18/S$12 -> 5340.397 | M18: =G18-F18 -> 97.2 | N18: =J18+L18 -> 14456.493 | O18: =N18+'prorrateo '!L11 -> 137238.24
A19: 11 | B19: 11 | C19: 5to. "B" | D19: PEDRO DANIEL, NIEVAS | E19: 5.21 | F19: 2773.4 | G19: 2998.2 | H19: =G19-F19 -> 224.8 | I19: =H19*7% -> 15.736 | J19: =M19*93.787 -> 21083.318 | K19: =K8*E19% -> -8316.9758 | L19: =L$8*E19/S$12 -> 5520.5294 | M19: =G19-F19 -> 224.8 | N19: =J19+L19 -> 26603.847 | O19: =N19+'prorrateo '!L12 -> 153527.04
A20: 12 | B20: 12 | C20: 6to. "A" | D20: PEDRO DANIEL, NIEVAS | E20: 5.11 | F20: 4496.3 | G20: 4665.5 | H20: =G20-F20 -> 169.2 | I20: =H20*7% -> 11.844 | J20: =M20*93.787 -> 15868.76 | K20: =K8*E20% -> -8157.341 | L20: =L$8*E20/S$12 -> 5414.5691 | M20: =G20-F20 -> 169.2 | N20: =J20+L20 -> 21283.33 | O20: =N20+'prorrateo '!L13 -> 145770.38
A21: 13 | B21: 13 | C21: 6to. "B" | D21: LEONARDO, PASCARELLI | E21: 5.09 | F21: 3467.1 | G21: 3467.1 | H21: =G21-F21 -> 0 | I21: =H21*7% -> 0 | J21: =M21*93.787 -> 0 | K21: =K8*E21% -> -8125.414 | L21: =L$8*E21/S$12 -> 5393.3771 | M21: =G21-F21 -> 0 | N21: =J21+L21 -> 5393.3771 | O21: =N21+'prorrateo '!L14 -> 205417
A22: 14 | B22: 14 | C22: 7mo. "A" | D22: LEONOR, LUCIA, LABIANCA | E22: 5.04 | F22: 2015.9 | G22: 2097.9 | H22: =G22-F22 -> 82 | I22: =H22*7% -> 5.74 | J22: =M22*93.787 -> 7690.534 | K22: =K8*E22% -> -8045.5966 | L22: =L$8*E22/S$12 -> 5340.397 | M22: =G22-F22 -> 82 | N22: =J22+L22 -> 13030.931 | O22: =N22+'prorrateo '!L15 -> 135812.67
A23: 15 | B23: 15 | C23: 7mo. "B" | D23: ANA LAURA, MEDINA | E23: 5.21 | F23: 4072.7 | G23: 4222.8 | H23: =G23-F23 -> 150.1 | I23: =H23*7% -> 10.507 | J23: =M23*93.787 -> 14077.429 | K23: =K8*E23% -> -8316.9758 | L23: =L$8*E23/S$12 -> 5520.5294 | M23: =G23-F23 -> 150.1 | N23: =J23+L23 -> 19597.958 | O23: =N23+'prorrateo '!L16 -> 224337.27
A24: 16 | B24: 16 | C24: 8vo. "A" | D24: ANGEL ANTONIO, RUDDOCK | E24: 5.04 | F24: 1462.2 | G24: 1529.3 | H24: =G24-F24 -> 67.1 | I24: =H24*7% -> 4.697 | J24: =M24*93.787 -> 6293.1077 | K24: =K8*E24% -> -8045.5966 | L24: =L$8*E24/S$12 -> 5340.397 | M24: =G24-F24 -> 67.1 | N24: =J24+L24 -> 11633.505 | O24: =N24+'prorrateo '!L17 -> 134415.25
A25: 17 | B25: 17 | C25: 8vo. "B" | D25: ALCOLEAS, CRISTIAN FABIO | E25: 5.21 | F25: 1352.5 | G25: 1452.3 | H25: =G25-F25 -> 99.8 | I25: =H25*7% -> 6.986 | J25: =M25*93.787 -> 9359.9426 | K25: =K8*E25% -> -8316.9758 | L25: =L$8*E25/S$12 -> 5520.5294 | M25: =G25-F25 -> 99.8 | N25: =J25+L25 -> 14880.472 | O25: =N25+'prorrateo '!L18 -> 141803.66
A26: 18 | B26: 18 | C26: 9no. "A" | D26: WALTER HUGO, SANDOVAL | E26: 7.4 | F26: 7102.6 | G26: 7289.3 | H26: =G26-F26 -> 186.7 | I26: =H26*7% -> 13.069 | J26: =M26*93.787 -> 17510.033 | K26: =K8*E26% -> -11812.979 | L26: =L$8*E26/S$12 -> 7841.059 | M26: =G26-F26 -> 186.7 | N26: =J26+L26 -> 25351.092 | O26: =N26+'prorrateo '!L19 -> 205625.87
A27: 19 | B27: 19 | C27: COCHERA 1 | D27: PEDRO DANIEL, NIEVAS | E27: 1.08 | H27: =G27-F27 -> 0 | I27: =H27*7% -> 0 | L27: =L$8*E27/S$12 -> 1144.3708 | M27: 0 | N27: =J27+L27 -> 1144.3708 | O27: =N27+'prorrateo '!L20 -> 102567.09
A28: 20 | C28: COCHERA 2 | E28: 1.08 | H28: 0 | I28: =H28*7% -> 0 | L28: =L$8*E28/S$12 -> 1144.3708 | M28: 0 | N28: =J28+L28 -> 1144.3708 | O28: =N28+'prorrateo '!L21 -> 43585.533
C29: COCHERA 3 | E29: 1.08 | L29: =L$8*E29/S$12 -> 1144.3708 | M29: 0 | N29: =J29+L29 -> 1144.3708 | O29: =N29+'prorrateo '!L22 -> 102567.09
C30: COCHERA 4 | E30: 1.08 | L30: =L$8*E30/S$12 -> 1144.3708 | M30: 0 | N30: =J30+L30 -> 1144.3708 | O30: =N30+'prorrateo '!L23 -> 43585.533
C31: COCHERA 5 | E31: 1.08 | L31: =L$8*E31/S$12 -> 1144.3708 | M31: 0 | N31: =J31+L31 -> 1144.3708 | O31: =N31+'prorrateo '!L24 -> 27454.744
C32: COCHERA 6 | E32: 1.08 | L32: =L$8*E32/S$12 -> 1144.3708 | M32: 0 | N32: =J32+L32 -> 1144.3708 | O32: =N32+'prorrateo '!L25 -> 43585.533
C33: COCHERA 7 | E33: 1.08 | L33: =L$8*E33/S$12 -> 1144.3708 | M33: 0 | N33: =J33+L33 -> 1144.3708 | O33: =N33+'prorrateo '!L26 -> 27454.744
C34: COCHERA 8 | E34: 1.08 | L34: =L$8*E34/S$12 -> 1144.3708 | M34: 0 | N34: =J34+L34 -> 1144.3708 | O34: =N34+'prorrateo '!L27 -> 27454.744
A35: 21 | C35: COCHERA 9 | E35: 1.08 | H35: 0 | I35: =H35*7% -> 0 | L35: =L$8*E35/S$12 -> 1144.3708 | M35: 0 | N35: =J35+L35 -> 1144.3708 | O35: =N35+'prorrateo '!L28 -> 43585.533
A36: 22 | C36: COCHERA 10 | E36: 1.08 | H36: 0 | I36: =H36*7% -> 0 | L36: =L$8*E36/S$12 -> 1144.3708 | M36: 0 | N36: =J36+L36 -> 1144.3708 | O36: =N36+'prorrateo '!L29 -> 27454.744
A37: 23 | H37: 0 | I37: =H37*7% -> 0 | L37: 0 | M37: 0 | N37: =J37+L37 -> 0
A38: 24 | J38: =SUM(J10:J37) -> 159634.85 | L38: =SUM(L10:L37) -> 105960.26 | N38: =SUM(N10:N37) -> 265595.11
E39: =SUM(E10:E38) -> 100 | I39: =SUM(I10:I38) -> 119.147 | L39: =L38+J38 -> 265595.11
A40: NOTA:
